final class CRRWDRTI {
  private static int a;

  private int[] b;

  private int[] c;

  private int[] d;

  private int[] e;

  private int[] f;

  private int[][][] g;

  private byte[][][] h;

  static int i;

  private boolean j;

  private static int k;

  private byte[][][] l;

  private int[][][] m;

  private byte[][][] n;

  private static final int[] o;

  private static int p;

  private int[][] q;

  private static final int[] r;

  private static boolean s;

  private byte[][][] t;

  private boolean u;

  private static final int[] v;

  static int w;

  private int x;

  private int y;

  private byte[][][] z;

  private byte[][][] A;

  private int B;

  static boolean C;

  private static final int[] D;

  private static int E;

  public CRRWDRTI(byte[][][], int, int, int, int[][][]);
    Code:
       0: aload_0
       1: invokespecial #52                 // Method java/lang/Object."<init>":()V
       4: aload_0
       5: iconst_1
       6: putfield      #154                // Field j:Z
       9: aload_0
      10: iconst_0
      11: putfield      #72                 // Field u:Z
      14: aload_0
      15: bipush        -53
      17: putfield      #127                // Field B:I
      20: bipush        99
      22: putstatic     #120                // Field w:I
      25: aload_0
      26: iload         4
      28: putfield      #153                // Field x:I
      31: aload_0
      32: iload_3
      33: putfield      #100                // Field y:I
      36: getstatic     #414                // Field client.Jj:I
      39: ifeq          48
      42: sipush        -320
      45: putstatic     #151                // Field E:I
      48: iload_2
      49: ifge          42
      52: aload_0
      53: aload         5
      55: putfield      #98                 // Field g:[[[I
      58: aload_0
      59: aload_1
      60: putfield      #117                // Field A:[[[B
      63: aload_0
      64: iconst_4
      65: aload_0
      66: getfield      #153                // Field x:I
      69: aload_0
      70: getfield      #100                // Field y:I
      73: multianewarray #32,  3            // class "[[[B"
      77: putfield      #89                 // Field t:[[[B
      80: aload_0
      81: iconst_4
      82: aload_0
      83: getfield      #153                // Field x:I
      86: aload_0
      87: getfield      #100                // Field y:I
      90: multianewarray #32,  3            // class "[[[B"
      94: putfield      #90                 // Field h:[[[B
      97: aload_0
      98: iconst_4
      99: aload_0
     100: getfield      #153                // Field x:I
     103: aload_0
     104: getfield      #100                // Field y:I
     107: multianewarray #32,  3            // class "[[[B"
     111: putfield      #88                 // Field n:[[[B
     114: aload_0
     115: iconst_4
     116: aload_0
     117: getfield      #153                // Field x:I
     120: aload_0
     121: getfield      #100                // Field y:I
     124: multianewarray #32,  3            // class "[[[B"
     128: putfield      #87                 // Field z:[[[B
     131: aload_0
     132: iconst_4
     133: aload_0
     134: getfield      #153                // Field x:I
     137: iconst_1
     138: iadd
     139: aload_0
     140: getfield      #100                // Field y:I
     143: iconst_1
     144: iadd
     145: multianewarray #33,  3            // class "[[[I"
     149: putfield      #118                // Field m:[[[I
     152: aload_0
     153: iconst_4
     154: aload_0
     155: getfield      #153                // Field x:I
     158: iconst_1
     159: iadd
     160: aload_0
     161: getfield      #100                // Field y:I
     164: iconst_1
     165: iadd
     166: multianewarray #32,  3            // class "[[[B"
     170: putfield      #142                // Field l:[[[B
     173: aload_0
     174: aload_0
     175: getfield      #153                // Field x:I
     178: iconst_1
     179: iadd
     180: aload_0
     181: getfield      #100                // Field y:I
     184: iconst_1
     185: iadd
     186: multianewarray #31,  2            // class "[[I"
     190: putfield      #111                // Field q:[[I
     193: aload_0
     194: aload_0
     195: getfield      #100                // Field y:I
     198: newarray       int
     200: putfield      #105                // Field b:[I
     203: aload_0
     204: aload_0
     205: getfield      #100                // Field y:I
     208: newarray       int
     210: putfield      #134                // Field c:[I
     213: aload_0
     214: aload_0
     215: getfield      #100                // Field y:I
     218: newarray       int
     220: putfield      #112                // Field d:[I
     223: aload_0
     224: aload_0
     225: getfield      #100                // Field y:I
     228: newarray       int
     230: putfield      #79                 // Field e:[I
     233: aload_0
     234: aload_0
     235: getfield      #100                // Field y:I
     238: newarray       int
     240: putfield      #150                // Field f:[I
     243: return
     244: astore        6
     246: new           #44                 // class java/lang/StringBuffer
     249: dup
     250: ldc           #23                 // String 40803,
     252: invokespecial #55                 // Method java/lang/StringBuffer."<init>":(Ljava/lang/String;)V
     255: aload_1
     256: invokevirtual #64                 // Method java/lang/StringBuffer.append:(Ljava/lang/Object;)Ljava/lang/StringBuffer;
     259: ldc           #16                 // String ,
     261: invokevirtual #65                 // Method java/lang/StringBuffer.append:(Ljava/lang/String;)Ljava/lang/StringBuffer;
     264: iload_2
     265: invokevirtual #63                 // Method java/lang/StringBuffer.append:(I)Ljava/lang/StringBuffer;
     268: ldc           #16                 // String ,
     270: invokevirtual #65                 // Method java/lang/StringBuffer.append:(Ljava/lang/String;)Ljava/lang/StringBuffer;
     273: iload_3
     274: invokevirtual #63                 // Method java/lang/StringBuffer.append:(I)Ljava/lang/StringBuffer;
     277: ldc           #16                 // String ,
     279: invokevirtual #65                 // Method java/lang/StringBuffer.append:(Ljava/lang/String;)Ljava/lang/StringBuffer;
     282: iload         4
     284: invokevirtual #63                 // Method java/lang/StringBuffer.append:(I)Ljava/lang/StringBuffer;
     287: ldc           #16                 // String ,
     289: invokevirtual #65                 // Method java/lang/StringBuffer.append:(Ljava/lang/String;)Ljava/lang/StringBuffer;
     292: aload         5
     294: invokevirtual #64                 // Method java/lang/StringBuffer.append:(Ljava/lang/Object;)Ljava/lang/StringBuffer;
     297: ldc           #16                 // String ,
     299: invokevirtual #65                 // Method java/lang/StringBuffer.append:(Ljava/lang/String;)Ljava/lang/StringBuffer;
     302: aload         6
     304: invokevirtual #149                // Method java/lang/Throwable.toString:()Ljava/lang/String;
     307: invokevirtual #65                 // Method java/lang/StringBuffer.append:(Ljava/lang/String;)Ljava/lang/StringBuffer;
     310: invokevirtual #148                // Method java/lang/StringBuffer.toString:()Ljava/lang/String;
     313: invokestatic  #132                // Method sign/signlink.reporterror:(Ljava/lang/String;)V
     316: new           #43                 // class java/lang/RuntimeException
     319: dup
     320: invokespecial #53                 // Method java/lang/RuntimeException."<init>":()V
     323: athrow
    Exception table:
       from    to  target type
          20   243   244   Class java/lang/RuntimeException

  private static final int a(int, int);
    Code:
       0: iload_0
       1: iload_1
       2: bipush        57
       4: imul
       5: iadd
       6: istore_2
       7: iload_2
       8: bipush        13
      10: ishl
      11: iload_2
      12: ixor
      13: istore_2
      14: iload_2
      15: iload_2
      16: iload_2
      17: imul
      18: sipush        15731
      21: imul
      22: ldc           #7                  // int 789221
      24: iadd
      25: imul
      26: ldc           #13                 // int 1376312589
      28: iadd
      29: ldc           #14                 // int 2147483647
      31: iand
      32: istore_3
      33: iload_3
      34: bipush        19
      36: ishr
      37: sipush        255
      40: iand
      41: ireturn

  public final void a(FTPNODIB[], NYFUGYQS, int);
    Code:
       0: getstatic     #414                // Field client.Jj:I
       3: istore        45
       5: iconst_0
       6: istore        4
       8: iload         45
      10: ifeq          113
      13: iconst_0
      14: istore        5
      16: iload         45
      18: ifeq          103
      21: iconst_0
      22: istore        6
      24: iload         45
      26: ifeq          93
      29: aload_0
      30: getfield      #117                // Field A:[[[B
      33: iload         4
      35: aaload
      36: iload         5
      38: aaload
      39: iload         6
      41: baload
      42: iconst_1
      43: iand
      44: iconst_1
      45: if_icmpne     90
      48: iload         4
      50: istore        7
      52: aload_0
      53: getfield      #117                // Field A:[[[B
      56: iconst_1
      57: aaload
      58: iload         5
      60: aaload
      61: iload         6
      63: baload
      64: iconst_2
      65: iand
      66: iconst_2
      67: if_icmpne     73
      70: iinc          7, -1
      73: iload         7
      75: iflt          90
      78: aload_1
      79: iload         7
      81: aaload
      82: iload         6
      84: iconst_0
      85: iload         5
      87: invokevirtual #67                 // Method FTPNODIB.a:(III)V
      90: iinc          6, 1
      93: iload         6
      95: bipush        104
      97: if_icmplt     29
     100: iinc          5, 1
     103: iload         5
     105: bipush        104
     107: if_icmplt     21
     110: iinc          4, 1
     113: iload         4
     115: iconst_4
     116: if_icmplt     13
     119: iload_3
     120: iconst_2
     121: if_icmplt     129
     124: iload_3
     125: iconst_2
     126: if_icmple     135
     129: sipush        329
     132: putstatic     #75                 // Field p:I
     135: getstatic     #104                // Field a:I
     138: invokestatic  #131                // Method java/lang/Math.random:()D
     141: ldc2_w        #163                // double 5.0d
     144: dmul
     145: d2i
     146: iconst_2
     147: isub
     148: iadd
     149: putstatic     #104                // Field a:I
     152: getstatic     #104                // Field a:I
     155: bipush        -8
     157: if_icmpge     165
     160: bipush        -8
     162: putstatic     #104                // Field a:I
     165: getstatic     #104                // Field a:I
     168: bipush        8
     170: if_icmple     178
     173: bipush        8
     175: putstatic     #104                // Field a:I
     178: getstatic     #110                // Field k:I
     181: invokestatic  #131                // Method java/lang/Math.random:()D
     184: ldc2_w        #163                // double 5.0d
     187: dmul
     188: d2i
     189: iconst_2
     190: isub
     191: iadd
     192: putstatic     #110                // Field k:I
     195: getstatic     #110                // Field k:I
     198: bipush        -16
     200: if_icmpge     208
     203: bipush        -16
     205: putstatic     #110                // Field k:I
     208: getstatic     #110                // Field k:I
     211: bipush        16
     213: if_icmple     221
     216: bipush        16
     218: putstatic     #110                // Field k:I
     221: iconst_0
     222: istore        5
     224: iload         45
     226: ifeq          1971
     229: aload_0
     230: getfield      #142                // Field l:[[[B
     233: iload         5
     235: aaload
     236: astore        6
     238: bipush        96
     240: istore        7
     242: sipush        768
     245: istore        8
     247: bipush        -50
     249: istore        9
     251: bipush        -10
     253: istore        10
     255: bipush        -50
     257: istore        11
     259: iload         9
     261: iload         9
     263: imul
     264: iload         10
     266: iload         10
     268: imul
     269: iadd
     270: iload         11
     272: iload         11
     274: imul
     275: iadd
     276: i2d
     277: invokestatic  #145                // Method java/lang/Math.sqrt:(D)D
     280: d2i
     281: istore        12
     283: iload         8
     285: iload         12
     287: imul
     288: bipush        8
     290: ishr
     291: istore        13
     293: iconst_1
     294: istore        14
     296: iload         45
     298: ifeq          544
     301: iconst_1
     302: istore        15
     304: iload         45
     306: ifeq          530
     309: aload_0
     310: getfield      #98                 // Field g:[[[I
     313: iload         5
     315: aaload
     316: iload         15
     318: iconst_1
     319: iadd
     320: aaload
     321: iload         14
     323: iaload
     324: aload_0
     325: getfield      #98                 // Field g:[[[I
     328: iload         5
     330: aaload
     331: iload         15
     333: iconst_1
     334: isub
     335: aaload
     336: iload         14
     338: iaload
     339: isub
     340: istore        16
     342: aload_0
     343: getfield      #98                 // Field g:[[[I
     346: iload         5
     348: aaload
     349: iload         15
     351: aaload
     352: iload         14
     354: iconst_1
     355: iadd
     356: iaload
     357: aload_0
     358: getfield      #98                 // Field g:[[[I
     361: iload         5
     363: aaload
     364: iload         15
     366: aaload
     367: iload         14
     369: iconst_1
     370: isub
     371: iaload
     372: isub
     373: istore        17
     375: iload         16
     377: iload         16
     379: imul
     380: ldc           #4                  // int 65536
     382: iadd
     383: iload         17
     385: iload         17
     387: imul
     388: iadd
     389: i2d
     390: invokestatic  #145                // Method java/lang/Math.sqrt:(D)D
     393: d2i
     394: istore        18
     396: iload         16
     398: bipush        8
     400: ishl
     401: iload         18
     403: idiv
     404: istore        19
     406: ldc           #4                  // int 65536
     408: iload         18
     410: idiv
     411: istore        20
     413: iload         17
     415: bipush        8
     417: ishl
     418: iload         18
     420: idiv
     421: istore        21
     423: iload         7
     425: iload         9
     427: iload         19
     429: imul
     430: iload         10
     432: iload         20
     434: imul
     435: iadd
     436: iload         11
     438: iload         21
     440: imul
     441: iadd
     442: iload         13
     444: idiv
     445: iadd
     446: istore        22
     448: aload         6
     450: iload         15
     452: iconst_1
     453: isub
     454: aaload
     455: iload         14
     457: baload
     458: iconst_2
     459: ishr
     460: aload         6
     462: iload         15
     464: iconst_1
     465: iadd
     466: aaload
     467: iload         14
     469: baload
     470: iconst_3
     471: ishr
     472: iadd
     473: aload         6
     475: iload         15
     477: aaload
     478: iload         14
     480: iconst_1
     481: isub
     482: baload
     483: iconst_2
     484: ishr
     485: iadd
     486: aload         6
     488: iload         15
     490: aaload
     491: iload         14
     493: iconst_1
     494: iadd
     495: baload
     496: iconst_3
     497: ishr
     498: iadd
     499: aload         6
     501: iload         15
     503: aaload
     504: iload         14
     506: baload
     507: iconst_1
     508: ishr
     509: iadd
     510: istore        23
     512: aload_0
     513: getfield      #111                // Field q:[[I
     516: iload         15
     518: aaload
     519: iload         14
     521: iload         22
     523: iload         23
     525: isub
     526: iastore
     527: iinc          15, 1
     530: iload         15
     532: aload_0
     533: getfield      #153                // Field x:I
     536: iconst_1
     537: isub
     538: if_icmplt     309
     541: iinc          14, 1
     544: iload         14
     546: aload_0
     547: getfield      #100                // Field y:I
     550: iconst_1
     551: isub
     552: if_icmplt     301
     555: iconst_0
     556: istore        15
     558: iload         45
     560: ifeq          606
     563: aload_0
     564: getfield      #105                // Field b:[I
     567: iload         15
     569: iconst_0
     570: iastore
     571: aload_0
     572: getfield      #134                // Field c:[I
     575: iload         15
     577: iconst_0
     578: iastore
     579: aload_0
     580: getfield      #112                // Field d:[I
     583: iload         15
     585: iconst_0
     586: iastore
     587: aload_0
     588: getfield      #79                 // Field e:[I
     591: iload         15
     593: iconst_0
     594: iastore
     595: aload_0
     596: getfield      #150                // Field f:[I
     599: iload         15
     601: iconst_0
     602: iastore
     603: iinc          15, 1
     606: iload         15
     608: aload_0
     609: getfield      #100                // Field y:I
     612: if_icmplt     563
     615: bipush        -5
     617: istore        16
     619: iload         45
     621: ifeq          1892
     624: iconst_0
     625: istore        17
     627: iload         45
     629: ifeq          885
     632: iload         16
     634: iconst_5
     635: iadd
     636: istore        18
     638: iload         18
     640: iflt          757
     643: iload         18
     645: aload_0
     646: getfield      #153                // Field x:I
     649: if_icmpge     757
     652: aload_0
     653: getfield      #89                 // Field t:[[[B
     656: iload         5
     658: aaload
     659: iload         18
     661: aaload
     662: iload         17
     664: baload
     665: sipush        255
     668: iand
     669: istore        19
     671: iload         19
     673: ifle          757
     676: getstatic     #114                // Field MNHKFPQO.d:[LMNHKFPQO;
     679: iload         19
     681: iconst_1
     682: isub
     683: aaload
     684: astore        20
     686: aload_0
     687: getfield      #105                // Field b:[I
     690: iload         17
     692: dup2
     693: iaload
     694: aload         20
     696: getfield      #102                // Field MNHKFPQO.m:I
     699: iadd
     700: iastore
     701: aload_0
     702: getfield      #134                // Field c:[I
     705: iload         17
     707: dup2
     708: iaload
     709: aload         20
     711: getfield      #133                // Field MNHKFPQO.k:I
     714: iadd
     715: iastore
     716: aload_0
     717: getfield      #112                // Field d:[I
     720: iload         17
     722: dup2
     723: iaload
     724: aload         20
     726: getfield      #108                // Field MNHKFPQO.l:I
     729: iadd
     730: iastore
     731: aload_0
     732: getfield      #79                 // Field e:[I
     735: iload         17
     737: dup2
     738: iaload
     739: aload         20
     741: getfield      #71                 // Field MNHKFPQO.n:I
     744: iadd
     745: iastore
     746: aload_0
     747: getfield      #150                // Field f:[I
     750: iload         17
     752: dup2
     753: iaload
     754: iconst_1
     755: iadd
     756: iastore
     757: iload         16
     759: iconst_5
     760: isub
     761: istore        19
     763: iload         19
     765: iflt          882
     768: iload         19
     770: aload_0
     771: getfield      #153                // Field x:I
     774: if_icmpge     882
     777: aload_0
     778: getfield      #89                 // Field t:[[[B
     781: iload         5
     783: aaload
     784: iload         19
     786: aaload
     787: iload         17
     789: baload
     790: sipush        255
     793: iand
     794: istore        20
     796: iload         20
     798: ifle          882
     801: getstatic     #114                // Field MNHKFPQO.d:[LMNHKFPQO;
     804: iload         20
     806: iconst_1
     807: isub
     808: aaload
     809: astore        21
     811: aload_0
     812: getfield      #105                // Field b:[I
     815: iload         17
     817: dup2
     818: iaload
     819: aload         21
     821: getfield      #102                // Field MNHKFPQO.m:I
     824: isub
     825: iastore
     826: aload_0
     827: getfield      #134                // Field c:[I
     830: iload         17
     832: dup2
     833: iaload
     834: aload         21
     836: getfield      #133                // Field MNHKFPQO.k:I
     839: isub
     840: iastore
     841: aload_0
     842: getfield      #112                // Field d:[I
     845: iload         17
     847: dup2
     848: iaload
     849: aload         21
     851: getfield      #108                // Field MNHKFPQO.l:I
     854: isub
     855: iastore
     856: aload_0
     857: getfield      #79                 // Field e:[I
     860: iload         17
     862: dup2
     863: iaload
     864: aload         21
     866: getfield      #71                 // Field MNHKFPQO.n:I
     869: isub
     870: iastore
     871: aload_0
     872: getfield      #150                // Field f:[I
     875: iload         17
     877: dup2
     878: iaload
     879: iconst_1
     880: isub
     881: iastore
     882: iinc          17, 1
     885: iload         17
     887: aload_0
     888: getfield      #100                // Field y:I
     891: if_icmplt     632
     894: iload         16
     896: iconst_1
     897: if_icmplt     1889
     900: iload         16
     902: aload_0
     903: getfield      #153                // Field x:I
     906: iconst_1
     907: isub
     908: if_icmpge     1889
     911: iconst_0
     912: istore        18
     914: iconst_0
     915: istore        19
     917: iconst_0
     918: istore        20
     920: iconst_0
     921: istore        21
     923: iconst_0
     924: istore        22
     926: bipush        -5
     928: istore        23
     930: iload         45
     932: ifeq          1878
     935: iload         23
     937: iconst_5
     938: iadd
     939: istore        24
     941: iload         24
     943: iflt          1015
     946: iload         24
     948: aload_0
     949: getfield      #100                // Field y:I
     952: if_icmpge     1015
     955: iload         18
     957: aload_0
     958: getfield      #105                // Field b:[I
     961: iload         24
     963: iaload
     964: iadd
     965: istore        18
     967: iload         19
     969: aload_0
     970: getfield      #134                // Field c:[I
     973: iload         24
     975: iaload
     976: iadd
     977: istore        19
     979: iload         20
     981: aload_0
     982: getfield      #112                // Field d:[I
     985: iload         24
     987: iaload
     988: iadd
     989: istore        20
     991: iload         21
     993: aload_0
     994: getfield      #79                 // Field e:[I
     997: iload         24
     999: iaload
    1000: iadd
    1001: istore        21
    1003: iload         22
    1005: aload_0
    1006: getfield      #150                // Field f:[I
    1009: iload         24
    1011: iaload
    1012: iadd
    1013: istore        22
    1015: iload         23
    1017: iconst_5
    1018: isub
    1019: istore        25
    1021: iload         25
    1023: iflt          1095
    1026: iload         25
    1028: aload_0
    1029: getfield      #100                // Field y:I
    1032: if_icmpge     1095
    1035: iload         18
    1037: aload_0
    1038: getfield      #105                // Field b:[I
    1041: iload         25
    1043: iaload
    1044: isub
    1045: istore        18
    1047: iload         19
    1049: aload_0
    1050: getfield      #134                // Field c:[I
    1053: iload         25
    1055: iaload
    1056: isub
    1057: istore        19
    1059: iload         20
    1061: aload_0
    1062: getfield      #112                // Field d:[I
    1065: iload         25
    1067: iaload
    1068: isub
    1069: istore        20
    1071: iload         21
    1073: aload_0
    1074: getfield      #79                 // Field e:[I
    1077: iload         25
    1079: iaload
    1080: isub
    1081: istore        21
    1083: iload         22
    1085: aload_0
    1086: getfield      #150                // Field f:[I
    1089: iload         25
    1091: iaload
    1092: isub
    1093: istore        22
    1095: iload         23
    1097: iconst_1
    1098: if_icmplt     1875
    1101: iload         23
    1103: aload_0
    1104: getfield      #100                // Field y:I
    1107: iconst_1
    1108: isub
    1109: if_icmpge     1875
    1112: getstatic     #116                // Field C:Z
    1115: ifeq          1174
    1118: aload_0
    1119: getfield      #117                // Field A:[[[B
    1122: iconst_0
    1123: aaload
    1124: iload         16
    1126: aaload
    1127: iload         23
    1129: baload
    1130: iconst_2
    1131: iand
    1132: ifne          1174
    1135: aload_0
    1136: getfield      #117                // Field A:[[[B
    1139: iload         5
    1141: aaload
    1142: iload         16
    1144: aaload
    1145: iload         23
    1147: baload
    1148: bipush        16
    1150: iand
    1151: ifne          1875
    1154: aload_0
    1155: iload         23
    1157: iload         5
    1159: iload         16
    1161: iconst_0
    1162: invokevirtual #152                // Method a:(IIII)I
    1165: getstatic     #70                 // Field i:I
    1168: if_icmpeq     1174
    1171: goto          1875
    1174: iload         5
    1176: getstatic     #120                // Field w:I
    1179: if_icmpge     1187
    1182: iload         5
    1184: putstatic     #120                // Field w:I
    1187: aload_0
    1188: getfield      #89                 // Field t:[[[B
    1191: iload         5
    1193: aaload
    1194: iload         16
    1196: aaload
    1197: iload         23
    1199: baload
    1200: sipush        255
    1203: iand
    1204: istore        26
    1206: aload_0
    1207: getfield      #90                 // Field h:[[[B
    1210: iload         5
    1212: aaload
    1213: iload         16
    1215: aaload
    1216: iload         23
    1218: baload
    1219: sipush        255
    1222: iand
    1223: istore        27
    1225: iload         26
    1227: ifgt          1235
    1230: iload         27
    1232: ifle          1875
    1235: aload_0
    1236: getfield      #98                 // Field g:[[[I
    1239: iload         5
    1241: aaload
    1242: iload         16
    1244: aaload
    1245: iload         23
    1247: iaload
    1248: istore        28
    1250: aload_0
    1251: getfield      #98                 // Field g:[[[I
    1254: iload         5
    1256: aaload
    1257: iload         16
    1259: iconst_1
    1260: iadd
    1261: aaload
    1262: iload         23
    1264: iaload
    1265: istore        29
    1267: aload_0
    1268: getfield      #98                 // Field g:[[[I
    1271: iload         5
    1273: aaload
    1274: iload         16
    1276: iconst_1
    1277: iadd
    1278: aaload
    1279: iload         23
    1281: iconst_1
    1282: iadd
    1283: iaload
    1284: istore        30
    1286: aload_0
    1287: getfield      #98                 // Field g:[[[I
    1290: iload         5
    1292: aaload
    1293: iload         16
    1295: aaload
    1296: iload         23
    1298: iconst_1
    1299: iadd
    1300: iaload
    1301: istore        31
    1303: aload_0
    1304: getfield      #111                // Field q:[[I
    1307: iload         16
    1309: aaload
    1310: iload         23
    1312: iaload
    1313: istore        32
    1315: aload_0
    1316: getfield      #111                // Field q:[[I
    1319: iload         16
    1321: iconst_1
    1322: iadd
    1323: aaload
    1324: iload         23
    1326: iaload
    1327: istore        33
    1329: aload_0
    1330: getfield      #111                // Field q:[[I
    1333: iload         16
    1335: iconst_1
    1336: iadd
    1337: aaload
    1338: iload         23
    1340: iconst_1
    1341: iadd
    1342: iaload
    1343: istore        34
    1345: aload_0
    1346: getfield      #111                // Field q:[[I
    1349: iload         16
    1351: aaload
    1352: iload         23
    1354: iconst_1
    1355: iadd
    1356: iaload
    1357: istore        35
    1359: iconst_m1
    1360: istore        36
    1362: iconst_m1
    1363: istore        37
    1365: iload         26
    1367: ifle          1465
    1370: iload         18
    1372: sipush        256
    1375: imul
    1376: iload         21
    1378: idiv
    1379: istore        38
    1381: iload         19
    1383: iload         22
    1385: idiv
    1386: istore        39
    1388: iload         20
    1390: iload         22
    1392: idiv
    1393: istore        40
    1395: aload_0
    1396: iload         38
    1398: iload         39
    1400: iload         40
    1402: invokespecial #96                 // Method b:(III)I
    1405: istore        36
    1407: iload         38
    1409: getstatic     #104                // Field a:I
    1412: iadd
    1413: sipush        255
    1416: iand
    1417: istore        38
    1419: iload         40
    1421: getstatic     #110                // Field k:I
    1424: iadd
    1425: istore        40
    1427: iload         40
    1429: ifge          1440
    1432: iconst_0
    1433: istore        40
    1435: iload         45
    1437: ifeq          1453
    1440: iload         40
    1442: sipush        255
    1445: if_icmple     1453
    1448: sipush        255
    1451: istore        40
    1453: aload_0
    1454: iload         38
    1456: iload         39
    1458: iload         40
    1460: invokespecial #96                 // Method b:(III)I
    1463: istore        37
    1465: iload         5
    1467: ifle          1564
    1470: iconst_1
    1471: istore        38
    1473: iload         26
    1475: ifne          1497
    1478: aload_0
    1479: getfield      #88                 // Field n:[[[B
    1482: iload         5
    1484: aaload
    1485: iload         16
    1487: aaload
    1488: iload         23
    1490: baload
    1491: ifeq          1497
    1494: iconst_0
    1495: istore        38
    1497: iload         27
    1499: ifle          1519
    1502: getstatic     #114                // Field MNHKFPQO.d:[LMNHKFPQO;
    1505: iload         27
    1507: iconst_1
    1508: isub
    1509: aaload
    1510: getfield      #125                // Field MNHKFPQO.i:Z
    1513: ifne          1519
    1516: iconst_0
    1517: istore        38
    1519: iload         38
    1521: ifeq          1564
    1524: iload         28
    1526: iload         29
    1528: if_icmpne     1564
    1531: iload         28
    1533: iload         30
    1535: if_icmpne     1564
    1538: iload         28
    1540: iload         31
    1542: if_icmpne     1564
    1545: aload_0
    1546: getfield      #118                // Field m:[[[I
    1549: iload         5
    1551: aaload
    1552: iload         16
    1554: aaload
    1555: iload         23
    1557: dup2
    1558: iaload
    1559: sipush        2340
    1562: ior
    1563: iastore
    1564: iconst_0
    1565: istore        38
    1567: iload         36
    1569: iconst_m1
    1570: if_icmpeq     1586
    1573: getstatic     #78                 // Field OPPOFIOL.V:[I
    1576: iload         37
    1578: bipush        96
    1580: invokestatic  #97                 // Method e:(II)I
    1583: iaload
    1584: istore        38
    1586: iload         27
    1588: ifne          1652
    1591: aload_2
    1592: iload         5
    1594: iload         16
    1596: iload         23
    1598: iconst_0
    1599: iconst_0
    1600: iconst_m1
    1601: iload         28
    1603: iload         29
    1605: iload         30
    1607: iload         31
    1609: iload         36
    1611: iload         32
    1613: invokestatic  #97                 // Method e:(II)I
    1616: iload         36
    1618: iload         33
    1620: invokestatic  #97                 // Method e:(II)I
    1623: iload         36
    1625: iload         34
    1627: invokestatic  #97                 // Method e:(II)I
    1630: iload         36
    1632: iload         35
    1634: invokestatic  #97                 // Method e:(II)I
    1637: iconst_0
    1638: iconst_0
    1639: iconst_0
    1640: iconst_0
    1641: iload         38
    1643: iconst_0
    1644: invokevirtual #136                // Method NYFUGYQS.a:(IIIIIIIIIIIIIIIIIIII)V
    1647: iload         45
    1649: ifeq          1875
    1652: aload_0
    1653: getfield      #88                 // Field n:[[[B
    1656: iload         5
    1658: aaload
    1659: iload         16
    1661: aaload
    1662: iload         23
    1664: baload
    1665: iconst_1
    1666: iadd
    1667: istore        39
    1669: aload_0
    1670: getfield      #87                 // Field z:[[[B
    1673: iload         5
    1675: aaload
    1676: iload         16
    1678: aaload
    1679: iload         23
    1681: baload
    1682: istore        40
    1684: getstatic     #114                // Field MNHKFPQO.d:[LMNHKFPQO;
    1687: iload         27
    1689: iconst_1
    1690: isub
    1691: aaload
    1692: astore        41
    1694: aload         41
    1696: getfield      #146                // Field MNHKFPQO.g:I
    1699: istore        42
    1701: iload         42
    1703: iflt          1724
    1706: iload         42
    1708: sipush        12660
    1711: invokestatic  #147                // Method OPPOFIOL.a:(II)I
    1714: istore        44
    1716: iconst_m1
    1717: istore        43
    1719: iload         45
    1721: ifeq          1787
    1724: aload         41
    1726: getfield      #77                 // Field MNHKFPQO.f:I
    1729: ldc           #10                 // int 16711935
    1731: if_icmpne     1749
    1734: iconst_0
    1735: istore        44
    1737: bipush        -2
    1739: istore        43
    1741: iconst_m1
    1742: istore        42
    1744: iload         45
    1746: ifeq          1787
    1749: aload_0
    1750: aload         41
    1752: getfield      #101                // Field MNHKFPQO.j:I
    1755: aload         41
    1757: getfield      #133                // Field MNHKFPQO.k:I
    1760: aload         41
    1762: getfield      #108                // Field MNHKFPQO.l:I
    1765: invokespecial #96                 // Method b:(III)I
    1768: istore        43
    1770: getstatic     #78                 // Field OPPOFIOL.V:[I
    1773: aload_0
    1774: aload         41
    1776: getfield      #119                // Field MNHKFPQO.o:I
    1779: bipush        96
    1781: invokespecial #95                 // Method c:(II)I
    1784: iaload
    1785: istore        44
    1787: aload_2
    1788: iload         5
    1790: iload         16
    1792: iload         23
    1794: iload         39
    1796: iload         40
    1798: iload         42
    1800: iload         28
    1802: iload         29
    1804: iload         30
    1806: iload         31
    1808: iload         36
    1810: iload         32
    1812: invokestatic  #97                 // Method e:(II)I
    1815: iload         36
    1817: iload         33
    1819: invokestatic  #97                 // Method e:(II)I
    1822: iload         36
    1824: iload         34
    1826: invokestatic  #97                 // Method e:(II)I
    1829: iload         36
    1831: iload         35
    1833: invokestatic  #97                 // Method e:(II)I
    1836: aload_0
    1837: iload         43
    1839: iload         32
    1841: invokespecial #95                 // Method c:(II)I
    1844: aload_0
    1845: iload         43
    1847: iload         33
    1849: invokespecial #95                 // Method c:(II)I
    1852: aload_0
    1853: iload         43
    1855: iload         34
    1857: invokespecial #95                 // Method c:(II)I
    1860: aload_0
    1861: iload         43
    1863: iload         35
    1865: invokespecial #95                 // Method c:(II)I
    1868: iload         38
    1870: iload         44
    1872: invokevirtual #136                // Method NYFUGYQS.a:(IIIIIIIIIIIIIIIIIIII)V
    1875: iinc          23, 1
    1878: iload         23
    1880: aload_0
    1881: getfield      #100                // Field y:I
    1884: iconst_5
    1885: iadd
    1886: if_icmplt     935
    1889: iinc          16, 1
    1892: iload         16
    1894: aload_0
    1895: getfield      #153                // Field x:I
    1898: iconst_5
    1899: iadd
    1900: if_icmplt     624
    1903: iconst_1
    1904: istore        17
    1906: iload         45
    1908: ifeq          1957
    1911: iconst_1
    1912: istore        18
    1914: iload         45
    1916: ifeq          1943
    1919: aload_2
    1920: iload         5
    1922: iload         18
    1924: iload         17
    1926: aload_0
    1927: iload         17
    1929: iload         5
    1931: iload         18
    1933: iconst_0
    1934: invokevirtual #152                // Method a:(IIII)I
    1937: invokevirtual #138                // Method NYFUGYQS.a:(IIII)V
    1940: iinc          18, 1
    1943: iload         18
    1945: aload_0
    1946: getfield      #153                // Field x:I
    1949: iconst_1
    1950: isub
    1951: if_icmplt     1919
    1954: iinc          17, 1
    1957: iload         17
    1959: aload_0
    1960: getfield      #100                // Field y:I
    1963: iconst_1
    1964: isub
    1965: if_icmplt     1911
    1968: iinc          5, 1
    1971: iload         5
    1973: iconst_4
    1974: if_icmplt     229
    1977: aload_2
    1978: bipush        -10
    1980: iconst_3
    1981: bipush        64
    1983: bipush        -50
    1985: sipush        768
    1988: bipush        -50
    1990: invokevirtual #143                // Method NYFUGYQS.a:(IBIIII)V
    1993: iconst_0
    1994: istore        6
    1996: iload         45
    1998: ifeq          2053
    2001: iconst_0
    2002: istore        7
    2004: iload         45
    2006: ifeq          2041
    2009: aload_0
    2010: getfield      #117                // Field A:[[[B
    2013: iconst_1
    2014: aaload
    2015: iload         6
    2017: aaload
    2018: iload         7
    2020: baload
    2021: iconst_2
    2022: iand
    2023: iconst_2
    2024: if_icmpne     2038
    2027: aload_2
    2028: iload         7
    2030: iload         6
    2032: sipush        -438
    2035: invokevirtual #129                // Method NYFUGYQS.a:(III)V
    2038: iinc          7, 1
    2041: iload         7
    2043: aload_0
    2044: getfield      #100                // Field y:I
    2047: if_icmplt     2009
    2050: iinc          6, 1
    2053: iload         6
    2055: aload_0
    2056: getfield      #153                // Field x:I
    2059: if_icmplt     2001
    2062: iconst_1
    2063: istore        7
    2065: iconst_2
    2066: istore        8
    2068: iconst_4
    2069: istore        9
    2071: iconst_0
    2072: istore        10
    2074: iload         45
    2076: ifeq          3290
    2079: iload         10
    2081: ifle          2102
    2084: iload         7
    2086: iconst_3
    2087: ishl
    2088: istore        7
    2090: iload         8
    2092: iconst_3
    2093: ishl
    2094: istore        8
    2096: iload         9
    2098: iconst_3
    2099: ishl
    2100: istore        9
    2102: iconst_0
    2103: istore        11
    2105: iload         45
    2107: ifeq          3280
    2110: iconst_0
    2111: istore        12
    2113: iload         45
    2115: ifeq          3268
    2118: iconst_0
    2119: istore        13
    2121: iload         45
    2123: ifeq          3256
    2126: aload_0
    2127: getfield      #118                // Field m:[[[I
    2130: iload         11
    2132: aaload
    2133: iload         13
    2135: aaload
    2136: iload         12
    2138: iaload
    2139: iload         7
    2141: iand
    2142: ifeq          2509
    2145: iload         12
    2147: istore        14
    2149: iload         12
    2151: istore        15
    2153: iload         11
    2155: istore        16
    2157: iload         11
    2159: istore        17
    2161: iload         45
    2163: ifeq          2169
    2166: iinc          14, -1
    2169: iload         14
    2171: ifle          2203
    2174: aload_0
    2175: getfield      #118                // Field m:[[[I
    2178: iload         11
    2180: aaload
    2181: iload         13
    2183: aaload
    2184: iload         14
    2186: iconst_1
    2187: isub
    2188: iaload
    2189: iload         7
    2191: iand
    2192: ifne          2166
    2195: iload         45
    2197: ifeq          2203
    2200: iinc          15, 1
    2203: iload         15
    2205: aload_0
    2206: getfield      #100                // Field y:I
    2209: if_icmpge     2284
    2212: aload_0
    2213: getfield      #118                // Field m:[[[I
    2216: iload         11
    2218: aaload
    2219: iload         13
    2221: aaload
    2222: iload         15
    2224: iconst_1
    2225: iadd
    2226: iaload
    2227: iload         7
    2229: iand
    2230: ifne          2200
    2233: iload         45
    2235: ifeq          2284
    2238: iload         14
    2240: istore        18
    2242: iload         45
    2244: ifeq          2274
    2247: aload_0
    2248: getfield      #118                // Field m:[[[I
    2251: iload         16
    2253: iconst_1
    2254: isub
    2255: aaload
    2256: iload         13
    2258: aaload
    2259: iload         18
    2261: iaload
    2262: iload         7
    2264: iand
    2265: ifne          2271
    2268: goto          2340
    2271: iinc          18, 1
    2274: iload         18
    2276: iload         15
    2278: if_icmple     2247
    2281: iinc          16, -1
    2284: iload         16
    2286: ifgt          2238
    2289: iload         45
    2291: ifeq          2340
    2294: iload         14
    2296: istore        18
    2298: iload         45
    2300: ifeq          2330
    2303: aload_0
    2304: getfield      #118                // Field m:[[[I
    2307: iload         17
    2309: iconst_1
    2310: iadd
    2311: aaload
    2312: iload         13
    2314: aaload
    2315: iload         18
    2317: iaload
    2318: iload         7
    2320: iand
    2321: ifne          2327
    2324: goto          2347
    2327: iinc          18, 1
    2330: iload         18
    2332: iload         15
    2334: if_icmple     2303
    2337: iinc          17, 1
    2340: iload         17
    2342: iload         10
    2344: if_icmplt     2294
    2347: iload         17
    2349: iconst_1
    2350: iadd
    2351: iload         16
    2353: isub
    2354: iload         15
    2356: iload         14
    2358: isub
    2359: iconst_1
    2360: iadd
    2361: imul
    2362: istore        18
    2364: iload         18
    2366: bipush        8
    2368: if_icmplt     2509
    2371: sipush        240
    2374: istore        19
    2376: aload_0
    2377: getfield      #98                 // Field g:[[[I
    2380: iload         17
    2382: aaload
    2383: iload         13
    2385: aaload
    2386: iload         14
    2388: iaload
    2389: iload         19
    2391: isub
    2392: istore        20
    2394: aload_0
    2395: getfield      #98                 // Field g:[[[I
    2398: iload         16
    2400: aaload
    2401: iload         13
    2403: aaload
    2404: iload         14
    2406: iaload
    2407: istore        21
    2409: iload         10
    2411: iload         13
    2413: sipush        128
    2416: imul
    2417: iload         21
    2419: iload         13
    2421: sipush        128
    2424: imul
    2425: iload         15
    2427: sipush        128
    2430: imul
    2431: sipush        128
    2434: iadd
    2435: iload         20
    2437: aload_0
    2438: getfield      #127                // Field B:I
    2441: iload         14
    2443: sipush        128
    2446: imul
    2447: iconst_1
    2448: invokestatic  #139                // Method NYFUGYQS.a:(IIIIIIIII)V
    2451: iload         16
    2453: istore        22
    2455: iload         45
    2457: ifeq          2502
    2460: iload         14
    2462: istore        23
    2464: iload         45
    2466: ifeq          2492
    2469: aload_0
    2470: getfield      #118                // Field m:[[[I
    2473: iload         22
    2475: aaload
    2476: iload         13
    2478: aaload
    2479: iload         23
    2481: dup2
    2482: iaload
    2483: iload         7
    2485: iconst_m1
    2486: ixor
    2487: iand
    2488: iastore
    2489: iinc          23, 1
    2492: iload         23
    2494: iload         15
    2496: if_icmple     2469
    2499: iinc          22, 1
    2502: iload         22
    2504: iload         17
    2506: if_icmple     2460
    2509: aload_0
    2510: getfield      #118                // Field m:[[[I
    2513: iload         11
    2515: aaload
    2516: iload         13
    2518: aaload
    2519: iload         12
    2521: iaload
    2522: iload         8
    2524: iand
    2525: ifeq          2892
    2528: iload         13
    2530: istore        14
    2532: iload         13
    2534: istore        15
    2536: iload         11
    2538: istore        16
    2540: iload         11
    2542: istore        17
    2544: iload         45
    2546: ifeq          2552
    2549: iinc          14, -1
    2552: iload         14
    2554: ifle          2586
    2557: aload_0
    2558: getfield      #118                // Field m:[[[I
    2561: iload         11
    2563: aaload
    2564: iload         14
    2566: iconst_1
    2567: isub
    2568: aaload
    2569: iload         12
    2571: iaload
    2572: iload         8
    2574: iand
    2575: ifne          2549
    2578: iload         45
    2580: ifeq          2586
    2583: iinc          15, 1
    2586: iload         15
    2588: aload_0
    2589: getfield      #153                // Field x:I
    2592: if_icmpge     2667
    2595: aload_0
    2596: getfield      #118                // Field m:[[[I
    2599: iload         11
    2601: aaload
    2602: iload         15
    2604: iconst_1
    2605: iadd
    2606: aaload
    2607: iload         12
    2609: iaload
    2610: iload         8
    2612: iand
    2613: ifne          2583
    2616: iload         45
    2618: ifeq          2667
    2621: iload         14
    2623: istore        18
    2625: iload         45
    2627: ifeq          2657
    2630: aload_0
    2631: getfield      #118                // Field m:[[[I
    2634: iload         16
    2636: iconst_1
    2637: isub
    2638: aaload
    2639: iload         18
    2641: aaload
    2642: iload         12
    2644: iaload
    2645: iload         8
    2647: iand
    2648: ifne          2654
    2651: goto          2723
    2654: iinc          18, 1
    2657: iload         18
    2659: iload         15
    2661: if_icmple     2630
    2664: iinc          16, -1
    2667: iload         16
    2669: ifgt          2621
    2672: iload         45
    2674: ifeq          2723
    2677: iload         14
    2679: istore        18
    2681: iload         45
    2683: ifeq          2713
    2686: aload_0
    2687: getfield      #118                // Field m:[[[I
    2690: iload         17
    2692: iconst_1
    2693: iadd
    2694: aaload
    2695: iload         18
    2697: aaload
    2698: iload         12
    2700: iaload
    2701: iload         8
    2703: iand
    2704: ifne          2710
    2707: goto          2730
    2710: iinc          18, 1
    2713: iload         18
    2715: iload         15
    2717: if_icmple     2686
    2720: iinc          17, 1
    2723: iload         17
    2725: iload         10
    2727: if_icmplt     2677
    2730: iload         17
    2732: iconst_1
    2733: iadd
    2734: iload         16
    2736: isub
    2737: iload         15
    2739: iload         14
    2741: isub
    2742: iconst_1
    2743: iadd
    2744: imul
    2745: istore        18
    2747: iload         18
    2749: bipush        8
    2751: if_icmplt     2892
    2754: sipush        240
    2757: istore        19
    2759: aload_0
    2760: getfield      #98                 // Field g:[[[I
    2763: iload         17
    2765: aaload
    2766: iload         14
    2768: aaload
    2769: iload         12
    2771: iaload
    2772: iload         19
    2774: isub
    2775: istore        20
    2777: aload_0
    2778: getfield      #98                 // Field g:[[[I
    2781: iload         16
    2783: aaload
    2784: iload         14
    2786: aaload
    2787: iload         12
    2789: iaload
    2790: istore        21
    2792: iload         10
    2794: iload         14
    2796: sipush        128
    2799: imul
    2800: iload         21
    2802: iload         15
    2804: sipush        128
    2807: imul
    2808: sipush        128
    2811: iadd
    2812: iload         12
    2814: sipush        128
    2817: imul
    2818: iload         20
    2820: aload_0
    2821: getfield      #127                // Field B:I
    2824: iload         12
    2826: sipush        128
    2829: imul
    2830: iconst_2
    2831: invokestatic  #139                // Method NYFUGYQS.a:(IIIIIIIII)V
    2834: iload         16
    2836: istore        22
    2838: iload         45
    2840: ifeq          2885
    2843: iload         14
    2845: istore        23
    2847: iload         45
    2849: ifeq          2875
    2852: aload_0
    2853: getfield      #118                // Field m:[[[I
    2856: iload         22
    2858: aaload
    2859: iload         23
    2861: aaload
    2862: iload         12
    2864: dup2
    2865: iaload
    2866: iload         8
    2868: iconst_m1
    2869: ixor
    2870: iand
    2871: iastore
    2872: iinc          23, 1
    2875: iload         23
    2877: iload         15
    2879: if_icmple     2852
    2882: iinc          22, 1
    2885: iload         22
    2887: iload         17
    2889: if_icmple     2843
    2892: aload_0
    2893: getfield      #118                // Field m:[[[I
    2896: iload         11
    2898: aaload
    2899: iload         13
    2901: aaload
    2902: iload         12
    2904: iaload
    2905: iload         9
    2907: iand
    2908: ifeq          3253
    2911: iload         13
    2913: istore        14
    2915: iload         13
    2917: istore        15
    2919: iload         12
    2921: istore        16
    2923: iload         12
    2925: istore        17
    2927: iload         45
    2929: ifeq          2935
    2932: iinc          16, -1
    2935: iload         16
    2937: ifle          2969
    2940: aload_0
    2941: getfield      #118                // Field m:[[[I
    2944: iload         11
    2946: aaload
    2947: iload         13
    2949: aaload
    2950: iload         16
    2952: iconst_1
    2953: isub
    2954: iaload
    2955: iload         9
    2957: iand
    2958: ifne          2932
    2961: iload         45
    2963: ifeq          2969
    2966: iinc          17, 1
    2969: iload         17
    2971: aload_0
    2972: getfield      #100                // Field y:I
    2975: if_icmpge     3050
    2978: aload_0
    2979: getfield      #118                // Field m:[[[I
    2982: iload         11
    2984: aaload
    2985: iload         13
    2987: aaload
    2988: iload         17
    2990: iconst_1
    2991: iadd
    2992: iaload
    2993: iload         9
    2995: iand
    2996: ifne          2966
    2999: iload         45
    3001: ifeq          3050
    3004: iload         16
    3006: istore        18
    3008: iload         45
    3010: ifeq          3040
    3013: aload_0
    3014: getfield      #118                // Field m:[[[I
    3017: iload         11
    3019: aaload
    3020: iload         14
    3022: iconst_1
    3023: isub
    3024: aaload
    3025: iload         18
    3027: iaload
    3028: iload         9
    3030: iand
    3031: ifne          3037
    3034: goto          3106
    3037: iinc          18, 1
    3040: iload         18
    3042: iload         17
    3044: if_icmple     3013
    3047: iinc          14, -1
    3050: iload         14
    3052: ifgt          3004
    3055: iload         45
    3057: ifeq          3106
    3060: iload         16
    3062: istore        18
    3064: iload         45
    3066: ifeq          3096
    3069: aload_0
    3070: getfield      #118                // Field m:[[[I
    3073: iload         11
    3075: aaload
    3076: iload         15
    3078: iconst_1
    3079: iadd
    3080: aaload
    3081: iload         18
    3083: iaload
    3084: iload         9
    3086: iand
    3087: ifne          3093
    3090: goto          3115
    3093: iinc          18, 1
    3096: iload         18
    3098: iload         17
    3100: if_icmple     3069
    3103: iinc          15, 1
    3106: iload         15
    3108: aload_0
    3109: getfield      #153                // Field x:I
    3112: if_icmplt     3060
    3115: iload         15
    3117: iload         14
    3119: isub
    3120: iconst_1
    3121: iadd
    3122: iload         17
    3124: iload         16
    3126: isub
    3127: iconst_1
    3128: iadd
    3129: imul
    3130: iconst_4
    3131: if_icmplt     3253
    3134: aload_0
    3135: getfield      #98                 // Field g:[[[I
    3138: iload         11
    3140: aaload
    3141: iload         14
    3143: aaload
    3144: iload         16
    3146: iaload
    3147: istore        18
    3149: iload         10
    3151: iload         14
    3153: sipush        128
    3156: imul
    3157: iload         18
    3159: iload         15
    3161: sipush        128
    3164: imul
    3165: sipush        128
    3168: iadd
    3169: iload         17
    3171: sipush        128
    3174: imul
    3175: sipush        128
    3178: iadd
    3179: iload         18
    3181: aload_0
    3182: getfield      #127                // Field B:I
    3185: iload         16
    3187: sipush        128
    3190: imul
    3191: iconst_4
    3192: invokestatic  #139                // Method NYFUGYQS.a:(IIIIIIIII)V
    3195: iload         14
    3197: istore        19
    3199: iload         45
    3201: ifeq          3246
    3204: iload         16
    3206: istore        20
    3208: iload         45
    3210: ifeq          3236
    3213: aload_0
    3214: getfield      #118                // Field m:[[[I
    3217: iload         11
    3219: aaload
    3220: iload         19
    3222: aaload
    3223: iload         20
    3225: dup2
    3226: iaload
    3227: iload         9
    3229: iconst_m1
    3230: ixor
    3231: iand
    3232: iastore
    3233: iinc          20, 1
    3236: iload         20
    3238: iload         17
    3240: if_icmple     3213
    3243: iinc          19, 1
    3246: iload         19
    3248: iload         15
    3250: if_icmple     3204
    3253: iinc          13, 1
    3256: iload         13
    3258: aload_0
    3259: getfield      #153                // Field x:I
    3262: if_icmple     2126
    3265: iinc          12, 1
    3268: iload         12
    3270: aload_0
    3271: getfield      #100                // Field y:I
    3274: if_icmple     2118
    3277: iinc          11, 1
    3280: iload         11
    3282: iload         10
    3284: if_icmple     2110
    3287: iinc          10, 1
    3290: iload         10
    3292: iconst_4
    3293: if_icmplt     2079
    3296: return
    3297: astore        4
    3299: new           #44                 // class java/lang/StringBuffer
    3302: dup
    3303: ldc           #30                 // String 90532,
    3305: invokespecial #55                 // Method java/lang/StringBuffer."<init>":(Ljava/lang/String;)V
    3308: aload_1
    3309: invokevirtual #64                 // Method java/lang/StringBuffer.append:(Ljava/lang/Object;)Ljava/lang/StringBuffer;
    3312: ldc           #16                 // String ,
    3314: invokevirtual #65                 // Method java/lang/StringBuffer.append:(Ljava/lang/String;)Ljava/lang/StringBuffer;
    3317: aload_2
    3318: invokevirtual #64                 // Method java/lang/StringBuffer.append:(Ljava/lang/Object;)Ljava/lang/StringBuffer;
    3321: ldc           #16                 // String ,
    3323: invokevirtual #65                 // Method java/lang/StringBuffer.append:(Ljava/lang/String;)Ljava/lang/StringBuffer;
    3326: iload_3
    3327: invokevirtual #63                 // Method java/lang/StringBuffer.append:(I)Ljava/lang/StringBuffer;
    3330: ldc           #16                 // String ,
    3332: invokevirtual #65                 // Method java/lang/StringBuffer.append:(Ljava/lang/String;)Ljava/lang/StringBuffer;
    3335: aload         4
    3337: invokevirtual #149                // Method java/lang/Throwable.toString:()Ljava/lang/String;
    3340: invokevirtual #65                 // Method java/lang/StringBuffer.append:(Ljava/lang/String;)Ljava/lang/StringBuffer;
    3343: invokevirtual #148                // Method java/lang/StringBuffer.toString:()Ljava/lang/String;
    3346: invokestatic  #132                // Method sign/signlink.reporterror:(Ljava/lang/String;)V
    3349: new           #43                 // class java/lang/RuntimeException
    3352: dup
    3353: invokespecial #53                 // Method java/lang/RuntimeException."<init>":()V
    3356: athrow
    Exception table:
       from    to  target type
           5  3296  3297   Class java/lang/RuntimeException

  private static final int b(int, int);
    Code:
       0: iload_0
       1: ldc           #2                  // int 45365
       3: iadd
       4: iload_1
       5: ldc           #5                  // int 91923
       7: iadd
       8: iconst_4
       9: invokestatic  #107                // Method a:(III)I
      12: sipush        128
      15: isub
      16: iload_0
      17: sipush        10294
      20: iadd
      21: iload_1
      22: ldc           #1                  // int 37821
      24: iadd
      25: iconst_2
      26: invokestatic  #107                // Method a:(III)I
      29: sipush        128
      32: isub
      33: iconst_1
      34: ishr
      35: iadd
      36: iload_0
      37: iload_1
      38: iconst_1
      39: invokestatic  #107                // Method a:(III)I
      42: sipush        128
      45: isub
      46: iconst_2
      47: ishr
      48: iadd
      49: istore_2
      50: iload_2
      51: i2d
      52: ldc2_w        #161                // double 0.3d
      55: dmul
      56: d2i
      57: bipush        35
      59: iadd
      60: istore_2
      61: iload_2
      62: bipush        10
      64: if_icmpge     76
      67: bipush        10
      69: istore_2
      70: getstatic     #414                // Field client.Jj:I
      73: ifeq          85
      76: iload_2
      77: bipush        60
      79: if_icmple     85
      82: bipush        60
      84: istore_2
      85: iload_2
      86: ireturn

  public static final void a(byte, MBMGIXGO, GHOWLKWN);
    Code:
       0: getstatic     #414                // Field client.Jj:I
       3: istore        7
       5: iconst_m1
       6: istore_3
       7: iload_0
       8: bipush        -107
      10: if_icmpeq     27
      13: getstatic     #160                // Field s:Z
      16: ifeq          23
      19: iconst_0
      20: goto          24
      23: iconst_1
      24: putstatic     #160                // Field s:Z
      27: aload_1
      28: invokevirtual #99                 // Method MBMGIXGO.k:()I
      31: istore        4
      33: iload         4
      35: ifeq          84
      38: iload_3
      39: iload         4
      41: iadd
      42: istore_3
      43: iload_3
      44: invokestatic  #113                // Method YZDBYLRM.a:(I)LYZDBYLRM;
      47: astore        5
      49: aload         5
      51: aload_2
      52: sipush        -235
      55: invokevirtual #128                // Method YZDBYLRM.a:(LGHOWLKWN;I)V
      58: aload_1
      59: invokevirtual #99                 // Method MBMGIXGO.k:()I
      62: istore        6
      64: iload         6
      66: ifeq          79
      69: aload_1
      70: invokevirtual #92                 // Method MBMGIXGO.c:()I
      73: pop
      74: iload         7
      76: ifeq          58
      79: iload         7
      81: ifeq          27
      84: return
      85: astore_3
      86: new           #44                 // class java/lang/StringBuffer
      89: dup
      90: ldc           #28                 // String 73405,
      92: invokespecial #55                 // Method java/lang/StringBuffer."<init>":(Ljava/lang/String;)V
      95: iload_0
      96: invokevirtual #63                 // Method java/lang/StringBuffer.append:(I)Ljava/lang/StringBuffer;
      99: ldc           #16                 // String ,
     101: invokevirtual #65                 // Method java/lang/StringBuffer.append:(Ljava/lang/String;)Ljava/lang/StringBuffer;
     104: aload_1
     105: invokevirtual #64                 // Method java/lang/StringBuffer.append:(Ljava/lang/Object;)Ljava/lang/StringBuffer;
     108: ldc           #16                 // String ,
     110: invokevirtual #65                 // Method java/lang/StringBuffer.append:(Ljava/lang/String;)Ljava/lang/StringBuffer;
     113: aload_2
     114: invokevirtual #64                 // Method java/lang/StringBuffer.append:(Ljava/lang/Object;)Ljava/lang/StringBuffer;
     117: ldc           #16                 // String ,
     119: invokevirtual #65                 // Method java/lang/StringBuffer.append:(Ljava/lang/String;)Ljava/lang/StringBuffer;
     122: aload_3
     123: invokevirtual #149                // Method java/lang/Throwable.toString:()Ljava/lang/String;
     126: invokevirtual #65                 // Method java/lang/StringBuffer.append:(Ljava/lang/String;)Ljava/lang/StringBuffer;
     129: invokevirtual #148                // Method java/lang/StringBuffer.toString:()Ljava/lang/String;
     132: invokestatic  #132                // Method sign/signlink.reporterror:(Ljava/lang/String;)V
     135: new           #43                 // class java/lang/RuntimeException
     138: dup
     139: invokespecial #53                 // Method java/lang/RuntimeException."<init>":()V
     142: athrow
    Exception table:
       from    to  target type
           5    84    85   Class java/lang/RuntimeException

  public final void a(int, int, int, int, int);
    Code:
       0: getstatic     #414                // Field client.Jj:I
       3: istore        8
       5: iload_1
       6: istore        6
       8: iload         8
      10: ifeq          247
      13: iload         5
      15: istore        7
      17: iload         8
      19: ifeq          234
      22: iload         7
      24: iflt          231
      27: iload         7
      29: aload_0
      30: getfield      #153                // Field x:I
      33: if_icmpge     231
      36: iload         6
      38: iflt          231
      41: iload         6
      43: aload_0
      44: getfield      #100                // Field y:I
      47: if_icmpge     231
      50: aload_0
      51: getfield      #142                // Field l:[[[B
      54: iconst_0
      55: aaload
      56: iload         7
      58: aaload
      59: iload         6
      61: bipush        127
      63: bastore
      64: iload         7
      66: iload         5
      68: if_icmpne     102
      71: iload         7
      73: ifle          102
      76: aload_0
      77: getfield      #98                 // Field g:[[[I
      80: iconst_0
      81: aaload
      82: iload         7
      84: aaload
      85: iload         6
      87: aload_0
      88: getfield      #98                 // Field g:[[[I
      91: iconst_0
      92: aaload
      93: iload         7
      95: iconst_1
      96: isub
      97: aaload
      98: iload         6
     100: iaload
     101: iastore
     102: iload         7
     104: iload         5
     106: iload         4
     108: iadd
     109: if_icmpne     149
     112: iload         7
     114: aload_0
     115: getfield      #153                // Field x:I
     118: iconst_1
     119: isub
     120: if_icmpge     149
     123: aload_0
     124: getfield      #98                 // Field g:[[[I
     127: iconst_0
     128: aaload
     129: iload         7
     131: aaload
     132: iload         6
     134: aload_0
     135: getfield      #98                 // Field g:[[[I
     138: iconst_0
     139: aaload
     140: iload         7
     142: iconst_1
     143: iadd
     144: aaload
     145: iload         6
     147: iaload
     148: iastore
     149: iload         6
     151: iload_1
     152: if_icmpne     186
     155: iload         6
     157: ifle          186
     160: aload_0
     161: getfield      #98                 // Field g:[[[I
     164: iconst_0
     165: aaload
     166: iload         7
     168: aaload
     169: iload         6
     171: aload_0
     172: getfield      #98                 // Field g:[[[I
     175: iconst_0
     176: aaload
     177: iload         7
     179: aaload
     180: iload         6
     182: iconst_1
     183: isub
     184: iaload
     185: iastore
     186: iload         6
     188: iload_1
     189: iload_2
     190: iadd
     191: if_icmpne     231
     194: iload         6
     196: aload_0
     197: getfield      #100                // Field y:I
     200: iconst_1
     201: isub
     202: if_icmpge     231
     205: aload_0
     206: getfield      #98                 // Field g:[[[I
     209: iconst_0
     210: aaload
     211: iload         7
     213: aaload
     214: iload         6
     216: aload_0
     217: getfield      #98                 // Field g:[[[I
     220: iconst_0
     221: aaload
     222: iload         7
     224: aaload
     225: iload         6
     227: iconst_1
     228: iadd
     229: iaload
     230: iastore
     231: iinc          7, 1
     234: iload         7
     236: iload         5
     238: iload         4
     240: iadd
     241: if_icmple     22
     244: iinc          6, 1
     247: iload         6
     249: iload_1
     250: iload_2
     251: iadd
     252: if_icmple     13
     255: iload_3
     256: ifeq          346
     259: sipush        284
     262: putstatic     #151                // Field E:I
     265: return
     266: astore        6
     268: new           #44                 // class java/lang/StringBuffer
     271: dup
     272: ldc           #27                 // String 73091,
     274: invokespecial #55                 // Method java/lang/StringBuffer."<init>":(Ljava/lang/String;)V
     277: iload_1
     278: invokevirtual #63                 // Method java/lang/StringBuffer.append:(I)Ljava/lang/StringBuffer;
     281: ldc           #16                 // String ,
     283: invokevirtual #65                 // Method java/lang/StringBuffer.append:(Ljava/lang/String;)Ljava/lang/StringBuffer;
     286: iload_2
     287: invokevirtual #63                 // Method java/lang/StringBuffer.append:(I)Ljava/lang/StringBuffer;
     290: ldc           #16                 // String ,
     292: invokevirtual #65                 // Method java/lang/StringBuffer.append:(Ljava/lang/String;)Ljava/lang/StringBuffer;
     295: iload_3
     296: invokevirtual #63                 // Method java/lang/StringBuffer.append:(I)Ljava/lang/StringBuffer;
     299: ldc           #16                 // String ,
     301: invokevirtual #65                 // Method java/lang/StringBuffer.append:(Ljava/lang/String;)Ljava/lang/StringBuffer;
     304: iload         4
     306: invokevirtual #63                 // Method java/lang/StringBuffer.append:(I)Ljava/lang/StringBuffer;
     309: ldc           #16                 // String ,
     311: invokevirtual #65                 // Method java/lang/StringBuffer.append:(Ljava/lang/String;)Ljava/lang/StringBuffer;
     314: iload         5
     316: invokevirtual #63                 // Method java/lang/StringBuffer.append:(I)Ljava/lang/StringBuffer;
     319: ldc           #16                 // String ,
     321: invokevirtual #65                 // Method java/lang/StringBuffer.append:(Ljava/lang/String;)Ljava/lang/StringBuffer;
     324: aload         6
     326: invokevirtual #149                // Method java/lang/Throwable.toString:()Ljava/lang/String;
     329: invokevirtual #65                 // Method java/lang/StringBuffer.append:(Ljava/lang/String;)Ljava/lang/StringBuffer;
     332: invokevirtual #148                // Method java/lang/StringBuffer.toString:()Ljava/lang/String;
     335: invokestatic  #132                // Method sign/signlink.reporterror:(Ljava/lang/String;)V
     338: new           #43                 // class java/lang/RuntimeException
     341: dup
     342: invokespecial #53                 // Method java/lang/RuntimeException."<init>":()V
     345: athrow
     346: return
    Exception table:
       from    to  target type
           5   265   266   Class java/lang/RuntimeException

  private final void a(int, NYFUGYQS, FTPNODIB, int, int, int, int, boolean, int);
    Code:
       0: getstatic     #414                // Field client.Jj:I
       3: istore        26
       5: getstatic     #116                // Field C:Z
       8: ifeq          63
      11: aload_0
      12: getfield      #117                // Field A:[[[B
      15: iconst_0
      16: aaload
      17: iload         6
      19: aaload
      20: iload_1
      21: baload
      22: iconst_2
      23: iand
      24: ifne          63
      27: aload_0
      28: getfield      #117                // Field A:[[[B
      31: iload         5
      33: aaload
      34: iload         6
      36: aaload
      37: iload_1
      38: baload
      39: bipush        16
      41: iand
      42: ifeq          46
      45: return
      46: aload_0
      47: iload_1
      48: iload         5
      50: iload         6
      52: iconst_0
      53: invokevirtual #152                // Method a:(IIII)I
      56: getstatic     #70                 // Field i:I
      59: if_icmpeq     63
      62: return
      63: iload         5
      65: getstatic     #120                // Field w:I
      68: if_icmpge     76
      71: iload         5
      73: putstatic     #120                // Field w:I
      76: aload_0
      77: getfield      #98                 // Field g:[[[I
      80: iload         5
      82: aaload
      83: iload         6
      85: aaload
      86: iload_1
      87: iaload
      88: istore        10
      90: aload_0
      91: getfield      #98                 // Field g:[[[I
      94: iload         5
      96: aaload
      97: iload         6
      99: iconst_1
     100: iadd
     101: aaload
     102: iload_1
     103: iaload
     104: istore        11
     106: aload_0
     107: getfield      #98                 // Field g:[[[I
     110: iload         5
     112: aaload
     113: iload         6
     115: iconst_1
     116: iadd
     117: aaload
     118: iload_1
     119: iconst_1
     120: iadd
     121: iaload
     122: istore        12
     124: aload_0
     125: getfield      #98                 // Field g:[[[I
     128: iload         5
     130: aaload
     131: iload         6
     133: aaload
     134: iload_1
     135: iconst_1
     136: iadd
     137: iaload
     138: istore        13
     140: iload         10
     142: iload         11
     144: iadd
     145: iload         12
     147: iadd
     148: iload         13
     150: iadd
     151: iconst_2
     152: ishr
     153: istore        14
     155: iload         7
     157: invokestatic  #113                // Method YZDBYLRM.a:(I)LYZDBYLRM;
     160: astore        15
     162: iload         6
     164: iload_1
     165: bipush        7
     167: ishl
     168: iadd
     169: iload         7
     171: bipush        14
     173: ishl
     174: iadd
     175: ldc           #12                 // int 1073741824
     177: iadd
     178: istore        16
     180: aload         15
     182: getfield      #57                 // Field YZDBYLRM.Q:Z
     185: ifne          195
     188: iload         16
     190: ldc           #15                 // int -2147483648
     192: iadd
     193: istore        16
     195: iload         9
     197: bipush        6
     199: ishl
     200: iload         4
     202: iadd
     203: i2b
     204: istore        17
     206: iload         8
     208: ifeq          212
     211: return
     212: iload         4
     214: bipush        22
     216: if_icmpne     363
     219: getstatic     #116                // Field C:Z
     222: ifeq          242
     225: aload         15
     227: getfield      #57                 // Field YZDBYLRM.Q:Z
     230: ifne          242
     233: aload         15
     235: getfield      #91                 // Field YZDBYLRM.a:Z
     238: ifne          242
     241: return
     242: aload         15
     244: getfield      #62                 // Field YZDBYLRM.T:I
     247: iconst_m1
     248: if_icmpne     284
     251: aload         15
     253: getfield      #122                // Field YZDBYLRM.x:[I
     256: ifnonnull     284
     259: aload         15
     261: bipush        22
     263: iload         9
     265: iload         10
     267: iload         11
     269: iload         12
     271: iload         13
     273: iconst_m1
     274: invokevirtual #94                 // Method YZDBYLRM.a:(IIIIIII)LZKARKDQW;
     277: astore        18
     279: iload         26
     281: ifeq          315
     284: new           #35                 // class WBWOBAFW
     287: dup
     288: iload         7
     290: iload         9
     292: bipush        22
     294: iload         11
     296: bipush        7
     298: iload         12
     300: iload         10
     302: iload         13
     304: aload         15
     306: getfield      #62                 // Field YZDBYLRM.T:I
     309: iconst_1
     310: invokespecial #54                 // Method WBWOBAFW."<init>":(IIIIBIIIIZ)V
     313: astore        18
     315: aload_2
     316: iload         5
     318: iload         14
     320: iload_1
     321: bipush        68
     323: aload         18
     325: iload         17
     327: iload         16
     329: iload         6
     331: invokevirtual #137                // Method NYFUGYQS.a:(IIIILXHHRODPC;BII)V
     334: aload         15
     336: getfield      #69                 // Field YZDBYLRM.F:Z
     339: ifeq          362
     342: aload         15
     344: getfield      #57                 // Field YZDBYLRM.Q:Z
     347: ifeq          362
     350: aload_3
     351: ifnull        362
     354: aload_3
     355: iload_1
     356: iconst_0
     357: iload         6
     359: invokevirtual #67                 // Method FTPNODIB.a:(III)V
     362: return
     363: iload         4
     365: bipush        10
     367: if_icmpeq     377
     370: iload         4
     372: bipush        11
     374: if_icmpne     737
     377: aload         15
     379: getfield      #62                 // Field YZDBYLRM.T:I
     382: iconst_m1
     383: if_icmpne     419
     386: aload         15
     388: getfield      #122                // Field YZDBYLRM.x:[I
     391: ifnonnull     419
     394: aload         15
     396: bipush        10
     398: iload         9
     400: iload         10
     402: iload         11
     404: iload         12
     406: iload         13
     408: iconst_m1
     409: invokevirtual #94                 // Method YZDBYLRM.a:(IIIIIII)LZKARKDQW;
     412: astore        18
     414: iload         26
     416: ifeq          450
     419: new           #35                 // class WBWOBAFW
     422: dup
     423: iload         7
     425: iload         9
     427: bipush        10
     429: iload         11
     431: bipush        7
     433: iload         12
     435: iload         10
     437: iload         13
     439: aload         15
     441: getfield      #62                 // Field YZDBYLRM.T:I
     444: iconst_1
     445: invokespecial #54                 // Method WBWOBAFW."<init>":(IIIIBIIIIZ)V
     448: astore        18
     450: aload         18
     452: ifnull        697
     455: iconst_0
     456: istore        21
     458: iload         4
     460: bipush        11
     462: if_icmpne     471
     465: iinc_w        21, 256
     471: iload         9
     473: iconst_1
     474: if_icmpeq     483
     477: iload         9
     479: iconst_3
     480: if_icmpne     502
     483: aload         15
     485: getfield      #109                // Field YZDBYLRM.z:I
     488: istore        19
     490: aload         15
     492: getfield      #157                // Field YZDBYLRM.i:I
     495: istore        20
     497: iload         26
     499: ifeq          516
     502: aload         15
     504: getfield      #157                // Field YZDBYLRM.i:I
     507: istore        19
     509: aload         15
     511: getfield      #109                // Field YZDBYLRM.z:I
     514: istore        20
     516: aload_2
     517: iload         16
     519: iload         17
     521: iload         14
     523: iload         20
     525: aload         18
     527: iload         19
     529: iload         5
     531: iload         21
     533: bipush        110
     535: iload_1
     536: iload         6
     538: invokevirtual #60                 // Method NYFUGYQS.a:(IBIILXHHRODPC;IIIBII)Z
     541: ifeq          697
     544: aload         15
     546: getfield      #141                // Field YZDBYLRM.R:Z
     549: ifeq          697
     552: aload         18
     554: instanceof    #36                 // class ZKARKDQW
     557: ifeq          572
     560: aload         18
     562: checkcast     #36                 // class ZKARKDQW
     565: astore        22
     567: iload         26
     569: ifeq          592
     572: aload         15
     574: bipush        10
     576: iload         9
     578: iload         10
     580: iload         11
     582: iload         12
     584: iload         13
     586: iconst_m1
     587: invokevirtual #94                 // Method YZDBYLRM.a:(IIIIIII)LZKARKDQW;
     590: astore        22
     592: aload         22
     594: ifnull        697
     597: iconst_0
     598: istore        23
     600: iload         26
     602: ifeq          690
     605: iconst_0
     606: istore        24
     608: iload         26
     610: ifeq          680
     613: aload         22
     615: getfield      #130                // Field ZKARKDQW.W:I
     618: iconst_4
     619: idiv
     620: istore        25
     622: iload         25
     624: bipush        30
     626: if_icmple     633
     629: bipush        30
     631: istore        25
     633: iload         25
     635: aload_0
     636: getfield      #142                // Field l:[[[B
     639: iload         5
     641: aaload
     642: iload         6
     644: iload         23
     646: iadd
     647: aaload
     648: iload_1
     649: iload         24
     651: iadd
     652: baload
     653: if_icmple     677
     656: aload_0
     657: getfield      #142                // Field l:[[[B
     660: iload         5
     662: aaload
     663: iload         6
     665: iload         23
     667: iadd
     668: aaload
     669: iload_1
     670: iload         24
     672: iadd
     673: iload         25
     675: i2b
     676: bastore
     677: iinc          24, 1
     680: iload         24
     682: iload         20
     684: if_icmple     613
     687: iinc          23, 1
     690: iload         23
     692: iload         19
     694: if_icmple     605
     697: aload         15
     699: getfield      #69                 // Field YZDBYLRM.F:Z
     702: ifeq          736
     705: aload_3
     706: ifnull        736
     709: aload_3
     710: aload         15
     712: getfield      #68                 // Field YZDBYLRM.v:Z
     715: getstatic     #75                 // Field p:I
     718: aload         15
     720: getfield      #157                // Field YZDBYLRM.i:I
     723: aload         15
     725: getfield      #109                // Field YZDBYLRM.z:I
     728: iload         6
     730: iload_1
     731: iload         9
     733: invokevirtual #59                 // Method FTPNODIB.a:(ZIIIIII)V
     736: return
     737: iload         4
     739: bipush        12
     741: if_icmplt     924
     744: aload         15
     746: getfield      #62                 // Field YZDBYLRM.T:I
     749: iconst_m1
     750: if_icmpne     786
     753: aload         15
     755: getfield      #122                // Field YZDBYLRM.x:[I
     758: ifnonnull     786
     761: aload         15
     763: iload         4
     765: iload         9
     767: iload         10
     769: iload         11
     771: iload         12
     773: iload         13
     775: iconst_m1
     776: invokevirtual #94                 // Method YZDBYLRM.a:(IIIIIII)LZKARKDQW;
     779: astore        18
     781: iload         26
     783: ifeq          817
     786: new           #35                 // class WBWOBAFW
     789: dup
     790: iload         7
     792: iload         9
     794: iload         4
     796: iload         11
     798: bipush        7
     800: iload         12
     802: iload         10
     804: iload         13
     806: aload         15
     808: getfield      #62                 // Field YZDBYLRM.T:I
     811: iconst_1
     812: invokespecial #54                 // Method WBWOBAFW."<init>":(IIIIBIIIIZ)V
     815: astore        18
     817: aload_2
     818: iload         16
     820: iload         17
     822: iload         14
     824: iconst_1
     825: aload         18
     827: iconst_1
     828: iload         5
     830: iconst_0
     831: bipush        110
     833: iload_1
     834: iload         6
     836: invokevirtual #60                 // Method NYFUGYQS.a:(IBIILXHHRODPC;IIIBII)Z
     839: pop
     840: iload         4
     842: bipush        12
     844: if_icmplt     884
     847: iload         4
     849: bipush        17
     851: if_icmpgt     884
     854: iload         4
     856: bipush        13
     858: if_icmpeq     884
     861: iload         5
     863: ifle          884
     866: aload_0
     867: getfield      #118                // Field m:[[[I
     870: iload         5
     872: aaload
     873: iload         6
     875: aaload
     876: iload_1
     877: dup2
     878: iaload
     879: sipush        2340
     882: ior
     883: iastore
     884: aload         15
     886: getfield      #69                 // Field YZDBYLRM.F:Z
     889: ifeq          923
     892: aload_3
     893: ifnull        923
     896: aload_3
     897: aload         15
     899: getfield      #68                 // Field YZDBYLRM.v:Z
     902: getstatic     #75                 // Field p:I
     905: aload         15
     907: getfield      #157                // Field YZDBYLRM.i:I
     910: aload         15
     912: getfield      #109                // Field YZDBYLRM.z:I
     915: iload         6
     917: iload_1
     918: iload         9
     920: invokevirtual #59                 // Method FTPNODIB.a:(ZIIIIII)V
     923: return
     924: iload         4
     926: ifne          1389
     929: aload         15
     931: getfield      #62                 // Field YZDBYLRM.T:I
     934: iconst_m1
     935: if_icmpne     970
     938: aload         15
     940: getfield      #122                // Field YZDBYLRM.x:[I
     943: ifnonnull     970
     946: aload         15
     948: iconst_0
     949: iload         9
     951: iload         10
     953: iload         11
     955: iload         12
     957: iload         13
     959: iconst_m1
     960: invokevirtual #94                 // Method YZDBYLRM.a:(IIIIIII)LZKARKDQW;
     963: astore        18
     965: iload         26
     967: ifeq          1000
     970: new           #35                 // class WBWOBAFW
     973: dup
     974: iload         7
     976: iload         9
     978: iconst_0
     979: iload         11
     981: bipush        7
     983: iload         12
     985: iload         10
     987: iload         13
     989: aload         15
     991: getfield      #62                 // Field YZDBYLRM.T:I
     994: iconst_1
     995: invokespecial #54                 // Method WBWOBAFW."<init>":(IIIIBIIIIZ)V
     998: astore        18
    1000: aload_2
    1001: getstatic     #158                // Field D:[I
    1004: iload         9
    1006: iaload
    1007: aload         18
    1009: iconst_1
    1010: iload         16
    1012: iload_1
    1013: iload         17
    1015: iload         6
    1017: aconst_null
    1018: iload         14
    1020: iconst_0
    1021: iload         5
    1023: invokevirtual #140                // Method NYFUGYQS.a:(ILXHHRODPC;ZIIBILXHHRODPC;III)V
    1026: iload         9
    1028: ifne          1100
    1031: aload         15
    1033: getfield      #141                // Field YZDBYLRM.R:Z
    1036: ifeq          1069
    1039: aload_0
    1040: getfield      #142                // Field l:[[[B
    1043: iload         5
    1045: aaload
    1046: iload         6
    1048: aaload
    1049: iload_1
    1050: bipush        50
    1052: bastore
    1053: aload_0
    1054: getfield      #142                // Field l:[[[B
    1057: iload         5
    1059: aaload
    1060: iload         6
    1062: aaload
    1063: iload_1
    1064: iconst_1
    1065: iadd
    1066: bipush        50
    1068: bastore
    1069: aload         15
    1071: getfield      #124                // Field YZDBYLRM.C:Z
    1074: ifeq          1332
    1077: aload_0
    1078: getfield      #118                // Field m:[[[I
    1081: iload         5
    1083: aaload
    1084: iload         6
    1086: aaload
    1087: iload_1
    1088: dup2
    1089: iaload
    1090: sipush        585
    1093: ior
    1094: iastore
    1095: iload         26
    1097: ifeq          1332
    1100: iload         9
    1102: iconst_1
    1103: if_icmpne     1181
    1106: aload         15
    1108: getfield      #141                // Field YZDBYLRM.R:Z
    1111: ifeq          1148
    1114: aload_0
    1115: getfield      #142                // Field l:[[[B
    1118: iload         5
    1120: aaload
    1121: iload         6
    1123: aaload
    1124: iload_1
    1125: iconst_1
    1126: iadd
    1127: bipush        50
    1129: bastore
    1130: aload_0
    1131: getfield      #142                // Field l:[[[B
    1134: iload         5
    1136: aaload
    1137: iload         6
    1139: iconst_1
    1140: iadd
    1141: aaload
    1142: iload_1
    1143: iconst_1
    1144: iadd
    1145: bipush        50
    1147: bastore
    1148: aload         15
    1150: getfield      #124                // Field YZDBYLRM.C:Z
    1153: ifeq          1332
    1156: aload_0
    1157: getfield      #118                // Field m:[[[I
    1160: iload         5
    1162: aaload
    1163: iload         6
    1165: aaload
    1166: iload_1
    1167: iconst_1
    1168: iadd
    1169: dup2
    1170: iaload
    1171: sipush        1170
    1174: ior
    1175: iastore
    1176: iload         26
    1178: ifeq          1332
    1181: iload         9
    1183: iconst_2
    1184: if_icmpne     1262
    1187: aload         15
    1189: getfield      #141                // Field YZDBYLRM.R:Z
    1192: ifeq          1229
    1195: aload_0
    1196: getfield      #142                // Field l:[[[B
    1199: iload         5
    1201: aaload
    1202: iload         6
    1204: iconst_1
    1205: iadd
    1206: aaload
    1207: iload_1
    1208: bipush        50
    1210: bastore
    1211: aload_0
    1212: getfield      #142                // Field l:[[[B
    1215: iload         5
    1217: aaload
    1218: iload         6
    1220: iconst_1
    1221: iadd
    1222: aaload
    1223: iload_1
    1224: iconst_1
    1225: iadd
    1226: bipush        50
    1228: bastore
    1229: aload         15
    1231: getfield      #124                // Field YZDBYLRM.C:Z
    1234: ifeq          1332
    1237: aload_0
    1238: getfield      #118                // Field m:[[[I
    1241: iload         5
    1243: aaload
    1244: iload         6
    1246: iconst_1
    1247: iadd
    1248: aaload
    1249: iload_1
    1250: dup2
    1251: iaload
    1252: sipush        585
    1255: ior
    1256: iastore
    1257: iload         26
    1259: ifeq          1332
    1262: iload         9
    1264: iconst_3
    1265: if_icmpne     1332
    1268: aload         15
    1270: getfield      #141                // Field YZDBYLRM.R:Z
    1273: ifeq          1306
    1276: aload_0
    1277: getfield      #142                // Field l:[[[B
    1280: iload         5
    1282: aaload
    1283: iload         6
    1285: aaload
    1286: iload_1
    1287: bipush        50
    1289: bastore
    1290: aload_0
    1291: getfield      #142                // Field l:[[[B
    1294: iload         5
    1296: aaload
    1297: iload         6
    1299: iconst_1
    1300: iadd
    1301: aaload
    1302: iload_1
    1303: bipush        50
    1305: bastore
    1306: aload         15
    1308: getfield      #124                // Field YZDBYLRM.C:Z
    1311: ifeq          1332
    1314: aload_0
    1315: getfield      #118                // Field m:[[[I
    1318: iload         5
    1320: aaload
    1321: iload         6
    1323: aaload
    1324: iload_1
    1325: dup2
    1326: iaload
    1327: sipush        1170
    1330: ior
    1331: iastore
    1332: aload         15
    1334: getfield      #69                 // Field YZDBYLRM.F:Z
    1337: ifeq          1361
    1340: aload_3
    1341: ifnull        1361
    1344: aload_3
    1345: iload_1
    1346: iload         9
    1348: iload         6
    1350: iload         4
    1352: iconst_1
    1353: aload         15
    1355: getfield      #68                 // Field YZDBYLRM.v:Z
    1358: invokevirtual #61                 // Method FTPNODIB.a:(IIIIBZ)V
    1361: aload         15
    1363: getfield      #156                // Field YZDBYLRM.N:I
    1366: bipush        16
    1368: if_icmpeq     1388
    1371: aload_2
    1372: iload_1
    1373: sipush        441
    1376: aload         15
    1378: getfield      #156                // Field YZDBYLRM.N:I
    1381: iload         6
    1383: iload         5
    1385: invokevirtual #121                // Method NYFUGYQS.a:(IIIII)V
    1388: return
    1389: iload         4
    1391: iconst_1
    1392: if_icmpne     1632
    1395: aload         15
    1397: getfield      #62                 // Field YZDBYLRM.T:I
    1400: iconst_m1
    1401: if_icmpne     1436
    1404: aload         15
    1406: getfield      #122                // Field YZDBYLRM.x:[I
    1409: ifnonnull     1436
    1412: aload         15
    1414: iconst_1
    1415: iload         9
    1417: iload         10
    1419: iload         11
    1421: iload         12
    1423: iload         13
    1425: iconst_m1
    1426: invokevirtual #94                 // Method YZDBYLRM.a:(IIIIIII)LZKARKDQW;
    1429: astore        18
    1431: iload         26
    1433: ifeq          1466
    1436: new           #35                 // class WBWOBAFW
    1439: dup
    1440: iload         7
    1442: iload         9
    1444: iconst_1
    1445: iload         11
    1447: bipush        7
    1449: iload         12
    1451: iload         10
    1453: iload         13
    1455: aload         15
    1457: getfield      #62                 // Field YZDBYLRM.T:I
    1460: iconst_1
    1461: invokespecial #54                 // Method WBWOBAFW."<init>":(IIIIBIIIIZ)V
    1464: astore        18
    1466: aload_2
    1467: getstatic     #159                // Field r:[I
    1470: iload         9
    1472: iaload
    1473: aload         18
    1475: iconst_1
    1476: iload         16
    1478: iload_1
    1479: iload         17
    1481: iload         6
    1483: aconst_null
    1484: iload         14
    1486: iconst_0
    1487: iload         5
    1489: invokevirtual #140                // Method NYFUGYQS.a:(ILXHHRODPC;ZIIBILXHHRODPC;III)V
    1492: aload         15
    1494: getfield      #141                // Field YZDBYLRM.R:Z
    1497: ifeq          1602
    1500: iload         9
    1502: ifne          1526
    1505: aload_0
    1506: getfield      #142                // Field l:[[[B
    1509: iload         5
    1511: aaload
    1512: iload         6
    1514: aaload
    1515: iload_1
    1516: iconst_1
    1517: iadd
    1518: bipush        50
    1520: bastore
    1521: iload         26
    1523: ifeq          1602
    1526: iload         9
    1528: iconst_1
    1529: if_icmpne     1555
    1532: aload_0
    1533: getfield      #142                // Field l:[[[B
    1536: iload         5
    1538: aaload
    1539: iload         6
    1541: iconst_1
    1542: iadd
    1543: aaload
    1544: iload_1
    1545: iconst_1
    1546: iadd
    1547: bipush        50
    1549: bastore
    1550: iload         26
    1552: ifeq          1602
    1555: iload         9
    1557: iconst_2
    1558: if_icmpne     1582
    1561: aload_0
    1562: getfield      #142                // Field l:[[[B
    1565: iload         5
    1567: aaload
    1568: iload         6
    1570: iconst_1
    1571: iadd
    1572: aaload
    1573: iload_1
    1574: bipush        50
    1576: bastore
    1577: iload         26
    1579: ifeq          1602
    1582: iload         9
    1584: iconst_3
    1585: if_icmpne     1602
    1588: aload_0
    1589: getfield      #142                // Field l:[[[B
    1592: iload         5
    1594: aaload
    1595: iload         6
    1597: aaload
    1598: iload_1
    1599: bipush        50
    1601: bastore
    1602: aload         15
    1604: getfield      #69                 // Field YZDBYLRM.F:Z
    1607: ifeq          1631
    1610: aload_3
    1611: ifnull        1631
    1614: aload_3
    1615: iload_1
    1616: iload         9
    1618: iload         6
    1620: iload         4
    1622: iconst_1
    1623: aload         15
    1625: getfield      #68                 // Field YZDBYLRM.v:Z
    1628: invokevirtual #61                 // Method FTPNODIB.a:(IIIIBZ)V
    1631: return
    1632: iload         4
    1634: iconst_2
    1635: if_icmpne     2057
    1638: iload         9
    1640: iconst_1
    1641: iadd
    1642: iconst_3
    1643: iand
    1644: istore        18
    1646: aload         15
    1648: getfield      #62                 // Field YZDBYLRM.T:I
    1651: iconst_m1
    1652: if_icmpne     1708
    1655: aload         15
    1657: getfield      #122                // Field YZDBYLRM.x:[I
    1660: ifnonnull     1708
    1663: aload         15
    1665: iconst_2
    1666: iconst_4
    1667: iload         9
    1669: iadd
    1670: iload         10
    1672: iload         11
    1674: iload         12
    1676: iload         13
    1678: iconst_m1
    1679: invokevirtual #94                 // Method YZDBYLRM.a:(IIIIIII)LZKARKDQW;
    1682: astore        19
    1684: aload         15
    1686: iconst_2
    1687: iload         18
    1689: iload         10
    1691: iload         11
    1693: iload         12
    1695: iload         13
    1697: iconst_m1
    1698: invokevirtual #94                 // Method YZDBYLRM.a:(IIIIIII)LZKARKDQW;
    1701: astore        20
    1703: iload         26
    1705: ifeq          1770
    1708: new           #35                 // class WBWOBAFW
    1711: dup
    1712: iload         7
    1714: iconst_4
    1715: iload         9
    1717: iadd
    1718: iconst_2
    1719: iload         11
    1721: bipush        7
    1723: iload         12
    1725: iload         10
    1727: iload         13
    1729: aload         15
    1731: getfield      #62                 // Field YZDBYLRM.T:I
    1734: iconst_1
    1735: invokespecial #54                 // Method WBWOBAFW."<init>":(IIIIBIIIIZ)V
    1738: astore        19
    1740: new           #35                 // class WBWOBAFW
    1743: dup
    1744: iload         7
    1746: iload         18
    1748: iconst_2
    1749: iload         11
    1751: bipush        7
    1753: iload         12
    1755: iload         10
    1757: iload         13
    1759: aload         15
    1761: getfield      #62                 // Field YZDBYLRM.T:I
    1764: iconst_1
    1765: invokespecial #54                 // Method WBWOBAFW."<init>":(IIIIBIIIIZ)V
    1768: astore        20
    1770: aload_2
    1771: getstatic     #158                // Field D:[I
    1774: iload         9
    1776: iaload
    1777: aload         19
    1779: iconst_1
    1780: iload         16
    1782: iload_1
    1783: iload         17
    1785: iload         6
    1787: aload         20
    1789: iload         14
    1791: getstatic     #158                // Field D:[I
    1794: iload         18
    1796: iaload
    1797: iload         5
    1799: invokevirtual #140                // Method NYFUGYQS.a:(ILXHHRODPC;ZIIBILXHHRODPC;III)V
    1802: aload         15
    1804: getfield      #124                // Field YZDBYLRM.C:Z
    1807: ifeq          2000
    1810: iload         9
    1812: ifne          1858
    1815: aload_0
    1816: getfield      #118                // Field m:[[[I
    1819: iload         5
    1821: aaload
    1822: iload         6
    1824: aaload
    1825: iload_1
    1826: dup2
    1827: iaload
    1828: sipush        585
    1831: ior
    1832: iastore
    1833: aload_0
    1834: getfield      #118                // Field m:[[[I
    1837: iload         5
    1839: aaload
    1840: iload         6
    1842: aaload
    1843: iload_1
    1844: iconst_1
    1845: iadd
    1846: dup2
    1847: iaload
    1848: sipush        1170
    1851: ior
    1852: iastore
    1853: iload         26
    1855: ifeq          2000
    1858: iload         9
    1860: iconst_1
    1861: if_icmpne     1909
    1864: aload_0
    1865: getfield      #118                // Field m:[[[I
    1868: iload         5
    1870: aaload
    1871: iload         6
    1873: aaload
    1874: iload_1
    1875: iconst_1
    1876: iadd
    1877: dup2
    1878: iaload
    1879: sipush        1170
    1882: ior
    1883: iastore
    1884: aload_0
    1885: getfield      #118                // Field m:[[[I
    1888: iload         5
    1890: aaload
    1891: iload         6
    1893: iconst_1
    1894: iadd
    1895: aaload
    1896: iload_1
    1897: dup2
    1898: iaload
    1899: sipush        585
    1902: ior
    1903: iastore
    1904: iload         26
    1906: ifeq          2000
    1909: iload         9
    1911: iconst_2
    1912: if_icmpne     1958
    1915: aload_0
    1916: getfield      #118                // Field m:[[[I
    1919: iload         5
    1921: aaload
    1922: iload         6
    1924: iconst_1
    1925: iadd
    1926: aaload
    1927: iload_1
    1928: dup2
    1929: iaload
    1930: sipush        585
    1933: ior
    1934: iastore
    1935: aload_0
    1936: getfield      #118                // Field m:[[[I
    1939: iload         5
    1941: aaload
    1942: iload         6
    1944: aaload
    1945: iload_1
    1946: dup2
    1947: iaload
    1948: sipush        1170
    1951: ior
    1952: iastore
    1953: iload         26
    1955: ifeq          2000
    1958: iload         9
    1960: iconst_3
    1961: if_icmpne     2000
    1964: aload_0
    1965: getfield      #118                // Field m:[[[I
    1968: iload         5
    1970: aaload
    1971: iload         6
    1973: aaload
    1974: iload_1
    1975: dup2
    1976: iaload
    1977: sipush        1170
    1980: ior
    1981: iastore
    1982: aload_0
    1983: getfield      #118                // Field m:[[[I
    1986: iload         5
    1988: aaload
    1989: iload         6
    1991: aaload
    1992: iload_1
    1993: dup2
    1994: iaload
    1995: sipush        585
    1998: ior
    1999: iastore
    2000: aload         15
    2002: getfield      #69                 // Field YZDBYLRM.F:Z
    2005: ifeq          2029
    2008: aload_3
    2009: ifnull        2029
    2012: aload_3
    2013: iload_1
    2014: iload         9
    2016: iload         6
    2018: iload         4
    2020: iconst_1
    2021: aload         15
    2023: getfield      #68                 // Field YZDBYLRM.v:Z
    2026: invokevirtual #61                 // Method FTPNODIB.a:(IIIIBZ)V
    2029: aload         15
    2031: getfield      #156                // Field YZDBYLRM.N:I
    2034: bipush        16
    2036: if_icmpeq     2056
    2039: aload_2
    2040: iload_1
    2041: sipush        441
    2044: aload         15
    2046: getfield      #156                // Field YZDBYLRM.N:I
    2049: iload         6
    2051: iload         5
    2053: invokevirtual #121                // Method NYFUGYQS.a:(IIIII)V
    2056: return
    2057: iload         4
    2059: iconst_3
    2060: if_icmpne     2300
    2063: aload         15
    2065: getfield      #62                 // Field YZDBYLRM.T:I
    2068: iconst_m1
    2069: if_icmpne     2104
    2072: aload         15
    2074: getfield      #122                // Field YZDBYLRM.x:[I
    2077: ifnonnull     2104
    2080: aload         15
    2082: iconst_3
    2083: iload         9
    2085: iload         10
    2087: iload         11
    2089: iload         12
    2091: iload         13
    2093: iconst_m1
    2094: invokevirtual #94                 // Method YZDBYLRM.a:(IIIIIII)LZKARKDQW;
    2097: astore        18
    2099: iload         26
    2101: ifeq          2134
    2104: new           #35                 // class WBWOBAFW
    2107: dup
    2108: iload         7
    2110: iload         9
    2112: iconst_3
    2113: iload         11
    2115: bipush        7
    2117: iload         12
    2119: iload         10
    2121: iload         13
    2123: aload         15
    2125: getfield      #62                 // Field YZDBYLRM.T:I
    2128: iconst_1
    2129: invokespecial #54                 // Method WBWOBAFW."<init>":(IIIIBIIIIZ)V
    2132: astore        18
    2134: aload_2
    2135: getstatic     #159                // Field r:[I
    2138: iload         9
    2140: iaload
    2141: aload         18
    2143: iconst_1
    2144: iload         16
    2146: iload_1
    2147: iload         17
    2149: iload         6
    2151: aconst_null
    2152: iload         14
    2154: iconst_0
    2155: iload         5
    2157: invokevirtual #140                // Method NYFUGYQS.a:(ILXHHRODPC;ZIIBILXHHRODPC;III)V
    2160: aload         15
    2162: getfield      #141                // Field YZDBYLRM.R:Z
    2165: ifeq          2270
    2168: iload         9
    2170: ifne          2194
    2173: aload_0
    2174: getfield      #142                // Field l:[[[B
    2177: iload         5
    2179: aaload
    2180: iload         6
    2182: aaload
    2183: iload_1
    2184: iconst_1
    2185: iadd
    2186: bipush        50
    2188: bastore
    2189: iload         26
    2191: ifeq          2270
    2194: iload         9
    2196: iconst_1
    2197: if_icmpne     2223
    2200: aload_0
    2201: getfield      #142                // Field l:[[[B
    2204: iload         5
    2206: aaload
    2207: iload         6
    2209: iconst_1
    2210: iadd
    2211: aaload
    2212: iload_1
    2213: iconst_1
    2214: iadd
    2215: bipush        50
    2217: bastore
    2218: iload         26
    2220: ifeq          2270
    2223: iload         9
    2225: iconst_2
    2226: if_icmpne     2250
    2229: aload_0
    2230: getfield      #142                // Field l:[[[B
    2233: iload         5
    2235: aaload
    2236: iload         6
    2238: iconst_1
    2239: iadd
    2240: aaload
    2241: iload_1
    2242: bipush        50
    2244: bastore
    2245: iload         26
    2247: ifeq          2270
    2250: iload         9
    2252: iconst_3
    2253: if_icmpne     2270
    2256: aload_0
    2257: getfield      #142                // Field l:[[[B
    2260: iload         5
    2262: aaload
    2263: iload         6
    2265: aaload
    2266: iload_1
    2267: bipush        50
    2269: bastore
    2270: aload         15
    2272: getfield      #69                 // Field YZDBYLRM.F:Z
    2275: ifeq          2299
    2278: aload_3
    2279: ifnull        2299
    2282: aload_3
    2283: iload_1
    2284: iload         9
    2286: iload         6
    2288: iload         4
    2290: iconst_1
    2291: aload         15
    2293: getfield      #68                 // Field YZDBYLRM.v:Z
    2296: invokevirtual #61                 // Method FTPNODIB.a:(IIIIBZ)V
    2299: return
    2300: iload         4
    2302: bipush        9
    2304: if_icmpne     2443
    2307: aload         15
    2309: getfield      #62                 // Field YZDBYLRM.T:I
    2312: iconst_m1
    2313: if_icmpne     2349
    2316: aload         15
    2318: getfield      #122                // Field YZDBYLRM.x:[I
    2321: ifnonnull     2349
    2324: aload         15
    2326: iload         4
    2328: iload         9
    2330: iload         10
    2332: iload         11
    2334: iload         12
    2336: iload         13
    2338: iconst_m1
    2339: invokevirtual #94                 // Method YZDBYLRM.a:(IIIIIII)LZKARKDQW;
    2342: astore        18
    2344: iload         26
    2346: ifeq          2380
    2349: new           #35                 // class WBWOBAFW
    2352: dup
    2353: iload         7
    2355: iload         9
    2357: iload         4
    2359: iload         11
    2361: bipush        7
    2363: iload         12
    2365: iload         10
    2367: iload         13
    2369: aload         15
    2371: getfield      #62                 // Field YZDBYLRM.T:I
    2374: iconst_1
    2375: invokespecial #54                 // Method WBWOBAFW."<init>":(IIIIBIIIIZ)V
    2378: astore        18
    2380: aload_2
    2381: iload         16
    2383: iload         17
    2385: iload         14
    2387: iconst_1
    2388: aload         18
    2390: iconst_1
    2391: iload         5
    2393: iconst_0
    2394: bipush        110
    2396: iload_1
    2397: iload         6
    2399: invokevirtual #60                 // Method NYFUGYQS.a:(IBIILXHHRODPC;IIIBII)Z
    2402: pop
    2403: aload         15
    2405: getfield      #69                 // Field YZDBYLRM.F:Z
    2408: ifeq          2442
    2411: aload_3
    2412: ifnull        2442
    2415: aload_3
    2416: aload         15
    2418: getfield      #68                 // Field YZDBYLRM.v:Z
    2421: getstatic     #75                 // Field p:I
    2424: aload         15
    2426: getfield      #157                // Field YZDBYLRM.i:I
    2429: aload         15
    2431: getfield      #109                // Field YZDBYLRM.z:I
    2434: iload         6
    2436: iload_1
    2437: iload         9
    2439: invokevirtual #59                 // Method FTPNODIB.a:(ZIIIIII)V
    2442: return
    2443: aload         15
    2445: getfield      #103                // Field YZDBYLRM.A:Z
    2448: ifeq          2543
    2451: iload         9
    2453: iconst_1
    2454: if_icmpne     2482
    2457: iload         13
    2459: istore        18
    2461: iload         12
    2463: istore        13
    2465: iload         11
    2467: istore        12
    2469: iload         10
    2471: istore        11
    2473: iload         18
    2475: istore        10
    2477: iload         26
    2479: ifeq          2543
    2482: iload         9
    2484: iconst_2
    2485: if_icmpne     2517
    2488: iload         13
    2490: istore        18
    2492: iload         11
    2494: istore        13
    2496: iload         18
    2498: istore        11
    2500: iload         12
    2502: istore        18
    2504: iload         10
    2506: istore        12
    2508: iload         18
    2510: istore        10
    2512: iload         26
    2514: ifeq          2543
    2517: iload         9
    2519: iconst_3
    2520: if_icmpne     2543
    2523: iload         13
    2525: istore        18
    2527: iload         10
    2529: istore        13
    2531: iload         11
    2533: istore        10
    2535: iload         12
    2537: istore        11
    2539: iload         18
    2541: istore        12
    2543: iload         4
    2545: iconst_4
    2546: if_icmpne     2653
    2549: aload         15
    2551: getfield      #62                 // Field YZDBYLRM.T:I
    2554: iconst_m1
    2555: if_icmpne     2589
    2558: aload         15
    2560: getfield      #122                // Field YZDBYLRM.x:[I
    2563: ifnonnull     2589
    2566: aload         15
    2568: iconst_4
    2569: iconst_0
    2570: iload         10
    2572: iload         11
    2574: iload         12
    2576: iload         13
    2578: iconst_m1
    2579: invokevirtual #94                 // Method YZDBYLRM.a:(IIIIIII)LZKARKDQW;
    2582: astore        18
    2584: iload         26
    2586: ifeq          2618
    2589: new           #35                 // class WBWOBAFW
    2592: dup
    2593: iload         7
    2595: iconst_0
    2596: iconst_4
    2597: iload         11
    2599: bipush        7
    2601: iload         12
    2603: iload         10
    2605: iload         13
    2607: aload         15
    2609: getfield      #62                 // Field YZDBYLRM.T:I
    2612: iconst_1
    2613: invokespecial #54                 // Method WBWOBAFW."<init>":(IIIIBIIIIZ)V
    2616: astore        18
    2618: aload_2
    2619: iload         16
    2621: iload_1
    2622: iload         9
    2624: sipush        512
    2627: imul
    2628: sipush        -460
    2631: iload         5
    2633: iconst_0
    2634: iload         14
    2636: aload         18
    2638: iload         6
    2640: iload         17
    2642: iconst_0
    2643: getstatic     #158                // Field D:[I
    2646: iload         9
    2648: iaload
    2649: invokevirtual #135                // Method NYFUGYQS.a:(IIIIIIILXHHRODPC;IBII)V
    2652: return
    2653: iload         4
    2655: iconst_5
    2656: if_icmpne     2816
    2659: bipush        16
    2661: istore        18
    2663: aload_2
    2664: iload         5
    2666: iload         6
    2668: iload_1
    2669: invokevirtual #155                // Method NYFUGYQS.c:(III)I
    2672: istore        19
    2674: iload         19
    2676: ifle          2696
    2679: iload         19
    2681: bipush        14
    2683: ishr
    2684: sipush        32767
    2687: iand
    2688: invokestatic  #113                // Method YZDBYLRM.a:(I)LYZDBYLRM;
    2691: getfield      #156                // Field YZDBYLRM.N:I
    2694: istore        18
    2696: aload         15
    2698: getfield      #62                 // Field YZDBYLRM.T:I
    2701: iconst_m1
    2702: if_icmpne     2736
    2705: aload         15
    2707: getfield      #122                // Field YZDBYLRM.x:[I
    2710: ifnonnull     2736
    2713: aload         15
    2715: iconst_4
    2716: iconst_0
    2717: iload         10
    2719: iload         11
    2721: iload         12
    2723: iload         13
    2725: iconst_m1
    2726: invokevirtual #94                 // Method YZDBYLRM.a:(IIIIIII)LZKARKDQW;
    2729: astore        20
    2731: iload         26
    2733: ifeq          2765
    2736: new           #35                 // class WBWOBAFW
    2739: dup
    2740: iload         7
    2742: iconst_0
    2743: iconst_4
    2744: iload         11
    2746: bipush        7
    2748: iload         12
    2750: iload         10
    2752: iload         13
    2754: aload         15
    2756: getfield      #62                 // Field YZDBYLRM.T:I
    2759: iconst_1
    2760: invokespecial #54                 // Method WBWOBAFW."<init>":(IIIIBIIIIZ)V
    2763: astore        20
    2765: aload_2
    2766: iload         16
    2768: iload_1
    2769: iload         9
    2771: sipush        512
    2774: imul
    2775: sipush        -460
    2778: iload         5
    2780: getstatic     #81                 // Field o:[I
    2783: iload         9
    2785: iaload
    2786: iload         18
    2788: imul
    2789: iload         14
    2791: aload         20
    2793: iload         6
    2795: iload         17
    2797: getstatic     #82                 // Field v:[I
    2800: iload         9
    2802: iaload
    2803: iload         18
    2805: imul
    2806: getstatic     #158                // Field D:[I
    2809: iload         9
    2811: iaload
    2812: invokevirtual #135                // Method NYFUGYQS.a:(IIIIIIILXHHRODPC;IBII)V
    2815: return
    2816: iload         4
    2818: bipush        6
    2820: if_icmpne     2920
    2823: aload         15
    2825: getfield      #62                 // Field YZDBYLRM.T:I
    2828: iconst_m1
    2829: if_icmpne     2863
    2832: aload         15
    2834: getfield      #122                // Field YZDBYLRM.x:[I
    2837: ifnonnull     2863
    2840: aload         15
    2842: iconst_4
    2843: iconst_0
    2844: iload         10
    2846: iload         11
    2848: iload         12
    2850: iload         13
    2852: iconst_m1
    2853: invokevirtual #94                 // Method YZDBYLRM.a:(IIIIIII)LZKARKDQW;
    2856: astore        18
    2858: iload         26
    2860: ifeq          2892
    2863: new           #35                 // class WBWOBAFW
    2866: dup
    2867: iload         7
    2869: iconst_0
    2870: iconst_4
    2871: iload         11
    2873: bipush        7
    2875: iload         12
    2877: iload         10
    2879: iload         13
    2881: aload         15
    2883: getfield      #62                 // Field YZDBYLRM.T:I
    2886: iconst_1
    2887: invokespecial #54                 // Method WBWOBAFW."<init>":(IIIIBIIIIZ)V
    2890: astore        18
    2892: aload_2
    2893: iload         16
    2895: iload_1
    2896: iload         9
    2898: sipush        -460
    2901: iload         5
    2903: iconst_0
    2904: iload         14
    2906: aload         18
    2908: iload         6
    2910: iload         17
    2912: iconst_0
    2913: sipush        256
    2916: invokevirtual #135                // Method NYFUGYQS.a:(IIIIIIILXHHRODPC;IBII)V
    2919: return
    2920: iload         4
    2922: bipush        7
    2924: if_icmpne     3024
    2927: aload         15
    2929: getfield      #62                 // Field YZDBYLRM.T:I
    2932: iconst_m1
    2933: if_icmpne     2967
    2936: aload         15
    2938: getfield      #122                // Field YZDBYLRM.x:[I
    2941: ifnonnull     2967
    2944: aload         15
    2946: iconst_4
    2947: iconst_0
    2948: iload         10
    2950: iload         11
    2952: iload         12
    2954: iload         13
    2956: iconst_m1
    2957: invokevirtual #94                 // Method YZDBYLRM.a:(IIIIIII)LZKARKDQW;
    2960: astore        18
    2962: iload         26
    2964: ifeq          2996
    2967: new           #35                 // class WBWOBAFW
    2970: dup
    2971: iload         7
    2973: iconst_0
    2974: iconst_4
    2975: iload         11
    2977: bipush        7
    2979: iload         12
    2981: iload         10
    2983: iload         13
    2985: aload         15
    2987: getfield      #62                 // Field YZDBYLRM.T:I
    2990: iconst_1
    2991: invokespecial #54                 // Method WBWOBAFW."<init>":(IIIIBIIIIZ)V
    2994: astore        18
    2996: aload_2
    2997: iload         16
    2999: iload_1
    3000: iload         9
    3002: sipush        -460
    3005: iload         5
    3007: iconst_0
    3008: iload         14
    3010: aload         18
    3012: iload         6
    3014: iload         17
    3016: iconst_0
    3017: sipush        512
    3020: invokevirtual #135                // Method NYFUGYQS.a:(IIIIIIILXHHRODPC;IBII)V
    3023: return
    3024: iload         4
    3026: bipush        8
    3028: if_icmpne     3248
    3031: aload         15
    3033: getfield      #62                 // Field YZDBYLRM.T:I
    3036: iconst_m1
    3037: if_icmpne     3071
    3040: aload         15
    3042: getfield      #122                // Field YZDBYLRM.x:[I
    3045: ifnonnull     3071
    3048: aload         15
    3050: iconst_4
    3051: iconst_0
    3052: iload         10
    3054: iload         11
    3056: iload         12
    3058: iload         13
    3060: iconst_m1
    3061: invokevirtual #94                 // Method YZDBYLRM.a:(IIIIIII)LZKARKDQW;
    3064: astore        18
    3066: iload         26
    3068: ifeq          3100
    3071: new           #35                 // class WBWOBAFW
    3074: dup
    3075: iload         7
    3077: iconst_0
    3078: iconst_4
    3079: iload         11
    3081: bipush        7
    3083: iload         12
    3085: iload         10
    3087: iload         13
    3089: aload         15
    3091: getfield      #62                 // Field YZDBYLRM.T:I
    3094: iconst_1
    3095: invokespecial #54                 // Method WBWOBAFW."<init>":(IIIIBIIIIZ)V
    3098: astore        18
    3100: aload_2
    3101: iload         16
    3103: iload_1
    3104: iload         9
    3106: sipush        -460
    3109: iload         5
    3111: iconst_0
    3112: iload         14
    3114: aload         18
    3116: iload         6
    3118: iload         17
    3120: iconst_0
    3121: sipush        768
    3124: invokevirtual #135                // Method NYFUGYQS.a:(IIIIIIILXHHRODPC;IBII)V
    3127: return
    3128: astore        10
    3130: new           #44                 // class java/lang/StringBuffer
    3133: dup
    3134: ldc           #19                 // String 16863,
    3136: invokespecial #55                 // Method java/lang/StringBuffer."<init>":(Ljava/lang/String;)V
    3139: iload_1
    3140: invokevirtual #63                 // Method java/lang/StringBuffer.append:(I)Ljava/lang/StringBuffer;
    3143: ldc           #16                 // String ,
    3145: invokevirtual #65                 // Method java/lang/StringBuffer.append:(Ljava/lang/String;)Ljava/lang/StringBuffer;
    3148: aload_2
    3149: invokevirtual #64                 // Method java/lang/StringBuffer.append:(Ljava/lang/Object;)Ljava/lang/StringBuffer;
    3152: ldc           #16                 // String ,
    3154: invokevirtual #65                 // Method java/lang/StringBuffer.append:(Ljava/lang/String;)Ljava/lang/StringBuffer;
    3157: aload_3
    3158: invokevirtual #64                 // Method java/lang/StringBuffer.append:(Ljava/lang/Object;)Ljava/lang/StringBuffer;
    3161: ldc           #16                 // String ,
    3163: invokevirtual #65                 // Method java/lang/StringBuffer.append:(Ljava/lang/String;)Ljava/lang/StringBuffer;
    3166: iload         4
    3168: invokevirtual #63                 // Method java/lang/StringBuffer.append:(I)Ljava/lang/StringBuffer;
    3171: ldc           #16                 // String ,
    3173: invokevirtual #65                 // Method java/lang/StringBuffer.append:(Ljava/lang/String;)Ljava/lang/StringBuffer;
    3176: iload         5
    3178: invokevirtual #63                 // Method java/lang/StringBuffer.append:(I)Ljava/lang/StringBuffer;
    3181: ldc           #16                 // String ,
    3183: invokevirtual #65                 // Method java/lang/StringBuffer.append:(Ljava/lang/String;)Ljava/lang/StringBuffer;
    3186: iload         6
    3188: invokevirtual #63                 // Method java/lang/StringBuffer.append:(I)Ljava/lang/StringBuffer;
    3191: ldc           #16                 // String ,
    3193: invokevirtual #65                 // Method java/lang/StringBuffer.append:(Ljava/lang/String;)Ljava/lang/StringBuffer;
    3196: iload         7
    3198: invokevirtual #63                 // Method java/lang/StringBuffer.append:(I)Ljava/lang/StringBuffer;
    3201: ldc           #16                 // String ,
    3203: invokevirtual #65                 // Method java/lang/StringBuffer.append:(Ljava/lang/String;)Ljava/lang/StringBuffer;
    3206: iload         8
    3208: invokevirtual #66                 // Method java/lang/StringBuffer.append:(Z)Ljava/lang/StringBuffer;
    3211: ldc           #16                 // String ,
    3213: invokevirtual #65                 // Method java/lang/StringBuffer.append:(Ljava/lang/String;)Ljava/lang/StringBuffer;
    3216: iload         9
    3218: invokevirtual #63                 // Method java/lang/StringBuffer.append:(I)Ljava/lang/StringBuffer;
    3221: ldc           #16                 // String ,
    3223: invokevirtual #65                 // Method java/lang/StringBuffer.append:(Ljava/lang/String;)Ljava/lang/StringBuffer;
    3226: aload         10
    3228: invokevirtual #149                // Method java/lang/Throwable.toString:()Ljava/lang/String;
    3231: invokevirtual #65                 // Method java/lang/StringBuffer.append:(Ljava/lang/String;)Ljava/lang/StringBuffer;
    3234: invokevirtual #148                // Method java/lang/StringBuffer.toString:()Ljava/lang/String;
    3237: invokestatic  #132                // Method sign/signlink.reporterror:(Ljava/lang/String;)V
    3240: new           #43                 // class java/lang/RuntimeException
    3243: dup
    3244: invokespecial #53                 // Method java/lang/RuntimeException."<init>":()V
    3247: athrow
    3248: return
    Exception table:
       from    to  target type
           5  3128  3128   Class java/lang/RuntimeException

  private static final int a(int, int, int);
    Code:
       0: iload_0
       1: iload_2
       2: idiv
       3: istore_3
       4: iload_0
       5: iload_2
       6: iconst_1
       7: isub
       8: iand
       9: istore        4
      11: iload_1
      12: iload_2
      13: idiv
      14: istore        5
      16: iload_1
      17: iload_2
      18: iconst_1
      19: isub
      20: iand
      21: istore        6
      23: iload_3
      24: iload         5
      26: invokestatic  #144                // Method d:(II)I
      29: istore        7
      31: iload_3
      32: iconst_1
      33: iadd
      34: iload         5
      36: invokestatic  #144                // Method d:(II)I
      39: istore        8
      41: iload_3
      42: iload         5
      44: iconst_1
      45: iadd
      46: invokestatic  #144                // Method d:(II)I
      49: istore        9
      51: iload_3
      52: iconst_1
      53: iadd
      54: iload         5
      56: iconst_1
      57: iadd
      58: invokestatic  #144                // Method d:(II)I
      61: istore        10
      63: iload         7
      65: iload         8
      67: iload         4
      69: iload_2
      70: invokestatic  #106                // Method b:(IIII)I
      73: istore        11
      75: iload         9
      77: iload         10
      79: iload         4
      81: iload_2
      82: invokestatic  #106                // Method b:(IIII)I
      85: istore        12
      87: iload         11
      89: iload         12
      91: iload         6
      93: iload_2
      94: invokestatic  #106                // Method b:(IIII)I
      97: ireturn

  private final int b(int, int, int);
    Code:
       0: iload_3
       1: sipush        179
       4: if_icmple     11
       7: iload_2
       8: iconst_2
       9: idiv
      10: istore_2
      11: iload_3
      12: sipush        192
      15: if_icmple     22
      18: iload_2
      19: iconst_2
      20: idiv
      21: istore_2
      22: iload_3
      23: sipush        217
      26: if_icmple     33
      29: iload_2
      30: iconst_2
      31: idiv
      32: istore_2
      33: iload_3
      34: sipush        243
      37: if_icmple     44
      40: iload_2
      41: iconst_2
      42: idiv
      43: istore_2
      44: iload_1
      45: iconst_4
      46: idiv
      47: bipush        10
      49: ishl
      50: iload_2
      51: bipush        32
      53: idiv
      54: bipush        7
      56: ishl
      57: iadd
      58: iload_3
      59: iconst_2
      60: idiv
      61: iadd
      62: istore        4
      64: iload         4
      66: ireturn

  public static final boolean c(int, int, int);
    Code:
       0: iload_0
       1: invokestatic  #113                // Method YZDBYLRM.a:(I)LYZDBYLRM;
       4: astore_3
       5: iload_2
       6: bipush        8
       8: if_icmpeq     28
      11: iconst_1
      12: istore        4
      14: getstatic     #414                // Field client.Jj:I
      17: ifeq          23
      20: iinc          4, 1
      23: iload         4
      25: ifgt          20
      28: iload_1
      29: bipush        11
      31: if_icmpne     37
      34: bipush        10
      36: istore_1
      37: iload_1
      38: iconst_5
      39: if_icmplt     50
      42: iload_1
      43: bipush        8
      45: if_icmpgt     50
      48: iconst_4
      49: istore_1
      50: aload_3
      51: iload_1
      52: iconst_1
      53: invokevirtual #73                 // Method YZDBYLRM.a:(IZ)Z
      56: ireturn
      57: astore_3
      58: new           #44                 // class java/lang/StringBuffer
      61: dup
      62: ldc           #25                 // String 51637,
      64: invokespecial #55                 // Method java/lang/StringBuffer."<init>":(Ljava/lang/String;)V
      67: iload_0
      68: invokevirtual #63                 // Method java/lang/StringBuffer.append:(I)Ljava/lang/StringBuffer;
      71: ldc           #16                 // String ,
      73: invokevirtual #65                 // Method java/lang/StringBuffer.append:(Ljava/lang/String;)Ljava/lang/StringBuffer;
      76: iload_1
      77: invokevirtual #63                 // Method java/lang/StringBuffer.append:(I)Ljava/lang/StringBuffer;
      80: ldc           #16                 // String ,
      82: invokevirtual #65                 // Method java/lang/StringBuffer.append:(Ljava/lang/String;)Ljava/lang/StringBuffer;
      85: iload_2
      86: invokevirtual #63                 // Method java/lang/StringBuffer.append:(I)Ljava/lang/StringBuffer;
      89: ldc           #16                 // String ,
      91: invokevirtual #65                 // Method java/lang/StringBuffer.append:(Ljava/lang/String;)Ljava/lang/StringBuffer;
      94: aload_3
      95: invokevirtual #149                // Method java/lang/Throwable.toString:()Ljava/lang/String;
      98: invokevirtual #65                 // Method java/lang/StringBuffer.append:(Ljava/lang/String;)Ljava/lang/StringBuffer;
     101: invokevirtual #148                // Method java/lang/StringBuffer.toString:()Ljava/lang/String;
     104: invokestatic  #132                // Method sign/signlink.reporterror:(Ljava/lang/String;)V
     107: new           #43                 // class java/lang/RuntimeException
     110: dup
     111: invokespecial #53                 // Method java/lang/RuntimeException."<init>":()V
     114: athrow
    Exception table:
       from    to  target type
           0    57    57   Class java/lang/RuntimeException

  public final void a(int, int, FTPNODIB[], int, int, int, byte[], int, int, int);
    Code:
       0: getstatic     #414                // Field client.Jj:I
       3: istore        16
       5: iconst_0
       6: istore        11
       8: iload         16
      10: ifeq          94
      13: iconst_0
      14: istore        12
      16: iload         16
      18: ifeq          84
      21: iload         5
      23: iload         11
      25: iadd
      26: ifle          81
      29: iload         5
      31: iload         11
      33: iadd
      34: bipush        103
      36: if_icmpge     81
      39: iload         10
      41: iload         12
      43: iadd
      44: ifle          81
      47: iload         10
      49: iload         12
      51: iadd
      52: bipush        103
      54: if_icmpge     81
      57: aload_3
      58: iload         9
      60: aaload
      61: getfield      #76                 // Field FTPNODIB.m:[[I
      64: iload         5
      66: iload         11
      68: iadd
      69: aaload
      70: iload         10
      72: iload         12
      74: iadd
      75: dup2
      76: iaload
      77: ldc           #11                 // int -16777217
      79: iand
      80: iastore
      81: iinc          12, 1
      84: iload         12
      86: bipush        8
      88: if_icmplt     21
      91: iinc          11, 1
      94: iload         11
      96: bipush        8
      98: if_icmplt     13
     101: iload         4
     103: bipush        9
     105: if_icmplt     115
     108: iload         4
     110: bipush        9
     112: if_icmple     131
     115: iconst_1
     116: istore        12
     118: iload         16
     120: ifeq          126
     123: iinc          12, 1
     126: iload         12
     128: ifgt          123
     131: new           #39                 // class MBMGIXGO
     134: dup
     135: aload         7
     137: sipush        891
     140: invokespecial #56                 // Method MBMGIXGO."<init>":([BI)V
     143: astore        12
     145: iconst_0
     146: istore        13
     148: iload         16
     150: ifeq          304
     153: iconst_0
     154: istore        14
     156: iload         16
     158: ifeq          294
     161: iconst_0
     162: istore        15
     164: iload         16
     166: ifeq          284
     169: iload         13
     171: iload_1
     172: if_icmpne     266
     175: iload         14
     177: iload         6
     179: if_icmplt     266
     182: iload         14
     184: iload         6
     186: bipush        8
     188: iadd
     189: if_icmpge     266
     192: iload         15
     194: iload         8
     196: if_icmplt     266
     199: iload         15
     201: iload         8
     203: bipush        8
     205: iadd
     206: if_icmpge     266
     209: aload_0
     210: iload         10
     212: iload         15
     214: bipush        7
     216: iand
     217: iload_2
     218: sipush        -383
     221: iload         14
     223: bipush        7
     225: iand
     226: invokestatic  #85                 // Method CDEJWOSB.a:(IIII)I
     229: iadd
     230: iconst_0
     231: aload         12
     233: iload         5
     235: iload_2
     236: iload         15
     238: bipush        7
     240: iand
     241: iload         14
     243: bipush        7
     245: iand
     246: iconst_0
     247: invokestatic  #84                 // Method CDEJWOSB.a:(IIIZ)I
     250: iadd
     251: iload         9
     253: iload_2
     254: sipush        942
     257: iconst_0
     258: invokespecial #115                // Method a:(IILMBMGIXGO;IIIII)V
     261: iload         16
     263: ifeq          281
     266: aload_0
     267: iconst_m1
     268: iconst_0
     269: aload         12
     271: iconst_m1
     272: iconst_0
     273: iconst_0
     274: sipush        942
     277: iconst_0
     278: invokespecial #115                // Method a:(IILMBMGIXGO;IIIII)V
     281: iinc          15, 1
     284: iload         15
     286: bipush        64
     288: if_icmplt     169
     291: iinc          14, 1
     294: iload         14
     296: bipush        64
     298: if_icmplt     161
     301: iinc          13, 1
     304: iload         13
     306: iconst_4
     307: if_icmplt     153
     310: return
     311: astore        11
     313: new           #44                 // class java/lang/StringBuffer
     316: dup
     317: ldc           #21                 // String 28153,
     319: invokespecial #55                 // Method java/lang/StringBuffer."<init>":(Ljava/lang/String;)V
     322: iload_1
     323: invokevirtual #63                 // Method java/lang/StringBuffer.append:(I)Ljava/lang/StringBuffer;
     326: ldc           #16                 // String ,
     328: invokevirtual #65                 // Method java/lang/StringBuffer.append:(Ljava/lang/String;)Ljava/lang/StringBuffer;
     331: iload_2
     332: invokevirtual #63                 // Method java/lang/StringBuffer.append:(I)Ljava/lang/StringBuffer;
     335: ldc           #16                 // String ,
     337: invokevirtual #65                 // Method java/lang/StringBuffer.append:(Ljava/lang/String;)Ljava/lang/StringBuffer;
     340: aload_3
     341: invokevirtual #64                 // Method java/lang/StringBuffer.append:(Ljava/lang/Object;)Ljava/lang/StringBuffer;
     344: ldc           #16                 // String ,
     346: invokevirtual #65                 // Method java/lang/StringBuffer.append:(Ljava/lang/String;)Ljava/lang/StringBuffer;
     349: iload         4
     351: invokevirtual #63                 // Method java/lang/StringBuffer.append:(I)Ljava/lang/StringBuffer;
     354: ldc           #16                 // String ,
     356: invokevirtual #65                 // Method java/lang/StringBuffer.append:(Ljava/lang/String;)Ljava/lang/StringBuffer;
     359: iload         5
     361: invokevirtual #63                 // Method java/lang/StringBuffer.append:(I)Ljava/lang/StringBuffer;
     364: ldc           #16                 // String ,
     366: invokevirtual #65                 // Method java/lang/StringBuffer.append:(Ljava/lang/String;)Ljava/lang/StringBuffer;
     369: iload         6
     371: invokevirtual #63                 // Method java/lang/StringBuffer.append:(I)Ljava/lang/StringBuffer;
     374: ldc           #16                 // String ,
     376: invokevirtual #65                 // Method java/lang/StringBuffer.append:(Ljava/lang/String;)Ljava/lang/StringBuffer;
     379: aload         7
     381: invokevirtual #64                 // Method java/lang/StringBuffer.append:(Ljava/lang/Object;)Ljava/lang/StringBuffer;
     384: ldc           #16                 // String ,
     386: invokevirtual #65                 // Method java/lang/StringBuffer.append:(Ljava/lang/String;)Ljava/lang/StringBuffer;
     389: iload         8
     391: invokevirtual #63                 // Method java/lang/StringBuffer.append:(I)Ljava/lang/StringBuffer;
     394: ldc           #16                 // String ,
     396: invokevirtual #65                 // Method java/lang/StringBuffer.append:(Ljava/lang/String;)Ljava/lang/StringBuffer;
     399: iload         9
     401: invokevirtual #63                 // Method java/lang/StringBuffer.append:(I)Ljava/lang/StringBuffer;
     404: ldc           #16                 // String ,
     406: invokevirtual #65                 // Method java/lang/StringBuffer.append:(Ljava/lang/String;)Ljava/lang/StringBuffer;
     409: iload         10
     411: invokevirtual #63                 // Method java/lang/StringBuffer.append:(I)Ljava/lang/StringBuffer;
     414: ldc           #16                 // String ,
     416: invokevirtual #65                 // Method java/lang/StringBuffer.append:(Ljava/lang/String;)Ljava/lang/StringBuffer;
     419: aload         11
     421: invokevirtual #149                // Method java/lang/Throwable.toString:()Ljava/lang/String;
     424: invokevirtual #65                 // Method java/lang/StringBuffer.append:(Ljava/lang/String;)Ljava/lang/StringBuffer;
     427: invokevirtual #148                // Method java/lang/StringBuffer.toString:()Ljava/lang/String;
     430: invokestatic  #132                // Method sign/signlink.reporterror:(Ljava/lang/String;)V
     433: new           #43                 // class java/lang/RuntimeException
     436: dup
     437: invokespecial #53                 // Method java/lang/RuntimeException."<init>":()V
     440: athrow
    Exception table:
       from    to  target type
           5   310   311   Class java/lang/RuntimeException

  public final void a(byte[], int, int, int, int, byte, FTPNODIB[]);
    Code:
       0: getstatic     #414                // Field client.Jj:I
       3: istore        13
       5: iconst_0
       6: istore        8
       8: iload         13
      10: ifeq          107
      13: iconst_0
      14: istore        9
      16: iload         13
      18: ifeq          97
      21: iconst_0
      22: istore        10
      24: iload         13
      26: ifeq          87
      29: iload_3
      30: iload         9
      32: iadd
      33: ifle          84
      36: iload_3
      37: iload         9
      39: iadd
      40: bipush        103
      42: if_icmpge     84
      45: iload_2
      46: iload         10
      48: iadd
      49: ifle          84
      52: iload_2
      53: iload         10
      55: iadd
      56: bipush        103
      58: if_icmpge     84
      61: aload         7
      63: iload         8
      65: aaload
      66: getfield      #76                 // Field FTPNODIB.m:[[I
      69: iload_3
      70: iload         9
      72: iadd
      73: aaload
      74: iload_2
      75: iload         10
      77: iadd
      78: dup2
      79: iaload
      80: ldc           #11                 // int -16777217
      82: iand
      83: iastore
      84: iinc          10, 1
      87: iload         10
      89: bipush        64
      91: if_icmplt     29
      94: iinc          9, 1
      97: iload         9
      99: bipush        64
     101: if_icmplt     21
     104: iinc          8, 1
     107: iload         8
     109: iconst_4
     110: if_icmplt     13
     113: new           #39                 // class MBMGIXGO
     116: dup
     117: aload_1
     118: sipush        891
     121: invokespecial #56                 // Method MBMGIXGO."<init>":([BI)V
     124: astore        9
     126: iconst_0
     127: istore        10
     129: iload         13
     131: ifeq          197
     134: iconst_0
     135: istore        11
     137: iload         13
     139: ifeq          187
     142: iconst_0
     143: istore        12
     145: iload         13
     147: ifeq          177
     150: aload_0
     151: iload         12
     153: iload_2
     154: iadd
     155: iload         5
     157: aload         9
     159: iload         11
     161: iload_3
     162: iadd
     163: iload         10
     165: iconst_0
     166: sipush        942
     169: iload         4
     171: invokespecial #115                // Method a:(IILMBMGIXGO;IIIII)V
     174: iinc          12, 1
     177: iload         12
     179: bipush        64
     181: if_icmplt     150
     184: iinc          11, 1
     187: iload         11
     189: bipush        64
     191: if_icmplt     142
     194: iinc          10, 1
     197: iload         10
     199: iconst_4
     200: if_icmplt     134
     203: iload         6
     205: iconst_4
     206: if_icmpeq     326
     209: aload_0
     210: aload_0
     211: getfield      #72                 // Field u:Z
     214: ifeq          221
     217: iconst_0
     218: goto          222
     221: iconst_1
     222: putfield      #72                 // Field u:Z
     225: return
     226: astore        8
     228: new           #44                 // class java/lang/StringBuffer
     231: dup
     232: ldc           #24                 // String 41691,
     234: invokespecial #55                 // Method java/lang/StringBuffer."<init>":(Ljava/lang/String;)V
     237: aload_1
     238: invokevirtual #64                 // Method java/lang/StringBuffer.append:(Ljava/lang/Object;)Ljava/lang/StringBuffer;
     241: ldc           #16                 // String ,
     243: invokevirtual #65                 // Method java/lang/StringBuffer.append:(Ljava/lang/String;)Ljava/lang/StringBuffer;
     246: iload_2
     247: invokevirtual #63                 // Method java/lang/StringBuffer.append:(I)Ljava/lang/StringBuffer;
     250: ldc           #16                 // String ,
     252: invokevirtual #65                 // Method java/lang/StringBuffer.append:(Ljava/lang/String;)Ljava/lang/StringBuffer;
     255: iload_3
     256: invokevirtual #63                 // Method java/lang/StringBuffer.append:(I)Ljava/lang/StringBuffer;
     259: ldc           #16                 // String ,
     261: invokevirtual #65                 // Method java/lang/StringBuffer.append:(Ljava/lang/String;)Ljava/lang/StringBuffer;
     264: iload         4
     266: invokevirtual #63                 // Method java/lang/StringBuffer.append:(I)Ljava/lang/StringBuffer;
     269: ldc           #16                 // String ,
     271: invokevirtual #65                 // Method java/lang/StringBuffer.append:(Ljava/lang/String;)Ljava/lang/StringBuffer;
     274: iload         5
     276: invokevirtual #63                 // Method java/lang/StringBuffer.append:(I)Ljava/lang/StringBuffer;
     279: ldc           #16                 // String ,
     281: invokevirtual #65                 // Method java/lang/StringBuffer.append:(Ljava/lang/String;)Ljava/lang/StringBuffer;
     284: iload         6
     286: invokevirtual #63                 // Method java/lang/StringBuffer.append:(I)Ljava/lang/StringBuffer;
     289: ldc           #16                 // String ,
     291: invokevirtual #65                 // Method java/lang/StringBuffer.append:(Ljava/lang/String;)Ljava/lang/StringBuffer;
     294: aload         7
     296: invokevirtual #64                 // Method java/lang/StringBuffer.append:(Ljava/lang/Object;)Ljava/lang/StringBuffer;
     299: ldc           #16                 // String ,
     301: invokevirtual #65                 // Method java/lang/StringBuffer.append:(Ljava/lang/String;)Ljava/lang/StringBuffer;
     304: aload         8
     306: invokevirtual #149                // Method java/lang/Throwable.toString:()Ljava/lang/String;
     309: invokevirtual #65                 // Method java/lang/StringBuffer.append:(Ljava/lang/String;)Ljava/lang/StringBuffer;
     312: invokevirtual #148                // Method java/lang/StringBuffer.toString:()Ljava/lang/String;
     315: invokestatic  #132                // Method sign/signlink.reporterror:(Ljava/lang/String;)V
     318: new           #43                 // class java/lang/RuntimeException
     321: dup
     322: invokespecial #53                 // Method java/lang/RuntimeException."<init>":()V
     325: athrow
     326: return
    Exception table:
       from    to  target type
           5   225   226   Class java/lang/RuntimeException

  private final void a(int, int, MBMGIXGO, int, int, int, int, int);
    Code:
       0: getstatic     #414                // Field client.Jj:I
       3: istore        11
       5: bipush        36
       7: iload         7
       9: idiv
      10: istore        7
      12: iload         4
      14: iflt          326
      17: iload         4
      19: bipush        104
      21: if_icmpge     326
      24: iload_1
      25: iflt          326
      28: iload_1
      29: bipush        104
      31: if_icmpge     326
      34: aload_0
      35: getfield      #117                // Field A:[[[B
      38: iload         5
      40: aaload
      41: iload         4
      43: aaload
      44: iload_1
      45: iconst_0
      46: bastore
      47: aload_3
      48: invokevirtual #92                 // Method MBMGIXGO.c:()I
      51: istore        9
      53: iload         9
      55: ifne          127
      58: iload         5
      60: ifne          96
      63: aload_0
      64: getfield      #98                 // Field g:[[[I
      67: iconst_0
      68: aaload
      69: iload         4
      71: aaload
      72: iload_1
      73: ldc           #8                  // int 932731
      75: iload         4
      77: iadd
      78: iload         8
      80: iadd
      81: ldc           #6                  // int 556238
      83: iload_1
      84: iadd
      85: iload_2
      86: iadd
      87: invokestatic  #126                // Method b:(II)I
      90: ineg
      91: bipush        8
      93: imul
      94: iastore
      95: return
      96: aload_0
      97: getfield      #98                 // Field g:[[[I
     100: iload         5
     102: aaload
     103: iload         4
     105: aaload
     106: iload_1
     107: aload_0
     108: getfield      #98                 // Field g:[[[I
     111: iload         5
     113: iconst_1
     114: isub
     115: aaload
     116: iload         4
     118: aaload
     119: iload_1
     120: iaload
     121: sipush        240
     124: isub
     125: iastore
     126: return
     127: iload         9
     129: iconst_1
     130: if_icmpne     204
     133: aload_3
     134: invokevirtual #92                 // Method MBMGIXGO.c:()I
     137: istore        10
     139: iload         10
     141: iconst_1
     142: if_icmpne     148
     145: iconst_0
     146: istore        10
     148: iload         5
     150: ifne          171
     153: aload_0
     154: getfield      #98                 // Field g:[[[I
     157: iconst_0
     158: aaload
     159: iload         4
     161: aaload
     162: iload_1
     163: iload         10
     165: ineg
     166: bipush        8
     168: imul
     169: iastore
     170: return
     171: aload_0
     172: getfield      #98                 // Field g:[[[I
     175: iload         5
     177: aaload
     178: iload         4
     180: aaload
     181: iload_1
     182: aload_0
     183: getfield      #98                 // Field g:[[[I
     186: iload         5
     188: iconst_1
     189: isub
     190: aaload
     191: iload         4
     193: aaload
     194: iload_1
     195: iaload
     196: iload         10
     198: bipush        8
     200: imul
     201: isub
     202: iastore
     203: return
     204: iload         9
     206: bipush        49
     208: if_icmpgt     273
     211: aload_0
     212: getfield      #90                 // Field h:[[[B
     215: iload         5
     217: aaload
     218: iload         4
     220: aaload
     221: iload_1
     222: aload_3
     223: invokevirtual #93                 // Method MBMGIXGO.d:()B
     226: bastore
     227: aload_0
     228: getfield      #88                 // Field n:[[[B
     231: iload         5
     233: aaload
     234: iload         4
     236: aaload
     237: iload_1
     238: iload         9
     240: iconst_2
     241: isub
     242: iconst_4
     243: idiv
     244: i2b
     245: bastore
     246: aload_0
     247: getfield      #87                 // Field z:[[[B
     250: iload         5
     252: aaload
     253: iload         4
     255: aaload
     256: iload_1
     257: iload         9
     259: iconst_2
     260: isub
     261: iload         6
     263: iadd
     264: iconst_3
     265: iand
     266: i2b
     267: bastore
     268: iload         11
     270: ifeq          47
     273: iload         9
     275: bipush        81
     277: if_icmpgt     303
     280: aload_0
     281: getfield      #117                // Field A:[[[B
     284: iload         5
     286: aaload
     287: iload         4
     289: aaload
     290: iload_1
     291: iload         9
     293: bipush        49
     295: isub
     296: i2b
     297: bastore
     298: iload         11
     300: ifeq          47
     303: aload_0
     304: getfield      #89                 // Field t:[[[B
     307: iload         5
     309: aaload
     310: iload         4
     312: aaload
     313: iload_1
     314: iload         9
     316: bipush        81
     318: isub
     319: i2b
     320: bastore
     321: iload         11
     323: ifeq          47
     326: aload_3
     327: invokevirtual #92                 // Method MBMGIXGO.c:()I
     330: istore        9
     332: iload         9
     334: ifeq          366
     337: iload         9
     339: iconst_1
     340: if_icmpne     349
     343: aload_3
     344: invokevirtual #92                 // Method MBMGIXGO.c:()I
     347: pop
     348: return
     349: iload         9
     351: bipush        49
     353: if_icmpgt     326
     356: aload_3
     357: invokevirtual #92                 // Method MBMGIXGO.c:()I
     360: pop
     361: iload         11
     363: ifeq          326
     366: return
     367: astore        9
     369: new           #44                 // class java/lang/StringBuffer
     372: dup
     373: ldc           #22                 // String 30203,
     375: invokespecial #55                 // Method java/lang/StringBuffer."<init>":(Ljava/lang/String;)V
     378: iload_1
     379: invokevirtual #63                 // Method java/lang/StringBuffer.append:(I)Ljava/lang/StringBuffer;
     382: ldc           #16                 // String ,
     384: invokevirtual #65                 // Method java/lang/StringBuffer.append:(Ljava/lang/String;)Ljava/lang/StringBuffer;
     387: iload_2
     388: invokevirtual #63                 // Method java/lang/StringBuffer.append:(I)Ljava/lang/StringBuffer;
     391: ldc           #16                 // String ,
     393: invokevirtual #65                 // Method java/lang/StringBuffer.append:(Ljava/lang/String;)Ljava/lang/StringBuffer;
     396: aload_3
     397: invokevirtual #64                 // Method java/lang/StringBuffer.append:(Ljava/lang/Object;)Ljava/lang/StringBuffer;
     400: ldc           #16                 // String ,
     402: invokevirtual #65                 // Method java/lang/StringBuffer.append:(Ljava/lang/String;)Ljava/lang/StringBuffer;
     405: iload         4
     407: invokevirtual #63                 // Method java/lang/StringBuffer.append:(I)Ljava/lang/StringBuffer;
     410: ldc           #16                 // String ,
     412: invokevirtual #65                 // Method java/lang/StringBuffer.append:(Ljava/lang/String;)Ljava/lang/StringBuffer;
     415: iload         5
     417: invokevirtual #63                 // Method java/lang/StringBuffer.append:(I)Ljava/lang/StringBuffer;
     420: ldc           #16                 // String ,
     422: invokevirtual #65                 // Method java/lang/StringBuffer.append:(Ljava/lang/String;)Ljava/lang/StringBuffer;
     425: iload         6
     427: invokevirtual #63                 // Method java/lang/StringBuffer.append:(I)Ljava/lang/StringBuffer;
     430: ldc           #16                 // String ,
     432: invokevirtual #65                 // Method java/lang/StringBuffer.append:(Ljava/lang/String;)Ljava/lang/StringBuffer;
     435: iload         7
     437: invokevirtual #63                 // Method java/lang/StringBuffer.append:(I)Ljava/lang/StringBuffer;
     440: ldc           #16                 // String ,
     442: invokevirtual #65                 // Method java/lang/StringBuffer.append:(Ljava/lang/String;)Ljava/lang/StringBuffer;
     445: iload         8
     447: invokevirtual #63                 // Method java/lang/StringBuffer.append:(I)Ljava/lang/StringBuffer;
     450: ldc           #16                 // String ,
     452: invokevirtual #65                 // Method java/lang/StringBuffer.append:(Ljava/lang/String;)Ljava/lang/StringBuffer;
     455: aload         9
     457: invokevirtual #149                // Method java/lang/Throwable.toString:()Ljava/lang/String;
     460: invokevirtual #65                 // Method java/lang/StringBuffer.append:(Ljava/lang/String;)Ljava/lang/StringBuffer;
     463: invokevirtual #148                // Method java/lang/StringBuffer.toString:()Ljava/lang/String;
     466: invokestatic  #132                // Method sign/signlink.reporterror:(Ljava/lang/String;)V
     469: new           #43                 // class java/lang/RuntimeException
     472: dup
     473: invokespecial #53                 // Method java/lang/RuntimeException."<init>":()V
     476: athrow
    Exception table:
       from    to  target type
           5   366   367   Class java/lang/RuntimeException

  public int a(int, int, int, int);
    Code:
       0: iload         4
       2: ifeq          7
       5: iconst_2
       6: ireturn
       7: aload_0
       8: getfield      #117                // Field A:[[[B
      11: iload_2
      12: aaload
      13: iload_3
      14: aaload
      15: iload_1
      16: baload
      17: bipush        8
      19: iand
      20: ifeq          25
      23: iconst_0
      24: ireturn
      25: iload_2
      26: ifle          48
      29: aload_0
      30: getfield      #117                // Field A:[[[B
      33: iconst_1
      34: aaload
      35: iload_3
      36: aaload
      37: iload_1
      38: baload
      39: iconst_2
      40: iand
      41: ifeq          48
      44: iload_2
      45: iconst_1
      46: isub
      47: ireturn
      48: iload_2
      49: ireturn
      50: astore        5
      52: new           #44                 // class java/lang/StringBuffer
      55: dup
      56: ldc           #26                 // String 5828,
      58: invokespecial #55                 // Method java/lang/StringBuffer."<init>":(Ljava/lang/String;)V
      61: iload_1
      62: invokevirtual #63                 // Method java/lang/StringBuffer.append:(I)Ljava/lang/StringBuffer;
      65: ldc           #16                 // String ,
      67: invokevirtual #65                 // Method java/lang/StringBuffer.append:(Ljava/lang/String;)Ljava/lang/StringBuffer;
      70: iload_2
      71: invokevirtual #63                 // Method java/lang/StringBuffer.append:(I)Ljava/lang/StringBuffer;
      74: ldc           #16                 // String ,
      76: invokevirtual #65                 // Method java/lang/StringBuffer.append:(Ljava/lang/String;)Ljava/lang/StringBuffer;
      79: iload_3
      80: invokevirtual #63                 // Method java/lang/StringBuffer.append:(I)Ljava/lang/StringBuffer;
      83: ldc           #16                 // String ,
      85: invokevirtual #65                 // Method java/lang/StringBuffer.append:(Ljava/lang/String;)Ljava/lang/StringBuffer;
      88: iload         4
      90: invokevirtual #63                 // Method java/lang/StringBuffer.append:(I)Ljava/lang/StringBuffer;
      93: ldc           #16                 // String ,
      95: invokevirtual #65                 // Method java/lang/StringBuffer.append:(Ljava/lang/String;)Ljava/lang/StringBuffer;
      98: aload         5
     100: invokevirtual #149                // Method java/lang/Throwable.toString:()Ljava/lang/String;
     103: invokevirtual #65                 // Method java/lang/StringBuffer.append:(Ljava/lang/String;)Ljava/lang/StringBuffer;
     106: invokevirtual #148                // Method java/lang/StringBuffer.toString:()Ljava/lang/String;
     109: invokestatic  #132                // Method sign/signlink.reporterror:(Ljava/lang/String;)V
     112: new           #43                 // class java/lang/RuntimeException
     115: dup
     116: invokespecial #53                 // Method java/lang/RuntimeException."<init>":()V
     119: athrow
    Exception table:
       from    to  target type
           0    50    50   Class java/lang/RuntimeException

  public final void a(FTPNODIB[], NYFUGYQS, int, int, int, boolean, int, byte[], int, int, int);
    Code:
       0: getstatic     #414                // Field client.Jj:I
       3: istore        28
       5: new           #39                 // class MBMGIXGO
       8: dup
       9: aload         8
      11: sipush        891
      14: invokespecial #56                 // Method MBMGIXGO."<init>":([BI)V
      17: astore        12
      19: iconst_m1
      20: istore        13
      22: iload         6
      24: ifne          43
      27: aload_0
      28: aload_0
      29: getfield      #72                 // Field u:Z
      32: ifeq          39
      35: iconst_0
      36: goto          40
      39: iconst_1
      40: putfield      #72                 // Field u:Z
      43: aload         12
      45: invokevirtual #99                 // Method MBMGIXGO.k:()I
      48: istore        14
      50: iload         14
      52: ifeq          339
      55: iload         13
      57: iload         14
      59: iadd
      60: istore        13
      62: iconst_0
      63: istore        15
      65: aload         12
      67: invokevirtual #99                 // Method MBMGIXGO.k:()I
      70: istore        16
      72: iload         16
      74: ifeq          334
      77: iload         15
      79: iload         16
      81: iconst_1
      82: isub
      83: iadd
      84: istore        15
      86: iload         15
      88: bipush        63
      90: iand
      91: istore        17
      93: iload         15
      95: bipush        6
      97: ishr
      98: bipush        63
     100: iand
     101: istore        18
     103: iload         15
     105: bipush        12
     107: ishr
     108: istore        19
     110: aload         12
     112: invokevirtual #92                 // Method MBMGIXGO.c:()I
     115: istore        20
     117: iload         20
     119: iconst_2
     120: ishr
     121: istore        21
     123: iload         20
     125: iconst_3
     126: iand
     127: istore        22
     129: iload         19
     131: iload_3
     132: if_icmpne     65
     135: iload         18
     137: iload         9
     139: if_icmplt     65
     142: iload         18
     144: iload         9
     146: bipush        8
     148: iadd
     149: if_icmpge     65
     152: iload         17
     154: iload         5
     156: if_icmplt     65
     159: iload         17
     161: iload         5
     163: bipush        8
     165: iadd
     166: if_icmpge     65
     169: iload         13
     171: invokestatic  #113                // Method YZDBYLRM.a:(I)LYZDBYLRM;
     174: astore        23
     176: iload         4
     178: iload         10
     180: aload         23
     182: getfield      #109                // Field YZDBYLRM.z:I
     185: iload         18
     187: bipush        7
     189: iand
     190: bipush        113
     192: iload         17
     194: bipush        7
     196: iand
     197: aload         23
     199: getfield      #157                // Field YZDBYLRM.i:I
     202: invokestatic  #83                 // Method CDEJWOSB.a:(IIIBII)I
     205: iadd
     206: istore        24
     208: iload         11
     210: sipush        -433
     213: iload         17
     215: bipush        7
     217: iand
     218: aload         23
     220: getfield      #109                // Field YZDBYLRM.z:I
     223: iload         10
     225: aload         23
     227: getfield      #157                // Field YZDBYLRM.i:I
     230: iload         18
     232: bipush        7
     234: iand
     235: invokestatic  #86                 // Method CDEJWOSB.a:(IIIIII)I
     238: iadd
     239: istore        25
     241: iload         24
     243: ifle          65
     246: iload         25
     248: ifle          65
     251: iload         24
     253: bipush        103
     255: if_icmpge     65
     258: iload         25
     260: bipush        103
     262: if_icmpge     65
     265: iload         19
     267: istore        26
     269: aload_0
     270: getfield      #117                // Field A:[[[B
     273: iconst_1
     274: aaload
     275: iload         24
     277: aaload
     278: iload         25
     280: baload
     281: iconst_2
     282: iand
     283: iconst_2
     284: if_icmpne     290
     287: iinc          26, -1
     290: aconst_null
     291: astore        27
     293: iload         26
     295: iflt          304
     298: aload_1
     299: iload         26
     301: aaload
     302: astore        27
     304: aload_0
     305: iload         25
     307: aload_2
     308: aload         27
     310: iload         21
     312: iload         7
     314: iload         24
     316: iload         13
     318: iconst_0
     319: iload         22
     321: iload         10
     323: iadd
     324: iconst_3
     325: iand
     326: invokespecial #58                 // Method a:(ILNYFUGYQS;LFTPNODIB;IIIIZI)V
     329: iload         28
     331: ifeq          65
     334: iload         28
     336: ifeq          43
     339: return
     340: astore        12
     342: new           #44                 // class java/lang/StringBuffer
     345: dup
     346: ldc           #18                 // String 1483,
     348: invokespecial #55                 // Method java/lang/StringBuffer."<init>":(Ljava/lang/String;)V
     351: aload_1
     352: invokevirtual #64                 // Method java/lang/StringBuffer.append:(Ljava/lang/Object;)Ljava/lang/StringBuffer;
     355: ldc           #16                 // String ,
     357: invokevirtual #65                 // Method java/lang/StringBuffer.append:(Ljava/lang/String;)Ljava/lang/StringBuffer;
     360: aload_2
     361: invokevirtual #64                 // Method java/lang/StringBuffer.append:(Ljava/lang/Object;)Ljava/lang/StringBuffer;
     364: ldc           #16                 // String ,
     366: invokevirtual #65                 // Method java/lang/StringBuffer.append:(Ljava/lang/String;)Ljava/lang/StringBuffer;
     369: iload_3
     370: invokevirtual #63                 // Method java/lang/StringBuffer.append:(I)Ljava/lang/StringBuffer;
     373: ldc           #16                 // String ,
     375: invokevirtual #65                 // Method java/lang/StringBuffer.append:(Ljava/lang/String;)Ljava/lang/StringBuffer;
     378: iload         4
     380: invokevirtual #63                 // Method java/lang/StringBuffer.append:(I)Ljava/lang/StringBuffer;
     383: ldc           #16                 // String ,
     385: invokevirtual #65                 // Method java/lang/StringBuffer.append:(Ljava/lang/String;)Ljava/lang/StringBuffer;
     388: iload         5
     390: invokevirtual #63                 // Method java/lang/StringBuffer.append:(I)Ljava/lang/StringBuffer;
     393: ldc           #16                 // String ,
     395: invokevirtual #65                 // Method java/lang/StringBuffer.append:(Ljava/lang/String;)Ljava/lang/StringBuffer;
     398: iload         6
     400: invokevirtual #66                 // Method java/lang/StringBuffer.append:(Z)Ljava/lang/StringBuffer;
     403: ldc           #16                 // String ,
     405: invokevirtual #65                 // Method java/lang/StringBuffer.append:(Ljava/lang/String;)Ljava/lang/StringBuffer;
     408: iload         7
     410: invokevirtual #63                 // Method java/lang/StringBuffer.append:(I)Ljava/lang/StringBuffer;
     413: ldc           #16                 // String ,
     415: invokevirtual #65                 // Method java/lang/StringBuffer.append:(Ljava/lang/String;)Ljava/lang/StringBuffer;
     418: aload         8
     420: invokevirtual #64                 // Method java/lang/StringBuffer.append:(Ljava/lang/Object;)Ljava/lang/StringBuffer;
     423: ldc           #16                 // String ,
     425: invokevirtual #65                 // Method java/lang/StringBuffer.append:(Ljava/lang/String;)Ljava/lang/StringBuffer;
     428: iload         9
     430: invokevirtual #63                 // Method java/lang/StringBuffer.append:(I)Ljava/lang/StringBuffer;
     433: ldc           #16                 // String ,
     435: invokevirtual #65                 // Method java/lang/StringBuffer.append:(Ljava/lang/String;)Ljava/lang/StringBuffer;
     438: iload         10
     440: invokevirtual #63                 // Method java/lang/StringBuffer.append:(I)Ljava/lang/StringBuffer;
     443: ldc           #16                 // String ,
     445: invokevirtual #65                 // Method java/lang/StringBuffer.append:(Ljava/lang/String;)Ljava/lang/StringBuffer;
     448: iload         11
     450: invokevirtual #63                 // Method java/lang/StringBuffer.append:(I)Ljava/lang/StringBuffer;
     453: ldc           #16                 // String ,
     455: invokevirtual #65                 // Method java/lang/StringBuffer.append:(Ljava/lang/String;)Ljava/lang/StringBuffer;
     458: aload         12
     460: invokevirtual #149                // Method java/lang/Throwable.toString:()Ljava/lang/String;
     463: invokevirtual #65                 // Method java/lang/StringBuffer.append:(Ljava/lang/String;)Ljava/lang/StringBuffer;
     466: invokevirtual #148                // Method java/lang/StringBuffer.toString:()Ljava/lang/String;
     469: invokestatic  #132                // Method sign/signlink.reporterror:(Ljava/lang/String;)V
     472: new           #43                 // class java/lang/RuntimeException
     475: dup
     476: invokespecial #53                 // Method java/lang/RuntimeException."<init>":()V
     479: athrow
    Exception table:
       from    to  target type
           5   339   340   Class java/lang/RuntimeException

  private static final int b(int, int, int, int);
    Code:
       0: ldc           #4                  // int 65536
       2: getstatic     #80                 // Field OPPOFIOL.K:[I
       5: iload_2
       6: sipush        1024
       9: imul
      10: iload_3
      11: idiv
      12: iaload
      13: isub
      14: iconst_1
      15: ishr
      16: istore        4
      18: iload_0
      19: ldc           #4                  // int 65536
      21: iload         4
      23: isub
      24: imul
      25: bipush        16
      27: ishr
      28: iload_1
      29: iload         4
      31: imul
      32: bipush        16
      34: ishr
      35: iadd
      36: ireturn

  private final int c(int, int);
    Code:
       0: getstatic     #414                // Field client.Jj:I
       3: istore_3
       4: iload_1
       5: bipush        -2
       7: if_icmpne     13
      10: ldc           #9                  // int 12345678
      12: ireturn
      13: iload_1
      14: iconst_m1
      15: if_icmpne     44
      18: iload_2
      19: ifge          28
      22: iconst_0
      23: istore_2
      24: iload_3
      25: ifeq          37
      28: iload_2
      29: bipush        127
      31: if_icmple     37
      34: bipush        127
      36: istore_2
      37: bipush        127
      39: iload_2
      40: isub
      41: istore_2
      42: iload_2
      43: ireturn
      44: iload_2
      45: iload_1
      46: bipush        127
      48: iand
      49: imul
      50: sipush        128
      53: idiv
      54: istore_2
      55: iload_2
      56: iconst_2
      57: if_icmpge     66
      60: iconst_2
      61: istore_2
      62: iload_3
      63: ifeq          75
      66: iload_2
      67: bipush        126
      69: if_icmple     75
      72: bipush        126
      74: istore_2
      75: iload_1
      76: ldc           #3                  // int 65408
      78: iand
      79: iload_2
      80: iadd
      81: ireturn

  private static final int d(int, int);
    Code:
       0: iload_0
       1: iconst_1
       2: isub
       3: iload_1
       4: iconst_1
       5: isub
       6: invokestatic  #123                // Method a:(II)I
       9: iload_0
      10: iconst_1
      11: iadd
      12: iload_1
      13: iconst_1
      14: isub
      15: invokestatic  #123                // Method a:(II)I
      18: iadd
      19: iload_0
      20: iconst_1
      21: isub
      22: iload_1
      23: iconst_1
      24: iadd
      25: invokestatic  #123                // Method a:(II)I
      28: iadd
      29: iload_0
      30: iconst_1
      31: iadd
      32: iload_1
      33: iconst_1
      34: iadd
      35: invokestatic  #123                // Method a:(II)I
      38: iadd
      39: istore_2
      40: iload_0
      41: iconst_1
      42: isub
      43: iload_1
      44: invokestatic  #123                // Method a:(II)I
      47: iload_0
      48: iconst_1
      49: iadd
      50: iload_1
      51: invokestatic  #123                // Method a:(II)I
      54: iadd
      55: iload_0
      56: iload_1
      57: iconst_1
      58: isub
      59: invokestatic  #123                // Method a:(II)I
      62: iadd
      63: iload_0
      64: iload_1
      65: iconst_1
      66: iadd
      67: invokestatic  #123                // Method a:(II)I
      70: iadd
      71: istore_3
      72: iload_0
      73: iload_1
      74: invokestatic  #123                // Method a:(II)I
      77: istore        4
      79: iload_2
      80: bipush        16
      82: idiv
      83: iload_3
      84: bipush        8
      86: idiv
      87: iadd
      88: iload         4
      90: iconst_4
      91: idiv
      92: iadd
      93: ireturn

  private static final int e(int, int);
    Code:
       0: iload_0
       1: iconst_m1
       2: if_icmpne     8
       5: ldc           #9                  // int 12345678
       7: ireturn
       8: iload_1
       9: iload_0
      10: bipush        127
      12: iand
      13: imul
      14: sipush        128
      17: idiv
      18: istore_1
      19: iload_1
      20: iconst_2
      21: if_icmpge     32
      24: iconst_2
      25: istore_1
      26: getstatic     #414                // Field client.Jj:I
      29: ifeq          41
      32: iload_1
      33: bipush        126
      35: if_icmple     41
      38: bipush        126
      40: istore_1
      41: iload_0
      42: ldc           #3                  // int 65408
      44: iand
      45: iload_1
      46: iadd
      47: ireturn

  public static final void a(NYFUGYQS, int, int, int, int, FTPNODIB, int[][][], int, int, int, byte);
    Code:
       0: getstatic     #414                // Field client.Jj:I
       3: istore        23
       5: aload         6
       7: iload         4
       9: aaload
      10: iload         7
      12: aaload
      13: iload_2
      14: iaload
      15: istore        11
      17: aload         6
      19: iload         4
      21: aaload
      22: iload         7
      24: iconst_1
      25: iadd
      26: aaload
      27: iload_2
      28: iaload
      29: istore        12
      31: aload         6
      33: iload         4
      35: aaload
      36: iload         7
      38: iconst_1
      39: iadd
      40: aaload
      41: iload_2
      42: iconst_1
      43: iadd
      44: iaload
      45: istore        13
      47: aload         6
      49: iload         4
      51: aaload
      52: iload         7
      54: aaload
      55: iload_2
      56: iconst_1
      57: iadd
      58: iaload
      59: istore        14
      61: iload         10
      63: bipush        93
      65: if_icmpeq     74
      68: sipush        -145
      71: putstatic     #151                // Field E:I
      74: iload         11
      76: iload         12
      78: iadd
      79: iload         13
      81: iadd
      82: iload         14
      84: iadd
      85: iconst_2
      86: ishr
      87: istore        15
      89: iload         8
      91: invokestatic  #113                // Method YZDBYLRM.a:(I)LYZDBYLRM;
      94: astore        16
      96: iload         7
      98: iload_2
      99: bipush        7
     101: ishl
     102: iadd
     103: iload         8
     105: bipush        14
     107: ishl
     108: iadd
     109: ldc           #12                 // int 1073741824
     111: iadd
     112: istore        17
     114: aload         16
     116: getfield      #57                 // Field YZDBYLRM.Q:Z
     119: ifne          129
     122: iload         17
     124: ldc           #15                 // int -2147483648
     126: iadd
     127: istore        17
     129: iload_1
     130: bipush        6
     132: ishl
     133: iload_3
     134: iadd
     135: i2b
     136: istore        18
     138: iload_3
     139: bipush        22
     141: if_icmpne     260
     144: aload         16
     146: getfield      #62                 // Field YZDBYLRM.T:I
     149: iconst_m1
     150: if_icmpne     185
     153: aload         16
     155: getfield      #122                // Field YZDBYLRM.x:[I
     158: ifnonnull     185
     161: aload         16
     163: bipush        22
     165: iload_1
     166: iload         11
     168: iload         12
     170: iload         13
     172: iload         14
     174: iconst_m1
     175: invokevirtual #94                 // Method YZDBYLRM.a:(IIIIIII)LZKARKDQW;
     178: astore        19
     180: iload         23
     182: ifeq          215
     185: new           #35                 // class WBWOBAFW
     188: dup
     189: iload         8
     191: iload_1
     192: bipush        22
     194: iload         12
     196: bipush        7
     198: iload         13
     200: iload         11
     202: iload         14
     204: aload         16
     206: getfield      #62                 // Field YZDBYLRM.T:I
     209: iconst_1
     210: invokespecial #54                 // Method WBWOBAFW."<init>":(IIIIBIIIIZ)V
     213: astore        19
     215: aload_0
     216: iload         9
     218: iload         15
     220: iload_2
     221: bipush        68
     223: aload         19
     225: iload         18
     227: iload         17
     229: iload         7
     231: invokevirtual #137                // Method NYFUGYQS.a:(IIIILXHHRODPC;BII)V
     234: aload         16
     236: getfield      #69                 // Field YZDBYLRM.F:Z
     239: ifeq          259
     242: aload         16
     244: getfield      #57                 // Field YZDBYLRM.Q:Z
     247: ifeq          259
     250: aload         5
     252: iload_2
     253: iconst_0
     254: iload         7
     256: invokevirtual #67                 // Method FTPNODIB.a:(III)V
     259: return
     260: iload_3
     261: bipush        10
     263: if_icmpeq     272
     266: iload_3
     267: bipush        11
     269: if_icmpne     468
     272: aload         16
     274: getfield      #62                 // Field YZDBYLRM.T:I
     277: iconst_m1
     278: if_icmpne     313
     281: aload         16
     283: getfield      #122                // Field YZDBYLRM.x:[I
     286: ifnonnull     313
     289: aload         16
     291: bipush        10
     293: iload_1
     294: iload         11
     296: iload         12
     298: iload         13
     300: iload         14
     302: iconst_m1
     303: invokevirtual #94                 // Method YZDBYLRM.a:(IIIIIII)LZKARKDQW;
     306: astore        19
     308: iload         23
     310: ifeq          343
     313: new           #35                 // class WBWOBAFW
     316: dup
     317: iload         8
     319: iload_1
     320: bipush        10
     322: iload         12
     324: bipush        7
     326: iload         13
     328: iload         11
     330: iload         14
     332: aload         16
     334: getfield      #62                 // Field YZDBYLRM.T:I
     337: iconst_1
     338: invokespecial #54                 // Method WBWOBAFW."<init>":(IIIIBIIIIZ)V
     341: astore        19
     343: aload         19
     345: ifnull        432
     348: iconst_0
     349: istore        22
     351: iload_3
     352: bipush        11
     354: if_icmpne     363
     357: iinc_w        22, 256
     363: iload_1
     364: iconst_1
     365: if_icmpeq     373
     368: iload_1
     369: iconst_3
     370: if_icmpne     392
     373: aload         16
     375: getfield      #109                // Field YZDBYLRM.z:I
     378: istore        20
     380: aload         16
     382: getfield      #157                // Field YZDBYLRM.i:I
     385: istore        21
     387: iload         23
     389: ifeq          406
     392: aload         16
     394: getfield      #157                // Field YZDBYLRM.i:I
     397: istore        20
     399: aload         16
     401: getfield      #109                // Field YZDBYLRM.z:I
     404: istore        21
     406: aload_0
     407: iload         17
     409: iload         18
     411: iload         15
     413: iload         21
     415: aload         19
     417: iload         20
     419: iload         9
     421: iload         22
     423: bipush        110
     425: iload_2
     426: iload         7
     428: invokevirtual #60                 // Method NYFUGYQS.a:(IBIILXHHRODPC;IIIBII)Z
     431: pop
     432: aload         16
     434: getfield      #69                 // Field YZDBYLRM.F:Z
     437: ifeq          467
     440: aload         5
     442: aload         16
     444: getfield      #68                 // Field YZDBYLRM.v:Z
     447: getstatic     #75                 // Field p:I
     450: aload         16
     452: getfield      #157                // Field YZDBYLRM.i:I
     455: aload         16
     457: getfield      #109                // Field YZDBYLRM.z:I
     460: iload         7
     462: iload_2
     463: iload_1
     464: invokevirtual #59                 // Method FTPNODIB.a:(ZIIIIII)V
     467: return
     468: iload_3
     469: bipush        12
     471: if_icmplt     602
     474: aload         16
     476: getfield      #62                 // Field YZDBYLRM.T:I
     479: iconst_m1
     480: if_icmpne     514
     483: aload         16
     485: getfield      #122                // Field YZDBYLRM.x:[I
     488: ifnonnull     514
     491: aload         16
     493: iload_3
     494: iload_1
     495: iload         11
     497: iload         12
     499: iload         13
     501: iload         14
     503: iconst_m1
     504: invokevirtual #94                 // Method YZDBYLRM.a:(IIIIIII)LZKARKDQW;
     507: astore        19
     509: iload         23
     511: ifeq          543
     514: new           #35                 // class WBWOBAFW
     517: dup
     518: iload         8
     520: iload_1
     521: iload_3
     522: iload         12
     524: bipush        7
     526: iload         13
     528: iload         11
     530: iload         14
     532: aload         16
     534: getfield      #62                 // Field YZDBYLRM.T:I
     537: iconst_1
     538: invokespecial #54                 // Method WBWOBAFW."<init>":(IIIIBIIIIZ)V
     541: astore        19
     543: aload_0
     544: iload         17
     546: iload         18
     548: iload         15
     550: iconst_1
     551: aload         19
     553: iconst_1
     554: iload         9
     556: iconst_0
     557: bipush        110
     559: iload_2
     560: iload         7
     562: invokevirtual #60                 // Method NYFUGYQS.a:(IBIILXHHRODPC;IIIBII)Z
     565: pop
     566: aload         16
     568: getfield      #69                 // Field YZDBYLRM.F:Z
     571: ifeq          601
     574: aload         5
     576: aload         16
     578: getfield      #68                 // Field YZDBYLRM.v:Z
     581: getstatic     #75                 // Field p:I
     584: aload         16
     586: getfield      #157                // Field YZDBYLRM.i:I
     589: aload         16
     591: getfield      #109                // Field YZDBYLRM.z:I
     594: iload         7
     596: iload_2
     597: iload_1
     598: invokevirtual #59                 // Method FTPNODIB.a:(ZIIIIII)V
     601: return
     602: iload_3
     603: ifne          725
     606: aload         16
     608: getfield      #62                 // Field YZDBYLRM.T:I
     611: iconst_m1
     612: if_icmpne     646
     615: aload         16
     617: getfield      #122                // Field YZDBYLRM.x:[I
     620: ifnonnull     646
     623: aload         16
     625: iconst_0
     626: iload_1
     627: iload         11
     629: iload         12
     631: iload         13
     633: iload         14
     635: iconst_m1
     636: invokevirtual #94                 // Method YZDBYLRM.a:(IIIIIII)LZKARKDQW;
     639: astore        19
     641: iload         23
     643: ifeq          675
     646: new           #35                 // class WBWOBAFW
     649: dup
     650: iload         8
     652: iload_1
     653: iconst_0
     654: iload         12
     656: bipush        7
     658: iload         13
     660: iload         11
     662: iload         14
     664: aload         16
     666: getfield      #62                 // Field YZDBYLRM.T:I
     669: iconst_1
     670: invokespecial #54                 // Method WBWOBAFW."<init>":(IIIIBIIIIZ)V
     673: astore        19
     675: aload_0
     676: getstatic     #158                // Field D:[I
     679: iload_1
     680: iaload
     681: aload         19
     683: iconst_1
     684: iload         17
     686: iload_2
     687: iload         18
     689: iload         7
     691: aconst_null
     692: iload         15
     694: iconst_0
     695: iload         9
     697: invokevirtual #140                // Method NYFUGYQS.a:(ILXHHRODPC;ZIIBILXHHRODPC;III)V
     700: aload         16
     702: getfield      #69                 // Field YZDBYLRM.F:Z
     705: ifeq          724
     708: aload         5
     710: iload_2
     711: iload_1
     712: iload         7
     714: iload_3
     715: iconst_1
     716: aload         16
     718: getfield      #68                 // Field YZDBYLRM.v:Z
     721: invokevirtual #61                 // Method FTPNODIB.a:(IIIIBZ)V
     724: return
     725: iload_3
     726: iconst_1
     727: if_icmpne     849
     730: aload         16
     732: getfield      #62                 // Field YZDBYLRM.T:I
     735: iconst_m1
     736: if_icmpne     770
     739: aload         16
     741: getfield      #122                // Field YZDBYLRM.x:[I
     744: ifnonnull     770
     747: aload         16
     749: iconst_1
     750: iload_1
     751: iload         11
     753: iload         12
     755: iload         13
     757: iload         14
     759: iconst_m1
     760: invokevirtual #94                 // Method YZDBYLRM.a:(IIIIIII)LZKARKDQW;
     763: astore        19
     765: iload         23
     767: ifeq          799
     770: new           #35                 // class WBWOBAFW
     773: dup
     774: iload         8
     776: iload_1
     777: iconst_1
     778: iload         12
     780: bipush        7
     782: iload         13
     784: iload         11
     786: iload         14
     788: aload         16
     790: getfield      #62                 // Field YZDBYLRM.T:I
     793: iconst_1
     794: invokespecial #54                 // Method WBWOBAFW."<init>":(IIIIBIIIIZ)V
     797: astore        19
     799: aload_0
     800: getstatic     #159                // Field r:[I
     803: iload_1
     804: iaload
     805: aload         19
     807: iconst_1
     808: iload         17
     810: iload_2
     811: iload         18
     813: iload         7
     815: aconst_null
     816: iload         15
     818: iconst_0
     819: iload         9
     821: invokevirtual #140                // Method NYFUGYQS.a:(ILXHHRODPC;ZIIBILXHHRODPC;III)V
     824: aload         16
     826: getfield      #69                 // Field YZDBYLRM.F:Z
     829: ifeq          848
     832: aload         5
     834: iload_2
     835: iload_1
     836: iload         7
     838: iload_3
     839: iconst_1
     840: aload         16
     842: getfield      #68                 // Field YZDBYLRM.v:Z
     845: invokevirtual #61                 // Method FTPNODIB.a:(IIIIBZ)V
     848: return
     849: iload_3
     850: iconst_2
     851: if_icmpne     1039
     854: iload_1
     855: iconst_1
     856: iadd
     857: iconst_3
     858: iand
     859: istore        19
     861: aload         16
     863: getfield      #62                 // Field YZDBYLRM.T:I
     866: iconst_m1
     867: if_icmpne     922
     870: aload         16
     872: getfield      #122                // Field YZDBYLRM.x:[I
     875: ifnonnull     922
     878: aload         16
     880: iconst_2
     881: iconst_4
     882: iload_1
     883: iadd
     884: iload         11
     886: iload         12
     888: iload         13
     890: iload         14
     892: iconst_m1
     893: invokevirtual #94                 // Method YZDBYLRM.a:(IIIIIII)LZKARKDQW;
     896: astore        20
     898: aload         16
     900: iconst_2
     901: iload         19
     903: iload         11
     905: iload         12
     907: iload         13
     909: iload         14
     911: iconst_m1
     912: invokevirtual #94                 // Method YZDBYLRM.a:(IIIIIII)LZKARKDQW;
     915: astore        21
     917: iload         23
     919: ifeq          983
     922: new           #35                 // class WBWOBAFW
     925: dup
     926: iload         8
     928: iconst_4
     929: iload_1
     930: iadd
     931: iconst_2
     932: iload         12
     934: bipush        7
     936: iload         13
     938: iload         11
     940: iload         14
     942: aload         16
     944: getfield      #62                 // Field YZDBYLRM.T:I
     947: iconst_1
     948: invokespecial #54                 // Method WBWOBAFW."<init>":(IIIIBIIIIZ)V
     951: astore        20
     953: new           #35                 // class WBWOBAFW
     956: dup
     957: iload         8
     959: iload         19
     961: iconst_2
     962: iload         12
     964: bipush        7
     966: iload         13
     968: iload         11
     970: iload         14
     972: aload         16
     974: getfield      #62                 // Field YZDBYLRM.T:I
     977: iconst_1
     978: invokespecial #54                 // Method WBWOBAFW."<init>":(IIIIBIIIIZ)V
     981: astore        21
     983: aload_0
     984: getstatic     #158                // Field D:[I
     987: iload_1
     988: iaload
     989: aload         20
     991: iconst_1
     992: iload         17
     994: iload_2
     995: iload         18
     997: iload         7
     999: aload         21
    1001: iload         15
    1003: getstatic     #158                // Field D:[I
    1006: iload         19
    1008: iaload
    1009: iload         9
    1011: invokevirtual #140                // Method NYFUGYQS.a:(ILXHHRODPC;ZIIBILXHHRODPC;III)V
    1014: aload         16
    1016: getfield      #69                 // Field YZDBYLRM.F:Z
    1019: ifeq          1038
    1022: aload         5
    1024: iload_2
    1025: iload_1
    1026: iload         7
    1028: iload_3
    1029: iconst_1
    1030: aload         16
    1032: getfield      #68                 // Field YZDBYLRM.v:Z
    1035: invokevirtual #61                 // Method FTPNODIB.a:(IIIIBZ)V
    1038: return
    1039: iload_3
    1040: iconst_3
    1041: if_icmpne     1163
    1044: aload         16
    1046: getfield      #62                 // Field YZDBYLRM.T:I
    1049: iconst_m1
    1050: if_icmpne     1084
    1053: aload         16
    1055: getfield      #122                // Field YZDBYLRM.x:[I
    1058: ifnonnull     1084
    1061: aload         16
    1063: iconst_3
    1064: iload_1
    1065: iload         11
    1067: iload         12
    1069: iload         13
    1071: iload         14
    1073: iconst_m1
    1074: invokevirtual #94                 // Method YZDBYLRM.a:(IIIIIII)LZKARKDQW;
    1077: astore        19
    1079: iload         23
    1081: ifeq          1113
    1084: new           #35                 // class WBWOBAFW
    1087: dup
    1088: iload         8
    1090: iload_1
    1091: iconst_3
    1092: iload         12
    1094: bipush        7
    1096: iload         13
    1098: iload         11
    1100: iload         14
    1102: aload         16
    1104: getfield      #62                 // Field YZDBYLRM.T:I
    1107: iconst_1
    1108: invokespecial #54                 // Method WBWOBAFW."<init>":(IIIIBIIIIZ)V
    1111: astore        19
    1113: aload_0
    1114: getstatic     #159                // Field r:[I
    1117: iload_1
    1118: iaload
    1119: aload         19
    1121: iconst_1
    1122: iload         17
    1124: iload_2
    1125: iload         18
    1127: iload         7
    1129: aconst_null
    1130: iload         15
    1132: iconst_0
    1133: iload         9
    1135: invokevirtual #140                // Method NYFUGYQS.a:(ILXHHRODPC;ZIIBILXHHRODPC;III)V
    1138: aload         16
    1140: getfield      #69                 // Field YZDBYLRM.F:Z
    1143: ifeq          1162
    1146: aload         5
    1148: iload_2
    1149: iload_1
    1150: iload         7
    1152: iload_3
    1153: iconst_1
    1154: aload         16
    1156: getfield      #68                 // Field YZDBYLRM.v:Z
    1159: invokevirtual #61                 // Method FTPNODIB.a:(IIIIBZ)V
    1162: return
    1163: iload_3
    1164: bipush        9
    1166: if_icmpne     1297
    1169: aload         16
    1171: getfield      #62                 // Field YZDBYLRM.T:I
    1174: iconst_m1
    1175: if_icmpne     1209
    1178: aload         16
    1180: getfield      #122                // Field YZDBYLRM.x:[I
    1183: ifnonnull     1209
    1186: aload         16
    1188: iload_3
    1189: iload_1
    1190: iload         11
    1192: iload         12
    1194: iload         13
    1196: iload         14
    1198: iconst_m1
    1199: invokevirtual #94                 // Method YZDBYLRM.a:(IIIIIII)LZKARKDQW;
    1202: astore        19
    1204: iload         23
    1206: ifeq          1238
    1209: new           #35                 // class WBWOBAFW
    1212: dup
    1213: iload         8
    1215: iload_1
    1216: iload_3
    1217: iload         12
    1219: bipush        7
    1221: iload         13
    1223: iload         11
    1225: iload         14
    1227: aload         16
    1229: getfield      #62                 // Field YZDBYLRM.T:I
    1232: iconst_1
    1233: invokespecial #54                 // Method WBWOBAFW."<init>":(IIIIBIIIIZ)V
    1236: astore        19
    1238: aload_0
    1239: iload         17
    1241: iload         18
    1243: iload         15
    1245: iconst_1
    1246: aload         19
    1248: iconst_1
    1249: iload         9
    1251: iconst_0
    1252: bipush        110
    1254: iload_2
    1255: iload         7
    1257: invokevirtual #60                 // Method NYFUGYQS.a:(IBIILXHHRODPC;IIIBII)Z
    1260: pop
    1261: aload         16
    1263: getfield      #69                 // Field YZDBYLRM.F:Z
    1266: ifeq          1296
    1269: aload         5
    1271: aload         16
    1273: getfield      #68                 // Field YZDBYLRM.v:Z
    1276: getstatic     #75                 // Field p:I
    1279: aload         16
    1281: getfield      #157                // Field YZDBYLRM.i:I
    1284: aload         16
    1286: getfield      #109                // Field YZDBYLRM.z:I
    1289: iload         7
    1291: iload_2
    1292: iload_1
    1293: invokevirtual #59                 // Method FTPNODIB.a:(ZIIIIII)V
    1296: return
    1297: aload         16
    1299: getfield      #103                // Field YZDBYLRM.A:Z
    1302: ifeq          1394
    1305: iload_1
    1306: iconst_1
    1307: if_icmpne     1335
    1310: iload         14
    1312: istore        19
    1314: iload         13
    1316: istore        14
    1318: iload         12
    1320: istore        13
    1322: iload         11
    1324: istore        12
    1326: iload         19
    1328: istore        11
    1330: iload         23
    1332: ifeq          1394
    1335: iload_1
    1336: iconst_2
    1337: if_icmpne     1369
    1340: iload         14
    1342: istore        19
    1344: iload         12
    1346: istore        14
    1348: iload         19
    1350: istore        12
    1352: iload         13
    1354: istore        19
    1356: iload         11
    1358: istore        13
    1360: iload         19
    1362: istore        11
    1364: iload         23
    1366: ifeq          1394
    1369: iload_1
    1370: iconst_3
    1371: if_icmpne     1394
    1374: iload         14
    1376: istore        19
    1378: iload         11
    1380: istore        14
    1382: iload         12
    1384: istore        11
    1386: iload         13
    1388: istore        12
    1390: iload         19
    1392: istore        13
    1394: iload_3
    1395: iconst_4
    1396: if_icmpne     1501
    1399: aload         16
    1401: getfield      #62                 // Field YZDBYLRM.T:I
    1404: iconst_m1
    1405: if_icmpne     1439
    1408: aload         16
    1410: getfield      #122                // Field YZDBYLRM.x:[I
    1413: ifnonnull     1439
    1416: aload         16
    1418: iconst_4
    1419: iconst_0
    1420: iload         11
    1422: iload         12
    1424: iload         13
    1426: iload         14
    1428: iconst_m1
    1429: invokevirtual #94                 // Method YZDBYLRM.a:(IIIIIII)LZKARKDQW;
    1432: astore        19
    1434: iload         23
    1436: ifeq          1468
    1439: new           #35                 // class WBWOBAFW
    1442: dup
    1443: iload         8
    1445: iconst_0
    1446: iconst_4
    1447: iload         12
    1449: bipush        7
    1451: iload         13
    1453: iload         11
    1455: iload         14
    1457: aload         16
    1459: getfield      #62                 // Field YZDBYLRM.T:I
    1462: iconst_1
    1463: invokespecial #54                 // Method WBWOBAFW."<init>":(IIIIBIIIIZ)V
    1466: astore        19
    1468: aload_0
    1469: iload         17
    1471: iload_2
    1472: iload_1
    1473: sipush        512
    1476: imul
    1477: sipush        -460
    1480: iload         9
    1482: iconst_0
    1483: iload         15
    1485: aload         19
    1487: iload         7
    1489: iload         18
    1491: iconst_0
    1492: getstatic     #158                // Field D:[I
    1495: iload_1
    1496: iaload
    1497: invokevirtual #135                // Method NYFUGYQS.a:(IIIIIIILXHHRODPC;IBII)V
    1500: return
    1501: iload_3
    1502: iconst_5
    1503: if_icmpne     1659
    1506: bipush        16
    1508: istore        19
    1510: aload_0
    1511: iload         9
    1513: iload         7
    1515: iload_2
    1516: invokevirtual #155                // Method NYFUGYQS.c:(III)I
    1519: istore        20
    1521: iload         20
    1523: ifle          1543
    1526: iload         20
    1528: bipush        14
    1530: ishr
    1531: sipush        32767
    1534: iand
    1535: invokestatic  #113                // Method YZDBYLRM.a:(I)LYZDBYLRM;
    1538: getfield      #156                // Field YZDBYLRM.N:I
    1541: istore        19
    1543: aload         16
    1545: getfield      #62                 // Field YZDBYLRM.T:I
    1548: iconst_m1
    1549: if_icmpne     1583
    1552: aload         16
    1554: getfield      #122                // Field YZDBYLRM.x:[I
    1557: ifnonnull     1583
    1560: aload         16
    1562: iconst_4
    1563: iconst_0
    1564: iload         11
    1566: iload         12
    1568: iload         13
    1570: iload         14
    1572: iconst_m1
    1573: invokevirtual #94                 // Method YZDBYLRM.a:(IIIIIII)LZKARKDQW;
    1576: astore        21
    1578: iload         23
    1580: ifeq          1612
    1583: new           #35                 // class WBWOBAFW
    1586: dup
    1587: iload         8
    1589: iconst_0
    1590: iconst_4
    1591: iload         12
    1593: bipush        7
    1595: iload         13
    1597: iload         11
    1599: iload         14
    1601: aload         16
    1603: getfield      #62                 // Field YZDBYLRM.T:I
    1606: iconst_1
    1607: invokespecial #54                 // Method WBWOBAFW."<init>":(IIIIBIIIIZ)V
    1610: astore        21
    1612: aload_0
    1613: iload         17
    1615: iload_2
    1616: iload_1
    1617: sipush        512
    1620: imul
    1621: sipush        -460
    1624: iload         9
    1626: getstatic     #81                 // Field o:[I
    1629: iload_1
    1630: iaload
    1631: iload         19
    1633: imul
    1634: iload         15
    1636: aload         21
    1638: iload         7
    1640: iload         18
    1642: getstatic     #82                 // Field v:[I
    1645: iload_1
    1646: iaload
    1647: iload         19
    1649: imul
    1650: getstatic     #158                // Field D:[I
    1653: iload_1
    1654: iaload
    1655: invokevirtual #135                // Method NYFUGYQS.a:(IIIIIIILXHHRODPC;IBII)V
    1658: return
    1659: iload_3
    1660: bipush        6
    1662: if_icmpne     1761
    1665: aload         16
    1667: getfield      #62                 // Field YZDBYLRM.T:I
    1670: iconst_m1
    1671: if_icmpne     1705
    1674: aload         16
    1676: getfield      #122                // Field YZDBYLRM.x:[I
    1679: ifnonnull     1705
    1682: aload         16
    1684: iconst_4
    1685: iconst_0
    1686: iload         11
    1688: iload         12
    1690: iload         13
    1692: iload         14
    1694: iconst_m1
    1695: invokevirtual #94                 // Method YZDBYLRM.a:(IIIIIII)LZKARKDQW;
    1698: astore        19
    1700: iload         23
    1702: ifeq          1734
    1705: new           #35                 // class WBWOBAFW
    1708: dup
    1709: iload         8
    1711: iconst_0
    1712: iconst_4
    1713: iload         12
    1715: bipush        7
    1717: iload         13
    1719: iload         11
    1721: iload         14
    1723: aload         16
    1725: getfield      #62                 // Field YZDBYLRM.T:I
    1728: iconst_1
    1729: invokespecial #54                 // Method WBWOBAFW."<init>":(IIIIBIIIIZ)V
    1732: astore        19
    1734: aload_0
    1735: iload         17
    1737: iload_2
    1738: iload_1
    1739: sipush        -460
    1742: iload         9
    1744: iconst_0
    1745: iload         15
    1747: aload         19
    1749: iload         7
    1751: iload         18
    1753: iconst_0
    1754: sipush        256
    1757: invokevirtual #135                // Method NYFUGYQS.a:(IIIIIIILXHHRODPC;IBII)V
    1760: return
    1761: iload_3
    1762: bipush        7
    1764: if_icmpne     1863
    1767: aload         16
    1769: getfield      #62                 // Field YZDBYLRM.T:I
    1772: iconst_m1
    1773: if_icmpne     1807
    1776: aload         16
    1778: getfield      #122                // Field YZDBYLRM.x:[I
    1781: ifnonnull     1807
    1784: aload         16
    1786: iconst_4
    1787: iconst_0
    1788: iload         11
    1790: iload         12
    1792: iload         13
    1794: iload         14
    1796: iconst_m1
    1797: invokevirtual #94                 // Method YZDBYLRM.a:(IIIIIII)LZKARKDQW;
    1800: astore        19
    1802: iload         23
    1804: ifeq          1836
    1807: new           #35                 // class WBWOBAFW
    1810: dup
    1811: iload         8
    1813: iconst_0
    1814: iconst_4
    1815: iload         12
    1817: bipush        7
    1819: iload         13
    1821: iload         11
    1823: iload         14
    1825: aload         16
    1827: getfield      #62                 // Field YZDBYLRM.T:I
    1830: iconst_1
    1831: invokespecial #54                 // Method WBWOBAFW."<init>":(IIIIBIIIIZ)V
    1834: astore        19
    1836: aload_0
    1837: iload         17
    1839: iload_2
    1840: iload_1
    1841: sipush        -460
    1844: iload         9
    1846: iconst_0
    1847: iload         15
    1849: aload         19
    1851: iload         7
    1853: iload         18
    1855: iconst_0
    1856: sipush        512
    1859: invokevirtual #135                // Method NYFUGYQS.a:(IIIIIIILXHHRODPC;IBII)V
    1862: return
    1863: iload_3
    1864: bipush        8
    1866: if_icmpne     2104
    1869: aload         16
    1871: getfield      #62                 // Field YZDBYLRM.T:I
    1874: iconst_m1
    1875: if_icmpne     1909
    1878: aload         16
    1880: getfield      #122                // Field YZDBYLRM.x:[I
    1883: ifnonnull     1909
    1886: aload         16
    1888: iconst_4
    1889: iconst_0
    1890: iload         11
    1892: iload         12
    1894: iload         13
    1896: iload         14
    1898: iconst_m1
    1899: invokevirtual #94                 // Method YZDBYLRM.a:(IIIIIII)LZKARKDQW;
    1902: astore        19
    1904: iload         23
    1906: ifeq          1938
    1909: new           #35                 // class WBWOBAFW
    1912: dup
    1913: iload         8
    1915: iconst_0
    1916: iconst_4
    1917: iload         12
    1919: bipush        7
    1921: iload         13
    1923: iload         11
    1925: iload         14
    1927: aload         16
    1929: getfield      #62                 // Field YZDBYLRM.T:I
    1932: iconst_1
    1933: invokespecial #54                 // Method WBWOBAFW."<init>":(IIIIBIIIIZ)V
    1936: astore        19
    1938: aload_0
    1939: iload         17
    1941: iload_2
    1942: iload_1
    1943: sipush        -460
    1946: iload         9
    1948: iconst_0
    1949: iload         15
    1951: aload         19
    1953: iload         7
    1955: iload         18
    1957: iconst_0
    1958: sipush        768
    1961: invokevirtual #135                // Method NYFUGYQS.a:(IIIIIIILXHHRODPC;IBII)V
    1964: return
    1965: astore        11
    1967: new           #44                 // class java/lang/StringBuffer
    1970: dup
    1971: ldc           #29                 // String 89985,
    1973: invokespecial #55                 // Method java/lang/StringBuffer."<init>":(Ljava/lang/String;)V
    1976: aload_0
    1977: invokevirtual #64                 // Method java/lang/StringBuffer.append:(Ljava/lang/Object;)Ljava/lang/StringBuffer;
    1980: ldc           #16                 // String ,
    1982: invokevirtual #65                 // Method java/lang/StringBuffer.append:(Ljava/lang/String;)Ljava/lang/StringBuffer;
    1985: iload_1
    1986: invokevirtual #63                 // Method java/lang/StringBuffer.append:(I)Ljava/lang/StringBuffer;
    1989: ldc           #16                 // String ,
    1991: invokevirtual #65                 // Method java/lang/StringBuffer.append:(Ljava/lang/String;)Ljava/lang/StringBuffer;
    1994: iload_2
    1995: invokevirtual #63                 // Method java/lang/StringBuffer.append:(I)Ljava/lang/StringBuffer;
    1998: ldc           #16                 // String ,
    2000: invokevirtual #65                 // Method java/lang/StringBuffer.append:(Ljava/lang/String;)Ljava/lang/StringBuffer;
    2003: iload_3
    2004: invokevirtual #63                 // Method java/lang/StringBuffer.append:(I)Ljava/lang/StringBuffer;
    2007: ldc           #16                 // String ,
    2009: invokevirtual #65                 // Method java/lang/StringBuffer.append:(Ljava/lang/String;)Ljava/lang/StringBuffer;
    2012: iload         4
    2014: invokevirtual #63                 // Method java/lang/StringBuffer.append:(I)Ljava/lang/StringBuffer;
    2017: ldc           #16                 // String ,
    2019: invokevirtual #65                 // Method java/lang/StringBuffer.append:(Ljava/lang/String;)Ljava/lang/StringBuffer;
    2022: aload         5
    2024: invokevirtual #64                 // Method java/lang/StringBuffer.append:(Ljava/lang/Object;)Ljava/lang/StringBuffer;
    2027: ldc           #16                 // String ,
    2029: invokevirtual #65                 // Method java/lang/StringBuffer.append:(Ljava/lang/String;)Ljava/lang/StringBuffer;
    2032: aload         6
    2034: invokevirtual #64                 // Method java/lang/StringBuffer.append:(Ljava/lang/Object;)Ljava/lang/StringBuffer;
    2037: ldc           #16                 // String ,
    2039: invokevirtual #65                 // Method java/lang/StringBuffer.append:(Ljava/lang/String;)Ljava/lang/StringBuffer;
    2042: iload         7
    2044: invokevirtual #63                 // Method java/lang/StringBuffer.append:(I)Ljava/lang/StringBuffer;
    2047: ldc           #16                 // String ,
    2049: invokevirtual #65                 // Method java/lang/StringBuffer.append:(Ljava/lang/String;)Ljava/lang/StringBuffer;
    2052: iload         8
    2054: invokevirtual #63                 // Method java/lang/StringBuffer.append:(I)Ljava/lang/StringBuffer;
    2057: ldc           #16                 // String ,
    2059: invokevirtual #65                 // Method java/lang/StringBuffer.append:(Ljava/lang/String;)Ljava/lang/StringBuffer;
    2062: iload         9
    2064: invokevirtual #63                 // Method java/lang/StringBuffer.append:(I)Ljava/lang/StringBuffer;
    2067: ldc           #16                 // String ,
    2069: invokevirtual #65                 // Method java/lang/StringBuffer.append:(Ljava/lang/String;)Ljava/lang/StringBuffer;
    2072: iload         10
    2074: invokevirtual #63                 // Method java/lang/StringBuffer.append:(I)Ljava/lang/StringBuffer;
    2077: ldc           #16                 // String ,
    2079: invokevirtual #65                 // Method java/lang/StringBuffer.append:(Ljava/lang/String;)Ljava/lang/StringBuffer;
    2082: aload         11
    2084: invokevirtual #149                // Method java/lang/Throwable.toString:()Ljava/lang/String;
    2087: invokevirtual #65                 // Method java/lang/StringBuffer.append:(Ljava/lang/String;)Ljava/lang/StringBuffer;
    2090: invokevirtual #148                // Method java/lang/StringBuffer.toString:()Ljava/lang/String;
    2093: invokestatic  #132                // Method sign/signlink.reporterror:(Ljava/lang/String;)V
    2096: new           #43                 // class java/lang/RuntimeException
    2099: dup
    2100: invokespecial #53                 // Method java/lang/RuntimeException."<init>":()V
    2103: athrow
    2104: return
    Exception table:
       from    to  target type
           5  1965  1965   Class java/lang/RuntimeException

  public static final boolean a(int, byte[], int, int);
    Code:
       0: getstatic     #414                // Field client.Jj:I
       3: istore        17
       5: iload_3
       6: bipush        6
       8: if_icmplt     17
      11: iload_3
      12: bipush        6
      14: if_icmple     25
      17: new           #41                 // class java/lang/NullPointerException
      20: dup
      21: invokespecial #51                 // Method java/lang/NullPointerException."<init>":()V
      24: athrow
      25: iconst_1
      26: istore        4
      28: new           #39                 // class MBMGIXGO
      31: dup
      32: aload_1
      33: sipush        891
      36: invokespecial #56                 // Method MBMGIXGO."<init>":([BI)V
      39: astore        5
      41: iconst_m1
      42: istore        6
      44: aload         5
      46: invokevirtual #99                 // Method MBMGIXGO.k:()I
      49: istore        7
      51: iload         7
      53: ifeq          240
      56: iload         6
      58: iload         7
      60: iadd
      61: istore        6
      63: iconst_0
      64: istore        8
      66: iconst_0
      67: istore        9
      69: iload         9
      71: ifeq          97
      74: aload         5
      76: invokevirtual #99                 // Method MBMGIXGO.k:()I
      79: istore        10
      81: iload         10
      83: ifeq          235
      86: aload         5
      88: invokevirtual #92                 // Method MBMGIXGO.c:()I
      91: pop
      92: iload         17
      94: ifeq          69
      97: aload         5
      99: invokevirtual #99                 // Method MBMGIXGO.k:()I
     102: istore        10
     104: iload         10
     106: ifeq          235
     109: iload         8
     111: iload         10
     113: iconst_1
     114: isub
     115: iadd
     116: istore        8
     118: iload         8
     120: bipush        63
     122: iand
     123: istore        11
     125: iload         8
     127: bipush        6
     129: ishr
     130: bipush        63
     132: iand
     133: istore        12
     135: aload         5
     137: invokevirtual #92                 // Method MBMGIXGO.c:()I
     140: iconst_2
     141: ishr
     142: istore        13
     144: iload         12
     146: iload_0
     147: iadd
     148: istore        14
     150: iload         11
     152: iload_2
     153: iadd
     154: istore        15
     156: iload         14
     158: ifle          69
     161: iload         15
     163: ifle          69
     166: iload         14
     168: bipush        103
     170: if_icmpge     69
     173: iload         15
     175: bipush        103
     177: if_icmpge     69
     180: iload         6
     182: invokestatic  #113                // Method YZDBYLRM.a:(I)LYZDBYLRM;
     185: astore        16
     187: iload         13
     189: bipush        22
     191: if_icmpne     216
     194: getstatic     #116                // Field C:Z
     197: ifeq          216
     200: aload         16
     202: getfield      #57                 // Field YZDBYLRM.Q:Z
     205: ifne          216
     208: aload         16
     210: getfield      #91                 // Field YZDBYLRM.a:Z
     213: ifeq          230
     216: iload         4
     218: aload         16
     220: iconst_1
     221: invokevirtual #74                 // Method YZDBYLRM.a:(Z)Z
     224: iand
     225: istore        4
     227: iconst_1
     228: istore        9
     230: iload         17
     232: ifeq          69
     235: iload         17
     237: ifeq          44
     240: iload         4
     242: ireturn
     243: astore        4
     245: new           #44                 // class java/lang/StringBuffer
     248: dup
     249: ldc           #17                 // String 14134,
     251: invokespecial #55                 // Method java/lang/StringBuffer."<init>":(Ljava/lang/String;)V
     254: iload_0
     255: invokevirtual #63                 // Method java/lang/StringBuffer.append:(I)Ljava/lang/StringBuffer;
     258: ldc           #16                 // String ,
     260: invokevirtual #65                 // Method java/lang/StringBuffer.append:(Ljava/lang/String;)Ljava/lang/StringBuffer;
     263: aload_1
     264: invokevirtual #64                 // Method java/lang/StringBuffer.append:(Ljava/lang/Object;)Ljava/lang/StringBuffer;
     267: ldc           #16                 // String ,
     269: invokevirtual #65                 // Method java/lang/StringBuffer.append:(Ljava/lang/String;)Ljava/lang/StringBuffer;
     272: iload_2
     273: invokevirtual #63                 // Method java/lang/StringBuffer.append:(I)Ljava/lang/StringBuffer;
     276: ldc           #16                 // String ,
     278: invokevirtual #65                 // Method java/lang/StringBuffer.append:(Ljava/lang/String;)Ljava/lang/StringBuffer;
     281: iload_3
     282: invokevirtual #63                 // Method java/lang/StringBuffer.append:(I)Ljava/lang/StringBuffer;
     285: ldc           #16                 // String ,
     287: invokevirtual #65                 // Method java/lang/StringBuffer.append:(Ljava/lang/String;)Ljava/lang/StringBuffer;
     290: aload         4
     292: invokevirtual #149                // Method java/lang/Throwable.toString:()Ljava/lang/String;
     295: invokevirtual #65                 // Method java/lang/StringBuffer.append:(Ljava/lang/String;)Ljava/lang/StringBuffer;
     298: invokevirtual #148                // Method java/lang/StringBuffer.toString:()Ljava/lang/String;
     301: invokestatic  #132                // Method sign/signlink.reporterror:(Ljava/lang/String;)V
     304: new           #43                 // class java/lang/RuntimeException
     307: dup
     308: invokespecial #53                 // Method java/lang/RuntimeException."<init>":()V
     311: athrow
    Exception table:
       from    to  target type
           5   243   243   Class java/lang/RuntimeException

  public final void a(int, FTPNODIB[], int, int, NYFUGYQS, byte[]);
    Code:
       0: getstatic     #414                // Field client.Jj:I
       3: istore        22
       5: iload         4
       7: bipush        7
       9: if_icmplt     19
      12: iload         4
      14: bipush        7
      16: if_icmple     20
      19: return
      20: new           #39                 // class MBMGIXGO
      23: dup
      24: aload         6
      26: sipush        891
      29: invokespecial #56                 // Method MBMGIXGO."<init>":([BI)V
      32: astore        7
      34: iconst_m1
      35: istore        8
      37: aload         7
      39: invokevirtual #99                 // Method MBMGIXGO.k:()I
      42: istore        9
      44: iload         9
      46: ifeq          229
      49: iload         8
      51: iload         9
      53: iadd
      54: istore        8
      56: iconst_0
      57: istore        10
      59: aload         7
      61: invokevirtual #99                 // Method MBMGIXGO.k:()I
      64: istore        11
      66: iload         11
      68: ifeq          224
      71: iload         10
      73: iload         11
      75: iconst_1
      76: isub
      77: iadd
      78: istore        10
      80: iload         10
      82: bipush        63
      84: iand
      85: istore        12
      87: iload         10
      89: bipush        6
      91: ishr
      92: bipush        63
      94: iand
      95: istore        13
      97: iload         10
      99: bipush        12
     101: ishr
     102: istore        14
     104: aload         7
     106: invokevirtual #92                 // Method MBMGIXGO.c:()I
     109: istore        15
     111: iload         15
     113: iconst_2
     114: ishr
     115: istore        16
     117: iload         15
     119: iconst_3
     120: iand
     121: istore        17
     123: iload         13
     125: iload_1
     126: iadd
     127: istore        18
     129: iload         12
     131: iload_3
     132: iadd
     133: istore        19
     135: iload         18
     137: ifle          59
     140: iload         19
     142: ifle          59
     145: iload         18
     147: bipush        103
     149: if_icmpge     59
     152: iload         19
     154: bipush        103
     156: if_icmpge     59
     159: iload         14
     161: istore        20
     163: aload_0
     164: getfield      #117                // Field A:[[[B
     167: iconst_1
     168: aaload
     169: iload         18
     171: aaload
     172: iload         19
     174: baload
     175: iconst_2
     176: iand
     177: iconst_2
     178: if_icmpne     184
     181: iinc          20, -1
     184: aconst_null
     185: astore        21
     187: iload         20
     189: iflt          198
     192: aload_2
     193: iload         20
     195: aaload
     196: astore        21
     198: aload_0
     199: iload         19
     201: aload         5
     203: aload         21
     205: iload         16
     207: iload         14
     209: iload         18
     211: iload         8
     213: iconst_0
     214: iload         17
     216: invokespecial #58                 // Method a:(ILNYFUGYQS;LFTPNODIB;IIIIZI)V
     219: iload         22
     221: ifeq          59
     224: iload         22
     226: ifeq          37
     229: return
     230: astore        7
     232: new           #44                 // class java/lang/StringBuffer
     235: dup
     236: ldc           #20                 // String 18363,
     238: invokespecial #55                 // Method java/lang/StringBuffer."<init>":(Ljava/lang/String;)V
     241: iload_1
     242: invokevirtual #63                 // Method java/lang/StringBuffer.append:(I)Ljava/lang/StringBuffer;
     245: ldc           #16                 // String ,
     247: invokevirtual #65                 // Method java/lang/StringBuffer.append:(Ljava/lang/String;)Ljava/lang/StringBuffer;
     250: aload_2
     251: invokevirtual #64                 // Method java/lang/StringBuffer.append:(Ljava/lang/Object;)Ljava/lang/StringBuffer;
     254: ldc           #16                 // String ,
     256: invokevirtual #65                 // Method java/lang/StringBuffer.append:(Ljava/lang/String;)Ljava/lang/StringBuffer;
     259: iload_3
     260: invokevirtual #63                 // Method java/lang/StringBuffer.append:(I)Ljava/lang/StringBuffer;
     263: ldc           #16                 // String ,
     265: invokevirtual #65                 // Method java/lang/StringBuffer.append:(Ljava/lang/String;)Ljava/lang/StringBuffer;
     268: iload         4
     270: invokevirtual #63                 // Method java/lang/StringBuffer.append:(I)Ljava/lang/StringBuffer;
     273: ldc           #16                 // String ,
     275: invokevirtual #65                 // Method java/lang/StringBuffer.append:(Ljava/lang/String;)Ljava/lang/StringBuffer;
     278: aload         5
     280: invokevirtual #64                 // Method java/lang/StringBuffer.append:(Ljava/lang/Object;)Ljava/lang/StringBuffer;
     283: ldc           #16                 // String ,
     285: invokevirtual #65                 // Method java/lang/StringBuffer.append:(Ljava/lang/String;)Ljava/lang/StringBuffer;
     288: aload         6
     290: invokevirtual #64                 // Method java/lang/StringBuffer.append:(Ljava/lang/Object;)Ljava/lang/StringBuffer;
     293: ldc           #16                 // String ,
     295: invokevirtual #65                 // Method java/lang/StringBuffer.append:(Ljava/lang/String;)Ljava/lang/StringBuffer;
     298: aload         7
     300: invokevirtual #149                // Method java/lang/Throwable.toString:()Ljava/lang/String;
     303: invokevirtual #65                 // Method java/lang/StringBuffer.append:(Ljava/lang/String;)Ljava/lang/StringBuffer;
     306: invokevirtual #148                // Method java/lang/StringBuffer.toString:()Ljava/lang/String;
     309: invokestatic  #132                // Method sign/signlink.reporterror:(Ljava/lang/String;)V
     312: new           #43                 // class java/lang/RuntimeException
     315: dup
     316: invokespecial #53                 // Method java/lang/RuntimeException."<init>":()V
     319: athrow
    Exception table:
       from    to  target type
           5   229   230   Class java/lang/RuntimeException

  static {};
    Code:
       0: invokestatic  #131                // Method java/lang/Math.random:()D
       3: ldc2_w        #165                // double 17.0d
       6: dmul
       7: d2i
       8: bipush        8
      10: isub
      11: putstatic     #104                // Field a:I
      14: invokestatic  #131                // Method java/lang/Math.random:()D
      17: ldc2_w        #167                // double 33.0d
      20: dmul
      21: d2i
      22: bipush        16
      24: isub
      25: putstatic     #110                // Field k:I
      28: iconst_4
      29: newarray       int
      31: dup
      32: iconst_0
      33: iconst_1
      34: iastore
      35: dup
      36: iconst_2
      37: iconst_m1
      38: iastore
      39: putstatic     #81                 // Field o:[I
      42: sipush        323
      45: putstatic     #75                 // Field p:I
      48: iconst_4
      49: newarray       int
      51: dup
      52: iconst_0
      53: bipush        16
      55: iastore
      56: dup
      57: iconst_1
      58: bipush        32
      60: iastore
      61: dup
      62: iconst_2
      63: bipush        64
      65: iastore
      66: dup
      67: iconst_3
      68: sipush        128
      71: iastore
      72: putstatic     #159                // Field r:[I
      75: iconst_4
      76: newarray       int
      78: dup
      79: iconst_1
      80: iconst_m1
      81: iastore
      82: dup
      83: iconst_3
      84: iconst_1
      85: iastore
      86: putstatic     #82                 // Field v:[I
      89: bipush        99
      91: putstatic     #120                // Field w:I
      94: iconst_1
      95: putstatic     #116                // Field C:Z
      98: iconst_4
      99: newarray       int
     101: dup
     102: iconst_0
     103: iconst_1
     104: iastore
     105: dup
     106: iconst_1
     107: iconst_2
     108: iastore
     109: dup
     110: iconst_2
     111: iconst_4
     112: iastore
     113: dup
     114: iconst_3
     115: bipush        8
     117: iastore
     118: putstatic     #158                // Field D:[I
     121: sipush        -388
     124: putstatic     #151                // Field E:I
     127: return
}
