public class GHOWLKWN extends VJKFYAWG implements java.lang.Runnable {
  private int b;

  private LHGXPZPG c;

  private int d;

  public java.lang.String e;

  private int f;

  private long g;

  private boolean h;

  private int[] i;

  private java.util.zip.CRC32 j;

  private byte[] k;

  private int l;

  public int m;

  private byte[][] n;

  private client o;

  private LHGXPZPG p;

  private static int q;

  private int r;

  private int s;

  private int[] t;

  public int u;

  private int[] v;

  private int w;

  private int x;

  private boolean y;

  private java.io.OutputStream z;

  private boolean A;

  private int[] B;

  private boolean C;

  private LHGXPZPG D;

  private byte[] E;

  private int[] F;

  private BISVHPUN G;

  private java.io.InputStream H;

  private java.net.Socket I;

  private int[][] J;

  private int[][] K;

  private int L;

  private int M;

  private LHGXPZPG N;

  private PHKHJKBS O;

  private LHGXPZPG P;

  private int[] Q;

  private byte[] R;

  private int S;

  private final boolean a(int, byte, int, byte[]);
    Code:
       0: aload         4
       2: ifnull        12
       5: aload         4
       7: arraylength
       8: iconst_2
       9: if_icmpge     14
      12: iconst_0
      13: ireturn
      14: aload         4
      16: arraylength
      17: iconst_2
      18: isub
      19: istore        5
      21: aload         4
      23: iload         5
      25: baload
      26: sipush        255
      29: iand
      30: bipush        8
      32: ishl
      33: aload         4
      35: iload         5
      37: iconst_1
      38: iadd
      39: baload
      40: sipush        255
      43: iand
      44: iadd
      45: istore        6
      47: iload_2
      48: iconst_3
      49: if_icmpeq     68
      52: aload_0
      53: aload_0
      54: getfield      #84                 // Field h:Z
      57: ifeq          64
      60: iconst_0
      61: goto          65
      64: iconst_1
      65: putfield      #84                 // Field h:Z
      68: aload_0
      69: getfield      #97                 // Field j:Ljava/util/zip/CRC32;
      72: invokevirtual #161                // Method java/util/zip/CRC32.reset:()V
      75: aload_0
      76: getfield      #97                 // Field j:Ljava/util/zip/CRC32;
      79: aload         4
      81: iconst_0
      82: iload         5
      84: invokevirtual #180                // Method java/util/zip/CRC32.update:([BII)V
      87: aload_0
      88: getfield      #97                 // Field j:Ljava/util/zip/CRC32;
      91: invokevirtual #108                // Method java/util/zip/CRC32.getValue:()J
      94: l2i
      95: istore        7
      97: iload         6
      99: iload_1
     100: if_icmpeq     105
     103: iconst_0
     104: ireturn
     105: iload         7
     107: iload_3
     108: if_icmpeq     113
     111: iconst_0
     112: ireturn
     113: iconst_1
     114: ireturn
     115: astore        5
     117: new           #61                 // class java/lang/StringBuffer
     120: dup
     121: ldc           #12                 // String 46053,
     123: invokespecial #81                 // Method java/lang/StringBuffer."<init>":(Ljava/lang/String;)V
     126: iload_1
     127: invokevirtual #88                 // Method java/lang/StringBuffer.append:(I)Ljava/lang/StringBuffer;
     130: ldc           #6                  // String ,
     132: invokevirtual #90                 // Method java/lang/StringBuffer.append:(Ljava/lang/String;)Ljava/lang/StringBuffer;
     135: iload_2
     136: invokevirtual #88                 // Method java/lang/StringBuffer.append:(I)Ljava/lang/StringBuffer;
     139: ldc           #6                  // String ,
     141: invokevirtual #90                 // Method java/lang/StringBuffer.append:(Ljava/lang/String;)Ljava/lang/StringBuffer;
     144: iload_3
     145: invokevirtual #88                 // Method java/lang/StringBuffer.append:(I)Ljava/lang/StringBuffer;
     148: ldc           #6                  // String ,
     150: invokevirtual #90                 // Method java/lang/StringBuffer.append:(Ljava/lang/String;)Ljava/lang/StringBuffer;
     153: aload         4
     155: invokevirtual #89                 // Method java/lang/StringBuffer.append:(Ljava/lang/Object;)Ljava/lang/StringBuffer;
     158: ldc           #6                  // String ,
     160: invokevirtual #90                 // Method java/lang/StringBuffer.append:(Ljava/lang/String;)Ljava/lang/StringBuffer;
     163: aload         5
     165: invokevirtual #176                // Method java/lang/Throwable.toString:()Ljava/lang/String;
     168: invokevirtual #90                 // Method java/lang/StringBuffer.append:(Ljava/lang/String;)Ljava/lang/StringBuffer;
     171: invokevirtual #175                // Method java/lang/StringBuffer.toString:()Ljava/lang/String;
     174: invokestatic  #159                // Method sign/signlink.reporterror:(Ljava/lang/String;)V
     177: new           #59                 // class java/lang/RuntimeException
     180: dup
     181: invokespecial #73                 // Method java/lang/RuntimeException."<init>":()V
     184: athrow
    Exception table:
       from    to  target type
           0   115   115   Class java/lang/RuntimeException

  private final void b(int);
    Code:
       0: getstatic     #486                // Field client.Jj:I
       3: istore        10
       5: iload_1
       6: iflt          25
       9: aload_0
      10: aload_0
      11: getfield      #84                 // Field h:Z
      14: ifeq          21
      17: iconst_0
      18: goto          22
      21: iconst_1
      22: putfield      #84                 // Field h:Z
      25: aload_0
      26: getfield      #143                // Field H:Ljava/io/InputStream;
      29: invokevirtual #92                 // Method java/io/InputStream.available:()I
      32: istore_2
      33: aload_0
      34: getfield      #138                // Field s:I
      37: ifne          447
      40: iload_2
      41: bipush        6
      43: if_icmplt     447
      46: aload_0
      47: iconst_1
      48: putfield      #100                // Field C:Z
      51: iconst_0
      52: istore_3
      53: iload         10
      55: ifeq          77
      58: iload_3
      59: aload_0
      60: getfield      #143                // Field H:Ljava/io/InputStream;
      63: aload_0
      64: getfield      #126                // Field k:[B
      67: iload_3
      68: bipush        6
      70: iload_3
      71: isub
      72: invokevirtual #157                // Method java/io/InputStream.read:([BII)I
      75: iadd
      76: istore_3
      77: iload_3
      78: bipush        6
      80: if_icmplt     58
      83: aload_0
      84: getfield      #126                // Field k:[B
      87: iconst_0
      88: baload
      89: sipush        255
      92: iand
      93: istore        4
      95: aload_0
      96: getfield      #126                // Field k:[B
      99: iconst_1
     100: baload
     101: sipush        255
     104: iand
     105: bipush        8
     107: ishl
     108: aload_0
     109: getfield      #126                // Field k:[B
     112: iconst_2
     113: baload
     114: sipush        255
     117: iand
     118: iadd
     119: istore        5
     121: aload_0
     122: getfield      #126                // Field k:[B
     125: iconst_3
     126: baload
     127: sipush        255
     130: iand
     131: bipush        8
     133: ishl
     134: aload_0
     135: getfield      #126                // Field k:[B
     138: iconst_4
     139: baload
     140: sipush        255
     143: iand
     144: iadd
     145: istore        6
     147: aload_0
     148: getfield      #126                // Field k:[B
     151: iconst_5
     152: baload
     153: sipush        255
     156: iand
     157: istore        7
     159: aload_0
     160: aconst_null
     161: putfield      #134                // Field O:LPHKHJKBS;
     164: aload_0
     165: getfield      #136                // Field c:LLHGXPZPG;
     168: invokevirtual #171                // Method LHGXPZPG.b:()LPKVMXVTO;
     171: checkcast     #68                 // class PHKHJKBS
     174: astore        8
     176: iload         10
     178: ifeq          233
     181: aload         8
     183: getfield      #112                // Field PHKHJKBS.i:I
     186: iload         4
     188: if_icmpne     207
     191: aload         8
     193: getfield      #113                // Field PHKHJKBS.k:I
     196: iload         5
     198: if_icmpne     207
     201: aload_0
     202: aload         8
     204: putfield      #134                // Field O:LPHKHJKBS;
     207: aload_0
     208: getfield      #134                // Field O:LPHKHJKBS;
     211: ifnull        220
     214: aload         8
     216: iconst_0
     217: putfield      #101                // Field PHKHJKBS.m:I
     220: aload_0
     221: getfield      #136                // Field c:LLHGXPZPG;
     224: iconst_0
     225: invokevirtual #128                // Method LHGXPZPG.a:(Z)LPKVMXVTO;
     228: checkcast     #68                 // class PHKHJKBS
     231: astore        8
     233: aload         8
     235: ifnonnull     181
     238: aload_0
     239: getfield      #134                // Field O:LPHKHJKBS;
     242: ifnull        401
     245: aload_0
     246: iconst_0
     247: putfield      #174                // Field S:I
     250: iload         6
     252: ifne          350
     255: new           #61                 // class java/lang/StringBuffer
     258: dup
     259: ldc           #24                 // String Rej:
     261: invokespecial #81                 // Method java/lang/StringBuffer."<init>":(Ljava/lang/String;)V
     264: iload         4
     266: invokevirtual #88                 // Method java/lang/StringBuffer.append:(I)Ljava/lang/StringBuffer;
     269: ldc           #5                  // String ,
     271: invokevirtual #90                 // Method java/lang/StringBuffer.append:(Ljava/lang/String;)Ljava/lang/StringBuffer;
     274: iload         5
     276: invokevirtual #88                 // Method java/lang/StringBuffer.append:(I)Ljava/lang/StringBuffer;
     279: invokevirtual #175                // Method java/lang/StringBuffer.toString:()Ljava/lang/String;
     282: invokestatic  #159                // Method sign/signlink.reporterror:(Ljava/lang/String;)V
     285: aload_0
     286: getfield      #134                // Field O:LPHKHJKBS;
     289: aconst_null
     290: putfield      #93                 // Field PHKHJKBS.j:[B
     293: aload_0
     294: getfield      #134                // Field O:LPHKHJKBS;
     297: getfield      #181                // Field PHKHJKBS.l:Z
     300: ifeq          333
     303: aload_0
     304: getfield      #132                // Field D:LLHGXPZPG;
     307: astore        9
     309: aload         9
     311: monitorenter
     312: aload_0
     313: getfield      #132                // Field D:LLHGXPZPG;
     316: aload_0
     317: getfield      #134                // Field O:LPHKHJKBS;
     320: invokevirtual #86                 // Method LHGXPZPG.a:(LPKVMXVTO;)V
     323: aload         9
     325: monitorexit
     326: goto          340
     329: aload         9
     331: monitorexit
     332: athrow
     333: aload_0
     334: getfield      #134                // Field O:LPHKHJKBS;
     337: invokevirtual #177                // Method PKVMXVTO.a:()V
     340: aload_0
     341: aconst_null
     342: putfield      #134                // Field O:LPHKHJKBS;
     345: iload         10
     347: ifeq          401
     350: aload_0
     351: getfield      #134                // Field O:LPHKHJKBS;
     354: getfield      #93                 // Field PHKHJKBS.j:[B
     357: ifnonnull     376
     360: iload         7
     362: ifne          376
     365: aload_0
     366: getfield      #134                // Field O:LPHKHJKBS;
     369: iload         6
     371: newarray       byte
     373: putfield      #93                 // Field PHKHJKBS.j:[B
     376: aload_0
     377: getfield      #134                // Field O:LPHKHJKBS;
     380: getfield      #93                 // Field PHKHJKBS.j:[B
     383: ifnonnull     401
     386: iload         7
     388: ifeq          401
     391: new           #53                 // class java/io/IOException
     394: dup
     395: ldc           #36                 // String missing start of file
     397: invokespecial #79                 // Method java/io/IOException."<init>":(Ljava/lang/String;)V
     400: athrow
     401: aload_0
     402: iload         7
     404: sipush        500
     407: imul
     408: putfield      #137                // Field r:I
     411: aload_0
     412: sipush        500
     415: putfield      #138                // Field s:I
     418: aload_0
     419: getfield      #138                // Field s:I
     422: iload         6
     424: iload         7
     426: sipush        500
     429: imul
     430: isub
     431: if_icmple     447
     434: aload_0
     435: iload         6
     437: iload         7
     439: sipush        500
     442: imul
     443: isub
     444: putfield      #138                // Field s:I
     447: aload_0
     448: getfield      #138                // Field s:I
     451: ifle          767
     454: iload_2
     455: aload_0
     456: getfield      #138                // Field s:I
     459: if_icmplt     767
     462: aload_0
     463: iconst_1
     464: putfield      #100                // Field C:Z
     467: aload_0
     468: getfield      #126                // Field k:[B
     471: astore_3
     472: iconst_0
     473: istore        4
     475: aload_0
     476: getfield      #134                // Field O:LPHKHJKBS;
     479: ifnull        496
     482: aload_0
     483: getfield      #134                // Field O:LPHKHJKBS;
     486: getfield      #93                 // Field PHKHJKBS.j:[B
     489: astore_3
     490: aload_0
     491: getfield      #137                // Field r:I
     494: istore        4
     496: iconst_0
     497: istore        5
     499: iload         10
     501: ifeq          529
     504: iload         5
     506: aload_0
     507: getfield      #143                // Field H:Ljava/io/InputStream;
     510: aload_3
     511: iload         5
     513: iload         4
     515: iadd
     516: aload_0
     517: getfield      #138                // Field s:I
     520: iload         5
     522: isub
     523: invokevirtual #157                // Method java/io/InputStream.read:([BII)I
     526: iadd
     527: istore        5
     529: iload         5
     531: aload_0
     532: getfield      #138                // Field s:I
     535: if_icmplt     504
     538: aload_0
     539: getfield      #138                // Field s:I
     542: aload_0
     543: getfield      #137                // Field r:I
     546: iadd
     547: aload_3
     548: arraylength
     549: if_icmplt     688
     552: aload_0
     553: getfield      #134                // Field O:LPHKHJKBS;
     556: ifnull        688
     559: aload_0
     560: getfield      #119                // Field o:Lclient;
     563: getfield      #94                 // Field client.Ad:[LIGSLDTHC;
     566: iconst_0
     567: aaload
     568: ifnull        603
     571: aload_0
     572: getfield      #119                // Field o:Lclient;
     575: getfield      #94                 // Field client.Ad:[LIGSLDTHC;
     578: aload_0
     579: getfield      #134                // Field O:LPHKHJKBS;
     582: getfield      #112                // Field PHKHJKBS.i:I
     585: iconst_1
     586: iadd
     587: aaload
     588: aload_3
     589: arraylength
     590: aload_3
     591: iconst_2
     592: aload_0
     593: getfield      #134                // Field O:LPHKHJKBS;
     596: getfield      #113                // Field PHKHJKBS.k:I
     599: invokevirtual #167                // Method IGSLDTHC.a:(I[BBI)Z
     602: pop
     603: aload_0
     604: getfield      #134                // Field O:LPHKHJKBS;
     607: getfield      #181                // Field PHKHJKBS.l:Z
     610: ifne          641
     613: aload_0
     614: getfield      #134                // Field O:LPHKHJKBS;
     617: getfield      #112                // Field PHKHJKBS.i:I
     620: iconst_3
     621: if_icmpne     641
     624: aload_0
     625: getfield      #134                // Field O:LPHKHJKBS;
     628: iconst_1
     629: putfield      #181                // Field PHKHJKBS.l:Z
     632: aload_0
     633: getfield      #134                // Field O:LPHKHJKBS;
     636: bipush        93
     638: putfield      #112                // Field PHKHJKBS.i:I
     641: aload_0
     642: getfield      #134                // Field O:LPHKHJKBS;
     645: getfield      #181                // Field PHKHJKBS.l:Z
     648: ifeq          681
     651: aload_0
     652: getfield      #132                // Field D:LLHGXPZPG;
     655: astore        6
     657: aload         6
     659: monitorenter
     660: aload_0
     661: getfield      #132                // Field D:LLHGXPZPG;
     664: aload_0
     665: getfield      #134                // Field O:LPHKHJKBS;
     668: invokevirtual #86                 // Method LHGXPZPG.a:(LPKVMXVTO;)V
     671: aload         6
     673: monitorexit
     674: goto          688
     677: aload         6
     679: monitorexit
     680: athrow
     681: aload_0
     682: getfield      #134                // Field O:LPHKHJKBS;
     685: invokevirtual #177                // Method PKVMXVTO.a:()V
     688: aload_0
     689: iconst_0
     690: putfield      #138                // Field s:I
     693: return
     694: astore_2
     695: aload_0
     696: getfield      #145                // Field I:Ljava/net/Socket;
     699: invokevirtual #96                 // Method java/net/Socket.close:()V
     702: goto          706
     705: pop
     706: aload_0
     707: aconst_null
     708: putfield      #145                // Field I:Ljava/net/Socket;
     711: aload_0
     712: aconst_null
     713: putfield      #143                // Field H:Ljava/io/InputStream;
     716: aload_0
     717: aconst_null
     718: putfield      #144                // Field z:Ljava/io/OutputStream;
     721: aload_0
     722: iconst_0
     723: putfield      #138                // Field s:I
     726: return
     727: astore_2
     728: new           #61                 // class java/lang/StringBuffer
     731: dup
     732: ldc           #18                 // String 81261,
     734: invokespecial #81                 // Method java/lang/StringBuffer."<init>":(Ljava/lang/String;)V
     737: iload_1
     738: invokevirtual #88                 // Method java/lang/StringBuffer.append:(I)Ljava/lang/StringBuffer;
     741: ldc           #6                  // String ,
     743: invokevirtual #90                 // Method java/lang/StringBuffer.append:(Ljava/lang/String;)Ljava/lang/StringBuffer;
     746: aload_2
     747: invokevirtual #176                // Method java/lang/Throwable.toString:()Ljava/lang/String;
     750: invokevirtual #90                 // Method java/lang/StringBuffer.append:(Ljava/lang/String;)Ljava/lang/StringBuffer;
     753: invokevirtual #175                // Method java/lang/StringBuffer.toString:()Ljava/lang/String;
     756: invokestatic  #159                // Method sign/signlink.reporterror:(Ljava/lang/String;)V
     759: new           #59                 // class java/lang/RuntimeException
     762: dup
     763: invokespecial #73                 // Method java/lang/RuntimeException."<init>":()V
     766: athrow
     767: return
    Exception table:
       from    to  target type
         312   323   329   any
         660   671   677   any
          25   693   694   Class java/io/IOException
         695   702   705   Class java/lang/Exception
           5   727   727   Class java/lang/RuntimeException

  public final void a(XTGLDHGX, client);
    Code:
       0: getstatic     #486                // Field client.Jj:I
       3: istore        14
       5: iconst_4
       6: anewarray     #60                 // class java/lang/String
       9: dup
      10: iconst_0
      11: ldc           #39                 // String model_version
      13: aastore
      14: dup
      15: iconst_1
      16: ldc           #27                 // String anim_version
      18: aastore
      19: dup
      20: iconst_2
      21: ldc           #35                 // String midi_version
      23: aastore
      24: dup
      25: iconst_3
      26: ldc           #32                 // String map_version
      28: aastore
      29: astore_3
      30: iconst_0
      31: istore        4
      33: iload         14
      35: ifeq          128
      38: aload_1
      39: aload_3
      40: iload         4
      42: aaload
      43: aconst_null
      44: invokevirtual #110                // Method XTGLDHGX.a:(Ljava/lang/String;[B)[B
      47: astore        5
      49: aload         5
      51: arraylength
      52: iconst_2
      53: idiv
      54: istore        6
      56: new           #51                 // class MBMGIXGO
      59: dup
      60: aload         5
      62: sipush        891
      65: invokespecial #83                 // Method MBMGIXGO."<init>":([BI)V
      68: astore        7
      70: aload_0
      71: getfield      #182                // Field J:[[I
      74: iload         4
      76: iload         6
      78: newarray       int
      80: aastore
      81: aload_0
      82: getfield      #148                // Field n:[[B
      85: iload         4
      87: iload         6
      89: newarray       byte
      91: aastore
      92: iconst_0
      93: istore        8
      95: iload         14
      97: ifeq          118
     100: aload_0
     101: getfield      #182                // Field J:[[I
     104: iload         4
     106: aaload
     107: iload         8
     109: aload         7
     111: invokevirtual #103                // Method MBMGIXGO.e:()I
     114: iastore
     115: iinc          8, 1
     118: iload         8
     120: iload         6
     122: if_icmplt     100
     125: iinc          4, 1
     128: iload         4
     130: iconst_4
     131: if_icmplt     38
     134: iconst_4
     135: anewarray     #60                 // class java/lang/String
     138: dup
     139: iconst_0
     140: ldc           #37                 // String model_crc
     142: aastore
     143: dup
     144: iconst_1
     145: ldc           #25                 // String anim_crc
     147: aastore
     148: dup
     149: iconst_2
     150: ldc           #33                 // String midi_crc
     152: aastore
     153: dup
     154: iconst_3
     155: ldc           #30                 // String map_crc
     157: aastore
     158: astore        5
     160: iconst_0
     161: istore        6
     163: iload         14
     165: ifeq          248
     168: aload_1
     169: aload         5
     171: iload         6
     173: aaload
     174: aconst_null
     175: invokevirtual #110                // Method XTGLDHGX.a:(Ljava/lang/String;[B)[B
     178: astore        7
     180: aload         7
     182: arraylength
     183: iconst_4
     184: idiv
     185: istore        8
     187: new           #51                 // class MBMGIXGO
     190: dup
     191: aload         7
     193: sipush        891
     196: invokespecial #83                 // Method MBMGIXGO."<init>":([BI)V
     199: astore        9
     201: aload_0
     202: getfield      #98                 // Field K:[[I
     205: iload         6
     207: iload         8
     209: newarray       int
     211: aastore
     212: iconst_0
     213: istore        10
     215: iload         14
     217: ifeq          238
     220: aload_0
     221: getfield      #98                 // Field K:[[I
     224: iload         6
     226: aaload
     227: iload         10
     229: aload         9
     231: invokevirtual #104                // Method MBMGIXGO.h:()I
     234: iastore
     235: iinc          10, 1
     238: iload         10
     240: iload         8
     242: if_icmplt     220
     245: iinc          6, 1
     248: iload         6
     250: iconst_4
     251: if_icmplt     168
     254: aload_1
     255: ldc           #38                 // String model_index
     257: aconst_null
     258: invokevirtual #110                // Method XTGLDHGX.a:(Ljava/lang/String;[B)[B
     261: astore        7
     263: aload_0
     264: getfield      #182                // Field J:[[I
     267: iconst_0
     268: aaload
     269: arraylength
     270: istore        8
     272: aload_0
     273: iload         8
     275: newarray       byte
     277: putfield      #125                // Field R:[B
     280: iconst_0
     281: istore        9
     283: iload         14
     285: ifeq          324
     288: iload         9
     290: aload         7
     292: arraylength
     293: if_icmpge     313
     296: aload_0
     297: getfield      #125                // Field R:[B
     300: iload         9
     302: aload         7
     304: iload         9
     306: baload
     307: bastore
     308: iload         14
     310: ifeq          321
     313: aload_0
     314: getfield      #125                // Field R:[B
     317: iload         9
     319: iconst_0
     320: bastore
     321: iinc          9, 1
     324: iload         9
     326: iload         8
     328: if_icmplt     288
     331: aload_1
     332: ldc           #31                 // String map_index
     334: aconst_null
     335: invokevirtual #110                // Method XTGLDHGX.a:(Ljava/lang/String;[B)[B
     338: astore        7
     340: new           #51                 // class MBMGIXGO
     343: dup
     344: aload         7
     346: sipush        891
     349: invokespecial #83                 // Method MBMGIXGO."<init>":([BI)V
     352: astore        10
     354: aload         7
     356: arraylength
     357: bipush        7
     359: idiv
     360: istore        8
     362: aload_0
     363: iload         8
     365: newarray       int
     367: putfield      #123                // Field Q:[I
     370: aload_0
     371: iload         8
     373: newarray       int
     375: putfield      #122                // Field v:[I
     378: aload_0
     379: iload         8
     381: newarray       int
     383: putfield      #121                // Field i:[I
     386: aload_0
     387: iload         8
     389: newarray       int
     391: putfield      #120                // Field B:[I
     394: iconst_0
     395: istore        11
     397: iload         14
     399: ifeq          453
     402: aload_0
     403: getfield      #123                // Field Q:[I
     406: iload         11
     408: aload         10
     410: invokevirtual #103                // Method MBMGIXGO.e:()I
     413: iastore
     414: aload_0
     415: getfield      #122                // Field v:[I
     418: iload         11
     420: aload         10
     422: invokevirtual #103                // Method MBMGIXGO.e:()I
     425: iastore
     426: aload_0
     427: getfield      #121                // Field i:[I
     430: iload         11
     432: aload         10
     434: invokevirtual #103                // Method MBMGIXGO.e:()I
     437: iastore
     438: aload_0
     439: getfield      #120                // Field B:[I
     442: iload         11
     444: aload         10
     446: invokevirtual #102                // Method MBMGIXGO.c:()I
     449: iastore
     450: iinc          11, 1
     453: iload         11
     455: iload         8
     457: if_icmplt     402
     460: aload_1
     461: ldc           #26                 // String anim_index
     463: aconst_null
     464: invokevirtual #110                // Method XTGLDHGX.a:(Ljava/lang/String;[B)[B
     467: astore        7
     469: new           #51                 // class MBMGIXGO
     472: dup
     473: aload         7
     475: sipush        891
     478: invokespecial #83                 // Method MBMGIXGO."<init>":([BI)V
     481: astore        10
     483: aload         7
     485: arraylength
     486: iconst_2
     487: idiv
     488: istore        8
     490: aload_0
     491: iload         8
     493: newarray       int
     495: putfield      #87                 // Field F:[I
     498: iconst_0
     499: istore        12
     501: iload         14
     503: ifeq          521
     506: aload_0
     507: getfield      #87                 // Field F:[I
     510: iload         12
     512: aload         10
     514: invokevirtual #103                // Method MBMGIXGO.e:()I
     517: iastore
     518: iinc          12, 1
     521: iload         12
     523: iload         8
     525: if_icmplt     506
     528: aload_1
     529: ldc           #34                 // String midi_index
     531: aconst_null
     532: invokevirtual #110                // Method XTGLDHGX.a:(Ljava/lang/String;[B)[B
     535: astore        7
     537: new           #51                 // class MBMGIXGO
     540: dup
     541: aload         7
     543: sipush        891
     546: invokespecial #83                 // Method MBMGIXGO."<init>":([BI)V
     549: astore        10
     551: aload         7
     553: arraylength
     554: istore        8
     556: aload_0
     557: iload         8
     559: newarray       int
     561: putfield      #124                // Field t:[I
     564: iconst_0
     565: istore        13
     567: iload         14
     569: ifeq          587
     572: aload_0
     573: getfield      #124                // Field t:[I
     576: iload         13
     578: aload         10
     580: invokevirtual #102                // Method MBMGIXGO.c:()I
     583: iastore
     584: iinc          13, 1
     587: iload         13
     589: iload         8
     591: if_icmplt     572
     594: aload_0
     595: aload_2
     596: putfield      #119                // Field o:Lclient;
     599: aload_0
     600: iconst_1
     601: putfield      #139                // Field y:Z
     604: aload_0
     605: getfield      #119                // Field o:Lclient;
     608: aload_0
     609: iconst_2
     610: invokevirtual #172                // Method client.a:(Ljava/lang/Runnable;I)V
     613: return

  public final int a();
    Code:
       0: aload_0
       1: getfield      #131                // Field G:LBISVHPUN;
       4: astore_2
       5: aload_2
       6: monitorenter
       7: aload_0
       8: getfield      #131                // Field G:LBISVHPUN;
      11: invokevirtual #115                // Method BISVHPUN.c:()I
      14: istore_1
      15: jsr           23
      18: iload_1
      19: ireturn
      20: aload_2
      21: monitorexit
      22: athrow
      23: astore_3
      24: aload_2
      25: monitorexit
      26: ret           3
    Exception table:
       from    to  target type
           7    20    20   any

  public final void b();
    Code:
       0: aload_0
       1: iconst_0
       2: putfield      #139                // Field y:Z
       5: return

  public final void a(boolean, int);
    Code:
       0: aload_0
       1: getfield      #123                // Field Q:[I
       4: arraylength
       5: istore_3
       6: iload_2
       7: ifeq          15
      10: bipush        20
      12: putstatic     #162                // Field q:I
      15: iconst_0
      16: istore        4
      18: getstatic     #486                // Field client.Jj:I
      21: ifeq          71
      24: iload_1
      25: ifne          38
      28: aload_0
      29: getfield      #120                // Field B:[I
      32: iload         4
      34: iaload
      35: ifeq          68
      38: aload_0
      39: iconst_2
      40: iconst_3
      41: aload_0
      42: getfield      #121                // Field i:[I
      45: iload         4
      47: iaload
      48: bipush        8
      50: invokevirtual #154                // Method a:(BIIB)V
      53: aload_0
      54: iconst_2
      55: iconst_3
      56: aload_0
      57: getfield      #122                // Field v:[I
      60: iload         4
      62: iaload
      63: bipush        8
      65: invokevirtual #154                // Method a:(BIIB)V
      68: iinc          4, 1
      71: iload         4
      73: iload_3
      74: if_icmplt     24
      77: return
      78: astore_3
      79: new           #61                 // class java/lang/StringBuffer
      82: dup
      83: ldc           #15                 // String 6116,
      85: invokespecial #81                 // Method java/lang/StringBuffer."<init>":(Ljava/lang/String;)V
      88: iload_1
      89: invokevirtual #91                 // Method java/lang/StringBuffer.append:(Z)Ljava/lang/StringBuffer;
      92: ldc           #6                  // String ,
      94: invokevirtual #90                 // Method java/lang/StringBuffer.append:(Ljava/lang/String;)Ljava/lang/StringBuffer;
      97: iload_2
      98: invokevirtual #88                 // Method java/lang/StringBuffer.append:(I)Ljava/lang/StringBuffer;
     101: ldc           #6                  // String ,
     103: invokevirtual #90                 // Method java/lang/StringBuffer.append:(Ljava/lang/String;)Ljava/lang/StringBuffer;
     106: aload_3
     107: invokevirtual #176                // Method java/lang/Throwable.toString:()Ljava/lang/String;
     110: invokevirtual #90                 // Method java/lang/StringBuffer.append:(Ljava/lang/String;)Ljava/lang/StringBuffer;
     113: invokevirtual #175                // Method java/lang/StringBuffer.toString:()Ljava/lang/String;
     116: invokestatic  #159                // Method sign/signlink.reporterror:(Ljava/lang/String;)V
     119: new           #59                 // class java/lang/RuntimeException
     122: dup
     123: invokespecial #73                 // Method java/lang/RuntimeException."<init>":()V
     126: athrow
    Exception table:
       from    to  target type
           0    77    78   Class java/lang/RuntimeException

  public final int a(int, int);
    Code:
       0: iload_1
       1: ifgt          20
       4: aload_0
       5: aload_0
       6: getfield      #169                // Field A:Z
       9: ifeq          16
      12: iconst_0
      13: goto          17
      16: iconst_1
      17: putfield      #169                // Field A:Z
      20: aload_0
      21: getfield      #182                // Field J:[[I
      24: iload_2
      25: aaload
      26: arraylength
      27: ireturn
      28: astore_3
      29: new           #61                 // class java/lang/StringBuffer
      32: dup
      33: ldc           #16                 // String 72363,
      35: invokespecial #81                 // Method java/lang/StringBuffer."<init>":(Ljava/lang/String;)V
      38: iload_1
      39: invokevirtual #88                 // Method java/lang/StringBuffer.append:(I)Ljava/lang/StringBuffer;
      42: ldc           #6                  // String ,
      44: invokevirtual #90                 // Method java/lang/StringBuffer.append:(Ljava/lang/String;)Ljava/lang/StringBuffer;
      47: iload_2
      48: invokevirtual #88                 // Method java/lang/StringBuffer.append:(I)Ljava/lang/StringBuffer;
      51: ldc           #6                  // String ,
      53: invokevirtual #90                 // Method java/lang/StringBuffer.append:(Ljava/lang/String;)Ljava/lang/StringBuffer;
      56: aload_3
      57: invokevirtual #176                // Method java/lang/Throwable.toString:()Ljava/lang/String;
      60: invokevirtual #90                 // Method java/lang/StringBuffer.append:(Ljava/lang/String;)Ljava/lang/StringBuffer;
      63: invokevirtual #175                // Method java/lang/StringBuffer.toString:()Ljava/lang/String;
      66: invokestatic  #159                // Method sign/signlink.reporterror:(Ljava/lang/String;)V
      69: new           #59                 // class java/lang/RuntimeException
      72: dup
      73: invokespecial #73                 // Method java/lang/RuntimeException."<init>":()V
      76: athrow
    Exception table:
       from    to  target type
           0    28    28   Class java/lang/RuntimeException

  private final void a(int, PHKHJKBS);
    Code:
       0: getstatic     #486                // Field client.Jj:I
       3: istore        6
       5: iload_1
       6: bipush        8
       8: if_icmplt     17
      11: iload_1
      12: bipush        8
      14: if_icmple     24
      17: aload_0
      18: sipush        -339
      21: putfield      #118                // Field x:I
      24: aload_0
      25: getfield      #145                // Field I:Ljava/net/Socket;
      28: ifnonnull     133
      31: invokestatic  #99                 // Method java/lang/System.currentTimeMillis:()J
      34: lstore_3
      35: lload_3
      36: aload_0
      37: getfield      #114                // Field g:J
      40: lsub
      41: ldc2_w        #185                // long 4000l
      44: lcmp
      45: ifge          49
      48: return
      49: aload_0
      50: lload_3
      51: putfield      #114                // Field g:J
      54: aload_0
      55: aload_0
      56: getfield      #119                // Field o:Lclient;
      59: ldc           #2                  // int 43594
      61: getstatic     #147                // Field client.od:I
      64: iadd
      65: invokevirtual #146                // Method client.j:(I)Ljava/net/Socket;
      68: putfield      #145                // Field I:Ljava/net/Socket;
      71: aload_0
      72: aload_0
      73: getfield      #145                // Field I:Ljava/net/Socket;
      76: invokevirtual #105                // Method java/net/Socket.getInputStream:()Ljava/io/InputStream;
      79: putfield      #143                // Field H:Ljava/io/InputStream;
      82: aload_0
      83: aload_0
      84: getfield      #145                // Field I:Ljava/net/Socket;
      87: invokevirtual #107                // Method java/net/Socket.getOutputStream:()Ljava/io/OutputStream;
      90: putfield      #144                // Field z:Ljava/io/OutputStream;
      93: aload_0
      94: getfield      #144                // Field z:Ljava/io/OutputStream;
      97: bipush        15
      99: invokevirtual #183                // Method java/io/OutputStream.write:(I)V
     102: iconst_0
     103: istore        5
     105: iload         6
     107: ifeq          121
     110: aload_0
     111: getfield      #143                // Field H:Ljava/io/InputStream;
     114: invokevirtual #156                // Method java/io/InputStream.read:()I
     117: pop
     118: iinc          5, 1
     121: iload         5
     123: bipush        8
     125: if_icmplt     110
     128: aload_0
     129: iconst_0
     130: putfield      #174                // Field S:I
     133: aload_0
     134: getfield      #126                // Field k:[B
     137: iconst_0
     138: aload_2
     139: getfield      #112                // Field PHKHJKBS.i:I
     142: i2b
     143: bastore
     144: aload_0
     145: getfield      #126                // Field k:[B
     148: iconst_1
     149: aload_2
     150: getfield      #113                // Field PHKHJKBS.k:I
     153: bipush        8
     155: ishr
     156: i2b
     157: bastore
     158: aload_0
     159: getfield      #126                // Field k:[B
     162: iconst_2
     163: aload_2
     164: getfield      #113                // Field PHKHJKBS.k:I
     167: i2b
     168: bastore
     169: aload_2
     170: getfield      #181                // Field PHKHJKBS.l:Z
     173: ifeq          188
     176: aload_0
     177: getfield      #126                // Field k:[B
     180: iconst_3
     181: iconst_2
     182: bastore
     183: iload         6
     185: ifeq          217
     188: aload_0
     189: getfield      #119                // Field o:Lclient;
     192: getfield      #117                // Field client.gh:Z
     195: ifne          210
     198: aload_0
     199: getfield      #126                // Field k:[B
     202: iconst_3
     203: iconst_1
     204: bastore
     205: iload         6
     207: ifeq          217
     210: aload_0
     211: getfield      #126                // Field k:[B
     214: iconst_3
     215: iconst_0
     216: bastore
     217: aload_0
     218: getfield      #144                // Field z:Ljava/io/OutputStream;
     221: aload_0
     222: getfield      #126                // Field k:[B
     225: iconst_0
     226: iconst_4
     227: invokevirtual #184                // Method java/io/OutputStream.write:([BII)V
     230: aload_0
     231: iconst_0
     232: putfield      #155                // Field f:I
     235: aload_0
     236: sipush        -10000
     239: putfield      #133                // Field u:I
     242: return
     243: astore_3
     244: aload_0
     245: getfield      #145                // Field I:Ljava/net/Socket;
     248: invokevirtual #96                 // Method java/net/Socket.close:()V
     251: goto          255
     254: pop
     255: aload_0
     256: aconst_null
     257: putfield      #145                // Field I:Ljava/net/Socket;
     260: aload_0
     261: aconst_null
     262: putfield      #143                // Field H:Ljava/io/InputStream;
     265: aload_0
     266: aconst_null
     267: putfield      #144                // Field z:Ljava/io/OutputStream;
     270: aload_0
     271: iconst_0
     272: putfield      #138                // Field s:I
     275: aload_0
     276: dup
     277: getfield      #133                // Field u:I
     280: iconst_1
     281: iadd
     282: putfield      #133                // Field u:I
     285: return
     286: astore_3
     287: new           #61                 // class java/lang/StringBuffer
     290: dup
     291: ldc           #22                 // String 96894,
     293: invokespecial #81                 // Method java/lang/StringBuffer."<init>":(Ljava/lang/String;)V
     296: iload_1
     297: invokevirtual #88                 // Method java/lang/StringBuffer.append:(I)Ljava/lang/StringBuffer;
     300: ldc           #6                  // String ,
     302: invokevirtual #90                 // Method java/lang/StringBuffer.append:(Ljava/lang/String;)Ljava/lang/StringBuffer;
     305: aload_2
     306: invokevirtual #89                 // Method java/lang/StringBuffer.append:(Ljava/lang/Object;)Ljava/lang/StringBuffer;
     309: ldc           #6                  // String ,
     311: invokevirtual #90                 // Method java/lang/StringBuffer.append:(Ljava/lang/String;)Ljava/lang/StringBuffer;
     314: aload_3
     315: invokevirtual #176                // Method java/lang/Throwable.toString:()Ljava/lang/String;
     318: invokevirtual #90                 // Method java/lang/StringBuffer.append:(Ljava/lang/String;)Ljava/lang/StringBuffer;
     321: invokevirtual #175                // Method java/lang/StringBuffer.toString:()Ljava/lang/String;
     324: invokestatic  #159                // Method sign/signlink.reporterror:(Ljava/lang/String;)V
     327: new           #59                 // class java/lang/RuntimeException
     330: dup
     331: invokespecial #73                 // Method java/lang/RuntimeException."<init>":()V
     334: athrow
    Exception table:
       from    to  target type
          24   242   243   Class java/io/IOException
         244   251   254   Class java/lang/Exception
           5   286   286   Class java/lang/RuntimeException

  public final int c(int);
    Code:
       0: iload_1
       1: ifeq          10
       4: aload_0
       5: bipush        -76
       7: putfield      #118                // Field x:I
      10: aload_0
      11: getfield      #87                 // Field F:[I
      14: arraylength
      15: ireturn
      16: astore_2
      17: new           #61                 // class java/lang/StringBuffer
      20: dup
      21: ldc           #21                 // String 92552,
      23: invokespecial #81                 // Method java/lang/StringBuffer."<init>":(Ljava/lang/String;)V
      26: iload_1
      27: invokevirtual #88                 // Method java/lang/StringBuffer.append:(I)Ljava/lang/StringBuffer;
      30: ldc           #6                  // String ,
      32: invokevirtual #90                 // Method java/lang/StringBuffer.append:(Ljava/lang/String;)Ljava/lang/StringBuffer;
      35: aload_2
      36: invokevirtual #176                // Method java/lang/Throwable.toString:()Ljava/lang/String;
      39: invokevirtual #90                 // Method java/lang/StringBuffer.append:(Ljava/lang/String;)Ljava/lang/StringBuffer;
      42: invokevirtual #175                // Method java/lang/StringBuffer.toString:()Ljava/lang/String;
      45: invokestatic  #159                // Method sign/signlink.reporterror:(Ljava/lang/String;)V
      48: new           #59                 // class java/lang/RuntimeException
      51: dup
      52: invokespecial #73                 // Method java/lang/RuntimeException."<init>":()V
      55: athrow
    Exception table:
       from    to  target type
           0    16    16   Class java/lang/RuntimeException

  public final void b(int, int);
    Code:
       0: iload_1
       1: iflt          28
       4: iload_1
       5: aload_0
       6: getfield      #182                // Field J:[[I
       9: arraylength
      10: if_icmpgt     28
      13: iload_2
      14: iflt          28
      17: iload_2
      18: aload_0
      19: getfield      #182                // Field J:[[I
      22: iload_1
      23: aaload
      24: arraylength
      25: if_icmple     29
      28: return
      29: aload_0
      30: getfield      #182                // Field J:[[I
      33: iload_1
      34: aaload
      35: iload_2
      36: iaload
      37: ifne          41
      40: return
      41: aload_0
      42: getfield      #131                // Field G:LBISVHPUN;
      45: astore_3
      46: aload_3
      47: monitorenter
      48: aload_0
      49: getfield      #131                // Field G:LBISVHPUN;
      52: invokevirtual #170                // Method BISVHPUN.b:()LPPOHBEGB;
      55: checkcast     #68                 // class PHKHJKBS
      58: astore        5
      60: getstatic     #486                // Field client.Jj:I
      63: ifeq          101
      66: aload         5
      68: getfield      #112                // Field PHKHJKBS.i:I
      71: iload_1
      72: if_icmpne     88
      75: aload         5
      77: getfield      #113                // Field PHKHJKBS.k:I
      80: iload_2
      81: if_icmpne     88
      84: jsr           176
      87: return
      88: aload_0
      89: getfield      #131                // Field G:LBISVHPUN;
      92: iconst_0
      93: invokevirtual #127                // Method BISVHPUN.a:(Z)LPPOHBEGB;
      96: checkcast     #68                 // class PHKHJKBS
      99: astore        5
     101: aload         5
     103: ifnonnull     66
     106: new           #68                 // class PHKHJKBS
     109: dup
     110: invokespecial #75                 // Method PHKHJKBS."<init>":()V
     113: astore        5
     115: aload         5
     117: iload_1
     118: putfield      #112                // Field PHKHJKBS.i:I
     121: aload         5
     123: iload_2
     124: putfield      #113                // Field PHKHJKBS.k:I
     127: aload         5
     129: iconst_1
     130: putfield      #181                // Field PHKHJKBS.l:Z
     133: aload_0
     134: getfield      #141                // Field P:LLHGXPZPG;
     137: astore        6
     139: aload         6
     141: monitorenter
     142: aload_0
     143: getfield      #141                // Field P:LLHGXPZPG;
     146: aload         5
     148: invokevirtual #86                 // Method LHGXPZPG.a:(LPKVMXVTO;)V
     151: aload         6
     153: monitorexit
     154: goto          161
     157: aload         6
     159: monitorexit
     160: athrow
     161: aload_0
     162: getfield      #131                // Field G:LBISVHPUN;
     165: aload         5
     167: invokevirtual #85                 // Method BISVHPUN.a:(LPPOHBEGB;)V
     170: aload_3
     171: monitorexit
     172: return
     173: aload_3
     174: monitorexit
     175: athrow
     176: astore        4
     178: aload_3
     179: monitorexit
     180: ret           4
    Exception table:
       from    to  target type
         142   151   157   any
          48   170   173   any

  public final int c(int, int);
    Code:
       0: iload_2
       1: iflt          9
       4: bipush        -7
       6: putstatic     #162                // Field q:I
       9: aload_0
      10: getfield      #125                // Field R:[B
      13: iload_1
      14: baload
      15: sipush        255
      18: iand
      19: ireturn
      20: astore_3
      21: new           #61                 // class java/lang/StringBuffer
      24: dup
      25: ldc           #11                 // String 46001,
      27: invokespecial #81                 // Method java/lang/StringBuffer."<init>":(Ljava/lang/String;)V
      30: iload_1
      31: invokevirtual #88                 // Method java/lang/StringBuffer.append:(I)Ljava/lang/StringBuffer;
      34: ldc           #6                  // String ,
      36: invokevirtual #90                 // Method java/lang/StringBuffer.append:(Ljava/lang/String;)Ljava/lang/StringBuffer;
      39: iload_2
      40: invokevirtual #88                 // Method java/lang/StringBuffer.append:(I)Ljava/lang/StringBuffer;
      43: ldc           #6                  // String ,
      45: invokevirtual #90                 // Method java/lang/StringBuffer.append:(Ljava/lang/String;)Ljava/lang/StringBuffer;
      48: aload_3
      49: invokevirtual #176                // Method java/lang/Throwable.toString:()Ljava/lang/String;
      52: invokevirtual #90                 // Method java/lang/StringBuffer.append:(Ljava/lang/String;)Ljava/lang/StringBuffer;
      55: invokevirtual #175                // Method java/lang/StringBuffer.toString:()Ljava/lang/String;
      58: invokestatic  #159                // Method sign/signlink.reporterror:(Ljava/lang/String;)V
      61: new           #59                 // class java/lang/RuntimeException
      64: dup
      65: invokespecial #73                 // Method java/lang/RuntimeException."<init>":()V
      68: athrow
    Exception table:
       from    to  target type
           0    20    20   Class java/lang/RuntimeException

  public final void run();
    Code:
       0: getstatic     #486                // Field client.Jj:I
       3: istore        5
       5: iload         5
       7: ifeq          482
      10: aload_0
      11: dup
      12: getfield      #135                // Field m:I
      15: iconst_1
      16: iadd
      17: putfield      #135                // Field m:I
      20: bipush        20
      22: istore_1
      23: aload_0
      24: getfield      #150                // Field d:I
      27: ifne          45
      30: aload_0
      31: getfield      #119                // Field o:Lclient;
      34: getfield      #94                 // Field client.Ad:[LIGSLDTHC;
      37: iconst_0
      38: aaload
      39: ifnull        45
      42: bipush        50
      44: istore_1
      45: iload_1
      46: i2l
      47: invokestatic  #168                // Method java/lang/Thread.sleep:(J)V
      50: goto          54
      53: pop
      54: aload_0
      55: iconst_1
      56: putfield      #100                // Field C:Z
      59: iconst_0
      60: istore_2
      61: iload         5
      63: ifeq          123
      66: aload_0
      67: getfield      #100                // Field C:Z
      70: ifeq          129
      73: aload_0
      74: iconst_0
      75: putfield      #100                // Field C:Z
      78: aload_0
      79: iconst_1
      80: invokespecial #163                // Method b:(Z)V
      83: aload_0
      84: iconst_0
      85: invokespecial #165                // Method a:(Z)V
      88: aload_0
      89: getfield      #130                // Field L:I
      92: ifne          100
      95: iload_2
      96: iconst_5
      97: if_icmpge     129
     100: aload_0
     101: bipush        -56
     103: invokespecial #164                // Method a:(B)V
     106: aload_0
     107: getfield      #143                // Field H:Ljava/io/InputStream;
     110: ifnull        120
     113: aload_0
     114: sipush        -369
     117: invokespecial #166                // Method b:(I)V
     120: iinc          2, 1
     123: iload_2
     124: bipush        100
     126: if_icmplt     66
     129: iconst_0
     130: istore_3
     131: aload_0
     132: getfield      #136                // Field c:LLHGXPZPG;
     135: invokevirtual #171                // Method LHGXPZPG.b:()LPKVMXVTO;
     138: checkcast     #68                 // class PHKHJKBS
     141: astore        4
     143: iload         5
     145: ifeq          206
     148: aload         4
     150: getfield      #181                // Field PHKHJKBS.l:Z
     153: ifeq          193
     156: iconst_1
     157: istore_3
     158: aload         4
     160: dup
     161: getfield      #101                // Field PHKHJKBS.m:I
     164: iconst_1
     165: iadd
     166: putfield      #101                // Field PHKHJKBS.m:I
     169: aload         4
     171: getfield      #101                // Field PHKHJKBS.m:I
     174: bipush        50
     176: if_icmple     193
     179: aload         4
     181: iconst_0
     182: putfield      #101                // Field PHKHJKBS.m:I
     185: aload_0
     186: bipush        8
     188: aload         4
     190: invokespecial #140                // Method a:(ILPHKHJKBS;)V
     193: aload_0
     194: getfield      #136                // Field c:LLHGXPZPG;
     197: iconst_0
     198: invokevirtual #128                // Method LHGXPZPG.a:(Z)LPKVMXVTO;
     201: checkcast     #68                 // class PHKHJKBS
     204: astore        4
     206: aload         4
     208: ifnonnull     148
     211: iload_3
     212: ifne          287
     215: aload_0
     216: getfield      #136                // Field c:LLHGXPZPG;
     219: invokevirtual #171                // Method LHGXPZPG.b:()LPKVMXVTO;
     222: checkcast     #68                 // class PHKHJKBS
     225: astore        4
     227: iload         5
     229: ifeq          282
     232: iconst_1
     233: istore_3
     234: aload         4
     236: dup
     237: getfield      #101                // Field PHKHJKBS.m:I
     240: iconst_1
     241: iadd
     242: putfield      #101                // Field PHKHJKBS.m:I
     245: aload         4
     247: getfield      #101                // Field PHKHJKBS.m:I
     250: bipush        50
     252: if_icmple     269
     255: aload         4
     257: iconst_0
     258: putfield      #101                // Field PHKHJKBS.m:I
     261: aload_0
     262: bipush        8
     264: aload         4
     266: invokespecial #140                // Method a:(ILPHKHJKBS;)V
     269: aload_0
     270: getfield      #136                // Field c:LLHGXPZPG;
     273: iconst_0
     274: invokevirtual #128                // Method LHGXPZPG.a:(Z)LPKVMXVTO;
     277: checkcast     #68                 // class PHKHJKBS
     280: astore        4
     282: aload         4
     284: ifnonnull     232
     287: iload_3
     288: ifeq          347
     291: aload_0
     292: dup
     293: getfield      #174                // Field S:I
     296: iconst_1
     297: iadd
     298: putfield      #174                // Field S:I
     301: aload_0
     302: getfield      #174                // Field S:I
     305: sipush        750
     308: if_icmple     358
     311: aload_0
     312: getfield      #145                // Field I:Ljava/net/Socket;
     315: invokevirtual #96                 // Method java/net/Socket.close:()V
     318: goto          322
     321: pop
     322: aload_0
     323: aconst_null
     324: putfield      #145                // Field I:Ljava/net/Socket;
     327: aload_0
     328: aconst_null
     329: putfield      #143                // Field H:Ljava/io/InputStream;
     332: aload_0
     333: aconst_null
     334: putfield      #144                // Field z:Ljava/io/OutputStream;
     337: aload_0
     338: iconst_0
     339: putfield      #138                // Field s:I
     342: iload         5
     344: ifeq          358
     347: aload_0
     348: iconst_0
     349: putfield      #174                // Field S:I
     352: aload_0
     353: ldc           #1                  // String
     355: putfield      #152                // Field e:Ljava/lang/String;
     358: aload_0
     359: getfield      #119                // Field o:Lclient;
     362: getfield      #117                // Field client.gh:Z
     365: ifeq          482
     368: aload_0
     369: getfield      #145                // Field I:Ljava/net/Socket;
     372: ifnull        482
     375: aload_0
     376: getfield      #144                // Field z:Ljava/io/OutputStream;
     379: ifnull        482
     382: aload_0
     383: getfield      #150                // Field d:I
     386: ifgt          401
     389: aload_0
     390: getfield      #119                // Field o:Lclient;
     393: getfield      #94                 // Field client.Ad:[LIGSLDTHC;
     396: iconst_0
     397: aaload
     398: ifnonnull     482
     401: aload_0
     402: dup
     403: getfield      #155                // Field f:I
     406: iconst_1
     407: iadd
     408: putfield      #155                // Field f:I
     411: aload_0
     412: getfield      #155                // Field f:I
     415: sipush        500
     418: if_icmple     482
     421: aload_0
     422: iconst_0
     423: putfield      #155                // Field f:I
     426: aload_0
     427: getfield      #126                // Field k:[B
     430: iconst_0
     431: iconst_0
     432: bastore
     433: aload_0
     434: getfield      #126                // Field k:[B
     437: iconst_1
     438: iconst_0
     439: bastore
     440: aload_0
     441: getfield      #126                // Field k:[B
     444: iconst_2
     445: iconst_0
     446: bastore
     447: aload_0
     448: getfield      #126                // Field k:[B
     451: iconst_3
     452: bipush        10
     454: bastore
     455: aload_0
     456: getfield      #144                // Field z:Ljava/io/OutputStream;
     459: aload_0
     460: getfield      #126                // Field k:[B
     463: iconst_0
     464: iconst_4
     465: invokevirtual #184                // Method java/io/OutputStream.write:([BII)V
     468: goto          482
     471: pop
     472: aload_0
     473: sipush        5000
     476: putfield      #174                // Field S:I
     479: goto          482
     482: aload_0
     483: getfield      #139                // Field y:Z
     486: ifne          10
     489: return
     490: astore_1
     491: new           #61                 // class java/lang/StringBuffer
     494: dup
     495: ldc           #40                 // String od_ex
     497: invokespecial #81                 // Method java/lang/StringBuffer."<init>":(Ljava/lang/String;)V
     500: aload_1
     501: invokevirtual #106                // Method java/lang/Throwable.getMessage:()Ljava/lang/String;
     504: invokevirtual #90                 // Method java/lang/StringBuffer.append:(Ljava/lang/String;)Ljava/lang/StringBuffer;
     507: invokevirtual #175                // Method java/lang/StringBuffer.toString:()Ljava/lang/String;
     510: invokestatic  #159                // Method sign/signlink.reporterror:(Ljava/lang/String;)V
     513: return
    Exception table:
       from    to  target type
          45    50    53   Class java/lang/Exception
         311   318   321   Class java/lang/Exception
         455   468   471   Class java/io/IOException
           5   489   490   Class java/lang/Exception

  public final void a(int, int, boolean);
    Code:
       0: aload_0
       1: getfield      #119                // Field o:Lclient;
       4: getfield      #94                 // Field client.Ad:[LIGSLDTHC;
       7: iconst_0
       8: aaload
       9: ifnonnull     13
      12: return
      13: aload_0
      14: getfield      #182                // Field J:[[I
      17: iload_2
      18: aaload
      19: iload_1
      20: iaload
      21: ifne          25
      24: return
      25: aload_0
      26: getfield      #148                // Field n:[[B
      29: iload_2
      30: aaload
      31: iload_1
      32: baload
      33: ifne          37
      36: return
      37: aload_0
      38: getfield      #150                // Field d:I
      41: ifne          45
      44: return
      45: new           #68                 // class PHKHJKBS
      48: dup
      49: invokespecial #75                 // Method PHKHJKBS."<init>":()V
      52: astore        4
      54: aload         4
      56: iload_2
      57: putfield      #112                // Field PHKHJKBS.i:I
      60: aload         4
      62: iload_1
      63: putfield      #113                // Field PHKHJKBS.k:I
      66: iload_3
      67: ifeq          76
      70: sipush        -423
      73: putstatic     #162                // Field q:I
      76: aload         4
      78: iconst_0
      79: putfield      #181                // Field PHKHJKBS.l:Z
      82: aload_0
      83: getfield      #151                // Field p:LLHGXPZPG;
      86: astore        5
      88: aload         5
      90: monitorenter
      91: aload_0
      92: getfield      #151                // Field p:LLHGXPZPG;
      95: aload         4
      97: invokevirtual #86                 // Method LHGXPZPG.a:(LPKVMXVTO;)V
     100: aload         5
     102: monitorexit
     103: return
     104: aload         5
     106: monitorexit
     107: athrow
     108: astore        4
     110: new           #61                 // class java/lang/StringBuffer
     113: dup
     114: ldc           #7                  // String 1578,
     116: invokespecial #81                 // Method java/lang/StringBuffer."<init>":(Ljava/lang/String;)V
     119: iload_1
     120: invokevirtual #88                 // Method java/lang/StringBuffer.append:(I)Ljava/lang/StringBuffer;
     123: ldc           #6                  // String ,
     125: invokevirtual #90                 // Method java/lang/StringBuffer.append:(Ljava/lang/String;)Ljava/lang/StringBuffer;
     128: iload_2
     129: invokevirtual #88                 // Method java/lang/StringBuffer.append:(I)Ljava/lang/StringBuffer;
     132: ldc           #6                  // String ,
     134: invokevirtual #90                 // Method java/lang/StringBuffer.append:(Ljava/lang/String;)Ljava/lang/StringBuffer;
     137: iload_3
     138: invokevirtual #91                 // Method java/lang/StringBuffer.append:(Z)Ljava/lang/StringBuffer;
     141: ldc           #6                  // String ,
     143: invokevirtual #90                 // Method java/lang/StringBuffer.append:(Ljava/lang/String;)Ljava/lang/StringBuffer;
     146: aload         4
     148: invokevirtual #176                // Method java/lang/Throwable.toString:()Ljava/lang/String;
     151: invokevirtual #90                 // Method java/lang/StringBuffer.append:(Ljava/lang/String;)Ljava/lang/StringBuffer;
     154: invokevirtual #175                // Method java/lang/StringBuffer.toString:()Ljava/lang/String;
     157: invokestatic  #159                // Method sign/signlink.reporterror:(Ljava/lang/String;)V
     160: new           #59                 // class java/lang/RuntimeException
     163: dup
     164: invokespecial #73                 // Method java/lang/RuntimeException."<init>":()V
     167: athrow
    Exception table:
       from    to  target type
          91   100   104   any
           0   108   108   Class java/lang/RuntimeException

  public final PHKHJKBS c();
    Code:
       0: getstatic     #486                // Field client.Jj:I
       3: istore        5
       5: aload_0
       6: getfield      #132                // Field D:LLHGXPZPG;
       9: astore_2
      10: aload_2
      11: monitorenter
      12: aload_0
      13: getfield      #132                // Field D:LLHGXPZPG;
      16: invokevirtual #173                // Method LHGXPZPG.a:()LPKVMXVTO;
      19: checkcast     #68                 // class PHKHJKBS
      22: astore_1
      23: aload_2
      24: monitorexit
      25: goto          31
      28: aload_2
      29: monitorexit
      30: athrow
      31: aload_1
      32: ifnonnull     37
      35: aconst_null
      36: areturn
      37: aload_0
      38: getfield      #131                // Field G:LBISVHPUN;
      41: astore_2
      42: aload_2
      43: monitorenter
      44: aload_1
      45: invokevirtual #178                // Method PPOHBEGB.b:()V
      48: aload_2
      49: monitorexit
      50: goto          56
      53: aload_2
      54: monitorexit
      55: athrow
      56: aload_1
      57: getfield      #93                 // Field PHKHJKBS.j:[B
      60: ifnonnull     65
      63: aload_1
      64: areturn
      65: iconst_0
      66: istore_2
      67: new           #67                 // class java/util/zip/GZIPInputStream
      70: dup
      71: new           #52                 // class java/io/ByteArrayInputStream
      74: dup
      75: aload_1
      76: getfield      #93                 // Field PHKHJKBS.j:[B
      79: invokespecial #82                 // Method java/io/ByteArrayInputStream."<init>":([B)V
      82: invokespecial #78                 // Method java/util/zip/GZIPInputStream."<init>":(Ljava/io/InputStream;)V
      85: astore_3
      86: iload_2
      87: aload_0
      88: getfield      #179                // Field E:[B
      91: arraylength
      92: if_icmpne     105
      95: new           #59                 // class java/lang/RuntimeException
      98: dup
      99: ldc           #28                 // String buffer overflow!
     101: invokespecial #80                 // Method java/lang/RuntimeException."<init>":(Ljava/lang/String;)V
     104: athrow
     105: aload_3
     106: aload_0
     107: getfield      #179                // Field E:[B
     110: iload_2
     111: aload_0
     112: getfield      #179                // Field E:[B
     115: arraylength
     116: iload_2
     117: isub
     118: invokevirtual #158                // Method java/util/zip/GZIPInputStream.read:([BII)I
     121: istore        4
     123: iload         4
     125: iconst_m1
     126: if_icmpeq     139
     129: iload_2
     130: iload         4
     132: iadd
     133: istore_2
     134: iload         5
     136: ifeq          86
     139: goto          153
     142: pop
     143: new           #59                 // class java/lang/RuntimeException
     146: dup
     147: ldc           #29                 // String error unzipping
     149: invokespecial #80                 // Method java/lang/RuntimeException."<init>":(Ljava/lang/String;)V
     152: athrow
     153: aload_1
     154: iload_2
     155: newarray       byte
     157: putfield      #93                 // Field PHKHJKBS.j:[B
     160: iconst_0
     161: istore_3
     162: iload         5
     164: ifeq          182
     167: aload_1
     168: getfield      #93                 // Field PHKHJKBS.j:[B
     171: iload_3
     172: aload_0
     173: getfield      #179                // Field E:[B
     176: iload_3
     177: baload
     178: bastore
     179: iinc          3, 1
     182: iload_3
     183: iload_2
     184: if_icmplt     167
     187: aload_1
     188: areturn
    Exception table:
       from    to  target type
          12    23    28   any
          44    48    53   any
          67   139   142   Class java/io/IOException

  public final int a(int, int, int, int);
    Code:
       0: iload_2
       1: ifeq          8
       4: getstatic     #162                // Field q:I
       7: ireturn
       8: iload         4
      10: bipush        8
      12: ishl
      13: iload_3
      14: iadd
      15: istore        5
      17: iconst_0
      18: istore        6
      20: getstatic     #486                // Field client.Jj:I
      23: ifeq          61
      26: aload_0
      27: getfield      #123                // Field Q:[I
      30: iload         6
      32: iaload
      33: iload         5
      35: if_icmpne     58
      38: iload_1
      39: ifne          50
      42: aload_0
      43: getfield      #122                // Field v:[I
      46: iload         6
      48: iaload
      49: ireturn
      50: aload_0
      51: getfield      #121                // Field i:[I
      54: iload         6
      56: iaload
      57: ireturn
      58: iinc          6, 1
      61: iload         6
      63: aload_0
      64: getfield      #123                // Field Q:[I
      67: arraylength
      68: if_icmplt     26
      71: iconst_m1
      72: ireturn
      73: astore        5
      75: new           #61                 // class java/lang/StringBuffer
      78: dup
      79: ldc           #17                 // String 78844,
      81: invokespecial #81                 // Method java/lang/StringBuffer."<init>":(Ljava/lang/String;)V
      84: iload_1
      85: invokevirtual #88                 // Method java/lang/StringBuffer.append:(I)Ljava/lang/StringBuffer;
      88: ldc           #6                  // String ,
      90: invokevirtual #90                 // Method java/lang/StringBuffer.append:(Ljava/lang/String;)Ljava/lang/StringBuffer;
      93: iload_2
      94: invokevirtual #88                 // Method java/lang/StringBuffer.append:(I)Ljava/lang/StringBuffer;
      97: ldc           #6                  // String ,
      99: invokevirtual #90                 // Method java/lang/StringBuffer.append:(Ljava/lang/String;)Ljava/lang/StringBuffer;
     102: iload_3
     103: invokevirtual #88                 // Method java/lang/StringBuffer.append:(I)Ljava/lang/StringBuffer;
     106: ldc           #6                  // String ,
     108: invokevirtual #90                 // Method java/lang/StringBuffer.append:(Ljava/lang/String;)Ljava/lang/StringBuffer;
     111: iload         4
     113: invokevirtual #88                 // Method java/lang/StringBuffer.append:(I)Ljava/lang/StringBuffer;
     116: ldc           #6                  // String ,
     118: invokevirtual #90                 // Method java/lang/StringBuffer.append:(Ljava/lang/String;)Ljava/lang/StringBuffer;
     121: aload         5
     123: invokevirtual #176                // Method java/lang/Throwable.toString:()Ljava/lang/String;
     126: invokevirtual #90                 // Method java/lang/StringBuffer.append:(Ljava/lang/String;)Ljava/lang/StringBuffer;
     129: invokevirtual #175                // Method java/lang/StringBuffer.toString:()Ljava/lang/String;
     132: invokestatic  #159                // Method sign/signlink.reporterror:(Ljava/lang/String;)V
     135: new           #59                 // class java/lang/RuntimeException
     138: dup
     139: invokespecial #73                 // Method java/lang/RuntimeException."<init>":()V
     142: athrow
    Exception table:
       from    to  target type
           0    73    73   Class java/lang/RuntimeException

  public final void a(int);
    Code:
       0: aload_0
       1: iconst_0
       2: iload_1
       3: invokevirtual #109                // Method b:(II)V
       6: return

  public final void a(byte, int, int, byte);
    Code:
       0: iload         4
       2: bipush        8
       4: if_icmpne     16
       7: iconst_0
       8: istore        4
      10: getstatic     #486                // Field client.Jj:I
      13: ifeq          23
      16: aload_0
      17: sipush        237
      20: putfield      #111                // Field l:I
      23: aload_0
      24: getfield      #119                // Field o:Lclient;
      27: getfield      #94                 // Field client.Ad:[LIGSLDTHC;
      30: iconst_0
      31: aaload
      32: ifnonnull     36
      35: return
      36: aload_0
      37: getfield      #182                // Field J:[[I
      40: iload_2
      41: aaload
      42: iload_3
      43: iaload
      44: ifne          48
      47: return
      48: aload_0
      49: getfield      #119                // Field o:Lclient;
      52: getfield      #94                 // Field client.Ad:[LIGSLDTHC;
      55: iload_2
      56: iconst_1
      57: iadd
      58: aaload
      59: iconst_1
      60: iload_3
      61: invokevirtual #116                // Method IGSLDTHC.a:(ZI)[B
      64: astore        5
      66: aload_0
      67: aload_0
      68: getfield      #182                // Field J:[[I
      71: iload_2
      72: aaload
      73: iload_3
      74: iaload
      75: iconst_3
      76: aload_0
      77: getfield      #98                 // Field K:[[I
      80: iload_2
      81: aaload
      82: iload_3
      83: iaload
      84: aload         5
      86: invokespecial #95                 // Method a:(IBI[B)Z
      89: ifeq          93
      92: return
      93: aload_0
      94: getfield      #148                // Field n:[[B
      97: iload_2
      98: aaload
      99: iload_3
     100: iload_1
     101: bastore
     102: iload_1
     103: aload_0
     104: getfield      #150                // Field d:I
     107: if_icmple     115
     110: aload_0
     111: iload_1
     112: putfield      #150                // Field d:I
     115: aload_0
     116: dup
     117: getfield      #153                // Field b:I
     120: iconst_1
     121: iadd
     122: putfield      #153                // Field b:I
     125: return
     126: astore        5
     128: new           #61                 // class java/lang/StringBuffer
     131: dup
     132: ldc           #19                 // String 88351,
     134: invokespecial #81                 // Method java/lang/StringBuffer."<init>":(Ljava/lang/String;)V
     137: iload_1
     138: invokevirtual #88                 // Method java/lang/StringBuffer.append:(I)Ljava/lang/StringBuffer;
     141: ldc           #6                  // String ,
     143: invokevirtual #90                 // Method java/lang/StringBuffer.append:(Ljava/lang/String;)Ljava/lang/StringBuffer;
     146: iload_2
     147: invokevirtual #88                 // Method java/lang/StringBuffer.append:(I)Ljava/lang/StringBuffer;
     150: ldc           #6                  // String ,
     152: invokevirtual #90                 // Method java/lang/StringBuffer.append:(Ljava/lang/String;)Ljava/lang/StringBuffer;
     155: iload_3
     156: invokevirtual #88                 // Method java/lang/StringBuffer.append:(I)Ljava/lang/StringBuffer;
     159: ldc           #6                  // String ,
     161: invokevirtual #90                 // Method java/lang/StringBuffer.append:(Ljava/lang/String;)Ljava/lang/StringBuffer;
     164: iload         4
     166: invokevirtual #88                 // Method java/lang/StringBuffer.append:(I)Ljava/lang/StringBuffer;
     169: ldc           #6                  // String ,
     171: invokevirtual #90                 // Method java/lang/StringBuffer.append:(Ljava/lang/String;)Ljava/lang/StringBuffer;
     174: aload         5
     176: invokevirtual #176                // Method java/lang/Throwable.toString:()Ljava/lang/String;
     179: invokevirtual #90                 // Method java/lang/StringBuffer.append:(Ljava/lang/String;)Ljava/lang/StringBuffer;
     182: invokevirtual #175                // Method java/lang/StringBuffer.toString:()Ljava/lang/String;
     185: invokestatic  #159                // Method sign/signlink.reporterror:(Ljava/lang/String;)V
     188: new           #59                 // class java/lang/RuntimeException
     191: dup
     192: invokespecial #73                 // Method java/lang/RuntimeException."<init>":()V
     195: athrow
    Exception table:
       from    to  target type
           0   125   126   Class java/lang/RuntimeException

  public final boolean d(int, int);
    Code:
       0: getstatic     #486                // Field client.Jj:I
       3: istore        4
       5: iload         4
       7: ifeq          18
      10: new           #57                 // class java/lang/NullPointerException
      13: dup
      14: invokespecial #72                 // Method java/lang/NullPointerException."<init>":()V
      17: athrow
      18: iload_2
      19: ifge          10
      22: iconst_0
      23: istore_3
      24: iload         4
      26: ifeq          44
      29: aload_0
      30: getfield      #121                // Field i:[I
      33: iload_3
      34: iaload
      35: iload_1
      36: if_icmpne     41
      39: iconst_1
      40: ireturn
      41: iinc          3, 1
      44: iload_3
      45: aload_0
      46: getfield      #123                // Field Q:[I
      49: arraylength
      50: if_icmplt     29
      53: iconst_0
      54: ireturn
      55: astore_3
      56: new           #61                 // class java/lang/StringBuffer
      59: dup
      60: ldc           #14                 // String 5492,
      62: invokespecial #81                 // Method java/lang/StringBuffer."<init>":(Ljava/lang/String;)V
      65: iload_1
      66: invokevirtual #88                 // Method java/lang/StringBuffer.append:(I)Ljava/lang/StringBuffer;
      69: ldc           #6                  // String ,
      71: invokevirtual #90                 // Method java/lang/StringBuffer.append:(Ljava/lang/String;)Ljava/lang/StringBuffer;
      74: iload_2
      75: invokevirtual #88                 // Method java/lang/StringBuffer.append:(I)Ljava/lang/StringBuffer;
      78: ldc           #6                  // String ,
      80: invokevirtual #90                 // Method java/lang/StringBuffer.append:(Ljava/lang/String;)Ljava/lang/StringBuffer;
      83: aload_3
      84: invokevirtual #176                // Method java/lang/Throwable.toString:()Ljava/lang/String;
      87: invokevirtual #90                 // Method java/lang/StringBuffer.append:(Ljava/lang/String;)Ljava/lang/StringBuffer;
      90: invokevirtual #175                // Method java/lang/StringBuffer.toString:()Ljava/lang/String;
      93: invokestatic  #159                // Method sign/signlink.reporterror:(Ljava/lang/String;)V
      96: new           #59                 // class java/lang/RuntimeException
      99: dup
     100: invokespecial #73                 // Method java/lang/RuntimeException."<init>":()V
     103: athrow
    Exception table:
       from    to  target type
           5    55    55   Class java/lang/RuntimeException

  private final void a(boolean);
    Code:
       0: getstatic     #486                // Field client.Jj:I
       3: istore_3
       4: aload_0
       5: iconst_0
       6: putfield      #130                // Field L:I
       9: iload_1
      10: ifeq          14
      13: return
      14: aload_0
      15: iconst_0
      16: putfield      #129                // Field M:I
      19: aload_0
      20: getfield      #136                // Field c:LLHGXPZPG;
      23: invokevirtual #171                // Method LHGXPZPG.b:()LPKVMXVTO;
      26: checkcast     #68                 // class PHKHJKBS
      29: astore_2
      30: iload_3
      31: ifeq          77
      34: aload_2
      35: getfield      #181                // Field PHKHJKBS.l:Z
      38: ifeq          55
      41: aload_0
      42: dup
      43: getfield      #130                // Field L:I
      46: iconst_1
      47: iadd
      48: putfield      #130                // Field L:I
      51: iload_3
      52: ifeq          65
      55: aload_0
      56: dup
      57: getfield      #129                // Field M:I
      60: iconst_1
      61: iadd
      62: putfield      #129                // Field M:I
      65: aload_0
      66: getfield      #136                // Field c:LLHGXPZPG;
      69: iconst_0
      70: invokevirtual #128                // Method LHGXPZPG.a:(Z)LPKVMXVTO;
      73: checkcast     #68                 // class PHKHJKBS
      76: astore_2
      77: aload_2
      78: ifnonnull     34
      81: iload_3
      82: ifeq          172
      85: aload_0
      86: getfield      #142                // Field N:LLHGXPZPG;
      89: invokevirtual #173                // Method LHGXPZPG.a:()LPKVMXVTO;
      92: checkcast     #68                 // class PHKHJKBS
      95: astore_2
      96: aload_2
      97: ifnull        181
     100: aload_0
     101: getfield      #148                // Field n:[[B
     104: aload_2
     105: getfield      #112                // Field PHKHJKBS.i:I
     108: aaload
     109: aload_2
     110: getfield      #113                // Field PHKHJKBS.k:I
     113: baload
     114: ifeq          127
     117: aload_0
     118: dup
     119: getfield      #149                // Field w:I
     122: iconst_1
     123: iadd
     124: putfield      #149                // Field w:I
     127: aload_0
     128: getfield      #148                // Field n:[[B
     131: aload_2
     132: getfield      #112                // Field PHKHJKBS.i:I
     135: aaload
     136: aload_2
     137: getfield      #113                // Field PHKHJKBS.k:I
     140: iconst_0
     141: bastore
     142: aload_0
     143: getfield      #136                // Field c:LLHGXPZPG;
     146: aload_2
     147: invokevirtual #86                 // Method LHGXPZPG.a:(LPKVMXVTO;)V
     150: aload_0
     151: dup
     152: getfield      #130                // Field L:I
     155: iconst_1
     156: iadd
     157: putfield      #130                // Field L:I
     160: aload_0
     161: bipush        8
     163: aload_2
     164: invokespecial #140                // Method a:(ILPHKHJKBS;)V
     167: aload_0
     168: iconst_1
     169: putfield      #100                // Field C:Z
     172: aload_0
     173: getfield      #130                // Field L:I
     176: bipush        10
     178: if_icmplt     85
     181: return
     182: astore_2
     183: new           #61                 // class java/lang/StringBuffer
     186: dup
     187: ldc           #20                 // String 89950,
     189: invokespecial #81                 // Method java/lang/StringBuffer."<init>":(Ljava/lang/String;)V
     192: iload_1
     193: invokevirtual #91                 // Method java/lang/StringBuffer.append:(Z)Ljava/lang/StringBuffer;
     196: ldc           #6                  // String ,
     198: invokevirtual #90                 // Method java/lang/StringBuffer.append:(Ljava/lang/String;)Ljava/lang/StringBuffer;
     201: aload_2
     202: invokevirtual #176                // Method java/lang/Throwable.toString:()Ljava/lang/String;
     205: invokevirtual #90                 // Method java/lang/StringBuffer.append:(Ljava/lang/String;)Ljava/lang/StringBuffer;
     208: invokevirtual #175                // Method java/lang/StringBuffer.toString:()Ljava/lang/String;
     211: invokestatic  #159                // Method sign/signlink.reporterror:(Ljava/lang/String;)V
     214: new           #59                 // class java/lang/RuntimeException
     217: dup
     218: invokespecial #73                 // Method java/lang/RuntimeException."<init>":()V
     221: athrow
    Exception table:
       from    to  target type
           4   181   182   Class java/lang/RuntimeException

  public final void d(int);
    Code:
       0: iload_1
       1: ifeq          19
       4: iconst_1
       5: istore_2
       6: getstatic     #486                // Field client.Jj:I
       9: ifeq          15
      12: iinc          2, 1
      15: iload_2
      16: ifgt          12
      19: aload_0
      20: getfield      #151                // Field p:LLHGXPZPG;
      23: astore_2
      24: aload_2
      25: monitorenter
      26: aload_0
      27: getfield      #151                // Field p:LLHGXPZPG;
      30: invokevirtual #160                // Method LHGXPZPG.c:()V
      33: aload_2
      34: monitorexit
      35: return
      36: aload_2
      37: monitorexit
      38: athrow
      39: astore_2
      40: new           #61                 // class java/lang/StringBuffer
      43: dup
      44: ldc           #9                  // String 26326,
      46: invokespecial #81                 // Method java/lang/StringBuffer."<init>":(Ljava/lang/String;)V
      49: iload_1
      50: invokevirtual #88                 // Method java/lang/StringBuffer.append:(I)Ljava/lang/StringBuffer;
      53: ldc           #6                  // String ,
      55: invokevirtual #90                 // Method java/lang/StringBuffer.append:(Ljava/lang/String;)Ljava/lang/StringBuffer;
      58: aload_2
      59: invokevirtual #176                // Method java/lang/Throwable.toString:()Ljava/lang/String;
      62: invokevirtual #90                 // Method java/lang/StringBuffer.append:(Ljava/lang/String;)Ljava/lang/StringBuffer;
      65: invokevirtual #175                // Method java/lang/StringBuffer.toString:()Ljava/lang/String;
      68: invokestatic  #159                // Method sign/signlink.reporterror:(Ljava/lang/String;)V
      71: new           #59                 // class java/lang/RuntimeException
      74: dup
      75: invokespecial #73                 // Method java/lang/RuntimeException."<init>":()V
      78: athrow
    Exception table:
       from    to  target type
          26    33    36   any
           0    39    39   Class java/lang/RuntimeException

  private final void b(boolean);
    Code:
       0: iload_1
       1: ifne          5
       4: return
       5: aload_0
       6: getfield      #141                // Field P:LLHGXPZPG;
       9: astore_3
      10: aload_3
      11: monitorenter
      12: aload_0
      13: getfield      #141                // Field P:LLHGXPZPG;
      16: invokevirtual #173                // Method LHGXPZPG.a:()LPKVMXVTO;
      19: checkcast     #68                 // class PHKHJKBS
      22: astore_2
      23: aload_3
      24: monitorexit
      25: goto          192
      28: aload_3
      29: monitorexit
      30: athrow
      31: aload_0
      32: iconst_1
      33: putfield      #100                // Field C:Z
      36: aconst_null
      37: astore_3
      38: aload_0
      39: getfield      #119                // Field o:Lclient;
      42: getfield      #94                 // Field client.Ad:[LIGSLDTHC;
      45: iconst_0
      46: aaload
      47: ifnull        73
      50: aload_0
      51: getfield      #119                // Field o:Lclient;
      54: getfield      #94                 // Field client.Ad:[LIGSLDTHC;
      57: aload_2
      58: getfield      #112                // Field PHKHJKBS.i:I
      61: iconst_1
      62: iadd
      63: aaload
      64: iconst_1
      65: aload_2
      66: getfield      #113                // Field PHKHJKBS.k:I
      69: invokevirtual #116                // Method IGSLDTHC.a:(ZI)[B
      72: astore_3
      73: aload_0
      74: aload_0
      75: getfield      #182                // Field J:[[I
      78: aload_2
      79: getfield      #112                // Field PHKHJKBS.i:I
      82: aaload
      83: aload_2
      84: getfield      #113                // Field PHKHJKBS.k:I
      87: iaload
      88: iconst_3
      89: aload_0
      90: getfield      #98                 // Field K:[[I
      93: aload_2
      94: getfield      #112                // Field PHKHJKBS.i:I
      97: aaload
      98: aload_2
      99: getfield      #113                // Field PHKHJKBS.k:I
     102: iaload
     103: aload_3
     104: invokespecial #95                 // Method a:(IBI[B)Z
     107: ifne          112
     110: aconst_null
     111: astore_3
     112: aload_0
     113: getfield      #141                // Field P:LLHGXPZPG;
     116: astore        4
     118: aload         4
     120: monitorenter
     121: aload_3
     122: ifnonnull     139
     125: aload_0
     126: getfield      #142                // Field N:LLHGXPZPG;
     129: aload_2
     130: invokevirtual #86                 // Method LHGXPZPG.a:(LPKVMXVTO;)V
     133: getstatic     #486                // Field client.Jj:I
     136: ifeq          171
     139: aload_2
     140: aload_3
     141: putfield      #93                 // Field PHKHJKBS.j:[B
     144: aload_0
     145: getfield      #132                // Field D:LLHGXPZPG;
     148: astore        6
     150: aload         6
     152: monitorenter
     153: aload_0
     154: getfield      #132                // Field D:LLHGXPZPG;
     157: aload_2
     158: invokevirtual #86                 // Method LHGXPZPG.a:(LPKVMXVTO;)V
     161: aload         6
     163: monitorexit
     164: goto          171
     167: aload         6
     169: monitorexit
     170: athrow
     171: aload_0
     172: getfield      #141                // Field P:LLHGXPZPG;
     175: invokevirtual #173                // Method LHGXPZPG.a:()LPKVMXVTO;
     178: checkcast     #68                 // class PHKHJKBS
     181: astore_2
     182: aload         4
     184: monitorexit
     185: goto          192
     188: aload         4
     190: monitorexit
     191: athrow
     192: aload_2
     193: ifnonnull     31
     196: return
     197: astore_2
     198: new           #61                 // class java/lang/StringBuffer
     201: dup
     202: ldc           #8                  // String 20446,
     204: invokespecial #81                 // Method java/lang/StringBuffer."<init>":(Ljava/lang/String;)V
     207: iload_1
     208: invokevirtual #91                 // Method java/lang/StringBuffer.append:(Z)Ljava/lang/StringBuffer;
     211: ldc           #6                  // String ,
     213: invokevirtual #90                 // Method java/lang/StringBuffer.append:(Ljava/lang/String;)Ljava/lang/StringBuffer;
     216: aload_2
     217: invokevirtual #176                // Method java/lang/Throwable.toString:()Ljava/lang/String;
     220: invokevirtual #90                 // Method java/lang/StringBuffer.append:(Ljava/lang/String;)Ljava/lang/StringBuffer;
     223: invokevirtual #175                // Method java/lang/StringBuffer.toString:()Ljava/lang/String;
     226: invokestatic  #159                // Method sign/signlink.reporterror:(Ljava/lang/String;)V
     229: new           #59                 // class java/lang/RuntimeException
     232: dup
     233: invokespecial #73                 // Method java/lang/RuntimeException."<init>":()V
     236: athrow
    Exception table:
       from    to  target type
          12    23    28   any
         153   161   167   any
         121   182   188   any
           0   196   197   Class java/lang/RuntimeException

  private final void a(byte);
    Code:
       0: getstatic     #486                // Field client.Jj:I
       3: istore        7
       5: iload_1
       6: bipush        -56
       8: if_icmpeq     417
      11: iconst_1
      12: istore_2
      13: iload         7
      15: ifeq          21
      18: iinc          2, 1
      21: iload_2
      22: ifgt          18
      25: iload         7
      27: ifeq          417
      30: aload_0
      31: getfield      #150                // Field d:I
      34: ifeq          433
      37: aload_0
      38: getfield      #151                // Field p:LLHGXPZPG;
      41: astore_3
      42: aload_3
      43: monitorenter
      44: aload_0
      45: getfield      #151                // Field p:LLHGXPZPG;
      48: invokevirtual #173                // Method LHGXPZPG.a:()LPKVMXVTO;
      51: checkcast     #68                 // class PHKHJKBS
      54: astore_2
      55: aload_3
      56: monitorexit
      57: goto          218
      60: aload_3
      61: monitorexit
      62: athrow
      63: aload_0
      64: getfield      #148                // Field n:[[B
      67: aload_2
      68: getfield      #112                // Field PHKHJKBS.i:I
      71: aaload
      72: aload_2
      73: getfield      #113                // Field PHKHJKBS.k:I
      76: baload
      77: ifeq          192
      80: aload_0
      81: getfield      #148                // Field n:[[B
      84: aload_2
      85: getfield      #112                // Field PHKHJKBS.i:I
      88: aaload
      89: aload_2
      90: getfield      #113                // Field PHKHJKBS.k:I
      93: iconst_0
      94: bastore
      95: aload_0
      96: getfield      #136                // Field c:LLHGXPZPG;
      99: aload_2
     100: invokevirtual #86                 // Method LHGXPZPG.a:(LPKVMXVTO;)V
     103: aload_0
     104: bipush        8
     106: aload_2
     107: invokespecial #140                // Method a:(ILPHKHJKBS;)V
     110: aload_0
     111: iconst_1
     112: putfield      #100                // Field C:Z
     115: aload_0
     116: getfield      #149                // Field w:I
     119: aload_0
     120: getfield      #153                // Field b:I
     123: if_icmpge     136
     126: aload_0
     127: dup
     128: getfield      #149                // Field w:I
     131: iconst_1
     132: iadd
     133: putfield      #149                // Field w:I
     136: aload_0
     137: new           #61                 // class java/lang/StringBuffer
     140: dup
     141: ldc           #23                 // String Loading extra files -
     143: invokespecial #81                 // Method java/lang/StringBuffer."<init>":(Ljava/lang/String;)V
     146: aload_0
     147: getfield      #149                // Field w:I
     150: bipush        100
     152: imul
     153: aload_0
     154: getfield      #153                // Field b:I
     157: idiv
     158: invokevirtual #88                 // Method java/lang/StringBuffer.append:(I)Ljava/lang/StringBuffer;
     161: ldc           #4                  // String %
     163: invokevirtual #90                 // Method java/lang/StringBuffer.append:(Ljava/lang/String;)Ljava/lang/StringBuffer;
     166: invokevirtual #175                // Method java/lang/StringBuffer.toString:()Ljava/lang/String;
     169: putfield      #152                // Field e:Ljava/lang/String;
     172: aload_0
     173: dup
     174: getfield      #129                // Field M:I
     177: iconst_1
     178: iadd
     179: putfield      #129                // Field M:I
     182: aload_0
     183: getfield      #129                // Field M:I
     186: bipush        10
     188: if_icmpne     192
     191: return
     192: aload_0
     193: getfield      #151                // Field p:LLHGXPZPG;
     196: astore_3
     197: aload_3
     198: monitorenter
     199: aload_0
     200: getfield      #151                // Field p:LLHGXPZPG;
     203: invokevirtual #173                // Method LHGXPZPG.a:()LPKVMXVTO;
     206: checkcast     #68                 // class PHKHJKBS
     209: astore_2
     210: aload_3
     211: monitorexit
     212: goto          218
     215: aload_3
     216: monitorexit
     217: athrow
     218: aload_2
     219: ifnonnull     63
     222: iconst_0
     223: istore_3
     224: iload         7
     226: ifeq          402
     229: aload_0
     230: getfield      #148                // Field n:[[B
     233: iload_3
     234: aaload
     235: astore        4
     237: aload         4
     239: arraylength
     240: istore        5
     242: iconst_0
     243: istore        6
     245: iload         7
     247: ifeq          392
     250: aload         4
     252: iload         6
     254: baload
     255: aload_0
     256: getfield      #150                // Field d:I
     259: if_icmpne     389
     262: aload         4
     264: iload         6
     266: iconst_0
     267: bastore
     268: new           #68                 // class PHKHJKBS
     271: dup
     272: invokespecial #75                 // Method PHKHJKBS."<init>":()V
     275: astore_2
     276: aload_2
     277: iload_3
     278: putfield      #112                // Field PHKHJKBS.i:I
     281: aload_2
     282: iload         6
     284: putfield      #113                // Field PHKHJKBS.k:I
     287: aload_2
     288: iconst_0
     289: putfield      #181                // Field PHKHJKBS.l:Z
     292: aload_0
     293: getfield      #136                // Field c:LLHGXPZPG;
     296: aload_2
     297: invokevirtual #86                 // Method LHGXPZPG.a:(LPKVMXVTO;)V
     300: aload_0
     301: bipush        8
     303: aload_2
     304: invokespecial #140                // Method a:(ILPHKHJKBS;)V
     307: aload_0
     308: iconst_1
     309: putfield      #100                // Field C:Z
     312: aload_0
     313: getfield      #149                // Field w:I
     316: aload_0
     317: getfield      #153                // Field b:I
     320: if_icmpge     333
     323: aload_0
     324: dup
     325: getfield      #149                // Field w:I
     328: iconst_1
     329: iadd
     330: putfield      #149                // Field w:I
     333: aload_0
     334: new           #61                 // class java/lang/StringBuffer
     337: dup
     338: ldc           #23                 // String Loading extra files -
     340: invokespecial #81                 // Method java/lang/StringBuffer."<init>":(Ljava/lang/String;)V
     343: aload_0
     344: getfield      #149                // Field w:I
     347: bipush        100
     349: imul
     350: aload_0
     351: getfield      #153                // Field b:I
     354: idiv
     355: invokevirtual #88                 // Method java/lang/StringBuffer.append:(I)Ljava/lang/StringBuffer;
     358: ldc           #4                  // String %
     360: invokevirtual #90                 // Method java/lang/StringBuffer.append:(Ljava/lang/String;)Ljava/lang/StringBuffer;
     363: invokevirtual #175                // Method java/lang/StringBuffer.toString:()Ljava/lang/String;
     366: putfield      #152                // Field e:Ljava/lang/String;
     369: aload_0
     370: dup
     371: getfield      #129                // Field M:I
     374: iconst_1
     375: iadd
     376: putfield      #129                // Field M:I
     379: aload_0
     380: getfield      #129                // Field M:I
     383: bipush        10
     385: if_icmpne     389
     388: return
     389: iinc          6, 1
     392: iload         6
     394: iload         5
     396: if_icmplt     250
     399: iinc          3, 1
     402: iload_3
     403: iconst_4
     404: if_icmplt     229
     407: aload_0
     408: dup
     409: getfield      #150                // Field d:I
     412: iconst_1
     413: isub
     414: putfield      #150                // Field d:I
     417: aload_0
     418: getfield      #130                // Field L:I
     421: ifne          474
     424: aload_0
     425: getfield      #129                // Field M:I
     428: bipush        10
     430: if_icmplt     30
     433: return
     434: astore_2
     435: new           #61                 // class java/lang/StringBuffer
     438: dup
     439: ldc           #10                 // String 32156,
     441: invokespecial #81                 // Method java/lang/StringBuffer."<init>":(Ljava/lang/String;)V
     444: iload_1
     445: invokevirtual #88                 // Method java/lang/StringBuffer.append:(I)Ljava/lang/StringBuffer;
     448: ldc           #6                  // String ,
     450: invokevirtual #90                 // Method java/lang/StringBuffer.append:(Ljava/lang/String;)Ljava/lang/StringBuffer;
     453: aload_2
     454: invokevirtual #176                // Method java/lang/Throwable.toString:()Ljava/lang/String;
     457: invokevirtual #90                 // Method java/lang/StringBuffer.append:(Ljava/lang/String;)Ljava/lang/StringBuffer;
     460: invokevirtual #175                // Method java/lang/StringBuffer.toString:()Ljava/lang/String;
     463: invokestatic  #159                // Method sign/signlink.reporterror:(Ljava/lang/String;)V
     466: new           #59                 // class java/lang/RuntimeException
     469: dup
     470: invokespecial #73                 // Method java/lang/RuntimeException."<init>":()V
     473: athrow
     474: return
    Exception table:
       from    to  target type
          44    55    60   any
         199   210   215   any
           5   433   434   Class java/lang/RuntimeException

  public final boolean e(int, int);
    Code:
       0: iload_2
       1: iconst_5
       2: if_icmpeq     11
       5: sipush        169
       8: putstatic     #162                // Field q:I
      11: aload_0
      12: getfield      #124                // Field t:[I
      15: iload_1
      16: iaload
      17: iconst_1
      18: if_icmpne     23
      21: iconst_1
      22: ireturn
      23: iconst_0
      24: ireturn
      25: astore_3
      26: new           #61                 // class java/lang/StringBuffer
      29: dup
      30: ldc           #13                 // String 54888,
      32: invokespecial #81                 // Method java/lang/StringBuffer."<init>":(Ljava/lang/String;)V
      35: iload_1
      36: invokevirtual #88                 // Method java/lang/StringBuffer.append:(I)Ljava/lang/StringBuffer;
      39: ldc           #6                  // String ,
      41: invokevirtual #90                 // Method java/lang/StringBuffer.append:(Ljava/lang/String;)Ljava/lang/StringBuffer;
      44: iload_2
      45: invokevirtual #88                 // Method java/lang/StringBuffer.append:(I)Ljava/lang/StringBuffer;
      48: ldc           #6                  // String ,
      50: invokevirtual #90                 // Method java/lang/StringBuffer.append:(Ljava/lang/String;)Ljava/lang/StringBuffer;
      53: aload_3
      54: invokevirtual #176                // Method java/lang/Throwable.toString:()Ljava/lang/String;
      57: invokevirtual #90                 // Method java/lang/StringBuffer.append:(Ljava/lang/String;)Ljava/lang/StringBuffer;
      60: invokevirtual #175                // Method java/lang/StringBuffer.toString:()Ljava/lang/String;
      63: invokestatic  #159                // Method sign/signlink.reporterror:(Ljava/lang/String;)V
      66: new           #59                 // class java/lang/RuntimeException
      69: dup
      70: invokespecial #73                 // Method java/lang/RuntimeException."<init>":()V
      73: athrow
    Exception table:
       from    to  target type
           0    25    25   Class java/lang/RuntimeException

  public GHOWLKWN();
    Code:
       0: aload_0
       1: invokespecial #71                 // Method VJKFYAWG."<init>":()V
       4: aload_0
       5: new           #46                 // class LHGXPZPG
       8: dup
       9: sipush        169
      12: invokespecial #76                 // Method LHGXPZPG."<init>":(I)V
      15: putfield      #136                // Field c:LLHGXPZPG;
      18: aload_0
      19: ldc           #1                  // String
      21: putfield      #152                // Field e:Ljava/lang/String;
      24: aload_0
      25: iconst_1
      26: putfield      #84                 // Field h:Z
      29: aload_0
      30: new           #66                 // class java/util/zip/CRC32
      33: dup
      34: invokespecial #74                 // Method java/util/zip/CRC32."<init>":()V
      37: putfield      #97                 // Field j:Ljava/util/zip/CRC32;
      40: aload_0
      41: sipush        500
      44: newarray       byte
      46: putfield      #126                // Field k:[B
      49: aload_0
      50: sipush        923
      53: putfield      #111                // Field l:I
      56: aload_0
      57: iconst_4
      58: multianewarray #41,  1            // class "[[B"
      62: putfield      #148                // Field n:[[B
      65: aload_0
      66: new           #46                 // class LHGXPZPG
      69: dup
      70: sipush        169
      73: invokespecial #76                 // Method LHGXPZPG."<init>":(I)V
      76: putfield      #151                // Field p:LLHGXPZPG;
      79: aload_0
      80: sipush        13603
      83: putfield      #118                // Field x:I
      86: aload_0
      87: iconst_1
      88: putfield      #139                // Field y:Z
      91: aload_0
      92: iconst_0
      93: putfield      #169                // Field A:Z
      96: aload_0
      97: iconst_0
      98: putfield      #100                // Field C:Z
     101: aload_0
     102: new           #46                 // class LHGXPZPG
     105: dup
     106: sipush        169
     109: invokespecial #76                 // Method LHGXPZPG."<init>":(I)V
     112: putfield      #132                // Field D:LLHGXPZPG;
     115: aload_0
     116: ldc           #3                  // int 65000
     118: newarray       byte
     120: putfield      #179                // Field E:[B
     123: aload_0
     124: new           #47                 // class BISVHPUN
     127: dup
     128: getstatic     #162                // Field q:I
     131: invokespecial #77                 // Method BISVHPUN."<init>":(I)V
     134: putfield      #131                // Field G:LBISVHPUN;
     137: aload_0
     138: iconst_4
     139: multianewarray #42,  1            // class "[[I"
     143: putfield      #182                // Field J:[[I
     146: aload_0
     147: iconst_4
     148: multianewarray #42,  1            // class "[[I"
     152: putfield      #98                 // Field K:[[I
     155: aload_0
     156: new           #46                 // class LHGXPZPG
     159: dup
     160: sipush        169
     163: invokespecial #76                 // Method LHGXPZPG."<init>":(I)V
     166: putfield      #142                // Field N:LLHGXPZPG;
     169: aload_0
     170: new           #46                 // class LHGXPZPG
     173: dup
     174: sipush        169
     177: invokespecial #76                 // Method LHGXPZPG."<init>":(I)V
     180: putfield      #141                // Field P:LLHGXPZPG;
     183: return
}
