public class OPPOFIOL extends AFCKELYG {
  private static int x;

  private static int y;

  private static boolean z;

  public static boolean A;

  static boolean B;

  static boolean C;

  public static boolean D;

  public static int E;

  public static int F;

  public static int G;

  public static int[] H;

  public static int[] I;

  public static int[] J;

  public static int[] K;

  public static int[] L;

  static int M;

  public static DSMJIEPN[] N;

  static boolean[] O;

  static int[] P;

  static int Q;

  static int[][] R;

  static int[][] S;

  public static int[] T;

  public static int U;

  public static int[] V;

  static int[][] W;

  public static final void b(int);
    Code:
       0: aconst_null
       1: putstatic     #44                 // Field H:[I
       4: aconst_null
       5: putstatic     #44                 // Field H:[I
       8: aconst_null
       9: putstatic     #68                 // Field J:[I
      12: aconst_null
      13: putstatic     #43                 // Field K:[I
      16: aconst_null
      17: putstatic     #66                 // Field L:[I
      20: aconst_null
      21: putstatic     #75                 // Field N:[LDSMJIEPN;
      24: aconst_null
      25: putstatic     #79                 // Field O:[Z
      28: aconst_null
      29: putstatic     #73                 // Field P:[I
      32: aconst_null
      33: putstatic     #70                 // Field R:[[I
      36: aconst_null
      37: putstatic     #72                 // Field S:[[I
      40: aconst_null
      41: putstatic     #58                 // Field T:[I
      44: aconst_null
      45: putstatic     #41                 // Field V:[I
      48: aconst_null
      49: putstatic     #49                 // Field W:[[I
      52: iload_0
      53: iflt          112
      56: iconst_1
      57: istore_1
      58: getstatic     #289                // Field XHHRODPC.l:Z
      61: ifeq          67
      64: iinc          1, 1
      67: iload_1
      68: ifgt          64
      71: return
      72: astore_1
      73: new           #26                 // class java/lang/StringBuffer
      76: dup
      77: ldc           #14                 // String 80327,
      79: invokespecial #31                 // Method java/lang/StringBuffer."<init>":(Ljava/lang/String;)V
      82: iload_0
      83: invokevirtual #33                 // Method java/lang/StringBuffer.append:(I)Ljava/lang/StringBuffer;
      86: ldc           #8                  // String ,
      88: invokevirtual #35                 // Method java/lang/StringBuffer.append:(Ljava/lang/String;)Ljava/lang/StringBuffer;
      91: aload_1
      92: invokevirtual #77                 // Method java/lang/Throwable.toString:()Ljava/lang/String;
      95: invokevirtual #35                 // Method java/lang/StringBuffer.append:(Ljava/lang/String;)Ljava/lang/StringBuffer;
      98: invokevirtual #76                 // Method java/lang/StringBuffer.toString:()Ljava/lang/String;
     101: invokestatic  #65                 // Method sign/signlink.reporterror:(Ljava/lang/String;)V
     104: new           #24                 // class java/lang/RuntimeException
     107: dup
     108: invokespecial #29                 // Method java/lang/RuntimeException."<init>":()V
     111: athrow
     112: return
    Exception table:
       from    to  target type
           0    71    72   Class java/lang/RuntimeException

  public static final void a(byte);
    Code:
       0: getstatic     #289                // Field XHHRODPC.l:Z
       3: istore_2
       4: getstatic     #54                 // Field AFCKELYG.o:I
       7: newarray       int
       9: putstatic     #66                 // Field L:[I
      12: iload_0
      13: bipush        6
      15: if_icmpne     24
      18: iconst_0
      19: istore_0
      20: iload_2
      21: ifeq          37
      24: iconst_1
      25: istore_1
      26: iload_2
      27: ifeq          33
      30: iinc          1, 1
      33: iload_1
      34: ifgt          30
      37: iconst_0
      38: istore_1
      39: iload_2
      40: ifeq          56
      43: getstatic     #66                 // Field L:[I
      46: iload_1
      47: getstatic     #83                 // Field AFCKELYG.n:I
      50: iload_1
      51: imul
      52: iastore
      53: iinc          1, 1
      56: iload_1
      57: getstatic     #54                 // Field AFCKELYG.o:I
      60: if_icmplt     43
      63: getstatic     #83                 // Field AFCKELYG.n:I
      66: iconst_2
      67: idiv
      68: putstatic     #85                 // Field F:I
      71: getstatic     #54                 // Field AFCKELYG.o:I
      74: iconst_2
      75: idiv
      76: putstatic     #87                 // Field G:I
      79: return
      80: astore_1
      81: new           #26                 // class java/lang/StringBuffer
      84: dup
      85: ldc           #13                 // String 79230,
      87: invokespecial #31                 // Method java/lang/StringBuffer."<init>":(Ljava/lang/String;)V
      90: iload_0
      91: invokevirtual #33                 // Method java/lang/StringBuffer.append:(I)Ljava/lang/StringBuffer;
      94: ldc           #8                  // String ,
      96: invokevirtual #35                 // Method java/lang/StringBuffer.append:(Ljava/lang/String;)Ljava/lang/StringBuffer;
      99: aload_1
     100: invokevirtual #77                 // Method java/lang/Throwable.toString:()Ljava/lang/String;
     103: invokevirtual #35                 // Method java/lang/StringBuffer.append:(Ljava/lang/String;)Ljava/lang/StringBuffer;
     106: invokevirtual #76                 // Method java/lang/StringBuffer.toString:()Ljava/lang/String;
     109: invokestatic  #65                 // Method sign/signlink.reporterror:(Ljava/lang/String;)V
     112: new           #24                 // class java/lang/RuntimeException
     115: dup
     116: invokespecial #29                 // Method java/lang/RuntimeException."<init>":()V
     119: athrow
    Exception table:
       from    to  target type
           4    79    80   Class java/lang/RuntimeException

  public static final void a(int, int, int);
    Code:
       0: getstatic     #289                // Field XHHRODPC.l:Z
       3: istore        4
       5: iload_2
       6: newarray       int
       8: putstatic     #66                 // Field L:[I
      11: iload         4
      13: ifeq          17
      16: return
      17: iload_0
      18: ifge          16
      21: iconst_0
      22: istore_3
      23: iload         4
      25: ifeq          39
      28: getstatic     #66                 // Field L:[I
      31: iload_3
      32: iload_1
      33: iload_3
      34: imul
      35: iastore
      36: iinc          3, 1
      39: iload_3
      40: iload_2
      41: if_icmplt     28
      44: iload_1
      45: iconst_2
      46: idiv
      47: putstatic     #85                 // Field F:I
      50: iload_2
      51: iconst_2
      52: idiv
      53: putstatic     #87                 // Field G:I
      56: return
      57: astore_3
      58: new           #26                 // class java/lang/StringBuffer
      61: dup
      62: ldc           #16                 // String 8612,
      64: invokespecial #31                 // Method java/lang/StringBuffer."<init>":(Ljava/lang/String;)V
      67: iload_0
      68: invokevirtual #33                 // Method java/lang/StringBuffer.append:(I)Ljava/lang/StringBuffer;
      71: ldc           #8                  // String ,
      73: invokevirtual #35                 // Method java/lang/StringBuffer.append:(Ljava/lang/String;)Ljava/lang/StringBuffer;
      76: iload_1
      77: invokevirtual #33                 // Method java/lang/StringBuffer.append:(I)Ljava/lang/StringBuffer;
      80: ldc           #8                  // String ,
      82: invokevirtual #35                 // Method java/lang/StringBuffer.append:(Ljava/lang/String;)Ljava/lang/StringBuffer;
      85: iload_2
      86: invokevirtual #33                 // Method java/lang/StringBuffer.append:(I)Ljava/lang/StringBuffer;
      89: ldc           #8                  // String ,
      91: invokevirtual #35                 // Method java/lang/StringBuffer.append:(Ljava/lang/String;)Ljava/lang/StringBuffer;
      94: aload_3
      95: invokevirtual #77                 // Method java/lang/Throwable.toString:()Ljava/lang/String;
      98: invokevirtual #35                 // Method java/lang/StringBuffer.append:(Ljava/lang/String;)Ljava/lang/StringBuffer;
     101: invokevirtual #76                 // Method java/lang/StringBuffer.toString:()Ljava/lang/String;
     104: invokestatic  #65                 // Method sign/signlink.reporterror:(Ljava/lang/String;)V
     107: new           #24                 // class java/lang/RuntimeException
     110: dup
     111: invokespecial #29                 // Method java/lang/RuntimeException."<init>":()V
     114: athrow
    Exception table:
       from    to  target type
           5    56    57   Class java/lang/RuntimeException

  public static final void c(int);
    Code:
       0: iload_0
       1: iflt          8
       4: iload_0
       5: ifle          9
       8: return
       9: aconst_null
      10: putstatic     #70                 // Field R:[[I
      13: iconst_0
      14: istore_1
      15: getstatic     #289                // Field XHHRODPC.l:Z
      18: ifeq          30
      21: getstatic     #72                 // Field S:[[I
      24: iload_1
      25: aconst_null
      26: aastore
      27: iinc          1, 1
      30: iload_1
      31: bipush        50
      33: if_icmplt     21
      36: return
      37: astore_1
      38: new           #26                 // class java/lang/StringBuffer
      41: dup
      42: ldc           #15                 // String 84003,
      44: invokespecial #31                 // Method java/lang/StringBuffer."<init>":(Ljava/lang/String;)V
      47: iload_0
      48: invokevirtual #33                 // Method java/lang/StringBuffer.append:(I)Ljava/lang/StringBuffer;
      51: ldc           #8                  // String ,
      53: invokevirtual #35                 // Method java/lang/StringBuffer.append:(Ljava/lang/String;)Ljava/lang/StringBuffer;
      56: aload_1
      57: invokevirtual #77                 // Method java/lang/Throwable.toString:()Ljava/lang/String;
      60: invokevirtual #35                 // Method java/lang/StringBuffer.append:(Ljava/lang/String;)Ljava/lang/StringBuffer;
      63: invokevirtual #76                 // Method java/lang/StringBuffer.toString:()Ljava/lang/String;
      66: invokestatic  #65                 // Method sign/signlink.reporterror:(Ljava/lang/String;)V
      69: new           #24                 // class java/lang/RuntimeException
      72: dup
      73: invokespecial #29                 // Method java/lang/RuntimeException."<init>":()V
      76: athrow
    Exception table:
       from    to  target type
           0    36    37   Class java/lang/RuntimeException

  public static final void a(int, boolean);
    Code:
       0: getstatic     #289                // Field XHHRODPC.l:Z
       3: istore_3
       4: iload_1
       5: ifne          21
       8: iconst_1
       9: istore_2
      10: iload_3
      11: ifeq          17
      14: iinc          2, 1
      17: iload_2
      18: ifgt          14
      21: getstatic     #70                 // Field R:[[I
      24: ifnonnull     137
      27: iload_0
      28: putstatic     #71                 // Field Q:I
      31: getstatic     #57                 // Field A:Z
      34: ifeq          54
      37: getstatic     #71                 // Field Q:I
      40: sipush        16384
      43: multianewarray #18,  2            // class "[[I"
      47: putstatic     #70                 // Field R:[[I
      50: iload_3
      51: ifeq          66
      54: getstatic     #71                 // Field Q:I
      57: ldc           #4                  // int 65536
      59: multianewarray #18,  2            // class "[[I"
      63: putstatic     #70                 // Field R:[[I
      66: iconst_0
      67: istore_2
      68: iload_3
      69: ifeq          81
      72: getstatic     #72                 // Field S:[[I
      75: iload_2
      76: aconst_null
      77: aastore
      78: iinc          2, 1
      81: iload_2
      82: bipush        50
      84: if_icmplt     72
      87: return
      88: astore_2
      89: new           #26                 // class java/lang/StringBuffer
      92: dup
      93: ldc           #10                 // String 54075,
      95: invokespecial #31                 // Method java/lang/StringBuffer."<init>":(Ljava/lang/String;)V
      98: iload_0
      99: invokevirtual #33                 // Method java/lang/StringBuffer.append:(I)Ljava/lang/StringBuffer;
     102: ldc           #8                  // String ,
     104: invokevirtual #35                 // Method java/lang/StringBuffer.append:(Ljava/lang/String;)Ljava/lang/StringBuffer;
     107: iload_1
     108: invokevirtual #36                 // Method java/lang/StringBuffer.append:(Z)Ljava/lang/StringBuffer;
     111: ldc           #8                  // String ,
     113: invokevirtual #35                 // Method java/lang/StringBuffer.append:(Ljava/lang/String;)Ljava/lang/StringBuffer;
     116: aload_2
     117: invokevirtual #77                 // Method java/lang/Throwable.toString:()Ljava/lang/String;
     120: invokevirtual #35                 // Method java/lang/StringBuffer.append:(Ljava/lang/String;)Ljava/lang/StringBuffer;
     123: invokevirtual #76                 // Method java/lang/StringBuffer.toString:()Ljava/lang/String;
     126: invokestatic  #65                 // Method sign/signlink.reporterror:(Ljava/lang/String;)V
     129: new           #24                 // class java/lang/RuntimeException
     132: dup
     133: invokespecial #29                 // Method java/lang/RuntimeException."<init>":()V
     136: athrow
     137: return
    Exception table:
       from    to  target type
           4    87    88   Class java/lang/RuntimeException

  public static final void a(XTGLDHGX, int);
    Code:
       0: getstatic     #289                // Field XHHRODPC.l:Z
       3: istore_3
       4: iconst_0
       5: putstatic     #60                 // Field M:I
       8: iload_1
       9: ifeq          26
      12: getstatic     #51                 // Field z:Z
      15: ifeq          22
      18: iconst_0
      19: goto          23
      22: iconst_1
      23: putstatic     #51                 // Field z:Z
      26: iconst_0
      27: istore_2
      28: iload_3
      29: ifeq          110
      32: getstatic     #75                 // Field N:[LDSMJIEPN;
      35: iload_2
      36: new           #20                 // class DSMJIEPN
      39: dup
      40: aload_0
      41: iload_2
      42: invokestatic  #81                 // Method java/lang/String.valueOf:(I)Ljava/lang/String;
      45: iconst_0
      46: invokespecial #30                 // Method DSMJIEPN."<init>":(LXTGLDHGX;Ljava/lang/String;I)V
      49: aastore
      50: getstatic     #57                 // Field A:Z
      53: ifeq          83
      56: getstatic     #75                 // Field N:[LDSMJIEPN;
      59: iload_2
      60: aaload
      61: getfield      #61                 // Field DSMJIEPN.H:I
      64: sipush        128
      67: if_icmpne     83
      70: getstatic     #75                 // Field N:[LDSMJIEPN;
      73: iload_2
      74: aaload
      75: iconst_0
      76: invokevirtual #52                 // Method DSMJIEPN.b:(Z)V
      79: iload_3
      80: ifeq          92
      83: getstatic     #75                 // Field N:[LDSMJIEPN;
      86: iload_2
      87: aaload
      88: iconst_0
      89: invokevirtual #80                 // Method DSMJIEPN.c:(Z)V
      92: getstatic     #60                 // Field M:I
      95: iconst_1
      96: iadd
      97: putstatic     #60                 // Field M:I
     100: goto          107
     103: pop
     104: goto          107
     107: iinc          2, 1
     110: iload_2
     111: bipush        50
     113: if_icmplt     32
     116: return
     117: astore_2
     118: new           #26                 // class java/lang/StringBuffer
     121: dup
     122: ldc           #17                 // String 98799,
     124: invokespecial #31                 // Method java/lang/StringBuffer."<init>":(Ljava/lang/String;)V
     127: aload_0
     128: invokevirtual #34                 // Method java/lang/StringBuffer.append:(Ljava/lang/Object;)Ljava/lang/StringBuffer;
     131: ldc           #8                  // String ,
     133: invokevirtual #35                 // Method java/lang/StringBuffer.append:(Ljava/lang/String;)Ljava/lang/StringBuffer;
     136: iload_1
     137: invokevirtual #33                 // Method java/lang/StringBuffer.append:(I)Ljava/lang/StringBuffer;
     140: ldc           #8                  // String ,
     142: invokevirtual #35                 // Method java/lang/StringBuffer.append:(Ljava/lang/String;)Ljava/lang/StringBuffer;
     145: aload_2
     146: invokevirtual #77                 // Method java/lang/Throwable.toString:()Ljava/lang/String;
     149: invokevirtual #35                 // Method java/lang/StringBuffer.append:(Ljava/lang/String;)Ljava/lang/StringBuffer;
     152: invokevirtual #76                 // Method java/lang/StringBuffer.toString:()Ljava/lang/String;
     155: invokestatic  #65                 // Method sign/signlink.reporterror:(Ljava/lang/String;)V
     158: new           #24                 // class java/lang/RuntimeException
     161: dup
     162: invokespecial #29                 // Method java/lang/RuntimeException."<init>":()V
     165: athrow
    Exception table:
       from    to  target type
          32   100   103   Class java/lang/Exception
           4   116   117   Class java/lang/RuntimeException

  public static final int a(int, int);
    Code:
       0: iload_1
       1: sipush        12660
       4: if_icmpeq     9
       7: iconst_2
       8: ireturn
       9: getstatic     #73                 // Field P:[I
      12: iload_0
      13: iaload
      14: ifeq          23
      17: getstatic     #73                 // Field P:[I
      20: iload_0
      21: iaload
      22: ireturn
      23: iconst_0
      24: istore_2
      25: iconst_0
      26: istore_3
      27: iconst_0
      28: istore        4
      30: getstatic     #49                 // Field W:[[I
      33: iload_0
      34: aaload
      35: arraylength
      36: istore        5
      38: iconst_0
      39: istore        6
      41: getstatic     #289                // Field XHHRODPC.l:Z
      44: ifeq          103
      47: iload_2
      48: getstatic     #49                 // Field W:[[I
      51: iload_0
      52: aaload
      53: iload         6
      55: iaload
      56: bipush        16
      58: ishr
      59: sipush        255
      62: iand
      63: iadd
      64: istore_2
      65: iload_3
      66: getstatic     #49                 // Field W:[[I
      69: iload_0
      70: aaload
      71: iload         6
      73: iaload
      74: bipush        8
      76: ishr
      77: sipush        255
      80: iand
      81: iadd
      82: istore_3
      83: iload         4
      85: getstatic     #49                 // Field W:[[I
      88: iload_0
      89: aaload
      90: iload         6
      92: iaload
      93: sipush        255
      96: iand
      97: iadd
      98: istore        4
     100: iinc          6, 1
     103: iload         6
     105: iload         5
     107: if_icmplt     47
     110: iload_2
     111: iload         5
     113: idiv
     114: bipush        16
     116: ishl
     117: iload_3
     118: iload         5
     120: idiv
     121: bipush        8
     123: ishl
     124: iadd
     125: iload         4
     127: iload         5
     129: idiv
     130: iadd
     131: istore        7
     133: iload         7
     135: ldc2_w        #90                 // double 1.4d
     138: invokestatic  #48                 // Method a:(ID)I
     141: istore        7
     143: iload         7
     145: ifne          151
     148: iconst_1
     149: istore        7
     151: getstatic     #73                 // Field P:[I
     154: iload_0
     155: iload         7
     157: iastore
     158: iload         7
     160: ireturn
     161: astore_2
     162: new           #26                 // class java/lang/StringBuffer
     165: dup
     166: ldc           #9                  // String 10237,
     168: invokespecial #31                 // Method java/lang/StringBuffer."<init>":(Ljava/lang/String;)V
     171: iload_0
     172: invokevirtual #33                 // Method java/lang/StringBuffer.append:(I)Ljava/lang/StringBuffer;
     175: ldc           #8                  // String ,
     177: invokevirtual #35                 // Method java/lang/StringBuffer.append:(Ljava/lang/String;)Ljava/lang/StringBuffer;
     180: iload_1
     181: invokevirtual #33                 // Method java/lang/StringBuffer.append:(I)Ljava/lang/StringBuffer;
     184: ldc           #8                  // String ,
     186: invokevirtual #35                 // Method java/lang/StringBuffer.append:(Ljava/lang/String;)Ljava/lang/StringBuffer;
     189: aload_2
     190: invokevirtual #77                 // Method java/lang/Throwable.toString:()Ljava/lang/String;
     193: invokevirtual #35                 // Method java/lang/StringBuffer.append:(Ljava/lang/String;)Ljava/lang/StringBuffer;
     196: invokevirtual #76                 // Method java/lang/StringBuffer.toString:()Ljava/lang/String;
     199: invokestatic  #65                 // Method sign/signlink.reporterror:(Ljava/lang/String;)V
     202: new           #24                 // class java/lang/RuntimeException
     205: dup
     206: invokespecial #29                 // Method java/lang/RuntimeException."<init>":()V
     209: athrow
    Exception table:
       from    to  target type
           0   161   161   Class java/lang/RuntimeException

  public static final void b(int, int);
    Code:
       0: getstatic     #72                 // Field S:[[I
       3: iload_0
       4: aaload
       5: ifnonnull     9
       8: return
       9: getstatic     #70                 // Field R:[[I
      12: getstatic     #71                 // Field Q:I
      15: dup
      16: iconst_1
      17: iadd
      18: putstatic     #71                 // Field Q:I
      21: getstatic     #72                 // Field S:[[I
      24: iload_0
      25: aaload
      26: aastore
      27: getstatic     #289                // Field XHHRODPC.l:Z
      30: ifeq          38
      33: bipush        7
      35: putstatic     #55                 // Field x:I
      38: iload_1
      39: ifge          33
      42: getstatic     #72                 // Field S:[[I
      45: iload_0
      46: aconst_null
      47: aastore
      48: return
      49: astore_2
      50: new           #26                 // class java/lang/StringBuffer
      53: dup
      54: ldc           #11                 // String 64331,
      56: invokespecial #31                 // Method java/lang/StringBuffer."<init>":(Ljava/lang/String;)V
      59: iload_0
      60: invokevirtual #33                 // Method java/lang/StringBuffer.append:(I)Ljava/lang/StringBuffer;
      63: ldc           #8                  // String ,
      65: invokevirtual #35                 // Method java/lang/StringBuffer.append:(Ljava/lang/String;)Ljava/lang/StringBuffer;
      68: iload_1
      69: invokevirtual #33                 // Method java/lang/StringBuffer.append:(I)Ljava/lang/StringBuffer;
      72: ldc           #8                  // String ,
      74: invokevirtual #35                 // Method java/lang/StringBuffer.append:(Ljava/lang/String;)Ljava/lang/StringBuffer;
      77: aload_2
      78: invokevirtual #77                 // Method java/lang/Throwable.toString:()Ljava/lang/String;
      81: invokevirtual #35                 // Method java/lang/StringBuffer.append:(Ljava/lang/String;)Ljava/lang/StringBuffer;
      84: invokevirtual #76                 // Method java/lang/StringBuffer.toString:()Ljava/lang/String;
      87: invokestatic  #65                 // Method sign/signlink.reporterror:(Ljava/lang/String;)V
      90: new           #24                 // class java/lang/RuntimeException
      93: dup
      94: invokespecial #29                 // Method java/lang/RuntimeException."<init>":()V
      97: athrow
    Exception table:
       from    to  target type
           0    48    49   Class java/lang/RuntimeException

  public static final int[] d(int);
    Code:
       0: getstatic     #289                // Field XHHRODPC.l:Z
       3: istore        6
       5: getstatic     #58                 // Field T:[I
       8: iload_0
       9: getstatic     #59                 // Field U:I
      12: dup
      13: iconst_1
      14: iadd
      15: putstatic     #59                 // Field U:I
      18: iastore
      19: getstatic     #72                 // Field S:[[I
      22: iload_0
      23: aaload
      24: ifnull        33
      27: getstatic     #72                 // Field S:[[I
      30: iload_0
      31: aaload
      32: areturn
      33: getstatic     #71                 // Field Q:I
      36: ifle          66
      39: getstatic     #70                 // Field R:[[I
      42: getstatic     #71                 // Field Q:I
      45: iconst_1
      46: isub
      47: dup
      48: putstatic     #71                 // Field Q:I
      51: aaload
      52: astore_1
      53: getstatic     #70                 // Field R:[[I
      56: getstatic     #71                 // Field Q:I
      59: aconst_null
      60: aastore
      61: iload         6
      63: ifeq          135
      66: iconst_0
      67: istore_2
      68: iconst_m1
      69: istore_3
      70: iconst_0
      71: istore        4
      73: iload         6
      75: ifeq          115
      78: getstatic     #72                 // Field S:[[I
      81: iload         4
      83: aaload
      84: ifnull        112
      87: getstatic     #58                 // Field T:[I
      90: iload         4
      92: iaload
      93: iload_2
      94: if_icmplt     102
      97: iload_3
      98: iconst_m1
      99: if_icmpne     112
     102: getstatic     #58                 // Field T:[I
     105: iload         4
     107: iaload
     108: istore_2
     109: iload         4
     111: istore_3
     112: iinc          4, 1
     115: iload         4
     117: getstatic     #60                 // Field M:I
     120: if_icmplt     78
     123: getstatic     #72                 // Field S:[[I
     126: iload_3
     127: aaload
     128: astore_1
     129: getstatic     #72                 // Field S:[[I
     132: iload_3
     133: aconst_null
     134: aastore
     135: getstatic     #72                 // Field S:[[I
     138: iload_0
     139: aload_1
     140: aastore
     141: getstatic     #75                 // Field N:[LDSMJIEPN;
     144: iload_0
     145: aaload
     146: astore_2
     147: getstatic     #49                 // Field W:[[I
     150: iload_0
     151: aaload
     152: astore_3
     153: getstatic     #57                 // Field A:Z
     156: ifeq          278
     159: getstatic     #79                 // Field O:[Z
     162: iload_0
     163: iconst_0
     164: bastore
     165: iconst_0
     166: istore        4
     168: iload         6
     170: ifeq          265
     173: aload_1
     174: iload         4
     176: aload_3
     177: aload_2
     178: getfield      #38                 // Field DSMJIEPN.B:[B
     181: iload         4
     183: baload
     184: iaload
     185: ldc           #6                  // int 16316671
     187: iand
     188: dup_x2
     189: iastore
     190: istore        5
     192: iload         5
     194: ifne          203
     197: getstatic     #79                 // Field O:[Z
     200: iload_0
     201: iconst_1
     202: bastore
     203: aload_1
     204: sipush        4096
     207: iload         4
     209: iadd
     210: iload         5
     212: iload         5
     214: iconst_3
     215: iushr
     216: isub
     217: ldc           #6                  // int 16316671
     219: iand
     220: iastore
     221: aload_1
     222: sipush        8192
     225: iload         4
     227: iadd
     228: iload         5
     230: iload         5
     232: iconst_2
     233: iushr
     234: isub
     235: ldc           #6                  // int 16316671
     237: iand
     238: iastore
     239: aload_1
     240: sipush        12288
     243: iload         4
     245: iadd
     246: iload         5
     248: iload         5
     250: iconst_2
     251: iushr
     252: isub
     253: iload         5
     255: iconst_3
     256: iushr
     257: isub
     258: ldc           #6                  // int 16316671
     260: iand
     261: iastore
     262: iinc          4, 1
     265: iload         4
     267: sipush        4096
     270: if_icmplt     173
     273: iload         6
     275: ifeq          499
     278: aload_2
     279: getfield      #82                 // Field DSMJIEPN.D:I
     282: bipush        64
     284: if_icmpne     359
     287: iconst_0
     288: istore        4
     290: iload         6
     292: ifeq          346
     295: iconst_0
     296: istore        5
     298: iload         6
     300: ifeq          335
     303: aload_1
     304: iload         5
     306: iload         4
     308: bipush        7
     310: ishl
     311: iadd
     312: aload_3
     313: aload_2
     314: getfield      #38                 // Field DSMJIEPN.B:[B
     317: iload         5
     319: iconst_1
     320: ishr
     321: iload         4
     323: iconst_1
     324: ishr
     325: bipush        6
     327: ishl
     328: iadd
     329: baload
     330: iaload
     331: iastore
     332: iinc          5, 1
     335: iload         5
     337: sipush        128
     340: if_icmplt     303
     343: iinc          4, 1
     346: iload         4
     348: sipush        128
     351: if_icmplt     295
     354: iload         6
     356: ifeq          391
     359: iconst_0
     360: istore        4
     362: iload         6
     364: ifeq          383
     367: aload_1
     368: iload         4
     370: aload_3
     371: aload_2
     372: getfield      #38                 // Field DSMJIEPN.B:[B
     375: iload         4
     377: baload
     378: iaload
     379: iastore
     380: iinc          4, 1
     383: iload         4
     385: sipush        16384
     388: if_icmplt     367
     391: getstatic     #79                 // Field O:[Z
     394: iload_0
     395: iconst_0
     396: bastore
     397: iconst_0
     398: istore        4
     400: iload         6
     402: ifeq          491
     405: aload_1
     406: iload         4
     408: dup2
     409: iaload
     410: ldc           #6                  // int 16316671
     412: iand
     413: iastore
     414: aload_1
     415: iload         4
     417: iaload
     418: istore        5
     420: iload         5
     422: ifne          431
     425: getstatic     #79                 // Field O:[Z
     428: iload_0
     429: iconst_1
     430: bastore
     431: aload_1
     432: sipush        16384
     435: iload         4
     437: iadd
     438: iload         5
     440: iload         5
     442: iconst_3
     443: iushr
     444: isub
     445: ldc           #6                  // int 16316671
     447: iand
     448: iastore
     449: aload_1
     450: ldc           #1                  // int 32768
     452: iload         4
     454: iadd
     455: iload         5
     457: iload         5
     459: iconst_2
     460: iushr
     461: isub
     462: ldc           #6                  // int 16316671
     464: iand
     465: iastore
     466: aload_1
     467: ldc           #2                  // int 49152
     469: iload         4
     471: iadd
     472: iload         5
     474: iload         5
     476: iconst_2
     477: iushr
     478: isub
     479: iload         5
     481: iconst_3
     482: iushr
     483: isub
     484: ldc           #6                  // int 16316671
     486: iand
     487: iastore
     488: iinc          4, 1
     491: iload         4
     493: sipush        16384
     496: if_icmplt     405
     499: aload_1
     500: areturn

  public static final void a(double, byte);
    Code:
       0: getstatic     #289                // Field XHHRODPC.l:Z
       3: istore        28
       5: iload_2
       6: bipush        9
       8: if_icmpeq     25
      11: iconst_1
      12: istore_3
      13: iload         28
      15: ifeq          21
      18: iinc          3, 1
      21: iload_3
      22: ifgt          18
      25: dload_0
      26: invokestatic  #64                 // Method java/lang/Math.random:()D
      29: ldc2_w        #100                // double 0.03d
      32: dmul
      33: ldc2_w        #104                // double 0.015d
      36: dsub
      37: dadd
      38: dstore_0
      39: iconst_0
      40: istore_3
      41: iconst_0
      42: istore        4
      44: iload         28
      46: ifeq          581
      49: iload         4
      51: bipush        8
      53: idiv
      54: i2d
      55: ldc2_w        #102                // double 64.0d
      58: ddiv
      59: ldc2_w        #114                // double 0.0078125d
      62: dadd
      63: dstore        5
      65: iload         4
      67: bipush        7
      69: iand
      70: i2d
      71: ldc2_w        #98                 // double 8.0d
      74: ddiv
      75: ldc2_w        #110                // double 0.0625d
      78: dadd
      79: dstore        7
      81: iconst_0
      82: istore        9
      84: iload         28
      86: ifeq          570
      89: iload         9
      91: i2d
      92: ldc2_w        #106                // double 128.0d
      95: ddiv
      96: dstore        10
      98: dload         10
     100: dstore        12
     102: dload         10
     104: dstore        14
     106: dload         10
     108: dstore        16
     110: dload         7
     112: dconst_0
     113: dcmpl
     114: ifeq          498
     117: dload         10
     119: ldc2_w        #88                 // double 0.5d
     122: dcmpg
     123: ifge          140
     126: dload         10
     128: dconst_1
     129: dload         7
     131: dadd
     132: dmul
     133: dstore        18
     135: iload         28
     137: ifeq          153
     140: dload         10
     142: dload         7
     144: dadd
     145: dload         10
     147: dload         7
     149: dmul
     150: dsub
     151: dstore        18
     153: ldc2_w        #92                 // double 2.0d
     156: dload         10
     158: dmul
     159: dload         18
     161: dsub
     162: dstore        20
     164: dload         5
     166: ldc2_w        #118                // double 0.3333333333333333d
     169: dadd
     170: dstore        22
     172: dload         22
     174: dconst_1
     175: dcmpl
     176: ifle          185
     179: dload         22
     181: dconst_1
     182: dsub
     183: dstore        22
     185: dload         5
     187: dstore        24
     189: dload         5
     191: ldc2_w        #118                // double 0.3333333333333333d
     194: dsub
     195: dstore        26
     197: dload         26
     199: dconst_0
     200: dcmpg
     201: ifge          210
     204: dload         26
     206: dconst_1
     207: dadd
     208: dstore        26
     210: ldc2_w        #96                 // double 6.0d
     213: dload         22
     215: dmul
     216: dconst_1
     217: dcmpg
     218: ifge          243
     221: dload         20
     223: dload         18
     225: dload         20
     227: dsub
     228: ldc2_w        #96                 // double 6.0d
     231: dmul
     232: dload         22
     234: dmul
     235: dadd
     236: dstore        12
     238: iload         28
     240: ifeq          306
     243: ldc2_w        #92                 // double 2.0d
     246: dload         22
     248: dmul
     249: dconst_1
     250: dcmpg
     251: ifge          263
     254: dload         18
     256: dstore        12
     258: iload         28
     260: ifeq          306
     263: ldc2_w        #94                 // double 3.0d
     266: dload         22
     268: dmul
     269: ldc2_w        #92                 // double 2.0d
     272: dcmpg
     273: ifge          302
     276: dload         20
     278: dload         18
     280: dload         20
     282: dsub
     283: ldc2_w        #120                // double 0.6666666666666666d
     286: dload         22
     288: dsub
     289: dmul
     290: ldc2_w        #96                 // double 6.0d
     293: dmul
     294: dadd
     295: dstore        12
     297: iload         28
     299: ifeq          306
     302: dload         20
     304: dstore        12
     306: ldc2_w        #96                 // double 6.0d
     309: dload         24
     311: dmul
     312: dconst_1
     313: dcmpg
     314: ifge          339
     317: dload         20
     319: dload         18
     321: dload         20
     323: dsub
     324: ldc2_w        #96                 // double 6.0d
     327: dmul
     328: dload         24
     330: dmul
     331: dadd
     332: dstore        14
     334: iload         28
     336: ifeq          402
     339: ldc2_w        #92                 // double 2.0d
     342: dload         24
     344: dmul
     345: dconst_1
     346: dcmpg
     347: ifge          359
     350: dload         18
     352: dstore        14
     354: iload         28
     356: ifeq          402
     359: ldc2_w        #94                 // double 3.0d
     362: dload         24
     364: dmul
     365: ldc2_w        #92                 // double 2.0d
     368: dcmpg
     369: ifge          398
     372: dload         20
     374: dload         18
     376: dload         20
     378: dsub
     379: ldc2_w        #120                // double 0.6666666666666666d
     382: dload         24
     384: dsub
     385: dmul
     386: ldc2_w        #96                 // double 6.0d
     389: dmul
     390: dadd
     391: dstore        14
     393: iload         28
     395: ifeq          402
     398: dload         20
     400: dstore        14
     402: ldc2_w        #96                 // double 6.0d
     405: dload         26
     407: dmul
     408: dconst_1
     409: dcmpg
     410: ifge          435
     413: dload         20
     415: dload         18
     417: dload         20
     419: dsub
     420: ldc2_w        #96                 // double 6.0d
     423: dmul
     424: dload         26
     426: dmul
     427: dadd
     428: dstore        16
     430: iload         28
     432: ifeq          498
     435: ldc2_w        #92                 // double 2.0d
     438: dload         26
     440: dmul
     441: dconst_1
     442: dcmpg
     443: ifge          455
     446: dload         18
     448: dstore        16
     450: iload         28
     452: ifeq          498
     455: ldc2_w        #94                 // double 3.0d
     458: dload         26
     460: dmul
     461: ldc2_w        #92                 // double 2.0d
     464: dcmpg
     465: ifge          494
     468: dload         20
     470: dload         18
     472: dload         20
     474: dsub
     475: ldc2_w        #120                // double 0.6666666666666666d
     478: dload         26
     480: dsub
     481: dmul
     482: ldc2_w        #96                 // double 6.0d
     485: dmul
     486: dadd
     487: dstore        16
     489: iload         28
     491: ifeq          498
     494: dload         20
     496: dstore        16
     498: dload         12
     500: ldc2_w        #108                // double 256.0d
     503: dmul
     504: d2i
     505: istore        18
     507: dload         14
     509: ldc2_w        #108                // double 256.0d
     512: dmul
     513: d2i
     514: istore        19
     516: dload         16
     518: ldc2_w        #108                // double 256.0d
     521: dmul
     522: d2i
     523: istore        20
     525: iload         18
     527: bipush        16
     529: ishl
     530: iload         19
     532: bipush        8
     534: ishl
     535: iadd
     536: iload         20
     538: iadd
     539: istore        21
     541: iload         21
     543: dload_0
     544: invokestatic  #48                 // Method a:(ID)I
     547: istore        21
     549: iload         21
     551: ifne          557
     554: iconst_1
     555: istore        21
     557: getstatic     #41                 // Field V:[I
     560: iload_3
     561: iinc          3, 1
     564: iload         21
     566: iastore
     567: iinc          9, 1
     570: iload         9
     572: sipush        128
     575: if_icmplt     89
     578: iinc          4, 1
     581: iload         4
     583: sipush        512
     586: if_icmplt     49
     589: iconst_0
     590: istore        5
     592: iload         28
     594: ifeq          698
     597: getstatic     #75                 // Field N:[LDSMJIEPN;
     600: iload         5
     602: aaload
     603: ifnull        695
     606: getstatic     #75                 // Field N:[LDSMJIEPN;
     609: iload         5
     611: aaload
     612: getfield      #37                 // Field DSMJIEPN.C:[I
     615: astore        6
     617: getstatic     #49                 // Field W:[[I
     620: iload         5
     622: aload         6
     624: arraylength
     625: newarray       int
     627: aastore
     628: iconst_0
     629: istore        7
     631: iload         28
     633: ifeq          687
     636: getstatic     #49                 // Field W:[[I
     639: iload         5
     641: aaload
     642: iload         7
     644: aload         6
     646: iload         7
     648: iaload
     649: dload_0
     650: invokestatic  #48                 // Method a:(ID)I
     653: iastore
     654: getstatic     #49                 // Field W:[[I
     657: iload         5
     659: aaload
     660: iload         7
     662: iaload
     663: ldc           #6                  // int 16316671
     665: iand
     666: ifne          684
     669: iload         7
     671: ifeq          684
     674: getstatic     #49                 // Field W:[[I
     677: iload         5
     679: aaload
     680: iload         7
     682: iconst_1
     683: iastore
     684: iinc          7, 1
     687: iload         7
     689: aload         6
     691: arraylength
     692: if_icmplt     636
     695: iinc          5, 1
     698: iload         5
     700: bipush        50
     702: if_icmplt     597
     705: iconst_0
     706: istore        6
     708: iload         28
     710: ifeq          724
     713: iload         6
     715: sipush        -477
     718: invokestatic  #40                 // Method b:(II)V
     721: iinc          6, 1
     724: iload         6
     726: bipush        50
     728: if_icmplt     713
     731: return
     732: astore_3
     733: new           #26                 // class java/lang/StringBuffer
     736: dup
     737: ldc           #12                 // String 71578,
     739: invokespecial #31                 // Method java/lang/StringBuffer."<init>":(Ljava/lang/String;)V
     742: dload_0
     743: invokevirtual #32                 // Method java/lang/StringBuffer.append:(D)Ljava/lang/StringBuffer;
     746: ldc           #8                  // String ,
     748: invokevirtual #35                 // Method java/lang/StringBuffer.append:(Ljava/lang/String;)Ljava/lang/StringBuffer;
     751: iload_2
     752: invokevirtual #33                 // Method java/lang/StringBuffer.append:(I)Ljava/lang/StringBuffer;
     755: ldc           #8                  // String ,
     757: invokevirtual #35                 // Method java/lang/StringBuffer.append:(Ljava/lang/String;)Ljava/lang/StringBuffer;
     760: aload_3
     761: invokevirtual #77                 // Method java/lang/Throwable.toString:()Ljava/lang/String;
     764: invokevirtual #35                 // Method java/lang/StringBuffer.append:(Ljava/lang/String;)Ljava/lang/StringBuffer;
     767: invokevirtual #76                 // Method java/lang/StringBuffer.toString:()Ljava/lang/String;
     770: invokestatic  #65                 // Method sign/signlink.reporterror:(Ljava/lang/String;)V
     773: new           #24                 // class java/lang/RuntimeException
     776: dup
     777: invokespecial #29                 // Method java/lang/RuntimeException."<init>":()V
     780: athrow
    Exception table:
       from    to  target type
           5   731   732   Class java/lang/RuntimeException

  public static int a(int, double);
    Code:
       0: iload_0
       1: bipush        16
       3: ishr
       4: i2d
       5: ldc2_w        #108                // double 256.0d
       8: ddiv
       9: dstore_3
      10: iload_0
      11: bipush        8
      13: ishr
      14: sipush        255
      17: iand
      18: i2d
      19: ldc2_w        #108                // double 256.0d
      22: ddiv
      23: dstore        5
      25: iload_0
      26: sipush        255
      29: iand
      30: i2d
      31: ldc2_w        #108                // double 256.0d
      34: ddiv
      35: dstore        7
      37: dload_3
      38: dload_1
      39: invokestatic  #63                 // Method java/lang/Math.pow:(DD)D
      42: dstore_3
      43: dload         5
      45: dload_1
      46: invokestatic  #63                 // Method java/lang/Math.pow:(DD)D
      49: dstore        5
      51: dload         7
      53: dload_1
      54: invokestatic  #63                 // Method java/lang/Math.pow:(DD)D
      57: dstore        7
      59: dload_3
      60: ldc2_w        #108                // double 256.0d
      63: dmul
      64: d2i
      65: istore        9
      67: dload         5
      69: ldc2_w        #108                // double 256.0d
      72: dmul
      73: d2i
      74: istore        10
      76: dload         7
      78: ldc2_w        #108                // double 256.0d
      81: dmul
      82: d2i
      83: istore        11
      85: iload         9
      87: bipush        16
      89: ishl
      90: iload         10
      92: bipush        8
      94: ishl
      95: iadd
      96: iload         11
      98: iadd
      99: ireturn

  public static final void a(int, int, int, int, int, int, int, int, int);
    Code:
       0: getstatic     #289                // Field XHHRODPC.l:Z
       3: istore        15
       5: iconst_0
       6: istore        9
       8: iconst_0
       9: istore        10
      11: iload_1
      12: iload_0
      13: if_icmpeq     43
      16: iload         4
      18: iload_3
      19: isub
      20: bipush        16
      22: ishl
      23: iload_1
      24: iload_0
      25: isub
      26: idiv
      27: istore        9
      29: iload         7
      31: iload         6
      33: isub
      34: bipush        15
      36: ishl
      37: iload_1
      38: iload_0
      39: isub
      40: idiv
      41: istore        10
      43: iconst_0
      44: istore        11
      46: iconst_0
      47: istore        12
      49: iload_2
      50: iload_1
      51: if_icmpeq     82
      54: iload         5
      56: iload         4
      58: isub
      59: bipush        16
      61: ishl
      62: iload_2
      63: iload_1
      64: isub
      65: idiv
      66: istore        11
      68: iload         8
      70: iload         7
      72: isub
      73: bipush        15
      75: ishl
      76: iload_2
      77: iload_1
      78: isub
      79: idiv
      80: istore        12
      82: iconst_0
      83: istore        13
      85: iconst_0
      86: istore        14
      88: iload_2
      89: iload_0
      90: if_icmpeq     120
      93: iload_3
      94: iload         5
      96: isub
      97: bipush        16
      99: ishl
     100: iload_0
     101: iload_2
     102: isub
     103: idiv
     104: istore        13
     106: iload         6
     108: iload         8
     110: isub
     111: bipush        15
     113: ishl
     114: iload_0
     115: iload_2
     116: isub
     117: idiv
     118: istore        14
     120: iload_0
     121: iload_1
     122: if_icmpgt     1047
     125: iload_0
     126: iload_2
     127: if_icmpgt     1047
     130: iload_0
     131: getstatic     #86                 // Field AFCKELYG.q:I
     134: if_icmplt     138
     137: return
     138: iload_1
     139: getstatic     #86                 // Field AFCKELYG.q:I
     142: if_icmple     149
     145: getstatic     #86                 // Field AFCKELYG.q:I
     148: istore_1
     149: iload_2
     150: getstatic     #86                 // Field AFCKELYG.q:I
     153: if_icmple     160
     156: getstatic     #86                 // Field AFCKELYG.q:I
     159: istore_2
     160: iload_1
     161: iload_2
     162: if_icmpge     609
     165: iload_3
     166: bipush        16
     168: ishl
     169: dup
     170: istore_3
     171: istore        5
     173: iload         6
     175: bipush        15
     177: ishl
     178: dup
     179: istore        6
     181: istore        8
     183: iload_0
     184: ifge          223
     187: iload         5
     189: iload         13
     191: iload_0
     192: imul
     193: isub
     194: istore        5
     196: iload_3
     197: iload         9
     199: iload_0
     200: imul
     201: isub
     202: istore_3
     203: iload         8
     205: iload         14
     207: iload_0
     208: imul
     209: isub
     210: istore        8
     212: iload         6
     214: iload         10
     216: iload_0
     217: imul
     218: isub
     219: istore        6
     221: iconst_0
     222: istore_0
     223: iload         4
     225: bipush        16
     227: ishl
     228: istore        4
     230: iload         7
     232: bipush        15
     234: ishl
     235: istore        7
     237: iload_1
     238: ifge          261
     241: iload         4
     243: iload         11
     245: iload_1
     246: imul
     247: isub
     248: istore        4
     250: iload         7
     252: iload         12
     254: iload_1
     255: imul
     256: isub
     257: istore        7
     259: iconst_0
     260: istore_1
     261: iload_0
     262: iload_1
     263: if_icmpeq     273
     266: iload         13
     268: iload         9
     270: if_icmplt     285
     273: iload_0
     274: iload_1
     275: if_icmpne     447
     278: iload         13
     280: iload         11
     282: if_icmple     447
     285: iload_2
     286: iload_1
     287: isub
     288: istore_2
     289: iload_1
     290: iload_0
     291: isub
     292: istore_1
     293: getstatic     #66                 // Field L:[I
     296: iload_0
     297: iaload
     298: istore_0
     299: iload         15
     301: ifeq          364
     304: getstatic     #62                 // Field AFCKELYG.m:[I
     307: iload_0
     308: iconst_0
     309: iconst_0
     310: iload         5
     312: bipush        16
     314: ishr
     315: iload_3
     316: bipush        16
     318: ishr
     319: iload         8
     321: bipush        7
     323: ishr
     324: iload         6
     326: bipush        7
     328: ishr
     329: invokestatic  #50                 // Method a:([IIIIIIII)V
     332: iload         5
     334: iload         13
     336: iadd
     337: istore        5
     339: iload_3
     340: iload         9
     342: iadd
     343: istore_3
     344: iload         8
     346: iload         14
     348: iadd
     349: istore        8
     351: iload         6
     353: iload         10
     355: iadd
     356: istore        6
     358: iload_0
     359: getstatic     #83                 // Field AFCKELYG.n:I
     362: iadd
     363: istore_0
     364: iinc          1, -1
     367: iload_1
     368: ifge          304
     371: iload         15
     373: ifeq          439
     376: getstatic     #62                 // Field AFCKELYG.m:[I
     379: iload_0
     380: iconst_0
     381: iconst_0
     382: iload         5
     384: bipush        16
     386: ishr
     387: iload         4
     389: bipush        16
     391: ishr
     392: iload         8
     394: bipush        7
     396: ishr
     397: iload         7
     399: bipush        7
     401: ishr
     402: invokestatic  #50                 // Method a:([IIIIIIII)V
     405: iload         5
     407: iload         13
     409: iadd
     410: istore        5
     412: iload         4
     414: iload         11
     416: iadd
     417: istore        4
     419: iload         8
     421: iload         14
     423: iadd
     424: istore        8
     426: iload         7
     428: iload         12
     430: iadd
     431: istore        7
     433: iload_0
     434: getstatic     #83                 // Field AFCKELYG.n:I
     437: iadd
     438: istore_0
     439: iinc          2, -1
     442: iload_2
     443: ifge          376
     446: return
     447: iload_2
     448: iload_1
     449: isub
     450: istore_2
     451: iload_1
     452: iload_0
     453: isub
     454: istore_1
     455: getstatic     #66                 // Field L:[I
     458: iload_0
     459: iaload
     460: istore_0
     461: iload         15
     463: ifeq          526
     466: getstatic     #62                 // Field AFCKELYG.m:[I
     469: iload_0
     470: iconst_0
     471: iconst_0
     472: iload_3
     473: bipush        16
     475: ishr
     476: iload         5
     478: bipush        16
     480: ishr
     481: iload         6
     483: bipush        7
     485: ishr
     486: iload         8
     488: bipush        7
     490: ishr
     491: invokestatic  #50                 // Method a:([IIIIIIII)V
     494: iload         5
     496: iload         13
     498: iadd
     499: istore        5
     501: iload_3
     502: iload         9
     504: iadd
     505: istore_3
     506: iload         8
     508: iload         14
     510: iadd
     511: istore        8
     513: iload         6
     515: iload         10
     517: iadd
     518: istore        6
     520: iload_0
     521: getstatic     #83                 // Field AFCKELYG.n:I
     524: iadd
     525: istore_0
     526: iinc          1, -1
     529: iload_1
     530: ifge          466
     533: iload         15
     535: ifeq          601
     538: getstatic     #62                 // Field AFCKELYG.m:[I
     541: iload_0
     542: iconst_0
     543: iconst_0
     544: iload         4
     546: bipush        16
     548: ishr
     549: iload         5
     551: bipush        16
     553: ishr
     554: iload         7
     556: bipush        7
     558: ishr
     559: iload         8
     561: bipush        7
     563: ishr
     564: invokestatic  #50                 // Method a:([IIIIIIII)V
     567: iload         5
     569: iload         13
     571: iadd
     572: istore        5
     574: iload         4
     576: iload         11
     578: iadd
     579: istore        4
     581: iload         8
     583: iload         14
     585: iadd
     586: istore        8
     588: iload         7
     590: iload         12
     592: iadd
     593: istore        7
     595: iload_0
     596: getstatic     #83                 // Field AFCKELYG.n:I
     599: iadd
     600: istore_0
     601: iinc          2, -1
     604: iload_2
     605: ifge          538
     608: return
     609: iload_3
     610: bipush        16
     612: ishl
     613: dup
     614: istore_3
     615: istore        4
     617: iload         6
     619: bipush        15
     621: ishl
     622: dup
     623: istore        6
     625: istore        7
     627: iload_0
     628: ifge          667
     631: iload         4
     633: iload         13
     635: iload_0
     636: imul
     637: isub
     638: istore        4
     640: iload_3
     641: iload         9
     643: iload_0
     644: imul
     645: isub
     646: istore_3
     647: iload         7
     649: iload         14
     651: iload_0
     652: imul
     653: isub
     654: istore        7
     656: iload         6
     658: iload         10
     660: iload_0
     661: imul
     662: isub
     663: istore        6
     665: iconst_0
     666: istore_0
     667: iload         5
     669: bipush        16
     671: ishl
     672: istore        5
     674: iload         8
     676: bipush        15
     678: ishl
     679: istore        8
     681: iload_2
     682: ifge          705
     685: iload         5
     687: iload         11
     689: iload_2
     690: imul
     691: isub
     692: istore        5
     694: iload         8
     696: iload         12
     698: iload_2
     699: imul
     700: isub
     701: istore        8
     703: iconst_0
     704: istore_2
     705: iload_0
     706: iload_2
     707: if_icmpeq     717
     710: iload         13
     712: iload         9
     714: if_icmplt     729
     717: iload_0
     718: iload_2
     719: if_icmpne     888
     722: iload         11
     724: iload         9
     726: if_icmple     888
     729: iload_1
     730: iload_2
     731: isub
     732: istore_1
     733: iload_2
     734: iload_0
     735: isub
     736: istore_2
     737: getstatic     #66                 // Field L:[I
     740: iload_0
     741: iaload
     742: istore_0
     743: iload         15
     745: ifeq          808
     748: getstatic     #62                 // Field AFCKELYG.m:[I
     751: iload_0
     752: iconst_0
     753: iconst_0
     754: iload         4
     756: bipush        16
     758: ishr
     759: iload_3
     760: bipush        16
     762: ishr
     763: iload         7
     765: bipush        7
     767: ishr
     768: iload         6
     770: bipush        7
     772: ishr
     773: invokestatic  #50                 // Method a:([IIIIIIII)V
     776: iload         4
     778: iload         13
     780: iadd
     781: istore        4
     783: iload_3
     784: iload         9
     786: iadd
     787: istore_3
     788: iload         7
     790: iload         14
     792: iadd
     793: istore        7
     795: iload         6
     797: iload         10
     799: iadd
     800: istore        6
     802: iload_0
     803: getstatic     #83                 // Field AFCKELYG.n:I
     806: iadd
     807: istore_0
     808: iinc          2, -1
     811: iload_2
     812: ifge          748
     815: iload         15
     817: ifeq          880
     820: getstatic     #62                 // Field AFCKELYG.m:[I
     823: iload_0
     824: iconst_0
     825: iconst_0
     826: iload         5
     828: bipush        16
     830: ishr
     831: iload_3
     832: bipush        16
     834: ishr
     835: iload         8
     837: bipush        7
     839: ishr
     840: iload         6
     842: bipush        7
     844: ishr
     845: invokestatic  #50                 // Method a:([IIIIIIII)V
     848: iload         5
     850: iload         11
     852: iadd
     853: istore        5
     855: iload_3
     856: iload         9
     858: iadd
     859: istore_3
     860: iload         8
     862: iload         12
     864: iadd
     865: istore        8
     867: iload         6
     869: iload         10
     871: iadd
     872: istore        6
     874: iload_0
     875: getstatic     #83                 // Field AFCKELYG.n:I
     878: iadd
     879: istore_0
     880: iinc          1, -1
     883: iload_1
     884: ifge          820
     887: return
     888: iload_1
     889: iload_2
     890: isub
     891: istore_1
     892: iload_2
     893: iload_0
     894: isub
     895: istore_2
     896: getstatic     #66                 // Field L:[I
     899: iload_0
     900: iaload
     901: istore_0
     902: iload         15
     904: ifeq          967
     907: getstatic     #62                 // Field AFCKELYG.m:[I
     910: iload_0
     911: iconst_0
     912: iconst_0
     913: iload_3
     914: bipush        16
     916: ishr
     917: iload         4
     919: bipush        16
     921: ishr
     922: iload         6
     924: bipush        7
     926: ishr
     927: iload         7
     929: bipush        7
     931: ishr
     932: invokestatic  #50                 // Method a:([IIIIIIII)V
     935: iload         4
     937: iload         13
     939: iadd
     940: istore        4
     942: iload_3
     943: iload         9
     945: iadd
     946: istore_3
     947: iload         7
     949: iload         14
     951: iadd
     952: istore        7
     954: iload         6
     956: iload         10
     958: iadd
     959: istore        6
     961: iload_0
     962: getstatic     #83                 // Field AFCKELYG.n:I
     965: iadd
     966: istore_0
     967: iinc          2, -1
     970: iload_2
     971: ifge          907
     974: iload         15
     976: ifeq          1039
     979: getstatic     #62                 // Field AFCKELYG.m:[I
     982: iload_0
     983: iconst_0
     984: iconst_0
     985: iload_3
     986: bipush        16
     988: ishr
     989: iload         5
     991: bipush        16
     993: ishr
     994: iload         6
     996: bipush        7
     998: ishr
     999: iload         8
    1001: bipush        7
    1003: ishr
    1004: invokestatic  #50                 // Method a:([IIIIIIII)V
    1007: iload         5
    1009: iload         11
    1011: iadd
    1012: istore        5
    1014: iload_3
    1015: iload         9
    1017: iadd
    1018: istore_3
    1019: iload         8
    1021: iload         12
    1023: iadd
    1024: istore        8
    1026: iload         6
    1028: iload         10
    1030: iadd
    1031: istore        6
    1033: iload_0
    1034: getstatic     #83                 // Field AFCKELYG.n:I
    1037: iadd
    1038: istore_0
    1039: iinc          1, -1
    1042: iload_1
    1043: ifge          979
    1046: return
    1047: iload_1
    1048: iload_2
    1049: if_icmpgt     1953
    1052: iload_1
    1053: getstatic     #86                 // Field AFCKELYG.q:I
    1056: if_icmplt     1060
    1059: return
    1060: iload_2
    1061: getstatic     #86                 // Field AFCKELYG.q:I
    1064: if_icmple     1071
    1067: getstatic     #86                 // Field AFCKELYG.q:I
    1070: istore_2
    1071: iload_0
    1072: getstatic     #86                 // Field AFCKELYG.q:I
    1075: if_icmple     1082
    1078: getstatic     #86                 // Field AFCKELYG.q:I
    1081: istore_0
    1082: iload_2
    1083: iload_0
    1084: if_icmpge     1526
    1087: iload         4
    1089: bipush        16
    1091: ishl
    1092: dup
    1093: istore        4
    1095: istore_3
    1096: iload         7
    1098: bipush        15
    1100: ishl
    1101: dup
    1102: istore        7
    1104: istore        6
    1106: iload_1
    1107: ifge          1146
    1110: iload_3
    1111: iload         9
    1113: iload_1
    1114: imul
    1115: isub
    1116: istore_3
    1117: iload         4
    1119: iload         11
    1121: iload_1
    1122: imul
    1123: isub
    1124: istore        4
    1126: iload         6
    1128: iload         10
    1130: iload_1
    1131: imul
    1132: isub
    1133: istore        6
    1135: iload         7
    1137: iload         12
    1139: iload_1
    1140: imul
    1141: isub
    1142: istore        7
    1144: iconst_0
    1145: istore_1
    1146: iload         5
    1148: bipush        16
    1150: ishl
    1151: istore        5
    1153: iload         8
    1155: bipush        15
    1157: ishl
    1158: istore        8
    1160: iload_2
    1161: ifge          1184
    1164: iload         5
    1166: iload         13
    1168: iload_2
    1169: imul
    1170: isub
    1171: istore        5
    1173: iload         8
    1175: iload         14
    1177: iload_2
    1178: imul
    1179: isub
    1180: istore        8
    1182: iconst_0
    1183: istore_2
    1184: iload_1
    1185: iload_2
    1186: if_icmpeq     1196
    1189: iload         9
    1191: iload         11
    1193: if_icmplt     1208
    1196: iload_1
    1197: iload_2
    1198: if_icmpne     1367
    1201: iload         9
    1203: iload         13
    1205: if_icmple     1367
    1208: iload_0
    1209: iload_2
    1210: isub
    1211: istore_0
    1212: iload_2
    1213: iload_1
    1214: isub
    1215: istore_2
    1216: getstatic     #66                 // Field L:[I
    1219: iload_1
    1220: iaload
    1221: istore_1
    1222: iload         15
    1224: ifeq          1287
    1227: getstatic     #62                 // Field AFCKELYG.m:[I
    1230: iload_1
    1231: iconst_0
    1232: iconst_0
    1233: iload_3
    1234: bipush        16
    1236: ishr
    1237: iload         4
    1239: bipush        16
    1241: ishr
    1242: iload         6
    1244: bipush        7
    1246: ishr
    1247: iload         7
    1249: bipush        7
    1251: ishr
    1252: invokestatic  #50                 // Method a:([IIIIIIII)V
    1255: iload_3
    1256: iload         9
    1258: iadd
    1259: istore_3
    1260: iload         4
    1262: iload         11
    1264: iadd
    1265: istore        4
    1267: iload         6
    1269: iload         10
    1271: iadd
    1272: istore        6
    1274: iload         7
    1276: iload         12
    1278: iadd
    1279: istore        7
    1281: iload_1
    1282: getstatic     #83                 // Field AFCKELYG.n:I
    1285: iadd
    1286: istore_1
    1287: iinc          2, -1
    1290: iload_2
    1291: ifge          1227
    1294: iload         15
    1296: ifeq          1359
    1299: getstatic     #62                 // Field AFCKELYG.m:[I
    1302: iload_1
    1303: iconst_0
    1304: iconst_0
    1305: iload_3
    1306: bipush        16
    1308: ishr
    1309: iload         5
    1311: bipush        16
    1313: ishr
    1314: iload         6
    1316: bipush        7
    1318: ishr
    1319: iload         8
    1321: bipush        7
    1323: ishr
    1324: invokestatic  #50                 // Method a:([IIIIIIII)V
    1327: iload_3
    1328: iload         9
    1330: iadd
    1331: istore_3
    1332: iload         5
    1334: iload         13
    1336: iadd
    1337: istore        5
    1339: iload         6
    1341: iload         10
    1343: iadd
    1344: istore        6
    1346: iload         8
    1348: iload         14
    1350: iadd
    1351: istore        8
    1353: iload_1
    1354: getstatic     #83                 // Field AFCKELYG.n:I
    1357: iadd
    1358: istore_1
    1359: iinc          0, -1
    1362: iload_0
    1363: ifge          1299
    1366: return
    1367: iload_0
    1368: iload_2
    1369: isub
    1370: istore_0
    1371: iload_2
    1372: iload_1
    1373: isub
    1374: istore_2
    1375: getstatic     #66                 // Field L:[I
    1378: iload_1
    1379: iaload
    1380: istore_1
    1381: iload         15
    1383: ifeq          1446
    1386: getstatic     #62                 // Field AFCKELYG.m:[I
    1389: iload_1
    1390: iconst_0
    1391: iconst_0
    1392: iload         4
    1394: bipush        16
    1396: ishr
    1397: iload_3
    1398: bipush        16
    1400: ishr
    1401: iload         7
    1403: bipush        7
    1405: ishr
    1406: iload         6
    1408: bipush        7
    1410: ishr
    1411: invokestatic  #50                 // Method a:([IIIIIIII)V
    1414: iload_3
    1415: iload         9
    1417: iadd
    1418: istore_3
    1419: iload         4
    1421: iload         11
    1423: iadd
    1424: istore        4
    1426: iload         6
    1428: iload         10
    1430: iadd
    1431: istore        6
    1433: iload         7
    1435: iload         12
    1437: iadd
    1438: istore        7
    1440: iload_1
    1441: getstatic     #83                 // Field AFCKELYG.n:I
    1444: iadd
    1445: istore_1
    1446: iinc          2, -1
    1449: iload_2
    1450: ifge          1386
    1453: iload         15
    1455: ifeq          1518
    1458: getstatic     #62                 // Field AFCKELYG.m:[I
    1461: iload_1
    1462: iconst_0
    1463: iconst_0
    1464: iload         5
    1466: bipush        16
    1468: ishr
    1469: iload_3
    1470: bipush        16
    1472: ishr
    1473: iload         8
    1475: bipush        7
    1477: ishr
    1478: iload         6
    1480: bipush        7
    1482: ishr
    1483: invokestatic  #50                 // Method a:([IIIIIIII)V
    1486: iload_3
    1487: iload         9
    1489: iadd
    1490: istore_3
    1491: iload         5
    1493: iload         13
    1495: iadd
    1496: istore        5
    1498: iload         6
    1500: iload         10
    1502: iadd
    1503: istore        6
    1505: iload         8
    1507: iload         14
    1509: iadd
    1510: istore        8
    1512: iload_1
    1513: getstatic     #83                 // Field AFCKELYG.n:I
    1516: iadd
    1517: istore_1
    1518: iinc          0, -1
    1521: iload_0
    1522: ifge          1458
    1525: return
    1526: iload         4
    1528: bipush        16
    1530: ishl
    1531: dup
    1532: istore        4
    1534: istore        5
    1536: iload         7
    1538: bipush        15
    1540: ishl
    1541: dup
    1542: istore        7
    1544: istore        8
    1546: iload_1
    1547: ifge          1588
    1550: iload         5
    1552: iload         9
    1554: iload_1
    1555: imul
    1556: isub
    1557: istore        5
    1559: iload         4
    1561: iload         11
    1563: iload_1
    1564: imul
    1565: isub
    1566: istore        4
    1568: iload         8
    1570: iload         10
    1572: iload_1
    1573: imul
    1574: isub
    1575: istore        8
    1577: iload         7
    1579: iload         12
    1581: iload_1
    1582: imul
    1583: isub
    1584: istore        7
    1586: iconst_0
    1587: istore_1
    1588: iload_3
    1589: bipush        16
    1591: ishl
    1592: istore_3
    1593: iload         6
    1595: bipush        15
    1597: ishl
    1598: istore        6
    1600: iload_0
    1601: ifge          1622
    1604: iload_3
    1605: iload         13
    1607: iload_0
    1608: imul
    1609: isub
    1610: istore_3
    1611: iload         6
    1613: iload         14
    1615: iload_0
    1616: imul
    1617: isub
    1618: istore        6
    1620: iconst_0
    1621: istore_0
    1622: iload         9
    1624: iload         11
    1626: if_icmpge     1791
    1629: iload_2
    1630: iload_0
    1631: isub
    1632: istore_2
    1633: iload_0
    1634: iload_1
    1635: isub
    1636: istore_0
    1637: getstatic     #66                 // Field L:[I
    1640: iload_1
    1641: iaload
    1642: istore_1
    1643: iload         15
    1645: ifeq          1711
    1648: getstatic     #62                 // Field AFCKELYG.m:[I
    1651: iload_1
    1652: iconst_0
    1653: iconst_0
    1654: iload         5
    1656: bipush        16
    1658: ishr
    1659: iload         4
    1661: bipush        16
    1663: ishr
    1664: iload         8
    1666: bipush        7
    1668: ishr
    1669: iload         7
    1671: bipush        7
    1673: ishr
    1674: invokestatic  #50                 // Method a:([IIIIIIII)V
    1677: iload         5
    1679: iload         9
    1681: iadd
    1682: istore        5
    1684: iload         4
    1686: iload         11
    1688: iadd
    1689: istore        4
    1691: iload         8
    1693: iload         10
    1695: iadd
    1696: istore        8
    1698: iload         7
    1700: iload         12
    1702: iadd
    1703: istore        7
    1705: iload_1
    1706: getstatic     #83                 // Field AFCKELYG.n:I
    1709: iadd
    1710: istore_1
    1711: iinc          0, -1
    1714: iload_0
    1715: ifge          1648
    1718: iload         15
    1720: ifeq          1783
    1723: getstatic     #62                 // Field AFCKELYG.m:[I
    1726: iload_1
    1727: iconst_0
    1728: iconst_0
    1729: iload_3
    1730: bipush        16
    1732: ishr
    1733: iload         4
    1735: bipush        16
    1737: ishr
    1738: iload         6
    1740: bipush        7
    1742: ishr
    1743: iload         7
    1745: bipush        7
    1747: ishr
    1748: invokestatic  #50                 // Method a:([IIIIIIII)V
    1751: iload_3
    1752: iload         13
    1754: iadd
    1755: istore_3
    1756: iload         4
    1758: iload         11
    1760: iadd
    1761: istore        4
    1763: iload         6
    1765: iload         14
    1767: iadd
    1768: istore        6
    1770: iload         7
    1772: iload         12
    1774: iadd
    1775: istore        7
    1777: iload_1
    1778: getstatic     #83                 // Field AFCKELYG.n:I
    1781: iadd
    1782: istore_1
    1783: iinc          2, -1
    1786: iload_2
    1787: ifge          1723
    1790: return
    1791: iload_2
    1792: iload_0
    1793: isub
    1794: istore_2
    1795: iload_0
    1796: iload_1
    1797: isub
    1798: istore_0
    1799: getstatic     #66                 // Field L:[I
    1802: iload_1
    1803: iaload
    1804: istore_1
    1805: iload         15
    1807: ifeq          1873
    1810: getstatic     #62                 // Field AFCKELYG.m:[I
    1813: iload_1
    1814: iconst_0
    1815: iconst_0
    1816: iload         4
    1818: bipush        16
    1820: ishr
    1821: iload         5
    1823: bipush        16
    1825: ishr
    1826: iload         7
    1828: bipush        7
    1830: ishr
    1831: iload         8
    1833: bipush        7
    1835: ishr
    1836: invokestatic  #50                 // Method a:([IIIIIIII)V
    1839: iload         5
    1841: iload         9
    1843: iadd
    1844: istore        5
    1846: iload         4
    1848: iload         11
    1850: iadd
    1851: istore        4
    1853: iload         8
    1855: iload         10
    1857: iadd
    1858: istore        8
    1860: iload         7
    1862: iload         12
    1864: iadd
    1865: istore        7
    1867: iload_1
    1868: getstatic     #83                 // Field AFCKELYG.n:I
    1871: iadd
    1872: istore_1
    1873: iinc          0, -1
    1876: iload_0
    1877: ifge          1810
    1880: iload         15
    1882: ifeq          1945
    1885: getstatic     #62                 // Field AFCKELYG.m:[I
    1888: iload_1
    1889: iconst_0
    1890: iconst_0
    1891: iload         4
    1893: bipush        16
    1895: ishr
    1896: iload_3
    1897: bipush        16
    1899: ishr
    1900: iload         7
    1902: bipush        7
    1904: ishr
    1905: iload         6
    1907: bipush        7
    1909: ishr
    1910: invokestatic  #50                 // Method a:([IIIIIIII)V
    1913: iload_3
    1914: iload         13
    1916: iadd
    1917: istore_3
    1918: iload         4
    1920: iload         11
    1922: iadd
    1923: istore        4
    1925: iload         6
    1927: iload         14
    1929: iadd
    1930: istore        6
    1932: iload         7
    1934: iload         12
    1936: iadd
    1937: istore        7
    1939: iload_1
    1940: getstatic     #83                 // Field AFCKELYG.n:I
    1943: iadd
    1944: istore_1
    1945: iinc          2, -1
    1948: iload_2
    1949: ifge          1885
    1952: return
    1953: iload_2
    1954: getstatic     #86                 // Field AFCKELYG.q:I
    1957: if_icmplt     1961
    1960: return
    1961: iload_0
    1962: getstatic     #86                 // Field AFCKELYG.q:I
    1965: if_icmple     1972
    1968: getstatic     #86                 // Field AFCKELYG.q:I
    1971: istore_0
    1972: iload_1
    1973: getstatic     #86                 // Field AFCKELYG.q:I
    1976: if_icmple     1983
    1979: getstatic     #86                 // Field AFCKELYG.q:I
    1982: istore_1
    1983: iload_0
    1984: iload_1
    1985: if_icmpge     2415
    1988: iload         5
    1990: bipush        16
    1992: ishl
    1993: dup
    1994: istore        5
    1996: istore        4
    1998: iload         8
    2000: bipush        15
    2002: ishl
    2003: dup
    2004: istore        8
    2006: istore        7
    2008: iload_2
    2009: ifge          2050
    2012: iload         4
    2014: iload         11
    2016: iload_2
    2017: imul
    2018: isub
    2019: istore        4
    2021: iload         5
    2023: iload         13
    2025: iload_2
    2026: imul
    2027: isub
    2028: istore        5
    2030: iload         7
    2032: iload         12
    2034: iload_2
    2035: imul
    2036: isub
    2037: istore        7
    2039: iload         8
    2041: iload         14
    2043: iload_2
    2044: imul
    2045: isub
    2046: istore        8
    2048: iconst_0
    2049: istore_2
    2050: iload_3
    2051: bipush        16
    2053: ishl
    2054: istore_3
    2055: iload         6
    2057: bipush        15
    2059: ishl
    2060: istore        6
    2062: iload_0
    2063: ifge          2084
    2066: iload_3
    2067: iload         9
    2069: iload_0
    2070: imul
    2071: isub
    2072: istore_3
    2073: iload         6
    2075: iload         10
    2077: iload_0
    2078: imul
    2079: isub
    2080: istore        6
    2082: iconst_0
    2083: istore_0
    2084: iload         11
    2086: iload         13
    2088: if_icmpge     2253
    2091: iload_1
    2092: iload_0
    2093: isub
    2094: istore_1
    2095: iload_0
    2096: iload_2
    2097: isub
    2098: istore_0
    2099: getstatic     #66                 // Field L:[I
    2102: iload_2
    2103: iaload
    2104: istore_2
    2105: iload         15
    2107: ifeq          2173
    2110: getstatic     #62                 // Field AFCKELYG.m:[I
    2113: iload_2
    2114: iconst_0
    2115: iconst_0
    2116: iload         4
    2118: bipush        16
    2120: ishr
    2121: iload         5
    2123: bipush        16
    2125: ishr
    2126: iload         7
    2128: bipush        7
    2130: ishr
    2131: iload         8
    2133: bipush        7
    2135: ishr
    2136: invokestatic  #50                 // Method a:([IIIIIIII)V
    2139: iload         4
    2141: iload         11
    2143: iadd
    2144: istore        4
    2146: iload         5
    2148: iload         13
    2150: iadd
    2151: istore        5
    2153: iload         7
    2155: iload         12
    2157: iadd
    2158: istore        7
    2160: iload         8
    2162: iload         14
    2164: iadd
    2165: istore        8
    2167: iload_2
    2168: getstatic     #83                 // Field AFCKELYG.n:I
    2171: iadd
    2172: istore_2
    2173: iinc          0, -1
    2176: iload_0
    2177: ifge          2110
    2180: iload         15
    2182: ifeq          2245
    2185: getstatic     #62                 // Field AFCKELYG.m:[I
    2188: iload_2
    2189: iconst_0
    2190: iconst_0
    2191: iload         4
    2193: bipush        16
    2195: ishr
    2196: iload_3
    2197: bipush        16
    2199: ishr
    2200: iload         7
    2202: bipush        7
    2204: ishr
    2205: iload         6
    2207: bipush        7
    2209: ishr
    2210: invokestatic  #50                 // Method a:([IIIIIIII)V
    2213: iload         4
    2215: iload         11
    2217: iadd
    2218: istore        4
    2220: iload_3
    2221: iload         9
    2223: iadd
    2224: istore_3
    2225: iload         7
    2227: iload         12
    2229: iadd
    2230: istore        7
    2232: iload         6
    2234: iload         10
    2236: iadd
    2237: istore        6
    2239: iload_2
    2240: getstatic     #83                 // Field AFCKELYG.n:I
    2243: iadd
    2244: istore_2
    2245: iinc          1, -1
    2248: iload_1
    2249: ifge          2185
    2252: return
    2253: iload_1
    2254: iload_0
    2255: isub
    2256: istore_1
    2257: iload_0
    2258: iload_2
    2259: isub
    2260: istore_0
    2261: getstatic     #66                 // Field L:[I
    2264: iload_2
    2265: iaload
    2266: istore_2
    2267: iload         15
    2269: ifeq          2335
    2272: getstatic     #62                 // Field AFCKELYG.m:[I
    2275: iload_2
    2276: iconst_0
    2277: iconst_0
    2278: iload         5
    2280: bipush        16
    2282: ishr
    2283: iload         4
    2285: bipush        16
    2287: ishr
    2288: iload         8
    2290: bipush        7
    2292: ishr
    2293: iload         7
    2295: bipush        7
    2297: ishr
    2298: invokestatic  #50                 // Method a:([IIIIIIII)V
    2301: iload         4
    2303: iload         11
    2305: iadd
    2306: istore        4
    2308: iload         5
    2310: iload         13
    2312: iadd
    2313: istore        5
    2315: iload         7
    2317: iload         12
    2319: iadd
    2320: istore        7
    2322: iload         8
    2324: iload         14
    2326: iadd
    2327: istore        8
    2329: iload_2
    2330: getstatic     #83                 // Field AFCKELYG.n:I
    2333: iadd
    2334: istore_2
    2335: iinc          0, -1
    2338: iload_0
    2339: ifge          2272
    2342: iload         15
    2344: ifeq          2407
    2347: getstatic     #62                 // Field AFCKELYG.m:[I
    2350: iload_2
    2351: iconst_0
    2352: iconst_0
    2353: iload_3
    2354: bipush        16
    2356: ishr
    2357: iload         4
    2359: bipush        16
    2361: ishr
    2362: iload         6
    2364: bipush        7
    2366: ishr
    2367: iload         7
    2369: bipush        7
    2371: ishr
    2372: invokestatic  #50                 // Method a:([IIIIIIII)V
    2375: iload         4
    2377: iload         11
    2379: iadd
    2380: istore        4
    2382: iload_3
    2383: iload         9
    2385: iadd
    2386: istore_3
    2387: iload         7
    2389: iload         12
    2391: iadd
    2392: istore        7
    2394: iload         6
    2396: iload         10
    2398: iadd
    2399: istore        6
    2401: iload_2
    2402: getstatic     #83                 // Field AFCKELYG.n:I
    2405: iadd
    2406: istore_2
    2407: iinc          1, -1
    2410: iload_1
    2411: ifge          2347
    2414: return
    2415: iload         5
    2417: bipush        16
    2419: ishl
    2420: dup
    2421: istore        5
    2423: istore_3
    2424: iload         8
    2426: bipush        15
    2428: ishl
    2429: dup
    2430: istore        8
    2432: istore        6
    2434: iload_2
    2435: ifge          2474
    2438: iload_3
    2439: iload         11
    2441: iload_2
    2442: imul
    2443: isub
    2444: istore_3
    2445: iload         5
    2447: iload         13
    2449: iload_2
    2450: imul
    2451: isub
    2452: istore        5
    2454: iload         6
    2456: iload         12
    2458: iload_2
    2459: imul
    2460: isub
    2461: istore        6
    2463: iload         8
    2465: iload         14
    2467: iload_2
    2468: imul
    2469: isub
    2470: istore        8
    2472: iconst_0
    2473: istore_2
    2474: iload         4
    2476: bipush        16
    2478: ishl
    2479: istore        4
    2481: iload         7
    2483: bipush        15
    2485: ishl
    2486: istore        7
    2488: iload_1
    2489: ifge          2512
    2492: iload         4
    2494: iload         9
    2496: iload_1
    2497: imul
    2498: isub
    2499: istore        4
    2501: iload         7
    2503: iload         10
    2505: iload_1
    2506: imul
    2507: isub
    2508: istore        7
    2510: iconst_0
    2511: istore_1
    2512: iload         11
    2514: iload         13
    2516: if_icmpge     2681
    2519: iload_0
    2520: iload_1
    2521: isub
    2522: istore_0
    2523: iload_1
    2524: iload_2
    2525: isub
    2526: istore_1
    2527: getstatic     #66                 // Field L:[I
    2530: iload_2
    2531: iaload
    2532: istore_2
    2533: iload         15
    2535: ifeq          2598
    2538: getstatic     #62                 // Field AFCKELYG.m:[I
    2541: iload_2
    2542: iconst_0
    2543: iconst_0
    2544: iload_3
    2545: bipush        16
    2547: ishr
    2548: iload         5
    2550: bipush        16
    2552: ishr
    2553: iload         6
    2555: bipush        7
    2557: ishr
    2558: iload         8
    2560: bipush        7
    2562: ishr
    2563: invokestatic  #50                 // Method a:([IIIIIIII)V
    2566: iload_3
    2567: iload         11
    2569: iadd
    2570: istore_3
    2571: iload         5
    2573: iload         13
    2575: iadd
    2576: istore        5
    2578: iload         6
    2580: iload         12
    2582: iadd
    2583: istore        6
    2585: iload         8
    2587: iload         14
    2589: iadd
    2590: istore        8
    2592: iload_2
    2593: getstatic     #83                 // Field AFCKELYG.n:I
    2596: iadd
    2597: istore_2
    2598: iinc          1, -1
    2601: iload_1
    2602: ifge          2538
    2605: iload         15
    2607: ifeq          2673
    2610: getstatic     #62                 // Field AFCKELYG.m:[I
    2613: iload_2
    2614: iconst_0
    2615: iconst_0
    2616: iload         4
    2618: bipush        16
    2620: ishr
    2621: iload         5
    2623: bipush        16
    2625: ishr
    2626: iload         7
    2628: bipush        7
    2630: ishr
    2631: iload         8
    2633: bipush        7
    2635: ishr
    2636: invokestatic  #50                 // Method a:([IIIIIIII)V
    2639: iload         4
    2641: iload         9
    2643: iadd
    2644: istore        4
    2646: iload         5
    2648: iload         13
    2650: iadd
    2651: istore        5
    2653: iload         7
    2655: iload         10
    2657: iadd
    2658: istore        7
    2660: iload         8
    2662: iload         14
    2664: iadd
    2665: istore        8
    2667: iload_2
    2668: getstatic     #83                 // Field AFCKELYG.n:I
    2671: iadd
    2672: istore_2
    2673: iinc          0, -1
    2676: iload_0
    2677: ifge          2610
    2680: return
    2681: iload_0
    2682: iload_1
    2683: isub
    2684: istore_0
    2685: iload_1
    2686: iload_2
    2687: isub
    2688: istore_1
    2689: getstatic     #66                 // Field L:[I
    2692: iload_2
    2693: iaload
    2694: istore_2
    2695: iload         15
    2697: ifeq          2760
    2700: getstatic     #62                 // Field AFCKELYG.m:[I
    2703: iload_2
    2704: iconst_0
    2705: iconst_0
    2706: iload         5
    2708: bipush        16
    2710: ishr
    2711: iload_3
    2712: bipush        16
    2714: ishr
    2715: iload         8
    2717: bipush        7
    2719: ishr
    2720: iload         6
    2722: bipush        7
    2724: ishr
    2725: invokestatic  #50                 // Method a:([IIIIIIII)V
    2728: iload_3
    2729: iload         11
    2731: iadd
    2732: istore_3
    2733: iload         5
    2735: iload         13
    2737: iadd
    2738: istore        5
    2740: iload         6
    2742: iload         12
    2744: iadd
    2745: istore        6
    2747: iload         8
    2749: iload         14
    2751: iadd
    2752: istore        8
    2754: iload_2
    2755: getstatic     #83                 // Field AFCKELYG.n:I
    2758: iadd
    2759: istore_2
    2760: iinc          1, -1
    2763: iload_1
    2764: ifge          2700
    2767: iload         15
    2769: ifeq          2835
    2772: getstatic     #62                 // Field AFCKELYG.m:[I
    2775: iload_2
    2776: iconst_0
    2777: iconst_0
    2778: iload         5
    2780: bipush        16
    2782: ishr
    2783: iload         4
    2785: bipush        16
    2787: ishr
    2788: iload         8
    2790: bipush        7
    2792: ishr
    2793: iload         7
    2795: bipush        7
    2797: ishr
    2798: invokestatic  #50                 // Method a:([IIIIIIII)V
    2801: iload         4
    2803: iload         9
    2805: iadd
    2806: istore        4
    2808: iload         5
    2810: iload         13
    2812: iadd
    2813: istore        5
    2815: iload         7
    2817: iload         10
    2819: iadd
    2820: istore        7
    2822: iload         8
    2824: iload         14
    2826: iadd
    2827: istore        8
    2829: iload_2
    2830: getstatic     #83                 // Field AFCKELYG.n:I
    2833: iadd
    2834: istore_2
    2835: iinc          0, -1
    2838: iload_0
    2839: ifge          2772
    2842: return

  public static final void a(int[], int, int, int, int, int, int, int);
    Code:
       0: getstatic     #289                // Field XHHRODPC.l:Z
       3: istore        11
       5: getstatic     #56                 // Field D:Z
       8: ifeq          583
      11: getstatic     #53                 // Field B:Z
      14: ifeq          110
      17: iload         5
      19: iload         4
      21: isub
      22: iconst_3
      23: if_icmple     44
      26: iload         7
      28: iload         6
      30: isub
      31: iload         5
      33: iload         4
      35: isub
      36: idiv
      37: istore        8
      39: iload         11
      41: ifeq          47
      44: iconst_0
      45: istore        8
      47: iload         5
      49: getstatic     #84                 // Field AFCKELYG.t:I
      52: if_icmple     60
      55: getstatic     #84                 // Field AFCKELYG.t:I
      58: istore        5
      60: iload         4
      62: ifge          78
      65: iload         6
      67: iload         4
      69: iload         8
      71: imul
      72: isub
      73: istore        6
      75: iconst_0
      76: istore        4
      78: iload         4
      80: iload         5
      82: if_icmplt     86
      85: return
      86: iload_1
      87: iload         4
      89: iadd
      90: istore_1
      91: iload         5
      93: iload         4
      95: isub
      96: iconst_2
      97: ishr
      98: istore_3
      99: iload         8
     101: iconst_2
     102: ishl
     103: istore        8
     105: iload         11
     107: ifeq          159
     110: iload         4
     112: iload         5
     114: if_icmplt     118
     117: return
     118: iload_1
     119: iload         4
     121: iadd
     122: istore_1
     123: iload         5
     125: iload         4
     127: isub
     128: iconst_2
     129: ishr
     130: istore_3
     131: iload_3
     132: ifle          156
     135: iload         7
     137: iload         6
     139: isub
     140: getstatic     #44                 // Field H:[I
     143: iload_3
     144: iaload
     145: imul
     146: bipush        15
     148: ishr
     149: istore        8
     151: iload         11
     153: ifeq          159
     156: iconst_0
     157: istore        8
     159: getstatic     #78                 // Field E:I
     162: ifne          259
     165: iload         11
     167: ifeq          215
     170: getstatic     #41                 // Field V:[I
     173: iload         6
     175: bipush        8
     177: ishr
     178: iaload
     179: istore_2
     180: iload         6
     182: iload         8
     184: iadd
     185: istore        6
     187: aload_0
     188: iload_1
     189: iinc          1, 1
     192: iload_2
     193: iastore
     194: aload_0
     195: iload_1
     196: iinc          1, 1
     199: iload_2
     200: iastore
     201: aload_0
     202: iload_1
     203: iinc          1, 1
     206: iload_2
     207: iastore
     208: aload_0
     209: iload_1
     210: iinc          1, 1
     213: iload_2
     214: iastore
     215: iinc          3, -1
     218: iload_3
     219: ifge          170
     222: iload         5
     224: iload         4
     226: isub
     227: iconst_3
     228: iand
     229: istore_3
     230: iload_3
     231: ifle          582
     234: getstatic     #41                 // Field V:[I
     237: iload         6
     239: bipush        8
     241: ishr
     242: iaload
     243: istore_2
     244: aload_0
     245: iload_1
     246: iinc          1, 1
     249: iload_2
     250: iastore
     251: iinc          3, -1
     254: iload_3
     255: ifgt          244
     258: return
     259: getstatic     #78                 // Field E:I
     262: istore        9
     264: sipush        256
     267: getstatic     #78                 // Field E:I
     270: isub
     271: istore        10
     273: iload         11
     275: ifeq          479
     278: getstatic     #41                 // Field V:[I
     281: iload         6
     283: bipush        8
     285: ishr
     286: iaload
     287: istore_2
     288: iload         6
     290: iload         8
     292: iadd
     293: istore        6
     295: iload_2
     296: ldc           #7                  // int 16711935
     298: iand
     299: iload         10
     301: imul
     302: bipush        8
     304: ishr
     305: ldc           #7                  // int 16711935
     307: iand
     308: iload_2
     309: ldc           #3                  // int 65280
     311: iand
     312: iload         10
     314: imul
     315: bipush        8
     317: ishr
     318: ldc           #3                  // int 65280
     320: iand
     321: iadd
     322: istore_2
     323: aload_0
     324: iload_1
     325: iinc          1, 1
     328: iload_2
     329: aload_0
     330: iload_1
     331: iaload
     332: ldc           #7                  // int 16711935
     334: iand
     335: iload         9
     337: imul
     338: bipush        8
     340: ishr
     341: ldc           #7                  // int 16711935
     343: iand
     344: iadd
     345: aload_0
     346: iload_1
     347: iaload
     348: ldc           #3                  // int 65280
     350: iand
     351: iload         9
     353: imul
     354: bipush        8
     356: ishr
     357: ldc           #3                  // int 65280
     359: iand
     360: iadd
     361: iastore
     362: aload_0
     363: iload_1
     364: iinc          1, 1
     367: iload_2
     368: aload_0
     369: iload_1
     370: iaload
     371: ldc           #7                  // int 16711935
     373: iand
     374: iload         9
     376: imul
     377: bipush        8
     379: ishr
     380: ldc           #7                  // int 16711935
     382: iand
     383: iadd
     384: aload_0
     385: iload_1
     386: iaload
     387: ldc           #3                  // int 65280
     389: iand
     390: iload         9
     392: imul
     393: bipush        8
     395: ishr
     396: ldc           #3                  // int 65280
     398: iand
     399: iadd
     400: iastore
     401: aload_0
     402: iload_1
     403: iinc          1, 1
     406: iload_2
     407: aload_0
     408: iload_1
     409: iaload
     410: ldc           #7                  // int 16711935
     412: iand
     413: iload         9
     415: imul
     416: bipush        8
     418: ishr
     419: ldc           #7                  // int 16711935
     421: iand
     422: iadd
     423: aload_0
     424: iload_1
     425: iaload
     426: ldc           #3                  // int 65280
     428: iand
     429: iload         9
     431: imul
     432: bipush        8
     434: ishr
     435: ldc           #3                  // int 65280
     437: iand
     438: iadd
     439: iastore
     440: aload_0
     441: iload_1
     442: iinc          1, 1
     445: iload_2
     446: aload_0
     447: iload_1
     448: iaload
     449: ldc           #7                  // int 16711935
     451: iand
     452: iload         9
     454: imul
     455: bipush        8
     457: ishr
     458: ldc           #7                  // int 16711935
     460: iand
     461: iadd
     462: aload_0
     463: iload_1
     464: iaload
     465: ldc           #3                  // int 65280
     467: iand
     468: iload         9
     470: imul
     471: bipush        8
     473: ishr
     474: ldc           #3                  // int 65280
     476: iand
     477: iadd
     478: iastore
     479: iinc          3, -1
     482: iload_3
     483: ifge          278
     486: iload         5
     488: iload         4
     490: isub
     491: iconst_3
     492: iand
     493: istore_3
     494: iload_3
     495: ifle          582
     498: getstatic     #41                 // Field V:[I
     501: iload         6
     503: bipush        8
     505: ishr
     506: iaload
     507: istore_2
     508: iload_2
     509: ldc           #7                  // int 16711935
     511: iand
     512: iload         10
     514: imul
     515: bipush        8
     517: ishr
     518: ldc           #7                  // int 16711935
     520: iand
     521: iload_2
     522: ldc           #3                  // int 65280
     524: iand
     525: iload         10
     527: imul
     528: bipush        8
     530: ishr
     531: ldc           #3                  // int 65280
     533: iand
     534: iadd
     535: istore_2
     536: aload_0
     537: iload_1
     538: iinc          1, 1
     541: iload_2
     542: aload_0
     543: iload_1
     544: iaload
     545: ldc           #7                  // int 16711935
     547: iand
     548: iload         9
     550: imul
     551: bipush        8
     553: ishr
     554: ldc           #7                  // int 16711935
     556: iand
     557: iadd
     558: aload_0
     559: iload_1
     560: iaload
     561: ldc           #3                  // int 65280
     563: iand
     564: iload         9
     566: imul
     567: bipush        8
     569: ishr
     570: ldc           #3                  // int 65280
     572: iand
     573: iadd
     574: iastore
     575: iinc          3, -1
     578: iload_3
     579: ifgt          536
     582: return
     583: iload         4
     585: iload         5
     587: if_icmplt     591
     590: return
     591: iload         7
     593: iload         6
     595: isub
     596: iload         5
     598: iload         4
     600: isub
     601: idiv
     602: istore        8
     604: getstatic     #53                 // Field B:Z
     607: ifeq          649
     610: iload         5
     612: getstatic     #84                 // Field AFCKELYG.t:I
     615: if_icmple     623
     618: getstatic     #84                 // Field AFCKELYG.t:I
     621: istore        5
     623: iload         4
     625: ifge          641
     628: iload         6
     630: iload         4
     632: iload         8
     634: imul
     635: isub
     636: istore        6
     638: iconst_0
     639: istore        4
     641: iload         4
     643: iload         5
     645: if_icmplt     649
     648: return
     649: iload_1
     650: iload         4
     652: iadd
     653: istore_1
     654: iload         5
     656: iload         4
     658: isub
     659: istore_3
     660: getstatic     #78                 // Field E:I
     663: ifne          696
     666: aload_0
     667: iload_1
     668: iinc          1, 1
     671: getstatic     #41                 // Field V:[I
     674: iload         6
     676: bipush        8
     678: ishr
     679: iaload
     680: iastore
     681: iload         6
     683: iload         8
     685: iadd
     686: istore        6
     688: iinc          3, -1
     691: iload_3
     692: ifgt          666
     695: return
     696: getstatic     #78                 // Field E:I
     699: istore        9
     701: sipush        256
     704: getstatic     #78                 // Field E:I
     707: isub
     708: istore        10
     710: getstatic     #41                 // Field V:[I
     713: iload         6
     715: bipush        8
     717: ishr
     718: iaload
     719: istore_2
     720: iload         6
     722: iload         8
     724: iadd
     725: istore        6
     727: iload_2
     728: ldc           #7                  // int 16711935
     730: iand
     731: iload         10
     733: imul
     734: bipush        8
     736: ishr
     737: ldc           #7                  // int 16711935
     739: iand
     740: iload_2
     741: ldc           #3                  // int 65280
     743: iand
     744: iload         10
     746: imul
     747: bipush        8
     749: ishr
     750: ldc           #3                  // int 65280
     752: iand
     753: iadd
     754: istore_2
     755: aload_0
     756: iload_1
     757: iinc          1, 1
     760: iload_2
     761: aload_0
     762: iload_1
     763: iaload
     764: ldc           #7                  // int 16711935
     766: iand
     767: iload         9
     769: imul
     770: bipush        8
     772: ishr
     773: ldc           #7                  // int 16711935
     775: iand
     776: iadd
     777: aload_0
     778: iload_1
     779: iaload
     780: ldc           #3                  // int 65280
     782: iand
     783: iload         9
     785: imul
     786: bipush        8
     788: ishr
     789: ldc           #3                  // int 65280
     791: iand
     792: iadd
     793: iastore
     794: iinc          3, -1
     797: iload_3
     798: ifgt          710
     801: return

  public static final void c(int, int, int, int, int, int, int);
    Code:
       0: getstatic     #289                // Field XHHRODPC.l:Z
       3: istore        10
       5: iconst_0
       6: istore        7
       8: iload_1
       9: iload_0
      10: if_icmpeq     26
      13: iload         4
      15: iload_3
      16: isub
      17: bipush        16
      19: ishl
      20: iload_1
      21: iload_0
      22: isub
      23: idiv
      24: istore        7
      26: iconst_0
      27: istore        8
      29: iload_2
      30: iload_1
      31: if_icmpeq     48
      34: iload         5
      36: iload         4
      38: isub
      39: bipush        16
      41: ishl
      42: iload_2
      43: iload_1
      44: isub
      45: idiv
      46: istore        8
      48: iconst_0
      49: istore        9
      51: iload_2
      52: iload_0
      53: if_icmpeq     69
      56: iload_3
      57: iload         5
      59: isub
      60: bipush        16
      62: ishl
      63: iload_0
      64: iload_2
      65: isub
      66: idiv
      67: istore        9
      69: iload_0
      70: iload_1
      71: if_icmpgt     724
      74: iload_0
      75: iload_2
      76: if_icmpgt     724
      79: iload_0
      80: getstatic     #86                 // Field AFCKELYG.q:I
      83: if_icmplt     87
      86: return
      87: iload_1
      88: getstatic     #86                 // Field AFCKELYG.q:I
      91: if_icmple     98
      94: getstatic     #86                 // Field AFCKELYG.q:I
      97: istore_1
      98: iload_2
      99: getstatic     #86                 // Field AFCKELYG.q:I
     102: if_icmple     109
     105: getstatic     #86                 // Field AFCKELYG.q:I
     108: istore_2
     109: iload_1
     110: iload_2
     111: if_icmpge     422
     114: iload_3
     115: bipush        16
     117: ishl
     118: dup
     119: istore_3
     120: istore        5
     122: iload_0
     123: ifge          144
     126: iload         5
     128: iload         9
     130: iload_0
     131: imul
     132: isub
     133: istore        5
     135: iload_3
     136: iload         7
     138: iload_0
     139: imul
     140: isub
     141: istore_3
     142: iconst_0
     143: istore_0
     144: iload         4
     146: bipush        16
     148: ishl
     149: istore        4
     151: iload_1
     152: ifge          166
     155: iload         4
     157: iload         8
     159: iload_1
     160: imul
     161: isub
     162: istore        4
     164: iconst_0
     165: istore_1
     166: iload_0
     167: iload_1
     168: if_icmpeq     178
     171: iload         9
     173: iload         7
     175: if_icmplt     190
     178: iload_0
     179: iload_1
     180: if_icmpne     306
     183: iload         9
     185: iload         8
     187: if_icmple     306
     190: iload_2
     191: iload_1
     192: isub
     193: istore_2
     194: iload_1
     195: iload_0
     196: isub
     197: istore_1
     198: getstatic     #66                 // Field L:[I
     201: iload_0
     202: iaload
     203: istore_0
     204: iload         10
     206: ifeq          246
     209: getstatic     #62                 // Field AFCKELYG.m:[I
     212: iload_0
     213: iload         6
     215: iconst_0
     216: iload         5
     218: bipush        16
     220: ishr
     221: iload_3
     222: bipush        16
     224: ishr
     225: invokestatic  #47                 // Method a:([IIIIII)V
     228: iload         5
     230: iload         9
     232: iadd
     233: istore        5
     235: iload_3
     236: iload         7
     238: iadd
     239: istore_3
     240: iload_0
     241: getstatic     #83                 // Field AFCKELYG.n:I
     244: iadd
     245: istore_0
     246: iinc          1, -1
     249: iload_1
     250: ifge          209
     253: iload         10
     255: ifeq          298
     258: getstatic     #62                 // Field AFCKELYG.m:[I
     261: iload_0
     262: iload         6
     264: iconst_0
     265: iload         5
     267: bipush        16
     269: ishr
     270: iload         4
     272: bipush        16
     274: ishr
     275: invokestatic  #47                 // Method a:([IIIIII)V
     278: iload         5
     280: iload         9
     282: iadd
     283: istore        5
     285: iload         4
     287: iload         8
     289: iadd
     290: istore        4
     292: iload_0
     293: getstatic     #83                 // Field AFCKELYG.n:I
     296: iadd
     297: istore_0
     298: iinc          2, -1
     301: iload_2
     302: ifge          258
     305: return
     306: iload_2
     307: iload_1
     308: isub
     309: istore_2
     310: iload_1
     311: iload_0
     312: isub
     313: istore_1
     314: getstatic     #66                 // Field L:[I
     317: iload_0
     318: iaload
     319: istore_0
     320: iload         10
     322: ifeq          362
     325: getstatic     #62                 // Field AFCKELYG.m:[I
     328: iload_0
     329: iload         6
     331: iconst_0
     332: iload_3
     333: bipush        16
     335: ishr
     336: iload         5
     338: bipush        16
     340: ishr
     341: invokestatic  #47                 // Method a:([IIIIII)V
     344: iload         5
     346: iload         9
     348: iadd
     349: istore        5
     351: iload_3
     352: iload         7
     354: iadd
     355: istore_3
     356: iload_0
     357: getstatic     #83                 // Field AFCKELYG.n:I
     360: iadd
     361: istore_0
     362: iinc          1, -1
     365: iload_1
     366: ifge          325
     369: iload         10
     371: ifeq          414
     374: getstatic     #62                 // Field AFCKELYG.m:[I
     377: iload_0
     378: iload         6
     380: iconst_0
     381: iload         4
     383: bipush        16
     385: ishr
     386: iload         5
     388: bipush        16
     390: ishr
     391: invokestatic  #47                 // Method a:([IIIIII)V
     394: iload         5
     396: iload         9
     398: iadd
     399: istore        5
     401: iload         4
     403: iload         8
     405: iadd
     406: istore        4
     408: iload_0
     409: getstatic     #83                 // Field AFCKELYG.n:I
     412: iadd
     413: istore_0
     414: iinc          2, -1
     417: iload_2
     418: ifge          374
     421: return
     422: iload_3
     423: bipush        16
     425: ishl
     426: dup
     427: istore_3
     428: istore        4
     430: iload_0
     431: ifge          452
     434: iload         4
     436: iload         9
     438: iload_0
     439: imul
     440: isub
     441: istore        4
     443: iload_3
     444: iload         7
     446: iload_0
     447: imul
     448: isub
     449: istore_3
     450: iconst_0
     451: istore_0
     452: iload         5
     454: bipush        16
     456: ishl
     457: istore        5
     459: iload_2
     460: ifge          474
     463: iload         5
     465: iload         8
     467: iload_2
     468: imul
     469: isub
     470: istore        5
     472: iconst_0
     473: istore_2
     474: iload_0
     475: iload_2
     476: if_icmpeq     486
     479: iload         9
     481: iload         7
     483: if_icmplt     498
     486: iload_0
     487: iload_2
     488: if_icmpne     611
     491: iload         8
     493: iload         7
     495: if_icmple     611
     498: iload_1
     499: iload_2
     500: isub
     501: istore_1
     502: iload_2
     503: iload_0
     504: isub
     505: istore_2
     506: getstatic     #66                 // Field L:[I
     509: iload_0
     510: iaload
     511: istore_0
     512: iload         10
     514: ifeq          554
     517: getstatic     #62                 // Field AFCKELYG.m:[I
     520: iload_0
     521: iload         6
     523: iconst_0
     524: iload         4
     526: bipush        16
     528: ishr
     529: iload_3
     530: bipush        16
     532: ishr
     533: invokestatic  #47                 // Method a:([IIIIII)V
     536: iload         4
     538: iload         9
     540: iadd
     541: istore        4
     543: iload_3
     544: iload         7
     546: iadd
     547: istore_3
     548: iload_0
     549: getstatic     #83                 // Field AFCKELYG.n:I
     552: iadd
     553: istore_0
     554: iinc          2, -1
     557: iload_2
     558: ifge          517
     561: iload         10
     563: ifeq          603
     566: getstatic     #62                 // Field AFCKELYG.m:[I
     569: iload_0
     570: iload         6
     572: iconst_0
     573: iload         5
     575: bipush        16
     577: ishr
     578: iload_3
     579: bipush        16
     581: ishr
     582: invokestatic  #47                 // Method a:([IIIIII)V
     585: iload         5
     587: iload         8
     589: iadd
     590: istore        5
     592: iload_3
     593: iload         7
     595: iadd
     596: istore_3
     597: iload_0
     598: getstatic     #83                 // Field AFCKELYG.n:I
     601: iadd
     602: istore_0
     603: iinc          1, -1
     606: iload_1
     607: ifge          566
     610: return
     611: iload_1
     612: iload_2
     613: isub
     614: istore_1
     615: iload_2
     616: iload_0
     617: isub
     618: istore_2
     619: getstatic     #66                 // Field L:[I
     622: iload_0
     623: iaload
     624: istore_0
     625: iload         10
     627: ifeq          667
     630: getstatic     #62                 // Field AFCKELYG.m:[I
     633: iload_0
     634: iload         6
     636: iconst_0
     637: iload_3
     638: bipush        16
     640: ishr
     641: iload         4
     643: bipush        16
     645: ishr
     646: invokestatic  #47                 // Method a:([IIIIII)V
     649: iload         4
     651: iload         9
     653: iadd
     654: istore        4
     656: iload_3
     657: iload         7
     659: iadd
     660: istore_3
     661: iload_0
     662: getstatic     #83                 // Field AFCKELYG.n:I
     665: iadd
     666: istore_0
     667: iinc          2, -1
     670: iload_2
     671: ifge          630
     674: iload         10
     676: ifeq          716
     679: getstatic     #62                 // Field AFCKELYG.m:[I
     682: iload_0
     683: iload         6
     685: iconst_0
     686: iload_3
     687: bipush        16
     689: ishr
     690: iload         5
     692: bipush        16
     694: ishr
     695: invokestatic  #47                 // Method a:([IIIIII)V
     698: iload         5
     700: iload         8
     702: iadd
     703: istore        5
     705: iload_3
     706: iload         7
     708: iadd
     709: istore_3
     710: iload_0
     711: getstatic     #83                 // Field AFCKELYG.n:I
     714: iadd
     715: istore_0
     716: iinc          1, -1
     719: iload_1
     720: ifge          679
     723: return
     724: iload_1
     725: iload_2
     726: if_icmpgt     1358
     729: iload_1
     730: getstatic     #86                 // Field AFCKELYG.q:I
     733: if_icmplt     737
     736: return
     737: iload_2
     738: getstatic     #86                 // Field AFCKELYG.q:I
     741: if_icmple     748
     744: getstatic     #86                 // Field AFCKELYG.q:I
     747: istore_2
     748: iload_0
     749: getstatic     #86                 // Field AFCKELYG.q:I
     752: if_icmple     759
     755: getstatic     #86                 // Field AFCKELYG.q:I
     758: istore_0
     759: iload_2
     760: iload_0
     761: if_icmpge     1067
     764: iload         4
     766: bipush        16
     768: ishl
     769: dup
     770: istore        4
     772: istore_3
     773: iload_1
     774: ifge          795
     777: iload_3
     778: iload         7
     780: iload_1
     781: imul
     782: isub
     783: istore_3
     784: iload         4
     786: iload         8
     788: iload_1
     789: imul
     790: isub
     791: istore        4
     793: iconst_0
     794: istore_1
     795: iload         5
     797: bipush        16
     799: ishl
     800: istore        5
     802: iload_2
     803: ifge          817
     806: iload         5
     808: iload         9
     810: iload_2
     811: imul
     812: isub
     813: istore        5
     815: iconst_0
     816: istore_2
     817: iload_1
     818: iload_2
     819: if_icmpeq     829
     822: iload         7
     824: iload         8
     826: if_icmplt     841
     829: iload_1
     830: iload_2
     831: if_icmpne     954
     834: iload         7
     836: iload         9
     838: if_icmple     954
     841: iload_0
     842: iload_2
     843: isub
     844: istore_0
     845: iload_2
     846: iload_1
     847: isub
     848: istore_2
     849: getstatic     #66                 // Field L:[I
     852: iload_1
     853: iaload
     854: istore_1
     855: iload         10
     857: ifeq          897
     860: getstatic     #62                 // Field AFCKELYG.m:[I
     863: iload_1
     864: iload         6
     866: iconst_0
     867: iload_3
     868: bipush        16
     870: ishr
     871: iload         4
     873: bipush        16
     875: ishr
     876: invokestatic  #47                 // Method a:([IIIIII)V
     879: iload_3
     880: iload         7
     882: iadd
     883: istore_3
     884: iload         4
     886: iload         8
     888: iadd
     889: istore        4
     891: iload_1
     892: getstatic     #83                 // Field AFCKELYG.n:I
     895: iadd
     896: istore_1
     897: iinc          2, -1
     900: iload_2
     901: ifge          860
     904: iload         10
     906: ifeq          946
     909: getstatic     #62                 // Field AFCKELYG.m:[I
     912: iload_1
     913: iload         6
     915: iconst_0
     916: iload_3
     917: bipush        16
     919: ishr
     920: iload         5
     922: bipush        16
     924: ishr
     925: invokestatic  #47                 // Method a:([IIIIII)V
     928: iload_3
     929: iload         7
     931: iadd
     932: istore_3
     933: iload         5
     935: iload         9
     937: iadd
     938: istore        5
     940: iload_1
     941: getstatic     #83                 // Field AFCKELYG.n:I
     944: iadd
     945: istore_1
     946: iinc          0, -1
     949: iload_0
     950: ifge          909
     953: return
     954: iload_0
     955: iload_2
     956: isub
     957: istore_0
     958: iload_2
     959: iload_1
     960: isub
     961: istore_2
     962: getstatic     #66                 // Field L:[I
     965: iload_1
     966: iaload
     967: istore_1
     968: iload         10
     970: ifeq          1010
     973: getstatic     #62                 // Field AFCKELYG.m:[I
     976: iload_1
     977: iload         6
     979: iconst_0
     980: iload         4
     982: bipush        16
     984: ishr
     985: iload_3
     986: bipush        16
     988: ishr
     989: invokestatic  #47                 // Method a:([IIIIII)V
     992: iload_3
     993: iload         7
     995: iadd
     996: istore_3
     997: iload         4
     999: iload         8
    1001: iadd
    1002: istore        4
    1004: iload_1
    1005: getstatic     #83                 // Field AFCKELYG.n:I
    1008: iadd
    1009: istore_1
    1010: iinc          2, -1
    1013: iload_2
    1014: ifge          973
    1017: iload         10
    1019: ifeq          1059
    1022: getstatic     #62                 // Field AFCKELYG.m:[I
    1025: iload_1
    1026: iload         6
    1028: iconst_0
    1029: iload         5
    1031: bipush        16
    1033: ishr
    1034: iload_3
    1035: bipush        16
    1037: ishr
    1038: invokestatic  #47                 // Method a:([IIIIII)V
    1041: iload_3
    1042: iload         7
    1044: iadd
    1045: istore_3
    1046: iload         5
    1048: iload         9
    1050: iadd
    1051: istore        5
    1053: iload_1
    1054: getstatic     #83                 // Field AFCKELYG.n:I
    1057: iadd
    1058: istore_1
    1059: iinc          0, -1
    1062: iload_0
    1063: ifge          1022
    1066: return
    1067: iload         4
    1069: bipush        16
    1071: ishl
    1072: dup
    1073: istore        4
    1075: istore        5
    1077: iload_1
    1078: ifge          1101
    1081: iload         5
    1083: iload         7
    1085: iload_1
    1086: imul
    1087: isub
    1088: istore        5
    1090: iload         4
    1092: iload         8
    1094: iload_1
    1095: imul
    1096: isub
    1097: istore        4
    1099: iconst_0
    1100: istore_1
    1101: iload_3
    1102: bipush        16
    1104: ishl
    1105: istore_3
    1106: iload_0
    1107: ifge          1119
    1110: iload_3
    1111: iload         9
    1113: iload_0
    1114: imul
    1115: isub
    1116: istore_3
    1117: iconst_0
    1118: istore_0
    1119: iload         7
    1121: iload         8
    1123: if_icmpge     1242
    1126: iload_2
    1127: iload_0
    1128: isub
    1129: istore_2
    1130: iload_0
    1131: iload_1
    1132: isub
    1133: istore_0
    1134: getstatic     #66                 // Field L:[I
    1137: iload_1
    1138: iaload
    1139: istore_1
    1140: iload         10
    1142: ifeq          1185
    1145: getstatic     #62                 // Field AFCKELYG.m:[I
    1148: iload_1
    1149: iload         6
    1151: iconst_0
    1152: iload         5
    1154: bipush        16
    1156: ishr
    1157: iload         4
    1159: bipush        16
    1161: ishr
    1162: invokestatic  #47                 // Method a:([IIIIII)V
    1165: iload         5
    1167: iload         7
    1169: iadd
    1170: istore        5
    1172: iload         4
    1174: iload         8
    1176: iadd
    1177: istore        4
    1179: iload_1
    1180: getstatic     #83                 // Field AFCKELYG.n:I
    1183: iadd
    1184: istore_1
    1185: iinc          0, -1
    1188: iload_0
    1189: ifge          1145
    1192: iload         10
    1194: ifeq          1234
    1197: getstatic     #62                 // Field AFCKELYG.m:[I
    1200: iload_1
    1201: iload         6
    1203: iconst_0
    1204: iload_3
    1205: bipush        16
    1207: ishr
    1208: iload         4
    1210: bipush        16
    1212: ishr
    1213: invokestatic  #47                 // Method a:([IIIIII)V
    1216: iload_3
    1217: iload         9
    1219: iadd
    1220: istore_3
    1221: iload         4
    1223: iload         8
    1225: iadd
    1226: istore        4
    1228: iload_1
    1229: getstatic     #83                 // Field AFCKELYG.n:I
    1232: iadd
    1233: istore_1
    1234: iinc          2, -1
    1237: iload_2
    1238: ifge          1197
    1241: return
    1242: iload_2
    1243: iload_0
    1244: isub
    1245: istore_2
    1246: iload_0
    1247: iload_1
    1248: isub
    1249: istore_0
    1250: getstatic     #66                 // Field L:[I
    1253: iload_1
    1254: iaload
    1255: istore_1
    1256: iload         10
    1258: ifeq          1301
    1261: getstatic     #62                 // Field AFCKELYG.m:[I
    1264: iload_1
    1265: iload         6
    1267: iconst_0
    1268: iload         4
    1270: bipush        16
    1272: ishr
    1273: iload         5
    1275: bipush        16
    1277: ishr
    1278: invokestatic  #47                 // Method a:([IIIIII)V
    1281: iload         5
    1283: iload         7
    1285: iadd
    1286: istore        5
    1288: iload         4
    1290: iload         8
    1292: iadd
    1293: istore        4
    1295: iload_1
    1296: getstatic     #83                 // Field AFCKELYG.n:I
    1299: iadd
    1300: istore_1
    1301: iinc          0, -1
    1304: iload_0
    1305: ifge          1261
    1308: iload         10
    1310: ifeq          1350
    1313: getstatic     #62                 // Field AFCKELYG.m:[I
    1316: iload_1
    1317: iload         6
    1319: iconst_0
    1320: iload         4
    1322: bipush        16
    1324: ishr
    1325: iload_3
    1326: bipush        16
    1328: ishr
    1329: invokestatic  #47                 // Method a:([IIIIII)V
    1332: iload_3
    1333: iload         9
    1335: iadd
    1336: istore_3
    1337: iload         4
    1339: iload         8
    1341: iadd
    1342: istore        4
    1344: iload_1
    1345: getstatic     #83                 // Field AFCKELYG.n:I
    1348: iadd
    1349: istore_1
    1350: iinc          2, -1
    1353: iload_2
    1354: ifge          1313
    1357: return
    1358: iload_2
    1359: getstatic     #86                 // Field AFCKELYG.q:I
    1362: if_icmplt     1366
    1365: return
    1366: iload_0
    1367: getstatic     #86                 // Field AFCKELYG.q:I
    1370: if_icmple     1377
    1373: getstatic     #86                 // Field AFCKELYG.q:I
    1376: istore_0
    1377: iload_1
    1378: getstatic     #86                 // Field AFCKELYG.q:I
    1381: if_icmple     1388
    1384: getstatic     #86                 // Field AFCKELYG.q:I
    1387: istore_1
    1388: iload_0
    1389: iload_1
    1390: if_icmpge     1684
    1393: iload         5
    1395: bipush        16
    1397: ishl
    1398: dup
    1399: istore        5
    1401: istore        4
    1403: iload_2
    1404: ifge          1427
    1407: iload         4
    1409: iload         8
    1411: iload_2
    1412: imul
    1413: isub
    1414: istore        4
    1416: iload         5
    1418: iload         9
    1420: iload_2
    1421: imul
    1422: isub
    1423: istore        5
    1425: iconst_0
    1426: istore_2
    1427: iload_3
    1428: bipush        16
    1430: ishl
    1431: istore_3
    1432: iload_0
    1433: ifge          1445
    1436: iload_3
    1437: iload         7
    1439: iload_0
    1440: imul
    1441: isub
    1442: istore_3
    1443: iconst_0
    1444: istore_0
    1445: iload         8
    1447: iload         9
    1449: if_icmpge     1568
    1452: iload_1
    1453: iload_0
    1454: isub
    1455: istore_1
    1456: iload_0
    1457: iload_2
    1458: isub
    1459: istore_0
    1460: getstatic     #66                 // Field L:[I
    1463: iload_2
    1464: iaload
    1465: istore_2
    1466: iload         10
    1468: ifeq          1511
    1471: getstatic     #62                 // Field AFCKELYG.m:[I
    1474: iload_2
    1475: iload         6
    1477: iconst_0
    1478: iload         4
    1480: bipush        16
    1482: ishr
    1483: iload         5
    1485: bipush        16
    1487: ishr
    1488: invokestatic  #47                 // Method a:([IIIIII)V
    1491: iload         4
    1493: iload         8
    1495: iadd
    1496: istore        4
    1498: iload         5
    1500: iload         9
    1502: iadd
    1503: istore        5
    1505: iload_2
    1506: getstatic     #83                 // Field AFCKELYG.n:I
    1509: iadd
    1510: istore_2
    1511: iinc          0, -1
    1514: iload_0
    1515: ifge          1471
    1518: iload         10
    1520: ifeq          1560
    1523: getstatic     #62                 // Field AFCKELYG.m:[I
    1526: iload_2
    1527: iload         6
    1529: iconst_0
    1530: iload         4
    1532: bipush        16
    1534: ishr
    1535: iload_3
    1536: bipush        16
    1538: ishr
    1539: invokestatic  #47                 // Method a:([IIIIII)V
    1542: iload         4
    1544: iload         8
    1546: iadd
    1547: istore        4
    1549: iload_3
    1550: iload         7
    1552: iadd
    1553: istore_3
    1554: iload_2
    1555: getstatic     #83                 // Field AFCKELYG.n:I
    1558: iadd
    1559: istore_2
    1560: iinc          1, -1
    1563: iload_1
    1564: ifge          1523
    1567: return
    1568: iload_1
    1569: iload_0
    1570: isub
    1571: istore_1
    1572: iload_0
    1573: iload_2
    1574: isub
    1575: istore_0
    1576: getstatic     #66                 // Field L:[I
    1579: iload_2
    1580: iaload
    1581: istore_2
    1582: iload         10
    1584: ifeq          1627
    1587: getstatic     #62                 // Field AFCKELYG.m:[I
    1590: iload_2
    1591: iload         6
    1593: iconst_0
    1594: iload         5
    1596: bipush        16
    1598: ishr
    1599: iload         4
    1601: bipush        16
    1603: ishr
    1604: invokestatic  #47                 // Method a:([IIIIII)V
    1607: iload         4
    1609: iload         8
    1611: iadd
    1612: istore        4
    1614: iload         5
    1616: iload         9
    1618: iadd
    1619: istore        5
    1621: iload_2
    1622: getstatic     #83                 // Field AFCKELYG.n:I
    1625: iadd
    1626: istore_2
    1627: iinc          0, -1
    1630: iload_0
    1631: ifge          1587
    1634: iload         10
    1636: ifeq          1676
    1639: getstatic     #62                 // Field AFCKELYG.m:[I
    1642: iload_2
    1643: iload         6
    1645: iconst_0
    1646: iload_3
    1647: bipush        16
    1649: ishr
    1650: iload         4
    1652: bipush        16
    1654: ishr
    1655: invokestatic  #47                 // Method a:([IIIIII)V
    1658: iload         4
    1660: iload         8
    1662: iadd
    1663: istore        4
    1665: iload_3
    1666: iload         7
    1668: iadd
    1669: istore_3
    1670: iload_2
    1671: getstatic     #83                 // Field AFCKELYG.n:I
    1674: iadd
    1675: istore_2
    1676: iinc          1, -1
    1679: iload_1
    1680: ifge          1639
    1683: return
    1684: iload         5
    1686: bipush        16
    1688: ishl
    1689: dup
    1690: istore        5
    1692: istore_3
    1693: iload_2
    1694: ifge          1715
    1697: iload_3
    1698: iload         8
    1700: iload_2
    1701: imul
    1702: isub
    1703: istore_3
    1704: iload         5
    1706: iload         9
    1708: iload_2
    1709: imul
    1710: isub
    1711: istore        5
    1713: iconst_0
    1714: istore_2
    1715: iload         4
    1717: bipush        16
    1719: ishl
    1720: istore        4
    1722: iload_1
    1723: ifge          1737
    1726: iload         4
    1728: iload         7
    1730: iload_1
    1731: imul
    1732: isub
    1733: istore        4
    1735: iconst_0
    1736: istore_1
    1737: iload         8
    1739: iload         9
    1741: if_icmpge     1860
    1744: iload_0
    1745: iload_1
    1746: isub
    1747: istore_0
    1748: iload_1
    1749: iload_2
    1750: isub
    1751: istore_1
    1752: getstatic     #66                 // Field L:[I
    1755: iload_2
    1756: iaload
    1757: istore_2
    1758: iload         10
    1760: ifeq          1800
    1763: getstatic     #62                 // Field AFCKELYG.m:[I
    1766: iload_2
    1767: iload         6
    1769: iconst_0
    1770: iload_3
    1771: bipush        16
    1773: ishr
    1774: iload         5
    1776: bipush        16
    1778: ishr
    1779: invokestatic  #47                 // Method a:([IIIIII)V
    1782: iload_3
    1783: iload         8
    1785: iadd
    1786: istore_3
    1787: iload         5
    1789: iload         9
    1791: iadd
    1792: istore        5
    1794: iload_2
    1795: getstatic     #83                 // Field AFCKELYG.n:I
    1798: iadd
    1799: istore_2
    1800: iinc          1, -1
    1803: iload_1
    1804: ifge          1763
    1807: iload         10
    1809: ifeq          1852
    1812: getstatic     #62                 // Field AFCKELYG.m:[I
    1815: iload_2
    1816: iload         6
    1818: iconst_0
    1819: iload         4
    1821: bipush        16
    1823: ishr
    1824: iload         5
    1826: bipush        16
    1828: ishr
    1829: invokestatic  #47                 // Method a:([IIIIII)V
    1832: iload         4
    1834: iload         7
    1836: iadd
    1837: istore        4
    1839: iload         5
    1841: iload         9
    1843: iadd
    1844: istore        5
    1846: iload_2
    1847: getstatic     #83                 // Field AFCKELYG.n:I
    1850: iadd
    1851: istore_2
    1852: iinc          0, -1
    1855: iload_0
    1856: ifge          1812
    1859: return
    1860: iload_0
    1861: iload_1
    1862: isub
    1863: istore_0
    1864: iload_1
    1865: iload_2
    1866: isub
    1867: istore_1
    1868: getstatic     #66                 // Field L:[I
    1871: iload_2
    1872: iaload
    1873: istore_2
    1874: iload         10
    1876: ifeq          1916
    1879: getstatic     #62                 // Field AFCKELYG.m:[I
    1882: iload_2
    1883: iload         6
    1885: iconst_0
    1886: iload         5
    1888: bipush        16
    1890: ishr
    1891: iload_3
    1892: bipush        16
    1894: ishr
    1895: invokestatic  #47                 // Method a:([IIIIII)V
    1898: iload_3
    1899: iload         8
    1901: iadd
    1902: istore_3
    1903: iload         5
    1905: iload         9
    1907: iadd
    1908: istore        5
    1910: iload_2
    1911: getstatic     #83                 // Field AFCKELYG.n:I
    1914: iadd
    1915: istore_2
    1916: iinc          1, -1
    1919: iload_1
    1920: ifge          1879
    1923: iload         10
    1925: ifeq          1968
    1928: getstatic     #62                 // Field AFCKELYG.m:[I
    1931: iload_2
    1932: iload         6
    1934: iconst_0
    1935: iload         5
    1937: bipush        16
    1939: ishr
    1940: iload         4
    1942: bipush        16
    1944: ishr
    1945: invokestatic  #47                 // Method a:([IIIIII)V
    1948: iload         4
    1950: iload         7
    1952: iadd
    1953: istore        4
    1955: iload         5
    1957: iload         9
    1959: iadd
    1960: istore        5
    1962: iload_2
    1963: getstatic     #83                 // Field AFCKELYG.n:I
    1966: iadd
    1967: istore_2
    1968: iinc          0, -1
    1971: iload_0
    1972: ifge          1928
    1975: return

  public static final void a(int[], int, int, int, int, int);
    Code:
       0: getstatic     #289                // Field XHHRODPC.l:Z
       3: istore        8
       5: getstatic     #53                 // Field B:Z
       8: ifeq          32
      11: iload         5
      13: getstatic     #84                 // Field AFCKELYG.t:I
      16: if_icmple     24
      19: getstatic     #84                 // Field AFCKELYG.t:I
      22: istore        5
      24: iload         4
      26: ifge          32
      29: iconst_0
      30: istore        4
      32: iload         4
      34: iload         5
      36: if_icmplt     40
      39: return
      40: iload_1
      41: iload         4
      43: iadd
      44: istore_1
      45: iload         5
      47: iload         4
      49: isub
      50: iconst_2
      51: ishr
      52: istore_3
      53: getstatic     #78                 // Field E:I
      56: ifne          127
      59: iload         8
      61: ifeq          92
      64: aload_0
      65: iload_1
      66: iinc          1, 1
      69: iload_2
      70: iastore
      71: aload_0
      72: iload_1
      73: iinc          1, 1
      76: iload_2
      77: iastore
      78: aload_0
      79: iload_1
      80: iinc          1, 1
      83: iload_2
      84: iastore
      85: aload_0
      86: iload_1
      87: iinc          1, 1
      90: iload_2
      91: iastore
      92: iinc          3, -1
      95: iload_3
      96: ifge          64
      99: iload         5
     101: iload         4
     103: isub
     104: iconst_3
     105: iand
     106: istore_3
     107: iload         8
     109: ifeq          119
     112: aload_0
     113: iload_1
     114: iinc          1, 1
     117: iload_2
     118: iastore
     119: iinc          3, -1
     122: iload_3
     123: ifge          112
     126: return
     127: getstatic     #78                 // Field E:I
     130: istore        6
     132: sipush        256
     135: getstatic     #78                 // Field E:I
     138: isub
     139: istore        7
     141: iload_2
     142: ldc           #7                  // int 16711935
     144: iand
     145: iload         7
     147: imul
     148: bipush        8
     150: ishr
     151: ldc           #7                  // int 16711935
     153: iand
     154: iload_2
     155: ldc           #3                  // int 65280
     157: iand
     158: iload         7
     160: imul
     161: bipush        8
     163: ishr
     164: ldc           #3                  // int 65280
     166: iand
     167: iadd
     168: istore_2
     169: iload         8
     171: ifeq          330
     174: aload_0
     175: iload_1
     176: iinc          1, 1
     179: iload_2
     180: aload_0
     181: iload_1
     182: iaload
     183: ldc           #7                  // int 16711935
     185: iand
     186: iload         6
     188: imul
     189: bipush        8
     191: ishr
     192: ldc           #7                  // int 16711935
     194: iand
     195: iadd
     196: aload_0
     197: iload_1
     198: iaload
     199: ldc           #3                  // int 65280
     201: iand
     202: iload         6
     204: imul
     205: bipush        8
     207: ishr
     208: ldc           #3                  // int 65280
     210: iand
     211: iadd
     212: iastore
     213: aload_0
     214: iload_1
     215: iinc          1, 1
     218: iload_2
     219: aload_0
     220: iload_1
     221: iaload
     222: ldc           #7                  // int 16711935
     224: iand
     225: iload         6
     227: imul
     228: bipush        8
     230: ishr
     231: ldc           #7                  // int 16711935
     233: iand
     234: iadd
     235: aload_0
     236: iload_1
     237: iaload
     238: ldc           #3                  // int 65280
     240: iand
     241: iload         6
     243: imul
     244: bipush        8
     246: ishr
     247: ldc           #3                  // int 65280
     249: iand
     250: iadd
     251: iastore
     252: aload_0
     253: iload_1
     254: iinc          1, 1
     257: iload_2
     258: aload_0
     259: iload_1
     260: iaload
     261: ldc           #7                  // int 16711935
     263: iand
     264: iload         6
     266: imul
     267: bipush        8
     269: ishr
     270: ldc           #7                  // int 16711935
     272: iand
     273: iadd
     274: aload_0
     275: iload_1
     276: iaload
     277: ldc           #3                  // int 65280
     279: iand
     280: iload         6
     282: imul
     283: bipush        8
     285: ishr
     286: ldc           #3                  // int 65280
     288: iand
     289: iadd
     290: iastore
     291: aload_0
     292: iload_1
     293: iinc          1, 1
     296: iload_2
     297: aload_0
     298: iload_1
     299: iaload
     300: ldc           #7                  // int 16711935
     302: iand
     303: iload         6
     305: imul
     306: bipush        8
     308: ishr
     309: ldc           #7                  // int 16711935
     311: iand
     312: iadd
     313: aload_0
     314: iload_1
     315: iaload
     316: ldc           #3                  // int 65280
     318: iand
     319: iload         6
     321: imul
     322: bipush        8
     324: ishr
     325: ldc           #3                  // int 65280
     327: iand
     328: iadd
     329: iastore
     330: iinc          3, -1
     333: iload_3
     334: ifge          174
     337: iload         5
     339: iload         4
     341: isub
     342: iconst_3
     343: iand
     344: istore_3
     345: iload         8
     347: ifeq          389
     350: aload_0
     351: iload_1
     352: iinc          1, 1
     355: iload_2
     356: aload_0
     357: iload_1
     358: iaload
     359: ldc           #7                  // int 16711935
     361: iand
     362: iload         6
     364: imul
     365: bipush        8
     367: ishr
     368: ldc           #7                  // int 16711935
     370: iand
     371: iadd
     372: aload_0
     373: iload_1
     374: iaload
     375: ldc           #3                  // int 65280
     377: iand
     378: iload         6
     380: imul
     381: bipush        8
     383: ishr
     384: ldc           #3                  // int 65280
     386: iand
     387: iadd
     388: iastore
     389: iinc          3, -1
     392: iload_3
     393: ifge          350
     396: return

  public static final void a(int, int, int, int, int, int, int, int, int, int, int, int, int, int, int, int, int, int, int);
    Code:
       0: getstatic     #289                // Field XHHRODPC.l:Z
       3: istore        36
       5: iload         18
       7: invokestatic  #39                 // Method d:(I)[I
      10: astore        19
      12: getstatic     #79                 // Field O:[Z
      15: iload         18
      17: baload
      18: ifeq          25
      21: iconst_0
      22: goto          26
      25: iconst_1
      26: putstatic     #69                 // Field C:Z
      29: iload         9
      31: iload         10
      33: isub
      34: istore        10
      36: iload         12
      38: iload         13
      40: isub
      41: istore        13
      43: iload         15
      45: iload         16
      47: isub
      48: istore        16
      50: iload         11
      52: iload         9
      54: isub
      55: istore        11
      57: iload         14
      59: iload         12
      61: isub
      62: istore        14
      64: iload         17
      66: iload         15
      68: isub
      69: istore        17
      71: iload         11
      73: iload         12
      75: imul
      76: iload         14
      78: iload         9
      80: imul
      81: isub
      82: bipush        14
      84: ishl
      85: istore        20
      87: iload         14
      89: iload         15
      91: imul
      92: iload         17
      94: iload         12
      96: imul
      97: isub
      98: bipush        8
     100: ishl
     101: istore        21
     103: iload         17
     105: iload         9
     107: imul
     108: iload         11
     110: iload         15
     112: imul
     113: isub
     114: iconst_5
     115: ishl
     116: istore        22
     118: iload         10
     120: iload         12
     122: imul
     123: iload         13
     125: iload         9
     127: imul
     128: isub
     129: bipush        14
     131: ishl
     132: istore        23
     134: iload         13
     136: iload         15
     138: imul
     139: iload         16
     141: iload         12
     143: imul
     144: isub
     145: bipush        8
     147: ishl
     148: istore        24
     150: iload         16
     152: iload         9
     154: imul
     155: iload         10
     157: iload         15
     159: imul
     160: isub
     161: iconst_5
     162: ishl
     163: istore        25
     165: iload         13
     167: iload         11
     169: imul
     170: iload         10
     172: iload         14
     174: imul
     175: isub
     176: bipush        14
     178: ishl
     179: istore        26
     181: iload         16
     183: iload         14
     185: imul
     186: iload         13
     188: iload         17
     190: imul
     191: isub
     192: bipush        8
     194: ishl
     195: istore        27
     197: iload         10
     199: iload         17
     201: imul
     202: iload         16
     204: iload         11
     206: imul
     207: isub
     208: iconst_5
     209: ishl
     210: istore        28
     212: iconst_0
     213: istore        29
     215: iconst_0
     216: istore        30
     218: iload_1
     219: iload_0
     220: if_icmpeq     250
     223: iload         4
     225: iload_3
     226: isub
     227: bipush        16
     229: ishl
     230: iload_1
     231: iload_0
     232: isub
     233: idiv
     234: istore        29
     236: iload         7
     238: iload         6
     240: isub
     241: bipush        16
     243: ishl
     244: iload_1
     245: iload_0
     246: isub
     247: idiv
     248: istore        30
     250: iconst_0
     251: istore        31
     253: iconst_0
     254: istore        32
     256: iload_2
     257: iload_1
     258: if_icmpeq     289
     261: iload         5
     263: iload         4
     265: isub
     266: bipush        16
     268: ishl
     269: iload_2
     270: iload_1
     271: isub
     272: idiv
     273: istore        31
     275: iload         8
     277: iload         7
     279: isub
     280: bipush        16
     282: ishl
     283: iload_2
     284: iload_1
     285: isub
     286: idiv
     287: istore        32
     289: iconst_0
     290: istore        33
     292: iconst_0
     293: istore        34
     295: iload_2
     296: iload_0
     297: if_icmpeq     327
     300: iload_3
     301: iload         5
     303: isub
     304: bipush        16
     306: ishl
     307: iload_0
     308: iload_2
     309: isub
     310: idiv
     311: istore        33
     313: iload         6
     315: iload         8
     317: isub
     318: bipush        16
     320: ishl
     321: iload_0
     322: iload_2
     323: isub
     324: idiv
     325: istore        34
     327: iload_0
     328: iload_1
     329: if_icmpgt     1608
     332: iload_0
     333: iload_2
     334: if_icmpgt     1608
     337: iload_0
     338: getstatic     #86                 // Field AFCKELYG.q:I
     341: if_icmplt     345
     344: return
     345: iload_1
     346: getstatic     #86                 // Field AFCKELYG.q:I
     349: if_icmple     356
     352: getstatic     #86                 // Field AFCKELYG.q:I
     355: istore_1
     356: iload_2
     357: getstatic     #86                 // Field AFCKELYG.q:I
     360: if_icmple     367
     363: getstatic     #86                 // Field AFCKELYG.q:I
     366: istore_2
     367: iload_1
     368: iload_2
     369: if_icmpge     993
     372: iload_3
     373: bipush        16
     375: ishl
     376: dup
     377: istore_3
     378: istore        5
     380: iload         6
     382: bipush        16
     384: ishl
     385: dup
     386: istore        6
     388: istore        8
     390: iload_0
     391: ifge          430
     394: iload         5
     396: iload         33
     398: iload_0
     399: imul
     400: isub
     401: istore        5
     403: iload_3
     404: iload         29
     406: iload_0
     407: imul
     408: isub
     409: istore_3
     410: iload         8
     412: iload         34
     414: iload_0
     415: imul
     416: isub
     417: istore        8
     419: iload         6
     421: iload         30
     423: iload_0
     424: imul
     425: isub
     426: istore        6
     428: iconst_0
     429: istore_0
     430: iload         4
     432: bipush        16
     434: ishl
     435: istore        4
     437: iload         7
     439: bipush        16
     441: ishl
     442: istore        7
     444: iload_1
     445: ifge          468
     448: iload         4
     450: iload         31
     452: iload_1
     453: imul
     454: isub
     455: istore        4
     457: iload         7
     459: iload         32
     461: iload_1
     462: imul
     463: isub
     464: istore        7
     466: iconst_0
     467: istore_1
     468: iload_0
     469: getstatic     #87                 // Field G:I
     472: isub
     473: istore        35
     475: iload         20
     477: iload         22
     479: iload         35
     481: imul
     482: iadd
     483: istore        20
     485: iload         23
     487: iload         25
     489: iload         35
     491: imul
     492: iadd
     493: istore        23
     495: iload         26
     497: iload         28
     499: iload         35
     501: imul
     502: iadd
     503: istore        26
     505: iload_0
     506: iload_1
     507: if_icmpeq     517
     510: iload         33
     512: iload         29
     514: if_icmplt     529
     517: iload_0
     518: iload_1
     519: if_icmpne     761
     522: iload         33
     524: iload         31
     526: if_icmple     761
     529: iload_2
     530: iload_1
     531: isub
     532: istore_2
     533: iload_1
     534: iload_0
     535: isub
     536: istore_1
     537: getstatic     #66                 // Field L:[I
     540: iload_0
     541: iaload
     542: istore_0
     543: iload         36
     545: ifeq          643
     548: getstatic     #62                 // Field AFCKELYG.m:[I
     551: aload         19
     553: iconst_0
     554: iconst_0
     555: iload_0
     556: iload         5
     558: bipush        16
     560: ishr
     561: iload_3
     562: bipush        16
     564: ishr
     565: iload         8
     567: bipush        8
     569: ishr
     570: iload         6
     572: bipush        8
     574: ishr
     575: iload         20
     577: iload         23
     579: iload         26
     581: iload         21
     583: iload         24
     585: iload         27
     587: invokestatic  #74                 // Method a:([I[IIIIIIIIIIIIII)V
     590: iload         5
     592: iload         33
     594: iadd
     595: istore        5
     597: iload_3
     598: iload         29
     600: iadd
     601: istore_3
     602: iload         8
     604: iload         34
     606: iadd
     607: istore        8
     609: iload         6
     611: iload         30
     613: iadd
     614: istore        6
     616: iload_0
     617: getstatic     #83                 // Field AFCKELYG.n:I
     620: iadd
     621: istore_0
     622: iload         20
     624: iload         22
     626: iadd
     627: istore        20
     629: iload         23
     631: iload         25
     633: iadd
     634: istore        23
     636: iload         26
     638: iload         28
     640: iadd
     641: istore        26
     643: iinc          1, -1
     646: iload_1
     647: ifge          548
     650: iload         36
     652: ifeq          753
     655: getstatic     #62                 // Field AFCKELYG.m:[I
     658: aload         19
     660: iconst_0
     661: iconst_0
     662: iload_0
     663: iload         5
     665: bipush        16
     667: ishr
     668: iload         4
     670: bipush        16
     672: ishr
     673: iload         8
     675: bipush        8
     677: ishr
     678: iload         7
     680: bipush        8
     682: ishr
     683: iload         20
     685: iload         23
     687: iload         26
     689: iload         21
     691: iload         24
     693: iload         27
     695: invokestatic  #74                 // Method a:([I[IIIIIIIIIIIIII)V
     698: iload         5
     700: iload         33
     702: iadd
     703: istore        5
     705: iload         4
     707: iload         31
     709: iadd
     710: istore        4
     712: iload         8
     714: iload         34
     716: iadd
     717: istore        8
     719: iload         7
     721: iload         32
     723: iadd
     724: istore        7
     726: iload_0
     727: getstatic     #83                 // Field AFCKELYG.n:I
     730: iadd
     731: istore_0
     732: iload         20
     734: iload         22
     736: iadd
     737: istore        20
     739: iload         23
     741: iload         25
     743: iadd
     744: istore        23
     746: iload         26
     748: iload         28
     750: iadd
     751: istore        26
     753: iinc          2, -1
     756: iload_2
     757: ifge          655
     760: return
     761: iload_2
     762: iload_1
     763: isub
     764: istore_2
     765: iload_1
     766: iload_0
     767: isub
     768: istore_1
     769: getstatic     #66                 // Field L:[I
     772: iload_0
     773: iaload
     774: istore_0
     775: iload         36
     777: ifeq          875
     780: getstatic     #62                 // Field AFCKELYG.m:[I
     783: aload         19
     785: iconst_0
     786: iconst_0
     787: iload_0
     788: iload_3
     789: bipush        16
     791: ishr
     792: iload         5
     794: bipush        16
     796: ishr
     797: iload         6
     799: bipush        8
     801: ishr
     802: iload         8
     804: bipush        8
     806: ishr
     807: iload         20
     809: iload         23
     811: iload         26
     813: iload         21
     815: iload         24
     817: iload         27
     819: invokestatic  #74                 // Method a:([I[IIIIIIIIIIIIII)V
     822: iload         5
     824: iload         33
     826: iadd
     827: istore        5
     829: iload_3
     830: iload         29
     832: iadd
     833: istore_3
     834: iload         8
     836: iload         34
     838: iadd
     839: istore        8
     841: iload         6
     843: iload         30
     845: iadd
     846: istore        6
     848: iload_0
     849: getstatic     #83                 // Field AFCKELYG.n:I
     852: iadd
     853: istore_0
     854: iload         20
     856: iload         22
     858: iadd
     859: istore        20
     861: iload         23
     863: iload         25
     865: iadd
     866: istore        23
     868: iload         26
     870: iload         28
     872: iadd
     873: istore        26
     875: iinc          1, -1
     878: iload_1
     879: ifge          780
     882: iload         36
     884: ifeq          985
     887: getstatic     #62                 // Field AFCKELYG.m:[I
     890: aload         19
     892: iconst_0
     893: iconst_0
     894: iload_0
     895: iload         4
     897: bipush        16
     899: ishr
     900: iload         5
     902: bipush        16
     904: ishr
     905: iload         7
     907: bipush        8
     909: ishr
     910: iload         8
     912: bipush        8
     914: ishr
     915: iload         20
     917: iload         23
     919: iload         26
     921: iload         21
     923: iload         24
     925: iload         27
     927: invokestatic  #74                 // Method a:([I[IIIIIIIIIIIIII)V
     930: iload         5
     932: iload         33
     934: iadd
     935: istore        5
     937: iload         4
     939: iload         31
     941: iadd
     942: istore        4
     944: iload         8
     946: iload         34
     948: iadd
     949: istore        8
     951: iload         7
     953: iload         32
     955: iadd
     956: istore        7
     958: iload_0
     959: getstatic     #83                 // Field AFCKELYG.n:I
     962: iadd
     963: istore_0
     964: iload         20
     966: iload         22
     968: iadd
     969: istore        20
     971: iload         23
     973: iload         25
     975: iadd
     976: istore        23
     978: iload         26
     980: iload         28
     982: iadd
     983: istore        26
     985: iinc          2, -1
     988: iload_2
     989: ifge          887
     992: return
     993: iload_3
     994: bipush        16
     996: ishl
     997: dup
     998: istore_3
     999: istore        4
    1001: iload         6
    1003: bipush        16
    1005: ishl
    1006: dup
    1007: istore        6
    1009: istore        7
    1011: iload_0
    1012: ifge          1051
    1015: iload         4
    1017: iload         33
    1019: iload_0
    1020: imul
    1021: isub
    1022: istore        4
    1024: iload_3
    1025: iload         29
    1027: iload_0
    1028: imul
    1029: isub
    1030: istore_3
    1031: iload         7
    1033: iload         34
    1035: iload_0
    1036: imul
    1037: isub
    1038: istore        7
    1040: iload         6
    1042: iload         30
    1044: iload_0
    1045: imul
    1046: isub
    1047: istore        6
    1049: iconst_0
    1050: istore_0
    1051: iload         5
    1053: bipush        16
    1055: ishl
    1056: istore        5
    1058: iload         8
    1060: bipush        16
    1062: ishl
    1063: istore        8
    1065: iload_2
    1066: ifge          1089
    1069: iload         5
    1071: iload         31
    1073: iload_2
    1074: imul
    1075: isub
    1076: istore        5
    1078: iload         8
    1080: iload         32
    1082: iload_2
    1083: imul
    1084: isub
    1085: istore        8
    1087: iconst_0
    1088: istore_2
    1089: iload_0
    1090: getstatic     #87                 // Field G:I
    1093: isub
    1094: istore        35
    1096: iload         20
    1098: iload         22
    1100: iload         35
    1102: imul
    1103: iadd
    1104: istore        20
    1106: iload         23
    1108: iload         25
    1110: iload         35
    1112: imul
    1113: iadd
    1114: istore        23
    1116: iload         26
    1118: iload         28
    1120: iload         35
    1122: imul
    1123: iadd
    1124: istore        26
    1126: iload_0
    1127: iload_2
    1128: if_icmpeq     1138
    1131: iload         33
    1133: iload         29
    1135: if_icmplt     1150
    1138: iload_0
    1139: iload_2
    1140: if_icmpne     1379
    1143: iload         31
    1145: iload         29
    1147: if_icmple     1379
    1150: iload_1
    1151: iload_2
    1152: isub
    1153: istore_1
    1154: iload_2
    1155: iload_0
    1156: isub
    1157: istore_2
    1158: getstatic     #66                 // Field L:[I
    1161: iload_0
    1162: iaload
    1163: istore_0
    1164: iload         36
    1166: ifeq          1264
    1169: getstatic     #62                 // Field AFCKELYG.m:[I
    1172: aload         19
    1174: iconst_0
    1175: iconst_0
    1176: iload_0
    1177: iload         4
    1179: bipush        16
    1181: ishr
    1182: iload_3
    1183: bipush        16
    1185: ishr
    1186: iload         7
    1188: bipush        8
    1190: ishr
    1191: iload         6
    1193: bipush        8
    1195: ishr
    1196: iload         20
    1198: iload         23
    1200: iload         26
    1202: iload         21
    1204: iload         24
    1206: iload         27
    1208: invokestatic  #74                 // Method a:([I[IIIIIIIIIIIIII)V
    1211: iload         4
    1213: iload         33
    1215: iadd
    1216: istore        4
    1218: iload_3
    1219: iload         29
    1221: iadd
    1222: istore_3
    1223: iload         7
    1225: iload         34
    1227: iadd
    1228: istore        7
    1230: iload         6
    1232: iload         30
    1234: iadd
    1235: istore        6
    1237: iload_0
    1238: getstatic     #83                 // Field AFCKELYG.n:I
    1241: iadd
    1242: istore_0
    1243: iload         20
    1245: iload         22
    1247: iadd
    1248: istore        20
    1250: iload         23
    1252: iload         25
    1254: iadd
    1255: istore        23
    1257: iload         26
    1259: iload         28
    1261: iadd
    1262: istore        26
    1264: iinc          2, -1
    1267: iload_2
    1268: ifge          1169
    1271: iload         36
    1273: ifeq          1371
    1276: getstatic     #62                 // Field AFCKELYG.m:[I
    1279: aload         19
    1281: iconst_0
    1282: iconst_0
    1283: iload_0
    1284: iload         5
    1286: bipush        16
    1288: ishr
    1289: iload_3
    1290: bipush        16
    1292: ishr
    1293: iload         8
    1295: bipush        8
    1297: ishr
    1298: iload         6
    1300: bipush        8
    1302: ishr
    1303: iload         20
    1305: iload         23
    1307: iload         26
    1309: iload         21
    1311: iload         24
    1313: iload         27
    1315: invokestatic  #74                 // Method a:([I[IIIIIIIIIIIIII)V
    1318: iload         5
    1320: iload         31
    1322: iadd
    1323: istore        5
    1325: iload_3
    1326: iload         29
    1328: iadd
    1329: istore_3
    1330: iload         8
    1332: iload         32
    1334: iadd
    1335: istore        8
    1337: iload         6
    1339: iload         30
    1341: iadd
    1342: istore        6
    1344: iload_0
    1345: getstatic     #83                 // Field AFCKELYG.n:I
    1348: iadd
    1349: istore_0
    1350: iload         20
    1352: iload         22
    1354: iadd
    1355: istore        20
    1357: iload         23
    1359: iload         25
    1361: iadd
    1362: istore        23
    1364: iload         26
    1366: iload         28
    1368: iadd
    1369: istore        26
    1371: iinc          1, -1
    1374: iload_1
    1375: ifge          1276
    1378: return
    1379: iload_1
    1380: iload_2
    1381: isub
    1382: istore_1
    1383: iload_2
    1384: iload_0
    1385: isub
    1386: istore_2
    1387: getstatic     #66                 // Field L:[I
    1390: iload_0
    1391: iaload
    1392: istore_0
    1393: iload         36
    1395: ifeq          1493
    1398: getstatic     #62                 // Field AFCKELYG.m:[I
    1401: aload         19
    1403: iconst_0
    1404: iconst_0
    1405: iload_0
    1406: iload_3
    1407: bipush        16
    1409: ishr
    1410: iload         4
    1412: bipush        16
    1414: ishr
    1415: iload         6
    1417: bipush        8
    1419: ishr
    1420: iload         7
    1422: bipush        8
    1424: ishr
    1425: iload         20
    1427: iload         23
    1429: iload         26
    1431: iload         21
    1433: iload         24
    1435: iload         27
    1437: invokestatic  #74                 // Method a:([I[IIIIIIIIIIIIII)V
    1440: iload         4
    1442: iload         33
    1444: iadd
    1445: istore        4
    1447: iload_3
    1448: iload         29
    1450: iadd
    1451: istore_3
    1452: iload         7
    1454: iload         34
    1456: iadd
    1457: istore        7
    1459: iload         6
    1461: iload         30
    1463: iadd
    1464: istore        6
    1466: iload_0
    1467: getstatic     #83                 // Field AFCKELYG.n:I
    1470: iadd
    1471: istore_0
    1472: iload         20
    1474: iload         22
    1476: iadd
    1477: istore        20
    1479: iload         23
    1481: iload         25
    1483: iadd
    1484: istore        23
    1486: iload         26
    1488: iload         28
    1490: iadd
    1491: istore        26
    1493: iinc          2, -1
    1496: iload_2
    1497: ifge          1398
    1500: iload         36
    1502: ifeq          1600
    1505: getstatic     #62                 // Field AFCKELYG.m:[I
    1508: aload         19
    1510: iconst_0
    1511: iconst_0
    1512: iload_0
    1513: iload_3
    1514: bipush        16
    1516: ishr
    1517: iload         5
    1519: bipush        16
    1521: ishr
    1522: iload         6
    1524: bipush        8
    1526: ishr
    1527: iload         8
    1529: bipush        8
    1531: ishr
    1532: iload         20
    1534: iload         23
    1536: iload         26
    1538: iload         21
    1540: iload         24
    1542: iload         27
    1544: invokestatic  #74                 // Method a:([I[IIIIIIIIIIIIII)V
    1547: iload         5
    1549: iload         31
    1551: iadd
    1552: istore        5
    1554: iload_3
    1555: iload         29
    1557: iadd
    1558: istore_3
    1559: iload         8
    1561: iload         32
    1563: iadd
    1564: istore        8
    1566: iload         6
    1568: iload         30
    1570: iadd
    1571: istore        6
    1573: iload_0
    1574: getstatic     #83                 // Field AFCKELYG.n:I
    1577: iadd
    1578: istore_0
    1579: iload         20
    1581: iload         22
    1583: iadd
    1584: istore        20
    1586: iload         23
    1588: iload         25
    1590: iadd
    1591: istore        23
    1593: iload         26
    1595: iload         28
    1597: iadd
    1598: istore        26
    1600: iinc          1, -1
    1603: iload_1
    1604: ifge          1505
    1607: return
    1608: iload_1
    1609: iload_2
    1610: if_icmpgt     2868
    1613: iload_1
    1614: getstatic     #86                 // Field AFCKELYG.q:I
    1617: if_icmplt     1621
    1620: return
    1621: iload_2
    1622: getstatic     #86                 // Field AFCKELYG.q:I
    1625: if_icmple     1632
    1628: getstatic     #86                 // Field AFCKELYG.q:I
    1631: istore_2
    1632: iload_0
    1633: getstatic     #86                 // Field AFCKELYG.q:I
    1636: if_icmple     1643
    1639: getstatic     #86                 // Field AFCKELYG.q:I
    1642: istore_0
    1643: iload_2
    1644: iload_0
    1645: if_icmpge     2264
    1648: iload         4
    1650: bipush        16
    1652: ishl
    1653: dup
    1654: istore        4
    1656: istore_3
    1657: iload         7
    1659: bipush        16
    1661: ishl
    1662: dup
    1663: istore        7
    1665: istore        6
    1667: iload_1
    1668: ifge          1707
    1671: iload_3
    1672: iload         29
    1674: iload_1
    1675: imul
    1676: isub
    1677: istore_3
    1678: iload         4
    1680: iload         31
    1682: iload_1
    1683: imul
    1684: isub
    1685: istore        4
    1687: iload         6
    1689: iload         30
    1691: iload_1
    1692: imul
    1693: isub
    1694: istore        6
    1696: iload         7
    1698: iload         32
    1700: iload_1
    1701: imul
    1702: isub
    1703: istore        7
    1705: iconst_0
    1706: istore_1
    1707: iload         5
    1709: bipush        16
    1711: ishl
    1712: istore        5
    1714: iload         8
    1716: bipush        16
    1718: ishl
    1719: istore        8
    1721: iload_2
    1722: ifge          1745
    1725: iload         5
    1727: iload         33
    1729: iload_2
    1730: imul
    1731: isub
    1732: istore        5
    1734: iload         8
    1736: iload         34
    1738: iload_2
    1739: imul
    1740: isub
    1741: istore        8
    1743: iconst_0
    1744: istore_2
    1745: iload_1
    1746: getstatic     #87                 // Field G:I
    1749: isub
    1750: istore        35
    1752: iload         20
    1754: iload         22
    1756: iload         35
    1758: imul
    1759: iadd
    1760: istore        20
    1762: iload         23
    1764: iload         25
    1766: iload         35
    1768: imul
    1769: iadd
    1770: istore        23
    1772: iload         26
    1774: iload         28
    1776: iload         35
    1778: imul
    1779: iadd
    1780: istore        26
    1782: iload_1
    1783: iload_2
    1784: if_icmpeq     1794
    1787: iload         29
    1789: iload         31
    1791: if_icmplt     1806
    1794: iload_1
    1795: iload_2
    1796: if_icmpne     2035
    1799: iload         29
    1801: iload         33
    1803: if_icmple     2035
    1806: iload_0
    1807: iload_2
    1808: isub
    1809: istore_0
    1810: iload_2
    1811: iload_1
    1812: isub
    1813: istore_2
    1814: getstatic     #66                 // Field L:[I
    1817: iload_1
    1818: iaload
    1819: istore_1
    1820: iload         36
    1822: ifeq          1920
    1825: getstatic     #62                 // Field AFCKELYG.m:[I
    1828: aload         19
    1830: iconst_0
    1831: iconst_0
    1832: iload_1
    1833: iload_3
    1834: bipush        16
    1836: ishr
    1837: iload         4
    1839: bipush        16
    1841: ishr
    1842: iload         6
    1844: bipush        8
    1846: ishr
    1847: iload         7
    1849: bipush        8
    1851: ishr
    1852: iload         20
    1854: iload         23
    1856: iload         26
    1858: iload         21
    1860: iload         24
    1862: iload         27
    1864: invokestatic  #74                 // Method a:([I[IIIIIIIIIIIIII)V
    1867: iload_3
    1868: iload         29
    1870: iadd
    1871: istore_3
    1872: iload         4
    1874: iload         31
    1876: iadd
    1877: istore        4
    1879: iload         6
    1881: iload         30
    1883: iadd
    1884: istore        6
    1886: iload         7
    1888: iload         32
    1890: iadd
    1891: istore        7
    1893: iload_1
    1894: getstatic     #83                 // Field AFCKELYG.n:I
    1897: iadd
    1898: istore_1
    1899: iload         20
    1901: iload         22
    1903: iadd
    1904: istore        20
    1906: iload         23
    1908: iload         25
    1910: iadd
    1911: istore        23
    1913: iload         26
    1915: iload         28
    1917: iadd
    1918: istore        26
    1920: iinc          2, -1
    1923: iload_2
    1924: ifge          1825
    1927: iload         36
    1929: ifeq          2027
    1932: getstatic     #62                 // Field AFCKELYG.m:[I
    1935: aload         19
    1937: iconst_0
    1938: iconst_0
    1939: iload_1
    1940: iload_3
    1941: bipush        16
    1943: ishr
    1944: iload         5
    1946: bipush        16
    1948: ishr
    1949: iload         6
    1951: bipush        8
    1953: ishr
    1954: iload         8
    1956: bipush        8
    1958: ishr
    1959: iload         20
    1961: iload         23
    1963: iload         26
    1965: iload         21
    1967: iload         24
    1969: iload         27
    1971: invokestatic  #74                 // Method a:([I[IIIIIIIIIIIIII)V
    1974: iload_3
    1975: iload         29
    1977: iadd
    1978: istore_3
    1979: iload         5
    1981: iload         33
    1983: iadd
    1984: istore        5
    1986: iload         6
    1988: iload         30
    1990: iadd
    1991: istore        6
    1993: iload         8
    1995: iload         34
    1997: iadd
    1998: istore        8
    2000: iload_1
    2001: getstatic     #83                 // Field AFCKELYG.n:I
    2004: iadd
    2005: istore_1
    2006: iload         20
    2008: iload         22
    2010: iadd
    2011: istore        20
    2013: iload         23
    2015: iload         25
    2017: iadd
    2018: istore        23
    2020: iload         26
    2022: iload         28
    2024: iadd
    2025: istore        26
    2027: iinc          0, -1
    2030: iload_0
    2031: ifge          1932
    2034: return
    2035: iload_0
    2036: iload_2
    2037: isub
    2038: istore_0
    2039: iload_2
    2040: iload_1
    2041: isub
    2042: istore_2
    2043: getstatic     #66                 // Field L:[I
    2046: iload_1
    2047: iaload
    2048: istore_1
    2049: iload         36
    2051: ifeq          2149
    2054: getstatic     #62                 // Field AFCKELYG.m:[I
    2057: aload         19
    2059: iconst_0
    2060: iconst_0
    2061: iload_1
    2062: iload         4
    2064: bipush        16
    2066: ishr
    2067: iload_3
    2068: bipush        16
    2070: ishr
    2071: iload         7
    2073: bipush        8
    2075: ishr
    2076: iload         6
    2078: bipush        8
    2080: ishr
    2081: iload         20
    2083: iload         23
    2085: iload         26
    2087: iload         21
    2089: iload         24
    2091: iload         27
    2093: invokestatic  #74                 // Method a:([I[IIIIIIIIIIIIII)V
    2096: iload_3
    2097: iload         29
    2099: iadd
    2100: istore_3
    2101: iload         4
    2103: iload         31
    2105: iadd
    2106: istore        4
    2108: iload         6
    2110: iload         30
    2112: iadd
    2113: istore        6
    2115: iload         7
    2117: iload         32
    2119: iadd
    2120: istore        7
    2122: iload_1
    2123: getstatic     #83                 // Field AFCKELYG.n:I
    2126: iadd
    2127: istore_1
    2128: iload         20
    2130: iload         22
    2132: iadd
    2133: istore        20
    2135: iload         23
    2137: iload         25
    2139: iadd
    2140: istore        23
    2142: iload         26
    2144: iload         28
    2146: iadd
    2147: istore        26
    2149: iinc          2, -1
    2152: iload_2
    2153: ifge          2054
    2156: iload         36
    2158: ifeq          2256
    2161: getstatic     #62                 // Field AFCKELYG.m:[I
    2164: aload         19
    2166: iconst_0
    2167: iconst_0
    2168: iload_1
    2169: iload         5
    2171: bipush        16
    2173: ishr
    2174: iload_3
    2175: bipush        16
    2177: ishr
    2178: iload         8
    2180: bipush        8
    2182: ishr
    2183: iload         6
    2185: bipush        8
    2187: ishr
    2188: iload         20
    2190: iload         23
    2192: iload         26
    2194: iload         21
    2196: iload         24
    2198: iload         27
    2200: invokestatic  #74                 // Method a:([I[IIIIIIIIIIIIII)V
    2203: iload_3
    2204: iload         29
    2206: iadd
    2207: istore_3
    2208: iload         5
    2210: iload         33
    2212: iadd
    2213: istore        5
    2215: iload         6
    2217: iload         30
    2219: iadd
    2220: istore        6
    2222: iload         8
    2224: iload         34
    2226: iadd
    2227: istore        8
    2229: iload_1
    2230: getstatic     #83                 // Field AFCKELYG.n:I
    2233: iadd
    2234: istore_1
    2235: iload         20
    2237: iload         22
    2239: iadd
    2240: istore        20
    2242: iload         23
    2244: iload         25
    2246: iadd
    2247: istore        23
    2249: iload         26
    2251: iload         28
    2253: iadd
    2254: istore        26
    2256: iinc          0, -1
    2259: iload_0
    2260: ifge          2161
    2263: return
    2264: iload         4
    2266: bipush        16
    2268: ishl
    2269: dup
    2270: istore        4
    2272: istore        5
    2274: iload         7
    2276: bipush        16
    2278: ishl
    2279: dup
    2280: istore        7
    2282: istore        8
    2284: iload_1
    2285: ifge          2326
    2288: iload         5
    2290: iload         29
    2292: iload_1
    2293: imul
    2294: isub
    2295: istore        5
    2297: iload         4
    2299: iload         31
    2301: iload_1
    2302: imul
    2303: isub
    2304: istore        4
    2306: iload         8
    2308: iload         30
    2310: iload_1
    2311: imul
    2312: isub
    2313: istore        8
    2315: iload         7
    2317: iload         32
    2319: iload_1
    2320: imul
    2321: isub
    2322: istore        7
    2324: iconst_0
    2325: istore_1
    2326: iload_3
    2327: bipush        16
    2329: ishl
    2330: istore_3
    2331: iload         6
    2333: bipush        16
    2335: ishl
    2336: istore        6
    2338: iload_0
    2339: ifge          2360
    2342: iload_3
    2343: iload         33
    2345: iload_0
    2346: imul
    2347: isub
    2348: istore_3
    2349: iload         6
    2351: iload         34
    2353: iload_0
    2354: imul
    2355: isub
    2356: istore        6
    2358: iconst_0
    2359: istore_0
    2360: iload_1
    2361: getstatic     #87                 // Field G:I
    2364: isub
    2365: istore        35
    2367: iload         20
    2369: iload         22
    2371: iload         35
    2373: imul
    2374: iadd
    2375: istore        20
    2377: iload         23
    2379: iload         25
    2381: iload         35
    2383: imul
    2384: iadd
    2385: istore        23
    2387: iload         26
    2389: iload         28
    2391: iload         35
    2393: imul
    2394: iadd
    2395: istore        26
    2397: iload         29
    2399: iload         31
    2401: if_icmpge     2636
    2404: iload_2
    2405: iload_0
    2406: isub
    2407: istore_2
    2408: iload_0
    2409: iload_1
    2410: isub
    2411: istore_0
    2412: getstatic     #66                 // Field L:[I
    2415: iload_1
    2416: iaload
    2417: istore_1
    2418: iload         36
    2420: ifeq          2521
    2423: getstatic     #62                 // Field AFCKELYG.m:[I
    2426: aload         19
    2428: iconst_0
    2429: iconst_0
    2430: iload_1
    2431: iload         5
    2433: bipush        16
    2435: ishr
    2436: iload         4
    2438: bipush        16
    2440: ishr
    2441: iload         8
    2443: bipush        8
    2445: ishr
    2446: iload         7
    2448: bipush        8
    2450: ishr
    2451: iload         20
    2453: iload         23
    2455: iload         26
    2457: iload         21
    2459: iload         24
    2461: iload         27
    2463: invokestatic  #74                 // Method a:([I[IIIIIIIIIIIIII)V
    2466: iload         5
    2468: iload         29
    2470: iadd
    2471: istore        5
    2473: iload         4
    2475: iload         31
    2477: iadd
    2478: istore        4
    2480: iload         8
    2482: iload         30
    2484: iadd
    2485: istore        8
    2487: iload         7
    2489: iload         32
    2491: iadd
    2492: istore        7
    2494: iload_1
    2495: getstatic     #83                 // Field AFCKELYG.n:I
    2498: iadd
    2499: istore_1
    2500: iload         20
    2502: iload         22
    2504: iadd
    2505: istore        20
    2507: iload         23
    2509: iload         25
    2511: iadd
    2512: istore        23
    2514: iload         26
    2516: iload         28
    2518: iadd
    2519: istore        26
    2521: iinc          0, -1
    2524: iload_0
    2525: ifge          2423
    2528: iload         36
    2530: ifeq          2628
    2533: getstatic     #62                 // Field AFCKELYG.m:[I
    2536: aload         19
    2538: iconst_0
    2539: iconst_0
    2540: iload_1
    2541: iload_3
    2542: bipush        16
    2544: ishr
    2545: iload         4
    2547: bipush        16
    2549: ishr
    2550: iload         6
    2552: bipush        8
    2554: ishr
    2555: iload         7
    2557: bipush        8
    2559: ishr
    2560: iload         20
    2562: iload         23
    2564: iload         26
    2566: iload         21
    2568: iload         24
    2570: iload         27
    2572: invokestatic  #74                 // Method a:([I[IIIIIIIIIIIIII)V
    2575: iload_3
    2576: iload         33
    2578: iadd
    2579: istore_3
    2580: iload         4
    2582: iload         31
    2584: iadd
    2585: istore        4
    2587: iload         6
    2589: iload         34
    2591: iadd
    2592: istore        6
    2594: iload         7
    2596: iload         32
    2598: iadd
    2599: istore        7
    2601: iload_1
    2602: getstatic     #83                 // Field AFCKELYG.n:I
    2605: iadd
    2606: istore_1
    2607: iload         20
    2609: iload         22
    2611: iadd
    2612: istore        20
    2614: iload         23
    2616: iload         25
    2618: iadd
    2619: istore        23
    2621: iload         26
    2623: iload         28
    2625: iadd
    2626: istore        26
    2628: iinc          2, -1
    2631: iload_2
    2632: ifge          2533
    2635: return
    2636: iload_2
    2637: iload_0
    2638: isub
    2639: istore_2
    2640: iload_0
    2641: iload_1
    2642: isub
    2643: istore_0
    2644: getstatic     #66                 // Field L:[I
    2647: iload_1
    2648: iaload
    2649: istore_1
    2650: iload         36
    2652: ifeq          2753
    2655: getstatic     #62                 // Field AFCKELYG.m:[I
    2658: aload         19
    2660: iconst_0
    2661: iconst_0
    2662: iload_1
    2663: iload         4
    2665: bipush        16
    2667: ishr
    2668: iload         5
    2670: bipush        16
    2672: ishr
    2673: iload         7
    2675: bipush        8
    2677: ishr
    2678: iload         8
    2680: bipush        8
    2682: ishr
    2683: iload         20
    2685: iload         23
    2687: iload         26
    2689: iload         21
    2691: iload         24
    2693: iload         27
    2695: invokestatic  #74                 // Method a:([I[IIIIIIIIIIIIII)V
    2698: iload         5
    2700: iload         29
    2702: iadd
    2703: istore        5
    2705: iload         4
    2707: iload         31
    2709: iadd
    2710: istore        4
    2712: iload         8
    2714: iload         30
    2716: iadd
    2717: istore        8
    2719: iload         7
    2721: iload         32
    2723: iadd
    2724: istore        7
    2726: iload_1
    2727: getstatic     #83                 // Field AFCKELYG.n:I
    2730: iadd
    2731: istore_1
    2732: iload         20
    2734: iload         22
    2736: iadd
    2737: istore        20
    2739: iload         23
    2741: iload         25
    2743: iadd
    2744: istore        23
    2746: iload         26
    2748: iload         28
    2750: iadd
    2751: istore        26
    2753: iinc          0, -1
    2756: iload_0
    2757: ifge          2655
    2760: iload         36
    2762: ifeq          2860
    2765: getstatic     #62                 // Field AFCKELYG.m:[I
    2768: aload         19
    2770: iconst_0
    2771: iconst_0
    2772: iload_1
    2773: iload         4
    2775: bipush        16
    2777: ishr
    2778: iload_3
    2779: bipush        16
    2781: ishr
    2782: iload         7
    2784: bipush        8
    2786: ishr
    2787: iload         6
    2789: bipush        8
    2791: ishr
    2792: iload         20
    2794: iload         23
    2796: iload         26
    2798: iload         21
    2800: iload         24
    2802: iload         27
    2804: invokestatic  #74                 // Method a:([I[IIIIIIIIIIIIII)V
    2807: iload_3
    2808: iload         33
    2810: iadd
    2811: istore_3
    2812: iload         4
    2814: iload         31
    2816: iadd
    2817: istore        4
    2819: iload         6
    2821: iload         34
    2823: iadd
    2824: istore        6
    2826: iload         7
    2828: iload         32
    2830: iadd
    2831: istore        7
    2833: iload_1
    2834: getstatic     #83                 // Field AFCKELYG.n:I
    2837: iadd
    2838: istore_1
    2839: iload         20
    2841: iload         22
    2843: iadd
    2844: istore        20
    2846: iload         23
    2848: iload         25
    2850: iadd
    2851: istore        23
    2853: iload         26
    2855: iload         28
    2857: iadd
    2858: istore        26
    2860: iinc          2, -1
    2863: iload_2
    2864: ifge          2765
    2867: return
    2868: iload_2
    2869: getstatic     #86                 // Field AFCKELYG.q:I
    2872: if_icmplt     2876
    2875: return
    2876: iload_0
    2877: getstatic     #86                 // Field AFCKELYG.q:I
    2880: if_icmple     2887
    2883: getstatic     #86                 // Field AFCKELYG.q:I
    2886: istore_0
    2887: iload_1
    2888: getstatic     #86                 // Field AFCKELYG.q:I
    2891: if_icmple     2898
    2894: getstatic     #86                 // Field AFCKELYG.q:I
    2897: istore_1
    2898: iload_0
    2899: iload_1
    2900: if_icmpge     3507
    2903: iload         5
    2905: bipush        16
    2907: ishl
    2908: dup
    2909: istore        5
    2911: istore        4
    2913: iload         8
    2915: bipush        16
    2917: ishl
    2918: dup
    2919: istore        8
    2921: istore        7
    2923: iload_2
    2924: ifge          2965
    2927: iload         4
    2929: iload         31
    2931: iload_2
    2932: imul
    2933: isub
    2934: istore        4
    2936: iload         5
    2938: iload         33
    2940: iload_2
    2941: imul
    2942: isub
    2943: istore        5
    2945: iload         7
    2947: iload         32
    2949: iload_2
    2950: imul
    2951: isub
    2952: istore        7
    2954: iload         8
    2956: iload         34
    2958: iload_2
    2959: imul
    2960: isub
    2961: istore        8
    2963: iconst_0
    2964: istore_2
    2965: iload_3
    2966: bipush        16
    2968: ishl
    2969: istore_3
    2970: iload         6
    2972: bipush        16
    2974: ishl
    2975: istore        6
    2977: iload_0
    2978: ifge          2999
    2981: iload_3
    2982: iload         29
    2984: iload_0
    2985: imul
    2986: isub
    2987: istore_3
    2988: iload         6
    2990: iload         30
    2992: iload_0
    2993: imul
    2994: isub
    2995: istore        6
    2997: iconst_0
    2998: istore_0
    2999: iload_2
    3000: getstatic     #87                 // Field G:I
    3003: isub
    3004: istore        35
    3006: iload         20
    3008: iload         22
    3010: iload         35
    3012: imul
    3013: iadd
    3014: istore        20
    3016: iload         23
    3018: iload         25
    3020: iload         35
    3022: imul
    3023: iadd
    3024: istore        23
    3026: iload         26
    3028: iload         28
    3030: iload         35
    3032: imul
    3033: iadd
    3034: istore        26
    3036: iload         31
    3038: iload         33
    3040: if_icmpge     3275
    3043: iload_1
    3044: iload_0
    3045: isub
    3046: istore_1
    3047: iload_0
    3048: iload_2
    3049: isub
    3050: istore_0
    3051: getstatic     #66                 // Field L:[I
    3054: iload_2
    3055: iaload
    3056: istore_2
    3057: iload         36
    3059: ifeq          3160
    3062: getstatic     #62                 // Field AFCKELYG.m:[I
    3065: aload         19
    3067: iconst_0
    3068: iconst_0
    3069: iload_2
    3070: iload         4
    3072: bipush        16
    3074: ishr
    3075: iload         5
    3077: bipush        16
    3079: ishr
    3080: iload         7
    3082: bipush        8
    3084: ishr
    3085: iload         8
    3087: bipush        8
    3089: ishr
    3090: iload         20
    3092: iload         23
    3094: iload         26
    3096: iload         21
    3098: iload         24
    3100: iload         27
    3102: invokestatic  #74                 // Method a:([I[IIIIIIIIIIIIII)V
    3105: iload         4
    3107: iload         31
    3109: iadd
    3110: istore        4
    3112: iload         5
    3114: iload         33
    3116: iadd
    3117: istore        5
    3119: iload         7
    3121: iload         32
    3123: iadd
    3124: istore        7
    3126: iload         8
    3128: iload         34
    3130: iadd
    3131: istore        8
    3133: iload_2
    3134: getstatic     #83                 // Field AFCKELYG.n:I
    3137: iadd
    3138: istore_2
    3139: iload         20
    3141: iload         22
    3143: iadd
    3144: istore        20
    3146: iload         23
    3148: iload         25
    3150: iadd
    3151: istore        23
    3153: iload         26
    3155: iload         28
    3157: iadd
    3158: istore        26
    3160: iinc          0, -1
    3163: iload_0
    3164: ifge          3062
    3167: iload         36
    3169: ifeq          3267
    3172: getstatic     #62                 // Field AFCKELYG.m:[I
    3175: aload         19
    3177: iconst_0
    3178: iconst_0
    3179: iload_2
    3180: iload         4
    3182: bipush        16
    3184: ishr
    3185: iload_3
    3186: bipush        16
    3188: ishr
    3189: iload         7
    3191: bipush        8
    3193: ishr
    3194: iload         6
    3196: bipush        8
    3198: ishr
    3199: iload         20
    3201: iload         23
    3203: iload         26
    3205: iload         21
    3207: iload         24
    3209: iload         27
    3211: invokestatic  #74                 // Method a:([I[IIIIIIIIIIIIII)V
    3214: iload         4
    3216: iload         31
    3218: iadd
    3219: istore        4
    3221: iload_3
    3222: iload         29
    3224: iadd
    3225: istore_3
    3226: iload         7
    3228: iload         32
    3230: iadd
    3231: istore        7
    3233: iload         6
    3235: iload         30
    3237: iadd
    3238: istore        6
    3240: iload_2
    3241: getstatic     #83                 // Field AFCKELYG.n:I
    3244: iadd
    3245: istore_2
    3246: iload         20
    3248: iload         22
    3250: iadd
    3251: istore        20
    3253: iload         23
    3255: iload         25
    3257: iadd
    3258: istore        23
    3260: iload         26
    3262: iload         28
    3264: iadd
    3265: istore        26
    3267: iinc          1, -1
    3270: iload_1
    3271: ifge          3172
    3274: return
    3275: iload_1
    3276: iload_0
    3277: isub
    3278: istore_1
    3279: iload_0
    3280: iload_2
    3281: isub
    3282: istore_0
    3283: getstatic     #66                 // Field L:[I
    3286: iload_2
    3287: iaload
    3288: istore_2
    3289: iload         36
    3291: ifeq          3392
    3294: getstatic     #62                 // Field AFCKELYG.m:[I
    3297: aload         19
    3299: iconst_0
    3300: iconst_0
    3301: iload_2
    3302: iload         5
    3304: bipush        16
    3306: ishr
    3307: iload         4
    3309: bipush        16
    3311: ishr
    3312: iload         8
    3314: bipush        8
    3316: ishr
    3317: iload         7
    3319: bipush        8
    3321: ishr
    3322: iload         20
    3324: iload         23
    3326: iload         26
    3328: iload         21
    3330: iload         24
    3332: iload         27
    3334: invokestatic  #74                 // Method a:([I[IIIIIIIIIIIIII)V
    3337: iload         4
    3339: iload         31
    3341: iadd
    3342: istore        4
    3344: iload         5
    3346: iload         33
    3348: iadd
    3349: istore        5
    3351: iload         7
    3353: iload         32
    3355: iadd
    3356: istore        7
    3358: iload         8
    3360: iload         34
    3362: iadd
    3363: istore        8
    3365: iload_2
    3366: getstatic     #83                 // Field AFCKELYG.n:I
    3369: iadd
    3370: istore_2
    3371: iload         20
    3373: iload         22
    3375: iadd
    3376: istore        20
    3378: iload         23
    3380: iload         25
    3382: iadd
    3383: istore        23
    3385: iload         26
    3387: iload         28
    3389: iadd
    3390: istore        26
    3392: iinc          0, -1
    3395: iload_0
    3396: ifge          3294
    3399: iload         36
    3401: ifeq          3499
    3404: getstatic     #62                 // Field AFCKELYG.m:[I
    3407: aload         19
    3409: iconst_0
    3410: iconst_0
    3411: iload_2
    3412: iload_3
    3413: bipush        16
    3415: ishr
    3416: iload         4
    3418: bipush        16
    3420: ishr
    3421: iload         6
    3423: bipush        8
    3425: ishr
    3426: iload         7
    3428: bipush        8
    3430: ishr
    3431: iload         20
    3433: iload         23
    3435: iload         26
    3437: iload         21
    3439: iload         24
    3441: iload         27
    3443: invokestatic  #74                 // Method a:([I[IIIIIIIIIIIIII)V
    3446: iload         4
    3448: iload         31
    3450: iadd
    3451: istore        4
    3453: iload_3
    3454: iload         29
    3456: iadd
    3457: istore_3
    3458: iload         7
    3460: iload         32
    3462: iadd
    3463: istore        7
    3465: iload         6
    3467: iload         30
    3469: iadd
    3470: istore        6
    3472: iload_2
    3473: getstatic     #83                 // Field AFCKELYG.n:I
    3476: iadd
    3477: istore_2
    3478: iload         20
    3480: iload         22
    3482: iadd
    3483: istore        20
    3485: iload         23
    3487: iload         25
    3489: iadd
    3490: istore        23
    3492: iload         26
    3494: iload         28
    3496: iadd
    3497: istore        26
    3499: iinc          1, -1
    3502: iload_1
    3503: ifge          3404
    3506: return
    3507: iload         5
    3509: bipush        16
    3511: ishl
    3512: dup
    3513: istore        5
    3515: istore_3
    3516: iload         8
    3518: bipush        16
    3520: ishl
    3521: dup
    3522: istore        8
    3524: istore        6
    3526: iload_2
    3527: ifge          3566
    3530: iload_3
    3531: iload         31
    3533: iload_2
    3534: imul
    3535: isub
    3536: istore_3
    3537: iload         5
    3539: iload         33
    3541: iload_2
    3542: imul
    3543: isub
    3544: istore        5
    3546: iload         6
    3548: iload         32
    3550: iload_2
    3551: imul
    3552: isub
    3553: istore        6
    3555: iload         8
    3557: iload         34
    3559: iload_2
    3560: imul
    3561: isub
    3562: istore        8
    3564: iconst_0
    3565: istore_2
    3566: iload         4
    3568: bipush        16
    3570: ishl
    3571: istore        4
    3573: iload         7
    3575: bipush        16
    3577: ishl
    3578: istore        7
    3580: iload_1
    3581: ifge          3604
    3584: iload         4
    3586: iload         29
    3588: iload_1
    3589: imul
    3590: isub
    3591: istore        4
    3593: iload         7
    3595: iload         30
    3597: iload_1
    3598: imul
    3599: isub
    3600: istore        7
    3602: iconst_0
    3603: istore_1
    3604: iload_2
    3605: getstatic     #87                 // Field G:I
    3608: isub
    3609: istore        35
    3611: iload         20
    3613: iload         22
    3615: iload         35
    3617: imul
    3618: iadd
    3619: istore        20
    3621: iload         23
    3623: iload         25
    3625: iload         35
    3627: imul
    3628: iadd
    3629: istore        23
    3631: iload         26
    3633: iload         28
    3635: iload         35
    3637: imul
    3638: iadd
    3639: istore        26
    3641: iload         31
    3643: iload         33
    3645: if_icmpge     3880
    3648: iload_0
    3649: iload_1
    3650: isub
    3651: istore_0
    3652: iload_1
    3653: iload_2
    3654: isub
    3655: istore_1
    3656: getstatic     #66                 // Field L:[I
    3659: iload_2
    3660: iaload
    3661: istore_2
    3662: iload         36
    3664: ifeq          3762
    3667: getstatic     #62                 // Field AFCKELYG.m:[I
    3670: aload         19
    3672: iconst_0
    3673: iconst_0
    3674: iload_2
    3675: iload_3
    3676: bipush        16
    3678: ishr
    3679: iload         5
    3681: bipush        16
    3683: ishr
    3684: iload         6
    3686: bipush        8
    3688: ishr
    3689: iload         8
    3691: bipush        8
    3693: ishr
    3694: iload         20
    3696: iload         23
    3698: iload         26
    3700: iload         21
    3702: iload         24
    3704: iload         27
    3706: invokestatic  #74                 // Method a:([I[IIIIIIIIIIIIII)V
    3709: iload_3
    3710: iload         31
    3712: iadd
    3713: istore_3
    3714: iload         5
    3716: iload         33
    3718: iadd
    3719: istore        5
    3721: iload         6
    3723: iload         32
    3725: iadd
    3726: istore        6
    3728: iload         8
    3730: iload         34
    3732: iadd
    3733: istore        8
    3735: iload_2
    3736: getstatic     #83                 // Field AFCKELYG.n:I
    3739: iadd
    3740: istore_2
    3741: iload         20
    3743: iload         22
    3745: iadd
    3746: istore        20
    3748: iload         23
    3750: iload         25
    3752: iadd
    3753: istore        23
    3755: iload         26
    3757: iload         28
    3759: iadd
    3760: istore        26
    3762: iinc          1, -1
    3765: iload_1
    3766: ifge          3667
    3769: iload         36
    3771: ifeq          3872
    3774: getstatic     #62                 // Field AFCKELYG.m:[I
    3777: aload         19
    3779: iconst_0
    3780: iconst_0
    3781: iload_2
    3782: iload         4
    3784: bipush        16
    3786: ishr
    3787: iload         5
    3789: bipush        16
    3791: ishr
    3792: iload         7
    3794: bipush        8
    3796: ishr
    3797: iload         8
    3799: bipush        8
    3801: ishr
    3802: iload         20
    3804: iload         23
    3806: iload         26
    3808: iload         21
    3810: iload         24
    3812: iload         27
    3814: invokestatic  #74                 // Method a:([I[IIIIIIIIIIIIII)V
    3817: iload         4
    3819: iload         29
    3821: iadd
    3822: istore        4
    3824: iload         5
    3826: iload         33
    3828: iadd
    3829: istore        5
    3831: iload         7
    3833: iload         30
    3835: iadd
    3836: istore        7
    3838: iload         8
    3840: iload         34
    3842: iadd
    3843: istore        8
    3845: iload_2
    3846: getstatic     #83                 // Field AFCKELYG.n:I
    3849: iadd
    3850: istore_2
    3851: iload         20
    3853: iload         22
    3855: iadd
    3856: istore        20
    3858: iload         23
    3860: iload         25
    3862: iadd
    3863: istore        23
    3865: iload         26
    3867: iload         28
    3869: iadd
    3870: istore        26
    3872: iinc          0, -1
    3875: iload_0
    3876: ifge          3774
    3879: return
    3880: iload_0
    3881: iload_1
    3882: isub
    3883: istore_0
    3884: iload_1
    3885: iload_2
    3886: isub
    3887: istore_1
    3888: getstatic     #66                 // Field L:[I
    3891: iload_2
    3892: iaload
    3893: istore_2
    3894: iload         36
    3896: ifeq          3994
    3899: getstatic     #62                 // Field AFCKELYG.m:[I
    3902: aload         19
    3904: iconst_0
    3905: iconst_0
    3906: iload_2
    3907: iload         5
    3909: bipush        16
    3911: ishr
    3912: iload_3
    3913: bipush        16
    3915: ishr
    3916: iload         8
    3918: bipush        8
    3920: ishr
    3921: iload         6
    3923: bipush        8
    3925: ishr
    3926: iload         20
    3928: iload         23
    3930: iload         26
    3932: iload         21
    3934: iload         24
    3936: iload         27
    3938: invokestatic  #74                 // Method a:([I[IIIIIIIIIIIIII)V
    3941: iload_3
    3942: iload         31
    3944: iadd
    3945: istore_3
    3946: iload         5
    3948: iload         33
    3950: iadd
    3951: istore        5
    3953: iload         6
    3955: iload         32
    3957: iadd
    3958: istore        6
    3960: iload         8
    3962: iload         34
    3964: iadd
    3965: istore        8
    3967: iload_2
    3968: getstatic     #83                 // Field AFCKELYG.n:I
    3971: iadd
    3972: istore_2
    3973: iload         20
    3975: iload         22
    3977: iadd
    3978: istore        20
    3980: iload         23
    3982: iload         25
    3984: iadd
    3985: istore        23
    3987: iload         26
    3989: iload         28
    3991: iadd
    3992: istore        26
    3994: iinc          1, -1
    3997: iload_1
    3998: ifge          3899
    4001: iload         36
    4003: ifeq          4104
    4006: getstatic     #62                 // Field AFCKELYG.m:[I
    4009: aload         19
    4011: iconst_0
    4012: iconst_0
    4013: iload_2
    4014: iload         5
    4016: bipush        16
    4018: ishr
    4019: iload         4
    4021: bipush        16
    4023: ishr
    4024: iload         8
    4026: bipush        8
    4028: ishr
    4029: iload         7
    4031: bipush        8
    4033: ishr
    4034: iload         20
    4036: iload         23
    4038: iload         26
    4040: iload         21
    4042: iload         24
    4044: iload         27
    4046: invokestatic  #74                 // Method a:([I[IIIIIIIIIIIIII)V
    4049: iload         4
    4051: iload         29
    4053: iadd
    4054: istore        4
    4056: iload         5
    4058: iload         33
    4060: iadd
    4061: istore        5
    4063: iload         7
    4065: iload         30
    4067: iadd
    4068: istore        7
    4070: iload         8
    4072: iload         34
    4074: iadd
    4075: istore        8
    4077: iload_2
    4078: getstatic     #83                 // Field AFCKELYG.n:I
    4081: iadd
    4082: istore_2
    4083: iload         20
    4085: iload         22
    4087: iadd
    4088: istore        20
    4090: iload         23
    4092: iload         25
    4094: iadd
    4095: istore        23
    4097: iload         26
    4099: iload         28
    4101: iadd
    4102: istore        26
    4104: iinc          0, -1
    4107: iload_0
    4108: ifge          4006
    4111: return

  public static final void a(int[], int[], int, int, int, int, int, int, int, int, int, int, int, int, int);
    Code:
       0: getstatic     #289                // Field XHHRODPC.l:Z
       3: istore        25
       5: iload         5
       7: iload         6
       9: if_icmplt     13
      12: return
      13: getstatic     #53                 // Field B:Z
      16: ifeq          99
      19: iload         8
      21: iload         7
      23: isub
      24: iload         6
      26: iload         5
      28: isub
      29: idiv
      30: istore        15
      32: iload         6
      34: getstatic     #84                 // Field AFCKELYG.t:I
      37: if_icmple     45
      40: getstatic     #84                 // Field AFCKELYG.t:I
      43: istore        6
      45: iload         5
      47: ifge          63
      50: iload         7
      52: iload         5
      54: iload         15
      56: imul
      57: isub
      58: istore        7
      60: iconst_0
      61: istore        5
      63: iload         5
      65: iload         6
      67: if_icmplt     71
      70: return
      71: iload         6
      73: iload         5
      75: isub
      76: iconst_3
      77: ishr
      78: istore        16
      80: iload         15
      82: bipush        12
      84: ishl
      85: istore        15
      87: iload         7
      89: bipush        9
      91: ishl
      92: istore        7
      94: iload         25
      96: ifeq          153
      99: iload         6
     101: iload         5
     103: isub
     104: bipush        7
     106: if_icmple     140
     109: iload         6
     111: iload         5
     113: isub
     114: iconst_3
     115: ishr
     116: istore        16
     118: iload         8
     120: iload         7
     122: isub
     123: getstatic     #44                 // Field H:[I
     126: iload         16
     128: iaload
     129: imul
     130: bipush        6
     132: ishr
     133: istore        15
     135: iload         25
     137: ifeq          146
     140: iconst_0
     141: istore        16
     143: iconst_0
     144: istore        15
     146: iload         7
     148: bipush        9
     150: ishl
     151: istore        7
     153: iload         4
     155: iload         5
     157: iadd
     158: istore        4
     160: getstatic     #57                 // Field A:Z
     163: ifeq          1318
     166: iconst_0
     167: istore        17
     169: iconst_0
     170: istore        18
     172: iload         5
     174: getstatic     #85                 // Field F:I
     177: isub
     178: istore        20
     180: iload         9
     182: iload         12
     184: iconst_3
     185: ishr
     186: iload         20
     188: imul
     189: iadd
     190: istore        9
     192: iload         10
     194: iload         13
     196: iconst_3
     197: ishr
     198: iload         20
     200: imul
     201: iadd
     202: istore        10
     204: iload         11
     206: iload         14
     208: iconst_3
     209: ishr
     210: iload         20
     212: imul
     213: iadd
     214: istore        11
     216: iload         11
     218: bipush        12
     220: ishr
     221: istore        19
     223: iload         19
     225: ifeq          262
     228: iload         9
     230: iload         19
     232: idiv
     233: istore_2
     234: iload         10
     236: iload         19
     238: idiv
     239: istore_3
     240: iload_2
     241: ifge          251
     244: iconst_0
     245: istore_2
     246: iload         25
     248: ifeq          262
     251: iload_2
     252: sipush        4032
     255: if_icmple     262
     258: sipush        4032
     261: istore_2
     262: iload         9
     264: iload         12
     266: iadd
     267: istore        9
     269: iload         10
     271: iload         13
     273: iadd
     274: istore        10
     276: iload         11
     278: iload         14
     280: iadd
     281: istore        11
     283: iload         11
     285: bipush        12
     287: ishr
     288: istore        19
     290: iload         19
     292: ifeq          338
     295: iload         9
     297: iload         19
     299: idiv
     300: istore        17
     302: iload         10
     304: iload         19
     306: idiv
     307: istore        18
     309: iload         17
     311: bipush        7
     313: if_icmpge     325
     316: bipush        7
     318: istore        17
     320: iload         25
     322: ifeq          338
     325: iload         17
     327: sipush        4032
     330: if_icmple     338
     333: sipush        4032
     336: istore        17
     338: iload         17
     340: iload_2
     341: isub
     342: iconst_3
     343: ishr
     344: istore        21
     346: iload         18
     348: iload_3
     349: isub
     350: iconst_3
     351: ishr
     352: istore        22
     354: iload_2
     355: iload         7
     357: ldc           #5                  // int 6291456
     359: iand
     360: iconst_3
     361: ishr
     362: iadd
     363: istore_2
     364: iload         7
     366: bipush        23
     368: ishr
     369: istore        23
     371: getstatic     #69                 // Field C:Z
     374: ifeq          1246
     377: iload         25
     379: ifeq          750
     382: aload_0
     383: iload         4
     385: iinc          4, 1
     388: aload_1
     389: iload_3
     390: sipush        4032
     393: iand
     394: iload_2
     395: bipush        6
     397: ishr
     398: iadd
     399: iaload
     400: iload         23
     402: iushr
     403: iastore
     404: iload_2
     405: iload         21
     407: iadd
     408: istore_2
     409: iload_3
     410: iload         22
     412: iadd
     413: istore_3
     414: aload_0
     415: iload         4
     417: iinc          4, 1
     420: aload_1
     421: iload_3
     422: sipush        4032
     425: iand
     426: iload_2
     427: bipush        6
     429: ishr
     430: iadd
     431: iaload
     432: iload         23
     434: iushr
     435: iastore
     436: iload_2
     437: iload         21
     439: iadd
     440: istore_2
     441: iload_3
     442: iload         22
     444: iadd
     445: istore_3
     446: aload_0
     447: iload         4
     449: iinc          4, 1
     452: aload_1
     453: iload_3
     454: sipush        4032
     457: iand
     458: iload_2
     459: bipush        6
     461: ishr
     462: iadd
     463: iaload
     464: iload         23
     466: iushr
     467: iastore
     468: iload_2
     469: iload         21
     471: iadd
     472: istore_2
     473: iload_3
     474: iload         22
     476: iadd
     477: istore_3
     478: aload_0
     479: iload         4
     481: iinc          4, 1
     484: aload_1
     485: iload_3
     486: sipush        4032
     489: iand
     490: iload_2
     491: bipush        6
     493: ishr
     494: iadd
     495: iaload
     496: iload         23
     498: iushr
     499: iastore
     500: iload_2
     501: iload         21
     503: iadd
     504: istore_2
     505: iload_3
     506: iload         22
     508: iadd
     509: istore_3
     510: aload_0
     511: iload         4
     513: iinc          4, 1
     516: aload_1
     517: iload_3
     518: sipush        4032
     521: iand
     522: iload_2
     523: bipush        6
     525: ishr
     526: iadd
     527: iaload
     528: iload         23
     530: iushr
     531: iastore
     532: iload_2
     533: iload         21
     535: iadd
     536: istore_2
     537: iload_3
     538: iload         22
     540: iadd
     541: istore_3
     542: aload_0
     543: iload         4
     545: iinc          4, 1
     548: aload_1
     549: iload_3
     550: sipush        4032
     553: iand
     554: iload_2
     555: bipush        6
     557: ishr
     558: iadd
     559: iaload
     560: iload         23
     562: iushr
     563: iastore
     564: iload_2
     565: iload         21
     567: iadd
     568: istore_2
     569: iload_3
     570: iload         22
     572: iadd
     573: istore_3
     574: aload_0
     575: iload         4
     577: iinc          4, 1
     580: aload_1
     581: iload_3
     582: sipush        4032
     585: iand
     586: iload_2
     587: bipush        6
     589: ishr
     590: iadd
     591: iaload
     592: iload         23
     594: iushr
     595: iastore
     596: iload_2
     597: iload         21
     599: iadd
     600: istore_2
     601: iload_3
     602: iload         22
     604: iadd
     605: istore_3
     606: aload_0
     607: iload         4
     609: iinc          4, 1
     612: aload_1
     613: iload_3
     614: sipush        4032
     617: iand
     618: iload_2
     619: bipush        6
     621: ishr
     622: iadd
     623: iaload
     624: iload         23
     626: iushr
     627: iastore
     628: iload         17
     630: istore_2
     631: iload         18
     633: istore_3
     634: iload         9
     636: iload         12
     638: iadd
     639: istore        9
     641: iload         10
     643: iload         13
     645: iadd
     646: istore        10
     648: iload         11
     650: iload         14
     652: iadd
     653: istore        11
     655: iload         11
     657: bipush        12
     659: ishr
     660: istore        19
     662: iload         19
     664: ifeq          710
     667: iload         9
     669: iload         19
     671: idiv
     672: istore        17
     674: iload         10
     676: iload         19
     678: idiv
     679: istore        18
     681: iload         17
     683: bipush        7
     685: if_icmpge     697
     688: bipush        7
     690: istore        17
     692: iload         25
     694: ifeq          710
     697: iload         17
     699: sipush        4032
     702: if_icmple     710
     705: sipush        4032
     708: istore        17
     710: iload         17
     712: iload_2
     713: isub
     714: iconst_3
     715: ishr
     716: istore        21
     718: iload         18
     720: iload_3
     721: isub
     722: iconst_3
     723: ishr
     724: istore        22
     726: iload         7
     728: iload         15
     730: iadd
     731: istore        7
     733: iload_2
     734: iload         7
     736: ldc           #5                  // int 6291456
     738: iand
     739: iconst_3
     740: ishr
     741: iadd
     742: istore_2
     743: iload         7
     745: bipush        23
     747: ishr
     748: istore        23
     750: iload         16
     752: iinc          16, -1
     755: ifgt          382
     758: iload         6
     760: iload         5
     762: isub
     763: bipush        7
     765: iand
     766: istore        16
     768: iload         25
     770: ifeq          805
     773: aload_0
     774: iload         4
     776: iinc          4, 1
     779: aload_1
     780: iload_3
     781: sipush        4032
     784: iand
     785: iload_2
     786: bipush        6
     788: ishr
     789: iadd
     790: iaload
     791: iload         23
     793: iushr
     794: iastore
     795: iload_2
     796: iload         21
     798: iadd
     799: istore_2
     800: iload_3
     801: iload         22
     803: iadd
     804: istore_3
     805: iload         16
     807: iinc          16, -1
     810: ifgt          773
     813: return
     814: aload_1
     815: iload_3
     816: sipush        4032
     819: iand
     820: iload_2
     821: bipush        6
     823: ishr
     824: iadd
     825: iaload
     826: iload         23
     828: iushr
     829: dup
     830: istore        24
     832: ifeq          841
     835: aload_0
     836: iload         4
     838: iload         24
     840: iastore
     841: iinc          4, 1
     844: iload_2
     845: iload         21
     847: iadd
     848: istore_2
     849: iload_3
     850: iload         22
     852: iadd
     853: istore_3
     854: aload_1
     855: iload_3
     856: sipush        4032
     859: iand
     860: iload_2
     861: bipush        6
     863: ishr
     864: iadd
     865: iaload
     866: iload         23
     868: iushr
     869: dup
     870: istore        24
     872: ifeq          881
     875: aload_0
     876: iload         4
     878: iload         24
     880: iastore
     881: iinc          4, 1
     884: iload_2
     885: iload         21
     887: iadd
     888: istore_2
     889: iload_3
     890: iload         22
     892: iadd
     893: istore_3
     894: aload_1
     895: iload_3
     896: sipush        4032
     899: iand
     900: iload_2
     901: bipush        6
     903: ishr
     904: iadd
     905: iaload
     906: iload         23
     908: iushr
     909: dup
     910: istore        24
     912: ifeq          921
     915: aload_0
     916: iload         4
     918: iload         24
     920: iastore
     921: iinc          4, 1
     924: iload_2
     925: iload         21
     927: iadd
     928: istore_2
     929: iload_3
     930: iload         22
     932: iadd
     933: istore_3
     934: aload_1
     935: iload_3
     936: sipush        4032
     939: iand
     940: iload_2
     941: bipush        6
     943: ishr
     944: iadd
     945: iaload
     946: iload         23
     948: iushr
     949: dup
     950: istore        24
     952: ifeq          961
     955: aload_0
     956: iload         4
     958: iload         24
     960: iastore
     961: iinc          4, 1
     964: iload_2
     965: iload         21
     967: iadd
     968: istore_2
     969: iload_3
     970: iload         22
     972: iadd
     973: istore_3
     974: aload_1
     975: iload_3
     976: sipush        4032
     979: iand
     980: iload_2
     981: bipush        6
     983: ishr
     984: iadd
     985: iaload
     986: iload         23
     988: iushr
     989: dup
     990: istore        24
     992: ifeq          1001
     995: aload_0
     996: iload         4
     998: iload         24
    1000: iastore
    1001: iinc          4, 1
    1004: iload_2
    1005: iload         21
    1007: iadd
    1008: istore_2
    1009: iload_3
    1010: iload         22
    1012: iadd
    1013: istore_3
    1014: aload_1
    1015: iload_3
    1016: sipush        4032
    1019: iand
    1020: iload_2
    1021: bipush        6
    1023: ishr
    1024: iadd
    1025: iaload
    1026: iload         23
    1028: iushr
    1029: dup
    1030: istore        24
    1032: ifeq          1041
    1035: aload_0
    1036: iload         4
    1038: iload         24
    1040: iastore
    1041: iinc          4, 1
    1044: iload_2
    1045: iload         21
    1047: iadd
    1048: istore_2
    1049: iload_3
    1050: iload         22
    1052: iadd
    1053: istore_3
    1054: aload_1
    1055: iload_3
    1056: sipush        4032
    1059: iand
    1060: iload_2
    1061: bipush        6
    1063: ishr
    1064: iadd
    1065: iaload
    1066: iload         23
    1068: iushr
    1069: dup
    1070: istore        24
    1072: ifeq          1081
    1075: aload_0
    1076: iload         4
    1078: iload         24
    1080: iastore
    1081: iinc          4, 1
    1084: iload_2
    1085: iload         21
    1087: iadd
    1088: istore_2
    1089: iload_3
    1090: iload         22
    1092: iadd
    1093: istore_3
    1094: aload_1
    1095: iload_3
    1096: sipush        4032
    1099: iand
    1100: iload_2
    1101: bipush        6
    1103: ishr
    1104: iadd
    1105: iaload
    1106: iload         23
    1108: iushr
    1109: dup
    1110: istore        24
    1112: ifeq          1121
    1115: aload_0
    1116: iload         4
    1118: iload         24
    1120: iastore
    1121: iinc          4, 1
    1124: iload         17
    1126: istore_2
    1127: iload         18
    1129: istore_3
    1130: iload         9
    1132: iload         12
    1134: iadd
    1135: istore        9
    1137: iload         10
    1139: iload         13
    1141: iadd
    1142: istore        10
    1144: iload         11
    1146: iload         14
    1148: iadd
    1149: istore        11
    1151: iload         11
    1153: bipush        12
    1155: ishr
    1156: istore        19
    1158: iload         19
    1160: ifeq          1206
    1163: iload         9
    1165: iload         19
    1167: idiv
    1168: istore        17
    1170: iload         10
    1172: iload         19
    1174: idiv
    1175: istore        18
    1177: iload         17
    1179: bipush        7
    1181: if_icmpge     1193
    1184: bipush        7
    1186: istore        17
    1188: iload         25
    1190: ifeq          1206
    1193: iload         17
    1195: sipush        4032
    1198: if_icmple     1206
    1201: sipush        4032
    1204: istore        17
    1206: iload         17
    1208: iload_2
    1209: isub
    1210: iconst_3
    1211: ishr
    1212: istore        21
    1214: iload         18
    1216: iload_3
    1217: isub
    1218: iconst_3
    1219: ishr
    1220: istore        22
    1222: iload         7
    1224: iload         15
    1226: iadd
    1227: istore        7
    1229: iload_2
    1230: iload         7
    1232: ldc           #5                  // int 6291456
    1234: iand
    1235: iconst_3
    1236: ishr
    1237: iadd
    1238: istore_2
    1239: iload         7
    1241: bipush        23
    1243: ishr
    1244: istore        23
    1246: iload         16
    1248: iinc          16, -1
    1251: ifgt          814
    1254: iload         6
    1256: iload         5
    1258: isub
    1259: bipush        7
    1261: iand
    1262: istore        16
    1264: iload         25
    1266: ifeq          1309
    1269: aload_1
    1270: iload_3
    1271: sipush        4032
    1274: iand
    1275: iload_2
    1276: bipush        6
    1278: ishr
    1279: iadd
    1280: iaload
    1281: iload         23
    1283: iushr
    1284: dup
    1285: istore        24
    1287: ifeq          1296
    1290: aload_0
    1291: iload         4
    1293: iload         24
    1295: iastore
    1296: iinc          4, 1
    1299: iload_2
    1300: iload         21
    1302: iadd
    1303: istore_2
    1304: iload_3
    1305: iload         22
    1307: iadd
    1308: istore_3
    1309: iload         16
    1311: iinc          16, -1
    1314: ifgt          1269
    1317: return
    1318: iconst_0
    1319: istore        17
    1321: iconst_0
    1322: istore        18
    1324: iload         5
    1326: getstatic     #85                 // Field F:I
    1329: isub
    1330: istore        20
    1332: iload         9
    1334: iload         12
    1336: iconst_3
    1337: ishr
    1338: iload         20
    1340: imul
    1341: iadd
    1342: istore        9
    1344: iload         10
    1346: iload         13
    1348: iconst_3
    1349: ishr
    1350: iload         20
    1352: imul
    1353: iadd
    1354: istore        10
    1356: iload         11
    1358: iload         14
    1360: iconst_3
    1361: ishr
    1362: iload         20
    1364: imul
    1365: iadd
    1366: istore        11
    1368: iload         11
    1370: bipush        14
    1372: ishr
    1373: istore        19
    1375: iload         19
    1377: ifeq          1414
    1380: iload         9
    1382: iload         19
    1384: idiv
    1385: istore_2
    1386: iload         10
    1388: iload         19
    1390: idiv
    1391: istore_3
    1392: iload_2
    1393: ifge          1403
    1396: iconst_0
    1397: istore_2
    1398: iload         25
    1400: ifeq          1414
    1403: iload_2
    1404: sipush        16256
    1407: if_icmple     1414
    1410: sipush        16256
    1413: istore_2
    1414: iload         9
    1416: iload         12
    1418: iadd
    1419: istore        9
    1421: iload         10
    1423: iload         13
    1425: iadd
    1426: istore        10
    1428: iload         11
    1430: iload         14
    1432: iadd
    1433: istore        11
    1435: iload         11
    1437: bipush        14
    1439: ishr
    1440: istore        19
    1442: iload         19
    1444: ifeq          1490
    1447: iload         9
    1449: iload         19
    1451: idiv
    1452: istore        17
    1454: iload         10
    1456: iload         19
    1458: idiv
    1459: istore        18
    1461: iload         17
    1463: bipush        7
    1465: if_icmpge     1477
    1468: bipush        7
    1470: istore        17
    1472: iload         25
    1474: ifeq          1490
    1477: iload         17
    1479: sipush        16256
    1482: if_icmple     1490
    1485: sipush        16256
    1488: istore        17
    1490: iload         17
    1492: iload_2
    1493: isub
    1494: iconst_3
    1495: ishr
    1496: istore        21
    1498: iload         18
    1500: iload_3
    1501: isub
    1502: iconst_3
    1503: ishr
    1504: istore        22
    1506: iload_2
    1507: iload         7
    1509: ldc           #5                  // int 6291456
    1511: iand
    1512: iadd
    1513: istore_2
    1514: iload         7
    1516: bipush        23
    1518: ishr
    1519: istore        23
    1521: getstatic     #69                 // Field C:Z
    1524: ifeq          2392
    1527: iload         25
    1529: ifeq          1898
    1532: aload_0
    1533: iload         4
    1535: iinc          4, 1
    1538: aload_1
    1539: iload_3
    1540: sipush        16256
    1543: iand
    1544: iload_2
    1545: bipush        7
    1547: ishr
    1548: iadd
    1549: iaload
    1550: iload         23
    1552: iushr
    1553: iastore
    1554: iload_2
    1555: iload         21
    1557: iadd
    1558: istore_2
    1559: iload_3
    1560: iload         22
    1562: iadd
    1563: istore_3
    1564: aload_0
    1565: iload         4
    1567: iinc          4, 1
    1570: aload_1
    1571: iload_3
    1572: sipush        16256
    1575: iand
    1576: iload_2
    1577: bipush        7
    1579: ishr
    1580: iadd
    1581: iaload
    1582: iload         23
    1584: iushr
    1585: iastore
    1586: iload_2
    1587: iload         21
    1589: iadd
    1590: istore_2
    1591: iload_3
    1592: iload         22
    1594: iadd
    1595: istore_3
    1596: aload_0
    1597: iload         4
    1599: iinc          4, 1
    1602: aload_1
    1603: iload_3
    1604: sipush        16256
    1607: iand
    1608: iload_2
    1609: bipush        7
    1611: ishr
    1612: iadd
    1613: iaload
    1614: iload         23
    1616: iushr
    1617: iastore
    1618: iload_2
    1619: iload         21
    1621: iadd
    1622: istore_2
    1623: iload_3
    1624: iload         22
    1626: iadd
    1627: istore_3
    1628: aload_0
    1629: iload         4
    1631: iinc          4, 1
    1634: aload_1
    1635: iload_3
    1636: sipush        16256
    1639: iand
    1640: iload_2
    1641: bipush        7
    1643: ishr
    1644: iadd
    1645: iaload
    1646: iload         23
    1648: iushr
    1649: iastore
    1650: iload_2
    1651: iload         21
    1653: iadd
    1654: istore_2
    1655: iload_3
    1656: iload         22
    1658: iadd
    1659: istore_3
    1660: aload_0
    1661: iload         4
    1663: iinc          4, 1
    1666: aload_1
    1667: iload_3
    1668: sipush        16256
    1671: iand
    1672: iload_2
    1673: bipush        7
    1675: ishr
    1676: iadd
    1677: iaload
    1678: iload         23
    1680: iushr
    1681: iastore
    1682: iload_2
    1683: iload         21
    1685: iadd
    1686: istore_2
    1687: iload_3
    1688: iload         22
    1690: iadd
    1691: istore_3
    1692: aload_0
    1693: iload         4
    1695: iinc          4, 1
    1698: aload_1
    1699: iload_3
    1700: sipush        16256
    1703: iand
    1704: iload_2
    1705: bipush        7
    1707: ishr
    1708: iadd
    1709: iaload
    1710: iload         23
    1712: iushr
    1713: iastore
    1714: iload_2
    1715: iload         21
    1717: iadd
    1718: istore_2
    1719: iload_3
    1720: iload         22
    1722: iadd
    1723: istore_3
    1724: aload_0
    1725: iload         4
    1727: iinc          4, 1
    1730: aload_1
    1731: iload_3
    1732: sipush        16256
    1735: iand
    1736: iload_2
    1737: bipush        7
    1739: ishr
    1740: iadd
    1741: iaload
    1742: iload         23
    1744: iushr
    1745: iastore
    1746: iload_2
    1747: iload         21
    1749: iadd
    1750: istore_2
    1751: iload_3
    1752: iload         22
    1754: iadd
    1755: istore_3
    1756: aload_0
    1757: iload         4
    1759: iinc          4, 1
    1762: aload_1
    1763: iload_3
    1764: sipush        16256
    1767: iand
    1768: iload_2
    1769: bipush        7
    1771: ishr
    1772: iadd
    1773: iaload
    1774: iload         23
    1776: iushr
    1777: iastore
    1778: iload         17
    1780: istore_2
    1781: iload         18
    1783: istore_3
    1784: iload         9
    1786: iload         12
    1788: iadd
    1789: istore        9
    1791: iload         10
    1793: iload         13
    1795: iadd
    1796: istore        10
    1798: iload         11
    1800: iload         14
    1802: iadd
    1803: istore        11
    1805: iload         11
    1807: bipush        14
    1809: ishr
    1810: istore        19
    1812: iload         19
    1814: ifeq          1860
    1817: iload         9
    1819: iload         19
    1821: idiv
    1822: istore        17
    1824: iload         10
    1826: iload         19
    1828: idiv
    1829: istore        18
    1831: iload         17
    1833: bipush        7
    1835: if_icmpge     1847
    1838: bipush        7
    1840: istore        17
    1842: iload         25
    1844: ifeq          1860
    1847: iload         17
    1849: sipush        16256
    1852: if_icmple     1860
    1855: sipush        16256
    1858: istore        17
    1860: iload         17
    1862: iload_2
    1863: isub
    1864: iconst_3
    1865: ishr
    1866: istore        21
    1868: iload         18
    1870: iload_3
    1871: isub
    1872: iconst_3
    1873: ishr
    1874: istore        22
    1876: iload         7
    1878: iload         15
    1880: iadd
    1881: istore        7
    1883: iload_2
    1884: iload         7
    1886: ldc           #5                  // int 6291456
    1888: iand
    1889: iadd
    1890: istore_2
    1891: iload         7
    1893: bipush        23
    1895: ishr
    1896: istore        23
    1898: iload         16
    1900: iinc          16, -1
    1903: ifgt          1532
    1906: iload         6
    1908: iload         5
    1910: isub
    1911: bipush        7
    1913: iand
    1914: istore        16
    1916: iload         25
    1918: ifeq          1953
    1921: aload_0
    1922: iload         4
    1924: iinc          4, 1
    1927: aload_1
    1928: iload_3
    1929: sipush        16256
    1932: iand
    1933: iload_2
    1934: bipush        7
    1936: ishr
    1937: iadd
    1938: iaload
    1939: iload         23
    1941: iushr
    1942: iastore
    1943: iload_2
    1944: iload         21
    1946: iadd
    1947: istore_2
    1948: iload_3
    1949: iload         22
    1951: iadd
    1952: istore_3
    1953: iload         16
    1955: iinc          16, -1
    1958: ifgt          1921
    1961: return
    1962: aload_1
    1963: iload_3
    1964: sipush        16256
    1967: iand
    1968: iload_2
    1969: bipush        7
    1971: ishr
    1972: iadd
    1973: iaload
    1974: iload         23
    1976: iushr
    1977: dup
    1978: istore        24
    1980: ifeq          1989
    1983: aload_0
    1984: iload         4
    1986: iload         24
    1988: iastore
    1989: iinc          4, 1
    1992: iload_2
    1993: iload         21
    1995: iadd
    1996: istore_2
    1997: iload_3
    1998: iload         22
    2000: iadd
    2001: istore_3
    2002: aload_1
    2003: iload_3
    2004: sipush        16256
    2007: iand
    2008: iload_2
    2009: bipush        7
    2011: ishr
    2012: iadd
    2013: iaload
    2014: iload         23
    2016: iushr
    2017: dup
    2018: istore        24
    2020: ifeq          2029
    2023: aload_0
    2024: iload         4
    2026: iload         24
    2028: iastore
    2029: iinc          4, 1
    2032: iload_2
    2033: iload         21
    2035: iadd
    2036: istore_2
    2037: iload_3
    2038: iload         22
    2040: iadd
    2041: istore_3
    2042: aload_1
    2043: iload_3
    2044: sipush        16256
    2047: iand
    2048: iload_2
    2049: bipush        7
    2051: ishr
    2052: iadd
    2053: iaload
    2054: iload         23
    2056: iushr
    2057: dup
    2058: istore        24
    2060: ifeq          2069
    2063: aload_0
    2064: iload         4
    2066: iload         24
    2068: iastore
    2069: iinc          4, 1
    2072: iload_2
    2073: iload         21
    2075: iadd
    2076: istore_2
    2077: iload_3
    2078: iload         22
    2080: iadd
    2081: istore_3
    2082: aload_1
    2083: iload_3
    2084: sipush        16256
    2087: iand
    2088: iload_2
    2089: bipush        7
    2091: ishr
    2092: iadd
    2093: iaload
    2094: iload         23
    2096: iushr
    2097: dup
    2098: istore        24
    2100: ifeq          2109
    2103: aload_0
    2104: iload         4
    2106: iload         24
    2108: iastore
    2109: iinc          4, 1
    2112: iload_2
    2113: iload         21
    2115: iadd
    2116: istore_2
    2117: iload_3
    2118: iload         22
    2120: iadd
    2121: istore_3
    2122: aload_1
    2123: iload_3
    2124: sipush        16256
    2127: iand
    2128: iload_2
    2129: bipush        7
    2131: ishr
    2132: iadd
    2133: iaload
    2134: iload         23
    2136: iushr
    2137: dup
    2138: istore        24
    2140: ifeq          2149
    2143: aload_0
    2144: iload         4
    2146: iload         24
    2148: iastore
    2149: iinc          4, 1
    2152: iload_2
    2153: iload         21
    2155: iadd
    2156: istore_2
    2157: iload_3
    2158: iload         22
    2160: iadd
    2161: istore_3
    2162: aload_1
    2163: iload_3
    2164: sipush        16256
    2167: iand
    2168: iload_2
    2169: bipush        7
    2171: ishr
    2172: iadd
    2173: iaload
    2174: iload         23
    2176: iushr
    2177: dup
    2178: istore        24
    2180: ifeq          2189
    2183: aload_0
    2184: iload         4
    2186: iload         24
    2188: iastore
    2189: iinc          4, 1
    2192: iload_2
    2193: iload         21
    2195: iadd
    2196: istore_2
    2197: iload_3
    2198: iload         22
    2200: iadd
    2201: istore_3
    2202: aload_1
    2203: iload_3
    2204: sipush        16256
    2207: iand
    2208: iload_2
    2209: bipush        7
    2211: ishr
    2212: iadd
    2213: iaload
    2214: iload         23
    2216: iushr
    2217: dup
    2218: istore        24
    2220: ifeq          2229
    2223: aload_0
    2224: iload         4
    2226: iload         24
    2228: iastore
    2229: iinc          4, 1
    2232: iload_2
    2233: iload         21
    2235: iadd
    2236: istore_2
    2237: iload_3
    2238: iload         22
    2240: iadd
    2241: istore_3
    2242: aload_1
    2243: iload_3
    2244: sipush        16256
    2247: iand
    2248: iload_2
    2249: bipush        7
    2251: ishr
    2252: iadd
    2253: iaload
    2254: iload         23
    2256: iushr
    2257: dup
    2258: istore        24
    2260: ifeq          2269
    2263: aload_0
    2264: iload         4
    2266: iload         24
    2268: iastore
    2269: iinc          4, 1
    2272: iload         17
    2274: istore_2
    2275: iload         18
    2277: istore_3
    2278: iload         9
    2280: iload         12
    2282: iadd
    2283: istore        9
    2285: iload         10
    2287: iload         13
    2289: iadd
    2290: istore        10
    2292: iload         11
    2294: iload         14
    2296: iadd
    2297: istore        11
    2299: iload         11
    2301: bipush        14
    2303: ishr
    2304: istore        19
    2306: iload         19
    2308: ifeq          2354
    2311: iload         9
    2313: iload         19
    2315: idiv
    2316: istore        17
    2318: iload         10
    2320: iload         19
    2322: idiv
    2323: istore        18
    2325: iload         17
    2327: bipush        7
    2329: if_icmpge     2341
    2332: bipush        7
    2334: istore        17
    2336: iload         25
    2338: ifeq          2354
    2341: iload         17
    2343: sipush        16256
    2346: if_icmple     2354
    2349: sipush        16256
    2352: istore        17
    2354: iload         17
    2356: iload_2
    2357: isub
    2358: iconst_3
    2359: ishr
    2360: istore        21
    2362: iload         18
    2364: iload_3
    2365: isub
    2366: iconst_3
    2367: ishr
    2368: istore        22
    2370: iload         7
    2372: iload         15
    2374: iadd
    2375: istore        7
    2377: iload_2
    2378: iload         7
    2380: ldc           #5                  // int 6291456
    2382: iand
    2383: iadd
    2384: istore_2
    2385: iload         7
    2387: bipush        23
    2389: ishr
    2390: istore        23
    2392: iload         16
    2394: iinc          16, -1
    2397: ifgt          1962
    2400: iload         6
    2402: iload         5
    2404: isub
    2405: bipush        7
    2407: iand
    2408: istore        16
    2410: iload         25
    2412: ifeq          2455
    2415: aload_1
    2416: iload_3
    2417: sipush        16256
    2420: iand
    2421: iload_2
    2422: bipush        7
    2424: ishr
    2425: iadd
    2426: iaload
    2427: iload         23
    2429: iushr
    2430: dup
    2431: istore        24
    2433: ifeq          2442
    2436: aload_0
    2437: iload         4
    2439: iload         24
    2441: iastore
    2442: iinc          4, 1
    2445: iload_2
    2446: iload         21
    2448: iadd
    2449: istore_2
    2450: iload_3
    2451: iload         22
    2453: iadd
    2454: istore_3
    2455: iload         16
    2457: iinc          16, -1
    2460: ifgt          2415
    2463: return

  static {};
    Code:
       0: sipush        -436
       3: putstatic     #55                 // Field x:I
       6: sipush        -477
       9: putstatic     #46                 // Field y:I
      12: iconst_1
      13: putstatic     #51                 // Field z:Z
      16: iconst_1
      17: putstatic     #57                 // Field A:Z
      20: iconst_1
      21: putstatic     #56                 // Field D:Z
      24: sipush        512
      27: newarray       int
      29: putstatic     #44                 // Field H:[I
      32: sipush        2048
      35: newarray       int
      37: putstatic     #45                 // Field I:[I
      40: sipush        2048
      43: newarray       int
      45: putstatic     #68                 // Field J:[I
      48: sipush        2048
      51: newarray       int
      53: putstatic     #43                 // Field K:[I
      56: iconst_1
      57: istore_0
      58: goto          73
      61: getstatic     #44                 // Field H:[I
      64: iload_0
      65: ldc           #1                  // int 32768
      67: iload_0
      68: idiv
      69: iastore
      70: iinc          0, 1
      73: iload_0
      74: sipush        512
      77: if_icmplt     61
      80: iconst_1
      81: istore_1
      82: goto          97
      85: getstatic     #45                 // Field I:[I
      88: iload_1
      89: ldc           #4                  // int 65536
      91: iload_1
      92: idiv
      93: iastore
      94: iinc          1, 1
      97: iload_1
      98: sipush        2048
     101: if_icmplt     85
     104: iconst_0
     105: istore_2
     106: goto          150
     109: getstatic     #68                 // Field J:[I
     112: iload_2
     113: ldc2_w        #112                // double 65536.0d
     116: iload_2
     117: i2d
     118: ldc2_w        #116                // double 0.0030679615d
     121: dmul
     122: invokestatic  #67                 // Method java/lang/Math.sin:(D)D
     125: dmul
     126: d2i
     127: iastore
     128: getstatic     #43                 // Field K:[I
     131: iload_2
     132: ldc2_w        #112                // double 65536.0d
     135: iload_2
     136: i2d
     137: ldc2_w        #116                // double 0.0030679615d
     140: dmul
     141: invokestatic  #42                 // Method java/lang/Math.cos:(D)D
     144: dmul
     145: d2i
     146: iastore
     147: iinc          2, 1
     150: iload_2
     151: sipush        2048
     154: if_icmplt     109
     157: bipush        50
     159: anewarray     #20                 // class DSMJIEPN
     162: putstatic     #75                 // Field N:[LDSMJIEPN;
     165: bipush        50
     167: newarray       boolean
     169: putstatic     #79                 // Field O:[Z
     172: bipush        50
     174: newarray       int
     176: putstatic     #73                 // Field P:[I
     179: bipush        50
     181: multianewarray #18,  1            // class "[[I"
     185: putstatic     #72                 // Field S:[[I
     188: bipush        50
     190: newarray       int
     192: putstatic     #58                 // Field T:[I
     195: ldc           #4                  // int 65536
     197: newarray       int
     199: putstatic     #41                 // Field V:[I
     202: bipush        50
     204: multianewarray #18,  1            // class "[[I"
     208: putstatic     #49                 // Field W:[[I
     211: return
}
