Compiled from "Animable_Sub5.java"
final class Animable_Sub5 extends Animable {
  private int anInt1599;

  private final int[] anIntArray1600;

  private final int anInt1601;

  private final int anInt1602;

  private final int anInt1603;

  private final int anInt1604;

  private final int anInt1605;

  private final int anInt1606;

  private Animation aAnimation_1607;

  private int anInt1608;

  public static client clientInstance;

  private final int anInt1610;

  private final int anInt1611;

  private final int anInt1612;

  public Model getRotatedModel();
    Code:
       0: iconst_m1
       1: istore_1
       2: aload_0
       3: getfield      #1                  // Field aAnimation_1607:LAnimation;
       6: ifnull        170
       9: getstatic     #2                  // Field client.loopCycle:I
      12: aload_0
      13: getfield      #3                  // Field anInt1608:I
      16: isub
      17: istore_2
      18: iload_2
      19: bipush        100
      21: if_icmple     37
      24: aload_0
      25: getfield      #1                  // Field aAnimation_1607:LAnimation;
      28: getfield      #4                  // Field Animation.anInt356:I
      31: ifle          37
      34: bipush        100
      36: istore_2
      37: iload_2
      38: aload_0
      39: getfield      #1                  // Field aAnimation_1607:LAnimation;
      42: aload_0
      43: getfield      #5                  // Field anInt1599:I
      46: invokevirtual #6                  // Method Animation.method258:(I)I
      49: if_icmple     141
      52: iload_2
      53: aload_0
      54: getfield      #1                  // Field aAnimation_1607:LAnimation;
      57: aload_0
      58: getfield      #5                  // Field anInt1599:I
      61: invokevirtual #6                  // Method Animation.method258:(I)I
      64: isub
      65: istore_2
      66: aload_0
      67: dup
      68: getfield      #5                  // Field anInt1599:I
      71: iconst_1
      72: iadd
      73: putfield      #5                  // Field anInt1599:I
      76: aload_0
      77: getfield      #5                  // Field anInt1599:I
      80: aload_0
      81: getfield      #1                  // Field aAnimation_1607:LAnimation;
      84: getfield      #7                  // Field Animation.anInt352:I
      87: if_icmpge     93
      90: goto          37
      93: aload_0
      94: dup
      95: getfield      #5                  // Field anInt1599:I
      98: aload_0
      99: getfield      #1                  // Field aAnimation_1607:LAnimation;
     102: getfield      #4                  // Field Animation.anInt356:I
     105: isub
     106: putfield      #5                  // Field anInt1599:I
     109: aload_0
     110: getfield      #5                  // Field anInt1599:I
     113: iflt          133
     116: aload_0
     117: getfield      #5                  // Field anInt1599:I
     120: aload_0
     121: getfield      #1                  // Field aAnimation_1607:LAnimation;
     124: getfield      #7                  // Field Animation.anInt352:I
     127: if_icmpge     133
     130: goto          37
     133: aload_0
     134: aconst_null
     135: putfield      #1                  // Field aAnimation_1607:LAnimation;
     138: goto          141
     141: aload_0
     142: getstatic     #2                  // Field client.loopCycle:I
     145: iload_2
     146: isub
     147: putfield      #3                  // Field anInt1608:I
     150: aload_0
     151: getfield      #1                  // Field aAnimation_1607:LAnimation;
     154: ifnull        170
     157: aload_0
     158: getfield      #1                  // Field aAnimation_1607:LAnimation;
     161: getfield      #8                  // Field Animation.anIntArray353:[I
     164: aload_0
     165: getfield      #5                  // Field anInt1599:I
     168: iaload
     169: istore_1
     170: aload_0
     171: getfield      #9                  // Field anIntArray1600:[I
     174: ifnull        185
     177: aload_0
     178: invokespecial #10                 // Method method457:()LObjectDef;
     181: astore_2
     182: goto          193
     185: aload_0
     186: getfield      #11                 // Field anInt1610:I
     189: invokestatic  #12                 // Method ObjectDef.forID:(I)LObjectDef;
     192: astore_2
     193: aload_2
     194: ifnonnull     199
     197: aconst_null
     198: areturn
     199: aload_2
     200: aload_0
     201: getfield      #13                 // Field anInt1611:I
     204: aload_0
     205: getfield      #14                 // Field anInt1612:I
     208: aload_0
     209: getfield      #15                 // Field anInt1603:I
     212: aload_0
     213: getfield      #16                 // Field anInt1604:I
     216: aload_0
     217: getfield      #17                 // Field anInt1605:I
     220: aload_0
     221: getfield      #18                 // Field anInt1606:I
     224: iload_1
     225: invokevirtual #19                 // Method ObjectDef.method578:(IIIIIII)LModel;
     228: areturn

  private ObjectDef method457();
    Code:
       0: iconst_m1
       1: istore_1
       2: aload_0
       3: getfield      #20                 // Field anInt1601:I
       6: iconst_m1
       7: if_icmpeq     65
      10: getstatic     #21                 // Field VarBit.cache:[LVarBit;
      13: aload_0
      14: getfield      #20                 // Field anInt1601:I
      17: aaload
      18: astore_2
      19: aload_2
      20: getfield      #22                 // Field VarBit.anInt648:I
      23: istore_3
      24: aload_2
      25: getfield      #23                 // Field VarBit.anInt649:I
      28: istore        4
      30: aload_2
      31: getfield      #24                 // Field VarBit.anInt650:I
      34: istore        5
      36: getstatic     #25                 // Field client.anIntArray1232:[I
      39: iload         5
      41: iload         4
      43: isub
      44: iaload
      45: istore        6
      47: getstatic     #26                 // Field clientInstance:Lclient;
      50: getfield      #27                 // Field client.variousSettings:[I
      53: iload_3
      54: iaload
      55: iload         4
      57: ishr
      58: iload         6
      60: iand
      61: istore_1
      62: goto          85
      65: aload_0
      66: getfield      #28                 // Field anInt1602:I
      69: iconst_m1
      70: if_icmpeq     85
      73: getstatic     #26                 // Field clientInstance:Lclient;
      76: getfield      #27                 // Field client.variousSettings:[I
      79: aload_0
      80: getfield      #28                 // Field anInt1602:I
      83: iaload
      84: istore_1
      85: iload_1
      86: iflt          108
      89: iload_1
      90: aload_0
      91: getfield      #9                  // Field anIntArray1600:[I
      94: arraylength
      95: if_icmpge     108
      98: aload_0
      99: getfield      #9                  // Field anIntArray1600:[I
     102: iload_1
     103: iaload
     104: iconst_m1
     105: if_icmpne     110
     108: aconst_null
     109: areturn
     110: aload_0
     111: getfield      #9                  // Field anIntArray1600:[I
     114: iload_1
     115: iaload
     116: invokestatic  #12                 // Method ObjectDef.forID:(I)LObjectDef;
     119: areturn

  public Animable_Sub5(int, int, int, int, int, int, int, int, boolean);
    Code:
       0: aload_0
       1: invokespecial #29                 // Method Animable."<init>":()V
       4: aload_0
       5: iload_1
       6: putfield      #11                 // Field anInt1610:I
       9: aload_0
      10: iload_3
      11: putfield      #13                 // Field anInt1611:I
      14: aload_0
      15: iload_2
      16: putfield      #14                 // Field anInt1612:I
      19: aload_0
      20: iload         6
      22: putfield      #15                 // Field anInt1603:I
      25: aload_0
      26: iload         4
      28: putfield      #16                 // Field anInt1604:I
      31: aload_0
      32: iload         5
      34: putfield      #17                 // Field anInt1605:I
      37: aload_0
      38: iload         7
      40: putfield      #18                 // Field anInt1606:I
      43: iload         8
      45: iconst_m1
      46: if_icmpeq     130
      49: aload_0
      50: getstatic     #30                 // Field Animation.anims:[LAnimation;
      53: iload         8
      55: aaload
      56: putfield      #1                  // Field aAnimation_1607:LAnimation;
      59: aload_0
      60: iconst_0
      61: putfield      #5                  // Field anInt1599:I
      64: aload_0
      65: getstatic     #2                  // Field client.loopCycle:I
      68: putfield      #3                  // Field anInt1608:I
      71: iload         9
      73: ifeq          130
      76: aload_0
      77: getfield      #1                  // Field aAnimation_1607:LAnimation;
      80: getfield      #4                  // Field Animation.anInt356:I
      83: iconst_m1
      84: if_icmpeq     130
      87: aload_0
      88: invokestatic  #31                 // Method java/lang/Math.random:()D
      91: aload_0
      92: getfield      #1                  // Field aAnimation_1607:LAnimation;
      95: getfield      #7                  // Field Animation.anInt352:I
      98: i2d
      99: dmul
     100: d2i
     101: putfield      #5                  // Field anInt1599:I
     104: aload_0
     105: dup
     106: getfield      #3                  // Field anInt1608:I
     109: invokestatic  #31                 // Method java/lang/Math.random:()D
     112: aload_0
     113: getfield      #1                  // Field aAnimation_1607:LAnimation;
     116: aload_0
     117: getfield      #5                  // Field anInt1599:I
     120: invokevirtual #6                  // Method Animation.method258:(I)I
     123: i2d
     124: dmul
     125: d2i
     126: isub
     127: putfield      #3                  // Field anInt1608:I
     130: aload_0
     131: getfield      #11                 // Field anInt1610:I
     134: invokestatic  #12                 // Method ObjectDef.forID:(I)LObjectDef;
     137: astore        10
     139: aload_0
     140: aload         10
     142: getfield      #32                 // Field ObjectDef.anInt774:I
     145: putfield      #20                 // Field anInt1601:I
     148: aload_0
     149: aload         10
     151: getfield      #33                 // Field ObjectDef.anInt749:I
     154: putfield      #28                 // Field anInt1602:I
     157: aload_0
     158: aload         10
     160: getfield      #34                 // Field ObjectDef.childrenIDs:[I
     163: putfield      #9                  // Field anIntArray1600:[I
     166: return
}
