Compiled from "Background.java"
public final class Background extends DrawingArea {
  public byte[] aByteArray1450;

  public final int[] anIntArray1451;

  public int anInt1452;

  public int anInt1453;

  public int anInt1454;

  public int anInt1455;

  public int anInt1456;

  private int anInt1457;

  public Background(StreamLoader, java.lang.String, int);
    Code:
       0: aload_0
       1: invokespecial #1                  // Method DrawingArea."<init>":()V
       4: new           #2                  // class Stream
       7: dup
       8: aload_1
       9: new           #3                  // class java/lang/StringBuilder
      12: dup
      13: invokespecial #4                  // Method java/lang/StringBuilder."<init>":()V
      16: aload_2
      17: invokevirtual #5                  // Method java/lang/StringBuilder.append:(Ljava/lang/String;)Ljava/lang/StringBuilder;
      20: ldc           #6                  // String .dat
      22: invokevirtual #5                  // Method java/lang/StringBuilder.append:(Ljava/lang/String;)Ljava/lang/StringBuilder;
      25: invokevirtual #7                  // Method java/lang/StringBuilder.toString:()Ljava/lang/String;
      28: invokevirtual #8                  // Method StreamLoader.getDataForName:(Ljava/lang/String;)[B
      31: invokespecial #9                  // Method Stream."<init>":([B)V
      34: astore        4
      36: new           #2                  // class Stream
      39: dup
      40: aload_1
      41: ldc           #10                 // String index.dat
      43: invokevirtual #8                  // Method StreamLoader.getDataForName:(Ljava/lang/String;)[B
      46: invokespecial #9                  // Method Stream."<init>":([B)V
      49: astore        5
      51: aload         5
      53: aload         4
      55: invokevirtual #11                 // Method Stream.readUnsignedWord:()I
      58: putfield      #12                 // Field Stream.currentOffset:I
      61: aload_0
      62: aload         5
      64: invokevirtual #11                 // Method Stream.readUnsignedWord:()I
      67: putfield      #13                 // Field anInt1456:I
      70: aload_0
      71: aload         5
      73: invokevirtual #11                 // Method Stream.readUnsignedWord:()I
      76: putfield      #14                 // Field anInt1457:I
      79: aload         5
      81: invokevirtual #15                 // Method Stream.readUnsignedByte:()I
      84: istore        6
      86: aload_0
      87: iload         6
      89: newarray       int
      91: putfield      #16                 // Field anIntArray1451:[I
      94: iconst_0
      95: istore        7
      97: iload         7
      99: iload         6
     101: iconst_1
     102: isub
     103: if_icmpge     126
     106: aload_0
     107: getfield      #16                 // Field anIntArray1451:[I
     110: iload         7
     112: iconst_1
     113: iadd
     114: aload         5
     116: invokevirtual #17                 // Method Stream.read3Bytes:()I
     119: iastore
     120: iinc          7, 1
     123: goto          97
     126: iconst_0
     127: istore        7
     129: iload         7
     131: iload_3
     132: if_icmpge     184
     135: aload         5
     137: dup
     138: getfield      #12                 // Field Stream.currentOffset:I
     141: iconst_2
     142: iadd
     143: putfield      #12                 // Field Stream.currentOffset:I
     146: aload         4
     148: dup
     149: getfield      #12                 // Field Stream.currentOffset:I
     152: aload         5
     154: invokevirtual #11                 // Method Stream.readUnsignedWord:()I
     157: aload         5
     159: invokevirtual #11                 // Method Stream.readUnsignedWord:()I
     162: imul
     163: iadd
     164: putfield      #12                 // Field Stream.currentOffset:I
     167: aload         5
     169: dup
     170: getfield      #12                 // Field Stream.currentOffset:I
     173: iconst_1
     174: iadd
     175: putfield      #12                 // Field Stream.currentOffset:I
     178: iinc          7, 1
     181: goto          129
     184: aload_0
     185: aload         5
     187: invokevirtual #15                 // Method Stream.readUnsignedByte:()I
     190: putfield      #18                 // Field anInt1454:I
     193: aload_0
     194: aload         5
     196: invokevirtual #15                 // Method Stream.readUnsignedByte:()I
     199: putfield      #19                 // Field anInt1455:I
     202: aload_0
     203: aload         5
     205: invokevirtual #11                 // Method Stream.readUnsignedWord:()I
     208: putfield      #20                 // Field anInt1452:I
     211: aload_0
     212: aload         5
     214: invokevirtual #11                 // Method Stream.readUnsignedWord:()I
     217: putfield      #21                 // Field anInt1453:I
     220: aload         5
     222: invokevirtual #15                 // Method Stream.readUnsignedByte:()I
     225: istore        7
     227: aload_0
     228: getfield      #20                 // Field anInt1452:I
     231: aload_0
     232: getfield      #21                 // Field anInt1453:I
     235: imul
     236: istore        8
     238: aload_0
     239: iload         8
     241: newarray       byte
     243: putfield      #22                 // Field aByteArray1450:[B
     246: iload         7
     248: ifne          280
     251: iconst_0
     252: istore        9
     254: iload         9
     256: iload         8
     258: if_icmpge     279
     261: aload_0
     262: getfield      #22                 // Field aByteArray1450:[B
     265: iload         9
     267: aload         4
     269: invokevirtual #23                 // Method Stream.readSignedByte:()B
     272: bastore
     273: iinc          9, 1
     276: goto          254
     279: return
     280: iload         7
     282: iconst_1
     283: if_icmpne     342
     286: iconst_0
     287: istore        9
     289: iload         9
     291: aload_0
     292: getfield      #20                 // Field anInt1452:I
     295: if_icmpge     342
     298: iconst_0
     299: istore        10
     301: iload         10
     303: aload_0
     304: getfield      #21                 // Field anInt1453:I
     307: if_icmpge     336
     310: aload_0
     311: getfield      #22                 // Field aByteArray1450:[B
     314: iload         9
     316: iload         10
     318: aload_0
     319: getfield      #20                 // Field anInt1452:I
     322: imul
     323: iadd
     324: aload         4
     326: invokevirtual #23                 // Method Stream.readSignedByte:()B
     329: bastore
     330: iinc          10, 1
     333: goto          301
     336: iinc          9, 1
     339: goto          289
     342: return

  public void method356();
    Code:
       0: aload_0
       1: dup
       2: getfield      #13                 // Field anInt1456:I
       5: iconst_2
       6: idiv
       7: putfield      #13                 // Field anInt1456:I
      10: aload_0
      11: dup
      12: getfield      #14                 // Field anInt1457:I
      15: iconst_2
      16: idiv
      17: putfield      #14                 // Field anInt1457:I
      20: aload_0
      21: getfield      #13                 // Field anInt1456:I
      24: aload_0
      25: getfield      #14                 // Field anInt1457:I
      28: imul
      29: newarray       byte
      31: astore_1
      32: iconst_0
      33: istore_2
      34: iconst_0
      35: istore_3
      36: iload_3
      37: aload_0
      38: getfield      #21                 // Field anInt1453:I
      41: if_icmpge     102
      44: iconst_0
      45: istore        4
      47: iload         4
      49: aload_0
      50: getfield      #20                 // Field anInt1452:I
      53: if_icmpge     96
      56: aload_1
      57: iload         4
      59: aload_0
      60: getfield      #18                 // Field anInt1454:I
      63: iadd
      64: iconst_1
      65: ishr
      66: iload_3
      67: aload_0
      68: getfield      #19                 // Field anInt1455:I
      71: iadd
      72: iconst_1
      73: ishr
      74: aload_0
      75: getfield      #13                 // Field anInt1456:I
      78: imul
      79: iadd
      80: aload_0
      81: getfield      #22                 // Field aByteArray1450:[B
      84: iload_2
      85: iinc          2, 1
      88: baload
      89: bastore
      90: iinc          4, 1
      93: goto          47
      96: iinc          3, 1
      99: goto          36
     102: aload_0
     103: aload_1
     104: putfield      #22                 // Field aByteArray1450:[B
     107: aload_0
     108: aload_0
     109: getfield      #13                 // Field anInt1456:I
     112: putfield      #20                 // Field anInt1452:I
     115: aload_0
     116: aload_0
     117: getfield      #14                 // Field anInt1457:I
     120: putfield      #21                 // Field anInt1453:I
     123: aload_0
     124: iconst_0
     125: putfield      #18                 // Field anInt1454:I
     128: aload_0
     129: iconst_0
     130: putfield      #19                 // Field anInt1455:I
     133: return

  public void method357();
    Code:
       0: aload_0
       1: getfield      #20                 // Field anInt1452:I
       4: aload_0
       5: getfield      #13                 // Field anInt1456:I
       8: if_icmpne     23
      11: aload_0
      12: getfield      #21                 // Field anInt1453:I
      15: aload_0
      16: getfield      #14                 // Field anInt1457:I
      19: if_icmpne     23
      22: return
      23: aload_0
      24: getfield      #13                 // Field anInt1456:I
      27: aload_0
      28: getfield      #14                 // Field anInt1457:I
      31: imul
      32: newarray       byte
      34: astore_1
      35: iconst_0
      36: istore_2
      37: iconst_0
      38: istore_3
      39: iload_3
      40: aload_0
      41: getfield      #21                 // Field anInt1453:I
      44: if_icmpge     101
      47: iconst_0
      48: istore        4
      50: iload         4
      52: aload_0
      53: getfield      #20                 // Field anInt1452:I
      56: if_icmpge     95
      59: aload_1
      60: iload         4
      62: aload_0
      63: getfield      #18                 // Field anInt1454:I
      66: iadd
      67: iload_3
      68: aload_0
      69: getfield      #19                 // Field anInt1455:I
      72: iadd
      73: aload_0
      74: getfield      #13                 // Field anInt1456:I
      77: imul
      78: iadd
      79: aload_0
      80: getfield      #22                 // Field aByteArray1450:[B
      83: iload_2
      84: iinc          2, 1
      87: baload
      88: bastore
      89: iinc          4, 1
      92: goto          50
      95: iinc          3, 1
      98: goto          39
     101: aload_0
     102: aload_1
     103: putfield      #22                 // Field aByteArray1450:[B
     106: aload_0
     107: aload_0
     108: getfield      #13                 // Field anInt1456:I
     111: putfield      #20                 // Field anInt1452:I
     114: aload_0
     115: aload_0
     116: getfield      #14                 // Field anInt1457:I
     119: putfield      #21                 // Field anInt1453:I
     122: aload_0
     123: iconst_0
     124: putfield      #18                 // Field anInt1454:I
     127: aload_0
     128: iconst_0
     129: putfield      #19                 // Field anInt1455:I
     132: return

  public void method358();
    Code:
       0: aload_0
       1: getfield      #20                 // Field anInt1452:I
       4: aload_0
       5: getfield      #21                 // Field anInt1453:I
       8: imul
       9: newarray       byte
      11: astore_1
      12: iconst_0
      13: istore_2
      14: iconst_0
      15: istore_3
      16: iload_3
      17: aload_0
      18: getfield      #21                 // Field anInt1453:I
      21: if_icmpge     69
      24: aload_0
      25: getfield      #20                 // Field anInt1452:I
      28: iconst_1
      29: isub
      30: istore        4
      32: iload         4
      34: iflt          63
      37: aload_1
      38: iload_2
      39: iinc          2, 1
      42: aload_0
      43: getfield      #22                 // Field aByteArray1450:[B
      46: iload         4
      48: iload_3
      49: aload_0
      50: getfield      #20                 // Field anInt1452:I
      53: imul
      54: iadd
      55: baload
      56: bastore
      57: iinc          4, -1
      60: goto          32
      63: iinc          3, 1
      66: goto          16
      69: aload_0
      70: aload_1
      71: putfield      #22                 // Field aByteArray1450:[B
      74: aload_0
      75: aload_0
      76: getfield      #13                 // Field anInt1456:I
      79: aload_0
      80: getfield      #20                 // Field anInt1452:I
      83: isub
      84: aload_0
      85: getfield      #18                 // Field anInt1454:I
      88: isub
      89: putfield      #18                 // Field anInt1454:I
      92: return

  public void method359();
    Code:
       0: aload_0
       1: getfield      #20                 // Field anInt1452:I
       4: aload_0
       5: getfield      #21                 // Field anInt1453:I
       8: imul
       9: newarray       byte
      11: astore_1
      12: iconst_0
      13: istore_2
      14: aload_0
      15: getfield      #21                 // Field anInt1453:I
      18: iconst_1
      19: isub
      20: istore_3
      21: iload_3
      22: iflt          69
      25: iconst_0
      26: istore        4
      28: iload         4
      30: aload_0
      31: getfield      #20                 // Field anInt1452:I
      34: if_icmpge     63
      37: aload_1
      38: iload_2
      39: iinc          2, 1
      42: aload_0
      43: getfield      #22                 // Field aByteArray1450:[B
      46: iload         4
      48: iload_3
      49: aload_0
      50: getfield      #20                 // Field anInt1452:I
      53: imul
      54: iadd
      55: baload
      56: bastore
      57: iinc          4, 1
      60: goto          28
      63: iinc          3, -1
      66: goto          21
      69: aload_0
      70: aload_1
      71: putfield      #22                 // Field aByteArray1450:[B
      74: aload_0
      75: aload_0
      76: getfield      #14                 // Field anInt1457:I
      79: aload_0
      80: getfield      #21                 // Field anInt1453:I
      83: isub
      84: aload_0
      85: getfield      #19                 // Field anInt1455:I
      88: isub
      89: putfield      #19                 // Field anInt1455:I
      92: return

  public void method360(int, int, int);
    Code:
       0: iconst_0
       1: istore        4
       3: iload         4
       5: aload_0
       6: getfield      #16                 // Field anIntArray1451:[I
       9: arraylength
      10: if_icmpge     175
      13: aload_0
      14: getfield      #16                 // Field anIntArray1451:[I
      17: iload         4
      19: iaload
      20: bipush        16
      22: ishr
      23: sipush        255
      26: iand
      27: istore        5
      29: iload         5
      31: iload_1
      32: iadd
      33: istore        5
      35: iload         5
      37: ifge          46
      40: iconst_0
      41: istore        5
      43: goto          59
      46: iload         5
      48: sipush        255
      51: if_icmple     59
      54: sipush        255
      57: istore        5
      59: aload_0
      60: getfield      #16                 // Field anIntArray1451:[I
      63: iload         4
      65: iaload
      66: bipush        8
      68: ishr
      69: sipush        255
      72: iand
      73: istore        6
      75: iload         6
      77: iload_2
      78: iadd
      79: istore        6
      81: iload         6
      83: ifge          92
      86: iconst_0
      87: istore        6
      89: goto          105
      92: iload         6
      94: sipush        255
      97: if_icmple     105
     100: sipush        255
     103: istore        6
     105: aload_0
     106: getfield      #16                 // Field anIntArray1451:[I
     109: iload         4
     111: iaload
     112: sipush        255
     115: iand
     116: istore        7
     118: iload         7
     120: iload_3
     121: iadd
     122: istore        7
     124: iload         7
     126: ifge          135
     129: iconst_0
     130: istore        7
     132: goto          148
     135: iload         7
     137: sipush        255
     140: if_icmple     148
     143: sipush        255
     146: istore        7
     148: aload_0
     149: getfield      #16                 // Field anIntArray1451:[I
     152: iload         4
     154: iload         5
     156: bipush        16
     158: ishl
     159: iload         6
     161: bipush        8
     163: ishl
     164: iadd
     165: iload         7
     167: iadd
     168: iastore
     169: iinc          4, 1
     172: goto          3
     175: return

  public void method361(int, int);
    Code:
       0: iload_1
       1: aload_0
       2: getfield      #18                 // Field anInt1454:I
       5: iadd
       6: istore_1
       7: iload_2
       8: aload_0
       9: getfield      #19                 // Field anInt1455:I
      12: iadd
      13: istore_2
      14: iload_1
      15: iload_2
      16: getstatic     #24                 // Field DrawingArea.width:I
      19: imul
      20: iadd
      21: istore_3
      22: iconst_0
      23: istore        4
      25: aload_0
      26: getfield      #21                 // Field anInt1453:I
      29: istore        5
      31: aload_0
      32: getfield      #20                 // Field anInt1452:I
      35: istore        6
      37: getstatic     #24                 // Field DrawingArea.width:I
      40: iload         6
      42: isub
      43: istore        7
      45: iconst_0
      46: istore        8
      48: iload_2
      49: getstatic     #25                 // Field DrawingArea.topY:I
      52: if_icmpge     92
      55: getstatic     #25                 // Field DrawingArea.topY:I
      58: iload_2
      59: isub
      60: istore        9
      62: iload         5
      64: iload         9
      66: isub
      67: istore        5
      69: getstatic     #25                 // Field DrawingArea.topY:I
      72: istore_2
      73: iload         4
      75: iload         9
      77: iload         6
      79: imul
      80: iadd
      81: istore        4
      83: iload_3
      84: iload         9
      86: getstatic     #24                 // Field DrawingArea.width:I
      89: imul
      90: iadd
      91: istore_3
      92: iload_2
      93: iload         5
      95: iadd
      96: getstatic     #26                 // Field DrawingArea.bottomY:I
      99: if_icmple     115
     102: iload         5
     104: iload_2
     105: iload         5
     107: iadd
     108: getstatic     #26                 // Field DrawingArea.bottomY:I
     111: isub
     112: isub
     113: istore        5
     115: iload_1
     116: getstatic     #27                 // Field DrawingArea.topX:I
     119: if_icmpge     166
     122: getstatic     #27                 // Field DrawingArea.topX:I
     125: iload_1
     126: isub
     127: istore        9
     129: iload         6
     131: iload         9
     133: isub
     134: istore        6
     136: getstatic     #27                 // Field DrawingArea.topX:I
     139: istore_1
     140: iload         4
     142: iload         9
     144: iadd
     145: istore        4
     147: iload_3
     148: iload         9
     150: iadd
     151: istore_3
     152: iload         8
     154: iload         9
     156: iadd
     157: istore        8
     159: iload         7
     161: iload         9
     163: iadd
     164: istore        7
     166: iload_1
     167: iload         6
     169: iadd
     170: getstatic     #28                 // Field DrawingArea.bottomX:I
     173: if_icmple     207
     176: iload_1
     177: iload         6
     179: iadd
     180: getstatic     #28                 // Field DrawingArea.bottomX:I
     183: isub
     184: istore        9
     186: iload         6
     188: iload         9
     190: isub
     191: istore        6
     193: iload         8
     195: iload         9
     197: iadd
     198: istore        8
     200: iload         7
     202: iload         9
     204: iadd
     205: istore        7
     207: iload         6
     209: ifle          243
     212: iload         5
     214: ifle          243
     217: aload_0
     218: iload         5
     220: getstatic     #29                 // Field DrawingArea.pixels:[I
     223: aload_0
     224: getfield      #22                 // Field aByteArray1450:[B
     227: iload         7
     229: iload_3
     230: iload         6
     232: iload         4
     234: aload_0
     235: getfield      #16                 // Field anIntArray1451:[I
     238: iload         8
     240: invokespecial #30                 // Method method362:(I[I[BIIII[II)V
     243: return

  private void method362(int, int[], byte[], int, int, int, int, int[], int);
    Code:
       0: iload         6
       2: iconst_2
       3: ishr
       4: ineg
       5: istore        10
       7: iload         6
       9: iconst_3
      10: iand
      11: ineg
      12: istore        6
      14: iload_1
      15: ineg
      16: istore        11
      18: iload         11
      20: ifge          253
      23: iload         10
      25: istore        12
      27: iload         12
      29: ifge          182
      32: aload_3
      33: iload         7
      35: iinc          7, 1
      38: baload
      39: istore        13
      41: iload         13
      43: ifeq          65
      46: aload_2
      47: iload         5
      49: iinc          5, 1
      52: aload         8
      54: iload         13
      56: sipush        255
      59: iand
      60: iaload
      61: iastore
      62: goto          68
      65: iinc          5, 1
      68: aload_3
      69: iload         7
      71: iinc          7, 1
      74: baload
      75: istore        13
      77: iload         13
      79: ifeq          101
      82: aload_2
      83: iload         5
      85: iinc          5, 1
      88: aload         8
      90: iload         13
      92: sipush        255
      95: iand
      96: iaload
      97: iastore
      98: goto          104
     101: iinc          5, 1
     104: aload_3
     105: iload         7
     107: iinc          7, 1
     110: baload
     111: istore        13
     113: iload         13
     115: ifeq          137
     118: aload_2
     119: iload         5
     121: iinc          5, 1
     124: aload         8
     126: iload         13
     128: sipush        255
     131: iand
     132: iaload
     133: iastore
     134: goto          140
     137: iinc          5, 1
     140: aload_3
     141: iload         7
     143: iinc          7, 1
     146: baload
     147: istore        13
     149: iload         13
     151: ifeq          173
     154: aload_2
     155: iload         5
     157: iinc          5, 1
     160: aload         8
     162: iload         13
     164: sipush        255
     167: iand
     168: iaload
     169: iastore
     170: goto          176
     173: iinc          5, 1
     176: iinc          12, 1
     179: goto          27
     182: iload         6
     184: istore        12
     186: iload         12
     188: ifge          233
     191: aload_3
     192: iload         7
     194: iinc          7, 1
     197: baload
     198: istore        13
     200: iload         13
     202: ifeq          224
     205: aload_2
     206: iload         5
     208: iinc          5, 1
     211: aload         8
     213: iload         13
     215: sipush        255
     218: iand
     219: iaload
     220: iastore
     221: goto          227
     224: iinc          5, 1
     227: iinc          12, 1
     230: goto          186
     233: iload         5
     235: iload         4
     237: iadd
     238: istore        5
     240: iload         7
     242: iload         9
     244: iadd
     245: istore        7
     247: iinc          11, 1
     250: goto          18
     253: return
}
