Compiled from "Class11.java"
final class Class11 {
  private final int anInt290;

  private final int anInt291;

  private final int anInt292;

  private final int anInt293;

  public final int[][] anIntArrayArray294;

  public Class11();
    Code:
       0: aload_0
       1: invokespecial #1                  // Method java/lang/Object."<init>":()V
       4: aload_0
       5: iconst_0
       6: putfield      #2                  // Field anInt290:I
       9: aload_0
      10: iconst_0
      11: putfield      #3                  // Field anInt291:I
      14: aload_0
      15: bipush        104
      17: putfield      #4                  // Field anInt292:I
      20: aload_0
      21: bipush        104
      23: putfield      #5                  // Field anInt293:I
      26: aload_0
      27: aload_0
      28: getfield      #4                  // Field anInt292:I
      31: aload_0
      32: getfield      #5                  // Field anInt293:I
      35: multianewarray #6,  2             // class "[[I"
      39: putfield      #7                  // Field anIntArrayArray294:[[I
      42: aload_0
      43: invokevirtual #8                  // Method method210:()V
      46: return

  public void method210();
    Code:
       0: iconst_0
       1: istore_1
       2: iload_1
       3: aload_0
       4: getfield      #4                  // Field anInt292:I
       7: if_icmpge     83
      10: iconst_0
      11: istore_2
      12: iload_2
      13: aload_0
      14: getfield      #5                  // Field anInt293:I
      17: if_icmpge     77
      20: iload_1
      21: ifeq          48
      24: iload_2
      25: ifeq          48
      28: iload_1
      29: aload_0
      30: getfield      #4                  // Field anInt292:I
      33: iconst_1
      34: isub
      35: if_icmpeq     48
      38: iload_2
      39: aload_0
      40: getfield      #5                  // Field anInt293:I
      43: iconst_1
      44: isub
      45: if_icmpne     61
      48: aload_0
      49: getfield      #7                  // Field anIntArrayArray294:[[I
      52: iload_1
      53: aaload
      54: iload_2
      55: ldc           #9                  // int 16777215
      57: iastore
      58: goto          71
      61: aload_0
      62: getfield      #7                  // Field anIntArrayArray294:[[I
      65: iload_1
      66: aaload
      67: iload_2
      68: ldc           #10                 // int 16777216
      70: iastore
      71: iinc          2, 1
      74: goto          12
      77: iinc          1, 1
      80: goto          2
      83: return

  public void method211(int, int, int, int, boolean);
    Code:
       0: iload_3
       1: aload_0
       2: getfield      #2                  // Field anInt290:I
       5: isub
       6: istore_3
       7: iload_1
       8: aload_0
       9: getfield      #3                  // Field anInt291:I
      12: isub
      13: istore_1
      14: iload         4
      16: ifne          110
      19: iload_2
      20: ifne          42
      23: aload_0
      24: iload_3
      25: iload_1
      26: sipush        128
      29: invokespecial #11                 // Method method214:(III)V
      32: aload_0
      33: iload_3
      34: iconst_1
      35: isub
      36: iload_1
      37: bipush        8
      39: invokespecial #11                 // Method method214:(III)V
      42: iload_2
      43: iconst_1
      44: if_icmpne     64
      47: aload_0
      48: iload_3
      49: iload_1
      50: iconst_2
      51: invokespecial #11                 // Method method214:(III)V
      54: aload_0
      55: iload_3
      56: iload_1
      57: iconst_1
      58: iadd
      59: bipush        32
      61: invokespecial #11                 // Method method214:(III)V
      64: iload_2
      65: iconst_2
      66: if_icmpne     88
      69: aload_0
      70: iload_3
      71: iload_1
      72: bipush        8
      74: invokespecial #11                 // Method method214:(III)V
      77: aload_0
      78: iload_3
      79: iconst_1
      80: iadd
      81: iload_1
      82: sipush        128
      85: invokespecial #11                 // Method method214:(III)V
      88: iload_2
      89: iconst_3
      90: if_icmpne     110
      93: aload_0
      94: iload_3
      95: iload_1
      96: bipush        32
      98: invokespecial #11                 // Method method214:(III)V
     101: aload_0
     102: iload_3
     103: iload_1
     104: iconst_1
     105: isub
     106: iconst_2
     107: invokespecial #11                 // Method method214:(III)V
     110: iload         4
     112: iconst_1
     113: if_icmpeq     122
     116: iload         4
     118: iconst_3
     119: if_icmpne     217
     122: iload_2
     123: ifne          145
     126: aload_0
     127: iload_3
     128: iload_1
     129: iconst_1
     130: invokespecial #11                 // Method method214:(III)V
     133: aload_0
     134: iload_3
     135: iconst_1
     136: isub
     137: iload_1
     138: iconst_1
     139: iadd
     140: bipush        16
     142: invokespecial #11                 // Method method214:(III)V
     145: iload_2
     146: iconst_1
     147: if_icmpne     169
     150: aload_0
     151: iload_3
     152: iload_1
     153: iconst_4
     154: invokespecial #11                 // Method method214:(III)V
     157: aload_0
     158: iload_3
     159: iconst_1
     160: iadd
     161: iload_1
     162: iconst_1
     163: iadd
     164: bipush        64
     166: invokespecial #11                 // Method method214:(III)V
     169: iload_2
     170: iconst_2
     171: if_icmpne     193
     174: aload_0
     175: iload_3
     176: iload_1
     177: bipush        16
     179: invokespecial #11                 // Method method214:(III)V
     182: aload_0
     183: iload_3
     184: iconst_1
     185: iadd
     186: iload_1
     187: iconst_1
     188: isub
     189: iconst_1
     190: invokespecial #11                 // Method method214:(III)V
     193: iload_2
     194: iconst_3
     195: if_icmpne     217
     198: aload_0
     199: iload_3
     200: iload_1
     201: bipush        64
     203: invokespecial #11                 // Method method214:(III)V
     206: aload_0
     207: iload_3
     208: iconst_1
     209: isub
     210: iload_1
     211: iconst_1
     212: isub
     213: iconst_4
     214: invokespecial #11                 // Method method214:(III)V
     217: iload         4
     219: iconst_2
     220: if_icmpne     356
     223: iload_2
     224: ifne          256
     227: aload_0
     228: iload_3
     229: iload_1
     230: sipush        130
     233: invokespecial #11                 // Method method214:(III)V
     236: aload_0
     237: iload_3
     238: iconst_1
     239: isub
     240: iload_1
     241: bipush        8
     243: invokespecial #11                 // Method method214:(III)V
     246: aload_0
     247: iload_3
     248: iload_1
     249: iconst_1
     250: iadd
     251: bipush        32
     253: invokespecial #11                 // Method method214:(III)V
     256: iload_2
     257: iconst_1
     258: if_icmpne     290
     261: aload_0
     262: iload_3
     263: iload_1
     264: bipush        10
     266: invokespecial #11                 // Method method214:(III)V
     269: aload_0
     270: iload_3
     271: iload_1
     272: iconst_1
     273: iadd
     274: bipush        32
     276: invokespecial #11                 // Method method214:(III)V
     279: aload_0
     280: iload_3
     281: iconst_1
     282: iadd
     283: iload_1
     284: sipush        128
     287: invokespecial #11                 // Method method214:(III)V
     290: iload_2
     291: iconst_2
     292: if_icmpne     323
     295: aload_0
     296: iload_3
     297: iload_1
     298: bipush        40
     300: invokespecial #11                 // Method method214:(III)V
     303: aload_0
     304: iload_3
     305: iconst_1
     306: iadd
     307: iload_1
     308: sipush        128
     311: invokespecial #11                 // Method method214:(III)V
     314: aload_0
     315: iload_3
     316: iload_1
     317: iconst_1
     318: isub
     319: iconst_2
     320: invokespecial #11                 // Method method214:(III)V
     323: iload_2
     324: iconst_3
     325: if_icmpne     356
     328: aload_0
     329: iload_3
     330: iload_1
     331: sipush        160
     334: invokespecial #11                 // Method method214:(III)V
     337: aload_0
     338: iload_3
     339: iload_1
     340: iconst_1
     341: isub
     342: iconst_2
     343: invokespecial #11                 // Method method214:(III)V
     346: aload_0
     347: iload_3
     348: iconst_1
     349: isub
     350: iload_1
     351: bipush        8
     353: invokespecial #11                 // Method method214:(III)V
     356: iload         5
     358: ifeq          725
     361: iload         4
     363: ifne          463
     366: iload_2
     367: ifne          389
     370: aload_0
     371: iload_3
     372: iload_1
     373: ldc           #12                 // int 65536
     375: invokespecial #11                 // Method method214:(III)V
     378: aload_0
     379: iload_3
     380: iconst_1
     381: isub
     382: iload_1
     383: sipush        4096
     386: invokespecial #11                 // Method method214:(III)V
     389: iload_2
     390: iconst_1
     391: if_icmpne     414
     394: aload_0
     395: iload_3
     396: iload_1
     397: sipush        1024
     400: invokespecial #11                 // Method method214:(III)V
     403: aload_0
     404: iload_3
     405: iload_1
     406: iconst_1
     407: iadd
     408: sipush        16384
     411: invokespecial #11                 // Method method214:(III)V
     414: iload_2
     415: iconst_2
     416: if_icmpne     438
     419: aload_0
     420: iload_3
     421: iload_1
     422: sipush        4096
     425: invokespecial #11                 // Method method214:(III)V
     428: aload_0
     429: iload_3
     430: iconst_1
     431: iadd
     432: iload_1
     433: ldc           #12                 // int 65536
     435: invokespecial #11                 // Method method214:(III)V
     438: iload_2
     439: iconst_3
     440: if_icmpne     463
     443: aload_0
     444: iload_3
     445: iload_1
     446: sipush        16384
     449: invokespecial #11                 // Method method214:(III)V
     452: aload_0
     453: iload_3
     454: iload_1
     455: iconst_1
     456: isub
     457: sipush        1024
     460: invokespecial #11                 // Method method214:(III)V
     463: iload         4
     465: iconst_1
     466: if_icmpeq     475
     469: iload         4
     471: iconst_3
     472: if_icmpne     580
     475: iload_2
     476: ifne          501
     479: aload_0
     480: iload_3
     481: iload_1
     482: sipush        512
     485: invokespecial #11                 // Method method214:(III)V
     488: aload_0
     489: iload_3
     490: iconst_1
     491: isub
     492: iload_1
     493: iconst_1
     494: iadd
     495: sipush        8192
     498: invokespecial #11                 // Method method214:(III)V
     501: iload_2
     502: iconst_1
     503: if_icmpne     527
     506: aload_0
     507: iload_3
     508: iload_1
     509: sipush        2048
     512: invokespecial #11                 // Method method214:(III)V
     515: aload_0
     516: iload_3
     517: iconst_1
     518: iadd
     519: iload_1
     520: iconst_1
     521: iadd
     522: ldc           #13                 // int 32768
     524: invokespecial #11                 // Method method214:(III)V
     527: iload_2
     528: iconst_2
     529: if_icmpne     554
     532: aload_0
     533: iload_3
     534: iload_1
     535: sipush        8192
     538: invokespecial #11                 // Method method214:(III)V
     541: aload_0
     542: iload_3
     543: iconst_1
     544: iadd
     545: iload_1
     546: iconst_1
     547: isub
     548: sipush        512
     551: invokespecial #11                 // Method method214:(III)V
     554: iload_2
     555: iconst_3
     556: if_icmpne     580
     559: aload_0
     560: iload_3
     561: iload_1
     562: ldc           #13                 // int 32768
     564: invokespecial #11                 // Method method214:(III)V
     567: aload_0
     568: iload_3
     569: iconst_1
     570: isub
     571: iload_1
     572: iconst_1
     573: isub
     574: sipush        2048
     577: invokespecial #11                 // Method method214:(III)V
     580: iload         4
     582: iconst_2
     583: if_icmpne     725
     586: iload_2
     587: ifne          620
     590: aload_0
     591: iload_3
     592: iload_1
     593: ldc           #14                 // int 66560
     595: invokespecial #11                 // Method method214:(III)V
     598: aload_0
     599: iload_3
     600: iconst_1
     601: isub
     602: iload_1
     603: sipush        4096
     606: invokespecial #11                 // Method method214:(III)V
     609: aload_0
     610: iload_3
     611: iload_1
     612: iconst_1
     613: iadd
     614: sipush        16384
     617: invokespecial #11                 // Method method214:(III)V
     620: iload_2
     621: iconst_1
     622: if_icmpne     655
     625: aload_0
     626: iload_3
     627: iload_1
     628: sipush        5120
     631: invokespecial #11                 // Method method214:(III)V
     634: aload_0
     635: iload_3
     636: iload_1
     637: iconst_1
     638: iadd
     639: sipush        16384
     642: invokespecial #11                 // Method method214:(III)V
     645: aload_0
     646: iload_3
     647: iconst_1
     648: iadd
     649: iload_1
     650: ldc           #12                 // int 65536
     652: invokespecial #11                 // Method method214:(III)V
     655: iload_2
     656: iconst_2
     657: if_icmpne     690
     660: aload_0
     661: iload_3
     662: iload_1
     663: sipush        20480
     666: invokespecial #11                 // Method method214:(III)V
     669: aload_0
     670: iload_3
     671: iconst_1
     672: iadd
     673: iload_1
     674: ldc           #12                 // int 65536
     676: invokespecial #11                 // Method method214:(III)V
     679: aload_0
     680: iload_3
     681: iload_1
     682: iconst_1
     683: isub
     684: sipush        1024
     687: invokespecial #11                 // Method method214:(III)V
     690: iload_2
     691: iconst_3
     692: if_icmpne     725
     695: aload_0
     696: iload_3
     697: iload_1
     698: ldc           #15                 // int 81920
     700: invokespecial #11                 // Method method214:(III)V
     703: aload_0
     704: iload_3
     705: iload_1
     706: iconst_1
     707: isub
     708: sipush        1024
     711: invokespecial #11                 // Method method214:(III)V
     714: aload_0
     715: iload_3
     716: iconst_1
     717: isub
     718: iload_1
     719: sipush        4096
     722: invokespecial #11                 // Method method214:(III)V
     725: return

  public void method212(boolean, int, int, int, int, int);
    Code:
       0: sipush        256
       3: istore        7
       5: iload_1
       6: ifeq          16
       9: iload         7
      11: ldc           #16                 // int 131072
      13: iadd
      14: istore        7
      16: iload         4
      18: aload_0
      19: getfield      #2                  // Field anInt290:I
      22: isub
      23: istore        4
      25: iload         5
      27: aload_0
      28: getfield      #3                  // Field anInt291:I
      31: isub
      32: istore        5
      34: iload         6
      36: iconst_1
      37: if_icmpeq     46
      40: iload         6
      42: iconst_3
      43: if_icmpne     54
      46: iload_2
      47: istore        8
      49: iload_3
      50: istore_2
      51: iload         8
      53: istore_3
      54: iload         4
      56: istore        8
      58: iload         8
      60: iload         4
      62: iload_2
      63: iadd
      64: if_icmpge     130
      67: iload         8
      69: iflt          124
      72: iload         8
      74: aload_0
      75: getfield      #4                  // Field anInt292:I
      78: if_icmpge     124
      81: iload         5
      83: istore        9
      85: iload         9
      87: iload         5
      89: iload_3
      90: iadd
      91: if_icmpge     124
      94: iload         9
      96: iflt          118
      99: iload         9
     101: aload_0
     102: getfield      #5                  // Field anInt293:I
     105: if_icmpge     118
     108: aload_0
     109: iload         8
     111: iload         9
     113: iload         7
     115: invokespecial #11                 // Method method214:(III)V
     118: iinc          9, 1
     121: goto          85
     124: iinc          8, 1
     127: goto          58
     130: return

  public void method213(int, int);
    Code:
       0: iload_2
       1: aload_0
       2: getfield      #2                  // Field anInt290:I
       5: isub
       6: istore_2
       7: iload_1
       8: aload_0
       9: getfield      #3                  // Field anInt291:I
      12: isub
      13: istore_1
      14: aload_0
      15: getfield      #7                  // Field anIntArrayArray294:[[I
      18: iload_2
      19: aaload
      20: iload_1
      21: dup2
      22: iaload
      23: ldc           #17                 // int 2097152
      25: ior
      26: iastore
      27: return

  private void method214(int, int, int);
    Code:
       0: aload_0
       1: getfield      #7                  // Field anIntArrayArray294:[[I
       4: iload_1
       5: aaload
       6: iload_2
       7: dup2
       8: iaload
       9: iload_3
      10: ior
      11: iastore
      12: return

  public void method215(int, int, boolean, int, int);
    Code:
       0: iload         4
       2: aload_0
       3: getfield      #2                  // Field anInt290:I
       6: isub
       7: istore        4
       9: iload         5
      11: aload_0
      12: getfield      #3                  // Field anInt291:I
      15: isub
      16: istore        5
      18: iload_2
      19: ifne          129
      22: iload_1
      23: ifne          49
      26: aload_0
      27: sipush        128
      30: iload         4
      32: iload         5
      34: invokespecial #18                 // Method method217:(III)V
      37: aload_0
      38: bipush        8
      40: iload         4
      42: iconst_1
      43: isub
      44: iload         5
      46: invokespecial #18                 // Method method217:(III)V
      49: iload_1
      50: iconst_1
      51: if_icmpne     75
      54: aload_0
      55: iconst_2
      56: iload         4
      58: iload         5
      60: invokespecial #18                 // Method method217:(III)V
      63: aload_0
      64: bipush        32
      66: iload         4
      68: iload         5
      70: iconst_1
      71: iadd
      72: invokespecial #18                 // Method method217:(III)V
      75: iload_1
      76: iconst_2
      77: if_icmpne     103
      80: aload_0
      81: bipush        8
      83: iload         4
      85: iload         5
      87: invokespecial #18                 // Method method217:(III)V
      90: aload_0
      91: sipush        128
      94: iload         4
      96: iconst_1
      97: iadd
      98: iload         5
     100: invokespecial #18                 // Method method217:(III)V
     103: iload_1
     104: iconst_3
     105: if_icmpne     129
     108: aload_0
     109: bipush        32
     111: iload         4
     113: iload         5
     115: invokespecial #18                 // Method method217:(III)V
     118: aload_0
     119: iconst_2
     120: iload         4
     122: iload         5
     124: iconst_1
     125: isub
     126: invokespecial #18                 // Method method217:(III)V
     129: iload_2
     130: iconst_1
     131: if_icmpeq     139
     134: iload_2
     135: iconst_3
     136: if_icmpne     250
     139: iload_1
     140: ifne          166
     143: aload_0
     144: iconst_1
     145: iload         4
     147: iload         5
     149: invokespecial #18                 // Method method217:(III)V
     152: aload_0
     153: bipush        16
     155: iload         4
     157: iconst_1
     158: isub
     159: iload         5
     161: iconst_1
     162: iadd
     163: invokespecial #18                 // Method method217:(III)V
     166: iload_1
     167: iconst_1
     168: if_icmpne     194
     171: aload_0
     172: iconst_4
     173: iload         4
     175: iload         5
     177: invokespecial #18                 // Method method217:(III)V
     180: aload_0
     181: bipush        64
     183: iload         4
     185: iconst_1
     186: iadd
     187: iload         5
     189: iconst_1
     190: iadd
     191: invokespecial #18                 // Method method217:(III)V
     194: iload_1
     195: iconst_2
     196: if_icmpne     222
     199: aload_0
     200: bipush        16
     202: iload         4
     204: iload         5
     206: invokespecial #18                 // Method method217:(III)V
     209: aload_0
     210: iconst_1
     211: iload         4
     213: iconst_1
     214: iadd
     215: iload         5
     217: iconst_1
     218: isub
     219: invokespecial #18                 // Method method217:(III)V
     222: iload_1
     223: iconst_3
     224: if_icmpne     250
     227: aload_0
     228: bipush        64
     230: iload         4
     232: iload         5
     234: invokespecial #18                 // Method method217:(III)V
     237: aload_0
     238: iconst_4
     239: iload         4
     241: iconst_1
     242: isub
     243: iload         5
     245: iconst_1
     246: isub
     247: invokespecial #18                 // Method method217:(III)V
     250: iload_2
     251: iconst_2
     252: if_icmpne     412
     255: iload_1
     256: ifne          294
     259: aload_0
     260: sipush        130
     263: iload         4
     265: iload         5
     267: invokespecial #18                 // Method method217:(III)V
     270: aload_0
     271: bipush        8
     273: iload         4
     275: iconst_1
     276: isub
     277: iload         5
     279: invokespecial #18                 // Method method217:(III)V
     282: aload_0
     283: bipush        32
     285: iload         4
     287: iload         5
     289: iconst_1
     290: iadd
     291: invokespecial #18                 // Method method217:(III)V
     294: iload_1
     295: iconst_1
     296: if_icmpne     334
     299: aload_0
     300: bipush        10
     302: iload         4
     304: iload         5
     306: invokespecial #18                 // Method method217:(III)V
     309: aload_0
     310: bipush        32
     312: iload         4
     314: iload         5
     316: iconst_1
     317: iadd
     318: invokespecial #18                 // Method method217:(III)V
     321: aload_0
     322: sipush        128
     325: iload         4
     327: iconst_1
     328: iadd
     329: iload         5
     331: invokespecial #18                 // Method method217:(III)V
     334: iload_1
     335: iconst_2
     336: if_icmpne     373
     339: aload_0
     340: bipush        40
     342: iload         4
     344: iload         5
     346: invokespecial #18                 // Method method217:(III)V
     349: aload_0
     350: sipush        128
     353: iload         4
     355: iconst_1
     356: iadd
     357: iload         5
     359: invokespecial #18                 // Method method217:(III)V
     362: aload_0
     363: iconst_2
     364: iload         4
     366: iload         5
     368: iconst_1
     369: isub
     370: invokespecial #18                 // Method method217:(III)V
     373: iload_1
     374: iconst_3
     375: if_icmpne     412
     378: aload_0
     379: sipush        160
     382: iload         4
     384: iload         5
     386: invokespecial #18                 // Method method217:(III)V
     389: aload_0
     390: iconst_2
     391: iload         4
     393: iload         5
     395: iconst_1
     396: isub
     397: invokespecial #18                 // Method method217:(III)V
     400: aload_0
     401: bipush        8
     403: iload         4
     405: iconst_1
     406: isub
     407: iload         5
     409: invokespecial #18                 // Method method217:(III)V
     412: iload_3
     413: ifeq          832
     416: iload_2
     417: ifne          533
     420: iload_1
     421: ifne          447
     424: aload_0
     425: ldc           #12                 // int 65536
     427: iload         4
     429: iload         5
     431: invokespecial #18                 // Method method217:(III)V
     434: aload_0
     435: sipush        4096
     438: iload         4
     440: iconst_1
     441: isub
     442: iload         5
     444: invokespecial #18                 // Method method217:(III)V
     447: iload_1
     448: iconst_1
     449: if_icmpne     476
     452: aload_0
     453: sipush        1024
     456: iload         4
     458: iload         5
     460: invokespecial #18                 // Method method217:(III)V
     463: aload_0
     464: sipush        16384
     467: iload         4
     469: iload         5
     471: iconst_1
     472: iadd
     473: invokespecial #18                 // Method method217:(III)V
     476: iload_1
     477: iconst_2
     478: if_icmpne     504
     481: aload_0
     482: sipush        4096
     485: iload         4
     487: iload         5
     489: invokespecial #18                 // Method method217:(III)V
     492: aload_0
     493: ldc           #12                 // int 65536
     495: iload         4
     497: iconst_1
     498: iadd
     499: iload         5
     501: invokespecial #18                 // Method method217:(III)V
     504: iload_1
     505: iconst_3
     506: if_icmpne     533
     509: aload_0
     510: sipush        16384
     513: iload         4
     515: iload         5
     517: invokespecial #18                 // Method method217:(III)V
     520: aload_0
     521: sipush        1024
     524: iload         4
     526: iload         5
     528: iconst_1
     529: isub
     530: invokespecial #18                 // Method method217:(III)V
     533: iload_2
     534: iconst_1
     535: if_icmpeq     543
     538: iload_2
     539: iconst_3
     540: if_icmpne     664
     543: iload_1
     544: ifne          573
     547: aload_0
     548: sipush        512
     551: iload         4
     553: iload         5
     555: invokespecial #18                 // Method method217:(III)V
     558: aload_0
     559: sipush        8192
     562: iload         4
     564: iconst_1
     565: isub
     566: iload         5
     568: iconst_1
     569: iadd
     570: invokespecial #18                 // Method method217:(III)V
     573: iload_1
     574: iconst_1
     575: if_icmpne     603
     578: aload_0
     579: sipush        2048
     582: iload         4
     584: iload         5
     586: invokespecial #18                 // Method method217:(III)V
     589: aload_0
     590: ldc           #13                 // int 32768
     592: iload         4
     594: iconst_1
     595: iadd
     596: iload         5
     598: iconst_1
     599: iadd
     600: invokespecial #18                 // Method method217:(III)V
     603: iload_1
     604: iconst_2
     605: if_icmpne     634
     608: aload_0
     609: sipush        8192
     612: iload         4
     614: iload         5
     616: invokespecial #18                 // Method method217:(III)V
     619: aload_0
     620: sipush        512
     623: iload         4
     625: iconst_1
     626: iadd
     627: iload         5
     629: iconst_1
     630: isub
     631: invokespecial #18                 // Method method217:(III)V
     634: iload_1
     635: iconst_3
     636: if_icmpne     664
     639: aload_0
     640: ldc           #13                 // int 32768
     642: iload         4
     644: iload         5
     646: invokespecial #18                 // Method method217:(III)V
     649: aload_0
     650: sipush        2048
     653: iload         4
     655: iconst_1
     656: isub
     657: iload         5
     659: iconst_1
     660: isub
     661: invokespecial #18                 // Method method217:(III)V
     664: iload_2
     665: iconst_2
     666: if_icmpne     832
     669: iload_1
     670: ifne          709
     673: aload_0
     674: ldc           #14                 // int 66560
     676: iload         4
     678: iload         5
     680: invokespecial #18                 // Method method217:(III)V
     683: aload_0
     684: sipush        4096
     687: iload         4
     689: iconst_1
     690: isub
     691: iload         5
     693: invokespecial #18                 // Method method217:(III)V
     696: aload_0
     697: sipush        16384
     700: iload         4
     702: iload         5
     704: iconst_1
     705: iadd
     706: invokespecial #18                 // Method method217:(III)V
     709: iload_1
     710: iconst_1
     711: if_icmpne     750
     714: aload_0
     715: sipush        5120
     718: iload         4
     720: iload         5
     722: invokespecial #18                 // Method method217:(III)V
     725: aload_0
     726: sipush        16384
     729: iload         4
     731: iload         5
     733: iconst_1
     734: iadd
     735: invokespecial #18                 // Method method217:(III)V
     738: aload_0
     739: ldc           #12                 // int 65536
     741: iload         4
     743: iconst_1
     744: iadd
     745: iload         5
     747: invokespecial #18                 // Method method217:(III)V
     750: iload_1
     751: iconst_2
     752: if_icmpne     791
     755: aload_0
     756: sipush        20480
     759: iload         4
     761: iload         5
     763: invokespecial #18                 // Method method217:(III)V
     766: aload_0
     767: ldc           #12                 // int 65536
     769: iload         4
     771: iconst_1
     772: iadd
     773: iload         5
     775: invokespecial #18                 // Method method217:(III)V
     778: aload_0
     779: sipush        1024
     782: iload         4
     784: iload         5
     786: iconst_1
     787: isub
     788: invokespecial #18                 // Method method217:(III)V
     791: iload_1
     792: iconst_3
     793: if_icmpne     832
     796: aload_0
     797: ldc           #15                 // int 81920
     799: iload         4
     801: iload         5
     803: invokespecial #18                 // Method method217:(III)V
     806: aload_0
     807: sipush        1024
     810: iload         4
     812: iload         5
     814: iconst_1
     815: isub
     816: invokespecial #18                 // Method method217:(III)V
     819: aload_0
     820: sipush        4096
     823: iload         4
     825: iconst_1
     826: isub
     827: iload         5
     829: invokespecial #18                 // Method method217:(III)V
     832: return

  public void method216(int, int, int, int, int, boolean);
    Code:
       0: sipush        256
       3: istore        7
       5: iload         6
       7: ifeq          17
      10: iload         7
      12: ldc           #16                 // int 131072
      14: iadd
      15: istore        7
      17: iload_3
      18: aload_0
      19: getfield      #2                  // Field anInt290:I
      22: isub
      23: istore_3
      24: iload         4
      26: aload_0
      27: getfield      #3                  // Field anInt291:I
      30: isub
      31: istore        4
      33: iload_1
      34: iconst_1
      35: if_icmpeq     43
      38: iload_1
      39: iconst_3
      40: if_icmpne     53
      43: iload_2
      44: istore        8
      46: iload         5
      48: istore_2
      49: iload         8
      51: istore        5
      53: iload_3
      54: istore        8
      56: iload         8
      58: iload_3
      59: iload_2
      60: iadd
      61: if_icmpge     128
      64: iload         8
      66: iflt          122
      69: iload         8
      71: aload_0
      72: getfield      #4                  // Field anInt292:I
      75: if_icmpge     122
      78: iload         4
      80: istore        9
      82: iload         9
      84: iload         4
      86: iload         5
      88: iadd
      89: if_icmpge     122
      92: iload         9
      94: iflt          116
      97: iload         9
      99: aload_0
     100: getfield      #5                  // Field anInt293:I
     103: if_icmpge     116
     106: aload_0
     107: iload         7
     109: iload         8
     111: iload         9
     113: invokespecial #18                 // Method method217:(III)V
     116: iinc          9, 1
     119: goto          82
     122: iinc          8, 1
     125: goto          56
     128: return

  private void method217(int, int, int);
    Code:
       0: aload_0
       1: getfield      #7                  // Field anIntArrayArray294:[[I
       4: iload_2
       5: aaload
       6: iload_3
       7: dup2
       8: iaload
       9: ldc           #9                  // int 16777215
      11: iload_1
      12: isub
      13: iand
      14: iastore
      15: return

  public void method218(int, int);
    Code:
       0: iload_2
       1: aload_0
       2: getfield      #2                  // Field anInt290:I
       5: isub
       6: istore_2
       7: iload_1
       8: aload_0
       9: getfield      #3                  // Field anInt291:I
      12: isub
      13: istore_1
      14: aload_0
      15: getfield      #7                  // Field anIntArrayArray294:[[I
      18: iload_2
      19: aaload
      20: iload_1
      21: dup2
      22: iaload
      23: ldc           #19                 // int 14680063
      25: iand
      26: iastore
      27: return

  public boolean method219(int, int, int, int, int, int);
    Code:
       0: iload_2
       1: iload_1
       2: if_icmpne     13
       5: iload_3
       6: iload         6
       8: if_icmpne     13
      11: iconst_1
      12: ireturn
      13: iload_2
      14: aload_0
      15: getfield      #2                  // Field anInt290:I
      18: isub
      19: istore_2
      20: iload_3
      21: aload_0
      22: getfield      #3                  // Field anInt291:I
      25: isub
      26: istore_3
      27: iload_1
      28: aload_0
      29: getfield      #2                  // Field anInt290:I
      32: isub
      33: istore_1
      34: iload         6
      36: aload_0
      37: getfield      #3                  // Field anInt291:I
      40: isub
      41: istore        6
      43: iload         5
      45: ifne          363
      48: iload         4
      50: ifne          126
      53: iload_2
      54: iload_1
      55: iconst_1
      56: isub
      57: if_icmpne     68
      60: iload_3
      61: iload         6
      63: if_icmpne     68
      66: iconst_1
      67: ireturn
      68: iload_2
      69: iload_1
      70: if_icmpne     97
      73: iload_3
      74: iload         6
      76: iconst_1
      77: iadd
      78: if_icmpne     97
      81: aload_0
      82: getfield      #7                  // Field anIntArrayArray294:[[I
      85: iload_2
      86: aaload
      87: iload_3
      88: iaload
      89: ldc           #20                 // int 19398944
      91: iand
      92: ifne          97
      95: iconst_1
      96: ireturn
      97: iload_2
      98: iload_1
      99: if_icmpne     363
     102: iload_3
     103: iload         6
     105: iconst_1
     106: isub
     107: if_icmpne     363
     110: aload_0
     111: getfield      #7                  // Field anIntArrayArray294:[[I
     114: iload_2
     115: aaload
     116: iload_3
     117: iaload
     118: ldc           #21                 // int 19398914
     120: iand
     121: ifne          363
     124: iconst_1
     125: ireturn
     126: iload         4
     128: iconst_1
     129: if_icmpne     205
     132: iload_2
     133: iload_1
     134: if_icmpne     147
     137: iload_3
     138: iload         6
     140: iconst_1
     141: iadd
     142: if_icmpne     147
     145: iconst_1
     146: ireturn
     147: iload_2
     148: iload_1
     149: iconst_1
     150: isub
     151: if_icmpne     176
     154: iload_3
     155: iload         6
     157: if_icmpne     176
     160: aload_0
     161: getfield      #7                  // Field anIntArrayArray294:[[I
     164: iload_2
     165: aaload
     166: iload_3
     167: iaload
     168: ldc           #22                 // int 19398920
     170: iand
     171: ifne          176
     174: iconst_1
     175: ireturn
     176: iload_2
     177: iload_1
     178: iconst_1
     179: iadd
     180: if_icmpne     363
     183: iload_3
     184: iload         6
     186: if_icmpne     363
     189: aload_0
     190: getfield      #7                  // Field anIntArrayArray294:[[I
     193: iload_2
     194: aaload
     195: iload_3
     196: iaload
     197: ldc           #23                 // int 19399040
     199: iand
     200: ifne          363
     203: iconst_1
     204: ireturn
     205: iload         4
     207: iconst_2
     208: if_icmpne     284
     211: iload_2
     212: iload_1
     213: iconst_1
     214: iadd
     215: if_icmpne     226
     218: iload_3
     219: iload         6
     221: if_icmpne     226
     224: iconst_1
     225: ireturn
     226: iload_2
     227: iload_1
     228: if_icmpne     255
     231: iload_3
     232: iload         6
     234: iconst_1
     235: iadd
     236: if_icmpne     255
     239: aload_0
     240: getfield      #7                  // Field anIntArrayArray294:[[I
     243: iload_2
     244: aaload
     245: iload_3
     246: iaload
     247: ldc           #20                 // int 19398944
     249: iand
     250: ifne          255
     253: iconst_1
     254: ireturn
     255: iload_2
     256: iload_1
     257: if_icmpne     363
     260: iload_3
     261: iload         6
     263: iconst_1
     264: isub
     265: if_icmpne     363
     268: aload_0
     269: getfield      #7                  // Field anIntArrayArray294:[[I
     272: iload_2
     273: aaload
     274: iload_3
     275: iaload
     276: ldc           #21                 // int 19398914
     278: iand
     279: ifne          363
     282: iconst_1
     283: ireturn
     284: iload         4
     286: iconst_3
     287: if_icmpne     363
     290: iload_2
     291: iload_1
     292: if_icmpne     305
     295: iload_3
     296: iload         6
     298: iconst_1
     299: isub
     300: if_icmpne     305
     303: iconst_1
     304: ireturn
     305: iload_2
     306: iload_1
     307: iconst_1
     308: isub
     309: if_icmpne     334
     312: iload_3
     313: iload         6
     315: if_icmpne     334
     318: aload_0
     319: getfield      #7                  // Field anIntArrayArray294:[[I
     322: iload_2
     323: aaload
     324: iload_3
     325: iaload
     326: ldc           #22                 // int 19398920
     328: iand
     329: ifne          334
     332: iconst_1
     333: ireturn
     334: iload_2
     335: iload_1
     336: iconst_1
     337: iadd
     338: if_icmpne     363
     341: iload_3
     342: iload         6
     344: if_icmpne     363
     347: aload_0
     348: getfield      #7                  // Field anIntArrayArray294:[[I
     351: iload_2
     352: aaload
     353: iload_3
     354: iaload
     355: ldc           #23                 // int 19399040
     357: iand
     358: ifne          363
     361: iconst_1
     362: ireturn
     363: iload         5
     365: iconst_2
     366: if_icmpne     744
     369: iload         4
     371: ifne          462
     374: iload_2
     375: iload_1
     376: iconst_1
     377: isub
     378: if_icmpne     389
     381: iload_3
     382: iload         6
     384: if_icmpne     389
     387: iconst_1
     388: ireturn
     389: iload_2
     390: iload_1
     391: if_icmpne     404
     394: iload_3
     395: iload         6
     397: iconst_1
     398: iadd
     399: if_icmpne     404
     402: iconst_1
     403: ireturn
     404: iload_2
     405: iload_1
     406: iconst_1
     407: iadd
     408: if_icmpne     433
     411: iload_3
     412: iload         6
     414: if_icmpne     433
     417: aload_0
     418: getfield      #7                  // Field anIntArrayArray294:[[I
     421: iload_2
     422: aaload
     423: iload_3
     424: iaload
     425: ldc           #23                 // int 19399040
     427: iand
     428: ifne          433
     431: iconst_1
     432: ireturn
     433: iload_2
     434: iload_1
     435: if_icmpne     744
     438: iload_3
     439: iload         6
     441: iconst_1
     442: isub
     443: if_icmpne     744
     446: aload_0
     447: getfield      #7                  // Field anIntArrayArray294:[[I
     450: iload_2
     451: aaload
     452: iload_3
     453: iaload
     454: ldc           #21                 // int 19398914
     456: iand
     457: ifne          744
     460: iconst_1
     461: ireturn
     462: iload         4
     464: iconst_1
     465: if_icmpne     556
     468: iload_2
     469: iload_1
     470: iconst_1
     471: isub
     472: if_icmpne     497
     475: iload_3
     476: iload         6
     478: if_icmpne     497
     481: aload_0
     482: getfield      #7                  // Field anIntArrayArray294:[[I
     485: iload_2
     486: aaload
     487: iload_3
     488: iaload
     489: ldc           #22                 // int 19398920
     491: iand
     492: ifne          497
     495: iconst_1
     496: ireturn
     497: iload_2
     498: iload_1
     499: if_icmpne     512
     502: iload_3
     503: iload         6
     505: iconst_1
     506: iadd
     507: if_icmpne     512
     510: iconst_1
     511: ireturn
     512: iload_2
     513: iload_1
     514: iconst_1
     515: iadd
     516: if_icmpne     527
     519: iload_3
     520: iload         6
     522: if_icmpne     527
     525: iconst_1
     526: ireturn
     527: iload_2
     528: iload_1
     529: if_icmpne     744
     532: iload_3
     533: iload         6
     535: iconst_1
     536: isub
     537: if_icmpne     744
     540: aload_0
     541: getfield      #7                  // Field anIntArrayArray294:[[I
     544: iload_2
     545: aaload
     546: iload_3
     547: iaload
     548: ldc           #21                 // int 19398914
     550: iand
     551: ifne          744
     554: iconst_1
     555: ireturn
     556: iload         4
     558: iconst_2
     559: if_icmpne     650
     562: iload_2
     563: iload_1
     564: iconst_1
     565: isub
     566: if_icmpne     591
     569: iload_3
     570: iload         6
     572: if_icmpne     591
     575: aload_0
     576: getfield      #7                  // Field anIntArrayArray294:[[I
     579: iload_2
     580: aaload
     581: iload_3
     582: iaload
     583: ldc           #22                 // int 19398920
     585: iand
     586: ifne          591
     589: iconst_1
     590: ireturn
     591: iload_2
     592: iload_1
     593: if_icmpne     620
     596: iload_3
     597: iload         6
     599: iconst_1
     600: iadd
     601: if_icmpne     620
     604: aload_0
     605: getfield      #7                  // Field anIntArrayArray294:[[I
     608: iload_2
     609: aaload
     610: iload_3
     611: iaload
     612: ldc           #20                 // int 19398944
     614: iand
     615: ifne          620
     618: iconst_1
     619: ireturn
     620: iload_2
     621: iload_1
     622: iconst_1
     623: iadd
     624: if_icmpne     635
     627: iload_3
     628: iload         6
     630: if_icmpne     635
     633: iconst_1
     634: ireturn
     635: iload_2
     636: iload_1
     637: if_icmpne     744
     640: iload_3
     641: iload         6
     643: iconst_1
     644: isub
     645: if_icmpne     744
     648: iconst_1
     649: ireturn
     650: iload         4
     652: iconst_3
     653: if_icmpne     744
     656: iload_2
     657: iload_1
     658: iconst_1
     659: isub
     660: if_icmpne     671
     663: iload_3
     664: iload         6
     666: if_icmpne     671
     669: iconst_1
     670: ireturn
     671: iload_2
     672: iload_1
     673: if_icmpne     700
     676: iload_3
     677: iload         6
     679: iconst_1
     680: iadd
     681: if_icmpne     700
     684: aload_0
     685: getfield      #7                  // Field anIntArrayArray294:[[I
     688: iload_2
     689: aaload
     690: iload_3
     691: iaload
     692: ldc           #20                 // int 19398944
     694: iand
     695: ifne          700
     698: iconst_1
     699: ireturn
     700: iload_2
     701: iload_1
     702: iconst_1
     703: iadd
     704: if_icmpne     729
     707: iload_3
     708: iload         6
     710: if_icmpne     729
     713: aload_0
     714: getfield      #7                  // Field anIntArrayArray294:[[I
     717: iload_2
     718: aaload
     719: iload_3
     720: iaload
     721: ldc           #23                 // int 19399040
     723: iand
     724: ifne          729
     727: iconst_1
     728: ireturn
     729: iload_2
     730: iload_1
     731: if_icmpne     744
     734: iload_3
     735: iload         6
     737: iconst_1
     738: isub
     739: if_icmpne     744
     742: iconst_1
     743: ireturn
     744: iload         5
     746: bipush        9
     748: if_icmpne     867
     751: iload_2
     752: iload_1
     753: if_icmpne     780
     756: iload_3
     757: iload         6
     759: iconst_1
     760: iadd
     761: if_icmpne     780
     764: aload_0
     765: getfield      #7                  // Field anIntArrayArray294:[[I
     768: iload_2
     769: aaload
     770: iload_3
     771: iaload
     772: bipush        32
     774: iand
     775: ifne          780
     778: iconst_1
     779: ireturn
     780: iload_2
     781: iload_1
     782: if_icmpne     808
     785: iload_3
     786: iload         6
     788: iconst_1
     789: isub
     790: if_icmpne     808
     793: aload_0
     794: getfield      #7                  // Field anIntArrayArray294:[[I
     797: iload_2
     798: aaload
     799: iload_3
     800: iaload
     801: iconst_2
     802: iand
     803: ifne          808
     806: iconst_1
     807: ireturn
     808: iload_2
     809: iload_1
     810: iconst_1
     811: isub
     812: if_icmpne     837
     815: iload_3
     816: iload         6
     818: if_icmpne     837
     821: aload_0
     822: getfield      #7                  // Field anIntArrayArray294:[[I
     825: iload_2
     826: aaload
     827: iload_3
     828: iaload
     829: bipush        8
     831: iand
     832: ifne          837
     835: iconst_1
     836: ireturn
     837: iload_2
     838: iload_1
     839: iconst_1
     840: iadd
     841: if_icmpne     867
     844: iload_3
     845: iload         6
     847: if_icmpne     867
     850: aload_0
     851: getfield      #7                  // Field anIntArrayArray294:[[I
     854: iload_2
     855: aaload
     856: iload_3
     857: iaload
     858: sipush        128
     861: iand
     862: ifne          867
     865: iconst_1
     866: ireturn
     867: iconst_0
     868: ireturn

  public boolean method220(int, int, int, int, int, int);
    Code:
       0: iload         6
       2: iload_1
       3: if_icmpne     13
       6: iload_3
       7: iload_2
       8: if_icmpne     13
      11: iconst_1
      12: ireturn
      13: iload         6
      15: aload_0
      16: getfield      #2                  // Field anInt290:I
      19: isub
      20: istore        6
      22: iload_3
      23: aload_0
      24: getfield      #3                  // Field anInt291:I
      27: isub
      28: istore_3
      29: iload_1
      30: aload_0
      31: getfield      #2                  // Field anInt290:I
      34: isub
      35: istore_1
      36: iload_2
      37: aload_0
      38: getfield      #3                  // Field anInt291:I
      41: isub
      42: istore_2
      43: iload         4
      45: bipush        6
      47: if_icmpeq     57
      50: iload         4
      52: bipush        7
      54: if_icmpne     335
      57: iload         4
      59: bipush        7
      61: if_icmpne     72
      64: iload         5
      66: iconst_2
      67: iadd
      68: iconst_3
      69: iand
      70: istore        5
      72: iload         5
      74: ifne          137
      77: iload         6
      79: iload_1
      80: iconst_1
      81: iadd
      82: if_icmpne     108
      85: iload_3
      86: iload_2
      87: if_icmpne     108
      90: aload_0
      91: getfield      #7                  // Field anIntArrayArray294:[[I
      94: iload         6
      96: aaload
      97: iload_3
      98: iaload
      99: sipush        128
     102: iand
     103: ifne          108
     106: iconst_1
     107: ireturn
     108: iload         6
     110: iload_1
     111: if_icmpne     335
     114: iload_3
     115: iload_2
     116: iconst_1
     117: isub
     118: if_icmpne     335
     121: aload_0
     122: getfield      #7                  // Field anIntArrayArray294:[[I
     125: iload         6
     127: aaload
     128: iload_3
     129: iaload
     130: iconst_2
     131: iand
     132: ifne          335
     135: iconst_1
     136: ireturn
     137: iload         5
     139: iconst_1
     140: if_icmpne     202
     143: iload         6
     145: iload_1
     146: iconst_1
     147: isub
     148: if_icmpne     173
     151: iload_3
     152: iload_2
     153: if_icmpne     173
     156: aload_0
     157: getfield      #7                  // Field anIntArrayArray294:[[I
     160: iload         6
     162: aaload
     163: iload_3
     164: iaload
     165: bipush        8
     167: iand
     168: ifne          173
     171: iconst_1
     172: ireturn
     173: iload         6
     175: iload_1
     176: if_icmpne     335
     179: iload_3
     180: iload_2
     181: iconst_1
     182: isub
     183: if_icmpne     335
     186: aload_0
     187: getfield      #7                  // Field anIntArrayArray294:[[I
     190: iload         6
     192: aaload
     193: iload_3
     194: iaload
     195: iconst_2
     196: iand
     197: ifne          335
     200: iconst_1
     201: ireturn
     202: iload         5
     204: iconst_2
     205: if_icmpne     268
     208: iload         6
     210: iload_1
     211: iconst_1
     212: isub
     213: if_icmpne     238
     216: iload_3
     217: iload_2
     218: if_icmpne     238
     221: aload_0
     222: getfield      #7                  // Field anIntArrayArray294:[[I
     225: iload         6
     227: aaload
     228: iload_3
     229: iaload
     230: bipush        8
     232: iand
     233: ifne          238
     236: iconst_1
     237: ireturn
     238: iload         6
     240: iload_1
     241: if_icmpne     335
     244: iload_3
     245: iload_2
     246: iconst_1
     247: iadd
     248: if_icmpne     335
     251: aload_0
     252: getfield      #7                  // Field anIntArrayArray294:[[I
     255: iload         6
     257: aaload
     258: iload_3
     259: iaload
     260: bipush        32
     262: iand
     263: ifne          335
     266: iconst_1
     267: ireturn
     268: iload         5
     270: iconst_3
     271: if_icmpne     335
     274: iload         6
     276: iload_1
     277: iconst_1
     278: iadd
     279: if_icmpne     305
     282: iload_3
     283: iload_2
     284: if_icmpne     305
     287: aload_0
     288: getfield      #7                  // Field anIntArrayArray294:[[I
     291: iload         6
     293: aaload
     294: iload_3
     295: iaload
     296: sipush        128
     299: iand
     300: ifne          305
     303: iconst_1
     304: ireturn
     305: iload         6
     307: iload_1
     308: if_icmpne     335
     311: iload_3
     312: iload_2
     313: iconst_1
     314: iadd
     315: if_icmpne     335
     318: aload_0
     319: getfield      #7                  // Field anIntArrayArray294:[[I
     322: iload         6
     324: aaload
     325: iload_3
     326: iaload
     327: bipush        32
     329: iand
     330: ifne          335
     333: iconst_1
     334: ireturn
     335: iload         4
     337: bipush        8
     339: if_icmpne     462
     342: iload         6
     344: iload_1
     345: if_icmpne     372
     348: iload_3
     349: iload_2
     350: iconst_1
     351: iadd
     352: if_icmpne     372
     355: aload_0
     356: getfield      #7                  // Field anIntArrayArray294:[[I
     359: iload         6
     361: aaload
     362: iload_3
     363: iaload
     364: bipush        32
     366: iand
     367: ifne          372
     370: iconst_1
     371: ireturn
     372: iload         6
     374: iload_1
     375: if_icmpne     401
     378: iload_3
     379: iload_2
     380: iconst_1
     381: isub
     382: if_icmpne     401
     385: aload_0
     386: getfield      #7                  // Field anIntArrayArray294:[[I
     389: iload         6
     391: aaload
     392: iload_3
     393: iaload
     394: iconst_2
     395: iand
     396: ifne          401
     399: iconst_1
     400: ireturn
     401: iload         6
     403: iload_1
     404: iconst_1
     405: isub
     406: if_icmpne     431
     409: iload_3
     410: iload_2
     411: if_icmpne     431
     414: aload_0
     415: getfield      #7                  // Field anIntArrayArray294:[[I
     418: iload         6
     420: aaload
     421: iload_3
     422: iaload
     423: bipush        8
     425: iand
     426: ifne          431
     429: iconst_1
     430: ireturn
     431: iload         6
     433: iload_1
     434: iconst_1
     435: iadd
     436: if_icmpne     462
     439: iload_3
     440: iload_2
     441: if_icmpne     462
     444: aload_0
     445: getfield      #7                  // Field anIntArrayArray294:[[I
     448: iload         6
     450: aaload
     451: iload_3
     452: iaload
     453: sipush        128
     456: iand
     457: ifne          462
     460: iconst_1
     461: ireturn
     462: iconst_0
     463: ireturn

  public boolean method221(int, int, int, int, int, int, int);
    Code:
       0: iload_2
       1: iload         6
       3: iadd
       4: iconst_1
       5: isub
       6: istore        8
       8: iload_1
       9: iload         4
      11: iadd
      12: iconst_1
      13: isub
      14: istore        9
      16: iload_3
      17: iload_2
      18: if_icmplt     42
      21: iload_3
      22: iload         8
      24: if_icmpgt     42
      27: iload         7
      29: iload_1
      30: if_icmplt     42
      33: iload         7
      35: iload         9
      37: if_icmpgt     42
      40: iconst_1
      41: ireturn
      42: iload_3
      43: iload_2
      44: iconst_1
      45: isub
      46: if_icmpne     97
      49: iload         7
      51: iload_1
      52: if_icmplt     97
      55: iload         7
      57: iload         9
      59: if_icmpgt     97
      62: aload_0
      63: getfield      #7                  // Field anIntArrayArray294:[[I
      66: iload_3
      67: aload_0
      68: getfield      #2                  // Field anInt290:I
      71: isub
      72: aaload
      73: iload         7
      75: aload_0
      76: getfield      #3                  // Field anInt291:I
      79: isub
      80: iaload
      81: bipush        8
      83: iand
      84: ifne          97
      87: iload         5
      89: bipush        8
      91: iand
      92: ifne          97
      95: iconst_1
      96: ireturn
      97: iload_3
      98: iload         8
     100: iconst_1
     101: iadd
     102: if_icmpne     153
     105: iload         7
     107: iload_1
     108: if_icmplt     153
     111: iload         7
     113: iload         9
     115: if_icmpgt     153
     118: aload_0
     119: getfield      #7                  // Field anIntArrayArray294:[[I
     122: iload_3
     123: aload_0
     124: getfield      #2                  // Field anInt290:I
     127: isub
     128: aaload
     129: iload         7
     131: aload_0
     132: getfield      #3                  // Field anInt291:I
     135: isub
     136: iaload
     137: sipush        128
     140: iand
     141: ifne          153
     144: iload         5
     146: iconst_2
     147: iand
     148: ifne          153
     151: iconst_1
     152: ireturn
     153: iload         7
     155: iload_1
     156: iconst_1
     157: isub
     158: if_icmpne     203
     161: iload_3
     162: iload_2
     163: if_icmplt     203
     166: iload_3
     167: iload         8
     169: if_icmpgt     203
     172: aload_0
     173: getfield      #7                  // Field anIntArrayArray294:[[I
     176: iload_3
     177: aload_0
     178: getfield      #2                  // Field anInt290:I
     181: isub
     182: aaload
     183: iload         7
     185: aload_0
     186: getfield      #3                  // Field anInt291:I
     189: isub
     190: iaload
     191: iconst_2
     192: iand
     193: ifne          203
     196: iload         5
     198: iconst_4
     199: iand
     200: ifeq          255
     203: iload         7
     205: iload         9
     207: iconst_1
     208: iadd
     209: if_icmpne     259
     212: iload_3
     213: iload_2
     214: if_icmplt     259
     217: iload_3
     218: iload         8
     220: if_icmpgt     259
     223: aload_0
     224: getfield      #7                  // Field anIntArrayArray294:[[I
     227: iload_3
     228: aload_0
     229: getfield      #2                  // Field anInt290:I
     232: isub
     233: aaload
     234: iload         7
     236: aload_0
     237: getfield      #3                  // Field anInt291:I
     240: isub
     241: iaload
     242: bipush        32
     244: iand
     245: ifne          259
     248: iload         5
     250: iconst_1
     251: iand
     252: ifne          259
     255: iconst_1
     256: goto          260
     259: iconst_0
     260: ireturn
}
