Compiled from "Class13.java"
final class Class13 {
  private static final Class32 aClass32_305;

  Class13();
    Code:
       0: aload_0
       1: invokespecial #1                  // Method java/lang/Object."<init>":()V
       4: return

  public static int method225(byte[], int, byte[], int, int);
    Code:
       0: getstatic     #2                  // Field aClass32_305:LClass32;
       3: dup
       4: astore        5
       6: monitorenter
       7: getstatic     #2                  // Field aClass32_305:LClass32;
      10: aload_2
      11: putfield      #3                  // Field Class32.aByteArray563:[B
      14: getstatic     #2                  // Field aClass32_305:LClass32;
      17: iload         4
      19: putfield      #4                  // Field Class32.anInt564:I
      22: getstatic     #2                  // Field aClass32_305:LClass32;
      25: aload_0
      26: putfield      #5                  // Field Class32.aByteArray568:[B
      29: getstatic     #2                  // Field aClass32_305:LClass32;
      32: iconst_0
      33: putfield      #6                  // Field Class32.anInt569:I
      36: getstatic     #2                  // Field aClass32_305:LClass32;
      39: iload_3
      40: putfield      #7                  // Field Class32.anInt565:I
      43: getstatic     #2                  // Field aClass32_305:LClass32;
      46: iload_1
      47: putfield      #8                  // Field Class32.anInt570:I
      50: getstatic     #2                  // Field aClass32_305:LClass32;
      53: iconst_0
      54: putfield      #9                  // Field Class32.anInt577:I
      57: getstatic     #2                  // Field aClass32_305:LClass32;
      60: iconst_0
      61: putfield      #10                 // Field Class32.anInt576:I
      64: getstatic     #2                  // Field aClass32_305:LClass32;
      67: iconst_0
      68: putfield      #11                 // Field Class32.anInt566:I
      71: getstatic     #2                  // Field aClass32_305:LClass32;
      74: iconst_0
      75: putfield      #12                 // Field Class32.anInt567:I
      78: getstatic     #2                  // Field aClass32_305:LClass32;
      81: iconst_0
      82: putfield      #13                 // Field Class32.anInt571:I
      85: getstatic     #2                  // Field aClass32_305:LClass32;
      88: iconst_0
      89: putfield      #14                 // Field Class32.anInt572:I
      92: getstatic     #2                  // Field aClass32_305:LClass32;
      95: iconst_0
      96: putfield      #15                 // Field Class32.anInt579:I
      99: getstatic     #2                  // Field aClass32_305:LClass32;
     102: invokestatic  #16                 // Method method227:(LClass32;)V
     105: iload_1
     106: getstatic     #2                  // Field aClass32_305:LClass32;
     109: getfield      #8                  // Field Class32.anInt570:I
     112: isub
     113: istore_1
     114: iload_1
     115: aload         5
     117: monitorexit
     118: ireturn
     119: astore        6
     121: aload         5
     123: monitorexit
     124: aload         6
     126: athrow
    Exception table:
       from    to  target type
           7   118   119   any
         119   124   119   any

  private static void method226(Class32);
    Code:
       0: aload_0
       1: getfield      #17                 // Field Class32.aByte573:B
       4: istore_1
       5: aload_0
       6: getfield      #18                 // Field Class32.anInt574:I
       9: istore_2
      10: aload_0
      11: getfield      #19                 // Field Class32.anInt584:I
      14: istore_3
      15: aload_0
      16: getfield      #20                 // Field Class32.anInt582:I
      19: istore        4
      21: getstatic     #21                 // Field Class32.anIntArray587:[I
      24: astore        5
      26: aload_0
      27: getfield      #22                 // Field Class32.anInt581:I
      30: istore        6
      32: aload_0
      33: getfield      #5                  // Field Class32.aByteArray568:[B
      36: astore        7
      38: aload_0
      39: getfield      #6                  // Field Class32.anInt569:I
      42: istore        8
      44: aload_0
      45: getfield      #8                  // Field Class32.anInt570:I
      48: istore        9
      50: iload         9
      52: istore        10
      54: aload_0
      55: getfield      #23                 // Field Class32.anInt601:I
      58: iconst_1
      59: iadd
      60: istore        11
      62: iload_2
      63: ifle          122
      66: iload         9
      68: ifne          74
      71: goto          410
      74: iload_2
      75: iconst_1
      76: if_icmpne     82
      79: goto          100
      82: aload         7
      84: iload         8
      86: iload_1
      87: bastore
      88: iinc          2, -1
      91: iinc          8, 1
      94: iinc          9, -1
      97: goto          66
     100: iload         9
     102: ifne          110
     105: iconst_1
     106: istore_2
     107: goto          410
     110: aload         7
     112: iload         8
     114: iload_1
     115: bastore
     116: iinc          8, 1
     119: iinc          9, -1
     122: iconst_1
     123: istore        12
     125: iload         12
     127: ifeq          250
     130: iconst_0
     131: istore        12
     133: iload_3
     134: iload         11
     136: if_icmpne     144
     139: iconst_0
     140: istore_2
     141: goto          410
     144: iload         4
     146: i2b
     147: istore_1
     148: aload         5
     150: iload         6
     152: iaload
     153: istore        6
     155: iload         6
     157: sipush        255
     160: iand
     161: i2b
     162: istore        13
     164: iload         6
     166: bipush        8
     168: ishr
     169: istore        6
     171: iinc          3, 1
     174: iload         13
     176: iload         4
     178: if_icmpeq     213
     181: iload         13
     183: istore        4
     185: iload         9
     187: ifne          195
     190: iconst_1
     191: istore_2
     192: goto          410
     195: aload         7
     197: iload         8
     199: iload_1
     200: bastore
     201: iinc          8, 1
     204: iinc          9, -1
     207: iconst_1
     208: istore        12
     210: goto          125
     213: iload_3
     214: iload         11
     216: if_icmpeq     222
     219: goto          125
     222: iload         9
     224: ifne          232
     227: iconst_1
     228: istore_2
     229: goto          410
     232: aload         7
     234: iload         8
     236: iload_1
     237: bastore
     238: iinc          8, 1
     241: iinc          9, -1
     244: iconst_1
     245: istore        12
     247: goto          125
     250: iconst_2
     251: istore_2
     252: aload         5
     254: iload         6
     256: iaload
     257: istore        6
     259: iload         6
     261: sipush        255
     264: iand
     265: i2b
     266: istore        13
     268: iload         6
     270: bipush        8
     272: ishr
     273: istore        6
     275: iinc          3, 1
     278: iload_3
     279: iload         11
     281: if_icmpeq     407
     284: iload         13
     286: iload         4
     288: if_icmpeq     298
     291: iload         13
     293: istore        4
     295: goto          407
     298: iconst_3
     299: istore_2
     300: aload         5
     302: iload         6
     304: iaload
     305: istore        6
     307: iload         6
     309: sipush        255
     312: iand
     313: i2b
     314: istore        14
     316: iload         6
     318: bipush        8
     320: ishr
     321: istore        6
     323: iinc          3, 1
     326: iload_3
     327: iload         11
     329: if_icmpeq     407
     332: iload         14
     334: iload         4
     336: if_icmpeq     346
     339: iload         14
     341: istore        4
     343: goto          407
     346: aload         5
     348: iload         6
     350: iaload
     351: istore        6
     353: iload         6
     355: sipush        255
     358: iand
     359: i2b
     360: istore        15
     362: iload         6
     364: bipush        8
     366: ishr
     367: istore        6
     369: iinc          3, 1
     372: iload         15
     374: sipush        255
     377: iand
     378: iconst_4
     379: iadd
     380: istore_2
     381: aload         5
     383: iload         6
     385: iaload
     386: istore        6
     388: iload         6
     390: sipush        255
     393: iand
     394: i2b
     395: istore        4
     397: iload         6
     399: bipush        8
     401: ishr
     402: istore        6
     404: iinc          3, 1
     407: goto          62
     410: aload_0
     411: getfield      #13                 // Field Class32.anInt571:I
     414: istore        12
     416: aload_0
     417: dup
     418: getfield      #13                 // Field Class32.anInt571:I
     421: iload         10
     423: iload         9
     425: isub
     426: iadd
     427: putfield      #13                 // Field Class32.anInt571:I
     430: aload_0
     431: getfield      #13                 // Field Class32.anInt571:I
     434: iload         12
     436: if_icmpge     449
     439: aload_0
     440: dup
     441: getfield      #14                 // Field Class32.anInt572:I
     444: iconst_1
     445: iadd
     446: putfield      #14                 // Field Class32.anInt572:I
     449: aload_0
     450: iload_1
     451: putfield      #17                 // Field Class32.aByte573:B
     454: aload_0
     455: iload_2
     456: putfield      #18                 // Field Class32.anInt574:I
     459: aload_0
     460: iload_3
     461: putfield      #19                 // Field Class32.anInt584:I
     464: aload_0
     465: iload         4
     467: putfield      #20                 // Field Class32.anInt582:I
     470: aload         5
     472: putstatic     #21                 // Field Class32.anIntArray587:[I
     475: aload_0
     476: iload         6
     478: putfield      #22                 // Field Class32.anInt581:I
     481: aload_0
     482: aload         7
     484: putfield      #5                  // Field Class32.aByteArray568:[B
     487: aload_0
     488: iload         8
     490: putfield      #6                  // Field Class32.anInt569:I
     493: aload_0
     494: iload         9
     496: putfield      #8                  // Field Class32.anInt570:I
     499: return

  private static void method227(Class32);
    Code:
       0: iconst_0
       1: istore_1
       2: aconst_null
       3: astore_2
       4: aconst_null
       5: astore_3
       6: aconst_null
       7: astore        4
       9: aload_0
      10: iconst_1
      11: putfield      #24                 // Field Class32.anInt578:I
      14: getstatic     #21                 // Field Class32.anIntArray587:[I
      17: ifnonnull     32
      20: aload_0
      21: getfield      #24                 // Field Class32.anInt578:I
      24: ldc           #25                 // int 100000
      26: imul
      27: newarray       int
      29: putstatic     #21                 // Field Class32.anIntArray587:[I
      32: iconst_1
      33: istore        5
      35: iload         5
      37: ifeq          2074
      40: aload_0
      41: invokestatic  #26                 // Method method228:(LClass32;)B
      44: istore        6
      46: iload         6
      48: bipush        23
      50: if_icmpne     54
      53: return
      54: aload_0
      55: invokestatic  #26                 // Method method228:(LClass32;)B
      58: istore        6
      60: aload_0
      61: invokestatic  #26                 // Method method228:(LClass32;)B
      64: istore        6
      66: aload_0
      67: invokestatic  #26                 // Method method228:(LClass32;)B
      70: istore        6
      72: aload_0
      73: invokestatic  #26                 // Method method228:(LClass32;)B
      76: istore        6
      78: aload_0
      79: invokestatic  #26                 // Method method228:(LClass32;)B
      82: istore        6
      84: aload_0
      85: dup
      86: getfield      #15                 // Field Class32.anInt579:I
      89: iconst_1
      90: iadd
      91: putfield      #15                 // Field Class32.anInt579:I
      94: aload_0
      95: invokestatic  #26                 // Method method228:(LClass32;)B
      98: istore        6
     100: aload_0
     101: invokestatic  #26                 // Method method228:(LClass32;)B
     104: istore        6
     106: aload_0
     107: invokestatic  #26                 // Method method228:(LClass32;)B
     110: istore        6
     112: aload_0
     113: invokestatic  #26                 // Method method228:(LClass32;)B
     116: istore        6
     118: aload_0
     119: invokestatic  #27                 // Method method229:(LClass32;)B
     122: istore        6
     124: aload_0
     125: iload         6
     127: ifeq          134
     130: iconst_1
     131: goto          135
     134: iconst_0
     135: putfield      #28                 // Field Class32.aBoolean575:Z
     138: aload_0
     139: getfield      #28                 // Field Class32.aBoolean575:Z
     142: ifeq          153
     145: getstatic     #29                 // Field java/lang/System.out:Ljava/io/PrintStream;
     148: ldc           #30                 // String PANIC! RANDOMISED BLOCK!
     150: invokevirtual #31                 // Method java/io/PrintStream.println:(Ljava/lang/String;)V
     153: aload_0
     154: iconst_0
     155: putfield      #32                 // Field Class32.anInt580:I
     158: aload_0
     159: invokestatic  #26                 // Method method228:(LClass32;)B
     162: istore        6
     164: aload_0
     165: aload_0
     166: getfield      #32                 // Field Class32.anInt580:I
     169: bipush        8
     171: ishl
     172: iload         6
     174: sipush        255
     177: iand
     178: ior
     179: putfield      #32                 // Field Class32.anInt580:I
     182: aload_0
     183: invokestatic  #26                 // Method method228:(LClass32;)B
     186: istore        6
     188: aload_0
     189: aload_0
     190: getfield      #32                 // Field Class32.anInt580:I
     193: bipush        8
     195: ishl
     196: iload         6
     198: sipush        255
     201: iand
     202: ior
     203: putfield      #32                 // Field Class32.anInt580:I
     206: aload_0
     207: invokestatic  #26                 // Method method228:(LClass32;)B
     210: istore        6
     212: aload_0
     213: aload_0
     214: getfield      #32                 // Field Class32.anInt580:I
     217: bipush        8
     219: ishl
     220: iload         6
     222: sipush        255
     225: iand
     226: ior
     227: putfield      #32                 // Field Class32.anInt580:I
     230: iconst_0
     231: istore        7
     233: iload         7
     235: bipush        16
     237: if_icmpge     270
     240: aload_0
     241: invokestatic  #27                 // Method method229:(LClass32;)B
     244: istore        8
     246: aload_0
     247: getfield      #33                 // Field Class32.aBooleanArray590:[Z
     250: iload         7
     252: iload         8
     254: iconst_1
     255: if_icmpne     262
     258: iconst_1
     259: goto          263
     262: iconst_0
     263: bastore
     264: iinc          7, 1
     267: goto          233
     270: iconst_0
     271: istore        7
     273: iload         7
     275: sipush        256
     278: if_icmpge     295
     281: aload_0
     282: getfield      #34                 // Field Class32.aBooleanArray589:[Z
     285: iload         7
     287: iconst_0
     288: bastore
     289: iinc          7, 1
     292: goto          273
     295: iconst_0
     296: istore        7
     298: iload         7
     300: bipush        16
     302: if_icmpge     363
     305: aload_0
     306: getfield      #33                 // Field Class32.aBooleanArray590:[Z
     309: iload         7
     311: baload
     312: ifeq          357
     315: iconst_0
     316: istore        8
     318: iload         8
     320: bipush        16
     322: if_icmpge     357
     325: aload_0
     326: invokestatic  #27                 // Method method229:(LClass32;)B
     329: istore        9
     331: iload         9
     333: iconst_1
     334: if_icmpne     351
     337: aload_0
     338: getfield      #34                 // Field Class32.aBooleanArray589:[Z
     341: iload         7
     343: bipush        16
     345: imul
     346: iload         8
     348: iadd
     349: iconst_1
     350: bastore
     351: iinc          8, 1
     354: goto          318
     357: iinc          7, 1
     360: goto          298
     363: aload_0
     364: invokestatic  #35                 // Method method231:(LClass32;)V
     367: aload_0
     368: getfield      #36                 // Field Class32.anInt588:I
     371: iconst_2
     372: iadd
     373: istore        7
     375: iconst_3
     376: aload_0
     377: invokestatic  #37                 // Method method230:(ILClass32;)I
     380: istore        8
     382: bipush        15
     384: aload_0
     385: invokestatic  #37                 // Method method230:(ILClass32;)I
     388: istore        9
     390: iconst_0
     391: istore        10
     393: iload         10
     395: iload         9
     397: if_icmpge     439
     400: iconst_0
     401: istore        11
     403: aload_0
     404: invokestatic  #27                 // Method method229:(LClass32;)B
     407: istore        12
     409: iload         12
     411: ifne          417
     414: goto          423
     417: iinc          11, 1
     420: goto          403
     423: aload_0
     424: getfield      #38                 // Field Class32.aByteArray595:[B
     427: iload         10
     429: iload         11
     431: i2b
     432: bastore
     433: iinc          10, 1
     436: goto          393
     439: bipush        6
     441: newarray       byte
     443: astore        10
     445: iconst_0
     446: istore        11
     448: iload         11
     450: iload         8
     452: if_icmpge     472
     455: aload         10
     457: iload         11
     459: iload         11
     461: bastore
     462: iload         11
     464: iconst_1
     465: iadd
     466: i2b
     467: istore        11
     469: goto          448
     472: iconst_0
     473: istore        11
     475: iload         11
     477: iload         9
     479: if_icmpge     546
     482: aload_0
     483: getfield      #38                 // Field Class32.aByteArray595:[B
     486: iload         11
     488: baload
     489: istore        12
     491: aload         10
     493: iload         12
     495: baload
     496: istore        13
     498: iload         12
     500: ifle          525
     503: aload         10
     505: iload         12
     507: aload         10
     509: iload         12
     511: iconst_1
     512: isub
     513: baload
     514: bastore
     515: iload         12
     517: iconst_1
     518: isub
     519: i2b
     520: istore        12
     522: goto          498
     525: aload         10
     527: iconst_0
     528: iload         13
     530: bastore
     531: aload_0
     532: getfield      #39                 // Field Class32.aByteArray594:[B
     535: iload         11
     537: iload         13
     539: bastore
     540: iinc          11, 1
     543: goto          475
     546: iconst_0
     547: istore        11
     549: iload         11
     551: iload         8
     553: if_icmpge     635
     556: iconst_5
     557: aload_0
     558: invokestatic  #37                 // Method method230:(ILClass32;)I
     561: istore        12
     563: iconst_0
     564: istore        13
     566: iload         13
     568: iload         7
     570: if_icmpge     629
     573: aload_0
     574: invokestatic  #27                 // Method method229:(LClass32;)B
     577: istore        14
     579: iload         14
     581: ifne          587
     584: goto          610
     587: aload_0
     588: invokestatic  #27                 // Method method229:(LClass32;)B
     591: istore        14
     593: iload         14
     595: ifne          604
     598: iinc          12, 1
     601: goto          607
     604: iinc          12, -1
     607: goto          573
     610: aload_0
     611: getfield      #40                 // Field Class32.aByteArrayArray596:[[B
     614: iload         11
     616: aaload
     617: iload         13
     619: iload         12
     621: i2b
     622: bastore
     623: iinc          13, 1
     626: goto          566
     629: iinc          11, 1
     632: goto          549
     635: iconst_0
     636: istore        11
     638: iload         11
     640: iload         8
     642: if_icmpge     774
     645: bipush        32
     647: istore        12
     649: iconst_0
     650: istore        13
     652: iconst_0
     653: istore        14
     655: iload         14
     657: iload         7
     659: if_icmpge     722
     662: aload_0
     663: getfield      #40                 // Field Class32.aByteArrayArray596:[[B
     666: iload         11
     668: aaload
     669: iload         14
     671: baload
     672: iload         13
     674: if_icmple     689
     677: aload_0
     678: getfield      #40                 // Field Class32.aByteArrayArray596:[[B
     681: iload         11
     683: aaload
     684: iload         14
     686: baload
     687: istore        13
     689: aload_0
     690: getfield      #40                 // Field Class32.aByteArrayArray596:[[B
     693: iload         11
     695: aaload
     696: iload         14
     698: baload
     699: iload         12
     701: if_icmpge     716
     704: aload_0
     705: getfield      #40                 // Field Class32.aByteArrayArray596:[[B
     708: iload         11
     710: aaload
     711: iload         14
     713: baload
     714: istore        12
     716: iinc          14, 1
     719: goto          655
     722: aload_0
     723: getfield      #41                 // Field Class32.anIntArrayArray597:[[I
     726: iload         11
     728: aaload
     729: aload_0
     730: getfield      #42                 // Field Class32.anIntArrayArray598:[[I
     733: iload         11
     735: aaload
     736: aload_0
     737: getfield      #43                 // Field Class32.anIntArrayArray599:[[I
     740: iload         11
     742: aaload
     743: aload_0
     744: getfield      #40                 // Field Class32.aByteArrayArray596:[[B
     747: iload         11
     749: aaload
     750: iload         12
     752: iload         13
     754: iload         7
     756: invokestatic  #44                 // Method method232:([I[I[I[BIII)V
     759: aload_0
     760: getfield      #45                 // Field Class32.anIntArray600:[I
     763: iload         11
     765: iload         12
     767: iastore
     768: iinc          11, 1
     771: goto          638
     774: aload_0
     775: getfield      #36                 // Field Class32.anInt588:I
     778: iconst_1
     779: iadd
     780: istore        11
     782: ldc           #25                 // int 100000
     784: aload_0
     785: getfield      #24                 // Field Class32.anInt578:I
     788: imul
     789: istore        12
     791: iconst_m1
     792: istore        13
     794: iconst_0
     795: istore        14
     797: iconst_0
     798: istore        15
     800: iload         15
     802: sipush        255
     805: if_icmpgt     822
     808: aload_0
     809: getfield      #46                 // Field Class32.anIntArray583:[I
     812: iload         15
     814: iconst_0
     815: iastore
     816: iinc          15, 1
     819: goto          800
     822: sipush        4095
     825: istore        15
     827: bipush        15
     829: istore        16
     831: iload         16
     833: iflt          887
     836: bipush        15
     838: istore        17
     840: iload         17
     842: iflt          870
     845: aload_0
     846: getfield      #47                 // Field Class32.aByteArray592:[B
     849: iload         15
     851: iload         16
     853: bipush        16
     855: imul
     856: iload         17
     858: iadd
     859: i2b
     860: bastore
     861: iinc          15, -1
     864: iinc          17, -1
     867: goto          840
     870: aload_0
     871: getfield      #48                 // Field Class32.anIntArray593:[I
     874: iload         16
     876: iload         15
     878: iconst_1
     879: iadd
     880: iastore
     881: iinc          16, -1
     884: goto          831
     887: iconst_0
     888: istore        16
     890: iload         14
     892: ifne          944
     895: iinc          13, 1
     898: bipush        50
     900: istore        14
     902: aload_0
     903: getfield      #39                 // Field Class32.aByteArray594:[B
     906: iload         13
     908: baload
     909: istore        17
     911: aload_0
     912: getfield      #45                 // Field Class32.anIntArray600:[I
     915: iload         17
     917: iaload
     918: istore_1
     919: aload_0
     920: getfield      #41                 // Field Class32.anIntArrayArray597:[[I
     923: iload         17
     925: aaload
     926: astore_2
     927: aload_0
     928: getfield      #43                 // Field Class32.anIntArrayArray599:[[I
     931: iload         17
     933: aaload
     934: astore        4
     936: aload_0
     937: getfield      #42                 // Field Class32.anIntArrayArray598:[[I
     940: iload         17
     942: aaload
     943: astore_3
     944: iinc          14, -1
     947: iload_1
     948: istore        17
     950: iload         17
     952: aload_0
     953: invokestatic  #37                 // Method method230:(ILClass32;)I
     956: istore        18
     958: iload         18
     960: aload_2
     961: iload         17
     963: iaload
     964: if_icmple     988
     967: iinc          17, 1
     970: aload_0
     971: invokestatic  #27                 // Method method229:(LClass32;)B
     974: istore        19
     976: iload         18
     978: iconst_1
     979: ishl
     980: iload         19
     982: ior
     983: istore        18
     985: goto          958
     988: aload         4
     990: iload         18
     992: aload_3
     993: iload         17
     995: iaload
     996: isub
     997: iaload
     998: istore        20
    1000: iload         20
    1002: iload         11
    1004: if_icmpeq     1815
    1007: iload         20
    1009: ifeq          1018
    1012: iload         20
    1014: iconst_1
    1015: if_icmpne     1251
    1018: iconst_m1
    1019: istore        21
    1021: iconst_1
    1022: istore        22
    1024: iload         20
    1026: ifne          1039
    1029: iload         21
    1031: iload         22
    1033: iadd
    1034: istore        21
    1036: goto          1054
    1039: iload         20
    1041: iconst_1
    1042: if_icmpne     1054
    1045: iload         21
    1047: iconst_2
    1048: iload         22
    1050: imul
    1051: iadd
    1052: istore        21
    1054: iload         22
    1056: iconst_2
    1057: imul
    1058: istore        22
    1060: iload         14
    1062: ifne          1114
    1065: iinc          13, 1
    1068: bipush        50
    1070: istore        14
    1072: aload_0
    1073: getfield      #39                 // Field Class32.aByteArray594:[B
    1076: iload         13
    1078: baload
    1079: istore        23
    1081: aload_0
    1082: getfield      #45                 // Field Class32.anIntArray600:[I
    1085: iload         23
    1087: iaload
    1088: istore_1
    1089: aload_0
    1090: getfield      #41                 // Field Class32.anIntArrayArray597:[[I
    1093: iload         23
    1095: aaload
    1096: astore_2
    1097: aload_0
    1098: getfield      #43                 // Field Class32.anIntArrayArray599:[[I
    1101: iload         23
    1103: aaload
    1104: astore        4
    1106: aload_0
    1107: getfield      #42                 // Field Class32.anIntArrayArray598:[[I
    1110: iload         23
    1112: aaload
    1113: astore_3
    1114: iinc          14, -1
    1117: iload_1
    1118: istore        23
    1120: iload         23
    1122: aload_0
    1123: invokestatic  #37                 // Method method230:(ILClass32;)I
    1126: istore        24
    1128: iload         24
    1130: aload_2
    1131: iload         23
    1133: iaload
    1134: if_icmple     1158
    1137: iinc          23, 1
    1140: aload_0
    1141: invokestatic  #27                 // Method method229:(LClass32;)B
    1144: istore        25
    1146: iload         24
    1148: iconst_1
    1149: ishl
    1150: iload         25
    1152: ior
    1153: istore        24
    1155: goto          1128
    1158: aload         4
    1160: iload         24
    1162: aload_3
    1163: iload         23
    1165: iaload
    1166: isub
    1167: iaload
    1168: istore        20
    1170: iload         20
    1172: ifeq          1024
    1175: iload         20
    1177: iconst_1
    1178: if_icmpeq     1024
    1181: iinc          21, 1
    1184: aload_0
    1185: getfield      #49                 // Field Class32.aByteArray591:[B
    1188: aload_0
    1189: getfield      #47                 // Field Class32.aByteArray592:[B
    1192: aload_0
    1193: getfield      #48                 // Field Class32.anIntArray593:[I
    1196: iconst_0
    1197: iaload
    1198: baload
    1199: sipush        255
    1202: iand
    1203: baload
    1204: istore        23
    1206: aload_0
    1207: getfield      #46                 // Field Class32.anIntArray583:[I
    1210: iload         23
    1212: sipush        255
    1215: iand
    1216: dup2
    1217: iaload
    1218: iload         21
    1220: iadd
    1221: iastore
    1222: iload         21
    1224: ifle          1248
    1227: getstatic     #21                 // Field Class32.anIntArray587:[I
    1230: iload         16
    1232: iload         23
    1234: sipush        255
    1237: iand
    1238: iastore
    1239: iinc          16, 1
    1242: iinc          21, -1
    1245: goto          1222
    1248: goto          1000
    1251: iload         20
    1253: iconst_1
    1254: isub
    1255: istore        21
    1257: iload         21
    1259: bipush        16
    1261: if_icmpge     1418
    1264: aload_0
    1265: getfield      #48                 // Field Class32.anIntArray593:[I
    1268: iconst_0
    1269: iaload
    1270: istore        23
    1272: aload_0
    1273: getfield      #47                 // Field Class32.aByteArray592:[B
    1276: iload         23
    1278: iload         21
    1280: iadd
    1281: baload
    1282: istore        22
    1284: iload         21
    1286: iconst_3
    1287: if_icmple     1373
    1290: iload         23
    1292: iload         21
    1294: iadd
    1295: istore        24
    1297: aload_0
    1298: getfield      #47                 // Field Class32.aByteArray592:[B
    1301: iload         24
    1303: aload_0
    1304: getfield      #47                 // Field Class32.aByteArray592:[B
    1307: iload         24
    1309: iconst_1
    1310: isub
    1311: baload
    1312: bastore
    1313: aload_0
    1314: getfield      #47                 // Field Class32.aByteArray592:[B
    1317: iload         24
    1319: iconst_1
    1320: isub
    1321: aload_0
    1322: getfield      #47                 // Field Class32.aByteArray592:[B
    1325: iload         24
    1327: iconst_2
    1328: isub
    1329: baload
    1330: bastore
    1331: aload_0
    1332: getfield      #47                 // Field Class32.aByteArray592:[B
    1335: iload         24
    1337: iconst_2
    1338: isub
    1339: aload_0
    1340: getfield      #47                 // Field Class32.aByteArray592:[B
    1343: iload         24
    1345: iconst_3
    1346: isub
    1347: baload
    1348: bastore
    1349: aload_0
    1350: getfield      #47                 // Field Class32.aByteArray592:[B
    1353: iload         24
    1355: iconst_3
    1356: isub
    1357: aload_0
    1358: getfield      #47                 // Field Class32.aByteArray592:[B
    1361: iload         24
    1363: iconst_4
    1364: isub
    1365: baload
    1366: bastore
    1367: iinc          21, -4
    1370: goto          1284
    1373: iload         21
    1375: ifle          1406
    1378: aload_0
    1379: getfield      #47                 // Field Class32.aByteArray592:[B
    1382: iload         23
    1384: iload         21
    1386: iadd
    1387: aload_0
    1388: getfield      #47                 // Field Class32.aByteArray592:[B
    1391: iload         23
    1393: iload         21
    1395: iadd
    1396: iconst_1
    1397: isub
    1398: baload
    1399: bastore
    1400: iinc          21, -1
    1403: goto          1373
    1406: aload_0
    1407: getfield      #47                 // Field Class32.aByteArray592:[B
    1410: iload         23
    1412: iload         22
    1414: bastore
    1415: goto          1654
    1418: iload         21
    1420: bipush        16
    1422: idiv
    1423: istore        23
    1425: iload         21
    1427: bipush        16
    1429: irem
    1430: istore        24
    1432: aload_0
    1433: getfield      #48                 // Field Class32.anIntArray593:[I
    1436: iload         23
    1438: iaload
    1439: iload         24
    1441: iadd
    1442: istore        25
    1444: aload_0
    1445: getfield      #47                 // Field Class32.aByteArray592:[B
    1448: iload         25
    1450: baload
    1451: istore        22
    1453: iload         25
    1455: aload_0
    1456: getfield      #48                 // Field Class32.anIntArray593:[I
    1459: iload         23
    1461: iaload
    1462: if_icmple     1487
    1465: aload_0
    1466: getfield      #47                 // Field Class32.aByteArray592:[B
    1469: iload         25
    1471: aload_0
    1472: getfield      #47                 // Field Class32.aByteArray592:[B
    1475: iload         25
    1477: iconst_1
    1478: isub
    1479: baload
    1480: bastore
    1481: iinc          25, -1
    1484: goto          1453
    1487: aload_0
    1488: getfield      #48                 // Field Class32.anIntArray593:[I
    1491: iload         23
    1493: dup2
    1494: iaload
    1495: iconst_1
    1496: iadd
    1497: iastore
    1498: iload         23
    1500: ifle          1551
    1503: aload_0
    1504: getfield      #48                 // Field Class32.anIntArray593:[I
    1507: iload         23
    1509: dup2
    1510: iaload
    1511: iconst_1
    1512: isub
    1513: iastore
    1514: aload_0
    1515: getfield      #47                 // Field Class32.aByteArray592:[B
    1518: aload_0
    1519: getfield      #48                 // Field Class32.anIntArray593:[I
    1522: iload         23
    1524: iaload
    1525: aload_0
    1526: getfield      #47                 // Field Class32.aByteArray592:[B
    1529: aload_0
    1530: getfield      #48                 // Field Class32.anIntArray593:[I
    1533: iload         23
    1535: iconst_1
    1536: isub
    1537: iaload
    1538: bipush        16
    1540: iadd
    1541: iconst_1
    1542: isub
    1543: baload
    1544: bastore
    1545: iinc          23, -1
    1548: goto          1498
    1551: aload_0
    1552: getfield      #48                 // Field Class32.anIntArray593:[I
    1555: iconst_0
    1556: dup2
    1557: iaload
    1558: iconst_1
    1559: isub
    1560: iastore
    1561: aload_0
    1562: getfield      #47                 // Field Class32.aByteArray592:[B
    1565: aload_0
    1566: getfield      #48                 // Field Class32.anIntArray593:[I
    1569: iconst_0
    1570: iaload
    1571: iload         22
    1573: bastore
    1574: aload_0
    1575: getfield      #48                 // Field Class32.anIntArray593:[I
    1578: iconst_0
    1579: iaload
    1580: ifne          1654
    1583: sipush        4095
    1586: istore        26
    1588: bipush        15
    1590: istore        27
    1592: iload         27
    1594: iflt          1654
    1597: bipush        15
    1599: istore        28
    1601: iload         28
    1603: iflt          1637
    1606: aload_0
    1607: getfield      #47                 // Field Class32.aByteArray592:[B
    1610: iload         26
    1612: aload_0
    1613: getfield      #47                 // Field Class32.aByteArray592:[B
    1616: aload_0
    1617: getfield      #48                 // Field Class32.anIntArray593:[I
    1620: iload         27
    1622: iaload
    1623: iload         28
    1625: iadd
    1626: baload
    1627: bastore
    1628: iinc          26, -1
    1631: iinc          28, -1
    1634: goto          1601
    1637: aload_0
    1638: getfield      #48                 // Field Class32.anIntArray593:[I
    1641: iload         27
    1643: iload         26
    1645: iconst_1
    1646: iadd
    1647: iastore
    1648: iinc          27, -1
    1651: goto          1592
    1654: aload_0
    1655: getfield      #46                 // Field Class32.anIntArray583:[I
    1658: aload_0
    1659: getfield      #49                 // Field Class32.aByteArray591:[B
    1662: iload         22
    1664: sipush        255
    1667: iand
    1668: baload
    1669: sipush        255
    1672: iand
    1673: dup2
    1674: iaload
    1675: iconst_1
    1676: iadd
    1677: iastore
    1678: getstatic     #21                 // Field Class32.anIntArray587:[I
    1681: iload         16
    1683: aload_0
    1684: getfield      #49                 // Field Class32.aByteArray591:[B
    1687: iload         22
    1689: sipush        255
    1692: iand
    1693: baload
    1694: sipush        255
    1697: iand
    1698: iastore
    1699: iinc          16, 1
    1702: iload         14
    1704: ifne          1756
    1707: iinc          13, 1
    1710: bipush        50
    1712: istore        14
    1714: aload_0
    1715: getfield      #39                 // Field Class32.aByteArray594:[B
    1718: iload         13
    1720: baload
    1721: istore        23
    1723: aload_0
    1724: getfield      #45                 // Field Class32.anIntArray600:[I
    1727: iload         23
    1729: iaload
    1730: istore_1
    1731: aload_0
    1732: getfield      #41                 // Field Class32.anIntArrayArray597:[[I
    1735: iload         23
    1737: aaload
    1738: astore_2
    1739: aload_0
    1740: getfield      #43                 // Field Class32.anIntArrayArray599:[[I
    1743: iload         23
    1745: aaload
    1746: astore        4
    1748: aload_0
    1749: getfield      #42                 // Field Class32.anIntArrayArray598:[[I
    1752: iload         23
    1754: aaload
    1755: astore_3
    1756: iinc          14, -1
    1759: iload_1
    1760: istore        23
    1762: iload         23
    1764: aload_0
    1765: invokestatic  #37                 // Method method230:(ILClass32;)I
    1768: istore        24
    1770: iload         24
    1772: aload_2
    1773: iload         23
    1775: iaload
    1776: if_icmple     1800
    1779: iinc          23, 1
    1782: aload_0
    1783: invokestatic  #27                 // Method method229:(LClass32;)B
    1786: istore        25
    1788: iload         24
    1790: iconst_1
    1791: ishl
    1792: iload         25
    1794: ior
    1795: istore        24
    1797: goto          1770
    1800: aload         4
    1802: iload         24
    1804: aload_3
    1805: iload         23
    1807: iaload
    1808: isub
    1809: iaload
    1810: istore        20
    1812: goto          1000
    1815: aload_0
    1816: iconst_0
    1817: putfield      #18                 // Field Class32.anInt574:I
    1820: aload_0
    1821: iconst_0
    1822: putfield      #17                 // Field Class32.aByte573:B
    1825: aload_0
    1826: getfield      #50                 // Field Class32.anIntArray585:[I
    1829: iconst_0
    1830: iconst_0
    1831: iastore
    1832: iconst_1
    1833: istore        20
    1835: iload         20
    1837: sipush        256
    1840: if_icmpgt     1865
    1843: aload_0
    1844: getfield      #50                 // Field Class32.anIntArray585:[I
    1847: iload         20
    1849: aload_0
    1850: getfield      #46                 // Field Class32.anIntArray583:[I
    1853: iload         20
    1855: iconst_1
    1856: isub
    1857: iaload
    1858: iastore
    1859: iinc          20, 1
    1862: goto          1835
    1865: iconst_1
    1866: istore        20
    1868: iload         20
    1870: sipush        256
    1873: if_icmpgt     1901
    1876: aload_0
    1877: getfield      #50                 // Field Class32.anIntArray585:[I
    1880: iload         20
    1882: dup2
    1883: iaload
    1884: aload_0
    1885: getfield      #50                 // Field Class32.anIntArray585:[I
    1888: iload         20
    1890: iconst_1
    1891: isub
    1892: iaload
    1893: iadd
    1894: iastore
    1895: iinc          20, 1
    1898: goto          1868
    1901: iconst_0
    1902: istore        20
    1904: iload         20
    1906: iload         16
    1908: if_icmpge     1968
    1911: getstatic     #21                 // Field Class32.anIntArray587:[I
    1914: iload         20
    1916: iaload
    1917: sipush        255
    1920: iand
    1921: i2b
    1922: istore        21
    1924: getstatic     #21                 // Field Class32.anIntArray587:[I
    1927: aload_0
    1928: getfield      #50                 // Field Class32.anIntArray585:[I
    1931: iload         21
    1933: sipush        255
    1936: iand
    1937: iaload
    1938: dup2
    1939: iaload
    1940: iload         20
    1942: bipush        8
    1944: ishl
    1945: ior
    1946: iastore
    1947: aload_0
    1948: getfield      #50                 // Field Class32.anIntArray585:[I
    1951: iload         21
    1953: sipush        255
    1956: iand
    1957: dup2
    1958: iaload
    1959: iconst_1
    1960: iadd
    1961: iastore
    1962: iinc          20, 1
    1965: goto          1904
    1968: aload_0
    1969: getstatic     #21                 // Field Class32.anIntArray587:[I
    1972: aload_0
    1973: getfield      #32                 // Field Class32.anInt580:I
    1976: iaload
    1977: bipush        8
    1979: ishr
    1980: putfield      #22                 // Field Class32.anInt581:I
    1983: aload_0
    1984: iconst_0
    1985: putfield      #19                 // Field Class32.anInt584:I
    1988: aload_0
    1989: getstatic     #21                 // Field Class32.anIntArray587:[I
    1992: aload_0
    1993: getfield      #22                 // Field Class32.anInt581:I
    1996: iaload
    1997: putfield      #22                 // Field Class32.anInt581:I
    2000: aload_0
    2001: aload_0
    2002: getfield      #22                 // Field Class32.anInt581:I
    2005: sipush        255
    2008: iand
    2009: i2b
    2010: putfield      #20                 // Field Class32.anInt582:I
    2013: aload_0
    2014: dup
    2015: getfield      #22                 // Field Class32.anInt581:I
    2018: bipush        8
    2020: ishr
    2021: putfield      #22                 // Field Class32.anInt581:I
    2024: aload_0
    2025: dup
    2026: getfield      #19                 // Field Class32.anInt584:I
    2029: iconst_1
    2030: iadd
    2031: putfield      #19                 // Field Class32.anInt584:I
    2034: aload_0
    2035: iload         16
    2037: putfield      #23                 // Field Class32.anInt601:I
    2040: aload_0
    2041: invokestatic  #51                 // Method method226:(LClass32;)V
    2044: aload_0
    2045: getfield      #19                 // Field Class32.anInt584:I
    2048: aload_0
    2049: getfield      #23                 // Field Class32.anInt601:I
    2052: iconst_1
    2053: iadd
    2054: if_icmpne     2068
    2057: aload_0
    2058: getfield      #18                 // Field Class32.anInt574:I
    2061: ifne          2068
    2064: iconst_1
    2065: goto          2069
    2068: iconst_0
    2069: istore        5
    2071: goto          35
    2074: return

  private static byte method228(Class32);
    Code:
       0: bipush        8
       2: aload_0
       3: invokestatic  #37                 // Method method230:(ILClass32;)I
       6: i2b
       7: ireturn

  private static byte method229(Class32);
    Code:
       0: iconst_1
       1: aload_0
       2: invokestatic  #37                 // Method method230:(ILClass32;)I
       5: i2b
       6: ireturn

  private static int method230(int, Class32);
    Code:
       0: aload_1
       1: getfield      #9                  // Field Class32.anInt577:I
       4: iload_0
       5: if_icmplt     41
       8: aload_1
       9: getfield      #10                 // Field Class32.anInt576:I
      12: aload_1
      13: getfield      #9                  // Field Class32.anInt577:I
      16: iload_0
      17: isub
      18: ishr
      19: iconst_1
      20: iload_0
      21: ishl
      22: iconst_1
      23: isub
      24: iand
      25: istore_3
      26: aload_1
      27: dup
      28: getfield      #9                  // Field Class32.anInt577:I
      31: iload_0
      32: isub
      33: putfield      #9                  // Field Class32.anInt577:I
      36: iload_3
      37: istore_2
      38: goto          127
      41: aload_1
      42: aload_1
      43: getfield      #10                 // Field Class32.anInt576:I
      46: bipush        8
      48: ishl
      49: aload_1
      50: getfield      #3                  // Field Class32.aByteArray563:[B
      53: aload_1
      54: getfield      #4                  // Field Class32.anInt564:I
      57: baload
      58: sipush        255
      61: iand
      62: ior
      63: putfield      #10                 // Field Class32.anInt576:I
      66: aload_1
      67: dup
      68: getfield      #9                  // Field Class32.anInt577:I
      71: bipush        8
      73: iadd
      74: putfield      #9                  // Field Class32.anInt577:I
      77: aload_1
      78: dup
      79: getfield      #4                  // Field Class32.anInt564:I
      82: iconst_1
      83: iadd
      84: putfield      #4                  // Field Class32.anInt564:I
      87: aload_1
      88: dup
      89: getfield      #7                  // Field Class32.anInt565:I
      92: iconst_1
      93: isub
      94: putfield      #7                  // Field Class32.anInt565:I
      97: aload_1
      98: dup
      99: getfield      #11                 // Field Class32.anInt566:I
     102: iconst_1
     103: iadd
     104: putfield      #11                 // Field Class32.anInt566:I
     107: aload_1
     108: getfield      #11                 // Field Class32.anInt566:I
     111: ifne          0
     114: aload_1
     115: dup
     116: getfield      #12                 // Field Class32.anInt567:I
     119: iconst_1
     120: iadd
     121: putfield      #12                 // Field Class32.anInt567:I
     124: goto          0
     127: iload_2
     128: ireturn

  private static void method231(Class32);
    Code:
       0: aload_0
       1: iconst_0
       2: putfield      #36                 // Field Class32.anInt588:I
       5: iconst_0
       6: istore_1
       7: iload_1
       8: sipush        256
      11: if_icmpge     50
      14: aload_0
      15: getfield      #34                 // Field Class32.aBooleanArray589:[Z
      18: iload_1
      19: baload
      20: ifeq          44
      23: aload_0
      24: getfield      #49                 // Field Class32.aByteArray591:[B
      27: aload_0
      28: getfield      #36                 // Field Class32.anInt588:I
      31: iload_1
      32: i2b
      33: bastore
      34: aload_0
      35: dup
      36: getfield      #36                 // Field Class32.anInt588:I
      39: iconst_1
      40: iadd
      41: putfield      #36                 // Field Class32.anInt588:I
      44: iinc          1, 1
      47: goto          7
      50: return

  private static void method232(int[], int[], int[], byte[], int, int, int);
    Code:
       0: iconst_0
       1: istore        7
       3: iload         4
       5: istore        8
       7: iload         8
       9: iload         5
      11: if_icmpgt     54
      14: iconst_0
      15: istore        9
      17: iload         9
      19: iload         6
      21: if_icmpge     48
      24: aload_3
      25: iload         9
      27: baload
      28: iload         8
      30: if_icmpne     42
      33: aload_2
      34: iload         7
      36: iload         9
      38: iastore
      39: iinc          7, 1
      42: iinc          9, 1
      45: goto          17
      48: iinc          8, 1
      51: goto          7
      54: iconst_0
      55: istore        8
      57: iload         8
      59: bipush        23
      61: if_icmpge     75
      64: aload_1
      65: iload         8
      67: iconst_0
      68: iastore
      69: iinc          8, 1
      72: goto          57
      75: iconst_0
      76: istore        8
      78: iload         8
      80: iload         6
      82: if_icmpge     103
      85: aload_1
      86: aload_3
      87: iload         8
      89: baload
      90: iconst_1
      91: iadd
      92: dup2
      93: iaload
      94: iconst_1
      95: iadd
      96: iastore
      97: iinc          8, 1
     100: goto          78
     103: iconst_1
     104: istore        8
     106: iload         8
     108: bipush        23
     110: if_icmpge     132
     113: aload_1
     114: iload         8
     116: dup2
     117: iaload
     118: aload_1
     119: iload         8
     121: iconst_1
     122: isub
     123: iaload
     124: iadd
     125: iastore
     126: iinc          8, 1
     129: goto          106
     132: iconst_0
     133: istore        8
     135: iload         8
     137: bipush        23
     139: if_icmpge     153
     142: aload_0
     143: iload         8
     145: iconst_0
     146: iastore
     147: iinc          8, 1
     150: goto          135
     153: iconst_0
     154: istore        8
     156: iload         4
     158: istore        9
     160: iload         9
     162: iload         5
     164: if_icmpgt     203
     167: iload         8
     169: aload_1
     170: iload         9
     172: iconst_1
     173: iadd
     174: iaload
     175: aload_1
     176: iload         9
     178: iaload
     179: isub
     180: iadd
     181: istore        8
     183: aload_0
     184: iload         9
     186: iload         8
     188: iconst_1
     189: isub
     190: iastore
     191: iload         8
     193: iconst_1
     194: ishl
     195: istore        8
     197: iinc          9, 1
     200: goto          160
     203: iload         4
     205: iconst_1
     206: iadd
     207: istore        9
     209: iload         9
     211: iload         5
     213: if_icmpgt     241
     216: aload_1
     217: iload         9
     219: aload_0
     220: iload         9
     222: iconst_1
     223: isub
     224: iaload
     225: iconst_1
     226: iadd
     227: iconst_1
     228: ishl
     229: aload_1
     230: iload         9
     232: iaload
     233: isub
     234: iastore
     235: iinc          9, 1
     238: goto          209
     241: return

  static {};
    Code:
       0: new           #52                 // class Class32
       3: dup
       4: invokespecial #53                 // Method Class32."<init>":()V
       7: putstatic     #2                  // Field aClass32_305:LClass32;
      10: return
}
