Compiled from "Class43.java"
final class Class43 {
  final int anInt716;

  final int anInt717;

  final int anInt718;

  final int anInt719;

  final int anInt720;

  boolean aBoolean721;

  final int anInt722;

  public Class43(int, int, int, int, int, int, boolean);
    Code:
       0: aload_0
       1: invokespecial #1                  // Method java/lang/Object."<init>":()V
       4: aload_0
       5: iconst_1
       6: putfield      #2                  // Field aBoolean721:Z
       9: aload_0
      10: iload_1
      11: putfield      #3                  // Field anInt716:I
      14: aload_0
      15: iload_2
      16: putfield      #4                  // Field anInt717:I
      19: aload_0
      20: iload_3
      21: putfield      #5                  // Field anInt718:I
      24: aload_0
      25: iload         4
      27: putfield      #6                  // Field anInt719:I
      30: aload_0
      31: iload         5
      33: putfield      #7                  // Field anInt720:I
      36: aload_0
      37: iload         6
      39: putfield      #8                  // Field anInt722:I
      42: aload_0
      43: iload         7
      45: putfield      #2                  // Field aBoolean721:Z
      48: return
}
