Compiled from "Class40.java"
final class Class40 {
  final int[] anIntArray673;

  final int[] anIntArray674;

  final int[] anIntArray675;

  final int[] anIntArray676;

  final int[] anIntArray677;

  final int[] anIntArray678;

  final int[] anIntArray679;

  final int[] anIntArray680;

  final int[] anIntArray681;

  int[] anIntArray682;

  final boolean aBoolean683;

  final int anInt684;

  final int anInt685;

  final int anInt686;

  final int anInt687;

  static final int[] anIntArray688;

  static final int[] anIntArray689;

  static final int[] anIntArray690;

  static final int[] anIntArray691;

  static final int[] anIntArray692;

  static final int[] anIntArray693;

  static final int[] anIntArray694;

  static final int[] anIntArray695;

  private static final int[][] anIntArrayArray696;

  private static final int[][] anIntArrayArray697;

  public Class40(int, int, int, int, int, int, int, int, int, int, int, int, int, int, int, int, int, int, int);
    Code:
       0: aload_0
       1: invokespecial #1                  // Method java/lang/Object."<init>":()V
       4: aload_0
       5: iload         13
       7: iload         12
       9: if_icmpne     30
      12: iload         13
      14: iload         4
      16: if_icmpne     30
      19: iload         13
      21: iload         11
      23: if_icmpne     30
      26: iconst_1
      27: goto          31
      30: iconst_0
      31: putfield      #2                  // Field aBoolean683:Z
      34: aload_0
      35: iload         14
      37: putfield      #3                  // Field anInt684:I
      40: aload_0
      41: iload         7
      43: putfield      #4                  // Field anInt685:I
      46: aload_0
      47: iload         9
      49: putfield      #5                  // Field anInt686:I
      52: aload_0
      53: iload         19
      55: putfield      #6                  // Field anInt687:I
      58: sipush        128
      61: istore        20
      63: iload         20
      65: iconst_2
      66: idiv
      67: istore        21
      69: iload         20
      71: iconst_4
      72: idiv
      73: istore        22
      75: iload         20
      77: iconst_3
      78: imul
      79: iconst_4
      80: idiv
      81: istore        23
      83: getstatic     #7                  // Field anIntArrayArray696:[[I
      86: iload         14
      88: aaload
      89: astore        24
      91: aload         24
      93: arraylength
      94: istore        25
      96: aload_0
      97: iload         25
      99: newarray       int
     101: putfield      #8                  // Field anIntArray673:[I
     104: aload_0
     105: iload         25
     107: newarray       int
     109: putfield      #9                  // Field anIntArray674:[I
     112: aload_0
     113: iload         25
     115: newarray       int
     117: putfield      #10                 // Field anIntArray675:[I
     120: iload         25
     122: newarray       int
     124: astore        26
     126: iload         25
     128: newarray       int
     130: astore        27
     132: iload         18
     134: iload         20
     136: imul
     137: istore        28
     139: iload_1
     140: iload         20
     142: imul
     143: istore        29
     145: iconst_0
     146: istore        30
     148: iload         30
     150: iload         25
     152: if_icmpge     949
     155: aload         24
     157: iload         30
     159: iaload
     160: istore        31
     162: iload         31
     164: iconst_1
     165: iand
     166: ifne          193
     169: iload         31
     171: bipush        8
     173: if_icmpgt     193
     176: iload         31
     178: iload         7
     180: isub
     181: iload         7
     183: isub
     184: iconst_1
     185: isub
     186: bipush        7
     188: iand
     189: iconst_1
     190: iadd
     191: istore        31
     193: iload         31
     195: bipush        8
     197: if_icmple     222
     200: iload         31
     202: bipush        12
     204: if_icmpgt     222
     207: iload         31
     209: bipush        9
     211: isub
     212: iload         7
     214: isub
     215: iconst_3
     216: iand
     217: bipush        9
     219: iadd
     220: istore        31
     222: iload         31
     224: bipush        12
     226: if_icmple     251
     229: iload         31
     231: bipush        16
     233: if_icmpgt     251
     236: iload         31
     238: bipush        13
     240: isub
     241: iload         7
     243: isub
     244: iconst_3
     245: iand
     246: bipush        13
     248: iadd
     249: istore        31
     251: iload         31
     253: iconst_1
     254: if_icmpne     279
     257: iload         28
     259: istore        32
     261: iload         29
     263: istore        33
     265: iload         13
     267: istore        34
     269: iload         8
     271: istore        35
     273: iload_2
     274: istore        36
     276: goto          902
     279: iload         31
     281: iconst_2
     282: if_icmpne     325
     285: iload         28
     287: iload         21
     289: iadd
     290: istore        32
     292: iload         29
     294: istore        33
     296: iload         13
     298: iload         12
     300: iadd
     301: iconst_1
     302: ishr
     303: istore        34
     305: iload         8
     307: iload         17
     309: iadd
     310: iconst_1
     311: ishr
     312: istore        35
     314: iload_2
     315: iload         16
     317: iadd
     318: iconst_1
     319: ishr
     320: istore        36
     322: goto          902
     325: iload         31
     327: iconst_3
     328: if_icmpne     357
     331: iload         28
     333: iload         20
     335: iadd
     336: istore        32
     338: iload         29
     340: istore        33
     342: iload         12
     344: istore        34
     346: iload         17
     348: istore        35
     350: iload         16
     352: istore        36
     354: goto          902
     357: iload         31
     359: iconst_4
     360: if_icmpne     407
     363: iload         28
     365: iload         20
     367: iadd
     368: istore        32
     370: iload         29
     372: iload         21
     374: iadd
     375: istore        33
     377: iload         12
     379: iload         4
     381: iadd
     382: iconst_1
     383: ishr
     384: istore        34
     386: iload         17
     388: iload         10
     390: iadd
     391: iconst_1
     392: ishr
     393: istore        35
     395: iload         16
     397: iload         6
     399: iadd
     400: iconst_1
     401: ishr
     402: istore        36
     404: goto          902
     407: iload         31
     409: iconst_5
     410: if_icmpne     442
     413: iload         28
     415: iload         20
     417: iadd
     418: istore        32
     420: iload         29
     422: iload         20
     424: iadd
     425: istore        33
     427: iload         4
     429: istore        34
     431: iload         10
     433: istore        35
     435: iload         6
     437: istore        36
     439: goto          902
     442: iload         31
     444: bipush        6
     446: if_icmpne     492
     449: iload         28
     451: iload         21
     453: iadd
     454: istore        32
     456: iload         29
     458: iload         20
     460: iadd
     461: istore        33
     463: iload         4
     465: iload         11
     467: iadd
     468: iconst_1
     469: ishr
     470: istore        34
     472: iload         10
     474: iload_3
     475: iadd
     476: iconst_1
     477: ishr
     478: istore        35
     480: iload         6
     482: iload         15
     484: iadd
     485: iconst_1
     486: ishr
     487: istore        36
     489: goto          902
     492: iload         31
     494: bipush        7
     496: if_icmpne     524
     499: iload         28
     501: istore        32
     503: iload         29
     505: iload         20
     507: iadd
     508: istore        33
     510: iload         11
     512: istore        34
     514: iload_3
     515: istore        35
     517: iload         15
     519: istore        36
     521: goto          902
     524: iload         31
     526: bipush        8
     528: if_icmpne     570
     531: iload         28
     533: istore        32
     535: iload         29
     537: iload         21
     539: iadd
     540: istore        33
     542: iload         11
     544: iload         13
     546: iadd
     547: iconst_1
     548: ishr
     549: istore        34
     551: iload_3
     552: iload         8
     554: iadd
     555: iconst_1
     556: ishr
     557: istore        35
     559: iload         15
     561: iload_2
     562: iadd
     563: iconst_1
     564: ishr
     565: istore        36
     567: goto          902
     570: iload         31
     572: bipush        9
     574: if_icmpne     620
     577: iload         28
     579: iload         21
     581: iadd
     582: istore        32
     584: iload         29
     586: iload         22
     588: iadd
     589: istore        33
     591: iload         13
     593: iload         12
     595: iadd
     596: iconst_1
     597: ishr
     598: istore        34
     600: iload         8
     602: iload         17
     604: iadd
     605: iconst_1
     606: ishr
     607: istore        35
     609: iload_2
     610: iload         16
     612: iadd
     613: iconst_1
     614: ishr
     615: istore        36
     617: goto          902
     620: iload         31
     622: bipush        10
     624: if_icmpne     671
     627: iload         28
     629: iload         23
     631: iadd
     632: istore        32
     634: iload         29
     636: iload         21
     638: iadd
     639: istore        33
     641: iload         12
     643: iload         4
     645: iadd
     646: iconst_1
     647: ishr
     648: istore        34
     650: iload         17
     652: iload         10
     654: iadd
     655: iconst_1
     656: ishr
     657: istore        35
     659: iload         16
     661: iload         6
     663: iadd
     664: iconst_1
     665: ishr
     666: istore        36
     668: goto          902
     671: iload         31
     673: bipush        11
     675: if_icmpne     721
     678: iload         28
     680: iload         21
     682: iadd
     683: istore        32
     685: iload         29
     687: iload         23
     689: iadd
     690: istore        33
     692: iload         4
     694: iload         11
     696: iadd
     697: iconst_1
     698: ishr
     699: istore        34
     701: iload         10
     703: iload_3
     704: iadd
     705: iconst_1
     706: ishr
     707: istore        35
     709: iload         6
     711: iload         15
     713: iadd
     714: iconst_1
     715: ishr
     716: istore        36
     718: goto          902
     721: iload         31
     723: bipush        12
     725: if_icmpne     770
     728: iload         28
     730: iload         22
     732: iadd
     733: istore        32
     735: iload         29
     737: iload         21
     739: iadd
     740: istore        33
     742: iload         11
     744: iload         13
     746: iadd
     747: iconst_1
     748: ishr
     749: istore        34
     751: iload_3
     752: iload         8
     754: iadd
     755: iconst_1
     756: ishr
     757: istore        35
     759: iload         15
     761: iload_2
     762: iadd
     763: iconst_1
     764: ishr
     765: istore        36
     767: goto          902
     770: iload         31
     772: bipush        13
     774: if_icmpne     805
     777: iload         28
     779: iload         22
     781: iadd
     782: istore        32
     784: iload         29
     786: iload         22
     788: iadd
     789: istore        33
     791: iload         13
     793: istore        34
     795: iload         8
     797: istore        35
     799: iload_2
     800: istore        36
     802: goto          902
     805: iload         31
     807: bipush        14
     809: if_icmpne     841
     812: iload         28
     814: iload         23
     816: iadd
     817: istore        32
     819: iload         29
     821: iload         22
     823: iadd
     824: istore        33
     826: iload         12
     828: istore        34
     830: iload         17
     832: istore        35
     834: iload         16
     836: istore        36
     838: goto          902
     841: iload         31
     843: bipush        15
     845: if_icmpne     877
     848: iload         28
     850: iload         23
     852: iadd
     853: istore        32
     855: iload         29
     857: iload         23
     859: iadd
     860: istore        33
     862: iload         4
     864: istore        34
     866: iload         10
     868: istore        35
     870: iload         6
     872: istore        36
     874: goto          902
     877: iload         28
     879: iload         22
     881: iadd
     882: istore        32
     884: iload         29
     886: iload         23
     888: iadd
     889: istore        33
     891: iload         11
     893: istore        34
     895: iload_3
     896: istore        35
     898: iload         15
     900: istore        36
     902: aload_0
     903: getfield      #8                  // Field anIntArray673:[I
     906: iload         30
     908: iload         32
     910: iastore
     911: aload_0
     912: getfield      #9                  // Field anIntArray674:[I
     915: iload         30
     917: iload         34
     919: iastore
     920: aload_0
     921: getfield      #10                 // Field anIntArray675:[I
     924: iload         30
     926: iload         33
     928: iastore
     929: aload         26
     931: iload         30
     933: iload         35
     935: iastore
     936: aload         27
     938: iload         30
     940: iload         36
     942: iastore
     943: iinc          30, 1
     946: goto          148
     949: getstatic     #11                 // Field anIntArrayArray697:[[I
     952: iload         14
     954: aaload
     955: astore        30
     957: aload         30
     959: arraylength
     960: iconst_4
     961: idiv
     962: istore        31
     964: aload_0
     965: iload         31
     967: newarray       int
     969: putfield      #12                 // Field anIntArray679:[I
     972: aload_0
     973: iload         31
     975: newarray       int
     977: putfield      #13                 // Field anIntArray680:[I
     980: aload_0
     981: iload         31
     983: newarray       int
     985: putfield      #14                 // Field anIntArray681:[I
     988: aload_0
     989: iload         31
     991: newarray       int
     993: putfield      #15                 // Field anIntArray676:[I
     996: aload_0
     997: iload         31
     999: newarray       int
    1001: putfield      #16                 // Field anIntArray677:[I
    1004: aload_0
    1005: iload         31
    1007: newarray       int
    1009: putfield      #17                 // Field anIntArray678:[I
    1012: iload         5
    1014: iconst_m1
    1015: if_icmpeq     1026
    1018: aload_0
    1019: iload         31
    1021: newarray       int
    1023: putfield      #18                 // Field anIntArray682:[I
    1026: iconst_0
    1027: istore        32
    1029: iconst_0
    1030: istore        33
    1032: iload         33
    1034: iload         31
    1036: if_icmpge     1265
    1039: aload         30
    1041: iload         32
    1043: iaload
    1044: istore        34
    1046: aload         30
    1048: iload         32
    1050: iconst_1
    1051: iadd
    1052: iaload
    1053: istore        35
    1055: aload         30
    1057: iload         32
    1059: iconst_2
    1060: iadd
    1061: iaload
    1062: istore        36
    1064: aload         30
    1066: iload         32
    1068: iconst_3
    1069: iadd
    1070: iaload
    1071: istore        37
    1073: iinc          32, 4
    1076: iload         35
    1078: iconst_4
    1079: if_icmpge     1091
    1082: iload         35
    1084: iload         7
    1086: isub
    1087: iconst_3
    1088: iand
    1089: istore        35
    1091: iload         36
    1093: iconst_4
    1094: if_icmpge     1106
    1097: iload         36
    1099: iload         7
    1101: isub
    1102: iconst_3
    1103: iand
    1104: istore        36
    1106: iload         37
    1108: iconst_4
    1109: if_icmpge     1121
    1112: iload         37
    1114: iload         7
    1116: isub
    1117: iconst_3
    1118: iand
    1119: istore        37
    1121: aload_0
    1122: getfield      #12                 // Field anIntArray679:[I
    1125: iload         33
    1127: iload         35
    1129: iastore
    1130: aload_0
    1131: getfield      #13                 // Field anIntArray680:[I
    1134: iload         33
    1136: iload         36
    1138: iastore
    1139: aload_0
    1140: getfield      #14                 // Field anIntArray681:[I
    1143: iload         33
    1145: iload         37
    1147: iastore
    1148: iload         34
    1150: ifne          1207
    1153: aload_0
    1154: getfield      #15                 // Field anIntArray676:[I
    1157: iload         33
    1159: aload         26
    1161: iload         35
    1163: iaload
    1164: iastore
    1165: aload_0
    1166: getfield      #16                 // Field anIntArray677:[I
    1169: iload         33
    1171: aload         26
    1173: iload         36
    1175: iaload
    1176: iastore
    1177: aload_0
    1178: getfield      #17                 // Field anIntArray678:[I
    1181: iload         33
    1183: aload         26
    1185: iload         37
    1187: iaload
    1188: iastore
    1189: aload_0
    1190: getfield      #18                 // Field anIntArray682:[I
    1193: ifnull        1259
    1196: aload_0
    1197: getfield      #18                 // Field anIntArray682:[I
    1200: iload         33
    1202: iconst_m1
    1203: iastore
    1204: goto          1259
    1207: aload_0
    1208: getfield      #15                 // Field anIntArray676:[I
    1211: iload         33
    1213: aload         27
    1215: iload         35
    1217: iaload
    1218: iastore
    1219: aload_0
    1220: getfield      #16                 // Field anIntArray677:[I
    1223: iload         33
    1225: aload         27
    1227: iload         36
    1229: iaload
    1230: iastore
    1231: aload_0
    1232: getfield      #17                 // Field anIntArray678:[I
    1235: iload         33
    1237: aload         27
    1239: iload         37
    1241: iaload
    1242: iastore
    1243: aload_0
    1244: getfield      #18                 // Field anIntArray682:[I
    1247: ifnull        1259
    1250: aload_0
    1251: getfield      #18                 // Field anIntArray682:[I
    1254: iload         33
    1256: iload         5
    1258: iastore
    1259: iinc          33, 1
    1262: goto          1032
    1265: iload         13
    1267: istore        33
    1269: iload         12
    1271: istore        34
    1273: iload         12
    1275: iload         33
    1277: if_icmpge     1284
    1280: iload         12
    1282: istore        33
    1284: iload         12
    1286: iload         34
    1288: if_icmple     1295
    1291: iload         12
    1293: istore        34
    1295: iload         4
    1297: iload         33
    1299: if_icmpge     1306
    1302: iload         4
    1304: istore        33
    1306: iload         4
    1308: iload         34
    1310: if_icmple     1317
    1313: iload         4
    1315: istore        34
    1317: iload         11
    1319: iload         33
    1321: if_icmpge     1328
    1324: iload         11
    1326: istore        33
    1328: iload         11
    1330: iload         34
    1332: if_icmple     1339
    1335: iload         11
    1337: istore        34
    1339: iload         33
    1341: bipush        14
    1343: idiv
    1344: istore        33
    1346: iload         34
    1348: bipush        14
    1350: idiv
    1351: istore        34
    1353: return

  static {};
    Code:
       0: bipush        6
       2: newarray       int
       4: putstatic     #19                 // Field anIntArray688:[I
       7: bipush        6
       9: newarray       int
      11: putstatic     #20                 // Field anIntArray689:[I
      14: bipush        6
      16: newarray       int
      18: putstatic     #21                 // Field anIntArray690:[I
      21: bipush        6
      23: newarray       int
      25: putstatic     #22                 // Field anIntArray691:[I
      28: bipush        6
      30: newarray       int
      32: putstatic     #23                 // Field anIntArray692:[I
      35: iconst_2
      36: newarray       int
      38: dup
      39: iconst_0
      40: iconst_1
      41: iastore
      42: dup
      43: iconst_1
      44: iconst_0
      45: iastore
      46: putstatic     #24                 // Field anIntArray693:[I
      49: iconst_2
      50: newarray       int
      52: dup
      53: iconst_0
      54: iconst_2
      55: iastore
      56: dup
      57: iconst_1
      58: iconst_1
      59: iastore
      60: putstatic     #25                 // Field anIntArray694:[I
      63: iconst_2
      64: newarray       int
      66: dup
      67: iconst_0
      68: iconst_3
      69: iastore
      70: dup
      71: iconst_1
      72: iconst_3
      73: iastore
      74: putstatic     #26                 // Field anIntArray695:[I
      77: bipush        13
      79: anewarray     #27                 // class "[I"
      82: dup
      83: iconst_0
      84: iconst_4
      85: newarray       int
      87: dup
      88: iconst_0
      89: iconst_1
      90: iastore
      91: dup
      92: iconst_1
      93: iconst_3
      94: iastore
      95: dup
      96: iconst_2
      97: iconst_5
      98: iastore
      99: dup
     100: iconst_3
     101: bipush        7
     103: iastore
     104: aastore
     105: dup
     106: iconst_1
     107: iconst_4
     108: newarray       int
     110: dup
     111: iconst_0
     112: iconst_1
     113: iastore
     114: dup
     115: iconst_1
     116: iconst_3
     117: iastore
     118: dup
     119: iconst_2
     120: iconst_5
     121: iastore
     122: dup
     123: iconst_3
     124: bipush        7
     126: iastore
     127: aastore
     128: dup
     129: iconst_2
     130: iconst_4
     131: newarray       int
     133: dup
     134: iconst_0
     135: iconst_1
     136: iastore
     137: dup
     138: iconst_1
     139: iconst_3
     140: iastore
     141: dup
     142: iconst_2
     143: iconst_5
     144: iastore
     145: dup
     146: iconst_3
     147: bipush        7
     149: iastore
     150: aastore
     151: dup
     152: iconst_3
     153: iconst_5
     154: newarray       int
     156: dup
     157: iconst_0
     158: iconst_1
     159: iastore
     160: dup
     161: iconst_1
     162: iconst_3
     163: iastore
     164: dup
     165: iconst_2
     166: iconst_5
     167: iastore
     168: dup
     169: iconst_3
     170: bipush        7
     172: iastore
     173: dup
     174: iconst_4
     175: bipush        6
     177: iastore
     178: aastore
     179: dup
     180: iconst_4
     181: iconst_5
     182: newarray       int
     184: dup
     185: iconst_0
     186: iconst_1
     187: iastore
     188: dup
     189: iconst_1
     190: iconst_3
     191: iastore
     192: dup
     193: iconst_2
     194: iconst_5
     195: iastore
     196: dup
     197: iconst_3
     198: bipush        7
     200: iastore
     201: dup
     202: iconst_4
     203: bipush        6
     205: iastore
     206: aastore
     207: dup
     208: iconst_5
     209: iconst_5
     210: newarray       int
     212: dup
     213: iconst_0
     214: iconst_1
     215: iastore
     216: dup
     217: iconst_1
     218: iconst_3
     219: iastore
     220: dup
     221: iconst_2
     222: iconst_5
     223: iastore
     224: dup
     225: iconst_3
     226: bipush        7
     228: iastore
     229: dup
     230: iconst_4
     231: bipush        6
     233: iastore
     234: aastore
     235: dup
     236: bipush        6
     238: iconst_5
     239: newarray       int
     241: dup
     242: iconst_0
     243: iconst_1
     244: iastore
     245: dup
     246: iconst_1
     247: iconst_3
     248: iastore
     249: dup
     250: iconst_2
     251: iconst_5
     252: iastore
     253: dup
     254: iconst_3
     255: bipush        7
     257: iastore
     258: dup
     259: iconst_4
     260: bipush        6
     262: iastore
     263: aastore
     264: dup
     265: bipush        7
     267: bipush        6
     269: newarray       int
     271: dup
     272: iconst_0
     273: iconst_1
     274: iastore
     275: dup
     276: iconst_1
     277: iconst_3
     278: iastore
     279: dup
     280: iconst_2
     281: iconst_5
     282: iastore
     283: dup
     284: iconst_3
     285: bipush        7
     287: iastore
     288: dup
     289: iconst_4
     290: iconst_2
     291: iastore
     292: dup
     293: iconst_5
     294: bipush        6
     296: iastore
     297: aastore
     298: dup
     299: bipush        8
     301: bipush        6
     303: newarray       int
     305: dup
     306: iconst_0
     307: iconst_1
     308: iastore
     309: dup
     310: iconst_1
     311: iconst_3
     312: iastore
     313: dup
     314: iconst_2
     315: iconst_5
     316: iastore
     317: dup
     318: iconst_3
     319: bipush        7
     321: iastore
     322: dup
     323: iconst_4
     324: iconst_2
     325: iastore
     326: dup
     327: iconst_5
     328: bipush        8
     330: iastore
     331: aastore
     332: dup
     333: bipush        9
     335: bipush        6
     337: newarray       int
     339: dup
     340: iconst_0
     341: iconst_1
     342: iastore
     343: dup
     344: iconst_1
     345: iconst_3
     346: iastore
     347: dup
     348: iconst_2
     349: iconst_5
     350: iastore
     351: dup
     352: iconst_3
     353: bipush        7
     355: iastore
     356: dup
     357: iconst_4
     358: iconst_2
     359: iastore
     360: dup
     361: iconst_5
     362: bipush        8
     364: iastore
     365: aastore
     366: dup
     367: bipush        10
     369: bipush        6
     371: newarray       int
     373: dup
     374: iconst_0
     375: iconst_1
     376: iastore
     377: dup
     378: iconst_1
     379: iconst_3
     380: iastore
     381: dup
     382: iconst_2
     383: iconst_5
     384: iastore
     385: dup
     386: iconst_3
     387: bipush        7
     389: iastore
     390: dup
     391: iconst_4
     392: bipush        11
     394: iastore
     395: dup
     396: iconst_5
     397: bipush        12
     399: iastore
     400: aastore
     401: dup
     402: bipush        11
     404: bipush        6
     406: newarray       int
     408: dup
     409: iconst_0
     410: iconst_1
     411: iastore
     412: dup
     413: iconst_1
     414: iconst_3
     415: iastore
     416: dup
     417: iconst_2
     418: iconst_5
     419: iastore
     420: dup
     421: iconst_3
     422: bipush        7
     424: iastore
     425: dup
     426: iconst_4
     427: bipush        11
     429: iastore
     430: dup
     431: iconst_5
     432: bipush        12
     434: iastore
     435: aastore
     436: dup
     437: bipush        12
     439: bipush        6
     441: newarray       int
     443: dup
     444: iconst_0
     445: iconst_1
     446: iastore
     447: dup
     448: iconst_1
     449: iconst_3
     450: iastore
     451: dup
     452: iconst_2
     453: iconst_5
     454: iastore
     455: dup
     456: iconst_3
     457: bipush        7
     459: iastore
     460: dup
     461: iconst_4
     462: bipush        13
     464: iastore
     465: dup
     466: iconst_5
     467: bipush        14
     469: iastore
     470: aastore
     471: putstatic     #7                  // Field anIntArrayArray696:[[I
     474: bipush        13
     476: anewarray     #27                 // class "[I"
     479: dup
     480: iconst_0
     481: bipush        8
     483: newarray       int
     485: dup
     486: iconst_0
     487: iconst_0
     488: iastore
     489: dup
     490: iconst_1
     491: iconst_1
     492: iastore
     493: dup
     494: iconst_2
     495: iconst_2
     496: iastore
     497: dup
     498: iconst_3
     499: iconst_3
     500: iastore
     501: dup
     502: iconst_4
     503: iconst_0
     504: iastore
     505: dup
     506: iconst_5
     507: iconst_0
     508: iastore
     509: dup
     510: bipush        6
     512: iconst_1
     513: iastore
     514: dup
     515: bipush        7
     517: iconst_3
     518: iastore
     519: aastore
     520: dup
     521: iconst_1
     522: bipush        8
     524: newarray       int
     526: dup
     527: iconst_0
     528: iconst_1
     529: iastore
     530: dup
     531: iconst_1
     532: iconst_1
     533: iastore
     534: dup
     535: iconst_2
     536: iconst_2
     537: iastore
     538: dup
     539: iconst_3
     540: iconst_3
     541: iastore
     542: dup
     543: iconst_4
     544: iconst_1
     545: iastore
     546: dup
     547: iconst_5
     548: iconst_0
     549: iastore
     550: dup
     551: bipush        6
     553: iconst_1
     554: iastore
     555: dup
     556: bipush        7
     558: iconst_3
     559: iastore
     560: aastore
     561: dup
     562: iconst_2
     563: bipush        8
     565: newarray       int
     567: dup
     568: iconst_0
     569: iconst_0
     570: iastore
     571: dup
     572: iconst_1
     573: iconst_1
     574: iastore
     575: dup
     576: iconst_2
     577: iconst_2
     578: iastore
     579: dup
     580: iconst_3
     581: iconst_3
     582: iastore
     583: dup
     584: iconst_4
     585: iconst_1
     586: iastore
     587: dup
     588: iconst_5
     589: iconst_0
     590: iastore
     591: dup
     592: bipush        6
     594: iconst_1
     595: iastore
     596: dup
     597: bipush        7
     599: iconst_3
     600: iastore
     601: aastore
     602: dup
     603: iconst_3
     604: bipush        12
     606: newarray       int
     608: dup
     609: iconst_0
     610: iconst_0
     611: iastore
     612: dup
     613: iconst_1
     614: iconst_0
     615: iastore
     616: dup
     617: iconst_2
     618: iconst_1
     619: iastore
     620: dup
     621: iconst_3
     622: iconst_2
     623: iastore
     624: dup
     625: iconst_4
     626: iconst_0
     627: iastore
     628: dup
     629: iconst_5
     630: iconst_0
     631: iastore
     632: dup
     633: bipush        6
     635: iconst_2
     636: iastore
     637: dup
     638: bipush        7
     640: iconst_4
     641: iastore
     642: dup
     643: bipush        8
     645: iconst_1
     646: iastore
     647: dup
     648: bipush        9
     650: iconst_0
     651: iastore
     652: dup
     653: bipush        10
     655: iconst_4
     656: iastore
     657: dup
     658: bipush        11
     660: iconst_3
     661: iastore
     662: aastore
     663: dup
     664: iconst_4
     665: bipush        12
     667: newarray       int
     669: dup
     670: iconst_0
     671: iconst_0
     672: iastore
     673: dup
     674: iconst_1
     675: iconst_0
     676: iastore
     677: dup
     678: iconst_2
     679: iconst_1
     680: iastore
     681: dup
     682: iconst_3
     683: iconst_4
     684: iastore
     685: dup
     686: iconst_4
     687: iconst_0
     688: iastore
     689: dup
     690: iconst_5
     691: iconst_0
     692: iastore
     693: dup
     694: bipush        6
     696: iconst_4
     697: iastore
     698: dup
     699: bipush        7
     701: iconst_3
     702: iastore
     703: dup
     704: bipush        8
     706: iconst_1
     707: iastore
     708: dup
     709: bipush        9
     711: iconst_1
     712: iastore
     713: dup
     714: bipush        10
     716: iconst_2
     717: iastore
     718: dup
     719: bipush        11
     721: iconst_4
     722: iastore
     723: aastore
     724: dup
     725: iconst_5
     726: bipush        12
     728: newarray       int
     730: dup
     731: iconst_0
     732: iconst_0
     733: iastore
     734: dup
     735: iconst_1
     736: iconst_0
     737: iastore
     738: dup
     739: iconst_2
     740: iconst_4
     741: iastore
     742: dup
     743: iconst_3
     744: iconst_3
     745: iastore
     746: dup
     747: iconst_4
     748: iconst_1
     749: iastore
     750: dup
     751: iconst_5
     752: iconst_0
     753: iastore
     754: dup
     755: bipush        6
     757: iconst_1
     758: iastore
     759: dup
     760: bipush        7
     762: iconst_2
     763: iastore
     764: dup
     765: bipush        8
     767: iconst_1
     768: iastore
     769: dup
     770: bipush        9
     772: iconst_0
     773: iastore
     774: dup
     775: bipush        10
     777: iconst_2
     778: iastore
     779: dup
     780: bipush        11
     782: iconst_4
     783: iastore
     784: aastore
     785: dup
     786: bipush        6
     788: bipush        12
     790: newarray       int
     792: dup
     793: iconst_0
     794: iconst_0
     795: iastore
     796: dup
     797: iconst_1
     798: iconst_1
     799: iastore
     800: dup
     801: iconst_2
     802: iconst_2
     803: iastore
     804: dup
     805: iconst_3
     806: iconst_4
     807: iastore
     808: dup
     809: iconst_4
     810: iconst_1
     811: iastore
     812: dup
     813: iconst_5
     814: iconst_0
     815: iastore
     816: dup
     817: bipush        6
     819: iconst_1
     820: iastore
     821: dup
     822: bipush        7
     824: iconst_4
     825: iastore
     826: dup
     827: bipush        8
     829: iconst_1
     830: iastore
     831: dup
     832: bipush        9
     834: iconst_0
     835: iastore
     836: dup
     837: bipush        10
     839: iconst_4
     840: iastore
     841: dup
     842: bipush        11
     844: iconst_3
     845: iastore
     846: aastore
     847: dup
     848: bipush        7
     850: bipush        16
     852: newarray       int
     854: dup
     855: iconst_0
     856: iconst_0
     857: iastore
     858: dup
     859: iconst_1
     860: iconst_4
     861: iastore
     862: dup
     863: iconst_2
     864: iconst_1
     865: iastore
     866: dup
     867: iconst_3
     868: iconst_2
     869: iastore
     870: dup
     871: iconst_4
     872: iconst_0
     873: iastore
     874: dup
     875: iconst_5
     876: iconst_4
     877: iastore
     878: dup
     879: bipush        6
     881: iconst_2
     882: iastore
     883: dup
     884: bipush        7
     886: iconst_5
     887: iastore
     888: dup
     889: bipush        8
     891: iconst_1
     892: iastore
     893: dup
     894: bipush        9
     896: iconst_0
     897: iastore
     898: dup
     899: bipush        10
     901: iconst_4
     902: iastore
     903: dup
     904: bipush        11
     906: iconst_5
     907: iastore
     908: dup
     909: bipush        12
     911: iconst_1
     912: iastore
     913: dup
     914: bipush        13
     916: iconst_0
     917: iastore
     918: dup
     919: bipush        14
     921: iconst_5
     922: iastore
     923: dup
     924: bipush        15
     926: iconst_3
     927: iastore
     928: aastore
     929: dup
     930: bipush        8
     932: bipush        16
     934: newarray       int
     936: dup
     937: iconst_0
     938: iconst_0
     939: iastore
     940: dup
     941: iconst_1
     942: iconst_4
     943: iastore
     944: dup
     945: iconst_2
     946: iconst_1
     947: iastore
     948: dup
     949: iconst_3
     950: iconst_2
     951: iastore
     952: dup
     953: iconst_4
     954: iconst_0
     955: iastore
     956: dup
     957: iconst_5
     958: iconst_4
     959: iastore
     960: dup
     961: bipush        6
     963: iconst_2
     964: iastore
     965: dup
     966: bipush        7
     968: iconst_3
     969: iastore
     970: dup
     971: bipush        8
     973: iconst_0
     974: iastore
     975: dup
     976: bipush        9
     978: iconst_4
     979: iastore
     980: dup
     981: bipush        10
     983: iconst_3
     984: iastore
     985: dup
     986: bipush        11
     988: iconst_5
     989: iastore
     990: dup
     991: bipush        12
     993: iconst_1
     994: iastore
     995: dup
     996: bipush        13
     998: iconst_0
     999: iastore
    1000: dup
    1001: bipush        14
    1003: iconst_4
    1004: iastore
    1005: dup
    1006: bipush        15
    1008: iconst_5
    1009: iastore
    1010: aastore
    1011: dup
    1012: bipush        9
    1014: bipush        16
    1016: newarray       int
    1018: dup
    1019: iconst_0
    1020: iconst_0
    1021: iastore
    1022: dup
    1023: iconst_1
    1024: iconst_0
    1025: iastore
    1026: dup
    1027: iconst_2
    1028: iconst_4
    1029: iastore
    1030: dup
    1031: iconst_3
    1032: iconst_5
    1033: iastore
    1034: dup
    1035: iconst_4
    1036: iconst_1
    1037: iastore
    1038: dup
    1039: iconst_5
    1040: iconst_4
    1041: iastore
    1042: dup
    1043: bipush        6
    1045: iconst_1
    1046: iastore
    1047: dup
    1048: bipush        7
    1050: iconst_2
    1051: iastore
    1052: dup
    1053: bipush        8
    1055: iconst_1
    1056: iastore
    1057: dup
    1058: bipush        9
    1060: iconst_4
    1061: iastore
    1062: dup
    1063: bipush        10
    1065: iconst_2
    1066: iastore
    1067: dup
    1068: bipush        11
    1070: iconst_3
    1071: iastore
    1072: dup
    1073: bipush        12
    1075: iconst_1
    1076: iastore
    1077: dup
    1078: bipush        13
    1080: iconst_4
    1081: iastore
    1082: dup
    1083: bipush        14
    1085: iconst_3
    1086: iastore
    1087: dup
    1088: bipush        15
    1090: iconst_5
    1091: iastore
    1092: aastore
    1093: dup
    1094: bipush        10
    1096: bipush        24
    1098: newarray       int
    1100: dup
    1101: iconst_0
    1102: iconst_0
    1103: iastore
    1104: dup
    1105: iconst_1
    1106: iconst_0
    1107: iastore
    1108: dup
    1109: iconst_2
    1110: iconst_1
    1111: iastore
    1112: dup
    1113: iconst_3
    1114: iconst_5
    1115: iastore
    1116: dup
    1117: iconst_4
    1118: iconst_0
    1119: iastore
    1120: dup
    1121: iconst_5
    1122: iconst_1
    1123: iastore
    1124: dup
    1125: bipush        6
    1127: iconst_4
    1128: iastore
    1129: dup
    1130: bipush        7
    1132: iconst_5
    1133: iastore
    1134: dup
    1135: bipush        8
    1137: iconst_0
    1138: iastore
    1139: dup
    1140: bipush        9
    1142: iconst_1
    1143: iastore
    1144: dup
    1145: bipush        10
    1147: iconst_2
    1148: iastore
    1149: dup
    1150: bipush        11
    1152: iconst_4
    1153: iastore
    1154: dup
    1155: bipush        12
    1157: iconst_1
    1158: iastore
    1159: dup
    1160: bipush        13
    1162: iconst_0
    1163: iastore
    1164: dup
    1165: bipush        14
    1167: iconst_5
    1168: iastore
    1169: dup
    1170: bipush        15
    1172: iconst_3
    1173: iastore
    1174: dup
    1175: bipush        16
    1177: iconst_1
    1178: iastore
    1179: dup
    1180: bipush        17
    1182: iconst_5
    1183: iastore
    1184: dup
    1185: bipush        18
    1187: iconst_4
    1188: iastore
    1189: dup
    1190: bipush        19
    1192: iconst_3
    1193: iastore
    1194: dup
    1195: bipush        20
    1197: iconst_1
    1198: iastore
    1199: dup
    1200: bipush        21
    1202: iconst_4
    1203: iastore
    1204: dup
    1205: bipush        22
    1207: iconst_2
    1208: iastore
    1209: dup
    1210: bipush        23
    1212: iconst_3
    1213: iastore
    1214: aastore
    1215: dup
    1216: bipush        11
    1218: bipush        24
    1220: newarray       int
    1222: dup
    1223: iconst_0
    1224: iconst_1
    1225: iastore
    1226: dup
    1227: iconst_1
    1228: iconst_0
    1229: iastore
    1230: dup
    1231: iconst_2
    1232: iconst_1
    1233: iastore
    1234: dup
    1235: iconst_3
    1236: iconst_5
    1237: iastore
    1238: dup
    1239: iconst_4
    1240: iconst_1
    1241: iastore
    1242: dup
    1243: iconst_5
    1244: iconst_1
    1245: iastore
    1246: dup
    1247: bipush        6
    1249: iconst_4
    1250: iastore
    1251: dup
    1252: bipush        7
    1254: iconst_5
    1255: iastore
    1256: dup
    1257: bipush        8
    1259: iconst_1
    1260: iastore
    1261: dup
    1262: bipush        9
    1264: iconst_1
    1265: iastore
    1266: dup
    1267: bipush        10
    1269: iconst_2
    1270: iastore
    1271: dup
    1272: bipush        11
    1274: iconst_4
    1275: iastore
    1276: dup
    1277: bipush        12
    1279: iconst_0
    1280: iastore
    1281: dup
    1282: bipush        13
    1284: iconst_0
    1285: iastore
    1286: dup
    1287: bipush        14
    1289: iconst_5
    1290: iastore
    1291: dup
    1292: bipush        15
    1294: iconst_3
    1295: iastore
    1296: dup
    1297: bipush        16
    1299: iconst_0
    1300: iastore
    1301: dup
    1302: bipush        17
    1304: iconst_5
    1305: iastore
    1306: dup
    1307: bipush        18
    1309: iconst_4
    1310: iastore
    1311: dup
    1312: bipush        19
    1314: iconst_3
    1315: iastore
    1316: dup
    1317: bipush        20
    1319: iconst_0
    1320: iastore
    1321: dup
    1322: bipush        21
    1324: iconst_4
    1325: iastore
    1326: dup
    1327: bipush        22
    1329: iconst_2
    1330: iastore
    1331: dup
    1332: bipush        23
    1334: iconst_3
    1335: iastore
    1336: aastore
    1337: dup
    1338: bipush        12
    1340: bipush        24
    1342: newarray       int
    1344: dup
    1345: iconst_0
    1346: iconst_1
    1347: iastore
    1348: dup
    1349: iconst_1
    1350: iconst_0
    1351: iastore
    1352: dup
    1353: iconst_2
    1354: iconst_5
    1355: iastore
    1356: dup
    1357: iconst_3
    1358: iconst_4
    1359: iastore
    1360: dup
    1361: iconst_4
    1362: iconst_1
    1363: iastore
    1364: dup
    1365: iconst_5
    1366: iconst_0
    1367: iastore
    1368: dup
    1369: bipush        6
    1371: iconst_1
    1372: iastore
    1373: dup
    1374: bipush        7
    1376: iconst_5
    1377: iastore
    1378: dup
    1379: bipush        8
    1381: iconst_0
    1382: iastore
    1383: dup
    1384: bipush        9
    1386: iconst_0
    1387: iastore
    1388: dup
    1389: bipush        10
    1391: iconst_4
    1392: iastore
    1393: dup
    1394: bipush        11
    1396: iconst_3
    1397: iastore
    1398: dup
    1399: bipush        12
    1401: iconst_0
    1402: iastore
    1403: dup
    1404: bipush        13
    1406: iconst_4
    1407: iastore
    1408: dup
    1409: bipush        14
    1411: iconst_5
    1412: iastore
    1413: dup
    1414: bipush        15
    1416: iconst_3
    1417: iastore
    1418: dup
    1419: bipush        16
    1421: iconst_0
    1422: iastore
    1423: dup
    1424: bipush        17
    1426: iconst_5
    1427: iastore
    1428: dup
    1429: bipush        18
    1431: iconst_2
    1432: iastore
    1433: dup
    1434: bipush        19
    1436: iconst_3
    1437: iastore
    1438: dup
    1439: bipush        20
    1441: iconst_0
    1442: iastore
    1443: dup
    1444: bipush        21
    1446: iconst_1
    1447: iastore
    1448: dup
    1449: bipush        22
    1451: iconst_2
    1452: iastore
    1453: dup
    1454: bipush        23
    1456: iconst_5
    1457: iastore
    1458: aastore
    1459: putstatic     #11                 // Field anIntArrayArray697:[[I
    1462: return
}
