Compiled from "IDK.java"
public final class IDK {
  public static int length;

  public static IDK[] cache;

  public int anInt657;

  private int[] anIntArray658;

  private final int[] anIntArray659;

  private final int[] anIntArray660;

  private final int[] anIntArray661;

  public boolean aBoolean662;

  public static void unpackConfig(StreamLoader);
    Code:
       0: new           #1                  // class Stream
       3: dup
       4: aload_0
       5: ldc           #2                  // String idk.dat
       7: invokevirtual #3                  // Method StreamLoader.getDataForName:(Ljava/lang/String;)[B
      10: invokespecial #4                  // Method Stream."<init>":([B)V
      13: astore_1
      14: aload_1
      15: invokevirtual #5                  // Method Stream.readUnsignedWord:()I
      18: putstatic     #6                  // Field length:I
      21: getstatic     #7                  // Field cache:[LIDK;
      24: ifnonnull     36
      27: getstatic     #6                  // Field length:I
      30: anewarray     #8                  // class IDK
      33: putstatic     #7                  // Field cache:[LIDK;
      36: iconst_0
      37: istore_2
      38: iload_2
      39: getstatic     #6                  // Field length:I
      42: if_icmpge     80
      45: getstatic     #7                  // Field cache:[LIDK;
      48: iload_2
      49: aaload
      50: ifnonnull     65
      53: getstatic     #7                  // Field cache:[LIDK;
      56: iload_2
      57: new           #8                  // class IDK
      60: dup
      61: invokespecial #9                  // Method "<init>":()V
      64: aastore
      65: getstatic     #7                  // Field cache:[LIDK;
      68: iload_2
      69: aaload
      70: aload_1
      71: invokespecial #10                 // Method readValues:(LStream;)V
      74: iinc          2, 1
      77: goto          38
      80: return

  private void readValues(Stream);
    Code:
       0: aload_1
       1: invokevirtual #11                 // Method Stream.readUnsignedByte:()I
       4: istore_2
       5: iload_2
       6: ifne          10
       9: return
      10: iload_2
      11: iconst_1
      12: if_icmpne     26
      15: aload_0
      16: aload_1
      17: invokevirtual #11                 // Method Stream.readUnsignedByte:()I
      20: putfield      #12                 // Field anInt657:I
      23: goto          194
      26: iload_2
      27: iconst_2
      28: if_icmpne     72
      31: aload_1
      32: invokevirtual #11                 // Method Stream.readUnsignedByte:()I
      35: istore_3
      36: aload_0
      37: iload_3
      38: newarray       int
      40: putfield      #13                 // Field anIntArray658:[I
      43: iconst_0
      44: istore        4
      46: iload         4
      48: iload_3
      49: if_icmpge     69
      52: aload_0
      53: getfield      #13                 // Field anIntArray658:[I
      56: iload         4
      58: aload_1
      59: invokevirtual #5                  // Method Stream.readUnsignedWord:()I
      62: iastore
      63: iinc          4, 1
      66: goto          46
      69: goto          194
      72: iload_2
      73: iconst_3
      74: if_icmpne     85
      77: aload_0
      78: iconst_1
      79: putfield      #14                 // Field aBoolean662:Z
      82: goto          194
      85: iload_2
      86: bipush        40
      88: if_icmplt     113
      91: iload_2
      92: bipush        50
      94: if_icmpge     113
      97: aload_0
      98: getfield      #15                 // Field anIntArray659:[I
     101: iload_2
     102: bipush        40
     104: isub
     105: aload_1
     106: invokevirtual #5                  // Method Stream.readUnsignedWord:()I
     109: iastore
     110: goto          194
     113: iload_2
     114: bipush        50
     116: if_icmplt     141
     119: iload_2
     120: bipush        60
     122: if_icmpge     141
     125: aload_0
     126: getfield      #16                 // Field anIntArray660:[I
     129: iload_2
     130: bipush        50
     132: isub
     133: aload_1
     134: invokevirtual #5                  // Method Stream.readUnsignedWord:()I
     137: iastore
     138: goto          194
     141: iload_2
     142: bipush        60
     144: if_icmplt     169
     147: iload_2
     148: bipush        70
     150: if_icmpge     169
     153: aload_0
     154: getfield      #17                 // Field anIntArray661:[I
     157: iload_2
     158: bipush        60
     160: isub
     161: aload_1
     162: invokevirtual #5                  // Method Stream.readUnsignedWord:()I
     165: iastore
     166: goto          194
     169: getstatic     #18                 // Field java/lang/System.out:Ljava/io/PrintStream;
     172: new           #19                 // class java/lang/StringBuilder
     175: dup
     176: invokespecial #20                 // Method java/lang/StringBuilder."<init>":()V
     179: ldc           #21                 // String Error unrecognised config code:
     181: invokevirtual #22                 // Method java/lang/StringBuilder.append:(Ljava/lang/String;)Ljava/lang/StringBuilder;
     184: iload_2
     185: invokevirtual #23                 // Method java/lang/StringBuilder.append:(I)Ljava/lang/StringBuilder;
     188: invokevirtual #24                 // Method java/lang/StringBuilder.toString:()Ljava/lang/String;
     191: invokevirtual #25                 // Method java/io/PrintStream.println:(Ljava/lang/String;)V
     194: goto          0

  public boolean method537();
    Code:
       0: aload_0
       1: getfield      #13                 // Field anIntArray658:[I
       4: ifnonnull     9
       7: iconst_1
       8: ireturn
       9: iconst_1
      10: istore_1
      11: iconst_0
      12: istore_2
      13: iload_2
      14: aload_0
      15: getfield      #13                 // Field anIntArray658:[I
      18: arraylength
      19: if_icmpge     42
      22: aload_0
      23: getfield      #13                 // Field anIntArray658:[I
      26: iload_2
      27: iaload
      28: invokestatic  #26                 // Method Model.method463:(I)Z
      31: ifne          36
      34: iconst_0
      35: istore_1
      36: iinc          2, 1
      39: goto          13
      42: iload_1
      43: ireturn

  public Model method538();
    Code:
       0: aload_0
       1: getfield      #13                 // Field anIntArray658:[I
       4: ifnonnull     9
       7: aconst_null
       8: areturn
       9: aload_0
      10: getfield      #13                 // Field anIntArray658:[I
      13: arraylength
      14: anewarray     #27                 // class Model
      17: astore_1
      18: iconst_0
      19: istore_2
      20: iload_2
      21: aload_0
      22: getfield      #13                 // Field anIntArray658:[I
      25: arraylength
      26: if_icmpge     47
      29: aload_1
      30: iload_2
      31: aload_0
      32: getfield      #13                 // Field anIntArray658:[I
      35: iload_2
      36: iaload
      37: invokestatic  #28                 // Method Model.method462:(I)LModel;
      40: aastore
      41: iinc          2, 1
      44: goto          20
      47: aload_1
      48: arraylength
      49: iconst_1
      50: if_icmpne     60
      53: aload_1
      54: iconst_0
      55: aaload
      56: astore_2
      57: goto          71
      60: new           #27                 // class Model
      63: dup
      64: aload_1
      65: arraylength
      66: aload_1
      67: invokespecial #29                 // Method Model."<init>":(I[LModel;)V
      70: astore_2
      71: iconst_0
      72: istore_3
      73: iload_3
      74: bipush        6
      76: if_icmpge     113
      79: aload_0
      80: getfield      #15                 // Field anIntArray659:[I
      83: iload_3
      84: iaload
      85: ifne          91
      88: goto          113
      91: aload_2
      92: aload_0
      93: getfield      #15                 // Field anIntArray659:[I
      96: iload_3
      97: iaload
      98: aload_0
      99: getfield      #16                 // Field anIntArray660:[I
     102: iload_3
     103: iaload
     104: invokevirtual #30                 // Method Model.method476:(II)V
     107: iinc          3, 1
     110: goto          73
     113: aload_2
     114: areturn

  public boolean method539();
    Code:
       0: iconst_1
       1: istore_1
       2: iconst_0
       3: istore_2
       4: iload_2
       5: iconst_5
       6: if_icmpge     39
       9: aload_0
      10: getfield      #17                 // Field anIntArray661:[I
      13: iload_2
      14: iaload
      15: iconst_m1
      16: if_icmpeq     33
      19: aload_0
      20: getfield      #17                 // Field anIntArray661:[I
      23: iload_2
      24: iaload
      25: invokestatic  #26                 // Method Model.method463:(I)Z
      28: ifne          33
      31: iconst_0
      32: istore_1
      33: iinc          2, 1
      36: goto          4
      39: iload_1
      40: ireturn

  public Model method540();
    Code:
       0: iconst_5
       1: anewarray     #27                 // class Model
       4: astore_1
       5: iconst_0
       6: istore_2
       7: iconst_0
       8: istore_3
       9: iload_3
      10: iconst_5
      11: if_icmpge     45
      14: aload_0
      15: getfield      #17                 // Field anIntArray661:[I
      18: iload_3
      19: iaload
      20: iconst_m1
      21: if_icmpeq     39
      24: aload_1
      25: iload_2
      26: iinc          2, 1
      29: aload_0
      30: getfield      #17                 // Field anIntArray661:[I
      33: iload_3
      34: iaload
      35: invokestatic  #28                 // Method Model.method462:(I)LModel;
      38: aastore
      39: iinc          3, 1
      42: goto          9
      45: new           #27                 // class Model
      48: dup
      49: iload_2
      50: aload_1
      51: invokespecial #29                 // Method Model."<init>":(I[LModel;)V
      54: astore_3
      55: iconst_0
      56: istore        4
      58: iload         4
      60: bipush        6
      62: if_icmpge     102
      65: aload_0
      66: getfield      #15                 // Field anIntArray659:[I
      69: iload         4
      71: iaload
      72: ifne          78
      75: goto          102
      78: aload_3
      79: aload_0
      80: getfield      #15                 // Field anIntArray659:[I
      83: iload         4
      85: iaload
      86: aload_0
      87: getfield      #16                 // Field anIntArray660:[I
      90: iload         4
      92: iaload
      93: invokevirtual #30                 // Method Model.method476:(II)V
      96: iinc          4, 1
      99: goto          58
     102: aload_3
     103: areturn

  private IDK();
    Code:
       0: aload_0
       1: invokespecial #31                 // Method java/lang/Object."<init>":()V
       4: aload_0
       5: iconst_5
       6: newarray       int
       8: dup
       9: iconst_0
      10: iconst_m1
      11: iastore
      12: dup
      13: iconst_1
      14: iconst_m1
      15: iastore
      16: dup
      17: iconst_2
      18: iconst_m1
      19: iastore
      20: dup
      21: iconst_3
      22: iconst_m1
      23: iastore
      24: dup
      25: iconst_4
      26: iconst_m1
      27: iastore
      28: putfield      #17                 // Field anIntArray661:[I
      31: aload_0
      32: iconst_m1
      33: putfield      #12                 // Field anInt657:I
      36: aload_0
      37: bipush        6
      39: newarray       int
      41: putfield      #15                 // Field anIntArray659:[I
      44: aload_0
      45: bipush        6
      47: newarray       int
      49: putfield      #16                 // Field anIntArray660:[I
      52: aload_0
      53: iconst_0
      54: putfield      #14                 // Field aBoolean662:Z
      57: return
}
