Compiled from "ItemDef.java"
public final class ItemDef {
  private byte aByte154;

  public int value;

  private int[] modifiedModelColors;

  public int id;

  static MRUNodes mruNodes1;

  public static MRUNodes mruNodes2;

  private int[] originalModelColors;

  public boolean membersObject;

  private int anInt162;

  private int certTemplateID;

  private int anInt164;

  private int anInt165;

  private int anInt166;

  private int anInt167;

  public java.lang.String[] groundActions;

  private int modelOffset1;

  public java.lang.String name;

  private static ItemDef[] cache;

  private int anInt173;

  private int modelID;

  private int anInt175;

  public boolean stackable;

  public byte[] description;

  private int certID;

  private static int cacheIndex;

  public int modelZoom;

  public static boolean isMembers;

  private static Stream stream;

  private int anInt184;

  private int anInt185;

  private int anInt188;

  public java.lang.String[] actions;

  public int modelRotation1;

  private int anInt191;

  private int anInt192;

  private int[] stackIDs;

  private int modelOffset2;

  private static int[] streamIndices;

  private int anInt196;

  private int anInt197;

  public int modelRotation2;

  private int anInt200;

  private int[] stackAmounts;

  public int team;

  public static int totalItems;

  private int anInt204;

  private byte aByte205;

  public static void nullLoader();
    Code:
       0: aconst_null
       1: putstatic     #1                  // Field mruNodes2:LMRUNodes;
       4: aconst_null
       5: putstatic     #2                  // Field mruNodes1:LMRUNodes;
       8: aconst_null
       9: putstatic     #3                  // Field streamIndices:[I
      12: aconst_null
      13: putstatic     #4                  // Field cache:[LItemDef;
      16: aconst_null
      17: putstatic     #5                  // Field stream:LStream;
      20: return

  public boolean method192(int);
    Code:
       0: aload_0
       1: getfield      #6                  // Field anInt175:I
       4: istore_2
       5: aload_0
       6: getfield      #7                  // Field anInt166:I
       9: istore_3
      10: iload_1
      11: iconst_1
      12: if_icmpne     25
      15: aload_0
      16: getfield      #8                  // Field anInt197:I
      19: istore_2
      20: aload_0
      21: getfield      #9                  // Field anInt173:I
      24: istore_3
      25: iload_2
      26: iconst_m1
      27: if_icmpne     32
      30: iconst_1
      31: ireturn
      32: iconst_1
      33: istore        4
      35: iload_2
      36: invokestatic  #10                 // Method Model.method463:(I)Z
      39: ifne          45
      42: iconst_0
      43: istore        4
      45: iload_3
      46: iconst_m1
      47: if_icmpeq     60
      50: iload_3
      51: invokestatic  #10                 // Method Model.method463:(I)Z
      54: ifne          60
      57: iconst_0
      58: istore        4
      60: iload         4
      62: ireturn

  public static void unpackConfig(StreamLoader);
    Code:
       0: new           #11                 // class Stream
       3: dup
       4: aload_0
       5: ldc           #12                 // String obj.dat
       7: invokevirtual #13                 // Method StreamLoader.getDataForName:(Ljava/lang/String;)[B
      10: invokespecial #14                 // Method Stream."<init>":([B)V
      13: putstatic     #5                  // Field stream:LStream;
      16: new           #11                 // class Stream
      19: dup
      20: aload_0
      21: ldc           #15                 // String obj.idx
      23: invokevirtual #13                 // Method StreamLoader.getDataForName:(Ljava/lang/String;)[B
      26: invokespecial #14                 // Method Stream."<init>":([B)V
      29: astore_1
      30: aload_1
      31: invokevirtual #16                 // Method Stream.readUnsignedWord:()I
      34: putstatic     #17                 // Field totalItems:I
      37: getstatic     #17                 // Field totalItems:I
      40: newarray       int
      42: putstatic     #3                  // Field streamIndices:[I
      45: iconst_2
      46: istore_2
      47: iconst_0
      48: istore_3
      49: iload_3
      50: getstatic     #17                 // Field totalItems:I
      53: if_icmpge     75
      56: getstatic     #3                  // Field streamIndices:[I
      59: iload_3
      60: iload_2
      61: iastore
      62: iload_2
      63: aload_1
      64: invokevirtual #16                 // Method Stream.readUnsignedWord:()I
      67: iadd
      68: istore_2
      69: iinc          3, 1
      72: goto          49
      75: bipush        10
      77: anewarray     #18                 // class ItemDef
      80: putstatic     #4                  // Field cache:[LItemDef;
      83: iconst_0
      84: istore_3
      85: iload_3
      86: bipush        10
      88: if_icmpge     109
      91: getstatic     #4                  // Field cache:[LItemDef;
      94: iload_3
      95: new           #18                 // class ItemDef
      98: dup
      99: invokespecial #19                 // Method "<init>":()V
     102: aastore
     103: iinc          3, 1
     106: goto          85
     109: return

  public Model method194(int);
    Code:
       0: aload_0
       1: getfield      #6                  // Field anInt175:I
       4: istore_2
       5: aload_0
       6: getfield      #7                  // Field anInt166:I
       9: istore_3
      10: iload_1
      11: iconst_1
      12: if_icmpne     25
      15: aload_0
      16: getfield      #8                  // Field anInt197:I
      19: istore_2
      20: aload_0
      21: getfield      #9                  // Field anInt173:I
      24: istore_3
      25: iload_2
      26: iconst_m1
      27: if_icmpne     32
      30: aconst_null
      31: areturn
      32: iload_2
      33: invokestatic  #20                 // Method Model.method462:(I)LModel;
      36: astore        4
      38: iload_3
      39: iconst_m1
      40: if_icmpeq     77
      43: iload_3
      44: invokestatic  #20                 // Method Model.method462:(I)LModel;
      47: astore        5
      49: iconst_2
      50: anewarray     #21                 // class Model
      53: dup
      54: iconst_0
      55: aload         4
      57: aastore
      58: dup
      59: iconst_1
      60: aload         5
      62: aastore
      63: astore        6
      65: new           #21                 // class Model
      68: dup
      69: iconst_2
      70: aload         6
      72: invokespecial #22                 // Method Model."<init>":(I[LModel;)V
      75: astore        4
      77: aload_0
      78: getfield      #23                 // Field modifiedModelColors:[I
      81: ifnull        122
      84: iconst_0
      85: istore        5
      87: iload         5
      89: aload_0
      90: getfield      #23                 // Field modifiedModelColors:[I
      93: arraylength
      94: if_icmpge     122
      97: aload         4
      99: aload_0
     100: getfield      #23                 // Field modifiedModelColors:[I
     103: iload         5
     105: iaload
     106: aload_0
     107: getfield      #24                 // Field originalModelColors:[I
     110: iload         5
     112: iaload
     113: invokevirtual #25                 // Method Model.method476:(II)V
     116: iinc          5, 1
     119: goto          87
     122: aload         4
     124: areturn

  public boolean method195(int);
    Code:
       0: aload_0
       1: getfield      #26                 // Field anInt165:I
       4: istore_2
       5: aload_0
       6: getfield      #27                 // Field anInt188:I
       9: istore_3
      10: aload_0
      11: getfield      #28                 // Field anInt185:I
      14: istore        4
      16: iload_1
      17: iconst_1
      18: if_icmpne     37
      21: aload_0
      22: getfield      #29                 // Field anInt200:I
      25: istore_2
      26: aload_0
      27: getfield      #30                 // Field anInt164:I
      30: istore_3
      31: aload_0
      32: getfield      #31                 // Field anInt162:I
      35: istore        4
      37: iload_2
      38: iconst_m1
      39: if_icmpne     44
      42: iconst_1
      43: ireturn
      44: iconst_1
      45: istore        5
      47: iload_2
      48: invokestatic  #10                 // Method Model.method463:(I)Z
      51: ifne          57
      54: iconst_0
      55: istore        5
      57: iload_3
      58: iconst_m1
      59: if_icmpeq     72
      62: iload_3
      63: invokestatic  #10                 // Method Model.method463:(I)Z
      66: ifne          72
      69: iconst_0
      70: istore        5
      72: iload         4
      74: iconst_m1
      75: if_icmpeq     89
      78: iload         4
      80: invokestatic  #10                 // Method Model.method463:(I)Z
      83: ifne          89
      86: iconst_0
      87: istore        5
      89: iload         5
      91: ireturn

  public Model method196(int);
    Code:
       0: aload_0
       1: getfield      #26                 // Field anInt165:I
       4: istore_2
       5: aload_0
       6: getfield      #27                 // Field anInt188:I
       9: istore_3
      10: aload_0
      11: getfield      #28                 // Field anInt185:I
      14: istore        4
      16: iload_1
      17: iconst_1
      18: if_icmpne     37
      21: aload_0
      22: getfield      #29                 // Field anInt200:I
      25: istore_2
      26: aload_0
      27: getfield      #30                 // Field anInt164:I
      30: istore_3
      31: aload_0
      32: getfield      #31                 // Field anInt162:I
      35: istore        4
      37: iload_2
      38: iconst_m1
      39: if_icmpne     44
      42: aconst_null
      43: areturn
      44: iload_2
      45: invokestatic  #20                 // Method Model.method462:(I)LModel;
      48: astore        5
      50: iload_3
      51: iconst_m1
      52: if_icmpeq     144
      55: iload         4
      57: iconst_m1
      58: if_icmpeq     110
      61: iload_3
      62: invokestatic  #20                 // Method Model.method462:(I)LModel;
      65: astore        6
      67: iload         4
      69: invokestatic  #20                 // Method Model.method462:(I)LModel;
      72: astore        7
      74: iconst_3
      75: anewarray     #21                 // class Model
      78: dup
      79: iconst_0
      80: aload         5
      82: aastore
      83: dup
      84: iconst_1
      85: aload         6
      87: aastore
      88: dup
      89: iconst_2
      90: aload         7
      92: aastore
      93: astore        8
      95: new           #21                 // class Model
      98: dup
      99: iconst_3
     100: aload         8
     102: invokespecial #22                 // Method Model."<init>":(I[LModel;)V
     105: astore        5
     107: goto          144
     110: iload_3
     111: invokestatic  #20                 // Method Model.method462:(I)LModel;
     114: astore        6
     116: iconst_2
     117: anewarray     #21                 // class Model
     120: dup
     121: iconst_0
     122: aload         5
     124: aastore
     125: dup
     126: iconst_1
     127: aload         6
     129: aastore
     130: astore        7
     132: new           #21                 // class Model
     135: dup
     136: iconst_2
     137: aload         7
     139: invokespecial #22                 // Method Model."<init>":(I[LModel;)V
     142: astore        5
     144: iload_1
     145: ifne          166
     148: aload_0
     149: getfield      #32                 // Field aByte205:B
     152: ifeq          166
     155: aload         5
     157: iconst_0
     158: aload_0
     159: getfield      #32                 // Field aByte205:B
     162: iconst_0
     163: invokevirtual #33                 // Method Model.method475:(III)V
     166: iload_1
     167: iconst_1
     168: if_icmpne     189
     171: aload_0
     172: getfield      #34                 // Field aByte154:B
     175: ifeq          189
     178: aload         5
     180: iconst_0
     181: aload_0
     182: getfield      #34                 // Field aByte154:B
     185: iconst_0
     186: invokevirtual #33                 // Method Model.method475:(III)V
     189: aload_0
     190: getfield      #23                 // Field modifiedModelColors:[I
     193: ifnull        234
     196: iconst_0
     197: istore        6
     199: iload         6
     201: aload_0
     202: getfield      #23                 // Field modifiedModelColors:[I
     205: arraylength
     206: if_icmpge     234
     209: aload         5
     211: aload_0
     212: getfield      #23                 // Field modifiedModelColors:[I
     215: iload         6
     217: iaload
     218: aload_0
     219: getfield      #24                 // Field originalModelColors:[I
     222: iload         6
     224: iaload
     225: invokevirtual #25                 // Method Model.method476:(II)V
     228: iinc          6, 1
     231: goto          199
     234: aload         5
     236: areturn

  private void setDefaults();
    Code:
       0: aload_0
       1: iconst_0
       2: putfield      #35                 // Field modelID:I
       5: aload_0
       6: aconst_null
       7: putfield      #36                 // Field name:Ljava/lang/String;
      10: aload_0
      11: aconst_null
      12: putfield      #37                 // Field description:[B
      15: aload_0
      16: aconst_null
      17: putfield      #23                 // Field modifiedModelColors:[I
      20: aload_0
      21: aconst_null
      22: putfield      #24                 // Field originalModelColors:[I
      25: aload_0
      26: sipush        2000
      29: putfield      #38                 // Field modelZoom:I
      32: aload_0
      33: iconst_0
      34: putfield      #39                 // Field modelRotation1:I
      37: aload_0
      38: iconst_0
      39: putfield      #40                 // Field modelRotation2:I
      42: aload_0
      43: iconst_0
      44: putfield      #41                 // Field anInt204:I
      47: aload_0
      48: iconst_0
      49: putfield      #42                 // Field modelOffset1:I
      52: aload_0
      53: iconst_0
      54: putfield      #43                 // Field modelOffset2:I
      57: aload_0
      58: iconst_0
      59: putfield      #44                 // Field stackable:Z
      62: aload_0
      63: iconst_1
      64: putfield      #45                 // Field value:I
      67: aload_0
      68: iconst_0
      69: putfield      #46                 // Field membersObject:Z
      72: aload_0
      73: aconst_null
      74: putfield      #47                 // Field groundActions:[Ljava/lang/String;
      77: aload_0
      78: aconst_null
      79: putfield      #48                 // Field actions:[Ljava/lang/String;
      82: aload_0
      83: iconst_m1
      84: putfield      #26                 // Field anInt165:I
      87: aload_0
      88: iconst_m1
      89: putfield      #27                 // Field anInt188:I
      92: aload_0
      93: iconst_0
      94: putfield      #32                 // Field aByte205:B
      97: aload_0
      98: iconst_m1
      99: putfield      #29                 // Field anInt200:I
     102: aload_0
     103: iconst_m1
     104: putfield      #30                 // Field anInt164:I
     107: aload_0
     108: iconst_0
     109: putfield      #34                 // Field aByte154:B
     112: aload_0
     113: iconst_m1
     114: putfield      #28                 // Field anInt185:I
     117: aload_0
     118: iconst_m1
     119: putfield      #31                 // Field anInt162:I
     122: aload_0
     123: iconst_m1
     124: putfield      #6                  // Field anInt175:I
     127: aload_0
     128: iconst_m1
     129: putfield      #7                  // Field anInt166:I
     132: aload_0
     133: iconst_m1
     134: putfield      #8                  // Field anInt197:I
     137: aload_0
     138: iconst_m1
     139: putfield      #9                  // Field anInt173:I
     142: aload_0
     143: aconst_null
     144: putfield      #49                 // Field stackIDs:[I
     147: aload_0
     148: aconst_null
     149: putfield      #50                 // Field stackAmounts:[I
     152: aload_0
     153: iconst_m1
     154: putfield      #51                 // Field certID:I
     157: aload_0
     158: iconst_m1
     159: putfield      #52                 // Field certTemplateID:I
     162: aload_0
     163: sipush        128
     166: putfield      #53                 // Field anInt167:I
     169: aload_0
     170: sipush        128
     173: putfield      #54                 // Field anInt192:I
     176: aload_0
     177: sipush        128
     180: putfield      #55                 // Field anInt191:I
     183: aload_0
     184: iconst_0
     185: putfield      #56                 // Field anInt196:I
     188: aload_0
     189: iconst_0
     190: putfield      #57                 // Field anInt184:I
     193: aload_0
     194: iconst_0
     195: putfield      #58                 // Field team:I
     198: return

  public static ItemDef forID(int);
    Code:
       0: iconst_0
       1: istore_1
       2: iload_1
       3: bipush        10
       5: if_icmpge     32
       8: getstatic     #4                  // Field cache:[LItemDef;
      11: iload_1
      12: aaload
      13: getfield      #59                 // Field id:I
      16: iload_0
      17: if_icmpne     26
      20: getstatic     #4                  // Field cache:[LItemDef;
      23: iload_1
      24: aaload
      25: areturn
      26: iinc          1, 1
      29: goto          2
      32: getstatic     #60                 // Field cacheIndex:I
      35: iconst_1
      36: iadd
      37: bipush        10
      39: irem
      40: putstatic     #60                 // Field cacheIndex:I
      43: getstatic     #4                  // Field cache:[LItemDef;
      46: getstatic     #60                 // Field cacheIndex:I
      49: aaload
      50: astore_1
      51: getstatic     #5                  // Field stream:LStream;
      54: getstatic     #3                  // Field streamIndices:[I
      57: iload_0
      58: iaload
      59: putfield      #61                 // Field Stream.currentOffset:I
      62: aload_1
      63: iload_0
      64: putfield      #59                 // Field id:I
      67: aload_1
      68: invokespecial #62                 // Method setDefaults:()V
      71: aload_1
      72: getstatic     #5                  // Field stream:LStream;
      75: invokespecial #63                 // Method readValues:(LStream;)V
      78: aload_1
      79: getfield      #52                 // Field certTemplateID:I
      82: iconst_m1
      83: if_icmpeq     90
      86: aload_1
      87: invokespecial #64                 // Method toNote:()V
      90: getstatic     #65                 // Field isMembers:Z
      93: ifne          133
      96: aload_1
      97: getfield      #46                 // Field membersObject:Z
     100: ifeq          133
     103: aload_1
     104: ldc           #66                 // String Members Object
     106: putfield      #36                 // Field name:Ljava/lang/String;
     109: aload_1
     110: ldc           #67                 // String Login to a members' server to use this object.
     112: invokevirtual #68                 // Method java/lang/String.getBytes:()[B
     115: putfield      #37                 // Field description:[B
     118: aload_1
     119: aconst_null
     120: putfield      #47                 // Field groundActions:[Ljava/lang/String;
     123: aload_1
     124: aconst_null
     125: putfield      #48                 // Field actions:[Ljava/lang/String;
     128: aload_1
     129: iconst_0
     130: putfield      #58                 // Field team:I
     133: aload_1
     134: areturn

  private void toNote();
    Code:
       0: aload_0
       1: getfield      #52                 // Field certTemplateID:I
       4: invokestatic  #69                 // Method forID:(I)LItemDef;
       7: astore_1
       8: aload_0
       9: aload_1
      10: getfield      #35                 // Field modelID:I
      13: putfield      #35                 // Field modelID:I
      16: aload_0
      17: aload_1
      18: getfield      #38                 // Field modelZoom:I
      21: putfield      #38                 // Field modelZoom:I
      24: aload_0
      25: aload_1
      26: getfield      #39                 // Field modelRotation1:I
      29: putfield      #39                 // Field modelRotation1:I
      32: aload_0
      33: aload_1
      34: getfield      #40                 // Field modelRotation2:I
      37: putfield      #40                 // Field modelRotation2:I
      40: aload_0
      41: aload_1
      42: getfield      #41                 // Field anInt204:I
      45: putfield      #41                 // Field anInt204:I
      48: aload_0
      49: aload_1
      50: getfield      #42                 // Field modelOffset1:I
      53: putfield      #42                 // Field modelOffset1:I
      56: aload_0
      57: aload_1
      58: getfield      #43                 // Field modelOffset2:I
      61: putfield      #43                 // Field modelOffset2:I
      64: aload_0
      65: aload_1
      66: getfield      #23                 // Field modifiedModelColors:[I
      69: putfield      #23                 // Field modifiedModelColors:[I
      72: aload_0
      73: aload_1
      74: getfield      #24                 // Field originalModelColors:[I
      77: putfield      #24                 // Field originalModelColors:[I
      80: aload_0
      81: getfield      #51                 // Field certID:I
      84: invokestatic  #69                 // Method forID:(I)LItemDef;
      87: astore_2
      88: aload_0
      89: aload_2
      90: getfield      #36                 // Field name:Ljava/lang/String;
      93: putfield      #36                 // Field name:Ljava/lang/String;
      96: aload_0
      97: aload_2
      98: getfield      #46                 // Field membersObject:Z
     101: putfield      #46                 // Field membersObject:Z
     104: aload_0
     105: aload_2
     106: getfield      #45                 // Field value:I
     109: putfield      #45                 // Field value:I
     112: ldc           #70                 // String a
     114: astore_3
     115: aload_2
     116: getfield      #36                 // Field name:Ljava/lang/String;
     119: iconst_0
     120: invokevirtual #71                 // Method java/lang/String.charAt:(I)C
     123: istore        4
     125: iload         4
     127: bipush        65
     129: if_icmpeq     160
     132: iload         4
     134: bipush        69
     136: if_icmpeq     160
     139: iload         4
     141: bipush        73
     143: if_icmpeq     160
     146: iload         4
     148: bipush        79
     150: if_icmpeq     160
     153: iload         4
     155: bipush        85
     157: if_icmpne     163
     160: ldc           #72                 // String an
     162: astore_3
     163: aload_0
     164: new           #73                 // class java/lang/StringBuilder
     167: dup
     168: invokespecial #74                 // Method java/lang/StringBuilder."<init>":()V
     171: ldc           #75                 // String Swap this note at any bank for
     173: invokevirtual #76                 // Method java/lang/StringBuilder.append:(Ljava/lang/String;)Ljava/lang/StringBuilder;
     176: aload_3
     177: invokevirtual #76                 // Method java/lang/StringBuilder.append:(Ljava/lang/String;)Ljava/lang/StringBuilder;
     180: ldc           #77                 // String
     182: invokevirtual #76                 // Method java/lang/StringBuilder.append:(Ljava/lang/String;)Ljava/lang/StringBuilder;
     185: aload_2
     186: getfield      #36                 // Field name:Ljava/lang/String;
     189: invokevirtual #76                 // Method java/lang/StringBuilder.append:(Ljava/lang/String;)Ljava/lang/StringBuilder;
     192: ldc           #78                 // String .
     194: invokevirtual #76                 // Method java/lang/StringBuilder.append:(Ljava/lang/String;)Ljava/lang/StringBuilder;
     197: invokevirtual #79                 // Method java/lang/StringBuilder.toString:()Ljava/lang/String;
     200: invokevirtual #68                 // Method java/lang/String.getBytes:()[B
     203: putfield      #37                 // Field description:[B
     206: aload_0
     207: iconst_1
     208: putfield      #44                 // Field stackable:Z
     211: return

  public static Sprite getSprite(int, int, int);
    Code:
       0: iload_2
       1: ifne          48
       4: getstatic     #2                  // Field mruNodes1:LMRUNodes;
       7: iload_0
       8: i2l
       9: invokevirtual #80                 // Method MRUNodes.insertFromCache:(J)LNodeSub;
      12: checkcast     #81                 // class Sprite
      15: astore_3
      16: aload_3
      17: ifnull        42
      20: aload_3
      21: getfield      #82                 // Field Sprite.anInt1445:I
      24: iload_1
      25: if_icmpeq     42
      28: aload_3
      29: getfield      #82                 // Field Sprite.anInt1445:I
      32: iconst_m1
      33: if_icmpeq     42
      36: aload_3
      37: invokevirtual #83                 // Method Sprite.unlink:()V
      40: aconst_null
      41: astore_3
      42: aload_3
      43: ifnull        48
      46: aload_3
      47: areturn
      48: iload_0
      49: invokestatic  #69                 // Method forID:(I)LItemDef;
      52: astore_3
      53: aload_3
      54: getfield      #49                 // Field stackIDs:[I
      57: ifnonnull     62
      60: iconst_m1
      61: istore_1
      62: iload_1
      63: iconst_1
      64: if_icmple     128
      67: iconst_m1
      68: istore        4
      70: iconst_0
      71: istore        5
      73: iload         5
      75: bipush        10
      77: if_icmpge     116
      80: iload_1
      81: aload_3
      82: getfield      #50                 // Field stackAmounts:[I
      85: iload         5
      87: iaload
      88: if_icmplt     110
      91: aload_3
      92: getfield      #50                 // Field stackAmounts:[I
      95: iload         5
      97: iaload
      98: ifeq          110
     101: aload_3
     102: getfield      #49                 // Field stackIDs:[I
     105: iload         5
     107: iaload
     108: istore        4
     110: iinc          5, 1
     113: goto          73
     116: iload         4
     118: iconst_m1
     119: if_icmpeq     128
     122: iload         4
     124: invokestatic  #69                 // Method forID:(I)LItemDef;
     127: astore_3
     128: aload_3
     129: iconst_1
     130: invokevirtual #84                 // Method method201:(I)LModel;
     133: astore        4
     135: aload         4
     137: ifnonnull     142
     140: aconst_null
     141: areturn
     142: aconst_null
     143: astore        5
     145: aload_3
     146: getfield      #52                 // Field certTemplateID:I
     149: iconst_m1
     150: if_icmpeq     172
     153: aload_3
     154: getfield      #51                 // Field certID:I
     157: bipush        10
     159: iconst_m1
     160: invokestatic  #85                 // Method getSprite:(III)LSprite;
     163: astore        5
     165: aload         5
     167: ifnonnull     172
     170: aconst_null
     171: areturn
     172: new           #81                 // class Sprite
     175: dup
     176: bipush        32
     178: bipush        32
     180: invokespecial #86                 // Method Sprite."<init>":(II)V
     183: astore        6
     185: getstatic     #87                 // Field Texture.textureInt1:I
     188: istore        7
     190: getstatic     #88                 // Field Texture.textureInt2:I
     193: istore        8
     195: getstatic     #89                 // Field Texture.anIntArray1472:[I
     198: astore        9
     200: getstatic     #90                 // Field DrawingArea.pixels:[I
     203: astore        10
     205: getstatic     #91                 // Field DrawingArea.width:I
     208: istore        11
     210: getstatic     #92                 // Field DrawingArea.height:I
     213: istore        12
     215: getstatic     #93                 // Field DrawingArea.topX:I
     218: istore        13
     220: getstatic     #94                 // Field DrawingArea.bottomX:I
     223: istore        14
     225: getstatic     #95                 // Field DrawingArea.topY:I
     228: istore        15
     230: getstatic     #96                 // Field DrawingArea.bottomY:I
     233: istore        16
     235: iconst_0
     236: putstatic     #97                 // Field Texture.aBoolean1464:Z
     239: bipush        32
     241: bipush        32
     243: aload         6
     245: getfield      #98                 // Field Sprite.myPixels:[I
     248: invokestatic  #99                 // Method DrawingArea.initDrawingArea:(II[I)V
     251: bipush        32
     253: iconst_0
     254: iconst_0
     255: iconst_0
     256: bipush        32
     258: invokestatic  #100                // Method DrawingArea.method336:(IIIII)V
     261: invokestatic  #101                // Method Texture.method364:()V
     264: aload_3
     265: getfield      #38                 // Field modelZoom:I
     268: istore        17
     270: iload_2
     271: iconst_m1
     272: if_icmpne     285
     275: iload         17
     277: i2d
     278: ldc2_w        #102                // double 1.5d
     281: dmul
     282: d2i
     283: istore        17
     285: iload_2
     286: ifle          299
     289: iload         17
     291: i2d
     292: ldc2_w        #104                // double 1.04d
     295: dmul
     296: d2i
     297: istore        17
     299: getstatic     #106                // Field Texture.anIntArray1470:[I
     302: aload_3
     303: getfield      #39                 // Field modelRotation1:I
     306: iaload
     307: iload         17
     309: imul
     310: bipush        16
     312: ishr
     313: istore        18
     315: getstatic     #107                // Field Texture.anIntArray1471:[I
     318: aload_3
     319: getfield      #39                 // Field modelRotation1:I
     322: iaload
     323: iload         17
     325: imul
     326: bipush        16
     328: ishr
     329: istore        19
     331: aload         4
     333: aload_3
     334: getfield      #40                 // Field modelRotation2:I
     337: aload_3
     338: getfield      #41                 // Field anInt204:I
     341: aload_3
     342: getfield      #39                 // Field modelRotation1:I
     345: aload_3
     346: getfield      #42                 // Field modelOffset1:I
     349: iload         18
     351: aload         4
     353: getfield      #108                // Field Model.modelHeight:I
     356: iconst_2
     357: idiv
     358: iadd
     359: aload_3
     360: getfield      #43                 // Field modelOffset2:I
     363: iadd
     364: iload         19
     366: aload_3
     367: getfield      #43                 // Field modelOffset2:I
     370: iadd
     371: invokevirtual #109                // Method Model.method482:(IIIIII)V
     374: bipush        31
     376: istore        20
     378: iload         20
     380: iflt          594
     383: bipush        31
     385: istore        21
     387: iload         21
     389: iflt          588
     392: aload         6
     394: getfield      #98                 // Field Sprite.myPixels:[I
     397: iload         20
     399: iload         21
     401: bipush        32
     403: imul
     404: iadd
     405: iaload
     406: ifne          582
     409: iload         20
     411: ifle          452
     414: aload         6
     416: getfield      #98                 // Field Sprite.myPixels:[I
     419: iload         20
     421: iconst_1
     422: isub
     423: iload         21
     425: bipush        32
     427: imul
     428: iadd
     429: iaload
     430: iconst_1
     431: if_icmple     452
     434: aload         6
     436: getfield      #98                 // Field Sprite.myPixels:[I
     439: iload         20
     441: iload         21
     443: bipush        32
     445: imul
     446: iadd
     447: iconst_1
     448: iastore
     449: goto          582
     452: iload         21
     454: ifle          495
     457: aload         6
     459: getfield      #98                 // Field Sprite.myPixels:[I
     462: iload         20
     464: iload         21
     466: iconst_1
     467: isub
     468: bipush        32
     470: imul
     471: iadd
     472: iaload
     473: iconst_1
     474: if_icmple     495
     477: aload         6
     479: getfield      #98                 // Field Sprite.myPixels:[I
     482: iload         20
     484: iload         21
     486: bipush        32
     488: imul
     489: iadd
     490: iconst_1
     491: iastore
     492: goto          582
     495: iload         20
     497: bipush        31
     499: if_icmpge     540
     502: aload         6
     504: getfield      #98                 // Field Sprite.myPixels:[I
     507: iload         20
     509: iconst_1
     510: iadd
     511: iload         21
     513: bipush        32
     515: imul
     516: iadd
     517: iaload
     518: iconst_1
     519: if_icmple     540
     522: aload         6
     524: getfield      #98                 // Field Sprite.myPixels:[I
     527: iload         20
     529: iload         21
     531: bipush        32
     533: imul
     534: iadd
     535: iconst_1
     536: iastore
     537: goto          582
     540: iload         21
     542: bipush        31
     544: if_icmpge     582
     547: aload         6
     549: getfield      #98                 // Field Sprite.myPixels:[I
     552: iload         20
     554: iload         21
     556: iconst_1
     557: iadd
     558: bipush        32
     560: imul
     561: iadd
     562: iaload
     563: iconst_1
     564: if_icmple     582
     567: aload         6
     569: getfield      #98                 // Field Sprite.myPixels:[I
     572: iload         20
     574: iload         21
     576: bipush        32
     578: imul
     579: iadd
     580: iconst_1
     581: iastore
     582: iinc          21, -1
     585: goto          387
     588: iinc          20, -1
     591: goto          378
     594: iload_2
     595: ifle          821
     598: bipush        31
     600: istore        20
     602: iload         20
     604: iflt          818
     607: bipush        31
     609: istore        21
     611: iload         21
     613: iflt          812
     616: aload         6
     618: getfield      #98                 // Field Sprite.myPixels:[I
     621: iload         20
     623: iload         21
     625: bipush        32
     627: imul
     628: iadd
     629: iaload
     630: ifne          806
     633: iload         20
     635: ifle          676
     638: aload         6
     640: getfield      #98                 // Field Sprite.myPixels:[I
     643: iload         20
     645: iconst_1
     646: isub
     647: iload         21
     649: bipush        32
     651: imul
     652: iadd
     653: iaload
     654: iconst_1
     655: if_icmpne     676
     658: aload         6
     660: getfield      #98                 // Field Sprite.myPixels:[I
     663: iload         20
     665: iload         21
     667: bipush        32
     669: imul
     670: iadd
     671: iload_2
     672: iastore
     673: goto          806
     676: iload         21
     678: ifle          719
     681: aload         6
     683: getfield      #98                 // Field Sprite.myPixels:[I
     686: iload         20
     688: iload         21
     690: iconst_1
     691: isub
     692: bipush        32
     694: imul
     695: iadd
     696: iaload
     697: iconst_1
     698: if_icmpne     719
     701: aload         6
     703: getfield      #98                 // Field Sprite.myPixels:[I
     706: iload         20
     708: iload         21
     710: bipush        32
     712: imul
     713: iadd
     714: iload_2
     715: iastore
     716: goto          806
     719: iload         20
     721: bipush        31
     723: if_icmpge     764
     726: aload         6
     728: getfield      #98                 // Field Sprite.myPixels:[I
     731: iload         20
     733: iconst_1
     734: iadd
     735: iload         21
     737: bipush        32
     739: imul
     740: iadd
     741: iaload
     742: iconst_1
     743: if_icmpne     764
     746: aload         6
     748: getfield      #98                 // Field Sprite.myPixels:[I
     751: iload         20
     753: iload         21
     755: bipush        32
     757: imul
     758: iadd
     759: iload_2
     760: iastore
     761: goto          806
     764: iload         21
     766: bipush        31
     768: if_icmpge     806
     771: aload         6
     773: getfield      #98                 // Field Sprite.myPixels:[I
     776: iload         20
     778: iload         21
     780: iconst_1
     781: iadd
     782: bipush        32
     784: imul
     785: iadd
     786: iaload
     787: iconst_1
     788: if_icmpne     806
     791: aload         6
     793: getfield      #98                 // Field Sprite.myPixels:[I
     796: iload         20
     798: iload         21
     800: bipush        32
     802: imul
     803: iadd
     804: iload_2
     805: iastore
     806: iinc          21, -1
     809: goto          611
     812: iinc          20, -1
     815: goto          602
     818: goto          919
     821: iload_2
     822: ifne          919
     825: bipush        31
     827: istore        20
     829: iload         20
     831: iflt          919
     834: bipush        31
     836: istore        21
     838: iload         21
     840: iflt          913
     843: aload         6
     845: getfield      #98                 // Field Sprite.myPixels:[I
     848: iload         20
     850: iload         21
     852: bipush        32
     854: imul
     855: iadd
     856: iaload
     857: ifne          907
     860: iload         20
     862: ifle          907
     865: iload         21
     867: ifle          907
     870: aload         6
     872: getfield      #98                 // Field Sprite.myPixels:[I
     875: iload         20
     877: iconst_1
     878: isub
     879: iload         21
     881: iconst_1
     882: isub
     883: bipush        32
     885: imul
     886: iadd
     887: iaload
     888: ifle          907
     891: aload         6
     893: getfield      #98                 // Field Sprite.myPixels:[I
     896: iload         20
     898: iload         21
     900: bipush        32
     902: imul
     903: iadd
     904: ldc           #110                // int 3153952
     906: iastore
     907: iinc          21, -1
     910: goto          838
     913: iinc          20, -1
     916: goto          829
     919: aload_3
     920: getfield      #52                 // Field certTemplateID:I
     923: iconst_m1
     924: if_icmpeq     976
     927: aload         5
     929: getfield      #111                // Field Sprite.anInt1444:I
     932: istore        20
     934: aload         5
     936: getfield      #82                 // Field Sprite.anInt1445:I
     939: istore        21
     941: aload         5
     943: bipush        32
     945: putfield      #111                // Field Sprite.anInt1444:I
     948: aload         5
     950: bipush        32
     952: putfield      #82                 // Field Sprite.anInt1445:I
     955: aload         5
     957: iconst_0
     958: iconst_0
     959: invokevirtual #112                // Method Sprite.drawSprite:(II)V
     962: aload         5
     964: iload         20
     966: putfield      #111                // Field Sprite.anInt1444:I
     969: aload         5
     971: iload         21
     973: putfield      #82                 // Field Sprite.anInt1445:I
     976: iload_2
     977: ifne          990
     980: getstatic     #2                  // Field mruNodes1:LMRUNodes;
     983: aload         6
     985: iload_0
     986: i2l
     987: invokevirtual #113                // Method MRUNodes.removeFromCache:(LNodeSub;J)V
     990: iload         12
     992: iload         11
     994: aload         10
     996: invokestatic  #99                 // Method DrawingArea.initDrawingArea:(II[I)V
     999: iload         16
    1001: iload         13
    1003: iload         14
    1005: iload         15
    1007: invokestatic  #114                // Method DrawingArea.setDrawingArea:(IIII)V
    1010: iload         7
    1012: putstatic     #87                 // Field Texture.textureInt1:I
    1015: iload         8
    1017: putstatic     #88                 // Field Texture.textureInt2:I
    1020: aload         9
    1022: putstatic     #89                 // Field Texture.anIntArray1472:[I
    1025: iconst_1
    1026: putstatic     #97                 // Field Texture.aBoolean1464:Z
    1029: aload_3
    1030: getfield      #44                 // Field stackable:Z
    1033: ifeq          1046
    1036: aload         6
    1038: bipush        33
    1040: putfield      #111                // Field Sprite.anInt1444:I
    1043: goto          1053
    1046: aload         6
    1048: bipush        32
    1050: putfield      #111                // Field Sprite.anInt1444:I
    1053: aload         6
    1055: iload_1
    1056: putfield      #82                 // Field Sprite.anInt1445:I
    1059: aload         6
    1061: areturn

  public Model method201(int);
    Code:
       0: aload_0
       1: getfield      #49                 // Field stackIDs:[I
       4: ifnull        68
       7: iload_1
       8: iconst_1
       9: if_icmple     68
      12: iconst_m1
      13: istore_2
      14: iconst_0
      15: istore_3
      16: iload_3
      17: bipush        10
      19: if_icmpge     54
      22: iload_1
      23: aload_0
      24: getfield      #50                 // Field stackAmounts:[I
      27: iload_3
      28: iaload
      29: if_icmplt     48
      32: aload_0
      33: getfield      #50                 // Field stackAmounts:[I
      36: iload_3
      37: iaload
      38: ifeq          48
      41: aload_0
      42: getfield      #49                 // Field stackIDs:[I
      45: iload_3
      46: iaload
      47: istore_2
      48: iinc          3, 1
      51: goto          16
      54: iload_2
      55: iconst_m1
      56: if_icmpeq     68
      59: iload_2
      60: invokestatic  #69                 // Method forID:(I)LItemDef;
      63: iconst_1
      64: invokevirtual #84                 // Method method201:(I)LModel;
      67: areturn
      68: getstatic     #1                  // Field mruNodes2:LMRUNodes;
      71: aload_0
      72: getfield      #59                 // Field id:I
      75: i2l
      76: invokevirtual #80                 // Method MRUNodes.insertFromCache:(J)LNodeSub;
      79: checkcast     #21                 // class Model
      82: astore_2
      83: aload_2
      84: ifnull        89
      87: aload_2
      88: areturn
      89: aload_0
      90: getfield      #35                 // Field modelID:I
      93: invokestatic  #20                 // Method Model.method462:(I)LModel;
      96: astore_2
      97: aload_2
      98: ifnonnull     103
     101: aconst_null
     102: areturn
     103: aload_0
     104: getfield      #53                 // Field anInt167:I
     107: sipush        128
     110: if_icmpne     133
     113: aload_0
     114: getfield      #54                 // Field anInt192:I
     117: sipush        128
     120: if_icmpne     133
     123: aload_0
     124: getfield      #55                 // Field anInt191:I
     127: sipush        128
     130: if_icmpeq     149
     133: aload_2
     134: aload_0
     135: getfield      #53                 // Field anInt167:I
     138: aload_0
     139: getfield      #55                 // Field anInt191:I
     142: aload_0
     143: getfield      #54                 // Field anInt192:I
     146: invokevirtual #115                // Method Model.method478:(III)V
     149: aload_0
     150: getfield      #23                 // Field modifiedModelColors:[I
     153: ifnull        189
     156: iconst_0
     157: istore_3
     158: iload_3
     159: aload_0
     160: getfield      #23                 // Field modifiedModelColors:[I
     163: arraylength
     164: if_icmpge     189
     167: aload_2
     168: aload_0
     169: getfield      #23                 // Field modifiedModelColors:[I
     172: iload_3
     173: iaload
     174: aload_0
     175: getfield      #24                 // Field originalModelColors:[I
     178: iload_3
     179: iaload
     180: invokevirtual #25                 // Method Model.method476:(II)V
     183: iinc          3, 1
     186: goto          158
     189: aload_2
     190: bipush        64
     192: aload_0
     193: getfield      #56                 // Field anInt196:I
     196: iadd
     197: sipush        768
     200: aload_0
     201: getfield      #57                 // Field anInt184:I
     204: iadd
     205: bipush        -50
     207: bipush        -10
     209: bipush        -50
     211: iconst_1
     212: invokevirtual #116                // Method Model.method479:(IIIIIZ)V
     215: aload_2
     216: iconst_1
     217: putfield      #117                // Field Model.aBoolean1659:Z
     220: getstatic     #1                  // Field mruNodes2:LMRUNodes;
     223: aload_2
     224: aload_0
     225: getfield      #59                 // Field id:I
     228: i2l
     229: invokevirtual #113                // Method MRUNodes.removeFromCache:(LNodeSub;J)V
     232: aload_2
     233: areturn

  public Model method202(int);
    Code:
       0: aload_0
       1: getfield      #49                 // Field stackIDs:[I
       4: ifnull        68
       7: iload_1
       8: iconst_1
       9: if_icmple     68
      12: iconst_m1
      13: istore_2
      14: iconst_0
      15: istore_3
      16: iload_3
      17: bipush        10
      19: if_icmpge     54
      22: iload_1
      23: aload_0
      24: getfield      #50                 // Field stackAmounts:[I
      27: iload_3
      28: iaload
      29: if_icmplt     48
      32: aload_0
      33: getfield      #50                 // Field stackAmounts:[I
      36: iload_3
      37: iaload
      38: ifeq          48
      41: aload_0
      42: getfield      #49                 // Field stackIDs:[I
      45: iload_3
      46: iaload
      47: istore_2
      48: iinc          3, 1
      51: goto          16
      54: iload_2
      55: iconst_m1
      56: if_icmpeq     68
      59: iload_2
      60: invokestatic  #69                 // Method forID:(I)LItemDef;
      63: iconst_1
      64: invokevirtual #118                // Method method202:(I)LModel;
      67: areturn
      68: aload_0
      69: getfield      #35                 // Field modelID:I
      72: invokestatic  #20                 // Method Model.method462:(I)LModel;
      75: astore_2
      76: aload_2
      77: ifnonnull     82
      80: aconst_null
      81: areturn
      82: aload_0
      83: getfield      #23                 // Field modifiedModelColors:[I
      86: ifnull        122
      89: iconst_0
      90: istore_3
      91: iload_3
      92: aload_0
      93: getfield      #23                 // Field modifiedModelColors:[I
      96: arraylength
      97: if_icmpge     122
     100: aload_2
     101: aload_0
     102: getfield      #23                 // Field modifiedModelColors:[I
     105: iload_3
     106: iaload
     107: aload_0
     108: getfield      #24                 // Field originalModelColors:[I
     111: iload_3
     112: iaload
     113: invokevirtual #25                 // Method Model.method476:(II)V
     116: iinc          3, 1
     119: goto          91
     122: aload_2
     123: areturn

  private void readValues(Stream);
    Code:
       0: aload_1
       1: invokevirtual #119                // Method Stream.readUnsignedByte:()I
       4: istore_2
       5: iload_2
       6: ifne          10
       9: return
      10: iload_2
      11: iconst_1
      12: if_icmpne     26
      15: aload_0
      16: aload_1
      17: invokevirtual #16                 // Method Stream.readUnsignedWord:()I
      20: putfield      #35                 // Field modelID:I
      23: goto          822
      26: iload_2
      27: iconst_2
      28: if_icmpne     42
      31: aload_0
      32: aload_1
      33: invokevirtual #120                // Method Stream.readString:()Ljava/lang/String;
      36: putfield      #36                 // Field name:Ljava/lang/String;
      39: goto          822
      42: iload_2
      43: iconst_3
      44: if_icmpne     58
      47: aload_0
      48: aload_1
      49: invokevirtual #121                // Method Stream.readBytes:()[B
      52: putfield      #37                 // Field description:[B
      55: goto          822
      58: iload_2
      59: iconst_4
      60: if_icmpne     74
      63: aload_0
      64: aload_1
      65: invokevirtual #16                 // Method Stream.readUnsignedWord:()I
      68: putfield      #38                 // Field modelZoom:I
      71: goto          822
      74: iload_2
      75: iconst_5
      76: if_icmpne     90
      79: aload_0
      80: aload_1
      81: invokevirtual #16                 // Method Stream.readUnsignedWord:()I
      84: putfield      #39                 // Field modelRotation1:I
      87: goto          822
      90: iload_2
      91: bipush        6
      93: if_icmpne     107
      96: aload_0
      97: aload_1
      98: invokevirtual #16                 // Method Stream.readUnsignedWord:()I
     101: putfield      #40                 // Field modelRotation2:I
     104: goto          822
     107: iload_2
     108: bipush        7
     110: if_icmpne     145
     113: aload_0
     114: aload_1
     115: invokevirtual #16                 // Method Stream.readUnsignedWord:()I
     118: putfield      #42                 // Field modelOffset1:I
     121: aload_0
     122: getfield      #42                 // Field modelOffset1:I
     125: sipush        32767
     128: if_icmple     822
     131: aload_0
     132: dup
     133: getfield      #42                 // Field modelOffset1:I
     136: ldc           #122                // int 65536
     138: isub
     139: putfield      #42                 // Field modelOffset1:I
     142: goto          822
     145: iload_2
     146: bipush        8
     148: if_icmpne     183
     151: aload_0
     152: aload_1
     153: invokevirtual #16                 // Method Stream.readUnsignedWord:()I
     156: putfield      #43                 // Field modelOffset2:I
     159: aload_0
     160: getfield      #43                 // Field modelOffset2:I
     163: sipush        32767
     166: if_icmple     822
     169: aload_0
     170: dup
     171: getfield      #43                 // Field modelOffset2:I
     174: ldc           #122                // int 65536
     176: isub
     177: putfield      #43                 // Field modelOffset2:I
     180: goto          822
     183: iload_2
     184: bipush        10
     186: if_icmpne     197
     189: aload_1
     190: invokevirtual #16                 // Method Stream.readUnsignedWord:()I
     193: pop
     194: goto          822
     197: iload_2
     198: bipush        11
     200: if_icmpne     211
     203: aload_0
     204: iconst_1
     205: putfield      #44                 // Field stackable:Z
     208: goto          822
     211: iload_2
     212: bipush        12
     214: if_icmpne     228
     217: aload_0
     218: aload_1
     219: invokevirtual #123                // Method Stream.readDWord:()I
     222: putfield      #45                 // Field value:I
     225: goto          822
     228: iload_2
     229: bipush        16
     231: if_icmpne     242
     234: aload_0
     235: iconst_1
     236: putfield      #46                 // Field membersObject:Z
     239: goto          822
     242: iload_2
     243: bipush        23
     245: if_icmpne     267
     248: aload_0
     249: aload_1
     250: invokevirtual #16                 // Method Stream.readUnsignedWord:()I
     253: putfield      #26                 // Field anInt165:I
     256: aload_0
     257: aload_1
     258: invokevirtual #124                // Method Stream.readSignedByte:()B
     261: putfield      #32                 // Field aByte205:B
     264: goto          822
     267: iload_2
     268: bipush        24
     270: if_icmpne     284
     273: aload_0
     274: aload_1
     275: invokevirtual #16                 // Method Stream.readUnsignedWord:()I
     278: putfield      #27                 // Field anInt188:I
     281: goto          822
     284: iload_2
     285: bipush        25
     287: if_icmpne     309
     290: aload_0
     291: aload_1
     292: invokevirtual #16                 // Method Stream.readUnsignedWord:()I
     295: putfield      #29                 // Field anInt200:I
     298: aload_0
     299: aload_1
     300: invokevirtual #124                // Method Stream.readSignedByte:()B
     303: putfield      #34                 // Field aByte154:B
     306: goto          822
     309: iload_2
     310: bipush        26
     312: if_icmpne     326
     315: aload_0
     316: aload_1
     317: invokevirtual #16                 // Method Stream.readUnsignedWord:()I
     320: putfield      #30                 // Field anInt164:I
     323: goto          822
     326: iload_2
     327: bipush        30
     329: if_icmplt     396
     332: iload_2
     333: bipush        35
     335: if_icmpge     396
     338: aload_0
     339: getfield      #47                 // Field groundActions:[Ljava/lang/String;
     342: ifnonnull     353
     345: aload_0
     346: iconst_5
     347: anewarray     #125                // class java/lang/String
     350: putfield      #47                 // Field groundActions:[Ljava/lang/String;
     353: aload_0
     354: getfield      #47                 // Field groundActions:[Ljava/lang/String;
     357: iload_2
     358: bipush        30
     360: isub
     361: aload_1
     362: invokevirtual #120                // Method Stream.readString:()Ljava/lang/String;
     365: aastore
     366: aload_0
     367: getfield      #47                 // Field groundActions:[Ljava/lang/String;
     370: iload_2
     371: bipush        30
     373: isub
     374: aaload
     375: ldc           #126                // String hidden
     377: invokevirtual #127                // Method java/lang/String.equalsIgnoreCase:(Ljava/lang/String;)Z
     380: ifeq          822
     383: aload_0
     384: getfield      #47                 // Field groundActions:[Ljava/lang/String;
     387: iload_2
     388: bipush        30
     390: isub
     391: aconst_null
     392: aastore
     393: goto          822
     396: iload_2
     397: bipush        35
     399: if_icmplt     439
     402: iload_2
     403: bipush        40
     405: if_icmpge     439
     408: aload_0
     409: getfield      #48                 // Field actions:[Ljava/lang/String;
     412: ifnonnull     423
     415: aload_0
     416: iconst_5
     417: anewarray     #125                // class java/lang/String
     420: putfield      #48                 // Field actions:[Ljava/lang/String;
     423: aload_0
     424: getfield      #48                 // Field actions:[Ljava/lang/String;
     427: iload_2
     428: bipush        35
     430: isub
     431: aload_1
     432: invokevirtual #120                // Method Stream.readString:()Ljava/lang/String;
     435: aastore
     436: goto          822
     439: iload_2
     440: bipush        40
     442: if_icmpne     504
     445: aload_1
     446: invokevirtual #119                // Method Stream.readUnsignedByte:()I
     449: istore_3
     450: aload_0
     451: iload_3
     452: newarray       int
     454: putfield      #23                 // Field modifiedModelColors:[I
     457: aload_0
     458: iload_3
     459: newarray       int
     461: putfield      #24                 // Field originalModelColors:[I
     464: iconst_0
     465: istore        4
     467: iload         4
     469: iload_3
     470: if_icmpge     501
     473: aload_0
     474: getfield      #23                 // Field modifiedModelColors:[I
     477: iload         4
     479: aload_1
     480: invokevirtual #16                 // Method Stream.readUnsignedWord:()I
     483: iastore
     484: aload_0
     485: getfield      #24                 // Field originalModelColors:[I
     488: iload         4
     490: aload_1
     491: invokevirtual #16                 // Method Stream.readUnsignedWord:()I
     494: iastore
     495: iinc          4, 1
     498: goto          467
     501: goto          822
     504: iload_2
     505: bipush        78
     507: if_icmpne     521
     510: aload_0
     511: aload_1
     512: invokevirtual #16                 // Method Stream.readUnsignedWord:()I
     515: putfield      #28                 // Field anInt185:I
     518: goto          822
     521: iload_2
     522: bipush        79
     524: if_icmpne     538
     527: aload_0
     528: aload_1
     529: invokevirtual #16                 // Method Stream.readUnsignedWord:()I
     532: putfield      #31                 // Field anInt162:I
     535: goto          822
     538: iload_2
     539: bipush        90
     541: if_icmpne     555
     544: aload_0
     545: aload_1
     546: invokevirtual #16                 // Method Stream.readUnsignedWord:()I
     549: putfield      #6                  // Field anInt175:I
     552: goto          822
     555: iload_2
     556: bipush        91
     558: if_icmpne     572
     561: aload_0
     562: aload_1
     563: invokevirtual #16                 // Method Stream.readUnsignedWord:()I
     566: putfield      #8                  // Field anInt197:I
     569: goto          822
     572: iload_2
     573: bipush        92
     575: if_icmpne     589
     578: aload_0
     579: aload_1
     580: invokevirtual #16                 // Method Stream.readUnsignedWord:()I
     583: putfield      #7                  // Field anInt166:I
     586: goto          822
     589: iload_2
     590: bipush        93
     592: if_icmpne     606
     595: aload_0
     596: aload_1
     597: invokevirtual #16                 // Method Stream.readUnsignedWord:()I
     600: putfield      #9                  // Field anInt173:I
     603: goto          822
     606: iload_2
     607: bipush        95
     609: if_icmpne     623
     612: aload_0
     613: aload_1
     614: invokevirtual #16                 // Method Stream.readUnsignedWord:()I
     617: putfield      #41                 // Field anInt204:I
     620: goto          822
     623: iload_2
     624: bipush        97
     626: if_icmpne     640
     629: aload_0
     630: aload_1
     631: invokevirtual #16                 // Method Stream.readUnsignedWord:()I
     634: putfield      #51                 // Field certID:I
     637: goto          822
     640: iload_2
     641: bipush        98
     643: if_icmpne     657
     646: aload_0
     647: aload_1
     648: invokevirtual #16                 // Method Stream.readUnsignedWord:()I
     651: putfield      #52                 // Field certTemplateID:I
     654: goto          822
     657: iload_2
     658: bipush        100
     660: if_icmplt     721
     663: iload_2
     664: bipush        110
     666: if_icmpge     721
     669: aload_0
     670: getfield      #49                 // Field stackIDs:[I
     673: ifnonnull     692
     676: aload_0
     677: bipush        10
     679: newarray       int
     681: putfield      #49                 // Field stackIDs:[I
     684: aload_0
     685: bipush        10
     687: newarray       int
     689: putfield      #50                 // Field stackAmounts:[I
     692: aload_0
     693: getfield      #49                 // Field stackIDs:[I
     696: iload_2
     697: bipush        100
     699: isub
     700: aload_1
     701: invokevirtual #16                 // Method Stream.readUnsignedWord:()I
     704: iastore
     705: aload_0
     706: getfield      #50                 // Field stackAmounts:[I
     709: iload_2
     710: bipush        100
     712: isub
     713: aload_1
     714: invokevirtual #16                 // Method Stream.readUnsignedWord:()I
     717: iastore
     718: goto          822
     721: iload_2
     722: bipush        110
     724: if_icmpne     738
     727: aload_0
     728: aload_1
     729: invokevirtual #16                 // Method Stream.readUnsignedWord:()I
     732: putfield      #53                 // Field anInt167:I
     735: goto          822
     738: iload_2
     739: bipush        111
     741: if_icmpne     755
     744: aload_0
     745: aload_1
     746: invokevirtual #16                 // Method Stream.readUnsignedWord:()I
     749: putfield      #54                 // Field anInt192:I
     752: goto          822
     755: iload_2
     756: bipush        112
     758: if_icmpne     772
     761: aload_0
     762: aload_1
     763: invokevirtual #16                 // Method Stream.readUnsignedWord:()I
     766: putfield      #55                 // Field anInt191:I
     769: goto          822
     772: iload_2
     773: bipush        113
     775: if_icmpne     789
     778: aload_0
     779: aload_1
     780: invokevirtual #124                // Method Stream.readSignedByte:()B
     783: putfield      #56                 // Field anInt196:I
     786: goto          822
     789: iload_2
     790: bipush        114
     792: if_icmpne     808
     795: aload_0
     796: aload_1
     797: invokevirtual #124                // Method Stream.readSignedByte:()B
     800: iconst_5
     801: imul
     802: putfield      #57                 // Field anInt184:I
     805: goto          822
     808: iload_2
     809: bipush        115
     811: if_icmpne     822
     814: aload_0
     815: aload_1
     816: invokevirtual #119                // Method Stream.readUnsignedByte:()I
     819: putfield      #58                 // Field team:I
     822: goto          0

  private ItemDef();
    Code:
       0: aload_0
       1: invokespecial #128                // Method java/lang/Object."<init>":()V
       4: aload_0
       5: iconst_m1
       6: putfield      #59                 // Field id:I
       9: return

  static {};
    Code:
       0: new           #129                // class MRUNodes
       3: dup
       4: bipush        100
       6: invokespecial #130                // Method MRUNodes."<init>":(I)V
       9: putstatic     #2                  // Field mruNodes1:LMRUNodes;
      12: new           #129                // class MRUNodes
      15: dup
      16: bipush        50
      18: invokespecial #130                // Method MRUNodes."<init>":(I)V
      21: putstatic     #1                  // Field mruNodes2:LMRUNodes;
      24: iconst_1
      25: putstatic     #65                 // Field isMembers:Z
      28: return
}
