Compiled from "NodeCache.java"
final class NodeCache {
  private final int size;

  private final Node[] cache;

  public NodeCache();
    Code:
       0: aload_0
       1: invokespecial #1                  // Method java/lang/Object."<init>":()V
       4: sipush        1024
       7: istore_1
       8: aload_0
       9: iload_1
      10: putfield      #2                  // Field size:I
      13: aload_0
      14: iload_1
      15: anewarray     #3                  // class Node
      18: putfield      #4                  // Field cache:[LNode;
      21: iconst_0
      22: istore_2
      23: iload_2
      24: iload_1
      25: if_icmpge     59
      28: aload_0
      29: getfield      #4                  // Field cache:[LNode;
      32: iload_2
      33: new           #3                  // class Node
      36: dup
      37: invokespecial #5                  // Method Node."<init>":()V
      40: dup_x2
      41: aastore
      42: astore_3
      43: aload_3
      44: aload_3
      45: putfield      #6                  // Field Node.prev:LNode;
      48: aload_3
      49: aload_3
      50: putfield      #7                  // Field Node.next:LNode;
      53: iinc          2, 1
      56: goto          23
      59: return

  public Node findNodeByID(long);
    Code:
       0: aload_0
       1: getfield      #4                  // Field cache:[LNode;
       4: lload_1
       5: aload_0
       6: getfield      #2                  // Field size:I
       9: iconst_1
      10: isub
      11: i2l
      12: land
      13: l2i
      14: aaload
      15: astore_3
      16: aload_3
      17: getfield      #6                  // Field Node.prev:LNode;
      20: astore        4
      22: aload         4
      24: aload_3
      25: if_acmpeq     51
      28: aload         4
      30: getfield      #8                  // Field Node.id:J
      33: lload_1
      34: lcmp
      35: ifne          41
      38: aload         4
      40: areturn
      41: aload         4
      43: getfield      #6                  // Field Node.prev:LNode;
      46: astore        4
      48: goto          22
      51: aconst_null
      52: areturn

  public void removeFromCache(Node, long);
    Code:
       0: aload_1
       1: getfield      #7                  // Field Node.next:LNode;
       4: ifnull        11
       7: aload_1
       8: invokevirtual #9                  // Method Node.unlink:()V
      11: aload_0
      12: getfield      #4                  // Field cache:[LNode;
      15: lload_2
      16: aload_0
      17: getfield      #2                  // Field size:I
      20: iconst_1
      21: isub
      22: i2l
      23: land
      24: l2i
      25: aaload
      26: astore        4
      28: aload_1
      29: aload         4
      31: getfield      #7                  // Field Node.next:LNode;
      34: putfield      #7                  // Field Node.next:LNode;
      37: aload_1
      38: aload         4
      40: putfield      #6                  // Field Node.prev:LNode;
      43: aload_1
      44: getfield      #7                  // Field Node.next:LNode;
      47: aload_1
      48: putfield      #6                  // Field Node.prev:LNode;
      51: aload_1
      52: getfield      #6                  // Field Node.prev:LNode;
      55: aload_1
      56: putfield      #7                  // Field Node.next:LNode;
      59: aload_1
      60: lload_2
      61: putfield      #8                  // Field Node.id:J
      64: return
      65: astore        4
      67: new           #11                 // class java/lang/StringBuilder
      70: dup
      71: invokespecial #12                 // Method java/lang/StringBuilder."<init>":()V
      74: ldc           #13                 // String 91499,
      76: invokevirtual #14                 // Method java/lang/StringBuilder.append:(Ljava/lang/String;)Ljava/lang/StringBuilder;
      79: aload_1
      80: invokevirtual #15                 // Method java/lang/StringBuilder.append:(Ljava/lang/Object;)Ljava/lang/StringBuilder;
      83: ldc           #16                 // String ,
      85: invokevirtual #14                 // Method java/lang/StringBuilder.append:(Ljava/lang/String;)Ljava/lang/StringBuilder;
      88: lload_2
      89: invokevirtual #17                 // Method java/lang/StringBuilder.append:(J)Ljava/lang/StringBuilder;
      92: ldc           #16                 // String ,
      94: invokevirtual #14                 // Method java/lang/StringBuilder.append:(Ljava/lang/String;)Ljava/lang/StringBuilder;
      97: bipush        7
      99: invokevirtual #18                 // Method java/lang/StringBuilder.append:(I)Ljava/lang/StringBuilder;
     102: ldc           #16                 // String ,
     104: invokevirtual #14                 // Method java/lang/StringBuilder.append:(Ljava/lang/String;)Ljava/lang/StringBuilder;
     107: aload         4
     109: invokevirtual #19                 // Method java/lang/RuntimeException.toString:()Ljava/lang/String;
     112: invokevirtual #14                 // Method java/lang/StringBuilder.append:(Ljava/lang/String;)Ljava/lang/StringBuilder;
     115: invokevirtual #20                 // Method java/lang/StringBuilder.toString:()Ljava/lang/String;
     118: invokestatic  #21                 // Method sign/signlink.reporterror:(Ljava/lang/String;)V
     121: new           #10                 // class java/lang/RuntimeException
     124: dup
     125: invokespecial #22                 // Method java/lang/RuntimeException."<init>":()V
     128: athrow
    Exception table:
       from    to  target type
           0    64    65   Class java/lang/RuntimeException
}
