Compiled from "Node.java"
public class Node {
  public long id;

  public Node prev;

  public Node next;

  public final void unlink();
    Code:
       0: aload_0
       1: getfield      #1                  // Field next:LNode;
       4: ifnonnull     10
       7: goto          42
      10: aload_0
      11: getfield      #1                  // Field next:LNode;
      14: aload_0
      15: getfield      #2                  // Field prev:LNode;
      18: putfield      #2                  // Field prev:LNode;
      21: aload_0
      22: getfield      #2                  // Field prev:LNode;
      25: aload_0
      26: getfield      #1                  // Field next:LNode;
      29: putfield      #1                  // Field next:LNode;
      32: aload_0
      33: aconst_null
      34: putfield      #2                  // Field prev:LNode;
      37: aload_0
      38: aconst_null
      39: putfield      #1                  // Field next:LNode;
      42: return

  public Node();
    Code:
       0: aload_0
       1: invokespecial #3                  // Method java/lang/Object."<init>":()V
       4: return
}
