Compiled from "ObjectDef.java"
public final class ObjectDef {
  public boolean aBoolean736;

  private byte aByte737;

  private int anInt738;

  public java.lang.String name;

  private int anInt740;

  private static final Model[] aModelArray741s;

  private byte aByte742;

  public int anInt744;

  private int anInt745;

  public int anInt746;

  private int[] originalModelColors;

  private int anInt748;

  public int anInt749;

  private boolean aBoolean751;

  public static boolean lowMem;

  private static Stream stream;

  public int type;

  private static int[] streamIndices;

  public boolean aBoolean757;

  public int anInt758;

  public int[] childrenIDs;

  private int anInt760;

  public int anInt761;

  public boolean aBoolean762;

  public boolean aBoolean764;

  public static client clientInstance;

  private boolean aBoolean766;

  public boolean aBoolean767;

  public int anInt768;

  private boolean aBoolean769;

  private static int cacheIndex;

  private int anInt772;

  private int[] anIntArray773;

  public int anInt774;

  public int anInt775;

  private int[] anIntArray776;

  public byte[] description;

  public boolean hasActions;

  public boolean aBoolean779;

  public static MRUNodes mruNodes2;

  public int anInt781;

  private static ObjectDef[] cache;

  private int anInt783;

  private int[] modifiedModelColors;

  public static MRUNodes mruNodes1;

  public java.lang.String[] actions;

  public static ObjectDef forID(int);
    Code:
       0: iconst_0
       1: istore_1
       2: iload_1
       3: bipush        20
       5: if_icmpge     32
       8: getstatic     #1                  // Field cache:[LObjectDef;
      11: iload_1
      12: aaload
      13: getfield      #2                  // Field type:I
      16: iload_0
      17: if_icmpne     26
      20: getstatic     #1                  // Field cache:[LObjectDef;
      23: iload_1
      24: aaload
      25: areturn
      26: iinc          1, 1
      29: goto          2
      32: getstatic     #3                  // Field cacheIndex:I
      35: iconst_1
      36: iadd
      37: bipush        20
      39: irem
      40: putstatic     #3                  // Field cacheIndex:I
      43: getstatic     #1                  // Field cache:[LObjectDef;
      46: getstatic     #3                  // Field cacheIndex:I
      49: aaload
      50: astore_1
      51: getstatic     #4                  // Field stream:LStream;
      54: getstatic     #5                  // Field streamIndices:[I
      57: iload_0
      58: iaload
      59: putfield      #6                  // Field Stream.currentOffset:I
      62: aload_1
      63: iload_0
      64: putfield      #2                  // Field type:I
      67: aload_1
      68: invokespecial #7                  // Method setDefaults:()V
      71: aload_1
      72: getstatic     #4                  // Field stream:LStream;
      75: invokespecial #8                  // Method readValues:(LStream;)V
      78: aload_1
      79: areturn

  private void setDefaults();
    Code:
       0: aload_0
       1: aconst_null
       2: putfield      #9                  // Field anIntArray773:[I
       5: aload_0
       6: aconst_null
       7: putfield      #10                 // Field anIntArray776:[I
      10: aload_0
      11: aconst_null
      12: putfield      #11                 // Field name:Ljava/lang/String;
      15: aload_0
      16: aconst_null
      17: putfield      #12                 // Field description:[B
      20: aload_0
      21: aconst_null
      22: putfield      #13                 // Field modifiedModelColors:[I
      25: aload_0
      26: aconst_null
      27: putfield      #14                 // Field originalModelColors:[I
      30: aload_0
      31: iconst_1
      32: putfield      #15                 // Field anInt744:I
      35: aload_0
      36: iconst_1
      37: putfield      #16                 // Field anInt761:I
      40: aload_0
      41: iconst_1
      42: putfield      #17                 // Field aBoolean767:Z
      45: aload_0
      46: iconst_1
      47: putfield      #18                 // Field aBoolean757:Z
      50: aload_0
      51: iconst_0
      52: putfield      #19                 // Field hasActions:Z
      55: aload_0
      56: iconst_0
      57: putfield      #20                 // Field aBoolean762:Z
      60: aload_0
      61: iconst_0
      62: putfield      #21                 // Field aBoolean769:Z
      65: aload_0
      66: iconst_0
      67: putfield      #22                 // Field aBoolean764:Z
      70: aload_0
      71: iconst_m1
      72: putfield      #23                 // Field anInt781:I
      75: aload_0
      76: bipush        16
      78: putfield      #24                 // Field anInt775:I
      81: aload_0
      82: iconst_0
      83: putfield      #25                 // Field aByte737:B
      86: aload_0
      87: iconst_0
      88: putfield      #26                 // Field aByte742:B
      91: aload_0
      92: aconst_null
      93: putfield      #27                 // Field actions:[Ljava/lang/String;
      96: aload_0
      97: iconst_m1
      98: putfield      #28                 // Field anInt746:I
     101: aload_0
     102: iconst_m1
     103: putfield      #29                 // Field anInt758:I
     106: aload_0
     107: iconst_0
     108: putfield      #30                 // Field aBoolean751:Z
     111: aload_0
     112: iconst_1
     113: putfield      #31                 // Field aBoolean779:Z
     116: aload_0
     117: sipush        128
     120: putfield      #32                 // Field anInt748:I
     123: aload_0
     124: sipush        128
     127: putfield      #33                 // Field anInt772:I
     130: aload_0
     131: sipush        128
     134: putfield      #34                 // Field anInt740:I
     137: aload_0
     138: iconst_0
     139: putfield      #35                 // Field anInt768:I
     142: aload_0
     143: iconst_0
     144: putfield      #36                 // Field anInt738:I
     147: aload_0
     148: iconst_0
     149: putfield      #37                 // Field anInt745:I
     152: aload_0
     153: iconst_0
     154: putfield      #38                 // Field anInt783:I
     157: aload_0
     158: iconst_0
     159: putfield      #39                 // Field aBoolean736:Z
     162: aload_0
     163: iconst_0
     164: putfield      #40                 // Field aBoolean766:Z
     167: aload_0
     168: iconst_m1
     169: putfield      #41                 // Field anInt760:I
     172: aload_0
     173: iconst_m1
     174: putfield      #42                 // Field anInt774:I
     177: aload_0
     178: iconst_m1
     179: putfield      #43                 // Field anInt749:I
     182: aload_0
     183: aconst_null
     184: putfield      #44                 // Field childrenIDs:[I
     187: return

  public void method574(OnDemandFetcher);
    Code:
       0: aload_0
       1: getfield      #9                  // Field anIntArray773:[I
       4: ifnonnull     8
       7: return
       8: iconst_0
       9: istore_2
      10: iload_2
      11: aload_0
      12: getfield      #9                  // Field anIntArray773:[I
      15: arraylength
      16: if_icmpge     39
      19: aload_1
      20: aload_0
      21: getfield      #9                  // Field anIntArray773:[I
      24: iload_2
      25: iaload
      26: ldc           #45                 // int 65535
      28: iand
      29: iconst_0
      30: invokevirtual #46                 // Method OnDemandFetcher.method560:(II)V
      33: iinc          2, 1
      36: goto          10
      39: return

  public static void nullLoader();
    Code:
       0: aconst_null
       1: putstatic     #47                 // Field mruNodes1:LMRUNodes;
       4: aconst_null
       5: putstatic     #48                 // Field mruNodes2:LMRUNodes;
       8: aconst_null
       9: putstatic     #5                  // Field streamIndices:[I
      12: aconst_null
      13: putstatic     #1                  // Field cache:[LObjectDef;
      16: aconst_null
      17: putstatic     #4                  // Field stream:LStream;
      20: return

  public static void unpackConfig(StreamLoader);
    Code:
       0: new           #49                 // class Stream
       3: dup
       4: aload_0
       5: ldc           #50                 // String loc.dat
       7: invokevirtual #51                 // Method StreamLoader.getDataForName:(Ljava/lang/String;)[B
      10: invokespecial #52                 // Method Stream."<init>":([B)V
      13: putstatic     #4                  // Field stream:LStream;
      16: new           #49                 // class Stream
      19: dup
      20: aload_0
      21: ldc           #53                 // String loc.idx
      23: invokevirtual #51                 // Method StreamLoader.getDataForName:(Ljava/lang/String;)[B
      26: invokespecial #52                 // Method Stream."<init>":([B)V
      29: astore_1
      30: aload_1
      31: invokevirtual #54                 // Method Stream.readUnsignedWord:()I
      34: istore_2
      35: iload_2
      36: newarray       int
      38: putstatic     #5                  // Field streamIndices:[I
      41: iconst_2
      42: istore_3
      43: iconst_0
      44: istore        4
      46: iload         4
      48: iload_2
      49: if_icmpge     72
      52: getstatic     #5                  // Field streamIndices:[I
      55: iload         4
      57: iload_3
      58: iastore
      59: iload_3
      60: aload_1
      61: invokevirtual #54                 // Method Stream.readUnsignedWord:()I
      64: iadd
      65: istore_3
      66: iinc          4, 1
      69: goto          46
      72: bipush        20
      74: anewarray     #55                 // class ObjectDef
      77: putstatic     #1                  // Field cache:[LObjectDef;
      80: iconst_0
      81: istore        4
      83: iload         4
      85: bipush        20
      87: if_icmpge     109
      90: getstatic     #1                  // Field cache:[LObjectDef;
      93: iload         4
      95: new           #55                 // class ObjectDef
      98: dup
      99: invokespecial #56                 // Method "<init>":()V
     102: aastore
     103: iinc          4, 1
     106: goto          83
     109: return

  public boolean method577(int);
    Code:
       0: aload_0
       1: getfield      #10                 // Field anIntArray776:[I
       4: ifnonnull     60
       7: aload_0
       8: getfield      #9                  // Field anIntArray773:[I
      11: ifnonnull     16
      14: iconst_1
      15: ireturn
      16: iload_1
      17: bipush        10
      19: if_icmpeq     24
      22: iconst_1
      23: ireturn
      24: iconst_1
      25: istore_2
      26: iconst_0
      27: istore_3
      28: iload_3
      29: aload_0
      30: getfield      #9                  // Field anIntArray773:[I
      33: arraylength
      34: if_icmpge     58
      37: iload_2
      38: aload_0
      39: getfield      #9                  // Field anIntArray773:[I
      42: iload_3
      43: iaload
      44: ldc           #45                 // int 65535
      46: iand
      47: invokestatic  #57                 // Method Model.method463:(I)Z
      50: iand
      51: istore_2
      52: iinc          3, 1
      55: goto          28
      58: iload_2
      59: ireturn
      60: iconst_0
      61: istore_2
      62: iload_2
      63: aload_0
      64: getfield      #10                 // Field anIntArray776:[I
      67: arraylength
      68: if_icmpge     100
      71: aload_0
      72: getfield      #10                 // Field anIntArray776:[I
      75: iload_2
      76: iaload
      77: iload_1
      78: if_icmpne     94
      81: aload_0
      82: getfield      #9                  // Field anIntArray773:[I
      85: iload_2
      86: iaload
      87: ldc           #45                 // int 65535
      89: iand
      90: invokestatic  #57                 // Method Model.method463:(I)Z
      93: ireturn
      94: iinc          2, 1
      97: goto          62
     100: iconst_1
     101: ireturn

  public Model method578(int, int, int, int, int, int, int);
    Code:
       0: aload_0
       1: iload_1
       2: iload         7
       4: iload_2
       5: invokespecial #58                 // Method method581:(III)LModel;
       8: astore        8
      10: aload         8
      12: ifnonnull     17
      15: aconst_null
      16: areturn
      17: aload_0
      18: getfield      #20                 // Field aBoolean762:Z
      21: ifne          31
      24: aload_0
      25: getfield      #21                 // Field aBoolean769:Z
      28: ifeq          50
      31: new           #59                 // class Model
      34: dup
      35: aload_0
      36: getfield      #20                 // Field aBoolean762:Z
      39: aload_0
      40: getfield      #21                 // Field aBoolean769:Z
      43: aload         8
      45: invokespecial #60                 // Method Model."<init>":(ZZLModel;)V
      48: astore        8
      50: aload_0
      51: getfield      #20                 // Field aBoolean762:Z
      54: ifeq          189
      57: iload_3
      58: iload         4
      60: iadd
      61: iload         5
      63: iadd
      64: iload         6
      66: iadd
      67: iconst_4
      68: idiv
      69: istore        9
      71: iconst_0
      72: istore        10
      74: iload         10
      76: aload         8
      78: getfield      #61                 // Field Model.anInt1626:I
      81: if_icmpge     184
      84: aload         8
      86: getfield      #62                 // Field Model.anIntArray1627:[I
      89: iload         10
      91: iaload
      92: istore        11
      94: aload         8
      96: getfield      #63                 // Field Model.anIntArray1629:[I
      99: iload         10
     101: iaload
     102: istore        12
     104: iload_3
     105: iload         4
     107: iload_3
     108: isub
     109: iload         11
     111: bipush        64
     113: iadd
     114: imul
     115: sipush        128
     118: idiv
     119: iadd
     120: istore        13
     122: iload         6
     124: iload         5
     126: iload         6
     128: isub
     129: iload         11
     131: bipush        64
     133: iadd
     134: imul
     135: sipush        128
     138: idiv
     139: iadd
     140: istore        14
     142: iload         13
     144: iload         14
     146: iload         13
     148: isub
     149: iload         12
     151: bipush        64
     153: iadd
     154: imul
     155: sipush        128
     158: idiv
     159: iadd
     160: istore        15
     162: aload         8
     164: getfield      #64                 // Field Model.anIntArray1628:[I
     167: iload         10
     169: dup2
     170: iaload
     171: iload         15
     173: iload         9
     175: isub
     176: iadd
     177: iastore
     178: iinc          10, 1
     181: goto          74
     184: aload         8
     186: invokevirtual #65                 // Method Model.method467:()V
     189: aload         8
     191: areturn

  public boolean method579();
    Code:
       0: aload_0
       1: getfield      #9                  // Field anIntArray773:[I
       4: ifnonnull     9
       7: iconst_1
       8: ireturn
       9: iconst_1
      10: istore_1
      11: iconst_0
      12: istore_2
      13: iload_2
      14: aload_0
      15: getfield      #9                  // Field anIntArray773:[I
      18: arraylength
      19: if_icmpge     43
      22: iload_1
      23: aload_0
      24: getfield      #9                  // Field anIntArray773:[I
      27: iload_2
      28: iaload
      29: ldc           #45                 // int 65535
      31: iand
      32: invokestatic  #57                 // Method Model.method463:(I)Z
      35: iand
      36: istore_1
      37: iinc          2, 1
      40: goto          13
      43: iload_1
      44: ireturn

  public ObjectDef method580();
    Code:
       0: iconst_m1
       1: istore_1
       2: aload_0
       3: getfield      #42                 // Field anInt774:I
       6: iconst_m1
       7: if_icmpeq     65
      10: getstatic     #66                 // Field VarBit.cache:[LVarBit;
      13: aload_0
      14: getfield      #42                 // Field anInt774:I
      17: aaload
      18: astore_2
      19: aload_2
      20: getfield      #67                 // Field VarBit.anInt648:I
      23: istore_3
      24: aload_2
      25: getfield      #68                 // Field VarBit.anInt649:I
      28: istore        4
      30: aload_2
      31: getfield      #69                 // Field VarBit.anInt650:I
      34: istore        5
      36: getstatic     #70                 // Field client.anIntArray1232:[I
      39: iload         5
      41: iload         4
      43: isub
      44: iaload
      45: istore        6
      47: getstatic     #71                 // Field clientInstance:Lclient;
      50: getfield      #72                 // Field client.variousSettings:[I
      53: iload_3
      54: iaload
      55: iload         4
      57: ishr
      58: iload         6
      60: iand
      61: istore_1
      62: goto          85
      65: aload_0
      66: getfield      #43                 // Field anInt749:I
      69: iconst_m1
      70: if_icmpeq     85
      73: getstatic     #71                 // Field clientInstance:Lclient;
      76: getfield      #72                 // Field client.variousSettings:[I
      79: aload_0
      80: getfield      #43                 // Field anInt749:I
      83: iaload
      84: istore_1
      85: iload_1
      86: iflt          108
      89: iload_1
      90: aload_0
      91: getfield      #44                 // Field childrenIDs:[I
      94: arraylength
      95: if_icmpge     108
      98: aload_0
      99: getfield      #44                 // Field childrenIDs:[I
     102: iload_1
     103: iaload
     104: iconst_m1
     105: if_icmpne     110
     108: aconst_null
     109: areturn
     110: aload_0
     111: getfield      #44                 // Field childrenIDs:[I
     114: iload_1
     115: iaload
     116: invokestatic  #73                 // Method forID:(I)LObjectDef;
     119: areturn

  private Model method581(int, int, int);
    Code:
       0: aconst_null
       1: astore        4
       3: aload_0
       4: getfield      #10                 // Field anIntArray776:[I
       7: ifnonnull     223
      10: iload_1
      11: bipush        10
      13: if_icmpeq     18
      16: aconst_null
      17: areturn
      18: aload_0
      19: getfield      #2                  // Field type:I
      22: bipush        6
      24: ishl
      25: iload_3
      26: iadd
      27: i2l
      28: iload_2
      29: iconst_1
      30: iadd
      31: i2l
      32: bipush        32
      34: lshl
      35: ladd
      36: lstore        5
      38: getstatic     #48                 // Field mruNodes2:LMRUNodes;
      41: lload         5
      43: invokevirtual #74                 // Method MRUNodes.insertFromCache:(J)LNodeSub;
      46: checkcast     #59                 // class Model
      49: astore        7
      51: aload         7
      53: ifnull        59
      56: aload         7
      58: areturn
      59: aload_0
      60: getfield      #9                  // Field anIntArray773:[I
      63: ifnonnull     68
      66: aconst_null
      67: areturn
      68: aload_0
      69: getfield      #30                 // Field aBoolean751:Z
      72: iload_3
      73: iconst_3
      74: if_icmple     81
      77: iconst_1
      78: goto          82
      81: iconst_0
      82: ixor
      83: istore        8
      85: aload_0
      86: getfield      #9                  // Field anIntArray773:[I
      89: arraylength
      90: istore        9
      92: iconst_0
      93: istore        10
      95: iload         10
      97: iload         9
      99: if_icmpge     200
     102: aload_0
     103: getfield      #9                  // Field anIntArray773:[I
     106: iload         10
     108: iaload
     109: istore        11
     111: iload         8
     113: ifeq          123
     116: iload         11
     118: ldc           #75                 // int 65536
     120: iadd
     121: istore        11
     123: getstatic     #47                 // Field mruNodes1:LMRUNodes;
     126: iload         11
     128: i2l
     129: invokevirtual #74                 // Method MRUNodes.insertFromCache:(J)LNodeSub;
     132: checkcast     #59                 // class Model
     135: astore        4
     137: aload         4
     139: ifnonnull     180
     142: iload         11
     144: ldc           #45                 // int 65535
     146: iand
     147: invokestatic  #76                 // Method Model.method462:(I)LModel;
     150: astore        4
     152: aload         4
     154: ifnonnull     159
     157: aconst_null
     158: areturn
     159: iload         8
     161: ifeq          169
     164: aload         4
     166: invokevirtual #77                 // Method Model.method477:()V
     169: getstatic     #47                 // Field mruNodes1:LMRUNodes;
     172: aload         4
     174: iload         11
     176: i2l
     177: invokevirtual #78                 // Method MRUNodes.removeFromCache:(LNodeSub;J)V
     180: iload         9
     182: iconst_1
     183: if_icmple     194
     186: getstatic     #79                 // Field aModelArray741s:[LModel;
     189: iload         10
     191: aload         4
     193: aastore
     194: iinc          10, 1
     197: goto          95
     200: iload         9
     202: iconst_1
     203: if_icmple     220
     206: new           #59                 // class Model
     209: dup
     210: iload         9
     212: getstatic     #79                 // Field aModelArray741s:[LModel;
     215: invokespecial #80                 // Method Model."<init>":(I[LModel;)V
     218: astore        4
     220: goto          415
     223: iconst_m1
     224: istore        7
     226: iconst_0
     227: istore        8
     229: iload         8
     231: aload_0
     232: getfield      #10                 // Field anIntArray776:[I
     235: arraylength
     236: if_icmpge     266
     239: aload_0
     240: getfield      #10                 // Field anIntArray776:[I
     243: iload         8
     245: iaload
     246: iload_1
     247: if_icmpeq     253
     250: goto          260
     253: iload         8
     255: istore        7
     257: goto          266
     260: iinc          8, 1
     263: goto          229
     266: iload         7
     268: iconst_m1
     269: if_icmpne     274
     272: aconst_null
     273: areturn
     274: aload_0
     275: getfield      #2                  // Field type:I
     278: bipush        6
     280: ishl
     281: iload         7
     283: iconst_3
     284: ishl
     285: iadd
     286: iload_3
     287: iadd
     288: i2l
     289: iload_2
     290: iconst_1
     291: iadd
     292: i2l
     293: bipush        32
     295: lshl
     296: ladd
     297: lstore        5
     299: getstatic     #48                 // Field mruNodes2:LMRUNodes;
     302: lload         5
     304: invokevirtual #74                 // Method MRUNodes.insertFromCache:(J)LNodeSub;
     307: checkcast     #59                 // class Model
     310: astore        8
     312: aload         8
     314: ifnull        320
     317: aload         8
     319: areturn
     320: aload_0
     321: getfield      #9                  // Field anIntArray773:[I
     324: iload         7
     326: iaload
     327: istore        9
     329: aload_0
     330: getfield      #30                 // Field aBoolean751:Z
     333: iload_3
     334: iconst_3
     335: if_icmple     342
     338: iconst_1
     339: goto          343
     342: iconst_0
     343: ixor
     344: istore        10
     346: iload         10
     348: ifeq          358
     351: iload         9
     353: ldc           #75                 // int 65536
     355: iadd
     356: istore        9
     358: getstatic     #47                 // Field mruNodes1:LMRUNodes;
     361: iload         9
     363: i2l
     364: invokevirtual #74                 // Method MRUNodes.insertFromCache:(J)LNodeSub;
     367: checkcast     #59                 // class Model
     370: astore        4
     372: aload         4
     374: ifnonnull     415
     377: iload         9
     379: ldc           #45                 // int 65535
     381: iand
     382: invokestatic  #76                 // Method Model.method462:(I)LModel;
     385: astore        4
     387: aload         4
     389: ifnonnull     394
     392: aconst_null
     393: areturn
     394: iload         10
     396: ifeq          404
     399: aload         4
     401: invokevirtual #77                 // Method Model.method477:()V
     404: getstatic     #47                 // Field mruNodes1:LMRUNodes;
     407: aload         4
     409: iload         9
     411: i2l
     412: invokevirtual #78                 // Method MRUNodes.removeFromCache:(LNodeSub;J)V
     415: aload_0
     416: getfield      #32                 // Field anInt748:I
     419: sipush        128
     422: if_icmpne     445
     425: aload_0
     426: getfield      #33                 // Field anInt772:I
     429: sipush        128
     432: if_icmpne     445
     435: aload_0
     436: getfield      #34                 // Field anInt740:I
     439: sipush        128
     442: if_icmpeq     449
     445: iconst_1
     446: goto          450
     449: iconst_0
     450: istore        7
     452: aload_0
     453: getfield      #36                 // Field anInt738:I
     456: ifne          473
     459: aload_0
     460: getfield      #37                 // Field anInt745:I
     463: ifne          473
     466: aload_0
     467: getfield      #38                 // Field anInt783:I
     470: ifeq          477
     473: iconst_1
     474: goto          478
     477: iconst_0
     478: istore        8
     480: new           #59                 // class Model
     483: dup
     484: aload_0
     485: getfield      #13                 // Field modifiedModelColors:[I
     488: ifnonnull     495
     491: iconst_1
     492: goto          496
     495: iconst_0
     496: iload_2
     497: invokestatic  #81                 // Method Class36.method532:(I)Z
     500: iload_3
     501: ifne          523
     504: iload_2
     505: iconst_m1
     506: if_icmpne     523
     509: iload         7
     511: ifne          523
     514: iload         8
     516: ifne          523
     519: iconst_1
     520: goto          524
     523: iconst_0
     524: aload         4
     526: invokespecial #82                 // Method Model."<init>":(ZZZLModel;)V
     529: astore        9
     531: iload_2
     532: iconst_m1
     533: if_icmpeq     565
     536: aload         9
     538: invokevirtual #83                 // Method Model.method469:()V
     541: aload         9
     543: iload_2
     544: invokevirtual #84                 // Method Model.method470:(I)V
     547: aload         9
     549: aconst_null
     550: checkcast     #85                 // class "[[I"
     553: putfield      #86                 // Field Model.anIntArrayArray1658:[[I
     556: aload         9
     558: aconst_null
     559: checkcast     #85                 // class "[[I"
     562: putfield      #87                 // Field Model.anIntArrayArray1657:[[I
     565: iload_3
     566: iinc          3, -1
     569: ifle          580
     572: aload         9
     574: invokevirtual #88                 // Method Model.method473:()V
     577: goto          565
     580: aload_0
     581: getfield      #13                 // Field modifiedModelColors:[I
     584: ifnull        625
     587: iconst_0
     588: istore        10
     590: iload         10
     592: aload_0
     593: getfield      #13                 // Field modifiedModelColors:[I
     596: arraylength
     597: if_icmpge     625
     600: aload         9
     602: aload_0
     603: getfield      #13                 // Field modifiedModelColors:[I
     606: iload         10
     608: iaload
     609: aload_0
     610: getfield      #14                 // Field originalModelColors:[I
     613: iload         10
     615: iaload
     616: invokevirtual #89                 // Method Model.method476:(II)V
     619: iinc          10, 1
     622: goto          590
     625: iload         7
     627: ifeq          647
     630: aload         9
     632: aload_0
     633: getfield      #32                 // Field anInt748:I
     636: aload_0
     637: getfield      #34                 // Field anInt740:I
     640: aload_0
     641: getfield      #33                 // Field anInt772:I
     644: invokevirtual #90                 // Method Model.method478:(III)V
     647: iload         8
     649: ifeq          669
     652: aload         9
     654: aload_0
     655: getfield      #36                 // Field anInt738:I
     658: aload_0
     659: getfield      #37                 // Field anInt745:I
     662: aload_0
     663: getfield      #38                 // Field anInt783:I
     666: invokevirtual #91                 // Method Model.method475:(III)V
     669: aload         9
     671: bipush        64
     673: aload_0
     674: getfield      #25                 // Field aByte737:B
     677: iadd
     678: sipush        768
     681: aload_0
     682: getfield      #26                 // Field aByte742:B
     685: iconst_5
     686: imul
     687: iadd
     688: bipush        -50
     690: bipush        -10
     692: bipush        -50
     694: aload_0
     695: getfield      #21                 // Field aBoolean769:Z
     698: ifne          705
     701: iconst_1
     702: goto          706
     705: iconst_0
     706: invokevirtual #92                 // Method Model.method479:(IIIIIZ)V
     709: aload_0
     710: getfield      #41                 // Field anInt760:I
     713: iconst_1
     714: if_icmpne     727
     717: aload         9
     719: aload         9
     721: getfield      #93                 // Field Model.modelHeight:I
     724: putfield      #94                 // Field Model.anInt1654:I
     727: getstatic     #48                 // Field mruNodes2:LMRUNodes;
     730: aload         9
     732: lload         5
     734: invokevirtual #78                 // Method MRUNodes.removeFromCache:(LNodeSub;J)V
     737: aload         9
     739: areturn

  private void readValues(Stream);
    Code:
       0: iconst_m1
       1: istore_2
       2: aload_1
       3: invokevirtual #95                 // Method Stream.readUnsignedByte:()I
       6: istore_3
       7: iload_3
       8: ifne          14
      11: goto          930
      14: iload_3
      15: iconst_1
      16: if_icmpne     116
      19: aload_1
      20: invokevirtual #95                 // Method Stream.readUnsignedByte:()I
      23: istore        4
      25: iload         4
      27: ifle          113
      30: aload_0
      31: getfield      #9                  // Field anIntArray773:[I
      34: ifnull        43
      37: getstatic     #96                 // Field lowMem:Z
      40: ifeq          100
      43: aload_0
      44: iload         4
      46: newarray       int
      48: putfield      #10                 // Field anIntArray776:[I
      51: aload_0
      52: iload         4
      54: newarray       int
      56: putfield      #9                  // Field anIntArray773:[I
      59: iconst_0
      60: istore        5
      62: iload         5
      64: iload         4
      66: if_icmpge     97
      69: aload_0
      70: getfield      #9                  // Field anIntArray773:[I
      73: iload         5
      75: aload_1
      76: invokevirtual #54                 // Method Stream.readUnsignedWord:()I
      79: iastore
      80: aload_0
      81: getfield      #10                 // Field anIntArray776:[I
      84: iload         5
      86: aload_1
      87: invokevirtual #95                 // Method Stream.readUnsignedByte:()I
      90: iastore
      91: iinc          5, 1
      94: goto          62
      97: goto          113
     100: aload_1
     101: dup
     102: getfield      #6                  // Field Stream.currentOffset:I
     105: iload         4
     107: iconst_3
     108: imul
     109: iadd
     110: putfield      #6                  // Field Stream.currentOffset:I
     113: goto          2
     116: iload_3
     117: iconst_2
     118: if_icmpne     132
     121: aload_0
     122: aload_1
     123: invokevirtual #97                 // Method Stream.readString:()Ljava/lang/String;
     126: putfield      #11                 // Field name:Ljava/lang/String;
     129: goto          2
     132: iload_3
     133: iconst_3
     134: if_icmpne     148
     137: aload_0
     138: aload_1
     139: invokevirtual #98                 // Method Stream.readBytes:()[B
     142: putfield      #12                 // Field description:[B
     145: goto          2
     148: iload_3
     149: iconst_5
     150: if_icmpne     236
     153: aload_1
     154: invokevirtual #95                 // Method Stream.readUnsignedByte:()I
     157: istore        4
     159: iload         4
     161: ifle          233
     164: aload_0
     165: getfield      #9                  // Field anIntArray773:[I
     168: ifnull        177
     171: getstatic     #96                 // Field lowMem:Z
     174: ifeq          220
     177: aload_0
     178: aconst_null
     179: putfield      #10                 // Field anIntArray776:[I
     182: aload_0
     183: iload         4
     185: newarray       int
     187: putfield      #9                  // Field anIntArray773:[I
     190: iconst_0
     191: istore        5
     193: iload         5
     195: iload         4
     197: if_icmpge     217
     200: aload_0
     201: getfield      #9                  // Field anIntArray773:[I
     204: iload         5
     206: aload_1
     207: invokevirtual #54                 // Method Stream.readUnsignedWord:()I
     210: iastore
     211: iinc          5, 1
     214: goto          193
     217: goto          233
     220: aload_1
     221: dup
     222: getfield      #6                  // Field Stream.currentOffset:I
     225: iload         4
     227: iconst_2
     228: imul
     229: iadd
     230: putfield      #6                  // Field Stream.currentOffset:I
     233: goto          2
     236: iload_3
     237: bipush        14
     239: if_icmpne     253
     242: aload_0
     243: aload_1
     244: invokevirtual #95                 // Method Stream.readUnsignedByte:()I
     247: putfield      #15                 // Field anInt744:I
     250: goto          2
     253: iload_3
     254: bipush        15
     256: if_icmpne     270
     259: aload_0
     260: aload_1
     261: invokevirtual #95                 // Method Stream.readUnsignedByte:()I
     264: putfield      #16                 // Field anInt761:I
     267: goto          2
     270: iload_3
     271: bipush        17
     273: if_icmpne     284
     276: aload_0
     277: iconst_0
     278: putfield      #17                 // Field aBoolean767:Z
     281: goto          2
     284: iload_3
     285: bipush        18
     287: if_icmpne     298
     290: aload_0
     291: iconst_0
     292: putfield      #18                 // Field aBoolean757:Z
     295: goto          2
     298: iload_3
     299: bipush        19
     301: if_icmpne     322
     304: aload_1
     305: invokevirtual #95                 // Method Stream.readUnsignedByte:()I
     308: istore_2
     309: iload_2
     310: iconst_1
     311: if_icmpne     2
     314: aload_0
     315: iconst_1
     316: putfield      #19                 // Field hasActions:Z
     319: goto          2
     322: iload_3
     323: bipush        21
     325: if_icmpne     336
     328: aload_0
     329: iconst_1
     330: putfield      #20                 // Field aBoolean762:Z
     333: goto          2
     336: iload_3
     337: bipush        22
     339: if_icmpne     350
     342: aload_0
     343: iconst_1
     344: putfield      #21                 // Field aBoolean769:Z
     347: goto          2
     350: iload_3
     351: bipush        23
     353: if_icmpne     364
     356: aload_0
     357: iconst_1
     358: putfield      #22                 // Field aBoolean764:Z
     361: goto          2
     364: iload_3
     365: bipush        24
     367: if_icmpne     395
     370: aload_0
     371: aload_1
     372: invokevirtual #54                 // Method Stream.readUnsignedWord:()I
     375: putfield      #23                 // Field anInt781:I
     378: aload_0
     379: getfield      #23                 // Field anInt781:I
     382: ldc           #45                 // int 65535
     384: if_icmpne     2
     387: aload_0
     388: iconst_m1
     389: putfield      #23                 // Field anInt781:I
     392: goto          2
     395: iload_3
     396: bipush        28
     398: if_icmpne     412
     401: aload_0
     402: aload_1
     403: invokevirtual #95                 // Method Stream.readUnsignedByte:()I
     406: putfield      #24                 // Field anInt775:I
     409: goto          2
     412: iload_3
     413: bipush        29
     415: if_icmpne     429
     418: aload_0
     419: aload_1
     420: invokevirtual #99                 // Method Stream.readSignedByte:()B
     423: putfield      #25                 // Field aByte737:B
     426: goto          2
     429: iload_3
     430: bipush        39
     432: if_icmpne     446
     435: aload_0
     436: aload_1
     437: invokevirtual #99                 // Method Stream.readSignedByte:()B
     440: putfield      #26                 // Field aByte742:B
     443: goto          2
     446: iload_3
     447: bipush        30
     449: if_icmplt     516
     452: iload_3
     453: bipush        39
     455: if_icmpge     516
     458: aload_0
     459: getfield      #27                 // Field actions:[Ljava/lang/String;
     462: ifnonnull     473
     465: aload_0
     466: iconst_5
     467: anewarray     #100                // class java/lang/String
     470: putfield      #27                 // Field actions:[Ljava/lang/String;
     473: aload_0
     474: getfield      #27                 // Field actions:[Ljava/lang/String;
     477: iload_3
     478: bipush        30
     480: isub
     481: aload_1
     482: invokevirtual #97                 // Method Stream.readString:()Ljava/lang/String;
     485: aastore
     486: aload_0
     487: getfield      #27                 // Field actions:[Ljava/lang/String;
     490: iload_3
     491: bipush        30
     493: isub
     494: aaload
     495: ldc           #101                // String hidden
     497: invokevirtual #102                // Method java/lang/String.equalsIgnoreCase:(Ljava/lang/String;)Z
     500: ifeq          2
     503: aload_0
     504: getfield      #27                 // Field actions:[Ljava/lang/String;
     507: iload_3
     508: bipush        30
     510: isub
     511: aconst_null
     512: aastore
     513: goto          2
     516: iload_3
     517: bipush        40
     519: if_icmpne     585
     522: aload_1
     523: invokevirtual #95                 // Method Stream.readUnsignedByte:()I
     526: istore        4
     528: aload_0
     529: iload         4
     531: newarray       int
     533: putfield      #13                 // Field modifiedModelColors:[I
     536: aload_0
     537: iload         4
     539: newarray       int
     541: putfield      #14                 // Field originalModelColors:[I
     544: iconst_0
     545: istore        5
     547: iload         5
     549: iload         4
     551: if_icmpge     582
     554: aload_0
     555: getfield      #13                 // Field modifiedModelColors:[I
     558: iload         5
     560: aload_1
     561: invokevirtual #54                 // Method Stream.readUnsignedWord:()I
     564: iastore
     565: aload_0
     566: getfield      #14                 // Field originalModelColors:[I
     569: iload         5
     571: aload_1
     572: invokevirtual #54                 // Method Stream.readUnsignedWord:()I
     575: iastore
     576: iinc          5, 1
     579: goto          547
     582: goto          2
     585: iload_3
     586: bipush        60
     588: if_icmpne     602
     591: aload_0
     592: aload_1
     593: invokevirtual #54                 // Method Stream.readUnsignedWord:()I
     596: putfield      #28                 // Field anInt746:I
     599: goto          2
     602: iload_3
     603: bipush        62
     605: if_icmpne     616
     608: aload_0
     609: iconst_1
     610: putfield      #30                 // Field aBoolean751:Z
     613: goto          2
     616: iload_3
     617: bipush        64
     619: if_icmpne     630
     622: aload_0
     623: iconst_0
     624: putfield      #31                 // Field aBoolean779:Z
     627: goto          2
     630: iload_3
     631: bipush        65
     633: if_icmpne     647
     636: aload_0
     637: aload_1
     638: invokevirtual #54                 // Method Stream.readUnsignedWord:()I
     641: putfield      #32                 // Field anInt748:I
     644: goto          2
     647: iload_3
     648: bipush        66
     650: if_icmpne     664
     653: aload_0
     654: aload_1
     655: invokevirtual #54                 // Method Stream.readUnsignedWord:()I
     658: putfield      #33                 // Field anInt772:I
     661: goto          2
     664: iload_3
     665: bipush        67
     667: if_icmpne     681
     670: aload_0
     671: aload_1
     672: invokevirtual #54                 // Method Stream.readUnsignedWord:()I
     675: putfield      #34                 // Field anInt740:I
     678: goto          2
     681: iload_3
     682: bipush        68
     684: if_icmpne     698
     687: aload_0
     688: aload_1
     689: invokevirtual #54                 // Method Stream.readUnsignedWord:()I
     692: putfield      #29                 // Field anInt758:I
     695: goto          2
     698: iload_3
     699: bipush        69
     701: if_icmpne     715
     704: aload_0
     705: aload_1
     706: invokevirtual #95                 // Method Stream.readUnsignedByte:()I
     709: putfield      #35                 // Field anInt768:I
     712: goto          2
     715: iload_3
     716: bipush        70
     718: if_icmpne     732
     721: aload_0
     722: aload_1
     723: invokevirtual #103                // Method Stream.readSignedWord:()I
     726: putfield      #36                 // Field anInt738:I
     729: goto          2
     732: iload_3
     733: bipush        71
     735: if_icmpne     749
     738: aload_0
     739: aload_1
     740: invokevirtual #103                // Method Stream.readSignedWord:()I
     743: putfield      #37                 // Field anInt745:I
     746: goto          2
     749: iload_3
     750: bipush        72
     752: if_icmpne     766
     755: aload_0
     756: aload_1
     757: invokevirtual #103                // Method Stream.readSignedWord:()I
     760: putfield      #38                 // Field anInt783:I
     763: goto          2
     766: iload_3
     767: bipush        73
     769: if_icmpne     780
     772: aload_0
     773: iconst_1
     774: putfield      #39                 // Field aBoolean736:Z
     777: goto          2
     780: iload_3
     781: bipush        74
     783: if_icmpne     794
     786: aload_0
     787: iconst_1
     788: putfield      #40                 // Field aBoolean766:Z
     791: goto          2
     794: iload_3
     795: bipush        75
     797: if_icmpeq     803
     800: goto          814
     803: aload_0
     804: aload_1
     805: invokevirtual #95                 // Method Stream.readUnsignedByte:()I
     808: putfield      #41                 // Field anInt760:I
     811: goto          2
     814: iload_3
     815: bipush        77
     817: if_icmpne     2
     820: aload_0
     821: aload_1
     822: invokevirtual #54                 // Method Stream.readUnsignedWord:()I
     825: putfield      #42                 // Field anInt774:I
     828: aload_0
     829: getfield      #42                 // Field anInt774:I
     832: ldc           #45                 // int 65535
     834: if_icmpne     842
     837: aload_0
     838: iconst_m1
     839: putfield      #42                 // Field anInt774:I
     842: aload_0
     843: aload_1
     844: invokevirtual #54                 // Method Stream.readUnsignedWord:()I
     847: putfield      #43                 // Field anInt749:I
     850: aload_0
     851: getfield      #43                 // Field anInt749:I
     854: ldc           #45                 // int 65535
     856: if_icmpne     864
     859: aload_0
     860: iconst_m1
     861: putfield      #43                 // Field anInt749:I
     864: aload_1
     865: invokevirtual #95                 // Method Stream.readUnsignedByte:()I
     868: istore        4
     870: aload_0
     871: iload         4
     873: iconst_1
     874: iadd
     875: newarray       int
     877: putfield      #44                 // Field childrenIDs:[I
     880: iconst_0
     881: istore        5
     883: iload         5
     885: iload         4
     887: if_icmpgt     927
     890: aload_0
     891: getfield      #44                 // Field childrenIDs:[I
     894: iload         5
     896: aload_1
     897: invokevirtual #54                 // Method Stream.readUnsignedWord:()I
     900: iastore
     901: aload_0
     902: getfield      #44                 // Field childrenIDs:[I
     905: iload         5
     907: iaload
     908: ldc           #45                 // int 65535
     910: if_icmpne     921
     913: aload_0
     914: getfield      #44                 // Field childrenIDs:[I
     917: iload         5
     919: iconst_m1
     920: iastore
     921: iinc          5, 1
     924: goto          883
     927: goto          2
     930: iload_2
     931: iconst_m1
     932: if_icmpne     981
     935: aload_0
     936: aload_0
     937: getfield      #9                  // Field anIntArray773:[I
     940: ifnull        965
     943: aload_0
     944: getfield      #10                 // Field anIntArray776:[I
     947: ifnull        961
     950: aload_0
     951: getfield      #10                 // Field anIntArray776:[I
     954: iconst_0
     955: iaload
     956: bipush        10
     958: if_icmpne     965
     961: iconst_1
     962: goto          966
     965: iconst_0
     966: putfield      #19                 // Field hasActions:Z
     969: aload_0
     970: getfield      #27                 // Field actions:[Ljava/lang/String;
     973: ifnull        981
     976: aload_0
     977: iconst_1
     978: putfield      #19                 // Field hasActions:Z
     981: aload_0
     982: getfield      #40                 // Field aBoolean766:Z
     985: ifeq          998
     988: aload_0
     989: iconst_0
     990: putfield      #17                 // Field aBoolean767:Z
     993: aload_0
     994: iconst_0
     995: putfield      #18                 // Field aBoolean757:Z
     998: aload_0
     999: getfield      #41                 // Field anInt760:I
    1002: iconst_m1
    1003: if_icmpne     1022
    1006: aload_0
    1007: aload_0
    1008: getfield      #17                 // Field aBoolean767:Z
    1011: ifeq          1018
    1014: iconst_1
    1015: goto          1019
    1018: iconst_0
    1019: putfield      #41                 // Field anInt760:I
    1022: return

  private ObjectDef();
    Code:
       0: aload_0
       1: invokespecial #104                // Method java/lang/Object."<init>":()V
       4: aload_0
       5: iconst_m1
       6: putfield      #2                  // Field type:I
       9: return

  static {};
    Code:
       0: iconst_4
       1: anewarray     #59                 // class Model
       4: putstatic     #79                 // Field aModelArray741s:[LModel;
       7: new           #105                // class MRUNodes
      10: dup
      11: bipush        30
      13: invokespecial #106                // Method MRUNodes."<init>":(I)V
      16: putstatic     #48                 // Field mruNodes2:LMRUNodes;
      19: new           #105                // class MRUNodes
      22: dup
      23: sipush        500
      26: invokespecial #106                // Method MRUNodes."<init>":(I)V
      29: putstatic     #47                 // Field mruNodes1:LMRUNodes;
      32: return
}
