Compiled from "OnDemandFetcher.java"
public final class OnDemandFetcher extends OnDemandFetcherParent implements java.lang.Runnable {
  private int totalFiles;

  private final NodeList requested;

  private int anInt1332;

  public java.lang.String statusString;

  private int writeLoopCycle;

  private long openSocketTime;

  private int[] mapIndices3;

  private final java.util.zip.CRC32 crc32;

  private final byte[] ioBuffer;

  public int onDemandCycle;

  private final byte[][] fileStatus;

  private client clientInstance;

  private final NodeList aClass19_1344;

  private int completedSize;

  private int expectedSize;

  private int[] anIntArray1348;

  public int anInt1349;

  private int[] mapIndices2;

  private int filesLoaded;

  private boolean running;

  private java.io.OutputStream outputStream;

  private int[] mapIndices4;

  private boolean waiting;

  private final NodeList aClass19_1358;

  private final byte[] gzipInputBuffer;

  private int[] anIntArray1360;

  private final NodeSubList nodeSubList;

  private java.io.InputStream inputStream;

  private java.net.Socket socket;

  private final int[][] versions;

  private final int[][] crcs;

  private int uncompletedCount;

  private int completedCount;

  private final NodeList aClass19_1368;

  private OnDemandData current;

  private final NodeList aClass19_1370;

  private int[] mapIndices1;

  private byte[] modelIndices;

  private int loopCycle;

  private boolean crcMatches(int, int, byte[]);
    Code:
       0: aload_3
       1: ifnull        10
       4: aload_3
       5: arraylength
       6: iconst_2
       7: if_icmpge     12
      10: iconst_0
      11: ireturn
      12: aload_3
      13: arraylength
      14: iconst_2
      15: isub
      16: istore        4
      18: aload_3
      19: iload         4
      21: baload
      22: sipush        255
      25: iand
      26: bipush        8
      28: ishl
      29: aload_3
      30: iload         4
      32: iconst_1
      33: iadd
      34: baload
      35: sipush        255
      38: iand
      39: iadd
      40: istore        5
      42: aload_0
      43: getfield      #1                  // Field crc32:Ljava/util/zip/CRC32;
      46: invokevirtual #2                  // Method java/util/zip/CRC32.reset:()V
      49: aload_0
      50: getfield      #1                  // Field crc32:Ljava/util/zip/CRC32;
      53: aload_3
      54: iconst_0
      55: iload         4
      57: invokevirtual #3                  // Method java/util/zip/CRC32.update:([BII)V
      60: aload_0
      61: getfield      #1                  // Field crc32:Ljava/util/zip/CRC32;
      64: invokevirtual #4                  // Method java/util/zip/CRC32.getValue:()J
      67: l2i
      68: istore        6
      70: iload         5
      72: iload_1
      73: if_icmpne     86
      76: iload         6
      78: iload_2
      79: if_icmpne     86
      82: iconst_1
      83: goto          87
      86: iconst_0
      87: ireturn

  private void readData();
    Code:
       0: aload_0
       1: getfield      #5                  // Field inputStream:Ljava/io/InputStream;
       4: invokevirtual #6                  // Method java/io/InputStream.available:()I
       7: istore_1
       8: aload_0
       9: getfield      #7                  // Field expectedSize:I
      12: ifne          418
      15: iload_1
      16: bipush        6
      18: if_icmplt     418
      21: aload_0
      22: iconst_1
      23: putfield      #8                  // Field waiting:Z
      26: iconst_0
      27: istore_2
      28: iload_2
      29: bipush        6
      31: if_icmpge     56
      34: iload_2
      35: aload_0
      36: getfield      #5                  // Field inputStream:Ljava/io/InputStream;
      39: aload_0
      40: getfield      #9                  // Field ioBuffer:[B
      43: iload_2
      44: bipush        6
      46: iload_2
      47: isub
      48: invokevirtual #10                 // Method java/io/InputStream.read:([BII)I
      51: iadd
      52: istore_2
      53: goto          28
      56: aload_0
      57: getfield      #9                  // Field ioBuffer:[B
      60: iconst_0
      61: baload
      62: sipush        255
      65: iand
      66: istore_2
      67: aload_0
      68: getfield      #9                  // Field ioBuffer:[B
      71: iconst_1
      72: baload
      73: sipush        255
      76: iand
      77: bipush        8
      79: ishl
      80: aload_0
      81: getfield      #9                  // Field ioBuffer:[B
      84: iconst_2
      85: baload
      86: sipush        255
      89: iand
      90: iadd
      91: istore_3
      92: aload_0
      93: getfield      #9                  // Field ioBuffer:[B
      96: iconst_3
      97: baload
      98: sipush        255
     101: iand
     102: bipush        8
     104: ishl
     105: aload_0
     106: getfield      #9                  // Field ioBuffer:[B
     109: iconst_4
     110: baload
     111: sipush        255
     114: iand
     115: iadd
     116: istore        4
     118: aload_0
     119: getfield      #9                  // Field ioBuffer:[B
     122: iconst_5
     123: baload
     124: sipush        255
     127: iand
     128: istore        5
     130: aload_0
     131: aconst_null
     132: putfield      #11                 // Field current:LOnDemandData;
     135: aload_0
     136: getfield      #12                 // Field requested:LNodeList;
     139: invokevirtual #13                 // Method NodeList.reverseGetFirst:()LNode;
     142: checkcast     #14                 // class OnDemandData
     145: astore        6
     147: aload         6
     149: ifnull        204
     152: aload         6
     154: getfield      #15                 // Field OnDemandData.dataType:I
     157: iload_2
     158: if_icmpne     176
     161: aload         6
     163: getfield      #16                 // Field OnDemandData.ID:I
     166: iload_3
     167: if_icmpne     176
     170: aload_0
     171: aload         6
     173: putfield      #11                 // Field current:LOnDemandData;
     176: aload_0
     177: getfield      #11                 // Field current:LOnDemandData;
     180: ifnull        189
     183: aload         6
     185: iconst_0
     186: putfield      #17                 // Field OnDemandData.loopCycle:I
     189: aload_0
     190: getfield      #12                 // Field requested:LNodeList;
     193: invokevirtual #18                 // Method NodeList.reverseGetNext:()LNode;
     196: checkcast     #14                 // class OnDemandData
     199: astore        6
     201: goto          147
     204: aload_0
     205: getfield      #11                 // Field current:LOnDemandData;
     208: ifnull        372
     211: aload_0
     212: iconst_0
     213: putfield      #19                 // Field loopCycle:I
     216: iload         4
     218: ifne          321
     221: new           #20                 // class java/lang/StringBuilder
     224: dup
     225: invokespecial #21                 // Method java/lang/StringBuilder."<init>":()V
     228: ldc           #22                 // String Rej:
     230: invokevirtual #23                 // Method java/lang/StringBuilder.append:(Ljava/lang/String;)Ljava/lang/StringBuilder;
     233: iload_2
     234: invokevirtual #24                 // Method java/lang/StringBuilder.append:(I)Ljava/lang/StringBuilder;
     237: ldc           #25                 // String ,
     239: invokevirtual #23                 // Method java/lang/StringBuilder.append:(Ljava/lang/String;)Ljava/lang/StringBuilder;
     242: iload_3
     243: invokevirtual #24                 // Method java/lang/StringBuilder.append:(I)Ljava/lang/StringBuilder;
     246: invokevirtual #26                 // Method java/lang/StringBuilder.toString:()Ljava/lang/String;
     249: invokestatic  #27                 // Method sign/signlink.reporterror:(Ljava/lang/String;)V
     252: aload_0
     253: getfield      #11                 // Field current:LOnDemandData;
     256: aconst_null
     257: putfield      #28                 // Field OnDemandData.buffer:[B
     260: aload_0
     261: getfield      #11                 // Field current:LOnDemandData;
     264: getfield      #29                 // Field OnDemandData.incomplete:Z
     267: ifeq          306
     270: aload_0
     271: getfield      #30                 // Field aClass19_1358:LNodeList;
     274: dup
     275: astore        6
     277: monitorenter
     278: aload_0
     279: getfield      #30                 // Field aClass19_1358:LNodeList;
     282: aload_0
     283: getfield      #11                 // Field current:LOnDemandData;
     286: invokevirtual #31                 // Method NodeList.insertHead:(LNode;)V
     289: aload         6
     291: monitorexit
     292: goto          303
     295: astore        7
     297: aload         6
     299: monitorexit
     300: aload         7
     302: athrow
     303: goto          313
     306: aload_0
     307: getfield      #11                 // Field current:LOnDemandData;
     310: invokevirtual #32                 // Method OnDemandData.unlink:()V
     313: aload_0
     314: aconst_null
     315: putfield      #11                 // Field current:LOnDemandData;
     318: goto          372
     321: aload_0
     322: getfield      #11                 // Field current:LOnDemandData;
     325: getfield      #28                 // Field OnDemandData.buffer:[B
     328: ifnonnull     347
     331: iload         5
     333: ifne          347
     336: aload_0
     337: getfield      #11                 // Field current:LOnDemandData;
     340: iload         4
     342: newarray       byte
     344: putfield      #28                 // Field OnDemandData.buffer:[B
     347: aload_0
     348: getfield      #11                 // Field current:LOnDemandData;
     351: getfield      #28                 // Field OnDemandData.buffer:[B
     354: ifnonnull     372
     357: iload         5
     359: ifeq          372
     362: new           #33                 // class java/io/IOException
     365: dup
     366: ldc           #34                 // String missing start of file
     368: invokespecial #35                 // Method java/io/IOException."<init>":(Ljava/lang/String;)V
     371: athrow
     372: aload_0
     373: iload         5
     375: sipush        500
     378: imul
     379: putfield      #36                 // Field completedSize:I
     382: aload_0
     383: sipush        500
     386: putfield      #7                  // Field expectedSize:I
     389: aload_0
     390: getfield      #7                  // Field expectedSize:I
     393: iload         4
     395: iload         5
     397: sipush        500
     400: imul
     401: isub
     402: if_icmple     418
     405: aload_0
     406: iload         4
     408: iload         5
     410: sipush        500
     413: imul
     414: isub
     415: putfield      #7                  // Field expectedSize:I
     418: aload_0
     419: getfield      #7                  // Field expectedSize:I
     422: ifle          664
     425: iload_1
     426: aload_0
     427: getfield      #7                  // Field expectedSize:I
     430: if_icmplt     664
     433: aload_0
     434: iconst_1
     435: putfield      #8                  // Field waiting:Z
     438: aload_0
     439: getfield      #9                  // Field ioBuffer:[B
     442: astore_2
     443: iconst_0
     444: istore_3
     445: aload_0
     446: getfield      #11                 // Field current:LOnDemandData;
     449: ifnull        465
     452: aload_0
     453: getfield      #11                 // Field current:LOnDemandData;
     456: getfield      #28                 // Field OnDemandData.buffer:[B
     459: astore_2
     460: aload_0
     461: getfield      #36                 // Field completedSize:I
     464: istore_3
     465: iconst_0
     466: istore        4
     468: iload         4
     470: aload_0
     471: getfield      #7                  // Field expectedSize:I
     474: if_icmpge     504
     477: iload         4
     479: aload_0
     480: getfield      #5                  // Field inputStream:Ljava/io/InputStream;
     483: aload_2
     484: iload         4
     486: iload_3
     487: iadd
     488: aload_0
     489: getfield      #7                  // Field expectedSize:I
     492: iload         4
     494: isub
     495: invokevirtual #10                 // Method java/io/InputStream.read:([BII)I
     498: iadd
     499: istore        4
     501: goto          468
     504: aload_0
     505: getfield      #7                  // Field expectedSize:I
     508: aload_0
     509: getfield      #36                 // Field completedSize:I
     512: iadd
     513: aload_2
     514: arraylength
     515: if_icmplt     659
     518: aload_0
     519: getfield      #11                 // Field current:LOnDemandData;
     522: ifnull        659
     525: aload_0
     526: getfield      #37                 // Field clientInstance:Lclient;
     529: getfield      #38                 // Field client.decompressors:[LDecompressor;
     532: iconst_0
     533: aaload
     534: ifnull        568
     537: aload_0
     538: getfield      #37                 // Field clientInstance:Lclient;
     541: getfield      #38                 // Field client.decompressors:[LDecompressor;
     544: aload_0
     545: getfield      #11                 // Field current:LOnDemandData;
     548: getfield      #15                 // Field OnDemandData.dataType:I
     551: iconst_1
     552: iadd
     553: aaload
     554: aload_2
     555: arraylength
     556: aload_2
     557: aload_0
     558: getfield      #11                 // Field current:LOnDemandData;
     561: getfield      #16                 // Field OnDemandData.ID:I
     564: invokevirtual #39                 // Method Decompressor.method234:(I[BI)Z
     567: pop
     568: aload_0
     569: getfield      #11                 // Field current:LOnDemandData;
     572: getfield      #29                 // Field OnDemandData.incomplete:Z
     575: ifne          606
     578: aload_0
     579: getfield      #11                 // Field current:LOnDemandData;
     582: getfield      #15                 // Field OnDemandData.dataType:I
     585: iconst_3
     586: if_icmpne     606
     589: aload_0
     590: getfield      #11                 // Field current:LOnDemandData;
     593: iconst_1
     594: putfield      #29                 // Field OnDemandData.incomplete:Z
     597: aload_0
     598: getfield      #11                 // Field current:LOnDemandData;
     601: bipush        93
     603: putfield      #15                 // Field OnDemandData.dataType:I
     606: aload_0
     607: getfield      #11                 // Field current:LOnDemandData;
     610: getfield      #29                 // Field OnDemandData.incomplete:Z
     613: ifeq          652
     616: aload_0
     617: getfield      #30                 // Field aClass19_1358:LNodeList;
     620: dup
     621: astore        4
     623: monitorenter
     624: aload_0
     625: getfield      #30                 // Field aClass19_1358:LNodeList;
     628: aload_0
     629: getfield      #11                 // Field current:LOnDemandData;
     632: invokevirtual #31                 // Method NodeList.insertHead:(LNode;)V
     635: aload         4
     637: monitorexit
     638: goto          649
     641: astore        8
     643: aload         4
     645: monitorexit
     646: aload         8
     648: athrow
     649: goto          659
     652: aload_0
     653: getfield      #11                 // Field current:LOnDemandData;
     656: invokevirtual #32                 // Method OnDemandData.unlink:()V
     659: aload_0
     660: iconst_0
     661: putfield      #7                  // Field expectedSize:I
     664: goto          699
     667: astore_1
     668: aload_0
     669: getfield      #40                 // Field socket:Ljava/net/Socket;
     672: invokevirtual #41                 // Method java/net/Socket.close:()V
     675: goto          679
     678: astore_2
     679: aload_0
     680: aconst_null
     681: putfield      #40                 // Field socket:Ljava/net/Socket;
     684: aload_0
     685: aconst_null
     686: putfield      #5                  // Field inputStream:Ljava/io/InputStream;
     689: aload_0
     690: aconst_null
     691: putfield      #43                 // Field outputStream:Ljava/io/OutputStream;
     694: aload_0
     695: iconst_0
     696: putfield      #7                  // Field expectedSize:I
     699: return
    Exception table:
       from    to  target type
         278   292   295   any
         295   300   295   any
         624   638   641   any
         641   646   641   any
           0   664   667   Class java/io/IOException
         668   675   678   Class java/lang/Exception

  public void start(StreamLoader, client);
    Code:
       0: iconst_4
       1: anewarray     #44                 // class java/lang/String
       4: dup
       5: iconst_0
       6: ldc           #45                 // String model_version
       8: aastore
       9: dup
      10: iconst_1
      11: ldc           #46                 // String anim_version
      13: aastore
      14: dup
      15: iconst_2
      16: ldc           #47                 // String midi_version
      18: aastore
      19: dup
      20: iconst_3
      21: ldc           #48                 // String map_version
      23: aastore
      24: astore_3
      25: iconst_0
      26: istore        4
      28: iload         4
      30: iconst_4
      31: if_icmpge     121
      34: aload_1
      35: aload_3
      36: iload         4
      38: aaload
      39: invokevirtual #49                 // Method StreamLoader.getDataForName:(Ljava/lang/String;)[B
      42: astore        5
      44: aload         5
      46: arraylength
      47: iconst_2
      48: idiv
      49: istore        6
      51: new           #50                 // class Stream
      54: dup
      55: aload         5
      57: invokespecial #51                 // Method Stream."<init>":([B)V
      60: astore        7
      62: aload_0
      63: getfield      #52                 // Field versions:[[I
      66: iload         4
      68: iload         6
      70: newarray       int
      72: aastore
      73: aload_0
      74: getfield      #53                 // Field fileStatus:[[B
      77: iload         4
      79: iload         6
      81: newarray       byte
      83: aastore
      84: iconst_0
      85: istore        8
      87: iload         8
      89: iload         6
      91: if_icmpge     115
      94: aload_0
      95: getfield      #52                 // Field versions:[[I
      98: iload         4
     100: aaload
     101: iload         8
     103: aload         7
     105: invokevirtual #54                 // Method Stream.readUnsignedWord:()I
     108: iastore
     109: iinc          8, 1
     112: goto          87
     115: iinc          4, 1
     118: goto          28
     121: iconst_4
     122: anewarray     #44                 // class java/lang/String
     125: dup
     126: iconst_0
     127: ldc           #55                 // String model_crc
     129: aastore
     130: dup
     131: iconst_1
     132: ldc           #56                 // String anim_crc
     134: aastore
     135: dup
     136: iconst_2
     137: ldc           #57                 // String midi_crc
     139: aastore
     140: dup
     141: iconst_3
     142: ldc           #58                 // String map_crc
     144: aastore
     145: astore        4
     147: iconst_0
     148: istore        5
     150: iload         5
     152: iconst_4
     153: if_icmpge     233
     156: aload_1
     157: aload         4
     159: iload         5
     161: aaload
     162: invokevirtual #49                 // Method StreamLoader.getDataForName:(Ljava/lang/String;)[B
     165: astore        6
     167: aload         6
     169: arraylength
     170: iconst_4
     171: idiv
     172: istore        7
     174: new           #50                 // class Stream
     177: dup
     178: aload         6
     180: invokespecial #51                 // Method Stream."<init>":([B)V
     183: astore        8
     185: aload_0
     186: getfield      #59                 // Field crcs:[[I
     189: iload         5
     191: iload         7
     193: newarray       int
     195: aastore
     196: iconst_0
     197: istore        9
     199: iload         9
     201: iload         7
     203: if_icmpge     227
     206: aload_0
     207: getfield      #59                 // Field crcs:[[I
     210: iload         5
     212: aaload
     213: iload         9
     215: aload         8
     217: invokevirtual #60                 // Method Stream.readDWord:()I
     220: iastore
     221: iinc          9, 1
     224: goto          199
     227: iinc          5, 1
     230: goto          150
     233: aload_1
     234: ldc           #61                 // String model_index
     236: invokevirtual #49                 // Method StreamLoader.getDataForName:(Ljava/lang/String;)[B
     239: astore        5
     241: aload_0
     242: getfield      #52                 // Field versions:[[I
     245: iconst_0
     246: aaload
     247: arraylength
     248: istore        6
     250: aload_0
     251: iload         6
     253: newarray       byte
     255: putfield      #62                 // Field modelIndices:[B
     258: iconst_0
     259: istore        7
     261: iload         7
     263: iload         6
     265: if_icmpge     305
     268: iload         7
     270: aload         5
     272: arraylength
     273: if_icmpge     291
     276: aload_0
     277: getfield      #62                 // Field modelIndices:[B
     280: iload         7
     282: aload         5
     284: iload         7
     286: baload
     287: bastore
     288: goto          299
     291: aload_0
     292: getfield      #62                 // Field modelIndices:[B
     295: iload         7
     297: iconst_0
     298: bastore
     299: iinc          7, 1
     302: goto          261
     305: aload_1
     306: ldc           #63                 // String map_index
     308: invokevirtual #49                 // Method StreamLoader.getDataForName:(Ljava/lang/String;)[B
     311: astore        5
     313: new           #50                 // class Stream
     316: dup
     317: aload         5
     319: invokespecial #51                 // Method Stream."<init>":([B)V
     322: astore        7
     324: aload         5
     326: arraylength
     327: bipush        7
     329: idiv
     330: istore        6
     332: aload_0
     333: iload         6
     335: newarray       int
     337: putfield      #64                 // Field mapIndices1:[I
     340: aload_0
     341: iload         6
     343: newarray       int
     345: putfield      #65                 // Field mapIndices2:[I
     348: aload_0
     349: iload         6
     351: newarray       int
     353: putfield      #66                 // Field mapIndices3:[I
     356: aload_0
     357: iload         6
     359: newarray       int
     361: putfield      #67                 // Field mapIndices4:[I
     364: iconst_0
     365: istore        8
     367: iload         8
     369: iload         6
     371: if_icmpge     428
     374: aload_0
     375: getfield      #64                 // Field mapIndices1:[I
     378: iload         8
     380: aload         7
     382: invokevirtual #54                 // Method Stream.readUnsignedWord:()I
     385: iastore
     386: aload_0
     387: getfield      #65                 // Field mapIndices2:[I
     390: iload         8
     392: aload         7
     394: invokevirtual #54                 // Method Stream.readUnsignedWord:()I
     397: iastore
     398: aload_0
     399: getfield      #66                 // Field mapIndices3:[I
     402: iload         8
     404: aload         7
     406: invokevirtual #54                 // Method Stream.readUnsignedWord:()I
     409: iastore
     410: aload_0
     411: getfield      #67                 // Field mapIndices4:[I
     414: iload         8
     416: aload         7
     418: invokevirtual #68                 // Method Stream.readUnsignedByte:()I
     421: iastore
     422: iinc          8, 1
     425: goto          367
     428: aload_1
     429: ldc           #69                 // String anim_index
     431: invokevirtual #49                 // Method StreamLoader.getDataForName:(Ljava/lang/String;)[B
     434: astore        5
     436: new           #50                 // class Stream
     439: dup
     440: aload         5
     442: invokespecial #51                 // Method Stream."<init>":([B)V
     445: astore        7
     447: aload         5
     449: arraylength
     450: iconst_2
     451: idiv
     452: istore        6
     454: aload_0
     455: iload         6
     457: newarray       int
     459: putfield      #70                 // Field anIntArray1360:[I
     462: iconst_0
     463: istore        8
     465: iload         8
     467: iload         6
     469: if_icmpge     490
     472: aload_0
     473: getfield      #70                 // Field anIntArray1360:[I
     476: iload         8
     478: aload         7
     480: invokevirtual #54                 // Method Stream.readUnsignedWord:()I
     483: iastore
     484: iinc          8, 1
     487: goto          465
     490: aload_1
     491: ldc           #71                 // String midi_index
     493: invokevirtual #49                 // Method StreamLoader.getDataForName:(Ljava/lang/String;)[B
     496: astore        5
     498: new           #50                 // class Stream
     501: dup
     502: aload         5
     504: invokespecial #51                 // Method Stream."<init>":([B)V
     507: astore        7
     509: aload         5
     511: arraylength
     512: istore        6
     514: aload_0
     515: iload         6
     517: newarray       int
     519: putfield      #72                 // Field anIntArray1348:[I
     522: iconst_0
     523: istore        8
     525: iload         8
     527: iload         6
     529: if_icmpge     550
     532: aload_0
     533: getfield      #72                 // Field anIntArray1348:[I
     536: iload         8
     538: aload         7
     540: invokevirtual #68                 // Method Stream.readUnsignedByte:()I
     543: iastore
     544: iinc          8, 1
     547: goto          525
     550: aload_0
     551: aload_2
     552: putfield      #37                 // Field clientInstance:Lclient;
     555: aload_0
     556: iconst_1
     557: putfield      #73                 // Field running:Z
     560: aload_0
     561: getfield      #37                 // Field clientInstance:Lclient;
     564: aload_0
     565: iconst_2
     566: invokevirtual #74                 // Method client.startRunnable:(Ljava/lang/Runnable;I)V
     569: return

  public int getNodeCount();
    Code:
       0: aload_0
       1: getfield      #75                 // Field nodeSubList:LNodeSubList;
       4: dup
       5: astore_1
       6: monitorenter
       7: aload_0
       8: getfield      #75                 // Field nodeSubList:LNodeSubList;
      11: invokevirtual #76                 // Method NodeSubList.getNodeCount:()I
      14: aload_1
      15: monitorexit
      16: ireturn
      17: astore_2
      18: aload_1
      19: monitorexit
      20: aload_2
      21: athrow
    Exception table:
       from    to  target type
           7    16    17   any
          17    20    17   any

  public void disable();
    Code:
       0: aload_0
       1: iconst_0
       2: putfield      #73                 // Field running:Z
       5: return

  public void method554(boolean);
    Code:
       0: aload_0
       1: getfield      #64                 // Field mapIndices1:[I
       4: arraylength
       5: istore_2
       6: iconst_0
       7: istore_3
       8: iload_3
       9: iload_2
      10: if_icmpge     56
      13: iload_1
      14: ifne          26
      17: aload_0
      18: getfield      #67                 // Field mapIndices4:[I
      21: iload_3
      22: iaload
      23: ifeq          50
      26: aload_0
      27: iconst_2
      28: iconst_3
      29: aload_0
      30: getfield      #66                 // Field mapIndices3:[I
      33: iload_3
      34: iaload
      35: invokevirtual #77                 // Method method563:(BII)V
      38: aload_0
      39: iconst_2
      40: iconst_3
      41: aload_0
      42: getfield      #65                 // Field mapIndices2:[I
      45: iload_3
      46: iaload
      47: invokevirtual #77                 // Method method563:(BII)V
      50: iinc          3, 1
      53: goto          8
      56: return

  public int getVersionCount(int);
    Code:
       0: aload_0
       1: getfield      #52                 // Field versions:[[I
       4: iload_1
       5: aaload
       6: arraylength
       7: ireturn

  private void closeRequest(OnDemandData);
    Code:
       0: aload_0
       1: getfield      #40                 // Field socket:Ljava/net/Socket;
       4: ifnonnull     107
       7: invokestatic  #78                 // Method java/lang/System.currentTimeMillis:()J
      10: lstore_2
      11: lload_2
      12: aload_0
      13: getfield      #79                 // Field openSocketTime:J
      16: lsub
      17: ldc2_w        #80                 // long 4000l
      20: lcmp
      21: ifge          25
      24: return
      25: aload_0
      26: lload_2
      27: putfield      #79                 // Field openSocketTime:J
      30: aload_0
      31: aload_0
      32: getfield      #37                 // Field clientInstance:Lclient;
      35: ldc           #82                 // int 43594
      37: getstatic     #83                 // Field client.portOff:I
      40: iadd
      41: invokevirtual #84                 // Method client.openSocket:(I)Ljava/net/Socket;
      44: putfield      #40                 // Field socket:Ljava/net/Socket;
      47: aload_0
      48: aload_0
      49: getfield      #40                 // Field socket:Ljava/net/Socket;
      52: invokevirtual #85                 // Method java/net/Socket.getInputStream:()Ljava/io/InputStream;
      55: putfield      #5                  // Field inputStream:Ljava/io/InputStream;
      58: aload_0
      59: aload_0
      60: getfield      #40                 // Field socket:Ljava/net/Socket;
      63: invokevirtual #86                 // Method java/net/Socket.getOutputStream:()Ljava/io/OutputStream;
      66: putfield      #43                 // Field outputStream:Ljava/io/OutputStream;
      69: aload_0
      70: getfield      #43                 // Field outputStream:Ljava/io/OutputStream;
      73: bipush        15
      75: invokevirtual #87                 // Method java/io/OutputStream.write:(I)V
      78: iconst_0
      79: istore        4
      81: iload         4
      83: bipush        8
      85: if_icmpge     102
      88: aload_0
      89: getfield      #5                  // Field inputStream:Ljava/io/InputStream;
      92: invokevirtual #88                 // Method java/io/InputStream.read:()I
      95: pop
      96: iinc          4, 1
      99: goto          81
     102: aload_0
     103: iconst_0
     104: putfield      #19                 // Field loopCycle:I
     107: aload_0
     108: getfield      #9                  // Field ioBuffer:[B
     111: iconst_0
     112: aload_1
     113: getfield      #15                 // Field OnDemandData.dataType:I
     116: i2b
     117: bastore
     118: aload_0
     119: getfield      #9                  // Field ioBuffer:[B
     122: iconst_1
     123: aload_1
     124: getfield      #16                 // Field OnDemandData.ID:I
     127: bipush        8
     129: ishr
     130: i2b
     131: bastore
     132: aload_0
     133: getfield      #9                  // Field ioBuffer:[B
     136: iconst_2
     137: aload_1
     138: getfield      #16                 // Field OnDemandData.ID:I
     141: i2b
     142: bastore
     143: aload_1
     144: getfield      #29                 // Field OnDemandData.incomplete:Z
     147: ifeq          160
     150: aload_0
     151: getfield      #9                  // Field ioBuffer:[B
     154: iconst_3
     155: iconst_2
     156: bastore
     157: goto          187
     160: aload_0
     161: getfield      #37                 // Field clientInstance:Lclient;
     164: getfield      #89                 // Field client.loggedIn:Z
     167: ifne          180
     170: aload_0
     171: getfield      #9                  // Field ioBuffer:[B
     174: iconst_3
     175: iconst_1
     176: bastore
     177: goto          187
     180: aload_0
     181: getfield      #9                  // Field ioBuffer:[B
     184: iconst_3
     185: iconst_0
     186: bastore
     187: aload_0
     188: getfield      #43                 // Field outputStream:Ljava/io/OutputStream;
     191: aload_0
     192: getfield      #9                  // Field ioBuffer:[B
     195: iconst_0
     196: iconst_4
     197: invokevirtual #90                 // Method java/io/OutputStream.write:([BII)V
     200: aload_0
     201: iconst_0
     202: putfield      #91                 // Field writeLoopCycle:I
     205: aload_0
     206: sipush        -10000
     209: putfield      #92                 // Field anInt1349:I
     212: return
     213: astore_2
     214: aload_0
     215: getfield      #40                 // Field socket:Ljava/net/Socket;
     218: invokevirtual #41                 // Method java/net/Socket.close:()V
     221: goto          225
     224: astore_2
     225: aload_0
     226: aconst_null
     227: putfield      #40                 // Field socket:Ljava/net/Socket;
     230: aload_0
     231: aconst_null
     232: putfield      #5                  // Field inputStream:Ljava/io/InputStream;
     235: aload_0
     236: aconst_null
     237: putfield      #43                 // Field outputStream:Ljava/io/OutputStream;
     240: aload_0
     241: iconst_0
     242: putfield      #7                  // Field expectedSize:I
     245: aload_0
     246: dup
     247: getfield      #92                 // Field anInt1349:I
     250: iconst_1
     251: iadd
     252: putfield      #92                 // Field anInt1349:I
     255: return
    Exception table:
       from    to  target type
           0    24   213   Class java/io/IOException
          25   212   213   Class java/io/IOException
         214   221   224   Class java/lang/Exception

  public int getAnimCount();
    Code:
       0: aload_0
       1: getfield      #70                 // Field anIntArray1360:[I
       4: arraylength
       5: ireturn

  public void method558(int, int);
    Code:
       0: iload_1
       1: iflt          28
       4: iload_1
       5: aload_0
       6: getfield      #52                 // Field versions:[[I
       9: arraylength
      10: if_icmpgt     28
      13: iload_2
      14: iflt          28
      17: iload_2
      18: aload_0
      19: getfield      #52                 // Field versions:[[I
      22: iload_1
      23: aaload
      24: arraylength
      25: if_icmple     29
      28: return
      29: aload_0
      30: getfield      #52                 // Field versions:[[I
      33: iload_1
      34: aaload
      35: iload_2
      36: iaload
      37: ifne          41
      40: return
      41: aload_0
      42: getfield      #75                 // Field nodeSubList:LNodeSubList;
      45: dup
      46: astore_3
      47: monitorenter
      48: aload_0
      49: getfield      #75                 // Field nodeSubList:LNodeSubList;
      52: invokevirtual #93                 // Method NodeSubList.reverseGetFirst:()LNodeSub;
      55: checkcast     #14                 // class OnDemandData
      58: astore        4
      60: aload         4
      62: ifnull        101
      65: aload         4
      67: getfield      #15                 // Field OnDemandData.dataType:I
      70: iload_1
      71: if_icmpne     86
      74: aload         4
      76: getfield      #16                 // Field OnDemandData.ID:I
      79: iload_2
      80: if_icmpne     86
      83: aload_3
      84: monitorexit
      85: return
      86: aload_0
      87: getfield      #75                 // Field nodeSubList:LNodeSubList;
      90: invokevirtual #94                 // Method NodeSubList.reverseGetNext:()LNodeSub;
      93: checkcast     #14                 // class OnDemandData
      96: astore        4
      98: goto          60
     101: new           #14                 // class OnDemandData
     104: dup
     105: invokespecial #95                 // Method OnDemandData."<init>":()V
     108: astore        4
     110: aload         4
     112: iload_1
     113: putfield      #15                 // Field OnDemandData.dataType:I
     116: aload         4
     118: iload_2
     119: putfield      #16                 // Field OnDemandData.ID:I
     122: aload         4
     124: iconst_1
     125: putfield      #29                 // Field OnDemandData.incomplete:Z
     128: aload_0
     129: getfield      #96                 // Field aClass19_1370:LNodeList;
     132: dup
     133: astore        5
     135: monitorenter
     136: aload_0
     137: getfield      #96                 // Field aClass19_1370:LNodeList;
     140: aload         4
     142: invokevirtual #31                 // Method NodeList.insertHead:(LNode;)V
     145: aload         5
     147: monitorexit
     148: goto          159
     151: astore        6
     153: aload         5
     155: monitorexit
     156: aload         6
     158: athrow
     159: aload_0
     160: getfield      #75                 // Field nodeSubList:LNodeSubList;
     163: aload         4
     165: invokevirtual #97                 // Method NodeSubList.insertHead:(LNodeSub;)V
     168: aload_3
     169: monitorexit
     170: goto          180
     173: astore        7
     175: aload_3
     176: monitorexit
     177: aload         7
     179: athrow
     180: return
    Exception table:
       from    to  target type
         136   148   151   any
         151   156   151   any
          48    85   173   any
          86   170   173   any
         173   177   173   any

  public int getModelIndex(int);
    Code:
       0: aload_0
       1: getfield      #62                 // Field modelIndices:[B
       4: iload_1
       5: baload
       6: sipush        255
       9: iand
      10: ireturn

  public void run();
    Code:
       0: aload_0
       1: getfield      #73                 // Field running:Z
       4: ifeq          449
       7: aload_0
       8: dup
       9: getfield      #98                 // Field onDemandCycle:I
      12: iconst_1
      13: iadd
      14: putfield      #98                 // Field onDemandCycle:I
      17: bipush        20
      19: istore_1
      20: aload_0
      21: getfield      #99                 // Field anInt1332:I
      24: ifne          42
      27: aload_0
      28: getfield      #37                 // Field clientInstance:Lclient;
      31: getfield      #38                 // Field client.decompressors:[LDecompressor;
      34: iconst_0
      35: aaload
      36: ifnull        42
      39: bipush        50
      41: istore_1
      42: iload_1
      43: i2l
      44: invokestatic  #100                // Method java/lang/Thread.sleep:(J)V
      47: goto          51
      50: astore_2
      51: aload_0
      52: iconst_1
      53: putfield      #8                  // Field waiting:Z
      56: iconst_0
      57: istore_2
      58: iload_2
      59: bipush        100
      61: if_icmpge     123
      64: aload_0
      65: getfield      #8                  // Field waiting:Z
      68: ifne          74
      71: goto          123
      74: aload_0
      75: iconst_0
      76: putfield      #8                  // Field waiting:Z
      79: aload_0
      80: invokespecial #101                // Method checkReceived:()V
      83: aload_0
      84: invokespecial #102                // Method handleFailed:()V
      87: aload_0
      88: getfield      #103                // Field uncompletedCount:I
      91: ifne          102
      94: iload_2
      95: iconst_5
      96: if_icmplt     102
      99: goto          123
     102: aload_0
     103: invokespecial #104                // Method method568:()V
     106: aload_0
     107: getfield      #5                  // Field inputStream:Ljava/io/InputStream;
     110: ifnull        117
     113: aload_0
     114: invokespecial #105                // Method readData:()V
     117: iinc          2, 1
     120: goto          58
     123: iconst_0
     124: istore_2
     125: aload_0
     126: getfield      #12                 // Field requested:LNodeList;
     129: invokevirtual #13                 // Method NodeList.reverseGetFirst:()LNode;
     132: checkcast     #14                 // class OnDemandData
     135: astore_3
     136: aload_3
     137: ifnull        192
     140: aload_3
     141: getfield      #29                 // Field OnDemandData.incomplete:Z
     144: ifeq          178
     147: iconst_1
     148: istore_2
     149: aload_3
     150: dup
     151: getfield      #17                 // Field OnDemandData.loopCycle:I
     154: iconst_1
     155: iadd
     156: putfield      #17                 // Field OnDemandData.loopCycle:I
     159: aload_3
     160: getfield      #17                 // Field OnDemandData.loopCycle:I
     163: bipush        50
     165: if_icmple     178
     168: aload_3
     169: iconst_0
     170: putfield      #17                 // Field OnDemandData.loopCycle:I
     173: aload_0
     174: aload_3
     175: invokespecial #106                // Method closeRequest:(LOnDemandData;)V
     178: aload_0
     179: getfield      #12                 // Field requested:LNodeList;
     182: invokevirtual #18                 // Method NodeList.reverseGetNext:()LNode;
     185: checkcast     #14                 // class OnDemandData
     188: astore_3
     189: goto          136
     192: iload_2
     193: ifne          256
     196: aload_0
     197: getfield      #12                 // Field requested:LNodeList;
     200: invokevirtual #13                 // Method NodeList.reverseGetFirst:()LNode;
     203: checkcast     #14                 // class OnDemandData
     206: astore_3
     207: aload_3
     208: ifnull        256
     211: iconst_1
     212: istore_2
     213: aload_3
     214: dup
     215: getfield      #17                 // Field OnDemandData.loopCycle:I
     218: iconst_1
     219: iadd
     220: putfield      #17                 // Field OnDemandData.loopCycle:I
     223: aload_3
     224: getfield      #17                 // Field OnDemandData.loopCycle:I
     227: bipush        50
     229: if_icmple     242
     232: aload_3
     233: iconst_0
     234: putfield      #17                 // Field OnDemandData.loopCycle:I
     237: aload_0
     238: aload_3
     239: invokespecial #106                // Method closeRequest:(LOnDemandData;)V
     242: aload_0
     243: getfield      #12                 // Field requested:LNodeList;
     246: invokevirtual #18                 // Method NodeList.reverseGetNext:()LNode;
     249: checkcast     #14                 // class OnDemandData
     252: astore_3
     253: goto          207
     256: iload_2
     257: ifeq          314
     260: aload_0
     261: dup
     262: getfield      #19                 // Field loopCycle:I
     265: iconst_1
     266: iadd
     267: putfield      #19                 // Field loopCycle:I
     270: aload_0
     271: getfield      #19                 // Field loopCycle:I
     274: sipush        750
     277: if_icmple     325
     280: aload_0
     281: getfield      #40                 // Field socket:Ljava/net/Socket;
     284: invokevirtual #41                 // Method java/net/Socket.close:()V
     287: goto          291
     290: astore_3
     291: aload_0
     292: aconst_null
     293: putfield      #40                 // Field socket:Ljava/net/Socket;
     296: aload_0
     297: aconst_null
     298: putfield      #5                  // Field inputStream:Ljava/io/InputStream;
     301: aload_0
     302: aconst_null
     303: putfield      #43                 // Field outputStream:Ljava/io/OutputStream;
     306: aload_0
     307: iconst_0
     308: putfield      #7                  // Field expectedSize:I
     311: goto          325
     314: aload_0
     315: iconst_0
     316: putfield      #19                 // Field loopCycle:I
     319: aload_0
     320: ldc           #107                // String
     322: putfield      #108                // Field statusString:Ljava/lang/String;
     325: aload_0
     326: getfield      #37                 // Field clientInstance:Lclient;
     329: getfield      #89                 // Field client.loggedIn:Z
     332: ifeq          446
     335: aload_0
     336: getfield      #40                 // Field socket:Ljava/net/Socket;
     339: ifnull        446
     342: aload_0
     343: getfield      #43                 // Field outputStream:Ljava/io/OutputStream;
     346: ifnull        446
     349: aload_0
     350: getfield      #99                 // Field anInt1332:I
     353: ifgt          368
     356: aload_0
     357: getfield      #37                 // Field clientInstance:Lclient;
     360: getfield      #38                 // Field client.decompressors:[LDecompressor;
     363: iconst_0
     364: aaload
     365: ifnonnull     446
     368: aload_0
     369: dup
     370: getfield      #91                 // Field writeLoopCycle:I
     373: iconst_1
     374: iadd
     375: putfield      #91                 // Field writeLoopCycle:I
     378: aload_0
     379: getfield      #91                 // Field writeLoopCycle:I
     382: sipush        500
     385: if_icmple     446
     388: aload_0
     389: iconst_0
     390: putfield      #91                 // Field writeLoopCycle:I
     393: aload_0
     394: getfield      #9                  // Field ioBuffer:[B
     397: iconst_0
     398: iconst_0
     399: bastore
     400: aload_0
     401: getfield      #9                  // Field ioBuffer:[B
     404: iconst_1
     405: iconst_0
     406: bastore
     407: aload_0
     408: getfield      #9                  // Field ioBuffer:[B
     411: iconst_2
     412: iconst_0
     413: bastore
     414: aload_0
     415: getfield      #9                  // Field ioBuffer:[B
     418: iconst_3
     419: bipush        10
     421: bastore
     422: aload_0
     423: getfield      #43                 // Field outputStream:Ljava/io/OutputStream;
     426: aload_0
     427: getfield      #9                  // Field ioBuffer:[B
     430: iconst_0
     431: iconst_4
     432: invokevirtual #90                 // Method java/io/OutputStream.write:([BII)V
     435: goto          446
     438: astore_3
     439: aload_0
     440: sipush        5000
     443: putfield      #19                 // Field loopCycle:I
     446: goto          0
     449: goto          478
     452: astore_1
     453: new           #20                 // class java/lang/StringBuilder
     456: dup
     457: invokespecial #21                 // Method java/lang/StringBuilder."<init>":()V
     460: ldc           #109                // String od_ex
     462: invokevirtual #23                 // Method java/lang/StringBuilder.append:(Ljava/lang/String;)Ljava/lang/StringBuilder;
     465: aload_1
     466: invokevirtual #110                // Method java/lang/Exception.getMessage:()Ljava/lang/String;
     469: invokevirtual #23                 // Method java/lang/StringBuilder.append:(Ljava/lang/String;)Ljava/lang/StringBuilder;
     472: invokevirtual #26                 // Method java/lang/StringBuilder.toString:()Ljava/lang/String;
     475: invokestatic  #27                 // Method sign/signlink.reporterror:(Ljava/lang/String;)V
     478: return
    Exception table:
       from    to  target type
          42    47    50   Class java/lang/Exception
         280   287   290   Class java/lang/Exception
         422   435   438   Class java/io/IOException
           0   449   452   Class java/lang/Exception

  public void method560(int, int);
    Code:
       0: aload_0
       1: getfield      #37                 // Field clientInstance:Lclient;
       4: getfield      #38                 // Field client.decompressors:[LDecompressor;
       7: iconst_0
       8: aaload
       9: ifnonnull     13
      12: return
      13: aload_0
      14: getfield      #52                 // Field versions:[[I
      17: iload_2
      18: aaload
      19: iload_1
      20: iaload
      21: ifne          25
      24: return
      25: aload_0
      26: getfield      #53                 // Field fileStatus:[[B
      29: iload_2
      30: aaload
      31: iload_1
      32: baload
      33: ifne          37
      36: return
      37: aload_0
      38: getfield      #99                 // Field anInt1332:I
      41: ifne          45
      44: return
      45: new           #14                 // class OnDemandData
      48: dup
      49: invokespecial #95                 // Method OnDemandData."<init>":()V
      52: astore_3
      53: aload_3
      54: iload_2
      55: putfield      #15                 // Field OnDemandData.dataType:I
      58: aload_3
      59: iload_1
      60: putfield      #16                 // Field OnDemandData.ID:I
      63: aload_3
      64: iconst_0
      65: putfield      #29                 // Field OnDemandData.incomplete:Z
      68: aload_0
      69: getfield      #111                // Field aClass19_1344:LNodeList;
      72: dup
      73: astore        4
      75: monitorenter
      76: aload_0
      77: getfield      #111                // Field aClass19_1344:LNodeList;
      80: aload_3
      81: invokevirtual #31                 // Method NodeList.insertHead:(LNode;)V
      84: aload         4
      86: monitorexit
      87: goto          98
      90: astore        5
      92: aload         4
      94: monitorexit
      95: aload         5
      97: athrow
      98: return
    Exception table:
       from    to  target type
          76    87    90   any
          90    95    90   any

  public OnDemandData getNextNode();
    Code:
       0: aload_0
       1: getfield      #30                 // Field aClass19_1358:LNodeList;
       4: dup
       5: astore_2
       6: monitorenter
       7: aload_0
       8: getfield      #30                 // Field aClass19_1358:LNodeList;
      11: invokevirtual #112                // Method NodeList.popHead:()LNode;
      14: checkcast     #14                 // class OnDemandData
      17: astore_1
      18: aload_2
      19: monitorexit
      20: goto          28
      23: astore_3
      24: aload_2
      25: monitorexit
      26: aload_3
      27: athrow
      28: aload_1
      29: ifnonnull     34
      32: aconst_null
      33: areturn
      34: aload_0
      35: getfield      #75                 // Field nodeSubList:LNodeSubList;
      38: dup
      39: astore_2
      40: monitorenter
      41: aload_1
      42: invokevirtual #113                // Method OnDemandData.unlinkSub:()V
      45: aload_2
      46: monitorexit
      47: goto          57
      50: astore        4
      52: aload_2
      53: monitorexit
      54: aload         4
      56: athrow
      57: aload_1
      58: getfield      #28                 // Field OnDemandData.buffer:[B
      61: ifnonnull     66
      64: aload_1
      65: areturn
      66: iconst_0
      67: istore_2
      68: new           #114                // class java/util/zip/GZIPInputStream
      71: dup
      72: new           #115                // class java/io/ByteArrayInputStream
      75: dup
      76: aload_1
      77: getfield      #28                 // Field OnDemandData.buffer:[B
      80: invokespecial #116                // Method java/io/ByteArrayInputStream."<init>":([B)V
      83: invokespecial #117                // Method java/util/zip/GZIPInputStream."<init>":(Ljava/io/InputStream;)V
      86: astore_3
      87: iload_2
      88: aload_0
      89: getfield      #118                // Field gzipInputBuffer:[B
      92: arraylength
      93: if_icmpne     106
      96: new           #119                // class java/lang/RuntimeException
      99: dup
     100: ldc           #120                // String buffer overflow!
     102: invokespecial #121                // Method java/lang/RuntimeException."<init>":(Ljava/lang/String;)V
     105: athrow
     106: aload_3
     107: aload_0
     108: getfield      #118                // Field gzipInputBuffer:[B
     111: iload_2
     112: aload_0
     113: getfield      #118                // Field gzipInputBuffer:[B
     116: arraylength
     117: iload_2
     118: isub
     119: invokevirtual #122                // Method java/util/zip/GZIPInputStream.read:([BII)I
     122: istore        4
     124: iload         4
     126: iconst_m1
     127: if_icmpne     133
     130: goto          141
     133: iload_2
     134: iload         4
     136: iadd
     137: istore_2
     138: goto          87
     141: goto          155
     144: astore_3
     145: new           #119                // class java/lang/RuntimeException
     148: dup
     149: ldc           #123                // String error unzipping
     151: invokespecial #121                // Method java/lang/RuntimeException."<init>":(Ljava/lang/String;)V
     154: athrow
     155: aload_1
     156: iload_2
     157: newarray       byte
     159: putfield      #28                 // Field OnDemandData.buffer:[B
     162: aload_0
     163: getfield      #118                // Field gzipInputBuffer:[B
     166: iconst_0
     167: aload_1
     168: getfield      #28                 // Field OnDemandData.buffer:[B
     171: iconst_0
     172: iload_2
     173: invokestatic  #124                // Method java/lang/System.arraycopy:(Ljava/lang/Object;ILjava/lang/Object;II)V
     176: aload_1
     177: areturn
    Exception table:
       from    to  target type
           7    20    23   any
          23    26    23   any
          41    47    50   any
          50    54    50   any
          68   141   144   Class java/io/IOException

  public int method562(int, int, int);
    Code:
       0: iload_3
       1: bipush        8
       3: ishl
       4: iload_2
       5: iadd
       6: istore        4
       8: iconst_0
       9: istore        5
      11: iload         5
      13: aload_0
      14: getfield      #64                 // Field mapIndices1:[I
      17: arraylength
      18: if_icmpge     59
      21: aload_0
      22: getfield      #64                 // Field mapIndices1:[I
      25: iload         5
      27: iaload
      28: iload         4
      30: if_icmpne     53
      33: iload_1
      34: ifne          45
      37: aload_0
      38: getfield      #65                 // Field mapIndices2:[I
      41: iload         5
      43: iaload
      44: ireturn
      45: aload_0
      46: getfield      #66                 // Field mapIndices3:[I
      49: iload         5
      51: iaload
      52: ireturn
      53: iinc          5, 1
      56: goto          11
      59: iconst_m1
      60: ireturn

  public void method548(int);
    Code:
       0: aload_0
       1: iconst_0
       2: iload_1
       3: invokevirtual #125                // Method method558:(II)V
       6: return

  public void method563(byte, int, int);
    Code:
       0: aload_0
       1: getfield      #37                 // Field clientInstance:Lclient;
       4: getfield      #38                 // Field client.decompressors:[LDecompressor;
       7: iconst_0
       8: aaload
       9: ifnonnull     13
      12: return
      13: aload_0
      14: getfield      #52                 // Field versions:[[I
      17: iload_2
      18: aaload
      19: iload_3
      20: iaload
      21: ifne          25
      24: return
      25: aload_0
      26: getfield      #37                 // Field clientInstance:Lclient;
      29: getfield      #38                 // Field client.decompressors:[LDecompressor;
      32: iload_2
      33: iconst_1
      34: iadd
      35: aaload
      36: iload_3
      37: invokevirtual #126                // Method Decompressor.decompress:(I)[B
      40: astore        4
      42: aload_0
      43: aload_0
      44: getfield      #52                 // Field versions:[[I
      47: iload_2
      48: aaload
      49: iload_3
      50: iaload
      51: aload_0
      52: getfield      #59                 // Field crcs:[[I
      55: iload_2
      56: aaload
      57: iload_3
      58: iaload
      59: aload         4
      61: invokespecial #127                // Method crcMatches:(II[B)Z
      64: ifeq          68
      67: return
      68: aload_0
      69: getfield      #53                 // Field fileStatus:[[B
      72: iload_2
      73: aaload
      74: iload_3
      75: iload_1
      76: bastore
      77: iload_1
      78: aload_0
      79: getfield      #99                 // Field anInt1332:I
      82: if_icmple     90
      85: aload_0
      86: iload_1
      87: putfield      #99                 // Field anInt1332:I
      90: aload_0
      91: dup
      92: getfield      #128                // Field totalFiles:I
      95: iconst_1
      96: iadd
      97: putfield      #128                // Field totalFiles:I
     100: return

  public boolean method564(int);
    Code:
       0: iconst_0
       1: istore_2
       2: iload_2
       3: aload_0
       4: getfield      #64                 // Field mapIndices1:[I
       7: arraylength
       8: if_icmpge     29
      11: aload_0
      12: getfield      #66                 // Field mapIndices3:[I
      15: iload_2
      16: iaload
      17: iload_1
      18: if_icmpne     23
      21: iconst_1
      22: ireturn
      23: iinc          2, 1
      26: goto          2
      29: iconst_0
      30: ireturn

  private void handleFailed();
    Code:
       0: aload_0
       1: iconst_0
       2: putfield      #103                // Field uncompletedCount:I
       5: aload_0
       6: iconst_0
       7: putfield      #129                // Field completedCount:I
      10: aload_0
      11: getfield      #12                 // Field requested:LNodeList;
      14: invokevirtual #13                 // Method NodeList.reverseGetFirst:()LNode;
      17: checkcast     #14                 // class OnDemandData
      20: astore_1
      21: aload_1
      22: ifnull        69
      25: aload_1
      26: getfield      #29                 // Field OnDemandData.incomplete:Z
      29: ifeq          45
      32: aload_0
      33: dup
      34: getfield      #103                // Field uncompletedCount:I
      37: iconst_1
      38: iadd
      39: putfield      #103                // Field uncompletedCount:I
      42: goto          55
      45: aload_0
      46: dup
      47: getfield      #129                // Field completedCount:I
      50: iconst_1
      51: iadd
      52: putfield      #129                // Field completedCount:I
      55: aload_0
      56: getfield      #12                 // Field requested:LNodeList;
      59: invokevirtual #18                 // Method NodeList.reverseGetNext:()LNode;
      62: checkcast     #14                 // class OnDemandData
      65: astore_1
      66: goto          21
      69: aload_0
      70: getfield      #103                // Field uncompletedCount:I
      73: bipush        10
      75: if_icmpge     169
      78: aload_0
      79: getfield      #130                // Field aClass19_1368:LNodeList;
      82: invokevirtual #112                // Method NodeList.popHead:()LNode;
      85: checkcast     #14                 // class OnDemandData
      88: astore_1
      89: aload_1
      90: ifnonnull     96
      93: goto          169
      96: aload_0
      97: getfield      #53                 // Field fileStatus:[[B
     100: aload_1
     101: getfield      #15                 // Field OnDemandData.dataType:I
     104: aaload
     105: aload_1
     106: getfield      #16                 // Field OnDemandData.ID:I
     109: baload
     110: ifeq          123
     113: aload_0
     114: dup
     115: getfield      #131                // Field filesLoaded:I
     118: iconst_1
     119: iadd
     120: putfield      #131                // Field filesLoaded:I
     123: aload_0
     124: getfield      #53                 // Field fileStatus:[[B
     127: aload_1
     128: getfield      #15                 // Field OnDemandData.dataType:I
     131: aaload
     132: aload_1
     133: getfield      #16                 // Field OnDemandData.ID:I
     136: iconst_0
     137: bastore
     138: aload_0
     139: getfield      #12                 // Field requested:LNodeList;
     142: aload_1
     143: invokevirtual #31                 // Method NodeList.insertHead:(LNode;)V
     146: aload_0
     147: dup
     148: getfield      #103                // Field uncompletedCount:I
     151: iconst_1
     152: iadd
     153: putfield      #103                // Field uncompletedCount:I
     156: aload_0
     157: aload_1
     158: invokespecial #106                // Method closeRequest:(LOnDemandData;)V
     161: aload_0
     162: iconst_1
     163: putfield      #8                  // Field waiting:Z
     166: goto          69
     169: return

  public void method566();
    Code:
       0: aload_0
       1: getfield      #111                // Field aClass19_1344:LNodeList;
       4: dup
       5: astore_1
       6: monitorenter
       7: aload_0
       8: getfield      #111                // Field aClass19_1344:LNodeList;
      11: invokevirtual #132                // Method NodeList.removeAll:()V
      14: aload_1
      15: monitorexit
      16: goto          24
      19: astore_2
      20: aload_1
      21: monitorexit
      22: aload_2
      23: athrow
      24: return
    Exception table:
       from    to  target type
           7    16    19   any
          19    22    19   any

  private void checkReceived();
    Code:
       0: aload_0
       1: getfield      #96                 // Field aClass19_1370:LNodeList;
       4: dup
       5: astore_2
       6: monitorenter
       7: aload_0
       8: getfield      #96                 // Field aClass19_1370:LNodeList;
      11: invokevirtual #112                // Method NodeList.popHead:()LNode;
      14: checkcast     #14                 // class OnDemandData
      17: astore_1
      18: aload_2
      19: monitorexit
      20: goto          28
      23: astore_3
      24: aload_2
      25: monitorexit
      26: aload_3
      27: athrow
      28: aload_1
      29: ifnull        194
      32: aload_0
      33: iconst_1
      34: putfield      #8                  // Field waiting:Z
      37: aconst_null
      38: astore_2
      39: aload_0
      40: getfield      #37                 // Field clientInstance:Lclient;
      43: getfield      #38                 // Field client.decompressors:[LDecompressor;
      46: iconst_0
      47: aaload
      48: ifnull        73
      51: aload_0
      52: getfield      #37                 // Field clientInstance:Lclient;
      55: getfield      #38                 // Field client.decompressors:[LDecompressor;
      58: aload_1
      59: getfield      #15                 // Field OnDemandData.dataType:I
      62: iconst_1
      63: iadd
      64: aaload
      65: aload_1
      66: getfield      #16                 // Field OnDemandData.ID:I
      69: invokevirtual #126                // Method Decompressor.decompress:(I)[B
      72: astore_2
      73: aload_0
      74: aload_0
      75: getfield      #52                 // Field versions:[[I
      78: aload_1
      79: getfield      #15                 // Field OnDemandData.dataType:I
      82: aaload
      83: aload_1
      84: getfield      #16                 // Field OnDemandData.ID:I
      87: iaload
      88: aload_0
      89: getfield      #59                 // Field crcs:[[I
      92: aload_1
      93: getfield      #15                 // Field OnDemandData.dataType:I
      96: aaload
      97: aload_1
      98: getfield      #16                 // Field OnDemandData.ID:I
     101: iaload
     102: aload_2
     103: invokespecial #127                // Method crcMatches:(II[B)Z
     106: ifne          111
     109: aconst_null
     110: astore_2
     111: aload_0
     112: getfield      #96                 // Field aClass19_1370:LNodeList;
     115: dup
     116: astore_3
     117: monitorenter
     118: aload_2
     119: ifnonnull     133
     122: aload_0
     123: getfield      #130                // Field aClass19_1368:LNodeList;
     126: aload_1
     127: invokevirtual #31                 // Method NodeList.insertHead:(LNode;)V
     130: goto          168
     133: aload_1
     134: aload_2
     135: putfield      #28                 // Field OnDemandData.buffer:[B
     138: aload_0
     139: getfield      #30                 // Field aClass19_1358:LNodeList;
     142: dup
     143: astore        4
     145: monitorenter
     146: aload_0
     147: getfield      #30                 // Field aClass19_1358:LNodeList;
     150: aload_1
     151: invokevirtual #31                 // Method NodeList.insertHead:(LNode;)V
     154: aload         4
     156: monitorexit
     157: goto          168
     160: astore        5
     162: aload         4
     164: monitorexit
     165: aload         5
     167: athrow
     168: aload_0
     169: getfield      #96                 // Field aClass19_1370:LNodeList;
     172: invokevirtual #112                // Method NodeList.popHead:()LNode;
     175: checkcast     #14                 // class OnDemandData
     178: astore_1
     179: aload_3
     180: monitorexit
     181: goto          191
     184: astore        6
     186: aload_3
     187: monitorexit
     188: aload         6
     190: athrow
     191: goto          28
     194: return
    Exception table:
       from    to  target type
           7    20    23   any
          23    26    23   any
         146   157   160   any
         160   165   160   any
         118   181   184   any
         184   188   184   any

  private void method568();
    Code:
       0: aload_0
       1: getfield      #103                // Field uncompletedCount:I
       4: ifne          418
       7: aload_0
       8: getfield      #129                // Field completedCount:I
      11: bipush        10
      13: if_icmpge     418
      16: aload_0
      17: getfield      #99                 // Field anInt1332:I
      20: ifne          26
      23: goto          418
      26: aload_0
      27: getfield      #111                // Field aClass19_1344:LNodeList;
      30: dup
      31: astore_2
      32: monitorenter
      33: aload_0
      34: getfield      #111                // Field aClass19_1344:LNodeList;
      37: invokevirtual #112                // Method NodeList.popHead:()LNode;
      40: checkcast     #14                 // class OnDemandData
      43: astore_1
      44: aload_2
      45: monitorexit
      46: goto          54
      49: astore_3
      50: aload_2
      51: monitorexit
      52: aload_3
      53: athrow
      54: aload_1
      55: ifnull        221
      58: aload_0
      59: getfield      #53                 // Field fileStatus:[[B
      62: aload_1
      63: getfield      #15                 // Field OnDemandData.dataType:I
      66: aaload
      67: aload_1
      68: getfield      #16                 // Field OnDemandData.ID:I
      71: baload
      72: ifeq          188
      75: aload_0
      76: getfield      #53                 // Field fileStatus:[[B
      79: aload_1
      80: getfield      #15                 // Field OnDemandData.dataType:I
      83: aaload
      84: aload_1
      85: getfield      #16                 // Field OnDemandData.ID:I
      88: iconst_0
      89: bastore
      90: aload_0
      91: getfield      #12                 // Field requested:LNodeList;
      94: aload_1
      95: invokevirtual #31                 // Method NodeList.insertHead:(LNode;)V
      98: aload_0
      99: aload_1
     100: invokespecial #106                // Method closeRequest:(LOnDemandData;)V
     103: aload_0
     104: iconst_1
     105: putfield      #8                  // Field waiting:Z
     108: aload_0
     109: getfield      #131                // Field filesLoaded:I
     112: aload_0
     113: getfield      #128                // Field totalFiles:I
     116: if_icmpge     129
     119: aload_0
     120: dup
     121: getfield      #131                // Field filesLoaded:I
     124: iconst_1
     125: iadd
     126: putfield      #131                // Field filesLoaded:I
     129: aload_0
     130: new           #20                 // class java/lang/StringBuilder
     133: dup
     134: invokespecial #21                 // Method java/lang/StringBuilder."<init>":()V
     137: ldc           #133                // String Loading extra files -
     139: invokevirtual #23                 // Method java/lang/StringBuilder.append:(Ljava/lang/String;)Ljava/lang/StringBuilder;
     142: aload_0
     143: getfield      #131                // Field filesLoaded:I
     146: bipush        100
     148: imul
     149: aload_0
     150: getfield      #128                // Field totalFiles:I
     153: idiv
     154: invokevirtual #24                 // Method java/lang/StringBuilder.append:(I)Ljava/lang/StringBuilder;
     157: ldc           #134                // String %
     159: invokevirtual #23                 // Method java/lang/StringBuilder.append:(Ljava/lang/String;)Ljava/lang/StringBuilder;
     162: invokevirtual #26                 // Method java/lang/StringBuilder.toString:()Ljava/lang/String;
     165: putfield      #108                // Field statusString:Ljava/lang/String;
     168: aload_0
     169: dup
     170: getfield      #129                // Field completedCount:I
     173: iconst_1
     174: iadd
     175: putfield      #129                // Field completedCount:I
     178: aload_0
     179: getfield      #129                // Field completedCount:I
     182: bipush        10
     184: if_icmpne     188
     187: return
     188: aload_0
     189: getfield      #111                // Field aClass19_1344:LNodeList;
     192: dup
     193: astore_2
     194: monitorenter
     195: aload_0
     196: getfield      #111                // Field aClass19_1344:LNodeList;
     199: invokevirtual #112                // Method NodeList.popHead:()LNode;
     202: checkcast     #14                 // class OnDemandData
     205: astore_1
     206: aload_2
     207: monitorexit
     208: goto          218
     211: astore        4
     213: aload_2
     214: monitorexit
     215: aload         4
     217: athrow
     218: goto          54
     221: iconst_0
     222: istore_2
     223: iload_2
     224: iconst_4
     225: if_icmpge     405
     228: aload_0
     229: getfield      #53                 // Field fileStatus:[[B
     232: iload_2
     233: aaload
     234: astore_3
     235: aload_3
     236: arraylength
     237: istore        4
     239: iconst_0
     240: istore        5
     242: iload         5
     244: iload         4
     246: if_icmpge     399
     249: aload_3
     250: iload         5
     252: baload
     253: aload_0
     254: getfield      #99                 // Field anInt1332:I
     257: if_icmpne     393
     260: aload_3
     261: iload         5
     263: iconst_0
     264: bastore
     265: new           #14                 // class OnDemandData
     268: dup
     269: invokespecial #95                 // Method OnDemandData."<init>":()V
     272: astore        6
     274: aload         6
     276: iload_2
     277: putfield      #15                 // Field OnDemandData.dataType:I
     280: aload         6
     282: iload         5
     284: putfield      #16                 // Field OnDemandData.ID:I
     287: aload         6
     289: iconst_0
     290: putfield      #29                 // Field OnDemandData.incomplete:Z
     293: aload_0
     294: getfield      #12                 // Field requested:LNodeList;
     297: aload         6
     299: invokevirtual #31                 // Method NodeList.insertHead:(LNode;)V
     302: aload_0
     303: aload         6
     305: invokespecial #106                // Method closeRequest:(LOnDemandData;)V
     308: aload_0
     309: iconst_1
     310: putfield      #8                  // Field waiting:Z
     313: aload_0
     314: getfield      #131                // Field filesLoaded:I
     317: aload_0
     318: getfield      #128                // Field totalFiles:I
     321: if_icmpge     334
     324: aload_0
     325: dup
     326: getfield      #131                // Field filesLoaded:I
     329: iconst_1
     330: iadd
     331: putfield      #131                // Field filesLoaded:I
     334: aload_0
     335: new           #20                 // class java/lang/StringBuilder
     338: dup
     339: invokespecial #21                 // Method java/lang/StringBuilder."<init>":()V
     342: ldc           #133                // String Loading extra files -
     344: invokevirtual #23                 // Method java/lang/StringBuilder.append:(Ljava/lang/String;)Ljava/lang/StringBuilder;
     347: aload_0
     348: getfield      #131                // Field filesLoaded:I
     351: bipush        100
     353: imul
     354: aload_0
     355: getfield      #128                // Field totalFiles:I
     358: idiv
     359: invokevirtual #24                 // Method java/lang/StringBuilder.append:(I)Ljava/lang/StringBuilder;
     362: ldc           #134                // String %
     364: invokevirtual #23                 // Method java/lang/StringBuilder.append:(Ljava/lang/String;)Ljava/lang/StringBuilder;
     367: invokevirtual #26                 // Method java/lang/StringBuilder.toString:()Ljava/lang/String;
     370: putfield      #108                // Field statusString:Ljava/lang/String;
     373: aload_0
     374: dup
     375: getfield      #129                // Field completedCount:I
     378: iconst_1
     379: iadd
     380: putfield      #129                // Field completedCount:I
     383: aload_0
     384: getfield      #129                // Field completedCount:I
     387: bipush        10
     389: if_icmpne     393
     392: return
     393: iinc          5, 1
     396: goto          242
     399: iinc          2, 1
     402: goto          223
     405: aload_0
     406: dup
     407: getfield      #99                 // Field anInt1332:I
     410: iconst_1
     411: isub
     412: putfield      #99                 // Field anInt1332:I
     415: goto          0
     418: return
    Exception table:
       from    to  target type
          33    46    49   any
          49    52    49   any
         195   208   211   any
         211   215   211   any

  public boolean method569(int);
    Code:
       0: aload_0
       1: getfield      #72                 // Field anIntArray1348:[I
       4: iload_1
       5: iaload
       6: iconst_1
       7: if_icmpne     14
      10: iconst_1
      11: goto          15
      14: iconst_0
      15: ireturn

  public OnDemandFetcher();
    Code:
       0: aload_0
       1: invokespecial #135                // Method OnDemandFetcherParent."<init>":()V
       4: aload_0
       5: new           #136                // class NodeList
       8: dup
       9: invokespecial #137                // Method NodeList."<init>":()V
      12: putfield      #12                 // Field requested:LNodeList;
      15: aload_0
      16: ldc           #107                // String
      18: putfield      #108                // Field statusString:Ljava/lang/String;
      21: aload_0
      22: new           #138                // class java/util/zip/CRC32
      25: dup
      26: invokespecial #139                // Method java/util/zip/CRC32."<init>":()V
      29: putfield      #1                  // Field crc32:Ljava/util/zip/CRC32;
      32: aload_0
      33: sipush        500
      36: newarray       byte
      38: putfield      #9                  // Field ioBuffer:[B
      41: aload_0
      42: iconst_4
      43: anewarray     #140                // class "[B"
      46: putfield      #53                 // Field fileStatus:[[B
      49: aload_0
      50: new           #136                // class NodeList
      53: dup
      54: invokespecial #137                // Method NodeList."<init>":()V
      57: putfield      #111                // Field aClass19_1344:LNodeList;
      60: aload_0
      61: iconst_1
      62: putfield      #73                 // Field running:Z
      65: aload_0
      66: iconst_0
      67: putfield      #8                  // Field waiting:Z
      70: aload_0
      71: new           #136                // class NodeList
      74: dup
      75: invokespecial #137                // Method NodeList."<init>":()V
      78: putfield      #30                 // Field aClass19_1358:LNodeList;
      81: aload_0
      82: ldc           #141                // int 65000
      84: newarray       byte
      86: putfield      #118                // Field gzipInputBuffer:[B
      89: aload_0
      90: new           #142                // class NodeSubList
      93: dup
      94: invokespecial #143                // Method NodeSubList."<init>":()V
      97: putfield      #75                 // Field nodeSubList:LNodeSubList;
     100: aload_0
     101: iconst_4
     102: anewarray     #144                // class "[I"
     105: putfield      #52                 // Field versions:[[I
     108: aload_0
     109: iconst_4
     110: anewarray     #144                // class "[I"
     113: putfield      #59                 // Field crcs:[[I
     116: aload_0
     117: new           #136                // class NodeList
     120: dup
     121: invokespecial #137                // Method NodeList."<init>":()V
     124: putfield      #130                // Field aClass19_1368:LNodeList;
     127: aload_0
     128: new           #136                // class NodeList
     131: dup
     132: invokespecial #137                // Method NodeList."<init>":()V
     135: putfield      #96                 // Field aClass19_1370:LNodeList;
     138: return
}
