Compiled from "RSSocket.java"
final class RSSocket implements java.lang.Runnable {
  private java.io.InputStream inputStream;

  private java.io.OutputStream outputStream;

  private final java.net.Socket socket;

  private boolean closed;

  private final RSApplet rsApplet;

  private byte[] buffer;

  private int writeIndex;

  private int buffIndex;

  private boolean isWriter;

  private boolean hasIOError;

  public RSSocket(RSApplet, java.net.Socket) throws java.io.IOException;
    Code:
       0: aload_0
       1: invokespecial #1                  // Method java/lang/Object."<init>":()V
       4: aload_0
       5: iconst_0
       6: putfield      #2                  // Field closed:Z
       9: aload_0
      10: iconst_0
      11: putfield      #3                  // Field isWriter:Z
      14: aload_0
      15: iconst_0
      16: putfield      #4                  // Field hasIOError:Z
      19: aload_0
      20: aload_1
      21: putfield      #5                  // Field rsApplet:LRSApplet;
      24: aload_0
      25: aload_2
      26: putfield      #6                  // Field socket:Ljava/net/Socket;
      29: aload_0
      30: getfield      #6                  // Field socket:Ljava/net/Socket;
      33: sipush        30000
      36: invokevirtual #7                  // Method java/net/Socket.setSoTimeout:(I)V
      39: aload_0
      40: getfield      #6                  // Field socket:Ljava/net/Socket;
      43: iconst_1
      44: invokevirtual #8                  // Method java/net/Socket.setTcpNoDelay:(Z)V
      47: aload_0
      48: aload_0
      49: getfield      #6                  // Field socket:Ljava/net/Socket;
      52: invokevirtual #9                  // Method java/net/Socket.getInputStream:()Ljava/io/InputStream;
      55: putfield      #10                 // Field inputStream:Ljava/io/InputStream;
      58: aload_0
      59: aload_0
      60: getfield      #6                  // Field socket:Ljava/net/Socket;
      63: invokevirtual #11                 // Method java/net/Socket.getOutputStream:()Ljava/io/OutputStream;
      66: putfield      #12                 // Field outputStream:Ljava/io/OutputStream;
      69: return

  public void close();
    Code:
       0: aload_0
       1: iconst_1
       2: putfield      #2                  // Field closed:Z
       5: aload_0
       6: getfield      #10                 // Field inputStream:Ljava/io/InputStream;
       9: ifnull        19
      12: aload_0
      13: getfield      #10                 // Field inputStream:Ljava/io/InputStream;
      16: invokevirtual #13                 // Method java/io/InputStream.close:()V
      19: aload_0
      20: getfield      #12                 // Field outputStream:Ljava/io/OutputStream;
      23: ifnull        33
      26: aload_0
      27: getfield      #12                 // Field outputStream:Ljava/io/OutputStream;
      30: invokevirtual #14                 // Method java/io/OutputStream.close:()V
      33: aload_0
      34: getfield      #6                  // Field socket:Ljava/net/Socket;
      37: ifnull        47
      40: aload_0
      41: getfield      #6                  // Field socket:Ljava/net/Socket;
      44: invokevirtual #15                 // Method java/net/Socket.close:()V
      47: goto          59
      50: astore_1
      51: getstatic     #17                 // Field java/lang/System.out:Ljava/io/PrintStream;
      54: ldc           #18                 // String Error closing stream
      56: invokevirtual #19                 // Method java/io/PrintStream.println:(Ljava/lang/String;)V
      59: aload_0
      60: iconst_0
      61: putfield      #3                  // Field isWriter:Z
      64: aload_0
      65: dup
      66: astore_1
      67: monitorenter
      68: aload_0
      69: invokevirtual #20                 // Method java/lang/Object.notify:()V
      72: aload_1
      73: monitorexit
      74: goto          82
      77: astore_2
      78: aload_1
      79: monitorexit
      80: aload_2
      81: athrow
      82: aload_0
      83: aconst_null
      84: putfield      #21                 // Field buffer:[B
      87: return
    Exception table:
       from    to  target type
           5    47    50   Class java/io/IOException
          68    74    77   any
          77    80    77   any

  public int read() throws java.io.IOException;
    Code:
       0: aload_0
       1: getfield      #2                  // Field closed:Z
       4: ifeq          9
       7: iconst_0
       8: ireturn
       9: aload_0
      10: getfield      #10                 // Field inputStream:Ljava/io/InputStream;
      13: invokevirtual #22                 // Method java/io/InputStream.read:()I
      16: ireturn

  public int available() throws java.io.IOException;
    Code:
       0: aload_0
       1: getfield      #2                  // Field closed:Z
       4: ifeq          9
       7: iconst_0
       8: ireturn
       9: aload_0
      10: getfield      #10                 // Field inputStream:Ljava/io/InputStream;
      13: invokevirtual #23                 // Method java/io/InputStream.available:()I
      16: ireturn

  public void flushInputStream(byte[], int) throws java.io.IOException;
    Code:
       0: iconst_0
       1: istore_3
       2: aload_0
       3: getfield      #2                  // Field closed:Z
       6: ifeq          10
       9: return
      10: iload_2
      11: ifle          54
      14: aload_0
      15: getfield      #10                 // Field inputStream:Ljava/io/InputStream;
      18: aload_1
      19: iload_3
      20: iload_2
      21: invokevirtual #24                 // Method java/io/InputStream.read:([BII)I
      24: istore        4
      26: iload         4
      28: ifgt          41
      31: new           #16                 // class java/io/IOException
      34: dup
      35: ldc           #25                 // String EOF
      37: invokespecial #26                 // Method java/io/IOException."<init>":(Ljava/lang/String;)V
      40: athrow
      41: iload_3
      42: iload         4
      44: iadd
      45: istore_3
      46: iload_2
      47: iload         4
      49: isub
      50: istore_2
      51: goto          10
      54: return

  public void queueBytes(int, byte[]) throws java.io.IOException;
    Code:
       0: aload_0
       1: getfield      #2                  // Field closed:Z
       4: ifeq          8
       7: return
       8: aload_0
       9: getfield      #4                  // Field hasIOError:Z
      12: ifeq          30
      15: aload_0
      16: iconst_0
      17: putfield      #4                  // Field hasIOError:Z
      20: new           #16                 // class java/io/IOException
      23: dup
      24: ldc           #27                 // String Error in writer thread
      26: invokespecial #26                 // Method java/io/IOException."<init>":(Ljava/lang/String;)V
      29: athrow
      30: aload_0
      31: getfield      #21                 // Field buffer:[B
      34: ifnonnull     46
      37: aload_0
      38: sipush        5000
      41: newarray       byte
      43: putfield      #21                 // Field buffer:[B
      46: aload_0
      47: dup
      48: astore_3
      49: monitorenter
      50: iconst_0
      51: istore        4
      53: iload         4
      55: iload_1
      56: if_icmpge     121
      59: aload_0
      60: getfield      #21                 // Field buffer:[B
      63: aload_0
      64: getfield      #28                 // Field buffIndex:I
      67: aload_2
      68: iload         4
      70: baload
      71: bastore
      72: aload_0
      73: aload_0
      74: getfield      #28                 // Field buffIndex:I
      77: iconst_1
      78: iadd
      79: sipush        5000
      82: irem
      83: putfield      #28                 // Field buffIndex:I
      86: aload_0
      87: getfield      #28                 // Field buffIndex:I
      90: aload_0
      91: getfield      #29                 // Field writeIndex:I
      94: sipush        4900
      97: iadd
      98: sipush        5000
     101: irem
     102: if_icmpne     115
     105: new           #16                 // class java/io/IOException
     108: dup
     109: ldc           #30                 // String buffer overflow
     111: invokespecial #26                 // Method java/io/IOException."<init>":(Ljava/lang/String;)V
     114: athrow
     115: iinc          4, 1
     118: goto          53
     121: aload_0
     122: getfield      #3                  // Field isWriter:Z
     125: ifne          142
     128: aload_0
     129: iconst_1
     130: putfield      #3                  // Field isWriter:Z
     133: aload_0
     134: getfield      #5                  // Field rsApplet:LRSApplet;
     137: aload_0
     138: iconst_3
     139: invokevirtual #31                 // Method RSApplet.startRunnable:(Ljava/lang/Runnable;I)V
     142: aload_0
     143: invokevirtual #20                 // Method java/lang/Object.notify:()V
     146: aload_3
     147: monitorexit
     148: goto          158
     151: astore        5
     153: aload_3
     154: monitorexit
     155: aload         5
     157: athrow
     158: return
    Exception table:
       from    to  target type
          50   148   151   any
         151   155   151   any

  public void run();
    Code:
       0: aload_0
       1: getfield      #3                  // Field isWriter:Z
       4: ifeq          161
       7: aload_0
       8: dup
       9: astore_3
      10: monitorenter
      11: aload_0
      12: getfield      #28                 // Field buffIndex:I
      15: aload_0
      16: getfield      #29                 // Field writeIndex:I
      19: if_icmpne     31
      22: aload_0
      23: invokevirtual #32                 // Method java/lang/Object.wait:()V
      26: goto          31
      29: astore        4
      31: aload_0
      32: getfield      #3                  // Field isWriter:Z
      35: ifne          41
      38: aload_3
      39: monitorexit
      40: return
      41: aload_0
      42: getfield      #29                 // Field writeIndex:I
      45: istore_2
      46: aload_0
      47: getfield      #28                 // Field buffIndex:I
      50: aload_0
      51: getfield      #29                 // Field writeIndex:I
      54: if_icmplt     70
      57: aload_0
      58: getfield      #28                 // Field buffIndex:I
      61: aload_0
      62: getfield      #29                 // Field writeIndex:I
      65: isub
      66: istore_1
      67: goto          79
      70: sipush        5000
      73: aload_0
      74: getfield      #29                 // Field writeIndex:I
      77: isub
      78: istore_1
      79: aload_3
      80: monitorexit
      81: goto          91
      84: astore        5
      86: aload_3
      87: monitorexit
      88: aload         5
      90: athrow
      91: iload_1
      92: ifle          158
      95: aload_0
      96: getfield      #12                 // Field outputStream:Ljava/io/OutputStream;
      99: aload_0
     100: getfield      #21                 // Field buffer:[B
     103: iload_2
     104: iload_1
     105: invokevirtual #34                 // Method java/io/OutputStream.write:([BII)V
     108: goto          117
     111: astore_3
     112: aload_0
     113: iconst_1
     114: putfield      #4                  // Field hasIOError:Z
     117: aload_0
     118: aload_0
     119: getfield      #29                 // Field writeIndex:I
     122: iload_1
     123: iadd
     124: sipush        5000
     127: irem
     128: putfield      #29                 // Field writeIndex:I
     131: aload_0
     132: getfield      #28                 // Field buffIndex:I
     135: aload_0
     136: getfield      #29                 // Field writeIndex:I
     139: if_icmpne     149
     142: aload_0
     143: getfield      #12                 // Field outputStream:Ljava/io/OutputStream;
     146: invokevirtual #35                 // Method java/io/OutputStream.flush:()V
     149: goto          158
     152: astore_3
     153: aload_0
     154: iconst_1
     155: putfield      #4                  // Field hasIOError:Z
     158: goto          0
     161: return
    Exception table:
       from    to  target type
          22    26    29   Class java/lang/InterruptedException
          11    40    84   any
          41    81    84   any
          84    88    84   any
          95   108   111   Class java/io/IOException
         131   149   152   Class java/io/IOException

  public void printDebug();
    Code:
       0: getstatic     #17                 // Field java/lang/System.out:Ljava/io/PrintStream;
       3: new           #36                 // class java/lang/StringBuilder
       6: dup
       7: invokespecial #37                 // Method java/lang/StringBuilder."<init>":()V
      10: ldc           #38                 // String dummy:
      12: invokevirtual #39                 // Method java/lang/StringBuilder.append:(Ljava/lang/String;)Ljava/lang/StringBuilder;
      15: aload_0
      16: getfield      #2                  // Field closed:Z
      19: invokevirtual #40                 // Method java/lang/StringBuilder.append:(Z)Ljava/lang/StringBuilder;
      22: invokevirtual #41                 // Method java/lang/StringBuilder.toString:()Ljava/lang/String;
      25: invokevirtual #19                 // Method java/io/PrintStream.println:(Ljava/lang/String;)V
      28: getstatic     #17                 // Field java/lang/System.out:Ljava/io/PrintStream;
      31: new           #36                 // class java/lang/StringBuilder
      34: dup
      35: invokespecial #37                 // Method java/lang/StringBuilder."<init>":()V
      38: ldc           #42                 // String tcycl:
      40: invokevirtual #39                 // Method java/lang/StringBuilder.append:(Ljava/lang/String;)Ljava/lang/StringBuilder;
      43: aload_0
      44: getfield      #29                 // Field writeIndex:I
      47: invokevirtual #43                 // Method java/lang/StringBuilder.append:(I)Ljava/lang/StringBuilder;
      50: invokevirtual #41                 // Method java/lang/StringBuilder.toString:()Ljava/lang/String;
      53: invokevirtual #19                 // Method java/io/PrintStream.println:(Ljava/lang/String;)V
      56: getstatic     #17                 // Field java/lang/System.out:Ljava/io/PrintStream;
      59: new           #36                 // class java/lang/StringBuilder
      62: dup
      63: invokespecial #37                 // Method java/lang/StringBuilder."<init>":()V
      66: ldc           #44                 // String tnum:
      68: invokevirtual #39                 // Method java/lang/StringBuilder.append:(Ljava/lang/String;)Ljava/lang/StringBuilder;
      71: aload_0
      72: getfield      #28                 // Field buffIndex:I
      75: invokevirtual #43                 // Method java/lang/StringBuilder.append:(I)Ljava/lang/StringBuilder;
      78: invokevirtual #41                 // Method java/lang/StringBuilder.toString:()Ljava/lang/String;
      81: invokevirtual #19                 // Method java/io/PrintStream.println:(Ljava/lang/String;)V
      84: getstatic     #17                 // Field java/lang/System.out:Ljava/io/PrintStream;
      87: new           #36                 // class java/lang/StringBuilder
      90: dup
      91: invokespecial #37                 // Method java/lang/StringBuilder."<init>":()V
      94: ldc           #45                 // String writer:
      96: invokevirtual #39                 // Method java/lang/StringBuilder.append:(Ljava/lang/String;)Ljava/lang/StringBuilder;
      99: aload_0
     100: getfield      #3                  // Field isWriter:Z
     103: invokevirtual #40                 // Method java/lang/StringBuilder.append:(Z)Ljava/lang/StringBuilder;
     106: invokevirtual #41                 // Method java/lang/StringBuilder.toString:()Ljava/lang/String;
     109: invokevirtual #19                 // Method java/io/PrintStream.println:(Ljava/lang/String;)V
     112: getstatic     #17                 // Field java/lang/System.out:Ljava/io/PrintStream;
     115: new           #36                 // class java/lang/StringBuilder
     118: dup
     119: invokespecial #37                 // Method java/lang/StringBuilder."<init>":()V
     122: ldc           #46                 // String ioerror:
     124: invokevirtual #39                 // Method java/lang/StringBuilder.append:(Ljava/lang/String;)Ljava/lang/StringBuilder;
     127: aload_0
     128: getfield      #4                  // Field hasIOError:Z
     131: invokevirtual #40                 // Method java/lang/StringBuilder.append:(Z)Ljava/lang/StringBuilder;
     134: invokevirtual #41                 // Method java/lang/StringBuilder.toString:()Ljava/lang/String;
     137: invokevirtual #19                 // Method java/io/PrintStream.println:(Ljava/lang/String;)V
     140: getstatic     #17                 // Field java/lang/System.out:Ljava/io/PrintStream;
     143: new           #36                 // class java/lang/StringBuilder
     146: dup
     147: invokespecial #37                 // Method java/lang/StringBuilder."<init>":()V
     150: ldc           #47                 // String available:
     152: invokevirtual #39                 // Method java/lang/StringBuilder.append:(Ljava/lang/String;)Ljava/lang/StringBuilder;
     155: aload_0
     156: invokevirtual #48                 // Method available:()I
     159: invokevirtual #43                 // Method java/lang/StringBuilder.append:(I)Ljava/lang/StringBuilder;
     162: invokevirtual #41                 // Method java/lang/StringBuilder.toString:()Ljava/lang/String;
     165: invokevirtual #19                 // Method java/io/PrintStream.println:(Ljava/lang/String;)V
     168: goto          172
     171: astore_1
     172: return
    Exception table:
       from    to  target type
         140   168   171   Class java/io/IOException
}
