Compiled from "Sprite.java"
public final class Sprite extends DrawingArea {
  public int[] myPixels;

  public int myWidth;

  public int myHeight;

  private int anInt1442;

  private int anInt1443;

  public int anInt1444;

  public int anInt1445;

  public Sprite(int, int);
    Code:
       0: aload_0
       1: invokespecial #1                  // Method DrawingArea."<init>":()V
       4: aload_0
       5: iload_1
       6: iload_2
       7: imul
       8: newarray       int
      10: putfield      #2                  // Field myPixels:[I
      13: aload_0
      14: aload_0
      15: iload_1
      16: dup_x1
      17: putfield      #3                  // Field anInt1444:I
      20: putfield      #4                  // Field myWidth:I
      23: aload_0
      24: aload_0
      25: iload_2
      26: dup_x1
      27: putfield      #5                  // Field anInt1445:I
      30: putfield      #6                  // Field myHeight:I
      33: aload_0
      34: aload_0
      35: iconst_0
      36: dup_x1
      37: putfield      #7                  // Field anInt1443:I
      40: putfield      #8                  // Field anInt1442:I
      43: return

  public Sprite(byte[], java.awt.Component);
    Code:
       0: aload_0
       1: invokespecial #1                  // Method DrawingArea."<init>":()V
       4: invokestatic  #9                  // Method java/awt/Toolkit.getDefaultToolkit:()Ljava/awt/Toolkit;
       7: aload_1
       8: invokevirtual #10                 // Method java/awt/Toolkit.createImage:([B)Ljava/awt/Image;
      11: astore_3
      12: new           #11                 // class java/awt/MediaTracker
      15: dup
      16: aload_2
      17: invokespecial #12                 // Method java/awt/MediaTracker."<init>":(Ljava/awt/Component;)V
      20: astore        4
      22: aload         4
      24: aload_3
      25: iconst_0
      26: invokevirtual #13                 // Method java/awt/MediaTracker.addImage:(Ljava/awt/Image;I)V
      29: aload         4
      31: invokevirtual #14                 // Method java/awt/MediaTracker.waitForAll:()V
      34: aload_0
      35: aload_3
      36: aload_2
      37: invokevirtual #15                 // Method java/awt/Image.getWidth:(Ljava/awt/image/ImageObserver;)I
      40: putfield      #4                  // Field myWidth:I
      43: aload_0
      44: aload_3
      45: aload_2
      46: invokevirtual #16                 // Method java/awt/Image.getHeight:(Ljava/awt/image/ImageObserver;)I
      49: putfield      #6                  // Field myHeight:I
      52: aload_0
      53: aload_0
      54: getfield      #4                  // Field myWidth:I
      57: putfield      #3                  // Field anInt1444:I
      60: aload_0
      61: aload_0
      62: getfield      #6                  // Field myHeight:I
      65: putfield      #5                  // Field anInt1445:I
      68: aload_0
      69: iconst_0
      70: putfield      #8                  // Field anInt1442:I
      73: aload_0
      74: iconst_0
      75: putfield      #7                  // Field anInt1443:I
      78: aload_0
      79: aload_0
      80: getfield      #4                  // Field myWidth:I
      83: aload_0
      84: getfield      #6                  // Field myHeight:I
      87: imul
      88: newarray       int
      90: putfield      #2                  // Field myPixels:[I
      93: new           #17                 // class java/awt/image/PixelGrabber
      96: dup
      97: aload_3
      98: iconst_0
      99: iconst_0
     100: aload_0
     101: getfield      #4                  // Field myWidth:I
     104: aload_0
     105: getfield      #6                  // Field myHeight:I
     108: aload_0
     109: getfield      #2                  // Field myPixels:[I
     112: iconst_0
     113: aload_0
     114: getfield      #4                  // Field myWidth:I
     117: invokespecial #18                 // Method java/awt/image/PixelGrabber."<init>":(Ljava/awt/Image;IIII[III)V
     120: astore        5
     122: aload         5
     124: invokevirtual #19                 // Method java/awt/image/PixelGrabber.grabPixels:()Z
     127: pop
     128: goto          140
     131: astore_3
     132: getstatic     #21                 // Field java/lang/System.out:Ljava/io/PrintStream;
     135: ldc           #22                 // String Error converting jpg
     137: invokevirtual #23                 // Method java/io/PrintStream.println:(Ljava/lang/String;)V
     140: return
    Exception table:
       from    to  target type
           4   128   131   Class java/lang/Exception

  public Sprite(StreamLoader, java.lang.String, int);
    Code:
       0: aload_0
       1: invokespecial #1                  // Method DrawingArea."<init>":()V
       4: new           #24                 // class Stream
       7: dup
       8: aload_1
       9: new           #25                 // class java/lang/StringBuilder
      12: dup
      13: invokespecial #26                 // Method java/lang/StringBuilder."<init>":()V
      16: aload_2
      17: invokevirtual #27                 // Method java/lang/StringBuilder.append:(Ljava/lang/String;)Ljava/lang/StringBuilder;
      20: ldc           #28                 // String .dat
      22: invokevirtual #27                 // Method java/lang/StringBuilder.append:(Ljava/lang/String;)Ljava/lang/StringBuilder;
      25: invokevirtual #29                 // Method java/lang/StringBuilder.toString:()Ljava/lang/String;
      28: invokevirtual #30                 // Method StreamLoader.getDataForName:(Ljava/lang/String;)[B
      31: invokespecial #31                 // Method Stream."<init>":([B)V
      34: astore        4
      36: new           #24                 // class Stream
      39: dup
      40: aload_1
      41: ldc           #32                 // String index.dat
      43: invokevirtual #30                 // Method StreamLoader.getDataForName:(Ljava/lang/String;)[B
      46: invokespecial #31                 // Method Stream."<init>":([B)V
      49: astore        5
      51: aload         5
      53: aload         4
      55: invokevirtual #33                 // Method Stream.readUnsignedWord:()I
      58: putfield      #34                 // Field Stream.currentOffset:I
      61: aload_0
      62: aload         5
      64: invokevirtual #33                 // Method Stream.readUnsignedWord:()I
      67: putfield      #3                  // Field anInt1444:I
      70: aload_0
      71: aload         5
      73: invokevirtual #33                 // Method Stream.readUnsignedWord:()I
      76: putfield      #5                  // Field anInt1445:I
      79: aload         5
      81: invokevirtual #35                 // Method Stream.readUnsignedByte:()I
      84: istore        6
      86: iload         6
      88: newarray       int
      90: astore        7
      92: iconst_0
      93: istore        8
      95: iload         8
      97: iload         6
      99: iconst_1
     100: isub
     101: if_icmpge     140
     104: aload         7
     106: iload         8
     108: iconst_1
     109: iadd
     110: aload         5
     112: invokevirtual #36                 // Method Stream.read3Bytes:()I
     115: iastore
     116: aload         7
     118: iload         8
     120: iconst_1
     121: iadd
     122: iaload
     123: ifne          134
     126: aload         7
     128: iload         8
     130: iconst_1
     131: iadd
     132: iconst_1
     133: iastore
     134: iinc          8, 1
     137: goto          95
     140: iconst_0
     141: istore        8
     143: iload         8
     145: iload_3
     146: if_icmpge     198
     149: aload         5
     151: dup
     152: getfield      #34                 // Field Stream.currentOffset:I
     155: iconst_2
     156: iadd
     157: putfield      #34                 // Field Stream.currentOffset:I
     160: aload         4
     162: dup
     163: getfield      #34                 // Field Stream.currentOffset:I
     166: aload         5
     168: invokevirtual #33                 // Method Stream.readUnsignedWord:()I
     171: aload         5
     173: invokevirtual #33                 // Method Stream.readUnsignedWord:()I
     176: imul
     177: iadd
     178: putfield      #34                 // Field Stream.currentOffset:I
     181: aload         5
     183: dup
     184: getfield      #34                 // Field Stream.currentOffset:I
     187: iconst_1
     188: iadd
     189: putfield      #34                 // Field Stream.currentOffset:I
     192: iinc          8, 1
     195: goto          143
     198: aload_0
     199: aload         5
     201: invokevirtual #35                 // Method Stream.readUnsignedByte:()I
     204: putfield      #8                  // Field anInt1442:I
     207: aload_0
     208: aload         5
     210: invokevirtual #35                 // Method Stream.readUnsignedByte:()I
     213: putfield      #7                  // Field anInt1443:I
     216: aload_0
     217: aload         5
     219: invokevirtual #33                 // Method Stream.readUnsignedWord:()I
     222: putfield      #4                  // Field myWidth:I
     225: aload_0
     226: aload         5
     228: invokevirtual #33                 // Method Stream.readUnsignedWord:()I
     231: putfield      #6                  // Field myHeight:I
     234: aload         5
     236: invokevirtual #35                 // Method Stream.readUnsignedByte:()I
     239: istore        8
     241: aload_0
     242: getfield      #4                  // Field myWidth:I
     245: aload_0
     246: getfield      #6                  // Field myHeight:I
     249: imul
     250: istore        9
     252: aload_0
     253: iload         9
     255: newarray       int
     257: putfield      #2                  // Field myPixels:[I
     260: iload         8
     262: ifne          297
     265: iconst_0
     266: istore        10
     268: iload         10
     270: iload         9
     272: if_icmpge     296
     275: aload_0
     276: getfield      #2                  // Field myPixels:[I
     279: iload         10
     281: aload         7
     283: aload         4
     285: invokevirtual #35                 // Method Stream.readUnsignedByte:()I
     288: iaload
     289: iastore
     290: iinc          10, 1
     293: goto          268
     296: return
     297: iload         8
     299: iconst_1
     300: if_icmpne     362
     303: iconst_0
     304: istore        10
     306: iload         10
     308: aload_0
     309: getfield      #4                  // Field myWidth:I
     312: if_icmpge     362
     315: iconst_0
     316: istore        11
     318: iload         11
     320: aload_0
     321: getfield      #6                  // Field myHeight:I
     324: if_icmpge     356
     327: aload_0
     328: getfield      #2                  // Field myPixels:[I
     331: iload         10
     333: iload         11
     335: aload_0
     336: getfield      #4                  // Field myWidth:I
     339: imul
     340: iadd
     341: aload         7
     343: aload         4
     345: invokevirtual #35                 // Method Stream.readUnsignedByte:()I
     348: iaload
     349: iastore
     350: iinc          11, 1
     353: goto          318
     356: iinc          10, 1
     359: goto          306
     362: return

  public void method343();
    Code:
       0: aload_0
       1: getfield      #6                  // Field myHeight:I
       4: aload_0
       5: getfield      #4                  // Field myWidth:I
       8: aload_0
       9: getfield      #2                  // Field myPixels:[I
      12: invokestatic  #37                 // Method DrawingArea.initDrawingArea:(II[I)V
      15: return

  public void method344(int, int, int);
    Code:
       0: iconst_0
       1: istore        4
       3: iload         4
       5: aload_0
       6: getfield      #2                  // Field myPixels:[I
       9: arraylength
      10: if_icmpge     177
      13: aload_0
      14: getfield      #2                  // Field myPixels:[I
      17: iload         4
      19: iaload
      20: istore        5
      22: iload         5
      24: ifeq          171
      27: iload         5
      29: bipush        16
      31: ishr
      32: sipush        255
      35: iand
      36: istore        6
      38: iload         6
      40: iload_1
      41: iadd
      42: istore        6
      44: iload         6
      46: iconst_1
      47: if_icmpge     56
      50: iconst_1
      51: istore        6
      53: goto          69
      56: iload         6
      58: sipush        255
      61: if_icmple     69
      64: sipush        255
      67: istore        6
      69: iload         5
      71: bipush        8
      73: ishr
      74: sipush        255
      77: iand
      78: istore        7
      80: iload         7
      82: iload_2
      83: iadd
      84: istore        7
      86: iload         7
      88: iconst_1
      89: if_icmpge     98
      92: iconst_1
      93: istore        7
      95: goto          111
      98: iload         7
     100: sipush        255
     103: if_icmple     111
     106: sipush        255
     109: istore        7
     111: iload         5
     113: sipush        255
     116: iand
     117: istore        8
     119: iload         8
     121: iload_3
     122: iadd
     123: istore        8
     125: iload         8
     127: iconst_1
     128: if_icmpge     137
     131: iconst_1
     132: istore        8
     134: goto          150
     137: iload         8
     139: sipush        255
     142: if_icmple     150
     145: sipush        255
     148: istore        8
     150: aload_0
     151: getfield      #2                  // Field myPixels:[I
     154: iload         4
     156: iload         6
     158: bipush        16
     160: ishl
     161: iload         7
     163: bipush        8
     165: ishl
     166: iadd
     167: iload         8
     169: iadd
     170: iastore
     171: iinc          4, 1
     174: goto          3
     177: return

  public void method345();
    Code:
       0: aload_0
       1: getfield      #3                  // Field anInt1444:I
       4: aload_0
       5: getfield      #5                  // Field anInt1445:I
       8: imul
       9: newarray       int
      11: astore_1
      12: iconst_0
      13: istore_2
      14: iload_2
      15: aload_0
      16: getfield      #6                  // Field myHeight:I
      19: if_icmpge     62
      22: aload_0
      23: getfield      #2                  // Field myPixels:[I
      26: iload_2
      27: aload_0
      28: getfield      #4                  // Field myWidth:I
      31: imul
      32: aload_1
      33: iload_2
      34: aload_0
      35: getfield      #7                  // Field anInt1443:I
      38: aload_0
      39: getfield      #3                  // Field anInt1444:I
      42: imul
      43: iadd
      44: aload_0
      45: getfield      #8                  // Field anInt1442:I
      48: iadd
      49: aload_0
      50: getfield      #4                  // Field myWidth:I
      53: invokestatic  #38                 // Method java/lang/System.arraycopy:(Ljava/lang/Object;ILjava/lang/Object;II)V
      56: iinc          2, 1
      59: goto          14
      62: aload_0
      63: aload_1
      64: putfield      #2                  // Field myPixels:[I
      67: aload_0
      68: aload_0
      69: getfield      #3                  // Field anInt1444:I
      72: putfield      #4                  // Field myWidth:I
      75: aload_0
      76: aload_0
      77: getfield      #5                  // Field anInt1445:I
      80: putfield      #6                  // Field myHeight:I
      83: aload_0
      84: iconst_0
      85: putfield      #8                  // Field anInt1442:I
      88: aload_0
      89: iconst_0
      90: putfield      #7                  // Field anInt1443:I
      93: return

  public void method346(int, int);
    Code:
       0: iload_1
       1: aload_0
       2: getfield      #8                  // Field anInt1442:I
       5: iadd
       6: istore_1
       7: iload_2
       8: aload_0
       9: getfield      #7                  // Field anInt1443:I
      12: iadd
      13: istore_2
      14: iload_1
      15: iload_2
      16: getstatic     #39                 // Field DrawingArea.width:I
      19: imul
      20: iadd
      21: istore_3
      22: iconst_0
      23: istore        4
      25: aload_0
      26: getfield      #6                  // Field myHeight:I
      29: istore        5
      31: aload_0
      32: getfield      #4                  // Field myWidth:I
      35: istore        6
      37: getstatic     #39                 // Field DrawingArea.width:I
      40: iload         6
      42: isub
      43: istore        7
      45: iconst_0
      46: istore        8
      48: iload_2
      49: getstatic     #40                 // Field DrawingArea.topY:I
      52: if_icmpge     92
      55: getstatic     #40                 // Field DrawingArea.topY:I
      58: iload_2
      59: isub
      60: istore        9
      62: iload         5
      64: iload         9
      66: isub
      67: istore        5
      69: getstatic     #40                 // Field DrawingArea.topY:I
      72: istore_2
      73: iload         4
      75: iload         9
      77: iload         6
      79: imul
      80: iadd
      81: istore        4
      83: iload_3
      84: iload         9
      86: getstatic     #39                 // Field DrawingArea.width:I
      89: imul
      90: iadd
      91: istore_3
      92: iload_2
      93: iload         5
      95: iadd
      96: getstatic     #41                 // Field DrawingArea.bottomY:I
      99: if_icmple     115
     102: iload         5
     104: iload_2
     105: iload         5
     107: iadd
     108: getstatic     #41                 // Field DrawingArea.bottomY:I
     111: isub
     112: isub
     113: istore        5
     115: iload_1
     116: getstatic     #42                 // Field DrawingArea.topX:I
     119: if_icmpge     166
     122: getstatic     #42                 // Field DrawingArea.topX:I
     125: iload_1
     126: isub
     127: istore        9
     129: iload         6
     131: iload         9
     133: isub
     134: istore        6
     136: getstatic     #42                 // Field DrawingArea.topX:I
     139: istore_1
     140: iload         4
     142: iload         9
     144: iadd
     145: istore        4
     147: iload_3
     148: iload         9
     150: iadd
     151: istore_3
     152: iload         8
     154: iload         9
     156: iadd
     157: istore        8
     159: iload         7
     161: iload         9
     163: iadd
     164: istore        7
     166: iload_1
     167: iload         6
     169: iadd
     170: getstatic     #43                 // Field DrawingArea.bottomX:I
     173: if_icmple     207
     176: iload_1
     177: iload         6
     179: iadd
     180: getstatic     #43                 // Field DrawingArea.bottomX:I
     183: isub
     184: istore        9
     186: iload         6
     188: iload         9
     190: isub
     191: istore        6
     193: iload         8
     195: iload         9
     197: iadd
     198: istore        8
     200: iload         7
     202: iload         9
     204: iadd
     205: istore        7
     207: iload         6
     209: ifle          242
     212: iload         5
     214: ifgt          220
     217: goto          242
     220: aload_0
     221: iload_3
     222: iload         6
     224: iload         5
     226: iload         8
     228: iload         4
     230: iload         7
     232: aload_0
     233: getfield      #2                  // Field myPixels:[I
     236: getstatic     #44                 // Field DrawingArea.pixels:[I
     239: invokespecial #45                 // Method method347:(IIIIII[I[I)V
     242: return

  private void method347(int, int, int, int, int, int, int[], int[]);
    Code:
       0: iload_2
       1: iconst_2
       2: ishr
       3: ineg
       4: istore        9
       6: iload_2
       7: iconst_3
       8: iand
       9: ineg
      10: istore_2
      11: iload_3
      12: ineg
      13: istore        10
      15: iload         10
      17: ifge          142
      20: iload         9
      22: istore        11
      24: iload         11
      26: ifge          95
      29: aload         8
      31: iload_1
      32: iinc          1, 1
      35: aload         7
      37: iload         5
      39: iinc          5, 1
      42: iaload
      43: iastore
      44: aload         8
      46: iload_1
      47: iinc          1, 1
      50: aload         7
      52: iload         5
      54: iinc          5, 1
      57: iaload
      58: iastore
      59: aload         8
      61: iload_1
      62: iinc          1, 1
      65: aload         7
      67: iload         5
      69: iinc          5, 1
      72: iaload
      73: iastore
      74: aload         8
      76: iload_1
      77: iinc          1, 1
      80: aload         7
      82: iload         5
      84: iinc          5, 1
      87: iaload
      88: iastore
      89: iinc          11, 1
      92: goto          24
      95: iload_2
      96: istore        11
      98: iload         11
     100: ifge          124
     103: aload         8
     105: iload_1
     106: iinc          1, 1
     109: aload         7
     111: iload         5
     113: iinc          5, 1
     116: iaload
     117: iastore
     118: iinc          11, 1
     121: goto          98
     124: iload_1
     125: iload         6
     127: iadd
     128: istore_1
     129: iload         5
     131: iload         4
     133: iadd
     134: istore        5
     136: iinc          10, 1
     139: goto          15
     142: return

  public void drawSprite1(int, int);
    Code:
       0: sipush        128
       3: istore_3
       4: iload_1
       5: aload_0
       6: getfield      #8                  // Field anInt1442:I
       9: iadd
      10: istore_1
      11: iload_2
      12: aload_0
      13: getfield      #7                  // Field anInt1443:I
      16: iadd
      17: istore_2
      18: iload_1
      19: iload_2
      20: getstatic     #39                 // Field DrawingArea.width:I
      23: imul
      24: iadd
      25: istore        4
      27: iconst_0
      28: istore        5
      30: aload_0
      31: getfield      #6                  // Field myHeight:I
      34: istore        6
      36: aload_0
      37: getfield      #4                  // Field myWidth:I
      40: istore        7
      42: getstatic     #39                 // Field DrawingArea.width:I
      45: iload         7
      47: isub
      48: istore        8
      50: iconst_0
      51: istore        9
      53: iload_2
      54: getstatic     #40                 // Field DrawingArea.topY:I
      57: if_icmpge     99
      60: getstatic     #40                 // Field DrawingArea.topY:I
      63: iload_2
      64: isub
      65: istore        10
      67: iload         6
      69: iload         10
      71: isub
      72: istore        6
      74: getstatic     #40                 // Field DrawingArea.topY:I
      77: istore_2
      78: iload         5
      80: iload         10
      82: iload         7
      84: imul
      85: iadd
      86: istore        5
      88: iload         4
      90: iload         10
      92: getstatic     #39                 // Field DrawingArea.width:I
      95: imul
      96: iadd
      97: istore        4
      99: iload_2
     100: iload         6
     102: iadd
     103: getstatic     #41                 // Field DrawingArea.bottomY:I
     106: if_icmple     122
     109: iload         6
     111: iload_2
     112: iload         6
     114: iadd
     115: getstatic     #41                 // Field DrawingArea.bottomY:I
     118: isub
     119: isub
     120: istore        6
     122: iload_1
     123: getstatic     #42                 // Field DrawingArea.topX:I
     126: if_icmpge     175
     129: getstatic     #42                 // Field DrawingArea.topX:I
     132: iload_1
     133: isub
     134: istore        10
     136: iload         7
     138: iload         10
     140: isub
     141: istore        7
     143: getstatic     #42                 // Field DrawingArea.topX:I
     146: istore_1
     147: iload         5
     149: iload         10
     151: iadd
     152: istore        5
     154: iload         4
     156: iload         10
     158: iadd
     159: istore        4
     161: iload         9
     163: iload         10
     165: iadd
     166: istore        9
     168: iload         8
     170: iload         10
     172: iadd
     173: istore        8
     175: iload_1
     176: iload         7
     178: iadd
     179: getstatic     #43                 // Field DrawingArea.bottomX:I
     182: if_icmple     216
     185: iload_1
     186: iload         7
     188: iadd
     189: getstatic     #43                 // Field DrawingArea.bottomX:I
     192: isub
     193: istore        10
     195: iload         7
     197: iload         10
     199: isub
     200: istore        7
     202: iload         9
     204: iload         10
     206: iadd
     207: istore        9
     209: iload         8
     211: iload         10
     213: iadd
     214: istore        8
     216: iload         7
     218: ifle          250
     221: iload         6
     223: ifle          250
     226: aload_0
     227: iload         5
     229: iload         7
     231: getstatic     #44                 // Field DrawingArea.pixels:[I
     234: aload_0
     235: getfield      #2                  // Field myPixels:[I
     238: iload         9
     240: iload         6
     242: iload         8
     244: iload_3
     245: iload         4
     247: invokespecial #46                 // Method method351:(II[I[IIIIII)V
     250: return

  public void drawSprite(int, int);
    Code:
       0: iload_1
       1: aload_0
       2: getfield      #8                  // Field anInt1442:I
       5: iadd
       6: istore_1
       7: iload_2
       8: aload_0
       9: getfield      #7                  // Field anInt1443:I
      12: iadd
      13: istore_2
      14: iload_1
      15: iload_2
      16: getstatic     #39                 // Field DrawingArea.width:I
      19: imul
      20: iadd
      21: istore_3
      22: iconst_0
      23: istore        4
      25: aload_0
      26: getfield      #6                  // Field myHeight:I
      29: istore        5
      31: aload_0
      32: getfield      #4                  // Field myWidth:I
      35: istore        6
      37: getstatic     #39                 // Field DrawingArea.width:I
      40: iload         6
      42: isub
      43: istore        7
      45: iconst_0
      46: istore        8
      48: iload_2
      49: getstatic     #40                 // Field DrawingArea.topY:I
      52: if_icmpge     92
      55: getstatic     #40                 // Field DrawingArea.topY:I
      58: iload_2
      59: isub
      60: istore        9
      62: iload         5
      64: iload         9
      66: isub
      67: istore        5
      69: getstatic     #40                 // Field DrawingArea.topY:I
      72: istore_2
      73: iload         4
      75: iload         9
      77: iload         6
      79: imul
      80: iadd
      81: istore        4
      83: iload_3
      84: iload         9
      86: getstatic     #39                 // Field DrawingArea.width:I
      89: imul
      90: iadd
      91: istore_3
      92: iload_2
      93: iload         5
      95: iadd
      96: getstatic     #41                 // Field DrawingArea.bottomY:I
      99: if_icmple     115
     102: iload         5
     104: iload_2
     105: iload         5
     107: iadd
     108: getstatic     #41                 // Field DrawingArea.bottomY:I
     111: isub
     112: isub
     113: istore        5
     115: iload_1
     116: getstatic     #42                 // Field DrawingArea.topX:I
     119: if_icmpge     166
     122: getstatic     #42                 // Field DrawingArea.topX:I
     125: iload_1
     126: isub
     127: istore        9
     129: iload         6
     131: iload         9
     133: isub
     134: istore        6
     136: getstatic     #42                 // Field DrawingArea.topX:I
     139: istore_1
     140: iload         4
     142: iload         9
     144: iadd
     145: istore        4
     147: iload_3
     148: iload         9
     150: iadd
     151: istore_3
     152: iload         8
     154: iload         9
     156: iadd
     157: istore        8
     159: iload         7
     161: iload         9
     163: iadd
     164: istore        7
     166: iload_1
     167: iload         6
     169: iadd
     170: getstatic     #43                 // Field DrawingArea.bottomX:I
     173: if_icmple     207
     176: iload_1
     177: iload         6
     179: iadd
     180: getstatic     #43                 // Field DrawingArea.bottomX:I
     183: isub
     184: istore        9
     186: iload         6
     188: iload         9
     190: isub
     191: istore        6
     193: iload         8
     195: iload         9
     197: iadd
     198: istore        8
     200: iload         7
     202: iload         9
     204: iadd
     205: istore        7
     207: iload         6
     209: ifle          239
     212: iload         5
     214: ifle          239
     217: aload_0
     218: getstatic     #44                 // Field DrawingArea.pixels:[I
     221: aload_0
     222: getfield      #2                  // Field myPixels:[I
     225: iload         4
     227: iload_3
     228: iload         6
     230: iload         5
     232: iload         7
     234: iload         8
     236: invokespecial #47                 // Method method349:([I[IIIIIII)V
     239: return

  private void method349(int[], int[], int, int, int, int, int, int);
    Code:
       0: iload         5
       2: iconst_2
       3: ishr
       4: ineg
       5: istore        10
       7: iload         5
       9: iconst_3
      10: iand
      11: ineg
      12: istore        5
      14: iload         6
      16: ineg
      17: istore        11
      19: iload         11
      21: ifge          212
      24: iload         10
      26: istore        12
      28: iload         12
      30: ifge          151
      33: aload_2
      34: iload_3
      35: iinc          3, 1
      38: iaload
      39: istore        9
      41: iload         9
      43: ifeq          58
      46: aload_1
      47: iload         4
      49: iinc          4, 1
      52: iload         9
      54: iastore
      55: goto          61
      58: iinc          4, 1
      61: aload_2
      62: iload_3
      63: iinc          3, 1
      66: iaload
      67: istore        9
      69: iload         9
      71: ifeq          86
      74: aload_1
      75: iload         4
      77: iinc          4, 1
      80: iload         9
      82: iastore
      83: goto          89
      86: iinc          4, 1
      89: aload_2
      90: iload_3
      91: iinc          3, 1
      94: iaload
      95: istore        9
      97: iload         9
      99: ifeq          114
     102: aload_1
     103: iload         4
     105: iinc          4, 1
     108: iload         9
     110: iastore
     111: goto          117
     114: iinc          4, 1
     117: aload_2
     118: iload_3
     119: iinc          3, 1
     122: iaload
     123: istore        9
     125: iload         9
     127: ifeq          142
     130: aload_1
     131: iload         4
     133: iinc          4, 1
     136: iload         9
     138: iastore
     139: goto          145
     142: iinc          4, 1
     145: iinc          12, 1
     148: goto          28
     151: iload         5
     153: istore        12
     155: iload         12
     157: ifge          194
     160: aload_2
     161: iload_3
     162: iinc          3, 1
     165: iaload
     166: istore        9
     168: iload         9
     170: ifeq          185
     173: aload_1
     174: iload         4
     176: iinc          4, 1
     179: iload         9
     181: iastore
     182: goto          188
     185: iinc          4, 1
     188: iinc          12, 1
     191: goto          155
     194: iload         4
     196: iload         7
     198: iadd
     199: istore        4
     201: iload_3
     202: iload         8
     204: iadd
     205: istore_3
     206: iinc          11, 1
     209: goto          19
     212: return

  private void method351(int, int, int[], int[], int, int, int, int, int);
    Code:
       0: sipush        256
       3: iload         8
       5: isub
       6: istore        11
       8: iload         6
      10: ineg
      11: istore        12
      13: iload         12
      15: ifge          128
      18: iload_2
      19: ineg
      20: istore        13
      22: iload         13
      24: ifge          110
      27: aload         4
      29: iload_1
      30: iinc          1, 1
      33: iaload
      34: istore        10
      36: iload         10
      38: ifeq          101
      41: aload_3
      42: iload         9
      44: iaload
      45: istore        14
      47: aload_3
      48: iload         9
      50: iinc          9, 1
      53: iload         10
      55: ldc           #48                 // int 16711935
      57: iand
      58: iload         8
      60: imul
      61: iload         14
      63: ldc           #48                 // int 16711935
      65: iand
      66: iload         11
      68: imul
      69: iadd
      70: ldc           #49                 // int -16711936
      72: iand
      73: iload         10
      75: ldc           #50                 // int 65280
      77: iand
      78: iload         8
      80: imul
      81: iload         14
      83: ldc           #50                 // int 65280
      85: iand
      86: iload         11
      88: imul
      89: iadd
      90: ldc           #51                 // int 16711680
      92: iand
      93: iadd
      94: bipush        8
      96: ishr
      97: iastore
      98: goto          104
     101: iinc          9, 1
     104: iinc          13, 1
     107: goto          22
     110: iload         9
     112: iload         7
     114: iadd
     115: istore        9
     117: iload_1
     118: iload         5
     120: iadd
     121: istore_1
     122: iinc          12, 1
     125: goto          13
     128: return

  public void method352(int, int, int[], int, int[], int, int, int, int, int);
    Code:
       0: iload         9
       2: ineg
       3: iconst_2
       4: idiv
       5: istore        11
       7: iload_1
       8: ineg
       9: iconst_2
      10: idiv
      11: istore        12
      13: iload_2
      14: i2d
      15: ldc2_w        #52                 // double 326.11d
      18: ddiv
      19: invokestatic  #54                 // Method java/lang/Math.sin:(D)D
      22: ldc2_w        #55                 // double 65536.0d
      25: dmul
      26: d2i
      27: istore        13
      29: iload_2
      30: i2d
      31: ldc2_w        #52                 // double 326.11d
      34: ddiv
      35: invokestatic  #57                 // Method java/lang/Math.cos:(D)D
      38: ldc2_w        #55                 // double 65536.0d
      41: dmul
      42: d2i
      43: istore        14
      45: iload         13
      47: iload         4
      49: imul
      50: bipush        8
      52: ishr
      53: istore        13
      55: iload         14
      57: iload         4
      59: imul
      60: bipush        8
      62: ishr
      63: istore        14
      65: iload         10
      67: bipush        16
      69: ishl
      70: iload         12
      72: iload         13
      74: imul
      75: iload         11
      77: iload         14
      79: imul
      80: iadd
      81: iadd
      82: istore        15
      84: iload         6
      86: bipush        16
      88: ishl
      89: iload         12
      91: iload         14
      93: imul
      94: iload         11
      96: iload         13
      98: imul
      99: isub
     100: iadd
     101: istore        16
     103: iload         8
     105: iload         7
     107: getstatic     #39                 // Field DrawingArea.width:I
     110: imul
     111: iadd
     112: istore        17
     114: iconst_0
     115: istore        7
     117: iload         7
     119: iload_1
     120: if_icmpge     247
     123: aload         5
     125: iload         7
     127: iaload
     128: istore        18
     130: iload         17
     132: iload         18
     134: iadd
     135: istore        19
     137: iload         15
     139: iload         14
     141: iload         18
     143: imul
     144: iadd
     145: istore        20
     147: iload         16
     149: iload         13
     151: iload         18
     153: imul
     154: isub
     155: istore        21
     157: aload_3
     158: iload         7
     160: iaload
     161: ineg
     162: istore        8
     164: iload         8
     166: ifge          219
     169: getstatic     #44                 // Field DrawingArea.pixels:[I
     172: iload         19
     174: iinc          19, 1
     177: aload_0
     178: getfield      #2                  // Field myPixels:[I
     181: iload         20
     183: bipush        16
     185: ishr
     186: iload         21
     188: bipush        16
     190: ishr
     191: aload_0
     192: getfield      #4                  // Field myWidth:I
     195: imul
     196: iadd
     197: iaload
     198: iastore
     199: iload         20
     201: iload         14
     203: iadd
     204: istore        20
     206: iload         21
     208: iload         13
     210: isub
     211: istore        21
     213: iinc          8, 1
     216: goto          164
     219: iload         15
     221: iload         13
     223: iadd
     224: istore        15
     226: iload         16
     228: iload         14
     230: iadd
     231: istore        16
     233: iload         17
     235: getstatic     #39                 // Field DrawingArea.width:I
     238: iadd
     239: istore        17
     241: iinc          7, 1
     244: goto          117
     247: goto          252
     250: astore        11
     252: return
    Exception table:
       from    to  target type
           0   247   250   Class java/lang/Exception

  public void method353(int, double, int);
    Code:
       0: bipush        15
       2: istore        5
       4: bipush        20
       6: istore        6
       8: bipush        15
      10: istore        7
      12: sipush        256
      15: istore        8
      17: bipush        20
      19: istore        9
      21: iload         6
      23: ineg
      24: iconst_2
      25: idiv
      26: istore        10
      28: iload         9
      30: ineg
      31: iconst_2
      32: idiv
      33: istore        11
      35: dload_2
      36: invokestatic  #54                 // Method java/lang/Math.sin:(D)D
      39: ldc2_w        #55                 // double 65536.0d
      42: dmul
      43: d2i
      44: istore        12
      46: dload_2
      47: invokestatic  #57                 // Method java/lang/Math.cos:(D)D
      50: ldc2_w        #55                 // double 65536.0d
      53: dmul
      54: d2i
      55: istore        13
      57: iload         12
      59: iload         8
      61: imul
      62: bipush        8
      64: ishr
      65: istore        12
      67: iload         13
      69: iload         8
      71: imul
      72: bipush        8
      74: ishr
      75: istore        13
      77: iload         7
      79: bipush        16
      81: ishl
      82: iload         11
      84: iload         12
      86: imul
      87: iload         10
      89: iload         13
      91: imul
      92: iadd
      93: iadd
      94: istore        14
      96: iload         5
      98: bipush        16
     100: ishl
     101: iload         11
     103: iload         13
     105: imul
     106: iload         10
     108: iload         12
     110: imul
     111: isub
     112: iadd
     113: istore        15
     115: iload         4
     117: iload_1
     118: getstatic     #39                 // Field DrawingArea.width:I
     121: imul
     122: iadd
     123: istore        16
     125: iconst_0
     126: istore_1
     127: iload_1
     128: iload         9
     130: if_icmpge     248
     133: iload         16
     135: istore        17
     137: iload         14
     139: istore        18
     141: iload         15
     143: istore        19
     145: iload         6
     147: ineg
     148: istore        4
     150: iload         4
     152: ifge          220
     155: aload_0
     156: getfield      #2                  // Field myPixels:[I
     159: iload         18
     161: bipush        16
     163: ishr
     164: iload         19
     166: bipush        16
     168: ishr
     169: aload_0
     170: getfield      #4                  // Field myWidth:I
     173: imul
     174: iadd
     175: iaload
     176: istore        20
     178: iload         20
     180: ifeq          197
     183: getstatic     #44                 // Field DrawingArea.pixels:[I
     186: iload         17
     188: iinc          17, 1
     191: iload         20
     193: iastore
     194: goto          200
     197: iinc          17, 1
     200: iload         18
     202: iload         13
     204: iadd
     205: istore        18
     207: iload         19
     209: iload         12
     211: isub
     212: istore        19
     214: iinc          4, 1
     217: goto          150
     220: iload         14
     222: iload         12
     224: iadd
     225: istore        14
     227: iload         15
     229: iload         13
     231: iadd
     232: istore        15
     234: iload         16
     236: getstatic     #39                 // Field DrawingArea.width:I
     239: iadd
     240: istore        16
     242: iinc          1, 1
     245: goto          127
     248: goto          253
     251: astore        10
     253: return
    Exception table:
       from    to  target type
          21   248   251   Class java/lang/Exception

  public void method354(Background, int, int);
    Code:
       0: iload_3
       1: aload_0
       2: getfield      #8                  // Field anInt1442:I
       5: iadd
       6: istore_3
       7: iload_2
       8: aload_0
       9: getfield      #7                  // Field anInt1443:I
      12: iadd
      13: istore_2
      14: iload_3
      15: iload_2
      16: getstatic     #39                 // Field DrawingArea.width:I
      19: imul
      20: iadd
      21: istore        4
      23: iconst_0
      24: istore        5
      26: aload_0
      27: getfield      #6                  // Field myHeight:I
      30: istore        6
      32: aload_0
      33: getfield      #4                  // Field myWidth:I
      36: istore        7
      38: getstatic     #39                 // Field DrawingArea.width:I
      41: iload         7
      43: isub
      44: istore        8
      46: iconst_0
      47: istore        9
      49: iload_2
      50: getstatic     #40                 // Field DrawingArea.topY:I
      53: if_icmpge     95
      56: getstatic     #40                 // Field DrawingArea.topY:I
      59: iload_2
      60: isub
      61: istore        10
      63: iload         6
      65: iload         10
      67: isub
      68: istore        6
      70: getstatic     #40                 // Field DrawingArea.topY:I
      73: istore_2
      74: iload         5
      76: iload         10
      78: iload         7
      80: imul
      81: iadd
      82: istore        5
      84: iload         4
      86: iload         10
      88: getstatic     #39                 // Field DrawingArea.width:I
      91: imul
      92: iadd
      93: istore        4
      95: iload_2
      96: iload         6
      98: iadd
      99: getstatic     #41                 // Field DrawingArea.bottomY:I
     102: if_icmple     118
     105: iload         6
     107: iload_2
     108: iload         6
     110: iadd
     111: getstatic     #41                 // Field DrawingArea.bottomY:I
     114: isub
     115: isub
     116: istore        6
     118: iload_3
     119: getstatic     #42                 // Field DrawingArea.topX:I
     122: if_icmpge     171
     125: getstatic     #42                 // Field DrawingArea.topX:I
     128: iload_3
     129: isub
     130: istore        10
     132: iload         7
     134: iload         10
     136: isub
     137: istore        7
     139: getstatic     #42                 // Field DrawingArea.topX:I
     142: istore_3
     143: iload         5
     145: iload         10
     147: iadd
     148: istore        5
     150: iload         4
     152: iload         10
     154: iadd
     155: istore        4
     157: iload         9
     159: iload         10
     161: iadd
     162: istore        9
     164: iload         8
     166: iload         10
     168: iadd
     169: istore        8
     171: iload_3
     172: iload         7
     174: iadd
     175: getstatic     #43                 // Field DrawingArea.bottomX:I
     178: if_icmple     212
     181: iload_3
     182: iload         7
     184: iadd
     185: getstatic     #43                 // Field DrawingArea.bottomX:I
     188: isub
     189: istore        10
     191: iload         7
     193: iload         10
     195: isub
     196: istore        7
     198: iload         9
     200: iload         10
     202: iadd
     203: istore        9
     205: iload         8
     207: iload         10
     209: iadd
     210: istore        8
     212: iload         7
     214: ifle          250
     217: iload         6
     219: ifle          250
     222: aload_0
     223: aload_0
     224: getfield      #2                  // Field myPixels:[I
     227: iload         7
     229: aload_1
     230: getfield      #58                 // Field Background.aByteArray1450:[B
     233: iload         6
     235: getstatic     #44                 // Field DrawingArea.pixels:[I
     238: iconst_0
     239: iload         8
     241: iload         4
     243: iload         9
     245: iload         5
     247: invokespecial #59                 // Method method355:([II[BI[IIIIII)V
     250: return

  private void method355(int[], int, byte[], int, int[], int, int, int, int, int);
    Code:
       0: iload_2
       1: iconst_2
       2: ishr
       3: ineg
       4: istore        11
       6: iload_2
       7: iconst_3
       8: iand
       9: ineg
      10: istore_2
      11: iload         4
      13: ineg
      14: istore        12
      16: iload         12
      18: ifge          255
      21: iload         11
      23: istore        13
      25: iload         13
      27: ifge          184
      30: aload_1
      31: iload         10
      33: iinc          10, 1
      36: iaload
      37: istore        6
      39: iload         6
      41: ifeq          64
      44: aload_3
      45: iload         8
      47: baload
      48: ifne          64
      51: aload         5
      53: iload         8
      55: iinc          8, 1
      58: iload         6
      60: iastore
      61: goto          67
      64: iinc          8, 1
      67: aload_1
      68: iload         10
      70: iinc          10, 1
      73: iaload
      74: istore        6
      76: iload         6
      78: ifeq          101
      81: aload_3
      82: iload         8
      84: baload
      85: ifne          101
      88: aload         5
      90: iload         8
      92: iinc          8, 1
      95: iload         6
      97: iastore
      98: goto          104
     101: iinc          8, 1
     104: aload_1
     105: iload         10
     107: iinc          10, 1
     110: iaload
     111: istore        6
     113: iload         6
     115: ifeq          138
     118: aload_3
     119: iload         8
     121: baload
     122: ifne          138
     125: aload         5
     127: iload         8
     129: iinc          8, 1
     132: iload         6
     134: iastore
     135: goto          141
     138: iinc          8, 1
     141: aload_1
     142: iload         10
     144: iinc          10, 1
     147: iaload
     148: istore        6
     150: iload         6
     152: ifeq          175
     155: aload_3
     156: iload         8
     158: baload
     159: ifne          175
     162: aload         5
     164: iload         8
     166: iinc          8, 1
     169: iload         6
     171: iastore
     172: goto          178
     175: iinc          8, 1
     178: iinc          13, 1
     181: goto          25
     184: iload_2
     185: istore        13
     187: iload         13
     189: ifge          235
     192: aload_1
     193: iload         10
     195: iinc          10, 1
     198: iaload
     199: istore        6
     201: iload         6
     203: ifeq          226
     206: aload_3
     207: iload         8
     209: baload
     210: ifne          226
     213: aload         5
     215: iload         8
     217: iinc          8, 1
     220: iload         6
     222: iastore
     223: goto          229
     226: iinc          8, 1
     229: iinc          13, 1
     232: goto          187
     235: iload         8
     237: iload         7
     239: iadd
     240: istore        8
     242: iload         10
     244: iload         9
     246: iadd
     247: istore        10
     249: iinc          12, 1
     252: goto          16
     255: return
}
