Compiled from "Stream.java"
public final class Stream extends NodeSub {
  public byte[] buffer;

  public int currentOffset;

  public int bitPosition;

  private static final int[] anIntArray1409;

  public ISAACRandomGen encryption;

  private static int anInt1412;

  private static final NodeList nodeList;

  public static Stream create();
    Code:
       0: getstatic     #1                  // Field nodeList:LNodeList;
       3: dup
       4: astore_0
       5: monitorenter
       6: aconst_null
       7: astore_1
       8: getstatic     #2                  // Field anInt1412:I
      11: ifle          32
      14: getstatic     #2                  // Field anInt1412:I
      17: iconst_1
      18: isub
      19: putstatic     #2                  // Field anInt1412:I
      22: getstatic     #1                  // Field nodeList:LNodeList;
      25: invokevirtual #3                  // Method NodeList.popHead:()LNode;
      28: checkcast     #4                  // class Stream
      31: astore_1
      32: aload_1
      33: ifnull        45
      36: aload_1
      37: iconst_0
      38: putfield      #5                  // Field currentOffset:I
      41: aload_1
      42: aload_0
      43: monitorexit
      44: areturn
      45: aload_0
      46: monitorexit
      47: goto          55
      50: astore_2
      51: aload_0
      52: monitorexit
      53: aload_2
      54: athrow
      55: new           #4                  // class Stream
      58: dup
      59: invokespecial #6                  // Method "<init>":()V
      62: astore_0
      63: aload_0
      64: iconst_0
      65: putfield      #5                  // Field currentOffset:I
      68: aload_0
      69: sipush        5000
      72: newarray       byte
      74: putfield      #7                  // Field buffer:[B
      77: aload_0
      78: areturn
    Exception table:
       from    to  target type
           6    44    50   any
          45    47    50   any
          50    53    50   any

  private Stream();
    Code:
       0: aload_0
       1: invokespecial #8                  // Method NodeSub."<init>":()V
       4: return

  public Stream(byte[]);
    Code:
       0: aload_0
       1: invokespecial #8                  // Method NodeSub."<init>":()V
       4: aload_0
       5: aload_1
       6: putfield      #7                  // Field buffer:[B
       9: aload_0
      10: iconst_0
      11: putfield      #5                  // Field currentOffset:I
      14: return

  public void createFrame(int);
    Code:
       0: aload_0
       1: getfield      #7                  // Field buffer:[B
       4: aload_0
       5: dup
       6: getfield      #5                  // Field currentOffset:I
       9: dup_x1
      10: iconst_1
      11: iadd
      12: putfield      #5                  // Field currentOffset:I
      15: iload_1
      16: aload_0
      17: getfield      #9                  // Field encryption:LISAACRandomGen;
      20: invokevirtual #10                 // Method ISAACRandomGen.getNextKey:()I
      23: iadd
      24: i2b
      25: bastore
      26: return

  public void writeWordBigEndian(int);
    Code:
       0: aload_0
       1: getfield      #7                  // Field buffer:[B
       4: aload_0
       5: dup
       6: getfield      #5                  // Field currentOffset:I
       9: dup_x1
      10: iconst_1
      11: iadd
      12: putfield      #5                  // Field currentOffset:I
      15: iload_1
      16: i2b
      17: bastore
      18: return

  public void writeWord(int);
    Code:
       0: aload_0
       1: getfield      #7                  // Field buffer:[B
       4: aload_0
       5: dup
       6: getfield      #5                  // Field currentOffset:I
       9: dup_x1
      10: iconst_1
      11: iadd
      12: putfield      #5                  // Field currentOffset:I
      15: iload_1
      16: bipush        8
      18: ishr
      19: i2b
      20: bastore
      21: aload_0
      22: getfield      #7                  // Field buffer:[B
      25: aload_0
      26: dup
      27: getfield      #5                  // Field currentOffset:I
      30: dup_x1
      31: iconst_1
      32: iadd
      33: putfield      #5                  // Field currentOffset:I
      36: iload_1
      37: i2b
      38: bastore
      39: return

  public void method400(int);
    Code:
       0: aload_0
       1: getfield      #7                  // Field buffer:[B
       4: aload_0
       5: dup
       6: getfield      #5                  // Field currentOffset:I
       9: dup_x1
      10: iconst_1
      11: iadd
      12: putfield      #5                  // Field currentOffset:I
      15: iload_1
      16: i2b
      17: bastore
      18: aload_0
      19: getfield      #7                  // Field buffer:[B
      22: aload_0
      23: dup
      24: getfield      #5                  // Field currentOffset:I
      27: dup_x1
      28: iconst_1
      29: iadd
      30: putfield      #5                  // Field currentOffset:I
      33: iload_1
      34: bipush        8
      36: ishr
      37: i2b
      38: bastore
      39: return

  public void writeDWordBigEndian(int);
    Code:
       0: aload_0
       1: getfield      #7                  // Field buffer:[B
       4: aload_0
       5: dup
       6: getfield      #5                  // Field currentOffset:I
       9: dup_x1
      10: iconst_1
      11: iadd
      12: putfield      #5                  // Field currentOffset:I
      15: iload_1
      16: bipush        16
      18: ishr
      19: i2b
      20: bastore
      21: aload_0
      22: getfield      #7                  // Field buffer:[B
      25: aload_0
      26: dup
      27: getfield      #5                  // Field currentOffset:I
      30: dup_x1
      31: iconst_1
      32: iadd
      33: putfield      #5                  // Field currentOffset:I
      36: iload_1
      37: bipush        8
      39: ishr
      40: i2b
      41: bastore
      42: aload_0
      43: getfield      #7                  // Field buffer:[B
      46: aload_0
      47: dup
      48: getfield      #5                  // Field currentOffset:I
      51: dup_x1
      52: iconst_1
      53: iadd
      54: putfield      #5                  // Field currentOffset:I
      57: iload_1
      58: i2b
      59: bastore
      60: return

  public void writeDWord(int);
    Code:
       0: aload_0
       1: getfield      #7                  // Field buffer:[B
       4: aload_0
       5: dup
       6: getfield      #5                  // Field currentOffset:I
       9: dup_x1
      10: iconst_1
      11: iadd
      12: putfield      #5                  // Field currentOffset:I
      15: iload_1
      16: bipush        24
      18: ishr
      19: i2b
      20: bastore
      21: aload_0
      22: getfield      #7                  // Field buffer:[B
      25: aload_0
      26: dup
      27: getfield      #5                  // Field currentOffset:I
      30: dup_x1
      31: iconst_1
      32: iadd
      33: putfield      #5                  // Field currentOffset:I
      36: iload_1
      37: bipush        16
      39: ishr
      40: i2b
      41: bastore
      42: aload_0
      43: getfield      #7                  // Field buffer:[B
      46: aload_0
      47: dup
      48: getfield      #5                  // Field currentOffset:I
      51: dup_x1
      52: iconst_1
      53: iadd
      54: putfield      #5                  // Field currentOffset:I
      57: iload_1
      58: bipush        8
      60: ishr
      61: i2b
      62: bastore
      63: aload_0
      64: getfield      #7                  // Field buffer:[B
      67: aload_0
      68: dup
      69: getfield      #5                  // Field currentOffset:I
      72: dup_x1
      73: iconst_1
      74: iadd
      75: putfield      #5                  // Field currentOffset:I
      78: iload_1
      79: i2b
      80: bastore
      81: return

  public void method403(int);
    Code:
       0: aload_0
       1: getfield      #7                  // Field buffer:[B
       4: aload_0
       5: dup
       6: getfield      #5                  // Field currentOffset:I
       9: dup_x1
      10: iconst_1
      11: iadd
      12: putfield      #5                  // Field currentOffset:I
      15: iload_1
      16: i2b
      17: bastore
      18: aload_0
      19: getfield      #7                  // Field buffer:[B
      22: aload_0
      23: dup
      24: getfield      #5                  // Field currentOffset:I
      27: dup_x1
      28: iconst_1
      29: iadd
      30: putfield      #5                  // Field currentOffset:I
      33: iload_1
      34: bipush        8
      36: ishr
      37: i2b
      38: bastore
      39: aload_0
      40: getfield      #7                  // Field buffer:[B
      43: aload_0
      44: dup
      45: getfield      #5                  // Field currentOffset:I
      48: dup_x1
      49: iconst_1
      50: iadd
      51: putfield      #5                  // Field currentOffset:I
      54: iload_1
      55: bipush        16
      57: ishr
      58: i2b
      59: bastore
      60: aload_0
      61: getfield      #7                  // Field buffer:[B
      64: aload_0
      65: dup
      66: getfield      #5                  // Field currentOffset:I
      69: dup_x1
      70: iconst_1
      71: iadd
      72: putfield      #5                  // Field currentOffset:I
      75: iload_1
      76: bipush        24
      78: ishr
      79: i2b
      80: bastore
      81: return

  public void writeQWord(long);
    Code:
       0: aload_0
       1: getfield      #7                  // Field buffer:[B
       4: aload_0
       5: dup
       6: getfield      #5                  // Field currentOffset:I
       9: dup_x1
      10: iconst_1
      11: iadd
      12: putfield      #5                  // Field currentOffset:I
      15: lload_1
      16: bipush        56
      18: lshr
      19: l2i
      20: i2b
      21: bastore
      22: aload_0
      23: getfield      #7                  // Field buffer:[B
      26: aload_0
      27: dup
      28: getfield      #5                  // Field currentOffset:I
      31: dup_x1
      32: iconst_1
      33: iadd
      34: putfield      #5                  // Field currentOffset:I
      37: lload_1
      38: bipush        48
      40: lshr
      41: l2i
      42: i2b
      43: bastore
      44: aload_0
      45: getfield      #7                  // Field buffer:[B
      48: aload_0
      49: dup
      50: getfield      #5                  // Field currentOffset:I
      53: dup_x1
      54: iconst_1
      55: iadd
      56: putfield      #5                  // Field currentOffset:I
      59: lload_1
      60: bipush        40
      62: lshr
      63: l2i
      64: i2b
      65: bastore
      66: aload_0
      67: getfield      #7                  // Field buffer:[B
      70: aload_0
      71: dup
      72: getfield      #5                  // Field currentOffset:I
      75: dup_x1
      76: iconst_1
      77: iadd
      78: putfield      #5                  // Field currentOffset:I
      81: lload_1
      82: bipush        32
      84: lshr
      85: l2i
      86: i2b
      87: bastore
      88: aload_0
      89: getfield      #7                  // Field buffer:[B
      92: aload_0
      93: dup
      94: getfield      #5                  // Field currentOffset:I
      97: dup_x1
      98: iconst_1
      99: iadd
     100: putfield      #5                  // Field currentOffset:I
     103: lload_1
     104: bipush        24
     106: lshr
     107: l2i
     108: i2b
     109: bastore
     110: aload_0
     111: getfield      #7                  // Field buffer:[B
     114: aload_0
     115: dup
     116: getfield      #5                  // Field currentOffset:I
     119: dup_x1
     120: iconst_1
     121: iadd
     122: putfield      #5                  // Field currentOffset:I
     125: lload_1
     126: bipush        16
     128: lshr
     129: l2i
     130: i2b
     131: bastore
     132: aload_0
     133: getfield      #7                  // Field buffer:[B
     136: aload_0
     137: dup
     138: getfield      #5                  // Field currentOffset:I
     141: dup_x1
     142: iconst_1
     143: iadd
     144: putfield      #5                  // Field currentOffset:I
     147: lload_1
     148: bipush        8
     150: lshr
     151: l2i
     152: i2b
     153: bastore
     154: aload_0
     155: getfield      #7                  // Field buffer:[B
     158: aload_0
     159: dup
     160: getfield      #5                  // Field currentOffset:I
     163: dup_x1
     164: iconst_1
     165: iadd
     166: putfield      #5                  // Field currentOffset:I
     169: lload_1
     170: l2i
     171: i2b
     172: bastore
     173: goto          219
     176: astore_3
     177: new           #12                 // class java/lang/StringBuilder
     180: dup
     181: invokespecial #13                 // Method java/lang/StringBuilder."<init>":()V
     184: ldc           #14                 // String 14395, 5,
     186: invokevirtual #15                 // Method java/lang/StringBuilder.append:(Ljava/lang/String;)Ljava/lang/StringBuilder;
     189: lload_1
     190: invokevirtual #16                 // Method java/lang/StringBuilder.append:(J)Ljava/lang/StringBuilder;
     193: ldc           #17                 // String ,
     195: invokevirtual #15                 // Method java/lang/StringBuilder.append:(Ljava/lang/String;)Ljava/lang/StringBuilder;
     198: aload_3
     199: invokevirtual #18                 // Method java/lang/RuntimeException.toString:()Ljava/lang/String;
     202: invokevirtual #15                 // Method java/lang/StringBuilder.append:(Ljava/lang/String;)Ljava/lang/StringBuilder;
     205: invokevirtual #19                 // Method java/lang/StringBuilder.toString:()Ljava/lang/String;
     208: invokestatic  #20                 // Method sign/signlink.reporterror:(Ljava/lang/String;)V
     211: new           #11                 // class java/lang/RuntimeException
     214: dup
     215: invokespecial #21                 // Method java/lang/RuntimeException."<init>":()V
     218: athrow
     219: return
    Exception table:
       from    to  target type
           0   173   176   Class java/lang/RuntimeException

  public void writeString(java.lang.String);
    Code:
       0: aload_1
       1: invokevirtual #22                 // Method java/lang/String.getBytes:()[B
       4: iconst_0
       5: aload_0
       6: getfield      #7                  // Field buffer:[B
       9: aload_0
      10: getfield      #5                  // Field currentOffset:I
      13: aload_1
      14: invokevirtual #23                 // Method java/lang/String.length:()I
      17: invokestatic  #24                 // Method java/lang/System.arraycopy:(Ljava/lang/Object;ILjava/lang/Object;II)V
      20: aload_0
      21: dup
      22: getfield      #5                  // Field currentOffset:I
      25: aload_1
      26: invokevirtual #23                 // Method java/lang/String.length:()I
      29: iadd
      30: putfield      #5                  // Field currentOffset:I
      33: aload_0
      34: getfield      #7                  // Field buffer:[B
      37: aload_0
      38: dup
      39: getfield      #5                  // Field currentOffset:I
      42: dup_x1
      43: iconst_1
      44: iadd
      45: putfield      #5                  // Field currentOffset:I
      48: bipush        10
      50: bastore
      51: return

  public void writeBytes(byte[], int, int);
    Code:
       0: iload_3
       1: istore        4
       3: iload         4
       5: iload_3
       6: iload_2
       7: iadd
       8: if_icmpge     37
      11: aload_0
      12: getfield      #7                  // Field buffer:[B
      15: aload_0
      16: dup
      17: getfield      #5                  // Field currentOffset:I
      20: dup_x1
      21: iconst_1
      22: iadd
      23: putfield      #5                  // Field currentOffset:I
      26: aload_1
      27: iload         4
      29: baload
      30: bastore
      31: iinc          4, 1
      34: goto          3
      37: return

  public void writeBytes(int);
    Code:
       0: aload_0
       1: getfield      #7                  // Field buffer:[B
       4: aload_0
       5: getfield      #5                  // Field currentOffset:I
       8: iload_1
       9: isub
      10: iconst_1
      11: isub
      12: iload_1
      13: i2b
      14: bastore
      15: return

  public int readUnsignedByte();
    Code:
       0: aload_0
       1: getfield      #7                  // Field buffer:[B
       4: aload_0
       5: dup
       6: getfield      #5                  // Field currentOffset:I
       9: dup_x1
      10: iconst_1
      11: iadd
      12: putfield      #5                  // Field currentOffset:I
      15: baload
      16: sipush        255
      19: iand
      20: ireturn

  public byte readSignedByte();
    Code:
       0: aload_0
       1: getfield      #7                  // Field buffer:[B
       4: aload_0
       5: dup
       6: getfield      #5                  // Field currentOffset:I
       9: dup_x1
      10: iconst_1
      11: iadd
      12: putfield      #5                  // Field currentOffset:I
      15: baload
      16: ireturn

  public int readUnsignedWord();
    Code:
       0: aload_0
       1: dup
       2: getfield      #5                  // Field currentOffset:I
       5: iconst_2
       6: iadd
       7: putfield      #5                  // Field currentOffset:I
      10: aload_0
      11: getfield      #7                  // Field buffer:[B
      14: aload_0
      15: getfield      #5                  // Field currentOffset:I
      18: iconst_2
      19: isub
      20: baload
      21: sipush        255
      24: iand
      25: bipush        8
      27: ishl
      28: aload_0
      29: getfield      #7                  // Field buffer:[B
      32: aload_0
      33: getfield      #5                  // Field currentOffset:I
      36: iconst_1
      37: isub
      38: baload
      39: sipush        255
      42: iand
      43: iadd
      44: ireturn

  public int readSignedWord();
    Code:
       0: aload_0
       1: dup
       2: getfield      #5                  // Field currentOffset:I
       5: iconst_2
       6: iadd
       7: putfield      #5                  // Field currentOffset:I
      10: aload_0
      11: getfield      #7                  // Field buffer:[B
      14: aload_0
      15: getfield      #5                  // Field currentOffset:I
      18: iconst_2
      19: isub
      20: baload
      21: sipush        255
      24: iand
      25: bipush        8
      27: ishl
      28: aload_0
      29: getfield      #7                  // Field buffer:[B
      32: aload_0
      33: getfield      #5                  // Field currentOffset:I
      36: iconst_1
      37: isub
      38: baload
      39: sipush        255
      42: iand
      43: iadd
      44: istore_1
      45: iload_1
      46: sipush        32767
      49: if_icmple     57
      52: iload_1
      53: ldc           #25                 // int 65536
      55: isub
      56: istore_1
      57: iload_1
      58: ireturn

  public int read3Bytes();
    Code:
       0: aload_0
       1: dup
       2: getfield      #5                  // Field currentOffset:I
       5: iconst_3
       6: iadd
       7: putfield      #5                  // Field currentOffset:I
      10: aload_0
      11: getfield      #7                  // Field buffer:[B
      14: aload_0
      15: getfield      #5                  // Field currentOffset:I
      18: iconst_3
      19: isub
      20: baload
      21: sipush        255
      24: iand
      25: bipush        16
      27: ishl
      28: aload_0
      29: getfield      #7                  // Field buffer:[B
      32: aload_0
      33: getfield      #5                  // Field currentOffset:I
      36: iconst_2
      37: isub
      38: baload
      39: sipush        255
      42: iand
      43: bipush        8
      45: ishl
      46: iadd
      47: aload_0
      48: getfield      #7                  // Field buffer:[B
      51: aload_0
      52: getfield      #5                  // Field currentOffset:I
      55: iconst_1
      56: isub
      57: baload
      58: sipush        255
      61: iand
      62: iadd
      63: ireturn

  public int readDWord();
    Code:
       0: aload_0
       1: dup
       2: getfield      #5                  // Field currentOffset:I
       5: iconst_4
       6: iadd
       7: putfield      #5                  // Field currentOffset:I
      10: aload_0
      11: getfield      #7                  // Field buffer:[B
      14: aload_0
      15: getfield      #5                  // Field currentOffset:I
      18: iconst_4
      19: isub
      20: baload
      21: sipush        255
      24: iand
      25: bipush        24
      27: ishl
      28: aload_0
      29: getfield      #7                  // Field buffer:[B
      32: aload_0
      33: getfield      #5                  // Field currentOffset:I
      36: iconst_3
      37: isub
      38: baload
      39: sipush        255
      42: iand
      43: bipush        16
      45: ishl
      46: iadd
      47: aload_0
      48: getfield      #7                  // Field buffer:[B
      51: aload_0
      52: getfield      #5                  // Field currentOffset:I
      55: iconst_2
      56: isub
      57: baload
      58: sipush        255
      61: iand
      62: bipush        8
      64: ishl
      65: iadd
      66: aload_0
      67: getfield      #7                  // Field buffer:[B
      70: aload_0
      71: getfield      #5                  // Field currentOffset:I
      74: iconst_1
      75: isub
      76: baload
      77: sipush        255
      80: iand
      81: iadd
      82: ireturn

  public long readQWord();
    Code:
       0: aload_0
       1: invokevirtual #26                 // Method readDWord:()I
       4: i2l
       5: ldc2_w        #27                 // long 4294967295l
       8: land
       9: lstore_1
      10: aload_0
      11: invokevirtual #26                 // Method readDWord:()I
      14: i2l
      15: ldc2_w        #27                 // long 4294967295l
      18: land
      19: lstore_3
      20: lload_1
      21: bipush        32
      23: lshl
      24: lload_3
      25: ladd
      26: lreturn

  public java.lang.String readString();
    Code:
       0: aload_0
       1: getfield      #5                  // Field currentOffset:I
       4: istore_1
       5: aload_0
       6: getfield      #7                  // Field buffer:[B
       9: aload_0
      10: dup
      11: getfield      #5                  // Field currentOffset:I
      14: dup_x1
      15: iconst_1
      16: iadd
      17: putfield      #5                  // Field currentOffset:I
      20: baload
      21: bipush        10
      23: if_icmpeq     29
      26: goto          5
      29: new           #29                 // class java/lang/String
      32: dup
      33: aload_0
      34: getfield      #7                  // Field buffer:[B
      37: iload_1
      38: aload_0
      39: getfield      #5                  // Field currentOffset:I
      42: iload_1
      43: isub
      44: iconst_1
      45: isub
      46: invokespecial #30                 // Method java/lang/String."<init>":([BII)V
      49: areturn

  public byte[] readBytes();
    Code:
       0: aload_0
       1: getfield      #5                  // Field currentOffset:I
       4: istore_1
       5: aload_0
       6: getfield      #7                  // Field buffer:[B
       9: aload_0
      10: dup
      11: getfield      #5                  // Field currentOffset:I
      14: dup_x1
      15: iconst_1
      16: iadd
      17: putfield      #5                  // Field currentOffset:I
      20: baload
      21: bipush        10
      23: if_icmpeq     29
      26: goto          5
      29: aload_0
      30: getfield      #5                  // Field currentOffset:I
      33: iload_1
      34: isub
      35: iconst_1
      36: isub
      37: newarray       byte
      39: astore_2
      40: aload_0
      41: getfield      #7                  // Field buffer:[B
      44: iload_1
      45: aload_2
      46: iload_1
      47: iload_1
      48: isub
      49: aload_0
      50: getfield      #5                  // Field currentOffset:I
      53: iconst_1
      54: isub
      55: iload_1
      56: isub
      57: invokestatic  #24                 // Method java/lang/System.arraycopy:(Ljava/lang/Object;ILjava/lang/Object;II)V
      60: aload_2
      61: areturn

  public void readBytes(int, int, byte[]);
    Code:
       0: iload_2
       1: istore        4
       3: iload         4
       5: iload_2
       6: iload_1
       7: iadd
       8: if_icmpge     37
      11: aload_3
      12: iload         4
      14: aload_0
      15: getfield      #7                  // Field buffer:[B
      18: aload_0
      19: dup
      20: getfield      #5                  // Field currentOffset:I
      23: dup_x1
      24: iconst_1
      25: iadd
      26: putfield      #5                  // Field currentOffset:I
      29: baload
      30: bastore
      31: iinc          4, 1
      34: goto          3
      37: return

  public void initBitAccess();
    Code:
       0: aload_0
       1: aload_0
       2: getfield      #5                  // Field currentOffset:I
       5: bipush        8
       7: imul
       8: putfield      #31                 // Field bitPosition:I
      11: return

  public int readBits(int);
    Code:
       0: aload_0
       1: getfield      #31                 // Field bitPosition:I
       4: iconst_3
       5: ishr
       6: istore_2
       7: bipush        8
       9: aload_0
      10: getfield      #31                 // Field bitPosition:I
      13: bipush        7
      15: iand
      16: isub
      17: istore_3
      18: iconst_0
      19: istore        4
      21: aload_0
      22: dup
      23: getfield      #31                 // Field bitPosition:I
      26: iload_1
      27: iadd
      28: putfield      #31                 // Field bitPosition:I
      31: iload_1
      32: iload_3
      33: if_icmple     70
      36: iload         4
      38: aload_0
      39: getfield      #7                  // Field buffer:[B
      42: iload_2
      43: iinc          2, 1
      46: baload
      47: getstatic     #32                 // Field anIntArray1409:[I
      50: iload_3
      51: iaload
      52: iand
      53: iload_1
      54: iload_3
      55: isub
      56: ishl
      57: iadd
      58: istore        4
      60: iload_1
      61: iload_3
      62: isub
      63: istore_1
      64: bipush        8
      66: istore_3
      67: goto          31
      70: iload_1
      71: iload_3
      72: if_icmpne     95
      75: iload         4
      77: aload_0
      78: getfield      #7                  // Field buffer:[B
      81: iload_2
      82: baload
      83: getstatic     #32                 // Field anIntArray1409:[I
      86: iload_3
      87: iaload
      88: iand
      89: iadd
      90: istore        4
      92: goto          116
      95: iload         4
      97: aload_0
      98: getfield      #7                  // Field buffer:[B
     101: iload_2
     102: baload
     103: iload_3
     104: iload_1
     105: isub
     106: ishr
     107: getstatic     #32                 // Field anIntArray1409:[I
     110: iload_1
     111: iaload
     112: iand
     113: iadd
     114: istore        4
     116: iload         4
     118: ireturn

  public void finishBitAccess();
    Code:
       0: aload_0
       1: aload_0
       2: getfield      #31                 // Field bitPosition:I
       5: bipush        7
       7: iadd
       8: bipush        8
      10: idiv
      11: putfield      #5                  // Field currentOffset:I
      14: return

  public int method421();
    Code:
       0: aload_0
       1: getfield      #7                  // Field buffer:[B
       4: aload_0
       5: getfield      #5                  // Field currentOffset:I
       8: baload
       9: sipush        255
      12: iand
      13: istore_1
      14: iload_1
      15: sipush        128
      18: if_icmpge     29
      21: aload_0
      22: invokevirtual #33                 // Method readUnsignedByte:()I
      25: bipush        64
      27: isub
      28: ireturn
      29: aload_0
      30: invokevirtual #34                 // Method readUnsignedWord:()I
      33: ldc           #35                 // int 49152
      35: isub
      36: ireturn

  public int method422();
    Code:
       0: aload_0
       1: getfield      #7                  // Field buffer:[B
       4: aload_0
       5: getfield      #5                  // Field currentOffset:I
       8: baload
       9: sipush        255
      12: iand
      13: istore_1
      14: iload_1
      15: sipush        128
      18: if_icmpge     26
      21: aload_0
      22: invokevirtual #33                 // Method readUnsignedByte:()I
      25: ireturn
      26: aload_0
      27: invokevirtual #34                 // Method readUnsignedWord:()I
      30: ldc           #36                 // int 32768
      32: isub
      33: ireturn

  public void doKeys();
    Code:
       0: aload_0
       1: getfield      #5                  // Field currentOffset:I
       4: istore_1
       5: aload_0
       6: iconst_0
       7: putfield      #5                  // Field currentOffset:I
      10: iload_1
      11: newarray       byte
      13: astore_2
      14: aload_0
      15: iload_1
      16: iconst_0
      17: aload_2
      18: invokevirtual #37                 // Method readBytes:(II[B)V
      21: new           #38                 // class java/math/BigInteger
      24: dup
      25: aload_2
      26: invokespecial #39                 // Method java/math/BigInteger."<init>":([B)V
      29: astore_3
      30: aload_3
      31: astore        4
      33: aload         4
      35: invokevirtual #40                 // Method java/math/BigInteger.toByteArray:()[B
      38: astore        5
      40: aload_0
      41: iconst_0
      42: putfield      #5                  // Field currentOffset:I
      45: aload_0
      46: aload         5
      48: arraylength
      49: invokevirtual #41                 // Method writeWordBigEndian:(I)V
      52: aload_0
      53: aload         5
      55: aload         5
      57: arraylength
      58: iconst_0
      59: invokevirtual #42                 // Method writeBytes:([BII)V
      62: return

  public void method424(int);
    Code:
       0: aload_0
       1: getfield      #7                  // Field buffer:[B
       4: aload_0
       5: dup
       6: getfield      #5                  // Field currentOffset:I
       9: dup_x1
      10: iconst_1
      11: iadd
      12: putfield      #5                  // Field currentOffset:I
      15: iload_1
      16: ineg
      17: i2b
      18: bastore
      19: return

  public void method425(int);
    Code:
       0: aload_0
       1: getfield      #7                  // Field buffer:[B
       4: aload_0
       5: dup
       6: getfield      #5                  // Field currentOffset:I
       9: dup_x1
      10: iconst_1
      11: iadd
      12: putfield      #5                  // Field currentOffset:I
      15: sipush        128
      18: iload_1
      19: isub
      20: i2b
      21: bastore
      22: return

  public int method426();
    Code:
       0: aload_0
       1: getfield      #7                  // Field buffer:[B
       4: aload_0
       5: dup
       6: getfield      #5                  // Field currentOffset:I
       9: dup_x1
      10: iconst_1
      11: iadd
      12: putfield      #5                  // Field currentOffset:I
      15: baload
      16: sipush        128
      19: isub
      20: sipush        255
      23: iand
      24: ireturn

  public int method427();
    Code:
       0: aload_0
       1: getfield      #7                  // Field buffer:[B
       4: aload_0
       5: dup
       6: getfield      #5                  // Field currentOffset:I
       9: dup_x1
      10: iconst_1
      11: iadd
      12: putfield      #5                  // Field currentOffset:I
      15: baload
      16: ineg
      17: sipush        255
      20: iand
      21: ireturn

  public int method428();
    Code:
       0: sipush        128
       3: aload_0
       4: getfield      #7                  // Field buffer:[B
       7: aload_0
       8: dup
       9: getfield      #5                  // Field currentOffset:I
      12: dup_x1
      13: iconst_1
      14: iadd
      15: putfield      #5                  // Field currentOffset:I
      18: baload
      19: isub
      20: sipush        255
      23: iand
      24: ireturn

  public byte method429();
    Code:
       0: aload_0
       1: getfield      #7                  // Field buffer:[B
       4: aload_0
       5: dup
       6: getfield      #5                  // Field currentOffset:I
       9: dup_x1
      10: iconst_1
      11: iadd
      12: putfield      #5                  // Field currentOffset:I
      15: baload
      16: ineg
      17: i2b
      18: ireturn

  public byte method430();
    Code:
       0: sipush        128
       3: aload_0
       4: getfield      #7                  // Field buffer:[B
       7: aload_0
       8: dup
       9: getfield      #5                  // Field currentOffset:I
      12: dup_x1
      13: iconst_1
      14: iadd
      15: putfield      #5                  // Field currentOffset:I
      18: baload
      19: isub
      20: i2b
      21: ireturn

  public void method431(int);
    Code:
       0: aload_0
       1: getfield      #7                  // Field buffer:[B
       4: aload_0
       5: dup
       6: getfield      #5                  // Field currentOffset:I
       9: dup_x1
      10: iconst_1
      11: iadd
      12: putfield      #5                  // Field currentOffset:I
      15: iload_1
      16: i2b
      17: bastore
      18: aload_0
      19: getfield      #7                  // Field buffer:[B
      22: aload_0
      23: dup
      24: getfield      #5                  // Field currentOffset:I
      27: dup_x1
      28: iconst_1
      29: iadd
      30: putfield      #5                  // Field currentOffset:I
      33: iload_1
      34: bipush        8
      36: ishr
      37: i2b
      38: bastore
      39: return

  public void method432(int);
    Code:
       0: aload_0
       1: getfield      #7                  // Field buffer:[B
       4: aload_0
       5: dup
       6: getfield      #5                  // Field currentOffset:I
       9: dup_x1
      10: iconst_1
      11: iadd
      12: putfield      #5                  // Field currentOffset:I
      15: iload_1
      16: bipush        8
      18: ishr
      19: i2b
      20: bastore
      21: aload_0
      22: getfield      #7                  // Field buffer:[B
      25: aload_0
      26: dup
      27: getfield      #5                  // Field currentOffset:I
      30: dup_x1
      31: iconst_1
      32: iadd
      33: putfield      #5                  // Field currentOffset:I
      36: iload_1
      37: sipush        128
      40: iadd
      41: i2b
      42: bastore
      43: return

  public void method433(int);
    Code:
       0: aload_0
       1: getfield      #7                  // Field buffer:[B
       4: aload_0
       5: dup
       6: getfield      #5                  // Field currentOffset:I
       9: dup_x1
      10: iconst_1
      11: iadd
      12: putfield      #5                  // Field currentOffset:I
      15: iload_1
      16: sipush        128
      19: iadd
      20: i2b
      21: bastore
      22: aload_0
      23: getfield      #7                  // Field buffer:[B
      26: aload_0
      27: dup
      28: getfield      #5                  // Field currentOffset:I
      31: dup_x1
      32: iconst_1
      33: iadd
      34: putfield      #5                  // Field currentOffset:I
      37: iload_1
      38: bipush        8
      40: ishr
      41: i2b
      42: bastore
      43: return

  public int method434();
    Code:
       0: aload_0
       1: dup
       2: getfield      #5                  // Field currentOffset:I
       5: iconst_2
       6: iadd
       7: putfield      #5                  // Field currentOffset:I
      10: aload_0
      11: getfield      #7                  // Field buffer:[B
      14: aload_0
      15: getfield      #5                  // Field currentOffset:I
      18: iconst_1
      19: isub
      20: baload
      21: sipush        255
      24: iand
      25: bipush        8
      27: ishl
      28: aload_0
      29: getfield      #7                  // Field buffer:[B
      32: aload_0
      33: getfield      #5                  // Field currentOffset:I
      36: iconst_2
      37: isub
      38: baload
      39: sipush        255
      42: iand
      43: iadd
      44: ireturn

  public int method435();
    Code:
       0: aload_0
       1: dup
       2: getfield      #5                  // Field currentOffset:I
       5: iconst_2
       6: iadd
       7: putfield      #5                  // Field currentOffset:I
      10: aload_0
      11: getfield      #7                  // Field buffer:[B
      14: aload_0
      15: getfield      #5                  // Field currentOffset:I
      18: iconst_2
      19: isub
      20: baload
      21: sipush        255
      24: iand
      25: bipush        8
      27: ishl
      28: aload_0
      29: getfield      #7                  // Field buffer:[B
      32: aload_0
      33: getfield      #5                  // Field currentOffset:I
      36: iconst_1
      37: isub
      38: baload
      39: sipush        128
      42: isub
      43: sipush        255
      46: iand
      47: iadd
      48: ireturn

  public int method436();
    Code:
       0: aload_0
       1: dup
       2: getfield      #5                  // Field currentOffset:I
       5: iconst_2
       6: iadd
       7: putfield      #5                  // Field currentOffset:I
      10: aload_0
      11: getfield      #7                  // Field buffer:[B
      14: aload_0
      15: getfield      #5                  // Field currentOffset:I
      18: iconst_1
      19: isub
      20: baload
      21: sipush        255
      24: iand
      25: bipush        8
      27: ishl
      28: aload_0
      29: getfield      #7                  // Field buffer:[B
      32: aload_0
      33: getfield      #5                  // Field currentOffset:I
      36: iconst_2
      37: isub
      38: baload
      39: sipush        128
      42: isub
      43: sipush        255
      46: iand
      47: iadd
      48: ireturn

  public int method437();
    Code:
       0: aload_0
       1: dup
       2: getfield      #5                  // Field currentOffset:I
       5: iconst_2
       6: iadd
       7: putfield      #5                  // Field currentOffset:I
      10: aload_0
      11: getfield      #7                  // Field buffer:[B
      14: aload_0
      15: getfield      #5                  // Field currentOffset:I
      18: iconst_1
      19: isub
      20: baload
      21: sipush        255
      24: iand
      25: bipush        8
      27: ishl
      28: aload_0
      29: getfield      #7                  // Field buffer:[B
      32: aload_0
      33: getfield      #5                  // Field currentOffset:I
      36: iconst_2
      37: isub
      38: baload
      39: sipush        255
      42: iand
      43: iadd
      44: istore_1
      45: iload_1
      46: sipush        32767
      49: if_icmple     57
      52: iload_1
      53: ldc           #25                 // int 65536
      55: isub
      56: istore_1
      57: iload_1
      58: ireturn

  public int method438();
    Code:
       0: aload_0
       1: dup
       2: getfield      #5                  // Field currentOffset:I
       5: iconst_2
       6: iadd
       7: putfield      #5                  // Field currentOffset:I
      10: aload_0
      11: getfield      #7                  // Field buffer:[B
      14: aload_0
      15: getfield      #5                  // Field currentOffset:I
      18: iconst_1
      19: isub
      20: baload
      21: sipush        255
      24: iand
      25: bipush        8
      27: ishl
      28: aload_0
      29: getfield      #7                  // Field buffer:[B
      32: aload_0
      33: getfield      #5                  // Field currentOffset:I
      36: iconst_2
      37: isub
      38: baload
      39: sipush        128
      42: isub
      43: sipush        255
      46: iand
      47: iadd
      48: istore_1
      49: iload_1
      50: sipush        32767
      53: if_icmple     61
      56: iload_1
      57: ldc           #25                 // int 65536
      59: isub
      60: istore_1
      61: iload_1
      62: ireturn

  public int method439();
    Code:
       0: aload_0
       1: dup
       2: getfield      #5                  // Field currentOffset:I
       5: iconst_4
       6: iadd
       7: putfield      #5                  // Field currentOffset:I
      10: aload_0
      11: getfield      #7                  // Field buffer:[B
      14: aload_0
      15: getfield      #5                  // Field currentOffset:I
      18: iconst_2
      19: isub
      20: baload
      21: sipush        255
      24: iand
      25: bipush        24
      27: ishl
      28: aload_0
      29: getfield      #7                  // Field buffer:[B
      32: aload_0
      33: getfield      #5                  // Field currentOffset:I
      36: iconst_1
      37: isub
      38: baload
      39: sipush        255
      42: iand
      43: bipush        16
      45: ishl
      46: iadd
      47: aload_0
      48: getfield      #7                  // Field buffer:[B
      51: aload_0
      52: getfield      #5                  // Field currentOffset:I
      55: iconst_4
      56: isub
      57: baload
      58: sipush        255
      61: iand
      62: bipush        8
      64: ishl
      65: iadd
      66: aload_0
      67: getfield      #7                  // Field buffer:[B
      70: aload_0
      71: getfield      #5                  // Field currentOffset:I
      74: iconst_3
      75: isub
      76: baload
      77: sipush        255
      80: iand
      81: iadd
      82: ireturn

  public int method440();
    Code:
       0: aload_0
       1: dup
       2: getfield      #5                  // Field currentOffset:I
       5: iconst_4
       6: iadd
       7: putfield      #5                  // Field currentOffset:I
      10: aload_0
      11: getfield      #7                  // Field buffer:[B
      14: aload_0
      15: getfield      #5                  // Field currentOffset:I
      18: iconst_3
      19: isub
      20: baload
      21: sipush        255
      24: iand
      25: bipush        24
      27: ishl
      28: aload_0
      29: getfield      #7                  // Field buffer:[B
      32: aload_0
      33: getfield      #5                  // Field currentOffset:I
      36: iconst_4
      37: isub
      38: baload
      39: sipush        255
      42: iand
      43: bipush        16
      45: ishl
      46: iadd
      47: aload_0
      48: getfield      #7                  // Field buffer:[B
      51: aload_0
      52: getfield      #5                  // Field currentOffset:I
      55: iconst_1
      56: isub
      57: baload
      58: sipush        255
      61: iand
      62: bipush        8
      64: ishl
      65: iadd
      66: aload_0
      67: getfield      #7                  // Field buffer:[B
      70: aload_0
      71: getfield      #5                  // Field currentOffset:I
      74: iconst_2
      75: isub
      76: baload
      77: sipush        255
      80: iand
      81: iadd
      82: ireturn

  public void method441(int, byte[], int);
    Code:
       0: iload_1
       1: iload_3
       2: iadd
       3: iconst_1
       4: isub
       5: istore        4
       7: iload         4
       9: iload_1
      10: if_icmplt     44
      13: aload_0
      14: getfield      #7                  // Field buffer:[B
      17: aload_0
      18: dup
      19: getfield      #5                  // Field currentOffset:I
      22: dup_x1
      23: iconst_1
      24: iadd
      25: putfield      #5                  // Field currentOffset:I
      28: aload_2
      29: iload         4
      31: baload
      32: sipush        128
      35: iadd
      36: i2b
      37: bastore
      38: iinc          4, -1
      41: goto          7
      44: return

  public void method442(int, int, byte[]);
    Code:
       0: iload_2
       1: iload_1
       2: iadd
       3: iconst_1
       4: isub
       5: istore        4
       7: iload         4
       9: iload_2
      10: if_icmplt     39
      13: aload_3
      14: iload         4
      16: aload_0
      17: getfield      #7                  // Field buffer:[B
      20: aload_0
      21: dup
      22: getfield      #5                  // Field currentOffset:I
      25: dup_x1
      26: iconst_1
      27: iadd
      28: putfield      #5                  // Field currentOffset:I
      31: baload
      32: bastore
      33: iinc          4, -1
      36: goto          7
      39: return

  static {};
    Code:
       0: bipush        33
       2: newarray       int
       4: dup
       5: iconst_0
       6: iconst_0
       7: iastore
       8: dup
       9: iconst_1
      10: iconst_1
      11: iastore
      12: dup
      13: iconst_2
      14: iconst_3
      15: iastore
      16: dup
      17: iconst_3
      18: bipush        7
      20: iastore
      21: dup
      22: iconst_4
      23: bipush        15
      25: iastore
      26: dup
      27: iconst_5
      28: bipush        31
      30: iastore
      31: dup
      32: bipush        6
      34: bipush        63
      36: iastore
      37: dup
      38: bipush        7
      40: bipush        127
      42: iastore
      43: dup
      44: bipush        8
      46: sipush        255
      49: iastore
      50: dup
      51: bipush        9
      53: sipush        511
      56: iastore
      57: dup
      58: bipush        10
      60: sipush        1023
      63: iastore
      64: dup
      65: bipush        11
      67: sipush        2047
      70: iastore
      71: dup
      72: bipush        12
      74: sipush        4095
      77: iastore
      78: dup
      79: bipush        13
      81: sipush        8191
      84: iastore
      85: dup
      86: bipush        14
      88: sipush        16383
      91: iastore
      92: dup
      93: bipush        15
      95: sipush        32767
      98: iastore
      99: dup
     100: bipush        16
     102: ldc           #43                 // int 65535
     104: iastore
     105: dup
     106: bipush        17
     108: ldc           #44                 // int 131071
     110: iastore
     111: dup
     112: bipush        18
     114: ldc           #45                 // int 262143
     116: iastore
     117: dup
     118: bipush        19
     120: ldc           #46                 // int 524287
     122: iastore
     123: dup
     124: bipush        20
     126: ldc           #47                 // int 1048575
     128: iastore
     129: dup
     130: bipush        21
     132: ldc           #48                 // int 2097151
     134: iastore
     135: dup
     136: bipush        22
     138: ldc           #49                 // int 4194303
     140: iastore
     141: dup
     142: bipush        23
     144: ldc           #50                 // int 8388607
     146: iastore
     147: dup
     148: bipush        24
     150: ldc           #51                 // int 16777215
     152: iastore
     153: dup
     154: bipush        25
     156: ldc           #52                 // int 33554431
     158: iastore
     159: dup
     160: bipush        26
     162: ldc           #53                 // int 67108863
     164: iastore
     165: dup
     166: bipush        27
     168: ldc           #54                 // int 134217727
     170: iastore
     171: dup
     172: bipush        28
     174: ldc           #55                 // int 268435455
     176: iastore
     177: dup
     178: bipush        29
     180: ldc           #56                 // int 536870911
     182: iastore
     183: dup
     184: bipush        30
     186: ldc           #57                 // int 1073741823
     188: iastore
     189: dup
     190: bipush        31
     192: ldc           #58                 // int 2147483647
     194: iastore
     195: dup
     196: bipush        32
     198: iconst_m1
     199: iastore
     200: putstatic     #32                 // Field anIntArray1409:[I
     203: new           #59                 // class NodeList
     206: dup
     207: invokespecial #60                 // Method NodeList."<init>":()V
     210: putstatic     #1                  // Field nodeList:LNodeList;
     213: return
}
