Compiled from "TextInput.java"
final class TextInput {
  private static final boolean aBoolean630;

  private static final char[] aCharArray631;

  private static final Stream stream;

  private static final char[] validChars;

  TextInput();
    Code:
       0: aload_0
       1: invokespecial #1                  // Method java/lang/Object."<init>":()V
       4: return

  public static java.lang.String method525(int, Stream);
    Code:
       0: iconst_0
       1: istore_2
       2: iconst_m1
       3: istore_3
       4: iconst_0
       5: istore        4
       7: iload         4
       9: iload_0
      10: if_icmpge     159
      13: aload_1
      14: invokevirtual #2                  // Method Stream.readUnsignedByte:()I
      17: istore        5
      19: iload         5
      21: iconst_4
      22: ishr
      23: bipush        15
      25: iand
      26: istore        6
      28: iload_3
      29: iconst_m1
      30: if_icmpne     63
      33: iload         6
      35: bipush        13
      37: if_icmpge     57
      40: getstatic     #3                  // Field aCharArray631:[C
      43: iload_2
      44: iinc          2, 1
      47: getstatic     #4                  // Field validChars:[C
      50: iload         6
      52: caload
      53: castore
      54: goto          87
      57: iload         6
      59: istore_3
      60: goto          87
      63: getstatic     #3                  // Field aCharArray631:[C
      66: iload_2
      67: iinc          2, 1
      70: getstatic     #4                  // Field validChars:[C
      73: iload_3
      74: iconst_4
      75: ishl
      76: iload         6
      78: iadd
      79: sipush        195
      82: isub
      83: caload
      84: castore
      85: iconst_m1
      86: istore_3
      87: iload         5
      89: bipush        15
      91: iand
      92: istore        6
      94: iload_3
      95: iconst_m1
      96: if_icmpne     129
      99: iload         6
     101: bipush        13
     103: if_icmpge     123
     106: getstatic     #3                  // Field aCharArray631:[C
     109: iload_2
     110: iinc          2, 1
     113: getstatic     #4                  // Field validChars:[C
     116: iload         6
     118: caload
     119: castore
     120: goto          153
     123: iload         6
     125: istore_3
     126: goto          153
     129: getstatic     #3                  // Field aCharArray631:[C
     132: iload_2
     133: iinc          2, 1
     136: getstatic     #4                  // Field validChars:[C
     139: iload_3
     140: iconst_4
     141: ishl
     142: iload         6
     144: iadd
     145: sipush        195
     148: isub
     149: caload
     150: castore
     151: iconst_m1
     152: istore_3
     153: iinc          4, 1
     156: goto          7
     159: iconst_1
     160: istore        4
     162: iconst_0
     163: istore        5
     165: iload         5
     167: iload_2
     168: if_icmpge     243
     171: getstatic     #3                  // Field aCharArray631:[C
     174: iload         5
     176: caload
     177: istore        6
     179: iload         4
     181: ifeq          213
     184: iload         6
     186: bipush        97
     188: if_icmplt     213
     191: iload         6
     193: bipush        122
     195: if_icmpgt     213
     198: getstatic     #3                  // Field aCharArray631:[C
     201: iload         5
     203: dup2
     204: caload
     205: ldc           #5                  // int 65504
     207: iadd
     208: i2c
     209: castore
     210: iconst_0
     211: istore        4
     213: iload         6
     215: bipush        46
     217: if_icmpeq     234
     220: iload         6
     222: bipush        33
     224: if_icmpeq     234
     227: iload         6
     229: bipush        63
     231: if_icmpne     237
     234: iconst_1
     235: istore        4
     237: iinc          5, 1
     240: goto          165
     243: new           #6                  // class java/lang/String
     246: dup
     247: getstatic     #3                  // Field aCharArray631:[C
     250: iconst_0
     251: iload_2
     252: invokespecial #7                  // Method java/lang/String."<init>":([CII)V
     255: areturn

  public static void method526(java.lang.String, Stream);
    Code:
       0: aload_0
       1: invokevirtual #8                  // Method java/lang/String.length:()I
       4: bipush        80
       6: if_icmple     17
       9: aload_0
      10: iconst_0
      11: bipush        80
      13: invokevirtual #9                  // Method java/lang/String.substring:(II)Ljava/lang/String;
      16: astore_0
      17: aload_0
      18: invokevirtual #10                 // Method java/lang/String.toLowerCase:()Ljava/lang/String;
      21: astore_0
      22: iconst_m1
      23: istore_2
      24: iconst_0
      25: istore_3
      26: iload_3
      27: aload_0
      28: invokevirtual #8                  // Method java/lang/String.length:()I
      31: if_icmpge     169
      34: aload_0
      35: iload_3
      36: invokevirtual #11                 // Method java/lang/String.charAt:(I)C
      39: istore        4
      41: iconst_0
      42: istore        5
      44: iconst_0
      45: istore        6
      47: iload         6
      49: getstatic     #4                  // Field validChars:[C
      52: arraylength
      53: if_icmpge     83
      56: iload         4
      58: getstatic     #4                  // Field validChars:[C
      61: iload         6
      63: caload
      64: if_icmpeq     70
      67: goto          77
      70: iload         6
      72: istore        5
      74: goto          83
      77: iinc          6, 1
      80: goto          47
      83: iload         5
      85: bipush        12
      87: if_icmple     96
      90: iinc_w        5, 195
      96: iload_2
      97: iconst_m1
      98: if_icmpne     123
     101: iload         5
     103: bipush        13
     105: if_icmpge     114
     108: iload         5
     110: istore_2
     111: goto          163
     114: aload_1
     115: iload         5
     117: invokevirtual #12                 // Method Stream.writeWordBigEndian:(I)V
     120: goto          163
     123: iload         5
     125: bipush        13
     127: if_icmpge     145
     130: aload_1
     131: iload_2
     132: iconst_4
     133: ishl
     134: iload         5
     136: iadd
     137: invokevirtual #12                 // Method Stream.writeWordBigEndian:(I)V
     140: iconst_m1
     141: istore_2
     142: goto          163
     145: aload_1
     146: iload_2
     147: iconst_4
     148: ishl
     149: iload         5
     151: iconst_4
     152: ishr
     153: iadd
     154: invokevirtual #12                 // Method Stream.writeWordBigEndian:(I)V
     157: iload         5
     159: bipush        15
     161: iand
     162: istore_2
     163: iinc          3, 1
     166: goto          26
     169: iload_2
     170: iconst_m1
     171: if_icmpeq     181
     174: aload_1
     175: iload_2
     176: iconst_4
     177: ishl
     178: invokevirtual #12                 // Method Stream.writeWordBigEndian:(I)V
     181: return

  public static java.lang.String processText(java.lang.String);
    Code:
       0: getstatic     #13                 // Field stream:LStream;
       3: iconst_0
       4: putfield      #14                 // Field Stream.currentOffset:I
       7: aload_0
       8: getstatic     #13                 // Field stream:LStream;
      11: invokestatic  #15                 // Method method526:(Ljava/lang/String;LStream;)V
      14: getstatic     #13                 // Field stream:LStream;
      17: getfield      #14                 // Field Stream.currentOffset:I
      20: istore_1
      21: getstatic     #13                 // Field stream:LStream;
      24: iconst_0
      25: putfield      #14                 // Field Stream.currentOffset:I
      28: iload_1
      29: getstatic     #13                 // Field stream:LStream;
      32: invokestatic  #16                 // Method method525:(ILStream;)Ljava/lang/String;
      35: astore_2
      36: aload_2
      37: areturn

  static {};
    Code:
       0: bipush        100
       2: newarray       char
       4: putstatic     #3                  // Field aCharArray631:[C
       7: new           #17                 // class Stream
      10: dup
      11: bipush        100
      13: newarray       byte
      15: invokespecial #18                 // Method Stream."<init>":([B)V
      18: putstatic     #13                 // Field stream:LStream;
      21: bipush        61
      23: newarray       char
      25: dup
      26: iconst_0
      27: bipush        32
      29: castore
      30: dup
      31: iconst_1
      32: bipush        101
      34: castore
      35: dup
      36: iconst_2
      37: bipush        116
      39: castore
      40: dup
      41: iconst_3
      42: bipush        97
      44: castore
      45: dup
      46: iconst_4
      47: bipush        111
      49: castore
      50: dup
      51: iconst_5
      52: bipush        105
      54: castore
      55: dup
      56: bipush        6
      58: bipush        104
      60: castore
      61: dup
      62: bipush        7
      64: bipush        110
      66: castore
      67: dup
      68: bipush        8
      70: bipush        115
      72: castore
      73: dup
      74: bipush        9
      76: bipush        114
      78: castore
      79: dup
      80: bipush        10
      82: bipush        100
      84: castore
      85: dup
      86: bipush        11
      88: bipush        108
      90: castore
      91: dup
      92: bipush        12
      94: bipush        117
      96: castore
      97: dup
      98: bipush        13
     100: bipush        109
     102: castore
     103: dup
     104: bipush        14
     106: bipush        119
     108: castore
     109: dup
     110: bipush        15
     112: bipush        99
     114: castore
     115: dup
     116: bipush        16
     118: bipush        121
     120: castore
     121: dup
     122: bipush        17
     124: bipush        102
     126: castore
     127: dup
     128: bipush        18
     130: bipush        103
     132: castore
     133: dup
     134: bipush        19
     136: bipush        112
     138: castore
     139: dup
     140: bipush        20
     142: bipush        98
     144: castore
     145: dup
     146: bipush        21
     148: bipush        118
     150: castore
     151: dup
     152: bipush        22
     154: bipush        107
     156: castore
     157: dup
     158: bipush        23
     160: bipush        120
     162: castore
     163: dup
     164: bipush        24
     166: bipush        106
     168: castore
     169: dup
     170: bipush        25
     172: bipush        113
     174: castore
     175: dup
     176: bipush        26
     178: bipush        122
     180: castore
     181: dup
     182: bipush        27
     184: bipush        48
     186: castore
     187: dup
     188: bipush        28
     190: bipush        49
     192: castore
     193: dup
     194: bipush        29
     196: bipush        50
     198: castore
     199: dup
     200: bipush        30
     202: bipush        51
     204: castore
     205: dup
     206: bipush        31
     208: bipush        52
     210: castore
     211: dup
     212: bipush        32
     214: bipush        53
     216: castore
     217: dup
     218: bipush        33
     220: bipush        54
     222: castore
     223: dup
     224: bipush        34
     226: bipush        55
     228: castore
     229: dup
     230: bipush        35
     232: bipush        56
     234: castore
     235: dup
     236: bipush        36
     238: bipush        57
     240: castore
     241: dup
     242: bipush        37
     244: bipush        32
     246: castore
     247: dup
     248: bipush        38
     250: bipush        33
     252: castore
     253: dup
     254: bipush        39
     256: bipush        63
     258: castore
     259: dup
     260: bipush        40
     262: bipush        46
     264: castore
     265: dup
     266: bipush        41
     268: bipush        44
     270: castore
     271: dup
     272: bipush        42
     274: bipush        58
     276: castore
     277: dup
     278: bipush        43
     280: bipush        59
     282: castore
     283: dup
     284: bipush        44
     286: bipush        40
     288: castore
     289: dup
     290: bipush        45
     292: bipush        41
     294: castore
     295: dup
     296: bipush        46
     298: bipush        45
     300: castore
     301: dup
     302: bipush        47
     304: bipush        38
     306: castore
     307: dup
     308: bipush        48
     310: bipush        42
     312: castore
     313: dup
     314: bipush        49
     316: bipush        92
     318: castore
     319: dup
     320: bipush        50
     322: bipush        39
     324: castore
     325: dup
     326: bipush        51
     328: bipush        64
     330: castore
     331: dup
     332: bipush        52
     334: bipush        35
     336: castore
     337: dup
     338: bipush        53
     340: bipush        43
     342: castore
     343: dup
     344: bipush        54
     346: bipush        61
     348: castore
     349: dup
     350: bipush        55
     352: sipush        163
     355: castore
     356: dup
     357: bipush        56
     359: bipush        36
     361: castore
     362: dup
     363: bipush        57
     365: bipush        37
     367: castore
     368: dup
     369: bipush        58
     371: bipush        34
     373: castore
     374: dup
     375: bipush        59
     377: bipush        91
     379: castore
     380: dup
     381: bipush        60
     383: bipush        93
     385: castore
     386: putstatic     #4                  // Field validChars:[C
     389: return
}
