Compiled from "Texture.java"
final class Texture extends DrawingArea {
  public static final int anInt1459;

  public static boolean lowMem;

  static boolean aBoolean1462;

  private static boolean aBoolean1463;

  public static boolean aBoolean1464;

  public static int anInt1465;

  public static int textureInt1;

  public static int textureInt2;

  private static int[] anIntArray1468;

  public static final int[] anIntArray1469;

  public static int[] anIntArray1470;

  public static int[] anIntArray1471;

  public static int[] anIntArray1472;

  private static int anInt1473;

  public static Background[] aBackgroundArray1474s;

  private static boolean[] aBooleanArray1475;

  private static int[] anIntArray1476;

  private static int anInt1477;

  private static int[][] anIntArrayArray1478;

  private static int[][] anIntArrayArray1479;

  public static int[] anIntArray1480;

  public static int anInt1481;

  public static int[] anIntArray1482;

  private static int[][] anIntArrayArray1483;

  Texture();
    Code:
       0: aload_0
       1: invokespecial #1                  // Method DrawingArea."<init>":()V
       4: return

  public static void nullLoader();
    Code:
       0: aconst_null
       1: putstatic     #2                  // Field anIntArray1468:[I
       4: aconst_null
       5: putstatic     #2                  // Field anIntArray1468:[I
       8: aconst_null
       9: putstatic     #3                  // Field anIntArray1470:[I
      12: aconst_null
      13: putstatic     #4                  // Field anIntArray1471:[I
      16: aconst_null
      17: putstatic     #5                  // Field anIntArray1472:[I
      20: aconst_null
      21: putstatic     #6                  // Field aBackgroundArray1474s:[LBackground;
      24: aconst_null
      25: putstatic     #7                  // Field aBooleanArray1475:[Z
      28: aconst_null
      29: putstatic     #8                  // Field anIntArray1476:[I
      32: aconst_null
      33: checkcast     #9                  // class "[[I"
      36: putstatic     #10                 // Field anIntArrayArray1478:[[I
      39: aconst_null
      40: checkcast     #9                  // class "[[I"
      43: putstatic     #11                 // Field anIntArrayArray1479:[[I
      46: aconst_null
      47: putstatic     #12                 // Field anIntArray1480:[I
      50: aconst_null
      51: putstatic     #13                 // Field anIntArray1482:[I
      54: aconst_null
      55: checkcast     #9                  // class "[[I"
      58: putstatic     #14                 // Field anIntArrayArray1483:[[I
      61: return

  public static void method364();
    Code:
       0: getstatic     #15                 // Field DrawingArea.height:I
       3: newarray       int
       5: putstatic     #5                  // Field anIntArray1472:[I
       8: iconst_0
       9: istore_0
      10: iload_0
      11: getstatic     #15                 // Field DrawingArea.height:I
      14: if_icmpge     33
      17: getstatic     #5                  // Field anIntArray1472:[I
      20: iload_0
      21: getstatic     #16                 // Field DrawingArea.width:I
      24: iload_0
      25: imul
      26: iastore
      27: iinc          0, 1
      30: goto          10
      33: getstatic     #16                 // Field DrawingArea.width:I
      36: iconst_2
      37: idiv
      38: putstatic     #17                 // Field textureInt1:I
      41: getstatic     #15                 // Field DrawingArea.height:I
      44: iconst_2
      45: idiv
      46: putstatic     #18                 // Field textureInt2:I
      49: return

  public static void method365(int, int);
    Code:
       0: iload_1
       1: newarray       int
       3: putstatic     #5                  // Field anIntArray1472:[I
       6: iconst_0
       7: istore_2
       8: iload_2
       9: iload_1
      10: if_icmpge     27
      13: getstatic     #5                  // Field anIntArray1472:[I
      16: iload_2
      17: iload_0
      18: iload_2
      19: imul
      20: iastore
      21: iinc          2, 1
      24: goto          8
      27: iload_0
      28: iconst_2
      29: idiv
      30: putstatic     #17                 // Field textureInt1:I
      33: iload_1
      34: iconst_2
      35: idiv
      36: putstatic     #18                 // Field textureInt2:I
      39: return

  public static void method366();
    Code:
       0: aconst_null
       1: checkcast     #9                  // class "[[I"
       4: putstatic     #10                 // Field anIntArrayArray1478:[[I
       7: iconst_0
       8: istore_0
       9: iload_0
      10: bipush        50
      12: if_icmpge     27
      15: getstatic     #11                 // Field anIntArrayArray1479:[[I
      18: iload_0
      19: aconst_null
      20: aastore
      21: iinc          0, 1
      24: goto          9
      27: return

  public static void method367();
    Code:
       0: getstatic     #10                 // Field anIntArrayArray1478:[[I
       3: ifnonnull     65
       6: bipush        20
       8: putstatic     #19                 // Field anInt1477:I
      11: getstatic     #20                 // Field lowMem:Z
      14: ifeq          33
      17: getstatic     #19                 // Field anInt1477:I
      20: sipush        16384
      23: multianewarray #9,  2             // class "[[I"
      27: putstatic     #10                 // Field anIntArrayArray1478:[[I
      30: goto          45
      33: getstatic     #19                 // Field anInt1477:I
      36: ldc           #21                 // int 65536
      38: multianewarray #9,  2             // class "[[I"
      42: putstatic     #10                 // Field anIntArrayArray1478:[[I
      45: iconst_0
      46: istore_0
      47: iload_0
      48: bipush        50
      50: if_icmpge     65
      53: getstatic     #11                 // Field anIntArrayArray1479:[[I
      56: iload_0
      57: aconst_null
      58: aastore
      59: iinc          0, 1
      62: goto          47
      65: return

  public static void method368(StreamLoader);
    Code:
       0: iconst_0
       1: putstatic     #22                 // Field anInt1473:I
       4: iconst_0
       5: istore_1
       6: iload_1
       7: bipush        50
       9: if_icmpge     87
      12: getstatic     #6                  // Field aBackgroundArray1474s:[LBackground;
      15: iload_1
      16: new           #23                 // class Background
      19: dup
      20: aload_0
      21: iload_1
      22: invokestatic  #24                 // Method java/lang/String.valueOf:(I)Ljava/lang/String;
      25: iconst_0
      26: invokespecial #25                 // Method Background."<init>":(LStreamLoader;Ljava/lang/String;I)V
      29: aastore
      30: getstatic     #20                 // Field lowMem:Z
      33: ifeq          61
      36: getstatic     #6                  // Field aBackgroundArray1474s:[LBackground;
      39: iload_1
      40: aaload
      41: getfield      #26                 // Field Background.anInt1456:I
      44: sipush        128
      47: if_icmpne     61
      50: getstatic     #6                  // Field aBackgroundArray1474s:[LBackground;
      53: iload_1
      54: aaload
      55: invokevirtual #27                 // Method Background.method356:()V
      58: goto          69
      61: getstatic     #6                  // Field aBackgroundArray1474s:[LBackground;
      64: iload_1
      65: aaload
      66: invokevirtual #28                 // Method Background.method357:()V
      69: getstatic     #22                 // Field anInt1473:I
      72: iconst_1
      73: iadd
      74: putstatic     #22                 // Field anInt1473:I
      77: goto          81
      80: astore_2
      81: iinc          1, 1
      84: goto          6
      87: return
    Exception table:
       from    to  target type
          12    77    80   Class java/lang/Exception

  public static int method369(int);
    Code:
       0: getstatic     #8                  // Field anIntArray1476:[I
       3: iload_0
       4: iaload
       5: ifeq          14
       8: getstatic     #8                  // Field anIntArray1476:[I
      11: iload_0
      12: iaload
      13: ireturn
      14: iconst_0
      15: istore_1
      16: iconst_0
      17: istore_2
      18: iconst_0
      19: istore_3
      20: getstatic     #14                 // Field anIntArrayArray1483:[[I
      23: iload_0
      24: aaload
      25: arraylength
      26: istore        4
      28: iconst_0
      29: istore        5
      31: iload         5
      33: iload         4
      35: if_icmpge     95
      38: iload_1
      39: getstatic     #14                 // Field anIntArrayArray1483:[[I
      42: iload_0
      43: aaload
      44: iload         5
      46: iaload
      47: bipush        16
      49: ishr
      50: sipush        255
      53: iand
      54: iadd
      55: istore_1
      56: iload_2
      57: getstatic     #14                 // Field anIntArrayArray1483:[[I
      60: iload_0
      61: aaload
      62: iload         5
      64: iaload
      65: bipush        8
      67: ishr
      68: sipush        255
      71: iand
      72: iadd
      73: istore_2
      74: iload_3
      75: getstatic     #14                 // Field anIntArrayArray1483:[[I
      78: iload_0
      79: aaload
      80: iload         5
      82: iaload
      83: sipush        255
      86: iand
      87: iadd
      88: istore_3
      89: iinc          5, 1
      92: goto          31
      95: iload_1
      96: iload         4
      98: idiv
      99: bipush        16
     101: ishl
     102: iload_2
     103: iload         4
     105: idiv
     106: bipush        8
     108: ishl
     109: iadd
     110: iload_3
     111: iload         4
     113: idiv
     114: iadd
     115: istore        5
     117: iload         5
     119: ldc2_w        #30                 // double 1.4d
     122: invokestatic  #32                 // Method method373:(ID)I
     125: istore        5
     127: iload         5
     129: ifne          135
     132: iconst_1
     133: istore        5
     135: getstatic     #8                  // Field anIntArray1476:[I
     138: iload_0
     139: iload         5
     141: iastore
     142: iload         5
     144: ireturn

  public static void method370(int);
    Code:
       0: getstatic     #11                 // Field anIntArrayArray1479:[[I
       3: iload_0
       4: aaload
       5: ifnonnull     9
       8: return
       9: getstatic     #10                 // Field anIntArrayArray1478:[[I
      12: getstatic     #19                 // Field anInt1477:I
      15: dup
      16: iconst_1
      17: iadd
      18: putstatic     #19                 // Field anInt1477:I
      21: getstatic     #11                 // Field anIntArrayArray1479:[[I
      24: iload_0
      25: aaload
      26: aastore
      27: getstatic     #11                 // Field anIntArrayArray1479:[[I
      30: iload_0
      31: aconst_null
      32: aastore
      33: return

  private static int[] method371(int);
    Code:
       0: getstatic     #12                 // Field anIntArray1480:[I
       3: iload_0
       4: getstatic     #33                 // Field anInt1481:I
       7: dup
       8: iconst_1
       9: iadd
      10: putstatic     #33                 // Field anInt1481:I
      13: iastore
      14: getstatic     #11                 // Field anIntArrayArray1479:[[I
      17: iload_0
      18: aaload
      19: ifnull        28
      22: getstatic     #11                 // Field anIntArrayArray1479:[[I
      25: iload_0
      26: aaload
      27: areturn
      28: getstatic     #19                 // Field anInt1477:I
      31: ifle          59
      34: getstatic     #10                 // Field anIntArrayArray1478:[[I
      37: getstatic     #19                 // Field anInt1477:I
      40: iconst_1
      41: isub
      42: dup
      43: putstatic     #19                 // Field anInt1477:I
      46: aaload
      47: astore_1
      48: getstatic     #10                 // Field anIntArrayArray1478:[[I
      51: getstatic     #19                 // Field anInt1477:I
      54: aconst_null
      55: aastore
      56: goto          126
      59: iconst_0
      60: istore_2
      61: iconst_m1
      62: istore_3
      63: iconst_0
      64: istore        4
      66: iload         4
      68: getstatic     #22                 // Field anInt1473:I
      71: if_icmpge     114
      74: getstatic     #11                 // Field anIntArrayArray1479:[[I
      77: iload         4
      79: aaload
      80: ifnull        108
      83: getstatic     #12                 // Field anIntArray1480:[I
      86: iload         4
      88: iaload
      89: iload_2
      90: if_icmplt     98
      93: iload_3
      94: iconst_m1
      95: if_icmpne     108
      98: getstatic     #12                 // Field anIntArray1480:[I
     101: iload         4
     103: iaload
     104: istore_2
     105: iload         4
     107: istore_3
     108: iinc          4, 1
     111: goto          66
     114: getstatic     #11                 // Field anIntArrayArray1479:[[I
     117: iload_3
     118: aaload
     119: astore_1
     120: getstatic     #11                 // Field anIntArrayArray1479:[[I
     123: iload_3
     124: aconst_null
     125: aastore
     126: getstatic     #11                 // Field anIntArrayArray1479:[[I
     129: iload_0
     130: aload_1
     131: aastore
     132: getstatic     #6                  // Field aBackgroundArray1474s:[LBackground;
     135: iload_0
     136: aaload
     137: astore_2
     138: getstatic     #14                 // Field anIntArrayArray1483:[[I
     141: iload_0
     142: aaload
     143: astore_3
     144: getstatic     #20                 // Field lowMem:Z
     147: ifeq          265
     150: getstatic     #7                  // Field aBooleanArray1475:[Z
     153: iload_0
     154: iconst_0
     155: bastore
     156: iconst_0
     157: istore        4
     159: iload         4
     161: sipush        4096
     164: if_icmpge     262
     167: aload_1
     168: iload         4
     170: aload_3
     171: aload_2
     172: getfield      #34                 // Field Background.aByteArray1450:[B
     175: iload         4
     177: baload
     178: iaload
     179: ldc           #35                 // int 16316671
     181: iand
     182: dup_x2
     183: iastore
     184: istore        5
     186: iload         5
     188: ifne          197
     191: getstatic     #7                  // Field aBooleanArray1475:[Z
     194: iload_0
     195: iconst_1
     196: bastore
     197: aload_1
     198: sipush        4096
     201: iload         4
     203: iadd
     204: iload         5
     206: iload         5
     208: iconst_3
     209: iushr
     210: isub
     211: ldc           #35                 // int 16316671
     213: iand
     214: iastore
     215: aload_1
     216: sipush        8192
     219: iload         4
     221: iadd
     222: iload         5
     224: iload         5
     226: iconst_2
     227: iushr
     228: isub
     229: ldc           #35                 // int 16316671
     231: iand
     232: iastore
     233: aload_1
     234: sipush        12288
     237: iload         4
     239: iadd
     240: iload         5
     242: iload         5
     244: iconst_2
     245: iushr
     246: isub
     247: iload         5
     249: iconst_3
     250: iushr
     251: isub
     252: ldc           #35                 // int 16316671
     254: iand
     255: iastore
     256: iinc          4, 1
     259: goto          159
     262: goto          476
     265: aload_2
     266: getfield      #36                 // Field Background.anInt1452:I
     269: bipush        64
     271: if_icmpne     340
     274: iconst_0
     275: istore        4
     277: iload         4
     279: sipush        128
     282: if_icmpge     337
     285: iconst_0
     286: istore        5
     288: iload         5
     290: sipush        128
     293: if_icmpge     331
     296: aload_1
     297: iload         5
     299: iload         4
     301: bipush        7
     303: ishl
     304: iadd
     305: aload_3
     306: aload_2
     307: getfield      #34                 // Field Background.aByteArray1450:[B
     310: iload         5
     312: iconst_1
     313: ishr
     314: iload         4
     316: iconst_1
     317: ishr
     318: bipush        6
     320: ishl
     321: iadd
     322: baload
     323: iaload
     324: iastore
     325: iinc          5, 1
     328: goto          288
     331: iinc          4, 1
     334: goto          277
     337: goto          370
     340: iconst_0
     341: istore        4
     343: iload         4
     345: sipush        16384
     348: if_icmpge     370
     351: aload_1
     352: iload         4
     354: aload_3
     355: aload_2
     356: getfield      #34                 // Field Background.aByteArray1450:[B
     359: iload         4
     361: baload
     362: iaload
     363: iastore
     364: iinc          4, 1
     367: goto          343
     370: getstatic     #7                  // Field aBooleanArray1475:[Z
     373: iload_0
     374: iconst_0
     375: bastore
     376: iconst_0
     377: istore        4
     379: iload         4
     381: sipush        16384
     384: if_icmpge     476
     387: aload_1
     388: iload         4
     390: dup2
     391: iaload
     392: ldc           #35                 // int 16316671
     394: iand
     395: iastore
     396: aload_1
     397: iload         4
     399: iaload
     400: istore        5
     402: iload         5
     404: ifne          413
     407: getstatic     #7                  // Field aBooleanArray1475:[Z
     410: iload_0
     411: iconst_1
     412: bastore
     413: aload_1
     414: sipush        16384
     417: iload         4
     419: iadd
     420: iload         5
     422: iload         5
     424: iconst_3
     425: iushr
     426: isub
     427: ldc           #35                 // int 16316671
     429: iand
     430: iastore
     431: aload_1
     432: ldc           #37                 // int 32768
     434: iload         4
     436: iadd
     437: iload         5
     439: iload         5
     441: iconst_2
     442: iushr
     443: isub
     444: ldc           #35                 // int 16316671
     446: iand
     447: iastore
     448: aload_1
     449: ldc           #38                 // int 49152
     451: iload         4
     453: iadd
     454: iload         5
     456: iload         5
     458: iconst_2
     459: iushr
     460: isub
     461: iload         5
     463: iconst_3
     464: iushr
     465: isub
     466: ldc           #35                 // int 16316671
     468: iand
     469: iastore
     470: iinc          4, 1
     473: goto          379
     476: aload_1
     477: areturn

  public static void method372(double);
    Code:
       0: dload_0
       1: invokestatic  #39                 // Method java/lang/Math.random:()D
       4: ldc2_w        #40                 // double 0.03d
       7: dmul
       8: ldc2_w        #42                 // double 0.015d
      11: dsub
      12: dadd
      13: dstore_0
      14: iconst_0
      15: istore_2
      16: iconst_0
      17: istore_3
      18: iload_3
      19: sipush        512
      22: if_icmpge     536
      25: iload_3
      26: bipush        8
      28: idiv
      29: i2d
      30: ldc2_w        #44                 // double 64.0d
      33: ddiv
      34: ldc2_w        #46                 // double 0.0078125d
      37: dadd
      38: dstore        4
      40: iload_3
      41: bipush        7
      43: iand
      44: i2d
      45: ldc2_w        #48                 // double 8.0d
      48: ddiv
      49: ldc2_w        #50                 // double 0.0625d
      52: dadd
      53: dstore        6
      55: iconst_0
      56: istore        8
      58: iload         8
      60: sipush        128
      63: if_icmpge     530
      66: iload         8
      68: i2d
      69: ldc2_w        #52                 // double 128.0d
      72: ddiv
      73: dstore        9
      75: dload         9
      77: dstore        11
      79: dload         9
      81: dstore        13
      83: dload         9
      85: dstore        15
      87: dload         6
      89: dconst_0
      90: dcmpl
      91: ifeq          455
      94: dload         9
      96: ldc2_w        #54                 // double 0.5d
      99: dcmpg
     100: ifge          115
     103: dload         9
     105: dconst_1
     106: dload         6
     108: dadd
     109: dmul
     110: dstore        17
     112: goto          128
     115: dload         9
     117: dload         6
     119: dadd
     120: dload         9
     122: dload         6
     124: dmul
     125: dsub
     126: dstore        17
     128: ldc2_w        #56                 // double 2.0d
     131: dload         9
     133: dmul
     134: dload         17
     136: dsub
     137: dstore        19
     139: dload         4
     141: ldc2_w        #58                 // double 0.3333333333333333d
     144: dadd
     145: dstore        21
     147: dload         21
     149: dconst_1
     150: dcmpl
     151: ifle          160
     154: dload         21
     156: dconst_1
     157: dsub
     158: dstore        21
     160: dload         4
     162: dstore        23
     164: dload         4
     166: ldc2_w        #58                 // double 0.3333333333333333d
     169: dsub
     170: dstore        25
     172: dload         25
     174: dconst_0
     175: dcmpg
     176: ifge          185
     179: dload         25
     181: dconst_1
     182: dadd
     183: dstore        25
     185: ldc2_w        #60                 // double 6.0d
     188: dload         21
     190: dmul
     191: dconst_1
     192: dcmpg
     193: ifge          216
     196: dload         19
     198: dload         17
     200: dload         19
     202: dsub
     203: ldc2_w        #60                 // double 6.0d
     206: dmul
     207: dload         21
     209: dmul
     210: dadd
     211: dstore        11
     213: goto          275
     216: ldc2_w        #56                 // double 2.0d
     219: dload         21
     221: dmul
     222: dconst_1
     223: dcmpg
     224: ifge          234
     227: dload         17
     229: dstore        11
     231: goto          275
     234: ldc2_w        #62                 // double 3.0d
     237: dload         21
     239: dmul
     240: ldc2_w        #56                 // double 2.0d
     243: dcmpg
     244: ifge          271
     247: dload         19
     249: dload         17
     251: dload         19
     253: dsub
     254: ldc2_w        #64                 // double 0.6666666666666666d
     257: dload         21
     259: dsub
     260: dmul
     261: ldc2_w        #60                 // double 6.0d
     264: dmul
     265: dadd
     266: dstore        11
     268: goto          275
     271: dload         19
     273: dstore        11
     275: ldc2_w        #60                 // double 6.0d
     278: dload         23
     280: dmul
     281: dconst_1
     282: dcmpg
     283: ifge          306
     286: dload         19
     288: dload         17
     290: dload         19
     292: dsub
     293: ldc2_w        #60                 // double 6.0d
     296: dmul
     297: dload         23
     299: dmul
     300: dadd
     301: dstore        13
     303: goto          365
     306: ldc2_w        #56                 // double 2.0d
     309: dload         23
     311: dmul
     312: dconst_1
     313: dcmpg
     314: ifge          324
     317: dload         17
     319: dstore        13
     321: goto          365
     324: ldc2_w        #62                 // double 3.0d
     327: dload         23
     329: dmul
     330: ldc2_w        #56                 // double 2.0d
     333: dcmpg
     334: ifge          361
     337: dload         19
     339: dload         17
     341: dload         19
     343: dsub
     344: ldc2_w        #64                 // double 0.6666666666666666d
     347: dload         23
     349: dsub
     350: dmul
     351: ldc2_w        #60                 // double 6.0d
     354: dmul
     355: dadd
     356: dstore        13
     358: goto          365
     361: dload         19
     363: dstore        13
     365: ldc2_w        #60                 // double 6.0d
     368: dload         25
     370: dmul
     371: dconst_1
     372: dcmpg
     373: ifge          396
     376: dload         19
     378: dload         17
     380: dload         19
     382: dsub
     383: ldc2_w        #60                 // double 6.0d
     386: dmul
     387: dload         25
     389: dmul
     390: dadd
     391: dstore        15
     393: goto          455
     396: ldc2_w        #56                 // double 2.0d
     399: dload         25
     401: dmul
     402: dconst_1
     403: dcmpg
     404: ifge          414
     407: dload         17
     409: dstore        15
     411: goto          455
     414: ldc2_w        #62                 // double 3.0d
     417: dload         25
     419: dmul
     420: ldc2_w        #56                 // double 2.0d
     423: dcmpg
     424: ifge          451
     427: dload         19
     429: dload         17
     431: dload         19
     433: dsub
     434: ldc2_w        #64                 // double 0.6666666666666666d
     437: dload         25
     439: dsub
     440: dmul
     441: ldc2_w        #60                 // double 6.0d
     444: dmul
     445: dadd
     446: dstore        15
     448: goto          455
     451: dload         19
     453: dstore        15
     455: dload         11
     457: ldc2_w        #66                 // double 256.0d
     460: dmul
     461: d2i
     462: istore        17
     464: dload         13
     466: ldc2_w        #66                 // double 256.0d
     469: dmul
     470: d2i
     471: istore        18
     473: dload         15
     475: ldc2_w        #66                 // double 256.0d
     478: dmul
     479: d2i
     480: istore        19
     482: iload         17
     484: bipush        16
     486: ishl
     487: iload         18
     489: bipush        8
     491: ishl
     492: iadd
     493: iload         19
     495: iadd
     496: istore        20
     498: iload         20
     500: dload_0
     501: invokestatic  #32                 // Method method373:(ID)I
     504: istore        20
     506: iload         20
     508: ifne          514
     511: iconst_1
     512: istore        20
     514: getstatic     #13                 // Field anIntArray1482:[I
     517: iload_2
     518: iinc          2, 1
     521: iload         20
     523: iastore
     524: iinc          8, 1
     527: goto          58
     530: iinc          3, 1
     533: goto          18
     536: iconst_0
     537: istore_3
     538: iload_3
     539: bipush        50
     541: if_icmpge     640
     544: getstatic     #6                  // Field aBackgroundArray1474s:[LBackground;
     547: iload_3
     548: aaload
     549: ifnull        634
     552: getstatic     #6                  // Field aBackgroundArray1474s:[LBackground;
     555: iload_3
     556: aaload
     557: getfield      #68                 // Field Background.anIntArray1451:[I
     560: astore        4
     562: getstatic     #14                 // Field anIntArrayArray1483:[[I
     565: iload_3
     566: aload         4
     568: arraylength
     569: newarray       int
     571: aastore
     572: iconst_0
     573: istore        5
     575: iload         5
     577: aload         4
     579: arraylength
     580: if_icmpge     634
     583: getstatic     #14                 // Field anIntArrayArray1483:[[I
     586: iload_3
     587: aaload
     588: iload         5
     590: aload         4
     592: iload         5
     594: iaload
     595: dload_0
     596: invokestatic  #32                 // Method method373:(ID)I
     599: iastore
     600: getstatic     #14                 // Field anIntArrayArray1483:[[I
     603: iload_3
     604: aaload
     605: iload         5
     607: iaload
     608: ldc           #35                 // int 16316671
     610: iand
     611: ifne          628
     614: iload         5
     616: ifeq          628
     619: getstatic     #14                 // Field anIntArrayArray1483:[[I
     622: iload_3
     623: aaload
     624: iload         5
     626: iconst_1
     627: iastore
     628: iinc          5, 1
     631: goto          575
     634: iinc          3, 1
     637: goto          538
     640: iconst_0
     641: istore_3
     642: iload_3
     643: bipush        50
     645: if_icmpge     658
     648: iload_3
     649: invokestatic  #69                 // Method method370:(I)V
     652: iinc          3, 1
     655: goto          642
     658: return

  private static int method373(int, double);
    Code:
       0: iload_0
       1: bipush        16
       3: ishr
       4: i2d
       5: ldc2_w        #66                 // double 256.0d
       8: ddiv
       9: dstore_3
      10: iload_0
      11: bipush        8
      13: ishr
      14: sipush        255
      17: iand
      18: i2d
      19: ldc2_w        #66                 // double 256.0d
      22: ddiv
      23: dstore        5
      25: iload_0
      26: sipush        255
      29: iand
      30: i2d
      31: ldc2_w        #66                 // double 256.0d
      34: ddiv
      35: dstore        7
      37: dload_3
      38: dload_1
      39: invokestatic  #70                 // Method java/lang/Math.pow:(DD)D
      42: dstore_3
      43: dload         5
      45: dload_1
      46: invokestatic  #70                 // Method java/lang/Math.pow:(DD)D
      49: dstore        5
      51: dload         7
      53: dload_1
      54: invokestatic  #70                 // Method java/lang/Math.pow:(DD)D
      57: dstore        7
      59: dload_3
      60: ldc2_w        #66                 // double 256.0d
      63: dmul
      64: d2i
      65: istore        9
      67: dload         5
      69: ldc2_w        #66                 // double 256.0d
      72: dmul
      73: d2i
      74: istore        10
      76: dload         7
      78: ldc2_w        #66                 // double 256.0d
      81: dmul
      82: d2i
      83: istore        11
      85: iload         9
      87: bipush        16
      89: ishl
      90: iload         10
      92: bipush        8
      94: ishl
      95: iadd
      96: iload         11
      98: iadd
      99: ireturn

  public static void method374(int, int, int, int, int, int, int, int, int);
    Code:
       0: iconst_0
       1: istore        9
       3: iconst_0
       4: istore        10
       6: iload_1
       7: iload_0
       8: if_icmpeq     38
      11: iload         4
      13: iload_3
      14: isub
      15: bipush        16
      17: ishl
      18: iload_1
      19: iload_0
      20: isub
      21: idiv
      22: istore        9
      24: iload         7
      26: iload         6
      28: isub
      29: bipush        15
      31: ishl
      32: iload_1
      33: iload_0
      34: isub
      35: idiv
      36: istore        10
      38: iconst_0
      39: istore        11
      41: iconst_0
      42: istore        12
      44: iload_2
      45: iload_1
      46: if_icmpeq     77
      49: iload         5
      51: iload         4
      53: isub
      54: bipush        16
      56: ishl
      57: iload_2
      58: iload_1
      59: isub
      60: idiv
      61: istore        11
      63: iload         8
      65: iload         7
      67: isub
      68: bipush        15
      70: ishl
      71: iload_2
      72: iload_1
      73: isub
      74: idiv
      75: istore        12
      77: iconst_0
      78: istore        13
      80: iconst_0
      81: istore        14
      83: iload_2
      84: iload_0
      85: if_icmpeq     115
      88: iload_3
      89: iload         5
      91: isub
      92: bipush        16
      94: ishl
      95: iload_0
      96: iload_2
      97: isub
      98: idiv
      99: istore        13
     101: iload         6
     103: iload         8
     105: isub
     106: bipush        15
     108: ishl
     109: iload_0
     110: iload_2
     111: isub
     112: idiv
     113: istore        14
     115: iload_0
     116: iload_1
     117: if_icmpgt     1010
     120: iload_0
     121: iload_2
     122: if_icmpgt     1010
     125: iload_0
     126: getstatic     #71                 // Field DrawingArea.bottomY:I
     129: if_icmplt     133
     132: return
     133: iload_1
     134: getstatic     #71                 // Field DrawingArea.bottomY:I
     137: if_icmple     144
     140: getstatic     #71                 // Field DrawingArea.bottomY:I
     143: istore_1
     144: iload_2
     145: getstatic     #71                 // Field DrawingArea.bottomY:I
     148: if_icmple     155
     151: getstatic     #71                 // Field DrawingArea.bottomY:I
     154: istore_2
     155: iload_1
     156: iload_2
     157: if_icmpge     588
     160: iload_3
     161: bipush        16
     163: ishl
     164: dup
     165: istore_3
     166: istore        5
     168: iload         6
     170: bipush        15
     172: ishl
     173: dup
     174: istore        6
     176: istore        8
     178: iload_0
     179: ifge          218
     182: iload         5
     184: iload         13
     186: iload_0
     187: imul
     188: isub
     189: istore        5
     191: iload_3
     192: iload         9
     194: iload_0
     195: imul
     196: isub
     197: istore_3
     198: iload         8
     200: iload         14
     202: iload_0
     203: imul
     204: isub
     205: istore        8
     207: iload         6
     209: iload         10
     211: iload_0
     212: imul
     213: isub
     214: istore        6
     216: iconst_0
     217: istore_0
     218: iload         4
     220: bipush        16
     222: ishl
     223: istore        4
     225: iload         7
     227: bipush        15
     229: ishl
     230: istore        7
     232: iload_1
     233: ifge          256
     236: iload         4
     238: iload         11
     240: iload_1
     241: imul
     242: isub
     243: istore        4
     245: iload         7
     247: iload         12
     249: iload_1
     250: imul
     251: isub
     252: istore        7
     254: iconst_0
     255: istore_1
     256: iload_0
     257: iload_1
     258: if_icmpeq     268
     261: iload         13
     263: iload         9
     265: if_icmplt     280
     268: iload_0
     269: iload_1
     270: if_icmpne     434
     273: iload         13
     275: iload         11
     277: if_icmple     434
     280: iload_2
     281: iload_1
     282: isub
     283: istore_2
     284: iload_1
     285: iload_0
     286: isub
     287: istore_1
     288: getstatic     #5                  // Field anIntArray1472:[I
     291: iload_0
     292: iaload
     293: istore_0
     294: iinc          1, -1
     297: iload_1
     298: iflt          362
     301: getstatic     #72                 // Field DrawingArea.pixels:[I
     304: iload_0
     305: iload         5
     307: bipush        16
     309: ishr
     310: iload_3
     311: bipush        16
     313: ishr
     314: iload         8
     316: bipush        7
     318: ishr
     319: iload         6
     321: bipush        7
     323: ishr
     324: invokestatic  #73                 // Method method375:([IIIIII)V
     327: iload         5
     329: iload         13
     331: iadd
     332: istore        5
     334: iload_3
     335: iload         9
     337: iadd
     338: istore_3
     339: iload         8
     341: iload         14
     343: iadd
     344: istore        8
     346: iload         6
     348: iload         10
     350: iadd
     351: istore        6
     353: iload_0
     354: getstatic     #16                 // Field DrawingArea.width:I
     357: iadd
     358: istore_0
     359: goto          294
     362: iinc          2, -1
     365: iload_2
     366: iflt          433
     369: getstatic     #72                 // Field DrawingArea.pixels:[I
     372: iload_0
     373: iload         5
     375: bipush        16
     377: ishr
     378: iload         4
     380: bipush        16
     382: ishr
     383: iload         8
     385: bipush        7
     387: ishr
     388: iload         7
     390: bipush        7
     392: ishr
     393: invokestatic  #73                 // Method method375:([IIIIII)V
     396: iload         5
     398: iload         13
     400: iadd
     401: istore        5
     403: iload         4
     405: iload         11
     407: iadd
     408: istore        4
     410: iload         8
     412: iload         14
     414: iadd
     415: istore        8
     417: iload         7
     419: iload         12
     421: iadd
     422: istore        7
     424: iload_0
     425: getstatic     #16                 // Field DrawingArea.width:I
     428: iadd
     429: istore_0
     430: goto          362
     433: return
     434: iload_2
     435: iload_1
     436: isub
     437: istore_2
     438: iload_1
     439: iload_0
     440: isub
     441: istore_1
     442: getstatic     #5                  // Field anIntArray1472:[I
     445: iload_0
     446: iaload
     447: istore_0
     448: iinc          1, -1
     451: iload_1
     452: iflt          516
     455: getstatic     #72                 // Field DrawingArea.pixels:[I
     458: iload_0
     459: iload_3
     460: bipush        16
     462: ishr
     463: iload         5
     465: bipush        16
     467: ishr
     468: iload         6
     470: bipush        7
     472: ishr
     473: iload         8
     475: bipush        7
     477: ishr
     478: invokestatic  #73                 // Method method375:([IIIIII)V
     481: iload         5
     483: iload         13
     485: iadd
     486: istore        5
     488: iload_3
     489: iload         9
     491: iadd
     492: istore_3
     493: iload         8
     495: iload         14
     497: iadd
     498: istore        8
     500: iload         6
     502: iload         10
     504: iadd
     505: istore        6
     507: iload_0
     508: getstatic     #16                 // Field DrawingArea.width:I
     511: iadd
     512: istore_0
     513: goto          448
     516: iinc          2, -1
     519: iload_2
     520: iflt          587
     523: getstatic     #72                 // Field DrawingArea.pixels:[I
     526: iload_0
     527: iload         4
     529: bipush        16
     531: ishr
     532: iload         5
     534: bipush        16
     536: ishr
     537: iload         7
     539: bipush        7
     541: ishr
     542: iload         8
     544: bipush        7
     546: ishr
     547: invokestatic  #73                 // Method method375:([IIIIII)V
     550: iload         5
     552: iload         13
     554: iadd
     555: istore        5
     557: iload         4
     559: iload         11
     561: iadd
     562: istore        4
     564: iload         8
     566: iload         14
     568: iadd
     569: istore        8
     571: iload         7
     573: iload         12
     575: iadd
     576: istore        7
     578: iload_0
     579: getstatic     #16                 // Field DrawingArea.width:I
     582: iadd
     583: istore_0
     584: goto          516
     587: return
     588: iload_3
     589: bipush        16
     591: ishl
     592: dup
     593: istore_3
     594: istore        4
     596: iload         6
     598: bipush        15
     600: ishl
     601: dup
     602: istore        6
     604: istore        7
     606: iload_0
     607: ifge          646
     610: iload         4
     612: iload         13
     614: iload_0
     615: imul
     616: isub
     617: istore        4
     619: iload_3
     620: iload         9
     622: iload_0
     623: imul
     624: isub
     625: istore_3
     626: iload         7
     628: iload         14
     630: iload_0
     631: imul
     632: isub
     633: istore        7
     635: iload         6
     637: iload         10
     639: iload_0
     640: imul
     641: isub
     642: istore        6
     644: iconst_0
     645: istore_0
     646: iload         5
     648: bipush        16
     650: ishl
     651: istore        5
     653: iload         8
     655: bipush        15
     657: ishl
     658: istore        8
     660: iload_2
     661: ifge          684
     664: iload         5
     666: iload         11
     668: iload_2
     669: imul
     670: isub
     671: istore        5
     673: iload         8
     675: iload         12
     677: iload_2
     678: imul
     679: isub
     680: istore        8
     682: iconst_0
     683: istore_2
     684: iload_0
     685: iload_2
     686: if_icmpeq     696
     689: iload         13
     691: iload         9
     693: if_icmplt     708
     696: iload_0
     697: iload_2
     698: if_icmpne     859
     701: iload         11
     703: iload         9
     705: if_icmple     859
     708: iload_1
     709: iload_2
     710: isub
     711: istore_1
     712: iload_2
     713: iload_0
     714: isub
     715: istore_2
     716: getstatic     #5                  // Field anIntArray1472:[I
     719: iload_0
     720: iaload
     721: istore_0
     722: iinc          2, -1
     725: iload_2
     726: iflt          790
     729: getstatic     #72                 // Field DrawingArea.pixels:[I
     732: iload_0
     733: iload         4
     735: bipush        16
     737: ishr
     738: iload_3
     739: bipush        16
     741: ishr
     742: iload         7
     744: bipush        7
     746: ishr
     747: iload         6
     749: bipush        7
     751: ishr
     752: invokestatic  #73                 // Method method375:([IIIIII)V
     755: iload         4
     757: iload         13
     759: iadd
     760: istore        4
     762: iload_3
     763: iload         9
     765: iadd
     766: istore_3
     767: iload         7
     769: iload         14
     771: iadd
     772: istore        7
     774: iload         6
     776: iload         10
     778: iadd
     779: istore        6
     781: iload_0
     782: getstatic     #16                 // Field DrawingArea.width:I
     785: iadd
     786: istore_0
     787: goto          722
     790: iinc          1, -1
     793: iload_1
     794: iflt          858
     797: getstatic     #72                 // Field DrawingArea.pixels:[I
     800: iload_0
     801: iload         5
     803: bipush        16
     805: ishr
     806: iload_3
     807: bipush        16
     809: ishr
     810: iload         8
     812: bipush        7
     814: ishr
     815: iload         6
     817: bipush        7
     819: ishr
     820: invokestatic  #73                 // Method method375:([IIIIII)V
     823: iload         5
     825: iload         11
     827: iadd
     828: istore        5
     830: iload_3
     831: iload         9
     833: iadd
     834: istore_3
     835: iload         8
     837: iload         12
     839: iadd
     840: istore        8
     842: iload         6
     844: iload         10
     846: iadd
     847: istore        6
     849: iload_0
     850: getstatic     #16                 // Field DrawingArea.width:I
     853: iadd
     854: istore_0
     855: goto          790
     858: return
     859: iload_1
     860: iload_2
     861: isub
     862: istore_1
     863: iload_2
     864: iload_0
     865: isub
     866: istore_2
     867: getstatic     #5                  // Field anIntArray1472:[I
     870: iload_0
     871: iaload
     872: istore_0
     873: iinc          2, -1
     876: iload_2
     877: iflt          941
     880: getstatic     #72                 // Field DrawingArea.pixels:[I
     883: iload_0
     884: iload_3
     885: bipush        16
     887: ishr
     888: iload         4
     890: bipush        16
     892: ishr
     893: iload         6
     895: bipush        7
     897: ishr
     898: iload         7
     900: bipush        7
     902: ishr
     903: invokestatic  #73                 // Method method375:([IIIIII)V
     906: iload         4
     908: iload         13
     910: iadd
     911: istore        4
     913: iload_3
     914: iload         9
     916: iadd
     917: istore_3
     918: iload         7
     920: iload         14
     922: iadd
     923: istore        7
     925: iload         6
     927: iload         10
     929: iadd
     930: istore        6
     932: iload_0
     933: getstatic     #16                 // Field DrawingArea.width:I
     936: iadd
     937: istore_0
     938: goto          873
     941: iinc          1, -1
     944: iload_1
     945: iflt          1009
     948: getstatic     #72                 // Field DrawingArea.pixels:[I
     951: iload_0
     952: iload_3
     953: bipush        16
     955: ishr
     956: iload         5
     958: bipush        16
     960: ishr
     961: iload         6
     963: bipush        7
     965: ishr
     966: iload         8
     968: bipush        7
     970: ishr
     971: invokestatic  #73                 // Method method375:([IIIIII)V
     974: iload         5
     976: iload         11
     978: iadd
     979: istore        5
     981: iload_3
     982: iload         9
     984: iadd
     985: istore_3
     986: iload         8
     988: iload         12
     990: iadd
     991: istore        8
     993: iload         6
     995: iload         10
     997: iadd
     998: istore        6
    1000: iload_0
    1001: getstatic     #16                 // Field DrawingArea.width:I
    1004: iadd
    1005: istore_0
    1006: goto          941
    1009: return
    1010: iload_1
    1011: iload_2
    1012: if_icmpgt     1884
    1015: iload_1
    1016: getstatic     #71                 // Field DrawingArea.bottomY:I
    1019: if_icmplt     1023
    1022: return
    1023: iload_2
    1024: getstatic     #71                 // Field DrawingArea.bottomY:I
    1027: if_icmple     1034
    1030: getstatic     #71                 // Field DrawingArea.bottomY:I
    1033: istore_2
    1034: iload_0
    1035: getstatic     #71                 // Field DrawingArea.bottomY:I
    1038: if_icmple     1045
    1041: getstatic     #71                 // Field DrawingArea.bottomY:I
    1044: istore_0
    1045: iload_2
    1046: iload_0
    1047: if_icmpge     1473
    1050: iload         4
    1052: bipush        16
    1054: ishl
    1055: dup
    1056: istore        4
    1058: istore_3
    1059: iload         7
    1061: bipush        15
    1063: ishl
    1064: dup
    1065: istore        7
    1067: istore        6
    1069: iload_1
    1070: ifge          1109
    1073: iload_3
    1074: iload         9
    1076: iload_1
    1077: imul
    1078: isub
    1079: istore_3
    1080: iload         4
    1082: iload         11
    1084: iload_1
    1085: imul
    1086: isub
    1087: istore        4
    1089: iload         6
    1091: iload         10
    1093: iload_1
    1094: imul
    1095: isub
    1096: istore        6
    1098: iload         7
    1100: iload         12
    1102: iload_1
    1103: imul
    1104: isub
    1105: istore        7
    1107: iconst_0
    1108: istore_1
    1109: iload         5
    1111: bipush        16
    1113: ishl
    1114: istore        5
    1116: iload         8
    1118: bipush        15
    1120: ishl
    1121: istore        8
    1123: iload_2
    1124: ifge          1147
    1127: iload         5
    1129: iload         13
    1131: iload_2
    1132: imul
    1133: isub
    1134: istore        5
    1136: iload         8
    1138: iload         14
    1140: iload_2
    1141: imul
    1142: isub
    1143: istore        8
    1145: iconst_0
    1146: istore_2
    1147: iload_1
    1148: iload_2
    1149: if_icmpeq     1159
    1152: iload         9
    1154: iload         11
    1156: if_icmplt     1171
    1159: iload_1
    1160: iload_2
    1161: if_icmpne     1322
    1164: iload         9
    1166: iload         13
    1168: if_icmple     1322
    1171: iload_0
    1172: iload_2
    1173: isub
    1174: istore_0
    1175: iload_2
    1176: iload_1
    1177: isub
    1178: istore_2
    1179: getstatic     #5                  // Field anIntArray1472:[I
    1182: iload_1
    1183: iaload
    1184: istore_1
    1185: iinc          2, -1
    1188: iload_2
    1189: iflt          1253
    1192: getstatic     #72                 // Field DrawingArea.pixels:[I
    1195: iload_1
    1196: iload_3
    1197: bipush        16
    1199: ishr
    1200: iload         4
    1202: bipush        16
    1204: ishr
    1205: iload         6
    1207: bipush        7
    1209: ishr
    1210: iload         7
    1212: bipush        7
    1214: ishr
    1215: invokestatic  #73                 // Method method375:([IIIIII)V
    1218: iload_3
    1219: iload         9
    1221: iadd
    1222: istore_3
    1223: iload         4
    1225: iload         11
    1227: iadd
    1228: istore        4
    1230: iload         6
    1232: iload         10
    1234: iadd
    1235: istore        6
    1237: iload         7
    1239: iload         12
    1241: iadd
    1242: istore        7
    1244: iload_1
    1245: getstatic     #16                 // Field DrawingArea.width:I
    1248: iadd
    1249: istore_1
    1250: goto          1185
    1253: iinc          0, -1
    1256: iload_0
    1257: iflt          1321
    1260: getstatic     #72                 // Field DrawingArea.pixels:[I
    1263: iload_1
    1264: iload_3
    1265: bipush        16
    1267: ishr
    1268: iload         5
    1270: bipush        16
    1272: ishr
    1273: iload         6
    1275: bipush        7
    1277: ishr
    1278: iload         8
    1280: bipush        7
    1282: ishr
    1283: invokestatic  #73                 // Method method375:([IIIIII)V
    1286: iload_3
    1287: iload         9
    1289: iadd
    1290: istore_3
    1291: iload         5
    1293: iload         13
    1295: iadd
    1296: istore        5
    1298: iload         6
    1300: iload         10
    1302: iadd
    1303: istore        6
    1305: iload         8
    1307: iload         14
    1309: iadd
    1310: istore        8
    1312: iload_1
    1313: getstatic     #16                 // Field DrawingArea.width:I
    1316: iadd
    1317: istore_1
    1318: goto          1253
    1321: return
    1322: iload_0
    1323: iload_2
    1324: isub
    1325: istore_0
    1326: iload_2
    1327: iload_1
    1328: isub
    1329: istore_2
    1330: getstatic     #5                  // Field anIntArray1472:[I
    1333: iload_1
    1334: iaload
    1335: istore_1
    1336: iinc          2, -1
    1339: iload_2
    1340: iflt          1404
    1343: getstatic     #72                 // Field DrawingArea.pixels:[I
    1346: iload_1
    1347: iload         4
    1349: bipush        16
    1351: ishr
    1352: iload_3
    1353: bipush        16
    1355: ishr
    1356: iload         7
    1358: bipush        7
    1360: ishr
    1361: iload         6
    1363: bipush        7
    1365: ishr
    1366: invokestatic  #73                 // Method method375:([IIIIII)V
    1369: iload_3
    1370: iload         9
    1372: iadd
    1373: istore_3
    1374: iload         4
    1376: iload         11
    1378: iadd
    1379: istore        4
    1381: iload         6
    1383: iload         10
    1385: iadd
    1386: istore        6
    1388: iload         7
    1390: iload         12
    1392: iadd
    1393: istore        7
    1395: iload_1
    1396: getstatic     #16                 // Field DrawingArea.width:I
    1399: iadd
    1400: istore_1
    1401: goto          1336
    1404: iinc          0, -1
    1407: iload_0
    1408: iflt          1472
    1411: getstatic     #72                 // Field DrawingArea.pixels:[I
    1414: iload_1
    1415: iload         5
    1417: bipush        16
    1419: ishr
    1420: iload_3
    1421: bipush        16
    1423: ishr
    1424: iload         8
    1426: bipush        7
    1428: ishr
    1429: iload         6
    1431: bipush        7
    1433: ishr
    1434: invokestatic  #73                 // Method method375:([IIIIII)V
    1437: iload_3
    1438: iload         9
    1440: iadd
    1441: istore_3
    1442: iload         5
    1444: iload         13
    1446: iadd
    1447: istore        5
    1449: iload         6
    1451: iload         10
    1453: iadd
    1454: istore        6
    1456: iload         8
    1458: iload         14
    1460: iadd
    1461: istore        8
    1463: iload_1
    1464: getstatic     #16                 // Field DrawingArea.width:I
    1467: iadd
    1468: istore_1
    1469: goto          1404
    1472: return
    1473: iload         4
    1475: bipush        16
    1477: ishl
    1478: dup
    1479: istore        4
    1481: istore        5
    1483: iload         7
    1485: bipush        15
    1487: ishl
    1488: dup
    1489: istore        7
    1491: istore        8
    1493: iload_1
    1494: ifge          1535
    1497: iload         5
    1499: iload         9
    1501: iload_1
    1502: imul
    1503: isub
    1504: istore        5
    1506: iload         4
    1508: iload         11
    1510: iload_1
    1511: imul
    1512: isub
    1513: istore        4
    1515: iload         8
    1517: iload         10
    1519: iload_1
    1520: imul
    1521: isub
    1522: istore        8
    1524: iload         7
    1526: iload         12
    1528: iload_1
    1529: imul
    1530: isub
    1531: istore        7
    1533: iconst_0
    1534: istore_1
    1535: iload_3
    1536: bipush        16
    1538: ishl
    1539: istore_3
    1540: iload         6
    1542: bipush        15
    1544: ishl
    1545: istore        6
    1547: iload_0
    1548: ifge          1569
    1551: iload_3
    1552: iload         13
    1554: iload_0
    1555: imul
    1556: isub
    1557: istore_3
    1558: iload         6
    1560: iload         14
    1562: iload_0
    1563: imul
    1564: isub
    1565: istore        6
    1567: iconst_0
    1568: istore_0
    1569: iload         9
    1571: iload         11
    1573: if_icmpge     1730
    1576: iload_2
    1577: iload_0
    1578: isub
    1579: istore_2
    1580: iload_0
    1581: iload_1
    1582: isub
    1583: istore_0
    1584: getstatic     #5                  // Field anIntArray1472:[I
    1587: iload_1
    1588: iaload
    1589: istore_1
    1590: iinc          0, -1
    1593: iload_0
    1594: iflt          1661
    1597: getstatic     #72                 // Field DrawingArea.pixels:[I
    1600: iload_1
    1601: iload         5
    1603: bipush        16
    1605: ishr
    1606: iload         4
    1608: bipush        16
    1610: ishr
    1611: iload         8
    1613: bipush        7
    1615: ishr
    1616: iload         7
    1618: bipush        7
    1620: ishr
    1621: invokestatic  #73                 // Method method375:([IIIIII)V
    1624: iload         5
    1626: iload         9
    1628: iadd
    1629: istore        5
    1631: iload         4
    1633: iload         11
    1635: iadd
    1636: istore        4
    1638: iload         8
    1640: iload         10
    1642: iadd
    1643: istore        8
    1645: iload         7
    1647: iload         12
    1649: iadd
    1650: istore        7
    1652: iload_1
    1653: getstatic     #16                 // Field DrawingArea.width:I
    1656: iadd
    1657: istore_1
    1658: goto          1590
    1661: iinc          2, -1
    1664: iload_2
    1665: iflt          1729
    1668: getstatic     #72                 // Field DrawingArea.pixels:[I
    1671: iload_1
    1672: iload_3
    1673: bipush        16
    1675: ishr
    1676: iload         4
    1678: bipush        16
    1680: ishr
    1681: iload         6
    1683: bipush        7
    1685: ishr
    1686: iload         7
    1688: bipush        7
    1690: ishr
    1691: invokestatic  #73                 // Method method375:([IIIIII)V
    1694: iload_3
    1695: iload         13
    1697: iadd
    1698: istore_3
    1699: iload         4
    1701: iload         11
    1703: iadd
    1704: istore        4
    1706: iload         6
    1708: iload         14
    1710: iadd
    1711: istore        6
    1713: iload         7
    1715: iload         12
    1717: iadd
    1718: istore        7
    1720: iload_1
    1721: getstatic     #16                 // Field DrawingArea.width:I
    1724: iadd
    1725: istore_1
    1726: goto          1661
    1729: return
    1730: iload_2
    1731: iload_0
    1732: isub
    1733: istore_2
    1734: iload_0
    1735: iload_1
    1736: isub
    1737: istore_0
    1738: getstatic     #5                  // Field anIntArray1472:[I
    1741: iload_1
    1742: iaload
    1743: istore_1
    1744: iinc          0, -1
    1747: iload_0
    1748: iflt          1815
    1751: getstatic     #72                 // Field DrawingArea.pixels:[I
    1754: iload_1
    1755: iload         4
    1757: bipush        16
    1759: ishr
    1760: iload         5
    1762: bipush        16
    1764: ishr
    1765: iload         7
    1767: bipush        7
    1769: ishr
    1770: iload         8
    1772: bipush        7
    1774: ishr
    1775: invokestatic  #73                 // Method method375:([IIIIII)V
    1778: iload         5
    1780: iload         9
    1782: iadd
    1783: istore        5
    1785: iload         4
    1787: iload         11
    1789: iadd
    1790: istore        4
    1792: iload         8
    1794: iload         10
    1796: iadd
    1797: istore        8
    1799: iload         7
    1801: iload         12
    1803: iadd
    1804: istore        7
    1806: iload_1
    1807: getstatic     #16                 // Field DrawingArea.width:I
    1810: iadd
    1811: istore_1
    1812: goto          1744
    1815: iinc          2, -1
    1818: iload_2
    1819: iflt          1883
    1822: getstatic     #72                 // Field DrawingArea.pixels:[I
    1825: iload_1
    1826: iload         4
    1828: bipush        16
    1830: ishr
    1831: iload_3
    1832: bipush        16
    1834: ishr
    1835: iload         7
    1837: bipush        7
    1839: ishr
    1840: iload         6
    1842: bipush        7
    1844: ishr
    1845: invokestatic  #73                 // Method method375:([IIIIII)V
    1848: iload_3
    1849: iload         13
    1851: iadd
    1852: istore_3
    1853: iload         4
    1855: iload         11
    1857: iadd
    1858: istore        4
    1860: iload         6
    1862: iload         14
    1864: iadd
    1865: istore        6
    1867: iload         7
    1869: iload         12
    1871: iadd
    1872: istore        7
    1874: iload_1
    1875: getstatic     #16                 // Field DrawingArea.width:I
    1878: iadd
    1879: istore_1
    1880: goto          1815
    1883: return
    1884: iload_2
    1885: getstatic     #71                 // Field DrawingArea.bottomY:I
    1888: if_icmplt     1892
    1891: return
    1892: iload_0
    1893: getstatic     #71                 // Field DrawingArea.bottomY:I
    1896: if_icmple     1903
    1899: getstatic     #71                 // Field DrawingArea.bottomY:I
    1902: istore_0
    1903: iload_1
    1904: getstatic     #71                 // Field DrawingArea.bottomY:I
    1907: if_icmple     1914
    1910: getstatic     #71                 // Field DrawingArea.bottomY:I
    1913: istore_1
    1914: iload_0
    1915: iload_1
    1916: if_icmpge     2330
    1919: iload         5
    1921: bipush        16
    1923: ishl
    1924: dup
    1925: istore        5
    1927: istore        4
    1929: iload         8
    1931: bipush        15
    1933: ishl
    1934: dup
    1935: istore        8
    1937: istore        7
    1939: iload_2
    1940: ifge          1981
    1943: iload         4
    1945: iload         11
    1947: iload_2
    1948: imul
    1949: isub
    1950: istore        4
    1952: iload         5
    1954: iload         13
    1956: iload_2
    1957: imul
    1958: isub
    1959: istore        5
    1961: iload         7
    1963: iload         12
    1965: iload_2
    1966: imul
    1967: isub
    1968: istore        7
    1970: iload         8
    1972: iload         14
    1974: iload_2
    1975: imul
    1976: isub
    1977: istore        8
    1979: iconst_0
    1980: istore_2
    1981: iload_3
    1982: bipush        16
    1984: ishl
    1985: istore_3
    1986: iload         6
    1988: bipush        15
    1990: ishl
    1991: istore        6
    1993: iload_0
    1994: ifge          2015
    1997: iload_3
    1998: iload         9
    2000: iload_0
    2001: imul
    2002: isub
    2003: istore_3
    2004: iload         6
    2006: iload         10
    2008: iload_0
    2009: imul
    2010: isub
    2011: istore        6
    2013: iconst_0
    2014: istore_0
    2015: iload         11
    2017: iload         13
    2019: if_icmpge     2176
    2022: iload_1
    2023: iload_0
    2024: isub
    2025: istore_1
    2026: iload_0
    2027: iload_2
    2028: isub
    2029: istore_0
    2030: getstatic     #5                  // Field anIntArray1472:[I
    2033: iload_2
    2034: iaload
    2035: istore_2
    2036: iinc          0, -1
    2039: iload_0
    2040: iflt          2107
    2043: getstatic     #72                 // Field DrawingArea.pixels:[I
    2046: iload_2
    2047: iload         4
    2049: bipush        16
    2051: ishr
    2052: iload         5
    2054: bipush        16
    2056: ishr
    2057: iload         7
    2059: bipush        7
    2061: ishr
    2062: iload         8
    2064: bipush        7
    2066: ishr
    2067: invokestatic  #73                 // Method method375:([IIIIII)V
    2070: iload         4
    2072: iload         11
    2074: iadd
    2075: istore        4
    2077: iload         5
    2079: iload         13
    2081: iadd
    2082: istore        5
    2084: iload         7
    2086: iload         12
    2088: iadd
    2089: istore        7
    2091: iload         8
    2093: iload         14
    2095: iadd
    2096: istore        8
    2098: iload_2
    2099: getstatic     #16                 // Field DrawingArea.width:I
    2102: iadd
    2103: istore_2
    2104: goto          2036
    2107: iinc          1, -1
    2110: iload_1
    2111: iflt          2175
    2114: getstatic     #72                 // Field DrawingArea.pixels:[I
    2117: iload_2
    2118: iload         4
    2120: bipush        16
    2122: ishr
    2123: iload_3
    2124: bipush        16
    2126: ishr
    2127: iload         7
    2129: bipush        7
    2131: ishr
    2132: iload         6
    2134: bipush        7
    2136: ishr
    2137: invokestatic  #73                 // Method method375:([IIIIII)V
    2140: iload         4
    2142: iload         11
    2144: iadd
    2145: istore        4
    2147: iload_3
    2148: iload         9
    2150: iadd
    2151: istore_3
    2152: iload         7
    2154: iload         12
    2156: iadd
    2157: istore        7
    2159: iload         6
    2161: iload         10
    2163: iadd
    2164: istore        6
    2166: iload_2
    2167: getstatic     #16                 // Field DrawingArea.width:I
    2170: iadd
    2171: istore_2
    2172: goto          2107
    2175: return
    2176: iload_1
    2177: iload_0
    2178: isub
    2179: istore_1
    2180: iload_0
    2181: iload_2
    2182: isub
    2183: istore_0
    2184: getstatic     #5                  // Field anIntArray1472:[I
    2187: iload_2
    2188: iaload
    2189: istore_2
    2190: iinc          0, -1
    2193: iload_0
    2194: iflt          2261
    2197: getstatic     #72                 // Field DrawingArea.pixels:[I
    2200: iload_2
    2201: iload         5
    2203: bipush        16
    2205: ishr
    2206: iload         4
    2208: bipush        16
    2210: ishr
    2211: iload         8
    2213: bipush        7
    2215: ishr
    2216: iload         7
    2218: bipush        7
    2220: ishr
    2221: invokestatic  #73                 // Method method375:([IIIIII)V
    2224: iload         4
    2226: iload         11
    2228: iadd
    2229: istore        4
    2231: iload         5
    2233: iload         13
    2235: iadd
    2236: istore        5
    2238: iload         7
    2240: iload         12
    2242: iadd
    2243: istore        7
    2245: iload         8
    2247: iload         14
    2249: iadd
    2250: istore        8
    2252: iload_2
    2253: getstatic     #16                 // Field DrawingArea.width:I
    2256: iadd
    2257: istore_2
    2258: goto          2190
    2261: iinc          1, -1
    2264: iload_1
    2265: iflt          2329
    2268: getstatic     #72                 // Field DrawingArea.pixels:[I
    2271: iload_2
    2272: iload_3
    2273: bipush        16
    2275: ishr
    2276: iload         4
    2278: bipush        16
    2280: ishr
    2281: iload         6
    2283: bipush        7
    2285: ishr
    2286: iload         7
    2288: bipush        7
    2290: ishr
    2291: invokestatic  #73                 // Method method375:([IIIIII)V
    2294: iload         4
    2296: iload         11
    2298: iadd
    2299: istore        4
    2301: iload_3
    2302: iload         9
    2304: iadd
    2305: istore_3
    2306: iload         7
    2308: iload         12
    2310: iadd
    2311: istore        7
    2313: iload         6
    2315: iload         10
    2317: iadd
    2318: istore        6
    2320: iload_2
    2321: getstatic     #16                 // Field DrawingArea.width:I
    2324: iadd
    2325: istore_2
    2326: goto          2261
    2329: return
    2330: iload         5
    2332: bipush        16
    2334: ishl
    2335: dup
    2336: istore        5
    2338: istore_3
    2339: iload         8
    2341: bipush        15
    2343: ishl
    2344: dup
    2345: istore        8
    2347: istore        6
    2349: iload_2
    2350: ifge          2389
    2353: iload_3
    2354: iload         11
    2356: iload_2
    2357: imul
    2358: isub
    2359: istore_3
    2360: iload         5
    2362: iload         13
    2364: iload_2
    2365: imul
    2366: isub
    2367: istore        5
    2369: iload         6
    2371: iload         12
    2373: iload_2
    2374: imul
    2375: isub
    2376: istore        6
    2378: iload         8
    2380: iload         14
    2382: iload_2
    2383: imul
    2384: isub
    2385: istore        8
    2387: iconst_0
    2388: istore_2
    2389: iload         4
    2391: bipush        16
    2393: ishl
    2394: istore        4
    2396: iload         7
    2398: bipush        15
    2400: ishl
    2401: istore        7
    2403: iload_1
    2404: ifge          2427
    2407: iload         4
    2409: iload         9
    2411: iload_1
    2412: imul
    2413: isub
    2414: istore        4
    2416: iload         7
    2418: iload         10
    2420: iload_1
    2421: imul
    2422: isub
    2423: istore        7
    2425: iconst_0
    2426: istore_1
    2427: iload         11
    2429: iload         13
    2431: if_icmpge     2588
    2434: iload_0
    2435: iload_1
    2436: isub
    2437: istore_0
    2438: iload_1
    2439: iload_2
    2440: isub
    2441: istore_1
    2442: getstatic     #5                  // Field anIntArray1472:[I
    2445: iload_2
    2446: iaload
    2447: istore_2
    2448: iinc          1, -1
    2451: iload_1
    2452: iflt          2516
    2455: getstatic     #72                 // Field DrawingArea.pixels:[I
    2458: iload_2
    2459: iload_3
    2460: bipush        16
    2462: ishr
    2463: iload         5
    2465: bipush        16
    2467: ishr
    2468: iload         6
    2470: bipush        7
    2472: ishr
    2473: iload         8
    2475: bipush        7
    2477: ishr
    2478: invokestatic  #73                 // Method method375:([IIIIII)V
    2481: iload_3
    2482: iload         11
    2484: iadd
    2485: istore_3
    2486: iload         5
    2488: iload         13
    2490: iadd
    2491: istore        5
    2493: iload         6
    2495: iload         12
    2497: iadd
    2498: istore        6
    2500: iload         8
    2502: iload         14
    2504: iadd
    2505: istore        8
    2507: iload_2
    2508: getstatic     #16                 // Field DrawingArea.width:I
    2511: iadd
    2512: istore_2
    2513: goto          2448
    2516: iinc          0, -1
    2519: iload_0
    2520: iflt          2587
    2523: getstatic     #72                 // Field DrawingArea.pixels:[I
    2526: iload_2
    2527: iload         4
    2529: bipush        16
    2531: ishr
    2532: iload         5
    2534: bipush        16
    2536: ishr
    2537: iload         7
    2539: bipush        7
    2541: ishr
    2542: iload         8
    2544: bipush        7
    2546: ishr
    2547: invokestatic  #73                 // Method method375:([IIIIII)V
    2550: iload         4
    2552: iload         9
    2554: iadd
    2555: istore        4
    2557: iload         5
    2559: iload         13
    2561: iadd
    2562: istore        5
    2564: iload         7
    2566: iload         10
    2568: iadd
    2569: istore        7
    2571: iload         8
    2573: iload         14
    2575: iadd
    2576: istore        8
    2578: iload_2
    2579: getstatic     #16                 // Field DrawingArea.width:I
    2582: iadd
    2583: istore_2
    2584: goto          2516
    2587: return
    2588: iload_0
    2589: iload_1
    2590: isub
    2591: istore_0
    2592: iload_1
    2593: iload_2
    2594: isub
    2595: istore_1
    2596: getstatic     #5                  // Field anIntArray1472:[I
    2599: iload_2
    2600: iaload
    2601: istore_2
    2602: iinc          1, -1
    2605: iload_1
    2606: iflt          2670
    2609: getstatic     #72                 // Field DrawingArea.pixels:[I
    2612: iload_2
    2613: iload         5
    2615: bipush        16
    2617: ishr
    2618: iload_3
    2619: bipush        16
    2621: ishr
    2622: iload         8
    2624: bipush        7
    2626: ishr
    2627: iload         6
    2629: bipush        7
    2631: ishr
    2632: invokestatic  #73                 // Method method375:([IIIIII)V
    2635: iload_3
    2636: iload         11
    2638: iadd
    2639: istore_3
    2640: iload         5
    2642: iload         13
    2644: iadd
    2645: istore        5
    2647: iload         6
    2649: iload         12
    2651: iadd
    2652: istore        6
    2654: iload         8
    2656: iload         14
    2658: iadd
    2659: istore        8
    2661: iload_2
    2662: getstatic     #16                 // Field DrawingArea.width:I
    2665: iadd
    2666: istore_2
    2667: goto          2602
    2670: iinc          0, -1
    2673: iload_0
    2674: iflt          2741
    2677: getstatic     #72                 // Field DrawingArea.pixels:[I
    2680: iload_2
    2681: iload         5
    2683: bipush        16
    2685: ishr
    2686: iload         4
    2688: bipush        16
    2690: ishr
    2691: iload         8
    2693: bipush        7
    2695: ishr
    2696: iload         7
    2698: bipush        7
    2700: ishr
    2701: invokestatic  #73                 // Method method375:([IIIIII)V
    2704: iload         4
    2706: iload         9
    2708: iadd
    2709: istore        4
    2711: iload         5
    2713: iload         13
    2715: iadd
    2716: istore        5
    2718: iload         7
    2720: iload         10
    2722: iadd
    2723: istore        7
    2725: iload         8
    2727: iload         14
    2729: iadd
    2730: istore        8
    2732: iload_2
    2733: getstatic     #16                 // Field DrawingArea.width:I
    2736: iadd
    2737: istore_2
    2738: goto          2670
    2741: return

  private static void method375(int[], int, int, int, int, int);
    Code:
       0: getstatic     #74                 // Field aBoolean1464:Z
       3: ifeq          577
       6: getstatic     #75                 // Field aBoolean1462:Z
       9: ifeq          88
      12: iload_3
      13: iload_2
      14: isub
      15: iconst_3
      16: if_icmple     33
      19: iload         5
      21: iload         4
      23: isub
      24: iload_3
      25: iload_2
      26: isub
      27: idiv
      28: istore        8
      30: goto          36
      33: iconst_0
      34: istore        8
      36: iload_3
      37: getstatic     #76                 // Field DrawingArea.centerX:I
      40: if_icmple     47
      43: getstatic     #76                 // Field DrawingArea.centerX:I
      46: istore_3
      47: iload_2
      48: ifge          62
      51: iload         4
      53: iload_2
      54: iload         8
      56: imul
      57: isub
      58: istore        4
      60: iconst_0
      61: istore_2
      62: iload_2
      63: iload_3
      64: if_icmplt     68
      67: return
      68: iload_1
      69: iload_2
      70: iadd
      71: istore_1
      72: iload_3
      73: iload_2
      74: isub
      75: iconst_2
      76: ishr
      77: istore        7
      79: iload         8
      81: iconst_2
      82: ishl
      83: istore        8
      85: goto          133
      88: iload_2
      89: iload_3
      90: if_icmplt     94
      93: return
      94: iload_1
      95: iload_2
      96: iadd
      97: istore_1
      98: iload_3
      99: iload_2
     100: isub
     101: iconst_2
     102: ishr
     103: istore        7
     105: iload         7
     107: ifle          130
     110: iload         5
     112: iload         4
     114: isub
     115: getstatic     #2                  // Field anIntArray1468:[I
     118: iload         7
     120: iaload
     121: imul
     122: bipush        15
     124: ishr
     125: istore        8
     127: goto          133
     130: iconst_0
     131: istore        8
     133: getstatic     #77                 // Field anInt1465:I
     136: ifne          240
     139: iinc          7, -1
     142: iload         7
     144: iflt          200
     147: getstatic     #13                 // Field anIntArray1482:[I
     150: iload         4
     152: bipush        8
     154: ishr
     155: iaload
     156: istore        6
     158: iload         4
     160: iload         8
     162: iadd
     163: istore        4
     165: aload_0
     166: iload_1
     167: iinc          1, 1
     170: iload         6
     172: iastore
     173: aload_0
     174: iload_1
     175: iinc          1, 1
     178: iload         6
     180: iastore
     181: aload_0
     182: iload_1
     183: iinc          1, 1
     186: iload         6
     188: iastore
     189: aload_0
     190: iload_1
     191: iinc          1, 1
     194: iload         6
     196: iastore
     197: goto          139
     200: iload_3
     201: iload_2
     202: isub
     203: iconst_3
     204: iand
     205: istore        7
     207: iload         7
     209: ifle          576
     212: getstatic     #13                 // Field anIntArray1482:[I
     215: iload         4
     217: bipush        8
     219: ishr
     220: iaload
     221: istore        6
     223: aload_0
     224: iload_1
     225: iinc          1, 1
     228: iload         6
     230: iastore
     231: iinc          7, -1
     234: iload         7
     236: ifgt          223
     239: return
     240: getstatic     #77                 // Field anInt1465:I
     243: istore        9
     245: sipush        256
     248: getstatic     #77                 // Field anInt1465:I
     251: isub
     252: istore        10
     254: iinc          7, -1
     257: iload         7
     259: iflt          474
     262: getstatic     #13                 // Field anIntArray1482:[I
     265: iload         4
     267: bipush        8
     269: ishr
     270: iaload
     271: istore        6
     273: iload         4
     275: iload         8
     277: iadd
     278: istore        4
     280: iload         6
     282: ldc           #78                 // int 16711935
     284: iand
     285: iload         10
     287: imul
     288: bipush        8
     290: ishr
     291: ldc           #78                 // int 16711935
     293: iand
     294: iload         6
     296: ldc           #79                 // int 65280
     298: iand
     299: iload         10
     301: imul
     302: bipush        8
     304: ishr
     305: ldc           #79                 // int 65280
     307: iand
     308: iadd
     309: istore        6
     311: aload_0
     312: iload_1
     313: iinc          1, 1
     316: iload         6
     318: aload_0
     319: iload_1
     320: iaload
     321: ldc           #78                 // int 16711935
     323: iand
     324: iload         9
     326: imul
     327: bipush        8
     329: ishr
     330: ldc           #78                 // int 16711935
     332: iand
     333: iadd
     334: aload_0
     335: iload_1
     336: iaload
     337: ldc           #79                 // int 65280
     339: iand
     340: iload         9
     342: imul
     343: bipush        8
     345: ishr
     346: ldc           #79                 // int 65280
     348: iand
     349: iadd
     350: iastore
     351: aload_0
     352: iload_1
     353: iinc          1, 1
     356: iload         6
     358: aload_0
     359: iload_1
     360: iaload
     361: ldc           #78                 // int 16711935
     363: iand
     364: iload         9
     366: imul
     367: bipush        8
     369: ishr
     370: ldc           #78                 // int 16711935
     372: iand
     373: iadd
     374: aload_0
     375: iload_1
     376: iaload
     377: ldc           #79                 // int 65280
     379: iand
     380: iload         9
     382: imul
     383: bipush        8
     385: ishr
     386: ldc           #79                 // int 65280
     388: iand
     389: iadd
     390: iastore
     391: aload_0
     392: iload_1
     393: iinc          1, 1
     396: iload         6
     398: aload_0
     399: iload_1
     400: iaload
     401: ldc           #78                 // int 16711935
     403: iand
     404: iload         9
     406: imul
     407: bipush        8
     409: ishr
     410: ldc           #78                 // int 16711935
     412: iand
     413: iadd
     414: aload_0
     415: iload_1
     416: iaload
     417: ldc           #79                 // int 65280
     419: iand
     420: iload         9
     422: imul
     423: bipush        8
     425: ishr
     426: ldc           #79                 // int 65280
     428: iand
     429: iadd
     430: iastore
     431: aload_0
     432: iload_1
     433: iinc          1, 1
     436: iload         6
     438: aload_0
     439: iload_1
     440: iaload
     441: ldc           #78                 // int 16711935
     443: iand
     444: iload         9
     446: imul
     447: bipush        8
     449: ishr
     450: ldc           #78                 // int 16711935
     452: iand
     453: iadd
     454: aload_0
     455: iload_1
     456: iaload
     457: ldc           #79                 // int 65280
     459: iand
     460: iload         9
     462: imul
     463: bipush        8
     465: ishr
     466: ldc           #79                 // int 65280
     468: iand
     469: iadd
     470: iastore
     471: goto          254
     474: iload_3
     475: iload_2
     476: isub
     477: iconst_3
     478: iand
     479: istore        7
     481: iload         7
     483: ifle          576
     486: getstatic     #13                 // Field anIntArray1482:[I
     489: iload         4
     491: bipush        8
     493: ishr
     494: iaload
     495: istore        6
     497: iload         6
     499: ldc           #78                 // int 16711935
     501: iand
     502: iload         10
     504: imul
     505: bipush        8
     507: ishr
     508: ldc           #78                 // int 16711935
     510: iand
     511: iload         6
     513: ldc           #79                 // int 65280
     515: iand
     516: iload         10
     518: imul
     519: bipush        8
     521: ishr
     522: ldc           #79                 // int 65280
     524: iand
     525: iadd
     526: istore        6
     528: aload_0
     529: iload_1
     530: iinc          1, 1
     533: iload         6
     535: aload_0
     536: iload_1
     537: iaload
     538: ldc           #78                 // int 16711935
     540: iand
     541: iload         9
     543: imul
     544: bipush        8
     546: ishr
     547: ldc           #78                 // int 16711935
     549: iand
     550: iadd
     551: aload_0
     552: iload_1
     553: iaload
     554: ldc           #79                 // int 65280
     556: iand
     557: iload         9
     559: imul
     560: bipush        8
     562: ishr
     563: ldc           #79                 // int 65280
     565: iand
     566: iadd
     567: iastore
     568: iinc          7, -1
     571: iload         7
     573: ifgt          528
     576: return
     577: iload_2
     578: iload_3
     579: if_icmplt     583
     582: return
     583: iload         5
     585: iload         4
     587: isub
     588: iload_3
     589: iload_2
     590: isub
     591: idiv
     592: istore        8
     594: getstatic     #75                 // Field aBoolean1462:Z
     597: ifeq          632
     600: iload_3
     601: getstatic     #76                 // Field DrawingArea.centerX:I
     604: if_icmple     611
     607: getstatic     #76                 // Field DrawingArea.centerX:I
     610: istore_3
     611: iload_2
     612: ifge          626
     615: iload         4
     617: iload_2
     618: iload         8
     620: imul
     621: isub
     622: istore        4
     624: iconst_0
     625: istore_2
     626: iload_2
     627: iload_3
     628: if_icmplt     632
     631: return
     632: iload_1
     633: iload_2
     634: iadd
     635: istore_1
     636: iload_3
     637: iload_2
     638: isub
     639: istore        7
     641: getstatic     #77                 // Field anInt1465:I
     644: ifne          678
     647: aload_0
     648: iload_1
     649: iinc          1, 1
     652: getstatic     #13                 // Field anIntArray1482:[I
     655: iload         4
     657: bipush        8
     659: ishr
     660: iaload
     661: iastore
     662: iload         4
     664: iload         8
     666: iadd
     667: istore        4
     669: iinc          7, -1
     672: iload         7
     674: ifgt          647
     677: return
     678: getstatic     #77                 // Field anInt1465:I
     681: istore        9
     683: sipush        256
     686: getstatic     #77                 // Field anInt1465:I
     689: isub
     690: istore        10
     692: getstatic     #13                 // Field anIntArray1482:[I
     695: iload         4
     697: bipush        8
     699: ishr
     700: iaload
     701: istore        6
     703: iload         4
     705: iload         8
     707: iadd
     708: istore        4
     710: iload         6
     712: ldc           #78                 // int 16711935
     714: iand
     715: iload         10
     717: imul
     718: bipush        8
     720: ishr
     721: ldc           #78                 // int 16711935
     723: iand
     724: iload         6
     726: ldc           #79                 // int 65280
     728: iand
     729: iload         10
     731: imul
     732: bipush        8
     734: ishr
     735: ldc           #79                 // int 65280
     737: iand
     738: iadd
     739: istore        6
     741: aload_0
     742: iload_1
     743: iinc          1, 1
     746: iload         6
     748: aload_0
     749: iload_1
     750: iaload
     751: ldc           #78                 // int 16711935
     753: iand
     754: iload         9
     756: imul
     757: bipush        8
     759: ishr
     760: ldc           #78                 // int 16711935
     762: iand
     763: iadd
     764: aload_0
     765: iload_1
     766: iaload
     767: ldc           #79                 // int 65280
     769: iand
     770: iload         9
     772: imul
     773: bipush        8
     775: ishr
     776: ldc           #79                 // int 65280
     778: iand
     779: iadd
     780: iastore
     781: iinc          7, -1
     784: iload         7
     786: ifgt          692
     789: return

  public static void method376(int, int, int, int, int, int, int);
    Code:
       0: iconst_0
       1: istore        7
       3: iload_1
       4: iload_0
       5: if_icmpeq     21
       8: iload         4
      10: iload_3
      11: isub
      12: bipush        16
      14: ishl
      15: iload_1
      16: iload_0
      17: isub
      18: idiv
      19: istore        7
      21: iconst_0
      22: istore        8
      24: iload_2
      25: iload_1
      26: if_icmpeq     43
      29: iload         5
      31: iload         4
      33: isub
      34: bipush        16
      36: ishl
      37: iload_2
      38: iload_1
      39: isub
      40: idiv
      41: istore        8
      43: iconst_0
      44: istore        9
      46: iload_2
      47: iload_0
      48: if_icmpeq     64
      51: iload_3
      52: iload         5
      54: isub
      55: bipush        16
      57: ishl
      58: iload_0
      59: iload_2
      60: isub
      61: idiv
      62: istore        9
      64: iload_0
      65: iload_1
      66: if_icmpgt     695
      69: iload_0
      70: iload_2
      71: if_icmpgt     695
      74: iload_0
      75: getstatic     #71                 // Field DrawingArea.bottomY:I
      78: if_icmplt     82
      81: return
      82: iload_1
      83: getstatic     #71                 // Field DrawingArea.bottomY:I
      86: if_icmple     93
      89: getstatic     #71                 // Field DrawingArea.bottomY:I
      92: istore_1
      93: iload_2
      94: getstatic     #71                 // Field DrawingArea.bottomY:I
      97: if_icmple     104
     100: getstatic     #71                 // Field DrawingArea.bottomY:I
     103: istore_2
     104: iload_1
     105: iload_2
     106: if_icmpge     405
     109: iload_3
     110: bipush        16
     112: ishl
     113: dup
     114: istore_3
     115: istore        5
     117: iload_0
     118: ifge          139
     121: iload         5
     123: iload         9
     125: iload_0
     126: imul
     127: isub
     128: istore        5
     130: iload_3
     131: iload         7
     133: iload_0
     134: imul
     135: isub
     136: istore_3
     137: iconst_0
     138: istore_0
     139: iload         4
     141: bipush        16
     143: ishl
     144: istore        4
     146: iload_1
     147: ifge          161
     150: iload         4
     152: iload         8
     154: iload_1
     155: imul
     156: isub
     157: istore        4
     159: iconst_0
     160: istore_1
     161: iload_0
     162: iload_1
     163: if_icmpeq     173
     166: iload         9
     168: iload         7
     170: if_icmplt     185
     173: iload_0
     174: iload_1
     175: if_icmpne     295
     178: iload         9
     180: iload         8
     182: if_icmple     295
     185: iload_2
     186: iload_1
     187: isub
     188: istore_2
     189: iload_1
     190: iload_0
     191: isub
     192: istore_1
     193: getstatic     #5                  // Field anIntArray1472:[I
     196: iload_0
     197: iaload
     198: istore_0
     199: iinc          1, -1
     202: iload_1
     203: iflt          245
     206: getstatic     #72                 // Field DrawingArea.pixels:[I
     209: iload_0
     210: iload         6
     212: iload         5
     214: bipush        16
     216: ishr
     217: iload_3
     218: bipush        16
     220: ishr
     221: invokestatic  #80                 // Method method377:([IIIII)V
     224: iload         5
     226: iload         9
     228: iadd
     229: istore        5
     231: iload_3
     232: iload         7
     234: iadd
     235: istore_3
     236: iload_0
     237: getstatic     #16                 // Field DrawingArea.width:I
     240: iadd
     241: istore_0
     242: goto          199
     245: iinc          2, -1
     248: iload_2
     249: iflt          294
     252: getstatic     #72                 // Field DrawingArea.pixels:[I
     255: iload_0
     256: iload         6
     258: iload         5
     260: bipush        16
     262: ishr
     263: iload         4
     265: bipush        16
     267: ishr
     268: invokestatic  #80                 // Method method377:([IIIII)V
     271: iload         5
     273: iload         9
     275: iadd
     276: istore        5
     278: iload         4
     280: iload         8
     282: iadd
     283: istore        4
     285: iload_0
     286: getstatic     #16                 // Field DrawingArea.width:I
     289: iadd
     290: istore_0
     291: goto          245
     294: return
     295: iload_2
     296: iload_1
     297: isub
     298: istore_2
     299: iload_1
     300: iload_0
     301: isub
     302: istore_1
     303: getstatic     #5                  // Field anIntArray1472:[I
     306: iload_0
     307: iaload
     308: istore_0
     309: iinc          1, -1
     312: iload_1
     313: iflt          355
     316: getstatic     #72                 // Field DrawingArea.pixels:[I
     319: iload_0
     320: iload         6
     322: iload_3
     323: bipush        16
     325: ishr
     326: iload         5
     328: bipush        16
     330: ishr
     331: invokestatic  #80                 // Method method377:([IIIII)V
     334: iload         5
     336: iload         9
     338: iadd
     339: istore        5
     341: iload_3
     342: iload         7
     344: iadd
     345: istore_3
     346: iload_0
     347: getstatic     #16                 // Field DrawingArea.width:I
     350: iadd
     351: istore_0
     352: goto          309
     355: iinc          2, -1
     358: iload_2
     359: iflt          404
     362: getstatic     #72                 // Field DrawingArea.pixels:[I
     365: iload_0
     366: iload         6
     368: iload         4
     370: bipush        16
     372: ishr
     373: iload         5
     375: bipush        16
     377: ishr
     378: invokestatic  #80                 // Method method377:([IIIII)V
     381: iload         5
     383: iload         9
     385: iadd
     386: istore        5
     388: iload         4
     390: iload         8
     392: iadd
     393: istore        4
     395: iload_0
     396: getstatic     #16                 // Field DrawingArea.width:I
     399: iadd
     400: istore_0
     401: goto          355
     404: return
     405: iload_3
     406: bipush        16
     408: ishl
     409: dup
     410: istore_3
     411: istore        4
     413: iload_0
     414: ifge          435
     417: iload         4
     419: iload         9
     421: iload_0
     422: imul
     423: isub
     424: istore        4
     426: iload_3
     427: iload         7
     429: iload_0
     430: imul
     431: isub
     432: istore_3
     433: iconst_0
     434: istore_0
     435: iload         5
     437: bipush        16
     439: ishl
     440: istore        5
     442: iload_2
     443: ifge          457
     446: iload         5
     448: iload         8
     450: iload_2
     451: imul
     452: isub
     453: istore        5
     455: iconst_0
     456: istore_2
     457: iload_0
     458: iload_2
     459: if_icmpeq     469
     462: iload         9
     464: iload         7
     466: if_icmplt     481
     469: iload_0
     470: iload_2
     471: if_icmpne     588
     474: iload         8
     476: iload         7
     478: if_icmple     588
     481: iload_1
     482: iload_2
     483: isub
     484: istore_1
     485: iload_2
     486: iload_0
     487: isub
     488: istore_2
     489: getstatic     #5                  // Field anIntArray1472:[I
     492: iload_0
     493: iaload
     494: istore_0
     495: iinc          2, -1
     498: iload_2
     499: iflt          541
     502: getstatic     #72                 // Field DrawingArea.pixels:[I
     505: iload_0
     506: iload         6
     508: iload         4
     510: bipush        16
     512: ishr
     513: iload_3
     514: bipush        16
     516: ishr
     517: invokestatic  #80                 // Method method377:([IIIII)V
     520: iload         4
     522: iload         9
     524: iadd
     525: istore        4
     527: iload_3
     528: iload         7
     530: iadd
     531: istore_3
     532: iload_0
     533: getstatic     #16                 // Field DrawingArea.width:I
     536: iadd
     537: istore_0
     538: goto          495
     541: iinc          1, -1
     544: iload_1
     545: iflt          587
     548: getstatic     #72                 // Field DrawingArea.pixels:[I
     551: iload_0
     552: iload         6
     554: iload         5
     556: bipush        16
     558: ishr
     559: iload_3
     560: bipush        16
     562: ishr
     563: invokestatic  #80                 // Method method377:([IIIII)V
     566: iload         5
     568: iload         8
     570: iadd
     571: istore        5
     573: iload_3
     574: iload         7
     576: iadd
     577: istore_3
     578: iload_0
     579: getstatic     #16                 // Field DrawingArea.width:I
     582: iadd
     583: istore_0
     584: goto          541
     587: return
     588: iload_1
     589: iload_2
     590: isub
     591: istore_1
     592: iload_2
     593: iload_0
     594: isub
     595: istore_2
     596: getstatic     #5                  // Field anIntArray1472:[I
     599: iload_0
     600: iaload
     601: istore_0
     602: iinc          2, -1
     605: iload_2
     606: iflt          648
     609: getstatic     #72                 // Field DrawingArea.pixels:[I
     612: iload_0
     613: iload         6
     615: iload_3
     616: bipush        16
     618: ishr
     619: iload         4
     621: bipush        16
     623: ishr
     624: invokestatic  #80                 // Method method377:([IIIII)V
     627: iload         4
     629: iload         9
     631: iadd
     632: istore        4
     634: iload_3
     635: iload         7
     637: iadd
     638: istore_3
     639: iload_0
     640: getstatic     #16                 // Field DrawingArea.width:I
     643: iadd
     644: istore_0
     645: goto          602
     648: iinc          1, -1
     651: iload_1
     652: iflt          694
     655: getstatic     #72                 // Field DrawingArea.pixels:[I
     658: iload_0
     659: iload         6
     661: iload_3
     662: bipush        16
     664: ishr
     665: iload         5
     667: bipush        16
     669: ishr
     670: invokestatic  #80                 // Method method377:([IIIII)V
     673: iload         5
     675: iload         8
     677: iadd
     678: istore        5
     680: iload_3
     681: iload         7
     683: iadd
     684: istore_3
     685: iload_0
     686: getstatic     #16                 // Field DrawingArea.width:I
     689: iadd
     690: istore_0
     691: goto          648
     694: return
     695: iload_1
     696: iload_2
     697: if_icmpgt     1305
     700: iload_1
     701: getstatic     #71                 // Field DrawingArea.bottomY:I
     704: if_icmplt     708
     707: return
     708: iload_2
     709: getstatic     #71                 // Field DrawingArea.bottomY:I
     712: if_icmple     719
     715: getstatic     #71                 // Field DrawingArea.bottomY:I
     718: istore_2
     719: iload_0
     720: getstatic     #71                 // Field DrawingArea.bottomY:I
     723: if_icmple     730
     726: getstatic     #71                 // Field DrawingArea.bottomY:I
     729: istore_0
     730: iload_2
     731: iload_0
     732: if_icmpge     1026
     735: iload         4
     737: bipush        16
     739: ishl
     740: dup
     741: istore        4
     743: istore_3
     744: iload_1
     745: ifge          766
     748: iload_3
     749: iload         7
     751: iload_1
     752: imul
     753: isub
     754: istore_3
     755: iload         4
     757: iload         8
     759: iload_1
     760: imul
     761: isub
     762: istore        4
     764: iconst_0
     765: istore_1
     766: iload         5
     768: bipush        16
     770: ishl
     771: istore        5
     773: iload_2
     774: ifge          788
     777: iload         5
     779: iload         9
     781: iload_2
     782: imul
     783: isub
     784: istore        5
     786: iconst_0
     787: istore_2
     788: iload_1
     789: iload_2
     790: if_icmpeq     800
     793: iload         7
     795: iload         8
     797: if_icmplt     812
     800: iload_1
     801: iload_2
     802: if_icmpne     919
     805: iload         7
     807: iload         9
     809: if_icmple     919
     812: iload_0
     813: iload_2
     814: isub
     815: istore_0
     816: iload_2
     817: iload_1
     818: isub
     819: istore_2
     820: getstatic     #5                  // Field anIntArray1472:[I
     823: iload_1
     824: iaload
     825: istore_1
     826: iinc          2, -1
     829: iload_2
     830: iflt          872
     833: getstatic     #72                 // Field DrawingArea.pixels:[I
     836: iload_1
     837: iload         6
     839: iload_3
     840: bipush        16
     842: ishr
     843: iload         4
     845: bipush        16
     847: ishr
     848: invokestatic  #80                 // Method method377:([IIIII)V
     851: iload_3
     852: iload         7
     854: iadd
     855: istore_3
     856: iload         4
     858: iload         8
     860: iadd
     861: istore        4
     863: iload_1
     864: getstatic     #16                 // Field DrawingArea.width:I
     867: iadd
     868: istore_1
     869: goto          826
     872: iinc          0, -1
     875: iload_0
     876: iflt          918
     879: getstatic     #72                 // Field DrawingArea.pixels:[I
     882: iload_1
     883: iload         6
     885: iload_3
     886: bipush        16
     888: ishr
     889: iload         5
     891: bipush        16
     893: ishr
     894: invokestatic  #80                 // Method method377:([IIIII)V
     897: iload_3
     898: iload         7
     900: iadd
     901: istore_3
     902: iload         5
     904: iload         9
     906: iadd
     907: istore        5
     909: iload_1
     910: getstatic     #16                 // Field DrawingArea.width:I
     913: iadd
     914: istore_1
     915: goto          872
     918: return
     919: iload_0
     920: iload_2
     921: isub
     922: istore_0
     923: iload_2
     924: iload_1
     925: isub
     926: istore_2
     927: getstatic     #5                  // Field anIntArray1472:[I
     930: iload_1
     931: iaload
     932: istore_1
     933: iinc          2, -1
     936: iload_2
     937: iflt          979
     940: getstatic     #72                 // Field DrawingArea.pixels:[I
     943: iload_1
     944: iload         6
     946: iload         4
     948: bipush        16
     950: ishr
     951: iload_3
     952: bipush        16
     954: ishr
     955: invokestatic  #80                 // Method method377:([IIIII)V
     958: iload_3
     959: iload         7
     961: iadd
     962: istore_3
     963: iload         4
     965: iload         8
     967: iadd
     968: istore        4
     970: iload_1
     971: getstatic     #16                 // Field DrawingArea.width:I
     974: iadd
     975: istore_1
     976: goto          933
     979: iinc          0, -1
     982: iload_0
     983: iflt          1025
     986: getstatic     #72                 // Field DrawingArea.pixels:[I
     989: iload_1
     990: iload         6
     992: iload         5
     994: bipush        16
     996: ishr
     997: iload_3
     998: bipush        16
    1000: ishr
    1001: invokestatic  #80                 // Method method377:([IIIII)V
    1004: iload_3
    1005: iload         7
    1007: iadd
    1008: istore_3
    1009: iload         5
    1011: iload         9
    1013: iadd
    1014: istore        5
    1016: iload_1
    1017: getstatic     #16                 // Field DrawingArea.width:I
    1020: iadd
    1021: istore_1
    1022: goto          979
    1025: return
    1026: iload         4
    1028: bipush        16
    1030: ishl
    1031: dup
    1032: istore        4
    1034: istore        5
    1036: iload_1
    1037: ifge          1060
    1040: iload         5
    1042: iload         7
    1044: iload_1
    1045: imul
    1046: isub
    1047: istore        5
    1049: iload         4
    1051: iload         8
    1053: iload_1
    1054: imul
    1055: isub
    1056: istore        4
    1058: iconst_0
    1059: istore_1
    1060: iload_3
    1061: bipush        16
    1063: ishl
    1064: istore_3
    1065: iload_0
    1066: ifge          1078
    1069: iload_3
    1070: iload         9
    1072: iload_0
    1073: imul
    1074: isub
    1075: istore_3
    1076: iconst_0
    1077: istore_0
    1078: iload         7
    1080: iload         8
    1082: if_icmpge     1195
    1085: iload_2
    1086: iload_0
    1087: isub
    1088: istore_2
    1089: iload_0
    1090: iload_1
    1091: isub
    1092: istore_0
    1093: getstatic     #5                  // Field anIntArray1472:[I
    1096: iload_1
    1097: iaload
    1098: istore_1
    1099: iinc          0, -1
    1102: iload_0
    1103: iflt          1148
    1106: getstatic     #72                 // Field DrawingArea.pixels:[I
    1109: iload_1
    1110: iload         6
    1112: iload         5
    1114: bipush        16
    1116: ishr
    1117: iload         4
    1119: bipush        16
    1121: ishr
    1122: invokestatic  #80                 // Method method377:([IIIII)V
    1125: iload         5
    1127: iload         7
    1129: iadd
    1130: istore        5
    1132: iload         4
    1134: iload         8
    1136: iadd
    1137: istore        4
    1139: iload_1
    1140: getstatic     #16                 // Field DrawingArea.width:I
    1143: iadd
    1144: istore_1
    1145: goto          1099
    1148: iinc          2, -1
    1151: iload_2
    1152: iflt          1194
    1155: getstatic     #72                 // Field DrawingArea.pixels:[I
    1158: iload_1
    1159: iload         6
    1161: iload_3
    1162: bipush        16
    1164: ishr
    1165: iload         4
    1167: bipush        16
    1169: ishr
    1170: invokestatic  #80                 // Method method377:([IIIII)V
    1173: iload_3
    1174: iload         9
    1176: iadd
    1177: istore_3
    1178: iload         4
    1180: iload         8
    1182: iadd
    1183: istore        4
    1185: iload_1
    1186: getstatic     #16                 // Field DrawingArea.width:I
    1189: iadd
    1190: istore_1
    1191: goto          1148
    1194: return
    1195: iload_2
    1196: iload_0
    1197: isub
    1198: istore_2
    1199: iload_0
    1200: iload_1
    1201: isub
    1202: istore_0
    1203: getstatic     #5                  // Field anIntArray1472:[I
    1206: iload_1
    1207: iaload
    1208: istore_1
    1209: iinc          0, -1
    1212: iload_0
    1213: iflt          1258
    1216: getstatic     #72                 // Field DrawingArea.pixels:[I
    1219: iload_1
    1220: iload         6
    1222: iload         4
    1224: bipush        16
    1226: ishr
    1227: iload         5
    1229: bipush        16
    1231: ishr
    1232: invokestatic  #80                 // Method method377:([IIIII)V
    1235: iload         5
    1237: iload         7
    1239: iadd
    1240: istore        5
    1242: iload         4
    1244: iload         8
    1246: iadd
    1247: istore        4
    1249: iload_1
    1250: getstatic     #16                 // Field DrawingArea.width:I
    1253: iadd
    1254: istore_1
    1255: goto          1209
    1258: iinc          2, -1
    1261: iload_2
    1262: iflt          1304
    1265: getstatic     #72                 // Field DrawingArea.pixels:[I
    1268: iload_1
    1269: iload         6
    1271: iload         4
    1273: bipush        16
    1275: ishr
    1276: iload_3
    1277: bipush        16
    1279: ishr
    1280: invokestatic  #80                 // Method method377:([IIIII)V
    1283: iload_3
    1284: iload         9
    1286: iadd
    1287: istore_3
    1288: iload         4
    1290: iload         8
    1292: iadd
    1293: istore        4
    1295: iload_1
    1296: getstatic     #16                 // Field DrawingArea.width:I
    1299: iadd
    1300: istore_1
    1301: goto          1258
    1304: return
    1305: iload_2
    1306: getstatic     #71                 // Field DrawingArea.bottomY:I
    1309: if_icmplt     1313
    1312: return
    1313: iload_0
    1314: getstatic     #71                 // Field DrawingArea.bottomY:I
    1317: if_icmple     1324
    1320: getstatic     #71                 // Field DrawingArea.bottomY:I
    1323: istore_0
    1324: iload_1
    1325: getstatic     #71                 // Field DrawingArea.bottomY:I
    1328: if_icmple     1335
    1331: getstatic     #71                 // Field DrawingArea.bottomY:I
    1334: istore_1
    1335: iload_0
    1336: iload_1
    1337: if_icmpge     1619
    1340: iload         5
    1342: bipush        16
    1344: ishl
    1345: dup
    1346: istore        5
    1348: istore        4
    1350: iload_2
    1351: ifge          1374
    1354: iload         4
    1356: iload         8
    1358: iload_2
    1359: imul
    1360: isub
    1361: istore        4
    1363: iload         5
    1365: iload         9
    1367: iload_2
    1368: imul
    1369: isub
    1370: istore        5
    1372: iconst_0
    1373: istore_2
    1374: iload_3
    1375: bipush        16
    1377: ishl
    1378: istore_3
    1379: iload_0
    1380: ifge          1392
    1383: iload_3
    1384: iload         7
    1386: iload_0
    1387: imul
    1388: isub
    1389: istore_3
    1390: iconst_0
    1391: istore_0
    1392: iload         8
    1394: iload         9
    1396: if_icmpge     1509
    1399: iload_1
    1400: iload_0
    1401: isub
    1402: istore_1
    1403: iload_0
    1404: iload_2
    1405: isub
    1406: istore_0
    1407: getstatic     #5                  // Field anIntArray1472:[I
    1410: iload_2
    1411: iaload
    1412: istore_2
    1413: iinc          0, -1
    1416: iload_0
    1417: iflt          1462
    1420: getstatic     #72                 // Field DrawingArea.pixels:[I
    1423: iload_2
    1424: iload         6
    1426: iload         4
    1428: bipush        16
    1430: ishr
    1431: iload         5
    1433: bipush        16
    1435: ishr
    1436: invokestatic  #80                 // Method method377:([IIIII)V
    1439: iload         4
    1441: iload         8
    1443: iadd
    1444: istore        4
    1446: iload         5
    1448: iload         9
    1450: iadd
    1451: istore        5
    1453: iload_2
    1454: getstatic     #16                 // Field DrawingArea.width:I
    1457: iadd
    1458: istore_2
    1459: goto          1413
    1462: iinc          1, -1
    1465: iload_1
    1466: iflt          1508
    1469: getstatic     #72                 // Field DrawingArea.pixels:[I
    1472: iload_2
    1473: iload         6
    1475: iload         4
    1477: bipush        16
    1479: ishr
    1480: iload_3
    1481: bipush        16
    1483: ishr
    1484: invokestatic  #80                 // Method method377:([IIIII)V
    1487: iload         4
    1489: iload         8
    1491: iadd
    1492: istore        4
    1494: iload_3
    1495: iload         7
    1497: iadd
    1498: istore_3
    1499: iload_2
    1500: getstatic     #16                 // Field DrawingArea.width:I
    1503: iadd
    1504: istore_2
    1505: goto          1462
    1508: return
    1509: iload_1
    1510: iload_0
    1511: isub
    1512: istore_1
    1513: iload_0
    1514: iload_2
    1515: isub
    1516: istore_0
    1517: getstatic     #5                  // Field anIntArray1472:[I
    1520: iload_2
    1521: iaload
    1522: istore_2
    1523: iinc          0, -1
    1526: iload_0
    1527: iflt          1572
    1530: getstatic     #72                 // Field DrawingArea.pixels:[I
    1533: iload_2
    1534: iload         6
    1536: iload         5
    1538: bipush        16
    1540: ishr
    1541: iload         4
    1543: bipush        16
    1545: ishr
    1546: invokestatic  #80                 // Method method377:([IIIII)V
    1549: iload         4
    1551: iload         8
    1553: iadd
    1554: istore        4
    1556: iload         5
    1558: iload         9
    1560: iadd
    1561: istore        5
    1563: iload_2
    1564: getstatic     #16                 // Field DrawingArea.width:I
    1567: iadd
    1568: istore_2
    1569: goto          1523
    1572: iinc          1, -1
    1575: iload_1
    1576: iflt          1618
    1579: getstatic     #72                 // Field DrawingArea.pixels:[I
    1582: iload_2
    1583: iload         6
    1585: iload_3
    1586: bipush        16
    1588: ishr
    1589: iload         4
    1591: bipush        16
    1593: ishr
    1594: invokestatic  #80                 // Method method377:([IIIII)V
    1597: iload         4
    1599: iload         8
    1601: iadd
    1602: istore        4
    1604: iload_3
    1605: iload         7
    1607: iadd
    1608: istore_3
    1609: iload_2
    1610: getstatic     #16                 // Field DrawingArea.width:I
    1613: iadd
    1614: istore_2
    1615: goto          1572
    1618: return
    1619: iload         5
    1621: bipush        16
    1623: ishl
    1624: dup
    1625: istore        5
    1627: istore_3
    1628: iload_2
    1629: ifge          1650
    1632: iload_3
    1633: iload         8
    1635: iload_2
    1636: imul
    1637: isub
    1638: istore_3
    1639: iload         5
    1641: iload         9
    1643: iload_2
    1644: imul
    1645: isub
    1646: istore        5
    1648: iconst_0
    1649: istore_2
    1650: iload         4
    1652: bipush        16
    1654: ishl
    1655: istore        4
    1657: iload_1
    1658: ifge          1672
    1661: iload         4
    1663: iload         7
    1665: iload_1
    1666: imul
    1667: isub
    1668: istore        4
    1670: iconst_0
    1671: istore_1
    1672: iload         8
    1674: iload         9
    1676: if_icmpge     1789
    1679: iload_0
    1680: iload_1
    1681: isub
    1682: istore_0
    1683: iload_1
    1684: iload_2
    1685: isub
    1686: istore_1
    1687: getstatic     #5                  // Field anIntArray1472:[I
    1690: iload_2
    1691: iaload
    1692: istore_2
    1693: iinc          1, -1
    1696: iload_1
    1697: iflt          1739
    1700: getstatic     #72                 // Field DrawingArea.pixels:[I
    1703: iload_2
    1704: iload         6
    1706: iload_3
    1707: bipush        16
    1709: ishr
    1710: iload         5
    1712: bipush        16
    1714: ishr
    1715: invokestatic  #80                 // Method method377:([IIIII)V
    1718: iload_3
    1719: iload         8
    1721: iadd
    1722: istore_3
    1723: iload         5
    1725: iload         9
    1727: iadd
    1728: istore        5
    1730: iload_2
    1731: getstatic     #16                 // Field DrawingArea.width:I
    1734: iadd
    1735: istore_2
    1736: goto          1693
    1739: iinc          0, -1
    1742: iload_0
    1743: iflt          1788
    1746: getstatic     #72                 // Field DrawingArea.pixels:[I
    1749: iload_2
    1750: iload         6
    1752: iload         4
    1754: bipush        16
    1756: ishr
    1757: iload         5
    1759: bipush        16
    1761: ishr
    1762: invokestatic  #80                 // Method method377:([IIIII)V
    1765: iload         4
    1767: iload         7
    1769: iadd
    1770: istore        4
    1772: iload         5
    1774: iload         9
    1776: iadd
    1777: istore        5
    1779: iload_2
    1780: getstatic     #16                 // Field DrawingArea.width:I
    1783: iadd
    1784: istore_2
    1785: goto          1739
    1788: return
    1789: iload_0
    1790: iload_1
    1791: isub
    1792: istore_0
    1793: iload_1
    1794: iload_2
    1795: isub
    1796: istore_1
    1797: getstatic     #5                  // Field anIntArray1472:[I
    1800: iload_2
    1801: iaload
    1802: istore_2
    1803: iinc          1, -1
    1806: iload_1
    1807: iflt          1849
    1810: getstatic     #72                 // Field DrawingArea.pixels:[I
    1813: iload_2
    1814: iload         6
    1816: iload         5
    1818: bipush        16
    1820: ishr
    1821: iload_3
    1822: bipush        16
    1824: ishr
    1825: invokestatic  #80                 // Method method377:([IIIII)V
    1828: iload_3
    1829: iload         8
    1831: iadd
    1832: istore_3
    1833: iload         5
    1835: iload         9
    1837: iadd
    1838: istore        5
    1840: iload_2
    1841: getstatic     #16                 // Field DrawingArea.width:I
    1844: iadd
    1845: istore_2
    1846: goto          1803
    1849: iinc          0, -1
    1852: iload_0
    1853: iflt          1898
    1856: getstatic     #72                 // Field DrawingArea.pixels:[I
    1859: iload_2
    1860: iload         6
    1862: iload         5
    1864: bipush        16
    1866: ishr
    1867: iload         4
    1869: bipush        16
    1871: ishr
    1872: invokestatic  #80                 // Method method377:([IIIII)V
    1875: iload         4
    1877: iload         7
    1879: iadd
    1880: istore        4
    1882: iload         5
    1884: iload         9
    1886: iadd
    1887: istore        5
    1889: iload_2
    1890: getstatic     #16                 // Field DrawingArea.width:I
    1893: iadd
    1894: istore_2
    1895: goto          1849
    1898: return

  private static void method377(int[], int, int, int, int);
    Code:
       0: getstatic     #75                 // Field aBoolean1462:Z
       3: ifeq          25
       6: iload         4
       8: getstatic     #76                 // Field DrawingArea.centerX:I
      11: if_icmple     19
      14: getstatic     #76                 // Field DrawingArea.centerX:I
      17: istore        4
      19: iload_3
      20: ifge          25
      23: iconst_0
      24: istore_3
      25: iload_3
      26: iload         4
      28: if_icmplt     32
      31: return
      32: iload_1
      33: iload_3
      34: iadd
      35: istore_1
      36: iload         4
      38: iload_3
      39: isub
      40: iconst_2
      41: ishr
      42: istore        5
      44: getstatic     #77                 // Field anInt1465:I
      47: ifne          116
      50: iinc          5, -1
      53: iload         5
      55: iflt          89
      58: aload_0
      59: iload_1
      60: iinc          1, 1
      63: iload_2
      64: iastore
      65: aload_0
      66: iload_1
      67: iinc          1, 1
      70: iload_2
      71: iastore
      72: aload_0
      73: iload_1
      74: iinc          1, 1
      77: iload_2
      78: iastore
      79: aload_0
      80: iload_1
      81: iinc          1, 1
      84: iload_2
      85: iastore
      86: goto          50
      89: iload         4
      91: iload_3
      92: isub
      93: iconst_3
      94: iand
      95: istore        5
      97: iinc          5, -1
     100: iload         5
     102: iflt          115
     105: aload_0
     106: iload_1
     107: iinc          1, 1
     110: iload_2
     111: iastore
     112: goto          97
     115: return
     116: getstatic     #77                 // Field anInt1465:I
     119: istore        6
     121: sipush        256
     124: getstatic     #77                 // Field anInt1465:I
     127: isub
     128: istore        7
     130: iload_2
     131: ldc           #78                 // int 16711935
     133: iand
     134: iload         7
     136: imul
     137: bipush        8
     139: ishr
     140: ldc           #78                 // int 16711935
     142: iand
     143: iload_2
     144: ldc           #79                 // int 65280
     146: iand
     147: iload         7
     149: imul
     150: bipush        8
     152: ishr
     153: ldc           #79                 // int 65280
     155: iand
     156: iadd
     157: istore_2
     158: iinc          5, -1
     161: iload         5
     163: iflt          325
     166: aload_0
     167: iload_1
     168: iinc          1, 1
     171: iload_2
     172: aload_0
     173: iload_1
     174: iaload
     175: ldc           #78                 // int 16711935
     177: iand
     178: iload         6
     180: imul
     181: bipush        8
     183: ishr
     184: ldc           #78                 // int 16711935
     186: iand
     187: iadd
     188: aload_0
     189: iload_1
     190: iaload
     191: ldc           #79                 // int 65280
     193: iand
     194: iload         6
     196: imul
     197: bipush        8
     199: ishr
     200: ldc           #79                 // int 65280
     202: iand
     203: iadd
     204: iastore
     205: aload_0
     206: iload_1
     207: iinc          1, 1
     210: iload_2
     211: aload_0
     212: iload_1
     213: iaload
     214: ldc           #78                 // int 16711935
     216: iand
     217: iload         6
     219: imul
     220: bipush        8
     222: ishr
     223: ldc           #78                 // int 16711935
     225: iand
     226: iadd
     227: aload_0
     228: iload_1
     229: iaload
     230: ldc           #79                 // int 65280
     232: iand
     233: iload         6
     235: imul
     236: bipush        8
     238: ishr
     239: ldc           #79                 // int 65280
     241: iand
     242: iadd
     243: iastore
     244: aload_0
     245: iload_1
     246: iinc          1, 1
     249: iload_2
     250: aload_0
     251: iload_1
     252: iaload
     253: ldc           #78                 // int 16711935
     255: iand
     256: iload         6
     258: imul
     259: bipush        8
     261: ishr
     262: ldc           #78                 // int 16711935
     264: iand
     265: iadd
     266: aload_0
     267: iload_1
     268: iaload
     269: ldc           #79                 // int 65280
     271: iand
     272: iload         6
     274: imul
     275: bipush        8
     277: ishr
     278: ldc           #79                 // int 65280
     280: iand
     281: iadd
     282: iastore
     283: aload_0
     284: iload_1
     285: iinc          1, 1
     288: iload_2
     289: aload_0
     290: iload_1
     291: iaload
     292: ldc           #78                 // int 16711935
     294: iand
     295: iload         6
     297: imul
     298: bipush        8
     300: ishr
     301: ldc           #78                 // int 16711935
     303: iand
     304: iadd
     305: aload_0
     306: iload_1
     307: iaload
     308: ldc           #79                 // int 65280
     310: iand
     311: iload         6
     313: imul
     314: bipush        8
     316: ishr
     317: ldc           #79                 // int 65280
     319: iand
     320: iadd
     321: iastore
     322: goto          158
     325: iload         4
     327: iload_3
     328: isub
     329: iconst_3
     330: iand
     331: istore        5
     333: iinc          5, -1
     336: iload         5
     338: iflt          383
     341: aload_0
     342: iload_1
     343: iinc          1, 1
     346: iload_2
     347: aload_0
     348: iload_1
     349: iaload
     350: ldc           #78                 // int 16711935
     352: iand
     353: iload         6
     355: imul
     356: bipush        8
     358: ishr
     359: ldc           #78                 // int 16711935
     361: iand
     362: iadd
     363: aload_0
     364: iload_1
     365: iaload
     366: ldc           #79                 // int 65280
     368: iand
     369: iload         6
     371: imul
     372: bipush        8
     374: ishr
     375: ldc           #79                 // int 65280
     377: iand
     378: iadd
     379: iastore
     380: goto          333
     383: return

  public static void method378(int, int, int, int, int, int, int, int, int, int, int, int, int, int, int, int, int, int, int);
    Code:
       0: iload         18
       2: invokestatic  #81                 // Method method371:(I)[I
       5: astore        19
       7: getstatic     #7                  // Field aBooleanArray1475:[Z
      10: iload         18
      12: baload
      13: ifne          20
      16: iconst_1
      17: goto          21
      20: iconst_0
      21: putstatic     #82                 // Field aBoolean1463:Z
      24: iload         9
      26: iload         10
      28: isub
      29: istore        10
      31: iload         12
      33: iload         13
      35: isub
      36: istore        13
      38: iload         15
      40: iload         16
      42: isub
      43: istore        16
      45: iload         11
      47: iload         9
      49: isub
      50: istore        11
      52: iload         14
      54: iload         12
      56: isub
      57: istore        14
      59: iload         17
      61: iload         15
      63: isub
      64: istore        17
      66: iload         11
      68: iload         12
      70: imul
      71: iload         14
      73: iload         9
      75: imul
      76: isub
      77: bipush        14
      79: ishl
      80: istore        20
      82: iload         14
      84: iload         15
      86: imul
      87: iload         17
      89: iload         12
      91: imul
      92: isub
      93: bipush        8
      95: ishl
      96: istore        21
      98: iload         17
     100: iload         9
     102: imul
     103: iload         11
     105: iload         15
     107: imul
     108: isub
     109: iconst_5
     110: ishl
     111: istore        22
     113: iload         10
     115: iload         12
     117: imul
     118: iload         13
     120: iload         9
     122: imul
     123: isub
     124: bipush        14
     126: ishl
     127: istore        23
     129: iload         13
     131: iload         15
     133: imul
     134: iload         16
     136: iload         12
     138: imul
     139: isub
     140: bipush        8
     142: ishl
     143: istore        24
     145: iload         16
     147: iload         9
     149: imul
     150: iload         10
     152: iload         15
     154: imul
     155: isub
     156: iconst_5
     157: ishl
     158: istore        25
     160: iload         13
     162: iload         11
     164: imul
     165: iload         10
     167: iload         14
     169: imul
     170: isub
     171: bipush        14
     173: ishl
     174: istore        26
     176: iload         16
     178: iload         14
     180: imul
     181: iload         13
     183: iload         17
     185: imul
     186: isub
     187: bipush        8
     189: ishl
     190: istore        27
     192: iload         10
     194: iload         17
     196: imul
     197: iload         16
     199: iload         11
     201: imul
     202: isub
     203: iconst_5
     204: ishl
     205: istore        28
     207: iconst_0
     208: istore        29
     210: iconst_0
     211: istore        30
     213: iload_1
     214: iload_0
     215: if_icmpeq     245
     218: iload         4
     220: iload_3
     221: isub
     222: bipush        16
     224: ishl
     225: iload_1
     226: iload_0
     227: isub
     228: idiv
     229: istore        29
     231: iload         7
     233: iload         6
     235: isub
     236: bipush        16
     238: ishl
     239: iload_1
     240: iload_0
     241: isub
     242: idiv
     243: istore        30
     245: iconst_0
     246: istore        31
     248: iconst_0
     249: istore        32
     251: iload_2
     252: iload_1
     253: if_icmpeq     284
     256: iload         5
     258: iload         4
     260: isub
     261: bipush        16
     263: ishl
     264: iload_2
     265: iload_1
     266: isub
     267: idiv
     268: istore        31
     270: iload         8
     272: iload         7
     274: isub
     275: bipush        16
     277: ishl
     278: iload_2
     279: iload_1
     280: isub
     281: idiv
     282: istore        32
     284: iconst_0
     285: istore        33
     287: iconst_0
     288: istore        34
     290: iload_2
     291: iload_0
     292: if_icmpeq     322
     295: iload_3
     296: iload         5
     298: isub
     299: bipush        16
     301: ishl
     302: iload_0
     303: iload_2
     304: isub
     305: idiv
     306: istore        33
     308: iload         6
     310: iload         8
     312: isub
     313: bipush        16
     315: ishl
     316: iload_0
     317: iload_2
     318: isub
     319: idiv
     320: istore        34
     322: iload_0
     323: iload_1
     324: if_icmpgt     1571
     327: iload_0
     328: iload_2
     329: if_icmpgt     1571
     332: iload_0
     333: getstatic     #71                 // Field DrawingArea.bottomY:I
     336: if_icmplt     340
     339: return
     340: iload_1
     341: getstatic     #71                 // Field DrawingArea.bottomY:I
     344: if_icmple     351
     347: getstatic     #71                 // Field DrawingArea.bottomY:I
     350: istore_1
     351: iload_2
     352: getstatic     #71                 // Field DrawingArea.bottomY:I
     355: if_icmple     362
     358: getstatic     #71                 // Field DrawingArea.bottomY:I
     361: istore_2
     362: iload_1
     363: iload_2
     364: if_icmpge     972
     367: iload_3
     368: bipush        16
     370: ishl
     371: dup
     372: istore_3
     373: istore        5
     375: iload         6
     377: bipush        16
     379: ishl
     380: dup
     381: istore        6
     383: istore        8
     385: iload_0
     386: ifge          425
     389: iload         5
     391: iload         33
     393: iload_0
     394: imul
     395: isub
     396: istore        5
     398: iload_3
     399: iload         29
     401: iload_0
     402: imul
     403: isub
     404: istore_3
     405: iload         8
     407: iload         34
     409: iload_0
     410: imul
     411: isub
     412: istore        8
     414: iload         6
     416: iload         30
     418: iload_0
     419: imul
     420: isub
     421: istore        6
     423: iconst_0
     424: istore_0
     425: iload         4
     427: bipush        16
     429: ishl
     430: istore        4
     432: iload         7
     434: bipush        16
     436: ishl
     437: istore        7
     439: iload_1
     440: ifge          463
     443: iload         4
     445: iload         31
     447: iload_1
     448: imul
     449: isub
     450: istore        4
     452: iload         7
     454: iload         32
     456: iload_1
     457: imul
     458: isub
     459: istore        7
     461: iconst_0
     462: istore_1
     463: iload_0
     464: getstatic     #18                 // Field textureInt2:I
     467: isub
     468: istore        35
     470: iload         20
     472: iload         22
     474: iload         35
     476: imul
     477: iadd
     478: istore        20
     480: iload         23
     482: iload         25
     484: iload         35
     486: imul
     487: iadd
     488: istore        23
     490: iload         26
     492: iload         28
     494: iload         35
     496: imul
     497: iadd
     498: istore        26
     500: iload_0
     501: iload_1
     502: if_icmpeq     512
     505: iload         33
     507: iload         29
     509: if_icmplt     524
     512: iload_0
     513: iload_1
     514: if_icmpne     748
     517: iload         33
     519: iload         31
     521: if_icmple     748
     524: iload_2
     525: iload_1
     526: isub
     527: istore_2
     528: iload_1
     529: iload_0
     530: isub
     531: istore_1
     532: getstatic     #5                  // Field anIntArray1472:[I
     535: iload_0
     536: iaload
     537: istore_0
     538: iinc          1, -1
     541: iload_1
     542: iflt          641
     545: getstatic     #72                 // Field DrawingArea.pixels:[I
     548: aload         19
     550: iload_0
     551: iload         5
     553: bipush        16
     555: ishr
     556: iload_3
     557: bipush        16
     559: ishr
     560: iload         8
     562: bipush        8
     564: ishr
     565: iload         6
     567: bipush        8
     569: ishr
     570: iload         20
     572: iload         23
     574: iload         26
     576: iload         21
     578: iload         24
     580: iload         27
     582: invokestatic  #83                 // Method method379:([I[IIIIIIIIIIII)V
     585: iload         5
     587: iload         33
     589: iadd
     590: istore        5
     592: iload_3
     593: iload         29
     595: iadd
     596: istore_3
     597: iload         8
     599: iload         34
     601: iadd
     602: istore        8
     604: iload         6
     606: iload         30
     608: iadd
     609: istore        6
     611: iload_0
     612: getstatic     #16                 // Field DrawingArea.width:I
     615: iadd
     616: istore_0
     617: iload         20
     619: iload         22
     621: iadd
     622: istore        20
     624: iload         23
     626: iload         25
     628: iadd
     629: istore        23
     631: iload         26
     633: iload         28
     635: iadd
     636: istore        26
     638: goto          538
     641: iinc          2, -1
     644: iload_2
     645: iflt          747
     648: getstatic     #72                 // Field DrawingArea.pixels:[I
     651: aload         19
     653: iload_0
     654: iload         5
     656: bipush        16
     658: ishr
     659: iload         4
     661: bipush        16
     663: ishr
     664: iload         8
     666: bipush        8
     668: ishr
     669: iload         7
     671: bipush        8
     673: ishr
     674: iload         20
     676: iload         23
     678: iload         26
     680: iload         21
     682: iload         24
     684: iload         27
     686: invokestatic  #83                 // Method method379:([I[IIIIIIIIIIII)V
     689: iload         5
     691: iload         33
     693: iadd
     694: istore        5
     696: iload         4
     698: iload         31
     700: iadd
     701: istore        4
     703: iload         8
     705: iload         34
     707: iadd
     708: istore        8
     710: iload         7
     712: iload         32
     714: iadd
     715: istore        7
     717: iload_0
     718: getstatic     #16                 // Field DrawingArea.width:I
     721: iadd
     722: istore_0
     723: iload         20
     725: iload         22
     727: iadd
     728: istore        20
     730: iload         23
     732: iload         25
     734: iadd
     735: istore        23
     737: iload         26
     739: iload         28
     741: iadd
     742: istore        26
     744: goto          641
     747: return
     748: iload_2
     749: iload_1
     750: isub
     751: istore_2
     752: iload_1
     753: iload_0
     754: isub
     755: istore_1
     756: getstatic     #5                  // Field anIntArray1472:[I
     759: iload_0
     760: iaload
     761: istore_0
     762: iinc          1, -1
     765: iload_1
     766: iflt          865
     769: getstatic     #72                 // Field DrawingArea.pixels:[I
     772: aload         19
     774: iload_0
     775: iload_3
     776: bipush        16
     778: ishr
     779: iload         5
     781: bipush        16
     783: ishr
     784: iload         6
     786: bipush        8
     788: ishr
     789: iload         8
     791: bipush        8
     793: ishr
     794: iload         20
     796: iload         23
     798: iload         26
     800: iload         21
     802: iload         24
     804: iload         27
     806: invokestatic  #83                 // Method method379:([I[IIIIIIIIIIII)V
     809: iload         5
     811: iload         33
     813: iadd
     814: istore        5
     816: iload_3
     817: iload         29
     819: iadd
     820: istore_3
     821: iload         8
     823: iload         34
     825: iadd
     826: istore        8
     828: iload         6
     830: iload         30
     832: iadd
     833: istore        6
     835: iload_0
     836: getstatic     #16                 // Field DrawingArea.width:I
     839: iadd
     840: istore_0
     841: iload         20
     843: iload         22
     845: iadd
     846: istore        20
     848: iload         23
     850: iload         25
     852: iadd
     853: istore        23
     855: iload         26
     857: iload         28
     859: iadd
     860: istore        26
     862: goto          762
     865: iinc          2, -1
     868: iload_2
     869: iflt          971
     872: getstatic     #72                 // Field DrawingArea.pixels:[I
     875: aload         19
     877: iload_0
     878: iload         4
     880: bipush        16
     882: ishr
     883: iload         5
     885: bipush        16
     887: ishr
     888: iload         7
     890: bipush        8
     892: ishr
     893: iload         8
     895: bipush        8
     897: ishr
     898: iload         20
     900: iload         23
     902: iload         26
     904: iload         21
     906: iload         24
     908: iload         27
     910: invokestatic  #83                 // Method method379:([I[IIIIIIIIIIII)V
     913: iload         5
     915: iload         33
     917: iadd
     918: istore        5
     920: iload         4
     922: iload         31
     924: iadd
     925: istore        4
     927: iload         8
     929: iload         34
     931: iadd
     932: istore        8
     934: iload         7
     936: iload         32
     938: iadd
     939: istore        7
     941: iload_0
     942: getstatic     #16                 // Field DrawingArea.width:I
     945: iadd
     946: istore_0
     947: iload         20
     949: iload         22
     951: iadd
     952: istore        20
     954: iload         23
     956: iload         25
     958: iadd
     959: istore        23
     961: iload         26
     963: iload         28
     965: iadd
     966: istore        26
     968: goto          865
     971: return
     972: iload_3
     973: bipush        16
     975: ishl
     976: dup
     977: istore_3
     978: istore        4
     980: iload         6
     982: bipush        16
     984: ishl
     985: dup
     986: istore        6
     988: istore        7
     990: iload_0
     991: ifge          1030
     994: iload         4
     996: iload         33
     998: iload_0
     999: imul
    1000: isub
    1001: istore        4
    1003: iload_3
    1004: iload         29
    1006: iload_0
    1007: imul
    1008: isub
    1009: istore_3
    1010: iload         7
    1012: iload         34
    1014: iload_0
    1015: imul
    1016: isub
    1017: istore        7
    1019: iload         6
    1021: iload         30
    1023: iload_0
    1024: imul
    1025: isub
    1026: istore        6
    1028: iconst_0
    1029: istore_0
    1030: iload         5
    1032: bipush        16
    1034: ishl
    1035: istore        5
    1037: iload         8
    1039: bipush        16
    1041: ishl
    1042: istore        8
    1044: iload_2
    1045: ifge          1068
    1048: iload         5
    1050: iload         31
    1052: iload_2
    1053: imul
    1054: isub
    1055: istore        5
    1057: iload         8
    1059: iload         32
    1061: iload_2
    1062: imul
    1063: isub
    1064: istore        8
    1066: iconst_0
    1067: istore_2
    1068: iload_0
    1069: getstatic     #18                 // Field textureInt2:I
    1072: isub
    1073: istore        35
    1075: iload         20
    1077: iload         22
    1079: iload         35
    1081: imul
    1082: iadd
    1083: istore        20
    1085: iload         23
    1087: iload         25
    1089: iload         35
    1091: imul
    1092: iadd
    1093: istore        23
    1095: iload         26
    1097: iload         28
    1099: iload         35
    1101: imul
    1102: iadd
    1103: istore        26
    1105: iload_0
    1106: iload_2
    1107: if_icmpeq     1117
    1110: iload         33
    1112: iload         29
    1114: if_icmplt     1129
    1117: iload_0
    1118: iload_2
    1119: if_icmpne     1350
    1122: iload         31
    1124: iload         29
    1126: if_icmple     1350
    1129: iload_1
    1130: iload_2
    1131: isub
    1132: istore_1
    1133: iload_2
    1134: iload_0
    1135: isub
    1136: istore_2
    1137: getstatic     #5                  // Field anIntArray1472:[I
    1140: iload_0
    1141: iaload
    1142: istore_0
    1143: iinc          2, -1
    1146: iload_2
    1147: iflt          1246
    1150: getstatic     #72                 // Field DrawingArea.pixels:[I
    1153: aload         19
    1155: iload_0
    1156: iload         4
    1158: bipush        16
    1160: ishr
    1161: iload_3
    1162: bipush        16
    1164: ishr
    1165: iload         7
    1167: bipush        8
    1169: ishr
    1170: iload         6
    1172: bipush        8
    1174: ishr
    1175: iload         20
    1177: iload         23
    1179: iload         26
    1181: iload         21
    1183: iload         24
    1185: iload         27
    1187: invokestatic  #83                 // Method method379:([I[IIIIIIIIIIII)V
    1190: iload         4
    1192: iload         33
    1194: iadd
    1195: istore        4
    1197: iload_3
    1198: iload         29
    1200: iadd
    1201: istore_3
    1202: iload         7
    1204: iload         34
    1206: iadd
    1207: istore        7
    1209: iload         6
    1211: iload         30
    1213: iadd
    1214: istore        6
    1216: iload_0
    1217: getstatic     #16                 // Field DrawingArea.width:I
    1220: iadd
    1221: istore_0
    1222: iload         20
    1224: iload         22
    1226: iadd
    1227: istore        20
    1229: iload         23
    1231: iload         25
    1233: iadd
    1234: istore        23
    1236: iload         26
    1238: iload         28
    1240: iadd
    1241: istore        26
    1243: goto          1143
    1246: iinc          1, -1
    1249: iload_1
    1250: iflt          1349
    1253: getstatic     #72                 // Field DrawingArea.pixels:[I
    1256: aload         19
    1258: iload_0
    1259: iload         5
    1261: bipush        16
    1263: ishr
    1264: iload_3
    1265: bipush        16
    1267: ishr
    1268: iload         8
    1270: bipush        8
    1272: ishr
    1273: iload         6
    1275: bipush        8
    1277: ishr
    1278: iload         20
    1280: iload         23
    1282: iload         26
    1284: iload         21
    1286: iload         24
    1288: iload         27
    1290: invokestatic  #83                 // Method method379:([I[IIIIIIIIIIII)V
    1293: iload         5
    1295: iload         31
    1297: iadd
    1298: istore        5
    1300: iload_3
    1301: iload         29
    1303: iadd
    1304: istore_3
    1305: iload         8
    1307: iload         32
    1309: iadd
    1310: istore        8
    1312: iload         6
    1314: iload         30
    1316: iadd
    1317: istore        6
    1319: iload_0
    1320: getstatic     #16                 // Field DrawingArea.width:I
    1323: iadd
    1324: istore_0
    1325: iload         20
    1327: iload         22
    1329: iadd
    1330: istore        20
    1332: iload         23
    1334: iload         25
    1336: iadd
    1337: istore        23
    1339: iload         26
    1341: iload         28
    1343: iadd
    1344: istore        26
    1346: goto          1246
    1349: return
    1350: iload_1
    1351: iload_2
    1352: isub
    1353: istore_1
    1354: iload_2
    1355: iload_0
    1356: isub
    1357: istore_2
    1358: getstatic     #5                  // Field anIntArray1472:[I
    1361: iload_0
    1362: iaload
    1363: istore_0
    1364: iinc          2, -1
    1367: iload_2
    1368: iflt          1467
    1371: getstatic     #72                 // Field DrawingArea.pixels:[I
    1374: aload         19
    1376: iload_0
    1377: iload_3
    1378: bipush        16
    1380: ishr
    1381: iload         4
    1383: bipush        16
    1385: ishr
    1386: iload         6
    1388: bipush        8
    1390: ishr
    1391: iload         7
    1393: bipush        8
    1395: ishr
    1396: iload         20
    1398: iload         23
    1400: iload         26
    1402: iload         21
    1404: iload         24
    1406: iload         27
    1408: invokestatic  #83                 // Method method379:([I[IIIIIIIIIIII)V
    1411: iload         4
    1413: iload         33
    1415: iadd
    1416: istore        4
    1418: iload_3
    1419: iload         29
    1421: iadd
    1422: istore_3
    1423: iload         7
    1425: iload         34
    1427: iadd
    1428: istore        7
    1430: iload         6
    1432: iload         30
    1434: iadd
    1435: istore        6
    1437: iload_0
    1438: getstatic     #16                 // Field DrawingArea.width:I
    1441: iadd
    1442: istore_0
    1443: iload         20
    1445: iload         22
    1447: iadd
    1448: istore        20
    1450: iload         23
    1452: iload         25
    1454: iadd
    1455: istore        23
    1457: iload         26
    1459: iload         28
    1461: iadd
    1462: istore        26
    1464: goto          1364
    1467: iinc          1, -1
    1470: iload_1
    1471: iflt          1570
    1474: getstatic     #72                 // Field DrawingArea.pixels:[I
    1477: aload         19
    1479: iload_0
    1480: iload_3
    1481: bipush        16
    1483: ishr
    1484: iload         5
    1486: bipush        16
    1488: ishr
    1489: iload         6
    1491: bipush        8
    1493: ishr
    1494: iload         8
    1496: bipush        8
    1498: ishr
    1499: iload         20
    1501: iload         23
    1503: iload         26
    1505: iload         21
    1507: iload         24
    1509: iload         27
    1511: invokestatic  #83                 // Method method379:([I[IIIIIIIIIIII)V
    1514: iload         5
    1516: iload         31
    1518: iadd
    1519: istore        5
    1521: iload_3
    1522: iload         29
    1524: iadd
    1525: istore_3
    1526: iload         8
    1528: iload         32
    1530: iadd
    1531: istore        8
    1533: iload         6
    1535: iload         30
    1537: iadd
    1538: istore        6
    1540: iload_0
    1541: getstatic     #16                 // Field DrawingArea.width:I
    1544: iadd
    1545: istore_0
    1546: iload         20
    1548: iload         22
    1550: iadd
    1551: istore        20
    1553: iload         23
    1555: iload         25
    1557: iadd
    1558: istore        23
    1560: iload         26
    1562: iload         28
    1564: iadd
    1565: istore        26
    1567: goto          1467
    1570: return
    1571: iload_1
    1572: iload_2
    1573: if_icmpgt     2799
    1576: iload_1
    1577: getstatic     #71                 // Field DrawingArea.bottomY:I
    1580: if_icmplt     1584
    1583: return
    1584: iload_2
    1585: getstatic     #71                 // Field DrawingArea.bottomY:I
    1588: if_icmple     1595
    1591: getstatic     #71                 // Field DrawingArea.bottomY:I
    1594: istore_2
    1595: iload_0
    1596: getstatic     #71                 // Field DrawingArea.bottomY:I
    1599: if_icmple     1606
    1602: getstatic     #71                 // Field DrawingArea.bottomY:I
    1605: istore_0
    1606: iload_2
    1607: iload_0
    1608: if_icmpge     2211
    1611: iload         4
    1613: bipush        16
    1615: ishl
    1616: dup
    1617: istore        4
    1619: istore_3
    1620: iload         7
    1622: bipush        16
    1624: ishl
    1625: dup
    1626: istore        7
    1628: istore        6
    1630: iload_1
    1631: ifge          1670
    1634: iload_3
    1635: iload         29
    1637: iload_1
    1638: imul
    1639: isub
    1640: istore_3
    1641: iload         4
    1643: iload         31
    1645: iload_1
    1646: imul
    1647: isub
    1648: istore        4
    1650: iload         6
    1652: iload         30
    1654: iload_1
    1655: imul
    1656: isub
    1657: istore        6
    1659: iload         7
    1661: iload         32
    1663: iload_1
    1664: imul
    1665: isub
    1666: istore        7
    1668: iconst_0
    1669: istore_1
    1670: iload         5
    1672: bipush        16
    1674: ishl
    1675: istore        5
    1677: iload         8
    1679: bipush        16
    1681: ishl
    1682: istore        8
    1684: iload_2
    1685: ifge          1708
    1688: iload         5
    1690: iload         33
    1692: iload_2
    1693: imul
    1694: isub
    1695: istore        5
    1697: iload         8
    1699: iload         34
    1701: iload_2
    1702: imul
    1703: isub
    1704: istore        8
    1706: iconst_0
    1707: istore_2
    1708: iload_1
    1709: getstatic     #18                 // Field textureInt2:I
    1712: isub
    1713: istore        35
    1715: iload         20
    1717: iload         22
    1719: iload         35
    1721: imul
    1722: iadd
    1723: istore        20
    1725: iload         23
    1727: iload         25
    1729: iload         35
    1731: imul
    1732: iadd
    1733: istore        23
    1735: iload         26
    1737: iload         28
    1739: iload         35
    1741: imul
    1742: iadd
    1743: istore        26
    1745: iload_1
    1746: iload_2
    1747: if_icmpeq     1757
    1750: iload         29
    1752: iload         31
    1754: if_icmplt     1769
    1757: iload_1
    1758: iload_2
    1759: if_icmpne     1990
    1762: iload         29
    1764: iload         33
    1766: if_icmple     1990
    1769: iload_0
    1770: iload_2
    1771: isub
    1772: istore_0
    1773: iload_2
    1774: iload_1
    1775: isub
    1776: istore_2
    1777: getstatic     #5                  // Field anIntArray1472:[I
    1780: iload_1
    1781: iaload
    1782: istore_1
    1783: iinc          2, -1
    1786: iload_2
    1787: iflt          1886
    1790: getstatic     #72                 // Field DrawingArea.pixels:[I
    1793: aload         19
    1795: iload_1
    1796: iload_3
    1797: bipush        16
    1799: ishr
    1800: iload         4
    1802: bipush        16
    1804: ishr
    1805: iload         6
    1807: bipush        8
    1809: ishr
    1810: iload         7
    1812: bipush        8
    1814: ishr
    1815: iload         20
    1817: iload         23
    1819: iload         26
    1821: iload         21
    1823: iload         24
    1825: iload         27
    1827: invokestatic  #83                 // Method method379:([I[IIIIIIIIIIII)V
    1830: iload_3
    1831: iload         29
    1833: iadd
    1834: istore_3
    1835: iload         4
    1837: iload         31
    1839: iadd
    1840: istore        4
    1842: iload         6
    1844: iload         30
    1846: iadd
    1847: istore        6
    1849: iload         7
    1851: iload         32
    1853: iadd
    1854: istore        7
    1856: iload_1
    1857: getstatic     #16                 // Field DrawingArea.width:I
    1860: iadd
    1861: istore_1
    1862: iload         20
    1864: iload         22
    1866: iadd
    1867: istore        20
    1869: iload         23
    1871: iload         25
    1873: iadd
    1874: istore        23
    1876: iload         26
    1878: iload         28
    1880: iadd
    1881: istore        26
    1883: goto          1783
    1886: iinc          0, -1
    1889: iload_0
    1890: iflt          1989
    1893: getstatic     #72                 // Field DrawingArea.pixels:[I
    1896: aload         19
    1898: iload_1
    1899: iload_3
    1900: bipush        16
    1902: ishr
    1903: iload         5
    1905: bipush        16
    1907: ishr
    1908: iload         6
    1910: bipush        8
    1912: ishr
    1913: iload         8
    1915: bipush        8
    1917: ishr
    1918: iload         20
    1920: iload         23
    1922: iload         26
    1924: iload         21
    1926: iload         24
    1928: iload         27
    1930: invokestatic  #83                 // Method method379:([I[IIIIIIIIIIII)V
    1933: iload_3
    1934: iload         29
    1936: iadd
    1937: istore_3
    1938: iload         5
    1940: iload         33
    1942: iadd
    1943: istore        5
    1945: iload         6
    1947: iload         30
    1949: iadd
    1950: istore        6
    1952: iload         8
    1954: iload         34
    1956: iadd
    1957: istore        8
    1959: iload_1
    1960: getstatic     #16                 // Field DrawingArea.width:I
    1963: iadd
    1964: istore_1
    1965: iload         20
    1967: iload         22
    1969: iadd
    1970: istore        20
    1972: iload         23
    1974: iload         25
    1976: iadd
    1977: istore        23
    1979: iload         26
    1981: iload         28
    1983: iadd
    1984: istore        26
    1986: goto          1886
    1989: return
    1990: iload_0
    1991: iload_2
    1992: isub
    1993: istore_0
    1994: iload_2
    1995: iload_1
    1996: isub
    1997: istore_2
    1998: getstatic     #5                  // Field anIntArray1472:[I
    2001: iload_1
    2002: iaload
    2003: istore_1
    2004: iinc          2, -1
    2007: iload_2
    2008: iflt          2107
    2011: getstatic     #72                 // Field DrawingArea.pixels:[I
    2014: aload         19
    2016: iload_1
    2017: iload         4
    2019: bipush        16
    2021: ishr
    2022: iload_3
    2023: bipush        16
    2025: ishr
    2026: iload         7
    2028: bipush        8
    2030: ishr
    2031: iload         6
    2033: bipush        8
    2035: ishr
    2036: iload         20
    2038: iload         23
    2040: iload         26
    2042: iload         21
    2044: iload         24
    2046: iload         27
    2048: invokestatic  #83                 // Method method379:([I[IIIIIIIIIIII)V
    2051: iload_3
    2052: iload         29
    2054: iadd
    2055: istore_3
    2056: iload         4
    2058: iload         31
    2060: iadd
    2061: istore        4
    2063: iload         6
    2065: iload         30
    2067: iadd
    2068: istore        6
    2070: iload         7
    2072: iload         32
    2074: iadd
    2075: istore        7
    2077: iload_1
    2078: getstatic     #16                 // Field DrawingArea.width:I
    2081: iadd
    2082: istore_1
    2083: iload         20
    2085: iload         22
    2087: iadd
    2088: istore        20
    2090: iload         23
    2092: iload         25
    2094: iadd
    2095: istore        23
    2097: iload         26
    2099: iload         28
    2101: iadd
    2102: istore        26
    2104: goto          2004
    2107: iinc          0, -1
    2110: iload_0
    2111: iflt          2210
    2114: getstatic     #72                 // Field DrawingArea.pixels:[I
    2117: aload         19
    2119: iload_1
    2120: iload         5
    2122: bipush        16
    2124: ishr
    2125: iload_3
    2126: bipush        16
    2128: ishr
    2129: iload         8
    2131: bipush        8
    2133: ishr
    2134: iload         6
    2136: bipush        8
    2138: ishr
    2139: iload         20
    2141: iload         23
    2143: iload         26
    2145: iload         21
    2147: iload         24
    2149: iload         27
    2151: invokestatic  #83                 // Method method379:([I[IIIIIIIIIIII)V
    2154: iload_3
    2155: iload         29
    2157: iadd
    2158: istore_3
    2159: iload         5
    2161: iload         33
    2163: iadd
    2164: istore        5
    2166: iload         6
    2168: iload         30
    2170: iadd
    2171: istore        6
    2173: iload         8
    2175: iload         34
    2177: iadd
    2178: istore        8
    2180: iload_1
    2181: getstatic     #16                 // Field DrawingArea.width:I
    2184: iadd
    2185: istore_1
    2186: iload         20
    2188: iload         22
    2190: iadd
    2191: istore        20
    2193: iload         23
    2195: iload         25
    2197: iadd
    2198: istore        23
    2200: iload         26
    2202: iload         28
    2204: iadd
    2205: istore        26
    2207: goto          2107
    2210: return
    2211: iload         4
    2213: bipush        16
    2215: ishl
    2216: dup
    2217: istore        4
    2219: istore        5
    2221: iload         7
    2223: bipush        16
    2225: ishl
    2226: dup
    2227: istore        7
    2229: istore        8
    2231: iload_1
    2232: ifge          2273
    2235: iload         5
    2237: iload         29
    2239: iload_1
    2240: imul
    2241: isub
    2242: istore        5
    2244: iload         4
    2246: iload         31
    2248: iload_1
    2249: imul
    2250: isub
    2251: istore        4
    2253: iload         8
    2255: iload         30
    2257: iload_1
    2258: imul
    2259: isub
    2260: istore        8
    2262: iload         7
    2264: iload         32
    2266: iload_1
    2267: imul
    2268: isub
    2269: istore        7
    2271: iconst_0
    2272: istore_1
    2273: iload_3
    2274: bipush        16
    2276: ishl
    2277: istore_3
    2278: iload         6
    2280: bipush        16
    2282: ishl
    2283: istore        6
    2285: iload_0
    2286: ifge          2307
    2289: iload_3
    2290: iload         33
    2292: iload_0
    2293: imul
    2294: isub
    2295: istore_3
    2296: iload         6
    2298: iload         34
    2300: iload_0
    2301: imul
    2302: isub
    2303: istore        6
    2305: iconst_0
    2306: istore_0
    2307: iload_1
    2308: getstatic     #18                 // Field textureInt2:I
    2311: isub
    2312: istore        35
    2314: iload         20
    2316: iload         22
    2318: iload         35
    2320: imul
    2321: iadd
    2322: istore        20
    2324: iload         23
    2326: iload         25
    2328: iload         35
    2330: imul
    2331: iadd
    2332: istore        23
    2334: iload         26
    2336: iload         28
    2338: iload         35
    2340: imul
    2341: iadd
    2342: istore        26
    2344: iload         29
    2346: iload         31
    2348: if_icmpge     2575
    2351: iload_2
    2352: iload_0
    2353: isub
    2354: istore_2
    2355: iload_0
    2356: iload_1
    2357: isub
    2358: istore_0
    2359: getstatic     #5                  // Field anIntArray1472:[I
    2362: iload_1
    2363: iaload
    2364: istore_1
    2365: iinc          0, -1
    2368: iload_0
    2369: iflt          2471
    2372: getstatic     #72                 // Field DrawingArea.pixels:[I
    2375: aload         19
    2377: iload_1
    2378: iload         5
    2380: bipush        16
    2382: ishr
    2383: iload         4
    2385: bipush        16
    2387: ishr
    2388: iload         8
    2390: bipush        8
    2392: ishr
    2393: iload         7
    2395: bipush        8
    2397: ishr
    2398: iload         20
    2400: iload         23
    2402: iload         26
    2404: iload         21
    2406: iload         24
    2408: iload         27
    2410: invokestatic  #83                 // Method method379:([I[IIIIIIIIIIII)V
    2413: iload         5
    2415: iload         29
    2417: iadd
    2418: istore        5
    2420: iload         4
    2422: iload         31
    2424: iadd
    2425: istore        4
    2427: iload         8
    2429: iload         30
    2431: iadd
    2432: istore        8
    2434: iload         7
    2436: iload         32
    2438: iadd
    2439: istore        7
    2441: iload_1
    2442: getstatic     #16                 // Field DrawingArea.width:I
    2445: iadd
    2446: istore_1
    2447: iload         20
    2449: iload         22
    2451: iadd
    2452: istore        20
    2454: iload         23
    2456: iload         25
    2458: iadd
    2459: istore        23
    2461: iload         26
    2463: iload         28
    2465: iadd
    2466: istore        26
    2468: goto          2365
    2471: iinc          2, -1
    2474: iload_2
    2475: iflt          2574
    2478: getstatic     #72                 // Field DrawingArea.pixels:[I
    2481: aload         19
    2483: iload_1
    2484: iload_3
    2485: bipush        16
    2487: ishr
    2488: iload         4
    2490: bipush        16
    2492: ishr
    2493: iload         6
    2495: bipush        8
    2497: ishr
    2498: iload         7
    2500: bipush        8
    2502: ishr
    2503: iload         20
    2505: iload         23
    2507: iload         26
    2509: iload         21
    2511: iload         24
    2513: iload         27
    2515: invokestatic  #83                 // Method method379:([I[IIIIIIIIIIII)V
    2518: iload_3
    2519: iload         33
    2521: iadd
    2522: istore_3
    2523: iload         4
    2525: iload         31
    2527: iadd
    2528: istore        4
    2530: iload         6
    2532: iload         34
    2534: iadd
    2535: istore        6
    2537: iload         7
    2539: iload         32
    2541: iadd
    2542: istore        7
    2544: iload_1
    2545: getstatic     #16                 // Field DrawingArea.width:I
    2548: iadd
    2549: istore_1
    2550: iload         20
    2552: iload         22
    2554: iadd
    2555: istore        20
    2557: iload         23
    2559: iload         25
    2561: iadd
    2562: istore        23
    2564: iload         26
    2566: iload         28
    2568: iadd
    2569: istore        26
    2571: goto          2471
    2574: return
    2575: iload_2
    2576: iload_0
    2577: isub
    2578: istore_2
    2579: iload_0
    2580: iload_1
    2581: isub
    2582: istore_0
    2583: getstatic     #5                  // Field anIntArray1472:[I
    2586: iload_1
    2587: iaload
    2588: istore_1
    2589: iinc          0, -1
    2592: iload_0
    2593: iflt          2695
    2596: getstatic     #72                 // Field DrawingArea.pixels:[I
    2599: aload         19
    2601: iload_1
    2602: iload         4
    2604: bipush        16
    2606: ishr
    2607: iload         5
    2609: bipush        16
    2611: ishr
    2612: iload         7
    2614: bipush        8
    2616: ishr
    2617: iload         8
    2619: bipush        8
    2621: ishr
    2622: iload         20
    2624: iload         23
    2626: iload         26
    2628: iload         21
    2630: iload         24
    2632: iload         27
    2634: invokestatic  #83                 // Method method379:([I[IIIIIIIIIIII)V
    2637: iload         5
    2639: iload         29
    2641: iadd
    2642: istore        5
    2644: iload         4
    2646: iload         31
    2648: iadd
    2649: istore        4
    2651: iload         8
    2653: iload         30
    2655: iadd
    2656: istore        8
    2658: iload         7
    2660: iload         32
    2662: iadd
    2663: istore        7
    2665: iload_1
    2666: getstatic     #16                 // Field DrawingArea.width:I
    2669: iadd
    2670: istore_1
    2671: iload         20
    2673: iload         22
    2675: iadd
    2676: istore        20
    2678: iload         23
    2680: iload         25
    2682: iadd
    2683: istore        23
    2685: iload         26
    2687: iload         28
    2689: iadd
    2690: istore        26
    2692: goto          2589
    2695: iinc          2, -1
    2698: iload_2
    2699: iflt          2798
    2702: getstatic     #72                 // Field DrawingArea.pixels:[I
    2705: aload         19
    2707: iload_1
    2708: iload         4
    2710: bipush        16
    2712: ishr
    2713: iload_3
    2714: bipush        16
    2716: ishr
    2717: iload         7
    2719: bipush        8
    2721: ishr
    2722: iload         6
    2724: bipush        8
    2726: ishr
    2727: iload         20
    2729: iload         23
    2731: iload         26
    2733: iload         21
    2735: iload         24
    2737: iload         27
    2739: invokestatic  #83                 // Method method379:([I[IIIIIIIIIIII)V
    2742: iload_3
    2743: iload         33
    2745: iadd
    2746: istore_3
    2747: iload         4
    2749: iload         31
    2751: iadd
    2752: istore        4
    2754: iload         6
    2756: iload         34
    2758: iadd
    2759: istore        6
    2761: iload         7
    2763: iload         32
    2765: iadd
    2766: istore        7
    2768: iload_1
    2769: getstatic     #16                 // Field DrawingArea.width:I
    2772: iadd
    2773: istore_1
    2774: iload         20
    2776: iload         22
    2778: iadd
    2779: istore        20
    2781: iload         23
    2783: iload         25
    2785: iadd
    2786: istore        23
    2788: iload         26
    2790: iload         28
    2792: iadd
    2793: istore        26
    2795: goto          2695
    2798: return
    2799: iload_2
    2800: getstatic     #71                 // Field DrawingArea.bottomY:I
    2803: if_icmplt     2807
    2806: return
    2807: iload_0
    2808: getstatic     #71                 // Field DrawingArea.bottomY:I
    2811: if_icmple     2818
    2814: getstatic     #71                 // Field DrawingArea.bottomY:I
    2817: istore_0
    2818: iload_1
    2819: getstatic     #71                 // Field DrawingArea.bottomY:I
    2822: if_icmple     2829
    2825: getstatic     #71                 // Field DrawingArea.bottomY:I
    2828: istore_1
    2829: iload_0
    2830: iload_1
    2831: if_icmpge     3422
    2834: iload         5
    2836: bipush        16
    2838: ishl
    2839: dup
    2840: istore        5
    2842: istore        4
    2844: iload         8
    2846: bipush        16
    2848: ishl
    2849: dup
    2850: istore        8
    2852: istore        7
    2854: iload_2
    2855: ifge          2896
    2858: iload         4
    2860: iload         31
    2862: iload_2
    2863: imul
    2864: isub
    2865: istore        4
    2867: iload         5
    2869: iload         33
    2871: iload_2
    2872: imul
    2873: isub
    2874: istore        5
    2876: iload         7
    2878: iload         32
    2880: iload_2
    2881: imul
    2882: isub
    2883: istore        7
    2885: iload         8
    2887: iload         34
    2889: iload_2
    2890: imul
    2891: isub
    2892: istore        8
    2894: iconst_0
    2895: istore_2
    2896: iload_3
    2897: bipush        16
    2899: ishl
    2900: istore_3
    2901: iload         6
    2903: bipush        16
    2905: ishl
    2906: istore        6
    2908: iload_0
    2909: ifge          2930
    2912: iload_3
    2913: iload         29
    2915: iload_0
    2916: imul
    2917: isub
    2918: istore_3
    2919: iload         6
    2921: iload         30
    2923: iload_0
    2924: imul
    2925: isub
    2926: istore        6
    2928: iconst_0
    2929: istore_0
    2930: iload_2
    2931: getstatic     #18                 // Field textureInt2:I
    2934: isub
    2935: istore        35
    2937: iload         20
    2939: iload         22
    2941: iload         35
    2943: imul
    2944: iadd
    2945: istore        20
    2947: iload         23
    2949: iload         25
    2951: iload         35
    2953: imul
    2954: iadd
    2955: istore        23
    2957: iload         26
    2959: iload         28
    2961: iload         35
    2963: imul
    2964: iadd
    2965: istore        26
    2967: iload         31
    2969: iload         33
    2971: if_icmpge     3198
    2974: iload_1
    2975: iload_0
    2976: isub
    2977: istore_1
    2978: iload_0
    2979: iload_2
    2980: isub
    2981: istore_0
    2982: getstatic     #5                  // Field anIntArray1472:[I
    2985: iload_2
    2986: iaload
    2987: istore_2
    2988: iinc          0, -1
    2991: iload_0
    2992: iflt          3094
    2995: getstatic     #72                 // Field DrawingArea.pixels:[I
    2998: aload         19
    3000: iload_2
    3001: iload         4
    3003: bipush        16
    3005: ishr
    3006: iload         5
    3008: bipush        16
    3010: ishr
    3011: iload         7
    3013: bipush        8
    3015: ishr
    3016: iload         8
    3018: bipush        8
    3020: ishr
    3021: iload         20
    3023: iload         23
    3025: iload         26
    3027: iload         21
    3029: iload         24
    3031: iload         27
    3033: invokestatic  #83                 // Method method379:([I[IIIIIIIIIIII)V
    3036: iload         4
    3038: iload         31
    3040: iadd
    3041: istore        4
    3043: iload         5
    3045: iload         33
    3047: iadd
    3048: istore        5
    3050: iload         7
    3052: iload         32
    3054: iadd
    3055: istore        7
    3057: iload         8
    3059: iload         34
    3061: iadd
    3062: istore        8
    3064: iload_2
    3065: getstatic     #16                 // Field DrawingArea.width:I
    3068: iadd
    3069: istore_2
    3070: iload         20
    3072: iload         22
    3074: iadd
    3075: istore        20
    3077: iload         23
    3079: iload         25
    3081: iadd
    3082: istore        23
    3084: iload         26
    3086: iload         28
    3088: iadd
    3089: istore        26
    3091: goto          2988
    3094: iinc          1, -1
    3097: iload_1
    3098: iflt          3197
    3101: getstatic     #72                 // Field DrawingArea.pixels:[I
    3104: aload         19
    3106: iload_2
    3107: iload         4
    3109: bipush        16
    3111: ishr
    3112: iload_3
    3113: bipush        16
    3115: ishr
    3116: iload         7
    3118: bipush        8
    3120: ishr
    3121: iload         6
    3123: bipush        8
    3125: ishr
    3126: iload         20
    3128: iload         23
    3130: iload         26
    3132: iload         21
    3134: iload         24
    3136: iload         27
    3138: invokestatic  #83                 // Method method379:([I[IIIIIIIIIIII)V
    3141: iload         4
    3143: iload         31
    3145: iadd
    3146: istore        4
    3148: iload_3
    3149: iload         29
    3151: iadd
    3152: istore_3
    3153: iload         7
    3155: iload         32
    3157: iadd
    3158: istore        7
    3160: iload         6
    3162: iload         30
    3164: iadd
    3165: istore        6
    3167: iload_2
    3168: getstatic     #16                 // Field DrawingArea.width:I
    3171: iadd
    3172: istore_2
    3173: iload         20
    3175: iload         22
    3177: iadd
    3178: istore        20
    3180: iload         23
    3182: iload         25
    3184: iadd
    3185: istore        23
    3187: iload         26
    3189: iload         28
    3191: iadd
    3192: istore        26
    3194: goto          3094
    3197: return
    3198: iload_1
    3199: iload_0
    3200: isub
    3201: istore_1
    3202: iload_0
    3203: iload_2
    3204: isub
    3205: istore_0
    3206: getstatic     #5                  // Field anIntArray1472:[I
    3209: iload_2
    3210: iaload
    3211: istore_2
    3212: iinc          0, -1
    3215: iload_0
    3216: iflt          3318
    3219: getstatic     #72                 // Field DrawingArea.pixels:[I
    3222: aload         19
    3224: iload_2
    3225: iload         5
    3227: bipush        16
    3229: ishr
    3230: iload         4
    3232: bipush        16
    3234: ishr
    3235: iload         8
    3237: bipush        8
    3239: ishr
    3240: iload         7
    3242: bipush        8
    3244: ishr
    3245: iload         20
    3247: iload         23
    3249: iload         26
    3251: iload         21
    3253: iload         24
    3255: iload         27
    3257: invokestatic  #83                 // Method method379:([I[IIIIIIIIIIII)V
    3260: iload         4
    3262: iload         31
    3264: iadd
    3265: istore        4
    3267: iload         5
    3269: iload         33
    3271: iadd
    3272: istore        5
    3274: iload         7
    3276: iload         32
    3278: iadd
    3279: istore        7
    3281: iload         8
    3283: iload         34
    3285: iadd
    3286: istore        8
    3288: iload_2
    3289: getstatic     #16                 // Field DrawingArea.width:I
    3292: iadd
    3293: istore_2
    3294: iload         20
    3296: iload         22
    3298: iadd
    3299: istore        20
    3301: iload         23
    3303: iload         25
    3305: iadd
    3306: istore        23
    3308: iload         26
    3310: iload         28
    3312: iadd
    3313: istore        26
    3315: goto          3212
    3318: iinc          1, -1
    3321: iload_1
    3322: iflt          3421
    3325: getstatic     #72                 // Field DrawingArea.pixels:[I
    3328: aload         19
    3330: iload_2
    3331: iload_3
    3332: bipush        16
    3334: ishr
    3335: iload         4
    3337: bipush        16
    3339: ishr
    3340: iload         6
    3342: bipush        8
    3344: ishr
    3345: iload         7
    3347: bipush        8
    3349: ishr
    3350: iload         20
    3352: iload         23
    3354: iload         26
    3356: iload         21
    3358: iload         24
    3360: iload         27
    3362: invokestatic  #83                 // Method method379:([I[IIIIIIIIIIII)V
    3365: iload         4
    3367: iload         31
    3369: iadd
    3370: istore        4
    3372: iload_3
    3373: iload         29
    3375: iadd
    3376: istore_3
    3377: iload         7
    3379: iload         32
    3381: iadd
    3382: istore        7
    3384: iload         6
    3386: iload         30
    3388: iadd
    3389: istore        6
    3391: iload_2
    3392: getstatic     #16                 // Field DrawingArea.width:I
    3395: iadd
    3396: istore_2
    3397: iload         20
    3399: iload         22
    3401: iadd
    3402: istore        20
    3404: iload         23
    3406: iload         25
    3408: iadd
    3409: istore        23
    3411: iload         26
    3413: iload         28
    3415: iadd
    3416: istore        26
    3418: goto          3318
    3421: return
    3422: iload         5
    3424: bipush        16
    3426: ishl
    3427: dup
    3428: istore        5
    3430: istore_3
    3431: iload         8
    3433: bipush        16
    3435: ishl
    3436: dup
    3437: istore        8
    3439: istore        6
    3441: iload_2
    3442: ifge          3481
    3445: iload_3
    3446: iload         31
    3448: iload_2
    3449: imul
    3450: isub
    3451: istore_3
    3452: iload         5
    3454: iload         33
    3456: iload_2
    3457: imul
    3458: isub
    3459: istore        5
    3461: iload         6
    3463: iload         32
    3465: iload_2
    3466: imul
    3467: isub
    3468: istore        6
    3470: iload         8
    3472: iload         34
    3474: iload_2
    3475: imul
    3476: isub
    3477: istore        8
    3479: iconst_0
    3480: istore_2
    3481: iload         4
    3483: bipush        16
    3485: ishl
    3486: istore        4
    3488: iload         7
    3490: bipush        16
    3492: ishl
    3493: istore        7
    3495: iload_1
    3496: ifge          3519
    3499: iload         4
    3501: iload         29
    3503: iload_1
    3504: imul
    3505: isub
    3506: istore        4
    3508: iload         7
    3510: iload         30
    3512: iload_1
    3513: imul
    3514: isub
    3515: istore        7
    3517: iconst_0
    3518: istore_1
    3519: iload_2
    3520: getstatic     #18                 // Field textureInt2:I
    3523: isub
    3524: istore        35
    3526: iload         20
    3528: iload         22
    3530: iload         35
    3532: imul
    3533: iadd
    3534: istore        20
    3536: iload         23
    3538: iload         25
    3540: iload         35
    3542: imul
    3543: iadd
    3544: istore        23
    3546: iload         26
    3548: iload         28
    3550: iload         35
    3552: imul
    3553: iadd
    3554: istore        26
    3556: iload         31
    3558: iload         33
    3560: if_icmpge     3787
    3563: iload_0
    3564: iload_1
    3565: isub
    3566: istore_0
    3567: iload_1
    3568: iload_2
    3569: isub
    3570: istore_1
    3571: getstatic     #5                  // Field anIntArray1472:[I
    3574: iload_2
    3575: iaload
    3576: istore_2
    3577: iinc          1, -1
    3580: iload_1
    3581: iflt          3680
    3584: getstatic     #72                 // Field DrawingArea.pixels:[I
    3587: aload         19
    3589: iload_2
    3590: iload_3
    3591: bipush        16
    3593: ishr
    3594: iload         5
    3596: bipush        16
    3598: ishr
    3599: iload         6
    3601: bipush        8
    3603: ishr
    3604: iload         8
    3606: bipush        8
    3608: ishr
    3609: iload         20
    3611: iload         23
    3613: iload         26
    3615: iload         21
    3617: iload         24
    3619: iload         27
    3621: invokestatic  #83                 // Method method379:([I[IIIIIIIIIIII)V
    3624: iload_3
    3625: iload         31
    3627: iadd
    3628: istore_3
    3629: iload         5
    3631: iload         33
    3633: iadd
    3634: istore        5
    3636: iload         6
    3638: iload         32
    3640: iadd
    3641: istore        6
    3643: iload         8
    3645: iload         34
    3647: iadd
    3648: istore        8
    3650: iload_2
    3651: getstatic     #16                 // Field DrawingArea.width:I
    3654: iadd
    3655: istore_2
    3656: iload         20
    3658: iload         22
    3660: iadd
    3661: istore        20
    3663: iload         23
    3665: iload         25
    3667: iadd
    3668: istore        23
    3670: iload         26
    3672: iload         28
    3674: iadd
    3675: istore        26
    3677: goto          3577
    3680: iinc          0, -1
    3683: iload_0
    3684: iflt          3786
    3687: getstatic     #72                 // Field DrawingArea.pixels:[I
    3690: aload         19
    3692: iload_2
    3693: iload         4
    3695: bipush        16
    3697: ishr
    3698: iload         5
    3700: bipush        16
    3702: ishr
    3703: iload         7
    3705: bipush        8
    3707: ishr
    3708: iload         8
    3710: bipush        8
    3712: ishr
    3713: iload         20
    3715: iload         23
    3717: iload         26
    3719: iload         21
    3721: iload         24
    3723: iload         27
    3725: invokestatic  #83                 // Method method379:([I[IIIIIIIIIIII)V
    3728: iload         4
    3730: iload         29
    3732: iadd
    3733: istore        4
    3735: iload         5
    3737: iload         33
    3739: iadd
    3740: istore        5
    3742: iload         7
    3744: iload         30
    3746: iadd
    3747: istore        7
    3749: iload         8
    3751: iload         34
    3753: iadd
    3754: istore        8
    3756: iload_2
    3757: getstatic     #16                 // Field DrawingArea.width:I
    3760: iadd
    3761: istore_2
    3762: iload         20
    3764: iload         22
    3766: iadd
    3767: istore        20
    3769: iload         23
    3771: iload         25
    3773: iadd
    3774: istore        23
    3776: iload         26
    3778: iload         28
    3780: iadd
    3781: istore        26
    3783: goto          3680
    3786: return
    3787: iload_0
    3788: iload_1
    3789: isub
    3790: istore_0
    3791: iload_1
    3792: iload_2
    3793: isub
    3794: istore_1
    3795: getstatic     #5                  // Field anIntArray1472:[I
    3798: iload_2
    3799: iaload
    3800: istore_2
    3801: iinc          1, -1
    3804: iload_1
    3805: iflt          3904
    3808: getstatic     #72                 // Field DrawingArea.pixels:[I
    3811: aload         19
    3813: iload_2
    3814: iload         5
    3816: bipush        16
    3818: ishr
    3819: iload_3
    3820: bipush        16
    3822: ishr
    3823: iload         8
    3825: bipush        8
    3827: ishr
    3828: iload         6
    3830: bipush        8
    3832: ishr
    3833: iload         20
    3835: iload         23
    3837: iload         26
    3839: iload         21
    3841: iload         24
    3843: iload         27
    3845: invokestatic  #83                 // Method method379:([I[IIIIIIIIIIII)V
    3848: iload_3
    3849: iload         31
    3851: iadd
    3852: istore_3
    3853: iload         5
    3855: iload         33
    3857: iadd
    3858: istore        5
    3860: iload         6
    3862: iload         32
    3864: iadd
    3865: istore        6
    3867: iload         8
    3869: iload         34
    3871: iadd
    3872: istore        8
    3874: iload_2
    3875: getstatic     #16                 // Field DrawingArea.width:I
    3878: iadd
    3879: istore_2
    3880: iload         20
    3882: iload         22
    3884: iadd
    3885: istore        20
    3887: iload         23
    3889: iload         25
    3891: iadd
    3892: istore        23
    3894: iload         26
    3896: iload         28
    3898: iadd
    3899: istore        26
    3901: goto          3801
    3904: iinc          0, -1
    3907: iload_0
    3908: iflt          4010
    3911: getstatic     #72                 // Field DrawingArea.pixels:[I
    3914: aload         19
    3916: iload_2
    3917: iload         5
    3919: bipush        16
    3921: ishr
    3922: iload         4
    3924: bipush        16
    3926: ishr
    3927: iload         8
    3929: bipush        8
    3931: ishr
    3932: iload         7
    3934: bipush        8
    3936: ishr
    3937: iload         20
    3939: iload         23
    3941: iload         26
    3943: iload         21
    3945: iload         24
    3947: iload         27
    3949: invokestatic  #83                 // Method method379:([I[IIIIIIIIIIII)V
    3952: iload         4
    3954: iload         29
    3956: iadd
    3957: istore        4
    3959: iload         5
    3961: iload         33
    3963: iadd
    3964: istore        5
    3966: iload         7
    3968: iload         30
    3970: iadd
    3971: istore        7
    3973: iload         8
    3975: iload         34
    3977: iadd
    3978: istore        8
    3980: iload_2
    3981: getstatic     #16                 // Field DrawingArea.width:I
    3984: iadd
    3985: istore_2
    3986: iload         20
    3988: iload         22
    3990: iadd
    3991: istore        20
    3993: iload         23
    3995: iload         25
    3997: iadd
    3998: istore        23
    4000: iload         26
    4002: iload         28
    4004: iadd
    4005: istore        26
    4007: goto          3904
    4010: return

  private static void method379(int[], int[], int, int, int, int, int, int, int, int, int, int, int);
    Code:
       0: iconst_0
       1: istore        13
       3: iconst_0
       4: istore        14
       6: iload_3
       7: iload         4
       9: if_icmplt     13
      12: return
      13: getstatic     #75                 // Field aBoolean1462:Z
      16: ifeq          91
      19: iload         6
      21: iload         5
      23: isub
      24: iload         4
      26: iload_3
      27: isub
      28: idiv
      29: istore        15
      31: iload         4
      33: getstatic     #76                 // Field DrawingArea.centerX:I
      36: if_icmple     44
      39: getstatic     #76                 // Field DrawingArea.centerX:I
      42: istore        4
      44: iload_3
      45: ifge          59
      48: iload         5
      50: iload_3
      51: iload         15
      53: imul
      54: isub
      55: istore        5
      57: iconst_0
      58: istore_3
      59: iload_3
      60: iload         4
      62: if_icmplt     66
      65: return
      66: iload         4
      68: iload_3
      69: isub
      70: iconst_3
      71: ishr
      72: istore        16
      74: iload         15
      76: bipush        12
      78: ishl
      79: istore        15
      81: iload         5
      83: bipush        9
      85: ishl
      86: istore        5
      88: goto          141
      91: iload         4
      93: iload_3
      94: isub
      95: bipush        7
      97: if_icmple     128
     100: iload         4
     102: iload_3
     103: isub
     104: iconst_3
     105: ishr
     106: istore        16
     108: iload         6
     110: iload         5
     112: isub
     113: getstatic     #2                  // Field anIntArray1468:[I
     116: iload         16
     118: iaload
     119: imul
     120: bipush        6
     122: ishr
     123: istore        15
     125: goto          134
     128: iconst_0
     129: istore        16
     131: iconst_0
     132: istore        15
     134: iload         5
     136: bipush        9
     138: ishl
     139: istore        5
     141: iload_2
     142: iload_3
     143: iadd
     144: istore_2
     145: getstatic     #20                 // Field lowMem:Z
     148: ifeq          1393
     151: iconst_0
     152: istore        17
     154: iconst_0
     155: istore        18
     157: iload_3
     158: getstatic     #17                 // Field textureInt1:I
     161: isub
     162: istore        19
     164: iload         7
     166: iload         10
     168: iconst_3
     169: ishr
     170: iload         19
     172: imul
     173: iadd
     174: istore        7
     176: iload         8
     178: iload         11
     180: iconst_3
     181: ishr
     182: iload         19
     184: imul
     185: iadd
     186: istore        8
     188: iload         9
     190: iload         12
     192: iconst_3
     193: ishr
     194: iload         19
     196: imul
     197: iadd
     198: istore        9
     200: iload         9
     202: bipush        12
     204: ishr
     205: istore        20
     207: iload         20
     209: ifeq          250
     212: iload         7
     214: iload         20
     216: idiv
     217: istore        13
     219: iload         8
     221: iload         20
     223: idiv
     224: istore        14
     226: iload         13
     228: ifge          237
     231: iconst_0
     232: istore        13
     234: goto          250
     237: iload         13
     239: sipush        4032
     242: if_icmple     250
     245: sipush        4032
     248: istore        13
     250: iload         7
     252: iload         10
     254: iadd
     255: istore        7
     257: iload         8
     259: iload         11
     261: iadd
     262: istore        8
     264: iload         9
     266: iload         12
     268: iadd
     269: istore        9
     271: iload         9
     273: bipush        12
     275: ishr
     276: istore        20
     278: iload         20
     280: ifeq          324
     283: iload         7
     285: iload         20
     287: idiv
     288: istore        17
     290: iload         8
     292: iload         20
     294: idiv
     295: istore        18
     297: iload         17
     299: bipush        7
     301: if_icmpge     311
     304: bipush        7
     306: istore        17
     308: goto          324
     311: iload         17
     313: sipush        4032
     316: if_icmple     324
     319: sipush        4032
     322: istore        17
     324: iload         17
     326: iload         13
     328: isub
     329: iconst_3
     330: ishr
     331: istore        21
     333: iload         18
     335: iload         14
     337: isub
     338: iconst_3
     339: ishr
     340: istore        22
     342: iload         13
     344: iload         5
     346: ldc           #84                 // int 6291456
     348: iand
     349: iconst_3
     350: ishr
     351: iadd
     352: istore        13
     354: iload         5
     356: bipush        23
     358: ishr
     359: istore        23
     361: getstatic     #82                 // Field aBoolean1463:Z
     364: ifeq          844
     367: iload         16
     369: iinc          16, -1
     372: ifle          786
     375: aload_0
     376: iload_2
     377: iinc          2, 1
     380: aload_1
     381: iload         14
     383: sipush        4032
     386: iand
     387: iload         13
     389: bipush        6
     391: ishr
     392: iadd
     393: iaload
     394: iload         23
     396: iushr
     397: iastore
     398: iload         13
     400: iload         21
     402: iadd
     403: istore        13
     405: iload         14
     407: iload         22
     409: iadd
     410: istore        14
     412: aload_0
     413: iload_2
     414: iinc          2, 1
     417: aload_1
     418: iload         14
     420: sipush        4032
     423: iand
     424: iload         13
     426: bipush        6
     428: ishr
     429: iadd
     430: iaload
     431: iload         23
     433: iushr
     434: iastore
     435: iload         13
     437: iload         21
     439: iadd
     440: istore        13
     442: iload         14
     444: iload         22
     446: iadd
     447: istore        14
     449: aload_0
     450: iload_2
     451: iinc          2, 1
     454: aload_1
     455: iload         14
     457: sipush        4032
     460: iand
     461: iload         13
     463: bipush        6
     465: ishr
     466: iadd
     467: iaload
     468: iload         23
     470: iushr
     471: iastore
     472: iload         13
     474: iload         21
     476: iadd
     477: istore        13
     479: iload         14
     481: iload         22
     483: iadd
     484: istore        14
     486: aload_0
     487: iload_2
     488: iinc          2, 1
     491: aload_1
     492: iload         14
     494: sipush        4032
     497: iand
     498: iload         13
     500: bipush        6
     502: ishr
     503: iadd
     504: iaload
     505: iload         23
     507: iushr
     508: iastore
     509: iload         13
     511: iload         21
     513: iadd
     514: istore        13
     516: iload         14
     518: iload         22
     520: iadd
     521: istore        14
     523: aload_0
     524: iload_2
     525: iinc          2, 1
     528: aload_1
     529: iload         14
     531: sipush        4032
     534: iand
     535: iload         13
     537: bipush        6
     539: ishr
     540: iadd
     541: iaload
     542: iload         23
     544: iushr
     545: iastore
     546: iload         13
     548: iload         21
     550: iadd
     551: istore        13
     553: iload         14
     555: iload         22
     557: iadd
     558: istore        14
     560: aload_0
     561: iload_2
     562: iinc          2, 1
     565: aload_1
     566: iload         14
     568: sipush        4032
     571: iand
     572: iload         13
     574: bipush        6
     576: ishr
     577: iadd
     578: iaload
     579: iload         23
     581: iushr
     582: iastore
     583: iload         13
     585: iload         21
     587: iadd
     588: istore        13
     590: iload         14
     592: iload         22
     594: iadd
     595: istore        14
     597: aload_0
     598: iload_2
     599: iinc          2, 1
     602: aload_1
     603: iload         14
     605: sipush        4032
     608: iand
     609: iload         13
     611: bipush        6
     613: ishr
     614: iadd
     615: iaload
     616: iload         23
     618: iushr
     619: iastore
     620: iload         13
     622: iload         21
     624: iadd
     625: istore        13
     627: iload         14
     629: iload         22
     631: iadd
     632: istore        14
     634: aload_0
     635: iload_2
     636: iinc          2, 1
     639: aload_1
     640: iload         14
     642: sipush        4032
     645: iand
     646: iload         13
     648: bipush        6
     650: ishr
     651: iadd
     652: iaload
     653: iload         23
     655: iushr
     656: iastore
     657: iload         17
     659: istore        13
     661: iload         18
     663: istore        14
     665: iload         7
     667: iload         10
     669: iadd
     670: istore        7
     672: iload         8
     674: iload         11
     676: iadd
     677: istore        8
     679: iload         9
     681: iload         12
     683: iadd
     684: istore        9
     686: iload         9
     688: bipush        12
     690: ishr
     691: istore        24
     693: iload         24
     695: ifeq          739
     698: iload         7
     700: iload         24
     702: idiv
     703: istore        17
     705: iload         8
     707: iload         24
     709: idiv
     710: istore        18
     712: iload         17
     714: bipush        7
     716: if_icmpge     726
     719: bipush        7
     721: istore        17
     723: goto          739
     726: iload         17
     728: sipush        4032
     731: if_icmple     739
     734: sipush        4032
     737: istore        17
     739: iload         17
     741: iload         13
     743: isub
     744: iconst_3
     745: ishr
     746: istore        21
     748: iload         18
     750: iload         14
     752: isub
     753: iconst_3
     754: ishr
     755: istore        22
     757: iload         5
     759: iload         15
     761: iadd
     762: istore        5
     764: iload         13
     766: iload         5
     768: ldc           #84                 // int 6291456
     770: iand
     771: iconst_3
     772: ishr
     773: iadd
     774: istore        13
     776: iload         5
     778: bipush        23
     780: ishr
     781: istore        23
     783: goto          367
     786: iload         4
     788: iload_3
     789: isub
     790: bipush        7
     792: iand
     793: istore        16
     795: iload         16
     797: iinc          16, -1
     800: ifle          843
     803: aload_0
     804: iload_2
     805: iinc          2, 1
     808: aload_1
     809: iload         14
     811: sipush        4032
     814: iand
     815: iload         13
     817: bipush        6
     819: ishr
     820: iadd
     821: iaload
     822: iload         23
     824: iushr
     825: iastore
     826: iload         13
     828: iload         21
     830: iadd
     831: istore        13
     833: iload         14
     835: iload         22
     837: iadd
     838: istore        14
     840: goto          795
     843: return
     844: iload         16
     846: iinc          16, -1
     849: ifle          1327
     852: aload_1
     853: iload         14
     855: sipush        4032
     858: iand
     859: iload         13
     861: bipush        6
     863: ishr
     864: iadd
     865: iaload
     866: iload         23
     868: iushr
     869: dup
     870: istore        24
     872: ifeq          880
     875: aload_0
     876: iload_2
     877: iload         24
     879: iastore
     880: iinc          2, 1
     883: iload         13
     885: iload         21
     887: iadd
     888: istore        13
     890: iload         14
     892: iload         22
     894: iadd
     895: istore        14
     897: aload_1
     898: iload         14
     900: sipush        4032
     903: iand
     904: iload         13
     906: bipush        6
     908: ishr
     909: iadd
     910: iaload
     911: iload         23
     913: iushr
     914: dup
     915: istore        24
     917: ifeq          925
     920: aload_0
     921: iload_2
     922: iload         24
     924: iastore
     925: iinc          2, 1
     928: iload         13
     930: iload         21
     932: iadd
     933: istore        13
     935: iload         14
     937: iload         22
     939: iadd
     940: istore        14
     942: aload_1
     943: iload         14
     945: sipush        4032
     948: iand
     949: iload         13
     951: bipush        6
     953: ishr
     954: iadd
     955: iaload
     956: iload         23
     958: iushr
     959: dup
     960: istore        24
     962: ifeq          970
     965: aload_0
     966: iload_2
     967: iload         24
     969: iastore
     970: iinc          2, 1
     973: iload         13
     975: iload         21
     977: iadd
     978: istore        13
     980: iload         14
     982: iload         22
     984: iadd
     985: istore        14
     987: aload_1
     988: iload         14
     990: sipush        4032
     993: iand
     994: iload         13
     996: bipush        6
     998: ishr
     999: iadd
    1000: iaload
    1001: iload         23
    1003: iushr
    1004: dup
    1005: istore        24
    1007: ifeq          1015
    1010: aload_0
    1011: iload_2
    1012: iload         24
    1014: iastore
    1015: iinc          2, 1
    1018: iload         13
    1020: iload         21
    1022: iadd
    1023: istore        13
    1025: iload         14
    1027: iload         22
    1029: iadd
    1030: istore        14
    1032: aload_1
    1033: iload         14
    1035: sipush        4032
    1038: iand
    1039: iload         13
    1041: bipush        6
    1043: ishr
    1044: iadd
    1045: iaload
    1046: iload         23
    1048: iushr
    1049: dup
    1050: istore        24
    1052: ifeq          1060
    1055: aload_0
    1056: iload_2
    1057: iload         24
    1059: iastore
    1060: iinc          2, 1
    1063: iload         13
    1065: iload         21
    1067: iadd
    1068: istore        13
    1070: iload         14
    1072: iload         22
    1074: iadd
    1075: istore        14
    1077: aload_1
    1078: iload         14
    1080: sipush        4032
    1083: iand
    1084: iload         13
    1086: bipush        6
    1088: ishr
    1089: iadd
    1090: iaload
    1091: iload         23
    1093: iushr
    1094: dup
    1095: istore        24
    1097: ifeq          1105
    1100: aload_0
    1101: iload_2
    1102: iload         24
    1104: iastore
    1105: iinc          2, 1
    1108: iload         13
    1110: iload         21
    1112: iadd
    1113: istore        13
    1115: iload         14
    1117: iload         22
    1119: iadd
    1120: istore        14
    1122: aload_1
    1123: iload         14
    1125: sipush        4032
    1128: iand
    1129: iload         13
    1131: bipush        6
    1133: ishr
    1134: iadd
    1135: iaload
    1136: iload         23
    1138: iushr
    1139: dup
    1140: istore        24
    1142: ifeq          1150
    1145: aload_0
    1146: iload_2
    1147: iload         24
    1149: iastore
    1150: iinc          2, 1
    1153: iload         13
    1155: iload         21
    1157: iadd
    1158: istore        13
    1160: iload         14
    1162: iload         22
    1164: iadd
    1165: istore        14
    1167: aload_1
    1168: iload         14
    1170: sipush        4032
    1173: iand
    1174: iload         13
    1176: bipush        6
    1178: ishr
    1179: iadd
    1180: iaload
    1181: iload         23
    1183: iushr
    1184: dup
    1185: istore        24
    1187: ifeq          1195
    1190: aload_0
    1191: iload_2
    1192: iload         24
    1194: iastore
    1195: iinc          2, 1
    1198: iload         17
    1200: istore        13
    1202: iload         18
    1204: istore        14
    1206: iload         7
    1208: iload         10
    1210: iadd
    1211: istore        7
    1213: iload         8
    1215: iload         11
    1217: iadd
    1218: istore        8
    1220: iload         9
    1222: iload         12
    1224: iadd
    1225: istore        9
    1227: iload         9
    1229: bipush        12
    1231: ishr
    1232: istore        25
    1234: iload         25
    1236: ifeq          1280
    1239: iload         7
    1241: iload         25
    1243: idiv
    1244: istore        17
    1246: iload         8
    1248: iload         25
    1250: idiv
    1251: istore        18
    1253: iload         17
    1255: bipush        7
    1257: if_icmpge     1267
    1260: bipush        7
    1262: istore        17
    1264: goto          1280
    1267: iload         17
    1269: sipush        4032
    1272: if_icmple     1280
    1275: sipush        4032
    1278: istore        17
    1280: iload         17
    1282: iload         13
    1284: isub
    1285: iconst_3
    1286: ishr
    1287: istore        21
    1289: iload         18
    1291: iload         14
    1293: isub
    1294: iconst_3
    1295: ishr
    1296: istore        22
    1298: iload         5
    1300: iload         15
    1302: iadd
    1303: istore        5
    1305: iload         13
    1307: iload         5
    1309: ldc           #84                 // int 6291456
    1311: iand
    1312: iconst_3
    1313: ishr
    1314: iadd
    1315: istore        13
    1317: iload         5
    1319: bipush        23
    1321: ishr
    1322: istore        23
    1324: goto          844
    1327: iload         4
    1329: iload_3
    1330: isub
    1331: bipush        7
    1333: iand
    1334: istore        16
    1336: iload         16
    1338: iinc          16, -1
    1341: ifle          1392
    1344: aload_1
    1345: iload         14
    1347: sipush        4032
    1350: iand
    1351: iload         13
    1353: bipush        6
    1355: ishr
    1356: iadd
    1357: iaload
    1358: iload         23
    1360: iushr
    1361: dup
    1362: istore        24
    1364: ifeq          1372
    1367: aload_0
    1368: iload_2
    1369: iload         24
    1371: iastore
    1372: iinc          2, 1
    1375: iload         13
    1377: iload         21
    1379: iadd
    1380: istore        13
    1382: iload         14
    1384: iload         22
    1386: iadd
    1387: istore        14
    1389: goto          1336
    1392: return
    1393: iconst_0
    1394: istore        17
    1396: iconst_0
    1397: istore        18
    1399: iload_3
    1400: getstatic     #17                 // Field textureInt1:I
    1403: isub
    1404: istore        19
    1406: iload         7
    1408: iload         10
    1410: iconst_3
    1411: ishr
    1412: iload         19
    1414: imul
    1415: iadd
    1416: istore        7
    1418: iload         8
    1420: iload         11
    1422: iconst_3
    1423: ishr
    1424: iload         19
    1426: imul
    1427: iadd
    1428: istore        8
    1430: iload         9
    1432: iload         12
    1434: iconst_3
    1435: ishr
    1436: iload         19
    1438: imul
    1439: iadd
    1440: istore        9
    1442: iload         9
    1444: bipush        14
    1446: ishr
    1447: istore        20
    1449: iload         20
    1451: ifeq          1492
    1454: iload         7
    1456: iload         20
    1458: idiv
    1459: istore        13
    1461: iload         8
    1463: iload         20
    1465: idiv
    1466: istore        14
    1468: iload         13
    1470: ifge          1479
    1473: iconst_0
    1474: istore        13
    1476: goto          1492
    1479: iload         13
    1481: sipush        16256
    1484: if_icmple     1492
    1487: sipush        16256
    1490: istore        13
    1492: iload         7
    1494: iload         10
    1496: iadd
    1497: istore        7
    1499: iload         8
    1501: iload         11
    1503: iadd
    1504: istore        8
    1506: iload         9
    1508: iload         12
    1510: iadd
    1511: istore        9
    1513: iload         9
    1515: bipush        14
    1517: ishr
    1518: istore        20
    1520: iload         20
    1522: ifeq          1566
    1525: iload         7
    1527: iload         20
    1529: idiv
    1530: istore        17
    1532: iload         8
    1534: iload         20
    1536: idiv
    1537: istore        18
    1539: iload         17
    1541: bipush        7
    1543: if_icmpge     1553
    1546: bipush        7
    1548: istore        17
    1550: goto          1566
    1553: iload         17
    1555: sipush        16256
    1558: if_icmple     1566
    1561: sipush        16256
    1564: istore        17
    1566: iload         17
    1568: iload         13
    1570: isub
    1571: iconst_3
    1572: ishr
    1573: istore        21
    1575: iload         18
    1577: iload         14
    1579: isub
    1580: iconst_3
    1581: ishr
    1582: istore        22
    1584: iload         13
    1586: iload         5
    1588: ldc           #84                 // int 6291456
    1590: iand
    1591: iadd
    1592: istore        13
    1594: iload         5
    1596: bipush        23
    1598: ishr
    1599: istore        23
    1601: getstatic     #82                 // Field aBoolean1463:Z
    1604: ifeq          2082
    1607: iload         16
    1609: iinc          16, -1
    1612: ifle          2024
    1615: aload_0
    1616: iload_2
    1617: iinc          2, 1
    1620: aload_1
    1621: iload         14
    1623: sipush        16256
    1626: iand
    1627: iload         13
    1629: bipush        7
    1631: ishr
    1632: iadd
    1633: iaload
    1634: iload         23
    1636: iushr
    1637: iastore
    1638: iload         13
    1640: iload         21
    1642: iadd
    1643: istore        13
    1645: iload         14
    1647: iload         22
    1649: iadd
    1650: istore        14
    1652: aload_0
    1653: iload_2
    1654: iinc          2, 1
    1657: aload_1
    1658: iload         14
    1660: sipush        16256
    1663: iand
    1664: iload         13
    1666: bipush        7
    1668: ishr
    1669: iadd
    1670: iaload
    1671: iload         23
    1673: iushr
    1674: iastore
    1675: iload         13
    1677: iload         21
    1679: iadd
    1680: istore        13
    1682: iload         14
    1684: iload         22
    1686: iadd
    1687: istore        14
    1689: aload_0
    1690: iload_2
    1691: iinc          2, 1
    1694: aload_1
    1695: iload         14
    1697: sipush        16256
    1700: iand
    1701: iload         13
    1703: bipush        7
    1705: ishr
    1706: iadd
    1707: iaload
    1708: iload         23
    1710: iushr
    1711: iastore
    1712: iload         13
    1714: iload         21
    1716: iadd
    1717: istore        13
    1719: iload         14
    1721: iload         22
    1723: iadd
    1724: istore        14
    1726: aload_0
    1727: iload_2
    1728: iinc          2, 1
    1731: aload_1
    1732: iload         14
    1734: sipush        16256
    1737: iand
    1738: iload         13
    1740: bipush        7
    1742: ishr
    1743: iadd
    1744: iaload
    1745: iload         23
    1747: iushr
    1748: iastore
    1749: iload         13
    1751: iload         21
    1753: iadd
    1754: istore        13
    1756: iload         14
    1758: iload         22
    1760: iadd
    1761: istore        14
    1763: aload_0
    1764: iload_2
    1765: iinc          2, 1
    1768: aload_1
    1769: iload         14
    1771: sipush        16256
    1774: iand
    1775: iload         13
    1777: bipush        7
    1779: ishr
    1780: iadd
    1781: iaload
    1782: iload         23
    1784: iushr
    1785: iastore
    1786: iload         13
    1788: iload         21
    1790: iadd
    1791: istore        13
    1793: iload         14
    1795: iload         22
    1797: iadd
    1798: istore        14
    1800: aload_0
    1801: iload_2
    1802: iinc          2, 1
    1805: aload_1
    1806: iload         14
    1808: sipush        16256
    1811: iand
    1812: iload         13
    1814: bipush        7
    1816: ishr
    1817: iadd
    1818: iaload
    1819: iload         23
    1821: iushr
    1822: iastore
    1823: iload         13
    1825: iload         21
    1827: iadd
    1828: istore        13
    1830: iload         14
    1832: iload         22
    1834: iadd
    1835: istore        14
    1837: aload_0
    1838: iload_2
    1839: iinc          2, 1
    1842: aload_1
    1843: iload         14
    1845: sipush        16256
    1848: iand
    1849: iload         13
    1851: bipush        7
    1853: ishr
    1854: iadd
    1855: iaload
    1856: iload         23
    1858: iushr
    1859: iastore
    1860: iload         13
    1862: iload         21
    1864: iadd
    1865: istore        13
    1867: iload         14
    1869: iload         22
    1871: iadd
    1872: istore        14
    1874: aload_0
    1875: iload_2
    1876: iinc          2, 1
    1879: aload_1
    1880: iload         14
    1882: sipush        16256
    1885: iand
    1886: iload         13
    1888: bipush        7
    1890: ishr
    1891: iadd
    1892: iaload
    1893: iload         23
    1895: iushr
    1896: iastore
    1897: iload         17
    1899: istore        13
    1901: iload         18
    1903: istore        14
    1905: iload         7
    1907: iload         10
    1909: iadd
    1910: istore        7
    1912: iload         8
    1914: iload         11
    1916: iadd
    1917: istore        8
    1919: iload         9
    1921: iload         12
    1923: iadd
    1924: istore        9
    1926: iload         9
    1928: bipush        14
    1930: ishr
    1931: istore        24
    1933: iload         24
    1935: ifeq          1979
    1938: iload         7
    1940: iload         24
    1942: idiv
    1943: istore        17
    1945: iload         8
    1947: iload         24
    1949: idiv
    1950: istore        18
    1952: iload         17
    1954: bipush        7
    1956: if_icmpge     1966
    1959: bipush        7
    1961: istore        17
    1963: goto          1979
    1966: iload         17
    1968: sipush        16256
    1971: if_icmple     1979
    1974: sipush        16256
    1977: istore        17
    1979: iload         17
    1981: iload         13
    1983: isub
    1984: iconst_3
    1985: ishr
    1986: istore        21
    1988: iload         18
    1990: iload         14
    1992: isub
    1993: iconst_3
    1994: ishr
    1995: istore        22
    1997: iload         5
    1999: iload         15
    2001: iadd
    2002: istore        5
    2004: iload         13
    2006: iload         5
    2008: ldc           #84                 // int 6291456
    2010: iand
    2011: iadd
    2012: istore        13
    2014: iload         5
    2016: bipush        23
    2018: ishr
    2019: istore        23
    2021: goto          1607
    2024: iload         4
    2026: iload_3
    2027: isub
    2028: bipush        7
    2030: iand
    2031: istore        16
    2033: iload         16
    2035: iinc          16, -1
    2038: ifle          2081
    2041: aload_0
    2042: iload_2
    2043: iinc          2, 1
    2046: aload_1
    2047: iload         14
    2049: sipush        16256
    2052: iand
    2053: iload         13
    2055: bipush        7
    2057: ishr
    2058: iadd
    2059: iaload
    2060: iload         23
    2062: iushr
    2063: iastore
    2064: iload         13
    2066: iload         21
    2068: iadd
    2069: istore        13
    2071: iload         14
    2073: iload         22
    2075: iadd
    2076: istore        14
    2078: goto          2033
    2081: return
    2082: iload         16
    2084: iinc          16, -1
    2087: ifle          2563
    2090: aload_1
    2091: iload         14
    2093: sipush        16256
    2096: iand
    2097: iload         13
    2099: bipush        7
    2101: ishr
    2102: iadd
    2103: iaload
    2104: iload         23
    2106: iushr
    2107: dup
    2108: istore        24
    2110: ifeq          2118
    2113: aload_0
    2114: iload_2
    2115: iload         24
    2117: iastore
    2118: iinc          2, 1
    2121: iload         13
    2123: iload         21
    2125: iadd
    2126: istore        13
    2128: iload         14
    2130: iload         22
    2132: iadd
    2133: istore        14
    2135: aload_1
    2136: iload         14
    2138: sipush        16256
    2141: iand
    2142: iload         13
    2144: bipush        7
    2146: ishr
    2147: iadd
    2148: iaload
    2149: iload         23
    2151: iushr
    2152: dup
    2153: istore        24
    2155: ifeq          2163
    2158: aload_0
    2159: iload_2
    2160: iload         24
    2162: iastore
    2163: iinc          2, 1
    2166: iload         13
    2168: iload         21
    2170: iadd
    2171: istore        13
    2173: iload         14
    2175: iload         22
    2177: iadd
    2178: istore        14
    2180: aload_1
    2181: iload         14
    2183: sipush        16256
    2186: iand
    2187: iload         13
    2189: bipush        7
    2191: ishr
    2192: iadd
    2193: iaload
    2194: iload         23
    2196: iushr
    2197: dup
    2198: istore        24
    2200: ifeq          2208
    2203: aload_0
    2204: iload_2
    2205: iload         24
    2207: iastore
    2208: iinc          2, 1
    2211: iload         13
    2213: iload         21
    2215: iadd
    2216: istore        13
    2218: iload         14
    2220: iload         22
    2222: iadd
    2223: istore        14
    2225: aload_1
    2226: iload         14
    2228: sipush        16256
    2231: iand
    2232: iload         13
    2234: bipush        7
    2236: ishr
    2237: iadd
    2238: iaload
    2239: iload         23
    2241: iushr
    2242: dup
    2243: istore        24
    2245: ifeq          2253
    2248: aload_0
    2249: iload_2
    2250: iload         24
    2252: iastore
    2253: iinc          2, 1
    2256: iload         13
    2258: iload         21
    2260: iadd
    2261: istore        13
    2263: iload         14
    2265: iload         22
    2267: iadd
    2268: istore        14
    2270: aload_1
    2271: iload         14
    2273: sipush        16256
    2276: iand
    2277: iload         13
    2279: bipush        7
    2281: ishr
    2282: iadd
    2283: iaload
    2284: iload         23
    2286: iushr
    2287: dup
    2288: istore        24
    2290: ifeq          2298
    2293: aload_0
    2294: iload_2
    2295: iload         24
    2297: iastore
    2298: iinc          2, 1
    2301: iload         13
    2303: iload         21
    2305: iadd
    2306: istore        13
    2308: iload         14
    2310: iload         22
    2312: iadd
    2313: istore        14
    2315: aload_1
    2316: iload         14
    2318: sipush        16256
    2321: iand
    2322: iload         13
    2324: bipush        7
    2326: ishr
    2327: iadd
    2328: iaload
    2329: iload         23
    2331: iushr
    2332: dup
    2333: istore        24
    2335: ifeq          2343
    2338: aload_0
    2339: iload_2
    2340: iload         24
    2342: iastore
    2343: iinc          2, 1
    2346: iload         13
    2348: iload         21
    2350: iadd
    2351: istore        13
    2353: iload         14
    2355: iload         22
    2357: iadd
    2358: istore        14
    2360: aload_1
    2361: iload         14
    2363: sipush        16256
    2366: iand
    2367: iload         13
    2369: bipush        7
    2371: ishr
    2372: iadd
    2373: iaload
    2374: iload         23
    2376: iushr
    2377: dup
    2378: istore        24
    2380: ifeq          2388
    2383: aload_0
    2384: iload_2
    2385: iload         24
    2387: iastore
    2388: iinc          2, 1
    2391: iload         13
    2393: iload         21
    2395: iadd
    2396: istore        13
    2398: iload         14
    2400: iload         22
    2402: iadd
    2403: istore        14
    2405: aload_1
    2406: iload         14
    2408: sipush        16256
    2411: iand
    2412: iload         13
    2414: bipush        7
    2416: ishr
    2417: iadd
    2418: iaload
    2419: iload         23
    2421: iushr
    2422: dup
    2423: istore        24
    2425: ifeq          2433
    2428: aload_0
    2429: iload_2
    2430: iload         24
    2432: iastore
    2433: iinc          2, 1
    2436: iload         17
    2438: istore        13
    2440: iload         18
    2442: istore        14
    2444: iload         7
    2446: iload         10
    2448: iadd
    2449: istore        7
    2451: iload         8
    2453: iload         11
    2455: iadd
    2456: istore        8
    2458: iload         9
    2460: iload         12
    2462: iadd
    2463: istore        9
    2465: iload         9
    2467: bipush        14
    2469: ishr
    2470: istore        25
    2472: iload         25
    2474: ifeq          2518
    2477: iload         7
    2479: iload         25
    2481: idiv
    2482: istore        17
    2484: iload         8
    2486: iload         25
    2488: idiv
    2489: istore        18
    2491: iload         17
    2493: bipush        7
    2495: if_icmpge     2505
    2498: bipush        7
    2500: istore        17
    2502: goto          2518
    2505: iload         17
    2507: sipush        16256
    2510: if_icmple     2518
    2513: sipush        16256
    2516: istore        17
    2518: iload         17
    2520: iload         13
    2522: isub
    2523: iconst_3
    2524: ishr
    2525: istore        21
    2527: iload         18
    2529: iload         14
    2531: isub
    2532: iconst_3
    2533: ishr
    2534: istore        22
    2536: iload         5
    2538: iload         15
    2540: iadd
    2541: istore        5
    2543: iload         13
    2545: iload         5
    2547: ldc           #84                 // int 6291456
    2549: iand
    2550: iadd
    2551: istore        13
    2553: iload         5
    2555: bipush        23
    2557: ishr
    2558: istore        23
    2560: goto          2082
    2563: iload         4
    2565: iload_3
    2566: isub
    2567: bipush        7
    2569: iand
    2570: istore        24
    2572: iload         24
    2574: iinc          24, -1
    2577: ifle          2628
    2580: aload_1
    2581: iload         14
    2583: sipush        16256
    2586: iand
    2587: iload         13
    2589: bipush        7
    2591: ishr
    2592: iadd
    2593: iaload
    2594: iload         23
    2596: iushr
    2597: dup
    2598: istore        25
    2600: ifeq          2608
    2603: aload_0
    2604: iload_2
    2605: iload         25
    2607: iastore
    2608: iinc          2, 1
    2611: iload         13
    2613: iload         21
    2615: iadd
    2616: istore        13
    2618: iload         14
    2620: iload         22
    2622: iadd
    2623: istore        14
    2625: goto          2572
    2628: return

  static {};
    Code:
       0: iconst_1
       1: putstatic     #20                 // Field lowMem:Z
       4: iconst_1
       5: putstatic     #74                 // Field aBoolean1464:Z
       8: bipush        50
      10: anewarray     #23                 // class Background
      13: putstatic     #6                  // Field aBackgroundArray1474s:[LBackground;
      16: bipush        50
      18: newarray       boolean
      20: putstatic     #7                  // Field aBooleanArray1475:[Z
      23: bipush        50
      25: newarray       int
      27: putstatic     #8                  // Field anIntArray1476:[I
      30: bipush        50
      32: anewarray     #85                 // class "[I"
      35: putstatic     #11                 // Field anIntArrayArray1479:[[I
      38: bipush        50
      40: newarray       int
      42: putstatic     #12                 // Field anIntArray1480:[I
      45: ldc           #21                 // int 65536
      47: newarray       int
      49: putstatic     #13                 // Field anIntArray1482:[I
      52: bipush        50
      54: anewarray     #85                 // class "[I"
      57: putstatic     #14                 // Field anIntArrayArray1483:[[I
      60: sipush        512
      63: newarray       int
      65: putstatic     #2                  // Field anIntArray1468:[I
      68: sipush        2048
      71: newarray       int
      73: putstatic     #86                 // Field anIntArray1469:[I
      76: sipush        2048
      79: newarray       int
      81: putstatic     #3                  // Field anIntArray1470:[I
      84: sipush        2048
      87: newarray       int
      89: putstatic     #4                  // Field anIntArray1471:[I
      92: iconst_1
      93: istore_0
      94: iload_0
      95: sipush        512
      98: if_icmpge     116
     101: getstatic     #2                  // Field anIntArray1468:[I
     104: iload_0
     105: ldc           #37                 // int 32768
     107: iload_0
     108: idiv
     109: iastore
     110: iinc          0, 1
     113: goto          94
     116: iconst_1
     117: istore_0
     118: iload_0
     119: sipush        2048
     122: if_icmpge     140
     125: getstatic     #86                 // Field anIntArray1469:[I
     128: iload_0
     129: ldc           #21                 // int 65536
     131: iload_0
     132: idiv
     133: iastore
     134: iinc          0, 1
     137: goto          118
     140: iconst_0
     141: istore_0
     142: iload_0
     143: sipush        2048
     146: if_icmpge     193
     149: getstatic     #3                  // Field anIntArray1470:[I
     152: iload_0
     153: ldc2_w        #87                 // double 65536.0d
     156: iload_0
     157: i2d
     158: ldc2_w        #89                 // double 0.0030679615d
     161: dmul
     162: invokestatic  #91                 // Method java/lang/Math.sin:(D)D
     165: dmul
     166: d2i
     167: iastore
     168: getstatic     #4                  // Field anIntArray1471:[I
     171: iload_0
     172: ldc2_w        #87                 // double 65536.0d
     175: iload_0
     176: i2d
     177: ldc2_w        #89                 // double 0.0030679615d
     180: dmul
     181: invokestatic  #92                 // Method java/lang/Math.cos:(D)D
     184: dmul
     185: d2i
     186: iastore
     187: iinc          0, 1
     190: goto          142
     193: return
}
