Compiled from "signlink.java"
public final class sign.signlink implements java.lang.Runnable {
  private static final int clientversion;

  public static int uid;

  public static int storeid;

  public static java.io.RandomAccessFile cache_dat;

  public static java.io.RandomAccessFile[] cache_idx;

  public static boolean sunjava;

  public static java.applet.Applet mainapp;

  private static boolean active;

  private static int threadliveid;

  private static java.net.InetAddress socketip;

  private static int socketreq;

  private static java.net.Socket socket;

  private static int threadreqpri;

  private static java.lang.Runnable threadreq;

  private static java.lang.String dnsreq;

  public static java.lang.String dns;

  private static java.lang.String urlreq;

  private static java.io.DataInputStream urlstream;

  private static int savelen;

  private static java.lang.String savereq;

  private static byte[] savebuf;

  private static boolean midiplay;

  private static int midipos;

  public static java.lang.String midi;

  public static int midivol;

  public static int midifade;

  private static boolean waveplay;

  private static int wavepos;

  public static java.lang.String wave;

  public static int wavevol;

  public static boolean reporterror;

  public static java.lang.String errorname;

  public static final void startpriv(java.net.InetAddress);
    Code:
       0: invokestatic  #101                // Method java/lang/Math.random:()D
       3: ldc2_w        #138                // double 9.9999999E7d
       6: dmul
       7: d2i
       8: putstatic     #117                // Field threadliveid:I
      11: getstatic     #71                 // Field active:Z
      14: ifeq          31
      17: ldc2_w        #134                // long 500l
      20: invokestatic  #111                // Method java/lang/Thread.sleep:(J)V
      23: goto          27
      26: pop
      27: iconst_0
      28: putstatic     #71                 // Field active:Z
      31: iconst_0
      32: putstatic     #114                // Field socketreq:I
      35: aconst_null
      36: putstatic     #118                // Field threadreq:Ljava/lang/Runnable;
      39: aconst_null
      40: putstatic     #81                 // Field dnsreq:Ljava/lang/String;
      43: aconst_null
      44: putstatic     #108                // Field savereq:Ljava/lang/String;
      47: aconst_null
      48: putstatic     #122                // Field urlreq:Ljava/lang/String;
      51: aload_0
      52: putstatic     #113                // Field socketip:Ljava/net/InetAddress;
      55: new           #52                 // class java/lang/Thread
      58: dup
      59: new           #57                 // class sign/signlink
      62: dup
      63: invokespecial #59                 // Method "<init>":()V
      66: invokespecial #62                 // Method java/lang/Thread."<init>":(Ljava/lang/Runnable;)V
      69: astore_1
      70: aload_1
      71: iconst_1
      72: invokevirtual #109                // Method java/lang/Thread.setDaemon:(Z)V
      75: aload_1
      76: invokevirtual #115                // Method java/lang/Thread.start:()V
      79: goto          95
      82: ldc2_w        #132                // long 50l
      85: invokestatic  #111                // Method java/lang/Thread.sleep:(J)V
      88: goto          95
      91: pop
      92: goto          95
      95: getstatic     #71                 // Field active:Z
      98: ifeq          82
     101: return
    Exception table:
       from    to  target type
          17    23    26   Class java/lang/Exception
          82    88    91   Class java/lang/Exception

  public final void run();
    Code:
       0: iconst_1
       1: putstatic     #71                 // Field active:Z
       4: invokestatic  #84                 // Method findcachedir:()Ljava/lang/String;
       7: astore_1
       8: aload_1
       9: invokestatic  #88                 // Method getuid:(Ljava/lang/String;)I
      12: putstatic     #121                // Field uid:I
      15: new           #37                 // class java/io/File
      18: dup
      19: new           #50                 // class java/lang/StringBuffer
      22: dup
      23: aload_1
      24: invokestatic  #124                // Method java/lang/String.valueOf:(Ljava/lang/Object;)Ljava/lang/String;
      27: invokespecial #67                 // Method java/lang/StringBuffer."<init>":(Ljava/lang/String;)V
      30: ldc           #26                 // String main_file_cache.dat
      32: invokevirtual #73                 // Method java/lang/StringBuffer.append:(Ljava/lang/String;)Ljava/lang/StringBuffer;
      35: invokevirtual #120                // Method java/lang/StringBuffer.toString:()Ljava/lang/String;
      38: invokespecial #63                 // Method java/io/File."<init>":(Ljava/lang/String;)V
      41: astore_2
      42: aload_2
      43: invokevirtual #83                 // Method java/io/File.exists:()Z
      46: ifeq          65
      49: aload_2
      50: invokevirtual #90                 // Method java/io/File.length:()J
      53: ldc2_w        #136                // long 52428800l
      56: lcmp
      57: ifle          65
      60: aload_2
      61: invokevirtual #79                 // Method java/io/File.delete:()Z
      64: pop
      65: new           #44                 // class java/io/RandomAccessFile
      68: dup
      69: new           #50                 // class java/lang/StringBuffer
      72: dup
      73: aload_1
      74: invokestatic  #124                // Method java/lang/String.valueOf:(Ljava/lang/Object;)Ljava/lang/String;
      77: invokespecial #67                 // Method java/lang/StringBuffer."<init>":(Ljava/lang/String;)V
      80: ldc           #26                 // String main_file_cache.dat
      82: invokevirtual #73                 // Method java/lang/StringBuffer.append:(Ljava/lang/String;)Ljava/lang/StringBuffer;
      85: invokevirtual #120                // Method java/lang/StringBuffer.toString:()Ljava/lang/String;
      88: ldc           #29                 // String rw
      90: invokespecial #68                 // Method java/io/RandomAccessFile."<init>":(Ljava/lang/String;Ljava/lang/String;)V
      93: putstatic     #74                 // Field cache_dat:Ljava/io/RandomAccessFile;
      96: iconst_0
      97: istore_3
      98: goto          141
     101: getstatic     #75                 // Field cache_idx:[Ljava/io/RandomAccessFile;
     104: iload_3
     105: new           #44                 // class java/io/RandomAccessFile
     108: dup
     109: new           #50                 // class java/lang/StringBuffer
     112: dup
     113: aload_1
     114: invokestatic  #124                // Method java/lang/String.valueOf:(Ljava/lang/Object;)Ljava/lang/String;
     117: invokespecial #67                 // Method java/lang/StringBuffer."<init>":(Ljava/lang/String;)V
     120: ldc           #27                 // String main_file_cache.idx
     122: invokevirtual #73                 // Method java/lang/StringBuffer.append:(Ljava/lang/String;)Ljava/lang/StringBuffer;
     125: iload_3
     126: invokevirtual #72                 // Method java/lang/StringBuffer.append:(I)Ljava/lang/StringBuffer;
     129: invokevirtual #120                // Method java/lang/StringBuffer.toString:()Ljava/lang/String;
     132: ldc           #29                 // String rw
     134: invokespecial #68                 // Method java/io/RandomAccessFile."<init>":(Ljava/lang/String;Ljava/lang/String;)V
     137: aastore
     138: iinc          3, 1
     141: iload_3
     142: iconst_5
     143: if_icmplt     101
     146: goto          154
     149: astore_2
     150: aload_2
     151: invokevirtual #99                 // Method java/lang/Throwable.printStackTrace:()V
     154: getstatic     #117                // Field threadliveid:I
     157: istore_2
     158: goto          467
     161: getstatic     #114                // Field socketreq:I
     164: ifeq          198
     167: new           #55                 // class java/net/Socket
     170: dup
     171: getstatic     #113                // Field socketip:Ljava/net/InetAddress;
     174: getstatic     #114                // Field socketreq:I
     177: invokespecial #69                 // Method java/net/Socket."<init>":(Ljava/net/InetAddress;I)V
     180: putstatic     #112                // Field socket:Ljava/net/Socket;
     183: goto          191
     186: pop
     187: aconst_null
     188: putstatic     #112                // Field socket:Ljava/net/Socket;
     191: iconst_0
     192: putstatic     #114                // Field socketreq:I
     195: goto          454
     198: getstatic     #118                // Field threadreq:Ljava/lang/Runnable;
     201: ifnull        238
     204: new           #52                 // class java/lang/Thread
     207: dup
     208: getstatic     #118                // Field threadreq:Ljava/lang/Runnable;
     211: invokespecial #62                 // Method java/lang/Thread."<init>":(Ljava/lang/Runnable;)V
     214: astore_3
     215: aload_3
     216: iconst_1
     217: invokevirtual #109                // Method java/lang/Thread.setDaemon:(Z)V
     220: aload_3
     221: invokevirtual #115                // Method java/lang/Thread.start:()V
     224: aload_3
     225: getstatic     #119                // Field threadreqpri:I
     228: invokevirtual #110                // Method java/lang/Thread.setPriority:(I)V
     231: aconst_null
     232: putstatic     #118                // Field threadreq:Ljava/lang/Runnable;
     235: goto          454
     238: getstatic     #81                 // Field dnsreq:Ljava/lang/String;
     241: ifnull        272
     244: getstatic     #81                 // Field dnsreq:Ljava/lang/String;
     247: invokestatic  #85                 // Method java/net/InetAddress.getByName:(Ljava/lang/String;)Ljava/net/InetAddress;
     250: invokevirtual #87                 // Method java/net/InetAddress.getHostName:()Ljava/lang/String;
     253: putstatic     #80                 // Field dns:Ljava/lang/String;
     256: goto          265
     259: pop
     260: ldc           #32                 // String unknown
     262: putstatic     #80                 // Field dns:Ljava/lang/String;
     265: aconst_null
     266: putstatic     #81                 // Field dnsreq:Ljava/lang/String;
     269: goto          454
     272: getstatic     #108                // Field savereq:Ljava/lang/String;
     275: ifnull        407
     278: getstatic     #106                // Field savebuf:[B
     281: ifnull        334
     284: new           #39                 // class java/io/FileOutputStream
     287: dup
     288: new           #50                 // class java/lang/StringBuffer
     291: dup
     292: aload_1
     293: invokestatic  #124                // Method java/lang/String.valueOf:(Ljava/lang/Object;)Ljava/lang/String;
     296: invokespecial #67                 // Method java/lang/StringBuffer."<init>":(Ljava/lang/String;)V
     299: getstatic     #108                // Field savereq:Ljava/lang/String;
     302: invokevirtual #73                 // Method java/lang/StringBuffer.append:(Ljava/lang/String;)Ljava/lang/StringBuffer;
     305: invokevirtual #120                // Method java/lang/StringBuffer.toString:()Ljava/lang/String;
     308: invokespecial #65                 // Method java/io/FileOutputStream."<init>":(Ljava/lang/String;)V
     311: astore_3
     312: aload_3
     313: getstatic     #106                // Field savebuf:[B
     316: iconst_0
     317: getstatic     #107                // Field savelen:I
     320: invokevirtual #128                // Method java/io/FileOutputStream.write:([BII)V
     323: aload_3
     324: invokevirtual #76                 // Method java/io/FileOutputStream.close:()V
     327: goto          334
     330: pop
     331: goto          334
     334: getstatic     #126                // Field waveplay:Z
     337: ifeq          367
     340: new           #50                 // class java/lang/StringBuffer
     343: dup
     344: aload_1
     345: invokestatic  #124                // Method java/lang/String.valueOf:(Ljava/lang/Object;)Ljava/lang/String;
     348: invokespecial #67                 // Method java/lang/StringBuffer."<init>":(Ljava/lang/String;)V
     351: getstatic     #108                // Field savereq:Ljava/lang/String;
     354: invokevirtual #73                 // Method java/lang/StringBuffer.append:(Ljava/lang/String;)Ljava/lang/StringBuffer;
     357: invokevirtual #120                // Method java/lang/StringBuffer.toString:()Ljava/lang/String;
     360: putstatic     #125                // Field wave:Ljava/lang/String;
     363: iconst_0
     364: putstatic     #126                // Field waveplay:Z
     367: getstatic     #93                 // Field midiplay:Z
     370: ifeq          400
     373: new           #50                 // class java/lang/StringBuffer
     376: dup
     377: aload_1
     378: invokestatic  #124                // Method java/lang/String.valueOf:(Ljava/lang/Object;)Ljava/lang/String;
     381: invokespecial #67                 // Method java/lang/StringBuffer."<init>":(Ljava/lang/String;)V
     384: getstatic     #108                // Field savereq:Ljava/lang/String;
     387: invokevirtual #73                 // Method java/lang/StringBuffer.append:(Ljava/lang/String;)Ljava/lang/StringBuffer;
     390: invokevirtual #120                // Method java/lang/StringBuffer.toString:()Ljava/lang/String;
     393: putstatic     #92                 // Field midi:Ljava/lang/String;
     396: iconst_0
     397: putstatic     #93                 // Field midiplay:Z
     400: aconst_null
     401: putstatic     #108                // Field savereq:Ljava/lang/String;
     404: goto          454
     407: getstatic     #122                // Field urlreq:Ljava/lang/String;
     410: ifnull        454
     413: new           #35                 // class java/io/DataInputStream
     416: dup
     417: new           #56                 // class java/net/URL
     420: dup
     421: getstatic     #91                 // Field mainapp:Ljava/applet/Applet;
     424: invokevirtual #86                 // Method java/applet/Applet.getCodeBase:()Ljava/net/URL;
     427: getstatic     #122                // Field urlreq:Ljava/lang/String;
     430: invokespecial #70                 // Method java/net/URL."<init>":(Ljava/net/URL;Ljava/lang/String;)V
     433: invokevirtual #96                 // Method java/net/URL.openStream:()Ljava/io/InputStream;
     436: invokespecial #60                 // Method java/io/DataInputStream."<init>":(Ljava/io/InputStream;)V
     439: putstatic     #123                // Field urlstream:Ljava/io/DataInputStream;
     442: goto          450
     445: pop
     446: aconst_null
     447: putstatic     #123                // Field urlstream:Ljava/io/DataInputStream;
     450: aconst_null
     451: putstatic     #122                // Field urlreq:Ljava/lang/String;
     454: ldc2_w        #132                // long 50l
     457: invokestatic  #111                // Method java/lang/Thread.sleep:(J)V
     460: goto          467
     463: pop
     464: goto          467
     467: getstatic     #117                // Field threadliveid:I
     470: iload_2
     471: if_icmpeq     161
     474: return
    Exception table:
       from    to  target type
          15   146   149   Class java/lang/Exception
         167   183   186   Class java/lang/Exception
         244   256   259   Class java/lang/Exception
         284   327   330   Class java/lang/Exception
         413   442   445   Class java/lang/Exception
         454   460   463   Class java/lang/Exception

  public static final java.lang.String findcachedir();
    Code:
       0: bipush        14
       2: anewarray     #49                 // class java/lang/String
       5: dup
       6: iconst_0
       7: ldc           #15                 // String c:/windows/
       9: aastore
      10: dup
      11: iconst_1
      12: ldc           #16                 // String c:/winnt/
      14: aastore
      15: dup
      16: iconst_2
      17: ldc           #19                 // String d:/windows/
      19: aastore
      20: dup
      21: iconst_3
      22: ldc           #20                 // String d:/winnt/
      24: aastore
      25: dup
      26: iconst_4
      27: ldc           #21                 // String e:/windows/
      29: aastore
      30: dup
      31: iconst_5
      32: ldc           #22                 // String e:/winnt/
      34: aastore
      35: dup
      36: bipush        6
      38: ldc           #23                 // String f:/windows/
      40: aastore
      41: dup
      42: bipush        7
      44: ldc           #24                 // String f:/winnt/
      46: aastore
      47: dup
      48: bipush        8
      50: ldc           #13                 // String c:/
      52: aastore
      53: dup
      54: bipush        9
      56: ldc           #33                 // String ~/
      58: aastore
      59: dup
      60: bipush        10
      62: ldc           #11                 // String /tmp/
      64: aastore
      65: dup
      66: bipush        11
      68: ldc           #1                  // String
      70: aastore
      71: dup
      72: bipush        12
      74: ldc           #14                 // String c:/rscache
      76: aastore
      77: dup
      78: bipush        13
      80: ldc           #10                 // String /rscache
      82: aastore
      83: astore_0
      84: getstatic     #116                // Field storeid:I
      87: bipush        32
      89: if_icmplt     100
      92: getstatic     #116                // Field storeid:I
      95: bipush        34
      97: if_icmple     105
     100: bipush        32
     102: putstatic     #116                // Field storeid:I
     105: new           #50                 // class java/lang/StringBuffer
     108: dup
     109: ldc           #6                  // String .file_store_
     111: invokespecial #67                 // Method java/lang/StringBuffer."<init>":(Ljava/lang/String;)V
     114: getstatic     #116                // Field storeid:I
     117: invokevirtual #72                 // Method java/lang/StringBuffer.append:(I)Ljava/lang/StringBuffer;
     120: invokevirtual #120                // Method java/lang/StringBuffer.toString:()Ljava/lang/String;
     123: astore_1
     124: iconst_0
     125: istore_2
     126: goto          238
     129: aload_0
     130: iload_2
     131: aaload
     132: astore_3
     133: aload_3
     134: invokevirtual #89                 // Method java/lang/String.length:()I
     137: ifle          161
     140: new           #37                 // class java/io/File
     143: dup
     144: aload_3
     145: invokespecial #63                 // Method java/io/File."<init>":(Ljava/lang/String;)V
     148: astore        4
     150: aload         4
     152: invokevirtual #83                 // Method java/io/File.exists:()Z
     155: ifne          161
     158: goto          235
     161: new           #37                 // class java/io/File
     164: dup
     165: new           #50                 // class java/lang/StringBuffer
     168: dup
     169: aload_3
     170: invokestatic  #124                // Method java/lang/String.valueOf:(Ljava/lang/Object;)Ljava/lang/String;
     173: invokespecial #67                 // Method java/lang/StringBuffer."<init>":(Ljava/lang/String;)V
     176: aload_1
     177: invokevirtual #73                 // Method java/lang/StringBuffer.append:(Ljava/lang/String;)Ljava/lang/StringBuffer;
     180: invokevirtual #120                // Method java/lang/StringBuffer.toString:()Ljava/lang/String;
     183: invokespecial #63                 // Method java/io/File."<init>":(Ljava/lang/String;)V
     186: astore        4
     188: aload         4
     190: invokevirtual #83                 // Method java/io/File.exists:()Z
     193: ifne          207
     196: aload         4
     198: invokevirtual #95                 // Method java/io/File.mkdir:()Z
     201: ifne          207
     204: goto          235
     207: new           #50                 // class java/lang/StringBuffer
     210: dup
     211: aload_3
     212: invokestatic  #124                // Method java/lang/String.valueOf:(Ljava/lang/Object;)Ljava/lang/String;
     215: invokespecial #67                 // Method java/lang/StringBuffer."<init>":(Ljava/lang/String;)V
     218: aload_1
     219: invokevirtual #73                 // Method java/lang/StringBuffer.append:(Ljava/lang/String;)Ljava/lang/StringBuffer;
     222: ldc           #9                  // String /
     224: invokevirtual #73                 // Method java/lang/StringBuffer.append:(Ljava/lang/String;)Ljava/lang/StringBuffer;
     227: invokevirtual #120                // Method java/lang/StringBuffer.toString:()Ljava/lang/String;
     230: areturn
     231: pop
     232: goto          235
     235: iinc          2, 1
     238: iload_2
     239: aload_0
     240: arraylength
     241: if_icmplt     129
     244: aconst_null
     245: areturn
    Exception table:
       from    to  target type
         129   231   231   Class java/lang/Exception

  private static final int getuid(java.lang.String);
    Code:
       0: new           #37                 // class java/io/File
       3: dup
       4: new           #50                 // class java/lang/StringBuffer
       7: dup
       8: aload_0
       9: invokestatic  #124                // Method java/lang/String.valueOf:(Ljava/lang/Object;)Ljava/lang/String;
      12: invokespecial #67                 // Method java/lang/StringBuffer."<init>":(Ljava/lang/String;)V
      15: ldc           #31                 // String uid.dat
      17: invokevirtual #73                 // Method java/lang/StringBuffer.append:(Ljava/lang/String;)Ljava/lang/StringBuffer;
      20: invokevirtual #120                // Method java/lang/StringBuffer.toString:()Ljava/lang/String;
      23: invokespecial #63                 // Method java/io/File."<init>":(Ljava/lang/String;)V
      26: astore_1
      27: aload_1
      28: invokevirtual #83                 // Method java/io/File.exists:()Z
      31: ifeq          45
      34: aload_1
      35: invokevirtual #90                 // Method java/io/File.length:()J
      38: ldc2_w        #130                // long 4l
      41: lcmp
      42: ifge          99
      45: new           #36                 // class java/io/DataOutputStream
      48: dup
      49: new           #39                 // class java/io/FileOutputStream
      52: dup
      53: new           #50                 // class java/lang/StringBuffer
      56: dup
      57: aload_0
      58: invokestatic  #124                // Method java/lang/String.valueOf:(Ljava/lang/Object;)Ljava/lang/String;
      61: invokespecial #67                 // Method java/lang/StringBuffer."<init>":(Ljava/lang/String;)V
      64: ldc           #31                 // String uid.dat
      66: invokevirtual #73                 // Method java/lang/StringBuffer.append:(Ljava/lang/String;)Ljava/lang/StringBuffer;
      69: invokevirtual #120                // Method java/lang/StringBuffer.toString:()Ljava/lang/String;
      72: invokespecial #65                 // Method java/io/FileOutputStream."<init>":(Ljava/lang/String;)V
      75: invokespecial #61                 // Method java/io/DataOutputStream."<init>":(Ljava/io/OutputStream;)V
      78: astore_2
      79: aload_2
      80: invokestatic  #101                // Method java/lang/Math.random:()D
      83: ldc2_w        #138                // double 9.9999999E7d
      86: dmul
      87: d2i
      88: invokevirtual #129                // Method java/io/DataOutputStream.writeInt:(I)V
      91: aload_2
      92: invokevirtual #78                 // Method java/io/FilterOutputStream.close:()V
      95: goto          99
      98: pop
      99: new           #35                 // class java/io/DataInputStream
     102: dup
     103: new           #38                 // class java/io/FileInputStream
     106: dup
     107: new           #50                 // class java/lang/StringBuffer
     110: dup
     111: aload_0
     112: invokestatic  #124                // Method java/lang/String.valueOf:(Ljava/lang/Object;)Ljava/lang/String;
     115: invokespecial #67                 // Method java/lang/StringBuffer."<init>":(Ljava/lang/String;)V
     118: ldc           #31                 // String uid.dat
     120: invokevirtual #73                 // Method java/lang/StringBuffer.append:(Ljava/lang/String;)Ljava/lang/StringBuffer;
     123: invokevirtual #120                // Method java/lang/StringBuffer.toString:()Ljava/lang/String;
     126: invokespecial #64                 // Method java/io/FileInputStream."<init>":(Ljava/lang/String;)V
     129: invokespecial #60                 // Method java/io/DataInputStream."<init>":(Ljava/io/InputStream;)V
     132: astore_1
     133: aload_1
     134: invokevirtual #102                // Method java/io/DataInputStream.readInt:()I
     137: istore_2
     138: aload_1
     139: invokevirtual #77                 // Method java/io/FilterInputStream.close:()V
     142: iload_2
     143: iconst_1
     144: iadd
     145: ireturn
     146: pop
     147: iconst_0
     148: ireturn
    Exception table:
       from    to  target type
           0    95    98   Class java/lang/Exception
          99   146   146   Class java/lang/Exception

  public static final synchronized java.net.Socket opensocket(int) throws java.io.IOException;
    Code:
       0: iload_0
       1: putstatic     #114                // Field socketreq:I
       4: goto          20
       7: ldc2_w        #132                // long 50l
      10: invokestatic  #111                // Method java/lang/Thread.sleep:(J)V
      13: goto          20
      16: pop
      17: goto          20
      20: getstatic     #114                // Field socketreq:I
      23: ifne          7
      26: getstatic     #112                // Field socket:Ljava/net/Socket;
      29: ifnonnull     42
      32: new           #42                 // class java/io/IOException
      35: dup
      36: ldc           #17                 // String could not open socket
      38: invokespecial #66                 // Method java/io/IOException."<init>":(Ljava/lang/String;)V
      41: athrow
      42: getstatic     #112                // Field socket:Ljava/net/Socket;
      45: areturn
    Exception table:
       from    to  target type
           7    13    16   Class java/lang/Exception

  public static final synchronized java.io.DataInputStream openurl(java.lang.String) throws java.io.IOException;
    Code:
       0: aload_0
       1: putstatic     #122                // Field urlreq:Ljava/lang/String;
       4: goto          20
       7: ldc2_w        #132                // long 50l
      10: invokestatic  #111                // Method java/lang/Thread.sleep:(J)V
      13: goto          20
      16: pop
      17: goto          20
      20: getstatic     #122                // Field urlreq:Ljava/lang/String;
      23: ifnonnull     7
      26: getstatic     #123                // Field urlstream:Ljava/io/DataInputStream;
      29: ifnonnull     56
      32: new           #42                 // class java/io/IOException
      35: dup
      36: new           #50                 // class java/lang/StringBuffer
      39: dup
      40: ldc           #18                 // String could not open:
      42: invokespecial #67                 // Method java/lang/StringBuffer."<init>":(Ljava/lang/String;)V
      45: aload_0
      46: invokevirtual #73                 // Method java/lang/StringBuffer.append:(Ljava/lang/String;)Ljava/lang/StringBuffer;
      49: invokevirtual #120                // Method java/lang/StringBuffer.toString:()Ljava/lang/String;
      52: invokespecial #66                 // Method java/io/IOException."<init>":(Ljava/lang/String;)V
      55: athrow
      56: getstatic     #123                // Field urlstream:Ljava/io/DataInputStream;
      59: areturn
    Exception table:
       from    to  target type
           7    13    16   Class java/lang/Exception

  public static final synchronized void dnslookup(java.lang.String);
    Code:
       0: aload_0
       1: putstatic     #80                 // Field dns:Ljava/lang/String;
       4: aload_0
       5: putstatic     #81                 // Field dnsreq:Ljava/lang/String;
       8: return

  public static final synchronized void startthread(java.lang.Runnable, int);
    Code:
       0: iload_1
       1: putstatic     #119                // Field threadreqpri:I
       4: aload_0
       5: putstatic     #118                // Field threadreq:Ljava/lang/Runnable;
       8: return

  public static final synchronized boolean wavesave(byte[], int);
    Code:
       0: iload_1
       1: ldc           #3                  // int 2000000
       3: if_icmple     8
       6: iconst_0
       7: ireturn
       8: getstatic     #108                // Field savereq:Ljava/lang/String;
      11: ifnull        16
      14: iconst_0
      15: ireturn
      16: getstatic     #127                // Field wavepos:I
      19: iconst_1
      20: iadd
      21: iconst_5
      22: irem
      23: putstatic     #127                // Field wavepos:I
      26: iload_1
      27: putstatic     #107                // Field savelen:I
      30: aload_0
      31: putstatic     #106                // Field savebuf:[B
      34: iconst_1
      35: putstatic     #126                // Field waveplay:Z
      38: new           #50                 // class java/lang/StringBuffer
      41: dup
      42: ldc           #30                 // String sound
      44: invokespecial #67                 // Method java/lang/StringBuffer."<init>":(Ljava/lang/String;)V
      47: getstatic     #127                // Field wavepos:I
      50: invokevirtual #72                 // Method java/lang/StringBuffer.append:(I)Ljava/lang/StringBuffer;
      53: ldc           #8                  // String .wav
      55: invokevirtual #73                 // Method java/lang/StringBuffer.append:(Ljava/lang/String;)Ljava/lang/StringBuffer;
      58: invokevirtual #120                // Method java/lang/StringBuffer.toString:()Ljava/lang/String;
      61: putstatic     #108                // Field savereq:Ljava/lang/String;
      64: iconst_1
      65: ireturn

  public static final synchronized boolean wavereplay();
    Code:
       0: getstatic     #108                // Field savereq:Ljava/lang/String;
       3: ifnull        8
       6: iconst_0
       7: ireturn
       8: aconst_null
       9: putstatic     #106                // Field savebuf:[B
      12: iconst_1
      13: putstatic     #126                // Field waveplay:Z
      16: new           #50                 // class java/lang/StringBuffer
      19: dup
      20: ldc           #30                 // String sound
      22: invokespecial #67                 // Method java/lang/StringBuffer."<init>":(Ljava/lang/String;)V
      25: getstatic     #127                // Field wavepos:I
      28: invokevirtual #72                 // Method java/lang/StringBuffer.append:(I)Ljava/lang/StringBuffer;
      31: ldc           #8                  // String .wav
      33: invokevirtual #73                 // Method java/lang/StringBuffer.append:(Ljava/lang/String;)Ljava/lang/StringBuffer;
      36: invokevirtual #120                // Method java/lang/StringBuffer.toString:()Ljava/lang/String;
      39: putstatic     #108                // Field savereq:Ljava/lang/String;
      42: iconst_1
      43: ireturn

  public static final synchronized void midisave(byte[], int);
    Code:
       0: iload_1
       1: ldc           #3                  // int 2000000
       3: if_icmple     7
       6: return
       7: getstatic     #108                // Field savereq:Ljava/lang/String;
      10: ifnull        14
      13: return
      14: getstatic     #94                 // Field midipos:I
      17: iconst_1
      18: iadd
      19: iconst_5
      20: irem
      21: putstatic     #94                 // Field midipos:I
      24: iload_1
      25: putstatic     #107                // Field savelen:I
      28: aload_0
      29: putstatic     #106                // Field savebuf:[B
      32: iconst_1
      33: putstatic     #93                 // Field midiplay:Z
      36: new           #50                 // class java/lang/StringBuffer
      39: dup
      40: ldc           #25                 // String jingle
      42: invokespecial #67                 // Method java/lang/StringBuffer."<init>":(Ljava/lang/String;)V
      45: getstatic     #94                 // Field midipos:I
      48: invokevirtual #72                 // Method java/lang/StringBuffer.append:(I)Ljava/lang/StringBuffer;
      51: ldc           #7                  // String .mid
      53: invokevirtual #73                 // Method java/lang/StringBuffer.append:(Ljava/lang/String;)Ljava/lang/StringBuffer;
      56: invokevirtual #120                // Method java/lang/StringBuffer.toString:()Ljava/lang/String;
      59: putstatic     #108                // Field savereq:Ljava/lang/String;
      62: return

  public static final void reporterror(java.lang.String);
    Code:
       0: getstatic     #105                // Field reporterror:Z
       3: ifne          7
       6: return
       7: getstatic     #71                 // Field active:Z
      10: ifne          14
      13: return
      14: getstatic     #98                 // Field java/lang/System.out:Ljava/io/PrintStream;
      17: new           #50                 // class java/lang/StringBuffer
      20: dup
      21: ldc           #12                 // String Error:
      23: invokespecial #67                 // Method java/lang/StringBuffer."<init>":(Ljava/lang/String;)V
      26: aload_0
      27: invokevirtual #73                 // Method java/lang/StringBuffer.append:(Ljava/lang/String;)Ljava/lang/StringBuffer;
      30: invokevirtual #120                // Method java/lang/StringBuffer.toString:()Ljava/lang/String;
      33: invokevirtual #100                // Method java/io/PrintStream.println:(Ljava/lang/String;)V
      36: aload_0
      37: bipush        58
      39: bipush        95
      41: invokevirtual #104                // Method java/lang/String.replace:(CC)Ljava/lang/String;
      44: astore_0
      45: aload_0
      46: bipush        64
      48: bipush        95
      50: invokevirtual #104                // Method java/lang/String.replace:(CC)Ljava/lang/String;
      53: astore_0
      54: aload_0
      55: bipush        38
      57: bipush        95
      59: invokevirtual #104                // Method java/lang/String.replace:(CC)Ljava/lang/String;
      62: astore_0
      63: aload_0
      64: bipush        35
      66: bipush        95
      68: invokevirtual #104                // Method java/lang/String.replace:(CC)Ljava/lang/String;
      71: astore_0
      72: new           #50                 // class java/lang/StringBuffer
      75: dup
      76: ldc           #28                 // String reporterror
      78: invokespecial #67                 // Method java/lang/StringBuffer."<init>":(Ljava/lang/String;)V
      81: sipush        317
      84: invokevirtual #72                 // Method java/lang/StringBuffer.append:(I)Ljava/lang/StringBuffer;
      87: ldc           #5                  // String .cgi?error=
      89: invokevirtual #73                 // Method java/lang/StringBuffer.append:(Ljava/lang/String;)Ljava/lang/StringBuffer;
      92: getstatic     #82                 // Field errorname:Ljava/lang/String;
      95: invokevirtual #73                 // Method java/lang/StringBuffer.append:(Ljava/lang/String;)Ljava/lang/StringBuffer;
      98: ldc           #4                  // String
     100: invokevirtual #73                 // Method java/lang/StringBuffer.append:(Ljava/lang/String;)Ljava/lang/StringBuffer;
     103: aload_0
     104: invokevirtual #73                 // Method java/lang/StringBuffer.append:(Ljava/lang/String;)Ljava/lang/StringBuffer;
     107: invokevirtual #120                // Method java/lang/StringBuffer.toString:()Ljava/lang/String;
     110: invokestatic  #97                 // Method openurl:(Ljava/lang/String;)Ljava/io/DataInputStream;
     113: astore_1
     114: aload_1
     115: invokevirtual #103                // Method java/io/DataInputStream.readLine:()Ljava/lang/String;
     118: pop
     119: aload_1
     120: invokevirtual #77                 // Method java/io/FilterInputStream.close:()V
     123: return
     124: pop
     125: return
    Exception table:
       from    to  target type
          36   123   124   Class java/io/IOException

  public sign.signlink();
    Code:
       0: aload_0
       1: invokespecial #58                 // Method java/lang/Object."<init>":()V
       4: return

  static {};
    Code:
       0: bipush        32
       2: putstatic     #116                // Field storeid:I
       5: aconst_null
       6: putstatic     #74                 // Field cache_dat:Ljava/io/RandomAccessFile;
       9: iconst_5
      10: anewarray     #44                 // class java/io/RandomAccessFile
      13: putstatic     #75                 // Field cache_idx:[Ljava/io/RandomAccessFile;
      16: aconst_null
      17: putstatic     #91                 // Field mainapp:Ljava/applet/Applet;
      20: aconst_null
      21: putstatic     #112                // Field socket:Ljava/net/Socket;
      24: iconst_1
      25: putstatic     #119                // Field threadreqpri:I
      28: aconst_null
      29: putstatic     #118                // Field threadreq:Ljava/lang/Runnable;
      32: aconst_null
      33: putstatic     #81                 // Field dnsreq:Ljava/lang/String;
      36: aconst_null
      37: putstatic     #80                 // Field dns:Ljava/lang/String;
      40: aconst_null
      41: putstatic     #122                // Field urlreq:Ljava/lang/String;
      44: aconst_null
      45: putstatic     #123                // Field urlstream:Ljava/io/DataInputStream;
      48: aconst_null
      49: putstatic     #108                // Field savereq:Ljava/lang/String;
      52: aconst_null
      53: putstatic     #106                // Field savebuf:[B
      56: aconst_null
      57: putstatic     #92                 // Field midi:Ljava/lang/String;
      60: aconst_null
      61: putstatic     #125                // Field wave:Ljava/lang/String;
      64: iconst_1
      65: putstatic     #105                // Field reporterror:Z
      68: ldc           #1                  // String
      70: putstatic     #82                 // Field errorname:Ljava/lang/String;
      73: return
}
