Compiled from "Animable_Sub4.java"
final class Animable_Sub4 extends Animable {
  public final int anInt1571;

  public final int anInt1572;

  private double aDouble1574;

  private double aDouble1575;

  private double aDouble1576;

  private double aDouble1577;

  private double aDouble1578;

  private boolean aBoolean1579;

  private final int anInt1580;

  private final int anInt1581;

  private final int anInt1582;

  public final int anInt1583;

  public double aDouble1585;

  public double aDouble1586;

  public double aDouble1587;

  private final int anInt1588;

  private final int anInt1589;

  public final int anInt1590;

  private final SpotAnim aSpotAnim_1592;

  private int anInt1593;

  private int anInt1594;

  public int anInt1595;

  private int anInt1596;

  public final int anInt1597;

  public void method455(int, int, int, int);
    Code:
       0: aload_0
       1: getfield      #1                  // Field aBoolean1579:Z
       4: ifne          93
       7: iload         4
       9: aload_0
      10: getfield      #2                  // Field anInt1580:I
      13: isub
      14: i2d
      15: dstore        5
      17: iload_2
      18: aload_0
      19: getfield      #3                  // Field anInt1581:I
      22: isub
      23: i2d
      24: dstore        7
      26: dload         5
      28: dload         5
      30: dmul
      31: dload         7
      33: dload         7
      35: dmul
      36: dadd
      37: invokestatic  #4                  // Method java/lang/Math.sqrt:(D)D
      40: dstore        9
      42: aload_0
      43: aload_0
      44: getfield      #2                  // Field anInt1580:I
      47: i2d
      48: dload         5
      50: aload_0
      51: getfield      #5                  // Field anInt1589:I
      54: i2d
      55: dmul
      56: dload         9
      58: ddiv
      59: dadd
      60: putfield      #6                  // Field aDouble1585:D
      63: aload_0
      64: aload_0
      65: getfield      #3                  // Field anInt1581:I
      68: i2d
      69: dload         7
      71: aload_0
      72: getfield      #5                  // Field anInt1589:I
      75: i2d
      76: dmul
      77: dload         9
      79: ddiv
      80: dadd
      81: putfield      #7                  // Field aDouble1586:D
      84: aload_0
      85: aload_0
      86: getfield      #8                  // Field anInt1582:I
      89: i2d
      90: putfield      #9                  // Field aDouble1587:D
      93: aload_0
      94: getfield      #10                 // Field anInt1572:I
      97: iconst_1
      98: iadd
      99: iload_1
     100: isub
     101: i2d
     102: dstore        5
     104: aload_0
     105: iload         4
     107: i2d
     108: aload_0
     109: getfield      #6                  // Field aDouble1585:D
     112: dsub
     113: dload         5
     115: ddiv
     116: putfield      #11                 // Field aDouble1574:D
     119: aload_0
     120: iload_2
     121: i2d
     122: aload_0
     123: getfield      #7                  // Field aDouble1586:D
     126: dsub
     127: dload         5
     129: ddiv
     130: putfield      #12                 // Field aDouble1575:D
     133: aload_0
     134: aload_0
     135: getfield      #11                 // Field aDouble1574:D
     138: aload_0
     139: getfield      #11                 // Field aDouble1574:D
     142: dmul
     143: aload_0
     144: getfield      #12                 // Field aDouble1575:D
     147: aload_0
     148: getfield      #12                 // Field aDouble1575:D
     151: dmul
     152: dadd
     153: invokestatic  #4                  // Method java/lang/Math.sqrt:(D)D
     156: putfield      #13                 // Field aDouble1576:D
     159: aload_0
     160: getfield      #1                  // Field aBoolean1579:Z
     163: ifne          188
     166: aload_0
     167: aload_0
     168: getfield      #13                 // Field aDouble1576:D
     171: dneg
     172: aload_0
     173: getfield      #14                 // Field anInt1588:I
     176: i2d
     177: ldc2_w        #15                 // double 0.02454369d
     180: dmul
     181: invokestatic  #17                 // Method java/lang/Math.tan:(D)D
     184: dmul
     185: putfield      #18                 // Field aDouble1577:D
     188: aload_0
     189: ldc2_w        #19                 // double 2.0d
     192: iload_3
     193: i2d
     194: aload_0
     195: getfield      #9                  // Field aDouble1587:D
     198: dsub
     199: aload_0
     200: getfield      #18                 // Field aDouble1577:D
     203: dload         5
     205: dmul
     206: dsub
     207: dmul
     208: dload         5
     210: dload         5
     212: dmul
     213: ddiv
     214: putfield      #21                 // Field aDouble1578:D
     217: return

  public Model getRotatedModel();
    Code:
       0: aload_0
       1: getfield      #22                 // Field aSpotAnim_1592:LSpotAnim;
       4: invokevirtual #23                 // Method SpotAnim.getModel:()LModel;
       7: astore_1
       8: aload_1
       9: ifnonnull     14
      12: aconst_null
      13: areturn
      14: iconst_m1
      15: istore_2
      16: aload_0
      17: getfield      #22                 // Field aSpotAnim_1592:LSpotAnim;
      20: getfield      #24                 // Field SpotAnim.aAnimation_407:LAnimation;
      23: ifnull        42
      26: aload_0
      27: getfield      #22                 // Field aSpotAnim_1592:LSpotAnim;
      30: getfield      #24                 // Field SpotAnim.aAnimation_407:LAnimation;
      33: getfield      #25                 // Field Animation.anIntArray353:[I
      36: aload_0
      37: getfield      #26                 // Field anInt1593:I
      40: iaload
      41: istore_2
      42: new           #27                 // class Model
      45: dup
      46: iconst_1
      47: iload_2
      48: invokestatic  #28                 // Method Class36.method532:(I)Z
      51: iconst_0
      52: aload_1
      53: invokespecial #29                 // Method Model."<init>":(ZZZLModel;)V
      56: astore_3
      57: iload_2
      58: iconst_m1
      59: if_icmpeq     87
      62: aload_3
      63: invokevirtual #30                 // Method Model.method469:()V
      66: aload_3
      67: iload_2
      68: invokevirtual #31                 // Method Model.method470:(I)V
      71: aload_3
      72: aconst_null
      73: checkcast     #32                 // class "[[I"
      76: putfield      #33                 // Field Model.anIntArrayArray1658:[[I
      79: aload_3
      80: aconst_null
      81: checkcast     #32                 // class "[[I"
      84: putfield      #34                 // Field Model.anIntArrayArray1657:[[I
      87: aload_0
      88: getfield      #22                 // Field aSpotAnim_1592:LSpotAnim;
      91: getfield      #35                 // Field SpotAnim.anInt410:I
      94: sipush        128
      97: if_icmpne     113
     100: aload_0
     101: getfield      #22                 // Field aSpotAnim_1592:LSpotAnim;
     104: getfield      #36                 // Field SpotAnim.anInt411:I
     107: sipush        128
     110: if_icmpeq     138
     113: aload_3
     114: aload_0
     115: getfield      #22                 // Field aSpotAnim_1592:LSpotAnim;
     118: getfield      #35                 // Field SpotAnim.anInt410:I
     121: aload_0
     122: getfield      #22                 // Field aSpotAnim_1592:LSpotAnim;
     125: getfield      #35                 // Field SpotAnim.anInt410:I
     128: aload_0
     129: getfield      #22                 // Field aSpotAnim_1592:LSpotAnim;
     132: getfield      #36                 // Field SpotAnim.anInt411:I
     135: invokevirtual #37                 // Method Model.method478:(III)V
     138: aload_3
     139: aload_0
     140: getfield      #38                 // Field anInt1596:I
     143: invokevirtual #39                 // Method Model.method474:(I)V
     146: aload_3
     147: bipush        64
     149: aload_0
     150: getfield      #22                 // Field aSpotAnim_1592:LSpotAnim;
     153: getfield      #40                 // Field SpotAnim.anInt413:I
     156: iadd
     157: sipush        850
     160: aload_0
     161: getfield      #22                 // Field aSpotAnim_1592:LSpotAnim;
     164: getfield      #41                 // Field SpotAnim.anInt414:I
     167: iadd
     168: bipush        -30
     170: bipush        -50
     172: bipush        -30
     174: iconst_1
     175: invokevirtual #42                 // Method Model.method479:(IIIIIZ)V
     178: aload_3
     179: areturn

  public Animable_Sub4(int, int, int, int, int, int, int, int, int, int, int);
    Code:
       0: aload_0
       1: invokespecial #43                 // Method Animable."<init>":()V
       4: aload_0
       5: iconst_0
       6: putfield      #1                  // Field aBoolean1579:Z
       9: aload_0
      10: getstatic     #44                 // Field SpotAnim.cache:[LSpotAnim;
      13: iload         11
      15: aaload
      16: putfield      #22                 // Field aSpotAnim_1592:LSpotAnim;
      19: aload_0
      20: iload         6
      22: putfield      #45                 // Field anInt1597:I
      25: aload_0
      26: iload         9
      28: putfield      #2                  // Field anInt1580:I
      31: aload_0
      32: iload         8
      34: putfield      #3                  // Field anInt1581:I
      37: aload_0
      38: iload         7
      40: putfield      #8                  // Field anInt1582:I
      43: aload_0
      44: iload_3
      45: putfield      #46                 // Field anInt1571:I
      48: aload_0
      49: iload         4
      51: putfield      #10                 // Field anInt1572:I
      54: aload_0
      55: iload_1
      56: putfield      #14                 // Field anInt1588:I
      59: aload_0
      60: iload         5
      62: putfield      #5                  // Field anInt1589:I
      65: aload_0
      66: iload         10
      68: putfield      #47                 // Field anInt1590:I
      71: aload_0
      72: iload_2
      73: putfield      #48                 // Field anInt1583:I
      76: aload_0
      77: iconst_0
      78: putfield      #1                  // Field aBoolean1579:Z
      81: return

  public void method456(int);
    Code:
       0: aload_0
       1: iconst_1
       2: putfield      #1                  // Field aBoolean1579:Z
       5: aload_0
       6: dup
       7: getfield      #6                  // Field aDouble1585:D
      10: aload_0
      11: getfield      #11                 // Field aDouble1574:D
      14: iload_1
      15: i2d
      16: dmul
      17: dadd
      18: putfield      #6                  // Field aDouble1585:D
      21: aload_0
      22: dup
      23: getfield      #7                  // Field aDouble1586:D
      26: aload_0
      27: getfield      #12                 // Field aDouble1575:D
      30: iload_1
      31: i2d
      32: dmul
      33: dadd
      34: putfield      #7                  // Field aDouble1586:D
      37: aload_0
      38: dup
      39: getfield      #9                  // Field aDouble1587:D
      42: aload_0
      43: getfield      #18                 // Field aDouble1577:D
      46: iload_1
      47: i2d
      48: dmul
      49: ldc2_w        #49                 // double 0.5d
      52: aload_0
      53: getfield      #21                 // Field aDouble1578:D
      56: dmul
      57: iload_1
      58: i2d
      59: dmul
      60: iload_1
      61: i2d
      62: dmul
      63: dadd
      64: dadd
      65: putfield      #9                  // Field aDouble1587:D
      68: aload_0
      69: dup
      70: getfield      #18                 // Field aDouble1577:D
      73: aload_0
      74: getfield      #21                 // Field aDouble1578:D
      77: iload_1
      78: i2d
      79: dmul
      80: dadd
      81: putfield      #18                 // Field aDouble1577:D
      84: aload_0
      85: aload_0
      86: getfield      #11                 // Field aDouble1574:D
      89: aload_0
      90: getfield      #12                 // Field aDouble1575:D
      93: invokestatic  #51                 // Method java/lang/Math.atan2:(DD)D
      96: ldc2_w        #52                 // double 325.949d
      99: dmul
     100: d2i
     101: sipush        1024
     104: iadd
     105: sipush        2047
     108: iand
     109: putfield      #54                 // Field anInt1595:I
     112: aload_0
     113: aload_0
     114: getfield      #18                 // Field aDouble1577:D
     117: aload_0
     118: getfield      #13                 // Field aDouble1576:D
     121: invokestatic  #51                 // Method java/lang/Math.atan2:(DD)D
     124: ldc2_w        #52                 // double 325.949d
     127: dmul
     128: d2i
     129: sipush        2047
     132: iand
     133: putfield      #38                 // Field anInt1596:I
     136: aload_0
     137: getfield      #22                 // Field aSpotAnim_1592:LSpotAnim;
     140: getfield      #24                 // Field SpotAnim.aAnimation_407:LAnimation;
     143: ifnull        237
     146: aload_0
     147: dup
     148: getfield      #55                 // Field anInt1594:I
     151: iload_1
     152: iadd
     153: putfield      #55                 // Field anInt1594:I
     156: aload_0
     157: getfield      #55                 // Field anInt1594:I
     160: aload_0
     161: getfield      #22                 // Field aSpotAnim_1592:LSpotAnim;
     164: getfield      #24                 // Field SpotAnim.aAnimation_407:LAnimation;
     167: aload_0
     168: getfield      #26                 // Field anInt1593:I
     171: invokevirtual #56                 // Method Animation.method258:(I)I
     174: if_icmple     237
     177: aload_0
     178: dup
     179: getfield      #55                 // Field anInt1594:I
     182: aload_0
     183: getfield      #22                 // Field aSpotAnim_1592:LSpotAnim;
     186: getfield      #24                 // Field SpotAnim.aAnimation_407:LAnimation;
     189: aload_0
     190: getfield      #26                 // Field anInt1593:I
     193: invokevirtual #56                 // Method Animation.method258:(I)I
     196: iconst_1
     197: iadd
     198: isub
     199: putfield      #55                 // Field anInt1594:I
     202: aload_0
     203: dup
     204: getfield      #26                 // Field anInt1593:I
     207: iconst_1
     208: iadd
     209: putfield      #26                 // Field anInt1593:I
     212: aload_0
     213: getfield      #26                 // Field anInt1593:I
     216: aload_0
     217: getfield      #22                 // Field aSpotAnim_1592:LSpotAnim;
     220: getfield      #24                 // Field SpotAnim.aAnimation_407:LAnimation;
     223: getfield      #57                 // Field Animation.anInt352:I
     226: if_icmplt     156
     229: aload_0
     230: iconst_0
     231: putfield      #26                 // Field anInt1593:I
     234: goto          156
     237: return
}
