Compiled from "Animation.java"
public final class Animation {
  public static Animation[] anims;

  public int anInt352;

  public int[] anIntArray353;

  public int[] anIntArray354;

  private int[] anIntArray355;

  public int anInt356;

  public int[] anIntArray357;

  public boolean aBoolean358;

  public int anInt359;

  public int anInt360;

  public int anInt361;

  public int anInt362;

  public int anInt363;

  public int anInt364;

  public int anInt365;

  public static int anInt367;

  public static void unpackConfig(StreamLoader);
    Code:
       0: new           #1                  // class Stream
       3: dup
       4: aload_0
       5: ldc           #2                  // String seq.dat
       7: invokevirtual #3                  // Method StreamLoader.getDataForName:(Ljava/lang/String;)[B
      10: invokespecial #4                  // Method Stream."<init>":([B)V
      13: astore_1
      14: aload_1
      15: invokevirtual #5                  // Method Stream.readUnsignedWord:()I
      18: istore_2
      19: getstatic     #6                  // Field anims:[LAnimation;
      22: ifnonnull     32
      25: iload_2
      26: anewarray     #7                  // class Animation
      29: putstatic     #6                  // Field anims:[LAnimation;
      32: iconst_0
      33: istore_3
      34: iload_3
      35: iload_2
      36: if_icmpge     74
      39: getstatic     #6                  // Field anims:[LAnimation;
      42: iload_3
      43: aaload
      44: ifnonnull     59
      47: getstatic     #6                  // Field anims:[LAnimation;
      50: iload_3
      51: new           #7                  // class Animation
      54: dup
      55: invokespecial #8                  // Method "<init>":()V
      58: aastore
      59: getstatic     #6                  // Field anims:[LAnimation;
      62: iload_3
      63: aaload
      64: aload_1
      65: invokespecial #9                  // Method readValues:(LStream;)V
      68: iinc          3, 1
      71: goto          34
      74: return

  public int method258(int);
    Code:
       0: aload_0
       1: getfield      #10                 // Field anIntArray355:[I
       4: iload_1
       5: iaload
       6: istore_2
       7: iload_2
       8: ifne          37
      11: aload_0
      12: getfield      #11                 // Field anIntArray353:[I
      15: iload_1
      16: iaload
      17: invokestatic  #12                 // Method Class36.method531:(I)LClass36;
      20: astore_3
      21: aload_3
      22: ifnull        37
      25: aload_0
      26: getfield      #10                 // Field anIntArray355:[I
      29: iload_1
      30: aload_3
      31: getfield      #13                 // Field Class36.anInt636:I
      34: dup_x2
      35: iastore
      36: istore_2
      37: iload_2
      38: ifne          43
      41: iconst_1
      42: istore_2
      43: iload_2
      44: ireturn

  private void readValues(Stream);
    Code:
       0: aload_1
       1: invokevirtual #14                 // Method Stream.readUnsignedByte:()I
       4: istore_2
       5: iload_2
       6: ifne          12
       9: goto          367
      12: iload_2
      13: iconst_1
      14: if_icmpne     122
      17: aload_0
      18: aload_1
      19: invokevirtual #14                 // Method Stream.readUnsignedByte:()I
      22: putfield      #15                 // Field anInt352:I
      25: aload_0
      26: aload_0
      27: getfield      #15                 // Field anInt352:I
      30: newarray       int
      32: putfield      #11                 // Field anIntArray353:[I
      35: aload_0
      36: aload_0
      37: getfield      #15                 // Field anInt352:I
      40: newarray       int
      42: putfield      #16                 // Field anIntArray354:[I
      45: aload_0
      46: aload_0
      47: getfield      #15                 // Field anInt352:I
      50: newarray       int
      52: putfield      #10                 // Field anIntArray355:[I
      55: iconst_0
      56: istore_3
      57: iload_3
      58: aload_0
      59: getfield      #15                 // Field anInt352:I
      62: if_icmpge     119
      65: aload_0
      66: getfield      #11                 // Field anIntArray353:[I
      69: iload_3
      70: aload_1
      71: invokevirtual #5                  // Method Stream.readUnsignedWord:()I
      74: iastore
      75: aload_0
      76: getfield      #16                 // Field anIntArray354:[I
      79: iload_3
      80: aload_1
      81: invokevirtual #5                  // Method Stream.readUnsignedWord:()I
      84: iastore
      85: aload_0
      86: getfield      #16                 // Field anIntArray354:[I
      89: iload_3
      90: iaload
      91: ldc           #17                 // int 65535
      93: if_icmpne     103
      96: aload_0
      97: getfield      #16                 // Field anIntArray354:[I
     100: iload_3
     101: iconst_m1
     102: iastore
     103: aload_0
     104: getfield      #10                 // Field anIntArray355:[I
     107: iload_3
     108: aload_1
     109: invokevirtual #5                  // Method Stream.readUnsignedWord:()I
     112: iastore
     113: iinc          3, 1
     116: goto          57
     119: goto          364
     122: iload_2
     123: iconst_2
     124: if_icmpne     138
     127: aload_0
     128: aload_1
     129: invokevirtual #5                  // Method Stream.readUnsignedWord:()I
     132: putfield      #18                 // Field anInt356:I
     135: goto          364
     138: iload_2
     139: iconst_3
     140: if_icmpne     194
     143: aload_1
     144: invokevirtual #14                 // Method Stream.readUnsignedByte:()I
     147: istore_3
     148: aload_0
     149: iload_3
     150: iconst_1
     151: iadd
     152: newarray       int
     154: putfield      #19                 // Field anIntArray357:[I
     157: iconst_0
     158: istore        4
     160: iload         4
     162: iload_3
     163: if_icmpge     183
     166: aload_0
     167: getfield      #19                 // Field anIntArray357:[I
     170: iload         4
     172: aload_1
     173: invokevirtual #14                 // Method Stream.readUnsignedByte:()I
     176: iastore
     177: iinc          4, 1
     180: goto          160
     183: aload_0
     184: getfield      #19                 // Field anIntArray357:[I
     187: iload_3
     188: ldc           #20                 // int 9999999
     190: iastore
     191: goto          364
     194: iload_2
     195: iconst_4
     196: if_icmpne     207
     199: aload_0
     200: iconst_1
     201: putfield      #21                 // Field aBoolean358:Z
     204: goto          364
     207: iload_2
     208: iconst_5
     209: if_icmpne     223
     212: aload_0
     213: aload_1
     214: invokevirtual #14                 // Method Stream.readUnsignedByte:()I
     217: putfield      #22                 // Field anInt359:I
     220: goto          364
     223: iload_2
     224: bipush        6
     226: if_icmpne     240
     229: aload_0
     230: aload_1
     231: invokevirtual #5                  // Method Stream.readUnsignedWord:()I
     234: putfield      #23                 // Field anInt360:I
     237: goto          364
     240: iload_2
     241: bipush        7
     243: if_icmpne     257
     246: aload_0
     247: aload_1
     248: invokevirtual #5                  // Method Stream.readUnsignedWord:()I
     251: putfield      #24                 // Field anInt361:I
     254: goto          364
     257: iload_2
     258: bipush        8
     260: if_icmpne     274
     263: aload_0
     264: aload_1
     265: invokevirtual #14                 // Method Stream.readUnsignedByte:()I
     268: putfield      #25                 // Field anInt362:I
     271: goto          364
     274: iload_2
     275: bipush        9
     277: if_icmpne     291
     280: aload_0
     281: aload_1
     282: invokevirtual #14                 // Method Stream.readUnsignedByte:()I
     285: putfield      #26                 // Field anInt363:I
     288: goto          364
     291: iload_2
     292: bipush        10
     294: if_icmpne     308
     297: aload_0
     298: aload_1
     299: invokevirtual #14                 // Method Stream.readUnsignedByte:()I
     302: putfield      #27                 // Field anInt364:I
     305: goto          364
     308: iload_2
     309: bipush        11
     311: if_icmpne     325
     314: aload_0
     315: aload_1
     316: invokevirtual #14                 // Method Stream.readUnsignedByte:()I
     319: putfield      #28                 // Field anInt365:I
     322: goto          364
     325: iload_2
     326: bipush        12
     328: if_icmpne     339
     331: aload_1
     332: invokevirtual #29                 // Method Stream.readDWord:()I
     335: pop
     336: goto          364
     339: getstatic     #30                 // Field java/lang/System.out:Ljava/io/PrintStream;
     342: new           #31                 // class java/lang/StringBuilder
     345: dup
     346: invokespecial #32                 // Method java/lang/StringBuilder."<init>":()V
     349: ldc           #33                 // String Error unrecognised seq config code:
     351: invokevirtual #34                 // Method java/lang/StringBuilder.append:(Ljava/lang/String;)Ljava/lang/StringBuilder;
     354: iload_2
     355: invokevirtual #35                 // Method java/lang/StringBuilder.append:(I)Ljava/lang/StringBuilder;
     358: invokevirtual #36                 // Method java/lang/StringBuilder.toString:()Ljava/lang/String;
     361: invokevirtual #37                 // Method java/io/PrintStream.println:(Ljava/lang/String;)V
     364: goto          0
     367: aload_0
     368: getfield      #15                 // Field anInt352:I
     371: ifne          421
     374: aload_0
     375: iconst_1
     376: putfield      #15                 // Field anInt352:I
     379: aload_0
     380: iconst_1
     381: newarray       int
     383: putfield      #11                 // Field anIntArray353:[I
     386: aload_0
     387: getfield      #11                 // Field anIntArray353:[I
     390: iconst_0
     391: iconst_m1
     392: iastore
     393: aload_0
     394: iconst_1
     395: newarray       int
     397: putfield      #16                 // Field anIntArray354:[I
     400: aload_0
     401: getfield      #16                 // Field anIntArray354:[I
     404: iconst_0
     405: iconst_m1
     406: iastore
     407: aload_0
     408: iconst_1
     409: newarray       int
     411: putfield      #10                 // Field anIntArray355:[I
     414: aload_0
     415: getfield      #10                 // Field anIntArray355:[I
     418: iconst_0
     419: iconst_m1
     420: iastore
     421: aload_0
     422: getfield      #26                 // Field anInt363:I
     425: iconst_m1
     426: if_icmpne     449
     429: aload_0
     430: getfield      #19                 // Field anIntArray357:[I
     433: ifnull        444
     436: aload_0
     437: iconst_2
     438: putfield      #26                 // Field anInt363:I
     441: goto          449
     444: aload_0
     445: iconst_0
     446: putfield      #26                 // Field anInt363:I
     449: aload_0
     450: getfield      #27                 // Field anInt364:I
     453: iconst_m1
     454: if_icmpne     475
     457: aload_0
     458: getfield      #19                 // Field anIntArray357:[I
     461: ifnull        470
     464: aload_0
     465: iconst_2
     466: putfield      #27                 // Field anInt364:I
     469: return
     470: aload_0
     471: iconst_0
     472: putfield      #27                 // Field anInt364:I
     475: return

  private Animation();
    Code:
       0: aload_0
       1: invokespecial #38                 // Method java/lang/Object."<init>":()V
       4: aload_0
       5: iconst_m1
       6: putfield      #18                 // Field anInt356:I
       9: aload_0
      10: iconst_0
      11: putfield      #21                 // Field aBoolean358:Z
      14: aload_0
      15: iconst_5
      16: putfield      #22                 // Field anInt359:I
      19: aload_0
      20: iconst_m1
      21: putfield      #23                 // Field anInt360:I
      24: aload_0
      25: iconst_m1
      26: putfield      #24                 // Field anInt361:I
      29: aload_0
      30: bipush        99
      32: putfield      #25                 // Field anInt362:I
      35: aload_0
      36: iconst_m1
      37: putfield      #26                 // Field anInt363:I
      40: aload_0
      41: iconst_m1
      42: putfield      #27                 // Field anInt364:I
      45: aload_0
      46: iconst_2
      47: putfield      #28                 // Field anInt365:I
      50: return
}
