Compiled from "Censor.java"
final class Censor {
  private static int[] anIntArray620;

  private static char[][] aCharArrayArray621;

  private static byte[][][] aByteArrayArrayArray622;

  private static char[][] aCharArrayArray623;

  private static char[][] aCharArrayArray624;

  private static int[] anIntArray625;

  private static final java.lang.String[] exceptions;

  Censor();
    Code:
       0: aload_0
       1: invokespecial #1                  // Method java/lang/Object."<init>":()V
       4: return

  public static void loadConfig(StreamLoader);
    Code:
       0: new           #2                  // class Stream
       3: dup
       4: aload_0
       5: ldc           #3                  // String fragmentsenc.txt
       7: invokevirtual #4                  // Method StreamLoader.getDataForName:(Ljava/lang/String;)[B
      10: invokespecial #5                  // Method Stream."<init>":([B)V
      13: astore_1
      14: new           #2                  // class Stream
      17: dup
      18: aload_0
      19: ldc           #6                  // String badenc.txt
      21: invokevirtual #4                  // Method StreamLoader.getDataForName:(Ljava/lang/String;)[B
      24: invokespecial #5                  // Method Stream."<init>":([B)V
      27: astore_2
      28: new           #2                  // class Stream
      31: dup
      32: aload_0
      33: ldc           #7                  // String domainenc.txt
      35: invokevirtual #4                  // Method StreamLoader.getDataForName:(Ljava/lang/String;)[B
      38: invokespecial #5                  // Method Stream."<init>":([B)V
      41: astore_3
      42: new           #2                  // class Stream
      45: dup
      46: aload_0
      47: ldc           #8                  // String tldlist.txt
      49: invokevirtual #4                  // Method StreamLoader.getDataForName:(Ljava/lang/String;)[B
      52: invokespecial #5                  // Method Stream."<init>":([B)V
      55: astore        4
      57: aload_1
      58: aload_2
      59: aload_3
      60: aload         4
      62: invokestatic  #9                  // Method readValues:(LStream;LStream;LStream;LStream;)V
      65: return

  private static void readValues(Stream, Stream, Stream, Stream);
    Code:
       0: aload_1
       1: invokestatic  #10                 // Method readBadEnc:(LStream;)V
       4: aload_2
       5: invokestatic  #11                 // Method readDomainEnc:(LStream;)V
       8: aload_0
       9: invokestatic  #12                 // Method readFragmentsEnc:(LStream;)V
      12: aload_3
      13: invokestatic  #13                 // Method readTldList:(LStream;)V
      16: return

  private static void readTldList(Stream);
    Code:
       0: aload_0
       1: invokevirtual #14                 // Method Stream.readDWord:()I
       4: istore_1
       5: iload_1
       6: anewarray     #15                 // class "[C"
       9: putstatic     #16                 // Field aCharArrayArray624:[[C
      12: iload_1
      13: newarray       int
      15: putstatic     #17                 // Field anIntArray625:[I
      18: iconst_0
      19: istore_2
      20: iload_2
      21: iload_1
      22: if_icmpge     78
      25: getstatic     #17                 // Field anIntArray625:[I
      28: iload_2
      29: aload_0
      30: invokevirtual #18                 // Method Stream.readUnsignedByte:()I
      33: iastore
      34: aload_0
      35: invokevirtual #18                 // Method Stream.readUnsignedByte:()I
      38: newarray       char
      40: astore_3
      41: iconst_0
      42: istore        4
      44: iload         4
      46: aload_3
      47: arraylength
      48: if_icmpge     66
      51: aload_3
      52: iload         4
      54: aload_0
      55: invokevirtual #18                 // Method Stream.readUnsignedByte:()I
      58: i2c
      59: castore
      60: iinc          4, 1
      63: goto          44
      66: getstatic     #16                 // Field aCharArrayArray624:[[C
      69: iload_2
      70: aload_3
      71: aastore
      72: iinc          2, 1
      75: goto          20
      78: return

  private static void readBadEnc(Stream);
    Code:
       0: aload_0
       1: invokevirtual #14                 // Method Stream.readDWord:()I
       4: istore_1
       5: iload_1
       6: anewarray     #15                 // class "[C"
       9: putstatic     #19                 // Field aCharArrayArray621:[[C
      12: iload_1
      13: anewarray     #20                 // class "[[B"
      16: putstatic     #21                 // Field aByteArrayArrayArray622:[[[B
      19: aload_0
      20: getstatic     #19                 // Field aCharArrayArray621:[[C
      23: getstatic     #21                 // Field aByteArrayArrayArray622:[[[B
      26: invokestatic  #22                 // Method method493:(LStream;[[C[[[B)V
      29: return

  private static void readDomainEnc(Stream);
    Code:
       0: aload_0
       1: invokevirtual #14                 // Method Stream.readDWord:()I
       4: istore_1
       5: iload_1
       6: anewarray     #15                 // class "[C"
       9: putstatic     #23                 // Field aCharArrayArray623:[[C
      12: getstatic     #23                 // Field aCharArrayArray623:[[C
      15: aload_0
      16: invokestatic  #24                 // Method method494:([[CLStream;)V
      19: return

  private static void readFragmentsEnc(Stream);
    Code:
       0: aload_0
       1: invokevirtual #14                 // Method Stream.readDWord:()I
       4: newarray       int
       6: putstatic     #25                 // Field anIntArray620:[I
       9: iconst_0
      10: istore_1
      11: iload_1
      12: getstatic     #25                 // Field anIntArray620:[I
      15: arraylength
      16: if_icmpge     34
      19: getstatic     #25                 // Field anIntArray620:[I
      22: iload_1
      23: aload_0
      24: invokevirtual #26                 // Method Stream.readUnsignedWord:()I
      27: iastore
      28: iinc          1, 1
      31: goto          11
      34: return

  private static void method493(Stream, char[][], byte[][][]);
    Code:
       0: iconst_0
       1: istore_3
       2: iload_3
       3: aload_1
       4: arraylength
       5: if_icmpge     117
       8: aload_0
       9: invokevirtual #18                 // Method Stream.readUnsignedByte:()I
      12: newarray       char
      14: astore        4
      16: iconst_0
      17: istore        5
      19: iload         5
      21: aload         4
      23: arraylength
      24: if_icmpge     43
      27: aload         4
      29: iload         5
      31: aload_0
      32: invokevirtual #18                 // Method Stream.readUnsignedByte:()I
      35: i2c
      36: castore
      37: iinc          5, 1
      40: goto          19
      43: aload_1
      44: iload_3
      45: aload         4
      47: aastore
      48: aload_0
      49: invokevirtual #18                 // Method Stream.readUnsignedByte:()I
      52: iconst_2
      53: multianewarray #20,  2            // class "[[B"
      57: astore        5
      59: iconst_0
      60: istore        6
      62: iload         6
      64: aload         5
      66: arraylength
      67: if_icmpge     100
      70: aload         5
      72: iload         6
      74: aaload
      75: iconst_0
      76: aload_0
      77: invokevirtual #18                 // Method Stream.readUnsignedByte:()I
      80: i2b
      81: bastore
      82: aload         5
      84: iload         6
      86: aaload
      87: iconst_1
      88: aload_0
      89: invokevirtual #18                 // Method Stream.readUnsignedByte:()I
      92: i2b
      93: bastore
      94: iinc          6, 1
      97: goto          62
     100: aload         5
     102: arraylength
     103: ifle          111
     106: aload_2
     107: iload_3
     108: aload         5
     110: aastore
     111: iinc          3, 1
     114: goto          2
     117: return

  private static void method494(char[][], Stream);
    Code:
       0: iconst_0
       1: istore_2
       2: iload_2
       3: aload_0
       4: arraylength
       5: if_icmpge     50
       8: aload_1
       9: invokevirtual #18                 // Method Stream.readUnsignedByte:()I
      12: newarray       char
      14: astore_3
      15: iconst_0
      16: istore        4
      18: iload         4
      20: aload_3
      21: arraylength
      22: if_icmpge     40
      25: aload_3
      26: iload         4
      28: aload_1
      29: invokevirtual #18                 // Method Stream.readUnsignedByte:()I
      32: i2c
      33: castore
      34: iinc          4, 1
      37: goto          18
      40: aload_0
      41: iload_2
      42: aload_3
      43: aastore
      44: iinc          2, 1
      47: goto          2
      50: return

  private static void method495(char[]);
    Code:
       0: iconst_0
       1: istore_1
       2: iconst_0
       3: istore_2
       4: iload_2
       5: aload_0
       6: arraylength
       7: if_icmpge     64
      10: aload_0
      11: iload_2
      12: caload
      13: invokestatic  #27                 // Method method496:(C)Z
      16: ifeq          28
      19: aload_0
      20: iload_1
      21: aload_0
      22: iload_2
      23: caload
      24: castore
      25: goto          33
      28: aload_0
      29: iload_1
      30: bipush        32
      32: castore
      33: iload_1
      34: ifeq          55
      37: aload_0
      38: iload_1
      39: caload
      40: bipush        32
      42: if_icmpne     55
      45: aload_0
      46: iload_1
      47: iconst_1
      48: isub
      49: caload
      50: bipush        32
      52: if_icmpeq     58
      55: iinc          1, 1
      58: iinc          2, 1
      61: goto          4
      64: iload_1
      65: istore_2
      66: iload_2
      67: aload_0
      68: arraylength
      69: if_icmpge     83
      72: aload_0
      73: iload_2
      74: bipush        32
      76: castore
      77: iinc          2, 1
      80: goto          66
      83: return

  private static boolean method496(char);
    Code:
       0: iload_0
       1: bipush        32
       3: if_icmplt     12
       6: iload_0
       7: bipush        127
       9: if_icmple     44
      12: iload_0
      13: bipush        32
      15: if_icmpeq     44
      18: iload_0
      19: bipush        10
      21: if_icmpeq     44
      24: iload_0
      25: bipush        9
      27: if_icmpeq     44
      30: iload_0
      31: sipush        163
      34: if_icmpeq     44
      37: iload_0
      38: sipush        8364
      41: if_icmpne     48
      44: iconst_1
      45: goto          49
      48: iconst_0
      49: ireturn

  public static java.lang.String doCensor(java.lang.String);
    Code:
       0: invokestatic  #28                 // Method java/lang/System.currentTimeMillis:()J
       3: lstore_1
       4: aload_0
       5: invokevirtual #29                 // Method java/lang/String.toCharArray:()[C
       8: astore_3
       9: aload_3
      10: invokestatic  #30                 // Method method495:([C)V
      13: new           #31                 // class java/lang/String
      16: dup
      17: aload_3
      18: invokespecial #32                 // Method java/lang/String."<init>":([C)V
      21: invokevirtual #33                 // Method java/lang/String.trim:()Ljava/lang/String;
      24: astore        4
      26: aload         4
      28: invokevirtual #34                 // Method java/lang/String.toLowerCase:()Ljava/lang/String;
      31: invokevirtual #29                 // Method java/lang/String.toCharArray:()[C
      34: astore_3
      35: aload         4
      37: invokevirtual #34                 // Method java/lang/String.toLowerCase:()Ljava/lang/String;
      40: astore        5
      42: aload_3
      43: invokestatic  #35                 // Method method505:([C)V
      46: aload_3
      47: invokestatic  #36                 // Method method500:([C)V
      50: aload_3
      51: invokestatic  #37                 // Method method501:([C)V
      54: aload_3
      55: invokestatic  #38                 // Method method514:([C)V
      58: iconst_0
      59: istore        6
      61: iload         6
      63: getstatic     #39                 // Field exceptions:[Ljava/lang/String;
      66: arraylength
      67: if_icmpge     127
      70: iconst_m1
      71: istore        7
      73: aload         5
      75: getstatic     #39                 // Field exceptions:[Ljava/lang/String;
      78: iload         6
      80: aaload
      81: iload         7
      83: iconst_1
      84: iadd
      85: invokevirtual #40                 // Method java/lang/String.indexOf:(Ljava/lang/String;I)I
      88: dup
      89: istore        7
      91: iconst_m1
      92: if_icmpeq     121
      95: getstatic     #39                 // Field exceptions:[Ljava/lang/String;
      98: iload         6
     100: aaload
     101: invokevirtual #29                 // Method java/lang/String.toCharArray:()[C
     104: astore        8
     106: aload         8
     108: iconst_0
     109: aload_3
     110: iload         7
     112: aload         8
     114: arraylength
     115: invokestatic  #41                 // Method java/lang/System.arraycopy:(Ljava/lang/Object;ILjava/lang/Object;II)V
     118: goto          73
     121: iinc          6, 1
     124: goto          61
     127: aload         4
     129: invokevirtual #29                 // Method java/lang/String.toCharArray:()[C
     132: aload_3
     133: invokestatic  #42                 // Method method498:([C[C)V
     136: aload_3
     137: invokestatic  #43                 // Method method499:([C)V
     140: invokestatic  #28                 // Method java/lang/System.currentTimeMillis:()J
     143: lstore        6
     145: new           #31                 // class java/lang/String
     148: dup
     149: aload_3
     150: invokespecial #32                 // Method java/lang/String."<init>":([C)V
     153: invokevirtual #33                 // Method java/lang/String.trim:()Ljava/lang/String;
     156: areturn

  private static void method498(char[], char[]);
    Code:
       0: iconst_0
       1: istore_2
       2: iload_2
       3: aload_0
       4: arraylength
       5: if_icmpge     37
       8: aload_1
       9: iload_2
      10: caload
      11: bipush        42
      13: if_icmpeq     31
      16: aload_0
      17: iload_2
      18: caload
      19: invokestatic  #44                 // Method isUpperCaseLetter:(C)Z
      22: ifeq          31
      25: aload_1
      26: iload_2
      27: aload_0
      28: iload_2
      29: caload
      30: castore
      31: iinc          2, 1
      34: goto          2
      37: return

  private static void method499(char[]);
    Code:
       0: iconst_1
       1: istore_1
       2: iconst_0
       3: istore_2
       4: iload_2
       5: aload_0
       6: arraylength
       7: if_icmpge     66
      10: aload_0
      11: iload_2
      12: caload
      13: istore_3
      14: iload_3
      15: invokestatic  #45                 // Method isLetter:(C)Z
      18: ifeq          58
      21: iload_1
      22: ifeq          37
      25: iload_3
      26: invokestatic  #46                 // Method isLowerCaseLetter:(C)Z
      29: ifeq          60
      32: iconst_0
      33: istore_1
      34: goto          60
      37: iload_3
      38: invokestatic  #44                 // Method isUpperCaseLetter:(C)Z
      41: ifeq          60
      44: aload_0
      45: iload_2
      46: iload_3
      47: bipush        97
      49: iadd
      50: bipush        65
      52: isub
      53: i2c
      54: castore
      55: goto          60
      58: iconst_1
      59: istore_1
      60: iinc          2, 1
      63: goto          4
      66: return

  private static void method500(char[]);
    Code:
       0: iconst_0
       1: istore_1
       2: iload_1
       3: iconst_2
       4: if_icmpge     44
       7: getstatic     #19                 // Field aCharArrayArray621:[[C
      10: arraylength
      11: iconst_1
      12: isub
      13: istore_2
      14: iload_2
      15: iflt          38
      18: getstatic     #21                 // Field aByteArrayArrayArray622:[[[B
      21: iload_2
      22: aaload
      23: aload_0
      24: getstatic     #19                 // Field aCharArrayArray621:[[C
      27: iload_2
      28: aaload
      29: invokestatic  #47                 // Method method509:([[B[C[C)V
      32: iinc          2, -1
      35: goto          14
      38: iinc          1, 1
      41: goto          2
      44: return

  private static void method501(char[]);
    Code:
       0: aload_0
       1: invokevirtual #48                 // Method "[C".clone:()Ljava/lang/Object;
       4: checkcast     #15                 // class "[C"
       7: astore_1
       8: iconst_3
       9: newarray       char
      11: dup
      12: iconst_0
      13: bipush        40
      15: castore
      16: dup
      17: iconst_1
      18: bipush        97
      20: castore
      21: dup
      22: iconst_2
      23: bipush        41
      25: castore
      26: astore_2
      27: aconst_null
      28: checkcast     #20                 // class "[[B"
      31: aload_1
      32: aload_2
      33: invokestatic  #47                 // Method method509:([[B[C[C)V
      36: aload_0
      37: invokevirtual #49                 // Method "[C".clone:()Ljava/lang/Object;
      40: checkcast     #15                 // class "[C"
      43: astore_3
      44: iconst_3
      45: newarray       char
      47: dup
      48: iconst_0
      49: bipush        100
      51: castore
      52: dup
      53: iconst_1
      54: bipush        111
      56: castore
      57: dup
      58: iconst_2
      59: bipush        116
      61: castore
      62: astore        4
      64: aconst_null
      65: checkcast     #20                 // class "[[B"
      68: aload_3
      69: aload         4
      71: invokestatic  #47                 // Method method509:([[B[C[C)V
      74: getstatic     #23                 // Field aCharArrayArray623:[[C
      77: arraylength
      78: iconst_1
      79: isub
      80: istore        5
      82: iload         5
      84: iflt          105
      87: aload_0
      88: getstatic     #23                 // Field aCharArrayArray623:[[C
      91: iload         5
      93: aaload
      94: aload_3
      95: aload_1
      96: invokestatic  #50                 // Method method502:([C[C[C[C)V
      99: iinc          5, -1
     102: goto          82
     105: return

  private static void method502(char[], char[], char[], char[]);
    Code:
       0: aload_1
       1: arraylength
       2: aload_0
       3: arraylength
       4: if_icmple     8
       7: return
       8: iconst_0
       9: istore        5
      11: iload         5
      13: aload_0
      14: arraylength
      15: aload_1
      16: arraylength
      17: isub
      18: if_icmpgt     254
      21: iload         5
      23: istore        6
      25: iconst_0
      26: istore        7
      28: iconst_1
      29: istore        4
      31: iload         6
      33: aload_0
      34: arraylength
      35: if_icmpge     171
      38: aload_0
      39: iload         6
      41: caload
      42: istore        9
      44: iconst_0
      45: istore        10
      47: iload         6
      49: iconst_1
      50: iadd
      51: aload_0
      52: arraylength
      53: if_icmpge     64
      56: aload_0
      57: iload         6
      59: iconst_1
      60: iadd
      61: caload
      62: istore        10
      64: iload         7
      66: aload_1
      67: arraylength
      68: if_icmpge     101
      71: iload         9
      73: aload_1
      74: iload         7
      76: caload
      77: iload         10
      79: invokestatic  #51                 // Method method511:(CCC)I
      82: dup
      83: istore        8
      85: ifle          101
      88: iload         6
      90: iload         8
      92: iadd
      93: istore        6
      95: iinc          7, 1
      98: goto          31
     101: iload         7
     103: ifne          109
     106: goto          171
     109: iload         9
     111: aload_1
     112: iload         7
     114: iconst_1
     115: isub
     116: caload
     117: iload         10
     119: invokestatic  #51                 // Method method511:(CCC)I
     122: dup
     123: istore        8
     125: ifle          147
     128: iload         6
     130: iload         8
     132: iadd
     133: istore        6
     135: iload         7
     137: iconst_1
     138: if_icmpne     31
     141: iinc          4, 1
     144: goto          31
     147: iload         7
     149: aload_1
     150: arraylength
     151: if_icmpge     171
     154: iload         9
     156: invokestatic  #52                 // Method method517:(C)Z
     159: ifne          165
     162: goto          171
     165: iinc          6, 1
     168: goto          31
     171: iload         7
     173: aload_1
     174: arraylength
     175: if_icmplt     244
     178: iconst_0
     179: istore        8
     181: aload_0
     182: aload_3
     183: iload         5
     185: invokestatic  #53                 // Method method503:([C[CI)I
     188: istore        9
     190: aload_2
     191: iload         6
     193: iconst_1
     194: isub
     195: aload_0
     196: invokestatic  #54                 // Method method504:([CI[C)I
     199: istore        10
     201: iload         9
     203: iconst_2
     204: if_icmpgt     213
     207: iload         10
     209: iconst_2
     210: if_icmple     216
     213: iconst_1
     214: istore        8
     216: iload         8
     218: ifeq          244
     221: iload         5
     223: istore        11
     225: iload         11
     227: iload         6
     229: if_icmpge     244
     232: aload_0
     233: iload         11
     235: bipush        42
     237: castore
     238: iinc          11, 1
     241: goto          225
     244: iload         5
     246: iload         4
     248: iadd
     249: istore        5
     251: goto          11
     254: return

  private static int method503(char[], char[], int);
    Code:
       0: iload_2
       1: ifne          6
       4: iconst_2
       5: ireturn
       6: iload_2
       7: iconst_1
       8: isub
       9: istore_3
      10: iload_3
      11: iflt          42
      14: aload_0
      15: iload_3
      16: caload
      17: invokestatic  #52                 // Method method517:(C)Z
      20: ifne          26
      23: goto          42
      26: aload_0
      27: iload_3
      28: caload
      29: bipush        64
      31: if_icmpne     36
      34: iconst_3
      35: ireturn
      36: iinc          3, -1
      39: goto          10
      42: iconst_0
      43: istore_3
      44: iload_2
      45: iconst_1
      46: isub
      47: istore        4
      49: iload         4
      51: iflt          85
      54: aload_1
      55: iload         4
      57: caload
      58: invokestatic  #52                 // Method method517:(C)Z
      61: ifne          67
      64: goto          85
      67: aload_1
      68: iload         4
      70: caload
      71: bipush        42
      73: if_icmpne     79
      76: iinc          3, 1
      79: iinc          4, -1
      82: goto          49
      85: iload_3
      86: iconst_3
      87: if_icmplt     92
      90: iconst_4
      91: ireturn
      92: aload_0
      93: iload_2
      94: iconst_1
      95: isub
      96: caload
      97: invokestatic  #52                 // Method method517:(C)Z
     100: ifne          107
     103: iconst_0
     104: goto          108
     107: iconst_1
     108: ireturn

  private static int method504(char[], int, char[]);
    Code:
       0: iload_1
       1: iconst_1
       2: iadd
       3: aload_2
       4: arraylength
       5: if_icmpne     10
       8: iconst_2
       9: ireturn
      10: iload_1
      11: iconst_1
      12: iadd
      13: istore_3
      14: iload_3
      15: aload_2
      16: arraylength
      17: if_icmpge     56
      20: aload_2
      21: iload_3
      22: caload
      23: invokestatic  #52                 // Method method517:(C)Z
      26: ifne          32
      29: goto          56
      32: aload_2
      33: iload_3
      34: caload
      35: bipush        46
      37: if_icmpeq     48
      40: aload_2
      41: iload_3
      42: caload
      43: bipush        44
      45: if_icmpne     50
      48: iconst_3
      49: ireturn
      50: iinc          3, 1
      53: goto          14
      56: iconst_0
      57: istore_3
      58: iload_1
      59: iconst_1
      60: iadd
      61: istore        4
      63: iload         4
      65: aload_2
      66: arraylength
      67: if_icmpge     101
      70: aload_0
      71: iload         4
      73: caload
      74: invokestatic  #52                 // Method method517:(C)Z
      77: ifne          83
      80: goto          101
      83: aload_0
      84: iload         4
      86: caload
      87: bipush        42
      89: if_icmpne     95
      92: iinc          3, 1
      95: iinc          4, 1
      98: goto          63
     101: iload_3
     102: iconst_3
     103: if_icmplt     108
     106: iconst_4
     107: ireturn
     108: aload_2
     109: iload_1
     110: iconst_1
     111: iadd
     112: caload
     113: invokestatic  #52                 // Method method517:(C)Z
     116: ifne          123
     119: iconst_0
     120: goto          124
     123: iconst_1
     124: ireturn

  private static void method505(char[]);
    Code:
       0: aload_0
       1: invokevirtual #55                 // Method "[C".clone:()Ljava/lang/Object;
       4: checkcast     #15                 // class "[C"
       7: astore_1
       8: iconst_3
       9: newarray       char
      11: dup
      12: iconst_0
      13: bipush        100
      15: castore
      16: dup
      17: iconst_1
      18: bipush        111
      20: castore
      21: dup
      22: iconst_2
      23: bipush        116
      25: castore
      26: astore_2
      27: aconst_null
      28: checkcast     #20                 // class "[[B"
      31: aload_1
      32: aload_2
      33: invokestatic  #47                 // Method method509:([[B[C[C)V
      36: aload_0
      37: invokevirtual #56                 // Method "[C".clone:()Ljava/lang/Object;
      40: checkcast     #15                 // class "[C"
      43: astore_3
      44: iconst_5
      45: newarray       char
      47: dup
      48: iconst_0
      49: bipush        115
      51: castore
      52: dup
      53: iconst_1
      54: bipush        108
      56: castore
      57: dup
      58: iconst_2
      59: bipush        97
      61: castore
      62: dup
      63: iconst_3
      64: bipush        115
      66: castore
      67: dup
      68: iconst_4
      69: bipush        104
      71: castore
      72: astore        4
      74: aconst_null
      75: checkcast     #20                 // class "[[B"
      78: aload_3
      79: aload         4
      81: invokestatic  #47                 // Method method509:([[B[C[C)V
      84: iconst_0
      85: istore        5
      87: iload         5
      89: getstatic     #16                 // Field aCharArrayArray624:[[C
      92: arraylength
      93: if_icmpge     120
      96: aload_3
      97: getstatic     #16                 // Field aCharArrayArray624:[[C
     100: iload         5
     102: aaload
     103: getstatic     #17                 // Field anIntArray625:[I
     106: iload         5
     108: iaload
     109: aload_1
     110: aload_0
     111: invokestatic  #57                 // Method method506:([C[CI[C[C)V
     114: iinc          5, 1
     117: goto          87
     120: return

  private static void method506(char[], char[], int, char[], char[]);
    Code:
       0: aload_1
       1: arraylength
       2: aload         4
       4: arraylength
       5: if_icmple     9
       8: return
       9: iconst_0
      10: istore        6
      12: iload         6
      14: aload         4
      16: arraylength
      17: aload_1
      18: arraylength
      19: isub
      20: if_icmpgt     626
      23: iload         6
      25: istore        7
      27: iconst_0
      28: istore        8
      30: iconst_1
      31: istore        5
      33: iload         7
      35: aload         4
      37: arraylength
      38: if_icmpge     177
      41: aload         4
      43: iload         7
      45: caload
      46: istore        10
      48: iconst_0
      49: istore        11
      51: iload         7
      53: iconst_1
      54: iadd
      55: aload         4
      57: arraylength
      58: if_icmpge     70
      61: aload         4
      63: iload         7
      65: iconst_1
      66: iadd
      67: caload
      68: istore        11
      70: iload         8
      72: aload_1
      73: arraylength
      74: if_icmpge     107
      77: iload         10
      79: aload_1
      80: iload         8
      82: caload
      83: iload         11
      85: invokestatic  #51                 // Method method511:(CCC)I
      88: dup
      89: istore        9
      91: ifle          107
      94: iload         7
      96: iload         9
      98: iadd
      99: istore        7
     101: iinc          8, 1
     104: goto          33
     107: iload         8
     109: ifne          115
     112: goto          177
     115: iload         10
     117: aload_1
     118: iload         8
     120: iconst_1
     121: isub
     122: caload
     123: iload         11
     125: invokestatic  #51                 // Method method511:(CCC)I
     128: dup
     129: istore        9
     131: ifle          153
     134: iload         7
     136: iload         9
     138: iadd
     139: istore        7
     141: iload         8
     143: iconst_1
     144: if_icmpne     33
     147: iinc          5, 1
     150: goto          33
     153: iload         8
     155: aload_1
     156: arraylength
     157: if_icmpge     177
     160: iload         10
     162: invokestatic  #52                 // Method method517:(C)Z
     165: ifne          171
     168: goto          177
     171: iinc          7, 1
     174: goto          33
     177: iload         8
     179: aload_1
     180: arraylength
     181: if_icmplt     616
     184: iconst_0
     185: istore        9
     187: aload         4
     189: iload         6
     191: aload_3
     192: invokestatic  #58                 // Method method507:([CI[C)I
     195: istore        10
     197: aload         4
     199: aload_0
     200: iload         7
     202: iconst_1
     203: isub
     204: invokestatic  #59                 // Method method508:([C[CI)I
     207: istore        11
     209: iload_2
     210: iconst_1
     211: if_icmpne     227
     214: iload         10
     216: ifle          227
     219: iload         11
     221: ifle          227
     224: iconst_1
     225: istore        9
     227: iload_2
     228: iconst_2
     229: if_icmpne     257
     232: iload         10
     234: iconst_2
     235: if_icmple     243
     238: iload         11
     240: ifgt          254
     243: iload         10
     245: ifle          257
     248: iload         11
     250: iconst_2
     251: if_icmple     257
     254: iconst_1
     255: istore        9
     257: iload_2
     258: iconst_3
     259: if_icmpne     276
     262: iload         10
     264: ifle          276
     267: iload         11
     269: iconst_2
     270: if_icmple     276
     273: iconst_1
     274: istore        9
     276: iload_2
     277: iconst_3
     278: if_icmpne     296
     281: iload         10
     283: iconst_2
     284: if_icmple     296
     287: iload         11
     289: ifle          296
     292: iconst_1
     293: goto          297
     296: iconst_0
     297: istore        12
     299: iload         9
     301: ifeq          616
     304: iload         6
     306: istore        13
     308: iload         7
     310: iconst_1
     311: isub
     312: istore        14
     314: iload         10
     316: iconst_2
     317: if_icmple     450
     320: iload         10
     322: iconst_4
     323: if_icmpne     386
     326: iconst_0
     327: istore        15
     329: iload         13
     331: iconst_1
     332: isub
     333: istore        16
     335: iload         16
     337: iflt          386
     340: iload         15
     342: ifeq          364
     345: aload_3
     346: iload         16
     348: caload
     349: bipush        42
     351: if_icmpeq     357
     354: goto          386
     357: iload         16
     359: istore        13
     361: goto          380
     364: aload_3
     365: iload         16
     367: caload
     368: bipush        42
     370: if_icmpne     380
     373: iload         16
     375: istore        13
     377: iconst_1
     378: istore        15
     380: iinc          16, -1
     383: goto          335
     386: iconst_0
     387: istore        15
     389: iload         13
     391: iconst_1
     392: isub
     393: istore        16
     395: iload         16
     397: iflt          450
     400: iload         15
     402: ifeq          426
     405: aload         4
     407: iload         16
     409: caload
     410: invokestatic  #52                 // Method method517:(C)Z
     413: ifeq          419
     416: goto          450
     419: iload         16
     421: istore        13
     423: goto          444
     426: aload         4
     428: iload         16
     430: caload
     431: invokestatic  #52                 // Method method517:(C)Z
     434: ifne          444
     437: iconst_1
     438: istore        15
     440: iload         16
     442: istore        13
     444: iinc          16, -1
     447: goto          395
     450: iload         11
     452: iconst_2
     453: if_icmple     592
     456: iload         11
     458: iconst_4
     459: if_icmpne     525
     462: iconst_0
     463: istore        15
     465: iload         14
     467: iconst_1
     468: iadd
     469: istore        16
     471: iload         16
     473: aload         4
     475: arraylength
     476: if_icmpge     525
     479: iload         15
     481: ifeq          503
     484: aload_0
     485: iload         16
     487: caload
     488: bipush        42
     490: if_icmpeq     496
     493: goto          525
     496: iload         16
     498: istore        14
     500: goto          519
     503: aload_0
     504: iload         16
     506: caload
     507: bipush        42
     509: if_icmpne     519
     512: iload         16
     514: istore        14
     516: iconst_1
     517: istore        15
     519: iinc          16, 1
     522: goto          471
     525: iconst_0
     526: istore        15
     528: iload         14
     530: iconst_1
     531: iadd
     532: istore        16
     534: iload         16
     536: aload         4
     538: arraylength
     539: if_icmpge     592
     542: iload         15
     544: ifeq          568
     547: aload         4
     549: iload         16
     551: caload
     552: invokestatic  #52                 // Method method517:(C)Z
     555: ifeq          561
     558: goto          592
     561: iload         16
     563: istore        14
     565: goto          586
     568: aload         4
     570: iload         16
     572: caload
     573: invokestatic  #52                 // Method method517:(C)Z
     576: ifne          586
     579: iconst_1
     580: istore        15
     582: iload         16
     584: istore        14
     586: iinc          16, 1
     589: goto          534
     592: iload         13
     594: istore        15
     596: iload         15
     598: iload         14
     600: if_icmpgt     616
     603: aload         4
     605: iload         15
     607: bipush        42
     609: castore
     610: iinc          15, 1
     613: goto          596
     616: iload         6
     618: iload         5
     620: iadd
     621: istore        6
     623: goto          12
     626: return

  private static int method507(char[], int, char[]);
    Code:
       0: iload_1
       1: ifne          6
       4: iconst_2
       5: ireturn
       6: iload_1
       7: iconst_1
       8: isub
       9: istore_3
      10: iload_3
      11: iflt          50
      14: aload_0
      15: iload_3
      16: caload
      17: invokestatic  #52                 // Method method517:(C)Z
      20: ifne          26
      23: goto          50
      26: aload_0
      27: iload_3
      28: caload
      29: bipush        44
      31: if_icmpeq     42
      34: aload_0
      35: iload_3
      36: caload
      37: bipush        46
      39: if_icmpne     44
      42: iconst_3
      43: ireturn
      44: iinc          3, -1
      47: goto          10
      50: iconst_0
      51: istore_3
      52: iload_1
      53: iconst_1
      54: isub
      55: istore        4
      57: iload         4
      59: iflt          93
      62: aload_2
      63: iload         4
      65: caload
      66: invokestatic  #52                 // Method method517:(C)Z
      69: ifne          75
      72: goto          93
      75: aload_2
      76: iload         4
      78: caload
      79: bipush        42
      81: if_icmpne     87
      84: iinc          3, 1
      87: iinc          4, -1
      90: goto          57
      93: iload_3
      94: iconst_3
      95: if_icmplt     100
      98: iconst_4
      99: ireturn
     100: aload_0
     101: iload_1
     102: iconst_1
     103: isub
     104: caload
     105: invokestatic  #52                 // Method method517:(C)Z
     108: ifne          115
     111: iconst_0
     112: goto          116
     115: iconst_1
     116: ireturn

  private static int method508(char[], char[], int);
    Code:
       0: iload_2
       1: iconst_1
       2: iadd
       3: aload_0
       4: arraylength
       5: if_icmpne     10
       8: iconst_2
       9: ireturn
      10: iload_2
      11: iconst_1
      12: iadd
      13: istore_3
      14: iload_3
      15: aload_0
      16: arraylength
      17: if_icmpge     56
      20: aload_0
      21: iload_3
      22: caload
      23: invokestatic  #52                 // Method method517:(C)Z
      26: ifne          32
      29: goto          56
      32: aload_0
      33: iload_3
      34: caload
      35: bipush        92
      37: if_icmpeq     48
      40: aload_0
      41: iload_3
      42: caload
      43: bipush        47
      45: if_icmpne     50
      48: iconst_3
      49: ireturn
      50: iinc          3, 1
      53: goto          14
      56: iconst_0
      57: istore_3
      58: iload_2
      59: iconst_1
      60: iadd
      61: istore        4
      63: iload         4
      65: aload_0
      66: arraylength
      67: if_icmpge     101
      70: aload_1
      71: iload         4
      73: caload
      74: invokestatic  #52                 // Method method517:(C)Z
      77: ifne          83
      80: goto          101
      83: aload_1
      84: iload         4
      86: caload
      87: bipush        42
      89: if_icmpne     95
      92: iinc          3, 1
      95: iinc          4, 1
      98: goto          63
     101: iload_3
     102: iconst_5
     103: if_icmplt     108
     106: iconst_4
     107: ireturn
     108: aload_0
     109: iload_2
     110: iconst_1
     111: iadd
     112: caload
     113: invokestatic  #52                 // Method method517:(C)Z
     116: ifne          123
     119: iconst_0
     120: goto          124
     123: iconst_1
     124: ireturn

  private static void method509(byte[][], char[], char[]);
    Code:
       0: aload_2
       1: arraylength
       2: aload_1
       3: arraylength
       4: if_icmple     8
       7: return
       8: iconst_1
       9: istore_3
      10: iconst_0
      11: istore        5
      13: iload         5
      15: aload_1
      16: arraylength
      17: aload_2
      18: arraylength
      19: isub
      20: if_icmpgt     794
      23: iload         5
      25: istore        6
      27: iconst_0
      28: istore        7
      30: iconst_0
      31: istore        8
      33: iconst_1
      34: istore        4
      36: iconst_0
      37: istore        9
      39: iconst_0
      40: istore        10
      42: iconst_0
      43: istore        11
      45: iload         6
      47: aload_1
      48: arraylength
      49: if_icmpge     288
      52: iload         10
      54: ifeq          62
      57: iload         11
      59: ifne          288
      62: aload_1
      63: iload         6
      65: caload
      66: istore        13
      68: iconst_0
      69: istore        14
      71: iload         6
      73: iconst_1
      74: iadd
      75: aload_1
      76: arraylength
      77: if_icmpge     88
      80: aload_1
      81: iload         6
      83: iconst_1
      84: iadd
      85: caload
      86: istore        14
      88: iload         7
      90: aload_2
      91: arraylength
      92: if_icmpge     167
      95: iload         14
      97: iload         13
      99: aload_2
     100: iload         7
     102: caload
     103: invokestatic  #60                 // Method method512:(CCC)I
     106: dup
     107: istore        12
     109: ifle          167
     112: iload         12
     114: iconst_1
     115: if_icmpne     129
     118: iload         13
     120: invokestatic  #61                 // Method isDigit:(C)Z
     123: ifeq          129
     126: iconst_1
     127: istore        10
     129: iload         12
     131: iconst_2
     132: if_icmpne     154
     135: iload         13
     137: invokestatic  #61                 // Method isDigit:(C)Z
     140: ifne          151
     143: iload         14
     145: invokestatic  #61                 // Method isDigit:(C)Z
     148: ifeq          154
     151: iconst_1
     152: istore        10
     154: iload         6
     156: iload         12
     158: iadd
     159: istore        6
     161: iinc          7, 1
     164: goto          45
     167: iload         7
     169: ifne          175
     172: goto          288
     175: iload         14
     177: iload         13
     179: aload_2
     180: iload         7
     182: iconst_1
     183: isub
     184: caload
     185: invokestatic  #60                 // Method method512:(CCC)I
     188: dup
     189: istore        12
     191: ifle          213
     194: iload         6
     196: iload         12
     198: iadd
     199: istore        6
     201: iload         7
     203: iconst_1
     204: if_icmpne     45
     207: iinc          4, 1
     210: goto          45
     213: iload         7
     215: aload_2
     216: arraylength
     217: if_icmpge     288
     220: iload         13
     222: invokestatic  #62                 // Method method518:(C)Z
     225: ifne          231
     228: goto          288
     231: iload         13
     233: invokestatic  #52                 // Method method517:(C)Z
     236: ifeq          249
     239: iload         13
     241: bipush        39
     243: if_icmpeq     249
     246: iconst_1
     247: istore        9
     249: iload         13
     251: invokestatic  #61                 // Method isDigit:(C)Z
     254: ifeq          260
     257: iconst_1
     258: istore        11
     260: iinc          6, 1
     263: iinc          8, 1
     266: iload         8
     268: bipush        100
     270: imul
     271: iload         6
     273: iload         5
     275: isub
     276: idiv
     277: bipush        90
     279: if_icmple     285
     282: goto          288
     285: goto          45
     288: iload         7
     290: aload_2
     291: arraylength
     292: if_icmplt     784
     295: iload         10
     297: ifeq          305
     300: iload         11
     302: ifne          784
     305: iconst_1
     306: istore        12
     308: iload         9
     310: ifne          384
     313: bipush        32
     315: istore        13
     317: iload         5
     319: iconst_1
     320: isub
     321: iflt          332
     324: aload_1
     325: iload         5
     327: iconst_1
     328: isub
     329: caload
     330: istore        13
     332: bipush        32
     334: istore        14
     336: iload         6
     338: aload_1
     339: arraylength
     340: if_icmpge     349
     343: aload_1
     344: iload         6
     346: caload
     347: istore        14
     349: iload         13
     351: invokestatic  #63                 // Method method513:(C)B
     354: istore        15
     356: iload         14
     358: invokestatic  #63                 // Method method513:(C)B
     361: istore        16
     363: aload_0
     364: ifnull        381
     367: iload         15
     369: aload_0
     370: iload         16
     372: invokestatic  #64                 // Method method510:(B[[BB)Z
     375: ifeq          381
     378: iconst_0
     379: istore        12
     381: goto          666
     384: iconst_0
     385: istore        13
     387: iconst_0
     388: istore        14
     390: iload         5
     392: iconst_1
     393: isub
     394: iflt          420
     397: aload_1
     398: iload         5
     400: iconst_1
     401: isub
     402: caload
     403: invokestatic  #52                 // Method method517:(C)Z
     406: ifeq          423
     409: aload_1
     410: iload         5
     412: iconst_1
     413: isub
     414: caload
     415: bipush        39
     417: if_icmpeq     423
     420: iconst_1
     421: istore        13
     423: iload         6
     425: aload_1
     426: arraylength
     427: if_icmpge     449
     430: aload_1
     431: iload         6
     433: caload
     434: invokestatic  #52                 // Method method517:(C)Z
     437: ifeq          452
     440: aload_1
     441: iload         6
     443: caload
     444: bipush        39
     446: if_icmpeq     452
     449: iconst_1
     450: istore        14
     452: iload         13
     454: ifeq          462
     457: iload         14
     459: ifne          666
     462: iconst_0
     463: istore        15
     465: iload         5
     467: iconst_2
     468: isub
     469: istore        16
     471: iload         13
     473: ifeq          480
     476: iload         5
     478: istore        16
     480: iload         15
     482: ifne          658
     485: iload         16
     487: iload         6
     489: if_icmpge     658
     492: iload         16
     494: iflt          652
     497: aload_1
     498: iload         16
     500: caload
     501: invokestatic  #52                 // Method method517:(C)Z
     504: ifeq          516
     507: aload_1
     508: iload         16
     510: caload
     511: bipush        39
     513: if_icmpne     652
     516: iconst_3
     517: newarray       char
     519: astore        17
     521: iconst_0
     522: istore        18
     524: iload         18
     526: iconst_3
     527: if_icmpge     586
     530: iload         16
     532: iload         18
     534: iadd
     535: aload_1
     536: arraylength
     537: if_icmpge     586
     540: aload_1
     541: iload         16
     543: iload         18
     545: iadd
     546: caload
     547: invokestatic  #52                 // Method method517:(C)Z
     550: ifeq          568
     553: aload_1
     554: iload         16
     556: iload         18
     558: iadd
     559: caload
     560: bipush        39
     562: if_icmpeq     568
     565: goto          586
     568: aload         17
     570: iload         18
     572: aload_1
     573: iload         16
     575: iload         18
     577: iadd
     578: caload
     579: castore
     580: iinc          18, 1
     583: goto          524
     586: iconst_1
     587: istore        19
     589: iload         18
     591: ifne          597
     594: iconst_0
     595: istore        19
     597: iload         18
     599: iconst_3
     600: if_icmpge     636
     603: iload         16
     605: iconst_1
     606: isub
     607: iflt          636
     610: aload_1
     611: iload         16
     613: iconst_1
     614: isub
     615: caload
     616: invokestatic  #52                 // Method method517:(C)Z
     619: ifeq          633
     622: aload_1
     623: iload         16
     625: iconst_1
     626: isub
     627: caload
     628: bipush        39
     630: if_icmpne     636
     633: iconst_0
     634: istore        19
     636: iload         19
     638: ifeq          652
     641: aload         17
     643: invokestatic  #65                 // Method method523:([C)Z
     646: ifne          652
     649: iconst_1
     650: istore        15
     652: iinc          16, 1
     655: goto          480
     658: iload         15
     660: ifne          666
     663: iconst_0
     664: istore        12
     666: iload         12
     668: ifeq          784
     671: iconst_0
     672: istore        13
     674: iconst_0
     675: istore        14
     677: iconst_m1
     678: istore        15
     680: iload         5
     682: istore        16
     684: iload         16
     686: iload         6
     688: if_icmpge     730
     691: aload_1
     692: iload         16
     694: caload
     695: invokestatic  #61                 // Method isDigit:(C)Z
     698: ifeq          707
     701: iinc          13, 1
     704: goto          724
     707: aload_1
     708: iload         16
     710: caload
     711: invokestatic  #45                 // Method isLetter:(C)Z
     714: ifeq          724
     717: iinc          14, 1
     720: iload         16
     722: istore        15
     724: iinc          16, 1
     727: goto          684
     730: iload         15
     732: iconst_m1
     733: if_icmple     748
     736: iload         13
     738: iload         6
     740: iconst_1
     741: isub
     742: iload         15
     744: isub
     745: isub
     746: istore        13
     748: iload         13
     750: iload         14
     752: if_icmpgt     781
     755: iload         5
     757: istore        16
     759: iload         16
     761: iload         6
     763: if_icmpge     778
     766: aload_1
     767: iload         16
     769: bipush        42
     771: castore
     772: iinc          16, 1
     775: goto          759
     778: goto          784
     781: iconst_1
     782: istore        4
     784: iload         5
     786: iload         4
     788: iadd
     789: istore        5
     791: goto          13
     794: return

  private static boolean method510(byte, byte[][], byte);
    Code:
       0: iconst_0
       1: istore_3
       2: aload_1
       3: iload_3
       4: aaload
       5: iconst_0
       6: baload
       7: iload_0
       8: if_icmpne     22
      11: aload_1
      12: iload_3
      13: aaload
      14: iconst_1
      15: baload
      16: iload_2
      17: if_icmpne     22
      20: iconst_1
      21: ireturn
      22: aload_1
      23: arraylength
      24: iconst_1
      25: isub
      26: istore        4
      28: aload_1
      29: iload         4
      31: aaload
      32: iconst_0
      33: baload
      34: iload_0
      35: if_icmpne     50
      38: aload_1
      39: iload         4
      41: aaload
      42: iconst_1
      43: baload
      44: iload_2
      45: if_icmpne     50
      48: iconst_1
      49: ireturn
      50: iload_3
      51: iload         4
      53: iadd
      54: iconst_2
      55: idiv
      56: istore        5
      58: aload_1
      59: iload         5
      61: aaload
      62: iconst_0
      63: baload
      64: iload_0
      65: if_icmpne     80
      68: aload_1
      69: iload         5
      71: aaload
      72: iconst_1
      73: baload
      74: iload_2
      75: if_icmpne     80
      78: iconst_1
      79: ireturn
      80: iload_0
      81: aload_1
      82: iload         5
      84: aaload
      85: iconst_0
      86: baload
      87: if_icmplt     110
      90: iload_0
      91: aload_1
      92: iload         5
      94: aaload
      95: iconst_0
      96: baload
      97: if_icmpne     117
     100: iload_2
     101: aload_1
     102: iload         5
     104: aaload
     105: iconst_1
     106: baload
     107: if_icmpge     117
     110: iload         5
     112: istore        4
     114: goto          120
     117: iload         5
     119: istore_3
     120: iload_3
     121: iload         4
     123: if_icmpeq     134
     126: iload_3
     127: iconst_1
     128: iadd
     129: iload         4
     131: if_icmpne     50
     134: iconst_0
     135: ireturn

  private static int method511(char, char, char);
    Code:
       0: iload_1
       1: iload_0
       2: if_icmpne     7
       5: iconst_1
       6: ireturn
       7: iload_1
       8: bipush        111
      10: if_icmpne     21
      13: iload_0
      14: bipush        48
      16: if_icmpne     21
      19: iconst_1
      20: ireturn
      21: iload_1
      22: bipush        111
      24: if_icmpne     41
      27: iload_0
      28: bipush        40
      30: if_icmpne     41
      33: iload_2
      34: bipush        41
      36: if_icmpne     41
      39: iconst_2
      40: ireturn
      41: iload_1
      42: bipush        99
      44: if_icmpne     67
      47: iload_0
      48: bipush        40
      50: if_icmpeq     65
      53: iload_0
      54: bipush        60
      56: if_icmpeq     65
      59: iload_0
      60: bipush        91
      62: if_icmpne     67
      65: iconst_1
      66: ireturn
      67: iload_1
      68: bipush        101
      70: if_icmpne     82
      73: iload_0
      74: sipush        8364
      77: if_icmpne     82
      80: iconst_1
      81: ireturn
      82: iload_1
      83: bipush        115
      85: if_icmpne     96
      88: iload_0
      89: bipush        36
      91: if_icmpne     96
      94: iconst_1
      95: ireturn
      96: iload_1
      97: bipush        108
      99: if_icmpne     108
     102: iload_0
     103: bipush        105
     105: if_icmpeq     112
     108: iconst_0
     109: goto          113
     112: iconst_1
     113: ireturn

  private static int method512(char, char, char);
    Code:
       0: iload_2
       1: iload_1
       2: if_icmpne     7
       5: iconst_1
       6: ireturn
       7: iload_2
       8: bipush        97
      10: if_icmplt     405
      13: iload_2
      14: bipush        109
      16: if_icmpgt     405
      19: iload_2
      20: bipush        97
      22: if_icmpne     63
      25: iload_1
      26: bipush        52
      28: if_icmpeq     43
      31: iload_1
      32: bipush        64
      34: if_icmpeq     43
      37: iload_1
      38: bipush        94
      40: if_icmpne     45
      43: iconst_1
      44: ireturn
      45: iload_1
      46: bipush        47
      48: if_icmpne     57
      51: iload_0
      52: bipush        92
      54: if_icmpeq     61
      57: iconst_0
      58: goto          62
      61: iconst_2
      62: ireturn
      63: iload_2
      64: bipush        98
      66: if_icmpne     113
      69: iload_1
      70: bipush        54
      72: if_icmpeq     81
      75: iload_1
      76: bipush        56
      78: if_icmpne     83
      81: iconst_1
      82: ireturn
      83: iload_1
      84: bipush        49
      86: if_icmpne     95
      89: iload_0
      90: bipush        51
      92: if_icmpeq     111
      95: iload_1
      96: bipush        105
      98: if_icmpne     107
     101: iload_0
     102: bipush        51
     104: if_icmpeq     111
     107: iconst_0
     108: goto          112
     111: iconst_2
     112: ireturn
     113: iload_2
     114: bipush        99
     116: if_icmpne     149
     119: iload_1
     120: bipush        40
     122: if_icmpeq     147
     125: iload_1
     126: bipush        60
     128: if_icmpeq     147
     131: iload_1
     132: bipush        123
     134: if_icmpeq     147
     137: iload_1
     138: bipush        91
     140: if_icmpeq     147
     143: iconst_0
     144: goto          148
     147: iconst_1
     148: ireturn
     149: iload_2
     150: bipush        100
     152: if_icmpne     185
     155: iload_1
     156: bipush        91
     158: if_icmpne     167
     161: iload_0
     162: bipush        41
     164: if_icmpeq     183
     167: iload_1
     168: bipush        105
     170: if_icmpne     179
     173: iload_0
     174: bipush        41
     176: if_icmpeq     183
     179: iconst_0
     180: goto          184
     183: iconst_2
     184: ireturn
     185: iload_2
     186: bipush        101
     188: if_icmpne     210
     191: iload_1
     192: bipush        51
     194: if_icmpeq     208
     197: iload_1
     198: sipush        8364
     201: if_icmpeq     208
     204: iconst_0
     205: goto          209
     208: iconst_1
     209: ireturn
     210: iload_2
     211: bipush        102
     213: if_icmpne     243
     216: iload_1
     217: bipush        112
     219: if_icmpne     230
     222: iload_0
     223: bipush        104
     225: if_icmpne     230
     228: iconst_2
     229: ireturn
     230: iload_1
     231: sipush        163
     234: if_icmpeq     241
     237: iconst_0
     238: goto          242
     241: iconst_1
     242: ireturn
     243: iload_2
     244: bipush        103
     246: if_icmpne     273
     249: iload_1
     250: bipush        57
     252: if_icmpeq     271
     255: iload_1
     256: bipush        54
     258: if_icmpeq     271
     261: iload_1
     262: bipush        113
     264: if_icmpeq     271
     267: iconst_0
     268: goto          272
     271: iconst_1
     272: ireturn
     273: iload_2
     274: bipush        104
     276: if_icmpne     291
     279: iload_1
     280: bipush        35
     282: if_icmpeq     289
     285: iconst_0
     286: goto          290
     289: iconst_1
     290: ireturn
     291: iload_2
     292: bipush        105
     294: if_icmpne     351
     297: iload_1
     298: bipush        121
     300: if_icmpeq     349
     303: iload_1
     304: bipush        108
     306: if_icmpeq     349
     309: iload_1
     310: bipush        106
     312: if_icmpeq     349
     315: iload_1
     316: bipush        49
     318: if_icmpeq     349
     321: iload_1
     322: bipush        33
     324: if_icmpeq     349
     327: iload_1
     328: bipush        58
     330: if_icmpeq     349
     333: iload_1
     334: bipush        59
     336: if_icmpeq     349
     339: iload_1
     340: bipush        124
     342: if_icmpeq     349
     345: iconst_0
     346: goto          350
     349: iconst_1
     350: ireturn
     351: iload_2
     352: bipush        106
     354: if_icmpne     359
     357: iconst_0
     358: ireturn
     359: iload_2
     360: bipush        107
     362: if_icmpne     367
     365: iconst_0
     366: ireturn
     367: iload_2
     368: bipush        108
     370: if_icmpne     397
     373: iload_1
     374: bipush        49
     376: if_icmpeq     395
     379: iload_1
     380: bipush        124
     382: if_icmpeq     395
     385: iload_1
     386: bipush        105
     388: if_icmpeq     395
     391: iconst_0
     392: goto          396
     395: iconst_1
     396: ireturn
     397: iload_2
     398: bipush        109
     400: if_icmpne     405
     403: iconst_0
     404: ireturn
     405: iload_2
     406: bipush        110
     408: if_icmplt     787
     411: iload_2
     412: bipush        122
     414: if_icmpgt     787
     417: iload_2
     418: bipush        110
     420: if_icmpne     425
     423: iconst_0
     424: ireturn
     425: iload_2
     426: bipush        111
     428: if_icmpne     499
     431: iload_1
     432: bipush        48
     434: if_icmpeq     443
     437: iload_1
     438: bipush        42
     440: if_icmpne     445
     443: iconst_1
     444: ireturn
     445: iload_1
     446: bipush        40
     448: if_icmpne     457
     451: iload_0
     452: bipush        41
     454: if_icmpeq     497
     457: iload_1
     458: bipush        91
     460: if_icmpne     469
     463: iload_0
     464: bipush        93
     466: if_icmpeq     497
     469: iload_1
     470: bipush        123
     472: if_icmpne     481
     475: iload_0
     476: bipush        125
     478: if_icmpeq     497
     481: iload_1
     482: bipush        60
     484: if_icmpne     493
     487: iload_0
     488: bipush        62
     490: if_icmpeq     497
     493: iconst_0
     494: goto          498
     497: iconst_2
     498: ireturn
     499: iload_2
     500: bipush        112
     502: if_icmpne     507
     505: iconst_0
     506: ireturn
     507: iload_2
     508: bipush        113
     510: if_icmpne     515
     513: iconst_0
     514: ireturn
     515: iload_2
     516: bipush        114
     518: if_icmpne     523
     521: iconst_0
     522: ireturn
     523: iload_2
     524: bipush        115
     526: if_icmpne     559
     529: iload_1
     530: bipush        53
     532: if_icmpeq     557
     535: iload_1
     536: bipush        122
     538: if_icmpeq     557
     541: iload_1
     542: bipush        36
     544: if_icmpeq     557
     547: iload_1
     548: bipush        50
     550: if_icmpeq     557
     553: iconst_0
     554: goto          558
     557: iconst_1
     558: ireturn
     559: iload_2
     560: bipush        116
     562: if_icmpne     583
     565: iload_1
     566: bipush        55
     568: if_icmpeq     581
     571: iload_1
     572: bipush        43
     574: if_icmpeq     581
     577: iconst_0
     578: goto          582
     581: iconst_1
     582: ireturn
     583: iload_2
     584: bipush        117
     586: if_icmpne     639
     589: iload_1
     590: bipush        118
     592: if_icmpne     597
     595: iconst_1
     596: ireturn
     597: iload_1
     598: bipush        92
     600: if_icmpne     609
     603: iload_0
     604: bipush        47
     606: if_icmpeq     637
     609: iload_1
     610: bipush        92
     612: if_icmpne     621
     615: iload_0
     616: bipush        124
     618: if_icmpeq     637
     621: iload_1
     622: bipush        124
     624: if_icmpne     633
     627: iload_0
     628: bipush        47
     630: if_icmpeq     637
     633: iconst_0
     634: goto          638
     637: iconst_2
     638: ireturn
     639: iload_2
     640: bipush        118
     642: if_icmpne     687
     645: iload_1
     646: bipush        92
     648: if_icmpne     657
     651: iload_0
     652: bipush        47
     654: if_icmpeq     685
     657: iload_1
     658: bipush        92
     660: if_icmpne     669
     663: iload_0
     664: bipush        124
     666: if_icmpeq     685
     669: iload_1
     670: bipush        124
     672: if_icmpne     681
     675: iload_0
     676: bipush        47
     678: if_icmpeq     685
     681: iconst_0
     682: goto          686
     685: iconst_2
     686: ireturn
     687: iload_2
     688: bipush        119
     690: if_icmpne     711
     693: iload_1
     694: bipush        118
     696: if_icmpne     705
     699: iload_0
     700: bipush        118
     702: if_icmpeq     709
     705: iconst_0
     706: goto          710
     709: iconst_2
     710: ireturn
     711: iload_2
     712: bipush        120
     714: if_icmpne     771
     717: iload_1
     718: bipush        41
     720: if_icmpne     729
     723: iload_0
     724: bipush        40
     726: if_icmpeq     769
     729: iload_1
     730: bipush        125
     732: if_icmpne     741
     735: iload_0
     736: bipush        123
     738: if_icmpeq     769
     741: iload_1
     742: bipush        93
     744: if_icmpne     753
     747: iload_0
     748: bipush        91
     750: if_icmpeq     769
     753: iload_1
     754: bipush        62
     756: if_icmpne     765
     759: iload_0
     760: bipush        60
     762: if_icmpeq     769
     765: iconst_0
     766: goto          770
     769: iconst_2
     770: ireturn
     771: iload_2
     772: bipush        121
     774: if_icmpne     779
     777: iconst_0
     778: ireturn
     779: iload_2
     780: bipush        122
     782: if_icmpne     787
     785: iconst_0
     786: ireturn
     787: iload_2
     788: bipush        48
     790: if_icmplt     881
     793: iload_2
     794: bipush        57
     796: if_icmpgt     881
     799: iload_2
     800: bipush        48
     802: if_icmpne     861
     805: iload_1
     806: bipush        111
     808: if_icmpeq     817
     811: iload_1
     812: bipush        79
     814: if_icmpne     819
     817: iconst_1
     818: ireturn
     819: iload_1
     820: bipush        40
     822: if_icmpne     831
     825: iload_0
     826: bipush        41
     828: if_icmpeq     859
     831: iload_1
     832: bipush        123
     834: if_icmpne     843
     837: iload_0
     838: bipush        125
     840: if_icmpeq     859
     843: iload_1
     844: bipush        91
     846: if_icmpne     855
     849: iload_0
     850: bipush        93
     852: if_icmpeq     859
     855: iconst_0
     856: goto          860
     859: iconst_2
     860: ireturn
     861: iload_2
     862: bipush        49
     864: if_icmpne     879
     867: iload_1
     868: bipush        108
     870: if_icmpeq     877
     873: iconst_0
     874: goto          878
     877: iconst_1
     878: ireturn
     879: iconst_0
     880: ireturn
     881: iload_2
     882: bipush        44
     884: if_icmpne     899
     887: iload_1
     888: bipush        46
     890: if_icmpeq     897
     893: iconst_0
     894: goto          898
     897: iconst_1
     898: ireturn
     899: iload_2
     900: bipush        46
     902: if_icmpne     917
     905: iload_1
     906: bipush        44
     908: if_icmpeq     915
     911: iconst_0
     912: goto          916
     915: iconst_1
     916: ireturn
     917: iload_2
     918: bipush        33
     920: if_icmpne     935
     923: iload_1
     924: bipush        105
     926: if_icmpeq     933
     929: iconst_0
     930: goto          934
     933: iconst_1
     934: ireturn
     935: iconst_0
     936: ireturn

  private static byte method513(char);
    Code:
       0: iload_0
       1: bipush        97
       3: if_icmplt     20
       6: iload_0
       7: bipush        122
       9: if_icmpgt     20
      12: iload_0
      13: bipush        97
      15: isub
      16: iconst_1
      17: iadd
      18: i2b
      19: ireturn
      20: iload_0
      21: bipush        39
      23: if_icmpne     29
      26: bipush        28
      28: ireturn
      29: iload_0
      30: bipush        48
      32: if_icmplt     50
      35: iload_0
      36: bipush        57
      38: if_icmpgt     50
      41: iload_0
      42: bipush        48
      44: isub
      45: bipush        29
      47: iadd
      48: i2b
      49: ireturn
      50: bipush        27
      52: ireturn

  private static void method514(char[]);
    Code:
       0: iconst_0
       1: istore_2
       2: iconst_0
       3: istore_3
       4: iconst_0
       5: istore        4
       7: aload_0
       8: iload_2
       9: invokestatic  #66                 // Method method515:([CI)I
      12: dup
      13: istore_1
      14: iconst_m1
      15: if_icmpeq     178
      18: iconst_0
      19: istore        5
      21: iload_2
      22: istore        6
      24: iload         6
      26: iflt          69
      29: iload         6
      31: iload_1
      32: if_icmpge     69
      35: iload         5
      37: ifne          69
      40: aload_0
      41: iload         6
      43: caload
      44: invokestatic  #52                 // Method method517:(C)Z
      47: ifne          63
      50: aload_0
      51: iload         6
      53: caload
      54: invokestatic  #62                 // Method method518:(C)Z
      57: ifne          63
      60: iconst_1
      61: istore        5
      63: iinc          6, 1
      66: goto          24
      69: iload         5
      71: ifeq          76
      74: iconst_0
      75: istore_3
      76: iload_3
      77: ifne          83
      80: iload_1
      81: istore        4
      83: aload_0
      84: iload_1
      85: invokestatic  #67                 // Method method516:([CI)I
      88: istore_2
      89: iconst_0
      90: istore        6
      92: iload_1
      93: istore        7
      95: iload         7
      97: iload_2
      98: if_icmpge     122
     101: iload         6
     103: bipush        10
     105: imul
     106: aload_0
     107: iload         7
     109: caload
     110: iadd
     111: bipush        48
     113: isub
     114: istore        6
     116: iinc          7, 1
     119: goto          95
     122: iload         6
     124: sipush        255
     127: if_icmpgt     138
     130: iload_2
     131: iload_1
     132: isub
     133: bipush        8
     135: if_icmple     143
     138: iconst_0
     139: istore_3
     140: goto          146
     143: iinc          3, 1
     146: iload_3
     147: iconst_4
     148: if_icmpne     175
     151: iload         4
     153: istore        7
     155: iload         7
     157: iload_2
     158: if_icmpge     173
     161: aload_0
     162: iload         7
     164: bipush        42
     166: castore
     167: iinc          7, 1
     170: goto          155
     173: iconst_0
     174: istore_3
     175: goto          7
     178: return

  private static int method515(char[], int);
    Code:
       0: iload_1
       1: istore_2
       2: iload_2
       3: aload_0
       4: arraylength
       5: if_icmpge     36
       8: iload_2
       9: iflt          36
      12: aload_0
      13: iload_2
      14: caload
      15: bipush        48
      17: if_icmplt     30
      20: aload_0
      21: iload_2
      22: caload
      23: bipush        57
      25: if_icmpgt     30
      28: iload_2
      29: ireturn
      30: iinc          2, 1
      33: goto          2
      36: iconst_m1
      37: ireturn

  private static int method516(char[], int);
    Code:
       0: iload_1
       1: istore_2
       2: iload_2
       3: aload_0
       4: arraylength
       5: if_icmpge     36
       8: iload_2
       9: iflt          36
      12: aload_0
      13: iload_2
      14: caload
      15: bipush        48
      17: if_icmplt     28
      20: aload_0
      21: iload_2
      22: caload
      23: bipush        57
      25: if_icmple     30
      28: iload_2
      29: ireturn
      30: iinc          2, 1
      33: goto          2
      36: aload_0
      37: arraylength
      38: ireturn

  private static boolean method517(char);
    Code:
       0: iload_0
       1: invokestatic  #45                 // Method isLetter:(C)Z
       4: ifne          18
       7: iload_0
       8: invokestatic  #61                 // Method isDigit:(C)Z
      11: ifne          18
      14: iconst_1
      15: goto          19
      18: iconst_0
      19: ireturn

  private static boolean method518(char);
    Code:
       0: iload_0
       1: bipush        97
       3: if_icmplt     42
       6: iload_0
       7: bipush        122
       9: if_icmpgt     42
      12: iload_0
      13: bipush        118
      15: if_icmpeq     42
      18: iload_0
      19: bipush        120
      21: if_icmpeq     42
      24: iload_0
      25: bipush        106
      27: if_icmpeq     42
      30: iload_0
      31: bipush        113
      33: if_icmpeq     42
      36: iload_0
      37: bipush        122
      39: if_icmpne     46
      42: iconst_1
      43: goto          47
      46: iconst_0
      47: ireturn

  private static boolean isLetter(char);
    Code:
       0: iload_0
       1: bipush        97
       3: if_icmplt     12
       6: iload_0
       7: bipush        122
       9: if_icmple     24
      12: iload_0
      13: bipush        65
      15: if_icmplt     28
      18: iload_0
      19: bipush        90
      21: if_icmpgt     28
      24: iconst_1
      25: goto          29
      28: iconst_0
      29: ireturn

  private static boolean isDigit(char);
    Code:
       0: iload_0
       1: bipush        48
       3: if_icmplt     16
       6: iload_0
       7: bipush        57
       9: if_icmpgt     16
      12: iconst_1
      13: goto          17
      16: iconst_0
      17: ireturn

  private static boolean isLowerCaseLetter(char);
    Code:
       0: iload_0
       1: bipush        97
       3: if_icmplt     16
       6: iload_0
       7: bipush        122
       9: if_icmpgt     16
      12: iconst_1
      13: goto          17
      16: iconst_0
      17: ireturn

  private static boolean isUpperCaseLetter(char);
    Code:
       0: iload_0
       1: bipush        65
       3: if_icmplt     16
       6: iload_0
       7: bipush        90
       9: if_icmpgt     16
      12: iconst_1
      13: goto          17
      16: iconst_0
      17: ireturn

  private static boolean method523(char[]);
    Code:
       0: iconst_1
       1: istore_1
       2: iconst_0
       3: istore_2
       4: iload_2
       5: aload_0
       6: arraylength
       7: if_icmpge     33
      10: aload_0
      11: iload_2
      12: caload
      13: invokestatic  #61                 // Method isDigit:(C)Z
      16: ifne          27
      19: aload_0
      20: iload_2
      21: caload
      22: ifeq          27
      25: iconst_0
      26: istore_1
      27: iinc          2, 1
      30: goto          4
      33: iload_1
      34: ifeq          39
      37: iconst_1
      38: ireturn
      39: aload_0
      40: invokestatic  #68                 // Method method524:([C)I
      43: istore_2
      44: iconst_0
      45: istore_3
      46: getstatic     #25                 // Field anIntArray620:[I
      49: arraylength
      50: iconst_1
      51: isub
      52: istore        4
      54: iload_2
      55: getstatic     #25                 // Field anIntArray620:[I
      58: iload_3
      59: iaload
      60: if_icmpeq     73
      63: iload_2
      64: getstatic     #25                 // Field anIntArray620:[I
      67: iload         4
      69: iaload
      70: if_icmpne     75
      73: iconst_1
      74: ireturn
      75: iload_3
      76: iload         4
      78: iadd
      79: iconst_2
      80: idiv
      81: istore        5
      83: iload_2
      84: getstatic     #25                 // Field anIntArray620:[I
      87: iload         5
      89: iaload
      90: if_icmpne     95
      93: iconst_1
      94: ireturn
      95: iload_2
      96: getstatic     #25                 // Field anIntArray620:[I
      99: iload         5
     101: iaload
     102: if_icmpge     112
     105: iload         5
     107: istore        4
     109: goto          115
     112: iload         5
     114: istore_3
     115: iload_3
     116: iload         4
     118: if_icmpeq     129
     121: iload_3
     122: iconst_1
     123: iadd
     124: iload         4
     126: if_icmpne     75
     129: iconst_0
     130: ireturn

  private static int method524(char[]);
    Code:
       0: aload_0
       1: arraylength
       2: bipush        6
       4: if_icmple     9
       7: iconst_0
       8: ireturn
       9: iconst_0
      10: istore_1
      11: iconst_0
      12: istore_2
      13: iload_2
      14: aload_0
      15: arraylength
      16: if_icmpge     112
      19: aload_0
      20: aload_0
      21: arraylength
      22: iload_2
      23: isub
      24: iconst_1
      25: isub
      26: caload
      27: istore_3
      28: iload_3
      29: bipush        97
      31: if_icmplt     55
      34: iload_3
      35: bipush        122
      37: if_icmpgt     55
      40: iload_1
      41: bipush        38
      43: imul
      44: iload_3
      45: bipush        97
      47: isub
      48: iconst_1
      49: iadd
      50: iadd
      51: istore_1
      52: goto          106
      55: iload_3
      56: bipush        39
      58: if_icmpne     72
      61: iload_1
      62: bipush        38
      64: imul
      65: bipush        27
      67: iadd
      68: istore_1
      69: goto          106
      72: iload_3
      73: bipush        48
      75: if_icmplt     100
      78: iload_3
      79: bipush        57
      81: if_icmpgt     100
      84: iload_1
      85: bipush        38
      87: imul
      88: iload_3
      89: bipush        48
      91: isub
      92: bipush        28
      94: iadd
      95: iadd
      96: istore_1
      97: goto          106
     100: iload_3
     101: ifeq          106
     104: iconst_0
     105: ireturn
     106: iinc          2, 1
     109: goto          13
     112: iload_1
     113: ireturn

  static {};
    Code:
       0: bipush        10
       2: anewarray     #31                 // class java/lang/String
       5: dup
       6: iconst_0
       7: ldc           #69                 // String cook
       9: aastore
      10: dup
      11: iconst_1
      12: ldc           #70                 // String cook's
      14: aastore
      15: dup
      16: iconst_2
      17: ldc           #71                 // String cooks
      19: aastore
      20: dup
      21: iconst_3
      22: ldc           #72                 // String seeks
      24: aastore
      25: dup
      26: iconst_4
      27: ldc           #73                 // String sheet
      29: aastore
      30: dup
      31: iconst_5
      32: ldc           #74                 // String woop
      34: aastore
      35: dup
      36: bipush        6
      38: ldc           #75                 // String woops
      40: aastore
      41: dup
      42: bipush        7
      44: ldc           #76                 // String faq
      46: aastore
      47: dup
      48: bipush        8
      50: ldc           #77                 // String noob
      52: aastore
      53: dup
      54: bipush        9
      56: ldc           #78                 // String noobs
      58: aastore
      59: putstatic     #39                 // Field exceptions:[Ljava/lang/String;
      62: return
}
