Compiled from "Class4.java"
final class Class4 {
  Class4();
    Code:
       0: aload_0
       1: invokespecial #1                  // Method java/lang/Object."<init>":()V
       4: return

  public static int method155(int, int, int);
    Code:
       0: iload_0
       1: iconst_3
       2: iand
       3: istore_0
       4: iload_0
       5: ifne          10
       8: iload_2
       9: ireturn
      10: iload_0
      11: iconst_1
      12: if_icmpne     17
      15: iload_1
      16: ireturn
      17: iload_0
      18: iconst_2
      19: if_icmpne     27
      22: bipush        7
      24: iload_2
      25: isub
      26: ireturn
      27: bipush        7
      29: iload_1
      30: isub
      31: ireturn

  public static int method156(int, int, int);
    Code:
       0: iload_1
       1: iconst_3
       2: iand
       3: istore_1
       4: iload_1
       5: ifne          10
       8: iload_0
       9: ireturn
      10: iload_1
      11: iconst_1
      12: if_icmpne     20
      15: bipush        7
      17: iload_2
      18: isub
      19: ireturn
      20: iload_1
      21: iconst_2
      22: if_icmpne     30
      25: bipush        7
      27: iload_0
      28: isub
      29: ireturn
      30: iload_2
      31: ireturn

  public static int method157(int, int, int, int, int);
    Code:
       0: iload_0
       1: iconst_3
       2: iand
       3: istore_0
       4: iload_0
       5: ifne          10
       8: iload_2
       9: ireturn
      10: iload_0
      11: iconst_1
      12: if_icmpne     17
      15: iload_3
      16: ireturn
      17: iload_0
      18: iconst_2
      19: if_icmpne     32
      22: bipush        7
      24: iload_2
      25: isub
      26: iload         4
      28: iconst_1
      29: isub
      30: isub
      31: ireturn
      32: bipush        7
      34: iload_3
      35: isub
      36: iload_1
      37: iconst_1
      38: isub
      39: isub
      40: ireturn

  public static int method158(int, int, int, int, int);
    Code:
       0: iload_2
       1: iconst_3
       2: iand
       3: istore_2
       4: iload_2
       5: ifne          10
       8: iload_0
       9: ireturn
      10: iload_2
      11: iconst_1
      12: if_icmpne     25
      15: bipush        7
      17: iload         4
      19: isub
      20: iload_3
      21: iconst_1
      22: isub
      23: isub
      24: ireturn
      25: iload_2
      26: iconst_2
      27: if_icmpne     39
      30: bipush        7
      32: iload_0
      33: isub
      34: iload_1
      35: iconst_1
      36: isub
      37: isub
      38: ireturn
      39: iload         4
      41: ireturn
}
