Compiled from "Class18.java"
public final class Class18 {
  public final int[] anIntArray342;

  public final int[][] anIntArrayArray343;

  public Class18(Stream);
    Code:
       0: aload_0
       1: invokespecial #1                  // Method java/lang/Object."<init>":()V
       4: aload_1
       5: invokevirtual #2                  // Method Stream.readUnsignedByte:()I
       8: istore_2
       9: aload_0
      10: iload_2
      11: newarray       int
      13: putfield      #3                  // Field anIntArray342:[I
      16: aload_0
      17: iload_2
      18: anewarray     #4                  // class "[I"
      21: putfield      #5                  // Field anIntArrayArray343:[[I
      24: iconst_0
      25: istore_3
      26: iload_3
      27: iload_2
      28: if_icmpge     47
      31: aload_0
      32: getfield      #3                  // Field anIntArray342:[I
      35: iload_3
      36: aload_1
      37: invokevirtual #2                  // Method Stream.readUnsignedByte:()I
      40: iastore
      41: iinc          3, 1
      44: goto          26
      47: iconst_0
      48: istore_3
      49: iload_3
      50: iload_2
      51: if_icmpge     105
      54: aload_1
      55: invokevirtual #2                  // Method Stream.readUnsignedByte:()I
      58: istore        4
      60: aload_0
      61: getfield      #5                  // Field anIntArrayArray343:[[I
      64: iload_3
      65: iload         4
      67: newarray       int
      69: aastore
      70: iconst_0
      71: istore        5
      73: iload         5
      75: iload         4
      77: if_icmpge     99
      80: aload_0
      81: getfield      #5                  // Field anIntArrayArray343:[[I
      84: iload_3
      85: aaload
      86: iload         5
      88: aload_1
      89: invokevirtual #2                  // Method Stream.readUnsignedByte:()I
      92: iastore
      93: iinc          5, 1
      96: goto          73
      99: iinc          3, 1
     102: goto          49
     105: return
}
