Compiled from "Class36.java"
public final class Class36 {
  private static Class36[] aClass36Array635;

  public int anInt636;

  public Class18 aClass18_637;

  public int anInt638;

  public int[] anIntArray639;

  public int[] anIntArray640;

  public int[] anIntArray641;

  public int[] anIntArray642;

  private static boolean[] aBooleanArray643;

  public static void method528(int);
    Code:
       0: iload_0
       1: iconst_1
       2: iadd
       3: anewarray     #1                  // class Class36
       6: putstatic     #2                  // Field aClass36Array635:[LClass36;
       9: iload_0
      10: iconst_1
      11: iadd
      12: newarray       boolean
      14: putstatic     #3                  // Field aBooleanArray643:[Z
      17: iconst_0
      18: istore_1
      19: iload_1
      20: iload_0
      21: iconst_1
      22: iadd
      23: if_icmpge     38
      26: getstatic     #3                  // Field aBooleanArray643:[Z
      29: iload_1
      30: iconst_1
      31: bastore
      32: iinc          1, 1
      35: goto          19
      38: return

  public static void method529(byte[]);
    Code:
       0: new           #4                  // class Stream
       3: dup
       4: aload_0
       5: invokespecial #5                  // Method Stream."<init>":([B)V
       8: astore_1
       9: aload_1
      10: aload_0
      11: arraylength
      12: bipush        8
      14: isub
      15: putfield      #6                  // Field Stream.currentOffset:I
      18: aload_1
      19: invokevirtual #7                  // Method Stream.readUnsignedWord:()I
      22: istore_2
      23: aload_1
      24: invokevirtual #7                  // Method Stream.readUnsignedWord:()I
      27: istore_3
      28: aload_1
      29: invokevirtual #7                  // Method Stream.readUnsignedWord:()I
      32: istore        4
      34: aload_1
      35: invokevirtual #7                  // Method Stream.readUnsignedWord:()I
      38: istore        5
      40: iconst_0
      41: istore        6
      43: new           #4                  // class Stream
      46: dup
      47: aload_0
      48: invokespecial #5                  // Method Stream."<init>":([B)V
      51: astore        7
      53: aload         7
      55: iload         6
      57: putfield      #6                  // Field Stream.currentOffset:I
      60: iload         6
      62: iload_2
      63: iconst_2
      64: iadd
      65: iadd
      66: istore        6
      68: new           #4                  // class Stream
      71: dup
      72: aload_0
      73: invokespecial #5                  // Method Stream."<init>":([B)V
      76: astore        8
      78: aload         8
      80: iload         6
      82: putfield      #6                  // Field Stream.currentOffset:I
      85: iload         6
      87: iload_3
      88: iadd
      89: istore        6
      91: new           #4                  // class Stream
      94: dup
      95: aload_0
      96: invokespecial #5                  // Method Stream."<init>":([B)V
      99: astore        9
     101: aload         9
     103: iload         6
     105: putfield      #6                  // Field Stream.currentOffset:I
     108: iload         6
     110: iload         4
     112: iadd
     113: istore        6
     115: new           #4                  // class Stream
     118: dup
     119: aload_0
     120: invokespecial #5                  // Method Stream."<init>":([B)V
     123: astore        10
     125: aload         10
     127: iload         6
     129: putfield      #6                  // Field Stream.currentOffset:I
     132: iload         6
     134: iload         5
     136: iadd
     137: istore        6
     139: new           #4                  // class Stream
     142: dup
     143: aload_0
     144: invokespecial #5                  // Method Stream."<init>":([B)V
     147: astore        11
     149: aload         11
     151: iload         6
     153: putfield      #6                  // Field Stream.currentOffset:I
     156: new           #8                  // class Class18
     159: dup
     160: aload         11
     162: invokespecial #9                  // Method Class18."<init>":(LStream;)V
     165: astore        12
     167: aload         7
     169: invokevirtual #7                  // Method Stream.readUnsignedWord:()I
     172: istore        13
     174: sipush        500
     177: newarray       int
     179: astore        14
     181: sipush        500
     184: newarray       int
     186: astore        15
     188: sipush        500
     191: newarray       int
     193: astore        16
     195: sipush        500
     198: newarray       int
     200: astore        17
     202: iconst_0
     203: istore        18
     205: iload         18
     207: iload         13
     209: if_icmpge     619
     212: aload         7
     214: invokevirtual #7                  // Method Stream.readUnsignedWord:()I
     217: istore        19
     219: getstatic     #2                  // Field aClass36Array635:[LClass36;
     222: iload         19
     224: new           #1                  // class Class36
     227: dup
     228: invokespecial #10                 // Method "<init>":()V
     231: dup_x2
     232: aastore
     233: astore        20
     235: aload         20
     237: aload         10
     239: invokevirtual #11                 // Method Stream.readUnsignedByte:()I
     242: putfield      #12                 // Field anInt636:I
     245: aload         20
     247: aload         12
     249: putfield      #13                 // Field aClass18_637:LClass18;
     252: aload         7
     254: invokevirtual #11                 // Method Stream.readUnsignedByte:()I
     257: istore        21
     259: iconst_m1
     260: istore        22
     262: iconst_0
     263: istore        23
     265: iconst_0
     266: istore        24
     268: iload         24
     270: iload         21
     272: if_icmpge     502
     275: aload         8
     277: invokevirtual #11                 // Method Stream.readUnsignedByte:()I
     280: istore        25
     282: iload         25
     284: ifle          496
     287: aload         12
     289: getfield      #14                 // Field Class18.anIntArray342:[I
     292: iload         24
     294: iaload
     295: ifeq          362
     298: iload         24
     300: iconst_1
     301: isub
     302: istore        26
     304: iload         26
     306: iload         22
     308: if_icmple     362
     311: aload         12
     313: getfield      #14                 // Field Class18.anIntArray342:[I
     316: iload         26
     318: iaload
     319: ifeq          325
     322: goto          356
     325: aload         14
     327: iload         23
     329: iload         26
     331: iastore
     332: aload         15
     334: iload         23
     336: iconst_0
     337: iastore
     338: aload         16
     340: iload         23
     342: iconst_0
     343: iastore
     344: aload         17
     346: iload         23
     348: iconst_0
     349: iastore
     350: iinc          23, 1
     353: goto          362
     356: iinc          26, -1
     359: goto          304
     362: aload         14
     364: iload         23
     366: iload         24
     368: iastore
     369: iconst_0
     370: istore        26
     372: aload         12
     374: getfield      #14                 // Field Class18.anIntArray342:[I
     377: iload         24
     379: iaload
     380: iconst_3
     381: if_icmpne     389
     384: sipush        128
     387: istore        26
     389: iload         25
     391: iconst_1
     392: iand
     393: ifeq          409
     396: aload         15
     398: iload         23
     400: aload         9
     402: invokevirtual #15                 // Method Stream.method421:()I
     405: iastore
     406: goto          416
     409: aload         15
     411: iload         23
     413: iload         26
     415: iastore
     416: iload         25
     418: iconst_2
     419: iand
     420: ifeq          436
     423: aload         16
     425: iload         23
     427: aload         9
     429: invokevirtual #15                 // Method Stream.method421:()I
     432: iastore
     433: goto          443
     436: aload         16
     438: iload         23
     440: iload         26
     442: iastore
     443: iload         25
     445: iconst_4
     446: iand
     447: ifeq          463
     450: aload         17
     452: iload         23
     454: aload         9
     456: invokevirtual #15                 // Method Stream.method421:()I
     459: iastore
     460: goto          470
     463: aload         17
     465: iload         23
     467: iload         26
     469: iastore
     470: iload         24
     472: istore        22
     474: iinc          23, 1
     477: aload         12
     479: getfield      #14                 // Field Class18.anIntArray342:[I
     482: iload         24
     484: iaload
     485: iconst_5
     486: if_icmpne     496
     489: getstatic     #3                  // Field aBooleanArray643:[Z
     492: iload         19
     494: iconst_0
     495: bastore
     496: iinc          24, 1
     499: goto          268
     502: aload         20
     504: iload         23
     506: putfield      #16                 // Field anInt638:I
     509: aload         20
     511: iload         23
     513: newarray       int
     515: putfield      #17                 // Field anIntArray639:[I
     518: aload         20
     520: iload         23
     522: newarray       int
     524: putfield      #18                 // Field anIntArray640:[I
     527: aload         20
     529: iload         23
     531: newarray       int
     533: putfield      #19                 // Field anIntArray641:[I
     536: aload         20
     538: iload         23
     540: newarray       int
     542: putfield      #20                 // Field anIntArray642:[I
     545: iconst_0
     546: istore        24
     548: iload         24
     550: iload         23
     552: if_icmpge     613
     555: aload         20
     557: getfield      #17                 // Field anIntArray639:[I
     560: iload         24
     562: aload         14
     564: iload         24
     566: iaload
     567: iastore
     568: aload         20
     570: getfield      #18                 // Field anIntArray640:[I
     573: iload         24
     575: aload         15
     577: iload         24
     579: iaload
     580: iastore
     581: aload         20
     583: getfield      #19                 // Field anIntArray641:[I
     586: iload         24
     588: aload         16
     590: iload         24
     592: iaload
     593: iastore
     594: aload         20
     596: getfield      #20                 // Field anIntArray642:[I
     599: iload         24
     601: aload         17
     603: iload         24
     605: iaload
     606: iastore
     607: iinc          24, 1
     610: goto          548
     613: iinc          18, 1
     616: goto          205
     619: return

  public static void nullLoader();
    Code:
       0: aconst_null
       1: putstatic     #2                  // Field aClass36Array635:[LClass36;
       4: return

  public static Class36 method531(int);
    Code:
       0: getstatic     #2                  // Field aClass36Array635:[LClass36;
       3: ifnonnull     8
       6: aconst_null
       7: areturn
       8: getstatic     #2                  // Field aClass36Array635:[LClass36;
      11: iload_0
      12: aaload
      13: areturn

  public static boolean method532(int);
    Code:
       0: iload_0
       1: iconst_m1
       2: if_icmpne     9
       5: iconst_1
       6: goto          10
       9: iconst_0
      10: ireturn

  private Class36();
    Code:
       0: aload_0
       1: invokespecial #21                 // Method java/lang/Object."<init>":()V
       4: return
}
