Compiled from "DrawingArea.java"
public class DrawingArea extends NodeSub {
  public static int[] pixels;

  public static int width;

  public static int height;

  public static int topY;

  public static int bottomY;

  public static int topX;

  public static int bottomX;

  public static int centerX;

  public static int centerY;

  public static int anInt1387;

  public static void initDrawingArea(int, int, int[]);
    Code:
       0: aload_2
       1: putstatic     #1                  // Field pixels:[I
       4: iload_1
       5: putstatic     #2                  // Field width:I
       8: iload_0
       9: putstatic     #3                  // Field height:I
      12: iload_0
      13: iconst_0
      14: iload_1
      15: iconst_0
      16: invokestatic  #4                  // Method setDrawingArea:(IIII)V
      19: return

  public static void defaultDrawingAreaSize();
    Code:
       0: iconst_0
       1: putstatic     #5                  // Field topX:I
       4: iconst_0
       5: putstatic     #6                  // Field topY:I
       8: getstatic     #2                  // Field width:I
      11: putstatic     #7                  // Field bottomX:I
      14: getstatic     #3                  // Field height:I
      17: putstatic     #8                  // Field bottomY:I
      20: getstatic     #7                  // Field bottomX:I
      23: iconst_1
      24: isub
      25: putstatic     #9                  // Field centerX:I
      28: getstatic     #7                  // Field bottomX:I
      31: iconst_2
      32: idiv
      33: putstatic     #10                 // Field centerY:I
      36: return

  public static void setDrawingArea(int, int, int, int);
    Code:
       0: iload_1
       1: ifge          6
       4: iconst_0
       5: istore_1
       6: iload_3
       7: ifge          12
      10: iconst_0
      11: istore_3
      12: iload_2
      13: getstatic     #2                  // Field width:I
      16: if_icmple     23
      19: getstatic     #2                  // Field width:I
      22: istore_2
      23: iload_0
      24: getstatic     #3                  // Field height:I
      27: if_icmple     34
      30: getstatic     #3                  // Field height:I
      33: istore_0
      34: iload_1
      35: putstatic     #5                  // Field topX:I
      38: iload_3
      39: putstatic     #6                  // Field topY:I
      42: iload_2
      43: putstatic     #7                  // Field bottomX:I
      46: iload_0
      47: putstatic     #8                  // Field bottomY:I
      50: getstatic     #7                  // Field bottomX:I
      53: iconst_1
      54: isub
      55: putstatic     #9                  // Field centerX:I
      58: getstatic     #7                  // Field bottomX:I
      61: iconst_2
      62: idiv
      63: putstatic     #10                 // Field centerY:I
      66: getstatic     #8                  // Field bottomY:I
      69: iconst_2
      70: idiv
      71: putstatic     #11                 // Field anInt1387:I
      74: return

  public static void setAllPixelsToZero();
    Code:
       0: getstatic     #2                  // Field width:I
       3: getstatic     #3                  // Field height:I
       6: imul
       7: istore_0
       8: iconst_0
       9: istore_1
      10: iload_1
      11: iload_0
      12: if_icmpge     27
      15: getstatic     #1                  // Field pixels:[I
      18: iload_1
      19: iconst_0
      20: iastore
      21: iinc          1, 1
      24: goto          10
      27: return

  public static void method335(int, int, int, int, int, int);
    Code:
       0: iload         5
       2: getstatic     #5                  // Field topX:I
       5: if_icmpge     22
       8: iload_2
       9: getstatic     #5                  // Field topX:I
      12: iload         5
      14: isub
      15: isub
      16: istore_2
      17: getstatic     #5                  // Field topX:I
      20: istore        5
      22: iload_1
      23: getstatic     #6                  // Field topY:I
      26: if_icmpge     41
      29: iload_3
      30: getstatic     #6                  // Field topY:I
      33: iload_1
      34: isub
      35: isub
      36: istore_3
      37: getstatic     #6                  // Field topY:I
      40: istore_1
      41: iload         5
      43: iload_2
      44: iadd
      45: getstatic     #7                  // Field bottomX:I
      48: if_icmple     58
      51: getstatic     #7                  // Field bottomX:I
      54: iload         5
      56: isub
      57: istore_2
      58: iload_1
      59: iload_3
      60: iadd
      61: getstatic     #8                  // Field bottomY:I
      64: if_icmple     73
      67: getstatic     #8                  // Field bottomY:I
      70: iload_1
      71: isub
      72: istore_3
      73: sipush        256
      76: iload         4
      78: isub
      79: istore        6
      81: iload_0
      82: bipush        16
      84: ishr
      85: sipush        255
      88: iand
      89: iload         4
      91: imul
      92: istore        7
      94: iload_0
      95: bipush        8
      97: ishr
      98: sipush        255
     101: iand
     102: iload         4
     104: imul
     105: istore        8
     107: iload_0
     108: sipush        255
     111: iand
     112: iload         4
     114: imul
     115: istore        9
     117: getstatic     #2                  // Field width:I
     120: iload_2
     121: isub
     122: istore        10
     124: iload         5
     126: iload_1
     127: getstatic     #2                  // Field width:I
     130: imul
     131: iadd
     132: istore        11
     134: iconst_0
     135: istore        12
     137: iload         12
     139: iload_3
     140: if_icmpge     267
     143: iload_2
     144: ineg
     145: istore        13
     147: iload         13
     149: ifge          254
     152: getstatic     #1                  // Field pixels:[I
     155: iload         11
     157: iaload
     158: bipush        16
     160: ishr
     161: sipush        255
     164: iand
     165: iload         6
     167: imul
     168: istore        14
     170: getstatic     #1                  // Field pixels:[I
     173: iload         11
     175: iaload
     176: bipush        8
     178: ishr
     179: sipush        255
     182: iand
     183: iload         6
     185: imul
     186: istore        15
     188: getstatic     #1                  // Field pixels:[I
     191: iload         11
     193: iaload
     194: sipush        255
     197: iand
     198: iload         6
     200: imul
     201: istore        16
     203: iload         7
     205: iload         14
     207: iadd
     208: bipush        8
     210: ishr
     211: bipush        16
     213: ishl
     214: iload         8
     216: iload         15
     218: iadd
     219: bipush        8
     221: ishr
     222: bipush        8
     224: ishl
     225: iadd
     226: iload         9
     228: iload         16
     230: iadd
     231: bipush        8
     233: ishr
     234: iadd
     235: istore        17
     237: getstatic     #1                  // Field pixels:[I
     240: iload         11
     242: iinc          11, 1
     245: iload         17
     247: iastore
     248: iinc          13, 1
     251: goto          147
     254: iload         11
     256: iload         10
     258: iadd
     259: istore        11
     261: iinc          12, 1
     264: goto          137
     267: return

  public static void method336(int, int, int, int, int);
    Code:
       0: iload_2
       1: getstatic     #5                  // Field topX:I
       4: if_icmpge     21
       7: iload         4
       9: getstatic     #5                  // Field topX:I
      12: iload_2
      13: isub
      14: isub
      15: istore        4
      17: getstatic     #5                  // Field topX:I
      20: istore_2
      21: iload_1
      22: getstatic     #6                  // Field topY:I
      25: if_icmpge     40
      28: iload_0
      29: getstatic     #6                  // Field topY:I
      32: iload_1
      33: isub
      34: isub
      35: istore_0
      36: getstatic     #6                  // Field topY:I
      39: istore_1
      40: iload_2
      41: iload         4
      43: iadd
      44: getstatic     #7                  // Field bottomX:I
      47: if_icmple     57
      50: getstatic     #7                  // Field bottomX:I
      53: iload_2
      54: isub
      55: istore        4
      57: iload_1
      58: iload_0
      59: iadd
      60: getstatic     #8                  // Field bottomY:I
      63: if_icmple     72
      66: getstatic     #8                  // Field bottomY:I
      69: iload_1
      70: isub
      71: istore_0
      72: getstatic     #2                  // Field width:I
      75: iload         4
      77: isub
      78: istore        5
      80: iload_2
      81: iload_1
      82: getstatic     #2                  // Field width:I
      85: imul
      86: iadd
      87: istore        6
      89: iload_0
      90: ineg
      91: istore        7
      93: iload         7
      95: ifge          137
      98: iload         4
     100: ineg
     101: istore        8
     103: iload         8
     105: ifge          124
     108: getstatic     #1                  // Field pixels:[I
     111: iload         6
     113: iinc          6, 1
     116: iload_3
     117: iastore
     118: iinc          8, 1
     121: goto          103
     124: iload         6
     126: iload         5
     128: iadd
     129: istore        6
     131: iinc          7, 1
     134: goto          93
     137: return

  public static void fillPixels(int, int, int, int, int);
    Code:
       0: iload         4
       2: iload_3
       3: iload_1
       4: iload_0
       5: invokestatic  #12                 // Method method339:(IIII)V
       8: iload         4
      10: iload_2
      11: iadd
      12: iconst_1
      13: isub
      14: iload_3
      15: iload_1
      16: iload_0
      17: invokestatic  #12                 // Method method339:(IIII)V
      20: iload         4
      22: iload_3
      23: iload_2
      24: iload_0
      25: invokestatic  #13                 // Method method341:(IIII)V
      28: iload         4
      30: iload_3
      31: iload_2
      32: iload_0
      33: iload_1
      34: iadd
      35: iconst_1
      36: isub
      37: invokestatic  #13                 // Method method341:(IIII)V
      40: return

  public static void method338(int, int, int, int, int, int);
    Code:
       0: iload_3
       1: iload         4
       3: iload_0
       4: iload_2
       5: iload         5
       7: invokestatic  #14                 // Method method340:(IIIII)V
      10: iload_3
      11: iload         4
      13: iload_0
      14: iload_1
      15: iadd
      16: iconst_1
      17: isub
      18: iload_2
      19: iload         5
      21: invokestatic  #14                 // Method method340:(IIIII)V
      24: iload_1
      25: iconst_3
      26: if_icmplt     60
      29: iload_3
      30: iload         5
      32: iload_2
      33: iload_0
      34: iconst_1
      35: iadd
      36: iload_1
      37: iconst_2
      38: isub
      39: invokestatic  #15                 // Method method342:(IIIII)V
      42: iload_3
      43: iload         5
      45: iload         4
      47: iadd
      48: iconst_1
      49: isub
      50: iload_2
      51: iload_0
      52: iconst_1
      53: iadd
      54: iload_1
      55: iconst_2
      56: isub
      57: invokestatic  #15                 // Method method342:(IIIII)V
      60: return

  public static void method339(int, int, int, int);
    Code:
       0: iload_0
       1: getstatic     #6                  // Field topY:I
       4: if_icmplt     14
       7: iload_0
       8: getstatic     #8                  // Field bottomY:I
      11: if_icmplt     15
      14: return
      15: iload_3
      16: getstatic     #5                  // Field topX:I
      19: if_icmpge     34
      22: iload_2
      23: getstatic     #5                  // Field topX:I
      26: iload_3
      27: isub
      28: isub
      29: istore_2
      30: getstatic     #5                  // Field topX:I
      33: istore_3
      34: iload_3
      35: iload_2
      36: iadd
      37: getstatic     #7                  // Field bottomX:I
      40: if_icmple     49
      43: getstatic     #7                  // Field bottomX:I
      46: iload_3
      47: isub
      48: istore_2
      49: iload_3
      50: iload_0
      51: getstatic     #2                  // Field width:I
      54: imul
      55: iadd
      56: istore        4
      58: iconst_0
      59: istore        5
      61: iload         5
      63: iload_2
      64: if_icmpge     83
      67: getstatic     #1                  // Field pixels:[I
      70: iload         4
      72: iload         5
      74: iadd
      75: iload_1
      76: iastore
      77: iinc          5, 1
      80: goto          61
      83: return

  private static void method340(int, int, int, int, int);
    Code:
       0: iload_2
       1: getstatic     #6                  // Field topY:I
       4: if_icmplt     14
       7: iload_2
       8: getstatic     #8                  // Field bottomY:I
      11: if_icmplt     15
      14: return
      15: iload         4
      17: getstatic     #5                  // Field topX:I
      20: if_icmpge     37
      23: iload_1
      24: getstatic     #5                  // Field topX:I
      27: iload         4
      29: isub
      30: isub
      31: istore_1
      32: getstatic     #5                  // Field topX:I
      35: istore        4
      37: iload         4
      39: iload_1
      40: iadd
      41: getstatic     #7                  // Field bottomX:I
      44: if_icmple     54
      47: getstatic     #7                  // Field bottomX:I
      50: iload         4
      52: isub
      53: istore_1
      54: sipush        256
      57: iload_3
      58: isub
      59: istore        5
      61: iload_0
      62: bipush        16
      64: ishr
      65: sipush        255
      68: iand
      69: iload_3
      70: imul
      71: istore        6
      73: iload_0
      74: bipush        8
      76: ishr
      77: sipush        255
      80: iand
      81: iload_3
      82: imul
      83: istore        7
      85: iload_0
      86: sipush        255
      89: iand
      90: iload_3
      91: imul
      92: istore        8
      94: iload         4
      96: iload_2
      97: getstatic     #2                  // Field width:I
     100: imul
     101: iadd
     102: istore        9
     104: iconst_0
     105: istore        10
     107: iload         10
     109: iload_1
     110: if_icmpge     215
     113: getstatic     #1                  // Field pixels:[I
     116: iload         9
     118: iaload
     119: bipush        16
     121: ishr
     122: sipush        255
     125: iand
     126: iload         5
     128: imul
     129: istore        11
     131: getstatic     #1                  // Field pixels:[I
     134: iload         9
     136: iaload
     137: bipush        8
     139: ishr
     140: sipush        255
     143: iand
     144: iload         5
     146: imul
     147: istore        12
     149: getstatic     #1                  // Field pixels:[I
     152: iload         9
     154: iaload
     155: sipush        255
     158: iand
     159: iload         5
     161: imul
     162: istore        13
     164: iload         6
     166: iload         11
     168: iadd
     169: bipush        8
     171: ishr
     172: bipush        16
     174: ishl
     175: iload         7
     177: iload         12
     179: iadd
     180: bipush        8
     182: ishr
     183: bipush        8
     185: ishl
     186: iadd
     187: iload         8
     189: iload         13
     191: iadd
     192: bipush        8
     194: ishr
     195: iadd
     196: istore        14
     198: getstatic     #1                  // Field pixels:[I
     201: iload         9
     203: iinc          9, 1
     206: iload         14
     208: iastore
     209: iinc          10, 1
     212: goto          107
     215: return

  public static void method341(int, int, int, int);
    Code:
       0: iload_3
       1: getstatic     #5                  // Field topX:I
       4: if_icmplt     14
       7: iload_3
       8: getstatic     #7                  // Field bottomX:I
      11: if_icmplt     15
      14: return
      15: iload_0
      16: getstatic     #6                  // Field topY:I
      19: if_icmpge     34
      22: iload_2
      23: getstatic     #6                  // Field topY:I
      26: iload_0
      27: isub
      28: isub
      29: istore_2
      30: getstatic     #6                  // Field topY:I
      33: istore_0
      34: iload_0
      35: iload_2
      36: iadd
      37: getstatic     #8                  // Field bottomY:I
      40: if_icmple     49
      43: getstatic     #8                  // Field bottomY:I
      46: iload_0
      47: isub
      48: istore_2
      49: iload_3
      50: iload_0
      51: getstatic     #2                  // Field width:I
      54: imul
      55: iadd
      56: istore        4
      58: iconst_0
      59: istore        5
      61: iload         5
      63: iload_2
      64: if_icmpge     87
      67: getstatic     #1                  // Field pixels:[I
      70: iload         4
      72: iload         5
      74: getstatic     #2                  // Field width:I
      77: imul
      78: iadd
      79: iload_1
      80: iastore
      81: iinc          5, 1
      84: goto          61
      87: return

  private static void method342(int, int, int, int, int);
    Code:
       0: iload_1
       1: getstatic     #5                  // Field topX:I
       4: if_icmplt     14
       7: iload_1
       8: getstatic     #7                  // Field bottomX:I
      11: if_icmplt     15
      14: return
      15: iload_3
      16: getstatic     #6                  // Field topY:I
      19: if_icmpge     36
      22: iload         4
      24: getstatic     #6                  // Field topY:I
      27: iload_3
      28: isub
      29: isub
      30: istore        4
      32: getstatic     #6                  // Field topY:I
      35: istore_3
      36: iload_3
      37: iload         4
      39: iadd
      40: getstatic     #8                  // Field bottomY:I
      43: if_icmple     53
      46: getstatic     #8                  // Field bottomY:I
      49: iload_3
      50: isub
      51: istore        4
      53: sipush        256
      56: iload_2
      57: isub
      58: istore        5
      60: iload_0
      61: bipush        16
      63: ishr
      64: sipush        255
      67: iand
      68: iload_2
      69: imul
      70: istore        6
      72: iload_0
      73: bipush        8
      75: ishr
      76: sipush        255
      79: iand
      80: iload_2
      81: imul
      82: istore        7
      84: iload_0
      85: sipush        255
      88: iand
      89: iload_2
      90: imul
      91: istore        8
      93: iload_1
      94: iload_3
      95: getstatic     #2                  // Field width:I
      98: imul
      99: iadd
     100: istore        9
     102: iconst_0
     103: istore        10
     105: iload         10
     107: iload         4
     109: if_icmpge     219
     112: getstatic     #1                  // Field pixels:[I
     115: iload         9
     117: iaload
     118: bipush        16
     120: ishr
     121: sipush        255
     124: iand
     125: iload         5
     127: imul
     128: istore        11
     130: getstatic     #1                  // Field pixels:[I
     133: iload         9
     135: iaload
     136: bipush        8
     138: ishr
     139: sipush        255
     142: iand
     143: iload         5
     145: imul
     146: istore        12
     148: getstatic     #1                  // Field pixels:[I
     151: iload         9
     153: iaload
     154: sipush        255
     157: iand
     158: iload         5
     160: imul
     161: istore        13
     163: iload         6
     165: iload         11
     167: iadd
     168: bipush        8
     170: ishr
     171: bipush        16
     173: ishl
     174: iload         7
     176: iload         12
     178: iadd
     179: bipush        8
     181: ishr
     182: bipush        8
     184: ishl
     185: iadd
     186: iload         8
     188: iload         13
     190: iadd
     191: bipush        8
     193: ishr
     194: iadd
     195: istore        14
     197: getstatic     #1                  // Field pixels:[I
     200: iload         9
     202: iload         14
     204: iastore
     205: iload         9
     207: getstatic     #2                  // Field width:I
     210: iadd
     211: istore        9
     213: iinc          10, 1
     216: goto          105
     219: return

  DrawingArea();
    Code:
       0: aload_0
       1: invokespecial #16                 // Method NodeSub."<init>":()V
       4: return
}
