Compiled from "Entity.java"
public class Entity extends Animable {
  public int entScreenX;

  public int entScreenY;

  public final int index;

  public final int[] smallX;

  public final int[] smallY;

  public int interactingEntity;

  int anInt1503;

  int anInt1504;

  int anInt1505;

  public java.lang.String textSpoken;

  public int height;

  public int turnDirection;

  int anInt1511;

  int anInt1512;

  int anInt1513;

  final int[] hitArray;

  final int[] hitMarkTypes;

  final int[] hitsLoopCycle;

  int anInt1517;

  int anInt1518;

  int anInt1519;

  int anInt1520;

  int anInt1521;

  int anInt1522;

  int anInt1523;

  int anInt1524;

  int smallXYIndex;

  public int anim;

  int anInt1527;

  int anInt1528;

  int anInt1529;

  int anInt1530;

  int anInt1531;

  public int loopCycleStatus;

  public int currentHealth;

  public int maxHealth;

  int textCycle;

  int anInt1537;

  int anInt1538;

  int anInt1539;

  int anInt1540;

  boolean aBoolean1541;

  int anInt1542;

  int anInt1543;

  int anInt1544;

  int anInt1545;

  int anInt1546;

  int anInt1547;

  int anInt1548;

  int anInt1549;

  public int x;

  public int y;

  int anInt1552;

  final boolean[] aBooleanArray1553;

  int anInt1554;

  int anInt1555;

  int anInt1556;

  int anInt1557;

  public final void setPos(int, int, boolean);
    Code:
       0: aload_0
       1: getfield      #1                  // Field anim:I
       4: iconst_m1
       5: if_icmpeq     28
       8: getstatic     #2                  // Field Animation.anims:[LAnimation;
      11: aload_0
      12: getfield      #1                  // Field anim:I
      15: aaload
      16: getfield      #3                  // Field Animation.anInt364:I
      19: iconst_1
      20: if_icmpne     28
      23: aload_0
      24: iconst_m1
      25: putfield      #1                  // Field anim:I
      28: iload_3
      29: ifne          186
      32: iload_1
      33: aload_0
      34: getfield      #4                  // Field smallX:[I
      37: iconst_0
      38: iaload
      39: isub
      40: istore        4
      42: iload_2
      43: aload_0
      44: getfield      #5                  // Field smallY:[I
      47: iconst_0
      48: iaload
      49: isub
      50: istore        5
      52: iload         4
      54: bipush        -8
      56: if_icmplt     186
      59: iload         4
      61: bipush        8
      63: if_icmpgt     186
      66: iload         5
      68: bipush        -8
      70: if_icmplt     186
      73: iload         5
      75: bipush        8
      77: if_icmpgt     186
      80: aload_0
      81: getfield      #6                  // Field smallXYIndex:I
      84: bipush        9
      86: if_icmpge     99
      89: aload_0
      90: dup
      91: getfield      #6                  // Field smallXYIndex:I
      94: iconst_1
      95: iadd
      96: putfield      #6                  // Field smallXYIndex:I
      99: aload_0
     100: getfield      #6                  // Field smallXYIndex:I
     103: istore        6
     105: iload         6
     107: ifle          164
     110: aload_0
     111: getfield      #4                  // Field smallX:[I
     114: iload         6
     116: aload_0
     117: getfield      #4                  // Field smallX:[I
     120: iload         6
     122: iconst_1
     123: isub
     124: iaload
     125: iastore
     126: aload_0
     127: getfield      #5                  // Field smallY:[I
     130: iload         6
     132: aload_0
     133: getfield      #5                  // Field smallY:[I
     136: iload         6
     138: iconst_1
     139: isub
     140: iaload
     141: iastore
     142: aload_0
     143: getfield      #7                  // Field aBooleanArray1553:[Z
     146: iload         6
     148: aload_0
     149: getfield      #7                  // Field aBooleanArray1553:[Z
     152: iload         6
     154: iconst_1
     155: isub
     156: baload
     157: bastore
     158: iinc          6, -1
     161: goto          105
     164: aload_0
     165: getfield      #4                  // Field smallX:[I
     168: iconst_0
     169: iload_1
     170: iastore
     171: aload_0
     172: getfield      #5                  // Field smallY:[I
     175: iconst_0
     176: iload_2
     177: iastore
     178: aload_0
     179: getfield      #7                  // Field aBooleanArray1553:[Z
     182: iconst_0
     183: iconst_0
     184: bastore
     185: return
     186: aload_0
     187: iconst_0
     188: putfield      #6                  // Field smallXYIndex:I
     191: aload_0
     192: iconst_0
     193: putfield      #8                  // Field anInt1542:I
     196: aload_0
     197: iconst_0
     198: putfield      #9                  // Field anInt1503:I
     201: aload_0
     202: getfield      #4                  // Field smallX:[I
     205: iconst_0
     206: iload_1
     207: iastore
     208: aload_0
     209: getfield      #5                  // Field smallY:[I
     212: iconst_0
     213: iload_2
     214: iastore
     215: aload_0
     216: aload_0
     217: getfield      #4                  // Field smallX:[I
     220: iconst_0
     221: iaload
     222: sipush        128
     225: imul
     226: aload_0
     227: getfield      #10                 // Field anInt1540:I
     230: bipush        64
     232: imul
     233: iadd
     234: putfield      #11                 // Field x:I
     237: aload_0
     238: aload_0
     239: getfield      #5                  // Field smallY:[I
     242: iconst_0
     243: iaload
     244: sipush        128
     247: imul
     248: aload_0
     249: getfield      #10                 // Field anInt1540:I
     252: bipush        64
     254: imul
     255: iadd
     256: putfield      #12                 // Field y:I
     259: return

  public final void method446();
    Code:
       0: aload_0
       1: iconst_0
       2: putfield      #6                  // Field smallXYIndex:I
       5: aload_0
       6: iconst_0
       7: putfield      #8                  // Field anInt1542:I
      10: return

  public final void updateHitData(int, int, int);
    Code:
       0: iconst_0
       1: istore        4
       3: iload         4
       5: iconst_4
       6: if_icmpge     54
       9: aload_0
      10: getfield      #13                 // Field hitsLoopCycle:[I
      13: iload         4
      15: iaload
      16: iload_3
      17: if_icmpgt     48
      20: aload_0
      21: getfield      #14                 // Field hitArray:[I
      24: iload         4
      26: iload_2
      27: iastore
      28: aload_0
      29: getfield      #15                 // Field hitMarkTypes:[I
      32: iload         4
      34: iload_1
      35: iastore
      36: aload_0
      37: getfield      #13                 // Field hitsLoopCycle:[I
      40: iload         4
      42: iload_3
      43: bipush        70
      45: iadd
      46: iastore
      47: return
      48: iinc          4, 1
      51: goto          3
      54: return

  public final void moveInDir(boolean, int);
    Code:
       0: aload_0
       1: getfield      #4                  // Field smallX:[I
       4: iconst_0
       5: iaload
       6: istore_3
       7: aload_0
       8: getfield      #5                  // Field smallY:[I
      11: iconst_0
      12: iaload
      13: istore        4
      15: iload_2
      16: ifne          25
      19: iinc          3, -1
      22: iinc          4, 1
      25: iload_2
      26: iconst_1
      27: if_icmpne     33
      30: iinc          4, 1
      33: iload_2
      34: iconst_2
      35: if_icmpne     44
      38: iinc          3, 1
      41: iinc          4, 1
      44: iload_2
      45: iconst_3
      46: if_icmpne     52
      49: iinc          3, -1
      52: iload_2
      53: iconst_4
      54: if_icmpne     60
      57: iinc          3, 1
      60: iload_2
      61: iconst_5
      62: if_icmpne     71
      65: iinc          3, -1
      68: iinc          4, -1
      71: iload_2
      72: bipush        6
      74: if_icmpne     80
      77: iinc          4, -1
      80: iload_2
      81: bipush        7
      83: if_icmpne     92
      86: iinc          3, 1
      89: iinc          4, -1
      92: aload_0
      93: getfield      #1                  // Field anim:I
      96: iconst_m1
      97: if_icmpeq     120
     100: getstatic     #2                  // Field Animation.anims:[LAnimation;
     103: aload_0
     104: getfield      #1                  // Field anim:I
     107: aaload
     108: getfield      #3                  // Field Animation.anInt364:I
     111: iconst_1
     112: if_icmpne     120
     115: aload_0
     116: iconst_m1
     117: putfield      #1                  // Field anim:I
     120: aload_0
     121: getfield      #6                  // Field smallXYIndex:I
     124: bipush        9
     126: if_icmpge     139
     129: aload_0
     130: dup
     131: getfield      #6                  // Field smallXYIndex:I
     134: iconst_1
     135: iadd
     136: putfield      #6                  // Field smallXYIndex:I
     139: aload_0
     140: getfield      #6                  // Field smallXYIndex:I
     143: istore        5
     145: iload         5
     147: ifle          204
     150: aload_0
     151: getfield      #4                  // Field smallX:[I
     154: iload         5
     156: aload_0
     157: getfield      #4                  // Field smallX:[I
     160: iload         5
     162: iconst_1
     163: isub
     164: iaload
     165: iastore
     166: aload_0
     167: getfield      #5                  // Field smallY:[I
     170: iload         5
     172: aload_0
     173: getfield      #5                  // Field smallY:[I
     176: iload         5
     178: iconst_1
     179: isub
     180: iaload
     181: iastore
     182: aload_0
     183: getfield      #7                  // Field aBooleanArray1553:[Z
     186: iload         5
     188: aload_0
     189: getfield      #7                  // Field aBooleanArray1553:[Z
     192: iload         5
     194: iconst_1
     195: isub
     196: baload
     197: bastore
     198: iinc          5, -1
     201: goto          145
     204: aload_0
     205: getfield      #4                  // Field smallX:[I
     208: iconst_0
     209: iload_3
     210: iastore
     211: aload_0
     212: getfield      #5                  // Field smallY:[I
     215: iconst_0
     216: iload         4
     218: iastore
     219: aload_0
     220: getfield      #7                  // Field aBooleanArray1553:[Z
     223: iconst_0
     224: iload_1
     225: bastore
     226: return

  public boolean isVisible();
    Code:
       0: iconst_0
       1: ireturn

  Entity();
    Code:
       0: aload_0
       1: invokespecial #16                 // Method Animable."<init>":()V
       4: aload_0
       5: iconst_m1
       6: putfield      #17                 // Field index:I
       9: aload_0
      10: bipush        10
      12: newarray       int
      14: putfield      #4                  // Field smallX:[I
      17: aload_0
      18: bipush        10
      20: newarray       int
      22: putfield      #5                  // Field smallY:[I
      25: aload_0
      26: iconst_m1
      27: putfield      #18                 // Field interactingEntity:I
      30: aload_0
      31: bipush        32
      33: putfield      #19                 // Field anInt1504:I
      36: aload_0
      37: iconst_m1
      38: putfield      #20                 // Field anInt1505:I
      41: aload_0
      42: sipush        200
      45: putfield      #21                 // Field height:I
      48: aload_0
      49: iconst_m1
      50: putfield      #22                 // Field anInt1511:I
      53: aload_0
      54: iconst_m1
      55: putfield      #23                 // Field anInt1512:I
      58: aload_0
      59: iconst_4
      60: newarray       int
      62: putfield      #14                 // Field hitArray:[I
      65: aload_0
      66: iconst_4
      67: newarray       int
      69: putfield      #15                 // Field hitMarkTypes:[I
      72: aload_0
      73: iconst_4
      74: newarray       int
      76: putfield      #13                 // Field hitsLoopCycle:[I
      79: aload_0
      80: iconst_m1
      81: putfield      #24                 // Field anInt1517:I
      84: aload_0
      85: iconst_m1
      86: putfield      #25                 // Field anInt1520:I
      89: aload_0
      90: iconst_m1
      91: putfield      #1                  // Field anim:I
      94: aload_0
      95: sipush        -1000
      98: putfield      #26                 // Field loopCycleStatus:I
     101: aload_0
     102: bipush        100
     104: putfield      #27                 // Field textCycle:I
     107: aload_0
     108: iconst_1
     109: putfield      #10                 // Field anInt1540:I
     112: aload_0
     113: iconst_0
     114: putfield      #28                 // Field aBoolean1541:Z
     117: aload_0
     118: bipush        10
     120: newarray       boolean
     122: putfield      #7                  // Field aBooleanArray1553:[Z
     125: aload_0
     126: iconst_m1
     127: putfield      #29                 // Field anInt1554:I
     130: aload_0
     131: iconst_m1
     132: putfield      #30                 // Field anInt1555:I
     135: aload_0
     136: iconst_m1
     137: putfield      #31                 // Field anInt1556:I
     140: aload_0
     141: iconst_m1
     142: putfield      #32                 // Field anInt1557:I
     145: return
}
