Compiled from "Ground.java"
public final class Ground extends Node {
  int anInt1307;

  final int anInt1308;

  final int anInt1309;

  final int anInt1310;

  public Class43 aClass43_1311;

  public Class40 aClass40_1312;

  public Object1 obj1;

  public Object2 obj2;

  public Object3 obj3;

  public Object4 obj4;

  int anInt1317;

  public final Object5[] obj5Array;

  final int[] anIntArray1319;

  int anInt1320;

  int anInt1321;

  boolean aBoolean1322;

  boolean aBoolean1323;

  boolean aBoolean1324;

  int anInt1325;

  int anInt1326;

  int anInt1327;

  int anInt1328;

  public Ground aClass30_Sub3_1329;

  public Ground(int, int, int);
    Code:
       0: aload_0
       1: invokespecial #1                  // Method Node."<init>":()V
       4: aload_0
       5: iconst_5
       6: anewarray     #2                  // class Object5
       9: putfield      #3                  // Field obj5Array:[LObject5;
      12: aload_0
      13: iconst_5
      14: newarray       int
      16: putfield      #4                  // Field anIntArray1319:[I
      19: aload_0
      20: aload_0
      21: iload_1
      22: dup_x1
      23: putfield      #5                  // Field anInt1307:I
      26: putfield      #6                  // Field anInt1310:I
      29: aload_0
      30: iload_2
      31: putfield      #7                  // Field anInt1308:I
      34: aload_0
      35: iload_3
      36: putfield      #8                  // Field anInt1309:I
      39: return
}
