Compiled from "GUI.java"
public class GUI extends client {
  public javax.swing.JFrame mainFrame;

  public javax.swing.JPanel gamePanel;

  public GUI(java.lang.String[]);
    Code:
       0: aload_0
       1: invokespecial #1                  // Method client."<init>":()V
       4: ldc           #2                  // String javax.swing.plaf.metal.MetalLookAndFeel
       6: invokestatic  #3                  // Method javax/swing/UIManager.setLookAndFeel:(Ljava/lang/String;)V
       9: aload_0
      10: getfield      #4                  // Field server:Ljava/lang/String;
      13: invokestatic  #5                  // Method java/net/InetAddress.getByName:(Ljava/lang/String;)Ljava/net/InetAddress;
      16: invokestatic  #6                  // Method sign/signlink.startpriv:(Ljava/net/InetAddress;)V
      19: aload_0
      20: invokevirtual #7                  // Method initializeClientFrame:()V
      23: aload_0
      24: invokevirtual #8                  // Method init:()V
      27: goto          35
      30: astore_2
      31: aload_2
      32: invokevirtual #10                 // Method java/lang/Exception.printStackTrace:()V
      35: return
    Exception table:
       from    to  target type
           4    27    30   Class java/lang/Exception

  public void initializeClientFrame();
    Code:
       0: iconst_1
       1: invokestatic  #11                 // Method javax/swing/JFrame.setDefaultLookAndFeelDecorated:(Z)V
       4: iconst_0
       5: invokestatic  #12                 // Method javax/swing/JPopupMenu.setDefaultLightWeightPopupEnabled:(Z)V
       8: aload_0
       9: new           #13                 // class javax/swing/JFrame
      12: dup
      13: ldc           #14                 // String Client
      15: invokespecial #15                 // Method javax/swing/JFrame."<init>":(Ljava/lang/String;)V
      18: putfield      #16                 // Field mainFrame:Ljavax/swing/JFrame;
      21: aload_0
      22: getfield      #16                 // Field mainFrame:Ljavax/swing/JFrame;
      25: new           #17                 // class java/awt/BorderLayout
      28: dup
      29: invokespecial #18                 // Method java/awt/BorderLayout."<init>":()V
      32: invokevirtual #19                 // Method javax/swing/JFrame.setLayout:(Ljava/awt/LayoutManager;)V
      35: aload_0
      36: getfield      #16                 // Field mainFrame:Ljavax/swing/JFrame;
      39: iconst_3
      40: invokevirtual #20                 // Method javax/swing/JFrame.setDefaultCloseOperation:(I)V
      43: aload_0
      44: new           #21                 // class javax/swing/JPanel
      47: dup
      48: invokespecial #22                 // Method javax/swing/JPanel."<init>":()V
      51: putfield      #23                 // Field gamePanel:Ljavax/swing/JPanel;
      54: aload_0
      55: getfield      #23                 // Field gamePanel:Ljavax/swing/JPanel;
      58: new           #17                 // class java/awt/BorderLayout
      61: dup
      62: invokespecial #18                 // Method java/awt/BorderLayout."<init>":()V
      65: invokevirtual #24                 // Method javax/swing/JPanel.setLayout:(Ljava/awt/LayoutManager;)V
      68: aload_0
      69: getfield      #23                 // Field gamePanel:Ljavax/swing/JPanel;
      72: aload_0
      73: invokevirtual #25                 // Method javax/swing/JPanel.add:(Ljava/awt/Component;)Ljava/awt/Component;
      76: pop
      77: aload_0
      78: getfield      #23                 // Field gamePanel:Ljavax/swing/JPanel;
      81: new           #26                 // class java/awt/Dimension
      84: dup
      85: sipush        765
      88: sipush        503
      91: invokespecial #27                 // Method java/awt/Dimension."<init>":(II)V
      94: invokevirtual #28                 // Method javax/swing/JPanel.setPreferredSize:(Ljava/awt/Dimension;)V
      97: aload_0
      98: getfield      #16                 // Field mainFrame:Ljavax/swing/JFrame;
     101: invokevirtual #29                 // Method javax/swing/JFrame.getContentPane:()Ljava/awt/Container;
     104: aload_0
     105: getfield      #23                 // Field gamePanel:Ljavax/swing/JPanel;
     108: ldc           #30                 // String Center
     110: invokevirtual #31                 // Method java/awt/Container.add:(Ljava/awt/Component;Ljava/lang/Object;)V
     113: aload_0
     114: getfield      #16                 // Field mainFrame:Ljavax/swing/JFrame;
     117: invokevirtual #32                 // Method javax/swing/JFrame.pack:()V
     120: aload_0
     121: getfield      #16                 // Field mainFrame:Ljavax/swing/JFrame;
     124: iconst_1
     125: invokevirtual #33                 // Method javax/swing/JFrame.setVisible:(Z)V
     128: aload_0
     129: getfield      #16                 // Field mainFrame:Ljavax/swing/JFrame;
     132: iconst_0
     133: invokevirtual #34                 // Method javax/swing/JFrame.setResizable:(Z)V
     136: goto          144
     139: astore_1
     140: aload_1
     141: invokevirtual #10                 // Method java/lang/Exception.printStackTrace:()V
     144: return
    Exception table:
       from    to  target type
           0   136   139   Class java/lang/Exception

  public java.net.URL getCodeBase();
    Code:
       0: new           #35                 // class java/net/URL
       3: dup
       4: new           #36                 // class java/lang/StringBuilder
       7: dup
       8: invokespecial #37                 // Method java/lang/StringBuilder."<init>":()V
      11: ldc           #38                 // String http://
      13: invokevirtual #39                 // Method java/lang/StringBuilder.append:(Ljava/lang/String;)Ljava/lang/StringBuilder;
      16: aload_0
      17: getfield      #4                  // Field server:Ljava/lang/String;
      20: invokevirtual #39                 // Method java/lang/StringBuilder.append:(Ljava/lang/String;)Ljava/lang/StringBuilder;
      23: ldc           #40                 // String /cache
      25: invokevirtual #39                 // Method java/lang/StringBuilder.append:(Ljava/lang/String;)Ljava/lang/StringBuilder;
      28: invokevirtual #41                 // Method java/lang/StringBuilder.toString:()Ljava/lang/String;
      31: invokespecial #42                 // Method java/net/URL."<init>":(Ljava/lang/String;)V
      34: areturn
      35: astore_1
      36: aload_0
      37: invokespecial #43                 // Method client.getCodeBase:()Ljava/net/URL;
      40: areturn
    Exception table:
       from    to  target type
           0    34    35   Class java/lang/Exception

  public java.net.URL getDocumentBase();
    Code:
       0: aload_0
       1: invokevirtual #44                 // Method getCodeBase:()Ljava/net/URL;
       4: areturn
}
