Compiled from "ISAACRandomGen.java"
public final class ISAACRandomGen {
  private int count;

  private final int[] results;

  private final int[] memory;

  private int accumulator;

  private int lastResult;

  private int counter;

  public ISAACRandomGen(int[]);
    Code:
       0: aload_0
       1: invokespecial #1                  // Method java/lang/Object."<init>":()V
       4: aload_0
       5: sipush        256
       8: newarray       int
      10: putfield      #2                  // Field memory:[I
      13: aload_0
      14: sipush        256
      17: newarray       int
      19: putfield      #3                  // Field results:[I
      22: aload_1
      23: iconst_0
      24: aload_0
      25: getfield      #3                  // Field results:[I
      28: iconst_0
      29: aload_1
      30: arraylength
      31: invokestatic  #4                  // Method java/lang/System.arraycopy:(Ljava/lang/Object;ILjava/lang/Object;II)V
      34: aload_0
      35: invokespecial #5                  // Method initializeKeySet:()V
      38: return

  public int getNextKey();
    Code:
       0: aload_0
       1: dup
       2: getfield      #6                  // Field count:I
       5: dup_x1
       6: iconst_1
       7: isub
       8: putfield      #6                  // Field count:I
      11: ifne          25
      14: aload_0
      15: invokespecial #7                  // Method isaac:()V
      18: aload_0
      19: sipush        255
      22: putfield      #6                  // Field count:I
      25: aload_0
      26: getfield      #3                  // Field results:[I
      29: aload_0
      30: getfield      #6                  // Field count:I
      33: iaload
      34: ireturn

  private void isaac();
    Code:
       0: aload_0
       1: dup
       2: getfield      #8                  // Field lastResult:I
       5: aload_0
       6: dup
       7: getfield      #9                  // Field counter:I
      10: iconst_1
      11: iadd
      12: dup_x1
      13: putfield      #9                  // Field counter:I
      16: iadd
      17: putfield      #8                  // Field lastResult:I
      20: iconst_0
      21: istore_1
      22: iload_1
      23: sipush        256
      26: if_icmpge     222
      29: aload_0
      30: getfield      #2                  // Field memory:[I
      33: iload_1
      34: iaload
      35: istore_2
      36: iload_1
      37: iconst_3
      38: iand
      39: ifne          61
      42: aload_0
      43: dup
      44: getfield      #10                 // Field accumulator:I
      47: aload_0
      48: getfield      #10                 // Field accumulator:I
      51: bipush        13
      53: ishl
      54: ixor
      55: putfield      #10                 // Field accumulator:I
      58: goto          135
      61: iload_1
      62: iconst_3
      63: iand
      64: iconst_1
      65: if_icmpne     87
      68: aload_0
      69: dup
      70: getfield      #10                 // Field accumulator:I
      73: aload_0
      74: getfield      #10                 // Field accumulator:I
      77: bipush        6
      79: iushr
      80: ixor
      81: putfield      #10                 // Field accumulator:I
      84: goto          135
      87: iload_1
      88: iconst_3
      89: iand
      90: iconst_2
      91: if_icmpne     112
      94: aload_0
      95: dup
      96: getfield      #10                 // Field accumulator:I
      99: aload_0
     100: getfield      #10                 // Field accumulator:I
     103: iconst_2
     104: ishl
     105: ixor
     106: putfield      #10                 // Field accumulator:I
     109: goto          135
     112: iload_1
     113: iconst_3
     114: iand
     115: iconst_3
     116: if_icmpne     135
     119: aload_0
     120: dup
     121: getfield      #10                 // Field accumulator:I
     124: aload_0
     125: getfield      #10                 // Field accumulator:I
     128: bipush        16
     130: iushr
     131: ixor
     132: putfield      #10                 // Field accumulator:I
     135: aload_0
     136: dup
     137: getfield      #10                 // Field accumulator:I
     140: aload_0
     141: getfield      #2                  // Field memory:[I
     144: iload_1
     145: sipush        128
     148: iadd
     149: sipush        255
     152: iand
     153: iaload
     154: iadd
     155: putfield      #10                 // Field accumulator:I
     158: aload_0
     159: getfield      #2                  // Field memory:[I
     162: iload_1
     163: aload_0
     164: getfield      #2                  // Field memory:[I
     167: iload_2
     168: sipush        1020
     171: iand
     172: iconst_2
     173: ishr
     174: iaload
     175: aload_0
     176: getfield      #10                 // Field accumulator:I
     179: iadd
     180: aload_0
     181: getfield      #8                  // Field lastResult:I
     184: iadd
     185: dup
     186: istore_3
     187: iastore
     188: aload_0
     189: getfield      #3                  // Field results:[I
     192: iload_1
     193: aload_0
     194: aload_0
     195: getfield      #2                  // Field memory:[I
     198: iload_3
     199: bipush        8
     201: ishr
     202: sipush        1020
     205: iand
     206: iconst_2
     207: ishr
     208: iaload
     209: iload_2
     210: iadd
     211: dup_x1
     212: putfield      #8                  // Field lastResult:I
     215: iastore
     216: iinc          1, 1
     219: goto          22
     222: return

  private void initializeKeySet();
    Code:
       0: ldc           #11                 // int -1640531527
       2: dup
       3: istore        7
       5: dup
       6: istore        6
       8: dup
       9: istore        5
      11: dup
      12: istore        4
      14: dup
      15: istore_3
      16: dup
      17: istore_2
      18: dup
      19: istore_1
      20: istore        8
      22: iconst_0
      23: istore        9
      25: iload         9
      27: iconst_4
      28: if_icmpge     200
      31: iload         8
      33: iload_1
      34: bipush        11
      36: ishl
      37: ixor
      38: istore        8
      40: iload_3
      41: iload         8
      43: iadd
      44: istore_3
      45: iload_1
      46: iload_2
      47: iadd
      48: istore_1
      49: iload_1
      50: iload_2
      51: iconst_2
      52: iushr
      53: ixor
      54: istore_1
      55: iload         4
      57: iload_1
      58: iadd
      59: istore        4
      61: iload_2
      62: iload_3
      63: iadd
      64: istore_2
      65: iload_2
      66: iload_3
      67: bipush        8
      69: ishl
      70: ixor
      71: istore_2
      72: iload         5
      74: iload_2
      75: iadd
      76: istore        5
      78: iload_3
      79: iload         4
      81: iadd
      82: istore_3
      83: iload_3
      84: iload         4
      86: bipush        16
      88: iushr
      89: ixor
      90: istore_3
      91: iload         6
      93: iload_3
      94: iadd
      95: istore        6
      97: iload         4
      99: iload         5
     101: iadd
     102: istore        4
     104: iload         4
     106: iload         5
     108: bipush        10
     110: ishl
     111: ixor
     112: istore        4
     114: iload         7
     116: iload         4
     118: iadd
     119: istore        7
     121: iload         5
     123: iload         6
     125: iadd
     126: istore        5
     128: iload         5
     130: iload         6
     132: iconst_4
     133: iushr
     134: ixor
     135: istore        5
     137: iload         8
     139: iload         5
     141: iadd
     142: istore        8
     144: iload         6
     146: iload         7
     148: iadd
     149: istore        6
     151: iload         6
     153: iload         7
     155: bipush        8
     157: ishl
     158: ixor
     159: istore        6
     161: iload_1
     162: iload         6
     164: iadd
     165: istore_1
     166: iload         7
     168: iload         8
     170: iadd
     171: istore        7
     173: iload         7
     175: iload         8
     177: bipush        9
     179: iushr
     180: ixor
     181: istore        7
     183: iload_2
     184: iload         7
     186: iadd
     187: istore_2
     188: iload         8
     190: iload_1
     191: iadd
     192: istore        8
     194: iinc          9, 1
     197: goto          25
     200: iconst_0
     201: istore        9
     203: iload         9
     205: sipush        256
     208: if_icmpge     571
     211: iload         8
     213: aload_0
     214: getfield      #3                  // Field results:[I
     217: iload         9
     219: iaload
     220: iadd
     221: istore        8
     223: iload_1
     224: aload_0
     225: getfield      #3                  // Field results:[I
     228: iload         9
     230: iconst_1
     231: iadd
     232: iaload
     233: iadd
     234: istore_1
     235: iload_2
     236: aload_0
     237: getfield      #3                  // Field results:[I
     240: iload         9
     242: iconst_2
     243: iadd
     244: iaload
     245: iadd
     246: istore_2
     247: iload_3
     248: aload_0
     249: getfield      #3                  // Field results:[I
     252: iload         9
     254: iconst_3
     255: iadd
     256: iaload
     257: iadd
     258: istore_3
     259: iload         4
     261: aload_0
     262: getfield      #3                  // Field results:[I
     265: iload         9
     267: iconst_4
     268: iadd
     269: iaload
     270: iadd
     271: istore        4
     273: iload         5
     275: aload_0
     276: getfield      #3                  // Field results:[I
     279: iload         9
     281: iconst_5
     282: iadd
     283: iaload
     284: iadd
     285: istore        5
     287: iload         6
     289: aload_0
     290: getfield      #3                  // Field results:[I
     293: iload         9
     295: bipush        6
     297: iadd
     298: iaload
     299: iadd
     300: istore        6
     302: iload         7
     304: aload_0
     305: getfield      #3                  // Field results:[I
     308: iload         9
     310: bipush        7
     312: iadd
     313: iaload
     314: iadd
     315: istore        7
     317: iload         8
     319: iload_1
     320: bipush        11
     322: ishl
     323: ixor
     324: istore        8
     326: iload_3
     327: iload         8
     329: iadd
     330: istore_3
     331: iload_1
     332: iload_2
     333: iadd
     334: istore_1
     335: iload_1
     336: iload_2
     337: iconst_2
     338: iushr
     339: ixor
     340: istore_1
     341: iload         4
     343: iload_1
     344: iadd
     345: istore        4
     347: iload_2
     348: iload_3
     349: iadd
     350: istore_2
     351: iload_2
     352: iload_3
     353: bipush        8
     355: ishl
     356: ixor
     357: istore_2
     358: iload         5
     360: iload_2
     361: iadd
     362: istore        5
     364: iload_3
     365: iload         4
     367: iadd
     368: istore_3
     369: iload_3
     370: iload         4
     372: bipush        16
     374: iushr
     375: ixor
     376: istore_3
     377: iload         6
     379: iload_3
     380: iadd
     381: istore        6
     383: iload         4
     385: iload         5
     387: iadd
     388: istore        4
     390: iload         4
     392: iload         5
     394: bipush        10
     396: ishl
     397: ixor
     398: istore        4
     400: iload         7
     402: iload         4
     404: iadd
     405: istore        7
     407: iload         5
     409: iload         6
     411: iadd
     412: istore        5
     414: iload         5
     416: iload         6
     418: iconst_4
     419: iushr
     420: ixor
     421: istore        5
     423: iload         8
     425: iload         5
     427: iadd
     428: istore        8
     430: iload         6
     432: iload         7
     434: iadd
     435: istore        6
     437: iload         6
     439: iload         7
     441: bipush        8
     443: ishl
     444: ixor
     445: istore        6
     447: iload_1
     448: iload         6
     450: iadd
     451: istore_1
     452: iload         7
     454: iload         8
     456: iadd
     457: istore        7
     459: iload         7
     461: iload         8
     463: bipush        9
     465: iushr
     466: ixor
     467: istore        7
     469: iload_2
     470: iload         7
     472: iadd
     473: istore_2
     474: iload         8
     476: iload_1
     477: iadd
     478: istore        8
     480: aload_0
     481: getfield      #2                  // Field memory:[I
     484: iload         9
     486: iload         8
     488: iastore
     489: aload_0
     490: getfield      #2                  // Field memory:[I
     493: iload         9
     495: iconst_1
     496: iadd
     497: iload_1
     498: iastore
     499: aload_0
     500: getfield      #2                  // Field memory:[I
     503: iload         9
     505: iconst_2
     506: iadd
     507: iload_2
     508: iastore
     509: aload_0
     510: getfield      #2                  // Field memory:[I
     513: iload         9
     515: iconst_3
     516: iadd
     517: iload_3
     518: iastore
     519: aload_0
     520: getfield      #2                  // Field memory:[I
     523: iload         9
     525: iconst_4
     526: iadd
     527: iload         4
     529: iastore
     530: aload_0
     531: getfield      #2                  // Field memory:[I
     534: iload         9
     536: iconst_5
     537: iadd
     538: iload         5
     540: iastore
     541: aload_0
     542: getfield      #2                  // Field memory:[I
     545: iload         9
     547: bipush        6
     549: iadd
     550: iload         6
     552: iastore
     553: aload_0
     554: getfield      #2                  // Field memory:[I
     557: iload         9
     559: bipush        7
     561: iadd
     562: iload         7
     564: iastore
     565: iinc          9, 8
     568: goto          203
     571: iconst_0
     572: istore        9
     574: iload         9
     576: sipush        256
     579: if_icmpge     942
     582: iload         8
     584: aload_0
     585: getfield      #2                  // Field memory:[I
     588: iload         9
     590: iaload
     591: iadd
     592: istore        8
     594: iload_1
     595: aload_0
     596: getfield      #2                  // Field memory:[I
     599: iload         9
     601: iconst_1
     602: iadd
     603: iaload
     604: iadd
     605: istore_1
     606: iload_2
     607: aload_0
     608: getfield      #2                  // Field memory:[I
     611: iload         9
     613: iconst_2
     614: iadd
     615: iaload
     616: iadd
     617: istore_2
     618: iload_3
     619: aload_0
     620: getfield      #2                  // Field memory:[I
     623: iload         9
     625: iconst_3
     626: iadd
     627: iaload
     628: iadd
     629: istore_3
     630: iload         4
     632: aload_0
     633: getfield      #2                  // Field memory:[I
     636: iload         9
     638: iconst_4
     639: iadd
     640: iaload
     641: iadd
     642: istore        4
     644: iload         5
     646: aload_0
     647: getfield      #2                  // Field memory:[I
     650: iload         9
     652: iconst_5
     653: iadd
     654: iaload
     655: iadd
     656: istore        5
     658: iload         6
     660: aload_0
     661: getfield      #2                  // Field memory:[I
     664: iload         9
     666: bipush        6
     668: iadd
     669: iaload
     670: iadd
     671: istore        6
     673: iload         7
     675: aload_0
     676: getfield      #2                  // Field memory:[I
     679: iload         9
     681: bipush        7
     683: iadd
     684: iaload
     685: iadd
     686: istore        7
     688: iload         8
     690: iload_1
     691: bipush        11
     693: ishl
     694: ixor
     695: istore        8
     697: iload_3
     698: iload         8
     700: iadd
     701: istore_3
     702: iload_1
     703: iload_2
     704: iadd
     705: istore_1
     706: iload_1
     707: iload_2
     708: iconst_2
     709: iushr
     710: ixor
     711: istore_1
     712: iload         4
     714: iload_1
     715: iadd
     716: istore        4
     718: iload_2
     719: iload_3
     720: iadd
     721: istore_2
     722: iload_2
     723: iload_3
     724: bipush        8
     726: ishl
     727: ixor
     728: istore_2
     729: iload         5
     731: iload_2
     732: iadd
     733: istore        5
     735: iload_3
     736: iload         4
     738: iadd
     739: istore_3
     740: iload_3
     741: iload         4
     743: bipush        16
     745: iushr
     746: ixor
     747: istore_3
     748: iload         6
     750: iload_3
     751: iadd
     752: istore        6
     754: iload         4
     756: iload         5
     758: iadd
     759: istore        4
     761: iload         4
     763: iload         5
     765: bipush        10
     767: ishl
     768: ixor
     769: istore        4
     771: iload         7
     773: iload         4
     775: iadd
     776: istore        7
     778: iload         5
     780: iload         6
     782: iadd
     783: istore        5
     785: iload         5
     787: iload         6
     789: iconst_4
     790: iushr
     791: ixor
     792: istore        5
     794: iload         8
     796: iload         5
     798: iadd
     799: istore        8
     801: iload         6
     803: iload         7
     805: iadd
     806: istore        6
     808: iload         6
     810: iload         7
     812: bipush        8
     814: ishl
     815: ixor
     816: istore        6
     818: iload_1
     819: iload         6
     821: iadd
     822: istore_1
     823: iload         7
     825: iload         8
     827: iadd
     828: istore        7
     830: iload         7
     832: iload         8
     834: bipush        9
     836: iushr
     837: ixor
     838: istore        7
     840: iload_2
     841: iload         7
     843: iadd
     844: istore_2
     845: iload         8
     847: iload_1
     848: iadd
     849: istore        8
     851: aload_0
     852: getfield      #2                  // Field memory:[I
     855: iload         9
     857: iload         8
     859: iastore
     860: aload_0
     861: getfield      #2                  // Field memory:[I
     864: iload         9
     866: iconst_1
     867: iadd
     868: iload_1
     869: iastore
     870: aload_0
     871: getfield      #2                  // Field memory:[I
     874: iload         9
     876: iconst_2
     877: iadd
     878: iload_2
     879: iastore
     880: aload_0
     881: getfield      #2                  // Field memory:[I
     884: iload         9
     886: iconst_3
     887: iadd
     888: iload_3
     889: iastore
     890: aload_0
     891: getfield      #2                  // Field memory:[I
     894: iload         9
     896: iconst_4
     897: iadd
     898: iload         4
     900: iastore
     901: aload_0
     902: getfield      #2                  // Field memory:[I
     905: iload         9
     907: iconst_5
     908: iadd
     909: iload         5
     911: iastore
     912: aload_0
     913: getfield      #2                  // Field memory:[I
     916: iload         9
     918: bipush        6
     920: iadd
     921: iload         6
     923: iastore
     924: aload_0
     925: getfield      #2                  // Field memory:[I
     928: iload         9
     930: bipush        7
     932: iadd
     933: iload         7
     935: iastore
     936: iinc          9, 8
     939: goto          574
     942: aload_0
     943: invokespecial #7                  // Method isaac:()V
     946: aload_0
     947: sipush        256
     950: putfield      #6                  // Field count:I
     953: return
}
