Compiled from "Item.java"
final class Item extends Animable {
  public int ID;

  public int x;

  public int y;

  public int anInt1559;

  public final Model getRotatedModel();
    Code:
       0: aload_0
       1: getfield      #1                  // Field ID:I
       4: invokestatic  #2                  // Method ItemDef.forID:(I)LItemDef;
       7: astore_1
       8: aload_1
       9: aload_0
      10: getfield      #3                  // Field anInt1559:I
      13: invokevirtual #4                  // Method ItemDef.method201:(I)LModel;
      16: areturn

  public Item();
    Code:
       0: aload_0
       1: invokespecial #5                  // Method Animable."<init>":()V
       4: return
}
