Compiled from "MouseDetection.java"
final class MouseDetection implements java.lang.Runnable {
  private client clientInstance;

  public final java.lang.Object syncObject;

  public final int[] coordsY;

  public boolean running;

  public final int[] coordsX;

  public int coordsIndex;

  public void run();
    Code:
       0: aload_0
       1: getfield      #1                  // Field running:Z
       4: ifeq          89
       7: aload_0
       8: getfield      #2                  // Field syncObject:Ljava/lang/Object;
      11: dup
      12: astore_1
      13: monitorenter
      14: aload_0
      15: getfield      #3                  // Field coordsIndex:I
      18: sipush        500
      21: if_icmpge     66
      24: aload_0
      25: getfield      #4                  // Field coordsX:[I
      28: aload_0
      29: getfield      #3                  // Field coordsIndex:I
      32: aload_0
      33: getfield      #5                  // Field clientInstance:Lclient;
      36: getfield      #6                  // Field client.mouseX:I
      39: iastore
      40: aload_0
      41: getfield      #7                  // Field coordsY:[I
      44: aload_0
      45: getfield      #3                  // Field coordsIndex:I
      48: aload_0
      49: getfield      #5                  // Field clientInstance:Lclient;
      52: getfield      #8                  // Field client.mouseY:I
      55: iastore
      56: aload_0
      57: dup
      58: getfield      #3                  // Field coordsIndex:I
      61: iconst_1
      62: iadd
      63: putfield      #3                  // Field coordsIndex:I
      66: aload_1
      67: monitorexit
      68: goto          76
      71: astore_2
      72: aload_1
      73: monitorexit
      74: aload_2
      75: athrow
      76: ldc2_w        #9                  // long 50l
      79: invokestatic  #11                 // Method java/lang/Thread.sleep:(J)V
      82: goto          0
      85: astore_1
      86: goto          0
      89: return
    Exception table:
       from    to  target type
          14    68    71   any
          71    74    71   any
          76    82    85   Class java/lang/Exception

  public MouseDetection(client);
    Code:
       0: aload_0
       1: invokespecial #13                 // Method java/lang/Object."<init>":()V
       4: aload_0
       5: new           #14                 // class java/lang/Object
       8: dup
       9: invokespecial #13                 // Method java/lang/Object."<init>":()V
      12: putfield      #2                  // Field syncObject:Ljava/lang/Object;
      15: aload_0
      16: sipush        500
      19: newarray       int
      21: putfield      #7                  // Field coordsY:[I
      24: aload_0
      25: iconst_1
      26: putfield      #1                  // Field running:Z
      29: aload_0
      30: sipush        500
      33: newarray       int
      35: putfield      #4                  // Field coordsX:[I
      38: aload_0
      39: aload_1
      40: putfield      #5                  // Field clientInstance:Lclient;
      43: return
}
