Compiled from "MRUNodes.java"
public final class MRUNodes {
  private final NodeSub emptyNodeSub;

  private final int initialCount;

  private int spaceLeft;

  private final NodeCache nodeCache;

  private final NodeSubList nodeSubList;

  public MRUNodes(int);
    Code:
       0: aload_0
       1: invokespecial #1                  // Method java/lang/Object."<init>":()V
       4: aload_0
       5: new           #2                  // class NodeSub
       8: dup
       9: invokespecial #3                  // Method NodeSub."<init>":()V
      12: putfield      #4                  // Field emptyNodeSub:LNodeSub;
      15: aload_0
      16: new           #5                  // class NodeSubList
      19: dup
      20: invokespecial #6                  // Method NodeSubList."<init>":()V
      23: putfield      #7                  // Field nodeSubList:LNodeSubList;
      26: aload_0
      27: iload_1
      28: putfield      #8                  // Field initialCount:I
      31: aload_0
      32: iload_1
      33: putfield      #9                  // Field spaceLeft:I
      36: aload_0
      37: new           #10                 // class NodeCache
      40: dup
      41: invokespecial #11                 // Method NodeCache."<init>":()V
      44: putfield      #12                 // Field nodeCache:LNodeCache;
      47: return

  public NodeSub insertFromCache(long);
    Code:
       0: aload_0
       1: getfield      #12                 // Field nodeCache:LNodeCache;
       4: lload_1
       5: invokevirtual #13                 // Method NodeCache.findNodeByID:(J)LNode;
       8: checkcast     #2                  // class NodeSub
      11: astore_3
      12: aload_3
      13: ifnull        24
      16: aload_0
      17: getfield      #7                  // Field nodeSubList:LNodeSubList;
      20: aload_3
      21: invokevirtual #14                 // Method NodeSubList.insertHead:(LNodeSub;)V
      24: aload_3
      25: areturn

  public void removeFromCache(NodeSub, long);
    Code:
       0: aload_0
       1: getfield      #9                  // Field spaceLeft:I
       4: ifne          57
       7: aload_0
       8: getfield      #7                  // Field nodeSubList:LNodeSubList;
      11: invokevirtual #15                 // Method NodeSubList.popTail:()LNodeSub;
      14: astore        4
      16: aload         4
      18: invokevirtual #16                 // Method NodeSub.unlink:()V
      21: aload         4
      23: invokevirtual #17                 // Method NodeSub.unlinkSub:()V
      26: aload         4
      28: aload_0
      29: getfield      #4                  // Field emptyNodeSub:LNodeSub;
      32: if_acmpne     54
      35: aload_0
      36: getfield      #7                  // Field nodeSubList:LNodeSubList;
      39: invokevirtual #15                 // Method NodeSubList.popTail:()LNodeSub;
      42: astore        5
      44: aload         5
      46: invokevirtual #16                 // Method NodeSub.unlink:()V
      49: aload         5
      51: invokevirtual #17                 // Method NodeSub.unlinkSub:()V
      54: goto          67
      57: aload_0
      58: dup
      59: getfield      #9                  // Field spaceLeft:I
      62: iconst_1
      63: isub
      64: putfield      #9                  // Field spaceLeft:I
      67: aload_0
      68: getfield      #12                 // Field nodeCache:LNodeCache;
      71: aload_1
      72: lload_2
      73: invokevirtual #18                 // Method NodeCache.removeFromCache:(LNode;J)V
      76: aload_0
      77: getfield      #7                  // Field nodeSubList:LNodeSubList;
      80: aload_1
      81: invokevirtual #14                 // Method NodeSubList.insertHead:(LNodeSub;)V
      84: return
      85: astore        4
      87: new           #20                 // class java/lang/StringBuilder
      90: dup
      91: invokespecial #21                 // Method java/lang/StringBuilder."<init>":()V
      94: ldc           #22                 // String 47547,
      96: invokevirtual #23                 // Method java/lang/StringBuilder.append:(Ljava/lang/String;)Ljava/lang/StringBuilder;
      99: aload_1
     100: invokevirtual #24                 // Method java/lang/StringBuilder.append:(Ljava/lang/Object;)Ljava/lang/StringBuilder;
     103: ldc           #25                 // String ,
     105: invokevirtual #23                 // Method java/lang/StringBuilder.append:(Ljava/lang/String;)Ljava/lang/StringBuilder;
     108: lload_2
     109: invokevirtual #26                 // Method java/lang/StringBuilder.append:(J)Ljava/lang/StringBuilder;
     112: ldc           #25                 // String ,
     114: invokevirtual #23                 // Method java/lang/StringBuilder.append:(Ljava/lang/String;)Ljava/lang/StringBuilder;
     117: iconst_2
     118: invokevirtual #27                 // Method java/lang/StringBuilder.append:(I)Ljava/lang/StringBuilder;
     121: ldc           #25                 // String ,
     123: invokevirtual #23                 // Method java/lang/StringBuilder.append:(Ljava/lang/String;)Ljava/lang/StringBuilder;
     126: aload         4
     128: invokevirtual #28                 // Method java/lang/RuntimeException.toString:()Ljava/lang/String;
     131: invokevirtual #23                 // Method java/lang/StringBuilder.append:(Ljava/lang/String;)Ljava/lang/StringBuilder;
     134: invokevirtual #29                 // Method java/lang/StringBuilder.toString:()Ljava/lang/String;
     137: invokestatic  #30                 // Method sign/signlink.reporterror:(Ljava/lang/String;)V
     140: new           #19                 // class java/lang/RuntimeException
     143: dup
     144: invokespecial #31                 // Method java/lang/RuntimeException."<init>":()V
     147: athrow
    Exception table:
       from    to  target type
           0    84    85   Class java/lang/RuntimeException

  public void unlinkAll();
    Code:
       0: aload_0
       1: getfield      #7                  // Field nodeSubList:LNodeSubList;
       4: invokevirtual #15                 // Method NodeSubList.popTail:()LNodeSub;
       7: astore_1
       8: aload_1
       9: ifnull        23
      12: aload_1
      13: invokevirtual #16                 // Method NodeSub.unlink:()V
      16: aload_1
      17: invokevirtual #17                 // Method NodeSub.unlinkSub:()V
      20: goto          32
      23: aload_0
      24: aload_0
      25: getfield      #8                  // Field initialCount:I
      28: putfield      #9                  // Field spaceLeft:I
      31: return
      32: goto          0
}
