Compiled from "NodeSubList.java"
final class NodeSubList {
  private final NodeSub head;

  private NodeSub current;

  public NodeSubList();
    Code:
       0: aload_0
       1: invokespecial #1                  // Method java/lang/Object."<init>":()V
       4: aload_0
       5: new           #2                  // class NodeSub
       8: dup
       9: invokespecial #3                  // Method NodeSub."<init>":()V
      12: putfield      #4                  // Field head:LNodeSub;
      15: aload_0
      16: getfield      #4                  // Field head:LNodeSub;
      19: aload_0
      20: getfield      #4                  // Field head:LNodeSub;
      23: putfield      #5                  // Field NodeSub.prevNodeSub:LNodeSub;
      26: aload_0
      27: getfield      #4                  // Field head:LNodeSub;
      30: aload_0
      31: getfield      #4                  // Field head:LNodeSub;
      34: putfield      #6                  // Field NodeSub.nextNodeSub:LNodeSub;
      37: return

  public void insertHead(NodeSub);
    Code:
       0: aload_1
       1: getfield      #6                  // Field NodeSub.nextNodeSub:LNodeSub;
       4: ifnull        11
       7: aload_1
       8: invokevirtual #7                  // Method NodeSub.unlinkSub:()V
      11: aload_1
      12: aload_0
      13: getfield      #4                  // Field head:LNodeSub;
      16: getfield      #6                  // Field NodeSub.nextNodeSub:LNodeSub;
      19: putfield      #6                  // Field NodeSub.nextNodeSub:LNodeSub;
      22: aload_1
      23: aload_0
      24: getfield      #4                  // Field head:LNodeSub;
      27: putfield      #5                  // Field NodeSub.prevNodeSub:LNodeSub;
      30: aload_1
      31: getfield      #6                  // Field NodeSub.nextNodeSub:LNodeSub;
      34: aload_1
      35: putfield      #5                  // Field NodeSub.prevNodeSub:LNodeSub;
      38: aload_1
      39: getfield      #5                  // Field NodeSub.prevNodeSub:LNodeSub;
      42: aload_1
      43: putfield      #6                  // Field NodeSub.nextNodeSub:LNodeSub;
      46: return

  public NodeSub popTail();
    Code:
       0: aload_0
       1: getfield      #4                  // Field head:LNodeSub;
       4: getfield      #5                  // Field NodeSub.prevNodeSub:LNodeSub;
       7: astore_1
       8: aload_1
       9: aload_0
      10: getfield      #4                  // Field head:LNodeSub;
      13: if_acmpne     18
      16: aconst_null
      17: areturn
      18: aload_1
      19: invokevirtual #7                  // Method NodeSub.unlinkSub:()V
      22: aload_1
      23: areturn

  public NodeSub reverseGetFirst();
    Code:
       0: aload_0
       1: getfield      #4                  // Field head:LNodeSub;
       4: getfield      #5                  // Field NodeSub.prevNodeSub:LNodeSub;
       7: astore_1
       8: aload_1
       9: aload_0
      10: getfield      #4                  // Field head:LNodeSub;
      13: if_acmpne     23
      16: aload_0
      17: aconst_null
      18: putfield      #8                  // Field current:LNodeSub;
      21: aconst_null
      22: areturn
      23: aload_0
      24: aload_1
      25: getfield      #5                  // Field NodeSub.prevNodeSub:LNodeSub;
      28: putfield      #8                  // Field current:LNodeSub;
      31: aload_1
      32: areturn

  public NodeSub reverseGetNext();
    Code:
       0: aload_0
       1: getfield      #8                  // Field current:LNodeSub;
       4: astore_1
       5: aload_1
       6: aload_0
       7: getfield      #4                  // Field head:LNodeSub;
      10: if_acmpne     20
      13: aload_0
      14: aconst_null
      15: putfield      #8                  // Field current:LNodeSub;
      18: aconst_null
      19: areturn
      20: aload_0
      21: aload_1
      22: getfield      #5                  // Field NodeSub.prevNodeSub:LNodeSub;
      25: putfield      #8                  // Field current:LNodeSub;
      28: aload_1
      29: areturn

  public int getNodeCount();
    Code:
       0: iconst_0
       1: istore_1
       2: aload_0
       3: getfield      #4                  // Field head:LNodeSub;
       6: getfield      #5                  // Field NodeSub.prevNodeSub:LNodeSub;
       9: astore_2
      10: aload_2
      11: aload_0
      12: getfield      #4                  // Field head:LNodeSub;
      15: if_acmpeq     29
      18: iinc          1, 1
      21: aload_2
      22: getfield      #5                  // Field NodeSub.prevNodeSub:LNodeSub;
      25: astore_2
      26: goto          10
      29: iload_1
      30: ireturn
}
