Compiled from "ObjectManager.java"
final class ObjectManager {
  private static int anInt123;

  private final int[] anIntArray124;

  private final int[] anIntArray125;

  private final int[] anIntArray126;

  private final int[] anIntArray127;

  private final int[] anIntArray128;

  private final int[][][] anIntArrayArrayArray129;

  private final byte[][][] aByteArrayArrayArray130;

  static int anInt131;

  private static int anInt133;

  private final byte[][][] aByteArrayArrayArray134;

  private final int[][][] anIntArrayArrayArray135;

  private final byte[][][] aByteArrayArrayArray136;

  private static final int[] anIntArray137;

  private static final int anInt138;

  private final int[][] anIntArrayArray139;

  private static final int[] anIntArray140;

  private final byte[][][] aByteArrayArrayArray142;

  private static final int[] anIntArray144;

  static int anInt145;

  private final int anInt146;

  private final int anInt147;

  private final byte[][][] aByteArrayArrayArray148;

  private final byte[][][] aByteArrayArrayArray149;

  static boolean lowMem;

  private static final int[] anIntArray152;

  public ObjectManager(byte[][][], int[][][]);
    Code:
       0: aload_0
       1: invokespecial #1                  // Method java/lang/Object."<init>":()V
       4: bipush        99
       6: putstatic     #2                  // Field anInt145:I
       9: aload_0
      10: bipush        104
      12: putfield      #3                  // Field anInt146:I
      15: aload_0
      16: bipush        104
      18: putfield      #4                  // Field anInt147:I
      21: aload_0
      22: aload_2
      23: putfield      #5                  // Field anIntArrayArrayArray129:[[[I
      26: aload_0
      27: aload_1
      28: putfield      #6                  // Field aByteArrayArrayArray149:[[[B
      31: aload_0
      32: iconst_4
      33: aload_0
      34: getfield      #3                  // Field anInt146:I
      37: aload_0
      38: getfield      #4                  // Field anInt147:I
      41: multianewarray #7,  3             // class "[[[B"
      45: putfield      #8                  // Field aByteArrayArrayArray142:[[[B
      48: aload_0
      49: iconst_4
      50: aload_0
      51: getfield      #3                  // Field anInt146:I
      54: aload_0
      55: getfield      #4                  // Field anInt147:I
      58: multianewarray #7,  3             // class "[[[B"
      62: putfield      #9                  // Field aByteArrayArrayArray130:[[[B
      65: aload_0
      66: iconst_4
      67: aload_0
      68: getfield      #3                  // Field anInt146:I
      71: aload_0
      72: getfield      #4                  // Field anInt147:I
      75: multianewarray #7,  3             // class "[[[B"
      79: putfield      #10                 // Field aByteArrayArrayArray136:[[[B
      82: aload_0
      83: iconst_4
      84: aload_0
      85: getfield      #3                  // Field anInt146:I
      88: aload_0
      89: getfield      #4                  // Field anInt147:I
      92: multianewarray #7,  3             // class "[[[B"
      96: putfield      #11                 // Field aByteArrayArrayArray148:[[[B
      99: aload_0
     100: iconst_4
     101: aload_0
     102: getfield      #3                  // Field anInt146:I
     105: iconst_1
     106: iadd
     107: aload_0
     108: getfield      #4                  // Field anInt147:I
     111: iconst_1
     112: iadd
     113: multianewarray #12,  3            // class "[[[I"
     117: putfield      #13                 // Field anIntArrayArrayArray135:[[[I
     120: aload_0
     121: iconst_4
     122: aload_0
     123: getfield      #3                  // Field anInt146:I
     126: iconst_1
     127: iadd
     128: aload_0
     129: getfield      #4                  // Field anInt147:I
     132: iconst_1
     133: iadd
     134: multianewarray #7,  3             // class "[[[B"
     138: putfield      #14                 // Field aByteArrayArrayArray134:[[[B
     141: aload_0
     142: aload_0
     143: getfield      #3                  // Field anInt146:I
     146: iconst_1
     147: iadd
     148: aload_0
     149: getfield      #4                  // Field anInt147:I
     152: iconst_1
     153: iadd
     154: multianewarray #15,  2            // class "[[I"
     158: putfield      #16                 // Field anIntArrayArray139:[[I
     161: aload_0
     162: aload_0
     163: getfield      #4                  // Field anInt147:I
     166: newarray       int
     168: putfield      #17                 // Field anIntArray124:[I
     171: aload_0
     172: aload_0
     173: getfield      #4                  // Field anInt147:I
     176: newarray       int
     178: putfield      #18                 // Field anIntArray125:[I
     181: aload_0
     182: aload_0
     183: getfield      #4                  // Field anInt147:I
     186: newarray       int
     188: putfield      #19                 // Field anIntArray126:[I
     191: aload_0
     192: aload_0
     193: getfield      #4                  // Field anInt147:I
     196: newarray       int
     198: putfield      #20                 // Field anIntArray127:[I
     201: aload_0
     202: aload_0
     203: getfield      #4                  // Field anInt147:I
     206: newarray       int
     208: putfield      #21                 // Field anIntArray128:[I
     211: return

  private static int method170(int, int);
    Code:
       0: iload_0
       1: iload_1
       2: bipush        57
       4: imul
       5: iadd
       6: istore_2
       7: iload_2
       8: bipush        13
      10: ishl
      11: iload_2
      12: ixor
      13: istore_2
      14: iload_2
      15: iload_2
      16: iload_2
      17: imul
      18: sipush        15731
      21: imul
      22: ldc           #22                 // int 789221
      24: iadd
      25: imul
      26: ldc           #23                 // int 1376312589
      28: iadd
      29: ldc           #24                 // int 2147483647
      31: iand
      32: istore_3
      33: iload_3
      34: bipush        19
      36: ishr
      37: sipush        255
      40: iand
      41: ireturn

  public final void method171(Class11[], WorldController);
    Code:
       0: iconst_0
       1: istore_3
       2: iload_3
       3: iconst_4
       4: if_icmpge     103
       7: iconst_0
       8: istore        4
      10: iload         4
      12: bipush        104
      14: if_icmpge     97
      17: iconst_0
      18: istore        5
      20: iload         5
      22: bipush        104
      24: if_icmpge     91
      27: aload_0
      28: getfield      #6                  // Field aByteArrayArrayArray149:[[[B
      31: iload_3
      32: aaload
      33: iload         4
      35: aaload
      36: iload         5
      38: baload
      39: iconst_1
      40: iand
      41: iconst_1
      42: if_icmpne     85
      45: iload_3
      46: istore        6
      48: aload_0
      49: getfield      #6                  // Field aByteArrayArrayArray149:[[[B
      52: iconst_1
      53: aaload
      54: iload         4
      56: aaload
      57: iload         5
      59: baload
      60: iconst_2
      61: iand
      62: iconst_2
      63: if_icmpne     69
      66: iinc          6, -1
      69: iload         6
      71: iflt          85
      74: aload_1
      75: iload         6
      77: aaload
      78: iload         5
      80: iload         4
      82: invokevirtual #25                 // Method Class11.method213:(II)V
      85: iinc          5, 1
      88: goto          20
      91: iinc          4, 1
      94: goto          10
      97: iinc          3, 1
     100: goto          2
     103: getstatic     #26                 // Field anInt123:I
     106: invokestatic  #27                 // Method java/lang/Math.random:()D
     109: ldc2_w        #28                 // double 5.0d
     112: dmul
     113: d2i
     114: iconst_2
     115: isub
     116: iadd
     117: putstatic     #26                 // Field anInt123:I
     120: getstatic     #26                 // Field anInt123:I
     123: bipush        -8
     125: if_icmpge     133
     128: bipush        -8
     130: putstatic     #26                 // Field anInt123:I
     133: getstatic     #26                 // Field anInt123:I
     136: bipush        8
     138: if_icmple     146
     141: bipush        8
     143: putstatic     #26                 // Field anInt123:I
     146: getstatic     #30                 // Field anInt133:I
     149: invokestatic  #27                 // Method java/lang/Math.random:()D
     152: ldc2_w        #28                 // double 5.0d
     155: dmul
     156: d2i
     157: iconst_2
     158: isub
     159: iadd
     160: putstatic     #30                 // Field anInt133:I
     163: getstatic     #30                 // Field anInt133:I
     166: bipush        -16
     168: if_icmpge     176
     171: bipush        -16
     173: putstatic     #30                 // Field anInt133:I
     176: getstatic     #30                 // Field anInt133:I
     179: bipush        16
     181: if_icmple     189
     184: bipush        16
     186: putstatic     #30                 // Field anInt133:I
     189: iconst_0
     190: istore_3
     191: iload_3
     192: iconst_4
     193: if_icmpge     1883
     196: aload_0
     197: getfield      #14                 // Field aByteArrayArrayArray134:[[[B
     200: iload_3
     201: aaload
     202: astore        4
     204: bipush        96
     206: istore        5
     208: sipush        768
     211: istore        6
     213: bipush        -50
     215: istore        7
     217: bipush        -10
     219: istore        8
     221: bipush        -50
     223: istore        9
     225: iload         7
     227: iload         7
     229: imul
     230: iload         8
     232: iload         8
     234: imul
     235: iadd
     236: iload         9
     238: iload         9
     240: imul
     241: iadd
     242: i2d
     243: invokestatic  #31                 // Method java/lang/Math.sqrt:(D)D
     246: d2i
     247: istore        10
     249: iload         6
     251: iload         10
     253: imul
     254: bipush        8
     256: ishr
     257: istore        11
     259: iconst_1
     260: istore        12
     262: iload         12
     264: aload_0
     265: getfield      #4                  // Field anInt147:I
     268: iconst_1
     269: isub
     270: if_icmpge     513
     273: iconst_1
     274: istore        13
     276: iload         13
     278: aload_0
     279: getfield      #3                  // Field anInt146:I
     282: iconst_1
     283: isub
     284: if_icmpge     507
     287: aload_0
     288: getfield      #5                  // Field anIntArrayArrayArray129:[[[I
     291: iload_3
     292: aaload
     293: iload         13
     295: iconst_1
     296: iadd
     297: aaload
     298: iload         12
     300: iaload
     301: aload_0
     302: getfield      #5                  // Field anIntArrayArrayArray129:[[[I
     305: iload_3
     306: aaload
     307: iload         13
     309: iconst_1
     310: isub
     311: aaload
     312: iload         12
     314: iaload
     315: isub
     316: istore        14
     318: aload_0
     319: getfield      #5                  // Field anIntArrayArrayArray129:[[[I
     322: iload_3
     323: aaload
     324: iload         13
     326: aaload
     327: iload         12
     329: iconst_1
     330: iadd
     331: iaload
     332: aload_0
     333: getfield      #5                  // Field anIntArrayArrayArray129:[[[I
     336: iload_3
     337: aaload
     338: iload         13
     340: aaload
     341: iload         12
     343: iconst_1
     344: isub
     345: iaload
     346: isub
     347: istore        15
     349: iload         14
     351: iload         14
     353: imul
     354: ldc           #32                 // int 65536
     356: iadd
     357: iload         15
     359: iload         15
     361: imul
     362: iadd
     363: i2d
     364: invokestatic  #31                 // Method java/lang/Math.sqrt:(D)D
     367: d2i
     368: istore        16
     370: iload         14
     372: bipush        8
     374: ishl
     375: iload         16
     377: idiv
     378: istore        17
     380: ldc           #32                 // int 65536
     382: iload         16
     384: idiv
     385: istore        18
     387: iload         15
     389: bipush        8
     391: ishl
     392: iload         16
     394: idiv
     395: istore        19
     397: iload         5
     399: iload         7
     401: iload         17
     403: imul
     404: iload         8
     406: iload         18
     408: imul
     409: iadd
     410: iload         9
     412: iload         19
     414: imul
     415: iadd
     416: iload         11
     418: idiv
     419: iadd
     420: istore        20
     422: aload         4
     424: iload         13
     426: iconst_1
     427: isub
     428: aaload
     429: iload         12
     431: baload
     432: iconst_2
     433: ishr
     434: aload         4
     436: iload         13
     438: iconst_1
     439: iadd
     440: aaload
     441: iload         12
     443: baload
     444: iconst_3
     445: ishr
     446: iadd
     447: aload         4
     449: iload         13
     451: aaload
     452: iload         12
     454: iconst_1
     455: isub
     456: baload
     457: iconst_2
     458: ishr
     459: iadd
     460: aload         4
     462: iload         13
     464: aaload
     465: iload         12
     467: iconst_1
     468: iadd
     469: baload
     470: iconst_3
     471: ishr
     472: iadd
     473: aload         4
     475: iload         13
     477: aaload
     478: iload         12
     480: baload
     481: iconst_1
     482: ishr
     483: iadd
     484: istore        21
     486: aload_0
     487: getfield      #16                 // Field anIntArrayArray139:[[I
     490: iload         13
     492: aaload
     493: iload         12
     495: iload         20
     497: iload         21
     499: isub
     500: iastore
     501: iinc          13, 1
     504: goto          276
     507: iinc          12, 1
     510: goto          262
     513: iconst_0
     514: istore        12
     516: iload         12
     518: aload_0
     519: getfield      #4                  // Field anInt147:I
     522: if_icmpge     571
     525: aload_0
     526: getfield      #17                 // Field anIntArray124:[I
     529: iload         12
     531: iconst_0
     532: iastore
     533: aload_0
     534: getfield      #18                 // Field anIntArray125:[I
     537: iload         12
     539: iconst_0
     540: iastore
     541: aload_0
     542: getfield      #19                 // Field anIntArray126:[I
     545: iload         12
     547: iconst_0
     548: iastore
     549: aload_0
     550: getfield      #20                 // Field anIntArray127:[I
     553: iload         12
     555: iconst_0
     556: iastore
     557: aload_0
     558: getfield      #21                 // Field anIntArray128:[I
     561: iload         12
     563: iconst_0
     564: iastore
     565: iinc          12, 1
     568: goto          516
     571: bipush        -5
     573: istore        12
     575: iload         12
     577: aload_0
     578: getfield      #3                  // Field anInt146:I
     581: iconst_5
     582: iadd
     583: if_icmpge     1819
     586: iconst_0
     587: istore        13
     589: iload         13
     591: aload_0
     592: getfield      #4                  // Field anInt147:I
     595: if_icmpge     852
     598: iload         12
     600: iconst_5
     601: iadd
     602: istore        14
     604: iload         14
     606: iflt          722
     609: iload         14
     611: aload_0
     612: getfield      #3                  // Field anInt146:I
     615: if_icmpge     722
     618: aload_0
     619: getfield      #8                  // Field aByteArrayArrayArray142:[[[B
     622: iload_3
     623: aaload
     624: iload         14
     626: aaload
     627: iload         13
     629: baload
     630: sipush        255
     633: iand
     634: istore        15
     636: iload         15
     638: ifle          722
     641: getstatic     #33                 // Field Flo.cache:[LFlo;
     644: iload         15
     646: iconst_1
     647: isub
     648: aaload
     649: astore        16
     651: aload_0
     652: getfield      #17                 // Field anIntArray124:[I
     655: iload         13
     657: dup2
     658: iaload
     659: aload         16
     661: getfield      #34                 // Field Flo.anInt397:I
     664: iadd
     665: iastore
     666: aload_0
     667: getfield      #18                 // Field anIntArray125:[I
     670: iload         13
     672: dup2
     673: iaload
     674: aload         16
     676: getfield      #35                 // Field Flo.anInt395:I
     679: iadd
     680: iastore
     681: aload_0
     682: getfield      #19                 // Field anIntArray126:[I
     685: iload         13
     687: dup2
     688: iaload
     689: aload         16
     691: getfield      #36                 // Field Flo.anInt396:I
     694: iadd
     695: iastore
     696: aload_0
     697: getfield      #20                 // Field anIntArray127:[I
     700: iload         13
     702: dup2
     703: iaload
     704: aload         16
     706: getfield      #37                 // Field Flo.anInt398:I
     709: iadd
     710: iastore
     711: aload_0
     712: getfield      #21                 // Field anIntArray128:[I
     715: iload         13
     717: dup2
     718: iaload
     719: iconst_1
     720: iadd
     721: iastore
     722: iload         12
     724: iconst_5
     725: isub
     726: istore        15
     728: iload         15
     730: iflt          846
     733: iload         15
     735: aload_0
     736: getfield      #3                  // Field anInt146:I
     739: if_icmpge     846
     742: aload_0
     743: getfield      #8                  // Field aByteArrayArrayArray142:[[[B
     746: iload_3
     747: aaload
     748: iload         15
     750: aaload
     751: iload         13
     753: baload
     754: sipush        255
     757: iand
     758: istore        16
     760: iload         16
     762: ifle          846
     765: getstatic     #33                 // Field Flo.cache:[LFlo;
     768: iload         16
     770: iconst_1
     771: isub
     772: aaload
     773: astore        17
     775: aload_0
     776: getfield      #17                 // Field anIntArray124:[I
     779: iload         13
     781: dup2
     782: iaload
     783: aload         17
     785: getfield      #34                 // Field Flo.anInt397:I
     788: isub
     789: iastore
     790: aload_0
     791: getfield      #18                 // Field anIntArray125:[I
     794: iload         13
     796: dup2
     797: iaload
     798: aload         17
     800: getfield      #35                 // Field Flo.anInt395:I
     803: isub
     804: iastore
     805: aload_0
     806: getfield      #19                 // Field anIntArray126:[I
     809: iload         13
     811: dup2
     812: iaload
     813: aload         17
     815: getfield      #36                 // Field Flo.anInt396:I
     818: isub
     819: iastore
     820: aload_0
     821: getfield      #20                 // Field anIntArray127:[I
     824: iload         13
     826: dup2
     827: iaload
     828: aload         17
     830: getfield      #37                 // Field Flo.anInt398:I
     833: isub
     834: iastore
     835: aload_0
     836: getfield      #21                 // Field anIntArray128:[I
     839: iload         13
     841: dup2
     842: iaload
     843: iconst_1
     844: isub
     845: iastore
     846: iinc          13, 1
     849: goto          589
     852: iload         12
     854: iconst_1
     855: if_icmplt     1813
     858: iload         12
     860: aload_0
     861: getfield      #3                  // Field anInt146:I
     864: iconst_1
     865: isub
     866: if_icmpge     1813
     869: iconst_0
     870: istore        13
     872: iconst_0
     873: istore        14
     875: iconst_0
     876: istore        15
     878: iconst_0
     879: istore        16
     881: iconst_0
     882: istore        17
     884: bipush        -5
     886: istore        18
     888: iload         18
     890: aload_0
     891: getfield      #4                  // Field anInt147:I
     894: iconst_5
     895: iadd
     896: if_icmpge     1813
     899: iload         18
     901: iconst_5
     902: iadd
     903: istore        19
     905: iload         19
     907: iflt          979
     910: iload         19
     912: aload_0
     913: getfield      #4                  // Field anInt147:I
     916: if_icmpge     979
     919: iload         13
     921: aload_0
     922: getfield      #17                 // Field anIntArray124:[I
     925: iload         19
     927: iaload
     928: iadd
     929: istore        13
     931: iload         14
     933: aload_0
     934: getfield      #18                 // Field anIntArray125:[I
     937: iload         19
     939: iaload
     940: iadd
     941: istore        14
     943: iload         15
     945: aload_0
     946: getfield      #19                 // Field anIntArray126:[I
     949: iload         19
     951: iaload
     952: iadd
     953: istore        15
     955: iload         16
     957: aload_0
     958: getfield      #20                 // Field anIntArray127:[I
     961: iload         19
     963: iaload
     964: iadd
     965: istore        16
     967: iload         17
     969: aload_0
     970: getfield      #21                 // Field anIntArray128:[I
     973: iload         19
     975: iaload
     976: iadd
     977: istore        17
     979: iload         18
     981: iconst_5
     982: isub
     983: istore        20
     985: iload         20
     987: iflt          1059
     990: iload         20
     992: aload_0
     993: getfield      #4                  // Field anInt147:I
     996: if_icmpge     1059
     999: iload         13
    1001: aload_0
    1002: getfield      #17                 // Field anIntArray124:[I
    1005: iload         20
    1007: iaload
    1008: isub
    1009: istore        13
    1011: iload         14
    1013: aload_0
    1014: getfield      #18                 // Field anIntArray125:[I
    1017: iload         20
    1019: iaload
    1020: isub
    1021: istore        14
    1023: iload         15
    1025: aload_0
    1026: getfield      #19                 // Field anIntArray126:[I
    1029: iload         20
    1031: iaload
    1032: isub
    1033: istore        15
    1035: iload         16
    1037: aload_0
    1038: getfield      #20                 // Field anIntArray127:[I
    1041: iload         20
    1043: iaload
    1044: isub
    1045: istore        16
    1047: iload         17
    1049: aload_0
    1050: getfield      #21                 // Field anIntArray128:[I
    1053: iload         20
    1055: iaload
    1056: isub
    1057: istore        17
    1059: iload         18
    1061: iconst_1
    1062: if_icmplt     1807
    1065: iload         18
    1067: aload_0
    1068: getfield      #4                  // Field anInt147:I
    1071: iconst_1
    1072: isub
    1073: if_icmpge     1807
    1076: getstatic     #38                 // Field lowMem:Z
    1079: ifeq          1132
    1082: aload_0
    1083: getfield      #6                  // Field aByteArrayArrayArray149:[[[B
    1086: iconst_0
    1087: aaload
    1088: iload         12
    1090: aaload
    1091: iload         18
    1093: baload
    1094: iconst_2
    1095: iand
    1096: ifne          1132
    1099: aload_0
    1100: getfield      #6                  // Field aByteArrayArrayArray149:[[[B
    1103: iload_3
    1104: aaload
    1105: iload         12
    1107: aaload
    1108: iload         18
    1110: baload
    1111: bipush        16
    1113: iand
    1114: ifne          1807
    1117: aload_0
    1118: iload         18
    1120: iload_3
    1121: iload         12
    1123: invokespecial #39                 // Method method182:(III)I
    1126: getstatic     #40                 // Field anInt131:I
    1129: if_icmpne     1807
    1132: iload_3
    1133: getstatic     #2                  // Field anInt145:I
    1136: if_icmpge     1143
    1139: iload_3
    1140: putstatic     #2                  // Field anInt145:I
    1143: aload_0
    1144: getfield      #8                  // Field aByteArrayArrayArray142:[[[B
    1147: iload_3
    1148: aaload
    1149: iload         12
    1151: aaload
    1152: iload         18
    1154: baload
    1155: sipush        255
    1158: iand
    1159: istore        21
    1161: aload_0
    1162: getfield      #9                  // Field aByteArrayArrayArray130:[[[B
    1165: iload_3
    1166: aaload
    1167: iload         12
    1169: aaload
    1170: iload         18
    1172: baload
    1173: sipush        255
    1176: iand
    1177: istore        22
    1179: iload         21
    1181: ifgt          1189
    1184: iload         22
    1186: ifle          1807
    1189: aload_0
    1190: getfield      #5                  // Field anIntArrayArrayArray129:[[[I
    1193: iload_3
    1194: aaload
    1195: iload         12
    1197: aaload
    1198: iload         18
    1200: iaload
    1201: istore        23
    1203: aload_0
    1204: getfield      #5                  // Field anIntArrayArrayArray129:[[[I
    1207: iload_3
    1208: aaload
    1209: iload         12
    1211: iconst_1
    1212: iadd
    1213: aaload
    1214: iload         18
    1216: iaload
    1217: istore        24
    1219: aload_0
    1220: getfield      #5                  // Field anIntArrayArrayArray129:[[[I
    1223: iload_3
    1224: aaload
    1225: iload         12
    1227: iconst_1
    1228: iadd
    1229: aaload
    1230: iload         18
    1232: iconst_1
    1233: iadd
    1234: iaload
    1235: istore        25
    1237: aload_0
    1238: getfield      #5                  // Field anIntArrayArrayArray129:[[[I
    1241: iload_3
    1242: aaload
    1243: iload         12
    1245: aaload
    1246: iload         18
    1248: iconst_1
    1249: iadd
    1250: iaload
    1251: istore        26
    1253: aload_0
    1254: getfield      #16                 // Field anIntArrayArray139:[[I
    1257: iload         12
    1259: aaload
    1260: iload         18
    1262: iaload
    1263: istore        27
    1265: aload_0
    1266: getfield      #16                 // Field anIntArrayArray139:[[I
    1269: iload         12
    1271: iconst_1
    1272: iadd
    1273: aaload
    1274: iload         18
    1276: iaload
    1277: istore        28
    1279: aload_0
    1280: getfield      #16                 // Field anIntArrayArray139:[[I
    1283: iload         12
    1285: iconst_1
    1286: iadd
    1287: aaload
    1288: iload         18
    1290: iconst_1
    1291: iadd
    1292: iaload
    1293: istore        29
    1295: aload_0
    1296: getfield      #16                 // Field anIntArrayArray139:[[I
    1299: iload         12
    1301: aaload
    1302: iload         18
    1304: iconst_1
    1305: iadd
    1306: iaload
    1307: istore        30
    1309: iconst_m1
    1310: istore        31
    1312: iconst_m1
    1313: istore        32
    1315: iload         21
    1317: ifle          1413
    1320: iload         13
    1322: sipush        256
    1325: imul
    1326: iload         16
    1328: idiv
    1329: istore        33
    1331: iload         14
    1333: iload         17
    1335: idiv
    1336: istore        34
    1338: iload         15
    1340: iload         17
    1342: idiv
    1343: istore        35
    1345: aload_0
    1346: iload         33
    1348: iload         34
    1350: iload         35
    1352: invokespecial #41                 // Method method177:(III)I
    1355: istore        31
    1357: iload         33
    1359: getstatic     #26                 // Field anInt123:I
    1362: iadd
    1363: sipush        255
    1366: iand
    1367: istore        33
    1369: iload         35
    1371: getstatic     #30                 // Field anInt133:I
    1374: iadd
    1375: istore        35
    1377: iload         35
    1379: ifge          1388
    1382: iconst_0
    1383: istore        35
    1385: goto          1401
    1388: iload         35
    1390: sipush        255
    1393: if_icmple     1401
    1396: sipush        255
    1399: istore        35
    1401: aload_0
    1402: iload         33
    1404: iload         34
    1406: iload         35
    1408: invokespecial #41                 // Method method177:(III)I
    1411: istore        32
    1413: iload_3
    1414: ifle          1509
    1417: iconst_1
    1418: istore        33
    1420: iload         21
    1422: ifne          1443
    1425: aload_0
    1426: getfield      #10                 // Field aByteArrayArrayArray136:[[[B
    1429: iload_3
    1430: aaload
    1431: iload         12
    1433: aaload
    1434: iload         18
    1436: baload
    1437: ifeq          1443
    1440: iconst_0
    1441: istore        33
    1443: iload         22
    1445: ifle          1465
    1448: getstatic     #33                 // Field Flo.cache:[LFlo;
    1451: iload         22
    1453: iconst_1
    1454: isub
    1455: aaload
    1456: getfield      #42                 // Field Flo.aBoolean393:Z
    1459: ifne          1465
    1462: iconst_0
    1463: istore        33
    1465: iload         33
    1467: ifeq          1509
    1470: iload         23
    1472: iload         24
    1474: if_icmpne     1509
    1477: iload         23
    1479: iload         25
    1481: if_icmpne     1509
    1484: iload         23
    1486: iload         26
    1488: if_icmpne     1509
    1491: aload_0
    1492: getfield      #13                 // Field anIntArrayArrayArray135:[[[I
    1495: iload_3
    1496: aaload
    1497: iload         12
    1499: aaload
    1500: iload         18
    1502: dup2
    1503: iaload
    1504: sipush        2340
    1507: ior
    1508: iastore
    1509: iconst_0
    1510: istore        33
    1512: iload         31
    1514: iconst_m1
    1515: if_icmpeq     1531
    1518: getstatic     #43                 // Field Texture.anIntArray1482:[I
    1521: iload         32
    1523: bipush        96
    1525: invokestatic  #44                 // Method method187:(II)I
    1528: iaload
    1529: istore        33
    1531: iload         22
    1533: ifne          1594
    1536: aload_2
    1537: iload_3
    1538: iload         12
    1540: iload         18
    1542: iconst_0
    1543: iconst_0
    1544: iconst_m1
    1545: iload         23
    1547: iload         24
    1549: iload         25
    1551: iload         26
    1553: iload         31
    1555: iload         27
    1557: invokestatic  #44                 // Method method187:(II)I
    1560: iload         31
    1562: iload         28
    1564: invokestatic  #44                 // Method method187:(II)I
    1567: iload         31
    1569: iload         29
    1571: invokestatic  #44                 // Method method187:(II)I
    1574: iload         31
    1576: iload         30
    1578: invokestatic  #44                 // Method method187:(II)I
    1581: iconst_0
    1582: iconst_0
    1583: iconst_0
    1584: iconst_0
    1585: iload         33
    1587: iconst_0
    1588: invokevirtual #45                 // Method WorldController.method279:(IIIIIIIIIIIIIIIIIIII)V
    1591: goto          1807
    1594: aload_0
    1595: getfield      #10                 // Field aByteArrayArrayArray136:[[[B
    1598: iload_3
    1599: aaload
    1600: iload         12
    1602: aaload
    1603: iload         18
    1605: baload
    1606: iconst_1
    1607: iadd
    1608: istore        34
    1610: aload_0
    1611: getfield      #11                 // Field aByteArrayArrayArray148:[[[B
    1614: iload_3
    1615: aaload
    1616: iload         12
    1618: aaload
    1619: iload         18
    1621: baload
    1622: istore        35
    1624: getstatic     #33                 // Field Flo.cache:[LFlo;
    1627: iload         22
    1629: iconst_1
    1630: isub
    1631: aaload
    1632: astore        36
    1634: aload         36
    1636: getfield      #46                 // Field Flo.anInt391:I
    1639: istore        37
    1641: iload         37
    1643: iflt          1659
    1646: iload         37
    1648: invokestatic  #47                 // Method Texture.method369:(I)I
    1651: istore        39
    1653: iconst_m1
    1654: istore        38
    1656: goto          1720
    1659: aload         36
    1661: getfield      #48                 // Field Flo.anInt390:I
    1664: ldc           #49                 // int 16711935
    1666: if_icmpne     1682
    1669: iconst_0
    1670: istore        39
    1672: bipush        -2
    1674: istore        38
    1676: iconst_m1
    1677: istore        37
    1679: goto          1720
    1682: aload_0
    1683: aload         36
    1685: getfield      #50                 // Field Flo.anInt394:I
    1688: aload         36
    1690: getfield      #35                 // Field Flo.anInt395:I
    1693: aload         36
    1695: getfield      #36                 // Field Flo.anInt396:I
    1698: invokespecial #41                 // Method method177:(III)I
    1701: istore        38
    1703: getstatic     #43                 // Field Texture.anIntArray1482:[I
    1706: aload_0
    1707: aload         36
    1709: getfield      #51                 // Field Flo.anInt399:I
    1712: bipush        96
    1714: invokespecial #52                 // Method method185:(II)I
    1717: iaload
    1718: istore        39
    1720: aload_2
    1721: iload_3
    1722: iload         12
    1724: iload         18
    1726: iload         34
    1728: iload         35
    1730: iload         37
    1732: iload         23
    1734: iload         24
    1736: iload         25
    1738: iload         26
    1740: iload         31
    1742: iload         27
    1744: invokestatic  #44                 // Method method187:(II)I
    1747: iload         31
    1749: iload         28
    1751: invokestatic  #44                 // Method method187:(II)I
    1754: iload         31
    1756: iload         29
    1758: invokestatic  #44                 // Method method187:(II)I
    1761: iload         31
    1763: iload         30
    1765: invokestatic  #44                 // Method method187:(II)I
    1768: aload_0
    1769: iload         38
    1771: iload         27
    1773: invokespecial #52                 // Method method185:(II)I
    1776: aload_0
    1777: iload         38
    1779: iload         28
    1781: invokespecial #52                 // Method method185:(II)I
    1784: aload_0
    1785: iload         38
    1787: iload         29
    1789: invokespecial #52                 // Method method185:(II)I
    1792: aload_0
    1793: iload         38
    1795: iload         30
    1797: invokespecial #52                 // Method method185:(II)I
    1800: iload         33
    1802: iload         39
    1804: invokevirtual #45                 // Method WorldController.method279:(IIIIIIIIIIIIIIIIIIII)V
    1807: iinc          18, 1
    1810: goto          888
    1813: iinc          12, 1
    1816: goto          575
    1819: iconst_1
    1820: istore        12
    1822: iload         12
    1824: aload_0
    1825: getfield      #4                  // Field anInt147:I
    1828: iconst_1
    1829: isub
    1830: if_icmpge     1877
    1833: iconst_1
    1834: istore        13
    1836: iload         13
    1838: aload_0
    1839: getfield      #3                  // Field anInt146:I
    1842: iconst_1
    1843: isub
    1844: if_icmpge     1871
    1847: aload_2
    1848: iload_3
    1849: iload         13
    1851: iload         12
    1853: aload_0
    1854: iload         12
    1856: iload_3
    1857: iload         13
    1859: invokespecial #39                 // Method method182:(III)I
    1862: invokevirtual #53                 // Method WorldController.method278:(IIII)V
    1865: iinc          13, 1
    1868: goto          1836
    1871: iinc          12, 1
    1874: goto          1822
    1877: iinc          3, 1
    1880: goto          191
    1883: aload_2
    1884: bipush        -10
    1886: bipush        -50
    1888: bipush        -50
    1890: invokevirtual #54                 // Method WorldController.method305:(III)V
    1893: iconst_0
    1894: istore_3
    1895: iload_3
    1896: aload_0
    1897: getfield      #3                  // Field anInt146:I
    1900: if_icmpge     1951
    1903: iconst_0
    1904: istore        4
    1906: iload         4
    1908: aload_0
    1909: getfield      #4                  // Field anInt147:I
    1912: if_icmpge     1945
    1915: aload_0
    1916: getfield      #6                  // Field aByteArrayArrayArray149:[[[B
    1919: iconst_1
    1920: aaload
    1921: iload_3
    1922: aaload
    1923: iload         4
    1925: baload
    1926: iconst_2
    1927: iand
    1928: iconst_2
    1929: if_icmpne     1939
    1932: aload_2
    1933: iload         4
    1935: iload_3
    1936: invokevirtual #55                 // Method WorldController.method276:(II)V
    1939: iinc          4, 1
    1942: goto          1906
    1945: iinc          3, 1
    1948: goto          1895
    1951: iconst_1
    1952: istore_3
    1953: iconst_2
    1954: istore        4
    1956: iconst_4
    1957: istore        5
    1959: iconst_0
    1960: istore        6
    1962: iload         6
    1964: iconst_4
    1965: if_icmpge     3108
    1968: iload         6
    1970: ifle          1989
    1973: iload_3
    1974: iconst_3
    1975: ishl
    1976: istore_3
    1977: iload         4
    1979: iconst_3
    1980: ishl
    1981: istore        4
    1983: iload         5
    1985: iconst_3
    1986: ishl
    1987: istore        5
    1989: iconst_0
    1990: istore        7
    1992: iload         7
    1994: iload         6
    1996: if_icmpgt     3102
    1999: iconst_0
    2000: istore        8
    2002: iload         8
    2004: aload_0
    2005: getfield      #4                  // Field anInt147:I
    2008: if_icmpgt     3096
    2011: iconst_0
    2012: istore        9
    2014: iload         9
    2016: aload_0
    2017: getfield      #3                  // Field anInt146:I
    2020: if_icmpgt     3090
    2023: aload_0
    2024: getfield      #13                 // Field anIntArrayArrayArray135:[[[I
    2027: iload         7
    2029: aaload
    2030: iload         9
    2032: aaload
    2033: iload         8
    2035: iaload
    2036: iload_3
    2037: iand
    2038: ifeq          2380
    2041: iload         8
    2043: istore        10
    2045: iload         8
    2047: istore        11
    2049: iload         7
    2051: istore        12
    2053: iload         7
    2055: istore        13
    2057: iload         10
    2059: ifle          2088
    2062: aload_0
    2063: getfield      #13                 // Field anIntArrayArrayArray135:[[[I
    2066: iload         7
    2068: aaload
    2069: iload         9
    2071: aaload
    2072: iload         10
    2074: iconst_1
    2075: isub
    2076: iaload
    2077: iload_3
    2078: iand
    2079: ifeq          2088
    2082: iinc          10, -1
    2085: goto          2057
    2088: iload         11
    2090: aload_0
    2091: getfield      #4                  // Field anInt147:I
    2094: if_icmpge     2123
    2097: aload_0
    2098: getfield      #13                 // Field anIntArrayArrayArray135:[[[I
    2101: iload         7
    2103: aaload
    2104: iload         9
    2106: aaload
    2107: iload         11
    2109: iconst_1
    2110: iadd
    2111: iaload
    2112: iload_3
    2113: iand
    2114: ifeq          2123
    2117: iinc          11, 1
    2120: goto          2088
    2123: iload         12
    2125: ifle          2174
    2128: iload         10
    2130: istore        14
    2132: iload         14
    2134: iload         11
    2136: if_icmpgt     2168
    2139: aload_0
    2140: getfield      #13                 // Field anIntArrayArrayArray135:[[[I
    2143: iload         12
    2145: iconst_1
    2146: isub
    2147: aaload
    2148: iload         9
    2150: aaload
    2151: iload         14
    2153: iaload
    2154: iload_3
    2155: iand
    2156: ifne          2162
    2159: goto          2174
    2162: iinc          14, 1
    2165: goto          2132
    2168: iinc          12, -1
    2171: goto          2123
    2174: iload         13
    2176: iload         6
    2178: if_icmpge     2227
    2181: iload         10
    2183: istore        14
    2185: iload         14
    2187: iload         11
    2189: if_icmpgt     2221
    2192: aload_0
    2193: getfield      #13                 // Field anIntArrayArrayArray135:[[[I
    2196: iload         13
    2198: iconst_1
    2199: iadd
    2200: aaload
    2201: iload         9
    2203: aaload
    2204: iload         14
    2206: iaload
    2207: iload_3
    2208: iand
    2209: ifne          2215
    2212: goto          2227
    2215: iinc          14, 1
    2218: goto          2185
    2221: iinc          13, 1
    2224: goto          2174
    2227: iload         13
    2229: iconst_1
    2230: iadd
    2231: iload         12
    2233: isub
    2234: iload         11
    2236: iload         10
    2238: isub
    2239: iconst_1
    2240: iadd
    2241: imul
    2242: istore        14
    2244: iload         14
    2246: bipush        8
    2248: if_icmplt     2380
    2251: sipush        240
    2254: istore        15
    2256: aload_0
    2257: getfield      #5                  // Field anIntArrayArrayArray129:[[[I
    2260: iload         13
    2262: aaload
    2263: iload         9
    2265: aaload
    2266: iload         10
    2268: iaload
    2269: iload         15
    2271: isub
    2272: istore        16
    2274: aload_0
    2275: getfield      #5                  // Field anIntArrayArrayArray129:[[[I
    2278: iload         12
    2280: aaload
    2281: iload         9
    2283: aaload
    2284: iload         10
    2286: iaload
    2287: istore        17
    2289: iload         6
    2291: iload         9
    2293: sipush        128
    2296: imul
    2297: iload         17
    2299: iload         9
    2301: sipush        128
    2304: imul
    2305: iload         11
    2307: sipush        128
    2310: imul
    2311: sipush        128
    2314: iadd
    2315: iload         16
    2317: iload         10
    2319: sipush        128
    2322: imul
    2323: iconst_1
    2324: invokestatic  #56                 // Method WorldController.method277:(IIIIIIII)V
    2327: iload         12
    2329: istore        18
    2331: iload         18
    2333: iload         13
    2335: if_icmpgt     2380
    2338: iload         10
    2340: istore        19
    2342: iload         19
    2344: iload         11
    2346: if_icmpgt     2374
    2349: aload_0
    2350: getfield      #13                 // Field anIntArrayArrayArray135:[[[I
    2353: iload         18
    2355: aaload
    2356: iload         9
    2358: aaload
    2359: iload         19
    2361: dup2
    2362: iaload
    2363: iload_3
    2364: iconst_m1
    2365: ixor
    2366: iand
    2367: iastore
    2368: iinc          19, 1
    2371: goto          2342
    2374: iinc          18, 1
    2377: goto          2331
    2380: aload_0
    2381: getfield      #13                 // Field anIntArrayArrayArray135:[[[I
    2384: iload         7
    2386: aaload
    2387: iload         9
    2389: aaload
    2390: iload         8
    2392: iaload
    2393: iload         4
    2395: iand
    2396: ifeq          2743
    2399: iload         9
    2401: istore        10
    2403: iload         9
    2405: istore        11
    2407: iload         7
    2409: istore        12
    2411: iload         7
    2413: istore        13
    2415: iload         10
    2417: ifle          2447
    2420: aload_0
    2421: getfield      #13                 // Field anIntArrayArrayArray135:[[[I
    2424: iload         7
    2426: aaload
    2427: iload         10
    2429: iconst_1
    2430: isub
    2431: aaload
    2432: iload         8
    2434: iaload
    2435: iload         4
    2437: iand
    2438: ifeq          2447
    2441: iinc          10, -1
    2444: goto          2415
    2447: iload         11
    2449: aload_0
    2450: getfield      #3                  // Field anInt146:I
    2453: if_icmpge     2483
    2456: aload_0
    2457: getfield      #13                 // Field anIntArrayArrayArray135:[[[I
    2460: iload         7
    2462: aaload
    2463: iload         11
    2465: iconst_1
    2466: iadd
    2467: aaload
    2468: iload         8
    2470: iaload
    2471: iload         4
    2473: iand
    2474: ifeq          2483
    2477: iinc          11, 1
    2480: goto          2447
    2483: iload         12
    2485: ifle          2535
    2488: iload         10
    2490: istore        14
    2492: iload         14
    2494: iload         11
    2496: if_icmpgt     2529
    2499: aload_0
    2500: getfield      #13                 // Field anIntArrayArrayArray135:[[[I
    2503: iload         12
    2505: iconst_1
    2506: isub
    2507: aaload
    2508: iload         14
    2510: aaload
    2511: iload         8
    2513: iaload
    2514: iload         4
    2516: iand
    2517: ifne          2523
    2520: goto          2535
    2523: iinc          14, 1
    2526: goto          2492
    2529: iinc          12, -1
    2532: goto          2483
    2535: iload         13
    2537: iload         6
    2539: if_icmpge     2589
    2542: iload         10
    2544: istore        14
    2546: iload         14
    2548: iload         11
    2550: if_icmpgt     2583
    2553: aload_0
    2554: getfield      #13                 // Field anIntArrayArrayArray135:[[[I
    2557: iload         13
    2559: iconst_1
    2560: iadd
    2561: aaload
    2562: iload         14
    2564: aaload
    2565: iload         8
    2567: iaload
    2568: iload         4
    2570: iand
    2571: ifne          2577
    2574: goto          2589
    2577: iinc          14, 1
    2580: goto          2546
    2583: iinc          13, 1
    2586: goto          2535
    2589: iload         13
    2591: iconst_1
    2592: iadd
    2593: iload         12
    2595: isub
    2596: iload         11
    2598: iload         10
    2600: isub
    2601: iconst_1
    2602: iadd
    2603: imul
    2604: istore        14
    2606: iload         14
    2608: bipush        8
    2610: if_icmplt     2743
    2613: sipush        240
    2616: istore        15
    2618: aload_0
    2619: getfield      #5                  // Field anIntArrayArrayArray129:[[[I
    2622: iload         13
    2624: aaload
    2625: iload         10
    2627: aaload
    2628: iload         8
    2630: iaload
    2631: iload         15
    2633: isub
    2634: istore        16
    2636: aload_0
    2637: getfield      #5                  // Field anIntArrayArrayArray129:[[[I
    2640: iload         12
    2642: aaload
    2643: iload         10
    2645: aaload
    2646: iload         8
    2648: iaload
    2649: istore        17
    2651: iload         6
    2653: iload         10
    2655: sipush        128
    2658: imul
    2659: iload         17
    2661: iload         11
    2663: sipush        128
    2666: imul
    2667: sipush        128
    2670: iadd
    2671: iload         8
    2673: sipush        128
    2676: imul
    2677: iload         16
    2679: iload         8
    2681: sipush        128
    2684: imul
    2685: iconst_2
    2686: invokestatic  #56                 // Method WorldController.method277:(IIIIIIII)V
    2689: iload         12
    2691: istore        18
    2693: iload         18
    2695: iload         13
    2697: if_icmpgt     2743
    2700: iload         10
    2702: istore        19
    2704: iload         19
    2706: iload         11
    2708: if_icmpgt     2737
    2711: aload_0
    2712: getfield      #13                 // Field anIntArrayArrayArray135:[[[I
    2715: iload         18
    2717: aaload
    2718: iload         19
    2720: aaload
    2721: iload         8
    2723: dup2
    2724: iaload
    2725: iload         4
    2727: iconst_m1
    2728: ixor
    2729: iand
    2730: iastore
    2731: iinc          19, 1
    2734: goto          2704
    2737: iinc          18, 1
    2740: goto          2693
    2743: aload_0
    2744: getfield      #13                 // Field anIntArrayArrayArray135:[[[I
    2747: iload         7
    2749: aaload
    2750: iload         9
    2752: aaload
    2753: iload         8
    2755: iaload
    2756: iload         5
    2758: iand
    2759: ifeq          3084
    2762: iload         9
    2764: istore        10
    2766: iload         9
    2768: istore        11
    2770: iload         8
    2772: istore        12
    2774: iload         8
    2776: istore        13
    2778: iload         12
    2780: ifle          2810
    2783: aload_0
    2784: getfield      #13                 // Field anIntArrayArrayArray135:[[[I
    2787: iload         7
    2789: aaload
    2790: iload         9
    2792: aaload
    2793: iload         12
    2795: iconst_1
    2796: isub
    2797: iaload
    2798: iload         5
    2800: iand
    2801: ifeq          2810
    2804: iinc          12, -1
    2807: goto          2778
    2810: iload         13
    2812: aload_0
    2813: getfield      #4                  // Field anInt147:I
    2816: if_icmpge     2846
    2819: aload_0
    2820: getfield      #13                 // Field anIntArrayArrayArray135:[[[I
    2823: iload         7
    2825: aaload
    2826: iload         9
    2828: aaload
    2829: iload         13
    2831: iconst_1
    2832: iadd
    2833: iaload
    2834: iload         5
    2836: iand
    2837: ifeq          2846
    2840: iinc          13, 1
    2843: goto          2810
    2846: iload         10
    2848: ifle          2898
    2851: iload         12
    2853: istore        14
    2855: iload         14
    2857: iload         13
    2859: if_icmpgt     2892
    2862: aload_0
    2863: getfield      #13                 // Field anIntArrayArrayArray135:[[[I
    2866: iload         7
    2868: aaload
    2869: iload         10
    2871: iconst_1
    2872: isub
    2873: aaload
    2874: iload         14
    2876: iaload
    2877: iload         5
    2879: iand
    2880: ifne          2886
    2883: goto          2898
    2886: iinc          14, 1
    2889: goto          2855
    2892: iinc          10, -1
    2895: goto          2846
    2898: iload         11
    2900: aload_0
    2901: getfield      #3                  // Field anInt146:I
    2904: if_icmpge     2954
    2907: iload         12
    2909: istore        14
    2911: iload         14
    2913: iload         13
    2915: if_icmpgt     2948
    2918: aload_0
    2919: getfield      #13                 // Field anIntArrayArrayArray135:[[[I
    2922: iload         7
    2924: aaload
    2925: iload         11
    2927: iconst_1
    2928: iadd
    2929: aaload
    2930: iload         14
    2932: iaload
    2933: iload         5
    2935: iand
    2936: ifne          2942
    2939: goto          2954
    2942: iinc          14, 1
    2945: goto          2911
    2948: iinc          11, 1
    2951: goto          2898
    2954: iload         11
    2956: iload         10
    2958: isub
    2959: iconst_1
    2960: iadd
    2961: iload         13
    2963: iload         12
    2965: isub
    2966: iconst_1
    2967: iadd
    2968: imul
    2969: iconst_4
    2970: if_icmplt     3084
    2973: aload_0
    2974: getfield      #5                  // Field anIntArrayArrayArray129:[[[I
    2977: iload         7
    2979: aaload
    2980: iload         10
    2982: aaload
    2983: iload         12
    2985: iaload
    2986: istore        14
    2988: iload         6
    2990: iload         10
    2992: sipush        128
    2995: imul
    2996: iload         14
    2998: iload         11
    3000: sipush        128
    3003: imul
    3004: sipush        128
    3007: iadd
    3008: iload         13
    3010: sipush        128
    3013: imul
    3014: sipush        128
    3017: iadd
    3018: iload         14
    3020: iload         12
    3022: sipush        128
    3025: imul
    3026: iconst_4
    3027: invokestatic  #56                 // Method WorldController.method277:(IIIIIIII)V
    3030: iload         10
    3032: istore        15
    3034: iload         15
    3036: iload         11
    3038: if_icmpgt     3084
    3041: iload         12
    3043: istore        16
    3045: iload         16
    3047: iload         13
    3049: if_icmpgt     3078
    3052: aload_0
    3053: getfield      #13                 // Field anIntArrayArrayArray135:[[[I
    3056: iload         7
    3058: aaload
    3059: iload         15
    3061: aaload
    3062: iload         16
    3064: dup2
    3065: iaload
    3066: iload         5
    3068: iconst_m1
    3069: ixor
    3070: iand
    3071: iastore
    3072: iinc          16, 1
    3075: goto          3045
    3078: iinc          15, 1
    3081: goto          3034
    3084: iinc          9, 1
    3087: goto          2014
    3090: iinc          8, 1
    3093: goto          2002
    3096: iinc          7, 1
    3099: goto          1992
    3102: iinc          6, 1
    3105: goto          1962
    3108: return

  private static int method172(int, int);
    Code:
       0: iload_0
       1: ldc           #57                 // int 45365
       3: iadd
       4: iload_1
       5: ldc           #58                 // int 91923
       7: iadd
       8: iconst_4
       9: invokestatic  #59                 // Method method176:(III)I
      12: sipush        128
      15: isub
      16: iload_0
      17: sipush        10294
      20: iadd
      21: iload_1
      22: ldc           #60                 // int 37821
      24: iadd
      25: iconst_2
      26: invokestatic  #59                 // Method method176:(III)I
      29: sipush        128
      32: isub
      33: iconst_1
      34: ishr
      35: iadd
      36: iload_0
      37: iload_1
      38: iconst_1
      39: invokestatic  #59                 // Method method176:(III)I
      42: sipush        128
      45: isub
      46: iconst_2
      47: ishr
      48: iadd
      49: istore_2
      50: iload_2
      51: i2d
      52: ldc2_w        #61                 // double 0.3d
      55: dmul
      56: d2i
      57: bipush        35
      59: iadd
      60: istore_2
      61: iload_2
      62: bipush        10
      64: if_icmpge     73
      67: bipush        10
      69: istore_2
      70: goto          82
      73: iload_2
      74: bipush        60
      76: if_icmple     82
      79: bipush        60
      81: istore_2
      82: iload_2
      83: ireturn

  public static void method173(Stream, OnDemandFetcher);
    Code:
       0: iconst_m1
       1: istore_2
       2: aload_0
       3: invokevirtual #63                 // Method Stream.method422:()I
       6: istore_3
       7: iload_3
       8: ifne          14
      11: goto          55
      14: iload_2
      15: iload_3
      16: iadd
      17: istore_2
      18: iload_2
      19: invokestatic  #64                 // Method ObjectDef.forID:(I)LObjectDef;
      22: astore        4
      24: aload         4
      26: aload_1
      27: invokevirtual #65                 // Method ObjectDef.method574:(LOnDemandFetcher;)V
      30: aload_0
      31: invokevirtual #63                 // Method Stream.method422:()I
      34: istore        5
      36: iload         5
      38: ifne          44
      41: goto          52
      44: aload_0
      45: invokevirtual #66                 // Method Stream.readUnsignedByte:()I
      48: pop
      49: goto          30
      52: goto          2
      55: return

  public final void method174(int, int, int, int);
    Code:
       0: iload_1
       1: istore        5
       3: iload         5
       5: iload_1
       6: iload_2
       7: iadd
       8: if_icmpgt     244
      11: iload         4
      13: istore        6
      15: iload         6
      17: iload         4
      19: iload_3
      20: iadd
      21: if_icmpgt     238
      24: iload         6
      26: iflt          232
      29: iload         6
      31: aload_0
      32: getfield      #3                  // Field anInt146:I
      35: if_icmpge     232
      38: iload         5
      40: iflt          232
      43: iload         5
      45: aload_0
      46: getfield      #4                  // Field anInt147:I
      49: if_icmpge     232
      52: aload_0
      53: getfield      #14                 // Field aByteArrayArrayArray134:[[[B
      56: iconst_0
      57: aaload
      58: iload         6
      60: aaload
      61: iload         5
      63: bipush        127
      65: bastore
      66: iload         6
      68: iload         4
      70: if_icmpne     104
      73: iload         6
      75: ifle          104
      78: aload_0
      79: getfield      #5                  // Field anIntArrayArrayArray129:[[[I
      82: iconst_0
      83: aaload
      84: iload         6
      86: aaload
      87: iload         5
      89: aload_0
      90: getfield      #5                  // Field anIntArrayArrayArray129:[[[I
      93: iconst_0
      94: aaload
      95: iload         6
      97: iconst_1
      98: isub
      99: aaload
     100: iload         5
     102: iaload
     103: iastore
     104: iload         6
     106: iload         4
     108: iload_3
     109: iadd
     110: if_icmpne     150
     113: iload         6
     115: aload_0
     116: getfield      #3                  // Field anInt146:I
     119: iconst_1
     120: isub
     121: if_icmpge     150
     124: aload_0
     125: getfield      #5                  // Field anIntArrayArrayArray129:[[[I
     128: iconst_0
     129: aaload
     130: iload         6
     132: aaload
     133: iload         5
     135: aload_0
     136: getfield      #5                  // Field anIntArrayArrayArray129:[[[I
     139: iconst_0
     140: aaload
     141: iload         6
     143: iconst_1
     144: iadd
     145: aaload
     146: iload         5
     148: iaload
     149: iastore
     150: iload         5
     152: iload_1
     153: if_icmpne     187
     156: iload         5
     158: ifle          187
     161: aload_0
     162: getfield      #5                  // Field anIntArrayArrayArray129:[[[I
     165: iconst_0
     166: aaload
     167: iload         6
     169: aaload
     170: iload         5
     172: aload_0
     173: getfield      #5                  // Field anIntArrayArrayArray129:[[[I
     176: iconst_0
     177: aaload
     178: iload         6
     180: aaload
     181: iload         5
     183: iconst_1
     184: isub
     185: iaload
     186: iastore
     187: iload         5
     189: iload_1
     190: iload_2
     191: iadd
     192: if_icmpne     232
     195: iload         5
     197: aload_0
     198: getfield      #4                  // Field anInt147:I
     201: iconst_1
     202: isub
     203: if_icmpge     232
     206: aload_0
     207: getfield      #5                  // Field anIntArrayArrayArray129:[[[I
     210: iconst_0
     211: aaload
     212: iload         6
     214: aaload
     215: iload         5
     217: aload_0
     218: getfield      #5                  // Field anIntArrayArrayArray129:[[[I
     221: iconst_0
     222: aaload
     223: iload         6
     225: aaload
     226: iload         5
     228: iconst_1
     229: iadd
     230: iaload
     231: iastore
     232: iinc          6, 1
     235: goto          15
     238: iinc          5, 1
     241: goto          3
     244: return

  private void method175(int, WorldController, Class11, int, int, int, int, int);
    Code:
       0: getstatic     #38                 // Field lowMem:Z
       3: ifeq          57
       6: aload_0
       7: getfield      #6                  // Field aByteArrayArrayArray149:[[[B
      10: iconst_0
      11: aaload
      12: iload         6
      14: aaload
      15: iload_1
      16: baload
      17: iconst_2
      18: iand
      19: ifne          57
      22: aload_0
      23: getfield      #6                  // Field aByteArrayArrayArray149:[[[B
      26: iload         5
      28: aaload
      29: iload         6
      31: aaload
      32: iload_1
      33: baload
      34: bipush        16
      36: iand
      37: ifeq          41
      40: return
      41: aload_0
      42: iload_1
      43: iload         5
      45: iload         6
      47: invokespecial #39                 // Method method182:(III)I
      50: getstatic     #40                 // Field anInt131:I
      53: if_icmpeq     57
      56: return
      57: iload         5
      59: getstatic     #2                  // Field anInt145:I
      62: if_icmpge     70
      65: iload         5
      67: putstatic     #2                  // Field anInt145:I
      70: aload_0
      71: getfield      #5                  // Field anIntArrayArrayArray129:[[[I
      74: iload         5
      76: aaload
      77: iload         6
      79: aaload
      80: iload_1
      81: iaload
      82: istore        9
      84: aload_0
      85: getfield      #5                  // Field anIntArrayArrayArray129:[[[I
      88: iload         5
      90: aaload
      91: iload         6
      93: iconst_1
      94: iadd
      95: aaload
      96: iload_1
      97: iaload
      98: istore        10
     100: aload_0
     101: getfield      #5                  // Field anIntArrayArrayArray129:[[[I
     104: iload         5
     106: aaload
     107: iload         6
     109: iconst_1
     110: iadd
     111: aaload
     112: iload_1
     113: iconst_1
     114: iadd
     115: iaload
     116: istore        11
     118: aload_0
     119: getfield      #5                  // Field anIntArrayArrayArray129:[[[I
     122: iload         5
     124: aaload
     125: iload         6
     127: aaload
     128: iload_1
     129: iconst_1
     130: iadd
     131: iaload
     132: istore        12
     134: iload         9
     136: iload         10
     138: iadd
     139: iload         11
     141: iadd
     142: iload         12
     144: iadd
     145: iconst_2
     146: ishr
     147: istore        13
     149: iload         7
     151: invokestatic  #64                 // Method ObjectDef.forID:(I)LObjectDef;
     154: astore        14
     156: iload         6
     158: iload_1
     159: bipush        7
     161: ishl
     162: iadd
     163: iload         7
     165: bipush        14
     167: ishl
     168: iadd
     169: ldc           #67                 // int 1073741824
     171: iadd
     172: istore        15
     174: aload         14
     176: getfield      #68                 // Field ObjectDef.hasActions:Z
     179: ifne          189
     182: iload         15
     184: ldc           #69                 // int -2147483648
     186: isub
     187: istore        15
     189: iload         8
     191: bipush        6
     193: ishl
     194: iload         4
     196: iadd
     197: i2b
     198: istore        16
     200: iload         4
     202: bipush        22
     204: if_icmpne     350
     207: getstatic     #38                 // Field lowMem:Z
     210: ifeq          230
     213: aload         14
     215: getfield      #68                 // Field ObjectDef.hasActions:Z
     218: ifne          230
     221: aload         14
     223: getfield      #70                 // Field ObjectDef.aBoolean736:Z
     226: ifne          230
     229: return
     230: aload         14
     232: getfield      #71                 // Field ObjectDef.anInt781:I
     235: iconst_m1
     236: if_icmpne     270
     239: aload         14
     241: getfield      #72                 // Field ObjectDef.childrenIDs:[I
     244: ifnonnull     270
     247: aload         14
     249: bipush        22
     251: iload         8
     253: iload         9
     255: iload         10
     257: iload         11
     259: iload         12
     261: iconst_m1
     262: invokevirtual #73                 // Method ObjectDef.method578:(IIIIIII)LModel;
     265: astore        17
     267: goto          299
     270: new           #74                 // class Animable_Sub5
     273: dup
     274: iload         7
     276: iload         8
     278: bipush        22
     280: iload         10
     282: iload         11
     284: iload         9
     286: iload         12
     288: aload         14
     290: getfield      #71                 // Field ObjectDef.anInt781:I
     293: iconst_1
     294: invokespecial #75                 // Method Animable_Sub5."<init>":(IIIIIIIIZ)V
     297: astore        17
     299: aload_2
     300: iload         5
     302: iload         13
     304: iload_1
     305: aload         17
     307: checkcast     #76                 // class Animable
     310: checkcast     #76                 // class Animable
     313: iload         16
     315: iload         15
     317: iload         6
     319: invokevirtual #77                 // Method WorldController.method280:(IIILAnimable;BII)V
     322: aload         14
     324: getfield      #78                 // Field ObjectDef.aBoolean767:Z
     327: ifeq          349
     330: aload         14
     332: getfield      #68                 // Field ObjectDef.hasActions:Z
     335: ifeq          349
     338: aload_3
     339: ifnull        349
     342: aload_3
     343: iload_1
     344: iload         6
     346: invokevirtual #25                 // Method Class11.method213:(II)V
     349: return
     350: iload         4
     352: bipush        10
     354: if_icmpeq     364
     357: iload         4
     359: bipush        11
     361: if_icmpne     713
     364: aload         14
     366: getfield      #71                 // Field ObjectDef.anInt781:I
     369: iconst_m1
     370: if_icmpne     404
     373: aload         14
     375: getfield      #72                 // Field ObjectDef.childrenIDs:[I
     378: ifnonnull     404
     381: aload         14
     383: bipush        10
     385: iload         8
     387: iload         9
     389: iload         10
     391: iload         11
     393: iload         12
     395: iconst_m1
     396: invokevirtual #73                 // Method ObjectDef.method578:(IIIIIII)LModel;
     399: astore        17
     401: goto          433
     404: new           #74                 // class Animable_Sub5
     407: dup
     408: iload         7
     410: iload         8
     412: bipush        10
     414: iload         10
     416: iload         11
     418: iload         9
     420: iload         12
     422: aload         14
     424: getfield      #71                 // Field ObjectDef.anInt781:I
     427: iconst_1
     428: invokespecial #75                 // Method Animable_Sub5."<init>":(IIIIIIIIZ)V
     431: astore        17
     433: aload         17
     435: ifnull        676
     438: iconst_0
     439: istore        18
     441: iload         4
     443: bipush        11
     445: if_icmpne     454
     448: iinc_w        18, 256
     454: iload         8
     456: iconst_1
     457: if_icmpeq     466
     460: iload         8
     462: iconst_3
     463: if_icmpne     483
     466: aload         14
     468: getfield      #79                 // Field ObjectDef.anInt761:I
     471: istore        19
     473: aload         14
     475: getfield      #80                 // Field ObjectDef.anInt744:I
     478: istore        20
     480: goto          497
     483: aload         14
     485: getfield      #80                 // Field ObjectDef.anInt744:I
     488: istore        19
     490: aload         14
     492: getfield      #79                 // Field ObjectDef.anInt761:I
     495: istore        20
     497: aload_2
     498: iload         15
     500: iload         16
     502: iload         13
     504: iload         20
     506: aload         17
     508: checkcast     #76                 // class Animable
     511: checkcast     #76                 // class Animable
     514: iload         19
     516: iload         5
     518: iload         18
     520: iload_1
     521: iload         6
     523: invokevirtual #81                 // Method WorldController.method284:(IBIILAnimable;IIIII)Z
     526: ifeq          676
     529: aload         14
     531: getfield      #82                 // Field ObjectDef.aBoolean779:Z
     534: ifeq          676
     537: aload         17
     539: instanceof    #83                 // class Model
     542: ifeq          555
     545: aload         17
     547: checkcast     #83                 // class Model
     550: astore        21
     552: goto          575
     555: aload         14
     557: bipush        10
     559: iload         8
     561: iload         9
     563: iload         10
     565: iload         11
     567: iload         12
     569: iconst_m1
     570: invokevirtual #73                 // Method ObjectDef.method578:(IIIIIII)LModel;
     573: astore        21
     575: aload         21
     577: ifnull        676
     580: iconst_0
     581: istore        22
     583: iload         22
     585: iload         19
     587: if_icmpgt     676
     590: iconst_0
     591: istore        23
     593: iload         23
     595: iload         20
     597: if_icmpgt     670
     600: aload         21
     602: getfield      #84                 // Field Model.anInt1650:I
     605: iconst_4
     606: idiv
     607: istore        24
     609: iload         24
     611: bipush        30
     613: if_icmple     620
     616: bipush        30
     618: istore        24
     620: iload         24
     622: aload_0
     623: getfield      #14                 // Field aByteArrayArrayArray134:[[[B
     626: iload         5
     628: aaload
     629: iload         6
     631: iload         22
     633: iadd
     634: aaload
     635: iload_1
     636: iload         23
     638: iadd
     639: baload
     640: if_icmple     664
     643: aload_0
     644: getfield      #14                 // Field aByteArrayArrayArray134:[[[B
     647: iload         5
     649: aaload
     650: iload         6
     652: iload         22
     654: iadd
     655: aaload
     656: iload_1
     657: iload         23
     659: iadd
     660: iload         24
     662: i2b
     663: bastore
     664: iinc          23, 1
     667: goto          593
     670: iinc          22, 1
     673: goto          583
     676: aload         14
     678: getfield      #78                 // Field ObjectDef.aBoolean767:Z
     681: ifeq          712
     684: aload_3
     685: ifnull        712
     688: aload_3
     689: aload         14
     691: getfield      #85                 // Field ObjectDef.aBoolean757:Z
     694: aload         14
     696: getfield      #80                 // Field ObjectDef.anInt744:I
     699: aload         14
     701: getfield      #79                 // Field ObjectDef.anInt761:I
     704: iload         6
     706: iload_1
     707: iload         8
     709: invokevirtual #86                 // Method Class11.method212:(ZIIIII)V
     712: return
     713: iload         4
     715: bipush        12
     717: if_icmplt     897
     720: aload         14
     722: getfield      #71                 // Field ObjectDef.anInt781:I
     725: iconst_m1
     726: if_icmpne     760
     729: aload         14
     731: getfield      #72                 // Field ObjectDef.childrenIDs:[I
     734: ifnonnull     760
     737: aload         14
     739: iload         4
     741: iload         8
     743: iload         9
     745: iload         10
     747: iload         11
     749: iload         12
     751: iconst_m1
     752: invokevirtual #73                 // Method ObjectDef.method578:(IIIIIII)LModel;
     755: astore        17
     757: goto          789
     760: new           #74                 // class Animable_Sub5
     763: dup
     764: iload         7
     766: iload         8
     768: iload         4
     770: iload         10
     772: iload         11
     774: iload         9
     776: iload         12
     778: aload         14
     780: getfield      #71                 // Field ObjectDef.anInt781:I
     783: iconst_1
     784: invokespecial #75                 // Method Animable_Sub5."<init>":(IIIIIIIIZ)V
     787: astore        17
     789: aload_2
     790: iload         15
     792: iload         16
     794: iload         13
     796: iconst_1
     797: aload         17
     799: checkcast     #76                 // class Animable
     802: checkcast     #76                 // class Animable
     805: iconst_1
     806: iload         5
     808: iconst_0
     809: iload_1
     810: iload         6
     812: invokevirtual #81                 // Method WorldController.method284:(IBIILAnimable;IIIII)Z
     815: pop
     816: iload         4
     818: bipush        12
     820: if_icmplt     860
     823: iload         4
     825: bipush        17
     827: if_icmpgt     860
     830: iload         4
     832: bipush        13
     834: if_icmpeq     860
     837: iload         5
     839: ifle          860
     842: aload_0
     843: getfield      #13                 // Field anIntArrayArrayArray135:[[[I
     846: iload         5
     848: aaload
     849: iload         6
     851: aaload
     852: iload_1
     853: dup2
     854: iaload
     855: sipush        2340
     858: ior
     859: iastore
     860: aload         14
     862: getfield      #78                 // Field ObjectDef.aBoolean767:Z
     865: ifeq          896
     868: aload_3
     869: ifnull        896
     872: aload_3
     873: aload         14
     875: getfield      #85                 // Field ObjectDef.aBoolean757:Z
     878: aload         14
     880: getfield      #80                 // Field ObjectDef.anInt744:I
     883: aload         14
     885: getfield      #79                 // Field ObjectDef.anInt761:I
     888: iload         6
     890: iload_1
     891: iload         8
     893: invokevirtual #86                 // Method Class11.method212:(ZIIIII)V
     896: return
     897: iload         4
     899: ifne          1353
     902: aload         14
     904: getfield      #71                 // Field ObjectDef.anInt781:I
     907: iconst_m1
     908: if_icmpne     941
     911: aload         14
     913: getfield      #72                 // Field ObjectDef.childrenIDs:[I
     916: ifnonnull     941
     919: aload         14
     921: iconst_0
     922: iload         8
     924: iload         9
     926: iload         10
     928: iload         11
     930: iload         12
     932: iconst_m1
     933: invokevirtual #73                 // Method ObjectDef.method578:(IIIIIII)LModel;
     936: astore        17
     938: goto          969
     941: new           #74                 // class Animable_Sub5
     944: dup
     945: iload         7
     947: iload         8
     949: iconst_0
     950: iload         10
     952: iload         11
     954: iload         9
     956: iload         12
     958: aload         14
     960: getfield      #71                 // Field ObjectDef.anInt781:I
     963: iconst_1
     964: invokespecial #75                 // Method Animable_Sub5."<init>":(IIIIIIIIZ)V
     967: astore        17
     969: aload_2
     970: getstatic     #87                 // Field anIntArray152:[I
     973: iload         8
     975: iaload
     976: aload         17
     978: checkcast     #76                 // class Animable
     981: checkcast     #76                 // class Animable
     984: iload         15
     986: iload_1
     987: iload         16
     989: iload         6
     991: aconst_null
     992: iload         13
     994: iconst_0
     995: iload         5
     997: invokevirtual #88                 // Method WorldController.method282:(ILAnimable;IIBILAnimable;III)V
    1000: iload         8
    1002: ifne          1072
    1005: aload         14
    1007: getfield      #82                 // Field ObjectDef.aBoolean779:Z
    1010: ifeq          1043
    1013: aload_0
    1014: getfield      #14                 // Field aByteArrayArrayArray134:[[[B
    1017: iload         5
    1019: aaload
    1020: iload         6
    1022: aaload
    1023: iload_1
    1024: bipush        50
    1026: bastore
    1027: aload_0
    1028: getfield      #14                 // Field aByteArrayArrayArray134:[[[B
    1031: iload         5
    1033: aaload
    1034: iload         6
    1036: aaload
    1037: iload_1
    1038: iconst_1
    1039: iadd
    1040: bipush        50
    1042: bastore
    1043: aload         14
    1045: getfield      #89                 // Field ObjectDef.aBoolean764:Z
    1048: ifeq          1300
    1051: aload_0
    1052: getfield      #13                 // Field anIntArrayArrayArray135:[[[I
    1055: iload         5
    1057: aaload
    1058: iload         6
    1060: aaload
    1061: iload_1
    1062: dup2
    1063: iaload
    1064: sipush        585
    1067: ior
    1068: iastore
    1069: goto          1300
    1072: iload         8
    1074: iconst_1
    1075: if_icmpne     1151
    1078: aload         14
    1080: getfield      #82                 // Field ObjectDef.aBoolean779:Z
    1083: ifeq          1120
    1086: aload_0
    1087: getfield      #14                 // Field aByteArrayArrayArray134:[[[B
    1090: iload         5
    1092: aaload
    1093: iload         6
    1095: aaload
    1096: iload_1
    1097: iconst_1
    1098: iadd
    1099: bipush        50
    1101: bastore
    1102: aload_0
    1103: getfield      #14                 // Field aByteArrayArrayArray134:[[[B
    1106: iload         5
    1108: aaload
    1109: iload         6
    1111: iconst_1
    1112: iadd
    1113: aaload
    1114: iload_1
    1115: iconst_1
    1116: iadd
    1117: bipush        50
    1119: bastore
    1120: aload         14
    1122: getfield      #89                 // Field ObjectDef.aBoolean764:Z
    1125: ifeq          1300
    1128: aload_0
    1129: getfield      #13                 // Field anIntArrayArrayArray135:[[[I
    1132: iload         5
    1134: aaload
    1135: iload         6
    1137: aaload
    1138: iload_1
    1139: iconst_1
    1140: iadd
    1141: dup2
    1142: iaload
    1143: sipush        1170
    1146: ior
    1147: iastore
    1148: goto          1300
    1151: iload         8
    1153: iconst_2
    1154: if_icmpne     1230
    1157: aload         14
    1159: getfield      #82                 // Field ObjectDef.aBoolean779:Z
    1162: ifeq          1199
    1165: aload_0
    1166: getfield      #14                 // Field aByteArrayArrayArray134:[[[B
    1169: iload         5
    1171: aaload
    1172: iload         6
    1174: iconst_1
    1175: iadd
    1176: aaload
    1177: iload_1
    1178: bipush        50
    1180: bastore
    1181: aload_0
    1182: getfield      #14                 // Field aByteArrayArrayArray134:[[[B
    1185: iload         5
    1187: aaload
    1188: iload         6
    1190: iconst_1
    1191: iadd
    1192: aaload
    1193: iload_1
    1194: iconst_1
    1195: iadd
    1196: bipush        50
    1198: bastore
    1199: aload         14
    1201: getfield      #89                 // Field ObjectDef.aBoolean764:Z
    1204: ifeq          1300
    1207: aload_0
    1208: getfield      #13                 // Field anIntArrayArrayArray135:[[[I
    1211: iload         5
    1213: aaload
    1214: iload         6
    1216: iconst_1
    1217: iadd
    1218: aaload
    1219: iload_1
    1220: dup2
    1221: iaload
    1222: sipush        585
    1225: ior
    1226: iastore
    1227: goto          1300
    1230: iload         8
    1232: iconst_3
    1233: if_icmpne     1300
    1236: aload         14
    1238: getfield      #82                 // Field ObjectDef.aBoolean779:Z
    1241: ifeq          1274
    1244: aload_0
    1245: getfield      #14                 // Field aByteArrayArrayArray134:[[[B
    1248: iload         5
    1250: aaload
    1251: iload         6
    1253: aaload
    1254: iload_1
    1255: bipush        50
    1257: bastore
    1258: aload_0
    1259: getfield      #14                 // Field aByteArrayArrayArray134:[[[B
    1262: iload         5
    1264: aaload
    1265: iload         6
    1267: iconst_1
    1268: iadd
    1269: aaload
    1270: iload_1
    1271: bipush        50
    1273: bastore
    1274: aload         14
    1276: getfield      #89                 // Field ObjectDef.aBoolean764:Z
    1279: ifeq          1300
    1282: aload_0
    1283: getfield      #13                 // Field anIntArrayArrayArray135:[[[I
    1286: iload         5
    1288: aaload
    1289: iload         6
    1291: aaload
    1292: iload_1
    1293: dup2
    1294: iaload
    1295: sipush        1170
    1298: ior
    1299: iastore
    1300: aload         14
    1302: getfield      #78                 // Field ObjectDef.aBoolean767:Z
    1305: ifeq          1328
    1308: aload_3
    1309: ifnull        1328
    1312: aload_3
    1313: iload_1
    1314: iload         8
    1316: iload         6
    1318: iload         4
    1320: aload         14
    1322: getfield      #85                 // Field ObjectDef.aBoolean757:Z
    1325: invokevirtual #90                 // Method Class11.method211:(IIIIZ)V
    1328: aload         14
    1330: getfield      #91                 // Field ObjectDef.anInt775:I
    1333: bipush        16
    1335: if_icmpeq     1352
    1338: aload_2
    1339: iload_1
    1340: aload         14
    1342: getfield      #91                 // Field ObjectDef.anInt775:I
    1345: iload         6
    1347: iload         5
    1349: invokevirtual #92                 // Method WorldController.method290:(IIII)V
    1352: return
    1353: iload         4
    1355: iconst_1
    1356: if_icmpne     1590
    1359: aload         14
    1361: getfield      #71                 // Field ObjectDef.anInt781:I
    1364: iconst_m1
    1365: if_icmpne     1398
    1368: aload         14
    1370: getfield      #72                 // Field ObjectDef.childrenIDs:[I
    1373: ifnonnull     1398
    1376: aload         14
    1378: iconst_1
    1379: iload         8
    1381: iload         9
    1383: iload         10
    1385: iload         11
    1387: iload         12
    1389: iconst_m1
    1390: invokevirtual #73                 // Method ObjectDef.method578:(IIIIIII)LModel;
    1393: astore        17
    1395: goto          1426
    1398: new           #74                 // class Animable_Sub5
    1401: dup
    1402: iload         7
    1404: iload         8
    1406: iconst_1
    1407: iload         10
    1409: iload         11
    1411: iload         9
    1413: iload         12
    1415: aload         14
    1417: getfield      #71                 // Field ObjectDef.anInt781:I
    1420: iconst_1
    1421: invokespecial #75                 // Method Animable_Sub5."<init>":(IIIIIIIIZ)V
    1424: astore        17
    1426: aload_2
    1427: getstatic     #93                 // Field anIntArray140:[I
    1430: iload         8
    1432: iaload
    1433: aload         17
    1435: checkcast     #76                 // class Animable
    1438: checkcast     #76                 // class Animable
    1441: iload         15
    1443: iload_1
    1444: iload         16
    1446: iload         6
    1448: aconst_null
    1449: iload         13
    1451: iconst_0
    1452: iload         5
    1454: invokevirtual #88                 // Method WorldController.method282:(ILAnimable;IIBILAnimable;III)V
    1457: aload         14
    1459: getfield      #82                 // Field ObjectDef.aBoolean779:Z
    1462: ifeq          1561
    1465: iload         8
    1467: ifne          1489
    1470: aload_0
    1471: getfield      #14                 // Field aByteArrayArrayArray134:[[[B
    1474: iload         5
    1476: aaload
    1477: iload         6
    1479: aaload
    1480: iload_1
    1481: iconst_1
    1482: iadd
    1483: bipush        50
    1485: bastore
    1486: goto          1561
    1489: iload         8
    1491: iconst_1
    1492: if_icmpne     1516
    1495: aload_0
    1496: getfield      #14                 // Field aByteArrayArrayArray134:[[[B
    1499: iload         5
    1501: aaload
    1502: iload         6
    1504: iconst_1
    1505: iadd
    1506: aaload
    1507: iload_1
    1508: iconst_1
    1509: iadd
    1510: bipush        50
    1512: bastore
    1513: goto          1561
    1516: iload         8
    1518: iconst_2
    1519: if_icmpne     1541
    1522: aload_0
    1523: getfield      #14                 // Field aByteArrayArrayArray134:[[[B
    1526: iload         5
    1528: aaload
    1529: iload         6
    1531: iconst_1
    1532: iadd
    1533: aaload
    1534: iload_1
    1535: bipush        50
    1537: bastore
    1538: goto          1561
    1541: iload         8
    1543: iconst_3
    1544: if_icmpne     1561
    1547: aload_0
    1548: getfield      #14                 // Field aByteArrayArrayArray134:[[[B
    1551: iload         5
    1553: aaload
    1554: iload         6
    1556: aaload
    1557: iload_1
    1558: bipush        50
    1560: bastore
    1561: aload         14
    1563: getfield      #78                 // Field ObjectDef.aBoolean767:Z
    1566: ifeq          1589
    1569: aload_3
    1570: ifnull        1589
    1573: aload_3
    1574: iload_1
    1575: iload         8
    1577: iload         6
    1579: iload         4
    1581: aload         14
    1583: getfield      #85                 // Field ObjectDef.aBoolean757:Z
    1586: invokevirtual #90                 // Method Class11.method211:(IIIIZ)V
    1589: return
    1590: iload         4
    1592: iconst_2
    1593: if_icmpne     2010
    1596: iload         8
    1598: iconst_1
    1599: iadd
    1600: iconst_3
    1601: iand
    1602: istore        17
    1604: aload         14
    1606: getfield      #71                 // Field ObjectDef.anInt781:I
    1609: iconst_m1
    1610: if_icmpne     1664
    1613: aload         14
    1615: getfield      #72                 // Field ObjectDef.childrenIDs:[I
    1618: ifnonnull     1664
    1621: aload         14
    1623: iconst_2
    1624: iconst_4
    1625: iload         8
    1627: iadd
    1628: iload         9
    1630: iload         10
    1632: iload         11
    1634: iload         12
    1636: iconst_m1
    1637: invokevirtual #73                 // Method ObjectDef.method578:(IIIIIII)LModel;
    1640: astore        18
    1642: aload         14
    1644: iconst_2
    1645: iload         17
    1647: iload         9
    1649: iload         10
    1651: iload         11
    1653: iload         12
    1655: iconst_m1
    1656: invokevirtual #73                 // Method ObjectDef.method578:(IIIIIII)LModel;
    1659: astore        19
    1661: goto          1722
    1664: new           #74                 // class Animable_Sub5
    1667: dup
    1668: iload         7
    1670: iconst_4
    1671: iload         8
    1673: iadd
    1674: iconst_2
    1675: iload         10
    1677: iload         11
    1679: iload         9
    1681: iload         12
    1683: aload         14
    1685: getfield      #71                 // Field ObjectDef.anInt781:I
    1688: iconst_1
    1689: invokespecial #75                 // Method Animable_Sub5."<init>":(IIIIIIIIZ)V
    1692: astore        18
    1694: new           #74                 // class Animable_Sub5
    1697: dup
    1698: iload         7
    1700: iload         17
    1702: iconst_2
    1703: iload         10
    1705: iload         11
    1707: iload         9
    1709: iload         12
    1711: aload         14
    1713: getfield      #71                 // Field ObjectDef.anInt781:I
    1716: iconst_1
    1717: invokespecial #75                 // Method Animable_Sub5."<init>":(IIIIIIIIZ)V
    1720: astore        19
    1722: aload_2
    1723: getstatic     #87                 // Field anIntArray152:[I
    1726: iload         8
    1728: iaload
    1729: aload         18
    1731: checkcast     #76                 // class Animable
    1734: checkcast     #76                 // class Animable
    1737: iload         15
    1739: iload_1
    1740: iload         16
    1742: iload         6
    1744: aload         19
    1746: checkcast     #76                 // class Animable
    1749: checkcast     #76                 // class Animable
    1752: iload         13
    1754: getstatic     #87                 // Field anIntArray152:[I
    1757: iload         17
    1759: iaload
    1760: iload         5
    1762: invokevirtual #88                 // Method WorldController.method282:(ILAnimable;IIBILAnimable;III)V
    1765: aload         14
    1767: getfield      #89                 // Field ObjectDef.aBoolean764:Z
    1770: ifeq          1957
    1773: iload         8
    1775: ifne          1819
    1778: aload_0
    1779: getfield      #13                 // Field anIntArrayArrayArray135:[[[I
    1782: iload         5
    1784: aaload
    1785: iload         6
    1787: aaload
    1788: iload_1
    1789: dup2
    1790: iaload
    1791: sipush        585
    1794: ior
    1795: iastore
    1796: aload_0
    1797: getfield      #13                 // Field anIntArrayArrayArray135:[[[I
    1800: iload         5
    1802: aaload
    1803: iload         6
    1805: aaload
    1806: iload_1
    1807: iconst_1
    1808: iadd
    1809: dup2
    1810: iaload
    1811: sipush        1170
    1814: ior
    1815: iastore
    1816: goto          1957
    1819: iload         8
    1821: iconst_1
    1822: if_icmpne     1868
    1825: aload_0
    1826: getfield      #13                 // Field anIntArrayArrayArray135:[[[I
    1829: iload         5
    1831: aaload
    1832: iload         6
    1834: aaload
    1835: iload_1
    1836: iconst_1
    1837: iadd
    1838: dup2
    1839: iaload
    1840: sipush        1170
    1843: ior
    1844: iastore
    1845: aload_0
    1846: getfield      #13                 // Field anIntArrayArrayArray135:[[[I
    1849: iload         5
    1851: aaload
    1852: iload         6
    1854: iconst_1
    1855: iadd
    1856: aaload
    1857: iload_1
    1858: dup2
    1859: iaload
    1860: sipush        585
    1863: ior
    1864: iastore
    1865: goto          1957
    1868: iload         8
    1870: iconst_2
    1871: if_icmpne     1915
    1874: aload_0
    1875: getfield      #13                 // Field anIntArrayArrayArray135:[[[I
    1878: iload         5
    1880: aaload
    1881: iload         6
    1883: iconst_1
    1884: iadd
    1885: aaload
    1886: iload_1
    1887: dup2
    1888: iaload
    1889: sipush        585
    1892: ior
    1893: iastore
    1894: aload_0
    1895: getfield      #13                 // Field anIntArrayArrayArray135:[[[I
    1898: iload         5
    1900: aaload
    1901: iload         6
    1903: aaload
    1904: iload_1
    1905: dup2
    1906: iaload
    1907: sipush        1170
    1910: ior
    1911: iastore
    1912: goto          1957
    1915: iload         8
    1917: iconst_3
    1918: if_icmpne     1957
    1921: aload_0
    1922: getfield      #13                 // Field anIntArrayArrayArray135:[[[I
    1925: iload         5
    1927: aaload
    1928: iload         6
    1930: aaload
    1931: iload_1
    1932: dup2
    1933: iaload
    1934: sipush        1170
    1937: ior
    1938: iastore
    1939: aload_0
    1940: getfield      #13                 // Field anIntArrayArrayArray135:[[[I
    1943: iload         5
    1945: aaload
    1946: iload         6
    1948: aaload
    1949: iload_1
    1950: dup2
    1951: iaload
    1952: sipush        585
    1955: ior
    1956: iastore
    1957: aload         14
    1959: getfield      #78                 // Field ObjectDef.aBoolean767:Z
    1962: ifeq          1985
    1965: aload_3
    1966: ifnull        1985
    1969: aload_3
    1970: iload_1
    1971: iload         8
    1973: iload         6
    1975: iload         4
    1977: aload         14
    1979: getfield      #85                 // Field ObjectDef.aBoolean757:Z
    1982: invokevirtual #90                 // Method Class11.method211:(IIIIZ)V
    1985: aload         14
    1987: getfield      #91                 // Field ObjectDef.anInt775:I
    1990: bipush        16
    1992: if_icmpeq     2009
    1995: aload_2
    1996: iload_1
    1997: aload         14
    1999: getfield      #91                 // Field ObjectDef.anInt775:I
    2002: iload         6
    2004: iload         5
    2006: invokevirtual #92                 // Method WorldController.method290:(IIII)V
    2009: return
    2010: iload         4
    2012: iconst_3
    2013: if_icmpne     2247
    2016: aload         14
    2018: getfield      #71                 // Field ObjectDef.anInt781:I
    2021: iconst_m1
    2022: if_icmpne     2055
    2025: aload         14
    2027: getfield      #72                 // Field ObjectDef.childrenIDs:[I
    2030: ifnonnull     2055
    2033: aload         14
    2035: iconst_3
    2036: iload         8
    2038: iload         9
    2040: iload         10
    2042: iload         11
    2044: iload         12
    2046: iconst_m1
    2047: invokevirtual #73                 // Method ObjectDef.method578:(IIIIIII)LModel;
    2050: astore        17
    2052: goto          2083
    2055: new           #74                 // class Animable_Sub5
    2058: dup
    2059: iload         7
    2061: iload         8
    2063: iconst_3
    2064: iload         10
    2066: iload         11
    2068: iload         9
    2070: iload         12
    2072: aload         14
    2074: getfield      #71                 // Field ObjectDef.anInt781:I
    2077: iconst_1
    2078: invokespecial #75                 // Method Animable_Sub5."<init>":(IIIIIIIIZ)V
    2081: astore        17
    2083: aload_2
    2084: getstatic     #93                 // Field anIntArray140:[I
    2087: iload         8
    2089: iaload
    2090: aload         17
    2092: checkcast     #76                 // class Animable
    2095: checkcast     #76                 // class Animable
    2098: iload         15
    2100: iload_1
    2101: iload         16
    2103: iload         6
    2105: aconst_null
    2106: iload         13
    2108: iconst_0
    2109: iload         5
    2111: invokevirtual #88                 // Method WorldController.method282:(ILAnimable;IIBILAnimable;III)V
    2114: aload         14
    2116: getfield      #82                 // Field ObjectDef.aBoolean779:Z
    2119: ifeq          2218
    2122: iload         8
    2124: ifne          2146
    2127: aload_0
    2128: getfield      #14                 // Field aByteArrayArrayArray134:[[[B
    2131: iload         5
    2133: aaload
    2134: iload         6
    2136: aaload
    2137: iload_1
    2138: iconst_1
    2139: iadd
    2140: bipush        50
    2142: bastore
    2143: goto          2218
    2146: iload         8
    2148: iconst_1
    2149: if_icmpne     2173
    2152: aload_0
    2153: getfield      #14                 // Field aByteArrayArrayArray134:[[[B
    2156: iload         5
    2158: aaload
    2159: iload         6
    2161: iconst_1
    2162: iadd
    2163: aaload
    2164: iload_1
    2165: iconst_1
    2166: iadd
    2167: bipush        50
    2169: bastore
    2170: goto          2218
    2173: iload         8
    2175: iconst_2
    2176: if_icmpne     2198
    2179: aload_0
    2180: getfield      #14                 // Field aByteArrayArrayArray134:[[[B
    2183: iload         5
    2185: aaload
    2186: iload         6
    2188: iconst_1
    2189: iadd
    2190: aaload
    2191: iload_1
    2192: bipush        50
    2194: bastore
    2195: goto          2218
    2198: iload         8
    2200: iconst_3
    2201: if_icmpne     2218
    2204: aload_0
    2205: getfield      #14                 // Field aByteArrayArrayArray134:[[[B
    2208: iload         5
    2210: aaload
    2211: iload         6
    2213: aaload
    2214: iload_1
    2215: bipush        50
    2217: bastore
    2218: aload         14
    2220: getfield      #78                 // Field ObjectDef.aBoolean767:Z
    2223: ifeq          2246
    2226: aload_3
    2227: ifnull        2246
    2230: aload_3
    2231: iload_1
    2232: iload         8
    2234: iload         6
    2236: iload         4
    2238: aload         14
    2240: getfield      #85                 // Field ObjectDef.aBoolean757:Z
    2243: invokevirtual #90                 // Method Class11.method211:(IIIIZ)V
    2246: return
    2247: iload         4
    2249: bipush        9
    2251: if_icmpne     2387
    2254: aload         14
    2256: getfield      #71                 // Field ObjectDef.anInt781:I
    2259: iconst_m1
    2260: if_icmpne     2294
    2263: aload         14
    2265: getfield      #72                 // Field ObjectDef.childrenIDs:[I
    2268: ifnonnull     2294
    2271: aload         14
    2273: iload         4
    2275: iload         8
    2277: iload         9
    2279: iload         10
    2281: iload         11
    2283: iload         12
    2285: iconst_m1
    2286: invokevirtual #73                 // Method ObjectDef.method578:(IIIIIII)LModel;
    2289: astore        17
    2291: goto          2323
    2294: new           #74                 // class Animable_Sub5
    2297: dup
    2298: iload         7
    2300: iload         8
    2302: iload         4
    2304: iload         10
    2306: iload         11
    2308: iload         9
    2310: iload         12
    2312: aload         14
    2314: getfield      #71                 // Field ObjectDef.anInt781:I
    2317: iconst_1
    2318: invokespecial #75                 // Method Animable_Sub5."<init>":(IIIIIIIIZ)V
    2321: astore        17
    2323: aload_2
    2324: iload         15
    2326: iload         16
    2328: iload         13
    2330: iconst_1
    2331: aload         17
    2333: checkcast     #76                 // class Animable
    2336: checkcast     #76                 // class Animable
    2339: iconst_1
    2340: iload         5
    2342: iconst_0
    2343: iload_1
    2344: iload         6
    2346: invokevirtual #81                 // Method WorldController.method284:(IBIILAnimable;IIIII)Z
    2349: pop
    2350: aload         14
    2352: getfield      #78                 // Field ObjectDef.aBoolean767:Z
    2355: ifeq          2386
    2358: aload_3
    2359: ifnull        2386
    2362: aload_3
    2363: aload         14
    2365: getfield      #85                 // Field ObjectDef.aBoolean757:Z
    2368: aload         14
    2370: getfield      #80                 // Field ObjectDef.anInt744:I
    2373: aload         14
    2375: getfield      #79                 // Field ObjectDef.anInt761:I
    2378: iload         6
    2380: iload_1
    2381: iload         8
    2383: invokevirtual #86                 // Method Class11.method212:(ZIIIII)V
    2386: return
    2387: aload         14
    2389: getfield      #94                 // Field ObjectDef.aBoolean762:Z
    2392: ifeq          2483
    2395: iload         8
    2397: iconst_1
    2398: if_icmpne     2424
    2401: iload         12
    2403: istore        17
    2405: iload         11
    2407: istore        12
    2409: iload         10
    2411: istore        11
    2413: iload         9
    2415: istore        10
    2417: iload         17
    2419: istore        9
    2421: goto          2483
    2424: iload         8
    2426: iconst_2
    2427: if_icmpne     2457
    2430: iload         12
    2432: istore        17
    2434: iload         10
    2436: istore        12
    2438: iload         17
    2440: istore        10
    2442: iload         11
    2444: istore        17
    2446: iload         9
    2448: istore        11
    2450: iload         17
    2452: istore        9
    2454: goto          2483
    2457: iload         8
    2459: iconst_3
    2460: if_icmpne     2483
    2463: iload         12
    2465: istore        17
    2467: iload         9
    2469: istore        12
    2471: iload         10
    2473: istore        9
    2475: iload         11
    2477: istore        10
    2479: iload         17
    2481: istore        11
    2483: iload         4
    2485: iconst_4
    2486: if_icmpne     2592
    2489: aload         14
    2491: getfield      #71                 // Field ObjectDef.anInt781:I
    2494: iconst_m1
    2495: if_icmpne     2527
    2498: aload         14
    2500: getfield      #72                 // Field ObjectDef.childrenIDs:[I
    2503: ifnonnull     2527
    2506: aload         14
    2508: iconst_4
    2509: iconst_0
    2510: iload         9
    2512: iload         10
    2514: iload         11
    2516: iload         12
    2518: iconst_m1
    2519: invokevirtual #73                 // Method ObjectDef.method578:(IIIIIII)LModel;
    2522: astore        17
    2524: goto          2554
    2527: new           #74                 // class Animable_Sub5
    2530: dup
    2531: iload         7
    2533: iconst_0
    2534: iconst_4
    2535: iload         10
    2537: iload         11
    2539: iload         9
    2541: iload         12
    2543: aload         14
    2545: getfield      #71                 // Field ObjectDef.anInt781:I
    2548: iconst_1
    2549: invokespecial #75                 // Method Animable_Sub5."<init>":(IIIIIIIIZ)V
    2552: astore        17
    2554: aload_2
    2555: iload         15
    2557: iload_1
    2558: iload         8
    2560: sipush        512
    2563: imul
    2564: iload         5
    2566: iconst_0
    2567: iload         13
    2569: aload         17
    2571: checkcast     #76                 // class Animable
    2574: checkcast     #76                 // class Animable
    2577: iload         6
    2579: iload         16
    2581: iconst_0
    2582: getstatic     #87                 // Field anIntArray152:[I
    2585: iload         8
    2587: iaload
    2588: invokevirtual #95                 // Method WorldController.method283:(IIIIIILAnimable;IBII)V
    2591: return
    2592: iload         4
    2594: iconst_5
    2595: if_icmpne     2754
    2598: bipush        16
    2600: istore        17
    2602: aload_2
    2603: iload         5
    2605: iload         6
    2607: iload_1
    2608: invokevirtual #96                 // Method WorldController.method300:(III)I
    2611: istore        18
    2613: iload         18
    2615: ifle          2635
    2618: iload         18
    2620: bipush        14
    2622: ishr
    2623: sipush        32767
    2626: iand
    2627: invokestatic  #64                 // Method ObjectDef.forID:(I)LObjectDef;
    2630: getfield      #91                 // Field ObjectDef.anInt775:I
    2633: istore        17
    2635: aload         14
    2637: getfield      #71                 // Field ObjectDef.anInt781:I
    2640: iconst_m1
    2641: if_icmpne     2673
    2644: aload         14
    2646: getfield      #72                 // Field ObjectDef.childrenIDs:[I
    2649: ifnonnull     2673
    2652: aload         14
    2654: iconst_4
    2655: iconst_0
    2656: iload         9
    2658: iload         10
    2660: iload         11
    2662: iload         12
    2664: iconst_m1
    2665: invokevirtual #73                 // Method ObjectDef.method578:(IIIIIII)LModel;
    2668: astore        19
    2670: goto          2700
    2673: new           #74                 // class Animable_Sub5
    2676: dup
    2677: iload         7
    2679: iconst_0
    2680: iconst_4
    2681: iload         10
    2683: iload         11
    2685: iload         9
    2687: iload         12
    2689: aload         14
    2691: getfield      #71                 // Field ObjectDef.anInt781:I
    2694: iconst_1
    2695: invokespecial #75                 // Method Animable_Sub5."<init>":(IIIIIIIIZ)V
    2698: astore        19
    2700: aload_2
    2701: iload         15
    2703: iload_1
    2704: iload         8
    2706: sipush        512
    2709: imul
    2710: iload         5
    2712: getstatic     #97                 // Field anIntArray137:[I
    2715: iload         8
    2717: iaload
    2718: iload         17
    2720: imul
    2721: iload         13
    2723: aload         19
    2725: checkcast     #76                 // class Animable
    2728: checkcast     #76                 // class Animable
    2731: iload         6
    2733: iload         16
    2735: getstatic     #98                 // Field anIntArray144:[I
    2738: iload         8
    2740: iaload
    2741: iload         17
    2743: imul
    2744: getstatic     #87                 // Field anIntArray152:[I
    2747: iload         8
    2749: iaload
    2750: invokevirtual #95                 // Method WorldController.method283:(IIIIIILAnimable;IBII)V
    2753: return
    2754: iload         4
    2756: bipush        6
    2758: if_icmpne     2857
    2761: aload         14
    2763: getfield      #71                 // Field ObjectDef.anInt781:I
    2766: iconst_m1
    2767: if_icmpne     2799
    2770: aload         14
    2772: getfield      #72                 // Field ObjectDef.childrenIDs:[I
    2775: ifnonnull     2799
    2778: aload         14
    2780: iconst_4
    2781: iconst_0
    2782: iload         9
    2784: iload         10
    2786: iload         11
    2788: iload         12
    2790: iconst_m1
    2791: invokevirtual #73                 // Method ObjectDef.method578:(IIIIIII)LModel;
    2794: astore        17
    2796: goto          2826
    2799: new           #74                 // class Animable_Sub5
    2802: dup
    2803: iload         7
    2805: iconst_0
    2806: iconst_4
    2807: iload         10
    2809: iload         11
    2811: iload         9
    2813: iload         12
    2815: aload         14
    2817: getfield      #71                 // Field ObjectDef.anInt781:I
    2820: iconst_1
    2821: invokespecial #75                 // Method Animable_Sub5."<init>":(IIIIIIIIZ)V
    2824: astore        17
    2826: aload_2
    2827: iload         15
    2829: iload_1
    2830: iload         8
    2832: iload         5
    2834: iconst_0
    2835: iload         13
    2837: aload         17
    2839: checkcast     #76                 // class Animable
    2842: checkcast     #76                 // class Animable
    2845: iload         6
    2847: iload         16
    2849: iconst_0
    2850: sipush        256
    2853: invokevirtual #95                 // Method WorldController.method283:(IIIIIILAnimable;IBII)V
    2856: return
    2857: iload         4
    2859: bipush        7
    2861: if_icmpne     2960
    2864: aload         14
    2866: getfield      #71                 // Field ObjectDef.anInt781:I
    2869: iconst_m1
    2870: if_icmpne     2902
    2873: aload         14
    2875: getfield      #72                 // Field ObjectDef.childrenIDs:[I
    2878: ifnonnull     2902
    2881: aload         14
    2883: iconst_4
    2884: iconst_0
    2885: iload         9
    2887: iload         10
    2889: iload         11
    2891: iload         12
    2893: iconst_m1
    2894: invokevirtual #73                 // Method ObjectDef.method578:(IIIIIII)LModel;
    2897: astore        17
    2899: goto          2929
    2902: new           #74                 // class Animable_Sub5
    2905: dup
    2906: iload         7
    2908: iconst_0
    2909: iconst_4
    2910: iload         10
    2912: iload         11
    2914: iload         9
    2916: iload         12
    2918: aload         14
    2920: getfield      #71                 // Field ObjectDef.anInt781:I
    2923: iconst_1
    2924: invokespecial #75                 // Method Animable_Sub5."<init>":(IIIIIIIIZ)V
    2927: astore        17
    2929: aload_2
    2930: iload         15
    2932: iload_1
    2933: iload         8
    2935: iload         5
    2937: iconst_0
    2938: iload         13
    2940: aload         17
    2942: checkcast     #76                 // class Animable
    2945: checkcast     #76                 // class Animable
    2948: iload         6
    2950: iload         16
    2952: iconst_0
    2953: sipush        512
    2956: invokevirtual #95                 // Method WorldController.method283:(IIIIIILAnimable;IBII)V
    2959: return
    2960: iload         4
    2962: bipush        8
    2964: if_icmpne     3062
    2967: aload         14
    2969: getfield      #71                 // Field ObjectDef.anInt781:I
    2972: iconst_m1
    2973: if_icmpne     3005
    2976: aload         14
    2978: getfield      #72                 // Field ObjectDef.childrenIDs:[I
    2981: ifnonnull     3005
    2984: aload         14
    2986: iconst_4
    2987: iconst_0
    2988: iload         9
    2990: iload         10
    2992: iload         11
    2994: iload         12
    2996: iconst_m1
    2997: invokevirtual #73                 // Method ObjectDef.method578:(IIIIIII)LModel;
    3000: astore        17
    3002: goto          3032
    3005: new           #74                 // class Animable_Sub5
    3008: dup
    3009: iload         7
    3011: iconst_0
    3012: iconst_4
    3013: iload         10
    3015: iload         11
    3017: iload         9
    3019: iload         12
    3021: aload         14
    3023: getfield      #71                 // Field ObjectDef.anInt781:I
    3026: iconst_1
    3027: invokespecial #75                 // Method Animable_Sub5."<init>":(IIIIIIIIZ)V
    3030: astore        17
    3032: aload_2
    3033: iload         15
    3035: iload_1
    3036: iload         8
    3038: iload         5
    3040: iconst_0
    3041: iload         13
    3043: aload         17
    3045: checkcast     #76                 // class Animable
    3048: checkcast     #76                 // class Animable
    3051: iload         6
    3053: iload         16
    3055: iconst_0
    3056: sipush        768
    3059: invokevirtual #95                 // Method WorldController.method283:(IIIIIILAnimable;IBII)V
    3062: return

  private static int method176(int, int, int);
    Code:
       0: iload_0
       1: iload_2
       2: idiv
       3: istore_3
       4: iload_0
       5: iload_2
       6: iconst_1
       7: isub
       8: iand
       9: istore        4
      11: iload_1
      12: iload_2
      13: idiv
      14: istore        5
      16: iload_1
      17: iload_2
      18: iconst_1
      19: isub
      20: iand
      21: istore        6
      23: iload_3
      24: iload         5
      26: invokestatic  #99                 // Method method186:(II)I
      29: istore        7
      31: iload_3
      32: iconst_1
      33: iadd
      34: iload         5
      36: invokestatic  #99                 // Method method186:(II)I
      39: istore        8
      41: iload_3
      42: iload         5
      44: iconst_1
      45: iadd
      46: invokestatic  #99                 // Method method186:(II)I
      49: istore        9
      51: iload_3
      52: iconst_1
      53: iadd
      54: iload         5
      56: iconst_1
      57: iadd
      58: invokestatic  #99                 // Method method186:(II)I
      61: istore        10
      63: iload         7
      65: iload         8
      67: iload         4
      69: iload_2
      70: invokestatic  #100                // Method method184:(IIII)I
      73: istore        11
      75: iload         9
      77: iload         10
      79: iload         4
      81: iload_2
      82: invokestatic  #100                // Method method184:(IIII)I
      85: istore        12
      87: iload         11
      89: iload         12
      91: iload         6
      93: iload_2
      94: invokestatic  #100                // Method method184:(IIII)I
      97: ireturn

  private int method177(int, int, int);
    Code:
       0: iload_3
       1: sipush        179
       4: if_icmple     11
       7: iload_2
       8: iconst_2
       9: idiv
      10: istore_2
      11: iload_3
      12: sipush        192
      15: if_icmple     22
      18: iload_2
      19: iconst_2
      20: idiv
      21: istore_2
      22: iload_3
      23: sipush        217
      26: if_icmple     33
      29: iload_2
      30: iconst_2
      31: idiv
      32: istore_2
      33: iload_3
      34: sipush        243
      37: if_icmple     44
      40: iload_2
      41: iconst_2
      42: idiv
      43: istore_2
      44: iload_1
      45: iconst_4
      46: idiv
      47: bipush        10
      49: ishl
      50: iload_2
      51: bipush        32
      53: idiv
      54: bipush        7
      56: ishl
      57: iadd
      58: iload_3
      59: iconst_2
      60: idiv
      61: iadd
      62: ireturn

  public static boolean method178(int, int);
    Code:
       0: iload_0
       1: invokestatic  #64                 // Method ObjectDef.forID:(I)LObjectDef;
       4: astore_2
       5: iload_1
       6: bipush        11
       8: if_icmpne     14
      11: bipush        10
      13: istore_1
      14: iload_1
      15: iconst_5
      16: if_icmplt     27
      19: iload_1
      20: bipush        8
      22: if_icmpgt     27
      25: iconst_4
      26: istore_1
      27: aload_2
      28: iload_1
      29: invokevirtual #101                // Method ObjectDef.method577:(I)Z
      32: ireturn

  public final void method179(int, int, Class11[], int, int, byte[], int, int, int);
    Code:
       0: iconst_0
       1: istore        10
       3: iload         10
       5: bipush        8
       7: if_icmpge     92
      10: iconst_0
      11: istore        11
      13: iload         11
      15: bipush        8
      17: if_icmpge     86
      20: iload         4
      22: iload         10
      24: iadd
      25: ifle          80
      28: iload         4
      30: iload         10
      32: iadd
      33: bipush        103
      35: if_icmpge     80
      38: iload         9
      40: iload         11
      42: iadd
      43: ifle          80
      46: iload         9
      48: iload         11
      50: iadd
      51: bipush        103
      53: if_icmpge     80
      56: aload_3
      57: iload         8
      59: aaload
      60: getfield      #102                // Field Class11.anIntArrayArray294:[[I
      63: iload         4
      65: iload         10
      67: iadd
      68: aaload
      69: iload         9
      71: iload         11
      73: iadd
      74: dup2
      75: iaload
      76: ldc           #103                // int -16777217
      78: iand
      79: iastore
      80: iinc          11, 1
      83: goto          13
      86: iinc          10, 1
      89: goto          3
      92: new           #104                // class Stream
      95: dup
      96: aload         6
      98: invokespecial #105                // Method Stream."<init>":([B)V
     101: astore        10
     103: iconst_0
     104: istore        11
     106: iload         11
     108: iconst_4
     109: if_icmpge     250
     112: iconst_0
     113: istore        12
     115: iload         12
     117: bipush        64
     119: if_icmpge     244
     122: iconst_0
     123: istore        13
     125: iload         13
     127: bipush        64
     129: if_icmpge     238
     132: iload         11
     134: iload_1
     135: if_icmpne     220
     138: iload         12
     140: iload         5
     142: if_icmplt     220
     145: iload         12
     147: iload         5
     149: bipush        8
     151: iadd
     152: if_icmpge     220
     155: iload         13
     157: iload         7
     159: if_icmplt     220
     162: iload         13
     164: iload         7
     166: bipush        8
     168: iadd
     169: if_icmpge     220
     172: aload_0
     173: iload         9
     175: iload         13
     177: bipush        7
     179: iand
     180: iload_2
     181: iload         12
     183: bipush        7
     185: iand
     186: invokestatic  #106                // Method Class4.method156:(III)I
     189: iadd
     190: iconst_0
     191: aload         10
     193: iload         4
     195: iload_2
     196: iload         13
     198: bipush        7
     200: iand
     201: iload         12
     203: bipush        7
     205: iand
     206: invokestatic  #107                // Method Class4.method155:(III)I
     209: iadd
     210: iload         8
     212: iload_2
     213: iconst_0
     214: invokespecial #108                // Method method181:(IILStream;IIII)V
     217: goto          232
     220: aload_0
     221: iconst_m1
     222: iconst_0
     223: aload         10
     225: iconst_m1
     226: iconst_0
     227: iconst_0
     228: iconst_0
     229: invokespecial #108                // Method method181:(IILStream;IIII)V
     232: iinc          13, 1
     235: goto          125
     238: iinc          12, 1
     241: goto          115
     244: iinc          11, 1
     247: goto          106
     250: return

  public final void method180(byte[], int, int, int, int, Class11[]);
    Code:
       0: iconst_0
       1: istore        7
       3: iload         7
       5: iconst_4
       6: if_icmpge     102
       9: iconst_0
      10: istore        8
      12: iload         8
      14: bipush        64
      16: if_icmpge     96
      19: iconst_0
      20: istore        9
      22: iload         9
      24: bipush        64
      26: if_icmpge     90
      29: iload_3
      30: iload         8
      32: iadd
      33: ifle          84
      36: iload_3
      37: iload         8
      39: iadd
      40: bipush        103
      42: if_icmpge     84
      45: iload_2
      46: iload         9
      48: iadd
      49: ifle          84
      52: iload_2
      53: iload         9
      55: iadd
      56: bipush        103
      58: if_icmpge     84
      61: aload         6
      63: iload         7
      65: aaload
      66: getfield      #102                // Field Class11.anIntArrayArray294:[[I
      69: iload_3
      70: iload         8
      72: iadd
      73: aaload
      74: iload_2
      75: iload         9
      77: iadd
      78: dup2
      79: iaload
      80: ldc           #103                // int -16777217
      82: iand
      83: iastore
      84: iinc          9, 1
      87: goto          22
      90: iinc          8, 1
      93: goto          12
      96: iinc          7, 1
      99: goto          3
     102: new           #104                // class Stream
     105: dup
     106: aload_1
     107: invokespecial #105                // Method Stream."<init>":([B)V
     110: astore        7
     112: iconst_0
     113: istore        8
     115: iload         8
     117: iconst_4
     118: if_icmpge     180
     121: iconst_0
     122: istore        9
     124: iload         9
     126: bipush        64
     128: if_icmpge     174
     131: iconst_0
     132: istore        10
     134: iload         10
     136: bipush        64
     138: if_icmpge     168
     141: aload_0
     142: iload         10
     144: iload_2
     145: iadd
     146: iload         5
     148: aload         7
     150: iload         9
     152: iload_3
     153: iadd
     154: iload         8
     156: iconst_0
     157: iload         4
     159: invokespecial #108                // Method method181:(IILStream;IIII)V
     162: iinc          10, 1
     165: goto          134
     168: iinc          9, 1
     171: goto          124
     174: iinc          8, 1
     177: goto          115
     180: return

  private void method181(int, int, Stream, int, int, int, int);
    Code:
       0: iload         4
       2: iflt          308
       5: iload         4
       7: bipush        104
       9: if_icmpge     308
      12: iload_1
      13: iflt          308
      16: iload_1
      17: bipush        104
      19: if_icmpge     308
      22: aload_0
      23: getfield      #6                  // Field aByteArrayArrayArray149:[[[B
      26: iload         5
      28: aaload
      29: iload         4
      31: aaload
      32: iload_1
      33: iconst_0
      34: bastore
      35: aload_3
      36: invokevirtual #66                 // Method Stream.readUnsignedByte:()I
      39: istore        8
      41: iload         8
      43: ifne          115
      46: iload         5
      48: ifne          84
      51: aload_0
      52: getfield      #5                  // Field anIntArrayArrayArray129:[[[I
      55: iconst_0
      56: aaload
      57: iload         4
      59: aaload
      60: iload_1
      61: ldc           #109                // int 932731
      63: iload         4
      65: iadd
      66: iload         7
      68: iadd
      69: ldc           #110                // int 556238
      71: iload_1
      72: iadd
      73: iload_2
      74: iadd
      75: invokestatic  #111                // Method method172:(II)I
      78: ineg
      79: bipush        8
      81: imul
      82: iastore
      83: return
      84: aload_0
      85: getfield      #5                  // Field anIntArrayArrayArray129:[[[I
      88: iload         5
      90: aaload
      91: iload         4
      93: aaload
      94: iload_1
      95: aload_0
      96: getfield      #5                  // Field anIntArrayArrayArray129:[[[I
      99: iload         5
     101: iconst_1
     102: isub
     103: aaload
     104: iload         4
     106: aaload
     107: iload_1
     108: iaload
     109: sipush        240
     112: isub
     113: iastore
     114: return
     115: iload         8
     117: iconst_1
     118: if_icmpne     192
     121: aload_3
     122: invokevirtual #66                 // Method Stream.readUnsignedByte:()I
     125: istore        9
     127: iload         9
     129: iconst_1
     130: if_icmpne     136
     133: iconst_0
     134: istore        9
     136: iload         5
     138: ifne          159
     141: aload_0
     142: getfield      #5                  // Field anIntArrayArrayArray129:[[[I
     145: iconst_0
     146: aaload
     147: iload         4
     149: aaload
     150: iload_1
     151: iload         9
     153: ineg
     154: bipush        8
     156: imul
     157: iastore
     158: return
     159: aload_0
     160: getfield      #5                  // Field anIntArrayArrayArray129:[[[I
     163: iload         5
     165: aaload
     166: iload         4
     168: aaload
     169: iload_1
     170: aload_0
     171: getfield      #5                  // Field anIntArrayArrayArray129:[[[I
     174: iload         5
     176: iconst_1
     177: isub
     178: aaload
     179: iload         4
     181: aaload
     182: iload_1
     183: iaload
     184: iload         9
     186: bipush        8
     188: imul
     189: isub
     190: iastore
     191: return
     192: iload         8
     194: bipush        49
     196: if_icmpgt     259
     199: aload_0
     200: getfield      #9                  // Field aByteArrayArrayArray130:[[[B
     203: iload         5
     205: aaload
     206: iload         4
     208: aaload
     209: iload_1
     210: aload_3
     211: invokevirtual #112                // Method Stream.readSignedByte:()B
     214: bastore
     215: aload_0
     216: getfield      #10                 // Field aByteArrayArrayArray136:[[[B
     219: iload         5
     221: aaload
     222: iload         4
     224: aaload
     225: iload_1
     226: iload         8
     228: iconst_2
     229: isub
     230: iconst_4
     231: idiv
     232: i2b
     233: bastore
     234: aload_0
     235: getfield      #11                 // Field aByteArrayArrayArray148:[[[B
     238: iload         5
     240: aaload
     241: iload         4
     243: aaload
     244: iload_1
     245: iload         8
     247: iconst_2
     248: isub
     249: iload         6
     251: iadd
     252: iconst_3
     253: iand
     254: i2b
     255: bastore
     256: goto          305
     259: iload         8
     261: bipush        81
     263: if_icmpgt     287
     266: aload_0
     267: getfield      #6                  // Field aByteArrayArrayArray149:[[[B
     270: iload         5
     272: aaload
     273: iload         4
     275: aaload
     276: iload_1
     277: iload         8
     279: bipush        49
     281: isub
     282: i2b
     283: bastore
     284: goto          305
     287: aload_0
     288: getfield      #8                  // Field aByteArrayArrayArray142:[[[B
     291: iload         5
     293: aaload
     294: iload         4
     296: aaload
     297: iload_1
     298: iload         8
     300: bipush        81
     302: isub
     303: i2b
     304: bastore
     305: goto          35
     308: aload_3
     309: invokevirtual #66                 // Method Stream.readUnsignedByte:()I
     312: istore        8
     314: iload         8
     316: ifne          322
     319: goto          349
     322: iload         8
     324: iconst_1
     325: if_icmpne     334
     328: aload_3
     329: invokevirtual #66                 // Method Stream.readUnsignedByte:()I
     332: pop
     333: return
     334: iload         8
     336: bipush        49
     338: if_icmpgt     346
     341: aload_3
     342: invokevirtual #66                 // Method Stream.readUnsignedByte:()I
     345: pop
     346: goto          308
     349: return

  private int method182(int, int, int);
    Code:
       0: aload_0
       1: getfield      #6                  // Field aByteArrayArrayArray149:[[[B
       4: iload_2
       5: aaload
       6: iload_3
       7: aaload
       8: iload_1
       9: baload
      10: bipush        8
      12: iand
      13: ifeq          18
      16: iconst_0
      17: ireturn
      18: iload_2
      19: ifle          41
      22: aload_0
      23: getfield      #6                  // Field aByteArrayArrayArray149:[[[B
      26: iconst_1
      27: aaload
      28: iload_3
      29: aaload
      30: iload_1
      31: baload
      32: iconst_2
      33: iand
      34: ifeq          41
      37: iload_2
      38: iconst_1
      39: isub
      40: ireturn
      41: iload_2
      42: ireturn

  public final void method183(Class11[], WorldController, int, int, int, int, byte[], int, int, int);
    Code:
       0: new           #104                // class Stream
       3: dup
       4: aload         7
       6: invokespecial #105                // Method Stream."<init>":([B)V
       9: astore        11
      11: iconst_m1
      12: istore        12
      14: aload         11
      16: invokevirtual #63                 // Method Stream.method422:()I
      19: istore        13
      21: iload         13
      23: ifne          29
      26: goto          306
      29: iload         12
      31: iload         13
      33: iadd
      34: istore        12
      36: iconst_0
      37: istore        14
      39: aload         11
      41: invokevirtual #63                 // Method Stream.method422:()I
      44: istore        15
      46: iload         15
      48: ifne          54
      51: goto          303
      54: iload         14
      56: iload         15
      58: iconst_1
      59: isub
      60: iadd
      61: istore        14
      63: iload         14
      65: bipush        63
      67: iand
      68: istore        16
      70: iload         14
      72: bipush        6
      74: ishr
      75: bipush        63
      77: iand
      78: istore        17
      80: iload         14
      82: bipush        12
      84: ishr
      85: istore        18
      87: aload         11
      89: invokevirtual #66                 // Method Stream.readUnsignedByte:()I
      92: istore        19
      94: iload         19
      96: iconst_2
      97: ishr
      98: istore        20
     100: iload         19
     102: iconst_3
     103: iand
     104: istore        21
     106: iload         18
     108: iload_3
     109: if_icmpne     300
     112: iload         17
     114: iload         8
     116: if_icmplt     300
     119: iload         17
     121: iload         8
     123: bipush        8
     125: iadd
     126: if_icmpge     300
     129: iload         16
     131: iload         5
     133: if_icmplt     300
     136: iload         16
     138: iload         5
     140: bipush        8
     142: iadd
     143: if_icmpge     300
     146: iload         12
     148: invokestatic  #64                 // Method ObjectDef.forID:(I)LObjectDef;
     151: astore        22
     153: iload         4
     155: iload         9
     157: aload         22
     159: getfield      #79                 // Field ObjectDef.anInt761:I
     162: iload         17
     164: bipush        7
     166: iand
     167: iload         16
     169: bipush        7
     171: iand
     172: aload         22
     174: getfield      #80                 // Field ObjectDef.anInt744:I
     177: invokestatic  #113                // Method Class4.method157:(IIIII)I
     180: iadd
     181: istore        23
     183: iload         10
     185: iload         16
     187: bipush        7
     189: iand
     190: aload         22
     192: getfield      #79                 // Field ObjectDef.anInt761:I
     195: iload         9
     197: aload         22
     199: getfield      #80                 // Field ObjectDef.anInt744:I
     202: iload         17
     204: bipush        7
     206: iand
     207: invokestatic  #114                // Method Class4.method158:(IIIII)I
     210: iadd
     211: istore        24
     213: iload         23
     215: ifle          300
     218: iload         24
     220: ifle          300
     223: iload         23
     225: bipush        103
     227: if_icmpge     300
     230: iload         24
     232: bipush        103
     234: if_icmpge     300
     237: iload         18
     239: istore        25
     241: aload_0
     242: getfield      #6                  // Field aByteArrayArrayArray149:[[[B
     245: iconst_1
     246: aaload
     247: iload         23
     249: aaload
     250: iload         24
     252: baload
     253: iconst_2
     254: iand
     255: iconst_2
     256: if_icmpne     262
     259: iinc          25, -1
     262: aconst_null
     263: astore        26
     265: iload         25
     267: iflt          276
     270: aload_1
     271: iload         25
     273: aaload
     274: astore        26
     276: aload_0
     277: iload         24
     279: aload_2
     280: aload         26
     282: iload         20
     284: iload         6
     286: iload         23
     288: iload         12
     290: iload         21
     292: iload         9
     294: iadd
     295: iconst_3
     296: iand
     297: invokespecial #115                // Method method175:(ILWorldController;LClass11;IIIII)V
     300: goto          39
     303: goto          14
     306: return

  private static int method184(int, int, int, int);
    Code:
       0: ldc           #32                 // int 65536
       2: getstatic     #116                // Field Texture.anIntArray1471:[I
       5: iload_2
       6: sipush        1024
       9: imul
      10: iload_3
      11: idiv
      12: iaload
      13: isub
      14: iconst_1
      15: ishr
      16: istore        4
      18: iload_0
      19: ldc           #32                 // int 65536
      21: iload         4
      23: isub
      24: imul
      25: bipush        16
      27: ishr
      28: iload_1
      29: iload         4
      31: imul
      32: bipush        16
      34: ishr
      35: iadd
      36: ireturn

  private int method185(int, int);
    Code:
       0: iload_1
       1: bipush        -2
       3: if_icmpne     9
       6: ldc           #117                // int 12345678
       8: ireturn
       9: iload_1
      10: iconst_m1
      11: if_icmpne     39
      14: iload_2
      15: ifge          23
      18: iconst_0
      19: istore_2
      20: goto          32
      23: iload_2
      24: bipush        127
      26: if_icmple     32
      29: bipush        127
      31: istore_2
      32: bipush        127
      34: iload_2
      35: isub
      36: istore_2
      37: iload_2
      38: ireturn
      39: iload_2
      40: iload_1
      41: bipush        127
      43: iand
      44: imul
      45: sipush        128
      48: idiv
      49: istore_2
      50: iload_2
      51: iconst_2
      52: if_icmpge     60
      55: iconst_2
      56: istore_2
      57: goto          69
      60: iload_2
      61: bipush        126
      63: if_icmple     69
      66: bipush        126
      68: istore_2
      69: iload_1
      70: ldc           #118                // int 65408
      72: iand
      73: iload_2
      74: iadd
      75: ireturn

  private static int method186(int, int);
    Code:
       0: iload_0
       1: iconst_1
       2: isub
       3: iload_1
       4: iconst_1
       5: isub
       6: invokestatic  #119                // Method method170:(II)I
       9: iload_0
      10: iconst_1
      11: iadd
      12: iload_1
      13: iconst_1
      14: isub
      15: invokestatic  #119                // Method method170:(II)I
      18: iadd
      19: iload_0
      20: iconst_1
      21: isub
      22: iload_1
      23: iconst_1
      24: iadd
      25: invokestatic  #119                // Method method170:(II)I
      28: iadd
      29: iload_0
      30: iconst_1
      31: iadd
      32: iload_1
      33: iconst_1
      34: iadd
      35: invokestatic  #119                // Method method170:(II)I
      38: iadd
      39: istore_2
      40: iload_0
      41: iconst_1
      42: isub
      43: iload_1
      44: invokestatic  #119                // Method method170:(II)I
      47: iload_0
      48: iconst_1
      49: iadd
      50: iload_1
      51: invokestatic  #119                // Method method170:(II)I
      54: iadd
      55: iload_0
      56: iload_1
      57: iconst_1
      58: isub
      59: invokestatic  #119                // Method method170:(II)I
      62: iadd
      63: iload_0
      64: iload_1
      65: iconst_1
      66: iadd
      67: invokestatic  #119                // Method method170:(II)I
      70: iadd
      71: istore_3
      72: iload_0
      73: iload_1
      74: invokestatic  #119                // Method method170:(II)I
      77: istore        4
      79: iload_2
      80: bipush        16
      82: idiv
      83: iload_3
      84: bipush        8
      86: idiv
      87: iadd
      88: iload         4
      90: iconst_4
      91: idiv
      92: iadd
      93: ireturn

  private static int method187(int, int);
    Code:
       0: iload_0
       1: iconst_m1
       2: if_icmpne     8
       5: ldc           #117                // int 12345678
       7: ireturn
       8: iload_1
       9: iload_0
      10: bipush        127
      12: iand
      13: imul
      14: sipush        128
      17: idiv
      18: istore_1
      19: iload_1
      20: iconst_2
      21: if_icmpge     29
      24: iconst_2
      25: istore_1
      26: goto          38
      29: iload_1
      30: bipush        126
      32: if_icmple     38
      35: bipush        126
      37: istore_1
      38: iload_0
      39: ldc           #118                // int 65408
      41: iand
      42: iload_1
      43: iadd
      44: ireturn

  public static void method188(WorldController, int, int, int, int, Class11, int[][][], int, int, int);
    Code:
       0: aload         6
       2: iload         4
       4: aaload
       5: iload         7
       7: aaload
       8: iload_2
       9: iaload
      10: istore        10
      12: aload         6
      14: iload         4
      16: aaload
      17: iload         7
      19: iconst_1
      20: iadd
      21: aaload
      22: iload_2
      23: iaload
      24: istore        11
      26: aload         6
      28: iload         4
      30: aaload
      31: iload         7
      33: iconst_1
      34: iadd
      35: aaload
      36: iload_2
      37: iconst_1
      38: iadd
      39: iaload
      40: istore        12
      42: aload         6
      44: iload         4
      46: aaload
      47: iload         7
      49: aaload
      50: iload_2
      51: iconst_1
      52: iadd
      53: iaload
      54: istore        13
      56: iload         10
      58: iload         11
      60: iadd
      61: iload         12
      63: iadd
      64: iload         13
      66: iadd
      67: iconst_2
      68: ishr
      69: istore        14
      71: iload         8
      73: invokestatic  #64                 // Method ObjectDef.forID:(I)LObjectDef;
      76: astore        15
      78: iload         7
      80: iload_2
      81: bipush        7
      83: ishl
      84: iadd
      85: iload         8
      87: bipush        14
      89: ishl
      90: iadd
      91: ldc           #67                 // int 1073741824
      93: iadd
      94: istore        16
      96: aload         15
      98: getfield      #68                 // Field ObjectDef.hasActions:Z
     101: ifne          111
     104: iload         16
     106: ldc           #69                 // int -2147483648
     108: isub
     109: istore        16
     111: iload_1
     112: bipush        6
     114: ishl
     115: iload_3
     116: iadd
     117: i2b
     118: istore        17
     120: iload_3
     121: bipush        22
     123: if_icmpne     241
     126: aload         15
     128: getfield      #71                 // Field ObjectDef.anInt781:I
     131: iconst_m1
     132: if_icmpne     165
     135: aload         15
     137: getfield      #72                 // Field ObjectDef.childrenIDs:[I
     140: ifnonnull     165
     143: aload         15
     145: bipush        22
     147: iload_1
     148: iload         10
     150: iload         11
     152: iload         12
     154: iload         13
     156: iconst_m1
     157: invokevirtual #73                 // Method ObjectDef.method578:(IIIIIII)LModel;
     160: astore        18
     162: goto          193
     165: new           #74                 // class Animable_Sub5
     168: dup
     169: iload         8
     171: iload_1
     172: bipush        22
     174: iload         11
     176: iload         12
     178: iload         10
     180: iload         13
     182: aload         15
     184: getfield      #71                 // Field ObjectDef.anInt781:I
     187: iconst_1
     188: invokespecial #75                 // Method Animable_Sub5."<init>":(IIIIIIIIZ)V
     191: astore        18
     193: aload_0
     194: iload         9
     196: iload         14
     198: iload_2
     199: aload         18
     201: checkcast     #76                 // class Animable
     204: checkcast     #76                 // class Animable
     207: iload         17
     209: iload         16
     211: iload         7
     213: invokevirtual #77                 // Method WorldController.method280:(IIILAnimable;BII)V
     216: aload         15
     218: getfield      #78                 // Field ObjectDef.aBoolean767:Z
     221: ifeq          240
     224: aload         15
     226: getfield      #68                 // Field ObjectDef.hasActions:Z
     229: ifeq          240
     232: aload         5
     234: iload_2
     235: iload         7
     237: invokevirtual #25                 // Method Class11.method213:(II)V
     240: return
     241: iload_3
     242: bipush        10
     244: if_icmpeq     253
     247: iload_3
     248: bipush        11
     250: if_icmpne     444
     253: aload         15
     255: getfield      #71                 // Field ObjectDef.anInt781:I
     258: iconst_m1
     259: if_icmpne     292
     262: aload         15
     264: getfield      #72                 // Field ObjectDef.childrenIDs:[I
     267: ifnonnull     292
     270: aload         15
     272: bipush        10
     274: iload_1
     275: iload         10
     277: iload         11
     279: iload         12
     281: iload         13
     283: iconst_m1
     284: invokevirtual #73                 // Method ObjectDef.method578:(IIIIIII)LModel;
     287: astore        18
     289: goto          320
     292: new           #74                 // class Animable_Sub5
     295: dup
     296: iload         8
     298: iload_1
     299: bipush        10
     301: iload         11
     303: iload         12
     305: iload         10
     307: iload         13
     309: aload         15
     311: getfield      #71                 // Field ObjectDef.anInt781:I
     314: iconst_1
     315: invokespecial #75                 // Method Animable_Sub5."<init>":(IIIIIIIIZ)V
     318: astore        18
     320: aload         18
     322: ifnull        411
     325: iconst_0
     326: istore        19
     328: iload_3
     329: bipush        11
     331: if_icmpne     340
     334: iinc_w        19, 256
     340: iload_1
     341: iconst_1
     342: if_icmpeq     350
     345: iload_1
     346: iconst_3
     347: if_icmpne     367
     350: aload         15
     352: getfield      #79                 // Field ObjectDef.anInt761:I
     355: istore        20
     357: aload         15
     359: getfield      #80                 // Field ObjectDef.anInt744:I
     362: istore        21
     364: goto          381
     367: aload         15
     369: getfield      #80                 // Field ObjectDef.anInt744:I
     372: istore        20
     374: aload         15
     376: getfield      #79                 // Field ObjectDef.anInt761:I
     379: istore        21
     381: aload_0
     382: iload         16
     384: iload         17
     386: iload         14
     388: iload         21
     390: aload         18
     392: checkcast     #76                 // class Animable
     395: checkcast     #76                 // class Animable
     398: iload         20
     400: iload         9
     402: iload         19
     404: iload_2
     405: iload         7
     407: invokevirtual #81                 // Method WorldController.method284:(IBIILAnimable;IIIII)Z
     410: pop
     411: aload         15
     413: getfield      #78                 // Field ObjectDef.aBoolean767:Z
     416: ifeq          443
     419: aload         5
     421: aload         15
     423: getfield      #85                 // Field ObjectDef.aBoolean757:Z
     426: aload         15
     428: getfield      #80                 // Field ObjectDef.anInt744:I
     431: aload         15
     433: getfield      #79                 // Field ObjectDef.anInt761:I
     436: iload         7
     438: iload_2
     439: iload_1
     440: invokevirtual #86                 // Method Class11.method212:(ZIIIII)V
     443: return
     444: iload_3
     445: bipush        12
     447: if_icmplt     575
     450: aload         15
     452: getfield      #71                 // Field ObjectDef.anInt781:I
     455: iconst_m1
     456: if_icmpne     488
     459: aload         15
     461: getfield      #72                 // Field ObjectDef.childrenIDs:[I
     464: ifnonnull     488
     467: aload         15
     469: iload_3
     470: iload_1
     471: iload         10
     473: iload         11
     475: iload         12
     477: iload         13
     479: iconst_m1
     480: invokevirtual #73                 // Method ObjectDef.method578:(IIIIIII)LModel;
     483: astore        18
     485: goto          515
     488: new           #74                 // class Animable_Sub5
     491: dup
     492: iload         8
     494: iload_1
     495: iload_3
     496: iload         11
     498: iload         12
     500: iload         10
     502: iload         13
     504: aload         15
     506: getfield      #71                 // Field ObjectDef.anInt781:I
     509: iconst_1
     510: invokespecial #75                 // Method Animable_Sub5."<init>":(IIIIIIIIZ)V
     513: astore        18
     515: aload_0
     516: iload         16
     518: iload         17
     520: iload         14
     522: iconst_1
     523: aload         18
     525: checkcast     #76                 // class Animable
     528: checkcast     #76                 // class Animable
     531: iconst_1
     532: iload         9
     534: iconst_0
     535: iload_2
     536: iload         7
     538: invokevirtual #81                 // Method WorldController.method284:(IBIILAnimable;IIIII)Z
     541: pop
     542: aload         15
     544: getfield      #78                 // Field ObjectDef.aBoolean767:Z
     547: ifeq          574
     550: aload         5
     552: aload         15
     554: getfield      #85                 // Field ObjectDef.aBoolean757:Z
     557: aload         15
     559: getfield      #80                 // Field ObjectDef.anInt744:I
     562: aload         15
     564: getfield      #79                 // Field ObjectDef.anInt761:I
     567: iload         7
     569: iload_2
     570: iload_1
     571: invokevirtual #86                 // Method Class11.method212:(ZIIIII)V
     574: return
     575: iload_3
     576: ifne          698
     579: aload         15
     581: getfield      #71                 // Field ObjectDef.anInt781:I
     584: iconst_m1
     585: if_icmpne     617
     588: aload         15
     590: getfield      #72                 // Field ObjectDef.childrenIDs:[I
     593: ifnonnull     617
     596: aload         15
     598: iconst_0
     599: iload_1
     600: iload         10
     602: iload         11
     604: iload         12
     606: iload         13
     608: iconst_m1
     609: invokevirtual #73                 // Method ObjectDef.method578:(IIIIIII)LModel;
     612: astore        18
     614: goto          644
     617: new           #74                 // class Animable_Sub5
     620: dup
     621: iload         8
     623: iload_1
     624: iconst_0
     625: iload         11
     627: iload         12
     629: iload         10
     631: iload         13
     633: aload         15
     635: getfield      #71                 // Field ObjectDef.anInt781:I
     638: iconst_1
     639: invokespecial #75                 // Method Animable_Sub5."<init>":(IIIIIIIIZ)V
     642: astore        18
     644: aload_0
     645: getstatic     #87                 // Field anIntArray152:[I
     648: iload_1
     649: iaload
     650: aload         18
     652: checkcast     #76                 // class Animable
     655: checkcast     #76                 // class Animable
     658: iload         16
     660: iload_2
     661: iload         17
     663: iload         7
     665: aconst_null
     666: iload         14
     668: iconst_0
     669: iload         9
     671: invokevirtual #88                 // Method WorldController.method282:(ILAnimable;IIBILAnimable;III)V
     674: aload         15
     676: getfield      #78                 // Field ObjectDef.aBoolean767:Z
     679: ifeq          697
     682: aload         5
     684: iload_2
     685: iload_1
     686: iload         7
     688: iload_3
     689: aload         15
     691: getfield      #85                 // Field ObjectDef.aBoolean757:Z
     694: invokevirtual #90                 // Method Class11.method211:(IIIIZ)V
     697: return
     698: iload_3
     699: iconst_1
     700: if_icmpne     822
     703: aload         15
     705: getfield      #71                 // Field ObjectDef.anInt781:I
     708: iconst_m1
     709: if_icmpne     741
     712: aload         15
     714: getfield      #72                 // Field ObjectDef.childrenIDs:[I
     717: ifnonnull     741
     720: aload         15
     722: iconst_1
     723: iload_1
     724: iload         10
     726: iload         11
     728: iload         12
     730: iload         13
     732: iconst_m1
     733: invokevirtual #73                 // Method ObjectDef.method578:(IIIIIII)LModel;
     736: astore        18
     738: goto          768
     741: new           #74                 // class Animable_Sub5
     744: dup
     745: iload         8
     747: iload_1
     748: iconst_1
     749: iload         11
     751: iload         12
     753: iload         10
     755: iload         13
     757: aload         15
     759: getfield      #71                 // Field ObjectDef.anInt781:I
     762: iconst_1
     763: invokespecial #75                 // Method Animable_Sub5."<init>":(IIIIIIIIZ)V
     766: astore        18
     768: aload_0
     769: getstatic     #93                 // Field anIntArray140:[I
     772: iload_1
     773: iaload
     774: aload         18
     776: checkcast     #76                 // class Animable
     779: checkcast     #76                 // class Animable
     782: iload         16
     784: iload_2
     785: iload         17
     787: iload         7
     789: aconst_null
     790: iload         14
     792: iconst_0
     793: iload         9
     795: invokevirtual #88                 // Method WorldController.method282:(ILAnimable;IIBILAnimable;III)V
     798: aload         15
     800: getfield      #78                 // Field ObjectDef.aBoolean767:Z
     803: ifeq          821
     806: aload         5
     808: iload_2
     809: iload_1
     810: iload         7
     812: iload_3
     813: aload         15
     815: getfield      #85                 // Field ObjectDef.aBoolean757:Z
     818: invokevirtual #90                 // Method Class11.method211:(IIIIZ)V
     821: return
     822: iload_3
     823: iconst_2
     824: if_icmpne     1016
     827: iload_1
     828: iconst_1
     829: iadd
     830: iconst_3
     831: iand
     832: istore        18
     834: aload         15
     836: getfield      #71                 // Field ObjectDef.anInt781:I
     839: iconst_m1
     840: if_icmpne     893
     843: aload         15
     845: getfield      #72                 // Field ObjectDef.childrenIDs:[I
     848: ifnonnull     893
     851: aload         15
     853: iconst_2
     854: iconst_4
     855: iload_1
     856: iadd
     857: iload         10
     859: iload         11
     861: iload         12
     863: iload         13
     865: iconst_m1
     866: invokevirtual #73                 // Method ObjectDef.method578:(IIIIIII)LModel;
     869: astore        19
     871: aload         15
     873: iconst_2
     874: iload         18
     876: iload         10
     878: iload         11
     880: iload         12
     882: iload         13
     884: iconst_m1
     885: invokevirtual #73                 // Method ObjectDef.method578:(IIIIIII)LModel;
     888: astore        20
     890: goto          950
     893: new           #74                 // class Animable_Sub5
     896: dup
     897: iload         8
     899: iconst_4
     900: iload_1
     901: iadd
     902: iconst_2
     903: iload         11
     905: iload         12
     907: iload         10
     909: iload         13
     911: aload         15
     913: getfield      #71                 // Field ObjectDef.anInt781:I
     916: iconst_1
     917: invokespecial #75                 // Method Animable_Sub5."<init>":(IIIIIIIIZ)V
     920: astore        19
     922: new           #74                 // class Animable_Sub5
     925: dup
     926: iload         8
     928: iload         18
     930: iconst_2
     931: iload         11
     933: iload         12
     935: iload         10
     937: iload         13
     939: aload         15
     941: getfield      #71                 // Field ObjectDef.anInt781:I
     944: iconst_1
     945: invokespecial #75                 // Method Animable_Sub5."<init>":(IIIIIIIIZ)V
     948: astore        20
     950: aload_0
     951: getstatic     #87                 // Field anIntArray152:[I
     954: iload_1
     955: iaload
     956: aload         19
     958: checkcast     #76                 // class Animable
     961: checkcast     #76                 // class Animable
     964: iload         16
     966: iload_2
     967: iload         17
     969: iload         7
     971: aload         20
     973: checkcast     #76                 // class Animable
     976: checkcast     #76                 // class Animable
     979: iload         14
     981: getstatic     #87                 // Field anIntArray152:[I
     984: iload         18
     986: iaload
     987: iload         9
     989: invokevirtual #88                 // Method WorldController.method282:(ILAnimable;IIBILAnimable;III)V
     992: aload         15
     994: getfield      #78                 // Field ObjectDef.aBoolean767:Z
     997: ifeq          1015
    1000: aload         5
    1002: iload_2
    1003: iload_1
    1004: iload         7
    1006: iload_3
    1007: aload         15
    1009: getfield      #85                 // Field ObjectDef.aBoolean757:Z
    1012: invokevirtual #90                 // Method Class11.method211:(IIIIZ)V
    1015: return
    1016: iload_3
    1017: iconst_3
    1018: if_icmpne     1140
    1021: aload         15
    1023: getfield      #71                 // Field ObjectDef.anInt781:I
    1026: iconst_m1
    1027: if_icmpne     1059
    1030: aload         15
    1032: getfield      #72                 // Field ObjectDef.childrenIDs:[I
    1035: ifnonnull     1059
    1038: aload         15
    1040: iconst_3
    1041: iload_1
    1042: iload         10
    1044: iload         11
    1046: iload         12
    1048: iload         13
    1050: iconst_m1
    1051: invokevirtual #73                 // Method ObjectDef.method578:(IIIIIII)LModel;
    1054: astore        18
    1056: goto          1086
    1059: new           #74                 // class Animable_Sub5
    1062: dup
    1063: iload         8
    1065: iload_1
    1066: iconst_3
    1067: iload         11
    1069: iload         12
    1071: iload         10
    1073: iload         13
    1075: aload         15
    1077: getfield      #71                 // Field ObjectDef.anInt781:I
    1080: iconst_1
    1081: invokespecial #75                 // Method Animable_Sub5."<init>":(IIIIIIIIZ)V
    1084: astore        18
    1086: aload_0
    1087: getstatic     #93                 // Field anIntArray140:[I
    1090: iload_1
    1091: iaload
    1092: aload         18
    1094: checkcast     #76                 // class Animable
    1097: checkcast     #76                 // class Animable
    1100: iload         16
    1102: iload_2
    1103: iload         17
    1105: iload         7
    1107: aconst_null
    1108: iload         14
    1110: iconst_0
    1111: iload         9
    1113: invokevirtual #88                 // Method WorldController.method282:(ILAnimable;IIBILAnimable;III)V
    1116: aload         15
    1118: getfield      #78                 // Field ObjectDef.aBoolean767:Z
    1121: ifeq          1139
    1124: aload         5
    1126: iload_2
    1127: iload_1
    1128: iload         7
    1130: iload_3
    1131: aload         15
    1133: getfield      #85                 // Field ObjectDef.aBoolean757:Z
    1136: invokevirtual #90                 // Method Class11.method211:(IIIIZ)V
    1139: return
    1140: iload_3
    1141: bipush        9
    1143: if_icmpne     1271
    1146: aload         15
    1148: getfield      #71                 // Field ObjectDef.anInt781:I
    1151: iconst_m1
    1152: if_icmpne     1184
    1155: aload         15
    1157: getfield      #72                 // Field ObjectDef.childrenIDs:[I
    1160: ifnonnull     1184
    1163: aload         15
    1165: iload_3
    1166: iload_1
    1167: iload         10
    1169: iload         11
    1171: iload         12
    1173: iload         13
    1175: iconst_m1
    1176: invokevirtual #73                 // Method ObjectDef.method578:(IIIIIII)LModel;
    1179: astore        18
    1181: goto          1211
    1184: new           #74                 // class Animable_Sub5
    1187: dup
    1188: iload         8
    1190: iload_1
    1191: iload_3
    1192: iload         11
    1194: iload         12
    1196: iload         10
    1198: iload         13
    1200: aload         15
    1202: getfield      #71                 // Field ObjectDef.anInt781:I
    1205: iconst_1
    1206: invokespecial #75                 // Method Animable_Sub5."<init>":(IIIIIIIIZ)V
    1209: astore        18
    1211: aload_0
    1212: iload         16
    1214: iload         17
    1216: iload         14
    1218: iconst_1
    1219: aload         18
    1221: checkcast     #76                 // class Animable
    1224: checkcast     #76                 // class Animable
    1227: iconst_1
    1228: iload         9
    1230: iconst_0
    1231: iload_2
    1232: iload         7
    1234: invokevirtual #81                 // Method WorldController.method284:(IBIILAnimable;IIIII)Z
    1237: pop
    1238: aload         15
    1240: getfield      #78                 // Field ObjectDef.aBoolean767:Z
    1243: ifeq          1270
    1246: aload         5
    1248: aload         15
    1250: getfield      #85                 // Field ObjectDef.aBoolean757:Z
    1253: aload         15
    1255: getfield      #80                 // Field ObjectDef.anInt744:I
    1258: aload         15
    1260: getfield      #79                 // Field ObjectDef.anInt761:I
    1263: iload         7
    1265: iload_2
    1266: iload_1
    1267: invokevirtual #86                 // Method Class11.method212:(ZIIIII)V
    1270: return
    1271: aload         15
    1273: getfield      #94                 // Field ObjectDef.aBoolean762:Z
    1276: ifeq          1364
    1279: iload_1
    1280: iconst_1
    1281: if_icmpne     1307
    1284: iload         13
    1286: istore        18
    1288: iload         12
    1290: istore        13
    1292: iload         11
    1294: istore        12
    1296: iload         10
    1298: istore        11
    1300: iload         18
    1302: istore        10
    1304: goto          1364
    1307: iload_1
    1308: iconst_2
    1309: if_icmpne     1339
    1312: iload         13
    1314: istore        18
    1316: iload         11
    1318: istore        13
    1320: iload         18
    1322: istore        11
    1324: iload         12
    1326: istore        18
    1328: iload         10
    1330: istore        12
    1332: iload         18
    1334: istore        10
    1336: goto          1364
    1339: iload_1
    1340: iconst_3
    1341: if_icmpne     1364
    1344: iload         13
    1346: istore        18
    1348: iload         10
    1350: istore        13
    1352: iload         11
    1354: istore        10
    1356: iload         12
    1358: istore        11
    1360: iload         18
    1362: istore        12
    1364: iload_3
    1365: iconst_4
    1366: if_icmpne     1470
    1369: aload         15
    1371: getfield      #71                 // Field ObjectDef.anInt781:I
    1374: iconst_m1
    1375: if_icmpne     1407
    1378: aload         15
    1380: getfield      #72                 // Field ObjectDef.childrenIDs:[I
    1383: ifnonnull     1407
    1386: aload         15
    1388: iconst_4
    1389: iconst_0
    1390: iload         10
    1392: iload         11
    1394: iload         12
    1396: iload         13
    1398: iconst_m1
    1399: invokevirtual #73                 // Method ObjectDef.method578:(IIIIIII)LModel;
    1402: astore        18
    1404: goto          1434
    1407: new           #74                 // class Animable_Sub5
    1410: dup
    1411: iload         8
    1413: iconst_0
    1414: iconst_4
    1415: iload         11
    1417: iload         12
    1419: iload         10
    1421: iload         13
    1423: aload         15
    1425: getfield      #71                 // Field ObjectDef.anInt781:I
    1428: iconst_1
    1429: invokespecial #75                 // Method Animable_Sub5."<init>":(IIIIIIIIZ)V
    1432: astore        18
    1434: aload_0
    1435: iload         16
    1437: iload_2
    1438: iload_1
    1439: sipush        512
    1442: imul
    1443: iload         9
    1445: iconst_0
    1446: iload         14
    1448: aload         18
    1450: checkcast     #76                 // class Animable
    1453: checkcast     #76                 // class Animable
    1456: iload         7
    1458: iload         17
    1460: iconst_0
    1461: getstatic     #87                 // Field anIntArray152:[I
    1464: iload_1
    1465: iaload
    1466: invokevirtual #95                 // Method WorldController.method283:(IIIIIILAnimable;IBII)V
    1469: return
    1470: iload_3
    1471: iconst_5
    1472: if_icmpne     1627
    1475: bipush        16
    1477: istore        18
    1479: aload_0
    1480: iload         9
    1482: iload         7
    1484: iload_2
    1485: invokevirtual #96                 // Method WorldController.method300:(III)I
    1488: istore        19
    1490: iload         19
    1492: ifle          1512
    1495: iload         19
    1497: bipush        14
    1499: ishr
    1500: sipush        32767
    1503: iand
    1504: invokestatic  #64                 // Method ObjectDef.forID:(I)LObjectDef;
    1507: getfield      #91                 // Field ObjectDef.anInt775:I
    1510: istore        18
    1512: aload         15
    1514: getfield      #71                 // Field ObjectDef.anInt781:I
    1517: iconst_m1
    1518: if_icmpne     1550
    1521: aload         15
    1523: getfield      #72                 // Field ObjectDef.childrenIDs:[I
    1526: ifnonnull     1550
    1529: aload         15
    1531: iconst_4
    1532: iconst_0
    1533: iload         10
    1535: iload         11
    1537: iload         12
    1539: iload         13
    1541: iconst_m1
    1542: invokevirtual #73                 // Method ObjectDef.method578:(IIIIIII)LModel;
    1545: astore        20
    1547: goto          1577
    1550: new           #74                 // class Animable_Sub5
    1553: dup
    1554: iload         8
    1556: iconst_0
    1557: iconst_4
    1558: iload         11
    1560: iload         12
    1562: iload         10
    1564: iload         13
    1566: aload         15
    1568: getfield      #71                 // Field ObjectDef.anInt781:I
    1571: iconst_1
    1572: invokespecial #75                 // Method Animable_Sub5."<init>":(IIIIIIIIZ)V
    1575: astore        20
    1577: aload_0
    1578: iload         16
    1580: iload_2
    1581: iload_1
    1582: sipush        512
    1585: imul
    1586: iload         9
    1588: getstatic     #97                 // Field anIntArray137:[I
    1591: iload_1
    1592: iaload
    1593: iload         18
    1595: imul
    1596: iload         14
    1598: aload         20
    1600: checkcast     #76                 // class Animable
    1603: checkcast     #76                 // class Animable
    1606: iload         7
    1608: iload         17
    1610: getstatic     #98                 // Field anIntArray144:[I
    1613: iload_1
    1614: iaload
    1615: iload         18
    1617: imul
    1618: getstatic     #87                 // Field anIntArray152:[I
    1621: iload_1
    1622: iaload
    1623: invokevirtual #95                 // Method WorldController.method283:(IIIIIILAnimable;IBII)V
    1626: return
    1627: iload_3
    1628: bipush        6
    1630: if_icmpne     1728
    1633: aload         15
    1635: getfield      #71                 // Field ObjectDef.anInt781:I
    1638: iconst_m1
    1639: if_icmpne     1671
    1642: aload         15
    1644: getfield      #72                 // Field ObjectDef.childrenIDs:[I
    1647: ifnonnull     1671
    1650: aload         15
    1652: iconst_4
    1653: iconst_0
    1654: iload         10
    1656: iload         11
    1658: iload         12
    1660: iload         13
    1662: iconst_m1
    1663: invokevirtual #73                 // Method ObjectDef.method578:(IIIIIII)LModel;
    1666: astore        18
    1668: goto          1698
    1671: new           #74                 // class Animable_Sub5
    1674: dup
    1675: iload         8
    1677: iconst_0
    1678: iconst_4
    1679: iload         11
    1681: iload         12
    1683: iload         10
    1685: iload         13
    1687: aload         15
    1689: getfield      #71                 // Field ObjectDef.anInt781:I
    1692: iconst_1
    1693: invokespecial #75                 // Method Animable_Sub5."<init>":(IIIIIIIIZ)V
    1696: astore        18
    1698: aload_0
    1699: iload         16
    1701: iload_2
    1702: iload_1
    1703: iload         9
    1705: iconst_0
    1706: iload         14
    1708: aload         18
    1710: checkcast     #76                 // class Animable
    1713: checkcast     #76                 // class Animable
    1716: iload         7
    1718: iload         17
    1720: iconst_0
    1721: sipush        256
    1724: invokevirtual #95                 // Method WorldController.method283:(IIIIIILAnimable;IBII)V
    1727: return
    1728: iload_3
    1729: bipush        7
    1731: if_icmpne     1829
    1734: aload         15
    1736: getfield      #71                 // Field ObjectDef.anInt781:I
    1739: iconst_m1
    1740: if_icmpne     1772
    1743: aload         15
    1745: getfield      #72                 // Field ObjectDef.childrenIDs:[I
    1748: ifnonnull     1772
    1751: aload         15
    1753: iconst_4
    1754: iconst_0
    1755: iload         10
    1757: iload         11
    1759: iload         12
    1761: iload         13
    1763: iconst_m1
    1764: invokevirtual #73                 // Method ObjectDef.method578:(IIIIIII)LModel;
    1767: astore        18
    1769: goto          1799
    1772: new           #74                 // class Animable_Sub5
    1775: dup
    1776: iload         8
    1778: iconst_0
    1779: iconst_4
    1780: iload         11
    1782: iload         12
    1784: iload         10
    1786: iload         13
    1788: aload         15
    1790: getfield      #71                 // Field ObjectDef.anInt781:I
    1793: iconst_1
    1794: invokespecial #75                 // Method Animable_Sub5."<init>":(IIIIIIIIZ)V
    1797: astore        18
    1799: aload_0
    1800: iload         16
    1802: iload_2
    1803: iload_1
    1804: iload         9
    1806: iconst_0
    1807: iload         14
    1809: aload         18
    1811: checkcast     #76                 // class Animable
    1814: checkcast     #76                 // class Animable
    1817: iload         7
    1819: iload         17
    1821: iconst_0
    1822: sipush        512
    1825: invokevirtual #95                 // Method WorldController.method283:(IIIIIILAnimable;IBII)V
    1828: return
    1829: iload_3
    1830: bipush        8
    1832: if_icmpne     1929
    1835: aload         15
    1837: getfield      #71                 // Field ObjectDef.anInt781:I
    1840: iconst_m1
    1841: if_icmpne     1873
    1844: aload         15
    1846: getfield      #72                 // Field ObjectDef.childrenIDs:[I
    1849: ifnonnull     1873
    1852: aload         15
    1854: iconst_4
    1855: iconst_0
    1856: iload         10
    1858: iload         11
    1860: iload         12
    1862: iload         13
    1864: iconst_m1
    1865: invokevirtual #73                 // Method ObjectDef.method578:(IIIIIII)LModel;
    1868: astore        18
    1870: goto          1900
    1873: new           #74                 // class Animable_Sub5
    1876: dup
    1877: iload         8
    1879: iconst_0
    1880: iconst_4
    1881: iload         11
    1883: iload         12
    1885: iload         10
    1887: iload         13
    1889: aload         15
    1891: getfield      #71                 // Field ObjectDef.anInt781:I
    1894: iconst_1
    1895: invokespecial #75                 // Method Animable_Sub5."<init>":(IIIIIIIIZ)V
    1898: astore        18
    1900: aload_0
    1901: iload         16
    1903: iload_2
    1904: iload_1
    1905: iload         9
    1907: iconst_0
    1908: iload         14
    1910: aload         18
    1912: checkcast     #76                 // class Animable
    1915: checkcast     #76                 // class Animable
    1918: iload         7
    1920: iload         17
    1922: iconst_0
    1923: sipush        768
    1926: invokevirtual #95                 // Method WorldController.method283:(IIIIIILAnimable;IBII)V
    1929: return

  public static boolean method189(int, byte[], int);
    Code:
       0: iconst_1
       1: istore_3
       2: new           #104                // class Stream
       5: dup
       6: aload_1
       7: invokespecial #105                // Method Stream."<init>":([B)V
      10: astore        4
      12: iconst_m1
      13: istore        5
      15: aload         4
      17: invokevirtual #63                 // Method Stream.method422:()I
      20: istore        6
      22: iload         6
      24: ifne          30
      27: goto          211
      30: iload         5
      32: iload         6
      34: iadd
      35: istore        5
      37: iconst_0
      38: istore        7
      40: iconst_0
      41: istore        8
      43: iload         8
      45: ifeq          72
      48: aload         4
      50: invokevirtual #63                 // Method Stream.method422:()I
      53: istore        9
      55: iload         9
      57: ifne          63
      60: goto          208
      63: aload         4
      65: invokevirtual #66                 // Method Stream.readUnsignedByte:()I
      68: pop
      69: goto          43
      72: aload         4
      74: invokevirtual #63                 // Method Stream.method422:()I
      77: istore        9
      79: iload         9
      81: ifne          87
      84: goto          208
      87: iload         7
      89: iload         9
      91: iconst_1
      92: isub
      93: iadd
      94: istore        7
      96: iload         7
      98: bipush        63
     100: iand
     101: istore        10
     103: iload         7
     105: bipush        6
     107: ishr
     108: bipush        63
     110: iand
     111: istore        11
     113: aload         4
     115: invokevirtual #66                 // Method Stream.readUnsignedByte:()I
     118: iconst_2
     119: ishr
     120: istore        12
     122: iload         11
     124: iload_0
     125: iadd
     126: istore        13
     128: iload         10
     130: iload_2
     131: iadd
     132: istore        14
     134: iload         13
     136: ifle          205
     139: iload         14
     141: ifle          205
     144: iload         13
     146: bipush        103
     148: if_icmpge     205
     151: iload         14
     153: bipush        103
     155: if_icmpge     205
     158: iload         5
     160: invokestatic  #64                 // Method ObjectDef.forID:(I)LObjectDef;
     163: astore        15
     165: iload         12
     167: bipush        22
     169: if_icmpne     194
     172: getstatic     #38                 // Field lowMem:Z
     175: ifeq          194
     178: aload         15
     180: getfield      #68                 // Field ObjectDef.hasActions:Z
     183: ifne          194
     186: aload         15
     188: getfield      #70                 // Field ObjectDef.aBoolean736:Z
     191: ifeq          205
     194: iload_3
     195: aload         15
     197: invokevirtual #120                // Method ObjectDef.method579:()Z
     200: iand
     201: istore_3
     202: iconst_1
     203: istore        8
     205: goto          43
     208: goto          15
     211: iload_3
     212: ireturn

  public final void method190(int, Class11[], int, WorldController, byte[]);
    Code:
       0: new           #104                // class Stream
       3: dup
       4: aload         5
       6: invokespecial #105                // Method Stream."<init>":([B)V
       9: astore        6
      11: iconst_m1
      12: istore        7
      14: aload         6
      16: invokevirtual #63                 // Method Stream.method422:()I
      19: istore        8
      21: iload         8
      23: ifne          29
      26: goto          207
      29: iload         7
      31: iload         8
      33: iadd
      34: istore        7
      36: iconst_0
      37: istore        9
      39: aload         6
      41: invokevirtual #63                 // Method Stream.method422:()I
      44: istore        10
      46: iload         10
      48: ifne          54
      51: goto          204
      54: iload         9
      56: iload         10
      58: iconst_1
      59: isub
      60: iadd
      61: istore        9
      63: iload         9
      65: bipush        63
      67: iand
      68: istore        11
      70: iload         9
      72: bipush        6
      74: ishr
      75: bipush        63
      77: iand
      78: istore        12
      80: iload         9
      82: bipush        12
      84: ishr
      85: istore        13
      87: aload         6
      89: invokevirtual #66                 // Method Stream.readUnsignedByte:()I
      92: istore        14
      94: iload         14
      96: iconst_2
      97: ishr
      98: istore        15
     100: iload         14
     102: iconst_3
     103: iand
     104: istore        16
     106: iload         12
     108: iload_1
     109: iadd
     110: istore        17
     112: iload         11
     114: iload_3
     115: iadd
     116: istore        18
     118: iload         17
     120: ifle          201
     123: iload         18
     125: ifle          201
     128: iload         17
     130: bipush        103
     132: if_icmpge     201
     135: iload         18
     137: bipush        103
     139: if_icmpge     201
     142: iload         13
     144: istore        19
     146: aload_0
     147: getfield      #6                  // Field aByteArrayArrayArray149:[[[B
     150: iconst_1
     151: aaload
     152: iload         17
     154: aaload
     155: iload         18
     157: baload
     158: iconst_2
     159: iand
     160: iconst_2
     161: if_icmpne     167
     164: iinc          19, -1
     167: aconst_null
     168: astore        20
     170: iload         19
     172: iflt          181
     175: aload_2
     176: iload         19
     178: aaload
     179: astore        20
     181: aload_0
     182: iload         18
     184: aload         4
     186: aload         20
     188: iload         15
     190: iload         13
     192: iload         17
     194: iload         7
     196: iload         16
     198: invokespecial #115                // Method method175:(ILWorldController;LClass11;IIIII)V
     201: goto          39
     204: goto          14
     207: return

  static {};
    Code:
       0: invokestatic  #27                 // Method java/lang/Math.random:()D
       3: ldc2_w        #121                // double 17.0d
       6: dmul
       7: d2i
       8: bipush        8
      10: isub
      11: putstatic     #26                 // Field anInt123:I
      14: invokestatic  #27                 // Method java/lang/Math.random:()D
      17: ldc2_w        #123                // double 33.0d
      20: dmul
      21: d2i
      22: bipush        16
      24: isub
      25: putstatic     #30                 // Field anInt133:I
      28: iconst_4
      29: newarray       int
      31: dup
      32: iconst_0
      33: iconst_1
      34: iastore
      35: dup
      36: iconst_1
      37: iconst_0
      38: iastore
      39: dup
      40: iconst_2
      41: iconst_m1
      42: iastore
      43: dup
      44: iconst_3
      45: iconst_0
      46: iastore
      47: putstatic     #97                 // Field anIntArray137:[I
      50: iconst_4
      51: newarray       int
      53: dup
      54: iconst_0
      55: bipush        16
      57: iastore
      58: dup
      59: iconst_1
      60: bipush        32
      62: iastore
      63: dup
      64: iconst_2
      65: bipush        64
      67: iastore
      68: dup
      69: iconst_3
      70: sipush        128
      73: iastore
      74: putstatic     #93                 // Field anIntArray140:[I
      77: iconst_4
      78: newarray       int
      80: dup
      81: iconst_0
      82: iconst_0
      83: iastore
      84: dup
      85: iconst_1
      86: iconst_m1
      87: iastore
      88: dup
      89: iconst_2
      90: iconst_0
      91: iastore
      92: dup
      93: iconst_3
      94: iconst_1
      95: iastore
      96: putstatic     #98                 // Field anIntArray144:[I
      99: bipush        99
     101: putstatic     #2                  // Field anInt145:I
     104: iconst_1
     105: putstatic     #38                 // Field lowMem:Z
     108: iconst_4
     109: newarray       int
     111: dup
     112: iconst_0
     113: iconst_1
     114: iastore
     115: dup
     116: iconst_1
     117: iconst_2
     118: iastore
     119: dup
     120: iconst_2
     121: iconst_4
     122: iastore
     123: dup
     124: iconst_3
     125: bipush        8
     127: iastore
     128: putstatic     #87                 // Field anIntArray152:[I
     131: return
}
