Compiled from "RSApplet.java"
public class RSApplet extends java.applet.Applet implements java.lang.Runnable,java.awt.event.MouseListener,java.awt.event.MouseMotionListener,java.awt.event.KeyListener,java.awt.event.FocusListener,java.awt.event.WindowListener {
  private int anInt4;

  private int delayTime;

  int minDelay;

  private final long[] aLongArray7;

  int fps;

  boolean shouldDebug;

  int myWidth;

  int myHeight;

  java.awt.Graphics graphics;

  RSImageProducer fullGameScreen;

  RSFrame gameFrame;

  private boolean shouldClearScreen;

  boolean awtFocus;

  int idleTime;

  int clickMode2;

  public int mouseX;

  public int mouseY;

  private int clickMode1;

  private int clickX;

  private int clickY;

  private long clickTime;

  int clickMode3;

  int saveClickX;

  int saveClickY;

  long aLong29;

  final int[] keyArray;

  private final int[] charQueue;

  private int readIndex;

  private int writeIndex;

  public static int anInt34;

  final void createClientFrame(int, int);
    Code:
       0: aload_0
       1: iload_2
       2: putfield      #1                  // Field myWidth:I
       5: aload_0
       6: iload_1
       7: putfield      #2                  // Field myHeight:I
      10: aload_0
      11: new           #3                  // class RSFrame
      14: dup
      15: aload_0
      16: aload_0
      17: getfield      #1                  // Field myWidth:I
      20: aload_0
      21: getfield      #2                  // Field myHeight:I
      24: invokespecial #4                  // Method RSFrame."<init>":(LRSApplet;II)V
      27: putfield      #5                  // Field gameFrame:LRSFrame;
      30: aload_0
      31: aload_0
      32: invokevirtual #6                  // Method getGameComponent:()Ljava/awt/Component;
      35: invokevirtual #7                  // Method java/awt/Component.getGraphics:()Ljava/awt/Graphics;
      38: putfield      #8                  // Field graphics:Ljava/awt/Graphics;
      41: aload_0
      42: new           #9                  // class RSImageProducer
      45: dup
      46: aload_0
      47: getfield      #1                  // Field myWidth:I
      50: aload_0
      51: getfield      #2                  // Field myHeight:I
      54: aload_0
      55: invokevirtual #6                  // Method getGameComponent:()Ljava/awt/Component;
      58: invokespecial #10                 // Method RSImageProducer."<init>":(IILjava/awt/Component;)V
      61: putfield      #11                 // Field fullGameScreen:LRSImageProducer;
      64: aload_0
      65: aload_0
      66: iconst_1
      67: invokevirtual #12                 // Method startRunnable:(Ljava/lang/Runnable;I)V
      70: return

  final void initClientFrame(int, int);
    Code:
       0: aload_0
       1: iload_2
       2: putfield      #1                  // Field myWidth:I
       5: aload_0
       6: iload_1
       7: putfield      #2                  // Field myHeight:I
      10: aload_0
      11: aload_0
      12: invokevirtual #6                  // Method getGameComponent:()Ljava/awt/Component;
      15: invokevirtual #7                  // Method java/awt/Component.getGraphics:()Ljava/awt/Graphics;
      18: putfield      #8                  // Field graphics:Ljava/awt/Graphics;
      21: aload_0
      22: new           #9                  // class RSImageProducer
      25: dup
      26: aload_0
      27: getfield      #1                  // Field myWidth:I
      30: aload_0
      31: getfield      #2                  // Field myHeight:I
      34: aload_0
      35: invokevirtual #6                  // Method getGameComponent:()Ljava/awt/Component;
      38: invokespecial #10                 // Method RSImageProducer."<init>":(IILjava/awt/Component;)V
      41: putfield      #11                 // Field fullGameScreen:LRSImageProducer;
      44: aload_0
      45: aload_0
      46: iconst_1
      47: invokevirtual #12                 // Method startRunnable:(Ljava/lang/Runnable;I)V
      50: return

  public void run();
    Code:
       0: aload_0
       1: invokevirtual #6                  // Method getGameComponent:()Ljava/awt/Component;
       4: aload_0
       5: invokevirtual #13                 // Method java/awt/Component.addMouseListener:(Ljava/awt/event/MouseListener;)V
       8: aload_0
       9: invokevirtual #6                  // Method getGameComponent:()Ljava/awt/Component;
      12: aload_0
      13: invokevirtual #14                 // Method java/awt/Component.addMouseMotionListener:(Ljava/awt/event/MouseMotionListener;)V
      16: aload_0
      17: invokevirtual #6                  // Method getGameComponent:()Ljava/awt/Component;
      20: aload_0
      21: invokevirtual #15                 // Method java/awt/Component.addKeyListener:(Ljava/awt/event/KeyListener;)V
      24: aload_0
      25: invokevirtual #6                  // Method getGameComponent:()Ljava/awt/Component;
      28: aload_0
      29: invokevirtual #16                 // Method java/awt/Component.addFocusListener:(Ljava/awt/event/FocusListener;)V
      32: aload_0
      33: getfield      #5                  // Field gameFrame:LRSFrame;
      36: ifnull        47
      39: aload_0
      40: getfield      #5                  // Field gameFrame:LRSFrame;
      43: aload_0
      44: invokevirtual #17                 // Method RSFrame.addWindowListener:(Ljava/awt/event/WindowListener;)V
      47: aload_0
      48: iconst_0
      49: ldc           #18                 // String Loading...
      51: invokevirtual #19                 // Method drawLoadingText:(ILjava/lang/String;)V
      54: aload_0
      55: invokevirtual #20                 // Method startUp:()V
      58: iconst_0
      59: istore_1
      60: sipush        256
      63: istore_2
      64: iconst_1
      65: istore_3
      66: iconst_0
      67: istore        4
      69: iconst_0
      70: istore        5
      72: iconst_0
      73: istore        6
      75: iload         6
      77: bipush        10
      79: if_icmpge     98
      82: aload_0
      83: getfield      #21                 // Field aLongArray7:[J
      86: iload         6
      88: invokestatic  #22                 // Method java/lang/System.currentTimeMillis:()J
      91: lastore
      92: iinc          6, 1
      95: goto          75
      98: invokestatic  #22                 // Method java/lang/System.currentTimeMillis:()J
     101: lstore        6
     103: aload_0
     104: getfield      #23                 // Field anInt4:I
     107: iflt          698
     110: aload_0
     111: getfield      #23                 // Field anInt4:I
     114: ifle          139
     117: aload_0
     118: dup
     119: getfield      #23                 // Field anInt4:I
     122: iconst_1
     123: isub
     124: putfield      #23                 // Field anInt4:I
     127: aload_0
     128: getfield      #23                 // Field anInt4:I
     131: ifne          139
     134: aload_0
     135: invokespecial #24                 // Method exit:()V
     138: return
     139: iload_2
     140: istore        8
     142: iload_3
     143: istore        9
     145: sipush        300
     148: istore_2
     149: iconst_1
     150: istore_3
     151: invokestatic  #22                 // Method java/lang/System.currentTimeMillis:()J
     154: lstore        10
     156: aload_0
     157: getfield      #21                 // Field aLongArray7:[J
     160: iload_1
     161: laload
     162: lconst_0
     163: lcmp
     164: ifne          176
     167: iload         8
     169: istore_2
     170: iload         9
     172: istore_3
     173: goto          209
     176: lload         10
     178: aload_0
     179: getfield      #21                 // Field aLongArray7:[J
     182: iload_1
     183: laload
     184: lcmp
     185: ifle          209
     188: sipush        2560
     191: aload_0
     192: getfield      #25                 // Field delayTime:I
     195: imul
     196: i2l
     197: lload         10
     199: aload_0
     200: getfield      #21                 // Field aLongArray7:[J
     203: iload_1
     204: laload
     205: lsub
     206: ldiv
     207: l2i
     208: istore_2
     209: iload_2
     210: bipush        25
     212: if_icmpge     218
     215: bipush        25
     217: istore_2
     218: iload_2
     219: sipush        256
     222: if_icmple     250
     225: sipush        256
     228: istore_2
     229: aload_0
     230: getfield      #25                 // Field delayTime:I
     233: i2l
     234: lload         10
     236: aload_0
     237: getfield      #21                 // Field aLongArray7:[J
     240: iload_1
     241: laload
     242: lsub
     243: ldc2_w        #26                 // long 10l
     246: ldiv
     247: lsub
     248: l2i
     249: istore_3
     250: iload_3
     251: aload_0
     252: getfield      #25                 // Field delayTime:I
     255: if_icmple     263
     258: aload_0
     259: getfield      #25                 // Field delayTime:I
     262: istore_3
     263: aload_0
     264: getfield      #21                 // Field aLongArray7:[J
     267: iload_1
     268: lload         10
     270: lastore
     271: iload_1
     272: iconst_1
     273: iadd
     274: bipush        10
     276: irem
     277: istore_1
     278: iload_3
     279: iconst_1
     280: if_icmple     323
     283: iconst_0
     284: istore        12
     286: iload         12
     288: bipush        10
     290: if_icmpge     323
     293: aload_0
     294: getfield      #21                 // Field aLongArray7:[J
     297: iload         12
     299: laload
     300: lconst_0
     301: lcmp
     302: ifeq          317
     305: aload_0
     306: getfield      #21                 // Field aLongArray7:[J
     309: iload         12
     311: dup2
     312: laload
     313: iload_3
     314: i2l
     315: ladd
     316: lastore
     317: iinc          12, 1
     320: goto          286
     323: iload_3
     324: aload_0
     325: getfield      #28                 // Field minDelay:I
     328: if_icmpge     336
     331: aload_0
     332: getfield      #28                 // Field minDelay:I
     335: istore_3
     336: iload_3
     337: i2l
     338: invokestatic  #29                 // Method java/lang/Thread.sleep:(J)V
     341: goto          349
     344: astore        12
     346: iinc          5, 1
     349: iload         4
     351: sipush        256
     354: if_icmpge     415
     357: aload_0
     358: aload_0
     359: getfield      #31                 // Field clickMode1:I
     362: putfield      #32                 // Field clickMode3:I
     365: aload_0
     366: aload_0
     367: getfield      #33                 // Field clickX:I
     370: putfield      #34                 // Field saveClickX:I
     373: aload_0
     374: aload_0
     375: getfield      #35                 // Field clickY:I
     378: putfield      #36                 // Field saveClickY:I
     381: aload_0
     382: aload_0
     383: getfield      #37                 // Field clickTime:J
     386: putfield      #38                 // Field aLong29:J
     389: aload_0
     390: iconst_0
     391: putfield      #31                 // Field clickMode1:I
     394: aload_0
     395: invokevirtual #39                 // Method processGameLoop:()V
     398: aload_0
     399: aload_0
     400: getfield      #40                 // Field writeIndex:I
     403: putfield      #41                 // Field readIndex:I
     406: iload         4
     408: iload_2
     409: iadd
     410: istore        4
     412: goto          349
     415: iload         4
     417: sipush        255
     420: iand
     421: istore        4
     423: aload_0
     424: getfield      #25                 // Field delayTime:I
     427: ifle          448
     430: aload_0
     431: sipush        1000
     434: iload_2
     435: imul
     436: aload_0
     437: getfield      #25                 // Field delayTime:I
     440: sipush        256
     443: imul
     444: idiv
     445: putfield      #42                 // Field fps:I
     448: aload_0
     449: invokevirtual #43                 // Method processDrawing:()V
     452: aload_0
     453: getfield      #44                 // Field shouldDebug:Z
     456: ifeq          695
     459: getstatic     #45                 // Field java/lang/System.out:Ljava/io/PrintStream;
     462: new           #46                 // class java/lang/StringBuilder
     465: dup
     466: invokespecial #47                 // Method java/lang/StringBuilder."<init>":()V
     469: ldc           #48                 // String ntime:
     471: invokevirtual #49                 // Method java/lang/StringBuilder.append:(Ljava/lang/String;)Ljava/lang/StringBuilder;
     474: lload         10
     476: invokevirtual #50                 // Method java/lang/StringBuilder.append:(J)Ljava/lang/StringBuilder;
     479: invokevirtual #51                 // Method java/lang/StringBuilder.toString:()Ljava/lang/String;
     482: invokevirtual #52                 // Method java/io/PrintStream.println:(Ljava/lang/String;)V
     485: iconst_0
     486: istore        12
     488: iload         12
     490: bipush        10
     492: if_icmpge     556
     495: iload_1
     496: iload         12
     498: isub
     499: iconst_1
     500: isub
     501: bipush        20
     503: iadd
     504: bipush        10
     506: irem
     507: istore        13
     509: getstatic     #45                 // Field java/lang/System.out:Ljava/io/PrintStream;
     512: new           #46                 // class java/lang/StringBuilder
     515: dup
     516: invokespecial #47                 // Method java/lang/StringBuilder."<init>":()V
     519: ldc           #53                 // String otim
     521: invokevirtual #49                 // Method java/lang/StringBuilder.append:(Ljava/lang/String;)Ljava/lang/StringBuilder;
     524: iload         13
     526: invokevirtual #54                 // Method java/lang/StringBuilder.append:(I)Ljava/lang/StringBuilder;
     529: ldc           #55                 // String :
     531: invokevirtual #49                 // Method java/lang/StringBuilder.append:(Ljava/lang/String;)Ljava/lang/StringBuilder;
     534: aload_0
     535: getfield      #21                 // Field aLongArray7:[J
     538: iload         13
     540: laload
     541: invokevirtual #50                 // Method java/lang/StringBuilder.append:(J)Ljava/lang/StringBuilder;
     544: invokevirtual #51                 // Method java/lang/StringBuilder.toString:()Ljava/lang/String;
     547: invokevirtual #52                 // Method java/io/PrintStream.println:(Ljava/lang/String;)V
     550: iinc          12, 1
     553: goto          488
     556: getstatic     #45                 // Field java/lang/System.out:Ljava/io/PrintStream;
     559: new           #46                 // class java/lang/StringBuilder
     562: dup
     563: invokespecial #47                 // Method java/lang/StringBuilder."<init>":()V
     566: ldc           #56                 // String fps:
     568: invokevirtual #49                 // Method java/lang/StringBuilder.append:(Ljava/lang/String;)Ljava/lang/StringBuilder;
     571: aload_0
     572: getfield      #42                 // Field fps:I
     575: invokevirtual #54                 // Method java/lang/StringBuilder.append:(I)Ljava/lang/StringBuilder;
     578: ldc           #57                 // String  ratio:
     580: invokevirtual #49                 // Method java/lang/StringBuilder.append:(Ljava/lang/String;)Ljava/lang/StringBuilder;
     583: iload_2
     584: invokevirtual #54                 // Method java/lang/StringBuilder.append:(I)Ljava/lang/StringBuilder;
     587: ldc           #58                 // String  count:
     589: invokevirtual #49                 // Method java/lang/StringBuilder.append:(Ljava/lang/String;)Ljava/lang/StringBuilder;
     592: iload         4
     594: invokevirtual #54                 // Method java/lang/StringBuilder.append:(I)Ljava/lang/StringBuilder;
     597: invokevirtual #51                 // Method java/lang/StringBuilder.toString:()Ljava/lang/String;
     600: invokevirtual #52                 // Method java/io/PrintStream.println:(Ljava/lang/String;)V
     603: getstatic     #45                 // Field java/lang/System.out:Ljava/io/PrintStream;
     606: new           #46                 // class java/lang/StringBuilder
     609: dup
     610: invokespecial #47                 // Method java/lang/StringBuilder."<init>":()V
     613: ldc           #59                 // String del:
     615: invokevirtual #49                 // Method java/lang/StringBuilder.append:(Ljava/lang/String;)Ljava/lang/StringBuilder;
     618: iload_3
     619: invokevirtual #54                 // Method java/lang/StringBuilder.append:(I)Ljava/lang/StringBuilder;
     622: ldc           #60                 // String  deltime:
     624: invokevirtual #49                 // Method java/lang/StringBuilder.append:(Ljava/lang/String;)Ljava/lang/StringBuilder;
     627: aload_0
     628: getfield      #25                 // Field delayTime:I
     631: invokevirtual #54                 // Method java/lang/StringBuilder.append:(I)Ljava/lang/StringBuilder;
     634: ldc           #61                 // String  mindel:
     636: invokevirtual #49                 // Method java/lang/StringBuilder.append:(Ljava/lang/String;)Ljava/lang/StringBuilder;
     639: aload_0
     640: getfield      #28                 // Field minDelay:I
     643: invokevirtual #54                 // Method java/lang/StringBuilder.append:(I)Ljava/lang/StringBuilder;
     646: invokevirtual #51                 // Method java/lang/StringBuilder.toString:()Ljava/lang/String;
     649: invokevirtual #52                 // Method java/io/PrintStream.println:(Ljava/lang/String;)V
     652: getstatic     #45                 // Field java/lang/System.out:Ljava/io/PrintStream;
     655: new           #46                 // class java/lang/StringBuilder
     658: dup
     659: invokespecial #47                 // Method java/lang/StringBuilder."<init>":()V
     662: ldc           #62                 // String intex:
     664: invokevirtual #49                 // Method java/lang/StringBuilder.append:(Ljava/lang/String;)Ljava/lang/StringBuilder;
     667: iload         5
     669: invokevirtual #54                 // Method java/lang/StringBuilder.append:(I)Ljava/lang/StringBuilder;
     672: ldc           #63                 // String  opos:
     674: invokevirtual #49                 // Method java/lang/StringBuilder.append:(Ljava/lang/String;)Ljava/lang/StringBuilder;
     677: iload_1
     678: invokevirtual #54                 // Method java/lang/StringBuilder.append:(I)Ljava/lang/StringBuilder;
     681: invokevirtual #51                 // Method java/lang/StringBuilder.toString:()Ljava/lang/String;
     684: invokevirtual #52                 // Method java/io/PrintStream.println:(Ljava/lang/String;)V
     687: aload_0
     688: iconst_0
     689: putfield      #44                 // Field shouldDebug:Z
     692: iconst_0
     693: istore        5
     695: goto          103
     698: aload_0
     699: getfield      #23                 // Field anInt4:I
     702: iconst_m1
     703: if_icmpne     710
     706: aload_0
     707: invokespecial #24                 // Method exit:()V
     710: return
    Exception table:
       from    to  target type
         336   341   344   Class java/lang/InterruptedException

  private void exit();
    Code:
       0: aload_0
       1: bipush        -2
       3: putfield      #23                 // Field anInt4:I
       6: aload_0
       7: invokevirtual #64                 // Method cleanUpForQuit:()V
      10: aload_0
      11: getfield      #5                  // Field gameFrame:LRSFrame;
      14: ifnull        35
      17: ldc2_w        #65                 // long 1000l
      20: invokestatic  #29                 // Method java/lang/Thread.sleep:(J)V
      23: goto          27
      26: astore_1
      27: iconst_0
      28: invokestatic  #68                 // Method java/lang/System.exit:(I)V
      31: goto          35
      34: astore_1
      35: return
    Exception table:
       from    to  target type
          17    23    26   Class java/lang/Exception
          27    31    34   Class java/lang/Throwable

  final void method4(int);
    Code:
       0: aload_0
       1: sipush        1000
       4: iload_1
       5: idiv
       6: putfield      #25                 // Field delayTime:I
       9: return

  public final void start();
    Code:
       0: aload_0
       1: getfield      #23                 // Field anInt4:I
       4: iflt          12
       7: aload_0
       8: iconst_0
       9: putfield      #23                 // Field anInt4:I
      12: return

  public final void stop();
    Code:
       0: aload_0
       1: getfield      #23                 // Field anInt4:I
       4: iflt          19
       7: aload_0
       8: sipush        4000
      11: aload_0
      12: getfield      #25                 // Field delayTime:I
      15: idiv
      16: putfield      #23                 // Field anInt4:I
      19: return

  public final void destroy();
    Code:
       0: aload_0
       1: iconst_m1
       2: putfield      #23                 // Field anInt4:I
       5: ldc2_w        #70                 // long 5000l
       8: invokestatic  #29                 // Method java/lang/Thread.sleep:(J)V
      11: goto          15
      14: astore_1
      15: aload_0
      16: getfield      #23                 // Field anInt4:I
      19: iconst_m1
      20: if_icmpne     27
      23: aload_0
      24: invokespecial #24                 // Method exit:()V
      27: return
    Exception table:
       from    to  target type
           5    11    14   Class java/lang/Exception

  public final void update(java.awt.Graphics);
    Code:
       0: aload_0
       1: getfield      #8                  // Field graphics:Ljava/awt/Graphics;
       4: ifnonnull     12
       7: aload_0
       8: aload_1
       9: putfield      #8                  // Field graphics:Ljava/awt/Graphics;
      12: aload_0
      13: iconst_1
      14: putfield      #72                 // Field shouldClearScreen:Z
      17: aload_0
      18: invokevirtual #73                 // Method raiseWelcomeScreen:()V
      21: return

  public final void paint(java.awt.Graphics);
    Code:
       0: aload_0
       1: getfield      #8                  // Field graphics:Ljava/awt/Graphics;
       4: ifnonnull     12
       7: aload_0
       8: aload_1
       9: putfield      #8                  // Field graphics:Ljava/awt/Graphics;
      12: aload_0
      13: iconst_1
      14: putfield      #72                 // Field shouldClearScreen:Z
      17: aload_0
      18: invokevirtual #73                 // Method raiseWelcomeScreen:()V
      21: return

  public final void mousePressed(java.awt.event.MouseEvent);
    Code:
       0: aload_1
       1: invokevirtual #74                 // Method java/awt/event/MouseEvent.getX:()I
       4: istore_2
       5: aload_1
       6: invokevirtual #75                 // Method java/awt/event/MouseEvent.getY:()I
       9: istore_3
      10: aload_0
      11: getfield      #5                  // Field gameFrame:LRSFrame;
      14: ifnull        23
      17: iinc          2, -4
      20: iinc          3, -22
      23: aload_0
      24: iconst_0
      25: putfield      #76                 // Field idleTime:I
      28: aload_0
      29: iload_2
      30: putfield      #33                 // Field clickX:I
      33: aload_0
      34: iload_3
      35: putfield      #35                 // Field clickY:I
      38: aload_0
      39: invokestatic  #22                 // Method java/lang/System.currentTimeMillis:()J
      42: putfield      #37                 // Field clickTime:J
      45: aload_1
      46: invokevirtual #77                 // Method java/awt/event/MouseEvent.isMetaDown:()Z
      49: ifeq          65
      52: aload_0
      53: iconst_2
      54: putfield      #31                 // Field clickMode1:I
      57: aload_0
      58: iconst_2
      59: putfield      #78                 // Field clickMode2:I
      62: goto          75
      65: aload_0
      66: iconst_1
      67: putfield      #31                 // Field clickMode1:I
      70: aload_0
      71: iconst_1
      72: putfield      #78                 // Field clickMode2:I
      75: return

  public final void mouseReleased(java.awt.event.MouseEvent);
    Code:
       0: aload_0
       1: iconst_0
       2: putfield      #76                 // Field idleTime:I
       5: aload_0
       6: iconst_0
       7: putfield      #78                 // Field clickMode2:I
      10: return

  public final void mouseClicked(java.awt.event.MouseEvent);
    Code:
       0: return

  public final void mouseEntered(java.awt.event.MouseEvent);
    Code:
       0: return

  public final void mouseExited(java.awt.event.MouseEvent);
    Code:
       0: aload_0
       1: iconst_0
       2: putfield      #76                 // Field idleTime:I
       5: aload_0
       6: iconst_m1
       7: putfield      #79                 // Field mouseX:I
      10: aload_0
      11: iconst_m1
      12: putfield      #80                 // Field mouseY:I
      15: return

  public final void mouseDragged(java.awt.event.MouseEvent);
    Code:
       0: aload_1
       1: invokevirtual #74                 // Method java/awt/event/MouseEvent.getX:()I
       4: istore_2
       5: aload_1
       6: invokevirtual #75                 // Method java/awt/event/MouseEvent.getY:()I
       9: istore_3
      10: aload_0
      11: getfield      #5                  // Field gameFrame:LRSFrame;
      14: ifnull        23
      17: iinc          2, -4
      20: iinc          3, -22
      23: aload_0
      24: iconst_0
      25: putfield      #76                 // Field idleTime:I
      28: aload_0
      29: iload_2
      30: putfield      #79                 // Field mouseX:I
      33: aload_0
      34: iload_3
      35: putfield      #80                 // Field mouseY:I
      38: return

  public final void mouseMoved(java.awt.event.MouseEvent);
    Code:
       0: aload_1
       1: invokevirtual #74                 // Method java/awt/event/MouseEvent.getX:()I
       4: istore_2
       5: aload_1
       6: invokevirtual #75                 // Method java/awt/event/MouseEvent.getY:()I
       9: istore_3
      10: aload_0
      11: getfield      #5                  // Field gameFrame:LRSFrame;
      14: ifnull        23
      17: iinc          2, -4
      20: iinc          3, -22
      23: aload_0
      24: iconst_0
      25: putfield      #76                 // Field idleTime:I
      28: aload_0
      29: iload_2
      30: putfield      #79                 // Field mouseX:I
      33: aload_0
      34: iload_3
      35: putfield      #80                 // Field mouseY:I
      38: return

  public final void keyPressed(java.awt.event.KeyEvent);
    Code:
       0: aload_0
       1: iconst_0
       2: putfield      #76                 // Field idleTime:I
       5: aload_1
       6: invokevirtual #81                 // Method java/awt/event/KeyEvent.getKeyCode:()I
       9: istore_2
      10: aload_1
      11: invokevirtual #82                 // Method java/awt/event/KeyEvent.getKeyChar:()C
      14: istore_3
      15: iload_3
      16: bipush        30
      18: if_icmpge     23
      21: iconst_0
      22: istore_3
      23: iload_2
      24: bipush        37
      26: if_icmpne     31
      29: iconst_1
      30: istore_3
      31: iload_2
      32: bipush        39
      34: if_icmpne     39
      37: iconst_2
      38: istore_3
      39: iload_2
      40: bipush        38
      42: if_icmpne     47
      45: iconst_3
      46: istore_3
      47: iload_2
      48: bipush        40
      50: if_icmpne     55
      53: iconst_4
      54: istore_3
      55: iload_2
      56: bipush        17
      58: if_icmpne     63
      61: iconst_5
      62: istore_3
      63: iload_2
      64: bipush        8
      66: if_icmpne     72
      69: bipush        8
      71: istore_3
      72: iload_2
      73: bipush        127
      75: if_icmpne     81
      78: bipush        8
      80: istore_3
      81: iload_2
      82: bipush        9
      84: if_icmpne     90
      87: bipush        9
      89: istore_3
      90: iload_2
      91: bipush        10
      93: if_icmpne     99
      96: bipush        10
      98: istore_3
      99: iload_2
     100: bipush        112
     102: if_icmplt     120
     105: iload_2
     106: bipush        123
     108: if_icmpgt     120
     111: sipush        1008
     114: iload_2
     115: iadd
     116: bipush        112
     118: isub
     119: istore_3
     120: iload_2
     121: bipush        36
     123: if_icmpne     130
     126: sipush        1000
     129: istore_3
     130: iload_2
     131: bipush        35
     133: if_icmpne     140
     136: sipush        1001
     139: istore_3
     140: iload_2
     141: bipush        33
     143: if_icmpne     150
     146: sipush        1002
     149: istore_3
     150: iload_2
     151: bipush        34
     153: if_icmpne     160
     156: sipush        1003
     159: istore_3
     160: iload_3
     161: ifle          178
     164: iload_3
     165: sipush        128
     168: if_icmpge     178
     171: aload_0
     172: getfield      #83                 // Field keyArray:[I
     175: iload_3
     176: iconst_1
     177: iastore
     178: iload_3
     179: iconst_4
     180: if_icmple     206
     183: aload_0
     184: getfield      #84                 // Field charQueue:[I
     187: aload_0
     188: getfield      #40                 // Field writeIndex:I
     191: iload_3
     192: iastore
     193: aload_0
     194: aload_0
     195: getfield      #40                 // Field writeIndex:I
     198: iconst_1
     199: iadd
     200: bipush        127
     202: iand
     203: putfield      #40                 // Field writeIndex:I
     206: return

  public final void keyReleased(java.awt.event.KeyEvent);
    Code:
       0: aload_0
       1: iconst_0
       2: putfield      #76                 // Field idleTime:I
       5: aload_1
       6: invokevirtual #81                 // Method java/awt/event/KeyEvent.getKeyCode:()I
       9: istore_2
      10: aload_1
      11: invokevirtual #82                 // Method java/awt/event/KeyEvent.getKeyChar:()C
      14: istore_3
      15: iload_3
      16: bipush        30
      18: if_icmpge     23
      21: iconst_0
      22: istore_3
      23: iload_2
      24: bipush        37
      26: if_icmpne     31
      29: iconst_1
      30: istore_3
      31: iload_2
      32: bipush        39
      34: if_icmpne     39
      37: iconst_2
      38: istore_3
      39: iload_2
      40: bipush        38
      42: if_icmpne     47
      45: iconst_3
      46: istore_3
      47: iload_2
      48: bipush        40
      50: if_icmpne     55
      53: iconst_4
      54: istore_3
      55: iload_2
      56: bipush        17
      58: if_icmpne     63
      61: iconst_5
      62: istore_3
      63: iload_2
      64: bipush        8
      66: if_icmpne     72
      69: bipush        8
      71: istore_3
      72: iload_2
      73: bipush        127
      75: if_icmpne     81
      78: bipush        8
      80: istore_3
      81: iload_2
      82: bipush        9
      84: if_icmpne     90
      87: bipush        9
      89: istore_3
      90: iload_2
      91: bipush        10
      93: if_icmpne     99
      96: bipush        10
      98: istore_3
      99: iload_3
     100: ifle          117
     103: iload_3
     104: sipush        128
     107: if_icmpge     117
     110: aload_0
     111: getfield      #83                 // Field keyArray:[I
     114: iload_3
     115: iconst_0
     116: iastore
     117: return

  public final void keyTyped(java.awt.event.KeyEvent);
    Code:
       0: return

  final int readChar(int);
    Code:
       0: iload_1
       1: iflt          19
       4: iconst_1
       5: istore_2
       6: iload_2
       7: ifle          16
      10: iinc          2, 1
      13: goto          6
      16: goto          0
      19: iconst_m1
      20: istore_2
      21: aload_0
      22: getfield      #40                 // Field writeIndex:I
      25: aload_0
      26: getfield      #41                 // Field readIndex:I
      29: if_icmpeq     55
      32: aload_0
      33: getfield      #84                 // Field charQueue:[I
      36: aload_0
      37: getfield      #41                 // Field readIndex:I
      40: iaload
      41: istore_2
      42: aload_0
      43: aload_0
      44: getfield      #41                 // Field readIndex:I
      47: iconst_1
      48: iadd
      49: bipush        127
      51: iand
      52: putfield      #41                 // Field readIndex:I
      55: iload_2
      56: ireturn

  public final void focusGained(java.awt.event.FocusEvent);
    Code:
       0: aload_0
       1: iconst_1
       2: putfield      #85                 // Field awtFocus:Z
       5: aload_0
       6: iconst_1
       7: putfield      #72                 // Field shouldClearScreen:Z
      10: aload_0
      11: invokevirtual #73                 // Method raiseWelcomeScreen:()V
      14: return

  public final void focusLost(java.awt.event.FocusEvent);
    Code:
       0: aload_0
       1: iconst_0
       2: putfield      #85                 // Field awtFocus:Z
       5: iconst_0
       6: istore_2
       7: iload_2
       8: sipush        128
      11: if_icmpge     27
      14: aload_0
      15: getfield      #83                 // Field keyArray:[I
      18: iload_2
      19: iconst_0
      20: iastore
      21: iinc          2, 1
      24: goto          7
      27: return

  public final void windowActivated(java.awt.event.WindowEvent);
    Code:
       0: return

  public final void windowClosed(java.awt.event.WindowEvent);
    Code:
       0: return

  public final void windowClosing(java.awt.event.WindowEvent);
    Code:
       0: aload_0
       1: invokevirtual #86                 // Method destroy:()V
       4: return

  public final void windowDeactivated(java.awt.event.WindowEvent);
    Code:
       0: return

  public final void windowDeiconified(java.awt.event.WindowEvent);
    Code:
       0: return

  public final void windowIconified(java.awt.event.WindowEvent);
    Code:
       0: return

  public final void windowOpened(java.awt.event.WindowEvent);
    Code:
       0: return

  void startUp();
    Code:
       0: return

  void processGameLoop();
    Code:
       0: return

  void cleanUpForQuit();
    Code:
       0: return

  void processDrawing();
    Code:
       0: return

  void raiseWelcomeScreen();
    Code:
       0: return

  java.awt.Component getGameComponent();
    Code:
       0: aload_0
       1: getfield      #5                  // Field gameFrame:LRSFrame;
       4: ifnull        12
       7: aload_0
       8: getfield      #5                  // Field gameFrame:LRSFrame;
      11: areturn
      12: aload_0
      13: areturn

  public void startRunnable(java.lang.Runnable, int);
    Code:
       0: new           #87                 // class java/lang/Thread
       3: dup
       4: aload_1
       5: invokespecial #88                 // Method java/lang/Thread."<init>":(Ljava/lang/Runnable;)V
       8: astore_3
       9: aload_3
      10: invokevirtual #89                 // Method java/lang/Thread.start:()V
      13: aload_3
      14: iload_2
      15: invokevirtual #90                 // Method java/lang/Thread.setPriority:(I)V
      18: return

  void drawLoadingText(int, java.lang.String);
    Code:
       0: aload_0
       1: getfield      #8                  // Field graphics:Ljava/awt/Graphics;
       4: ifnonnull     42
       7: aload_0
       8: aload_0
       9: invokevirtual #6                  // Method getGameComponent:()Ljava/awt/Component;
      12: invokevirtual #7                  // Method java/awt/Component.getGraphics:()Ljava/awt/Graphics;
      15: putfield      #8                  // Field graphics:Ljava/awt/Graphics;
      18: aload_0
      19: invokevirtual #6                  // Method getGameComponent:()Ljava/awt/Component;
      22: invokevirtual #91                 // Method java/awt/Component.repaint:()V
      25: goto          29
      28: astore_3
      29: ldc2_w        #65                 // long 1000l
      32: invokestatic  #29                 // Method java/lang/Thread.sleep:(J)V
      35: goto          0
      38: astore_3
      39: goto          0
      42: new           #92                 // class java/awt/Font
      45: dup
      46: ldc           #93                 // String Helvetica
      48: iconst_1
      49: bipush        13
      51: invokespecial #94                 // Method java/awt/Font."<init>":(Ljava/lang/String;II)V
      54: astore_3
      55: aload_0
      56: invokevirtual #6                  // Method getGameComponent:()Ljava/awt/Component;
      59: aload_3
      60: invokevirtual #95                 // Method java/awt/Component.getFontMetrics:(Ljava/awt/Font;)Ljava/awt/FontMetrics;
      63: astore        4
      65: new           #92                 // class java/awt/Font
      68: dup
      69: ldc           #93                 // String Helvetica
      71: iconst_0
      72: bipush        13
      74: invokespecial #94                 // Method java/awt/Font."<init>":(Ljava/lang/String;II)V
      77: astore        5
      79: aload_0
      80: invokevirtual #6                  // Method getGameComponent:()Ljava/awt/Component;
      83: aload         5
      85: invokevirtual #95                 // Method java/awt/Component.getFontMetrics:(Ljava/awt/Font;)Ljava/awt/FontMetrics;
      88: pop
      89: aload_0
      90: getfield      #72                 // Field shouldClearScreen:Z
      93: ifeq          128
      96: aload_0
      97: getfield      #8                  // Field graphics:Ljava/awt/Graphics;
     100: getstatic     #96                 // Field java/awt/Color.black:Ljava/awt/Color;
     103: invokevirtual #97                 // Method java/awt/Graphics.setColor:(Ljava/awt/Color;)V
     106: aload_0
     107: getfield      #8                  // Field graphics:Ljava/awt/Graphics;
     110: iconst_0
     111: iconst_0
     112: aload_0
     113: getfield      #1                  // Field myWidth:I
     116: aload_0
     117: getfield      #2                  // Field myHeight:I
     120: invokevirtual #98                 // Method java/awt/Graphics.fillRect:(IIII)V
     123: aload_0
     124: iconst_0
     125: putfield      #72                 // Field shouldClearScreen:Z
     128: new           #99                 // class java/awt/Color
     131: dup
     132: sipush        140
     135: bipush        17
     137: bipush        17
     139: invokespecial #100                // Method java/awt/Color."<init>":(III)V
     142: astore        6
     144: aload_0
     145: getfield      #2                  // Field myHeight:I
     148: iconst_2
     149: idiv
     150: bipush        18
     152: isub
     153: istore        7
     155: aload_0
     156: getfield      #8                  // Field graphics:Ljava/awt/Graphics;
     159: aload         6
     161: invokevirtual #97                 // Method java/awt/Graphics.setColor:(Ljava/awt/Color;)V
     164: aload_0
     165: getfield      #8                  // Field graphics:Ljava/awt/Graphics;
     168: aload_0
     169: getfield      #1                  // Field myWidth:I
     172: iconst_2
     173: idiv
     174: sipush        152
     177: isub
     178: iload         7
     180: sipush        304
     183: bipush        34
     185: invokevirtual #101                // Method java/awt/Graphics.drawRect:(IIII)V
     188: aload_0
     189: getfield      #8                  // Field graphics:Ljava/awt/Graphics;
     192: aload_0
     193: getfield      #1                  // Field myWidth:I
     196: iconst_2
     197: idiv
     198: sipush        150
     201: isub
     202: iload         7
     204: iconst_2
     205: iadd
     206: iload_1
     207: iconst_3
     208: imul
     209: bipush        30
     211: invokevirtual #98                 // Method java/awt/Graphics.fillRect:(IIII)V
     214: aload_0
     215: getfield      #8                  // Field graphics:Ljava/awt/Graphics;
     218: getstatic     #96                 // Field java/awt/Color.black:Ljava/awt/Color;
     221: invokevirtual #97                 // Method java/awt/Graphics.setColor:(Ljava/awt/Color;)V
     224: aload_0
     225: getfield      #8                  // Field graphics:Ljava/awt/Graphics;
     228: aload_0
     229: getfield      #1                  // Field myWidth:I
     232: iconst_2
     233: idiv
     234: sipush        150
     237: isub
     238: iload_1
     239: iconst_3
     240: imul
     241: iadd
     242: iload         7
     244: iconst_2
     245: iadd
     246: sipush        300
     249: iload_1
     250: iconst_3
     251: imul
     252: isub
     253: bipush        30
     255: invokevirtual #98                 // Method java/awt/Graphics.fillRect:(IIII)V
     258: aload_0
     259: getfield      #8                  // Field graphics:Ljava/awt/Graphics;
     262: aload_3
     263: invokevirtual #102                // Method java/awt/Graphics.setFont:(Ljava/awt/Font;)V
     266: aload_0
     267: getfield      #8                  // Field graphics:Ljava/awt/Graphics;
     270: getstatic     #103                // Field java/awt/Color.white:Ljava/awt/Color;
     273: invokevirtual #97                 // Method java/awt/Graphics.setColor:(Ljava/awt/Color;)V
     276: aload_0
     277: getfield      #8                  // Field graphics:Ljava/awt/Graphics;
     280: aload_2
     281: aload_0
     282: getfield      #1                  // Field myWidth:I
     285: aload         4
     287: aload_2
     288: invokevirtual #104                // Method java/awt/FontMetrics.stringWidth:(Ljava/lang/String;)I
     291: isub
     292: iconst_2
     293: idiv
     294: iload         7
     296: bipush        22
     298: iadd
     299: invokevirtual #105                // Method java/awt/Graphics.drawString:(Ljava/lang/String;II)V
     302: return
    Exception table:
       from    to  target type
          18    25    28   Class java/lang/Exception
          29    35    38   Class java/lang/Exception

  RSApplet();
    Code:
       0: aload_0
       1: invokespecial #106                // Method java/applet/Applet."<init>":()V
       4: aload_0
       5: bipush        20
       7: putfield      #25                 // Field delayTime:I
      10: aload_0
      11: iconst_1
      12: putfield      #28                 // Field minDelay:I
      15: aload_0
      16: bipush        10
      18: newarray       long
      20: putfield      #21                 // Field aLongArray7:[J
      23: aload_0
      24: iconst_0
      25: putfield      #44                 // Field shouldDebug:Z
      28: aload_0
      29: iconst_1
      30: putfield      #72                 // Field shouldClearScreen:Z
      33: aload_0
      34: iconst_1
      35: putfield      #85                 // Field awtFocus:Z
      38: aload_0
      39: sipush        128
      42: newarray       int
      44: putfield      #83                 // Field keyArray:[I
      47: aload_0
      48: sipush        128
      51: newarray       int
      53: putfield      #84                 // Field charQueue:[I
      56: return
}
