Compiled from "RSFrame.java"
final class RSFrame extends java.awt.Frame {
  private final RSApplet rsApplet;

  public RSFrame(RSApplet, int, int);
    Code:
       0: aload_0
       1: invokespecial #1                  // Method java/awt/Frame."<init>":()V
       4: aload_0
       5: aload_1
       6: putfield      #2                  // Field rsApplet:LRSApplet;
       9: aload_0
      10: ldc           #3                  // String Jagex
      12: invokevirtual #4                  // Method setTitle:(Ljava/lang/String;)V
      15: aload_0
      16: iconst_0
      17: invokevirtual #5                  // Method setResizable:(Z)V
      20: aload_0
      21: iconst_1
      22: invokevirtual #6                  // Method setVisible:(Z)V
      25: aload_0
      26: invokevirtual #7                  // Method toFront:()V
      29: aload_0
      30: iload_2
      31: bipush        8
      33: iadd
      34: iload_3
      35: bipush        28
      37: iadd
      38: invokevirtual #8                  // Method setSize:(II)V
      41: return

  public java.awt.Graphics getGraphics();
    Code:
       0: aload_0
       1: invokespecial #9                  // Method java/awt/Frame.getGraphics:()Ljava/awt/Graphics;
       4: astore_1
       5: aload_1
       6: iconst_4
       7: bipush        24
       9: invokevirtual #10                 // Method java/awt/Graphics.translate:(II)V
      12: aload_1
      13: areturn

  public void update(java.awt.Graphics);
    Code:
       0: aload_0
       1: getfield      #2                  // Field rsApplet:LRSApplet;
       4: aload_1
       5: invokevirtual #11                 // Method RSApplet.update:(Ljava/awt/Graphics;)V
       8: return

  public void paint(java.awt.Graphics);
    Code:
       0: aload_0
       1: getfield      #2                  // Field rsApplet:LRSApplet;
       4: aload_1
       5: invokevirtual #12                 // Method RSApplet.paint:(Ljava/awt/Graphics;)V
       8: return
}
