Compiled from "SizeConstants.java"
final class SizeConstants {
  public static final int[] anIntArray552;

  public static final int[] packetSizes;

  SizeConstants();
    Code:
       0: aload_0
       1: invokespecial #1                  // Method java/lang/Object."<init>":()V
       4: return

  static {};
    Code:
       0: sipush        257
       3: newarray       int
       5: dup
       6: iconst_0
       7: bipush        6
       9: iastore
      10: dup
      11: iconst_1
      12: bipush        21
      14: iastore
      15: dup
      16: iconst_2
      17: bipush        25
      19: iastore
      20: dup
      21: iconst_3
      22: bipush        33
      24: iastore
      25: dup
      26: iconst_4
      27: sipush        254
      30: iastore
      31: dup
      32: iconst_5
      33: bipush        127
      35: iastore
      36: dup
      37: bipush        6
      39: sipush        183
      42: iastore
      43: dup
      44: bipush        7
      46: bipush        87
      48: iastore
      49: dup
      50: bipush        8
      52: sipush        216
      55: iastore
      56: dup
      57: bipush        9
      59: sipush        215
      62: iastore
      63: dup
      64: bipush        10
      66: sipush        211
      69: iastore
      70: dup
      71: bipush        11
      73: bipush        48
      75: iastore
      76: dup
      77: bipush        12
      79: bipush        15
      81: iastore
      82: dup
      83: bipush        13
      85: sipush        195
      88: iastore
      89: dup
      90: bipush        14
      92: sipush        149
      95: iastore
      96: dup
      97: bipush        15
      99: sipush        233
     102: iastore
     103: dup
     104: bipush        16
     106: sipush        162
     109: iastore
     110: dup
     111: bipush        17
     113: bipush        102
     115: iastore
     116: dup
     117: bipush        18
     119: bipush        104
     121: iastore
     122: dup
     123: bipush        19
     125: sipush        179
     128: iastore
     129: dup
     130: bipush        20
     132: sipush        222
     135: iastore
     136: dup
     137: bipush        21
     139: bipush        103
     141: iastore
     142: dup
     143: bipush        22
     145: sipush        224
     148: iastore
     149: dup
     150: bipush        23
     152: bipush        81
     154: iastore
     155: dup
     156: bipush        24
     158: sipush        152
     161: iastore
     162: dup
     163: bipush        25
     165: bipush        89
     167: iastore
     168: dup
     169: bipush        26
     171: bipush        45
     173: iastore
     174: dup
     175: bipush        27
     177: bipush        11
     179: iastore
     180: dup
     181: bipush        28
     183: sipush        197
     186: iastore
     187: dup
     188: bipush        29
     190: sipush        187
     193: iastore
     194: dup
     195: bipush        30
     197: sipush        210
     200: iastore
     201: dup
     202: bipush        31
     204: bipush        37
     206: iastore
     207: dup
     208: bipush        32
     210: sipush        135
     213: iastore
     214: dup
     215: bipush        33
     217: sipush        220
     220: iastore
     221: dup
     222: bipush        34
     224: sipush        137
     227: iastore
     228: dup
     229: bipush        35
     231: sipush        128
     234: iastore
     235: dup
     236: bipush        36
     238: bipush        63
     240: iastore
     241: dup
     242: bipush        37
     244: sipush        188
     247: iastore
     248: dup
     249: bipush        38
     251: sipush        207
     254: iastore
     255: dup
     256: bipush        39
     258: sipush        144
     261: iastore
     262: dup
     263: bipush        40
     265: sipush        201
     268: iastore
     269: dup
     270: bipush        41
     272: sipush        161
     275: iastore
     276: dup
     277: bipush        42
     279: bipush        28
     281: iastore
     282: dup
     283: bipush        43
     285: sipush        192
     288: iastore
     289: dup
     290: bipush        44
     292: sipush        206
     295: iastore
     296: dup
     297: bipush        45
     299: bipush        32
     301: iastore
     302: dup
     303: bipush        46
     305: bipush        115
     307: iastore
     308: dup
     309: bipush        47
     311: bipush        57
     313: iastore
     314: dup
     315: bipush        48
     317: sipush        196
     320: iastore
     321: dup
     322: bipush        49
     324: bipush        22
     326: iastore
     327: dup
     328: bipush        50
     330: sipush        132
     333: iastore
     334: dup
     335: bipush        51
     337: sipush        226
     340: iastore
     341: dup
     342: bipush        52
     344: sipush        227
     347: iastore
     348: dup
     349: bipush        53
     351: sipush        169
     354: iastore
     355: dup
     356: bipush        54
     358: sipush        237
     361: iastore
     362: dup
     363: bipush        55
     365: bipush        105
     367: iastore
     368: dup
     369: bipush        56
     371: sipush        174
     374: iastore
     375: dup
     376: bipush        57
     378: bipush        109
     380: iastore
     381: dup
     382: bipush        58
     384: iconst_5
     385: iastore
     386: dup
     387: bipush        59
     389: bipush        55
     391: iastore
     392: dup
     393: bipush        60
     395: sipush        205
     398: iastore
     399: dup
     400: bipush        61
     402: sipush        156
     405: iastore
     406: dup
     407: bipush        62
     409: bipush        8
     411: iastore
     412: dup
     413: bipush        63
     415: bipush        34
     417: iastore
     418: dup
     419: bipush        64
     421: bipush        113
     423: iastore
     424: dup
     425: bipush        65
     427: sipush        176
     430: iastore
     431: dup
     432: bipush        66
     434: sipush        209
     437: iastore
     438: dup
     439: bipush        67
     441: iconst_3
     442: iastore
     443: dup
     444: bipush        68
     446: bipush        50
     448: iastore
     449: dup
     450: bipush        69
     452: bipush        117
     454: iastore
     455: dup
     456: bipush        70
     458: bipush        122
     460: iastore
     461: dup
     462: bipush        71
     464: sipush        189
     467: iastore
     468: dup
     469: bipush        72
     471: bipush        101
     473: iastore
     474: dup
     475: bipush        73
     477: sipush        142
     480: iastore
     481: dup
     482: bipush        74
     484: sipush        246
     487: iastore
     488: dup
     489: bipush        75
     491: sipush        163
     494: iastore
     495: dup
     496: bipush        76
     498: sipush        238
     501: iastore
     502: dup
     503: bipush        77
     505: bipush        76
     507: iastore
     508: dup
     509: bipush        78
     511: bipush        74
     513: iastore
     514: dup
     515: bipush        79
     517: bipush        84
     519: iastore
     520: dup
     521: bipush        80
     523: bipush        91
     525: iastore
     526: dup
     527: bipush        81
     529: sipush        217
     532: iastore
     533: dup
     534: bipush        82
     536: bipush        58
     538: iastore
     539: dup
     540: bipush        83
     542: bipush        23
     544: iastore
     545: dup
     546: bipush        84
     548: bipush        118
     550: iastore
     551: dup
     552: bipush        85
     554: bipush        66
     556: iastore
     557: dup
     558: bipush        86
     560: bipush        35
     562: iastore
     563: dup
     564: bipush        87
     566: sipush        164
     569: iastore
     570: dup
     571: bipush        88
     573: bipush        114
     575: iastore
     576: dup
     577: bipush        89
     579: sipush        138
     582: iastore
     583: dup
     584: bipush        90
     586: bipush        96
     588: iastore
     589: dup
     590: bipush        91
     592: bipush        110
     594: iastore
     595: dup
     596: bipush        92
     598: bipush        29
     600: iastore
     601: dup
     602: bipush        93
     604: sipush        235
     607: iastore
     608: dup
     609: bipush        94
     611: sipush        147
     614: iastore
     615: dup
     616: bipush        95
     618: sipush        249
     621: iastore
     622: dup
     623: bipush        96
     625: sipush        214
     628: iastore
     629: dup
     630: bipush        97
     632: sipush        198
     635: iastore
     636: dup
     637: bipush        98
     639: sipush        242
     642: iastore
     643: dup
     644: bipush        99
     646: bipush        56
     648: iastore
     649: dup
     650: bipush        100
     652: bipush        94
     654: iastore
     655: dup
     656: bipush        101
     658: sipush        248
     661: iastore
     662: dup
     663: bipush        102
     665: bipush        59
     667: iastore
     668: dup
     669: bipush        103
     671: sipush        253
     674: iastore
     675: dup
     676: bipush        104
     678: sipush        150
     681: iastore
     682: dup
     683: bipush        105
     685: bipush        16
     687: iastore
     688: dup
     689: bipush        106
     691: bipush        13
     693: iastore
     694: dup
     695: bipush        107
     697: bipush        46
     699: iastore
     700: dup
     701: bipush        108
     703: bipush        24
     705: iastore
     706: dup
     707: bipush        109
     709: sipush        130
     712: iastore
     713: dup
     714: bipush        110
     716: sipush        232
     719: iastore
     720: dup
     721: bipush        111
     723: sipush        153
     726: iastore
     727: dup
     728: bipush        112
     730: sipush        167
     733: iastore
     734: dup
     735: bipush        113
     737: sipush        229
     740: iastore
     741: dup
     742: bipush        114
     744: bipush        79
     746: iastore
     747: dup
     748: bipush        115
     750: sipush        134
     753: iastore
     754: dup
     755: bipush        116
     757: bipush        26
     759: iastore
     760: dup
     761: bipush        117
     763: sipush        191
     766: iastore
     767: dup
     768: bipush        118
     770: iconst_0
     771: iastore
     772: dup
     773: bipush        119
     775: sipush        213
     778: iastore
     779: dup
     780: bipush        120
     782: sipush        204
     785: iastore
     786: dup
     787: bipush        121
     789: sipush        241
     792: iastore
     793: dup
     794: bipush        122
     796: sipush        160
     799: iastore
     800: dup
     801: bipush        123
     803: bipush        39
     805: iastore
     806: dup
     807: bipush        124
     809: sipush        180
     812: iastore
     813: dup
     814: bipush        125
     816: bipush        49
     818: iastore
     819: dup
     820: bipush        126
     822: sipush        250
     825: iastore
     826: dup
     827: bipush        127
     829: bipush        47
     831: iastore
     832: dup
     833: sipush        128
     836: sipush        140
     839: iastore
     840: dup
     841: sipush        129
     844: sipush        193
     847: iastore
     848: dup
     849: sipush        130
     852: sipush        202
     855: iastore
     856: dup
     857: sipush        131
     860: bipush        108
     862: iastore
     863: dup
     864: sipush        132
     867: bipush        120
     869: iastore
     870: dup
     871: sipush        133
     874: sipush        247
     877: iastore
     878: dup
     879: sipush        134
     882: bipush        106
     884: iastore
     885: dup
     886: sipush        135
     889: sipush        194
     892: iastore
     893: dup
     894: sipush        136
     897: bipush        65
     899: iastore
     900: dup
     901: sipush        137
     904: bipush        27
     906: iastore
     907: dup
     908: sipush        138
     911: bipush        93
     913: iastore
     914: dup
     915: sipush        139
     918: sipush        143
     921: iastore
     922: dup
     923: sipush        140
     926: sipush        186
     929: iastore
     930: dup
     931: sipush        141
     934: sipush        171
     937: iastore
     938: dup
     939: sipush        142
     942: bipush        125
     944: iastore
     945: dup
     946: sipush        143
     949: bipush        54
     951: iastore
     952: dup
     953: sipush        144
     956: sipush        155
     959: iastore
     960: dup
     961: sipush        145
     964: sipush        190
     967: iastore
     968: dup
     969: sipush        146
     972: sipush        139
     975: iastore
     976: dup
     977: sipush        147
     980: sipush        165
     983: iastore
     984: dup
     985: sipush        148
     988: bipush        77
     990: iastore
     991: dup
     992: sipush        149
     995: sipush        178
     998: iastore
     999: dup
    1000: sipush        150
    1003: bipush        72
    1005: iastore
    1006: dup
    1007: sipush        151
    1010: bipush        99
    1012: iastore
    1013: dup
    1014: sipush        152
    1017: bipush        61
    1019: iastore
    1020: dup
    1021: sipush        153
    1024: sipush        141
    1027: iastore
    1028: dup
    1029: sipush        154
    1032: bipush        116
    1034: iastore
    1035: dup
    1036: sipush        155
    1039: bipush        100
    1041: iastore
    1042: dup
    1043: sipush        156
    1046: bipush        80
    1048: iastore
    1049: dup
    1050: sipush        157
    1053: sipush        184
    1056: iastore
    1057: dup
    1058: sipush        158
    1061: sipush        154
    1064: iastore
    1065: dup
    1066: sipush        159
    1069: sipush        145
    1072: iastore
    1073: dup
    1074: sipush        160
    1077: sipush        131
    1080: iastore
    1081: dup
    1082: sipush        161
    1085: bipush        12
    1087: iastore
    1088: dup
    1089: sipush        162
    1092: bipush        90
    1094: iastore
    1095: dup
    1096: sipush        163
    1099: bipush        42
    1101: iastore
    1102: dup
    1103: sipush        164
    1106: sipush        255
    1109: iastore
    1110: dup
    1111: sipush        165
    1114: bipush        75
    1116: iastore
    1117: dup
    1118: sipush        166
    1121: bipush        44
    1123: iastore
    1124: dup
    1125: sipush        167
    1128: bipush        78
    1130: iastore
    1131: dup
    1132: sipush        168
    1135: sipush        172
    1138: iastore
    1139: dup
    1140: sipush        169
    1143: bipush        107
    1145: iastore
    1146: dup
    1147: sipush        170
    1150: bipush        52
    1152: iastore
    1153: dup
    1154: sipush        171
    1157: bipush        7
    1159: iastore
    1160: dup
    1161: sipush        172
    1164: bipush        119
    1166: iastore
    1167: dup
    1168: sipush        173
    1171: sipush        146
    1174: iastore
    1175: dup
    1176: sipush        174
    1179: bipush        38
    1181: iastore
    1182: dup
    1183: sipush        175
    1186: sipush        218
    1189: iastore
    1190: dup
    1191: sipush        176
    1194: bipush        10
    1196: iastore
    1197: dup
    1198: sipush        177
    1201: sipush        223
    1204: iastore
    1205: dup
    1206: sipush        178
    1209: sipush        182
    1212: iastore
    1213: dup
    1214: sipush        179
    1217: sipush        240
    1220: iastore
    1221: dup
    1222: sipush        180
    1225: sipush        159
    1228: iastore
    1229: dup
    1230: sipush        181
    1233: bipush        88
    1235: iastore
    1236: dup
    1237: sipush        182
    1240: sipush        158
    1243: iastore
    1244: dup
    1245: sipush        183
    1248: bipush        64
    1250: iastore
    1251: dup
    1252: sipush        184
    1255: sipush        221
    1258: iastore
    1259: dup
    1260: sipush        185
    1263: sipush        200
    1266: iastore
    1267: dup
    1268: sipush        186
    1271: iconst_1
    1272: iastore
    1273: dup
    1274: sipush        187
    1277: bipush        43
    1279: iastore
    1280: dup
    1281: sipush        188
    1284: sipush        252
    1287: iastore
    1288: dup
    1289: sipush        189
    1292: bipush        62
    1294: iastore
    1295: dup
    1296: sipush        190
    1299: bipush        40
    1301: iastore
    1302: dup
    1303: sipush        191
    1306: sipush        230
    1309: iastore
    1310: dup
    1311: sipush        192
    1314: sipush        129
    1317: iastore
    1318: dup
    1319: sipush        193
    1322: bipush        18
    1324: iastore
    1325: dup
    1326: sipush        194
    1329: bipush        111
    1331: iastore
    1332: dup
    1333: sipush        195
    1336: bipush        51
    1338: iastore
    1339: dup
    1340: sipush        196
    1343: bipush        17
    1345: iastore
    1346: dup
    1347: sipush        197
    1350: bipush        53
    1352: iastore
    1353: dup
    1354: sipush        198
    1357: sipush        136
    1360: iastore
    1361: dup
    1362: sipush        199
    1365: bipush        20
    1367: iastore
    1368: dup
    1369: sipush        200
    1372: bipush        60
    1374: iastore
    1375: dup
    1376: sipush        201
    1379: sipush        225
    1382: iastore
    1383: dup
    1384: sipush        202
    1387: bipush        30
    1389: iastore
    1390: dup
    1391: sipush        203
    1394: bipush        9
    1396: iastore
    1397: dup
    1398: sipush        204
    1401: sipush        239
    1404: iastore
    1405: dup
    1406: sipush        205
    1409: bipush        97
    1411: iastore
    1412: dup
    1413: sipush        206
    1416: sipush        234
    1419: iastore
    1420: dup
    1421: sipush        207
    1424: bipush        41
    1426: iastore
    1427: dup
    1428: sipush        208
    1431: sipush        203
    1434: iastore
    1435: dup
    1436: sipush        209
    1439: sipush        236
    1442: iastore
    1443: dup
    1444: sipush        210
    1447: bipush        36
    1449: iastore
    1450: dup
    1451: sipush        211
    1454: sipush        185
    1457: iastore
    1458: dup
    1459: sipush        212
    1462: sipush        212
    1465: iastore
    1466: dup
    1467: sipush        213
    1470: bipush        19
    1472: iastore
    1473: dup
    1474: sipush        214
    1477: sipush        245
    1480: iastore
    1481: dup
    1482: sipush        215
    1485: sipush        251
    1488: iastore
    1489: dup
    1490: sipush        216
    1493: sipush        208
    1496: iastore
    1497: dup
    1498: sipush        217
    1501: sipush        175
    1504: iastore
    1505: dup
    1506: sipush        218
    1509: sipush        243
    1512: iastore
    1513: dup
    1514: sipush        219
    1517: bipush        86
    1519: iastore
    1520: dup
    1521: sipush        220
    1524: iconst_2
    1525: iastore
    1526: dup
    1527: sipush        221
    1530: bipush        69
    1532: iastore
    1533: dup
    1534: sipush        222
    1537: sipush        181
    1540: iastore
    1541: dup
    1542: sipush        223
    1545: sipush        151
    1548: iastore
    1549: dup
    1550: sipush        224
    1553: bipush        14
    1555: iastore
    1556: dup
    1557: sipush        225
    1560: sipush        166
    1563: iastore
    1564: dup
    1565: sipush        226
    1568: bipush        70
    1570: iastore
    1571: dup
    1572: sipush        227
    1575: bipush        98
    1577: iastore
    1578: dup
    1579: sipush        228
    1582: bipush        124
    1584: iastore
    1585: dup
    1586: sipush        229
    1589: bipush        126
    1591: iastore
    1592: dup
    1593: sipush        230
    1596: bipush        67
    1598: iastore
    1599: dup
    1600: sipush        231
    1603: sipush        157
    1606: iastore
    1607: dup
    1608: sipush        232
    1611: sipush        199
    1614: iastore
    1615: dup
    1616: sipush        233
    1619: bipush        112
    1621: iastore
    1622: dup
    1623: sipush        234
    1626: bipush        123
    1628: iastore
    1629: dup
    1630: sipush        235
    1633: sipush        177
    1636: iastore
    1637: dup
    1638: sipush        236
    1641: bipush        82
    1643: iastore
    1644: dup
    1645: sipush        237
    1648: sipush        168
    1651: iastore
    1652: dup
    1653: sipush        238
    1656: bipush        71
    1658: iastore
    1659: dup
    1660: sipush        239
    1663: sipush        170
    1666: iastore
    1667: dup
    1668: sipush        240
    1671: bipush        95
    1673: iastore
    1674: dup
    1675: sipush        241
    1678: bipush        31
    1680: iastore
    1681: dup
    1682: sipush        242
    1685: bipush        92
    1687: iastore
    1688: dup
    1689: sipush        243
    1692: iconst_4
    1693: iastore
    1694: dup
    1695: sipush        244
    1698: sipush        231
    1701: iastore
    1702: dup
    1703: sipush        245
    1706: sipush        219
    1709: iastore
    1710: dup
    1711: sipush        246
    1714: bipush        73
    1716: iastore
    1717: dup
    1718: sipush        247
    1721: bipush        85
    1723: iastore
    1724: dup
    1725: sipush        248
    1728: sipush        244
    1731: iastore
    1732: dup
    1733: sipush        249
    1736: sipush        148
    1739: iastore
    1740: dup
    1741: sipush        250
    1744: sipush        173
    1747: iastore
    1748: dup
    1749: sipush        251
    1752: sipush        228
    1755: iastore
    1756: dup
    1757: sipush        252
    1760: bipush        121
    1762: iastore
    1763: dup
    1764: sipush        253
    1767: bipush        83
    1769: iastore
    1770: dup
    1771: sipush        254
    1774: sipush        133
    1777: iastore
    1778: dup
    1779: sipush        255
    1782: bipush        68
    1784: iastore
    1785: dup
    1786: sipush        256
    1789: iconst_0
    1790: iastore
    1791: putstatic     #2                  // Field anIntArray552:[I
    1794: sipush        257
    1797: newarray       int
    1799: dup
    1800: iconst_0
    1801: iconst_0
    1802: iastore
    1803: dup
    1804: iconst_1
    1805: iconst_0
    1806: iastore
    1807: dup
    1808: iconst_2
    1809: iconst_0
    1810: iastore
    1811: dup
    1812: iconst_3
    1813: iconst_0
    1814: iastore
    1815: dup
    1816: iconst_4
    1817: bipush        6
    1819: iastore
    1820: dup
    1821: iconst_5
    1822: iconst_0
    1823: iastore
    1824: dup
    1825: bipush        6
    1827: iconst_0
    1828: iastore
    1829: dup
    1830: bipush        7
    1832: iconst_0
    1833: iastore
    1834: dup
    1835: bipush        8
    1837: iconst_4
    1838: iastore
    1839: dup
    1840: bipush        9
    1842: iconst_0
    1843: iastore
    1844: dup
    1845: bipush        10
    1847: iconst_0
    1848: iastore
    1849: dup
    1850: bipush        11
    1852: iconst_0
    1853: iastore
    1854: dup
    1855: bipush        12
    1857: iconst_0
    1858: iastore
    1859: dup
    1860: bipush        13
    1862: iconst_0
    1863: iastore
    1864: dup
    1865: bipush        14
    1867: iconst_0
    1868: iastore
    1869: dup
    1870: bipush        15
    1872: iconst_0
    1873: iastore
    1874: dup
    1875: bipush        16
    1877: iconst_0
    1878: iastore
    1879: dup
    1880: bipush        17
    1882: iconst_0
    1883: iastore
    1884: dup
    1885: bipush        18
    1887: iconst_0
    1888: iastore
    1889: dup
    1890: bipush        19
    1892: iconst_0
    1893: iastore
    1894: dup
    1895: bipush        20
    1897: iconst_0
    1898: iastore
    1899: dup
    1900: bipush        21
    1902: iconst_0
    1903: iastore
    1904: dup
    1905: bipush        22
    1907: iconst_0
    1908: iastore
    1909: dup
    1910: bipush        23
    1912: iconst_0
    1913: iastore
    1914: dup
    1915: bipush        24
    1917: iconst_1
    1918: iastore
    1919: dup
    1920: bipush        25
    1922: iconst_0
    1923: iastore
    1924: dup
    1925: bipush        26
    1927: iconst_0
    1928: iastore
    1929: dup
    1930: bipush        27
    1932: iconst_0
    1933: iastore
    1934: dup
    1935: bipush        28
    1937: iconst_0
    1938: iastore
    1939: dup
    1940: bipush        29
    1942: iconst_0
    1943: iastore
    1944: dup
    1945: bipush        30
    1947: iconst_0
    1948: iastore
    1949: dup
    1950: bipush        31
    1952: iconst_0
    1953: iastore
    1954: dup
    1955: bipush        32
    1957: iconst_0
    1958: iastore
    1959: dup
    1960: bipush        33
    1962: iconst_0
    1963: iastore
    1964: dup
    1965: bipush        34
    1967: bipush        -2
    1969: iastore
    1970: dup
    1971: bipush        35
    1973: iconst_4
    1974: iastore
    1975: dup
    1976: bipush        36
    1978: iconst_3
    1979: iastore
    1980: dup
    1981: bipush        37
    1983: iconst_0
    1984: iastore
    1985: dup
    1986: bipush        38
    1988: iconst_0
    1989: iastore
    1990: dup
    1991: bipush        39
    1993: iconst_0
    1994: iastore
    1995: dup
    1996: bipush        40
    1998: iconst_0
    1999: iastore
    2000: dup
    2001: bipush        41
    2003: iconst_0
    2004: iastore
    2005: dup
    2006: bipush        42
    2008: iconst_0
    2009: iastore
    2010: dup
    2011: bipush        43
    2013: iconst_0
    2014: iastore
    2015: dup
    2016: bipush        44
    2018: iconst_5
    2019: iastore
    2020: dup
    2021: bipush        45
    2023: iconst_0
    2024: iastore
    2025: dup
    2026: bipush        46
    2028: iconst_0
    2029: iastore
    2030: dup
    2031: bipush        47
    2033: bipush        6
    2035: iastore
    2036: dup
    2037: bipush        48
    2039: iconst_0
    2040: iastore
    2041: dup
    2042: bipush        49
    2044: iconst_0
    2045: iastore
    2046: dup
    2047: bipush        50
    2049: bipush        9
    2051: iastore
    2052: dup
    2053: bipush        51
    2055: iconst_0
    2056: iastore
    2057: dup
    2058: bipush        52
    2060: iconst_0
    2061: iastore
    2062: dup
    2063: bipush        53
    2065: bipush        -2
    2067: iastore
    2068: dup
    2069: bipush        54
    2071: iconst_0
    2072: iastore
    2073: dup
    2074: bipush        55
    2076: iconst_0
    2077: iastore
    2078: dup
    2079: bipush        56
    2081: iconst_0
    2082: iastore
    2083: dup
    2084: bipush        57
    2086: iconst_0
    2087: iastore
    2088: dup
    2089: bipush        58
    2091: iconst_0
    2092: iastore
    2093: dup
    2094: bipush        59
    2096: iconst_0
    2097: iastore
    2098: dup
    2099: bipush        60
    2101: bipush        -2
    2103: iastore
    2104: dup
    2105: bipush        61
    2107: iconst_1
    2108: iastore
    2109: dup
    2110: bipush        62
    2112: iconst_0
    2113: iastore
    2114: dup
    2115: bipush        63
    2117: iconst_0
    2118: iastore
    2119: dup
    2120: bipush        64
    2122: iconst_2
    2123: iastore
    2124: dup
    2125: bipush        65
    2127: bipush        -2
    2129: iastore
    2130: dup
    2131: bipush        66
    2133: iconst_0
    2134: iastore
    2135: dup
    2136: bipush        67
    2138: iconst_0
    2139: iastore
    2140: dup
    2141: bipush        68
    2143: iconst_0
    2144: iastore
    2145: dup
    2146: bipush        69
    2148: iconst_0
    2149: iastore
    2150: dup
    2151: bipush        70
    2153: bipush        6
    2155: iastore
    2156: dup
    2157: bipush        71
    2159: iconst_3
    2160: iastore
    2161: dup
    2162: bipush        72
    2164: iconst_2
    2165: iastore
    2166: dup
    2167: bipush        73
    2169: iconst_4
    2170: iastore
    2171: dup
    2172: bipush        74
    2174: iconst_2
    2175: iastore
    2176: dup
    2177: bipush        75
    2179: iconst_4
    2180: iastore
    2181: dup
    2182: bipush        76
    2184: iconst_0
    2185: iastore
    2186: dup
    2187: bipush        77
    2189: iconst_0
    2190: iastore
    2191: dup
    2192: bipush        78
    2194: iconst_0
    2195: iastore
    2196: dup
    2197: bipush        79
    2199: iconst_4
    2200: iastore
    2201: dup
    2202: bipush        80
    2204: iconst_0
    2205: iastore
    2206: dup
    2207: bipush        81
    2209: bipush        -2
    2211: iastore
    2212: dup
    2213: bipush        82
    2215: iconst_0
    2216: iastore
    2217: dup
    2218: bipush        83
    2220: iconst_0
    2221: iastore
    2222: dup
    2223: bipush        84
    2225: bipush        7
    2227: iastore
    2228: dup
    2229: bipush        85
    2231: iconst_2
    2232: iastore
    2233: dup
    2234: bipush        86
    2236: iconst_0
    2237: iastore
    2238: dup
    2239: bipush        87
    2241: bipush        6
    2243: iastore
    2244: dup
    2245: bipush        88
    2247: iconst_0
    2248: iastore
    2249: dup
    2250: bipush        89
    2252: iconst_0
    2253: iastore
    2254: dup
    2255: bipush        90
    2257: iconst_0
    2258: iastore
    2259: dup
    2260: bipush        91
    2262: iconst_0
    2263: iastore
    2264: dup
    2265: bipush        92
    2267: iconst_0
    2268: iastore
    2269: dup
    2270: bipush        93
    2272: iconst_0
    2273: iastore
    2274: dup
    2275: bipush        94
    2277: iconst_0
    2278: iastore
    2279: dup
    2280: bipush        95
    2282: iconst_0
    2283: iastore
    2284: dup
    2285: bipush        96
    2287: iconst_0
    2288: iastore
    2289: dup
    2290: bipush        97
    2292: iconst_2
    2293: iastore
    2294: dup
    2295: bipush        98
    2297: iconst_0
    2298: iastore
    2299: dup
    2300: bipush        99
    2302: iconst_1
    2303: iastore
    2304: dup
    2305: bipush        100
    2307: iconst_0
    2308: iastore
    2309: dup
    2310: bipush        101
    2312: iconst_2
    2313: iastore
    2314: dup
    2315: bipush        102
    2317: iconst_0
    2318: iastore
    2319: dup
    2320: bipush        103
    2322: iconst_0
    2323: iastore
    2324: dup
    2325: bipush        104
    2327: iconst_m1
    2328: iastore
    2329: dup
    2330: bipush        105
    2332: iconst_4
    2333: iastore
    2334: dup
    2335: bipush        106
    2337: iconst_1
    2338: iastore
    2339: dup
    2340: bipush        107
    2342: iconst_0
    2343: iastore
    2344: dup
    2345: bipush        108
    2347: iconst_0
    2348: iastore
    2349: dup
    2350: bipush        109
    2352: iconst_0
    2353: iastore
    2354: dup
    2355: bipush        110
    2357: iconst_1
    2358: iastore
    2359: dup
    2360: bipush        111
    2362: iconst_0
    2363: iastore
    2364: dup
    2365: bipush        112
    2367: iconst_0
    2368: iastore
    2369: dup
    2370: bipush        113
    2372: iconst_0
    2373: iastore
    2374: dup
    2375: bipush        114
    2377: iconst_2
    2378: iastore
    2379: dup
    2380: bipush        115
    2382: iconst_0
    2383: iastore
    2384: dup
    2385: bipush        116
    2387: iconst_0
    2388: iastore
    2389: dup
    2390: bipush        117
    2392: bipush        15
    2394: iastore
    2395: dup
    2396: bipush        118
    2398: iconst_0
    2399: iastore
    2400: dup
    2401: bipush        119
    2403: iconst_0
    2404: iastore
    2405: dup
    2406: bipush        120
    2408: iconst_0
    2409: iastore
    2410: dup
    2411: bipush        121
    2413: iconst_4
    2414: iastore
    2415: dup
    2416: bipush        122
    2418: iconst_4
    2419: iastore
    2420: dup
    2421: bipush        123
    2423: iconst_0
    2424: iastore
    2425: dup
    2426: bipush        124
    2428: iconst_0
    2429: iastore
    2430: dup
    2431: bipush        125
    2433: iconst_0
    2434: iastore
    2435: dup
    2436: bipush        126
    2438: bipush        -2
    2440: iastore
    2441: dup
    2442: bipush        127
    2444: iconst_0
    2445: iastore
    2446: dup
    2447: sipush        128
    2450: iconst_0
    2451: iastore
    2452: dup
    2453: sipush        129
    2456: iconst_0
    2457: iastore
    2458: dup
    2459: sipush        130
    2462: iconst_0
    2463: iastore
    2464: dup
    2465: sipush        131
    2468: iconst_0
    2469: iastore
    2470: dup
    2471: sipush        132
    2474: iconst_0
    2475: iastore
    2476: dup
    2477: sipush        133
    2480: iconst_0
    2481: iastore
    2482: dup
    2483: sipush        134
    2486: bipush        6
    2488: iastore
    2489: dup
    2490: sipush        135
    2493: iconst_0
    2494: iastore
    2495: dup
    2496: sipush        136
    2499: iconst_0
    2500: iastore
    2501: dup
    2502: sipush        137
    2505: iconst_0
    2506: iastore
    2507: dup
    2508: sipush        138
    2511: iconst_0
    2512: iastore
    2513: dup
    2514: sipush        139
    2517: iconst_0
    2518: iastore
    2519: dup
    2520: sipush        140
    2523: iconst_0
    2524: iastore
    2525: dup
    2526: sipush        141
    2529: iconst_0
    2530: iastore
    2531: dup
    2532: sipush        142
    2535: iconst_2
    2536: iastore
    2537: dup
    2538: sipush        143
    2541: iconst_0
    2542: iastore
    2543: dup
    2544: sipush        144
    2547: iconst_0
    2548: iastore
    2549: dup
    2550: sipush        145
    2553: iconst_0
    2554: iastore
    2555: dup
    2556: sipush        146
    2559: iconst_0
    2560: iastore
    2561: dup
    2562: sipush        147
    2565: bipush        14
    2567: iastore
    2568: dup
    2569: sipush        148
    2572: iconst_0
    2573: iastore
    2574: dup
    2575: sipush        149
    2578: iconst_0
    2579: iastore
    2580: dup
    2581: sipush        150
    2584: iconst_0
    2585: iastore
    2586: dup
    2587: sipush        151
    2590: iconst_4
    2591: iastore
    2592: dup
    2593: sipush        152
    2596: iconst_0
    2597: iastore
    2598: dup
    2599: sipush        153
    2602: iconst_0
    2603: iastore
    2604: dup
    2605: sipush        154
    2608: iconst_0
    2609: iastore
    2610: dup
    2611: sipush        155
    2614: iconst_0
    2615: iastore
    2616: dup
    2617: sipush        156
    2620: iconst_3
    2621: iastore
    2622: dup
    2623: sipush        157
    2626: iconst_0
    2627: iastore
    2628: dup
    2629: sipush        158
    2632: iconst_0
    2633: iastore
    2634: dup
    2635: sipush        159
    2638: iconst_0
    2639: iastore
    2640: dup
    2641: sipush        160
    2644: iconst_4
    2645: iastore
    2646: dup
    2647: sipush        161
    2650: iconst_0
    2651: iastore
    2652: dup
    2653: sipush        162
    2656: iconst_0
    2657: iastore
    2658: dup
    2659: sipush        163
    2662: iconst_0
    2663: iastore
    2664: dup
    2665: sipush        164
    2668: iconst_2
    2669: iastore
    2670: dup
    2671: sipush        165
    2674: iconst_0
    2675: iastore
    2676: dup
    2677: sipush        166
    2680: bipush        6
    2682: iastore
    2683: dup
    2684: sipush        167
    2687: iconst_0
    2688: iastore
    2689: dup
    2690: sipush        168
    2693: iconst_0
    2694: iastore
    2695: dup
    2696: sipush        169
    2699: iconst_0
    2700: iastore
    2701: dup
    2702: sipush        170
    2705: iconst_0
    2706: iastore
    2707: dup
    2708: sipush        171
    2711: iconst_3
    2712: iastore
    2713: dup
    2714: sipush        172
    2717: iconst_0
    2718: iastore
    2719: dup
    2720: sipush        173
    2723: iconst_0
    2724: iastore
    2725: dup
    2726: sipush        174
    2729: iconst_5
    2730: iastore
    2731: dup
    2732: sipush        175
    2735: iconst_0
    2736: iastore
    2737: dup
    2738: sipush        176
    2741: bipush        10
    2743: iastore
    2744: dup
    2745: sipush        177
    2748: bipush        6
    2750: iastore
    2751: dup
    2752: sipush        178
    2755: iconst_0
    2756: iastore
    2757: dup
    2758: sipush        179
    2761: iconst_0
    2762: iastore
    2763: dup
    2764: sipush        180
    2767: iconst_0
    2768: iastore
    2769: dup
    2770: sipush        181
    2773: iconst_0
    2774: iastore
    2775: dup
    2776: sipush        182
    2779: iconst_0
    2780: iastore
    2781: dup
    2782: sipush        183
    2785: iconst_0
    2786: iastore
    2787: dup
    2788: sipush        184
    2791: iconst_0
    2792: iastore
    2793: dup
    2794: sipush        185
    2797: iconst_2
    2798: iastore
    2799: dup
    2800: sipush        186
    2803: iconst_0
    2804: iastore
    2805: dup
    2806: sipush        187
    2809: iconst_0
    2810: iastore
    2811: dup
    2812: sipush        188
    2815: iconst_0
    2816: iastore
    2817: dup
    2818: sipush        189
    2821: iconst_0
    2822: iastore
    2823: dup
    2824: sipush        190
    2827: iconst_0
    2828: iastore
    2829: dup
    2830: sipush        191
    2833: iconst_0
    2834: iastore
    2835: dup
    2836: sipush        192
    2839: iconst_0
    2840: iastore
    2841: dup
    2842: sipush        193
    2845: iconst_0
    2846: iastore
    2847: dup
    2848: sipush        194
    2851: iconst_0
    2852: iastore
    2853: dup
    2854: sipush        195
    2857: iconst_0
    2858: iastore
    2859: dup
    2860: sipush        196
    2863: iconst_m1
    2864: iastore
    2865: dup
    2866: sipush        197
    2869: iconst_0
    2870: iastore
    2871: dup
    2872: sipush        198
    2875: iconst_0
    2876: iastore
    2877: dup
    2878: sipush        199
    2881: iconst_0
    2882: iastore
    2883: dup
    2884: sipush        200
    2887: iconst_4
    2888: iastore
    2889: dup
    2890: sipush        201
    2893: iconst_0
    2894: iastore
    2895: dup
    2896: sipush        202
    2899: iconst_0
    2900: iastore
    2901: dup
    2902: sipush        203
    2905: iconst_0
    2906: iastore
    2907: dup
    2908: sipush        204
    2911: iconst_0
    2912: iastore
    2913: dup
    2914: sipush        205
    2917: iconst_0
    2918: iastore
    2919: dup
    2920: sipush        206
    2923: iconst_3
    2924: iastore
    2925: dup
    2926: sipush        207
    2929: iconst_0
    2930: iastore
    2931: dup
    2932: sipush        208
    2935: iconst_2
    2936: iastore
    2937: dup
    2938: sipush        209
    2941: iconst_0
    2942: iastore
    2943: dup
    2944: sipush        210
    2947: iconst_0
    2948: iastore
    2949: dup
    2950: sipush        211
    2953: iconst_0
    2954: iastore
    2955: dup
    2956: sipush        212
    2959: iconst_0
    2960: iastore
    2961: dup
    2962: sipush        213
    2965: iconst_0
    2966: iastore
    2967: dup
    2968: sipush        214
    2971: bipush        -2
    2973: iastore
    2974: dup
    2975: sipush        215
    2978: bipush        7
    2980: iastore
    2981: dup
    2982: sipush        216
    2985: iconst_0
    2986: iastore
    2987: dup
    2988: sipush        217
    2991: iconst_0
    2992: iastore
    2993: dup
    2994: sipush        218
    2997: iconst_2
    2998: iastore
    2999: dup
    3000: sipush        219
    3003: iconst_0
    3004: iastore
    3005: dup
    3006: sipush        220
    3009: iconst_0
    3010: iastore
    3011: dup
    3012: sipush        221
    3015: iconst_1
    3016: iastore
    3017: dup
    3018: sipush        222
    3021: iconst_0
    3022: iastore
    3023: dup
    3024: sipush        223
    3027: iconst_0
    3028: iastore
    3029: dup
    3030: sipush        224
    3033: iconst_0
    3034: iastore
    3035: dup
    3036: sipush        225
    3039: iconst_0
    3040: iastore
    3041: dup
    3042: sipush        226
    3045: iconst_0
    3046: iastore
    3047: dup
    3048: sipush        227
    3051: iconst_0
    3052: iastore
    3053: dup
    3054: sipush        228
    3057: iconst_0
    3058: iastore
    3059: dup
    3060: sipush        229
    3063: iconst_0
    3064: iastore
    3065: dup
    3066: sipush        230
    3069: bipush        8
    3071: iastore
    3072: dup
    3073: sipush        231
    3076: iconst_0
    3077: iastore
    3078: dup
    3079: sipush        232
    3082: iconst_0
    3083: iastore
    3084: dup
    3085: sipush        233
    3088: iconst_0
    3089: iastore
    3090: dup
    3091: sipush        234
    3094: iconst_0
    3095: iastore
    3096: dup
    3097: sipush        235
    3100: iconst_0
    3101: iastore
    3102: dup
    3103: sipush        236
    3106: iconst_0
    3107: iastore
    3108: dup
    3109: sipush        237
    3112: iconst_0
    3113: iastore
    3114: dup
    3115: sipush        238
    3118: iconst_0
    3119: iastore
    3120: dup
    3121: sipush        239
    3124: iconst_0
    3125: iastore
    3126: dup
    3127: sipush        240
    3130: iconst_2
    3131: iastore
    3132: dup
    3133: sipush        241
    3136: bipush        -2
    3138: iastore
    3139: dup
    3140: sipush        242
    3143: iconst_0
    3144: iastore
    3145: dup
    3146: sipush        243
    3149: iconst_0
    3150: iastore
    3151: dup
    3152: sipush        244
    3155: iconst_0
    3156: iastore
    3157: dup
    3158: sipush        245
    3161: iconst_0
    3162: iastore
    3163: dup
    3164: sipush        246
    3167: bipush        6
    3169: iastore
    3170: dup
    3171: sipush        247
    3174: iconst_0
    3175: iastore
    3176: dup
    3177: sipush        248
    3180: iconst_4
    3181: iastore
    3182: dup
    3183: sipush        249
    3186: iconst_3
    3187: iastore
    3188: dup
    3189: sipush        250
    3192: iconst_0
    3193: iastore
    3194: dup
    3195: sipush        251
    3198: iconst_0
    3199: iastore
    3200: dup
    3201: sipush        252
    3204: iconst_0
    3205: iastore
    3206: dup
    3207: sipush        253
    3210: iconst_m1
    3211: iastore
    3212: dup
    3213: sipush        254
    3216: bipush        6
    3218: iastore
    3219: dup
    3220: sipush        255
    3223: iconst_0
    3224: iastore
    3225: dup
    3226: sipush        256
    3229: iconst_0
    3230: iastore
    3231: putstatic     #3                  // Field packetSizes:[I
    3234: return
}
