Compiled from "Sounds.java"
final class Sounds {
  private static final Sounds[] aSoundsArray325s;

  public static final int[] anIntArray326;

  private static byte[] aByteArray327;

  private static Stream aStream_328;

  private final Class6[] aClass6Array329;

  private int anInt330;

  private int anInt331;

  private Sounds();
    Code:
       0: aload_0
       1: invokespecial #1                  // Method java/lang/Object."<init>":()V
       4: aload_0
       5: bipush        10
       7: anewarray     #2                  // class Class6
      10: putfield      #3                  // Field aClass6Array329:[LClass6;
      13: return

  public static void unpack(Stream);
    Code:
       0: ldc           #4                  // int 441000
       2: newarray       byte
       4: putstatic     #5                  // Field aByteArray327:[B
       7: new           #6                  // class Stream
      10: dup
      11: getstatic     #5                  // Field aByteArray327:[B
      14: invokespecial #7                  // Method Stream."<init>":([B)V
      17: putstatic     #8                  // Field aStream_328:LStream;
      20: invokestatic  #9                  // Method Class6.method166:()V
      23: aload_0
      24: invokevirtual #10                 // Method Stream.readUnsignedWord:()I
      27: istore_1
      28: iload_1
      29: ldc           #11                 // int 65535
      31: if_icmpne     35
      34: return
      35: getstatic     #12                 // Field aSoundsArray325s:[LSounds;
      38: iload_1
      39: new           #13                 // class Sounds
      42: dup
      43: invokespecial #14                 // Method "<init>":()V
      46: aastore
      47: getstatic     #12                 // Field aSoundsArray325s:[LSounds;
      50: iload_1
      51: aaload
      52: aload_0
      53: invokespecial #15                 // Method method242:(LStream;)V
      56: getstatic     #16                 // Field anIntArray326:[I
      59: iload_1
      60: getstatic     #12                 // Field aSoundsArray325s:[LSounds;
      63: iload_1
      64: aaload
      65: invokespecial #17                 // Method method243:()I
      68: iastore
      69: goto          23

  public static Stream method241(int, int);
    Code:
       0: getstatic     #12                 // Field aSoundsArray325s:[LSounds;
       3: iload_1
       4: aaload
       5: ifnull        20
       8: getstatic     #12                 // Field aSoundsArray325s:[LSounds;
      11: iload_1
      12: aaload
      13: astore_2
      14: aload_2
      15: iload_0
      16: invokespecial #18                 // Method method244:(I)LStream;
      19: areturn
      20: aconst_null
      21: areturn

  private void method242(Stream);
    Code:
       0: iconst_0
       1: istore_2
       2: iload_2
       3: bipush        10
       5: if_icmpge     56
       8: aload_1
       9: invokevirtual #19                 // Method Stream.readUnsignedByte:()I
      12: istore_3
      13: iload_3
      14: ifeq          50
      17: aload_1
      18: dup
      19: getfield      #20                 // Field Stream.currentOffset:I
      22: iconst_1
      23: isub
      24: putfield      #20                 // Field Stream.currentOffset:I
      27: aload_0
      28: getfield      #3                  // Field aClass6Array329:[LClass6;
      31: iload_2
      32: new           #2                  // class Class6
      35: dup
      36: invokespecial #21                 // Method Class6."<init>":()V
      39: aastore
      40: aload_0
      41: getfield      #3                  // Field aClass6Array329:[LClass6;
      44: iload_2
      45: aaload
      46: aload_1
      47: invokevirtual #22                 // Method Class6.method169:(LStream;)V
      50: iinc          2, 1
      53: goto          2
      56: aload_0
      57: aload_1
      58: invokevirtual #10                 // Method Stream.readUnsignedWord:()I
      61: putfield      #23                 // Field anInt330:I
      64: aload_0
      65: aload_1
      66: invokevirtual #10                 // Method Stream.readUnsignedWord:()I
      69: putfield      #24                 // Field anInt331:I
      72: return

  private int method243();
    Code:
       0: ldc           #25                 // int 9999999
       2: istore_1
       3: iconst_0
       4: istore_2
       5: iload_2
       6: bipush        10
       8: if_icmpge     55
      11: aload_0
      12: getfield      #3                  // Field aClass6Array329:[LClass6;
      15: iload_2
      16: aaload
      17: ifnull        49
      20: aload_0
      21: getfield      #3                  // Field aClass6Array329:[LClass6;
      24: iload_2
      25: aaload
      26: getfield      #26                 // Field Class6.anInt114:I
      29: bipush        20
      31: idiv
      32: iload_1
      33: if_icmpge     49
      36: aload_0
      37: getfield      #3                  // Field aClass6Array329:[LClass6;
      40: iload_2
      41: aaload
      42: getfield      #26                 // Field Class6.anInt114:I
      45: bipush        20
      47: idiv
      48: istore_1
      49: iinc          2, 1
      52: goto          5
      55: aload_0
      56: getfield      #23                 // Field anInt330:I
      59: aload_0
      60: getfield      #24                 // Field anInt331:I
      63: if_icmpge     85
      66: aload_0
      67: getfield      #23                 // Field anInt330:I
      70: bipush        20
      72: idiv
      73: iload_1
      74: if_icmpge     85
      77: aload_0
      78: getfield      #23                 // Field anInt330:I
      81: bipush        20
      83: idiv
      84: istore_1
      85: iload_1
      86: ldc           #25                 // int 9999999
      88: if_icmpeq     95
      91: iload_1
      92: ifne          97
      95: iconst_0
      96: ireturn
      97: iconst_0
      98: istore_2
      99: iload_2
     100: bipush        10
     102: if_icmpge     138
     105: aload_0
     106: getfield      #3                  // Field aClass6Array329:[LClass6;
     109: iload_2
     110: aaload
     111: ifnull        132
     114: aload_0
     115: getfield      #3                  // Field aClass6Array329:[LClass6;
     118: iload_2
     119: aaload
     120: dup
     121: getfield      #26                 // Field Class6.anInt114:I
     124: iload_1
     125: bipush        20
     127: imul
     128: isub
     129: putfield      #26                 // Field Class6.anInt114:I
     132: iinc          2, 1
     135: goto          99
     138: aload_0
     139: getfield      #23                 // Field anInt330:I
     142: aload_0
     143: getfield      #24                 // Field anInt331:I
     146: if_icmpge     175
     149: aload_0
     150: dup
     151: getfield      #23                 // Field anInt330:I
     154: iload_1
     155: bipush        20
     157: imul
     158: isub
     159: putfield      #23                 // Field anInt330:I
     162: aload_0
     163: dup
     164: getfield      #24                 // Field anInt331:I
     167: iload_1
     168: bipush        20
     170: imul
     171: isub
     172: putfield      #24                 // Field anInt331:I
     175: iload_1
     176: ireturn

  private Stream method244(int);
    Code:
       0: aload_0
       1: iload_1
       2: invokespecial #27                 // Method method245:(I)I
       5: istore_2
       6: getstatic     #8                  // Field aStream_328:LStream;
       9: iconst_0
      10: putfield      #20                 // Field Stream.currentOffset:I
      13: getstatic     #8                  // Field aStream_328:LStream;
      16: ldc           #28                 // int 1380533830
      18: invokevirtual #29                 // Method Stream.writeDWord:(I)V
      21: getstatic     #8                  // Field aStream_328:LStream;
      24: bipush        36
      26: iload_2
      27: iadd
      28: invokevirtual #30                 // Method Stream.method403:(I)V
      31: getstatic     #8                  // Field aStream_328:LStream;
      34: ldc           #31                 // int 1463899717
      36: invokevirtual #29                 // Method Stream.writeDWord:(I)V
      39: getstatic     #8                  // Field aStream_328:LStream;
      42: ldc           #32                 // int 1718449184
      44: invokevirtual #29                 // Method Stream.writeDWord:(I)V
      47: getstatic     #8                  // Field aStream_328:LStream;
      50: bipush        16
      52: invokevirtual #30                 // Method Stream.method403:(I)V
      55: getstatic     #8                  // Field aStream_328:LStream;
      58: iconst_1
      59: invokevirtual #33                 // Method Stream.method400:(I)V
      62: getstatic     #8                  // Field aStream_328:LStream;
      65: iconst_1
      66: invokevirtual #33                 // Method Stream.method400:(I)V
      69: getstatic     #8                  // Field aStream_328:LStream;
      72: sipush        22050
      75: invokevirtual #30                 // Method Stream.method403:(I)V
      78: getstatic     #8                  // Field aStream_328:LStream;
      81: sipush        22050
      84: invokevirtual #30                 // Method Stream.method403:(I)V
      87: getstatic     #8                  // Field aStream_328:LStream;
      90: iconst_1
      91: invokevirtual #33                 // Method Stream.method400:(I)V
      94: getstatic     #8                  // Field aStream_328:LStream;
      97: bipush        8
      99: invokevirtual #33                 // Method Stream.method400:(I)V
     102: getstatic     #8                  // Field aStream_328:LStream;
     105: ldc           #34                 // int 1684108385
     107: invokevirtual #29                 // Method Stream.writeDWord:(I)V
     110: getstatic     #8                  // Field aStream_328:LStream;
     113: iload_2
     114: invokevirtual #30                 // Method Stream.method403:(I)V
     117: getstatic     #8                  // Field aStream_328:LStream;
     120: dup
     121: getfield      #20                 // Field Stream.currentOffset:I
     124: iload_2
     125: iadd
     126: putfield      #20                 // Field Stream.currentOffset:I
     129: getstatic     #8                  // Field aStream_328:LStream;
     132: areturn

  private int method245(int);
    Code:
       0: iconst_0
       1: istore_2
       2: iconst_0
       3: istore_3
       4: iload_3
       5: bipush        10
       7: if_icmpge     68
      10: aload_0
      11: getfield      #3                  // Field aClass6Array329:[LClass6;
      14: iload_3
      15: aaload
      16: ifnull        62
      19: aload_0
      20: getfield      #3                  // Field aClass6Array329:[LClass6;
      23: iload_3
      24: aaload
      25: getfield      #35                 // Field Class6.anInt113:I
      28: aload_0
      29: getfield      #3                  // Field aClass6Array329:[LClass6;
      32: iload_3
      33: aaload
      34: getfield      #26                 // Field Class6.anInt114:I
      37: iadd
      38: iload_2
      39: if_icmple     62
      42: aload_0
      43: getfield      #3                  // Field aClass6Array329:[LClass6;
      46: iload_3
      47: aaload
      48: getfield      #35                 // Field Class6.anInt113:I
      51: aload_0
      52: getfield      #3                  // Field aClass6Array329:[LClass6;
      55: iload_3
      56: aaload
      57: getfield      #26                 // Field Class6.anInt114:I
      60: iadd
      61: istore_2
      62: iinc          3, 1
      65: goto          4
      68: iload_2
      69: ifne          74
      72: iconst_0
      73: ireturn
      74: sipush        22050
      77: iload_2
      78: imul
      79: sipush        1000
      82: idiv
      83: istore_3
      84: sipush        22050
      87: aload_0
      88: getfield      #23                 // Field anInt330:I
      91: imul
      92: sipush        1000
      95: idiv
      96: istore        4
      98: sipush        22050
     101: aload_0
     102: getfield      #24                 // Field anInt331:I
     105: imul
     106: sipush        1000
     109: idiv
     110: istore        5
     112: iload         4
     114: iflt          141
     117: iload         4
     119: iload_3
     120: if_icmpgt     141
     123: iload         5
     125: iflt          141
     128: iload         5
     130: iload_3
     131: if_icmpgt     141
     134: iload         4
     136: iload         5
     138: if_icmplt     143
     141: iconst_0
     142: istore_1
     143: iload_3
     144: iload         5
     146: iload         4
     148: isub
     149: iload_1
     150: iconst_1
     151: isub
     152: imul
     153: iadd
     154: istore        6
     156: bipush        44
     158: istore        7
     160: iload         7
     162: iload         6
     164: bipush        44
     166: iadd
     167: if_icmpge     184
     170: getstatic     #5                  // Field aByteArray327:[B
     173: iload         7
     175: bipush        -128
     177: bastore
     178: iinc          7, 1
     181: goto          160
     184: iconst_0
     185: istore        7
     187: iload         7
     189: bipush        10
     191: if_icmpge     315
     194: aload_0
     195: getfield      #3                  // Field aClass6Array329:[LClass6;
     198: iload         7
     200: aaload
     201: ifnull        309
     204: aload_0
     205: getfield      #3                  // Field aClass6Array329:[LClass6;
     208: iload         7
     210: aaload
     211: getfield      #35                 // Field Class6.anInt113:I
     214: sipush        22050
     217: imul
     218: sipush        1000
     221: idiv
     222: istore        8
     224: aload_0
     225: getfield      #3                  // Field aClass6Array329:[LClass6;
     228: iload         7
     230: aaload
     231: getfield      #26                 // Field Class6.anInt114:I
     234: sipush        22050
     237: imul
     238: sipush        1000
     241: idiv
     242: istore        9
     244: aload_0
     245: getfield      #3                  // Field aClass6Array329:[LClass6;
     248: iload         7
     250: aaload
     251: iload         8
     253: aload_0
     254: getfield      #3                  // Field aClass6Array329:[LClass6;
     257: iload         7
     259: aaload
     260: getfield      #35                 // Field Class6.anInt113:I
     263: invokevirtual #36                 // Method Class6.method167:(II)[I
     266: astore        10
     268: iconst_0
     269: istore        11
     271: iload         11
     273: iload         8
     275: if_icmpge     309
     278: getstatic     #5                  // Field aByteArray327:[B
     281: iload         11
     283: iload         9
     285: iadd
     286: bipush        44
     288: iadd
     289: dup2
     290: baload
     291: aload         10
     293: iload         11
     295: iaload
     296: bipush        8
     298: ishr
     299: i2b
     300: iadd
     301: i2b
     302: bastore
     303: iinc          11, 1
     306: goto          271
     309: iinc          7, 1
     312: goto          187
     315: iload_1
     316: iconst_1
     317: if_icmple     420
     320: iinc          4, 44
     323: iinc          5, 44
     326: iinc          3, 44
     329: iinc          6, 44
     332: iload         6
     334: iload_3
     335: isub
     336: istore        7
     338: iload_3
     339: iconst_1
     340: isub
     341: istore        8
     343: iload         8
     345: iload         5
     347: if_icmplt     371
     350: getstatic     #5                  // Field aByteArray327:[B
     353: iload         8
     355: iload         7
     357: iadd
     358: getstatic     #5                  // Field aByteArray327:[B
     361: iload         8
     363: baload
     364: bastore
     365: iinc          8, -1
     368: goto          343
     371: iconst_1
     372: istore        8
     374: iload         8
     376: iload_1
     377: if_icmpge     417
     380: iload         5
     382: iload         4
     384: isub
     385: iload         8
     387: imul
     388: istore        9
     390: getstatic     #5                  // Field aByteArray327:[B
     393: iload         4
     395: getstatic     #5                  // Field aByteArray327:[B
     398: iload         4
     400: iload         9
     402: iadd
     403: iload         5
     405: iload         4
     407: isub
     408: invokestatic  #37                 // Method java/lang/System.arraycopy:(Ljava/lang/Object;ILjava/lang/Object;II)V
     411: iinc          8, 1
     414: goto          374
     417: iinc          6, -44
     420: iload         6
     422: ireturn

  static {};
    Code:
       0: sipush        5000
       3: anewarray     #13                 // class Sounds
       6: putstatic     #12                 // Field aSoundsArray325s:[LSounds;
       9: sipush        5000
      12: newarray       int
      14: putstatic     #16                 // Field anIntArray326:[I
      17: return
}
