Compiled from "SpotAnim.java"
public final class SpotAnim {
  private final int anInt400;

  public static SpotAnim[] cache;

  private int anInt404;

  private int anInt405;

  private int anInt406;

  public Animation aAnimation_407;

  private final int[] anIntArray408;

  private final int[] anIntArray409;

  public int anInt410;

  public int anInt411;

  public int anInt412;

  public int anInt413;

  public int anInt414;

  public static MRUNodes aMRUNodes_415;

  public static void unpackConfig(StreamLoader);
    Code:
       0: new           #1                  // class Stream
       3: dup
       4: aload_0
       5: ldc           #2                  // String spotanim.dat
       7: invokevirtual #3                  // Method StreamLoader.getDataForName:(Ljava/lang/String;)[B
      10: invokespecial #4                  // Method Stream."<init>":([B)V
      13: astore_1
      14: aload_1
      15: invokevirtual #5                  // Method Stream.readUnsignedWord:()I
      18: istore_2
      19: getstatic     #6                  // Field cache:[LSpotAnim;
      22: ifnonnull     32
      25: iload_2
      26: anewarray     #7                  // class SpotAnim
      29: putstatic     #6                  // Field cache:[LSpotAnim;
      32: iconst_0
      33: istore_3
      34: iload_3
      35: iload_2
      36: if_icmpge     83
      39: getstatic     #6                  // Field cache:[LSpotAnim;
      42: iload_3
      43: aaload
      44: ifnonnull     59
      47: getstatic     #6                  // Field cache:[LSpotAnim;
      50: iload_3
      51: new           #7                  // class SpotAnim
      54: dup
      55: invokespecial #8                  // Method "<init>":()V
      58: aastore
      59: getstatic     #6                  // Field cache:[LSpotAnim;
      62: iload_3
      63: aaload
      64: iload_3
      65: putfield      #9                  // Field anInt404:I
      68: getstatic     #6                  // Field cache:[LSpotAnim;
      71: iload_3
      72: aaload
      73: aload_1
      74: invokespecial #10                 // Method readValues:(LStream;)V
      77: iinc          3, 1
      80: goto          34
      83: return

  private void readValues(Stream);
    Code:
       0: aload_1
       1: invokevirtual #11                 // Method Stream.readUnsignedByte:()I
       4: istore_2
       5: iload_2
       6: ifne          10
       9: return
      10: iload_2
      11: iconst_1
      12: if_icmpne     26
      15: aload_0
      16: aload_1
      17: invokevirtual #5                  // Method Stream.readUnsignedWord:()I
      20: putfield      #12                 // Field anInt405:I
      23: goto          224
      26: iload_2
      27: iconst_2
      28: if_icmpne     60
      31: aload_0
      32: aload_1
      33: invokevirtual #5                  // Method Stream.readUnsignedWord:()I
      36: putfield      #13                 // Field anInt406:I
      39: getstatic     #14                 // Field Animation.anims:[LAnimation;
      42: ifnull        224
      45: aload_0
      46: getstatic     #14                 // Field Animation.anims:[LAnimation;
      49: aload_0
      50: getfield      #13                 // Field anInt406:I
      53: aaload
      54: putfield      #15                 // Field aAnimation_407:LAnimation;
      57: goto          224
      60: iload_2
      61: iconst_4
      62: if_icmpne     76
      65: aload_0
      66: aload_1
      67: invokevirtual #5                  // Method Stream.readUnsignedWord:()I
      70: putfield      #16                 // Field anInt410:I
      73: goto          224
      76: iload_2
      77: iconst_5
      78: if_icmpne     92
      81: aload_0
      82: aload_1
      83: invokevirtual #5                  // Method Stream.readUnsignedWord:()I
      86: putfield      #17                 // Field anInt411:I
      89: goto          224
      92: iload_2
      93: bipush        6
      95: if_icmpne     109
      98: aload_0
      99: aload_1
     100: invokevirtual #5                  // Method Stream.readUnsignedWord:()I
     103: putfield      #18                 // Field anInt412:I
     106: goto          224
     109: iload_2
     110: bipush        7
     112: if_icmpne     126
     115: aload_0
     116: aload_1
     117: invokevirtual #11                 // Method Stream.readUnsignedByte:()I
     120: putfield      #19                 // Field anInt413:I
     123: goto          224
     126: iload_2
     127: bipush        8
     129: if_icmpne     143
     132: aload_0
     133: aload_1
     134: invokevirtual #11                 // Method Stream.readUnsignedByte:()I
     137: putfield      #20                 // Field anInt414:I
     140: goto          224
     143: iload_2
     144: bipush        40
     146: if_icmplt     171
     149: iload_2
     150: bipush        50
     152: if_icmpge     171
     155: aload_0
     156: getfield      #21                 // Field anIntArray408:[I
     159: iload_2
     160: bipush        40
     162: isub
     163: aload_1
     164: invokevirtual #5                  // Method Stream.readUnsignedWord:()I
     167: iastore
     168: goto          224
     171: iload_2
     172: bipush        50
     174: if_icmplt     199
     177: iload_2
     178: bipush        60
     180: if_icmpge     199
     183: aload_0
     184: getfield      #22                 // Field anIntArray409:[I
     187: iload_2
     188: bipush        50
     190: isub
     191: aload_1
     192: invokevirtual #5                  // Method Stream.readUnsignedWord:()I
     195: iastore
     196: goto          224
     199: getstatic     #23                 // Field java/lang/System.out:Ljava/io/PrintStream;
     202: new           #24                 // class java/lang/StringBuilder
     205: dup
     206: invokespecial #25                 // Method java/lang/StringBuilder."<init>":()V
     209: ldc           #26                 // String Error unrecognised spotanim config code:
     211: invokevirtual #27                 // Method java/lang/StringBuilder.append:(Ljava/lang/String;)Ljava/lang/StringBuilder;
     214: iload_2
     215: invokevirtual #28                 // Method java/lang/StringBuilder.append:(I)Ljava/lang/StringBuilder;
     218: invokevirtual #29                 // Method java/lang/StringBuilder.toString:()Ljava/lang/String;
     221: invokevirtual #30                 // Method java/io/PrintStream.println:(Ljava/lang/String;)V
     224: goto          0

  public Model getModel();
    Code:
       0: getstatic     #31                 // Field aMRUNodes_415:LMRUNodes;
       3: aload_0
       4: getfield      #9                  // Field anInt404:I
       7: i2l
       8: invokevirtual #32                 // Method MRUNodes.insertFromCache:(J)LNodeSub;
      11: checkcast     #33                 // class Model
      14: astore_1
      15: aload_1
      16: ifnull        21
      19: aload_1
      20: areturn
      21: aload_0
      22: getfield      #12                 // Field anInt405:I
      25: invokestatic  #34                 // Method Model.method462:(I)LModel;
      28: astore_1
      29: aload_1
      30: ifnonnull     35
      33: aconst_null
      34: areturn
      35: iconst_0
      36: istore_2
      37: iload_2
      38: bipush        6
      40: if_icmpge     74
      43: aload_0
      44: getfield      #21                 // Field anIntArray408:[I
      47: iconst_0
      48: iaload
      49: ifeq          68
      52: aload_1
      53: aload_0
      54: getfield      #21                 // Field anIntArray408:[I
      57: iload_2
      58: iaload
      59: aload_0
      60: getfield      #22                 // Field anIntArray409:[I
      63: iload_2
      64: iaload
      65: invokevirtual #35                 // Method Model.method476:(II)V
      68: iinc          2, 1
      71: goto          37
      74: getstatic     #31                 // Field aMRUNodes_415:LMRUNodes;
      77: aload_1
      78: aload_0
      79: getfield      #9                  // Field anInt404:I
      82: i2l
      83: invokevirtual #36                 // Method MRUNodes.removeFromCache:(LNodeSub;J)V
      86: aload_1
      87: areturn

  private SpotAnim();
    Code:
       0: aload_0
       1: invokespecial #37                 // Method java/lang/Object."<init>":()V
       4: aload_0
       5: bipush        9
       7: putfield      #38                 // Field anInt400:I
      10: aload_0
      11: iconst_m1
      12: putfield      #13                 // Field anInt406:I
      15: aload_0
      16: bipush        6
      18: newarray       int
      20: putfield      #21                 // Field anIntArray408:[I
      23: aload_0
      24: bipush        6
      26: newarray       int
      28: putfield      #22                 // Field anIntArray409:[I
      31: aload_0
      32: sipush        128
      35: putfield      #16                 // Field anInt410:I
      38: aload_0
      39: sipush        128
      42: putfield      #17                 // Field anInt411:I
      45: return

  static {};
    Code:
       0: new           #39                 // class MRUNodes
       3: dup
       4: bipush        30
       6: invokespecial #40                 // Method MRUNodes."<init>":(I)V
       9: putstatic     #31                 // Field aMRUNodes_415:LMRUNodes;
      12: return
}
