Compiled from "TextDrawingArea.java"
public final class TextDrawingArea extends DrawingArea {
  private final byte[][] aByteArrayArray1491;

  private final int[] anIntArray1492;

  private final int[] anIntArray1493;

  private final int[] anIntArray1494;

  private final int[] anIntArray1495;

  private final int[] anIntArray1496;

  public int anInt1497;

  private final java.util.Random aRandom1498;

  private boolean aBoolean1499;

  public TextDrawingArea(boolean, java.lang.String, StreamLoader);
    Code:
       0: aload_0
       1: invokespecial #1                  // Method DrawingArea."<init>":()V
       4: aload_0
       5: sipush        256
       8: anewarray     #2                  // class "[B"
      11: putfield      #3                  // Field aByteArrayArray1491:[[B
      14: aload_0
      15: sipush        256
      18: newarray       int
      20: putfield      #4                  // Field anIntArray1492:[I
      23: aload_0
      24: sipush        256
      27: newarray       int
      29: putfield      #5                  // Field anIntArray1493:[I
      32: aload_0
      33: sipush        256
      36: newarray       int
      38: putfield      #6                  // Field anIntArray1494:[I
      41: aload_0
      42: sipush        256
      45: newarray       int
      47: putfield      #7                  // Field anIntArray1495:[I
      50: aload_0
      51: sipush        256
      54: newarray       int
      56: putfield      #8                  // Field anIntArray1496:[I
      59: aload_0
      60: new           #9                  // class java/util/Random
      63: dup
      64: invokespecial #10                 // Method java/util/Random."<init>":()V
      67: putfield      #11                 // Field aRandom1498:Ljava/util/Random;
      70: aload_0
      71: iconst_0
      72: putfield      #12                 // Field aBoolean1499:Z
      75: new           #13                 // class Stream
      78: dup
      79: aload_3
      80: new           #14                 // class java/lang/StringBuilder
      83: dup
      84: invokespecial #15                 // Method java/lang/StringBuilder."<init>":()V
      87: aload_2
      88: invokevirtual #16                 // Method java/lang/StringBuilder.append:(Ljava/lang/String;)Ljava/lang/StringBuilder;
      91: ldc           #17                 // String .dat
      93: invokevirtual #16                 // Method java/lang/StringBuilder.append:(Ljava/lang/String;)Ljava/lang/StringBuilder;
      96: invokevirtual #18                 // Method java/lang/StringBuilder.toString:()Ljava/lang/String;
      99: invokevirtual #19                 // Method StreamLoader.getDataForName:(Ljava/lang/String;)[B
     102: invokespecial #20                 // Method Stream."<init>":([B)V
     105: astore        4
     107: new           #13                 // class Stream
     110: dup
     111: aload_3
     112: ldc           #21                 // String index.dat
     114: invokevirtual #19                 // Method StreamLoader.getDataForName:(Ljava/lang/String;)[B
     117: invokespecial #20                 // Method Stream."<init>":([B)V
     120: astore        5
     122: aload         5
     124: aload         4
     126: invokevirtual #22                 // Method Stream.readUnsignedWord:()I
     129: iconst_4
     130: iadd
     131: putfield      #23                 // Field Stream.currentOffset:I
     134: aload         5
     136: invokevirtual #24                 // Method Stream.readUnsignedByte:()I
     139: istore        6
     141: iload         6
     143: ifle          162
     146: aload         5
     148: dup
     149: getfield      #23                 // Field Stream.currentOffset:I
     152: iconst_3
     153: iload         6
     155: iconst_1
     156: isub
     157: imul
     158: iadd
     159: putfield      #23                 // Field Stream.currentOffset:I
     162: iconst_0
     163: istore        7
     165: iload         7
     167: sipush        256
     170: if_icmpge     535
     173: aload_0
     174: getfield      #6                  // Field anIntArray1494:[I
     177: iload         7
     179: aload         5
     181: invokevirtual #24                 // Method Stream.readUnsignedByte:()I
     184: iastore
     185: aload_0
     186: getfield      #7                  // Field anIntArray1495:[I
     189: iload         7
     191: aload         5
     193: invokevirtual #24                 // Method Stream.readUnsignedByte:()I
     196: iastore
     197: aload_0
     198: getfield      #4                  // Field anIntArray1492:[I
     201: iload         7
     203: aload         5
     205: invokevirtual #22                 // Method Stream.readUnsignedWord:()I
     208: dup_x2
     209: iastore
     210: istore        8
     212: aload_0
     213: getfield      #5                  // Field anIntArray1493:[I
     216: iload         7
     218: aload         5
     220: invokevirtual #22                 // Method Stream.readUnsignedWord:()I
     223: dup_x2
     224: iastore
     225: istore        9
     227: aload         5
     229: invokevirtual #24                 // Method Stream.readUnsignedByte:()I
     232: istore        10
     234: iload         8
     236: iload         9
     238: imul
     239: istore        11
     241: aload_0
     242: getfield      #3                  // Field aByteArrayArray1491:[[B
     245: iload         7
     247: iload         11
     249: newarray       byte
     251: aastore
     252: iload         10
     254: ifne          291
     257: iconst_0
     258: istore        12
     260: iload         12
     262: iload         11
     264: if_icmpge     288
     267: aload_0
     268: getfield      #3                  // Field aByteArrayArray1491:[[B
     271: iload         7
     273: aaload
     274: iload         12
     276: aload         4
     278: invokevirtual #25                 // Method Stream.readSignedByte:()B
     281: bastore
     282: iinc          12, 1
     285: goto          260
     288: goto          350
     291: iload         10
     293: iconst_1
     294: if_icmpne     350
     297: iconst_0
     298: istore        12
     300: iload         12
     302: iload         8
     304: if_icmpge     350
     307: iconst_0
     308: istore        13
     310: iload         13
     312: iload         9
     314: if_icmpge     344
     317: aload_0
     318: getfield      #3                  // Field aByteArrayArray1491:[[B
     321: iload         7
     323: aaload
     324: iload         12
     326: iload         13
     328: iload         8
     330: imul
     331: iadd
     332: aload         4
     334: invokevirtual #25                 // Method Stream.readSignedByte:()B
     337: bastore
     338: iinc          13, 1
     341: goto          310
     344: iinc          12, 1
     347: goto          300
     350: iload         9
     352: aload_0
     353: getfield      #26                 // Field anInt1497:I
     356: if_icmple     373
     359: iload         7
     361: sipush        128
     364: if_icmpge     373
     367: aload_0
     368: iload         9
     370: putfield      #26                 // Field anInt1497:I
     373: aload_0
     374: getfield      #6                  // Field anIntArray1494:[I
     377: iload         7
     379: iconst_1
     380: iastore
     381: aload_0
     382: getfield      #8                  // Field anIntArray1496:[I
     385: iload         7
     387: iload         8
     389: iconst_2
     390: iadd
     391: iastore
     392: iconst_0
     393: istore        12
     395: iload         9
     397: bipush        7
     399: idiv
     400: istore        13
     402: iload         13
     404: iload         9
     406: if_icmpge     433
     409: iload         12
     411: aload_0
     412: getfield      #3                  // Field aByteArrayArray1491:[[B
     415: iload         7
     417: aaload
     418: iload         13
     420: iload         8
     422: imul
     423: baload
     424: iadd
     425: istore        12
     427: iinc          13, 1
     430: goto          402
     433: iload         12
     435: iload         9
     437: bipush        7
     439: idiv
     440: if_icmpgt     462
     443: aload_0
     444: getfield      #8                  // Field anIntArray1496:[I
     447: iload         7
     449: dup2
     450: iaload
     451: iconst_1
     452: isub
     453: iastore
     454: aload_0
     455: getfield      #6                  // Field anIntArray1494:[I
     458: iload         7
     460: iconst_0
     461: iastore
     462: iconst_0
     463: istore        12
     465: iload         9
     467: bipush        7
     469: idiv
     470: istore        13
     472: iload         13
     474: iload         9
     476: if_icmpge     508
     479: iload         12
     481: aload_0
     482: getfield      #3                  // Field aByteArrayArray1491:[[B
     485: iload         7
     487: aaload
     488: iload         8
     490: iconst_1
     491: isub
     492: iload         13
     494: iload         8
     496: imul
     497: iadd
     498: baload
     499: iadd
     500: istore        12
     502: iinc          13, 1
     505: goto          472
     508: iload         12
     510: iload         9
     512: bipush        7
     514: idiv
     515: if_icmpgt     529
     518: aload_0
     519: getfield      #8                  // Field anIntArray1496:[I
     522: iload         7
     524: dup2
     525: iaload
     526: iconst_1
     527: isub
     528: iastore
     529: iinc          7, 1
     532: goto          165
     535: iload_1
     536: ifeq          556
     539: aload_0
     540: getfield      #8                  // Field anIntArray1496:[I
     543: bipush        32
     545: aload_0
     546: getfield      #8                  // Field anIntArray1496:[I
     549: bipush        73
     551: iaload
     552: iastore
     553: goto          570
     556: aload_0
     557: getfield      #8                  // Field anIntArray1496:[I
     560: bipush        32
     562: aload_0
     563: getfield      #8                  // Field anIntArray1496:[I
     566: bipush        105
     568: iaload
     569: iastore
     570: return

  public void method380(java.lang.String, int, int, int);
    Code:
       0: aload_0
       1: iload_3
       2: aload_1
       3: iload         4
       5: iload_2
       6: aload_0
       7: aload_1
       8: invokevirtual #27                 // Method method384:(Ljava/lang/String;)I
      11: isub
      12: invokevirtual #28                 // Method method385:(ILjava/lang/String;II)V
      15: return

  public void drawText(int, java.lang.String, int, int);
    Code:
       0: aload_0
       1: iload_1
       2: aload_2
       3: iload_3
       4: iload         4
       6: aload_0
       7: aload_2
       8: invokevirtual #27                 // Method method384:(Ljava/lang/String;)I
      11: iconst_2
      12: idiv
      13: isub
      14: invokevirtual #28                 // Method method385:(ILjava/lang/String;II)V
      17: return

  public void method382(int, int, java.lang.String, int, boolean);
    Code:
       0: aload_0
       1: iload         5
       3: iload_2
       4: aload_0
       5: aload_3
       6: invokevirtual #29                 // Method getTextWidth:(Ljava/lang/String;)I
       9: iconst_2
      10: idiv
      11: isub
      12: iload_1
      13: aload_3
      14: iload         4
      16: invokevirtual #30                 // Method method389:(ZIILjava/lang/String;I)V
      19: return

  public int getTextWidth(java.lang.String);
    Code:
       0: aload_1
       1: ifnonnull     6
       4: iconst_0
       5: ireturn
       6: iconst_0
       7: istore_2
       8: iconst_0
       9: istore_3
      10: iload_3
      11: aload_1
      12: invokevirtual #31                 // Method java/lang/String.length:()I
      15: if_icmpge     75
      18: aload_1
      19: iload_3
      20: invokevirtual #32                 // Method java/lang/String.charAt:(I)C
      23: bipush        64
      25: if_icmpne     56
      28: iload_3
      29: iconst_4
      30: iadd
      31: aload_1
      32: invokevirtual #31                 // Method java/lang/String.length:()I
      35: if_icmpge     56
      38: aload_1
      39: iload_3
      40: iconst_4
      41: iadd
      42: invokevirtual #32                 // Method java/lang/String.charAt:(I)C
      45: bipush        64
      47: if_icmpne     56
      50: iinc          3, 4
      53: goto          69
      56: iload_2
      57: aload_0
      58: getfield      #8                  // Field anIntArray1496:[I
      61: aload_1
      62: iload_3
      63: invokevirtual #32                 // Method java/lang/String.charAt:(I)C
      66: iaload
      67: iadd
      68: istore_2
      69: iinc          3, 1
      72: goto          10
      75: iload_2
      76: ireturn

  public int method384(java.lang.String);
    Code:
       0: aload_1
       1: ifnonnull     6
       4: iconst_0
       5: ireturn
       6: iconst_0
       7: istore_2
       8: iconst_0
       9: istore_3
      10: iload_3
      11: aload_1
      12: invokevirtual #31                 // Method java/lang/String.length:()I
      15: if_icmpge     37
      18: iload_2
      19: aload_0
      20: getfield      #8                  // Field anIntArray1496:[I
      23: aload_1
      24: iload_3
      25: invokevirtual #32                 // Method java/lang/String.charAt:(I)C
      28: iaload
      29: iadd
      30: istore_2
      31: iinc          3, 1
      34: goto          10
      37: iload_2
      38: ireturn

  public void method385(int, java.lang.String, int, int);
    Code:
       0: aload_2
       1: ifnonnull     5
       4: return
       5: iload_3
       6: aload_0
       7: getfield      #26                 // Field anInt1497:I
      10: isub
      11: istore_3
      12: iconst_0
      13: istore        5
      15: iload         5
      17: aload_2
      18: invokevirtual #31                 // Method java/lang/String.length:()I
      21: if_icmpge     102
      24: aload_2
      25: iload         5
      27: invokevirtual #32                 // Method java/lang/String.charAt:(I)C
      30: istore        6
      32: iload         6
      34: bipush        32
      36: if_icmpeq     84
      39: aload_0
      40: aload_0
      41: getfield      #3                  // Field aByteArrayArray1491:[[B
      44: iload         6
      46: aaload
      47: iload         4
      49: aload_0
      50: getfield      #6                  // Field anIntArray1494:[I
      53: iload         6
      55: iaload
      56: iadd
      57: iload_3
      58: aload_0
      59: getfield      #7                  // Field anIntArray1495:[I
      62: iload         6
      64: iaload
      65: iadd
      66: aload_0
      67: getfield      #4                  // Field anIntArray1492:[I
      70: iload         6
      72: iaload
      73: aload_0
      74: getfield      #5                  // Field anIntArray1493:[I
      77: iload         6
      79: iaload
      80: iload_1
      81: invokespecial #33                 // Method method392:([BIIIII)V
      84: iload         4
      86: aload_0
      87: getfield      #8                  // Field anIntArray1496:[I
      90: iload         6
      92: iaload
      93: iadd
      94: istore        4
      96: iinc          5, 1
      99: goto          15
     102: return

  public void method386(int, java.lang.String, int, int, int);
    Code:
       0: aload_2
       1: ifnonnull     5
       4: return
       5: iload_3
       6: aload_0
       7: aload_2
       8: invokevirtual #27                 // Method method384:(Ljava/lang/String;)I
      11: iconst_2
      12: idiv
      13: isub
      14: istore_3
      15: iload         5
      17: aload_0
      18: getfield      #26                 // Field anInt1497:I
      21: isub
      22: istore        5
      24: iconst_0
      25: istore        6
      27: iload         6
      29: aload_2
      30: invokevirtual #31                 // Method java/lang/String.length:()I
      33: if_icmpge     136
      36: aload_2
      37: iload         6
      39: invokevirtual #32                 // Method java/lang/String.charAt:(I)C
      42: istore        7
      44: iload         7
      46: bipush        32
      48: if_icmpeq     120
      51: aload_0
      52: aload_0
      53: getfield      #3                  // Field aByteArrayArray1491:[[B
      56: iload         7
      58: aaload
      59: iload_3
      60: aload_0
      61: getfield      #6                  // Field anIntArray1494:[I
      64: iload         7
      66: iaload
      67: iadd
      68: iload         5
      70: aload_0
      71: getfield      #7                  // Field anIntArray1495:[I
      74: iload         7
      76: iaload
      77: iadd
      78: iload         6
      80: i2d
      81: ldc2_w        #34                 // double 2.0d
      84: ddiv
      85: iload         4
      87: i2d
      88: ldc2_w        #36                 // double 5.0d
      91: ddiv
      92: dadd
      93: invokestatic  #38                 // Method java/lang/Math.sin:(D)D
      96: ldc2_w        #36                 // double 5.0d
      99: dmul
     100: d2i
     101: iadd
     102: aload_0
     103: getfield      #4                  // Field anIntArray1492:[I
     106: iload         7
     108: iaload
     109: aload_0
     110: getfield      #5                  // Field anIntArray1493:[I
     113: iload         7
     115: iaload
     116: iload_1
     117: invokespecial #33                 // Method method392:([BIIIII)V
     120: iload_3
     121: aload_0
     122: getfield      #8                  // Field anIntArray1496:[I
     125: iload         7
     127: iaload
     128: iadd
     129: istore_3
     130: iinc          6, 1
     133: goto          27
     136: return

  public void method387(int, java.lang.String, int, int, int);
    Code:
       0: aload_2
       1: ifnonnull     5
       4: return
       5: iload_1
       6: aload_0
       7: aload_2
       8: invokevirtual #27                 // Method method384:(Ljava/lang/String;)I
      11: iconst_2
      12: idiv
      13: isub
      14: istore_1
      15: iload         4
      17: aload_0
      18: getfield      #26                 // Field anInt1497:I
      21: isub
      22: istore        4
      24: iconst_0
      25: istore        6
      27: iload         6
      29: aload_2
      30: invokevirtual #31                 // Method java/lang/String.length:()I
      33: if_icmpge     159
      36: aload_2
      37: iload         6
      39: invokevirtual #32                 // Method java/lang/String.charAt:(I)C
      42: istore        7
      44: iload         7
      46: bipush        32
      48: if_icmpeq     143
      51: aload_0
      52: aload_0
      53: getfield      #3                  // Field aByteArrayArray1491:[[B
      56: iload         7
      58: aaload
      59: iload_1
      60: aload_0
      61: getfield      #6                  // Field anIntArray1494:[I
      64: iload         7
      66: iaload
      67: iadd
      68: iload         6
      70: i2d
      71: ldc2_w        #36                 // double 5.0d
      74: ddiv
      75: iload_3
      76: i2d
      77: ldc2_w        #36                 // double 5.0d
      80: ddiv
      81: dadd
      82: invokestatic  #38                 // Method java/lang/Math.sin:(D)D
      85: ldc2_w        #36                 // double 5.0d
      88: dmul
      89: d2i
      90: iadd
      91: iload         4
      93: aload_0
      94: getfield      #7                  // Field anIntArray1495:[I
      97: iload         7
      99: iaload
     100: iadd
     101: iload         6
     103: i2d
     104: ldc2_w        #39                 // double 3.0d
     107: ddiv
     108: iload_3
     109: i2d
     110: ldc2_w        #36                 // double 5.0d
     113: ddiv
     114: dadd
     115: invokestatic  #38                 // Method java/lang/Math.sin:(D)D
     118: ldc2_w        #36                 // double 5.0d
     121: dmul
     122: d2i
     123: iadd
     124: aload_0
     125: getfield      #4                  // Field anIntArray1492:[I
     128: iload         7
     130: iaload
     131: aload_0
     132: getfield      #5                  // Field anIntArray1493:[I
     135: iload         7
     137: iaload
     138: iload         5
     140: invokespecial #33                 // Method method392:([BIIIII)V
     143: iload_1
     144: aload_0
     145: getfield      #8                  // Field anIntArray1496:[I
     148: iload         7
     150: iaload
     151: iadd
     152: istore_1
     153: iinc          6, 1
     156: goto          27
     159: return

  public void method388(int, java.lang.String, int, int, int, int);
    Code:
       0: aload_2
       1: ifnonnull     5
       4: return
       5: ldc2_w        #41                 // double 7.0d
       8: iload_1
       9: i2d
      10: ldc2_w        #43                 // double 8.0d
      13: ddiv
      14: dsub
      15: dstore        7
      17: dload         7
      19: dconst_0
      20: dcmpg
      21: ifge          27
      24: dconst_0
      25: dstore        7
      27: iload         5
      29: aload_0
      30: aload_2
      31: invokevirtual #27                 // Method method384:(Ljava/lang/String;)I
      34: iconst_2
      35: idiv
      36: isub
      37: istore        5
      39: iload         4
      41: aload_0
      42: getfield      #26                 // Field anInt1497:I
      45: isub
      46: istore        4
      48: iconst_0
      49: istore        9
      51: iload         9
      53: aload_2
      54: invokevirtual #31                 // Method java/lang/String.length:()I
      57: if_icmpge     158
      60: aload_2
      61: iload         9
      63: invokevirtual #32                 // Method java/lang/String.charAt:(I)C
      66: istore        10
      68: iload         10
      70: bipush        32
      72: if_icmpeq     140
      75: aload_0
      76: aload_0
      77: getfield      #3                  // Field aByteArrayArray1491:[[B
      80: iload         10
      82: aaload
      83: iload         5
      85: aload_0
      86: getfield      #6                  // Field anIntArray1494:[I
      89: iload         10
      91: iaload
      92: iadd
      93: iload         4
      95: aload_0
      96: getfield      #7                  // Field anIntArray1495:[I
      99: iload         10
     101: iaload
     102: iadd
     103: iload         9
     105: i2d
     106: ldc2_w        #45                 // double 1.5d
     109: ddiv
     110: iload_3
     111: i2d
     112: dadd
     113: invokestatic  #38                 // Method java/lang/Math.sin:(D)D
     116: dload         7
     118: dmul
     119: d2i
     120: iadd
     121: aload_0
     122: getfield      #4                  // Field anIntArray1492:[I
     125: iload         10
     127: iaload
     128: aload_0
     129: getfield      #5                  // Field anIntArray1493:[I
     132: iload         10
     134: iaload
     135: iload         6
     137: invokespecial #33                 // Method method392:([BIIIII)V
     140: iload         5
     142: aload_0
     143: getfield      #8                  // Field anIntArray1496:[I
     146: iload         10
     148: iaload
     149: iadd
     150: istore        5
     152: iinc          9, 1
     155: goto          51
     158: return

  public void method389(boolean, int, int, java.lang.String, int);
    Code:
       0: aload_0
       1: iconst_0
       2: putfield      #12                 // Field aBoolean1499:Z
       5: iload_2
       6: istore        6
       8: aload         4
      10: ifnonnull     14
      13: return
      14: iload         5
      16: aload_0
      17: getfield      #26                 // Field anInt1497:I
      20: isub
      21: istore        5
      23: iconst_0
      24: istore        7
      26: iload         7
      28: aload         4
      30: invokevirtual #31                 // Method java/lang/String.length:()I
      33: if_icmpge     238
      36: aload         4
      38: iload         7
      40: invokevirtual #32                 // Method java/lang/String.charAt:(I)C
      43: bipush        64
      45: if_icmpne     108
      48: iload         7
      50: iconst_4
      51: iadd
      52: aload         4
      54: invokevirtual #31                 // Method java/lang/String.length:()I
      57: if_icmpge     108
      60: aload         4
      62: iload         7
      64: iconst_4
      65: iadd
      66: invokevirtual #32                 // Method java/lang/String.charAt:(I)C
      69: bipush        64
      71: if_icmpne     108
      74: aload_0
      75: aload         4
      77: iload         7
      79: iconst_1
      80: iadd
      81: iload         7
      83: iconst_4
      84: iadd
      85: invokevirtual #47                 // Method java/lang/String.substring:(II)Ljava/lang/String;
      88: invokespecial #48                 // Method getColorByName:(Ljava/lang/String;)I
      91: istore        8
      93: iload         8
      95: iconst_m1
      96: if_icmpeq     102
      99: iload         8
     101: istore_3
     102: iinc          7, 4
     105: goto          232
     108: aload         4
     110: iload         7
     112: invokevirtual #32                 // Method java/lang/String.charAt:(I)C
     115: istore        8
     117: iload         8
     119: bipush        32
     121: if_icmpeq     222
     124: iload_1
     125: ifeq          177
     128: aload_0
     129: aload_0
     130: getfield      #3                  // Field aByteArrayArray1491:[[B
     133: iload         8
     135: aaload
     136: iload_2
     137: aload_0
     138: getfield      #6                  // Field anIntArray1494:[I
     141: iload         8
     143: iaload
     144: iadd
     145: iconst_1
     146: iadd
     147: iload         5
     149: aload_0
     150: getfield      #7                  // Field anIntArray1495:[I
     153: iload         8
     155: iaload
     156: iadd
     157: iconst_1
     158: iadd
     159: aload_0
     160: getfield      #4                  // Field anIntArray1492:[I
     163: iload         8
     165: iaload
     166: aload_0
     167: getfield      #5                  // Field anIntArray1493:[I
     170: iload         8
     172: iaload
     173: iconst_0
     174: invokespecial #33                 // Method method392:([BIIIII)V
     177: aload_0
     178: aload_0
     179: getfield      #3                  // Field aByteArrayArray1491:[[B
     182: iload         8
     184: aaload
     185: iload_2
     186: aload_0
     187: getfield      #6                  // Field anIntArray1494:[I
     190: iload         8
     192: iaload
     193: iadd
     194: iload         5
     196: aload_0
     197: getfield      #7                  // Field anIntArray1495:[I
     200: iload         8
     202: iaload
     203: iadd
     204: aload_0
     205: getfield      #4                  // Field anIntArray1492:[I
     208: iload         8
     210: iaload
     211: aload_0
     212: getfield      #5                  // Field anIntArray1493:[I
     215: iload         8
     217: iaload
     218: iload_3
     219: invokespecial #33                 // Method method392:([BIIIII)V
     222: iload_2
     223: aload_0
     224: getfield      #8                  // Field anIntArray1496:[I
     227: iload         8
     229: iaload
     230: iadd
     231: istore_2
     232: iinc          7, 1
     235: goto          26
     238: aload_0
     239: getfield      #12                 // Field aBoolean1499:Z
     242: ifeq          269
     245: iload         5
     247: aload_0
     248: getfield      #26                 // Field anInt1497:I
     251: i2d
     252: ldc2_w        #49                 // double 0.7d
     255: dmul
     256: d2i
     257: iadd
     258: ldc           #51                 // int 8388608
     260: iload_2
     261: iload         6
     263: isub
     264: iload         6
     266: invokestatic  #52                 // Method DrawingArea.method339:(IIII)V
     269: return

  public void method390(int, int, java.lang.String, int, int);
    Code:
       0: aload_3
       1: ifnonnull     5
       4: return
       5: aload_0
       6: getfield      #11                 // Field aRandom1498:Ljava/util/Random;
       9: iload         4
      11: i2l
      12: invokevirtual #53                 // Method java/util/Random.setSeed:(J)V
      15: sipush        192
      18: aload_0
      19: getfield      #11                 // Field aRandom1498:Ljava/util/Random;
      22: invokevirtual #54                 // Method java/util/Random.nextInt:()I
      25: bipush        31
      27: iand
      28: iadd
      29: istore        6
      31: iload         5
      33: aload_0
      34: getfield      #26                 // Field anInt1497:I
      37: isub
      38: istore        5
      40: iconst_0
      41: istore        7
      43: iload         7
      45: aload_3
      46: invokevirtual #31                 // Method java/lang/String.length:()I
      49: if_icmpge     265
      52: aload_3
      53: iload         7
      55: invokevirtual #32                 // Method java/lang/String.charAt:(I)C
      58: bipush        64
      60: if_icmpne     120
      63: iload         7
      65: iconst_4
      66: iadd
      67: aload_3
      68: invokevirtual #31                 // Method java/lang/String.length:()I
      71: if_icmpge     120
      74: aload_3
      75: iload         7
      77: iconst_4
      78: iadd
      79: invokevirtual #32                 // Method java/lang/String.charAt:(I)C
      82: bipush        64
      84: if_icmpne     120
      87: aload_0
      88: aload_3
      89: iload         7
      91: iconst_1
      92: iadd
      93: iload         7
      95: iconst_4
      96: iadd
      97: invokevirtual #47                 // Method java/lang/String.substring:(II)Ljava/lang/String;
     100: invokespecial #48                 // Method getColorByName:(Ljava/lang/String;)I
     103: istore        8
     105: iload         8
     107: iconst_m1
     108: if_icmpeq     114
     111: iload         8
     113: istore_2
     114: iinc          7, 4
     117: goto          259
     120: aload_3
     121: iload         7
     123: invokevirtual #32                 // Method java/lang/String.charAt:(I)C
     126: istore        8
     128: iload         8
     130: bipush        32
     132: if_icmpeq     234
     135: aload_0
     136: sipush        192
     139: iload_1
     140: aload_0
     141: getfield      #6                  // Field anIntArray1494:[I
     144: iload         8
     146: iaload
     147: iadd
     148: iconst_1
     149: iadd
     150: aload_0
     151: getfield      #3                  // Field aByteArrayArray1491:[[B
     154: iload         8
     156: aaload
     157: aload_0
     158: getfield      #4                  // Field anIntArray1492:[I
     161: iload         8
     163: iaload
     164: iload         5
     166: aload_0
     167: getfield      #7                  // Field anIntArray1495:[I
     170: iload         8
     172: iaload
     173: iadd
     174: iconst_1
     175: iadd
     176: aload_0
     177: getfield      #5                  // Field anIntArray1493:[I
     180: iload         8
     182: iaload
     183: iconst_0
     184: invokespecial #55                 // Method method394:(II[BIIII)V
     187: aload_0
     188: iload         6
     190: iload_1
     191: aload_0
     192: getfield      #6                  // Field anIntArray1494:[I
     195: iload         8
     197: iaload
     198: iadd
     199: aload_0
     200: getfield      #3                  // Field aByteArrayArray1491:[[B
     203: iload         8
     205: aaload
     206: aload_0
     207: getfield      #4                  // Field anIntArray1492:[I
     210: iload         8
     212: iaload
     213: iload         5
     215: aload_0
     216: getfield      #7                  // Field anIntArray1495:[I
     219: iload         8
     221: iaload
     222: iadd
     223: aload_0
     224: getfield      #5                  // Field anIntArray1493:[I
     227: iload         8
     229: iaload
     230: iload_2
     231: invokespecial #55                 // Method method394:(II[BIIII)V
     234: iload_1
     235: aload_0
     236: getfield      #8                  // Field anIntArray1496:[I
     239: iload         8
     241: iaload
     242: iadd
     243: istore_1
     244: aload_0
     245: getfield      #11                 // Field aRandom1498:Ljava/util/Random;
     248: invokevirtual #54                 // Method java/util/Random.nextInt:()I
     251: iconst_3
     252: iand
     253: ifne          259
     256: iinc          1, 1
     259: iinc          7, 1
     262: goto          43
     265: return

  private int getColorByName(java.lang.String);
    Code:
       0: aload_1
       1: ldc           #56                 // String red
       3: invokevirtual #57                 // Method java/lang/String.equals:(Ljava/lang/Object;)Z
       6: ifeq          12
       9: ldc           #58                 // int 16711680
      11: ireturn
      12: aload_1
      13: ldc           #59                 // String gre
      15: invokevirtual #57                 // Method java/lang/String.equals:(Ljava/lang/Object;)Z
      18: ifeq          24
      21: ldc           #60                 // int 65280
      23: ireturn
      24: aload_1
      25: ldc           #61                 // String blu
      27: invokevirtual #57                 // Method java/lang/String.equals:(Ljava/lang/Object;)Z
      30: ifeq          37
      33: sipush        255
      36: ireturn
      37: aload_1
      38: ldc           #62                 // String yel
      40: invokevirtual #57                 // Method java/lang/String.equals:(Ljava/lang/Object;)Z
      43: ifeq          49
      46: ldc           #63                 // int 16776960
      48: ireturn
      49: aload_1
      50: ldc           #64                 // String cya
      52: invokevirtual #57                 // Method java/lang/String.equals:(Ljava/lang/Object;)Z
      55: ifeq          61
      58: ldc           #65                 // int 65535
      60: ireturn
      61: aload_1
      62: ldc           #66                 // String mag
      64: invokevirtual #57                 // Method java/lang/String.equals:(Ljava/lang/Object;)Z
      67: ifeq          73
      70: ldc           #67                 // int 16711935
      72: ireturn
      73: aload_1
      74: ldc           #68                 // String whi
      76: invokevirtual #57                 // Method java/lang/String.equals:(Ljava/lang/Object;)Z
      79: ifeq          85
      82: ldc           #69                 // int 16777215
      84: ireturn
      85: aload_1
      86: ldc           #70                 // String bla
      88: invokevirtual #57                 // Method java/lang/String.equals:(Ljava/lang/Object;)Z
      91: ifeq          96
      94: iconst_0
      95: ireturn
      96: aload_1
      97: ldc           #71                 // String lre
      99: invokevirtual #57                 // Method java/lang/String.equals:(Ljava/lang/Object;)Z
     102: ifeq          108
     105: ldc           #72                 // int 16748608
     107: ireturn
     108: aload_1
     109: ldc           #73                 // String dre
     111: invokevirtual #57                 // Method java/lang/String.equals:(Ljava/lang/Object;)Z
     114: ifeq          120
     117: ldc           #51                 // int 8388608
     119: ireturn
     120: aload_1
     121: ldc           #74                 // String dbl
     123: invokevirtual #57                 // Method java/lang/String.equals:(Ljava/lang/Object;)Z
     126: ifeq          133
     129: sipush        128
     132: ireturn
     133: aload_1
     134: ldc           #75                 // String or1
     136: invokevirtual #57                 // Method java/lang/String.equals:(Ljava/lang/Object;)Z
     139: ifeq          145
     142: ldc           #76                 // int 16756736
     144: ireturn
     145: aload_1
     146: ldc           #77                 // String or2
     148: invokevirtual #57                 // Method java/lang/String.equals:(Ljava/lang/Object;)Z
     151: ifeq          157
     154: ldc           #78                 // int 16740352
     156: ireturn
     157: aload_1
     158: ldc           #79                 // String or3
     160: invokevirtual #57                 // Method java/lang/String.equals:(Ljava/lang/Object;)Z
     163: ifeq          169
     166: ldc           #80                 // int 16723968
     168: ireturn
     169: aload_1
     170: ldc           #81                 // String gr1
     172: invokevirtual #57                 // Method java/lang/String.equals:(Ljava/lang/Object;)Z
     175: ifeq          181
     178: ldc           #82                 // int 12648192
     180: ireturn
     181: aload_1
     182: ldc           #83                 // String gr2
     184: invokevirtual #57                 // Method java/lang/String.equals:(Ljava/lang/Object;)Z
     187: ifeq          193
     190: ldc           #84                 // int 8453888
     192: ireturn
     193: aload_1
     194: ldc           #85                 // String gr3
     196: invokevirtual #57                 // Method java/lang/String.equals:(Ljava/lang/Object;)Z
     199: ifeq          205
     202: ldc           #86                 // int 4259584
     204: ireturn
     205: aload_1
     206: ldc           #87                 // String str
     208: invokevirtual #57                 // Method java/lang/String.equals:(Ljava/lang/Object;)Z
     211: ifeq          219
     214: aload_0
     215: iconst_1
     216: putfield      #12                 // Field aBoolean1499:Z
     219: aload_1
     220: ldc           #88                 // String end
     222: invokevirtual #57                 // Method java/lang/String.equals:(Ljava/lang/Object;)Z
     225: ifeq          233
     228: aload_0
     229: iconst_0
     230: putfield      #12                 // Field aBoolean1499:Z
     233: iconst_m1
     234: ireturn

  private void method392(byte[], int, int, int, int, int);
    Code:
       0: iload_2
       1: iload_3
       2: getstatic     #89                 // Field DrawingArea.width:I
       5: imul
       6: iadd
       7: istore        7
       9: getstatic     #89                 // Field DrawingArea.width:I
      12: iload         4
      14: isub
      15: istore        8
      17: iconst_0
      18: istore        9
      20: iconst_0
      21: istore        10
      23: iload_3
      24: getstatic     #90                 // Field DrawingArea.topY:I
      27: if_icmpge     69
      30: getstatic     #90                 // Field DrawingArea.topY:I
      33: iload_3
      34: isub
      35: istore        11
      37: iload         5
      39: iload         11
      41: isub
      42: istore        5
      44: getstatic     #90                 // Field DrawingArea.topY:I
      47: istore_3
      48: iload         10
      50: iload         11
      52: iload         4
      54: imul
      55: iadd
      56: istore        10
      58: iload         7
      60: iload         11
      62: getstatic     #89                 // Field DrawingArea.width:I
      65: imul
      66: iadd
      67: istore        7
      69: iload_3
      70: iload         5
      72: iadd
      73: getstatic     #91                 // Field DrawingArea.bottomY:I
      76: if_icmplt     94
      79: iload         5
      81: iload_3
      82: iload         5
      84: iadd
      85: getstatic     #91                 // Field DrawingArea.bottomY:I
      88: isub
      89: iconst_1
      90: iadd
      91: isub
      92: istore        5
      94: iload_2
      95: getstatic     #92                 // Field DrawingArea.topX:I
      98: if_icmpge     147
     101: getstatic     #92                 // Field DrawingArea.topX:I
     104: iload_2
     105: isub
     106: istore        11
     108: iload         4
     110: iload         11
     112: isub
     113: istore        4
     115: getstatic     #92                 // Field DrawingArea.topX:I
     118: istore_2
     119: iload         10
     121: iload         11
     123: iadd
     124: istore        10
     126: iload         7
     128: iload         11
     130: iadd
     131: istore        7
     133: iload         9
     135: iload         11
     137: iadd
     138: istore        9
     140: iload         8
     142: iload         11
     144: iadd
     145: istore        8
     147: iload_2
     148: iload         4
     150: iadd
     151: getstatic     #93                 // Field DrawingArea.bottomX:I
     154: if_icmplt     190
     157: iload_2
     158: iload         4
     160: iadd
     161: getstatic     #93                 // Field DrawingArea.bottomX:I
     164: isub
     165: iconst_1
     166: iadd
     167: istore        11
     169: iload         4
     171: iload         11
     173: isub
     174: istore        4
     176: iload         9
     178: iload         11
     180: iadd
     181: istore        9
     183: iload         8
     185: iload         11
     187: iadd
     188: istore        8
     190: iload         4
     192: ifle          222
     195: iload         5
     197: ifle          222
     200: aload_0
     201: getstatic     #94                 // Field DrawingArea.pixels:[I
     204: aload_1
     205: iload         6
     207: iload         10
     209: iload         7
     211: iload         4
     213: iload         5
     215: iload         8
     217: iload         9
     219: invokespecial #95                 // Method method393:([I[BIIIIIII)V
     222: return

  private void method393(int[], byte[], int, int, int, int, int, int, int);
    Code:
       0: iload         6
       2: iconst_2
       3: ishr
       4: ineg
       5: istore        10
       7: iload         6
       9: iconst_3
      10: iand
      11: ineg
      12: istore        6
      14: iload         7
      16: ineg
      17: istore        11
      19: iload         11
      21: ifge          194
      24: iload         10
      26: istore        12
      28: iload         12
      30: ifge          135
      33: aload_2
      34: iload         4
      36: iinc          4, 1
      39: baload
      40: ifeq          54
      43: aload_1
      44: iload         5
      46: iinc          5, 1
      49: iload_3
      50: iastore
      51: goto          57
      54: iinc          5, 1
      57: aload_2
      58: iload         4
      60: iinc          4, 1
      63: baload
      64: ifeq          78
      67: aload_1
      68: iload         5
      70: iinc          5, 1
      73: iload_3
      74: iastore
      75: goto          81
      78: iinc          5, 1
      81: aload_2
      82: iload         4
      84: iinc          4, 1
      87: baload
      88: ifeq          102
      91: aload_1
      92: iload         5
      94: iinc          5, 1
      97: iload_3
      98: iastore
      99: goto          105
     102: iinc          5, 1
     105: aload_2
     106: iload         4
     108: iinc          4, 1
     111: baload
     112: ifeq          126
     115: aload_1
     116: iload         5
     118: iinc          5, 1
     121: iload_3
     122: iastore
     123: goto          129
     126: iinc          5, 1
     129: iinc          12, 1
     132: goto          28
     135: iload         6
     137: istore        12
     139: iload         12
     141: ifge          174
     144: aload_2
     145: iload         4
     147: iinc          4, 1
     150: baload
     151: ifeq          165
     154: aload_1
     155: iload         5
     157: iinc          5, 1
     160: iload_3
     161: iastore
     162: goto          168
     165: iinc          5, 1
     168: iinc          12, 1
     171: goto          139
     174: iload         5
     176: iload         8
     178: iadd
     179: istore        5
     181: iload         4
     183: iload         9
     185: iadd
     186: istore        4
     188: iinc          11, 1
     191: goto          19
     194: return

  private void method394(int, int, byte[], int, int, int, int);
    Code:
       0: iload_2
       1: iload         5
       3: getstatic     #89                 // Field DrawingArea.width:I
       6: imul
       7: iadd
       8: istore        8
      10: getstatic     #89                 // Field DrawingArea.width:I
      13: iload         4
      15: isub
      16: istore        9
      18: iconst_0
      19: istore        10
      21: iconst_0
      22: istore        11
      24: iload         5
      26: getstatic     #90                 // Field DrawingArea.topY:I
      29: if_icmpge     73
      32: getstatic     #90                 // Field DrawingArea.topY:I
      35: iload         5
      37: isub
      38: istore        12
      40: iload         6
      42: iload         12
      44: isub
      45: istore        6
      47: getstatic     #90                 // Field DrawingArea.topY:I
      50: istore        5
      52: iload         11
      54: iload         12
      56: iload         4
      58: imul
      59: iadd
      60: istore        11
      62: iload         8
      64: iload         12
      66: getstatic     #89                 // Field DrawingArea.width:I
      69: imul
      70: iadd
      71: istore        8
      73: iload         5
      75: iload         6
      77: iadd
      78: getstatic     #91                 // Field DrawingArea.bottomY:I
      81: if_icmplt     100
      84: iload         6
      86: iload         5
      88: iload         6
      90: iadd
      91: getstatic     #91                 // Field DrawingArea.bottomY:I
      94: isub
      95: iconst_1
      96: iadd
      97: isub
      98: istore        6
     100: iload_2
     101: getstatic     #92                 // Field DrawingArea.topX:I
     104: if_icmpge     153
     107: getstatic     #92                 // Field DrawingArea.topX:I
     110: iload_2
     111: isub
     112: istore        12
     114: iload         4
     116: iload         12
     118: isub
     119: istore        4
     121: getstatic     #92                 // Field DrawingArea.topX:I
     124: istore_2
     125: iload         11
     127: iload         12
     129: iadd
     130: istore        11
     132: iload         8
     134: iload         12
     136: iadd
     137: istore        8
     139: iload         10
     141: iload         12
     143: iadd
     144: istore        10
     146: iload         9
     148: iload         12
     150: iadd
     151: istore        9
     153: iload_2
     154: iload         4
     156: iadd
     157: getstatic     #93                 // Field DrawingArea.bottomX:I
     160: if_icmplt     196
     163: iload_2
     164: iload         4
     166: iadd
     167: getstatic     #93                 // Field DrawingArea.bottomX:I
     170: isub
     171: iconst_1
     172: iadd
     173: istore        12
     175: iload         4
     177: iload         12
     179: isub
     180: istore        4
     182: iload         10
     184: iload         12
     186: iadd
     187: istore        10
     189: iload         9
     191: iload         12
     193: iadd
     194: istore        9
     196: iload         4
     198: ifle          206
     201: iload         6
     203: ifgt          207
     206: return
     207: aload_0
     208: aload_3
     209: iload         6
     211: iload         8
     213: getstatic     #94                 // Field DrawingArea.pixels:[I
     216: iload         11
     218: iload         4
     220: iload         10
     222: iload         9
     224: iload         7
     226: iload_1
     227: invokespecial #96                 // Method method395:([BII[IIIIIII)V
     230: return

  private void method395(byte[], int, int, int[], int, int, int, int, int, int);
    Code:
       0: iload         9
       2: ldc           #67                 // int 16711935
       4: iand
       5: iload         10
       7: imul
       8: ldc           #97                 // int -16711936
      10: iand
      11: iload         9
      13: ldc           #60                 // int 65280
      15: iand
      16: iload         10
      18: imul
      19: ldc           #58                 // int 16711680
      21: iand
      22: iadd
      23: bipush        8
      25: ishr
      26: istore        9
      28: sipush        256
      31: iload         10
      33: isub
      34: istore        10
      36: iload_2
      37: ineg
      38: istore        11
      40: iload         11
      42: ifge          137
      45: iload         6
      47: ineg
      48: istore        12
      50: iload         12
      52: ifge          119
      55: aload_1
      56: iload         5
      58: iinc          5, 1
      61: baload
      62: ifeq          110
      65: aload         4
      67: iload_3
      68: iaload
      69: istore        13
      71: aload         4
      73: iload_3
      74: iinc          3, 1
      77: iload         13
      79: ldc           #67                 // int 16711935
      81: iand
      82: iload         10
      84: imul
      85: ldc           #97                 // int -16711936
      87: iand
      88: iload         13
      90: ldc           #60                 // int 65280
      92: iand
      93: iload         10
      95: imul
      96: ldc           #58                 // int 16711680
      98: iand
      99: iadd
     100: bipush        8
     102: ishr
     103: iload         9
     105: iadd
     106: iastore
     107: goto          113
     110: iinc          3, 1
     113: iinc          12, 1
     116: goto          50
     119: iload_3
     120: iload         8
     122: iadd
     123: istore_3
     124: iload         5
     126: iload         7
     128: iadd
     129: istore        5
     131: iinc          11, 1
     134: goto          40
     137: return
}
