Compiled from "Varp.java"
public final class Varp {
  public static Varp[] cache;

  private static int anInt702;

  private static int[] anIntArray703;

  public int anInt709;

  public boolean aBoolean713;

  public static void unpackConfig(StreamLoader);
    Code:
       0: new           #1                  // class Stream
       3: dup
       4: aload_0
       5: ldc           #2                  // String varp.dat
       7: invokevirtual #3                  // Method StreamLoader.getDataForName:(Ljava/lang/String;)[B
      10: invokespecial #4                  // Method Stream."<init>":([B)V
      13: astore_1
      14: iconst_0
      15: putstatic     #5                  // Field anInt702:I
      18: aload_1
      19: invokevirtual #6                  // Method Stream.readUnsignedWord:()I
      22: istore_2
      23: getstatic     #7                  // Field cache:[LVarp;
      26: ifnonnull     36
      29: iload_2
      30: anewarray     #8                  // class Varp
      33: putstatic     #7                  // Field cache:[LVarp;
      36: getstatic     #9                  // Field anIntArray703:[I
      39: ifnonnull     48
      42: iload_2
      43: newarray       int
      45: putstatic     #9                  // Field anIntArray703:[I
      48: iconst_0
      49: istore_3
      50: iload_3
      51: iload_2
      52: if_icmpge     91
      55: getstatic     #7                  // Field cache:[LVarp;
      58: iload_3
      59: aaload
      60: ifnonnull     75
      63: getstatic     #7                  // Field cache:[LVarp;
      66: iload_3
      67: new           #8                  // class Varp
      70: dup
      71: invokespecial #10                 // Method "<init>":()V
      74: aastore
      75: getstatic     #7                  // Field cache:[LVarp;
      78: iload_3
      79: aaload
      80: aload_1
      81: iload_3
      82: invokespecial #11                 // Method readValues:(LStream;I)V
      85: iinc          3, 1
      88: goto          50
      91: aload_1
      92: getfield      #12                 // Field Stream.currentOffset:I
      95: aload_1
      96: getfield      #13                 // Field Stream.buffer:[B
      99: arraylength
     100: if_icmpeq     111
     103: getstatic     #14                 // Field java/lang/System.out:Ljava/io/PrintStream;
     106: ldc           #15                 // String varptype load mismatch
     108: invokevirtual #16                 // Method java/io/PrintStream.println:(Ljava/lang/String;)V
     111: return

  private void readValues(Stream, int);
    Code:
       0: aload_1
       1: invokevirtual #17                 // Method Stream.readUnsignedByte:()I
       4: istore_3
       5: iload_3
       6: ifne          10
       9: return
      10: iload_3
      11: iconst_1
      12: if_icmpne     23
      15: aload_1
      16: invokevirtual #17                 // Method Stream.readUnsignedByte:()I
      19: pop
      20: goto          204
      23: iload_3
      24: iconst_2
      25: if_icmpne     36
      28: aload_1
      29: invokevirtual #17                 // Method Stream.readUnsignedByte:()I
      32: pop
      33: goto          204
      36: iload_3
      37: iconst_3
      38: if_icmpne     58
      41: getstatic     #9                  // Field anIntArray703:[I
      44: getstatic     #5                  // Field anInt702:I
      47: dup
      48: iconst_1
      49: iadd
      50: putstatic     #5                  // Field anInt702:I
      53: iload_2
      54: iastore
      55: goto          204
      58: iload_3
      59: iconst_4
      60: if_icmpne     69
      63: iconst_2
      64: istore        4
      66: goto          204
      69: iload_3
      70: iconst_5
      71: if_icmpne     85
      74: aload_0
      75: aload_1
      76: invokevirtual #6                  // Method Stream.readUnsignedWord:()I
      79: putfield      #18                 // Field anInt709:I
      82: goto          204
      85: iload_3
      86: bipush        6
      88: if_icmpne     97
      91: iconst_2
      92: istore        4
      94: goto          204
      97: iload_3
      98: bipush        7
     100: if_icmpne     111
     103: aload_1
     104: invokevirtual #19                 // Method Stream.readDWord:()I
     107: pop
     108: goto          204
     111: iload_3
     112: bipush        8
     114: if_icmpne     125
     117: aload_0
     118: iconst_1
     119: putfield      #20                 // Field aBoolean713:Z
     122: goto          204
     125: iload_3
     126: bipush        10
     128: if_icmpne     139
     131: aload_1
     132: invokevirtual #21                 // Method Stream.readString:()Ljava/lang/String;
     135: pop
     136: goto          204
     139: iload_3
     140: bipush        11
     142: if_icmpne     153
     145: aload_0
     146: iconst_1
     147: putfield      #20                 // Field aBoolean713:Z
     150: goto          204
     153: iload_3
     154: bipush        12
     156: if_icmpne     167
     159: aload_1
     160: invokevirtual #19                 // Method Stream.readDWord:()I
     163: pop
     164: goto          204
     167: iload_3
     168: bipush        13
     170: if_icmpne     179
     173: iconst_2
     174: istore        4
     176: goto          204
     179: getstatic     #14                 // Field java/lang/System.out:Ljava/io/PrintStream;
     182: new           #22                 // class java/lang/StringBuilder
     185: dup
     186: invokespecial #23                 // Method java/lang/StringBuilder."<init>":()V
     189: ldc           #24                 // String Error unrecognised config code:
     191: invokevirtual #25                 // Method java/lang/StringBuilder.append:(Ljava/lang/String;)Ljava/lang/StringBuilder;
     194: iload_3
     195: invokevirtual #26                 // Method java/lang/StringBuilder.append:(I)Ljava/lang/StringBuilder;
     198: invokevirtual #27                 // Method java/lang/StringBuilder.toString:()Ljava/lang/String;
     201: invokevirtual #16                 // Method java/io/PrintStream.println:(Ljava/lang/String;)V
     204: goto          0

  private Varp();
    Code:
       0: aload_0
       1: invokespecial #28                 // Method java/lang/Object."<init>":()V
       4: aload_0
       5: iconst_0
       6: putfield      #20                 // Field aBoolean713:Z
       9: return
}
